{
  "type": "Feature",
  "properties": {
    "gn:admin1_code":"10.0",
    "gn:admin2_code":"94590.0",
    "gn:asciiname":"Markaz Shaykh",
    "gn:country_code":"IQ",
    "gn:dem":310,
    "gn:feature_class":"P",
    "gn:feature_code":"PPL",
    "gn:name":"Markaz Shaykh",
    "gn:population":0,
    "gn:timezone":"Asia/Baghdad",
    "iso:country":"IQ",
    "name:ara_x_preferred":[
        "\u0645\u0631\u0643\u0632 \u0634\u064a\u062e"
    ],
    "name:kur_x_preferred":[
        "Merkez Sh\u00eax"
    ],
    "name:kur_x_variant":[
        "Merkez",
        "\u0645\u06d5\u0631\u0643\u06d5\u0632 \u0634\u06ce\u062e",
        "\u0645\u06d5\u0631\u0643\u06d5\u0632"
    ],
    "name:und_x_variant":[
        "Markaz"
    ],
    "wof:name":"Markaz Shaykh",
    "wof:placetype":"locality"
},
  "geometry": {"coordinates":[45.43721,34.53462],"type":"Point"}
}