{
  "type": "Feature",
  "properties": {
    "gn:admin1_code":"13.0",
    "gn:admin2_code":"6770659.0",
    "gn:asciiname":"'Abd Allah Ibrahim",
    "gn:country_code":"IQ",
    "gn:dem":206,
    "gn:feature_class":"P",
    "gn:feature_code":"PPL",
    "gn:name":"\u2018Abd All\u0101h Ibr\u0101h\u012bm",
    "gn:population":0,
    "gn:timezone":"Asia/Baghdad",
    "iso:country":"IQ",
    "name:ara_x_preferred":[
        "\u0639\u0628\u062f \ufdf2 \u0627\u0628\u0631\u0627\u0647\u064a\u0645"
    ],
    "name:ara_x_variant":[
        "\u2018Abd All\u0101h Ibr\u0101h\u012bm"
    ],
    "wof:name":"'Abd Allah Ibrahim",
    "wof:placetype":"locality"
},
  "geometry": {"coordinates":[43.83891,35.42367],"type":"Point"}
}