{
  "type": "Feature",
  "properties": {
    "gn:admin1_code":"6.0",
    "gn:admin2_code":"99040.0",
    "gn:asciiname":"Qaryat at Tahmaziyah",
    "gn:country_code":"IQ",
    "gn:dem":34,
    "gn:feature_class":"P",
    "gn:feature_code":"PPL",
    "gn:name":"Qaryat a\u0163 \u0162ahm\u0101z\u012byah",
    "gn:population":0,
    "gn:timezone":"Asia/Baghdad",
    "iso:country":"IQ",
    "name:ara_x_preferred":[
        "\u0642\u0631\u064a\u0629 \u0627\u0644\u0637\u0647\u0645\u0627\u0632\u064a\u0629"
    ],
    "name:und_x_variant":[
        "\u0162ahm\u0101z\u012byah",
        "Tahm\u0101z\u012bya",
        "A\u0163 \u0162ahm\u0101z\u012byah",
        "Qaryat a\u0163 \u0162ahm\u0101z\u012byah"
    ],
    "wof:name":"Qaryat at Tahmaziyah",
    "wof:placetype":"locality"
},
  "geometry": {"coordinates":[44.37323,32.46327],"type":"Point"}
}