{
  "type": "Feature",
  "properties": {
    "gn:admin1_code":"13.0",
    "gn:admin2_code":"6770659.0",
    "gn:asciiname":"'Arab 'Aziz Hamad",
    "gn:country_code":"IQ",
    "gn:dem":175,
    "gn:feature_class":"P",
    "gn:feature_code":"PPLL",
    "gn:name":"\u2018Arab \u2018Az\u012bz \u1e28amad",
    "gn:population":0,
    "gn:timezone":"Asia/Baghdad",
    "iso:country":"IQ",
    "name:ara_x_preferred":[
        "\u0639\u0631\u0628 \u0639\u0632\u064a\u0632 \u062d\u0645\u062f"
    ],
    "name:und_x_variant":[
        "\u2018Arab \u2018Az\u012bz \u1e28amad"
    ],
    "wof:name":"'Arab 'Aziz Hamad",
    "wof:placetype":"locality"
},
  "geometry": {"coordinates":[43.74963,35.15486],"type":"Point"}
}