{
  "type": "Feature",
  "properties": {
    "gn:admin1_code":"5.0",
    "gn:admin2_code":"92051.0",
    "gn:asciiname":"Seruchawe",
    "gn:country_code":"IQ",
    "gn:dem":612,
    "gn:feature_class":"P",
    "gn:feature_code":"PPL",
    "gn:name":"Seruchawe",
    "gn:population":0,
    "gn:timezone":"Asia/Baghdad",
    "iso:country":"IQ",
    "name:ara_x_preferred":[
        "\u0633\u0631\u062c\u0627\u0648\u0629"
    ],
    "name:ara_x_variant":[
        "\u0633\u0631\u0649 \u062c\u0627\u0648"
    ],
    "name:kur_x_preferred":[
        "\u0633\u06d5\u0631\u0648\u0686\u0627\u0648\u06d5"
    ],
    "name:kur_x_variant":[
        "Saroochawa",
        "Seruchawe"
    ],
    "name:und_x_variant":[
        "S\u0113r\u016bch\u0101wah",
        "Seruchawa",
        "Sar\u00e1 J\u0101wa",
        "Sarj\u0101wah",
        "Sar\u00e1 J\u0101ww",
        "Saroochawa",
        "Saruchawa",
        "Saru Chawa"
    ],
    "wof:name":"Seruchawe",
    "wof:placetype":"locality"
},
  "geometry": {"coordinates":[44.75025,36.27723],"type":"Point"}
}