{
  "type": "Feature",
  "properties": {
    "gn:admin1_code":"9.0",
    "gn:admin2_code":"98623.0",
    "gn:asciiname":"Albu Hawalah",
    "gn:country_code":"IQ",
    "gn:dem":7,
    "gn:feature_class":"P",
    "gn:feature_code":"PPL",
    "gn:name":"\u0100lb\u016b \u1e28aw\u0101lah",
    "gn:population":0,
    "gn:timezone":"Asia/Baghdad",
    "iso:country":"IQ",
    "name:ara_x_preferred":[
        "\u0627\u0644\u0628\u0648 \u062d\u0648\u0627\u0644\u0647"
    ],
    "name:und_x_variant":[
        "\u0100lb\u016b \u1e28aw\u0101lah"
    ],
    "wof:name":"Albu Hawalah",
    "wof:placetype":"locality"
},
  "geometry": {"coordinates":[46.22263,31.16653],"type":"Point"}
}