{
  "type": "Feature",
  "properties": {
    "gn:admin1_code":"1.0",
    "gn:admin2_code":"6765480.0",
    "gn:asciiname":"Al Was",
    "gn:country_code":"IQ",
    "gn:dem":101,
    "gn:feature_class":"P",
    "gn:feature_code":"PPL",
    "gn:name":"Al Was",
    "gn:population":0,
    "gn:timezone":"Asia/Baghdad",
    "iso:country":"IQ",
    "name:ara_x_preferred":[
        "\u0627\u0644\u0648\u0633"
    ],
    "wof:name":"Al Was",
    "wof:placetype":"locality"
},
  "geometry": {"coordinates":[42.40978,34.02972],"type":"Point"}
}