{
  "type": "Feature",
  "properties": {
    "gn:admin1_code":"6.0",
    "gn:admin2_code":"6818313.0",
    "gn:asciiname":"Hamid Ibrahim",
    "gn:country_code":"IQ",
    "gn:dem":35,
    "gn:feature_class":"P",
    "gn:feature_code":"PPL",
    "gn:name":"\u1e28\u0101mid Ibr\u0101h\u012bm",
    "gn:population":0,
    "gn:timezone":"Asia/Baghdad",
    "iso:country":"IQ",
    "name:ara_x_preferred":[
        "\u062d\u0627\u0645\u062f \u0627\u0628\u0631\u0627\u0647\u064a\u0645"
    ],
    "name:ara_x_variant":[
        "\u1e28\u0101mid Ibr\u0101h\u012bm"
    ],
    "wof:name":"Hamid Ibrahim",
    "wof:placetype":"locality"
},
  "geometry": {"coordinates":[44.28467,32.90922],"type":"Point"}
}