{
  "type": "Feature",
  "properties": {
    "gn:admin1_code":"10.0",
    "gn:admin2_code":"97988.0",
    "gn:asciiname":"Nahiyat Khan Bani Sa'd",
    "gn:country_code":"IQ",
    "gn:dem":43,
    "gn:feature_class":"P",
    "gn:feature_code":"PPL",
    "gn:name":"N\u0101\u1e29iyat Kh\u0101n Ban\u012b Sa\u2018d",
    "gn:population":0,
    "gn:timezone":"Asia/Baghdad",
    "iso:country":"IQ",
    "name:ara_x_preferred":[
        "\u0646\u0627\u062d\u064a\u0629 \u062e\u0627\u0646 \u0628\u0646\u064a \u0633\u0639\u062f"
    ],
    "name:und_x_variant":[
        "Kh\u0101n Ban\u012b Sa\u2018d",
        "\u062e\u0627\u0646 \u0628\u0646\u064a \u0633\u0639\u062f",
        "Ban\u012b Sa\u2018d",
        "Kh\u0101n Bani Sa\u2018ad",
        "N\u0101\u1e29iyat Kh\u0101n Ban\u012b Sa\u2018d"
    ],
    "wof:name":"Nahiyat Khan Bani Sa'd",
    "wof:placetype":"locality"
},
  "geometry": {"coordinates":[44.54345,33.56556],"type":"Point"}
}