{
  "type": "Feature",
  "properties": {
    "gn:admin1_code":"4.0",
    "gn:admin2_code":"99763.0",
    "gn:asciiname":"'Arab al Humran",
    "gn:country_code":"IQ",
    "gn:dem":25,
    "gn:feature_class":"P",
    "gn:feature_code":"PPLL",
    "gn:name":"\u2018Arab al \u1e28umr\u0101n",
    "gn:population":0,
    "gn:timezone":"Asia/Baghdad",
    "iso:country":"IQ",
    "name:ara_x_preferred":[
        "\u0639\u0631\u0628 \u0627\u0644\u062d\u0645\u0631\u0627\u0646"
    ],
    "name:und_x_variant":[
        "\u2018Arab al \u1e28umr\u0101n"
    ],
    "wof:name":"'Arab al Humran",
    "wof:placetype":"locality"
},
  "geometry": {"coordinates":[44.76013,32.02776],"type":"Point"}
}