{
  "type": "Feature",
  "properties": {
    "gn:admin1_code":"18.0",
    "gn:admin2_code":"9166616.0",
    "gn:asciiname":"Qaryat al 'Adalah",
    "gn:country_code":"IQ",
    "gn:dem":45,
    "gn:feature_class":"P",
    "gn:feature_code":"PPL",
    "gn:name":"Qaryat al \u2018Ad\u0101lah",
    "gn:population":0,
    "gn:timezone":"Asia/Baghdad",
    "iso:country":"IQ",
    "name:ara_x_preferred":[
        "\u0642\u0631\u064a\u0629 \u0627\u0644\u0639\u062f\u0627\u0644\u0629"
    ],
    "name:und_x_variant":[
        "Qaryat al \u2018Ad\u0101lah"
    ],
    "wof:name":"Qaryat al 'Adalah",
    "wof:placetype":"locality"
},
  "geometry": {"coordinates":[44.25855,33.89501],"type":"Point"}
}