{
  "type": "Feature",
  "properties": {
    "gn:admin1_code":"4.0",
    "gn:admin2_code":"6850588.0",
    "gn:asciiname":"Qal'at Abu Hijam",
    "gn:country_code":"IQ",
    "gn:dem":14,
    "gn:feature_class":"P",
    "gn:feature_code":"PPL",
    "gn:name":"Qal\u2018at Ab\u016b \u1e28ij\u0101m",
    "gn:population":0,
    "gn:timezone":"Asia/Baghdad",
    "iso:country":"IQ",
    "name:ara_x_preferred":[
        "\u0642\u0644\u0639\u0629 \u0627\u0628\u0648 \u062d\u062c\u0627\u0645"
    ],
    "name:und_x_variant":[
        "Qal\u2018at Ab\u016b \u1e28ij\u0101m"
    ],
    "wof:name":"Qal'at Abu Hijam",
    "wof:placetype":"locality"
},
  "geometry": {"coordinates":[45.06454,31.54929000000001],"type":"Point"}
}