{
  "type": "Feature",
  "properties": {
    "gn:admin1_code":"2.0",
    "gn:admin2_code":"9166549.0",
    "gn:asciiname":"Dayir",
    "gn:country_code":"IQ",
    "gn:dem":0,
    "gn:feature_class":"P",
    "gn:feature_code":"PPL",
    "gn:name":"D\u0101yir",
    "gn:population":0,
    "gn:timezone":"Asia/Baghdad",
    "iso:country":"IQ",
    "name:ara_x_preferred":[
        "D\u0101yir"
    ],
    "wof:name":"Dayir",
    "wof:placetype":"locality"
},
  "geometry": {"coordinates":[48.45083,29.99861],"type":"Point"}
}