{
  "type": "Feature",
  "properties": {
    "gn:admin1_code":"5.0",
    "gn:admin2_code":"92743.0",
    "gn:asciiname":"Ghalu",
    "gn:country_code":"IQ",
    "gn:dem":772,
    "gn:feature_class":"P",
    "gn:feature_code":"PPL",
    "gn:name":"Gh\u0101l\u016b",
    "gn:population":0,
    "gn:timezone":"Asia/Baghdad",
    "iso:country":"IQ",
    "name:ara_x_preferred":[
        "Gh\u0101l\u016b"
    ],
    "wof:name":"Ghalu",
    "wof:placetype":"locality"
},
  "geometry": {"coordinates":[44.95167,36.3125],"type":"Point"}
}