{
  "type": "Feature",
  "properties": {
    "gn:admin1_code":"10.0",
    "gn:admin2_code":"99063.0",
    "gn:asciiname":"Khalifat Sayyid Jamil",
    "gn:country_code":"IQ",
    "gn:dem":55,
    "gn:feature_class":"P",
    "gn:feature_code":"PPL",
    "gn:name":"Khal\u012bfat Sayyid Jam\u012bl",
    "gn:population":0,
    "gn:timezone":"Asia/Baghdad",
    "iso:country":"IQ",
    "name:ara_x_preferred":[
        "\u062e\u0644\u064a\u0641\u0629 \u0633\u064a\u062f \u062c\u0645\u064a\u0644"
    ],
    "name:und_x_variant":[
        "Khal\u012bfat Sayyid Jam\u012bl"
    ],
    "wof:name":"Khalifat Sayyid Jamil",
    "wof:placetype":"locality"
},
  "geometry": {"coordinates":[44.86189,33.90908],"type":"Point"}
}