{
  "type": "Feature",
  "properties": {
    "gn:admin1_code":"5.0",
    "gn:admin2_code":"9166596.0",
    "gn:asciiname":"Harishah",
    "gn:country_code":"IQ",
    "gn:dem":690,
    "gn:feature_class":"P",
    "gn:feature_code":"PPL",
    "gn:name":"Har\u012bshah",
    "gn:population":0,
    "gn:timezone":"Asia/Baghdad",
    "iso:country":"IQ",
    "name:ara_x_preferred":[
        "\u0647\u06d5\u0631\u064a\u0634\u06d5"
    ],
    "name:kur_x_preferred":[
        "Her\u00eeshe"
    ],
    "name:kur_x_variant":[
        "Har\u00eeshe",
        "\u0647\u0627\u0631\u064a\u0634\u06d5"
    ],
    "name:und_x_variant":[
        "Har\u012bshah",
        "Habirshahah",
        "\u0647\u0628\u0631\u0634\u0647\u0647",
        "Arisha",
        "Hareesha"
    ],
    "wof:name":"Harishah",
    "wof:placetype":"locality"
},
  "geometry": {"coordinates":[44.88408,35.9905],"type":"Point"}
}