{
  "type": "Feature",
  "properties": {
    "gn:admin1_code":"7.0",
    "gn:asciiname":"Albu `Alwan",
    "gn:country_code":"IQ",
    "gn:dem":38,
    "gn:feature_class":"P",
    "gn:feature_code":"PPL",
    "gn:name":"\u0100lb\u016b \u2018Alw\u0101n",
    "gn:population":0,
    "gn:timezone":"Asia/Baghdad",
    "iso:country":"IQ",
    "name:ara_x_preferred":[
        "\u0100lb\u016b \u2018Alw\u0101n"
    ],
    "name:und_x_variant":[
        "\u0627\u0644\u0628\u0648 \u0639\u0627\u0645\u0631"
    ],
    "wof:name":"Albu `Alwan",
    "wof:placetype":"locality"
},
  "geometry": {"coordinates":[44.38477,33.46546],"type":"Point"}
}