{
  "type": "Feature",
  "properties": {
    "gn:admin1_code":"15.0",
    "gn:asciiname":"Az Zahra`",
    "gn:country_code":"IQ",
    "gn:dem":7,
    "gn:feature_class":"P",
    "gn:feature_code":"PPL",
    "gn:name":"Az Zahr\u0101\u2018",
    "gn:population":0,
    "gn:timezone":"Asia/Baghdad",
    "iso:country":"IQ",
    "name:ara_x_preferred":[
        "\u0627\u0644\u0632\u0647\u0631\u0627\u0621"
    ],
    "name:und_x_variant":[
        "Az Zahr\u0101\u2018"
    ],
    "wof:name":"Az Zahra`",
    "wof:placetype":"locality"
},
  "geometry": {"coordinates":[46.2775,31.0421],"type":"Point"}
}