{
  "type": "Feature",
  "properties": {
    "gn:admin1_code":"8.0",
    "gn:admin2_code":"97269.0",
    "gn:asciiname":"Yakmalah",
    "gn:country_code":"IQ",
    "gn:dem":815,
    "gn:feature_class":"P",
    "gn:feature_code":"PPL",
    "gn:name":"Yakm\u0101lah",
    "gn:population":0,
    "gn:timezone":"Asia/Baghdad",
    "iso:country":"IQ",
    "name:ara_x_preferred":[
        "\u064a\u0643\u0645\u0627\u0644\u0629"
    ],
    "name:kur_x_preferred":[
        "Yek Ma\u0142e"
    ],
    "name:kur_x_variant":[
        "\u064a\u06d5\u0643 \u0645\u0627\u06b5\u06d5",
        "\u00cakmale",
        "\u0626\u06ce\u0643\u0645\u0627\u0644\u06d5"
    ],
    "name:und_x_variant":[
        "Yakm\u0101la",
        "Yak Mala",
        "Yakm\u0101lah",
        "Ekmala"
    ],
    "wof:name":"Yakmalah",
    "wof:placetype":"locality"
},
  "geometry": {"coordinates":[43.04709,36.91664],"type":"Point"}
}