{
  "type": "Feature",
  "properties": {
    "gn:admin1_code":"7.0",
    "gn:admin2_code":"99101.0",
    "gn:asciiname":"'Arab Jiyad Hasan",
    "gn:country_code":"IQ",
    "gn:dem":33,
    "gn:feature_class":"P",
    "gn:feature_code":"PPL",
    "gn:name":"\u2018Arab Jiy\u0101d \u1e28asan",
    "gn:population":0,
    "gn:timezone":"Asia/Baghdad",
    "iso:country":"IQ",
    "name:ara_x_preferred":[
        "\u0639\u0631\u0628 \u062c\u064a\u0627\u062f \u062d\u0633\u0646"
    ],
    "name:und_x_variant":[
        "\u2018Arab Jay\u0101d \u1e28asan",
        "\u2018Arab Jiy\u0101d \u1e28asan"
    ],
    "wof:name":"'Arab Jiyad Hasan",
    "wof:placetype":"locality"
},
  "geometry": {"coordinates":[44.33859,33.06997],"type":"Point"}
}