{
  "type": "Feature",
  "properties": {
    "gn:admin1_code":"4.0",
    "gn:admin2_code":"6850588.0",
    "gn:asciiname":"Kalah",
    "gn:country_code":"IQ",
    "gn:dem":18,
    "gn:feature_class":"P",
    "gn:feature_code":"PPL",
    "gn:name":"Kalah",
    "gn:population":0,
    "gn:timezone":"Asia/Baghdad",
    "iso:country":"IQ",
    "name:ara_x_preferred":[
        "\u0643\u0644\u0647"
    ],
    "name:ast_x_preferred":[
        "Kalah"
    ],
    "name:bul_x_preferred":[
        "\u041a\u0430\u043b\u0430\u0445\u0430"
    ],
    "name:dan_x_preferred":[
        "Kalaha"
    ],
    "name:deu_x_preferred":[
        "Kalaha"
    ],
    "name:epo_x_preferred":[
        "Kalaho"
    ],
    "name:est_x_preferred":[
        "Kalah"
    ],
    "name:ita_x_preferred":[
        "Kalah"
    ],
    "name:nor_x_preferred":[
        "Kalaha"
    ],
    "name:pol_x_preferred":[
        "Kalaha"
    ],
    "name:rus_x_preferred":[
        "\u041a\u0430\u043b\u0430\u0445"
    ],
    "name:spa_x_preferred":[
        "Kalah"
    ],
    "name:swe_x_preferred":[
        "Kalah"
    ],
    "name:zho_x_preferred":[
        "\u7f8e\u570b\u64ad\u68cb"
    ],
    "wof:name":"Kalah",
    "wof:placetype":"locality"
},
  "geometry": {"coordinates":[44.7988,31.45503],"type":"Point"}
}