{
  "type": "Feature",
  "properties": {
    "gn:admin1_code":"15.0",
    "gn:admin2_code":"9166618.0",
    "gn:asciiname":"Bilursat",
    "gn:country_code":"IQ",
    "gn:dem":324,
    "gn:feature_class":"P",
    "gn:feature_code":"PPL",
    "gn:name":"Bil\u016brs\u0101t",
    "gn:population":0,
    "gn:timezone":"Asia/Baghdad",
    "iso:country":"IQ",
    "name:ara_x_preferred":[
        "\u0628\u0644\u0648\u0631\u0633\u0627\u062a"
    ],
    "name:ara_x_variant":[
        "Bil\u016brs\u0101t"
    ],
    "wof:name":"Bilursat",
    "wof:placetype":"locality"
},
  "geometry": {"coordinates":[42.94498,36.69912],"type":"Point"}
}