{
  "type": "Feature",
  "properties": {
    "gn:admin1_code":"10.0",
    "gn:admin2_code":"94590.0",
    "gn:asciiname":"Tul Farus",
    "gn:country_code":"IQ",
    "gn:dem":177,
    "gn:feature_class":"P",
    "gn:feature_code":"PPL",
    "gn:name":"T\u016bl Far\u016bs",
    "gn:population":0,
    "gn:timezone":"Asia/Baghdad",
    "iso:country":"IQ",
    "name:ara_x_preferred":[
        "\u062a\u0648\u0644 \u0641\u0631\u0648\u0633"
    ],
    "name:fas_x_preferred":[
        "\u062a\u0648\u0644\u0641\u06cc \u0631\u0648\u0634"
    ],
    "name:fas_x_variant":[
        "Tolafir\u014dsh",
        "Towlaf\u012b R\u016bsh"
    ],
    "name:und_x_variant":[
        "T\u016blah Fur\u016bsh",
        "Tolafarush",
        "\u0162\u016blah Fih R\u016bsh",
        "T\u016bl Far\u016bs"
    ],
    "wof:name":"Tul Farus",
    "wof:placetype":"locality"
},
  "geometry": {"coordinates":[45.37837,34.35743],"type":"Point"}
}