{
  "type": "Feature",
  "properties": {
    "gn:admin1_code":"5.0",
    "gn:admin2_code":"96204.0",
    "gn:asciiname":"Qaryat Saraw",
    "gn:country_code":"IQ",
    "gn:dem":507,
    "gn:feature_class":"P",
    "gn:feature_code":"PPL",
    "gn:name":"Qaryat Sar\u0101w",
    "gn:population":0,
    "gn:timezone":"Asia/Baghdad",
    "iso:country":"IQ",
    "name:ara_x_preferred":[
        "\u0642\u0631\u064a\u0629 \u0633\u0631\u0627\u0648"
    ],
    "name:fas_x_preferred":[
        "\u0633\u0631\u0627\u0648 \u0633\u0644\u06cc\u0645\u0627\u0646 \u0622\u0642\u0627"
    ],
    "name:fas_x_variant":[
        "Sar\u0101v-e Soleym\u0101n \u0100gh\u0101",
        "Gerd-e Sar\u0101v-e Soleym\u0101n",
        "\u06af\u0631\u062f \u0633\u0631\u0627\u0648 \u0633\u0644\u06cc\u0645\u0627\u0646"
    ],
    "name:kur_x_preferred":[
        "Seraw\u00ee Sub\u1e27an Agha"
    ],
    "name:kur_x_variant":[
        "Seray Sub\u1e27an Agha",
        "\u0633\u06d5\u0631\u0627\u0648\u0649 \u0633\u0648\u0628\u062d\u0627\u0646 \u0626\u0627\u063a\u0627",
        "\u0633\u06d5\u0631\u0627\u0649 \u0633\u0648\u0628\u062d\u0627\u0646 \u0626\u0627\u063a\u0627"
    ],
    "name:und_x_variant":[
        "Sar\u0101w-i Sl\u0113m\u0101n \u0100gh\u0101",
        "Qaryat Sar\u0101w",
        "Saraw"
    ],
    "wof:name":"Qaryat Saraw",
    "wof:placetype":"locality"
},
  "geometry": {"coordinates":[45.82689,35.37069],"type":"Point"}
}