{
  "type": "Feature",
  "properties": {
    "gn:admin1_code":"11.0",
    "gn:admin2_code":"9166592.0",
    "gn:asciiname":"Talinan",
    "gn:country_code":"IQ",
    "gn:dem":1175,
    "gn:feature_class":"P",
    "gn:feature_code":"PPL",
    "gn:name":"Tal\u00eenan",
    "gn:population":0,
    "gn:timezone":"Asia/Baghdad",
    "iso:country":"IQ",
    "name:ara_x_preferred":[
        "T\u0101lin\u0101n"
    ],
    "name:kur_x_preferred":[
        "\u062a\u0627\u0644\u064a\u0646\u0627\u0646"
    ],
    "name:kur_x_variant":[
        "Talinan",
        "Tal\u00eenan"
    ],
    "name:und_x_variant":[
        "Talm\u0101n",
        "T\u0101iman",
        "Talinan"
    ],
    "wof:name":"Talinan",
    "wof:placetype":"locality"
},
  "geometry": {"coordinates":[44.54899,36.4806],"type":"Point"}
}