{
  "type": "Feature",
  "properties": {
    "gn:admin1_code":"6.0",
    "gn:admin2_code":"99358.0",
    "gn:asciiname":"Muhammad al Hasan",
    "gn:country_code":"IQ",
    "gn:dem":32,
    "gn:feature_class":"P",
    "gn:feature_code":"PPL",
    "gn:name":"Mu\u1e29ammad al \u1e28asan",
    "gn:population":0,
    "gn:timezone":"Asia/Baghdad",
    "iso:country":"IQ",
    "name:ara_x_preferred":[
        "\u0645\u062d\u0645\u062f \u0627\u0644\u062d\u0633\u0646"
    ],
    "name:und_x_variant":[
        "Mu\u1e29ammad al \u1e28asan"
    ],
    "wof:name":"Muhammad al Hasan",
    "wof:placetype":"locality"
},
  "geometry": {"coordinates":[44.77026,32.30028],"type":"Point"}
}