{
  "type": "Feature",
  "properties": {
    "gn:admin1_code":"18.0",
    "gn:admin2_code":"91594.0",
    "gn:asciiname":"'Arab 'Ali al Mahmud",
    "gn:country_code":"IQ",
    "gn:dem":92,
    "gn:feature_class":"P",
    "gn:feature_code":"PPLL",
    "gn:name":"\u2018Arab \u2018Al\u012b al Ma\u1e29m\u016bd",
    "gn:population":0,
    "gn:timezone":"Asia/Baghdad",
    "iso:country":"IQ",
    "name:ara_x_preferred":[
        "\u0639\u0631\u0628 \u0639\u0644\u064a \u0627\u0644\u0645\u062d\u0645\u0648\u062f"
    ],
    "name:und_x_variant":[
        "\u2018Arab \u2018Al\u012b al Ma\u1e29m\u016bd"
    ],
    "wof:name":"'Arab 'Ali al Mahmud",
    "wof:placetype":"locality"
},
  "geometry": {"coordinates":[43.65601,34.25937],"type":"Point"}
}