{
  "type": "Feature",
  "properties": {
    "gn:admin1_code":"11.0",
    "gn:admin2_code":"93817.0",
    "gn:asciiname":"`Ali Mulla Dawud",
    "gn:country_code":"IQ",
    "gn:dem":258,
    "gn:feature_class":"P",
    "gn:feature_code":"PPL",
    "gn:name":"\u2018Al\u012b Mull\u0101 D\u0101wud",
    "gn:population":0,
    "gn:timezone":"Asia/Baghdad",
    "iso:country":"IQ",
    "name:ara_x_preferred":[
        "\u0639\u0644\u064a \u0645\u0644\u0627 \u062f\u0627\u0648\u062f"
    ],
    "name:und_x_variant":[
        "\u2018Al\u012b Mull\u0101 D\u0101wud"
    ],
    "wof:name":"`Ali Mulla Dawud",
    "wof:placetype":"locality"
},
  "geometry": {"coordinates":[43.6565,36.08981],"type":"Point"}
}