{
  "type": "Feature",
  "properties": {
    "gn:admin1_code":"4.0",
    "gn:admin2_code":"6850588.0",
    "gn:asciiname":"Hamid Abu Hisan",
    "gn:country_code":"IQ",
    "gn:dem":20,
    "gn:feature_class":"P",
    "gn:feature_code":"PPL",
    "gn:name":"\u1e28am\u012bd Ab\u016b \u1e28i\u015f\u0101n",
    "gn:population":0,
    "gn:timezone":"Asia/Baghdad",
    "iso:country":"IQ",
    "name:ara_x_preferred":[
        "\u062d\u0645\u064a\u062f \u0627\u0628\u0648 \u062d\u0635\u0627\u0646"
    ],
    "name:und_x_variant":[
        "\u1e28am\u012bd Ab\u016b \u1e28i\u015f\u0101n"
    ],
    "wof:name":"Hamid Abu Hisan",
    "wof:placetype":"locality"
},
  "geometry": {"coordinates":[44.98449,31.70319000000001],"type":"Point"}
}