{
  "type": "Feature",
  "properties": {
    "gn:admin1_code":"10.0",
    "gn:admin2_code":"99063.0",
    "gn:asciiname":"Qaryat ash Shaykhi",
    "gn:country_code":"IQ",
    "gn:dem":54,
    "gn:feature_class":"P",
    "gn:feature_code":"PPL",
    "gn:name":"Qaryat ash Shaykh\u012b",
    "gn:population":0,
    "gn:timezone":"Asia/Baghdad",
    "iso:country":"IQ",
    "name:ara_x_preferred":[
        "\u0642\u0631\u064a\u0629 \u0627\u0644\u0634\u064a\u062e\u064a"
    ],
    "name:und_x_variant":[
        "Qaryat ash Shaykh\u012b"
    ],
    "wof:name":"Qaryat ash Shaykhi",
    "wof:placetype":"locality"
},
  "geometry": {"coordinates":[44.76396,33.91014000000001],"type":"Point"}
}