{
  "type": "Feature",
  "properties": {
    "gn:admin1_code":"5.0",
    "gn:admin2_code":"9166600.0",
    "gn:asciiname":"Khan Rawuf Agha",
    "gn:country_code":"IQ",
    "gn:dem":439,
    "gn:feature_class":"P",
    "gn:feature_code":"PPL",
    "gn:name":"Kh\u0101n Raw\u016bf \u0100gh\u0101",
    "gn:population":0,
    "gn:timezone":"Asia/Baghdad",
    "iso:country":"IQ",
    "name:ara_x_preferred":[
        "\u062e\u0627\u0646 \u0631\u0648\u0648\u0641 \u0622\u063a\u0627"
    ],
    "name:kur_x_preferred":[
        "Xan\u00ee \u1e5ee\u00fbf Agha"
    ],
    "name:kur_x_variant":[
        "\u062e\u0627\u0646\u0649 \u0695\u06d5\u0648\u0648\u0641 \u0626\u0627\u063a\u0627",
        "\u062e\u0627\u0646 \u0695\u06d5\u0648\u0648\u0641 \u0626\u0627\u063a\u0627",
        "Xan \u1e5ee\u00fbf Agha"
    ],
    "name:und_x_variant":[
        "Kh\u0101n Raw\u016bf \u0100gh\u0101",
        "Khan-i Ra\u2019\u016bf \u0100gh\u0101",
        "Khan Rauf Agha"
    ],
    "wof:name":"Khan Rawuf Agha",
    "wof:placetype":"locality"
},
  "geometry": {"coordinates":[45.08094000000001,35.01017],"type":"Point"}
}