{
  "type": "Feature",
  "properties": {
    "gn:admin1_code":"15.0",
    "gn:admin2_code":"98612.0",
    "gn:asciiname":"Dust Qatil",
    "gn:country_code":"IQ",
    "gn:dem":407,
    "gn:feature_class":"P",
    "gn:feature_code":"PPL",
    "gn:name":"D\u016bst Qat\u012bl",
    "gn:population":0,
    "gn:timezone":"Asia/Baghdad",
    "iso:country":"IQ",
    "name:ara_x_preferred":[
        "\u062f\u0648\u0633\u062a \u0642\u062a\u064a\u0644"
    ],
    "name:kur_x_preferred":[
        "Dust Qet\u00eel"
    ],
    "name:kur_x_variant":[
        "\u062f\u0648\u0633\u062a \u0642\u06d5\u062a\u064a\u0644"
    ],
    "name:und_x_variant":[
        "D\u014dstq\u0101til",
        "D\u016bst Qat\u012bl"
    ],
    "wof:name":"Dust Qatil",
    "wof:placetype":"locality"
},
  "geometry": {"coordinates":[43.21667,36.65696],"type":"Point"}
}