{
  "type": "Feature",
  "properties": {
    "gn:admin1_code":"18.0",
    "gn:admin2_code":"90148.0",
    "gn:asciiname":"Qaryat Wahilah",
    "gn:country_code":"IQ",
    "gn:dem":129,
    "gn:feature_class":"P",
    "gn:feature_code":"PPL",
    "gn:name":"Qaryat Wa\u1e29\u012blah",
    "gn:population":0,
    "gn:timezone":"Asia/Baghdad",
    "iso:country":"IQ",
    "name:ara_x_preferred":[
        "\u0642\u0631\u064a\u0629 \u0648\u062d\u064a\u0644\u0629"
    ],
    "name:und_x_variant":[
        "Qaryat Wa\u1e29\u012blah"
    ],
    "wof:name":"Qaryat Wahilah",
    "wof:placetype":"locality"
},
  "geometry": {"coordinates":[43.75714,34.8384],"type":"Point"}
}