{
  "type": "Feature",
  "properties": {
    "gn:admin1_code":"15.0",
    "gn:admin2_code":"9166608.0",
    "gn:asciiname":"Sibayat Athari",
    "gn:country_code":"IQ",
    "gn:dem":291,
    "gn:feature_class":"P",
    "gn:feature_code":"PPL",
    "gn:name":"S\u012bb\u0101yat Athar\u012b",
    "gn:population":0,
    "gn:timezone":"Asia/Baghdad",
    "iso:country":"IQ",
    "name:ara_x_preferred":[
        "\u0633\u064a\u0628\u0627\u064a\u0647 \u0627\u062b\u0631\u064a"
    ],
    "name:und_x_variant":[
        "Shaml\u0101n",
        "\u0634\u0645\u0644\u0627\u0646",
        "S\u012bb\u0101yat Athar\u012b"
    ],
    "wof:name":"Sibayat Athari",
    "wof:placetype":"locality"
},
  "geometry": {"coordinates":[42.01663,35.8686],"type":"Point"}
}