{
  "type": "Feature",
  "properties": {
    "gn:admin1_code":"18.0",
    "gn:admin2_code":"90148.0",
    "gn:asciiname":"Qaryat 'Ali 'Ubayd",
    "gn:country_code":"IQ",
    "gn:dem":128,
    "gn:feature_class":"P",
    "gn:feature_code":"PPL",
    "gn:name":"Qaryat \u2018Al\u012b \u2018Ubayd",
    "gn:population":0,
    "gn:timezone":"Asia/Baghdad",
    "iso:country":"IQ",
    "name:ara_x_preferred":[
        "\u0642\u0631\u064a\u0629 \u0639\u0644\u064a \u0639\u0628\u064a\u062f"
    ],
    "name:und_x_variant":[
        "Qaryat \u2018Al\u012b \u2018Ubayd"
    ],
    "wof:name":"Qaryat 'Ali 'Ubayd",
    "wof:placetype":"locality"
},
  "geometry": {"coordinates":[43.43558,34.55753],"type":"Point"}
}