{
  "type": "Feature",
  "properties": {
    "gn:admin1_code":"6.0",
    "gn:admin2_code":"99040.0",
    "gn:asciiname":"Tall al Karghuli",
    "gn:country_code":"IQ",
    "gn:dem":31,
    "gn:feature_class":"P",
    "gn:feature_code":"PPL",
    "gn:name":"Tall al Kargh\u016bl\u012b",
    "gn:population":0,
    "gn:timezone":"Asia/Baghdad",
    "iso:country":"IQ",
    "name:ara_x_preferred":[
        "\u062a\u0644 \u0627\u0644\u0643\u0631\u063a\u0648\u0644\u064a"
    ],
    "name:und_x_variant":[
        "Tall al Kargh\u016bl\u012b"
    ],
    "wof:name":"Tall al Karghuli",
    "wof:placetype":"locality"
},
  "geometry": {"coordinates":[44.30889000000001,32.60428],"type":"Point"}
}