{
  "type": "Feature",
  "properties": {
    "gn:admin1_code":"14.0",
    "gn:admin2_code":"99610.0",
    "gn:asciiname":"Salaf Muslim",
    "gn:country_code":"IQ",
    "gn:dem":11,
    "gn:feature_class":"P",
    "gn:feature_code":"PPL",
    "gn:name":"Salaf Muslim",
    "gn:population":0,
    "gn:timezone":"Asia/Baghdad",
    "iso:country":"IQ",
    "name:ara_x_preferred":[
        "\u0633\u0644\u0641 \u0645\u0633\u0644\u0645"
    ],
    "name:und_x_variant":[
        "Salaf Musallam",
        "Mussalam",
        "Musallam",
        "Salaf Muslim"
    ],
    "wof:name":"Salaf Muslim",
    "wof:placetype":"locality"
},
  "geometry": {"coordinates":[46.94248,31.87925],"type":"Point"}
}