{
  "type": "Feature",
  "properties": {
    "gn:admin1_code":"3.0",
    "gn:admin2_code":"98534.0",
    "gn:asciiname":"Khabrat ash Shikhiyah",
    "gn:country_code":"IQ",
    "gn:dem":121,
    "gn:feature_class":"P",
    "gn:feature_code":"PPL",
    "gn:name":"Khabrat ash Sh\u012bkh\u012byah",
    "gn:population":0,
    "gn:timezone":"Asia/Baghdad",
    "iso:country":"IQ",
    "name:ara_x_preferred":[
        "\u062e\u0628\u0631\u0629 \u0627\u0644\u0634\u064a\u062e\u064a\u0629"
    ],
    "name:und_x_variant":[
        "Khabrat ash Sh\u012bkh\u012byah"
    ],
    "wof:name":"Khabrat ash Shikhiyah",
    "wof:placetype":"locality"
},
  "geometry": {"coordinates":[45.23327000000001,30.77189000000001],"type":"Point"}
}