{
  "type": "Feature",
  "properties": {
    "gn:admin1_code":"11.0",
    "gn:admin2_code":"9166534.0",
    "gn:asciiname":"Tolax",
    "gn:country_code":"IQ",
    "gn:dem":1367,
    "gn:feature_class":"P",
    "gn:feature_code":"PPL",
    "gn:name":"Tolax",
    "gn:population":0,
    "gn:timezone":"Asia/Baghdad",
    "iso:country":"IQ",
    "name:ara_x_preferred":[
        "\u062a\u0648\u0651\u0644\u062e\u0647"
    ],
    "name:kur_x_preferred":[
        "Qulxe"
    ],
    "name:kur_x_variant":[
        "\u0642\u0648\u0644\u062e\u06d5",
        "Tolax",
        "\u062a\u06c6\u0644\u0627\u062e"
    ],
    "name:und_x_variant":[
        "Qulkha",
        "T\u014dl\u0101kha",
        "Tawlkhah"
    ],
    "wof:name":"Tolax",
    "wof:placetype":"locality"
},
  "geometry": {"coordinates":[44.18066,37.2001],"type":"Point"}
}