{
  "type": "Feature",
  "properties": {
    "gn:admin1_code":"11.0",
    "gn:admin2_code":"9166592.0",
    "gn:asciiname":"Seran",
    "gn:country_code":"IQ",
    "gn:dem":1413,
    "gn:feature_class":"P",
    "gn:feature_code":"PPL",
    "gn:name":"S\u00ea\u1e5fan",
    "gn:population":0,
    "gn:timezone":"Asia/Baghdad",
    "iso:country":"IQ",
    "name:kur_x_preferred":[
        "S\u00ea\u1e5fan"
    ],
    "name:kur_x_variant":[
        "\u0633\u06ce\u0695\u0627\u0646"
    ],
    "wof:name":"Seran",
    "wof:placetype":"locality"
},
  "geometry": {"coordinates":[44.61395,36.92531],"type":"Point"}
}