{
  "type": "Feature",
  "properties": {
    "gn:admin1_code":"7.0",
    "gn:admin2_code":"99101.0",
    "gn:asciiname":"'Arab Ibrahim Hamadi",
    "gn:country_code":"IQ",
    "gn:dem":32,
    "gn:feature_class":"P",
    "gn:feature_code":"PPL",
    "gn:name":"\u2018Arab Ibr\u0101h\u012bm \u1e28am\u0101d\u012b",
    "gn:population":0,
    "gn:timezone":"Asia/Baghdad",
    "iso:country":"IQ",
    "name:ara_x_preferred":[
        "\u0639\u0631\u0628 \u0627\u0628\u0631\u0627\u0647\u064a\u0645 \u062d\u0645\u0627\u062f\u064a"
    ],
    "name:und_x_variant":[
        "\u2018Arab Ibr\u0101h\u012bm \u1e28am\u0101d\u012b"
    ],
    "wof:name":"'Arab Ibrahim Hamadi",
    "wof:placetype":"locality"
},
  "geometry": {"coordinates":[44.40321,32.90336],"type":"Point"}
}