{
  "type": "Feature",
  "properties": {
    "gn:admin1_code":"11.0",
    "gn:admin2_code":"93817.0",
    "gn:asciiname":"Du Karkan Hajji Husayn",
    "gn:country_code":"IQ",
    "gn:dem":235,
    "gn:feature_class":"P",
    "gn:feature_code":"PPL",
    "gn:name":"D\u016b Kark\u0101n \u1e28\u0101jj\u012b \u1e28usayn",
    "gn:population":0,
    "gn:timezone":"Asia/Baghdad",
    "iso:country":"IQ",
    "name:ara_x_preferred":[
        "\u062f\u0648 \u0643\u0631\u0643\u0627\u0646 \u062d\u0627\u062c\u064a \u062d\u0633\u064a\u0646"
    ],
    "name:kur_x_preferred":[
        "Dugrkan"
    ],
    "name:kur_x_variant":[
        "\u062f\u0648\u06af\u0631\u0643\u0627\u0646"
    ],
    "name:und_x_variant":[
        "D\u016b Kark\u0101n \u1e28\u0101jj\u012b \u1e28usayn"
    ],
    "wof:name":"Du Karkan Hajji Husayn",
    "wof:placetype":"locality"
},
  "geometry": {"coordinates":[43.47431,35.78431],"type":"Point"}
}