{
  "type": "Feature",
  "properties": {
    "gn:admin1_code":"9.0",
    "gn:admin2_code":"98623.0",
    "gn:asciiname":"Muhammad al Mulla Hasan",
    "gn:cc2":"IQ",
    "gn:country_code":"IQ",
    "gn:dem":7,
    "gn:feature_class":"P",
    "gn:feature_code":"PPL",
    "gn:name":"Mu\u1e29ammad al Mull\u0101 \u1e28asan",
    "gn:population":0,
    "gn:timezone":"Asia/Baghdad",
    "iso:country":"IQ",
    "name:und_x_variant":[
        "Muhammad al Mullan Husain",
        "Mu\u1e29ammad al Mull\u0101 \u1e28asan"
    ],
    "wof:name":"Muhammad al Mulla Hasan",
    "wof:placetype":"locality"
},
  "geometry": {"coordinates":[46.23333,31.38333],"type":"Point"}
}