{
  "type": "Feature",
  "properties": {
    "gn:admin1_code":"18.0",
    "gn:admin2_code":"6872046.0",
    "gn:asciiname":"'Ablush Muhammad",
    "gn:country_code":"IQ",
    "gn:dem":126,
    "gn:feature_class":"P",
    "gn:feature_code":"PPL",
    "gn:name":"\u2018Abl\u016bsh Mu\u1e29ammad",
    "gn:population":0,
    "gn:timezone":"Asia/Baghdad",
    "iso:country":"IQ",
    "name:ara_x_preferred":[
        "\u0639\u0628\u0644\u0648\u0634 \u0645\u062d\u0645\u062f"
    ],
    "name:und_x_variant":[
        "\u2018Abl\u016bsh Mu\u1e29ammad"
    ],
    "wof:name":"'Ablush Muhammad",
    "wof:placetype":"locality"
},
  "geometry": {"coordinates":[43.1794,34.82796],"type":"Point"}
}