{
  "type": "Feature",
  "properties": {
    "gn:admin1_code":"10.0",
    "gn:admin2_code":"9166680.0",
    "gn:asciiname":"Dawud ash Shatb",
    "gn:country_code":"IQ",
    "gn:dem":47,
    "gn:feature_class":"P",
    "gn:feature_code":"PPL",
    "gn:name":"D\u0101wud ash Sha\u0163b",
    "gn:population":0,
    "gn:timezone":"Asia/Baghdad",
    "iso:country":"IQ",
    "name:ara_x_preferred":[
        "\u062f\u0627\u0648\u062f \u0627\u0644\u0634\u0637\u0628"
    ],
    "name:und_x_variant":[
        "D\u0101w\u016bd",
        "D\u0101wud ash Sha\u0163b"
    ],
    "wof:name":"Dawud ash Shatb",
    "wof:placetype":"locality"
},
  "geometry": {"coordinates":[45.3374,33.5914],"type":"Point"}
}