{
  "type": "Feature",
  "properties": {
    "gn:admin1_code":"9.0",
    "gn:asciiname":"Hamad al `Abd Allah",
    "gn:country_code":"IQ",
    "gn:dem":8,
    "gn:feature_class":"P",
    "gn:feature_code":"PPL",
    "gn:name":"\u1e28amad al \u2018Abd All\u0101h",
    "gn:population":0,
    "gn:timezone":"Asia/Baghdad",
    "iso:country":"IQ",
    "name:ara_x_preferred":[
        "\u062d\u0645\u062f \u0627\u0644\u0639\u0628\u062f\u0627\u0644\u0644\u0647"
    ],
    "name:und_x_variant":[
        "Hatmad al Falq",
        "\u1e28amad al Falq",
        "\u1e28amad al \u2018Abd All\u0101h"
    ],
    "wof:name":"Hamad al `Abd Allah",
    "wof:placetype":"locality"
},
  "geometry": {"coordinates":[45.8002,31.14947],"type":"Point"}
}