{
  "type": "Feature",
  "properties": {
    "gn:admin1_code":"18.0",
    "gn:admin2_code":"6804454.0",
    "gn:asciiname":"Qaryat Masihuj",
    "gn:country_code":"IQ",
    "gn:dem":200,
    "gn:feature_class":"P",
    "gn:feature_code":"PPL",
    "gn:name":"Qaryat Masih\u016bj",
    "gn:population":0,
    "gn:timezone":"Asia/Baghdad",
    "iso:country":"IQ",
    "name:ara_x_preferred":[
        "\u0642\u0631\u064a\u0629 \u0645\u0633\u0647\u0648\u062c"
    ],
    "name:und_x_variant":[
        "Qaryat Masih\u016bj"
    ],
    "wof:name":"Qaryat Masihuj",
    "wof:placetype":"locality"
},
  "geometry": {"coordinates":[43.16352,35.29296],"type":"Point"}
}