{
  "type": "Feature",
  "properties": {
    "gn:admin1_code":"11.0",
    "gn:admin2_code":"9166534.0",
    "gn:asciiname":"Guzgah",
    "gn:country_code":"IQ",
    "gn:dem":1347,
    "gn:feature_class":"P",
    "gn:feature_code":"PPL",
    "gn:name":"G\u016bzgah",
    "gn:population":0,
    "gn:timezone":"Asia/Baghdad",
    "iso:country":"IQ",
    "name:ara_x_preferred":[
        "\u06af\u0648\u0632\u06af\u0647"
    ],
    "name:kur_x_preferred":[
        "G\u00eesk\u00ea"
    ],
    "name:kur_x_variant":[
        "\u06af\u064a\u0633\u0643\u06ce",
        "Gurk\u00ea",
        "\u06af\u0648\u0631\u0643\u06ce"
    ],
    "name:und_x_variant":[
        "G\u016bzgah",
        "Gurke",
        "Giske"
    ],
    "wof:name":"Guzgah",
    "wof:placetype":"locality"
},
  "geometry": {"coordinates":[44.3355,36.85474],"type":"Point"}
}