{
  "type": "Feature",
  "properties": {
    "gn:admin1_code":"10.0",
    "gn:admin2_code":"94590.0",
    "gn:asciiname":"Khalaf al Jasim",
    "gn:cc2":"IQ",
    "gn:country_code":"IQ",
    "gn:dem":95,
    "gn:feature_class":"P",
    "gn:feature_code":"PPL",
    "gn:name":"Khalaf al J\u0101sim",
    "gn:population":0,
    "gn:timezone":"Asia/Baghdad",
    "iso:country":"IQ",
    "name:und_x_variant":[
        "Khalaf al Jassim",
        "Khalaf al J\u0101sim"
    ],
    "wof:name":"Khalaf al Jasim",
    "wof:placetype":"locality"
},
  "geometry": {"coordinates":[45.01667,34.21667],"type":"Point"}
}