{
  "type": "Feature",
  "properties": {
    "gn:admin1_code":"18.0",
    "gn:admin2_code":"9166616.0",
    "gn:asciiname":"Mu'jab Mujbil",
    "gn:country_code":"IQ",
    "gn:dem":39,
    "gn:feature_class":"P",
    "gn:feature_code":"PPL",
    "gn:name":"Mu\u2018jab Mujbil",
    "gn:population":0,
    "gn:timezone":"Asia/Baghdad",
    "iso:country":"IQ",
    "name:ara_x_preferred":[
        "\u0645\u0639\u062c\u0628 \u0645\u062c\u0628\u0644"
    ],
    "name:und_x_variant":[
        "Mu\u2018jab Mujbil"
    ],
    "wof:name":"Mu'jab Mujbil",
    "wof:placetype":"locality"
},
  "geometry": {"coordinates":[44.01759000000001,33.68794],"type":"Point"}
}