{
  "type": "Feature",
  "properties": {
    "gn:admin1_code":"7.0",
    "gn:admin2_code":"99101.0",
    "gn:asciiname":"Tall Umm Kufayshah",
    "gn:country_code":"IQ",
    "gn:dem":38,
    "gn:feature_class":"P",
    "gn:feature_code":"PPLL",
    "gn:name":"Tall Umm Kufayshah",
    "gn:population":0,
    "gn:timezone":"Asia/Baghdad",
    "iso:country":"IQ",
    "name:ara_x_preferred":[
        "\u062a\u0644 \u0623\u0645 \u0643\u0641\u064a\u0634\u0629"
    ],
    "wof:name":"Tall Umm Kufayshah",
    "wof:placetype":"locality"
},
  "geometry": {"coordinates":[44.06589,33.21896],"type":"Point"}
}