{
  "type": "Feature",
  "properties": {
    "gn:admin1_code":"14.0",
    "gn:admin2_code":"92536.0",
    "gn:asciiname":"Abu Rubah",
    "gn:cc2":"IQ",
    "gn:country_code":"IQ",
    "gn:dem":7,
    "gn:feature_class":"P",
    "gn:feature_code":"PPL",
    "gn:name":"Ab\u016b R\u016bbah",
    "gn:population":0,
    "gn:timezone":"Asia/Baghdad",
    "iso:country":"IQ",
    "name:und_x_variant":[
        "Ab\u016b R\u016bba",
        "Ab\u016b Riy\u0101\u1e29",
        "Ab\u016b R\u016bbah"
    ],
    "wof:name":"Abu Rubah",
    "wof:placetype":"locality"
},
  "geometry": {"coordinates":[47.36667,31.43333],"type":"Point"}
}