{
  "type": "Feature",
  "properties": {
    "gn:admin1_code":"9.0",
    "gn:admin2_code":"98623.0",
    "gn:asciiname":"Jama'at Muhammad",
    "gn:country_code":"IQ",
    "gn:dem":7,
    "gn:feature_class":"P",
    "gn:feature_code":"PPL",
    "gn:name":"Jam\u0101\u2018at Mu\u1e29ammad",
    "gn:population":0,
    "gn:timezone":"Asia/Baghdad",
    "iso:country":"IQ",
    "name:und_x_variant":[
        "Jam\u0101\u2018at al Muhammad",
        "Jam\u0101\u2018at Mu\u1e29ammad"
    ],
    "wof:name":"Jama'at Muhammad",
    "wof:placetype":"locality"
},
  "geometry": {"coordinates":[46.34778,31.45222],"type":"Point"}
}