{
  "type": "Feature",
  "properties": {
    "gn:admin1_code":"15.0",
    "gn:admin2_code":"9166649.0",
    "gn:asciiname":"Qaryat al Jurn",
    "gn:country_code":"IQ",
    "gn:dem":301,
    "gn:feature_class":"P",
    "gn:feature_code":"PPL",
    "gn:name":"Qaryat al Jurn",
    "gn:population":0,
    "gn:timezone":"Asia/Baghdad",
    "iso:country":"IQ",
    "name:ara_x_preferred":[
        "\u0642\u0631\u064a\u0629 \u0627\u0644\u062c\u0631\u0646"
    ],
    "name:und_x_variant":[
        "Jirin",
        "Jurn",
        "\u062c\u0631\u0646",
        "Qaryat al Jurn",
        "Jurn 1"
    ],
    "wof:name":"Qaryat al Jurn",
    "wof:placetype":"locality"
},
  "geometry": {"coordinates":[42.99963,36.13955],"type":"Point"}
}