{
  "type": "Feature",
  "properties": {
    "gn:admin1_code":"11.0",
    "gn:admin2_code":"9166588.0",
    "gn:asciiname":"Bani Maran",
    "gn:country_code":"IQ",
    "gn:dem":557,
    "gn:feature_class":"P",
    "gn:feature_code":"PPL",
    "gn:name":"B\u0101n\u012b M\u0101r\u0101n",
    "gn:population":0,
    "gn:timezone":"Asia/Baghdad",
    "iso:country":"IQ",
    "name:ara_x_preferred":[
        "\u0628\u0627\u0646\u064a \u0645\u0627\u0631\u0627\u0646"
    ],
    "name:ara_x_variant":[
        "B\u0101n\u012b M\u0101r\u0101n"
    ],
    "name:fra_x_preferred":[
        "Banimaran"
    ],
    "name:kur_x_preferred":[
        "Ban\u00ee Maran"
    ],
    "name:kur_x_variant":[
        "\u0628\u0627\u0646\u0649 \u0645\u0627\u0631\u0627\u0646"
    ],
    "name:und_x_variant":[
        "Bany Maran"
    ],
    "wof:name":"Bani Maran",
    "wof:placetype":"locality"
},
  "geometry": {"coordinates":[44.38208,36.04599],"type":"Point"}
}