{
  "type": "Feature",
  "properties": {
    "gn:admin1_code":"15.0",
    "gn:admin2_code":"90392.0",
    "gn:asciiname":"Tall Wardan",
    "gn:country_code":"IQ",
    "gn:dem":348,
    "gn:feature_class":"P",
    "gn:feature_code":"PPL",
    "gn:name":"Tall Ward\u0101n",
    "gn:population":0,
    "gn:timezone":"Asia/Baghdad",
    "iso:country":"IQ",
    "name:ara_x_preferred":[
        "\u062a\u0644 \u0648\u0631\u062f\u0627\u0646"
    ],
    "name:kur_x_preferred":[
        "Tel Werdan"
    ],
    "name:kur_x_variant":[
        "\u062a\u06d5\u0644 \u0648\u06d5\u0631\u062f\u0627\u0646"
    ],
    "name:und_x_variant":[
        "Til Wardan",
        "Tall Ward\u0101n"
    ],
    "wof:name":"Tall Wardan",
    "wof:placetype":"locality"
},
  "geometry": {"coordinates":[42.35269,36.71675],"type":"Point"}
}