{
  "type": "Feature",
  "properties": {
    "gn:admin1_code":"17.0",
    "gn:admin2_code":"9166552.0",
    "gn:asciiname":"Halas Jabbar",
    "gn:country_code":"IQ",
    "gn:dem":24,
    "gn:feature_class":"P",
    "gn:feature_code":"PPL",
    "gn:name":"\u1e28ala\u015f Jabb\u0101r",
    "gn:population":0,
    "gn:timezone":"Asia/Baghdad",
    "iso:country":"IQ",
    "name:ara_x_preferred":[
        "\u062d\u0644\u0635 \u062c\u0628\u0627\u0631"
    ],
    "name:und_x_variant":[
        "\u1e28ala\u015f Jabb\u0101r"
    ],
    "wof:name":"Halas Jabbar",
    "wof:placetype":"locality"
},
  "geometry": {"coordinates":[44.49325,31.87909],"type":"Point"}
}