{
  "type": "Feature",
  "properties": {
    "gn:admin1_code":"10.0",
    "gn:admin2_code":"94590.0",
    "gn:asciiname":"'Arab Jawamir",
    "gn:country_code":"IQ",
    "gn:dem":107,
    "gn:feature_class":"P",
    "gn:feature_code":"PPL",
    "gn:name":"\u2018Arab Jaw\u0101m\u012br",
    "gn:population":0,
    "gn:timezone":"Asia/Baghdad",
    "iso:country":"IQ",
    "name:ara_x_preferred":[
        "\u0639\u0631\u0628 \u062c\u0648\u0627\u0645\u064a\u0631"
    ],
    "name:und_x_variant":[
        "Arab Juw\u0101m\u0113r",
        "\u2018Arab Jaw\u0101m\u012br"
    ],
    "wof:name":"'Arab Jawamir",
    "wof:placetype":"locality"
},
  "geometry": {"coordinates":[45.1304,34.1448],"type":"Point"}
}