{
  "type": "Feature",
  "properties": {
    "gn:admin1_code":"5.0",
    "gn:admin2_code":"9166600.0",
    "gn:asciiname":"Khani Mahmud Basha",
    "gn:cc2":"IQ",
    "gn:country_code":"IQ",
    "gn:dem":258,
    "gn:feature_class":"P",
    "gn:feature_code":"PPL",
    "gn:name":"Kh\u0101n\u012b Ma\u1e29m\u016bd B\u0101sh\u0101",
    "gn:population":0,
    "gn:timezone":"Asia/Baghdad",
    "iso:country":"IQ",
    "name:und_x_variant":[
        "Ma\u1e29m\u016bd P\u0101sh\u0101 Kh\u0101n\u012b",
        "Kh\u0101n-i-Mahm\u016bd P\u0101sha",
        "Kh\u0101n\u012b Ma\u1e29m\u016bd B\u0101sh\u0101"
    ],
    "wof:name":"Khani Mahmud Basha",
    "wof:placetype":"locality"
},
  "geometry": {"coordinates":[45.43333,34.68333],"type":"Point"}
}