{
  "type": "Feature",
  "properties": {
    "gn:admin1_code":"15.0",
    "gn:admin2_code":"98820.0",
    "gn:asciiname":"Wiriyah",
    "gn:country_code":"IQ",
    "gn:dem":674,
    "gn:feature_class":"P",
    "gn:feature_code":"PPL",
    "gn:name":"Wir\u012byah",
    "gn:population":0,
    "gn:timezone":"Asia/Baghdad",
    "iso:country":"IQ",
    "name:ara_x_preferred":[
        "\u0648\u0631\u064a\u06d5"
    ],
    "name:kur_x_preferred":[
        "S\u00fbriyan"
    ],
    "name:kur_x_variant":[
        "Suriya",
        "Wiriye",
        "\u0633\u0648\u0648\u0631\u064a\u0627\u0646",
        "\u0633\u0648\u0631\u064a\u0627"
    ],
    "name:und_x_variant":[
        "Wariya",
        "Wir\u012byah",
        "Wria",
        "Surya"
    ],
    "wof:name":"Wiriyah",
    "wof:placetype":"locality"
},
  "geometry": {"coordinates":[44.16301,36.70349],"type":"Point"}
}