{
  "type": "Feature",
  "properties": {
    "gn:admin1_code":"10.0",
    "gn:admin2_code":"99063.0",
    "gn:asciiname":"Qaryat as Sadimah",
    "gn:country_code":"IQ",
    "gn:dem":60,
    "gn:feature_class":"P",
    "gn:feature_code":"PPL",
    "gn:name":"Qaryat as Sad\u012bmah",
    "gn:population":0,
    "gn:timezone":"Asia/Baghdad",
    "iso:country":"IQ",
    "name:ara_x_preferred":[
        "\u0642\u0631\u064a\u0629 \u0627\u0644\u0633\u062f\u064a\u0645\u0629"
    ],
    "name:und_x_variant":[
        "As Sad\u012bmah",
        "\u0627\u0644\u0633\u062f\u064a\u0645\u0629",
        "Qaryat as Sad\u012bmah"
    ],
    "wof:name":"Qaryat as Sadimah",
    "wof:placetype":"locality"
},
  "geometry": {"coordinates":[44.94531,33.97564],"type":"Point"}
}