{
  "type": "Feature",
  "properties": {
    "gn:admin1_code":"15.0",
    "gn:admin2_code":"9166620.0",
    "gn:asciiname":"Marus Asibayah - Ash Sharqiyah",
    "gn:country_code":"IQ",
    "gn:dem":329,
    "gn:feature_class":"P",
    "gn:feature_code":"PPL",
    "gn:name":"Mar\u016bs As\u012bb\u0101yah - Ash Sharq\u012byah",
    "gn:population":0,
    "gn:timezone":"Asia/Baghdad",
    "iso:country":"IQ",
    "name:ara_x_preferred":[
        "\u0645\u0631\u0648\u0633 \u0627\u0633\u064a\u0628\u0627\u064a\u0629 - \u0627\u0644\u0634\u0631\u0642\u064a\u0629"
    ],
    "name:und_x_variant":[
        "Sibya",
        "Mar\u016bs As\u012bb\u0101yah - Ash Sharq\u012byah"
    ],
    "wof:name":"Marus Asibayah - Ash Sharqiyah",
    "wof:placetype":"locality"
},
  "geometry": {"coordinates":[42.1247,36.22651],"type":"Point"}
}