{
  "type": "Feature",
  "properties": {
    "gn:admin1_code":"15.0",
    "gn:admin2_code":"98612.0",
    "gn:asciiname":"Baybawzi",
    "gn:country_code":"IQ",
    "gn:dem":833,
    "gn:feature_class":"P",
    "gn:feature_code":"PPL",
    "gn:name":"Baybawz\u012b",
    "gn:population":0,
    "gn:timezone":"Asia/Baghdad",
    "iso:country":"IQ",
    "name:ara_x_preferred":[
        "\u0628\u064a\u0628\u0648\u0632\u064a"
    ],
    "name:kur_x_preferred":[
        "B\u00eaboz\u00ee"
    ],
    "name:kur_x_variant":[
        "\u0628\u06ce\u0628\u06c6\u0632\u0649",
        "B\u00eaboz\u00ea",
        "\u0628\u06ce\u0628\u06c6\u0632\u06ce"
    ],
    "name:und_x_variant":[
        "B\u012bboz\u012b",
        "Bibozy",
        "Baybawz\u012b",
        "Beboze"
    ],
    "wof:name":"Baybawzi",
    "wof:placetype":"locality"
},
  "geometry": {"coordinates":[43.31554000000001,36.88541],"type":"Point"}
}