{
  "type": "Feature",
  "properties": {
    "gn:admin1_code":"5.0",
    "gn:admin2_code":"9166600.0",
    "gn:asciiname":"Zanfikat 'Ali Wasman",
    "gn:country_code":"IQ",
    "gn:dem":577,
    "gn:feature_class":"P",
    "gn:feature_code":"PPL",
    "gn:name":"Zanfikat \u2018Al\u012b Wasm\u0101n",
    "gn:population":0,
    "gn:timezone":"Asia/Baghdad",
    "iso:country":"IQ",
    "name:ara_x_preferred":[
        "\u0632\u0646\u0641\u0643\u0629 \u0639\u0644\u064a \u0648\u0633\u0645\u0627\u0646"
    ],
    "name:kur_x_preferred":[
        "Zemawengey Ser\u00fb"
    ],
    "name:kur_x_variant":[
        "\u0632\u06d5\u0645\u0627\u0648\u06d5\u0646\u06af\u06d5\u0649 \u0633\u06d5\u0631\u0648\u0648"
    ],
    "name:und_x_variant":[
        "Zanfikat \u2018Al\u012b Wasm\u0101n",
        "Z\u0101nfiga-i \u2018Ali Wusm\u0101n",
        "\u2018Al\u012b Dusm\u0101n",
        "Zanfikah",
        "Zanifk\u0101",
        "\u0632\u0646\u0641\u0643\u0627",
        "\u0639\u0644\u064a \u062f\u0633\u0645\u0627\u0646"
    ],
    "wof:name":"Zanfikat 'Ali Wasman",
    "wof:placetype":"locality"
},
  "geometry": {"coordinates":[45.39925,34.89139],"type":"Point"}
}