{
  "type": "Feature",
  "properties": {
    "gn:admin1_code":"8.0",
    "gn:admin2_code":"97269.0",
    "gn:asciiname":"Gund Kuse",
    "gn:country_code":"IQ",
    "gn:dem":585,
    "gn:feature_class":"P",
    "gn:feature_code":"PPL",
    "gn:name":"Gund Kuse",
    "gn:population":0,
    "gn:timezone":"Asia/Baghdad",
    "iso:country":"IQ",
    "name:ara_x_preferred":[
        "\u0643\u0648\u0646\u062f \u0643\u0648\u0633\u0647"
    ],
    "name:kur_x_preferred":[
        "Kose"
    ],
    "name:kur_x_variant":[
        "\u0643\u06c6\u0633\u06d5",
        "Gund Kuse",
        "\u06af\u0648\u0646\u062f \u0643\u0648\u0633\u0647"
    ],
    "name:und_x_variant":[
        "Gundk\u014dsa",
        "Kosa",
        "K\u016bnd K\u016bsah",
        "Gundkusa"
    ],
    "wof:name":"Gund Kuse",
    "wof:placetype":"locality"
},
  "geometry": {"coordinates":[42.94385,37.09173],"type":"Point"}
}