{
  "type": "Feature",
  "properties": {
    "gn:admin1_code":"17.0",
    "gn:admin2_code":"9166629.0",
    "gn:asciiname":"Muhammad Khashan",
    "gn:country_code":"IQ",
    "gn:dem":27,
    "gn:feature_class":"P",
    "gn:feature_code":"PPL",
    "gn:name":"Mu\u1e29ammad Khash\u0101n",
    "gn:population":0,
    "gn:timezone":"Asia/Baghdad",
    "iso:country":"IQ",
    "name:ara_x_preferred":[
        "\u0645\u062d\u0645\u062f \u062e\u0634\u0627\u0646"
    ],
    "name:und_x_variant":[
        "Mu\u1e29ammad Khash\u0101n"
    ],
    "wof:name":"Muhammad Khashan",
    "wof:placetype":"locality"
},
  "geometry": {"coordinates":[44.54161,32.08827],"type":"Point"}
}