{
  "type": "Feature",
  "properties": {
    "gn:admin1_code":"5.0",
    "gn:admin2_code":"92743.0",
    "gn:asciiname":"Barikan",
    "gn:country_code":"IQ",
    "gn:dem":1026,
    "gn:feature_class":"P",
    "gn:feature_code":"PPL",
    "gn:name":"Barikan",
    "gn:population":0,
    "gn:timezone":"Asia/Baghdad",
    "iso:country":"IQ",
    "name:ara_x_preferred":[
        "B\u0101r\u012bk\u0101n"
    ],
    "name:ara_x_variant":[
        "\u0628\u0627\u0631\u064a\u0643\u0627\u0646"
    ],
    "name:kur_x_preferred":[
        "Bar\u00eekan"
    ],
    "wof:name":"Barikan",
    "wof:placetype":"locality"
},
  "geometry": {"coordinates":[45.0913,36.36318],"type":"Point"}
}