{
  "type": "Feature",
  "properties": {
    "gn:admin1_code":"10.0",
    "gn:admin2_code":"9166680.0",
    "gn:asciiname":"Jahiz",
    "gn:country_code":"IQ",
    "gn:dem":67,
    "gn:feature_class":"P",
    "gn:feature_code":"PPL",
    "gn:name":"J\u0101\u1e29iz\u0327",
    "gn:population":0,
    "gn:timezone":"Asia/Baghdad",
    "iso:country":"IQ",
    "name:ara_x_preferred":[
        "J\u0101\u1e29iz\u0327"
    ],
    "wof:name":"Jahiz",
    "wof:placetype":"locality"
},
  "geometry": {"coordinates":[45.21667,33.91667],"type":"Point"}
}