{
  "type": "Feature",
  "properties": {
    "gn:admin1_code":"5.0",
    "gn:admin2_code":"9166684.0",
    "gn:asciiname":"Daru Khan",
    "gn:country_code":"IQ",
    "gn:dem":1343,
    "gn:feature_class":"P",
    "gn:feature_code":"PPL",
    "gn:name":"D\u0101r\u016b Kh\u0101n",
    "gn:population":0,
    "gn:timezone":"Asia/Baghdad",
    "iso:country":"IQ",
    "name:fas_x_preferred":[
        "\u062f\u0627\u0631\u0648\u062e\u0627\u0646"
    ],
    "wof:name":"Daru Khan",
    "wof:placetype":"locality"
},
  "geometry": {"coordinates":[46.0765,35.7968],"type":"Point"}
}