{
  "type": "Feature",
  "properties": {
    "gn:admin1_code":"6.0",
    "gn:admin2_code":"99358.0",
    "gn:asciiname":"'Ubayd Al Jasim",
    "gn:country_code":"IQ",
    "gn:dem":25,
    "gn:feature_class":"P",
    "gn:feature_code":"PPL",
    "gn:name":"\u2018Ubayd \u0100l J\u0101sim",
    "gn:population":0,
    "gn:timezone":"Asia/Baghdad",
    "iso:country":"IQ",
    "name:ara_x_preferred":[
        "\u0639\u0628\u064a\u062f \u0622\u0644 \u062c\u0627\u0633\u0645"
    ],
    "name:und_x_variant":[
        "\u2018Ubayd \u0100l J\u0101sim"
    ],
    "wof:name":"'Ubayd Al Jasim",
    "wof:placetype":"locality"
},
  "geometry": {"coordinates":[44.57734,32.32078],"type":"Point"}
}