{
  "type": "Feature",
  "properties": {
    "gn:admin1_code":"15.0",
    "gn:admin2_code":"99414.0",
    "gn:asciiname":"Tall Rujm Marhir al Kabir",
    "gn:country_code":"IQ",
    "gn:dem":215,
    "gn:feature_class":"P",
    "gn:feature_code":"PPL",
    "gn:name":"Tall Rujm Marh\u012br al Kab\u012br",
    "gn:population":0,
    "gn:timezone":"Asia/Baghdad",
    "iso:country":"IQ",
    "name:ara_x_preferred":[
        "\u062a\u0644 \u0631\u062c\u0645 \u0645\u0631\u0647\u064a\u0631 \u0627\u0644\u0643\u0628\u064a\u0631"
    ],
    "name:und_x_variant":[
        "Tall Rujm Marh\u012br al Kab\u012br"
    ],
    "wof:name":"Tall Rujm Marhir al Kabir",
    "wof:placetype":"locality"
},
  "geometry": {"coordinates":[42.61626,35.79685],"type":"Point"}
}