{
  "type": "Feature",
  "properties": {
    "gn:admin1_code":"5.0",
    "gn:admin2_code":"92743.0",
    "gn:asciiname":"Spiye Herme",
    "gn:country_code":"IQ",
    "gn:dem":1136,
    "gn:feature_class":"P",
    "gn:feature_code":"PPLL",
    "gn:name":"Spiye Herm\u00ea",
    "gn:population":0,
    "gn:timezone":"Asia/Baghdad",
    "iso:country":"IQ",
    "name:kur_x_preferred":[
        "Spiye Herm\u00ea"
    ],
    "name:kur_x_variant":[
        "\u0633\u067e\u064a\u06d5 \u06be\u06d5\u0631\u0645\u06ce"
    ],
    "name:und_x_variant":[
        "Spya Harme"
    ],
    "wof:name":"Spiye Herme",
    "wof:placetype":"locality"
},
  "geometry": {"coordinates":[45.27349,36.20244],"type":"Point"}
}