{
  "type": "Feature",
  "properties": {
    "gn:admin1_code":"10.0",
    "gn:admin2_code":"9166680.0",
    "gn:asciiname":"Khalil Ibrahim",
    "gn:country_code":"IQ",
    "gn:dem":42,
    "gn:feature_class":"P",
    "gn:feature_code":"PPL",
    "gn:name":"Khal\u012bl Ibr\u0101h\u012bm",
    "gn:population":0,
    "gn:timezone":"Asia/Baghdad",
    "iso:country":"IQ",
    "name:ara_x_preferred":[
        "\u062e\u0644\u064a\u0644 \u0627\u0628\u0631\u0627\u0647\u064a\u0645"
    ],
    "name:ara_x_variant":[
        "\u062e\u0644\u064a\u0644 \u0625\u0628\u0631\u0627\u0647\u064a\u0645"
    ],
    "name:deu_x_preferred":[
        "Khalil Ibrahim"
    ],
    "name:ell_x_preferred":[
        "\u03a7\u03b1\u03bb\u03af\u03bb \u0399\u03bc\u03c0\u03c1\u03b1\u03ae\u03bc"
    ],
    "name:pol_x_preferred":[
        "Chalil Ibrahim"
    ],
    "name:swe_x_preferred":[
        "Khalil Ibrahim"
    ],
    "name:und_x_variant":[
        "Ibr\u0101h\u012bm",
        "Khal\u012bl Ibr\u0101h\u012bm"
    ],
    "wof:name":"Khalil Ibrahim",
    "wof:placetype":"locality"
},
  "geometry": {"coordinates":[44.91088,33.65389],"type":"Point"}
}