{
  "type": "Feature",
  "properties": {
    "gn:admin1_code":"8.0",
    "gn:admin2_code":"89569.0",
    "gn:asciiname":"Serko",
    "gn:country_code":"IQ",
    "gn:dem":843,
    "gn:feature_class":"P",
    "gn:feature_code":"PPL",
    "gn:name":"Serko",
    "gn:population":0,
    "gn:timezone":"Asia/Baghdad",
    "iso:country":"IQ",
    "name:ara_x_preferred":[
        "\u0633\u0631\u064a \u0628\u064a\u0633\u064a\u0644\u0647"
    ],
    "name:kur_x_preferred":[
        "Ser\u00ee B\u00ea S\u00eele"
    ],
    "name:kur_x_variant":[
        "\u0633\u06d5\u0631\u0649 \u0628\u06ce \u0633\u064a\u0644\u06d5",
        "Serko",
        "\u0633\u06d5\u0631\u0643\u06c6"
    ],
    "name:und_x_variant":[
        "Sar\u0113b\u012bs\u012bla",
        "Sary Besila",
        "Sar\u012b Bays\u012blah",
        "Sarke Besile"
    ],
    "wof:name":"Serko",
    "wof:placetype":"locality"
},
  "geometry": {"coordinates":[43.07927,37.22136],"type":"Point"}
}