{
  "type": "Feature",
  "properties": {
    "gn:admin1_code":"5.0",
    "gn:admin2_code":"91176.0",
    "gn:asciiname":"Gankawah",
    "gn:country_code":"IQ",
    "gn:dem":956,
    "gn:feature_class":"P",
    "gn:feature_code":"PPL",
    "gn:name":"Gank\u0101wah",
    "gn:population":0,
    "gn:timezone":"Asia/Baghdad",
    "iso:country":"IQ",
    "name:ara_x_preferred":[
        "\u0643\u0646\u0643\u0627\u0648\u0629"
    ],
    "name:ara_x_variant":[
        "\u06af\u0646\u0643\u0627\u0648\u0629"
    ],
    "name:kur_x_preferred":[
        "Genkaw"
    ],
    "name:kur_x_variant":[
        "\u06af\u06d5\u0646\u0643\u0627\u0648"
    ],
    "name:und_x_variant":[
        "Kank\u0101wah",
        "Gank\u0101wah",
        "Gankaw",
        "Gank\u0113wa"
    ],
    "wof:name":"Gankawah",
    "wof:placetype":"locality"
},
  "geometry": {"coordinates":[45.49975,35.70624],"type":"Point"}
}