{
  "type": "Feature",
  "properties": {
    "gn:admin1_code":"9.0",
    "gn:admin2_code":"98855.0",
    "gn:asciiname":"Al Falihiyah",
    "gn:country_code":"IQ",
    "gn:dem":9,
    "gn:feature_class":"P",
    "gn:feature_code":"PPL",
    "gn:name":"Al F\u0101li\u1e29\u012byah",
    "gn:population":0,
    "gn:timezone":"Asia/Baghdad",
    "iso:country":"IQ",
    "name:ara_x_preferred":[
        "\u0627\u0644\u0641\u0627\u0644\u062d\u064a\u0629"
    ],
    "name:und_x_variant":[
        "Al F\u0101li\u1e29\u012byah"
    ],
    "wof:name":"Al Falihiyah",
    "wof:placetype":"locality"
},
  "geometry": {"coordinates":[45.81644,31.14927],"type":"Point"}
}