{
  "type": "Feature",
  "properties": {
    "gn:admin1_code":"4.0",
    "gn:admin2_code":"6850588.0",
    "gn:asciiname":"Sayyid Falih",
    "gn:country_code":"IQ",
    "gn:dem":20,
    "gn:feature_class":"P",
    "gn:feature_code":"PPL",
    "gn:name":"Sayyid Fal\u012b\u1e29",
    "gn:population":0,
    "gn:timezone":"Asia/Baghdad",
    "iso:country":"IQ",
    "name:ara_x_preferred":[
        "\u0633\u064a\u062f \u0641\u0644\u064a\u062d"
    ],
    "name:und_x_variant":[
        "Saiyid Fal\u012bh",
        "Sayyid Fal\u012b\u1e29"
    ],
    "wof:name":"Sayyid Falih",
    "wof:placetype":"locality"
},
  "geometry": {"coordinates":[44.76881,31.48311],"type":"Point"}
}