{
  "type": "Feature",
  "properties": {
    "gn:admin1_code":"1.0",
    "gn:admin2_code":"99455.0",
    "gn:asciiname":"Hasan as Salim",
    "gn:country_code":"IQ",
    "gn:dem":36,
    "gn:feature_class":"P",
    "gn:feature_code":"PPL",
    "gn:name":"\u1e28asan as S\u0101lim",
    "gn:population":0,
    "gn:timezone":"Asia/Baghdad",
    "iso:country":"IQ",
    "name:ara_x_preferred":[
        "\u062d\u0633\u0646 \u0627\u0644\u0633\u0627\u0644\u0645"
    ],
    "name:und_x_variant":[
        "\u1e28asan as S\u0101lim"
    ],
    "wof:name":"Hasan as Salim",
    "wof:placetype":"locality"
},
  "geometry": {"coordinates":[43.95224,33.59747],"type":"Point"}
}