{
  "type": "Feature",
  "properties": {
    "gn:admin1_code":"4.0",
    "gn:admin2_code":"98634.0",
    "gn:asciiname":"'Abd Zayd Wali",
    "gn:country_code":"IQ",
    "gn:dem":27,
    "gn:feature_class":"P",
    "gn:feature_code":"PPL",
    "gn:name":"\u2018Abd Zayd W\u0101l\u012b",
    "gn:population":0,
    "gn:timezone":"Asia/Baghdad",
    "iso:country":"IQ",
    "name:ara_x_preferred":[
        "\u0639\u0628\u062f \u0632\u064a\u062f \u0648\u0627\u0644\u064a"
    ],
    "name:und_x_variant":[
        "\u2018Abd Zayd W\u0101l\u012b"
    ],
    "wof:name":"'Abd Zayd Wali",
    "wof:placetype":"locality"
},
  "geometry": {"coordinates":[44.53302,32.01526],"type":"Point"}
}