{
  "type": "Feature",
  "properties": {
    "gn:admin1_code":"5.0",
    "gn:admin2_code":"9166600.0",
    "gn:asciiname":"'Azbakan",
    "gn:country_code":"IQ",
    "gn:dem":368,
    "gn:feature_class":"P",
    "gn:feature_code":"PPL",
    "gn:name":"\u2018Azbak\u0101n",
    "gn:population":0,
    "gn:timezone":"Asia/Baghdad",
    "iso:country":"IQ",
    "name:ara_x_preferred":[
        "\u0639\u0632\u0628\u0643\u0627\u0646"
    ],
    "name:und_x_variant":[
        "\u2018Azbak\u0101n"
    ],
    "wof:name":"'Azbakan",
    "wof:placetype":"locality"
},
  "geometry": {"coordinates":[45.54933,34.89627],"type":"Point"}
}