{
  "type": "Feature",
  "properties": {
    "gn:admin1_code":"10.0",
    "gn:admin2_code":"94590.0",
    "gn:asciiname":"'Abd al Qadir Bak",
    "gn:country_code":"IQ",
    "gn:dem":164,
    "gn:feature_class":"P",
    "gn:feature_code":"PPL",
    "gn:name":"\u2018Abd al Q\u0101dir Bak",
    "gn:population":0,
    "gn:timezone":"Asia/Baghdad",
    "iso:country":"IQ",
    "name:ara_x_preferred":[
        "\u0639\u0628\u062f \u0627\u0644\u0642\u0627\u062f\u0631 \u0628\u0643"
    ],
    "name:und_x_variant":[
        "\u2018Abd al Q\u0101dir Bak"
    ],
    "wof:name":"'Abd al Qadir Bak",
    "wof:placetype":"locality"
},
  "geometry": {"coordinates":[45.21345,34.47226],"type":"Point"}
}