{
  "type": "Feature",
  "properties": {
    "gn:admin1_code":"16.0",
    "gn:admin2_code":"9166961.0",
    "gn:asciiname":"Jamil 'Abd 'Ali",
    "gn:country_code":"IQ",
    "gn:dem":28,
    "gn:feature_class":"P",
    "gn:feature_code":"PPL",
    "gn:name":"Jam\u012bl \u2018Abd \u2018Al\u012b",
    "gn:population":0,
    "gn:timezone":"Asia/Baghdad",
    "iso:country":"IQ",
    "name:ara_x_preferred":[
        "\u062c\u0645\u064a\u0644 \u0639\u0628\u062f \u0639\u0644\u064a"
    ],
    "name:und_x_variant":[
        "Jam\u012bl \u2018Abd \u2018Al\u012b"
    ],
    "wof:name":"Jamil 'Abd 'Ali",
    "wof:placetype":"locality"
},
  "geometry": {"coordinates":[44.96052,32.87886],"type":"Point"}
}