{
  "type": "Feature",
  "properties": {
    "gn:admin1_code":"10.0",
    "gn:admin2_code":"9166680.0",
    "gn:asciiname":"'Ali Hamud",
    "gn:country_code":"IQ",
    "gn:dem":45,
    "gn:feature_class":"P",
    "gn:feature_code":"PPL",
    "gn:name":"\u2018Al\u012b \u1e28am\u016bd",
    "gn:population":0,
    "gn:timezone":"Asia/Baghdad",
    "iso:country":"IQ",
    "name:ara_x_preferred":[
        "\u0639\u0644\u064a \u062d\u0645\u0648\u062f"
    ],
    "name:und_x_variant":[
        "\u2018Al\u012b \u1e28am\u016bd"
    ],
    "wof:name":"'Ali Hamud",
    "wof:placetype":"locality"
},
  "geometry": {"coordinates":[44.9596,33.77043],"type":"Point"}
}