{
  "type": "Feature",
  "properties": {
    "gn:admin1_code":"7.0",
    "gn:admin2_code":"9166545.0",
    "gn:asciiname":"Muhaybis 'Awwad",
    "gn:country_code":"IQ",
    "gn:dem":38,
    "gn:feature_class":"P",
    "gn:feature_code":"PPL",
    "gn:name":"Mu\u1e29aybis \u2018Aww\u0101d",
    "gn:population":0,
    "gn:timezone":"Asia/Baghdad",
    "iso:country":"IQ",
    "name:ara_x_preferred":[
        "\u0645\u062d\u064a\u0628\u0633 \u0639\u0648\u0627\u062f"
    ],
    "name:und_x_variant":[
        "Mu\u1e29aybis \u2018Aww\u0101d"
    ],
    "wof:name":"Muhaybis 'Awwad",
    "wof:placetype":"locality"
},
  "geometry": {"coordinates":[44.38824,33.17996],"type":"Point"}
}