{
  "type": "Feature",
  "properties": {
    "gn:admin1_code":"18.0",
    "gn:admin2_code":"91594.0",
    "gn:asciiname":"Hamud Sa'id",
    "gn:country_code":"IQ",
    "gn:dem":84,
    "gn:feature_class":"P",
    "gn:feature_code":"PPL",
    "gn:name":"\u1e28am\u016bd Sa\u2018\u012bd",
    "gn:population":0,
    "gn:timezone":"Asia/Baghdad",
    "iso:country":"IQ",
    "name:ara_x_preferred":[
        "\u062d\u0645\u0648\u062f \u0633\u0639\u064a\u062f"
    ],
    "name:und_x_variant":[
        "\u1e28am\u016bd Sa\u2018\u012bd"
    ],
    "wof:name":"Hamud Sa'id",
    "wof:placetype":"locality"
},
  "geometry": {"coordinates":[43.66492,34.22592],"type":"Point"}
}