{
  "type": "Feature",
  "properties": {
    "gn:admin1_code":"11.0",
    "gn:admin2_code":"9166592.0",
    "gn:asciiname":"Sernus",
    "gn:country_code":"IQ",
    "gn:dem":809,
    "gn:feature_class":"P",
    "gn:feature_code":"PPL",
    "gn:name":"Sern\u016bs",
    "gn:population":0,
    "gn:timezone":"Asia/Baghdad",
    "iso:country":"IQ",
    "wof:name":"Sernus",
    "wof:placetype":"locality"
},
  "geometry": {"coordinates":[44.75528,36.54917],"type":"Point"}
}