{
  "type": "Feature",
  "properties": {
    "gn:admin1_code":"7.0",
    "gn:admin2_code":"99101.0",
    "gn:asciiname":"'Abd Allah Muhammad",
    "gn:country_code":"IQ",
    "gn:dem":31,
    "gn:feature_class":"P",
    "gn:feature_code":"PPL",
    "gn:name":"\u2018Abd All\u0101h Mu\u1e29ammad",
    "gn:population":0,
    "gn:timezone":"Asia/Baghdad",
    "iso:country":"IQ",
    "name:ara_x_preferred":[
        "\u0639\u0628\u062f\u0627\u0644\u0644\u0647 \u0645\u062d\u0645\u062f"
    ],
    "name:und_x_variant":[
        "\u2018Abd All\u0101h Mu\u1e29ammad"
    ],
    "wof:name":"'Abd Allah Muhammad",
    "wof:placetype":"locality"
},
  "geometry": {"coordinates":[44.52412,32.94687],"type":"Point"}
}