{
  "type": "Feature",
  "properties": {
    "gn:admin1_code":"15.0",
    "gn:admin2_code":"9166608.0",
    "gn:asciiname":"Al Falus",
    "gn:country_code":"IQ",
    "gn:dem":430,
    "gn:feature_class":"P",
    "gn:feature_code":"PPL",
    "gn:name":"Al Fal\u016b\u015f",
    "gn:population":0,
    "gn:timezone":"Asia/Baghdad",
    "iso:country":"IQ",
    "name:ara_x_preferred":[
        "\u0627\u0644\u0641\u0644\u0648\u0635"
    ],
    "name:und_x_variant":[
        "Al Fal\u016b\u015f"
    ],
    "wof:name":"Al Falus",
    "wof:placetype":"locality"
},
  "geometry": {"coordinates":[41.32696,36.24166],"type":"Point"}
}