{
  "type": "Feature",
  "properties": {
    "gn:admin1_code":"4.0",
    "gn:admin2_code":"6850588.0",
    "gn:asciiname":"Salman Muhammad",
    "gn:country_code":"IQ",
    "gn:dem":20,
    "gn:feature_class":"P",
    "gn:feature_code":"PPL",
    "gn:name":"Salm\u0101n Mu\u1e29ammad",
    "gn:population":0,
    "gn:timezone":"Asia/Baghdad",
    "iso:country":"IQ",
    "name:ara_x_preferred":[
        "\u0633\u0644\u0645\u0627\u0646 \u0645\u062d\u0645\u062f"
    ],
    "name:und_x_variant":[
        "Salm\u0101n Mu\u1e29ammad"
    ],
    "wof:name":"Salman Muhammad",
    "wof:placetype":"locality"
},
  "geometry": {"coordinates":[44.92941,31.68055],"type":"Point"}
}