{
  "type": "Feature",
  "properties": {
    "gn:admin1_code":"7.0",
    "gn:admin2_code":"99101.0",
    "gn:asciiname":"Hassan Wadi",
    "gn:country_code":"IQ",
    "gn:dem":33,
    "gn:feature_class":"P",
    "gn:feature_code":"PPL",
    "gn:name":"\u1e28ass\u0101n W\u0101d\u012b",
    "gn:population":0,
    "gn:timezone":"Asia/Baghdad",
    "iso:country":"IQ",
    "name:ara_x_preferred":[
        "\u062d\u0633\u0627\u0646 \u0648\u0627\u062f\u064a"
    ],
    "name:und_x_variant":[
        "\u1e28ass\u0101n W\u0101d\u012b"
    ],
    "wof:name":"Hassan Wadi",
    "wof:placetype":"locality"
},
  "geometry": {"coordinates":[44.3523,32.92937],"type":"Point"}
}