{
  "type": "Feature",
  "properties": {
    "gn:admin1_code":"11.0",
    "gn:admin2_code":"93817.0",
    "gn:asciiname":"Qaryat Umm al 'Azam",
    "gn:country_code":"IQ",
    "gn:dem":184,
    "gn:feature_class":"P",
    "gn:feature_code":"PPL",
    "gn:name":"Qaryat Umm al \u2018Az\u0327\u0101m",
    "gn:population":0,
    "gn:timezone":"Asia/Baghdad",
    "iso:country":"IQ",
    "name:ara_x_preferred":[
        "\u0642\u0631\u064a\u0629 \u0627\u0645 \u0627\u0644\u0639\u0638\u0627\u0645"
    ],
    "name:und_x_variant":[
        "Umm al Ladham",
        "Qaryat Umm al \u2018Az\u0327\u0101m"
    ],
    "wof:name":"Qaryat Umm al 'Azam",
    "wof:placetype":"locality"
},
  "geometry": {"coordinates":[43.511,35.44736],"type":"Point"}
}