{
  "type": "Feature",
  "properties": {
    "gn:admin1_code":"9.0",
    "gn:admin2_code":"98700.0",
    "gn:asciiname":"'Ujaymi Majzab",
    "gn:country_code":"IQ",
    "gn:dem":13,
    "gn:feature_class":"P",
    "gn:feature_code":"PPL",
    "gn:name":"\u2018Ujaym\u012b Majz\u0101b",
    "gn:population":0,
    "gn:timezone":"Asia/Baghdad",
    "iso:country":"IQ",
    "name:ara_x_preferred":[
        "\u0639\u062c\u064a\u0645\u064a \u0645\u062c\u0632\u0627\u0628"
    ],
    "name:und_x_variant":[
        "\u2018Ujaym\u012b Majz\u0101b"
    ],
    "wof:name":"'Ujaymi Majzab",
    "wof:placetype":"locality"
},
  "geometry": {"coordinates":[46.25399,31.81461],"type":"Point"}
}