{
  "type": "Feature",
  "properties": {
    "gn:admin1_code":"5.0",
    "gn:admin2_code":"92743.0",
    "gn:asciiname":"Piran",
    "gn:country_code":"IQ",
    "gn:dem":505,
    "gn:feature_class":"P",
    "gn:feature_code":"PPL",
    "gn:name":"P\u012br\u0101n",
    "gn:population":0,
    "gn:timezone":"Asia/Baghdad",
    "iso:country":"IQ",
    "name:afr_x_preferred":[
        "Piran"
    ],
    "name:ara_x_preferred":[
        "P\u012br\u0101n"
    ],
    "name:ara_x_variant":[
        "\u0628\u064a\u0631\u0627\u0646"
    ],
    "name:arg_x_preferred":[
        "Piran"
    ],
    "name:bos_x_preferred":[
        "Piran"
    ],
    "name:bul_x_preferred":[
        "\u041f\u0438\u0440\u0430\u043d"
    ],
    "name:cat_x_preferred":[
        "Piran"
    ],
    "name:ceb_x_preferred":[
        "Piran"
    ],
    "name:ces_x_preferred":[
        "Piran"
    ],
    "name:dan_x_preferred":[
        "Piran"
    ],
    "name:deu_x_preferred":[
        "Piran"
    ],
    "name:ell_x_preferred":[
        "\u03a0\u03b9\u03c1\u03ac\u03bd"
    ],
    "name:epo_x_preferred":[
        "Piran"
    ],
    "name:est_x_preferred":[
        "Piran"
    ],
    "name:eus_x_preferred":[
        "Piran"
    ],
    "name:fas_x_preferred":[
        "\u067e\u06cc\u0631\u0627\u0646"
    ],
    "name:fin_x_preferred":[
        "Piran"
    ],
    "name:fra_x_preferred":[
        "Piran"
    ],
    "name:gle_x_preferred":[
        "Piran"
    ],
    "name:glg_x_preferred":[
        "Piran"
    ],
    "name:heb_x_preferred":[
        "\u05e4\u05d9\u05e8\u05d0\u05df"
    ],
    "name:hrv_x_preferred":[
        "Piran"
    ],
    "name:hun_x_preferred":[
        "Piran"
    ],
    "name:ind_x_preferred":[
        "Piran"
    ],
    "name:isl_x_preferred":[
        "P\u00edran"
    ],
    "name:ita_x_preferred":[
        "Pirano"
    ],
    "name:jpn_x_preferred":[
        "\u30d4\u30e9\u30f3"
    ],
    "name:kat_x_preferred":[
        "\u10de\u10d8\u10e0\u10d0\u10dc\u10d8"
    ],
    "name:kur_x_preferred":[
        "P\u00eerenan"
    ],
    "name:kur_x_variant":[
        "P\u00eeran",
        "\u067e\u064a\u0631\u06d5\u0646\u0627\u0646",
        "\u067e\u064a\u0631\u0627\u0646"
    ],
    "name:lat_x_preferred":[
        "Pyrrhanum"
    ],
    "name:lit_x_preferred":[
        "Piranas"
    ],
    "name:mkd_x_preferred":[
        "\u041f\u0438\u0440\u0430\u043d"
    ],
    "name:msa_x_preferred":[
        "Piran"
    ],
    "name:nld_x_preferred":[
        "Piran"
    ],
    "name:nor_x_preferred":[
        "Piran"
    ],
    "name:oci_x_preferred":[
        "Piran"
    ],
    "name:pol_x_preferred":[
        "Piran"
    ],
    "name:por_x_preferred":[
        "Piran"
    ],
    "name:ron_x_preferred":[
        "Piran"
    ],
    "name:rus_x_preferred":[
        "\u041f\u0438\u0440\u0430\u043d"
    ],
    "name:sco_x_preferred":[
        "Piran"
    ],
    "name:slk_x_preferred":[
        "Piran"
    ],
    "name:slv_x_preferred":[
        "Piran"
    ],
    "name:spa_x_preferred":[
        "Piran"
    ],
    "name:sqi_x_preferred":[
        "Piran"
    ],
    "name:srp_x_preferred":[
        "\u041f\u0438\u0440\u0430\u043d"
    ],
    "name:swe_x_preferred":[
        "Piran"
    ],
    "name:tur_x_preferred":[
        "Piran"
    ],
    "name:ukr_x_preferred":[
        "\u041f\u0456\u0440\u0430\u043d"
    ],
    "name:und_x_variant":[
        "Piranan",
        "Piran"
    ],
    "name:urd_x_preferred":[
        "\u067e\u06cc\u0631\u0627\u0646"
    ],
    "name:vec_x_preferred":[
        "Pir\u00e0n"
    ],
    "name:vie_x_preferred":[
        "Piran"
    ],
    "wof:name":"Piran",
    "wof:placetype":"locality"
},
  "geometry": {"coordinates":[45.08888,36.16502],"type":"Point"}
}