{
  "type": "Feature",
  "properties": {
    "gn:admin1_code":"5.0",
    "gn:admin2_code":"92743.0",
    "gn:asciiname":"Piran",
    "gn:country_code":"IQ",
    "gn:dem":505,
    "gn:feature_class":"P",
    "gn:feature_code":"PPL",
    "gn:name":"P\u012br\u0101n",
    "gn:population":0,
    "gn:timezone":"Asia/Baghdad",
    "iso:country":"IQ",
    "name:ara_x_preferred":[
        "P\u012br\u0101n"
    ],
    "name:kur_x_preferred":[
        "P\u00eerenan"
    ],
    "name:kur_x_variant":[
        "P\u00eeran",
        "\u067e\u064a\u0631\u06d5\u0646\u0627\u0646",
        "\u067e\u064a\u0631\u0627\u0646"
    ],
    "name:und_x_variant":[
        "Piranan",
        "Piran"
    ],
    "wof:name":"Piran",
    "wof:placetype":"locality"
},
  "geometry": {"coordinates":[45.08888,36.16502],"type":"Point"}
}