{
  "type": "Feature",
  "properties": {
    "gn:admin1_code":"9.0",
    "gn:admin2_code":"99185.0",
    "gn:asciiname":"Muhammad al Bandar",
    "gn:country_code":"IQ",
    "gn:dem":2,
    "gn:feature_class":"P",
    "gn:feature_code":"PPL",
    "gn:name":"Mu\u1e29ammad al Bandar",
    "gn:population":0,
    "gn:timezone":"Asia/Baghdad",
    "iso:country":"IQ",
    "name:ara_x_preferred":[
        "\u0645\u062d\u0645\u062f \u0627\u0644\u0628\u0646\u062f\u0631"
    ],
    "name:und_x_variant":[
        "Mu\u1e29ammad al Bandar"
    ],
    "wof:name":"Muhammad al Bandar",
    "wof:placetype":"locality"
},
  "geometry": {"coordinates":[46.82866,30.90502],"type":"Point"}
}