{
  "type": "Feature",
  "properties": {
    "gn:admin1_code":"15.0",
    "gn:admin2_code":"90392.0",
    "gn:asciiname":"Tall Abu Zahir",
    "gn:country_code":"IQ",
    "gn:dem":365,
    "gn:feature_class":"P",
    "gn:feature_code":"PPL",
    "gn:name":"Tall Ab\u016b Z\u0327\u0101hir",
    "gn:population":0,
    "gn:timezone":"Asia/Baghdad",
    "iso:country":"IQ",
    "name:kur_x_preferred":[
        "Tel Ebu Zah\u00eer"
    ],
    "name:kur_x_variant":[
        "\u062a\u06d5\u0644 \u0626\u06d5\u0628\u0648 \u0632\u0627\u0647\u064a\u0631",
        "Tel Ebu Tah\u00eer",
        "\u062a\u06d5\u0644 \u0626\u06d5\u0628\u0648 \u062a\u0627\u0647\u064a\u0631"
    ],
    "name:und_x_variant":[
        "Tall Abu Dhahir",
        "Tel Abu Dhahir",
        "Tall Ab\u016b Z\u0327\u0101hir"
    ],
    "wof:name":"Tall Abu Zahir",
    "wof:placetype":"locality"
},
  "geometry": {"coordinates":[42.46781,36.8329],"type":"Point"}
}