{
  "type": "Feature",
  "properties": {
    "gn:admin1_code":"16.0",
    "gn:admin2_code":"99132.0",
    "gn:asciiname":"Al 'Aradah",
    "gn:country_code":"IQ",
    "gn:dem":10,
    "gn:feature_class":"P",
    "gn:feature_code":"PPL",
    "gn:name":"Al \u2018Ar\u0101\u1e11ah",
    "gn:population":0,
    "gn:timezone":"Asia/Baghdad",
    "iso:country":"IQ",
    "name:ara_x_preferred":[
        "\u0627\u0644\u0639\u0631\u0627\u0636\u0629"
    ],
    "name:und_x_variant":[
        "Al \u2018Ar\u0101\u1e11ah"
    ],
    "wof:name":"Al 'Aradah",
    "wof:placetype":"locality"
},
  "geometry": {"coordinates":[46.30745,32.55529],"type":"Point"}
}