{
  "type": "Feature",
  "properties": {
    "gn:admin1_code":"2.0",
    "gn:admin2_code":"100049.0",
    "gn:asciiname":"Al Ziyadiyah",
    "gn:country_code":"IQ",
    "gn:dem":2,
    "gn:feature_class":"P",
    "gn:feature_code":"PPL",
    "gn:name":"Al Z\u012by\u0101d\u012byah",
    "gn:population":0,
    "gn:timezone":"Asia/Baghdad",
    "iso:country":"IQ",
    "name:fas_x_preferred":[
        "\u0627\u0644\u0632\u064a\u0627\u062f\u064a\u0647"
    ],
    "wof:name":"Al Ziyadiyah",
    "wof:placetype":"locality"
},
  "geometry": {"coordinates":[48.3023,30.2864],"type":"Point"}
}