{
  "type": "Feature",
  "properties": {
    "gn:admin1_code":"4.0",
    "gn:admin2_code":"6850588.0",
    "gn:asciiname":"'Aziz Kazar",
    "gn:country_code":"IQ",
    "gn:dem":20,
    "gn:feature_class":"P",
    "gn:feature_code":"PPL",
    "gn:name":"\u2018Az\u012bz Kaz\u0101r",
    "gn:population":0,
    "gn:timezone":"Asia/Baghdad",
    "iso:country":"IQ",
    "name:ara_x_preferred":[
        "\u0639\u0632\u064a\u0632 \u0643\u0632\u0627\u0631"
    ],
    "name:und_x_variant":[
        "\u2018Az\u012bz Kaz\u0101r"
    ],
    "wof:name":"'Aziz Kazar",
    "wof:placetype":"locality"
},
  "geometry": {"coordinates":[44.94154,31.71294],"type":"Point"}
}