{
  "type": "Feature",
  "properties": {
    "gn:admin1_code":"3.0",
    "gn:admin2_code":"9166626.0",
    "gn:asciiname":"'Abd 'Ali 'Ajil",
    "gn:country_code":"IQ",
    "gn:dem":9,
    "gn:feature_class":"P",
    "gn:feature_code":"PPL",
    "gn:name":"\u2018Abd \u2018Ali \u2018Aj\u012bl",
    "gn:population":0,
    "gn:timezone":"Asia/Baghdad",
    "iso:country":"IQ",
    "name:ara_x_preferred":[
        "\u0639\u0628\u062f \u0639\u0644\u064a \u0639\u062c\u064a\u0644"
    ],
    "name:ara_x_variant":[
        "\u2018Abd \u2018Ali \u2018Aj\u012bl"
    ],
    "name:und_x_variant":[
        "\u2018Abd \u2018Ali al \u2018Aj\u012bl",
        "\u2018Abd \u2018Al\u012b"
    ],
    "wof:name":"'Abd 'Ali 'Ajil",
    "wof:placetype":"locality"
},
  "geometry": {"coordinates":[45.63238,31.21094],"type":"Point"}
}