{
  "type": "Feature",
  "properties": {
    "gn:admin1_code":"18.0",
    "gn:admin2_code":"6783103.0",
    "gn:asciiname":"Qaryat 'Abd Allah al Matar",
    "gn:country_code":"IQ",
    "gn:dem":69,
    "gn:feature_class":"P",
    "gn:feature_code":"PPL",
    "gn:name":"Qaryat \u2018Abd All\u0101h al Ma\u0163ar",
    "gn:population":0,
    "gn:timezone":"Asia/Baghdad",
    "iso:country":"IQ",
    "name:ara_x_preferred":[
        "\u0642\u0631\u064a\u0629 \u0639\u0628\u062f \u0627\u0644\u0644\u0647 \u0627\u0644\u0645\u0637\u0631"
    ],
    "name:und_x_variant":[
        "Qaryat \u2018Abd All\u0101h al Ma\u0163ar"
    ],
    "wof:name":"Qaryat 'Abd Allah al Matar",
    "wof:placetype":"locality"
},
  "geometry": {"coordinates":[44.33379,34.27846],"type":"Point"}
}