{
  "type": "Feature",
  "properties": {
    "gn:admin1_code":"18.0",
    "gn:admin2_code":"6783103.0",
    "gn:asciiname":"Qaryat al Qal'ah",
    "gn:country_code":"IQ",
    "gn:dem":90,
    "gn:feature_class":"P",
    "gn:feature_code":"PPL",
    "gn:name":"Qaryat al Qal\u2018ah",
    "gn:population":0,
    "gn:timezone":"Asia/Baghdad",
    "iso:country":"IQ",
    "name:ara_x_preferred":[
        "\u0642\u0631\u064a\u0629 \u0627\u0644\u0642\u0644\u0639\u0647"
    ],
    "name:und_x_variant":[
        "Qaryat al Qal\u2018ah"
    ],
    "wof:name":"Qaryat al Qal'ah",
    "wof:placetype":"locality"
},
  "geometry": {"coordinates":[44.48182,34.4532],"type":"Point"}
}