{
  "type": "Feature",
  "properties": {
    "gn:admin1_code":"2.0",
    "gn:admin2_code":"99534.0",
    "gn:asciiname":"Qaryat az Zurayji",
    "gn:country_code":"IQ",
    "gn:dem":2,
    "gn:feature_class":"P",
    "gn:feature_code":"PPL",
    "gn:name":"Qaryat az Zurayj\u012b",
    "gn:population":0,
    "gn:timezone":"Asia/Baghdad",
    "iso:country":"IQ",
    "name:ara_x_preferred":[
        "\u0642\u0631\u064a\u0629 \u0627\u0644\u0632\u0631\u064a\u062c\u064a"
    ],
    "name:und_x_variant":[
        "Zaraji",
        "Zurayq\u012b",
        "Zurayj\u012b",
        "Qaryat az Zurayj\u012b"
    ],
    "wof:name":"Qaryat az Zurayji",
    "wof:placetype":"locality"
},
  "geometry": {"coordinates":[47.67845,30.76111],"type":"Point"}
}