{
  "type": "Feature",
  "properties": {
    "gn:admin1_code":"18.0",
    "gn:admin2_code":"6872046.0",
    "gn:asciiname":"Bayt Nayif Hammad",
    "gn:country_code":"IQ",
    "gn:dem":166,
    "gn:feature_class":"P",
    "gn:feature_code":"PPL",
    "gn:name":"Bayt N\u0101yif \u1e28amm\u0101d",
    "gn:population":0,
    "gn:timezone":"Asia/Baghdad",
    "iso:country":"IQ",
    "name:ara_x_preferred":[
        "\u0628\u064a\u062a \u0646\u0627\u064a\u0641 \u062d\u0645\u0627\u062f"
    ],
    "name:und_x_variant":[
        "Bayt N\u0101yif \u1e28amm\u0101d"
    ],
    "wof:name":"Bayt Nayif Hammad",
    "wof:placetype":"locality"
},
  "geometry": {"coordinates":[43.30853,35.10911],"type":"Point"}
}