{
  "type": "Feature",
  "properties": {
    "gn:admin1_code":"7.0",
    "gn:admin2_code":"9166668.0",
    "gn:asciiname":"Arab as Saydiyah",
    "gn:country_code":"IQ",
    "gn:dem":39,
    "gn:feature_class":"P",
    "gn:feature_code":"PPL",
    "gn:name":"Arab as Sayd\u012byah",
    "gn:population":0,
    "gn:timezone":"Asia/Baghdad",
    "iso:country":"IQ",
    "name:und_x_variant":[
        "Arab as Sayd\u012byah",
        "Arab as Sa\u2018d\u012byah"
    ],
    "wof:name":"Arab as Saydiyah",
    "wof:placetype":"locality"
},
  "geometry": {"coordinates":[44.46972,33.26361],"type":"Point"}
}