{
  "type": "Feature",
  "properties": {
    "gn:admin1_code":"18.0",
    "gn:admin2_code":"91594.0",
    "gn:asciiname":"Muhammad Yasin",
    "gn:country_code":"IQ",
    "gn:dem":74,
    "gn:feature_class":"P",
    "gn:feature_code":"PPL",
    "gn:name":"Mu\u1e29ammad Y\u0101s\u012bn",
    "gn:population":0,
    "gn:timezone":"Asia/Baghdad",
    "iso:country":"IQ",
    "name:ara_x_preferred":[
        "\u0645\u062d\u0645\u062f \u064a\u0627\u0633\u064a\u0646"
    ],
    "name:gor_x_preferred":[
        "Muhammad Yasin"
    ],
    "name:ind_x_preferred":[
        "Muhammad Yasin"
    ],
    "name:und_x_variant":[
        "Mu\u1e29ammad Y\u0101s\u012bn"
    ],
    "wof:name":"Muhammad Yasin",
    "wof:placetype":"locality"
},
  "geometry": {"coordinates":[43.77576,34.30739000000001],"type":"Point"}
}