{
  "type": "Feature",
  "properties": {
    "gn:admin1_code":"11.0",
    "gn:admin2_code":"9166592.0",
    "gn:asciiname":"Maslawk",
    "gn:country_code":"IQ",
    "gn:dem":1286,
    "gn:feature_class":"P",
    "gn:feature_code":"PPL",
    "gn:name":"Maslawk",
    "gn:population":0,
    "gn:timezone":"Asia/Baghdad",
    "iso:country":"IQ",
    "name:ara_x_preferred":[
        "\u0645\u0633\u0644\u0648\u0643"
    ],
    "name:kur_x_preferred":[
        "Meslok"
    ],
    "name:kur_x_variant":[
        "\u0645\u06d5\u0633\u0644\u06c6\u0643",
        "Misluk"
    ],
    "name:und_x_variant":[
        "Maslok",
        "Masl\u016bk"
    ],
    "wof:name":"Maslawk",
    "wof:placetype":"locality"
},
  "geometry": {"coordinates":[44.6323,37.03453],"type":"Point"}
}