{
  "type": "Feature",
  "properties": {
    "gn:admin1_code":"10.0",
    "gn:admin2_code":"99063.0",
    "gn:asciiname":"Qaryat al Ahmar",
    "gn:country_code":"IQ",
    "gn:dem":57,
    "gn:feature_class":"P",
    "gn:feature_code":"PPL",
    "gn:name":"Qaryat al A\u1e29mar",
    "gn:population":0,
    "gn:timezone":"Asia/Baghdad",
    "iso:country":"IQ",
    "name:ara_x_preferred":[
        "\u0642\u0631\u064a\u0629 \u0627\u0644\u0627\u062d\u0645\u0631"
    ],
    "name:und_x_variant":[
        "Qaryat al A\u1e29mar"
    ],
    "wof:name":"Qaryat al Ahmar",
    "wof:placetype":"locality"
},
  "geometry": {"coordinates":[44.89872,33.97149],"type":"Point"}
}