{
  "type": "Feature",
  "properties": {
    "gn:admin1_code":"18.0",
    "gn:admin2_code":"9166598.0",
    "gn:asciiname":"Sha'lan Satam",
    "gn:country_code":"IQ",
    "gn:dem":118,
    "gn:feature_class":"P",
    "gn:feature_code":"PPL",
    "gn:name":"Sha\u2018l\u0101n Sa\u0163\u0101m",
    "gn:population":0,
    "gn:timezone":"Asia/Baghdad",
    "iso:country":"IQ",
    "name:ara_x_preferred":[
        "\u0634\u0639\u0644\u0627\u0646 \u0633\u0637\u0627\u0645"
    ],
    "name:und_x_variant":[
        "Sha\u2018l\u0101n Sa\u0163\u0101m"
    ],
    "wof:name":"Sha'lan Satam",
    "wof:placetype":"locality"
},
  "geometry": {"coordinates":[44.22595,34.59188],"type":"Point"}
}