{
  "type": "Feature",
  "properties": {
    "gn:admin1_code":"6.0",
    "gn:admin2_code":"99358.0",
    "gn:asciiname":"Ad Dagharat",
    "gn:country_code":"IQ",
    "gn:dem":32,
    "gn:feature_class":"P",
    "gn:feature_code":"PPL",
    "gn:name":"Ad Dagh\u0101r\u0101t",
    "gn:population":0,
    "gn:timezone":"Asia/Baghdad",
    "iso:country":"IQ",
    "name:ara_x_preferred":[
        "\u0627\u0644\u062f\u063a\u0627\u0631\u0627\u062a"
    ],
    "name:und_x_variant":[
        "Ad Dagh\u0101r\u0101t"
    ],
    "wof:name":"Ad Dagharat",
    "wof:placetype":"locality"
},
  "geometry": {"coordinates":[44.56167,32.39107],"type":"Point"}
}