{
  "type": "Feature",
  "properties": {
    "gn:admin1_code":"7.0",
    "gn:admin2_code":"99101.0",
    "gn:asciiname":"Qaryat Imam Sayyid 'Abd Allah",
    "gn:country_code":"IQ",
    "gn:dem":37,
    "gn:feature_class":"P",
    "gn:feature_code":"PPL",
    "gn:name":"Qaryat Im\u0101m Sayyid \u2018Abd All\u0101h",
    "gn:population":0,
    "gn:timezone":"Asia/Baghdad",
    "iso:country":"IQ",
    "name:ara_x_preferred":[
        "\u0642\u0631\u064a\u0629 \u0627\u0645\u0627\u0645 \u0633\u064a\u062f \u0639\u0628\u062f\u0627\u0644\u0644\u0647"
    ],
    "name:ara_x_variant":[
        "\u0627\u0645\u0627\u0645 \u0633\u064a\u062f \u0639\u0628\u062f\u0627\u0644\u0644\u0647"
    ],
    "name:und_x_variant":[
        "Qaryat Im\u0101m Sayyid \u2018Abd All\u0101h",
        "Im\u0101m Sayyid \u2018Abd All\u0101h"
    ],
    "wof:name":"Qaryat Imam Sayyid 'Abd Allah",
    "wof:placetype":"locality"
},
  "geometry": {"coordinates":[44.25768,33.04895],"type":"Point"}
}