{
  "type": "Feature",
  "properties": {
    "gn:admin1_code":"18.0",
    "gn:admin2_code":"6872046.0",
    "gn:asciiname":"Qaryat Jawzah",
    "gn:country_code":"IQ",
    "gn:dem":136,
    "gn:feature_class":"P",
    "gn:feature_code":"PPL",
    "gn:name":"Qaryat Jawzah",
    "gn:population":0,
    "gn:timezone":"Asia/Baghdad",
    "iso:country":"IQ",
    "name:ara_x_preferred":[
        "\u0642\u0631\u064a\u0629 \u062c\u0648\u0632\u0629"
    ],
    "wof:name":"Qaryat Jawzah",
    "wof:placetype":"locality"
},
  "geometry": {"coordinates":[43.33751,34.57055],"type":"Point"}
}