{
  "type": "Feature",
  "properties": {
    "gn:admin1_code":"18.0",
    "gn:admin2_code":"6805736.0",
    "gn:asciiname":"Qaryat Albu 'Asi",
    "gn:country_code":"IQ",
    "gn:dem":49,
    "gn:feature_class":"P",
    "gn:feature_code":"PPL",
    "gn:name":"Qaryat \u0100lb\u016b \u2018\u0100\u015f\u012b",
    "gn:population":0,
    "gn:timezone":"Asia/Baghdad",
    "iso:country":"IQ",
    "name:ara_x_preferred":[
        "\u0642\u0631\u064a\u0629 \u0627\u0644\u0628\u0648\u0639\u0627\u0635\u064a"
    ],
    "name:und_x_variant":[
        "Qaryat \u0100lb\u016b \u2018\u0100\u015f\u012b"
    ],
    "wof:name":"Qaryat Albu 'Asi",
    "wof:placetype":"locality"
},
  "geometry": {"coordinates":[44.4114,33.91764000000001],"type":"Point"}
}