{
  "type": "Feature",
  "properties": {
    "gn:admin1_code":"18.0",
    "gn:admin2_code":"6805736.0",
    "gn:asciiname":"Mahmud al Arhim",
    "gn:country_code":"IQ",
    "gn:dem":48,
    "gn:feature_class":"P",
    "gn:feature_code":"PPL",
    "gn:name":"Ma\u1e29m\u016bd al Ar\u1e29\u012bm",
    "gn:population":0,
    "gn:timezone":"Asia/Baghdad",
    "iso:country":"IQ",
    "name:und_x_variant":[
        "Ma\u1e29m\u016bd ar Ra\u1e29\u012bm",
        "Ma\u1e29m\u016bd al Ar\u1e29\u012bm"
    ],
    "wof:name":"Mahmud al Arhim",
    "wof:placetype":"locality"
},
  "geometry": {"coordinates":[44.24556,34.03389],"type":"Point"}
}