{
  "type": "Feature",
  "properties": {
    "gn:admin1_code":"15.0",
    "gn:admin2_code":"9166608.0",
    "gn:asciiname":"Al Ukbibah",
    "gn:country_code":"IQ",
    "gn:dem":210,
    "gn:feature_class":"P",
    "gn:feature_code":"PPL",
    "gn:name":"Al Ukb\u012bbah",
    "gn:population":0,
    "gn:timezone":"Asia/Baghdad",
    "iso:country":"IQ",
    "name:ara_x_preferred":[
        "\u0627\u0644\u0627\u0643\u0628\u064a\u0628\u0629"
    ],
    "name:und_x_variant":[
        "Al Ukb\u012bbah"
    ],
    "wof:name":"Al Ukbibah",
    "wof:placetype":"locality"
},
  "geometry": {"coordinates":[41.80573,35.69507],"type":"Point"}
}