{
  "type": "Feature",
  "properties": {
    "gn:admin1_code":"14.0",
    "gn:admin2_code":"99305.0",
    "gn:asciiname":"'Arab Jawa",
    "gn:country_code":"IQ",
    "gn:dem":11,
    "gn:feature_class":"P",
    "gn:feature_code":"PPL",
    "gn:name":"\u2018Arab Jaw\u00e1",
    "gn:population":0,
    "gn:timezone":"Asia/Baghdad",
    "iso:country":"IQ",
    "name:ara_x_preferred":[
        "\u0639\u0631\u0628 \u062c\u0648\u0649"
    ],
    "name:und_x_variant":[
        "\u2018Arab Jaw\u00e1"
    ],
    "wof:name":"'Arab Jawa",
    "wof:placetype":"locality"
},
  "geometry": {"coordinates":[46.61694,32.50481],"type":"Point"}
}