{
  "type": "Feature",
  "properties": {
    "gn:admin1_code":"18.0",
    "gn:admin2_code":"6805736.0",
    "gn:asciiname":"'Adwan 'Abd",
    "gn:country_code":"IQ",
    "gn:dem":44,
    "gn:feature_class":"P",
    "gn:feature_code":"PPL",
    "gn:name":"\u2018Adw\u0101n \u2018Abd",
    "gn:population":0,
    "gn:timezone":"Asia/Baghdad",
    "iso:country":"IQ",
    "name:ara_x_preferred":[
        "\u0639\u062f\u0648\u0627\u0646 \u0639\u0628\u062f"
    ],
    "name:ara_x_variant":[
        "\u2018Adw\u0101n \u2018Abd"
    ],
    "wof:name":"'Adwan 'Abd",
    "wof:placetype":"locality"
},
  "geometry": {"coordinates":[44.08323,33.85648],"type":"Point"}
}