{
  "type": "Feature",
  "properties": {
    "gn:admin1_code":"15.0",
    "gn:admin2_code":"98612.0",
    "gn:asciiname":"Bire",
    "gn:country_code":"IQ",
    "gn:dem":816,
    "gn:feature_class":"P",
    "gn:feature_code":"PPL",
    "gn:name":"Bire",
    "gn:population":0,
    "gn:timezone":"Asia/Baghdad",
    "iso:country":"IQ",
    "name:ara_x_preferred":[
        "B\u012br\u0113"
    ],
    "name:kur_x_preferred":[
        "B\u00eer\u00ea"
    ],
    "name:kur_x_variant":[
        "\u0628\u064a\u0631\u06ce"
    ],
    "name:und_x_variant":[
        "B\u012bray",
        "Bire"
    ],
    "wof:name":"Bire",
    "wof:placetype":"locality"
},
  "geometry": {"coordinates":[43.48214,36.83658],"type":"Point"}
}