{
  "type": "Feature",
  "properties": {
    "gn:admin1_code":"6.0",
    "gn:admin2_code":"6818313.0",
    "gn:asciiname":"Khudayr adh Dhib",
    "gn:country_code":"IQ",
    "gn:dem":26,
    "gn:feature_class":"P",
    "gn:feature_code":"PPL",
    "gn:name":"Khu\u1e11ayr adh Dh\u012bb",
    "gn:population":0,
    "gn:timezone":"Asia/Baghdad",
    "iso:country":"IQ",
    "name:ara_x_preferred":[
        "\u062e\u0636\u064a\u0631 \u0627\u0644\u0630\u064a\u0628"
    ],
    "name:und_x_variant":[
        "Khu\u1e11ayr adh Dh\u012bb"
    ],
    "wof:name":"Khudayr adh Dhib",
    "wof:placetype":"locality"
},
  "geometry": {"coordinates":[44.93252,32.65867],"type":"Point"}
}