{
  "type": "Feature",
  "properties": {
    "gn:admin1_code":"6.0",
    "gn:admin2_code":"6818313.0",
    "gn:asciiname":"'Arab 'Ubayd Tayih",
    "gn:country_code":"IQ",
    "gn:dem":28,
    "gn:feature_class":"P",
    "gn:feature_code":"PPL",
    "gn:name":"\u2018Arab \u2018Ubayd T\u0101yih",
    "gn:population":0,
    "gn:timezone":"Asia/Baghdad",
    "iso:country":"IQ",
    "name:ara_x_preferred":[
        "\u0639\u0631\u0628 \u0639\u0628\u064a\u062f \u062a\u0627\u064a\u0647"
    ],
    "name:und_x_variant":[
        "\u2018Arab \u2018Ubayd T\u0101yih"
    ],
    "wof:name":"'Arab 'Ubayd Tayih",
    "wof:placetype":"locality"
},
  "geometry": {"coordinates":[44.56918,32.8047],"type":"Point"}
}