{
  "type": "Feature",
  "properties": {
    "gn:admin1_code":"7.0",
    "gn:admin2_code":"9166542.0",
    "gn:asciiname":"Qaryat al Hamdaniyah ash Shaniyah",
    "gn:country_code":"IQ",
    "gn:dem":39,
    "gn:feature_class":"P",
    "gn:feature_code":"PPL",
    "gn:name":"Qaryat al \u1e28amd\u0101n\u012byah ash Sh\u0101n\u012byah",
    "gn:population":0,
    "gn:timezone":"Asia/Baghdad",
    "iso:country":"IQ",
    "name:ara_x_preferred":[
        "\u0642\u0631\u064a\u0629 \u0627\u0644\u062d\u0645\u062f\u0627\u0646\u064a\u0629 \u0627\u0644\u0634\u0627\u0646\u064a\u0629"
    ],
    "name:und_x_variant":[
        "Qaryat al \u1e28amd\u0101n\u012byah ash Sh\u0101n\u012byah"
    ],
    "wof:name":"Qaryat al Hamdaniyah ash Shaniyah",
    "wof:placetype":"locality"
},
  "geometry": {"coordinates":[44.09091,33.35809],"type":"Point"}
}