{
  "type": "Feature",
  "properties": {
    "gn:admin1_code":"8.0",
    "gn:admin2_code":"99612.0",
    "gn:asciiname":"Girde Hambay",
    "gn:country_code":"IQ",
    "gn:dem":1847,
    "gn:elevation":"1987.0",
    "gn:feature_class":"P",
    "gn:feature_code":"PPL",
    "gn:name":"Gird\u0113 Hambay",
    "gn:population":0,
    "gn:timezone":"Asia/Baghdad",
    "iso:country":"IQ",
    "name:kur_x_preferred":[
        "Gir\u00ea Himb\u00ea"
    ],
    "name:kur_x_variant":[
        "\u06af\u0631\u06ce \u06be\u0645\u0628\u06ce"
    ],
    "name:und_x_variant":[
        "Gird Hambi"
    ],
    "wof:name":"Girde Hambay",
    "wof:placetype":"locality"
},
  "geometry": {"coordinates":[44.03032,37.25338],"type":"Point"}
}