{
  "type": "Feature",
  "properties": {
    "gn:admin1_code":"6.0",
    "gn:admin2_code":"6818313.0",
    "gn:asciiname":"Muhsin Dawud",
    "gn:country_code":"IQ",
    "gn:dem":29,
    "gn:feature_class":"P",
    "gn:feature_code":"PPL",
    "gn:name":"Mu\u1e29sin D\u0101wud",
    "gn:population":0,
    "gn:timezone":"Asia/Baghdad",
    "iso:country":"IQ",
    "name:ara_x_preferred":[
        "\u0645\u062d\u0633\u0646 \u062f\u0627\u0648\u062f"
    ],
    "name:ara_x_variant":[
        "Mu\u1e29sin D\u0101wud"
    ],
    "wof:name":"Muhsin Dawud",
    "wof:placetype":"locality"
},
  "geometry": {"coordinates":[44.4487,32.65373],"type":"Point"}
}