{
  "type": "Feature",
  "properties": {
    "gn:admin1_code":"15.0",
    "gn:admin2_code":"9166618.0",
    "gn:asciiname":"Dayrhal",
    "gn:country_code":"IQ",
    "gn:dem":307,
    "gn:feature_class":"P",
    "gn:feature_code":"PPL",
    "gn:name":"Dayr\u1e29al",
    "gn:population":0,
    "gn:timezone":"Asia/Baghdad",
    "iso:country":"IQ",
    "wof:name":"Dayrhal",
    "wof:placetype":"locality"
},
  "geometry": {"coordinates":[42.88333,36.66667],"type":"Point"}
}