{
  "type": "Feature",
  "properties": {
    "gn:admin1_code":"7.0",
    "gn:admin2_code":"9166542.0",
    "gn:asciiname":"Qaryat al Mahasinah",
    "gn:country_code":"IQ",
    "gn:dem":43,
    "gn:feature_class":"P",
    "gn:feature_code":"PPL",
    "gn:name":"Qaryat al Ma\u1e29\u0101sinah",
    "gn:population":0,
    "gn:timezone":"Asia/Baghdad",
    "iso:country":"IQ",
    "name:ara_x_preferred":[
        "\u0642\u0631\u064a\u0629 \u0627\u0644\u0645\u062d\u0627\u0633\u0646\u0629"
    ],
    "name:und_x_variant":[
        "Qaryat al Ma\u1e29\u0101sinah"
    ],
    "wof:name":"Qaryat al Mahasinah",
    "wof:placetype":"locality"
},
  "geometry": {"coordinates":[43.93461,33.20936],"type":"Point"}
}