{
  "type": "Feature",
  "properties": {
    "gn:admin1_code":"4.0",
    "gn:admin2_code":"99763.0",
    "gn:asciiname":"Nahiyat ad Daghgharah",
    "gn:country_code":"IQ",
    "gn:dem":27,
    "gn:feature_class":"P",
    "gn:feature_code":"PPL",
    "gn:name":"N\u0101\u1e29iyat ad Daghgh\u0101rah",
    "gn:population":0,
    "gn:timezone":"Asia/Baghdad",
    "iso:country":"IQ",
    "name:ara_x_preferred":[
        "\u0646\u0627\u062d\u064a\u0629 \u0627\u0644\u062f\u063a\u0627\u0631\u0629"
    ],
    "name:und_x_variant":[
        "Dagh\u0101rah",
        "Daghghara",
        "Ad Daghgh\u0101rah",
        "N\u0101\u1e29iyat ad Daghgh\u0101rah"
    ],
    "wof:name":"Nahiyat ad Daghgharah",
    "wof:placetype":"locality"
},
  "geometry": {"coordinates":[44.93305,32.13752],"type":"Point"}
}