{
  "type": "Feature",
  "properties": {
    "gn:admin1_code":"6.0",
    "gn:admin2_code":"6818313.0",
    "gn:asciiname":"Kirmash Dhiyab",
    "gn:country_code":"IQ",
    "gn:dem":29,
    "gn:feature_class":"P",
    "gn:feature_code":"PPL",
    "gn:name":"Kirm\u0101sh Dhiy\u0101b",
    "gn:population":0,
    "gn:timezone":"Asia/Baghdad",
    "iso:country":"IQ",
    "name:ara_x_preferred":[
        "\u0643\u0631\u0645\u0627\u0634 \u0630\u064a\u0627\u0628"
    ],
    "name:ara_x_variant":[
        "Kirm\u0101sh Dhiy\u0101b"
    ],
    "wof:name":"Kirmash Dhiyab",
    "wof:placetype":"locality"
},
  "geometry": {"coordinates":[44.51758,32.48329],"type":"Point"}
}