{
  "type": "Feature",
  "properties": {
    "gn:admin1_code":"10.0",
    "gn:admin2_code":"97988.0",
    "gn:asciiname":"Qariyat Zahra'",
    "gn:country_code":"IQ",
    "gn:dem":41,
    "gn:feature_class":"P",
    "gn:feature_code":"PPL",
    "gn:name":"Qar\u012byat Zahr\u0101\u2019",
    "gn:population":0,
    "gn:timezone":"Asia/Baghdad",
    "iso:country":"IQ",
    "wof:name":"Qariyat Zahra'",
    "wof:placetype":"locality"
},
  "geometry": {"coordinates":[44.5275,33.43167],"type":"Point"}
}