{
  "type": "Feature",
  "properties": {
    "gn:admin1_code":"3.0",
    "gn:admin2_code":"9166626.0",
    "gn:asciiname":"Karim",
    "gn:country_code":"IQ",
    "gn:dem":9,
    "gn:feature_class":"P",
    "gn:feature_code":"PPL",
    "gn:name":"Kar\u012bm",
    "gn:population":0,
    "gn:timezone":"Asia/Baghdad",
    "iso:country":"IQ",
    "name:ara_x_preferred":[
        "\u0643\u0631\u064a\u0645"
    ],
    "name:deu_x_preferred":[
        "Karim"
    ],
    "name:fas_x_preferred":[
        "\u06a9\u0631\u06cc\u0645"
    ],
    "name:fin_x_preferred":[
        "Karim"
    ],
    "name:fra_x_preferred":[
        "Karim"
    ],
    "name:ita_x_preferred":[
        "Karim"
    ],
    "name:nld_x_preferred":[
        "Karim"
    ],
    "name:pol_x_preferred":[
        "Karim"
    ],
    "name:spa_x_preferred":[
        "Karim"
    ],
    "name:swa_x_preferred":[
        "Karim"
    ],
    "name:swe_x_preferred":[
        "Karim"
    ],
    "name:und_x_variant":[
        "Kar\u012bm"
    ],
    "wof:name":"Karim",
    "wof:placetype":"locality"
},
  "geometry": {"coordinates":[45.69753,31.15966],"type":"Point"}
}