{
  "type": "Feature",
  "properties": {
    "gn:admin1_code":"4.0",
    "gn:admin2_code":"6850588.0",
    "gn:asciiname":"Tall Imjam",
    "gn:country_code":"IQ",
    "gn:dem":19,
    "gn:feature_class":"P",
    "gn:feature_code":"PPL",
    "gn:name":"Tall Imj\u0101m",
    "gn:population":0,
    "gn:timezone":"Asia/Baghdad",
    "iso:country":"IQ",
    "name:ara_x_preferred":[
        "\u062a\u0644 \u0627\u0645\u062c\u0627\u0645"
    ],
    "name:und_x_variant":[
        "Tall Imj\u0101m"
    ],
    "wof:name":"Tall Imjam",
    "wof:placetype":"locality"
},
  "geometry": {"coordinates":[45.00987,31.80288],"type":"Point"}
}