{
  "type": "Feature",
  "properties": {
    "gn:admin1_code":"8.0",
    "gn:admin2_code":"99612.0",
    "gn:asciiname":"Tahlawah",
    "gn:country_code":"IQ",
    "gn:dem":714,
    "gn:feature_class":"P",
    "gn:feature_code":"PPL",
    "gn:name":"Tahl\u0101wah",
    "gn:population":0,
    "gn:timezone":"Asia/Baghdad",
    "iso:country":"IQ",
    "name:ara_x_preferred":[
        "\u062a\u0647\u0644\u0627\u0648\u0647"
    ],
    "name:kur_x_preferred":[
        "Te\u1e27lawe"
    ],
    "name:kur_x_variant":[
        "\u062a\u06d5\u062d\u0644\u0627\u0648\u06d5",
        "Te\u1e27lava",
        "\u062a\u06d5\u062d\u0644\u0627\u06a4\u0627"
    ],
    "name:und_x_variant":[
        "Ta\u1e29l\u0101fah",
        "Tahl\u0101va",
        "Tahlaua",
        "Tahl\u0101wah",
        "Tahlava"
    ],
    "wof:name":"Tahlawah",
    "wof:placetype":"locality"
},
  "geometry": {"coordinates":[43.12262,37.1179],"type":"Point"}
}