{
  "type": "Feature",
  "properties": {
    "gn:admin1_code":"18.0",
    "gn:asciiname":"Al Fathah",
    "gn:country_code":"IQ",
    "gn:dem":125,
    "gn:feature_class":"P",
    "gn:feature_code":"PPL",
    "gn:name":"Al Fat\u1e29ah",
    "gn:population":0,
    "gn:timezone":"Asia/Baghdad",
    "iso:country":"IQ",
    "name:ara_x_preferred":[
        "\u0627\u0644\u0641\u062a\u062d\u0629"
    ],
    "name:und_x_variant":[
        "Al Fat\u1e29ah"
    ],
    "wof:name":"Al Fathah",
    "wof:placetype":"locality"
},
  "geometry": {"coordinates":[43.56013,35.05281],"type":"Point"}
}