{
  "type": "Feature",
  "properties": {
    "gn:admin1_code":"6.0",
    "gn:admin2_code":"99348.0",
    "gn:asciiname":"Khan Sayyid Nur",
    "gn:country_code":"IQ",
    "gn:dem":27,
    "gn:feature_class":"P",
    "gn:feature_code":"PPL",
    "gn:name":"Kh\u0101n Sayyid N\u016br",
    "gn:population":0,
    "gn:timezone":"Asia/Baghdad",
    "iso:country":"IQ",
    "name:ara_x_preferred":[
        "\u062e\u0627\u0646 \u0633\u064a\u062f \u0646\u0648\u0631"
    ],
    "name:und_x_variant":[
        "Kh\u0101n Sadn\u016br",
        "Kh\u0101n S\u012bdn\u0101r",
        "Kh\u0101n Sayyid N\u016br"
    ],
    "wof:name":"Khan Sayyid Nur",
    "wof:placetype":"locality"
},
  "geometry": {"coordinates":[44.35573,32.22085999999999],"type":"Point"}
}