{
  "type": "Feature",
  "properties": {
    "gn:admin1_code":"9.0",
    "gn:admin2_code":"99185.0",
    "gn:asciiname":"Likari",
    "gn:country_code":"IQ",
    "gn:dem":3,
    "gn:feature_class":"P",
    "gn:feature_code":"PPL",
    "gn:name":"L\u012bk\u0101r\u012b",
    "gn:population":0,
    "gn:timezone":"Asia/Baghdad",
    "iso:country":"IQ",
    "name:ara_x_preferred":[
        "L\u012bk\u0101r\u012b"
    ],
    "wof:name":"Likari",
    "wof:placetype":"locality"
},
  "geometry": {"coordinates":[47.11667,30.93333],"type":"Point"}
}