{
  "type": "Feature",
  "properties": {
    "gn:country":"IQ",
    "gn:fcode":"PPL",
    "gn:pop":23189,
    "iso:country":"IQ",
    "name:ara_x_preferred":[
        "Al Mishkh\u0101b"
    ],
    "name:ara_x_variant":[
        "\u0627\u0644\u0645\u0634\u062e\u0627\u0628"
    ],
    "name:unk_x_variant":[
        "Faisailiya"
    ],
    "qs:name":"Al Mishkh\u0101b",
    "qs:photos_9r":0,
    "qs:photos_sr":0,
    "qs:pop_sr":"7",
    "wof:name":"Al Mishkh\u0101b",
    "wof:placetype":"locality",
    "wof:population":23189
},
  "geometry": {"coordinates":[44.4893,31.80436],"type":"Point"}
}