{
  "type": "Feature",
  "properties": {
    "gn:admin1_code":"4.0",
    "gn:admin2_code":"98634.0",
    "gn:asciiname":"Jawad Al Kazim",
    "gn:country_code":"IQ",
    "gn:dem":21,
    "gn:feature_class":"P",
    "gn:feature_code":"PPL",
    "gn:name":"Jaw\u0101d \u0100l K\u0101z\u0327im",
    "gn:population":0,
    "gn:timezone":"Asia/Baghdad",
    "iso:country":"IQ",
    "name:ara_x_preferred":[
        "\u062c\u0648\u0627\u062f \u0627\u0644 \u0643\u0627\u0638\u0645"
    ],
    "name:und_x_variant":[
        "Jaw\u0101d \u0100l K\u0101z\u0327im"
    ],
    "wof:name":"Jawad Al Kazim",
    "wof:placetype":"locality"
},
  "geometry": {"coordinates":[44.66155,31.77277],"type":"Point"}
}