{
  "type": "Feature",
  "properties": {
    "gn:admin1_code":"5.0",
    "gn:admin2_code":"91176.0",
    "gn:asciiname":"Mawriyas",
    "gn:country_code":"IQ",
    "gn:dem":1067,
    "gn:feature_class":"P",
    "gn:feature_code":"PPL",
    "gn:name":"Mawriy\u0101s",
    "gn:population":0,
    "gn:timezone":"Asia/Baghdad",
    "iso:country":"IQ",
    "name:ara_x_preferred":[
        "\u0645\u0648\u0631\u064a\u0627\u0633"
    ],
    "name:kur_x_preferred":[
        "Moryas"
    ],
    "name:kur_x_variant":[
        "\u0645\u06c6\u0631\u064a\u0627\u0633"
    ],
    "name:und_x_variant":[
        "Murias",
        "Mawriy\u0101s",
        "M\u014dry\u0101s"
    ],
    "wof:name":"Mawriyas",
    "wof:placetype":"locality"
},
  "geometry": {"coordinates":[45.72509,35.46963],"type":"Point"}
}