{
  "type": "Feature",
  "properties": {
    "gn:admin1_code":"5.0",
    "gn:admin2_code":"98464.0",
    "gn:asciiname":"Jankalawah",
    "gn:country_code":"IQ",
    "gn:dem":773,
    "gn:feature_class":"P",
    "gn:feature_code":"PPL",
    "gn:name":"Jankal\u0101wah",
    "gn:population":0,
    "gn:timezone":"Asia/Baghdad",
    "iso:country":"IQ",
    "name:ara_x_preferred":[
        "\u062c\u0646\u0643\u0644\u0627\u0648\u0647"
    ],
    "name:und_x_variant":[
        "Jankal\u0101wah",
        "Jangal\u0101wa"
    ],
    "wof:name":"Jankalawah",
    "wof:placetype":"locality"
},
  "geometry": {"coordinates":[45.27146,35.59544],"type":"Point"}
}