{
  "type": "Feature",
  "properties": {
    "gn:admin1_code":"2.0",
    "gn:admin2_code":"9166563.0",
    "gn:asciiname":"Ar Rafi'ah",
    "gn:country_code":"IQ",
    "gn:dem":2,
    "gn:feature_class":"P",
    "gn:feature_code":"PPL",
    "gn:name":"Ar Raf\u012b\u2018ah",
    "gn:population":0,
    "gn:timezone":"Asia/Baghdad",
    "iso:country":"IQ",
    "name:ara_x_preferred":[
        "\u0627\u0644\u0631\u0641\u064a\u0639\u0629"
    ],
    "name:und_x_variant":[
        "Ar Raf\u012b\u2018ah"
    ],
    "wof:name":"Ar Rafi'ah",
    "wof:placetype":"locality"
},
  "geometry": {"coordinates":[47.38081,31.17898],"type":"Point"}
}