{
  "type": "Feature",
  "properties": {
    "gn:admin1_code":"8.0",
    "gn:admin2_code":"89569.0",
    "gn:asciiname":"Nurah Dinah",
    "gn:country_code":"IQ",
    "gn:dem":769,
    "gn:feature_class":"P",
    "gn:feature_code":"PPL",
    "gn:name":"N\u016brah D\u012bnah",
    "gn:population":0,
    "gn:timezone":"Asia/Baghdad",
    "iso:country":"IQ",
    "name:ara_x_preferred":[
        "\u0646\u0648\u0631\u0647 \u062f\u064a\u0646\u0647"
    ],
    "name:kur_x_preferred":[
        "Nurd\u00eena"
    ],
    "name:kur_x_variant":[
        "\u0646\u0648\u0631\u062f\u064a\u0646\u0627"
    ],
    "name:und_x_variant":[
        "N\u0101rd\u012bn\u0101",
        "N\u016brd\u012bna",
        "Nurdina",
        "N\u016brah D\u012bnah"
    ],
    "wof:name":"Nurah Dinah",
    "wof:placetype":"locality"
},
  "geometry": {"coordinates":[42.80283,37.2293],"type":"Point"}
}