{
  "type": "Feature",
  "properties": {
    "gn:admin1_code":"7.0",
    "gn:admin2_code":"9166569.0",
    "gn:asciiname":"'Atiyah Mahdi",
    "gn:country_code":"IQ",
    "gn:dem":36,
    "gn:feature_class":"P",
    "gn:feature_code":"PPL",
    "gn:name":"\u2018A\u0163\u012byah Mahd\u012b",
    "gn:population":0,
    "gn:timezone":"Asia/Baghdad",
    "iso:country":"IQ",
    "name:ara_x_preferred":[
        "\u0639\u0637\u064a\u0629 \u0645\u0647\u062f\u064a"
    ],
    "name:und_x_variant":[
        "\u2018A\u0163\u012byah Mahd\u012b"
    ],
    "wof:name":"'Atiyah Mahdi",
    "wof:placetype":"locality"
},
  "geometry": {"coordinates":[44.28541,33.61768],"type":"Point"}
}