{
  "type": "Feature",
  "properties": {
    "gn:admin1_code":"15.0",
    "gn:admin2_code":"9166608.0",
    "gn:asciiname":"Buthat al Hayal",
    "gn:country_code":"IQ",
    "gn:dem":294,
    "gn:feature_class":"P",
    "gn:feature_code":"PPL",
    "gn:name":"B\u016bthat al \u1e28ay\u0101l",
    "gn:population":0,
    "gn:timezone":"Asia/Baghdad",
    "iso:country":"IQ",
    "name:ara_x_preferred":[
        "\u0628\u0648\u062b\u0629 \u0627\u0644\u062d\u064a\u0627\u0644"
    ],
    "name:und_x_variant":[
        "B\u016bthat al \u1e28ay\u0101l"
    ],
    "wof:name":"Buthat al Hayal",
    "wof:placetype":"locality"
},
  "geometry": {"coordinates":[41.63123,35.95871],"type":"Point"}
}