{
  "type": "Feature",
  "properties": {
    "gn:admin1_code":"18.0",
    "gn:admin2_code":"9166598.0",
    "gn:asciiname":"'Arab 'Atwan Rumayd",
    "gn:country_code":"IQ",
    "gn:dem":97,
    "gn:feature_class":"P",
    "gn:feature_code":"PPLL",
    "gn:name":"\u2018Arab \u2018A\u0163w\u0101n Rumay\u1e11",
    "gn:population":0,
    "gn:timezone":"Asia/Baghdad",
    "iso:country":"IQ",
    "name:ara_x_preferred":[
        "\u0639\u0631\u0628 \u0639\u0637\u0648\u0627\u0646 \u0631\u0645\u064a\u0636"
    ],
    "name:und_x_variant":[
        "\u2018Arab \u2018A\u0163w\u0101n Rumay\u1e11"
    ],
    "wof:name":"'Arab 'Atwan Rumayd",
    "wof:placetype":"locality"
},
  "geometry": {"coordinates":[44.31277,34.54264000000001],"type":"Point"}
}