{
  "type": "Feature",
  "properties": {
    "gn:admin1_code":"15.0",
    "gn:admin2_code":"98612.0",
    "gn:asciiname":"Gird Kal",
    "gn:country_code":"IQ",
    "gn:dem":329,
    "gn:feature_class":"P",
    "gn:feature_code":"PPL",
    "gn:name":"Gird Kal",
    "gn:population":0,
    "gn:timezone":"Asia/Baghdad",
    "iso:country":"IQ",
    "name:kur_x_preferred":[
        "Gird Kal"
    ],
    "name:kur_x_variant":[
        "\u06af\u0631\u062f \u0643\u0627\u0644"
    ],
    "wof:name":"Gird Kal",
    "wof:placetype":"locality"
},
  "geometry": {"coordinates":[43.50187,36.53172],"type":"Point"}
}