{
  "type": "Feature",
  "properties": {
    "gn:admin1_code":"3.0",
    "gn:admin2_code":"9166568.0",
    "gn:asciiname":"Sayyid Nur",
    "gn:country_code":"IQ",
    "gn:dem":16,
    "gn:feature_class":"P",
    "gn:feature_code":"PPL",
    "gn:name":"Sayyid N\u016br",
    "gn:population":0,
    "gn:timezone":"Asia/Baghdad",
    "iso:country":"IQ",
    "name:ara_x_preferred":[
        "\u0633\u064a\u062f \u0646\u0648\u0631"
    ],
    "name:und_x_variant":[
        "Sayyid N\u016br"
    ],
    "wof:name":"Sayyid Nur",
    "wof:placetype":"locality"
},
  "geometry": {"coordinates":[45.15772,31.50673],"type":"Point"}
}