{
  "type": "Feature",
  "properties": {
    "gn:admin1_code":"16.0",
    "gn:admin2_code":"98460.0",
    "gn:asciiname":"Jamdal Radi",
    "gn:country_code":"IQ",
    "gn:dem":27,
    "gn:feature_class":"P",
    "gn:feature_code":"PPL",
    "gn:name":"Jamdal R\u0101\u1e11\u012b",
    "gn:population":0,
    "gn:timezone":"Asia/Baghdad",
    "iso:country":"IQ",
    "name:ara_x_preferred":[
        "\u062c\u0645\u062f\u0644 \u0631\u0627\u0636\u064a"
    ],
    "name:und_x_variant":[
        "Jamdal R\u0101\u1e11\u012b"
    ],
    "wof:name":"Jamdal Radi",
    "wof:placetype":"locality"
},
  "geometry": {"coordinates":[45.12003,32.75837],"type":"Point"}
}