{
  "type": "Feature",
  "properties": {
    "gn:admin1_code":"4.0",
    "gn:admin2_code":"6850588.0",
    "gn:asciiname":"As Sayyid Hamud",
    "gn:cc2":"IQ",
    "gn:country_code":"IQ",
    "gn:dem":22,
    "gn:feature_class":"P",
    "gn:feature_code":"PPL",
    "gn:name":"As Sayyid \u1e28am\u016bd",
    "gn:population":0,
    "gn:timezone":"Asia/Baghdad",
    "iso:country":"IQ",
    "name:und_x_variant":[
        "As Saiyid Ham\u016bd",
        "As Sayyid \u1e28am\u016bd"
    ],
    "wof:name":"As Sayyid Hamud",
    "wof:placetype":"locality"
},
  "geometry": {"coordinates":[44.96667,31.78333],"type":"Point"}
}