{
  "type": "Feature",
  "properties": {
    "gn:admin1_code":"7.0",
    "gn:admin2_code":"9179819.0",
    "gn:asciiname":"Qaryat at Tuwithah",
    "gn:country_code":"IQ",
    "gn:dem":36,
    "gn:feature_class":"P",
    "gn:feature_code":"PPL",
    "gn:name":"Qaryat at Tuw\u012bthah",
    "gn:population":0,
    "gn:timezone":"Asia/Baghdad",
    "iso:country":"IQ",
    "name:ara_x_preferred":[
        "\u0642\u0631\u064a\u0629 \u0627\u0644\u062a\u0648\u064a\u062b\u0629"
    ],
    "name:und_x_variant":[
        "Qaryat at Tuw\u012bthah"
    ],
    "wof:name":"Qaryat at Tuwithah",
    "wof:placetype":"locality"
},
  "geometry": {"coordinates":[44.51188,33.19952],"type":"Point"}
}