{
  "type": "Feature",
  "properties": {
    "gn:admin1_code":"11.0",
    "gn:admin2_code":"93817.0",
    "gn:asciiname":"Bash",
    "gn:country_code":"IQ",
    "gn:dem":196,
    "gn:feature_class":"P",
    "gn:feature_code":"PPL",
    "gn:name":"Bash",
    "gn:population":0,
    "gn:timezone":"Asia/Baghdad",
    "iso:country":"IQ",
    "name:ara_x_preferred":[
        "\u0628\u0627\u0634 \u0628\u0646\u062f"
    ],
    "name:ceb_x_preferred":[
        "Bash"
    ],
    "name:deu_x_preferred":[
        "Bash"
    ],
    "name:fra_x_preferred":[
        "Bash"
    ],
    "name:jpn_x_preferred":[
        "\u30d0\u30c3\u30b7\u30e5"
    ],
    "name:kur_x_preferred":[
        "Bash"
    ],
    "name:kur_x_variant":[
        "\u0628\u0627\u0634"
    ],
    "name:nds_x_preferred":[
        "Bash"
    ],
    "name:nld_x_preferred":[
        "The Bash"
    ],
    "name:por_x_preferred":[
        "Bash"
    ],
    "name:rus_x_preferred":[
        "Bash"
    ],
    "name:ukr_x_preferred":[
        "Bash"
    ],
    "name:und_x_variant":[
        "Bash Band",
        "B\u0101sh Band"
    ],
    "wof:name":"Bash",
    "wof:placetype":"locality"
},
  "geometry": {"coordinates":[43.60121,35.56188],"type":"Point"}
}