{
  "type": "Feature",
  "properties": {
    "gn:admin1_code":"15.0",
    "gn:asciiname":"As Sadr",
    "gn:country_code":"IQ",
    "gn:dem":6,
    "gn:feature_class":"P",
    "gn:feature_code":"PPL",
    "gn:name":"A\u015f \u015eadr",
    "gn:population":0,
    "gn:timezone":"Asia/Baghdad",
    "iso:country":"IQ",
    "name:ara_x_preferred":[
        "\u0627\u0644\u0635\u062f\u0631"
    ],
    "name:nno_x_preferred":[
        "As Sadr"
    ],
    "name:und_x_variant":[
        "A\u015f \u015eadr"
    ],
    "wof:name":"As Sadr",
    "wof:placetype":"locality"
},
  "geometry": {"coordinates":[46.23923,31.08277],"type":"Point"}
}