{
  "type": "Feature",
  "properties": {
    "gn:admin1_code":"11.0",
    "gn:admin2_code":"9166592.0",
    "gn:asciiname":"Hidini",
    "gn:country_code":"IQ",
    "gn:dem":950,
    "gn:feature_class":"P",
    "gn:feature_code":"PPL",
    "gn:name":"Hid\u012bn\u012b",
    "gn:population":0,
    "gn:timezone":"Asia/Baghdad",
    "iso:country":"IQ",
    "name:ara_x_preferred":[
        "\u0647\u062f\u064a\u0646\u064a"
    ],
    "name:ara_x_variant":[
        "Hid\u012bn\u012b"
    ],
    "name:kur_x_preferred":[
        "Hidn\u00ee"
    ],
    "name:kur_x_variant":[
        "\u0647\u062f\u0646\u0649",
        "Hedn\u00ea",
        "\u06be\u06d5\u062f\u0646\u06ce"
    ],
    "name:und_x_variant":[
        "Hadan",
        "Hadni",
        "Hidny"
    ],
    "wof:name":"Hidini",
    "wof:placetype":"locality"
},
  "geometry": {"coordinates":[44.47355,37.07336],"type":"Point"}
}