{
  "type": "Feature",
  "properties": {
    "gn:admin1_code":"8.0",
    "gn:admin2_code":"99612.0",
    "gn:asciiname":"Jadiduk",
    "gn:country_code":"IQ",
    "gn:dem":1003,
    "gn:feature_class":"P",
    "gn:feature_code":"PPL",
    "gn:name":"Jad\u012bduk",
    "gn:population":0,
    "gn:timezone":"Asia/Baghdad",
    "iso:country":"IQ",
    "name:ara_x_preferred":[
        "\u062c\u062f\u064a\u062f\u0643"
    ],
    "name:kur_x_preferred":[
        "Cid\u00eerk"
    ],
    "name:kur_x_variant":[
        "\u062c\u062f\u064a\u0631\u0643",
        "Cid\u00eedk\u00ea",
        "\u062c\u062f\u064a\u062f\u0643\u06ce"
    ],
    "name:und_x_variant":[
        "Jdirk",
        "Jad\u012bduk",
        "Jidirk",
        "Jdidke"
    ],
    "wof:name":"Jadiduk",
    "wof:placetype":"locality"
},
  "geometry": {"coordinates":[43.27986,37.20737],"type":"Point"}
}