{
  "type": "Feature",
  "properties": {
    "gn:admin1_code":"2.0",
    "gn:admin2_code":"99534.0",
    "gn:asciiname":"Abu Gharb",
    "gn:country_code":"IQ",
    "gn:dem":2,
    "gn:feature_class":"P",
    "gn:feature_code":"PPL",
    "gn:name":"Ab\u016b Gharb",
    "gn:population":0,
    "gn:timezone":"Asia/Baghdad",
    "iso:country":"IQ",
    "name:ara_x_preferred":[
        "\u0627\u0628\u0648 \u063a\u0631\u0628"
    ],
    "name:und_x_variant":[
        "Ab\u016b Gharb"
    ],
    "wof:name":"Abu Gharb",
    "wof:placetype":"locality"
},
  "geometry": {"coordinates":[47.63689,30.78038],"type":"Point"}
}