{
  "type": "Feature",
  "properties": {
    "gn:admin1_code":"5.0",
    "gn:admin2_code":"91176.0",
    "gn:asciiname":"Tutkan",
    "gn:country_code":"IQ",
    "gn:dem":1143,
    "gn:feature_class":"P",
    "gn:feature_code":"PPL",
    "gn:name":"T\u016btk\u0101n",
    "gn:population":0,
    "gn:timezone":"Asia/Baghdad",
    "iso:country":"IQ",
    "name:ara_x_preferred":[
        "T\u016btk\u0101n"
    ],
    "name:ara_x_variant":[
        "\u062a\u0648\u062a\u0643\u0627\u0646"
    ],
    "name:kur_x_preferred":[
        "Tutkan"
    ],
    "name:und_x_variant":[
        "Totkan"
    ],
    "wof:name":"Tutkan",
    "wof:placetype":"locality"
},
  "geometry": {"coordinates":[45.68249,35.76871],"type":"Point"}
}