{
  "type": "Feature",
  "properties": {
    "gn:admin1_code":"15.0",
    "gn:admin2_code":"9166649.0",
    "gn:asciiname":"Qaryat Na'na'ah",
    "gn:country_code":"IQ",
    "gn:dem":246,
    "gn:feature_class":"P",
    "gn:feature_code":"PPL",
    "gn:name":"Qaryat Na\u2018n\u0101\u2018ah",
    "gn:population":0,
    "gn:timezone":"Asia/Baghdad",
    "iso:country":"IQ",
    "name:ara_x_preferred":[
        "\u0642\u0631\u064a\u0629 \u0646\u0639\u0646\u0627\u0639\u0629"
    ],
    "name:und_x_variant":[
        "Qaryat Na\u2018n\u0101\u2018ah"
    ],
    "wof:name":"Qaryat Na'na'ah",
    "wof:placetype":"locality"
},
  "geometry": {"coordinates":[43.28926,36.00581],"type":"Point"}
}