{
  "type": "Feature",
  "properties": {
    "gn:admin1_code":"11.0",
    "gn:admin2_code":"9166592.0",
    "gn:asciiname":"Aloka",
    "gn:country_code":"IQ",
    "gn:dem":1266,
    "gn:feature_class":"P",
    "gn:feature_code":"PPL",
    "gn:name":"Aloka",
    "gn:population":0,
    "gn:timezone":"Asia/Baghdad",
    "iso:country":"IQ",
    "name:ara_x_preferred":[
        "Alok\u0101n"
    ],
    "name:kur_x_preferred":[
        "Aloka"
    ],
    "name:kur_x_variant":[
        "\u0626\u0627\u0644\u06c6\u0643\u0627"
    ],
    "name:und_x_variant":[
        "Al\u016bk\u0101n"
    ],
    "wof:name":"Aloka",
    "wof:placetype":"locality"
},
  "geometry": {"coordinates":[44.69713,36.9423],"type":"Point"}
}