{
  "type": "Feature",
  "properties": {
    "gn:admin1_code":"13.0",
    "gn:asciiname":"Si Qawjan",
    "gn:country_code":"IQ",
    "gn:dem":264,
    "gn:feature_class":"P",
    "gn:feature_code":"PPL",
    "gn:name":"S\u012b Qawj\u0101n",
    "gn:population":0,
    "gn:timezone":"Asia/Baghdad",
    "iso:country":"IQ",
    "name:ara_x_preferred":[
        "\u0633\u064a \u0642\u0648\u062c\u0627\u0646"
    ],
    "name:ara_x_variant":[
        "S\u012b Q\u016bj\u0101n"
    ],
    "name:kur_x_preferred":[
        "Qochan"
    ],
    "name:kur_x_variant":[
        "\u0642\u06c6\u0686\u0627\u0646"
    ],
    "name:und_x_variant":[
        "Se Quchan",
        "S\u012b Qawj\u0101n"
    ],
    "wof:name":"Si Qawjan",
    "wof:placetype":"locality"
},
  "geometry": {"coordinates":[43.82857,35.74087],"type":"Point"}
}