{
  "type": "Feature",
  "properties": {
    "gn:admin1_code":"5.0",
    "gn:admin2_code":"9166594.0",
    "gn:asciiname":"Bay Silamayn",
    "gn:country_code":"IQ",
    "gn:dem":539,
    "gn:feature_class":"P",
    "gn:feature_code":"PPL",
    "gn:name":"Bay Silamayn",
    "gn:population":0,
    "gn:timezone":"Asia/Baghdad",
    "iso:country":"IQ",
    "name:ara_x_preferred":[
        "\u0628\u064a \u0633\u0644\u0645\u064a\u0646"
    ],
    "name:fas_x_preferred":[
        "\u0628\u06cc\u0633\u0644\u0645\u06cc\u0646"
    ],
    "name:fas_x_variant":[
        "B\u012bsalm\u012bn"
    ],
    "name:kur_x_preferred":[
        "B\u00ea S\u0142em\u00ean"
    ],
    "name:kur_x_variant":[
        "\u0628\u06ce \u0633\u06b5\u06d5\u0645\u06ce\u0646"
    ],
    "name:und_x_variant":[
        "Baisalmain",
        "Baysalmayn",
        "B\u012bsalm\u0113n",
        "Saysalmayn",
        "Bay Silamayn",
        "Be Slamen"
    ],
    "wof:name":"Bay Silamayn",
    "wof:placetype":"locality"
},
  "geometry": {"coordinates":[45.84602,35.23811],"type":"Point"}
}