{
  "type": "Feature",
  "properties": {
    "gn:admin1_code":"5.0",
    "gn:admin2_code":"91176.0",
    "gn:asciiname":"Chnara",
    "gn:country_code":"IQ",
    "gn:dem":1257,
    "gn:feature_class":"P",
    "gn:feature_code":"PPL",
    "gn:name":"Chnara",
    "gn:population":0,
    "gn:timezone":"Asia/Baghdad",
    "iso:country":"IQ",
    "name:fas_x_preferred":[
        "\u0686\u0646\u0631\u06cc \u0634\u06cc\u062e \u0644\u0637\u06cc\u0641"
    ],
    "name:kur_x_preferred":[
        "Chinarey Sh\u00eax Let\u00eef"
    ],
    "name:kur_x_variant":[
        "Chinarey Sh\u00eax E\u0142mar\u00ean",
        "\u0686\u0646\u0627\u0631\u06d5\u0649 \u0634\u06ce\u062e \u0644\u06d5\u062a\u064a\u0641",
        "\u0686\u0646\u0627\u0631\u06d5\u0649 \u0634\u06ce\u062e \u0626\u06d5\u06b5\u0645\u0627\u0631\u06ce\u0646"
    ],
    "name:und_x_variant":[
        "Chinara-\u0113 Shaykh La\u0163\u012bf",
        "Chanr\u012b Sheykh La\u0163\u012bf",
        "Chnara",
        "Chinarah Shaykh La\u0163\u012bf"
    ],
    "wof:name":"Chnara",
    "wof:placetype":"locality"
},
  "geometry": {"coordinates":[45.7651,35.6941],"type":"Point"}
}