{
  "type": "Feature",
  "properties": {
    "gn:admin1_code":"9.0",
    "gn:admin2_code":"98700.0",
    "gn:asciiname":"Abu Jama'",
    "gn:country_code":"IQ",
    "gn:dem":12,
    "gn:feature_class":"P",
    "gn:feature_code":"PPL",
    "gn:name":"Ab\u016b Jam\u0101\u2019",
    "gn:population":0,
    "gn:timezone":"Asia/Baghdad",
    "iso:country":"IQ",
    "name:ara_x_preferred":[
        "\u0627\u0628\u0648 \u062c\u0645\u0627\u0621"
    ],
    "name:und_x_variant":[
        "Ab\u016b Jam\u0101\u2019"
    ],
    "wof:name":"Abu Jama'",
    "wof:placetype":"locality"
},
  "geometry": {"coordinates":[46.01094000000001,31.95693],"type":"Point"}
}