{
  "type": "Feature",
  "properties": {
    "gn:admin1_code":"7.0",
    "gn:admin2_code":"9166545.0",
    "gn:asciiname":"'Abbas Ahmad",
    "gn:country_code":"IQ",
    "gn:dem":35,
    "gn:feature_class":"P",
    "gn:feature_code":"PPL",
    "gn:name":"\u2018Abb\u0101s A\u1e29mad",
    "gn:population":0,
    "gn:timezone":"Asia/Baghdad",
    "iso:country":"IQ",
    "name:ara_x_preferred":[
        "\u0639\u0628\u0627\u0633 \u0627\u062d\u0645\u062f"
    ],
    "name:und_x_variant":[
        "\u2018Abb\u0101s A\u1e29mad"
    ],
    "wof:name":"'Abbas Ahmad",
    "wof:placetype":"locality"
},
  "geometry": {"coordinates":[44.44197,33.22821],"type":"Point"}
}