{
  "type": "Feature",
  "properties": {
    "gn:admin1_code":"7.0",
    "gn:admin2_code":"9167085.0",
    "gn:asciiname":"Mulla Muslih",
    "gn:country_code":"IQ",
    "gn:dem":42,
    "gn:feature_class":"P",
    "gn:feature_code":"PPL",
    "gn:name":"Mull\u0101 Mu\u015fli\u1e29",
    "gn:population":0,
    "gn:timezone":"Asia/Baghdad",
    "iso:country":"IQ",
    "name:ara_x_preferred":[
        "Mull\u0101 Mu\u015fli\u1e29"
    ],
    "name:und_x_variant":[
        "Mu\u015fli\u1e29"
    ],
    "wof:name":"Mulla Muslih",
    "wof:placetype":"locality"
},
  "geometry": {"coordinates":[44.35194,33.62333],"type":"Point"}
}