{
  "type": "Feature",
  "properties": {
    "gn:admin1_code":"15.0",
    "gn:admin2_code":"9166541.0",
    "gn:asciiname":"Qaryat Tawajinah al Qadimah",
    "gn:country_code":"IQ",
    "gn:dem":263,
    "gn:feature_class":"P",
    "gn:feature_code":"PPL",
    "gn:name":"Qaryat \u0162aw\u0101jinah al Qad\u012bmah",
    "gn:population":0,
    "gn:timezone":"Asia/Baghdad",
    "iso:country":"IQ",
    "name:ara_x_preferred":[
        "\u0642\u0631\u064a\u0629 \u0637\u0648\u0627\u062c\u0646\u0629 \u0627\u0644\u0642\u062f\u064a\u0645\u0629"
    ],
    "name:und_x_variant":[
        "Qaryat \u0162aw\u0101jinah al Qad\u012bmah"
    ],
    "wof:name":"Qaryat Tawajinah al Qadimah",
    "wof:placetype":"locality"
},
  "geometry": {"coordinates":[43.2864,36.22137],"type":"Point"}
}