{
  "type": "Feature",
  "properties": {
    "gn:admin1_code":"5.0",
    "gn:admin2_code":"9166596.0",
    "gn:asciiname":"Hawmar Qawm",
    "gn:country_code":"IQ",
    "gn:dem":1095,
    "gn:feature_class":"P",
    "gn:feature_code":"PPL",
    "gn:name":"Hawmar Qawm",
    "gn:population":0,
    "gn:timezone":"Asia/Baghdad",
    "iso:country":"IQ",
    "name:ara_x_preferred":[
        "\u0647\u0648\u0645\u0631 \u0642\u0648\u0645"
    ],
    "name:kur_x_preferred":[
        "Homer Qewm"
    ],
    "name:kur_x_variant":[
        "\u06be\u06c6\u0645\u06d5\u0631 \u0642\u06d5\u0648\u0645"
    ],
    "name:und_x_variant":[
        "\u2018Umar Qawn",
        "Homar Qawm",
        "H\u014dmarq\u014dm",
        "Hawmar Qawm",
        "Hamar Qawm"
    ],
    "wof:name":"Hawmar Qawm",
    "wof:placetype":"locality"
},
  "geometry": {"coordinates":[45.12885,35.85449000000001],"type":"Point"}
}