{
  "type": "Feature",
  "properties": {
    "gn:admin1_code":"18.0",
    "gn:admin2_code":"9166616.0",
    "gn:asciiname":"Tall as Sab'",
    "gn:country_code":"IQ",
    "gn:dem":52,
    "gn:feature_class":"P",
    "gn:feature_code":"PPL",
    "gn:name":"Tall as Sab\u2018",
    "gn:population":0,
    "gn:timezone":"Asia/Baghdad",
    "iso:country":"IQ",
    "name:ara_x_preferred":[
        "\u062a\u0644 \u0627\u0644\u0633\u0628\u0639"
    ],
    "name:und_x_variant":[
        "Tall as Sab\u2018"
    ],
    "wof:name":"Tall as Sab'",
    "wof:placetype":"locality"
},
  "geometry": {"coordinates":[43.84643,33.75704],"type":"Point"}
}