{
  "type": "Feature",
  "properties": {
    "gn:admin1_code":"1.0",
    "gn:admin2_code":"98678.0",
    "gn:asciiname":"Mahfur al Jandali",
    "gn:country_code":"IQ",
    "gn:dem":768,
    "gn:feature_class":"P",
    "gn:feature_code":"PPL",
    "gn:name":"Ma\u1e29f\u016br al Jandal\u012b",
    "gn:population":0,
    "gn:timezone":"Asia/Baghdad",
    "iso:country":"IQ",
    "name:ara_x_preferred":[
        "\u0645\u062d\u0641\u0648\u0631 \u0627\u0644\u062c\u0646\u062f\u0644\u064a"
    ],
    "name:und_x_variant":[
        "Ma\u1e29f\u016br al Jandal\u012b"
    ],
    "wof:name":"Mahfur al Jandali",
    "wof:placetype":"locality"
},
  "geometry": {"coordinates":[39.76358,33.13959000000001],"type":"Point"}
}