{
  "type": "Feature",
  "properties": {
    "gn:admin1_code":"10.0",
    "gn:admin2_code":"9166680.0",
    "gn:asciiname":"Qaryat Huzayran",
    "gn:country_code":"IQ",
    "gn:dem":39,
    "gn:feature_class":"P",
    "gn:feature_code":"PPL",
    "gn:name":"Qaryat \u1e28uzayr\u0101n",
    "gn:population":0,
    "gn:timezone":"Asia/Baghdad",
    "iso:country":"IQ",
    "name:ara_x_preferred":[
        "\u0642\u0631\u064a\u0629 \u062d\u0632\u064a\u0631\u0627\u0646"
    ],
    "name:und_x_variant":[
        "Qaryat \u1e28uzayr\u0101n"
    ],
    "wof:name":"Qaryat Huzayran",
    "wof:placetype":"locality"
},
  "geometry": {"coordinates":[45.03628,33.5915],"type":"Point"}
}