{
  "type": "Feature",
  "properties": {
    "gn:admin1_code":"9.0",
    "gn:admin2_code":"98623.0",
    "gn:asciiname":"Sayyid Rida",
    "gn:country_code":"IQ",
    "gn:dem":7,
    "gn:feature_class":"P",
    "gn:feature_code":"PPL",
    "gn:name":"Sayyid Ri\u1e11\u0101",
    "gn:population":0,
    "gn:timezone":"Asia/Baghdad",
    "iso:country":"IQ",
    "name:ara_x_preferred":[
        "\u0633\u064a\u062f \u0631\u0636\u0627"
    ],
    "name:und_x_variant":[
        "Sayyid Ri\u1e11\u0101"
    ],
    "wof:name":"Sayyid Rida",
    "wof:placetype":"locality"
},
  "geometry": {"coordinates":[46.0986,31.48082],"type":"Point"}
}