{
  "type": "Feature",
  "properties": {
    "gn:admin1_code":"6.0",
    "gn:admin2_code":"99358.0",
    "gn:asciiname":"Kamil 'Abd al Hussayn",
    "gn:country_code":"IQ",
    "gn:dem":25,
    "gn:feature_class":"P",
    "gn:feature_code":"PPL",
    "gn:name":"K\u0101mil \u2018Abd al \u1e28ussayn",
    "gn:population":0,
    "gn:timezone":"Asia/Baghdad",
    "iso:country":"IQ",
    "name:ara_x_preferred":[
        "\u0643\u0627\u0645\u0644 \u0639\u0628\u062f \u0627\u0644\u062d\u0633\u064a\u0646"
    ],
    "name:und_x_variant":[
        "K\u0101mil \u2018Abd al \u1e28ussayn"
    ],
    "wof:name":"Kamil 'Abd al Hussayn",
    "wof:placetype":"locality"
},
  "geometry": {"coordinates":[44.92578,32.36813],"type":"Point"}
}