{
  "type": "Feature",
  "properties": {
    "gn:admin1_code":"18.0",
    "gn:asciiname":"Ahmad al Husayn",
    "gn:country_code":"IQ",
    "gn:dem":37,
    "gn:feature_class":"P",
    "gn:feature_code":"PPL",
    "gn:name":"A\u1e29mad al \u1e28usayn",
    "gn:population":0,
    "gn:timezone":"Asia/Baghdad",
    "iso:country":"IQ",
    "name:und_x_variant":[
        "Ahmad al Husain",
        "A\u1e29mad al \u1e28usayn"
    ],
    "wof:name":"Ahmad al Husayn",
    "wof:placetype":"locality"
},
  "geometry": {"coordinates":[44.11222,33.53333],"type":"Point"}
}