{
  "type": "Feature",
  "properties": {
    "gn:admin1_code":"8.0",
    "gn:admin2_code":"98820.0",
    "gn:asciiname":"Jamshiti",
    "gn:country_code":"IQ",
    "gn:dem":692,
    "gn:feature_class":"P",
    "gn:feature_code":"PPL",
    "gn:name":"Jamsh\u012bt\u012b",
    "gn:population":0,
    "gn:timezone":"Asia/Baghdad",
    "iso:country":"IQ",
    "name:ara_x_preferred":[
        "\u062c\u0645\u0634\u064a\u062a\u064a"
    ],
    "name:kur_x_preferred":[
        "Cemsh\u00een\u00ee"
    ],
    "name:kur_x_variant":[
        "\u062c\u06d5\u0645\u0634\u064a\u0646\u0649",
        "Chem Shar\u00ealik",
        "Chem Sharlik",
        "\u0686\u06d5\u0645 \u0634\u0627\u0631\u06ce\u0644\u0643",
        "\u0686\u06d5\u0645 \u0634\u0627\u0631\u0644\u0643"
    ],
    "name:und_x_variant":[
        "Jamshini",
        "Cham Shirit\u012b",
        "Jamsh\u012bt\u012b"
    ],
    "wof:name":"Jamshiti",
    "wof:placetype":"locality"
},
  "geometry": {"coordinates":[43.7113,36.90901],"type":"Point"}
}