{
  "type": "Feature",
  "properties": {
    "gn:admin1_code":"16.0",
    "gn:admin2_code":"98460.0",
    "gn:asciiname":"Dar Hatim Kattab",
    "gn:country_code":"IQ",
    "gn:dem":24,
    "gn:feature_class":"P",
    "gn:feature_code":"PPL",
    "gn:name":"D\u0101r \u1e28\u0101tim Katt\u0101b",
    "gn:population":0,
    "gn:timezone":"Asia/Baghdad",
    "iso:country":"IQ",
    "name:ara_x_preferred":[
        "\u062f\u0627\u0631 \u062d\u0627\u062a\u0645 \u0643\u062a\u0627\u0628"
    ],
    "name:und_x_variant":[
        "D\u0101r \u1e28\u0101tim Katt\u0101b"
    ],
    "wof:name":"Dar Hatim Kattab",
    "wof:placetype":"locality"
},
  "geometry": {"coordinates":[45.27803,32.66801],"type":"Point"}
}