{
  "type": "Feature",
  "properties": {
    "gn:admin1_code":"7.0",
    "gn:admin2_code":"99173.0",
    "gn:asciiname":"'Abd Shuday'",
    "gn:country_code":"IQ",
    "gn:dem":36,
    "gn:feature_class":"P",
    "gn:feature_code":"PPL",
    "gn:name":"\u2018Abd Shuday\u2018",
    "gn:population":0,
    "gn:timezone":"Asia/Baghdad",
    "iso:country":"IQ",
    "name:ara_x_preferred":[
        "\u0639\u0628\u062f \u0634\u062f\u064a\u0639"
    ],
    "name:und_x_variant":[
        "\u2018Abd Shuday\u2018"
    ],
    "wof:name":"'Abd Shuday'",
    "wof:placetype":"locality"
},
  "geometry": {"coordinates":[44.18584,33.5124],"type":"Point"}
}