{
  "type": "Feature",
  "properties": {
    "gn:admin1_code":"13.0",
    "gn:admin2_code":"9166581.0",
    "gn:asciiname":"Tawfiq Agha",
    "gn:country_code":"IQ",
    "gn:dem":202,
    "gn:feature_class":"P",
    "gn:feature_code":"PPL",
    "gn:name":"Tawf\u012bq \u0100gh\u0101",
    "gn:population":0,
    "gn:timezone":"Asia/Baghdad",
    "iso:country":"IQ",
    "name:ara_x_preferred":[
        "\u062a\u0648\u0641\u064a\u0642 \u0622\u063a\u0627"
    ],
    "name:und_x_variant":[
        "Tawf\u012bq \u0100gh\u0101"
    ],
    "wof:name":"Tawfiq Agha",
    "wof:placetype":"locality"
},
  "geometry": {"coordinates":[44.44241,35.03753],"type":"Point"}
}