{
  "type": "Feature",
  "properties": {
    "gn:admin1_code":"5.0",
    "gn:admin2_code":"96204.0",
    "gn:asciiname":"Mastakan 'Ulya Zuru",
    "gn:country_code":"IQ",
    "gn:dem":499,
    "gn:feature_class":"P",
    "gn:feature_code":"PPL",
    "gn:name":"Mastak\u0101n \u2018Uly\u0101 Z\u016br\u016b",
    "gn:population":0,
    "gn:timezone":"Asia/Baghdad",
    "iso:country":"IQ",
    "name:ara_x_preferred":[
        "\u0645\u0633\u062a\u0643\u0627\u0646 \u0639\u0644\u064a\u0627 \u0632\u0648\u0631\u0648"
    ],
    "name:fas_x_preferred":[
        "\u0645\u0633\u062a\u06a9\u0627\u0646 \u0698\u0648\u0631\u0648"
    ],
    "name:fas_x_variant":[
        "Mastak\u0101n-e Zh\u016br\u016b"
    ],
    "name:kur_x_preferred":[
        "Mastekan\u00ee Ser\u00fb"
    ],
    "name:kur_x_variant":[
        "\u0645\u0627\u0633\u062a\u06d5\u0643\u0627\u0646\u0649 \u0633\u06d5\u0631\u0648\u0648"
    ],
    "name:und_x_variant":[
        "Mastak\u0101n-i Zh\u016br\u016b",
        "Mastak\u0101n \u2018Uly\u0101 Z\u016br\u016b",
        "Mastakan"
    ],
    "wof:name":"Mastakan 'Ulya Zuru",
    "wof:placetype":"locality"
},
  "geometry": {"coordinates":[45.91853,35.32660999999999],"type":"Point"}
}