{
  "type": "Feature",
  "properties": {
    "gn:admin1_code":"7.0",
    "gn:admin2_code":"9166569.0",
    "gn:asciiname":"Sayr Raml Mushwih",
    "gn:country_code":"IQ",
    "gn:dem":40,
    "gn:feature_class":"P",
    "gn:feature_code":"PPL",
    "gn:name":"\u015eayr Raml Mushwi\u1e29",
    "gn:population":0,
    "gn:timezone":"Asia/Baghdad",
    "iso:country":"IQ",
    "name:ara_x_preferred":[
        "\u0635\u064a\u0631 \u0631\u0645\u0644 \u0645\u0634\u0648\u062d"
    ],
    "name:und_x_variant":[
        "\u015eayr Raml Mushwi\u1e29"
    ],
    "wof:name":"Sayr Raml Mushwih",
    "wof:placetype":"locality"
},
  "geometry": {"coordinates":[44.20742,33.61515],"type":"Point"}
}