{
  "type": "Feature",
  "properties": {
    "gn:admin1_code":"6.0",
    "gn:admin2_code":"99358.0",
    "gn:asciiname":"Rasan Jawad",
    "gn:country_code":"IQ",
    "gn:dem":26,
    "gn:feature_class":"P",
    "gn:feature_code":"PPL",
    "gn:name":"Rasan Jaw\u0101d",
    "gn:population":0,
    "gn:timezone":"Asia/Baghdad",
    "iso:country":"IQ",
    "name:ara_x_preferred":[
        "\u0631\u0633\u0646 \u062c\u0648\u0627\u062f"
    ],
    "name:und_x_variant":[
        "Rasan Jaw\u0101d"
    ],
    "wof:name":"Rasan Jawad",
    "wof:placetype":"locality"
},
  "geometry": {"coordinates":[44.77477,32.43984],"type":"Point"}
}