{
  "type": "Feature",
  "properties": {
    "gn:admin1_code":"7.0",
    "gn:admin2_code":"9166569.0",
    "gn:asciiname":"Mahmud al Khalifah",
    "gn:country_code":"IQ",
    "gn:dem":37,
    "gn:feature_class":"P",
    "gn:feature_code":"PPL",
    "gn:name":"Ma\u1e29m\u016bd al Khal\u012bfah",
    "gn:population":0,
    "gn:timezone":"Asia/Baghdad",
    "iso:country":"IQ",
    "name:ara_x_preferred":[
        "\u0645\u062d\u0645\u0648\u062f \u0627\u0644\u062e\u0644\u064a\u0641\u0629"
    ],
    "name:und_x_variant":[
        "Ma\u1e29m\u016bd al Khal\u012bfah"
    ],
    "wof:name":"Mahmud al Khalifah",
    "wof:placetype":"locality"
},
  "geometry": {"coordinates":[44.28852,33.64499],"type":"Point"}
}