{
  "type": "Feature",
  "properties": {
    "gn:admin1_code":"7.0",
    "gn:admin2_code":"9166569.0",
    "gn:asciiname":"Qaryat Albu Firas",
    "gn:country_code":"IQ",
    "gn:dem":41,
    "gn:feature_class":"P",
    "gn:feature_code":"PPL",
    "gn:name":"Qaryat \u0100lb\u016b Fir\u0101s",
    "gn:population":0,
    "gn:timezone":"Asia/Baghdad",
    "iso:country":"IQ",
    "name:ara_x_preferred":[
        "\u0642\u0631\u064a\u0629 \u0627\u0644\u0628\u0648\u0627\u0644\u0641\u0631\u0627\u0633"
    ],
    "name:und_x_variant":[
        "Qaryat \u0100lb\u016b Fir\u0101s"
    ],
    "wof:name":"Qaryat Albu Firas",
    "wof:placetype":"locality"
},
  "geometry": {"coordinates":[44.25007,33.68737],"type":"Point"}
}