{
  "type": "Feature",
  "properties": {
    "gn:admin1_code":"7.0",
    "gn:admin2_code":"9179819.0",
    "gn:asciiname":"Dur al 'Ummal",
    "gn:country_code":"IQ",
    "gn:dem":37,
    "gn:feature_class":"P",
    "gn:feature_code":"PPL",
    "gn:name":"D\u016br al \u2018Umm\u0101l",
    "gn:population":0,
    "gn:timezone":"Asia/Baghdad",
    "iso:country":"IQ",
    "name:ara_x_preferred":[
        "\u062f\u0648\u0631 \u0627\u0644\u0639\u0645\u0627\u0644"
    ],
    "name:und_x_variant":[
        "D\u016br al \u2018Umm\u0101l"
    ],
    "wof:name":"Dur al 'Ummal",
    "wof:placetype":"locality"
},
  "geometry": {"coordinates":[44.73674000000001,33.28567],"type":"Point"}
}