{
  "type": "Feature",
  "properties": {
    "gn:admin1_code":"15.0",
    "gn:admin2_code":"9166649.0",
    "gn:asciiname":"Qaryat Khabatah",
    "gn:country_code":"IQ",
    "gn:dem":181,
    "gn:feature_class":"P",
    "gn:feature_code":"PPL",
    "gn:name":"Qaryat Khab\u0101\u0163ah",
    "gn:population":0,
    "gn:timezone":"Asia/Baghdad",
    "iso:country":"IQ",
    "name:ara_x_preferred":[
        "\u0642\u0631\u064a\u0629 \u062e\u0628\u0627\u0637\u0629"
    ],
    "name:und_x_variant":[
        "Khabata",
        "Khab\u0101\u0163ah",
        "Qaryat Khab\u0101\u0163ah"
    ],
    "wof:name":"Qaryat Khabatah",
    "wof:placetype":"locality"
},
  "geometry": {"coordinates":[43.32838,35.82884],"type":"Point"}
}