{
  "type": "Feature",
  "properties": {
    "gn:admin1_code":"7.0",
    "gn:admin2_code":"9167085.0",
    "gn:asciiname":"Ad Dawudiyah",
    "gn:country_code":"IQ",
    "gn:dem":41,
    "gn:feature_class":"P",
    "gn:feature_code":"PPL",
    "gn:name":"Ad D\u0101wud\u012byah",
    "gn:population":0,
    "gn:timezone":"Asia/Baghdad",
    "iso:country":"IQ",
    "name:ara_x_preferred":[
        "\u0627\u0644\u062f\u0627\u0648\u062f\u064a\u0629"
    ],
    "name:und_x_variant":[
        "D\u0101\u016bd\u012bya",
        "D\u0101w\u016bd\u012byah",
        "Ad D\u0101wud\u012byah"
    ],
    "wof:name":"Ad Dawudiyah",
    "wof:placetype":"locality"
},
  "geometry": {"coordinates":[44.31705,33.53798],"type":"Point"}
}