{
  "type": "Feature",
  "properties": {
    "gn:admin1_code":"18.0",
    "gn:admin2_code":"91594.0",
    "gn:asciiname":"'Ali Khalaf Rahim",
    "gn:country_code":"IQ",
    "gn:dem":89,
    "gn:feature_class":"P",
    "gn:feature_code":"PPL",
    "gn:name":"\u2018Al\u012b Khalaf Ra\u1e29\u012bm",
    "gn:population":0,
    "gn:timezone":"Asia/Baghdad",
    "iso:country":"IQ",
    "name:ara_x_preferred":[
        "\u0639\u0644\u064a \u062e\u0644\u0641 \u0631\u062d\u064a\u0645"
    ],
    "name:und_x_variant":[
        "\u2018Al\u012b Khalaf Ra\u1e29\u012bm"
    ],
    "wof:name":"'Ali Khalaf Rahim",
    "wof:placetype":"locality"
},
  "geometry": {"coordinates":[43.56181,34.15047],"type":"Point"}
}