{
  "type": "Feature",
  "properties": {
    "gn:admin1_code":"6.0",
    "gn:admin2_code":"99040.0",
    "gn:asciiname":"Sayyid",
    "gn:cc2":"IQ",
    "gn:country_code":"IQ",
    "gn:dem":32,
    "gn:feature_class":"P",
    "gn:feature_code":"PPL",
    "gn:name":"Sayyid",
    "gn:population":0,
    "gn:timezone":"Asia/Baghdad",
    "iso:country":"IQ",
    "name:und_x_variant":[
        "Saiyid",
        "Sayyid"
    ],
    "wof:name":"Sayyid",
    "wof:placetype":"locality"
},
  "geometry": {"coordinates":[44.26667,32.68333],"type":"Point"}
}