{
  "type": "Feature",
  "properties": {
    "gn:admin1_code":"18.0",
    "gn:admin2_code":"6805736.0",
    "gn:asciiname":"Az Zawr Albu Hathmah",
    "gn:country_code":"IQ",
    "gn:dem":40,
    "gn:feature_class":"P",
    "gn:feature_code":"PPL",
    "gn:name":"Az Zawr \u0100lb\u016b \u1e28athmah",
    "gn:population":0,
    "gn:timezone":"Asia/Baghdad",
    "iso:country":"IQ",
    "name:ara_x_preferred":[
        "\u0627\u0644\u0632\u0648\u0631 \u0627\u0644\u0628\u0648 \u062d\u062b\u0645\u0629"
    ],
    "name:und_x_variant":[
        "Az Zawr \u0100lb\u016b \u1e28athmah"
    ],
    "wof:name":"Az Zawr Albu Hathmah",
    "wof:placetype":"locality"
},
  "geometry": {"coordinates":[44.37633,33.99023],"type":"Point"}
}