{
  "type": "Feature",
  "properties": {
    "gn:admin1_code":"17.0",
    "gn:admin2_code":"9166552.0",
    "gn:asciiname":"Sayyid Khayyun",
    "gn:country_code":"IQ",
    "gn:dem":20,
    "gn:feature_class":"P",
    "gn:feature_code":"PPLL",
    "gn:name":"Sayyid Khayy\u016bn",
    "gn:population":0,
    "gn:timezone":"Asia/Baghdad",
    "iso:country":"IQ",
    "name:ara_x_preferred":[
        "\u0633\u064a\u062f \u062e\u064a\u0648\u0646"
    ],
    "name:und_x_variant":[
        "Sayyid Khayy\u016bn"
    ],
    "wof:name":"Sayyid Khayyun",
    "wof:placetype":"locality"
},
  "geometry": {"coordinates":[44.48674000000001,31.74235],"type":"Point"}
}