{
  "type": "Feature",
  "properties": {
    "gn:admin1_code":"7.0",
    "gn:admin2_code":"9179819.0",
    "gn:asciiname":"Rashid Attyah",
    "gn:country_code":"IQ",
    "gn:dem":35,
    "gn:feature_class":"P",
    "gn:feature_code":"PPL",
    "gn:name":"Ras\u1e29id Attyah",
    "gn:population":0,
    "gn:timezone":"Asia/Baghdad",
    "iso:country":"IQ",
    "name:und_x_variant":[
        "Ras\u1e29id Attyah"
    ],
    "wof:name":"Rashid Attyah",
    "wof:placetype":"locality"
},
  "geometry": {"coordinates":[44.54444,33.18444],"type":"Point"}
}