{
  "type": "Feature",
  "properties": {
    "gn:admin1_code":"18.0",
    "gn:admin2_code":"9167093.0",
    "gn:asciiname":"Jum'at Mahdi",
    "gn:country_code":"IQ",
    "gn:dem":76,
    "gn:feature_class":"P",
    "gn:feature_code":"PPL",
    "gn:name":"Jum\u2018at Mahd\u012b",
    "gn:population":0,
    "gn:timezone":"Asia/Baghdad",
    "iso:country":"IQ",
    "name:ara_x_preferred":[
        "\u062c\u0645\u0639\u0629 \u0645\u0647\u062f\u064a"
    ],
    "name:und_x_variant":[
        "Jum\u2018at Mahd\u012b"
    ],
    "wof:name":"Jum'at Mahdi",
    "wof:placetype":"locality"
},
  "geometry": {"coordinates":[43.6678,34.12081],"type":"Point"}
}