{
  "type": "Feature",
  "properties": {
    "gn:admin1_code":"4.0",
    "gn:admin2_code":"6850588.0",
    "gn:asciiname":"Ghazi Sa'd",
    "gn:country_code":"IQ",
    "gn:dem":16,
    "gn:feature_class":"P",
    "gn:feature_code":"PPL",
    "gn:name":"Gh\u0101z\u012b Sa\u2018d",
    "gn:population":0,
    "gn:timezone":"Asia/Baghdad",
    "iso:country":"IQ",
    "name:ara_x_preferred":[
        "\u063a\u0627\u0632\u064a \u0633\u0639\u062f"
    ],
    "name:und_x_variant":[
        "Gh\u0101z\u012b Sa\u2018d"
    ],
    "wof:name":"Ghazi Sa'd",
    "wof:placetype":"locality"
},
  "geometry": {"coordinates":[44.89821,31.66941],"type":"Point"}
}