{
  "type": "Feature",
  "properties": {
    "gn:admin1_code":"3.0",
    "gn:admin2_code":"9166568.0",
    "gn:asciiname":"Wali al Kanis",
    "gn:country_code":"IQ",
    "gn:dem":15,
    "gn:feature_class":"P",
    "gn:feature_code":"PPL",
    "gn:name":"W\u0101l\u012b al Kan\u012bs",
    "gn:population":0,
    "gn:timezone":"Asia/Baghdad",
    "iso:country":"IQ",
    "name:ara_x_preferred":[
        "\u0648\u0627\u0644\u064a \u0627\u0644\u06a9\u0646\u064a\u0633"
    ],
    "name:und_x_variant":[
        "W\u0101l\u012b al Kan\u012bs"
    ],
    "wof:name":"Wali al Kanis",
    "wof:placetype":"locality"
},
  "geometry": {"coordinates":[45.23199,31.48861],"type":"Point"}
}