{
  "type": "Feature",
  "properties": {
    "gn:admin1_code":"14.0",
    "gn:admin2_code":"92536.0",
    "gn:asciiname":"Qal'at Sayyid Hasan",
    "gn:country_code":"IQ",
    "gn:dem":8,
    "gn:feature_class":"P",
    "gn:feature_code":"PPL",
    "gn:name":"Qal\u2018at Sayyid \u1e28asan",
    "gn:population":0,
    "gn:timezone":"Asia/Baghdad",
    "iso:country":"IQ",
    "name:ara_x_preferred":[
        "\u0642\u0644\u0639\u0629 \u0633\u064a\u062f \u062d\u0633\u0646"
    ],
    "name:und_x_variant":[
        "Qal\u2018at Sayyid \u1e28asan"
    ],
    "wof:name":"Qal'at Sayyid Hasan",
    "wof:placetype":"locality"
},
  "geometry": {"coordinates":[47.32665,31.53619],"type":"Point"}
}