{
  "type": "Feature",
  "properties": {
    "gn:admin1_code":"18.0",
    "gn:admin2_code":"91594.0",
    "gn:asciiname":"'Arab Albu Hayush",
    "gn:country_code":"IQ",
    "gn:dem":73,
    "gn:feature_class":"P",
    "gn:feature_code":"PPLL",
    "gn:name":"\u2018Arab \u0100lb\u016b \u1e28ay\u016bsh",
    "gn:population":0,
    "gn:timezone":"Asia/Baghdad",
    "iso:country":"IQ",
    "name:ara_x_preferred":[
        "\u0639\u0631\u0628 \u0627\u0644\u0628\u0648 \u062d\u064a\u0648\u0634"
    ],
    "name:und_x_variant":[
        "\u2018Arab \u0100lb\u016b \u1e28ay\u016bsh"
    ],
    "wof:name":"'Arab Albu Hayush",
    "wof:placetype":"locality"
},
  "geometry": {"coordinates":[43.77594000000001,34.33884],"type":"Point"}
}