{
  "type": "Feature",
  "properties": {
    "gn:admin1_code":"15.0",
    "gn:admin2_code":"90392.0",
    "gn:asciiname":"Bir al Hilw",
    "gn:country_code":"IQ",
    "gn:dem":431,
    "gn:feature_class":"P",
    "gn:feature_code":"PPL",
    "gn:name":"B\u012br al \u1e28ilw",
    "gn:population":0,
    "gn:timezone":"Asia/Baghdad",
    "iso:country":"IQ",
    "name:ara_x_preferred":[
        "\u0628\u064a\u0631 \u0627\u0644\u062d\u0644\u0648"
    ],
    "name:kur_x_preferred":[
        "B\u00eer \u1e26lu"
    ],
    "name:kur_x_variant":[
        "\u0628\u064a\u0631 \u062d\u0644\u0648"
    ],
    "name:und_x_variant":[
        "Bir Hlw",
        "Bi\u2019r al \u1e28ulw",
        "B\u012br al \u1e28ulw"
    ],
    "wof:name":"Bir al Hilw",
    "wof:placetype":"locality"
},
  "geometry": {"coordinates":[42.28449000000001,36.5522],"type":"Point"}
}