{
  "type": "Feature",
  "properties": {
    "gn:admin1_code":"11.0",
    "gn:admin2_code":"9166591.0",
    "gn:asciiname":"Mawan",
    "gn:country_code":"IQ",
    "gn:dem":726,
    "gn:feature_class":"P",
    "gn:feature_code":"PPL",
    "gn:name":"Mawan",
    "gn:population":0,
    "gn:timezone":"Asia/Baghdad",
    "iso:country":"IQ",
    "name:ara_x_preferred":[
        "\u0627\u0644\u0645\u0627\u0648\u0627\u0646 \u0627\u0644\u0635\u063a\u064a\u0631"
    ],
    "name:kur_x_preferred":[
        "Mawan"
    ],
    "name:kur_x_variant":[
        "\u0645\u0627\u0648\u0627\u0646"
    ],
    "name:und_x_variant":[
        "Alm\u0101w\u0101n",
        "Al M\u0101w\u0101n a\u015f \u015eagh\u012br"
    ],
    "wof:name":"Mawan",
    "wof:placetype":"locality"
},
  "geometry": {"coordinates":[44.21745,36.40419],"type":"Point"}
}