{
  "type": "Feature",
  "properties": {
    "gn:admin1_code":"1.0",
    "gn:admin2_code":"9166650.0",
    "gn:asciiname":"Al Hadar",
    "gn:country_code":"IQ",
    "gn:dem":163,
    "gn:feature_class":"P",
    "gn:feature_code":"PPL",
    "gn:name":"Al \u1e28a\u1e11ar",
    "gn:population":0,
    "gn:timezone":"Asia/Baghdad",
    "iso:country":"IQ",
    "name:und_x_variant":[
        "Al \u1e28a\u1e11ar"
    ],
    "wof:name":"Al Hadar",
    "wof:placetype":"locality"
},
  "geometry": {"coordinates":[41.96667,34.46667],"type":"Point"}
}