{
  "type": "Feature",
  "properties": {
    "gn:admin1_code":"6.0",
    "gn:admin2_code":"6818313.0",
    "gn:asciiname":"Qaryat Ghazi",
    "gn:country_code":"IQ",
    "gn:dem":26,
    "gn:feature_class":"P",
    "gn:feature_code":"PPL",
    "gn:name":"Qaryat Gh\u0101z\u012b",
    "gn:population":0,
    "gn:timezone":"Asia/Baghdad",
    "iso:country":"IQ",
    "name:ara_x_preferred":[
        "\u0642\u0631\u064a\u0629 \u063a\u0627\u0632\u064a"
    ],
    "name:und_x_variant":[
        "Qaryat Gh\u0101z\u012b"
    ],
    "wof:name":"Qaryat Ghazi",
    "wof:placetype":"locality"
},
  "geometry": {"coordinates":[44.53595,32.66674],"type":"Point"}
}