{
  "type": "Feature",
  "properties": {
    "gn:admin1_code":"10.0",
    "gn:admin2_code":"94590.0",
    "gn:asciiname":"Saray",
    "gn:country_code":"IQ",
    "gn:dem":110,
    "gn:feature_class":"P",
    "gn:feature_code":"PPL",
    "gn:name":"Sar\u0101y",
    "gn:population":0,
    "gn:timezone":"Asia/Baghdad",
    "iso:country":"IQ",
    "name:ara_x_preferred":[
        "\u0633\u0631\u0627\u064a"
    ],
    "name:und_x_variant":[
        "Sarai",
        "Sar\u0101y"
    ],
    "wof:name":"Saray",
    "wof:placetype":"locality"
},
  "geometry": {"coordinates":[45.05016,34.0588],"type":"Point"}
}