{
  "type": "Feature",
  "properties": {
    "gn:admin1_code":"7.0",
    "gn:admin2_code":"99173.0",
    "gn:asciiname":"Mahmud Sa'id",
    "gn:country_code":"IQ",
    "gn:dem":41,
    "gn:feature_class":"P",
    "gn:feature_code":"PPL",
    "gn:name":"Ma\u1e29m\u016bd Sa\u2018\u012bd",
    "gn:population":0,
    "gn:timezone":"Asia/Baghdad",
    "iso:country":"IQ",
    "name:ara_x_preferred":[
        "\u0645\u062d\u0645\u0648\u062f \u0633\u0639\u064a\u062f"
    ],
    "name:und_x_variant":[
        "Ma\u1e29m\u016bd Sa\u2018\u012bd"
    ],
    "wof:name":"Mahmud Sa'id",
    "wof:placetype":"locality"
},
  "geometry": {"coordinates":[44.20658,33.56319],"type":"Point"}
}