{
  "type": "Feature",
  "properties": {
    "gn:admin1_code":"14.0",
    "gn:admin2_code":"9166562.0",
    "gn:asciiname":"Tall Abu Layla",
    "gn:country_code":"IQ",
    "gn:dem":5,
    "gn:feature_class":"P",
    "gn:feature_code":"PPL",
    "gn:name":"Tall Ab\u016b Layl\u00e1",
    "gn:population":0,
    "gn:timezone":"Asia/Baghdad",
    "iso:country":"IQ",
    "name:ara_x_preferred":[
        "\u062a\u0644 \u0627\u0628\u0648 \u0644\u064a\u0644\u0649"
    ],
    "name:und_x_variant":[
        "Tall Ab\u016b Layl\u012b",
        "Tall Ab\u016b Layl\u00e1"
    ],
    "wof:name":"Tall Abu Layla",
    "wof:placetype":"locality"
},
  "geometry": {"coordinates":[46.8708,31.24695],"type":"Point"}
}