{
  "type": "Feature",
  "properties": {
    "gn:admin1_code":"18.0",
    "gn:admin2_code":"6872046.0",
    "gn:asciiname":"Makhlaf Suhayl",
    "gn:country_code":"IQ",
    "gn:dem":140,
    "gn:feature_class":"P",
    "gn:feature_code":"PPL",
    "gn:name":"Makhlaf Suhayl",
    "gn:population":0,
    "gn:timezone":"Asia/Baghdad",
    "iso:country":"IQ",
    "name:ara_x_preferred":[
        "\u0645\u062e\u0644\u0641 \u0633\u0647\u064a\u0644"
    ],
    "wof:name":"Makhlaf Suhayl",
    "wof:placetype":"locality"
},
  "geometry": {"coordinates":[43.29472,34.58285],"type":"Point"}
}