{
  "type": "Feature",
  "properties": {
    "gn:admin1_code":"11.0",
    "gn:admin2_code":"9166592.0",
    "gn:asciiname":"Chinare",
    "gn:country_code":"IQ",
    "gn:dem":688,
    "gn:feature_class":"P",
    "gn:feature_code":"PPL",
    "gn:name":"Chinare",
    "gn:population":0,
    "gn:timezone":"Asia/Baghdad",
    "iso:country":"IQ",
    "name:ara_x_preferred":[
        "\u0686\u0646\u0627\u0631\u0647"
    ],
    "name:kur_x_preferred":[
        "Chinare"
    ],
    "name:und_x_variant":[
        "Chin\u0101ra",
        "Chin\u0101rah",
        "\u0686\u0646\u0627\u0631\u0647",
        "Chnar",
        "Chnara"
    ],
    "wof:name":"Chinare",
    "wof:placetype":"locality"
},
  "geometry": {"coordinates":[44.44865,36.98528],"type":"Point"}
}