{
  "type": "Feature",
  "properties": {
    "gn:admin1_code":"2.0",
    "gn:admin2_code":"9166563.0",
    "gn:asciiname":"Bayt Musa",
    "gn:country_code":"IQ",
    "gn:dem":4,
    "gn:feature_class":"P",
    "gn:feature_code":"PPL",
    "gn:name":"Bayt M\u016bs\u00e1",
    "gn:population":0,
    "gn:timezone":"Asia/Baghdad",
    "iso:country":"IQ",
    "name:ara_x_preferred":[
        "\u0628\u064a\u062a \u0645\u0648\u0633\u0649"
    ],
    "name:und_x_variant":[
        "Bayt M\u016bs\u00e1"
    ],
    "wof:name":"Bayt Musa",
    "wof:placetype":"locality"
},
  "geometry": {"coordinates":[47.36722,30.96786],"type":"Point"}
}