{
  "type": "Feature",
  "properties": {
    "gn:admin1_code":"11.0",
    "gn:admin2_code":"9166591.0",
    "gn:asciiname":"Solawk",
    "gn:country_code":"IQ",
    "gn:dem":1026,
    "gn:feature_class":"P",
    "gn:feature_code":"PPL",
    "gn:name":"Solawk",
    "gn:population":0,
    "gn:timezone":"Asia/Baghdad",
    "iso:country":"IQ",
    "name:ara_x_preferred":[
        "\u0633\u0648\u0644\u0627\u0648\u0643 \u0627\u0644\u0639\u0644\u064a\u0627"
    ],
    "name:kur_x_preferred":[
        "Solawk"
    ],
    "name:kur_x_variant":[
        "\u0633\u06c6\u0644\u0627\u0648\u0643"
    ],
    "name:und_x_variant":[
        "S\u016bl\u0101wka-i Zh\u016br\u016b",
        "S\u016bl\u0101waka-i Zh\u016br\u016b",
        "S\u016bl\u0101wk \u2018Uly\u0101",
        "Sulawk",
        "\u0633\u0648\u0644\u0627\u0648\u0643 \u0639\u0644\u064a\u0627",
        "S\u016bl\u0101wk al \u2018Uly\u0101"
    ],
    "wof:name":"Solawk",
    "wof:placetype":"locality"
},
  "geometry": {"coordinates":[44.41169,36.29482],"type":"Point"}
}