{
  "type": "Feature",
  "properties": {
    "gn:admin1_code":"5.0",
    "gn:admin2_code":"91176.0",
    "gn:asciiname":"Bur",
    "gn:country_code":"IQ",
    "gn:dem":1327,
    "gn:feature_class":"P",
    "gn:feature_code":"PPL",
    "gn:name":"B\u016br",
    "gn:population":0,
    "gn:timezone":"Asia/Baghdad",
    "iso:country":"IQ",
    "name:fas_x_preferred":[
        "\u0628\u0648\u0631"
    ],
    "wof:name":"Bur",
    "wof:placetype":"locality"
},
  "geometry": {"coordinates":[45.5951,35.8555],"type":"Point"}
}