{
  "type": "Feature",
  "properties": {
    "gn:admin1_code":"10.0",
    "gn:admin2_code":"9166680.0",
    "gn:asciiname":"Kadar",
    "gn:country_code":"IQ",
    "gn:dem":359,
    "gn:feature_class":"P",
    "gn:feature_code":"PPL",
    "gn:name":"Kad\u0101r",
    "gn:population":0,
    "gn:timezone":"Asia/Baghdad",
    "iso:country":"IQ",
    "name:ara_x_preferred":[
        "\u0643\u062f\u0627\u0631"
    ],
    "name:ceb_x_preferred":[
        "Kadar"
    ],
    "name:fra_x_preferred":[
        "Kadar"
    ],
    "name:kor_x_preferred":[
        "\uce74\ub2e4\ub974"
    ],
    "name:swe_x_preferred":[
        "Kadar"
    ],
    "name:und_x_variant":[
        "Kad\u0101r"
    ],
    "wof:name":"Kadar",
    "wof:placetype":"locality"
},
  "geometry": {"coordinates":[45.90363,33.62303],"type":"Point"}
}