{
  "type": "Feature",
  "properties": {
    "gn:admin1_code":"18.0",
    "gn:admin2_code":"90148.0",
    "gn:asciiname":"Muhammad 'Abd Allah",
    "gn:country_code":"IQ",
    "gn:dem":128,
    "gn:feature_class":"P",
    "gn:feature_code":"PPL",
    "gn:name":"Mu\u1e29ammad \u2018Abd All\u0101h",
    "gn:population":0,
    "gn:timezone":"Asia/Baghdad",
    "iso:country":"IQ",
    "name:ara_x_preferred":[
        "\u0645\u062d\u0645\u062f \u0639\u0628\u062f \ufdf2"
    ],
    "name:und_x_variant":[
        "Mu\u1e29ammad \u2018Abd All\u0101h"
    ],
    "wof:name":"Muhammad 'Abd Allah",
    "wof:placetype":"locality"
},
  "geometry": {"coordinates":[43.42558,34.54495],"type":"Point"}
}