{
  "type": "Feature",
  "properties": {
    "gn:admin1_code":"9.0",
    "gn:admin2_code":"98700.0",
    "gn:asciiname":"Zulaymat",
    "gn:cc2":"IQ",
    "gn:country_code":"IQ",
    "gn:dem":9,
    "gn:feature_class":"P",
    "gn:feature_code":"PPL",
    "gn:name":"Zulaym\u0101t",
    "gn:population":0,
    "gn:timezone":"Asia/Baghdad",
    "iso:country":"IQ",
    "name:und_x_variant":[
        "\u2018Ulaym\u0101t",
        "Zulaim\u0101t",
        "Zulaym\u0101t"
    ],
    "wof:name":"Zulaymat",
    "wof:placetype":"locality"
},
  "geometry": {"coordinates":[46.06667,31.56667],"type":"Point"}
}