{
  "type": "Feature",
  "properties": {
    "gn:admin1_code":"5.0",
    "gn:admin2_code":"92743.0",
    "gn:asciiname":"Dawlah Dizah",
    "gn:country_code":"IQ",
    "gn:dem":946,
    "gn:feature_class":"P",
    "gn:feature_code":"PPL",
    "gn:name":"Dawlah Dizah",
    "gn:population":0,
    "gn:timezone":"Asia/Baghdad",
    "iso:country":"IQ",
    "name:ara_x_preferred":[
        "\u062f\u0648\u0644\u0647 \u062f\u0632\u0629"
    ],
    "name:kur_x_preferred":[
        "Do\u0142e Dize"
    ],
    "name:kur_x_variant":[
        "\u062f\u06c6\u06b5\u06d5 \u062f\u0632\u06d5"
    ],
    "name:und_x_variant":[
        "Doladiza",
        "Dola Dza"
    ],
    "wof:name":"Dawlah Dizah",
    "wof:placetype":"locality"
},
  "geometry": {"coordinates":[45.20385,36.18858],"type":"Point"}
}