{
  "type": "Feature",
  "properties": {
    "gn:admin1_code":"8.0",
    "gn:admin2_code":"99612.0",
    "gn:asciiname":"Chimbilke",
    "gn:country_code":"IQ",
    "gn:dem":870,
    "gn:feature_class":"P",
    "gn:feature_code":"PPL",
    "gn:name":"Chimbilk\u00ea",
    "gn:population":0,
    "gn:timezone":"Asia/Baghdad",
    "iso:country":"IQ",
    "name:ara_x_preferred":[
        "\u0686\u0645\u064a\u062a\u0643\u0647"
    ],
    "name:kur_x_preferred":[
        "Chemitke"
    ],
    "name:kur_x_variant":[
        "\u0686\u06d5\u0645\u062a\u0643\u06d5",
        "Chimbilk\u00ea",
        "\u0686\u0645\u067b\u0644\u0643\u06ce"
    ],
    "name:und_x_variant":[
        "Chambalkah",
        "Chambalk\u0113",
        "Chimbilke",
        "Cham\u012btkah",
        "Chamitka"
    ],
    "wof:name":"Chimbilke",
    "wof:placetype":"locality"
},
  "geometry": {"coordinates":[43.29077,37.18152],"type":"Point"}
}