{
  "type": "Feature",
  "properties": {
    "gn:admin1_code":"5.0",
    "gn:admin2_code":"98464.0",
    "gn:asciiname":"Zir Kuwayz",
    "gn:country_code":"IQ",
    "gn:dem":884,
    "gn:feature_class":"P",
    "gn:feature_code":"PPL",
    "gn:name":"Z\u012br Kuwayz",
    "gn:population":0,
    "gn:timezone":"Asia/Baghdad",
    "iso:country":"IQ",
    "name:ara_x_preferred":[
        "\u0632\u064a\u0631 \u0643\u0648\u064a\u0632"
    ],
    "name:kur_x_preferred":[
        "Z\u1e5f Gw\u00eaz\u00ee Bichuk"
    ],
    "name:kur_x_variant":[
        "\u0632\u0695 \u06af\u0648\u06ce\u0632\u0649 \u0628\u0686\u0648\u0643"
    ],
    "name:und_x_variant":[
        "Z\u012br Kuwayz",
        "\u2018Zirg\u00f6z-i Pich\u016bk",
        "Kuchik Zerguez",
        "Kuchuk Zerguez",
        "Zergwez"
    ],
    "wof:name":"Zir Kuwayz",
    "wof:placetype":"locality"
},
  "geometry": {"coordinates":[45.47885,35.38746],"type":"Point"}
}