{
  "type": "Feature",
  "properties": {
    "gn:admin1_code":"10.0",
    "gn:admin2_code":"9166680.0",
    "gn:asciiname":"'Arab 'Ukam",
    "gn:country_code":"IQ",
    "gn:dem":37,
    "gn:feature_class":"P",
    "gn:feature_code":"PPL",
    "gn:name":"\u2018Arab \u2018Uk\u0101m",
    "gn:population":0,
    "gn:timezone":"Asia/Baghdad",
    "iso:country":"IQ",
    "name:ara_x_preferred":[
        "\u0639\u0631\u0628 \u0639\u0643\u0627\u0645"
    ],
    "name:und_x_variant":[
        "\u2018Arab \u2018Uk\u0101m"
    ],
    "wof:name":"'Arab 'Ukam",
    "wof:placetype":"locality"
},
  "geometry": {"coordinates":[45.17001,33.53778],"type":"Point"}
}