{
  "type": "Feature",
  "properties": {
    "gn:admin1_code":"13.0",
    "gn:admin2_code":"94786.0",
    "gn:asciiname":"Jabal Khabbaz",
    "gn:country_code":"IQ",
    "gn:dem":213,
    "gn:feature_class":"P",
    "gn:feature_code":"PPL",
    "gn:name":"Jabal Khabb\u0101z",
    "gn:population":0,
    "gn:timezone":"Asia/Baghdad",
    "iso:country":"IQ",
    "name:ara_x_preferred":[
        "\u062c\u0628\u0644 \u062e\u0628\u0627\u0632"
    ],
    "name:kur_x_preferred":[
        "Cebel Xutar"
    ],
    "name:kur_x_variant":[
        "Jabal Khutar",
        "\u062c\u06d5\u0628\u06d5\u0644 \u062e\u0648\u062a\u0627\u0631"
    ],
    "name:und_x_variant":[
        "Jabel Khabb\u0101z",
        "Jabal Khubb\u0101z",
        "Jabal Khabb\u0101z"
    ],
    "wof:name":"Jabal Khabbaz",
    "wof:placetype":"locality"
},
  "geometry": {"coordinates":[44.04625,35.35216],"type":"Point"}
}