{
  "type": "Feature",
  "properties": {
    "gn:admin1_code":"8.0",
    "gn:admin2_code":"99612.0",
    "gn:asciiname":"'Ayn Shaykh",
    "gn:country_code":"IQ",
    "gn:dem":1171,
    "gn:feature_class":"P",
    "gn:feature_code":"PPL",
    "gn:name":"\u2018Ayn Shaykh",
    "gn:population":0,
    "gn:timezone":"Asia/Baghdad",
    "iso:country":"IQ",
    "name:ara_x_preferred":[
        "\u0639\u064a\u0646 \u0634\u064a\u062e"
    ],
    "name:kur_x_preferred":[
        "\u2018Eyn Sh\u00eax"
    ],
    "name:kur_x_variant":[
        "\u0639\u06d5\u064a\u0646 \u0634\u06ce\u062e"
    ],
    "name:und_x_variant":[
        "Ayn Shaykh",
        "Ain Sheikh",
        "\u2018Ayn Shaykh"
    ],
    "wof:name":"'Ayn Shaykh",
    "wof:placetype":"locality"
},
  "geometry": {"coordinates":[43.3636,37.10734],"type":"Point"}
}