{
  "type": "Feature",
  "properties": {
    "gn:admin1_code":"15.0",
    "gn:admin2_code":"98820.0",
    "gn:asciiname":"Baysmakaran",
    "gn:country_code":"IQ",
    "gn:dem":564,
    "gn:feature_class":"P",
    "gn:feature_code":"PPL",
    "gn:name":"Baysmakar\u0101n",
    "gn:population":0,
    "gn:timezone":"Asia/Baghdad",
    "iso:country":"IQ",
    "name:ara_x_preferred":[
        "\u0628\u0633\u0645\u0643\u0631\u0627\u0646"
    ],
    "name:kur_x_preferred":[
        "B\u00easmekeran"
    ],
    "name:kur_x_variant":[
        "B\u00eesmkran",
        "\u0628\u06ce\u0633\u0645\u06d5\u0643\u06d5\u0631\u0627\u0646"
    ],
    "name:und_x_variant":[
        "Basmakar\u0101n",
        "Bismakaran",
        "Baysmakar\u0101n",
        "\u0628\u064a\u0633\u0645\u0643\u0631\u0627\u0646",
        "Besmakaran",
        "Bismkran"
    ],
    "wof:name":"Baysmakaran",
    "wof:placetype":"locality"
},
  "geometry": {"coordinates":[44.1351,36.6974],"type":"Point"}
}