{
  "type": "Feature",
  "properties": {
    "gn:admin1_code":"10.0",
    "gn:admin2_code":"94590.0",
    "gn:asciiname":"Mansuriyat al Jabal",
    "gn:country_code":"IQ",
    "gn:dem":68,
    "gn:feature_class":"P",
    "gn:feature_code":"PPL",
    "gn:name":"Man\u015f\u016br\u012byat al Jabal",
    "gn:population":0,
    "gn:timezone":"Asia/Baghdad",
    "iso:country":"IQ",
    "name:ara_x_preferred":[
        "\u0645\u0646\u0635\u0648\u0631\u064a\u0629 \u0627\u0644\u062c\u0628\u0644"
    ],
    "name:und_x_variant":[
        "Mans\u016briya al Jabal",
        "Man\u015f\u016br\u012byah al Jabal",
        "Manssuriyt al-Jabal",
        "Man\u015f\u016br\u012byat al Jabal"
    ],
    "wof:name":"Mansuriyat al Jabal",
    "wof:placetype":"locality"
},
  "geometry": {"coordinates":[44.95895,34.0807],"type":"Point"}
}