{
  "type": "Feature",
  "properties": {
    "gn:admin1_code":"12.0",
    "gn:admin2_code":"99345.0",
    "gn:asciiname":"Hasan ar Ruhaymi",
    "gn:country_code":"IQ",
    "gn:dem":32,
    "gn:feature_class":"P",
    "gn:feature_code":"PPL",
    "gn:name":"\u1e28asan ar Ruhaym\u012b",
    "gn:population":0,
    "gn:timezone":"Asia/Baghdad",
    "iso:country":"IQ",
    "name:ara_x_preferred":[
        "\u062d\u0633\u0646 \u0627\u0644\u0631\u0647\u064a\u0645\u064a"
    ],
    "name:und_x_variant":[
        "\u1e28asan ar Ruhaym\u012b"
    ],
    "wof:name":"Hasan ar Ruhaymi",
    "wof:placetype":"locality"
},
  "geometry": {"coordinates":[44.19303,32.50702],"type":"Point"}
}