{
  "type": "Feature",
  "properties": {
    "gn:admin1_code":"3.0",
    "gn:admin2_code":"9166568.0",
    "gn:asciiname":"Ishan al Muraybi",
    "gn:country_code":"IQ",
    "gn:dem":16,
    "gn:feature_class":"P",
    "gn:feature_code":"PPL",
    "gn:name":"\u012ash\u0101n al Murayb\u012b",
    "gn:population":0,
    "gn:timezone":"Asia/Baghdad",
    "iso:country":"IQ",
    "name:ara_x_preferred":[
        "\u0627\u064a\u0634\u0627\u0646 \u0627\u0644\u0645\u0631\u064a\u0628\u064a"
    ],
    "name:und_x_variant":[
        "\u012ash\u0101n al Murayb\u012b"
    ],
    "wof:name":"Ishan al Muraybi",
    "wof:placetype":"locality"
},
  "geometry": {"coordinates":[45.05132,31.40498],"type":"Point"}
}