{
  "type": "Feature",
  "properties": {
    "gn:admin1_code":"13.0",
    "gn:asciiname":"Khara'ib Tabah Sud",
    "gn:country_code":"IQ",
    "gn:dem":327,
    "gn:feature_class":"P",
    "gn:feature_code":"PPL",
    "gn:name":"Khar\u0101\u2019ib Tabah S\u016bd",
    "gn:population":0,
    "gn:timezone":"Asia/Baghdad",
    "iso:country":"IQ",
    "name:ara_x_preferred":[
        "\u062e\u0631\u0627\u0626\u0628 \u062a\u0628\u0647 \u0633\u0648\u062f"
    ],
    "name:ara_x_variant":[
        "\u062a\u0628\u0647 \u0633\u0648\u0632"
    ],
    "name:und_x_variant":[
        "Tepe Sabz",
        "Tabbah S\u016bz",
        "Tappah Sayz",
        "Tappah S\u016bd",
        "Tappah Sabz",
        "Tabah S\u016bz",
        "Khar\u0101\u2019ib Tabah S\u016bd"
    ],
    "wof:name":"Khara'ib Tabah Sud",
    "wof:placetype":"locality"
},
  "geometry": {"coordinates":[44.65659,35.17655999999999],"type":"Point"}
}