{
  "type": "Feature",
  "properties": {
    "gn:admin1_code":"15.0",
    "gn:admin2_code":"9166620.0",
    "gn:asciiname":"Karufi",
    "gn:country_code":"IQ",
    "gn:dem":381,
    "gn:feature_class":"P",
    "gn:feature_code":"PPL",
    "gn:name":"Kar\u016bf\u012b",
    "gn:population":0,
    "gn:timezone":"Asia/Baghdad",
    "iso:country":"IQ",
    "name:ara_x_preferred":[
        "\u0643\u0631\u0648\u0641\u064a"
    ],
    "name:und_x_variant":[
        "Kar\u016bf\u012b"
    ],
    "wof:name":"Karufi",
    "wof:placetype":"locality"
},
  "geometry": {"coordinates":[41.59071,36.18447000000001],"type":"Point"}
}