{
  "type": "Feature",
  "properties": {
    "gn:admin1_code":"5.0",
    "gn:admin2_code":"9166600.0",
    "gn:asciiname":"Zemawengey Gewre",
    "gn:country_code":"IQ",
    "gn:dem":570,
    "gn:feature_class":"P",
    "gn:feature_code":"PPL",
    "gn:name":"Zemawengey Gewre",
    "gn:population":0,
    "gn:timezone":"Asia/Baghdad",
    "iso:country":"IQ",
    "name:kur_x_preferred":[
        "Zengeke"
    ],
    "name:kur_x_variant":[
        "Zemawengey Gewre",
        "\u0632\u06d5\u0646\u06af\u06d5\u0643\u06d5",
        "\u0632\u06d5\u0645\u0627\u0648\u06d5\u0646\u06af\u06d5\u0649 \u06af\u06d5\u0648\u0631\u06d5"
    ],
    "name:und_x_variant":[
        "Zangaka"
    ],
    "wof:name":"Zemawengey Gewre",
    "wof:placetype":"locality"
},
  "geometry": {"coordinates":[45.4125,34.87917],"type":"Point"}
}