{
  "type": "Feature",
  "properties": {
    "gn:admin1_code":"10.0",
    "gn:admin2_code":"94296.0",
    "gn:asciiname":"Zargush al Jadid",
    "gn:country_code":"IQ",
    "gn:dem":110,
    "gn:feature_class":"P",
    "gn:feature_code":"PPL",
    "gn:name":"Zarg\u016bsh al Jad\u012bd",
    "gn:population":0,
    "gn:timezone":"Asia/Baghdad",
    "iso:country":"IQ",
    "name:ara_x_preferred":[
        "\u0632\u0631\u0643\u0648\u0634 \u0627\u0644\u062c\u062f\u064a\u062f"
    ],
    "name:ara_x_variant":[
        "\u0632\u0631\u06af\u0648\u0634 \u0627\u0644\u062c\u062f\u064a\u062f"
    ],
    "name:und_x_variant":[
        "Zarg\u016bsh al Jad\u012bd",
        "Zark\u016bsh al Jad\u012bd"
    ],
    "wof:name":"Zargush al Jadid",
    "wof:placetype":"locality"
},
  "geometry": {"coordinates":[44.8395,34.45706],"type":"Point"}
}