{
  "type": "Feature",
  "properties": {
    "gn:admin1_code":"1.0",
    "gn:admin2_code":"99455.0",
    "gn:asciiname":"'Amil Hasan",
    "gn:country_code":"IQ",
    "gn:dem":37,
    "gn:feature_class":"P",
    "gn:feature_code":"PPL",
    "gn:name":"\u2018Am\u012bl \u1e28asan",
    "gn:population":0,
    "gn:timezone":"Asia/Baghdad",
    "iso:country":"IQ",
    "name:ara_x_preferred":[
        "\u0639\u0645\u064a\u0644 \u062d\u0633\u0646"
    ],
    "name:und_x_variant":[
        "\u2018Am\u012bl \u1e28asan"
    ],
    "wof:name":"'Amil Hasan",
    "wof:placetype":"locality"
},
  "geometry": {"coordinates":[44.00324000000001,33.46464],"type":"Point"}
}