{
  "type": "Feature",
  "properties": {
    "gn:admin1_code":"18.0",
    "gn:admin2_code":"6804454.0",
    "gn:asciiname":"Khara'ib Kaharah",
    "gn:country_code":"IQ",
    "gn:dem":188,
    "gn:feature_class":"P",
    "gn:feature_code":"PPL",
    "gn:name":"Khar\u0101\u2019ib Kah\u0101rah",
    "gn:population":0,
    "gn:timezone":"Asia/Baghdad",
    "iso:country":"IQ",
    "name:ara_x_preferred":[
        "\u062e\u0631\u0627\u0626\u0628 \u0643\u0647\u0627\u0631\u0647"
    ],
    "name:und_x_variant":[
        "Khar\u0101\u2019ib Kah\u0101rah"
    ],
    "wof:name":"Khara'ib Kaharah",
    "wof:placetype":"locality"
},
  "geometry": {"coordinates":[43.32865,35.6619],"type":"Point"}
}