{
  "type": "Feature",
  "properties": {
    "gn:admin1_code":"9.0",
    "gn:admin2_code":"90509.0",
    "gn:asciiname":"Al Jawwil",
    "gn:country_code":"IQ",
    "gn:dem":5,
    "gn:feature_class":"P",
    "gn:feature_code":"PPL",
    "gn:name":"\u0100l Jawwil",
    "gn:population":0,
    "gn:timezone":"Asia/Baghdad",
    "iso:country":"IQ",
    "name:ara_x_preferred":[
        "\u0622\u0644 \u062c\u0648\u0644"
    ],
    "name:und_x_variant":[
        "\u0100l Jawwil"
    ],
    "wof:name":"Al Jawwil",
    "wof:placetype":"locality"
},
  "geometry": {"coordinates":[46.73983,30.96511],"type":"Point"}
}