{
  "type": "Feature",
  "properties": {
    "gn:admin1_code":"5.0",
    "gn:admin2_code":"98464.0",
    "gn:asciiname":"Qayran",
    "gn:country_code":"IQ",
    "gn:dem":861,
    "gn:feature_class":"P",
    "gn:feature_code":"PPL",
    "gn:name":"Qayr\u0101n",
    "gn:population":0,
    "gn:timezone":"Asia/Baghdad",
    "iso:country":"IQ",
    "name:ara_x_preferred":[
        "\u0642\u064a\u0631\u0627\u0646"
    ],
    "name:und_x_variant":[
        "Qayr\u0101n"
    ],
    "wof:name":"Qayran",
    "wof:placetype":"locality"
},
  "geometry": {"coordinates":[45.41763,35.60699],"type":"Point"}
}