{
  "type": "Feature",
  "properties": {
    "gn:admin1_code":"18.0",
    "gn:admin2_code":"6805736.0",
    "gn:asciiname":"Qaryat Albu Nasir",
    "gn:country_code":"IQ",
    "gn:dem":47,
    "gn:feature_class":"P",
    "gn:feature_code":"PPL",
    "gn:name":"Qaryat \u0100lb\u016b N\u0101\u015fir",
    "gn:population":0,
    "gn:timezone":"Asia/Baghdad",
    "iso:country":"IQ",
    "name:ara_x_preferred":[
        "\u0642\u0631\u064a\u0629 \u0627\u0644\u0628\u0648 \u0646\u0627\u0635\u0631"
    ],
    "name:und_x_variant":[
        "Qaryat \u0100lb\u016b N\u0101\u015fir"
    ],
    "wof:name":"Qaryat Albu Nasir",
    "wof:placetype":"locality"
},
  "geometry": {"coordinates":[44.34099000000001,33.92113],"type":"Point"}
}