{
  "type": "Feature",
  "properties": {
    "gn:admin1_code":"8.0",
    "gn:admin2_code":"99612.0",
    "gn:asciiname":"Day Rishk",
    "gn:country_code":"IQ",
    "gn:dem":1053,
    "gn:feature_class":"P",
    "gn:feature_code":"PPL",
    "gn:name":"Day Rishk",
    "gn:population":0,
    "gn:timezone":"Asia/Baghdad",
    "iso:country":"IQ",
    "name:ara_x_preferred":[
        "\u062f\u064a \u0631\u0634\u0643"
    ],
    "name:kur_x_preferred":[
        "D\u00ea \u1e5eishk"
    ],
    "name:kur_x_variant":[
        "\u062f\u06ce \u0695\u0634\u0643",
        "D\u00ea\u1e5fesh",
        "\u062f\u06ce\u0695\u06d5\u0634",
        "D\u00ea\u1e5fesh\u00ea",
        "\u062f\u06ce\u0695\u06d5\u0634\u06ce"
    ],
    "name:und_x_variant":[
        "D\u0113rish\u012b",
        "Darishk\u012b",
        "De Rishk",
        "Day Rishk",
        "Derash"
    ],
    "wof:name":"Day Rishk",
    "wof:placetype":"locality"
},
  "geometry": {"coordinates":[43.52513,37.03305],"type":"Point"}
}