{
  "type": "Feature",
  "properties": {
    "gn:admin1_code":"18.0",
    "gn:admin2_code":"6804454.0",
    "gn:asciiname":"Qaryat al Khadraniyah",
    "gn:country_code":"IQ",
    "gn:dem":157,
    "gn:feature_class":"P",
    "gn:feature_code":"PPL",
    "gn:name":"Qaryat al Kha\u1e11r\u0101n\u012byah",
    "gn:population":0,
    "gn:timezone":"Asia/Baghdad",
    "iso:country":"IQ",
    "name:ara_x_preferred":[
        "\u0642\u0631\u064a\u0629 \u0627\u0644\u062e\u0636\u0631\u0627\u0646\u064a\u0647"
    ],
    "name:und_x_variant":[
        "Khudr\u0101n\u012bya",
        "Hadraniya",
        "\u1e28adr\u0101n\u012byah",
        "Qaryat al Kha\u1e11r\u0101n\u012byah"
    ],
    "wof:name":"Qaryat al Khadraniyah",
    "wof:placetype":"locality"
},
  "geometry": {"coordinates":[43.24762,35.61156],"type":"Point"}
}