{
  "type": "Feature",
  "properties": {
    "gn:admin1_code":"15.0",
    "gn:admin2_code":"9166649.0",
    "gn:asciiname":"Imam Hamzah",
    "gn:country_code":"IQ",
    "gn:dem":316,
    "gn:feature_class":"P",
    "gn:feature_code":"PPL",
    "gn:name":"Im\u0101m \u1e28amzah",
    "gn:population":0,
    "gn:timezone":"Asia/Baghdad",
    "iso:country":"IQ",
    "name:ara_x_preferred":[
        "\u0627\u0645\u0627\u0645 \u062d\u0645\u0632\u0629"
    ],
    "name:und_x_variant":[
        "Im\u0101m \u1e28amzah"
    ],
    "wof:name":"Imam Hamzah",
    "wof:placetype":"locality"
},
  "geometry": {"coordinates":[42.97802,36.1849],"type":"Point"}
}