{
  "type": "Feature",
  "properties": {
    "gn:admin1_code":"18.0",
    "gn:admin2_code":"9166616.0",
    "gn:asciiname":"'Abbas Muhisan",
    "gn:country_code":"IQ",
    "gn:dem":42,
    "gn:feature_class":"P",
    "gn:feature_code":"PPL",
    "gn:name":"\u2018Abb\u0101s Mu\u1e29\u012bsan",
    "gn:population":0,
    "gn:timezone":"Asia/Baghdad",
    "iso:country":"IQ",
    "name:ara_x_preferred":[
        "\u0639\u0628\u0627\u0633 \u0645\u062d\u064a\u0633\u0646"
    ],
    "name:und_x_variant":[
        "\u2018Abb\u0101s Mu\u1e29\u012bsan"
    ],
    "wof:name":"'Abbas Muhisan",
    "wof:placetype":"locality"
},
  "geometry": {"coordinates":[44.08737,33.78001],"type":"Point"}
}