{
  "type": "Feature",
  "properties": {
    "gn:admin1_code":"11.0",
    "gn:admin2_code":"93817.0",
    "gn:asciiname":"Qaryat Karmardi",
    "gn:country_code":"IQ",
    "gn:dem":222,
    "gn:feature_class":"P",
    "gn:feature_code":"PPL",
    "gn:name":"Qaryat Karmard\u012b",
    "gn:population":0,
    "gn:timezone":"Asia/Baghdad",
    "iso:country":"IQ",
    "name:ara_x_preferred":[
        "\u0642\u0631\u064a\u0629 \u0643\u0631\u0645\u0631\u062f\u064a"
    ],
    "name:kur_x_preferred":[
        "Ker Mrd\u00ee"
    ],
    "name:kur_x_variant":[
        "\u0643\u06d5\u0631 \u0645\u0631\u062f\u0649"
    ],
    "name:und_x_variant":[
        "Karmaroli",
        "Karmardi",
        "Kar Mrdi",
        "Qaryat Karmard\u012b"
    ],
    "wof:name":"Qaryat Karmardi",
    "wof:placetype":"locality"
},
  "geometry": {"coordinates":[43.42542,35.72544],"type":"Point"}
}