{
  "type": "Feature",
  "properties": {
    "gn:admin1_code":"12.0",
    "gn:admin2_code":"9166603.0",
    "gn:asciiname":"Albu Mutlaq",
    "gn:country_code":"IQ",
    "gn:dem":50,
    "gn:feature_class":"P",
    "gn:feature_code":"PPL",
    "gn:name":"Alb\u016b Mu\u0163laq",
    "gn:population":0,
    "gn:timezone":"Asia/Baghdad",
    "iso:country":"IQ",
    "name:ara_x_preferred":[
        "\u0627\u0644\u0628\u0648 \u0645\u0637\u0644\u0643"
    ],
    "name:und_x_variant":[
        "Qa\u015fr \u0100b\u016b Mu\u0163laq",
        "Qa\u015fr \u0100lb\u016b Mu\u0163laq",
        "Alb\u016b Mu\u0163laq"
    ],
    "wof:name":"Albu Mutlaq",
    "wof:placetype":"locality"
},
  "geometry": {"coordinates":[43.51556,32.57757],"type":"Point"}
}