{
  "type": "Feature",
  "properties": {
    "gn:admin1_code":"14.0",
    "gn:admin2_code":"9166562.0",
    "gn:asciiname":"Salaf al Jadi",
    "gn:country_code":"IQ",
    "gn:dem":6,
    "gn:feature_class":"P",
    "gn:feature_code":"PPL",
    "gn:name":"Salaf al Jad\u012b",
    "gn:population":0,
    "gn:timezone":"Asia/Baghdad",
    "iso:country":"IQ",
    "name:ara_x_preferred":[
        "\u0633\u0644\u0641 \u0627\u0644\u062c\u062f\u064a"
    ],
    "name:und_x_variant":[
        "Al Jady",
        "Salaf al Jad\u012b"
    ],
    "wof:name":"Salaf al Jadi",
    "wof:placetype":"locality"
},
  "geometry": {"coordinates":[47.01378,31.3462],"type":"Point"}
}