{
  "type": "Feature",
  "properties": {
    "gn:admin1_code":"4.0",
    "gn:admin2_code":"99763.0",
    "gn:asciiname":"Abu Nufaykhah",
    "gn:country_code":"IQ",
    "gn:dem":27,
    "gn:feature_class":"P",
    "gn:feature_code":"PPL",
    "gn:name":"Ab\u016b Nufaykhah",
    "gn:population":0,
    "gn:timezone":"Asia/Baghdad",
    "iso:country":"IQ",
    "name:ara_x_preferred":[
        "\u0627\u0628\u0648 \u0646\u0641\u064a\u062e\u0629"
    ],
    "name:und_x_variant":[
        "Ab\u016b Nufaykhah"
    ],
    "wof:name":"Abu Nufaykhah",
    "wof:placetype":"locality"
},
  "geometry": {"coordinates":[44.94403,32.16748],"type":"Point"}
}