{
  "type": "Feature",
  "properties": {
    "gn:admin1_code":"8.0",
    "gn:admin2_code":"97269.0",
    "gn:asciiname":"Maltah Nasara",
    "gn:country_code":"IQ",
    "gn:dem":493,
    "gn:feature_class":"P",
    "gn:feature_code":"PPL",
    "gn:name":"M\u0101ltah Na\u015f\u0101r\u00e1",
    "gn:population":0,
    "gn:timezone":"Asia/Baghdad",
    "iso:country":"IQ",
    "name:ara_x_preferred":[
        "\u0645\u0627\u0644\u0637\u0629 \u0646\u0635\u0627\u0631\u0649"
    ],
    "name:ara_x_variant":[
        "\u0645\u0627\u0644\u0637\u0629 \u0646\u0635\u0627\u0631\u0649 \u0627\u0644\u0633\u0641\u0644\u0649"
    ],
    "name:kur_x_preferred":[
        "Malte Xuwar\u00ea"
    ],
    "name:kur_x_variant":[
        "\u0645\u0627\u0644\u062a\u0647 \u062e\u0648\u0627\u0631\u06ce",
        "Malt Xuwar\u00ee",
        "\u0645\u0627\u0644\u0637 \u062e\u0648\u0627\u0631\u0649"
    ],
    "name:und_x_variant":[
        "M\u0101ltah Na\u015f\u0101r\u012b",
        "M\u0101l\u0163ah Na\u015f\u0101r\u00e1",
        "M\u0101lta-\u0113 Na\u015f\u0101r\u0101",
        "M\u0101ltah Na\u015f\u0101r\u00e1 as Sufl\u00e1"
    ],
    "wof:name":"Maltah Nasara",
    "wof:placetype":"locality"
},
  "geometry": {"coordinates":[42.93362,36.85276],"type":"Point"}
}