{
  "type": "Feature",
  "properties": {
    "gn:admin1_code":"10.0",
    "gn:admin2_code":"9166680.0",
    "gn:asciiname":"Kazim Husayn",
    "gn:country_code":"IQ",
    "gn:dem":35,
    "gn:feature_class":"P",
    "gn:feature_code":"PPL",
    "gn:name":"K\u0101z\u0327im \u1e28usayn",
    "gn:population":0,
    "gn:timezone":"Asia/Baghdad",
    "iso:country":"IQ",
    "name:ara_x_preferred":[
        "\u0643\u0627\u0638\u0645 \u062d\u0633\u064a\u0646"
    ],
    "name:und_x_variant":[
        "K\u0101z\u0327im \u1e28usayn"
    ],
    "wof:name":"Kazim Husayn",
    "wof:placetype":"locality"
},
  "geometry": {"coordinates":[45.26149,33.50844],"type":"Point"}
}