{
  "type": "Feature",
  "properties": {
    "gn:admin1_code":"5.0",
    "gn:admin2_code":"96204.0",
    "gn:asciiname":"Bishtah",
    "gn:country_code":"IQ",
    "gn:dem":671,
    "gn:feature_class":"P",
    "gn:feature_code":"PPL",
    "gn:name":"Bishtah",
    "gn:population":0,
    "gn:timezone":"Asia/Baghdad",
    "iso:country":"IQ",
    "name:ara_x_preferred":[
        "\u0628\u0634\u062a\u0629"
    ],
    "name:fas_x_preferred":[
        "P\u012bshtah"
    ],
    "name:fas_x_variant":[
        "\u067e\u064a\u0634\u062a\u0647"
    ],
    "name:und_x_variant":[
        "Pusht",
        "Pishta",
        "Bishtah"
    ],
    "wof:name":"Bishtah",
    "wof:placetype":"locality"
},
  "geometry": {"coordinates":[45.8497,34.97555],"type":"Point"}
}