{
  "type": "Feature",
  "properties": {
    "gn:admin1_code":"13.0",
    "gn:admin2_code":"94786.0",
    "gn:asciiname":"Mu'ribat",
    "gn:country_code":"IQ",
    "gn:dem":202,
    "gn:feature_class":"P",
    "gn:feature_code":"PPL",
    "gn:name":"Mu\u2018rib\u0101t",
    "gn:population":0,
    "gn:timezone":"Asia/Baghdad",
    "iso:country":"IQ",
    "name:ara_x_preferred":[
        "\u0645\u0639\u0631\u0628\u0627\u062a"
    ],
    "name:ara_x_variant":[
        "Mu\u2018rib\u0101t"
    ],
    "wof:name":"Mu'ribat",
    "wof:placetype":"locality"
},
  "geometry": {"coordinates":[44.10277,35.23609000000001],"type":"Point"}
}