{
  "type": "Feature",
  "properties": {
    "gn:admin1_code":"5.0",
    "gn:admin2_code":"97416.0",
    "gn:asciiname":"Kalah Rashi",
    "gn:country_code":"IQ",
    "gn:dem":724,
    "gn:feature_class":"P",
    "gn:feature_code":"PPL",
    "gn:name":"Kalah Rash\u012b",
    "gn:population":0,
    "gn:timezone":"Asia/Baghdad",
    "iso:country":"IQ",
    "name:ara_x_preferred":[
        "\u0643\u0644\u0629 \u0631\u0634\u064a"
    ],
    "name:kur_x_preferred":[
        "Kele \u1e5eesh\u00ee"
    ],
    "name:kur_x_variant":[
        "Kele \u1e5eeshe Gewre",
        "\u0643\u06d5\u0644\u06d5 \u0695\u06d5\u0634\u0649",
        "\u0643\u06d5\u0644\u06d5 \u0695\u06d5\u0634\u06d5 \u06af\u06d5\u0648\u0631\u06d5"
    ],
    "name:und_x_variant":[
        "Kalah Rash\u012b",
        "Kalarash",
        "Kala Rashi"
    ],
    "wof:name":"Kalah Rashi",
    "wof:placetype":"locality"
},
  "geometry": {"coordinates":[45.16827,35.35463],"type":"Point"}
}