{
  "type": "Feature",
  "properties": {
    "gn:admin1_code":"7.0",
    "gn:admin2_code":"99173.0",
    "gn:asciiname":"Muhammad Khuraybit",
    "gn:country_code":"IQ",
    "gn:dem":38,
    "gn:feature_class":"P",
    "gn:feature_code":"PPL",
    "gn:name":"Mu\u1e29ammad Khuraybi\u0163",
    "gn:population":0,
    "gn:timezone":"Asia/Baghdad",
    "iso:country":"IQ",
    "name:ara_x_preferred":[
        "\u0645\u062d\u0645\u062f \u062e\u0631\u064a\u0628\u0637"
    ],
    "name:und_x_variant":[
        "Mu\u1e29ammad Khuraybi\u0163"
    ],
    "wof:name":"Muhammad Khuraybit",
    "wof:placetype":"locality"
},
  "geometry": {"coordinates":[44.1659,33.44606],"type":"Point"}
}