{
  "type": "Feature",
  "properties": {
    "gn:admin1_code":"6.0",
    "gn:admin2_code":"99358.0",
    "gn:asciiname":"Nahi 'Isa",
    "gn:country_code":"IQ",
    "gn:dem":28,
    "gn:feature_class":"P",
    "gn:feature_code":"PPL",
    "gn:name":"N\u0101h\u012b \u2018\u012as\u00e1",
    "gn:population":0,
    "gn:timezone":"Asia/Baghdad",
    "iso:country":"IQ",
    "name:ara_x_preferred":[
        "\u0646\u0627\u0647\u064a \u0639\u064a\u0633\u0649"
    ],
    "name:ara_x_variant":[
        "N\u0101h\u012b \u2018\u012as\u00e1"
    ],
    "wof:name":"Nahi 'Isa",
    "wof:placetype":"locality"
},
  "geometry": {"coordinates":[44.80976,32.275],"type":"Point"}
}