{
  "type": "Feature",
  "properties": {
    "gn:admin1_code":"6.0",
    "gn:admin2_code":"6818313.0",
    "gn:asciiname":"Qaryat Albu Sultan",
    "gn:country_code":"IQ",
    "gn:dem":33,
    "gn:feature_class":"P",
    "gn:feature_code":"PPL",
    "gn:name":"Qaryat \u0100lb\u016b Sul\u0163\u0101n",
    "gn:population":0,
    "gn:timezone":"Asia/Baghdad",
    "iso:country":"IQ",
    "name:ara_x_preferred":[
        "\u0642\u0631\u064a\u0629 \u0627\u0644\u0628\u0648 \u0633\u0644\u0637\u0627\u0646"
    ],
    "name:und_x_variant":[
        "Qaryat \u0100lb\u016b Sul\u0163\u0101n"
    ],
    "wof:name":"Qaryat Albu Sultan",
    "wof:placetype":"locality"
},
  "geometry": {"coordinates":[44.5066,32.49215],"type":"Point"}
}