{
  "type": "Feature",
  "properties": {
    "gn:admin1_code":"7.0",
    "gn:admin2_code":"99101.0",
    "gn:asciiname":"'Ali Mustaf",
    "gn:country_code":"IQ",
    "gn:dem":31,
    "gn:feature_class":"P",
    "gn:feature_code":"PPL",
    "gn:name":"\u2018Al\u012b Mu\u015f\u0163\u0101f",
    "gn:population":0,
    "gn:timezone":"Asia/Baghdad",
    "iso:country":"IQ",
    "name:ara_x_preferred":[
        "\u0639\u0644\u064a \u0645\u0635\u0637\u0627\u0641"
    ],
    "name:ara_x_variant":[
        "\u2018Al\u012b Mu\u015f\u0163\u0101f"
    ],
    "wof:name":"'Ali Mustaf",
    "wof:placetype":"locality"
},
  "geometry": {"coordinates":[44.42283,33.05439000000001],"type":"Point"}
}