{
  "type": "Feature",
  "properties": {
    "gn:admin1_code":"11.0",
    "gn:admin2_code":"95444.0",
    "gn:asciiname":"Jadidah Nidab",
    "gn:country_code":"IQ",
    "gn:dem":307,
    "gn:feature_class":"P",
    "gn:feature_code":"PPL",
    "gn:name":"Jad\u012bdah Nid\u0101b",
    "gn:population":0,
    "gn:timezone":"Asia/Baghdad",
    "iso:country":"IQ",
    "name:ara_x_preferred":[
        "\u062c\u062f\u064a\u062f\u0629 \u0646\u062f\u0627\u0628"
    ],
    "name:und_x_variant":[
        "Jad\u012bda",
        "Jideda",
        "Jad\u012bdah",
        "Jad\u012bdah Nid\u0101b"
    ],
    "wof:name":"Jadidah Nidab",
    "wof:placetype":"locality"
},
  "geometry": {"coordinates":[43.78387,36.28625],"type":"Point"}
}