{
  "type": "Feature",
  "properties": {
    "gn:admin1_code":"15.0",
    "gn:admin2_code":"9166620.0",
    "gn:asciiname":"Khanah Sur",
    "gn:country_code":"IQ",
    "gn:dem":491,
    "gn:feature_class":"P",
    "gn:feature_code":"PPL",
    "gn:name":"Kh\u0101nah S\u016br",
    "gn:population":0,
    "gn:timezone":"Asia/Baghdad",
    "iso:country":"IQ",
    "name:ara_x_preferred":[
        "\u062e\u0627\u0646\u0629 \u0633\u0648\u0631"
    ],
    "name:kur_x_preferred":[
        "Khina S\u00fbr"
    ],
    "name:kur_x_variant":[
        "\u062e\u0646\u06d5 \u0633\u0648\u0648\u0631"
    ],
    "name:und_x_variant":[
        "Khana Sor",
        "Kh\u0101n as S\u016br",
        "Kh\u0101nah S\u016br"
    ],
    "wof:name":"Khanah Sur",
    "wof:placetype":"locality"
},
  "geometry": {"coordinates":[41.61138,36.47777],"type":"Point"}
}