{
  "type": "Feature",
  "properties": {
    "gn:admin1_code":"10.0",
    "gn:admin2_code":"99063.0",
    "gn:asciiname":"Qaryat Habib ash Shallal",
    "gn:country_code":"IQ",
    "gn:dem":58,
    "gn:feature_class":"P",
    "gn:feature_code":"PPL",
    "gn:name":"Qaryat \u1e28ab\u012bb ash Shall\u0101l",
    "gn:population":0,
    "gn:timezone":"Asia/Baghdad",
    "iso:country":"IQ",
    "name:ara_x_preferred":[
        "\u0642\u0631\u064a\u0629 \u062d\u0628\u064a\u0628 \u0627\u0644\u0634\u0644\u0627\u0644"
    ],
    "name:und_x_variant":[
        "\u1e28ab\u012bb ash Shall\u0101l",
        "\u062d\u0628\u064a\u0628 \u0627\u0644\u0634\u0644\u0627\u0644",
        "Qaryat \u1e28ab\u012bb ash Shall\u0101l"
    ],
    "wof:name":"Qaryat Habib ash Shallal",
    "wof:placetype":"locality"
},
  "geometry": {"coordinates":[44.92592,33.93545],"type":"Point"}
}