{
  "type": "Feature",
  "properties": {
    "gn:admin1_code":"17.0",
    "gn:admin2_code":"9166552.0",
    "gn:asciiname":"Manazil as Sayyid Hassun",
    "gn:cc2":"IQ",
    "gn:country_code":"IQ",
    "gn:dem":19,
    "gn:feature_class":"P",
    "gn:feature_code":"PPL",
    "gn:name":"Man\u0101zil as Sayyid \u1e28ass\u016bn",
    "gn:population":0,
    "gn:timezone":"Asia/Baghdad",
    "iso:country":"IQ",
    "name:und_x_variant":[
        "As Sayyid \u1e28ass\u016bn",
        "Man\u0101zil Sayyid Na\u015fir",
        "Man\u0101zil Saiyid Nasur",
        "Man\u0101zil as Sayyid \u1e28ass\u016bn"
    ],
    "wof:name":"Manazil as Sayyid Hassun",
    "wof:placetype":"locality"
},
  "geometry": {"coordinates":[44.48056,31.74167000000001],"type":"Point"}
}