{
  "type": "Feature",
  "properties": {
    "gn:admin1_code":"18.0",
    "gn:admin2_code":"6805736.0",
    "gn:asciiname":"'Ubayd al Ahmad",
    "gn:country_code":"IQ",
    "gn:dem":48,
    "gn:feature_class":"P",
    "gn:feature_code":"PPL",
    "gn:name":"\u2018Ubayd al A\u1e29mad",
    "gn:population":0,
    "gn:timezone":"Asia/Baghdad",
    "iso:country":"IQ",
    "name:ara_x_preferred":[
        "\u0639\u0628\u064a\u062f \u0627\u0644\u0627\u062d\u0645\u062f"
    ],
    "name:und_x_variant":[
        "\u2018Ubayd al A\u1e29mad"
    ],
    "wof:name":"'Ubayd al Ahmad",
    "wof:placetype":"locality"
},
  "geometry": {"coordinates":[44.0728,33.95397],"type":"Point"}
}