{
  "type": "Feature",
  "properties": {
    "gn:admin1_code":"11.0",
    "gn:admin2_code":"9166592.0",
    "gn:asciiname":"Dayranah",
    "gn:country_code":"IQ",
    "gn:dem":631,
    "gn:feature_class":"P",
    "gn:feature_code":"PPL",
    "gn:name":"Dayr\u0101nah",
    "gn:population":0,
    "gn:timezone":"Asia/Baghdad",
    "iso:country":"IQ",
    "name:ara_x_preferred":[
        "\u062f\u064a\u0631\u0627\u0646\u0629"
    ],
    "name:kur_x_preferred":[
        "D\u00earna"
    ],
    "name:kur_x_variant":[
        "\u062f\u06ce\u0631\u0646\u0627"
    ],
    "name:und_x_variant":[
        "Dayr\u0101nah",
        "D\u0113r\u0101na",
        "Derana"
    ],
    "wof:name":"Dayranah",
    "wof:placetype":"locality"
},
  "geometry": {"coordinates":[44.54495,36.74989],"type":"Point"}
}