{
  "type": "Feature",
  "properties": {
    "gn:admin1_code":"10.0",
    "gn:admin2_code":"99063.0",
    "gn:asciiname":"Qarayt al Ashjari",
    "gn:country_code":"IQ",
    "gn:dem":51,
    "gn:feature_class":"P",
    "gn:feature_code":"PPL",
    "gn:name":"Qarayt al Ashjar\u012b",
    "gn:population":0,
    "gn:timezone":"Asia/Baghdad",
    "iso:country":"IQ",
    "name:ara_x_preferred":[
        "\u0642\u0631\u064a\u0629 \u0627\u0644\u0627\u0634\u062c\u0631\u064a"
    ],
    "name:und_x_variant":[
        "Qarayt al Ashjar\u012b"
    ],
    "wof:name":"Qarayt al Ashjari",
    "wof:placetype":"locality"
},
  "geometry": {"coordinates":[44.91549000000001,33.81817],"type":"Point"}
}