{
  "type": "Feature",
  "properties": {
    "gn:admin1_code":"18.0",
    "gn:admin2_code":"91594.0",
    "gn:asciiname":"Jabar Muhammad",
    "gn:country_code":"IQ",
    "gn:dem":80,
    "gn:feature_class":"P",
    "gn:feature_code":"PPL",
    "gn:name":"Jab\u0101r Mu\u1e29ammad",
    "gn:population":0,
    "gn:timezone":"Asia/Baghdad",
    "iso:country":"IQ",
    "name:ara_x_preferred":[
        "\u062c\u0628\u0627\u0631 \u0645\u062d\u0645\u062f"
    ],
    "name:und_x_variant":[
        "Jab\u0101r Mu\u1e29ammad"
    ],
    "wof:name":"Jabar Muhammad",
    "wof:placetype":"locality"
},
  "geometry": {"coordinates":[43.67814,34.1764],"type":"Point"}
}