{
  "type": "Feature",
  "properties": {
    "gn:admin1_code":"5.0",
    "gn:admin2_code":"9166596.0",
    "gn:asciiname":"Watah",
    "gn:country_code":"IQ",
    "gn:dem":515,
    "gn:feature_class":"P",
    "gn:feature_code":"PPL",
    "gn:name":"Watah",
    "gn:population":0,
    "gn:timezone":"Asia/Baghdad",
    "iso:country":"IQ",
    "name:ara_x_preferred":[
        "\u0648\u062a\u0629"
    ],
    "name:kur_x_preferred":[
        "Wete"
    ],
    "name:kur_x_variant":[
        "\u0648\u06d5\u062a\u0647",
        "Wat\u00ea",
        "\u0648\u0627\u062a\u06ce"
    ],
    "name:und_x_variant":[
        "W\u0101ta",
        "Wata",
        "Wate"
    ],
    "wof:name":"Watah",
    "wof:placetype":"locality"
},
  "geometry": {"coordinates":[45.00892,36.03166],"type":"Point"}
}