{
  "type": "Feature",
  "properties": {
    "gn:admin1_code":"7.0",
    "gn:admin2_code":"9166542.0",
    "gn:asciiname":"Qaryat al Huthut",
    "gn:country_code":"IQ",
    "gn:dem":42,
    "gn:feature_class":"P",
    "gn:feature_code":"PPL",
    "gn:name":"Qaryat al \u1e28u\u0163\u1e29\u016b\u0163",
    "gn:population":0,
    "gn:timezone":"Asia/Baghdad",
    "iso:country":"IQ",
    "name:ara_x_preferred":[
        "\u0642\u0631\u064a\u0629 \u0627\u0644\u062d\u0637\u062d\u0648\u0637"
    ],
    "name:und_x_variant":[
        "Qaryat al \u1e28u\u0163\u1e29\u016b\u0163"
    ],
    "wof:name":"Qaryat al Huthut",
    "wof:placetype":"locality"
},
  "geometry": {"coordinates":[43.97852,33.21196],"type":"Point"}
}