{
  "type": "Feature",
  "properties": {
    "gn:admin1_code":"11.0",
    "gn:admin2_code":"9166586.0",
    "gn:asciiname":"Sekran",
    "gn:country_code":"IQ",
    "gn:dem":1480,
    "gn:feature_class":"P",
    "gn:feature_code":"PPL",
    "gn:name":"Sekran",
    "gn:population":0,
    "gn:timezone":"Asia/Baghdad",
    "iso:country":"IQ",
    "name:ara_x_preferred":[
        "\u0633\u0643\u0627\u0631\u064a \u0633\u0643\u0631\u0627\u0646"
    ],
    "name:kur_x_preferred":[
        "Sekran"
    ],
    "name:kur_x_variant":[
        "\u0633\u06d5\u0643\u0631\u0627\u0646"
    ],
    "name:und_x_variant":[
        "Sak\u0101r\u012b Sakr\u0101n",
        "Sakr\u0101-i Sakr\u0101n",
        "Sakran"
    ],
    "wof:name":"Sekran",
    "wof:placetype":"locality"
},
  "geometry": {"coordinates":[44.91883,36.59089],"type":"Point"}
}