{
  "type": "Feature",
  "properties": {
    "gn:admin1_code":"10.0",
    "gn:admin2_code":"94590.0",
    "gn:asciiname":"Bahizah as Saghirah",
    "gn:country_code":"IQ",
    "gn:dem":113,
    "gn:feature_class":"P",
    "gn:feature_code":"PPL",
    "gn:name":"Bah\u012bzah a\u015f \u015eagh\u012brah",
    "gn:population":0,
    "gn:timezone":"Asia/Baghdad",
    "iso:country":"IQ",
    "name:ara_x_preferred":[
        "\u0628\u0647\u064a\u0632\u0629 \u0627\u0644\u0635\u063a\u064a\u0631\u0629"
    ],
    "name:und_x_variant":[
        "Bah\u012bzah a\u015f \u015eagh\u012brah"
    ],
    "wof:name":"Bahizah as Saghirah",
    "wof:placetype":"locality"
},
  "geometry": {"coordinates":[45.07906,34.3066],"type":"Point"}
}