{
  "type": "Feature",
  "properties": {
    "gn:admin1_code":"17.0",
    "gn:admin2_code":"9166629.0",
    "gn:asciiname":"Sayyid Husayn",
    "gn:country_code":"IQ",
    "gn:dem":24,
    "gn:feature_class":"P",
    "gn:feature_code":"PPL",
    "gn:name":"Sayyid \u1e28usayn",
    "gn:population":0,
    "gn:timezone":"Asia/Baghdad",
    "iso:country":"IQ",
    "name:ara_x_preferred":[
        "\u0633\u064a\u062f \u062d\u0633\u064a\u0646"
    ],
    "name:und_x_variant":[
        "Sayyid \u1e28usayn"
    ],
    "wof:name":"Sayyid Husayn",
    "wof:placetype":"locality"
},
  "geometry": {"coordinates":[44.51596,32.10496],"type":"Point"}
}