{
  "type": "Feature",
  "properties": {
    "gn:admin1_code":"15.0",
    "gn:admin2_code":"9166620.0",
    "gn:asciiname":"Sharaf ad Din",
    "gn:country_code":"IQ",
    "gn:dem":591,
    "gn:feature_class":"P",
    "gn:feature_code":"PPL",
    "gn:name":"Sharaf ad D\u012bn",
    "gn:population":0,
    "gn:timezone":"Asia/Baghdad",
    "iso:country":"IQ",
    "name:ara_x_preferred":[
        "\u0634\u0631\u0641 \u0627\u0644\u062f\u064a\u0646"
    ],
    "name:und_x_variant":[
        "Sharaf ad D\u012bn"
    ],
    "wof:name":"Sharaf ad Din",
    "wof:placetype":"locality"
},
  "geometry": {"coordinates":[41.86876,36.43001],"type":"Point"}
}