{
  "type": "Feature",
  "properties": {
    "gn:admin1_code":"14.0",
    "gn:admin2_code":"99610.0",
    "gn:asciiname":"Salaf Sakr",
    "gn:country_code":"IQ",
    "gn:dem":7,
    "gn:feature_class":"P",
    "gn:feature_code":"PPL",
    "gn:name":"Salaf Sakr",
    "gn:population":0,
    "gn:timezone":"Asia/Baghdad",
    "iso:country":"IQ",
    "name:ara_x_preferred":[
        "\u0633\u0644\u0641 \u0633\u0643\u0631"
    ],
    "wof:name":"Salaf Sakr",
    "wof:placetype":"locality"
},
  "geometry": {"coordinates":[47.57076,31.71319],"type":"Point"}
}