{
  "type": "Feature",
  "properties": {
    "gn:admin1_code":"5.0",
    "gn:admin2_code":"92051.0",
    "gn:asciiname":"Enguz",
    "gn:country_code":"IQ",
    "gn:dem":1012,
    "gn:feature_class":"P",
    "gn:feature_code":"PPL",
    "gn:name":"Enguz",
    "gn:population":0,
    "gn:timezone":"Asia/Baghdad",
    "iso:country":"IQ",
    "name:ara_x_preferred":[
        "Ank\u016bz"
    ],
    "name:ara_x_variant":[
        "\u0627\u0646\u0643\u0648\u0632"
    ],
    "name:kur_x_preferred":[
        "\u0626\u06d5\u0646\u06af\u0648\u0632"
    ],
    "name:kur_x_variant":[
        "Angoz",
        "Enguz"
    ],
    "name:und_x_variant":[
        "Ang\u014dz"
    ],
    "wof:name":"Enguz",
    "wof:placetype":"locality"
},
  "geometry": {"coordinates":[44.73387,36.32026],"type":"Point"}
}