{
  "type": "Feature",
  "properties": {
    "gn:admin1_code":"5.0",
    "gn:admin2_code":"98464.0",
    "gn:asciiname":"Karays",
    "gn:country_code":"IQ",
    "gn:dem":771,
    "gn:feature_class":"P",
    "gn:feature_code":"PPL",
    "gn:name":"K\u0101rays",
    "gn:population":0,
    "gn:timezone":"Asia/Baghdad",
    "iso:country":"IQ",
    "name:ara_x_preferred":[
        "K\u0101r\u012bbs"
    ],
    "name:ara_x_variant":[
        "\u0643\u0627\u0631\u064a\u0633"
    ],
    "name:kur_x_preferred":[
        "Kar\u00eaz"
    ],
    "name:kur_x_variant":[
        "Kar\u00eaze",
        "\u0643\u0627\u0631\u06ce\u0632",
        "\u0643\u0627\u0631\u06ce\u0632\u06d5"
    ],
    "name:und_x_variant":[
        "K\u0101r\u012bz",
        "\u0643\u0627\u0631\u064a\u0628\u0633",
        "K\u0101z\u012br",
        "K\u0101rays",
        "\u0643\u0627\u0631\u064a\u0633",
        "K\u0101r\u012bbs"
    ],
    "wof:name":"Karays",
    "wof:placetype":"locality"
},
  "geometry": {"coordinates":[45.51744,35.3534],"type":"Point"}
}