{
  "type": "Feature",
  "properties": {
    "gn:admin1_code":"18.0",
    "gn:admin2_code":"9167093.0",
    "gn:asciiname":"Jabir Makhlaf",
    "gn:country_code":"IQ",
    "gn:dem":94,
    "gn:feature_class":"P",
    "gn:feature_code":"PPL",
    "gn:name":"J\u0101bir Makhlaf",
    "gn:population":0,
    "gn:timezone":"Asia/Baghdad",
    "iso:country":"IQ",
    "name:ara_x_preferred":[
        "\u062c\u0627\u0628\u0631 \u0645\u062e\u0644\u0641"
    ],
    "name:und_x_variant":[
        "J\u0101bir Makhlaf"
    ],
    "wof:name":"Jabir Makhlaf",
    "wof:placetype":"locality"
},
  "geometry": {"coordinates":[43.48921,34.12701],"type":"Point"}
}