{
  "type": "Feature",
  "properties": {
    "gn:admin1_code":"14.0",
    "gn:admin2_code":"99610.0",
    "gn:asciiname":"Rashid",
    "gn:country_code":"IQ",
    "gn:dem":8,
    "gn:feature_class":"P",
    "gn:feature_code":"PPL",
    "gn:name":"R\u0101shid",
    "gn:population":0,
    "gn:timezone":"Asia/Baghdad",
    "iso:country":"IQ",
    "name:ara_x_preferred":[
        "\u0631\u0627\u0634\u062f"
    ],
    "name:ara_x_variant":[
        "R\u0101shid",
        "\u0631\u0634\u064a\u062f"
    ],
    "name:aze_x_preferred":[
        "R\u0259\u015fid"
    ],
    "name:bul_x_preferred":[
        "\u0420\u0430\u0448\u0438\u0434"
    ],
    "name:deu_x_preferred":[
        "Raschid"
    ],
    "name:fra_x_preferred":[
        "Rachid"
    ],
    "name:ita_x_preferred":[
        "Rashid"
    ],
    "name:kaz_x_preferred":[
        "\u0420\u0430\u0448\u0438\u0434 \u049b\u0430\u043b\u0430\u0441\u044b"
    ],
    "name:por_x_preferred":[
        "Rashid"
    ],
    "name:rus_x_preferred":[
        "\u0420\u0430\u0448\u0438\u0434"
    ],
    "name:swe_x_preferred":[
        "Rashid"
    ],
    "wof:name":"Rashid",
    "wof:placetype":"locality"
},
  "geometry": {"coordinates":[47.28957,31.80854],"type":"Point"}
}