{
  "type": "Feature",
  "properties": {
    "gn:admin1_code":"5.0",
    "gn:admin2_code":"91176.0",
    "gn:asciiname":"Basawe",
    "gn:country_code":"IQ",
    "gn:dem":979,
    "gn:feature_class":"P",
    "gn:feature_code":"PPL",
    "gn:name":"Basawe",
    "gn:population":0,
    "gn:timezone":"Asia/Baghdad",
    "iso:country":"IQ",
    "name:ara_x_preferred":[
        "B\u0101s\u0101w\u0101"
    ],
    "name:ara_x_variant":[
        "\u0628\u0627\u0633\u0627\u0648\u0627"
    ],
    "name:kur_x_preferred":[
        "Basawe"
    ],
    "name:kur_x_variant":[
        "\u0628\u0627\u0633\u0627\u0648\u06d5"
    ],
    "name:und_x_variant":[
        "Basawa"
    ],
    "wof:name":"Basawe",
    "wof:placetype":"locality"
},
  "geometry": {"coordinates":[45.35129000000001,35.93162],"type":"Point"}
}