{
  "type": "Feature",
  "properties": {
    "gn:admin1_code":"17.0",
    "gn:admin2_code":"9166552.0",
    "gn:asciiname":"Kazim Abu Taggah",
    "gn:country_code":"IQ",
    "gn:dem":22,
    "gn:feature_class":"P",
    "gn:feature_code":"PPL",
    "gn:name":"K\u0101z\u0327im Ab\u016b \u0162aggah",
    "gn:population":0,
    "gn:timezone":"Asia/Baghdad",
    "iso:country":"IQ",
    "name:ara_x_preferred":[
        "\u0643\u0627\u0638\u0645 \u0627\u0628\u0648 \u062e\u06af\u0647"
    ],
    "name:und_x_variant":[
        "K\u0101z\u0327im Ab\u016b \u0162aggah"
    ],
    "wof:name":"Kazim Abu Taggah",
    "wof:placetype":"locality"
},
  "geometry": {"coordinates":[44.44493,31.80452],"type":"Point"}
}