{
  "type": "Feature",
  "properties": {
    "gn:admin1_code":"13.0",
    "gn:admin2_code":"9166581.0",
    "gn:asciiname":"'Adnaniyah",
    "gn:country_code":"IQ",
    "gn:dem":202,
    "gn:feature_class":"P",
    "gn:feature_code":"PPL",
    "gn:name":"\u2018Adn\u0101n\u012byah",
    "gn:population":0,
    "gn:timezone":"Asia/Baghdad",
    "iso:country":"IQ",
    "name:ara_x_preferred":[
        "\u0639\u062f\u0646\u0627\u0646\u064a\u0629"
    ],
    "name:und_x_variant":[
        "\u2018Adn\u0101n\u012byah"
    ],
    "wof:name":"'Adnaniyah",
    "wof:placetype":"locality"
},
  "geometry": {"coordinates":[44.34824,35.10174],"type":"Point"}
}