{
  "type": "Feature",
  "properties": {
    "gn:admin1_code":"10.0",
    "gn:admin2_code":"99063.0",
    "gn:asciiname":"'Arab Bartun",
    "gn:country_code":"IQ",
    "gn:dem":43,
    "gn:feature_class":"P",
    "gn:feature_code":"PPL",
    "gn:name":"\u2018Arab Bart\u016bn",
    "gn:population":0,
    "gn:timezone":"Asia/Baghdad",
    "iso:country":"IQ",
    "name:ara_x_preferred":[
        "\u0639\u0631\u0628 \u0628\u0631\u0646\u0648\u0646"
    ],
    "name:und_x_variant":[
        "\u2018Arab Bart\u016bn"
    ],
    "wof:name":"'Arab Bartun",
    "wof:placetype":"locality"
},
  "geometry": {"coordinates":[44.60491,33.63377],"type":"Point"}
}