{
  "type": "Feature",
  "properties": {
    "gn:admin1_code":"9.0",
    "gn:admin2_code":"90509.0",
    "gn:asciiname":"Jama'at as Sayyid Husayn",
    "gn:country_code":"IQ",
    "gn:dem":4,
    "gn:feature_class":"P",
    "gn:feature_code":"PPLL",
    "gn:name":"Jam\u0101\u2018at as Sayyid \u1e28usayn",
    "gn:population":0,
    "gn:timezone":"Asia/Baghdad",
    "iso:country":"IQ",
    "name:ara_x_preferred":[
        "\u062c\u0645\u0627\u0639\u0629 \u0627\u0644\u0633\u064a\u062f \u062d\u0633\u064a\u0646"
    ],
    "name:und_x_variant":[
        "Jam\u0101\u2018at as Sayyid \u1e28usayn"
    ],
    "wof:name":"Jama'at as Sayyid Husayn",
    "wof:placetype":"locality"
},
  "geometry": {"coordinates":[46.46576,31.02856],"type":"Point"}
}