{
  "type": "Feature",
  "properties": {
    "gn:admin1_code":"18.0",
    "gn:admin2_code":"90148.0",
    "gn:asciiname":"'Abd at Turki",
    "gn:country_code":"IQ",
    "gn:dem":115,
    "gn:feature_class":"P",
    "gn:feature_code":"PPL",
    "gn:name":"\u2018Abd at Turk\u012b",
    "gn:population":0,
    "gn:timezone":"Asia/Baghdad",
    "iso:country":"IQ",
    "name:ara_x_preferred":[
        "\u0639\u0628\u062f \u0627\u0644\u062a\u0631\u0643\u064a"
    ],
    "name:und_x_variant":[
        "\u2018Abd at Turk\u012b"
    ],
    "wof:name":"'Abd at Turki",
    "wof:placetype":"locality"
},
  "geometry": {"coordinates":[43.98938,34.71972],"type":"Point"}
}