{
  "type": "Feature",
  "properties": {
    "gn:admin1_code":"8.0",
    "gn:admin2_code":"99612.0",
    "gn:asciiname":"Cheluke Spindar",
    "gn:country_code":"IQ",
    "gn:dem":999,
    "gn:feature_class":"P",
    "gn:feature_code":"PPL",
    "gn:name":"Cheluk\u00ea Sp\u00eendar",
    "gn:population":0,
    "gn:timezone":"Asia/Baghdad",
    "iso:country":"IQ",
    "name:ara_x_preferred":[
        "\u062c\u0644\u0648\u0643\u064a"
    ],
    "name:kur_x_preferred":[
        "Cheluk\u00ea Sp\u00eendar"
    ],
    "name:kur_x_variant":[
        "\u0686\u06d5\u0644\u0648\u0643\u06ce \u0633\u067e\u064a\u0646\u062f\u0627\u0631",
        "Clul\u00ee",
        "\u062c\u0644\u0648\u0644\u0649"
    ],
    "name:und_x_variant":[
        "Jal\u016bk\u012b",
        "Cholok\u012b",
        "Jluly"
    ],
    "wof:name":"Cheluke Spindar",
    "wof:placetype":"locality"
},
  "geometry": {"coordinates":[43.36208,36.94545],"type":"Point"}
}