{
  "type": "Feature",
  "properties": {
    "gn:admin1_code":"4.0",
    "gn:admin2_code":"6850588.0",
    "gn:asciiname":"'Abd 'Ali",
    "gn:country_code":"IQ",
    "gn:dem":20,
    "gn:feature_class":"P",
    "gn:feature_code":"PPL",
    "gn:name":"\u2018Abd \u2018Al\u012b",
    "gn:population":0,
    "gn:timezone":"Asia/Baghdad",
    "iso:country":"IQ",
    "name:ara_x_preferred":[
        "\u0639\u0628\u062f \u0639\u0644\u064a"
    ],
    "name:ara_x_variant":[
        "\u2018Abd \u2018Al\u012b"
    ],
    "name:und_x_variant":[
        "Abd \u2018Alt"
    ],
    "wof:name":"'Abd 'Ali",
    "wof:placetype":"locality"
},
  "geometry": {"coordinates":[45.00868,31.70453],"type":"Point"}
}