{
  "type": "Feature",
  "properties": {
    "gn:admin1_code":"18.0",
    "gn:admin2_code":"6805736.0",
    "gn:asciiname":"'Arab 'Ali Jasim",
    "gn:country_code":"IQ",
    "gn:dem":49,
    "gn:feature_class":"P",
    "gn:feature_code":"PPL",
    "gn:name":"\u2018Arab \u2018Al\u012b J\u0101sim",
    "gn:population":0,
    "gn:timezone":"Asia/Baghdad",
    "iso:country":"IQ",
    "name:ara_x_preferred":[
        "\u0639\u0631\u0628 \u0639\u0644\u064a \u062c\u0627\u0633\u0645"
    ],
    "name:und_x_variant":[
        "\u2018Arab \u2018Al\u012b J\u0101sim"
    ],
    "wof:name":"'Arab 'Ali Jasim",
    "wof:placetype":"locality"
},
  "geometry": {"coordinates":[44.20575,34.01973],"type":"Point"}
}