{
  "type": "Feature",
  "properties": {
    "gn:admin1_code":"17.0",
    "gn:admin2_code":"9166629.0",
    "gn:asciiname":"Salman Huwayd",
    "gn:country_code":"IQ",
    "gn:dem":25,
    "gn:feature_class":"P",
    "gn:feature_code":"PPL",
    "gn:name":"Salm\u0101n Huwayd",
    "gn:population":0,
    "gn:timezone":"Asia/Baghdad",
    "iso:country":"IQ",
    "name:ara_x_preferred":[
        "\u0633\u0644\u0645\u0627\u0646 \u0647\u0648\u064a\u062f"
    ],
    "name:und_x_variant":[
        "Salm\u0101n Huwayd"
    ],
    "wof:name":"Salman Huwayd",
    "wof:placetype":"locality"
},
  "geometry": {"coordinates":[44.55182,32.10987],"type":"Point"}
}