{
  "type": "Feature",
  "properties": {
    "gn:admin1_code":"14.0",
    "gn:admin2_code":"99610.0",
    "gn:asciiname":"Humayliyah",
    "gn:cc2":"IQ",
    "gn:country_code":"IQ",
    "gn:dem":9,
    "gn:feature_class":"P",
    "gn:feature_code":"PPL",
    "gn:name":"\u1e28umayl\u012byah",
    "gn:population":0,
    "gn:timezone":"Asia/Baghdad",
    "iso:country":"IQ",
    "name:und_x_variant":[
        "Humail\u012byah",
        "\u1e28umayl\u012byah"
    ],
    "wof:name":"Humayliyah",
    "wof:placetype":"locality"
},
  "geometry": {"coordinates":[47.48333,31.78333],"type":"Point"}
}