{
  "type": "Feature",
  "properties": {
    "gn:admin1_code":"5.0",
    "gn:admin2_code":"91176.0",
    "gn:asciiname":"Kawtir Qur",
    "gn:country_code":"IQ",
    "gn:dem":940,
    "gn:feature_class":"P",
    "gn:feature_code":"PPL",
    "gn:name":"Kawtir Qur",
    "gn:population":0,
    "gn:timezone":"Asia/Baghdad",
    "iso:country":"IQ",
    "name:ara_x_preferred":[
        "\u0643\u0648\u062a\u0631 \u0642\u0631"
    ],
    "name:kur_x_preferred":[
        "Kotr Qu\u1e5f"
    ],
    "name:kur_x_variant":[
        "\u0643\u06c6\u062a\u0631 \u0642\u0648\u0695"
    ],
    "name:und_x_variant":[
        "Kotir Qur"
    ],
    "wof:name":"Kawtir Qur",
    "wof:placetype":"locality"
},
  "geometry": {"coordinates":[45.7258,35.50723],"type":"Point"}
}