{
  "type": "Feature",
  "properties": {
    "gn:admin1_code":"6.0",
    "gn:admin2_code":"6818313.0",
    "gn:asciiname":"'Arab Mustaf Ahmad",
    "gn:country_code":"IQ",
    "gn:dem":35,
    "gn:feature_class":"P",
    "gn:feature_code":"PPL",
    "gn:name":"\u2018Arab Mu\u015ft\u0101f A\u1e29mad",
    "gn:population":0,
    "gn:timezone":"Asia/Baghdad",
    "iso:country":"IQ",
    "name:ara_x_preferred":[
        "\u0639\u0631\u0628 \u0645\u0635\u0637\u0627\u0641 \u0627\u062d\u0645\u062f"
    ],
    "name:und_x_variant":[
        "\u2018Arab Mu\u015ft\u0101f A\u1e29mad"
    ],
    "wof:name":"'Arab Mustaf Ahmad",
    "wof:placetype":"locality"
},
  "geometry": {"coordinates":[44.39055,32.84952],"type":"Point"}
}