{
  "type": "Feature",
  "properties": {
    "gn:admin1_code":"3.0",
    "gn:admin2_code":"9166626.0",
    "gn:asciiname":"Az Zarifiyah",
    "gn:country_code":"IQ",
    "gn:dem":9,
    "gn:feature_class":"P",
    "gn:feature_code":"PPL",
    "gn:name":"Az\u0327 Z\u0327ar\u012bf\u012byah",
    "gn:population":0,
    "gn:timezone":"Asia/Baghdad",
    "iso:country":"IQ",
    "name:ara_x_preferred":[
        "\u0627\u0644\u0638\u0631\u064a\u0641\u064a\u0629"
    ],
    "name:und_x_variant":[
        "Az\u0327 Z\u0327ar\u012bf\u012byah"
    ],
    "wof:name":"Az Zarifiyah",
    "wof:placetype":"locality"
},
  "geometry": {"coordinates":[45.61878,31.16297],"type":"Point"}
}