{
  "type": "Feature",
  "properties": {
    "gn:admin1_code":"10.0",
    "gn:admin2_code":"94590.0",
    "gn:asciiname":"Muhammad Humayli",
    "gn:country_code":"IQ",
    "gn:dem":145,
    "gn:feature_class":"P",
    "gn:feature_code":"PPL",
    "gn:name":"Mu\u1e29ammad Humayl\u012b",
    "gn:population":0,
    "gn:timezone":"Asia/Baghdad",
    "iso:country":"IQ",
    "name:ara_x_preferred":[
        "\u0645\u062d\u0645\u062f \u0647\u0645\u064a\u0644\u064a"
    ],
    "name:und_x_variant":[
        "Mu\u1e29ammad \u015e\u0101li\u1e29",
        "\u0645\u062d\u0645\u062f \u0635\u0627\u0644\u062d",
        "Mu\u1e29ammad Humayl\u012b"
    ],
    "wof:name":"Muhammad Humayli",
    "wof:placetype":"locality"
},
  "geometry": {"coordinates":[45.24983,34.37592],"type":"Point"}
}