{
  "type": "Feature",
  "properties": {
    "gn:admin1_code":"7.0",
    "gn:admin2_code":"99101.0",
    "gn:asciiname":"Muhammad Khafi",
    "gn:country_code":"IQ",
    "gn:dem":35,
    "gn:feature_class":"P",
    "gn:feature_code":"PPL",
    "gn:name":"Mu\u1e29ammad Khaf\u012b",
    "gn:population":0,
    "gn:timezone":"Asia/Baghdad",
    "iso:country":"IQ",
    "name:ara_x_preferred":[
        "\u0645\u062d\u0645\u062f \u062e\u0641\u064a"
    ],
    "name:und_x_variant":[
        "Mu\u1e29ammad Khaf\u012b"
    ],
    "wof:name":"Muhammad Khafi",
    "wof:placetype":"locality"
},
  "geometry": {"coordinates":[44.34885,32.98759],"type":"Point"}
}