{
  "type": "Feature",
  "properties": {
    "gn:admin1_code":"9.0",
    "gn:admin2_code":"98623.0",
    "gn:asciiname":"Na'if as Sarab",
    "gn:country_code":"IQ",
    "gn:dem":9,
    "gn:feature_class":"P",
    "gn:feature_code":"PPL",
    "gn:name":"N\u0101\u2019if as Sar\u0101b",
    "gn:population":0,
    "gn:timezone":"Asia/Baghdad",
    "iso:country":"IQ",
    "name:und_x_variant":[
        "N\u0101yif as Sar\u0101b",
        "N\u0101\u2019if as Sar\u0101b"
    ],
    "wof:name":"Na'if as Sarab",
    "wof:placetype":"locality"
},
  "geometry": {"coordinates":[46.23333,31.31667],"type":"Point"}
}