{
  "type": "Feature",
  "properties": {
    "gn:admin1_code":"4.0",
    "gn:admin2_code":"99763.0",
    "gn:asciiname":"Qaryat al Mahamidah",
    "gn:country_code":"IQ",
    "gn:dem":21,
    "gn:feature_class":"P",
    "gn:feature_code":"PPL",
    "gn:name":"Qaryat al Ma\u1e29\u0101midah",
    "gn:population":0,
    "gn:timezone":"Asia/Baghdad",
    "iso:country":"IQ",
    "name:ara_x_preferred":[
        "\u0642\u0631\u064a\u0629 \u0627\u0644\u0645\u062d\u0627\u0645\u062f\u0629"
    ],
    "name:und_x_variant":[
        "Qaryat al Ma\u1e29\u0101midah"
    ],
    "wof:name":"Qaryat al Mahamidah",
    "wof:placetype":"locality"
},
  "geometry": {"coordinates":[44.6456,32.09667],"type":"Point"}
}