{
  "type": "Feature",
  "properties": {
    "gn:admin1_code":"8.0",
    "gn:admin2_code":"99612.0",
    "gn:asciiname":"Dereluk",
    "gn:country_code":"IQ",
    "gn:dem":626,
    "gn:feature_class":"P",
    "gn:feature_code":"PPL",
    "gn:name":"D\u00earel\u00fbk",
    "gn:population":0,
    "gn:timezone":"Asia/Baghdad",
    "iso:country":"IQ",
    "wof:name":"Dereluk",
    "wof:placetype":"locality"
},
  "geometry": {"coordinates":[43.65188,37.05598],"type":"Point"}
}