{
  "type": "Feature",
  "properties": {
    "gn:admin1_code":"3.0",
    "gn:admin2_code":"9166568.0",
    "gn:asciiname":"Matruh al Gati'",
    "gn:country_code":"IQ",
    "gn:dem":15,
    "gn:feature_class":"P",
    "gn:feature_code":"PPLL",
    "gn:name":"Ma\u0163r\u016b\u1e29 al G\u0101\u0163i\u2018",
    "gn:population":0,
    "gn:timezone":"Asia/Baghdad",
    "iso:country":"IQ",
    "name:ara_x_preferred":[
        "\u0645\u0637\u0631\u0648\u062d \u0627\u0644\u06af\u0627\u0637\u0639"
    ],
    "name:und_x_variant":[
        "Ma\u0163r\u016b\u1e29 al G\u0101\u0163i\u2018"
    ],
    "wof:name":"Matruh al Gati'",
    "wof:placetype":"locality"
},
  "geometry": {"coordinates":[45.17203,31.39629],"type":"Point"}
}