{
  "type": "Feature",
  "properties": {
    "gn:admin1_code":"8.0",
    "gn:admin2_code":"9166607.0",
    "gn:asciiname":"Chambarakat",
    "gn:country_code":"IQ",
    "gn:dem":307,
    "gn:feature_class":"P",
    "gn:feature_code":"PPL",
    "gn:name":"Chambarak\u0101t",
    "gn:population":0,
    "gn:timezone":"Asia/Baghdad",
    "iso:country":"IQ",
    "wof:name":"Chambarakat",
    "wof:placetype":"locality"
},
  "geometry": {"coordinates":[42.75,36.75],"type":"Point"}
}