{
  "type": "Feature",
  "properties": {
    "gn:admin1_code":"10.0",
    "gn:admin2_code":"99170.0",
    "gn:asciiname":"Jasim as Salim",
    "gn:country_code":"IQ",
    "gn:dem":52,
    "gn:feature_class":"P",
    "gn:feature_code":"PPL",
    "gn:name":"J\u0101sim as S\u0101lim",
    "gn:population":0,
    "gn:timezone":"Asia/Baghdad",
    "iso:country":"IQ",
    "name:ara_x_preferred":[
        "\u062c\u0627\u0633\u0645 \u0627\u0644\u0633\u0627\u0644\u0645"
    ],
    "name:und_x_variant":[
        "J\u0101sim as S\u0101lim"
    ],
    "wof:name":"Jasim as Salim",
    "wof:placetype":"locality"
},
  "geometry": {"coordinates":[44.57588,33.88299],"type":"Point"}
}