{
  "type": "Feature",
  "properties": {
    "gn:admin1_code":"5.0",
    "gn:admin2_code":"9166600.0",
    "gn:asciiname":"Kelar",
    "gn:country_code":"IQ",
    "gn:dem":216,
    "gn:feature_class":"P",
    "gn:feature_code":"PPLA2",
    "gn:name":"Kelar",
    "gn:population":0,
    "gn:timezone":"Asia/Baghdad",
    "iso:country":"IQ",
    "name:ara_x_preferred":[
        "\u0643\u0644\u0627\u0631"
    ],
    "name:ckb_x_preferred":[
        "\u06a9\u06d5\u0644\u0627\u0631"
    ],
    "name:dsb_x_preferred":[
        "Kalar"
    ],
    "name:fas_x_preferred":[
        "\u06a9\u0644\u0627\u0631"
    ],
    "name:kur_x_preferred":[
        "Kelar"
    ],
    "name:kur_x_variant":[
        "\u0643\u06d5\u0644\u0627\u0631"
    ],
    "name:pol_x_preferred":[
        "Kalar"
    ],
    "name:rus_x_preferred":[
        "\u041a\u0435\u043b\u043b\u0430\u0440"
    ],
    "name:swe_x_preferred":[
        "Kalar"
    ],
    "name:und_x_variant":[
        "Klar",
        "Kall\u0101r",
        "Kal\u0101r"
    ],
    "name:urd_x_preferred":[
        "\u06a9\u0644\u0627\u0631"
    ],
    "wof:name":"Kelar",
    "wof:placetype":"locality"
},
  "geometry": {"coordinates":[45.31852,34.62805],"type":"Point"}
}