{
  "type": "Feature",
  "properties": {
    "gn:admin1_code":"8.0",
    "gn:admin2_code":"89569.0",
    "gn:asciiname":"Banik al 'Ulya",
    "gn:country_code":"IQ",
    "gn:dem":992,
    "gn:feature_class":"P",
    "gn:feature_code":"PPL",
    "gn:name":"B\u0101nik al \u2018Uly\u0101",
    "gn:population":0,
    "gn:timezone":"Asia/Baghdad",
    "iso:country":"IQ",
    "name:ara_x_preferred":[
        "\u0628\u0627\u0646\u0643 \u0627\u0644\u0639\u0644\u064a\u0627"
    ],
    "name:und_x_variant":[
        "B\u0101nik al \u2018Uly\u0101",
        "Bank Upper"
    ],
    "wof:name":"Banik al 'Ulya",
    "wof:placetype":"locality"
},
  "geometry": {"coordinates":[42.96888,37.22537],"type":"Point"}
}