{
  "type": "Feature",
  "properties": {
    "gn:admin1_code":"5.0",
    "gn:admin2_code":"98464.0",
    "gn:asciiname":"Qura Sardarawah",
    "gn:country_code":"IQ",
    "gn:dem":744,
    "gn:feature_class":"P",
    "gn:feature_code":"PPL",
    "gn:name":"Qur\u00e1 Sard\u0101r\u0101wah",
    "gn:population":0,
    "gn:timezone":"Asia/Baghdad",
    "iso:country":"IQ",
    "name:ara_x_preferred":[
        "\u0642\u0631\u0649 \u0633\u0631\u062f\u0627\u0631 \u0622\u0648\u0629"
    ],
    "name:und_x_variant":[
        "Qur\u00e1 Sard\u0101r \u0100wah",
        "Sarw\u0101r\u0101w\u0101"
    ],
    "wof:name":"Qura Sardarawah",
    "wof:placetype":"locality"
},
  "geometry": {"coordinates":[45.27269,35.5713],"type":"Point"}
}