{
  "type": "Feature",
  "properties": {
    "gn:admin1_code":"5.0",
    "gn:asciiname":"Naw Lanik",
    "gn:country_code":"IQ",
    "gn:dem":556,
    "gn:feature_class":"P",
    "gn:feature_code":"PPL",
    "gn:name":"Naw Lanik",
    "gn:population":0,
    "gn:timezone":"Asia/Baghdad",
    "iso:country":"IQ",
    "name:kur_x_preferred":[
        "Naw Lanik"
    ],
    "name:kur_x_variant":[
        "\u0646\u0627\u0648 \u0644\u0627\u0646\u0643"
    ],
    "name:und_x_variant":[
        "Naw Lank"
    ],
    "wof:name":"Naw Lanik",
    "wof:placetype":"locality"
},
  "geometry": {"coordinates":[44.69554,36.18277],"type":"Point"}
}