{
  "type": "Feature",
  "properties": {
    "gn:admin1_code":"6.0",
    "gn:admin2_code":"99358.0",
    "gn:asciiname":"Al'Id",
    "gn:country_code":"IQ",
    "gn:dem":26,
    "gn:feature_class":"P",
    "gn:feature_code":"PPL",
    "gn:name":"Al\u2018\u012ad",
    "gn:population":0,
    "gn:timezone":"Asia/Baghdad",
    "iso:country":"IQ",
    "name:ara_x_preferred":[
        "\u0627\u0644\u0639\u064a\u062f"
    ],
    "name:ara_x_variant":[
        "Al\u2018\u012ad"
    ],
    "wof:name":"Al'Id",
    "wof:placetype":"locality"
},
  "geometry": {"coordinates":[44.575,32.20709],"type":"Point"}
}