{
  "type": "Feature",
  "properties": {
    "gn:admin1_code":"6.0",
    "gn:admin2_code":"99358.0",
    "gn:asciiname":"Turki Hamad",
    "gn:country_code":"IQ",
    "gn:dem":26,
    "gn:feature_class":"P",
    "gn:feature_code":"PPL",
    "gn:name":"Turk\u012b \u1e28amad",
    "gn:population":0,
    "gn:timezone":"Asia/Baghdad",
    "iso:country":"IQ",
    "name:ara_x_preferred":[
        "\u062a\u0631\u0643\u064a \u062d\u0645\u062f"
    ],
    "name:und_x_variant":[
        "Turk\u012b \u1e28amad"
    ],
    "wof:name":"Turki Hamad",
    "wof:placetype":"locality"
},
  "geometry": {"coordinates":[44.53196,32.33502],"type":"Point"}
}