{
  "type": "Feature",
  "properties": {
    "gn:admin1_code":"6.0",
    "gn:admin2_code":"99358.0",
    "gn:asciiname":"Hassan",
    "gn:country_code":"IQ",
    "gn:dem":25,
    "gn:feature_class":"P",
    "gn:feature_code":"PPL",
    "gn:name":"\u1e28ass\u0101n",
    "gn:population":0,
    "gn:timezone":"Asia/Baghdad",
    "iso:country":"IQ",
    "name:ara_x_preferred":[
        "\u062d\u0633\u0627\u0646"
    ],
    "name:ara_x_variant":[
        "\u062d\u0633\u0646"
    ],
    "name:bih_x_preferred":[
        "\u0939\u093e\u0938\u0928"
    ],
    "name:cat_x_preferred":[
        "Hassan"
    ],
    "name:ceb_x_preferred":[
        "Hassan"
    ],
    "name:deu_x_preferred":[
        "Hassan"
    ],
    "name:fin_x_preferred":[
        "Hassan"
    ],
    "name:fra_x_preferred":[
        "Hassan"
    ],
    "name:heb_x_preferred":[
        "\u05d7\u05e1\u05df"
    ],
    "name:ita_x_preferred":[
        "Hassan"
    ],
    "name:jpn_x_preferred":[
        "\u30cf\u30b5\u30f3"
    ],
    "name:kaz_x_preferred":[
        "\u0425\u0430\u0441\u0430\u043d"
    ],
    "name:nld_x_preferred":[
        "Hassan"
    ],
    "name:oss_x_preferred":[
        "\u0425\u0430\u0441\u0430\u043d"
    ],
    "name:rus_x_preferred":[
        "\u0425\u0430\u0441\u0441\u0430\u043d"
    ],
    "name:spa_x_preferred":[
        "Hassan"
    ],
    "name:swe_x_preferred":[
        "Hassan"
    ],
    "name:ukr_x_preferred":[
        "\u0413\u0430\u0441\u0441\u0430\u043d"
    ],
    "name:und_x_variant":[
        "\u1e28asan",
        "\u1e28ass\u0101n"
    ],
    "wof:name":"Hassan",
    "wof:placetype":"locality"
},
  "geometry": {"coordinates":[44.65077,32.27107],"type":"Point"}
}