{
  "type": "Feature",
  "properties": {
    "gn:admin1_code":"11.0",
    "gn:admin2_code":"9166534.0",
    "gn:asciiname":"Piresal",
    "gn:country_code":"IQ",
    "gn:dem":452,
    "gn:feature_class":"P",
    "gn:feature_code":"PPL",
    "gn:name":"P\u00eeresa\u0142",
    "gn:population":0,
    "gn:timezone":"Asia/Baghdad",
    "iso:country":"IQ",
    "name:kur_x_preferred":[
        "P\u00eeresa\u0142"
    ],
    "name:kur_x_variant":[
        "\u067e\u064a\u0631\u06d5\u0633\u0627\u06b5"
    ],
    "name:und_x_variant":[
        "Pirasal"
    ],
    "wof:name":"Piresal",
    "wof:placetype":"locality"
},
  "geometry": {"coordinates":[44.15804,36.83673],"type":"Point"}
}