{
  "type": "Feature",
  "properties": {
    "gn:admin1_code":"3.0",
    "gn:admin2_code":"9166568.0",
    "gn:asciiname":"'Abd al Husayn ad Dukhan",
    "gn:country_code":"IQ",
    "gn:dem":14,
    "gn:feature_class":"P",
    "gn:feature_code":"PPL",
    "gn:name":"\u2018Abd al \u1e28usayn ad Dukh\u0101n",
    "gn:population":0,
    "gn:timezone":"Asia/Baghdad",
    "iso:country":"IQ",
    "name:ara_x_preferred":[
        "\u0639\u0628\u062f \u0627\u0644\u062d\u0633\u064a\u0646 \u0627\u0644\u062f\u062e\u0627\u0646"
    ],
    "name:und_x_variant":[
        "Ad Dukh\u0101n",
        "Aladd Kh\u0101n",
        "\u0627\u0644\u062f\u062e\u0627\u0646",
        "\u2018Abd al \u1e28usayn ad Dukh\u0101n"
    ],
    "wof:name":"'Abd al Husayn ad Dukhan",
    "wof:placetype":"locality"
},
  "geometry": {"coordinates":[45.29049000000001,31.55205],"type":"Point"}
}