{
  "type": "Feature",
  "properties": {
    "gn:admin1_code":"18.0",
    "gn:admin2_code":"91594.0",
    "gn:asciiname":"Ahmad Jasim Salman",
    "gn:country_code":"IQ",
    "gn:dem":98,
    "gn:feature_class":"P",
    "gn:feature_code":"PPL",
    "gn:name":"A\u1e29mad J\u0101sim Salm\u0101n",
    "gn:population":0,
    "gn:timezone":"Asia/Baghdad",
    "iso:country":"IQ",
    "name:ara_x_preferred":[
        "\u0627\u062d\u0645\u062f \u062c\u0627\u0633\u0645 \u0633\u0644\u0645\u0627\u0646"
    ],
    "name:und_x_variant":[
        "A\u1e29mad J\u0101sim Salm\u0101n"
    ],
    "wof:name":"Ahmad Jasim Salman",
    "wof:placetype":"locality"
},
  "geometry": {"coordinates":[43.52263,34.22816],"type":"Point"}
}