{
  "type": "Feature",
  "properties": {
    "gn:admin1_code":"10.0",
    "gn:admin2_code":"99170.0",
    "gn:asciiname":"Hasan al 'Abbas",
    "gn:country_code":"IQ",
    "gn:dem":51,
    "gn:feature_class":"P",
    "gn:feature_code":"PPL",
    "gn:name":"\u1e28asan al \u2018Abb\u0101s",
    "gn:population":0,
    "gn:timezone":"Asia/Baghdad",
    "iso:country":"IQ",
    "name:ara_x_preferred":[
        "\u062d\u0633\u0646 \u0627\u0644\u0639\u0628\u0627\u0633"
    ],
    "name:und_x_variant":[
        "\u1e28asan al \u2018Abb\u0101s"
    ],
    "wof:name":"Hasan al 'Abbas",
    "wof:placetype":"locality"
},
  "geometry": {"coordinates":[44.62288,33.91058],"type":"Point"}
}