{
  "type": "Feature",
  "properties": {
    "gn:admin1_code":"1.0",
    "gn:admin2_code":"9166579.0",
    "gn:asciiname":"Lumnah",
    "gn:country_code":"IQ",
    "gn:dem":76,
    "gn:feature_class":"P",
    "gn:feature_code":"PPL",
    "gn:name":"Lumnah",
    "gn:population":0,
    "gn:timezone":"Asia/Baghdad",
    "iso:country":"IQ",
    "name:ara_x_preferred":[
        "\u0644\u0645\u0646\u0629"
    ],
    "wof:name":"Lumnah",
    "wof:placetype":"locality"
},
  "geometry": {"coordinates":[42.58208,33.84394],"type":"Point"}
}