{
  "type": "Feature",
  "properties": {
    "gn:admin1_code":"11.0",
    "gn:admin2_code":"9166591.0",
    "gn:asciiname":"Soke",
    "gn:country_code":"IQ",
    "gn:dem":562,
    "gn:feature_class":"P",
    "gn:feature_code":"PPL",
    "gn:name":"Soke",
    "gn:population":0,
    "gn:timezone":"Asia/Baghdad",
    "iso:country":"IQ",
    "name:ara_x_preferred":[
        "\u0633\u0648\u0643\u0647"
    ],
    "name:ceb_x_preferred":[
        "Soke"
    ],
    "name:kur_x_preferred":[
        "Soke"
    ],
    "name:kur_x_variant":[
        "\u0633\u06c6\u0643\u0647",
        "Suke"
    ],
    "name:rus_x_preferred":[
        "\u0421\u043e\u043a\u044d"
    ],
    "name:swe_x_preferred":[
        "Soke"
    ],
    "name:und_x_variant":[
        "S\u016bke",
        "S\u016bkah",
        "Suka",
        "S\u016brk\u0101",
        "\u0633\u0648\u0631\u0643\u0627",
        "Soka",
        "Sawkah"
    ],
    "wof:name":"Soke",
    "wof:placetype":"locality"
},
  "geometry": {"coordinates":[44.02528,36.57298],"type":"Point"}
}