{
  "type": "Feature",
  "properties": {
    "gn:admin1_code":"1.0",
    "gn:admin2_code":"9166650.0",
    "gn:asciiname":"Al Jasibah",
    "gn:country_code":"IQ",
    "gn:dem":156,
    "gn:feature_class":"P",
    "gn:feature_code":"PPL",
    "gn:name":"Al Ja\u015f\u012bbah",
    "gn:population":0,
    "gn:timezone":"Asia/Baghdad",
    "iso:country":"IQ",
    "name:ara_x_preferred":[
        "\u0627\u0644\u062c\u0635\u064a\u0628\u0629"
    ],
    "name:und_x_variant":[
        "Al Ja\u015f\u012bbah"
    ],
    "wof:name":"Al Jasibah",
    "wof:placetype":"locality"
},
  "geometry": {"coordinates":[41.58931,34.44507],"type":"Point"}
}