{
  "type": "Feature",
  "properties": {
    "gn:admin1_code":"7.0",
    "gn:admin2_code":"99173.0",
    "gn:asciiname":"Hamid Rashid",
    "gn:country_code":"IQ",
    "gn:dem":37,
    "gn:feature_class":"P",
    "gn:feature_code":"PPL",
    "gn:name":"\u1e28am\u012bd Rash\u012bd",
    "gn:population":0,
    "gn:timezone":"Asia/Baghdad",
    "iso:country":"IQ",
    "name:ara_x_preferred":[
        "\u062d\u0645\u064a\u062f \u0631\u0634\u064a\u062f"
    ],
    "name:und_x_variant":[
        "\u1e28am\u012bd Rash\u012bd S\u0101lim",
        "\u062d\u0645\u064a\u062f \u0631\u0634\u064a\u062f \u0633\u0627\u0644\u0645",
        "\u1e28am\u012bd Rash\u012bd"
    ],
    "wof:name":"Hamid Rashid",
    "wof:placetype":"locality"
},
  "geometry": {"coordinates":[44.16685,33.56695999999999],"type":"Point"}
}