{
  "type": "Feature",
  "properties": {
    "gn:admin1_code":"5.0",
    "gn:admin2_code":"96204.0",
    "gn:asciiname":"Pay Ga",
    "gn:country_code":"IQ",
    "gn:dem":642,
    "gn:feature_class":"P",
    "gn:feature_code":"PPL",
    "gn:name":"Pay G\u0101",
    "gn:population":0,
    "gn:timezone":"Asia/Baghdad",
    "iso:country":"IQ",
    "name:ara_x_preferred":[
        "\u067e\u064a \u06af\u0627"
    ],
    "name:kur_x_preferred":[
        "P\u00eage"
    ],
    "name:kur_x_variant":[
        "P\u00ea Ga"
    ],
    "name:und_x_variant":[
        "Pay G\u0101",
        "Paga",
        "Y\u00e1 K\u0101",
        "Pega",
        "\u064a\u0649 \u0643\u0627",
        "\u067e\u06ce \u06af\u0627",
        "\u067e\u06ce\u06af\u0647"
    ],
    "wof:name":"Pay Ga",
    "wof:placetype":"locality"
},
  "geometry": {"coordinates":[46.06691,35.06216],"type":"Point"}
}