{
  "type": "Feature",
  "properties": {
    "gn:admin1_code":"14.0",
    "gn:admin2_code":"99097.0",
    "gn:asciiname":"Abu Zayd",
    "gn:cc2":"IQ",
    "gn:country_code":"IQ",
    "gn:dem":9,
    "gn:feature_class":"P",
    "gn:feature_code":"PPL",
    "gn:name":"Ab\u016b Zayd",
    "gn:population":0,
    "gn:timezone":"Asia/Baghdad",
    "iso:country":"IQ",
    "name:deu_x_preferred":[
        "Abu Zayd"
    ],
    "name:rus_x_preferred":[
        "\u0410\u0431\u0443 \u0417\u0435\u0439\u0434"
    ],
    "name:und_x_variant":[
        "Abu Zaid",
        "Ab\u016b Zayd"
    ],
    "wof:name":"Abu Zayd",
    "wof:placetype":"locality"
},
  "geometry": {"coordinates":[47.19972,31.63],"type":"Point"}
}