{
  "type": "Feature",
  "properties": {
    "gn:admin1_code":"9.0",
    "gn:admin2_code":"90509.0",
    "gn:asciiname":"Al Isma'il",
    "gn:country_code":"IQ",
    "gn:dem":2,
    "gn:feature_class":"P",
    "gn:feature_code":"PPL",
    "gn:name":"\u0100l Ism\u0101\u2018\u012bl",
    "gn:population":0,
    "gn:timezone":"Asia/Baghdad",
    "iso:country":"IQ",
    "name:ara_x_preferred":[
        "\u0622\u0644 \u0623\u0633\u0645\u0627\u0639\u064a\u0644"
    ],
    "name:ara_x_variant":[
        "\u0100l Ism\u0101\u2018\u012bl"
    ],
    "wof:name":"Al Isma'il",
    "wof:placetype":"locality"
},
  "geometry": {"coordinates":[46.70763,30.92012],"type":"Point"}
}