{
  "type": "Feature",
  "properties": {
    "gn:admin1_code":"13.0",
    "gn:admin2_code":"6770659.0",
    "gn:asciiname":"Muhammad Khalaf Husayn",
    "gn:country_code":"IQ",
    "gn:dem":194,
    "gn:feature_class":"P",
    "gn:feature_code":"PPL",
    "gn:name":"Mu\u1e29ammad Khalaf \u1e28usayn",
    "gn:population":0,
    "gn:timezone":"Asia/Baghdad",
    "iso:country":"IQ",
    "name:ara_x_preferred":[
        "\u0645\u062d\u0645\u062f \u062e\u0644\u0641 \u062d\u0633\u064a\u0646"
    ],
    "name:und_x_variant":[
        "Mu\u1e29ammad Khalaf \u1e28usayn"
    ],
    "wof:name":"Muhammad Khalaf Husayn",
    "wof:placetype":"locality"
},
  "geometry": {"coordinates":[43.82233,35.48385],"type":"Point"}
}