{
  "type": "Feature",
  "properties": {
    "gn:admin1_code":"6.0",
    "gn:admin2_code":"6818313.0",
    "gn:asciiname":"Sawadi",
    "gn:country_code":"IQ",
    "gn:dem":29,
    "gn:feature_class":"P",
    "gn:feature_code":"PPL",
    "gn:name":"Saw\u0101d\u012b",
    "gn:population":0,
    "gn:timezone":"Asia/Baghdad",
    "iso:country":"IQ",
    "name:und_x_variant":[
        "Saw\u0101d\u012b"
    ],
    "wof:name":"Sawadi",
    "wof:placetype":"locality"
},
  "geometry": {"coordinates":[44.61667,32.55],"type":"Point"}
}