{
  "type": "Feature",
  "properties": {
    "gn:admin1_code":"9.0",
    "gn:admin2_code":"98700.0",
    "gn:asciiname":"Al 'Ubayd",
    "gn:country_code":"IQ",
    "gn:dem":13,
    "gn:feature_class":"P",
    "gn:feature_code":"PPL",
    "gn:name":"\u0100l \u2018Ubayd",
    "gn:population":0,
    "gn:timezone":"Asia/Baghdad",
    "iso:country":"IQ",
    "name:ara_x_preferred":[
        "\u0622\u0644 \u0639\u0628\u064a\u062f"
    ],
    "name:und_x_variant":[
        "\u0100l \u2018Ubayd"
    ],
    "wof:name":"Al 'Ubayd",
    "wof:placetype":"locality"
},
  "geometry": {"coordinates":[46.0464,31.82853],"type":"Point"}
}