{
  "type": "Feature",
  "properties": {
    "gn:admin1_code":"16.0",
    "gn:admin2_code":"9166961.0",
    "gn:asciiname":"Salim Da'muth",
    "gn:country_code":"IQ",
    "gn:dem":28,
    "gn:feature_class":"P",
    "gn:feature_code":"PPL",
    "gn:name":"Sal\u012bm Da\u2018m\u016bth",
    "gn:population":0,
    "gn:timezone":"Asia/Baghdad",
    "iso:country":"IQ",
    "name:ara_x_preferred":[
        "\u0633\u0644\u064a\u0645 \u062f\u0639\u0645\u0648\u062b"
    ],
    "name:und_x_variant":[
        "Sal\u012bm Da\u2018m\u016bth"
    ],
    "wof:name":"Salim Da'muth",
    "wof:placetype":"locality"
},
  "geometry": {"coordinates":[44.87708,32.93688],"type":"Point"}
}