{
  "type": "Feature",
  "properties": {
    "gn:admin1_code":"6.0",
    "gn:admin2_code":"99358.0",
    "gn:asciiname":"Jazariyah",
    "gn:country_code":"IQ",
    "gn:dem":26,
    "gn:feature_class":"P",
    "gn:feature_code":"PPL",
    "gn:name":"Jazar\u012byah",
    "gn:population":0,
    "gn:timezone":"Asia/Baghdad",
    "iso:country":"IQ",
    "name:und_x_variant":[
        "Jazar\u012byah"
    ],
    "wof:name":"Jazariyah",
    "wof:placetype":"locality"
},
  "geometry": {"coordinates":[44.53333,32.23333],"type":"Point"}
}