{
  "type": "Feature",
  "properties": {
    "gn:admin1_code":"14.0",
    "gn:admin2_code":"99610.0",
    "gn:asciiname":"Salaf al Jadil",
    "gn:country_code":"IQ",
    "gn:dem":8,
    "gn:feature_class":"P",
    "gn:feature_code":"PPL",
    "gn:name":"Salaf al J\u0101dil",
    "gn:population":0,
    "gn:timezone":"Asia/Baghdad",
    "iso:country":"IQ",
    "name:ara_x_preferred":[
        "\u0633\u0644\u0641 \u0627\u0644\u062c\u0627\u062f\u0644"
    ],
    "name:und_x_variant":[
        "Al J\u0101dil",
        "Salaf al J\u0101dil"
    ],
    "wof:name":"Salaf al Jadil",
    "wof:placetype":"locality"
},
  "geometry": {"coordinates":[47.44302,31.79967000000001],"type":"Point"}
}