{
  "type": "Feature",
  "properties": {
    "gn:admin1_code":"6.0",
    "gn:admin2_code":"99348.0",
    "gn:asciiname":"Tumas ar Rahaj",
    "gn:country_code":"IQ",
    "gn:dem":37,
    "gn:feature_class":"P",
    "gn:feature_code":"PPL",
    "gn:name":"T\u016bm\u0101s ar Rah\u0101j",
    "gn:population":0,
    "gn:timezone":"Asia/Baghdad",
    "iso:country":"IQ",
    "name:und_x_variant":[
        "T\u016bm\u0101s ar Rah\u0101j"
    ],
    "wof:name":"Tumas ar Rahaj",
    "wof:placetype":"locality"
},
  "geometry": {"coordinates":[44.31028,32.37833],"type":"Point"}
}