{
  "type": "Feature",
  "properties": {
    "gn:admin1_code":"5.0",
    "gn:admin2_code":"97416.0",
    "gn:asciiname":"Mika'il Dartu Qala",
    "gn:country_code":"IQ",
    "gn:dem":473,
    "gn:feature_class":"P",
    "gn:feature_code":"PPL",
    "gn:name":"M\u012bk\u0101\u2019\u012bl D\u0101rt\u016b Qal\u0101",
    "gn:population":0,
    "gn:timezone":"Asia/Baghdad",
    "iso:country":"IQ",
    "name:ara_x_preferred":[
        "\u0645\u064a\u0643\u0627\u0626\u064a\u0644 \u062f\u0627\u0631\u062a\u0648 \u0642\u0644\u0627"
    ],
    "name:und_x_variant":[
        "M\u012bk\u0101\u2019\u012bl D\u0101rt\u016b Qal\u0101"
    ],
    "wof:name":"Mika'il Dartu Qala",
    "wof:placetype":"locality"
},
  "geometry": {"coordinates":[44.95749,35.23477000000001],"type":"Point"}
}