{
  "type": "Feature",
  "properties": {
    "gn:admin1_code":"1.0",
    "gn:admin2_code":"9166579.0",
    "gn:asciiname":"Musa Hammadi",
    "gn:country_code":"IQ",
    "gn:dem":104,
    "gn:feature_class":"P",
    "gn:feature_code":"PPL",
    "gn:name":"M\u016bs\u00e1 \u1e28amm\u0101d\u012b",
    "gn:population":0,
    "gn:timezone":"Asia/Baghdad",
    "iso:country":"IQ",
    "name:ara_x_preferred":[
        "\u0645\u0648\u0633\u0649 \u062d\u0645\u0627\u062f\u064a"
    ],
    "name:und_x_variant":[
        "M\u016bs\u00e1 \u1e28amm\u0101d\u012b"
    ],
    "wof:name":"Musa Hammadi",
    "wof:placetype":"locality"
},
  "geometry": {"coordinates":[42.94353,34.41827],"type":"Point"}
}