{
  "type": "Feature",
  "properties": {
    "gn:admin1_code":"18.0",
    "gn:admin2_code":"9167093.0",
    "gn:asciiname":"Hamid Ghafil 'Anad",
    "gn:country_code":"IQ",
    "gn:dem":79,
    "gn:feature_class":"P",
    "gn:feature_code":"PPL",
    "gn:name":"\u1e28am\u012bd Gh\u0101fil \u2018An\u0101d",
    "gn:population":0,
    "gn:timezone":"Asia/Baghdad",
    "iso:country":"IQ",
    "name:ara_x_preferred":[
        "\u062d\u0645\u064a\u062f \u063a\u0627\u0641\u0644 \u0639\u0646\u0627\u062f"
    ],
    "name:und_x_variant":[
        "\u1e28am\u012bd Gh\u0101fil \u2018An\u0101d"
    ],
    "wof:name":"Hamid Ghafil 'Anad",
    "wof:placetype":"locality"
},
  "geometry": {"coordinates":[43.67555,34.12522],"type":"Point"}
}