{
  "type": "Feature",
  "properties": {
    "gn:admin1_code":"15.0",
    "gn:admin2_code":"98820.0",
    "gn:asciiname":"Bishr Khara'ib",
    "gn:country_code":"IQ",
    "gn:dem":268,
    "gn:feature_class":"P",
    "gn:feature_code":"PPL",
    "gn:name":"Bishr Khar\u0101\u2019ib",
    "gn:population":0,
    "gn:timezone":"Asia/Baghdad",
    "iso:country":"IQ",
    "name:ara_x_preferred":[
        "\u0628\u0634\u0631 \u062e\u0631\u0627\u0626\u0628"
    ],
    "name:kur_x_preferred":[
        "Sh\u00eer\u00ee"
    ],
    "name:kur_x_variant":[
        "\u0634\u064a\u0631\u0649"
    ],
    "name:und_x_variant":[
        "Shiri",
        "Bishr Khar\u0101\u2019ib"
    ],
    "wof:name":"Bishr Khara'ib",
    "wof:placetype":"locality"
},
  "geometry": {"coordinates":[43.69131,36.30343],"type":"Point"}
}