{
  "type": "Feature",
  "properties": {
    "gn:admin1_code":"2.0",
    "gn:admin2_code":"99534.0",
    "gn:asciiname":"Rumaylah",
    "gn:cc2":"IQ",
    "gn:country_code":"IQ",
    "gn:dem":4,
    "gn:feature_class":"P",
    "gn:feature_code":"PPL",
    "gn:name":"Rumaylah",
    "gn:population":0,
    "gn:timezone":"Asia/Baghdad",
    "iso:country":"IQ",
    "name:und_x_variant":[
        "Rumaila",
        "Rumaylah"
    ],
    "wof:name":"Rumaylah",
    "wof:placetype":"locality"
},
  "geometry": {"coordinates":[47.61667,30.76667],"type":"Point"}
}