{
  "type": "Feature",
  "properties": {
    "gn:admin1_code":"15.0",
    "gn:admin2_code":"9166649.0",
    "gn:asciiname":"Ijhalah Gharbi",
    "gn:cc2":"IQ",
    "gn:country_code":"IQ",
    "gn:dem":170,
    "gn:feature_class":"P",
    "gn:feature_code":"PPL",
    "gn:name":"Ij\u1e29\u0101lah Gharb\u012b",
    "gn:population":0,
    "gn:timezone":"Asia/Baghdad",
    "iso:country":"IQ",
    "name:und_x_variant":[
        "Ijhala Gharb\u012b",
        "Ij\u1e29\u0101lah Gharb\u012b"
    ],
    "wof:name":"Ijhalah Gharbi",
    "wof:placetype":"locality"
},
  "geometry": {"coordinates":[43.28306,35.6975],"type":"Point"}
}