{
  "type": "Feature",
  "properties": {
    "gn:admin1_code":"7.0",
    "gn:admin2_code":"99173.0",
    "gn:asciiname":"Majid 'Anfis",
    "gn:country_code":"IQ",
    "gn:dem":37,
    "gn:feature_class":"P",
    "gn:feature_code":"PPL",
    "gn:name":"Maj\u012bd \u2018Anf\u012b\u015f",
    "gn:population":0,
    "gn:timezone":"Asia/Baghdad",
    "iso:country":"IQ",
    "name:ara_x_preferred":[
        "\u0645\u062c\u064a\u062f \u0639\u0646\u0641\u064a\u0635"
    ],
    "name:und_x_variant":[
        "Maj\u012bd \u2018Anf\u012b\u015f"
    ],
    "wof:name":"Majid 'Anfis",
    "wof:placetype":"locality"
},
  "geometry": {"coordinates":[44.1908,33.57649],"type":"Point"}
}