{
  "type": "Feature",
  "properties": {
    "gn:admin1_code":"14.0",
    "gn:admin2_code":"9166562.0",
    "gn:asciiname":"Al Bariyah",
    "gn:country_code":"IQ",
    "gn:dem":6,
    "gn:feature_class":"P",
    "gn:feature_code":"PPL",
    "gn:name":"Al Bar\u012byah",
    "gn:population":0,
    "gn:timezone":"Asia/Baghdad",
    "iso:country":"IQ",
    "name:ara_x_preferred":[
        "\u0627\u0644\u0628\u0631\u064a\u0651\u0629"
    ],
    "name:und_x_variant":[
        "Al Bar\u012byah"
    ],
    "wof:name":"Al Bariyah",
    "wof:placetype":"locality"
},
  "geometry": {"coordinates":[46.98673,31.48406],"type":"Point"}
}