{
  "type": "Feature",
  "properties": {
    "gn:admin1_code":"2.0",
    "gn:admin2_code":"100049.0",
    "gn:asciiname":"Matuh",
    "gn:country_code":"IQ",
    "gn:dem":2,
    "gn:feature_class":"P",
    "gn:feature_code":"PPL",
    "gn:name":"Ma\u0163\u016b\u1e29",
    "gn:population":0,
    "gn:timezone":"Asia/Baghdad",
    "iso:country":"IQ",
    "name:fas_x_preferred":[
        "\u0645\u0637\u0648\u062d"
    ],
    "name:fas_x_variant":[
        "Ma\u0163\u016b\u1e29"
    ],
    "wof:name":"Matuh",
    "wof:placetype":"locality"
},
  "geometry": {"coordinates":[48.1587,30.4146],"type":"Point"}
}