{
  "type": "Feature",
  "properties": {
    "gn:admin1_code":"18.0",
    "gn:admin2_code":"91594.0",
    "gn:asciiname":"Jasim Hasan Jasim",
    "gn:country_code":"IQ",
    "gn:dem":88,
    "gn:feature_class":"P",
    "gn:feature_code":"PPL",
    "gn:name":"J\u0101sim \u1e28asan J\u0101sim",
    "gn:population":0,
    "gn:timezone":"Asia/Baghdad",
    "iso:country":"IQ",
    "name:ara_x_preferred":[
        "\u062c\u0627\u0633\u0645 \u062d\u0633\u0646 \u062c\u0627\u0633\u0645"
    ],
    "name:und_x_variant":[
        "J\u0101sim \u1e28asan J\u0101sim"
    ],
    "wof:name":"Jasim Hasan Jasim",
    "wof:placetype":"locality"
},
  "geometry": {"coordinates":[43.61052,34.22454],"type":"Point"}
}