{
  "type": "Feature",
  "properties": {
    "gn:admin1_code":"10.0",
    "gn:admin2_code":"9166680.0",
    "gn:asciiname":"Qaryat al Kifah",
    "gn:country_code":"IQ",
    "gn:dem":78,
    "gn:feature_class":"P",
    "gn:feature_code":"PPL",
    "gn:name":"Qaryat al Kif\u0101\u1e29",
    "gn:population":0,
    "gn:timezone":"Asia/Baghdad",
    "iso:country":"IQ",
    "name:ara_x_preferred":[
        "\u0642\u0631\u064a\u0629 \u0627\u0644\u0643\u0641\u0627\u062d"
    ],
    "name:und_x_variant":[
        "Qaryat al Kif\u0101\u1e29"
    ],
    "wof:name":"Qaryat al Kifah",
    "wof:placetype":"locality"
},
  "geometry": {"coordinates":[45.28895,33.90373],"type":"Point"}
}