{
  "type": "Feature",
  "properties": {
    "gn:admin1_code":"13.0",
    "gn:admin2_code":"9166581.0",
    "gn:asciiname":"Jayman as Sughra",
    "gn:country_code":"IQ",
    "gn:dem":584,
    "gn:feature_class":"P",
    "gn:feature_code":"PPL",
    "gn:name":"Jayman a\u015f \u015eughr\u00e1",
    "gn:population":0,
    "gn:timezone":"Asia/Baghdad",
    "iso:country":"IQ",
    "name:ara_x_preferred":[
        "\u062c\u064a\u0645\u0646 \u0627\u0644\u0635\u063a\u0631\u0649"
    ],
    "name:und_x_variant":[
        "Jayman a\u015f \u015eughr\u00e1",
        "Jaman Buyuk",
        "Chayman a\u015f \u015eughr\u00e1",
        "\u0686\u064a\u0645\u0646 \u0627\u0644\u0635\u063a\u0631\u0649"
    ],
    "wof:name":"Jayman as Sughra",
    "wof:placetype":"locality"
},
  "geometry": {"coordinates":[44.56712,35.479],"type":"Point"}
}