{
  "type": "Feature",
  "properties": {
    "gn:admin1_code":"14.0",
    "gn:admin2_code":"99610.0",
    "gn:asciiname":"Salaf 'Awdah",
    "gn:country_code":"IQ",
    "gn:dem":33,
    "gn:feature_class":"P",
    "gn:feature_code":"PPL",
    "gn:name":"Salaf \u2018Awdah",
    "gn:population":0,
    "gn:timezone":"Asia/Baghdad",
    "iso:country":"IQ",
    "name:ara_x_preferred":[
        "\u0633\u0644\u0641 \u0639\u0648\u062f\u0647"
    ],
    "name:und_x_variant":[
        "Salaf \u2018Awdah"
    ],
    "wof:name":"Salaf 'Awdah",
    "wof:placetype":"locality"
},
  "geometry": {"coordinates":[47.59837,32.02764000000001],"type":"Point"}
}