{
  "type": "Feature",
  "properties": {
    "gn:admin1_code":"14.0",
    "gn:admin2_code":"9166562.0",
    "gn:asciiname":"Al 'Ariz",
    "gn:country_code":"IQ",
    "gn:dem":10,
    "gn:feature_class":"P",
    "gn:feature_code":"PPL",
    "gn:name":"Al \u2018Ar\u012bz",
    "gn:population":0,
    "gn:timezone":"Asia/Baghdad",
    "iso:country":"IQ",
    "name:ara_x_preferred":[
        "Al \u2018Ar\u012bz"
    ],
    "wof:name":"Al 'Ariz",
    "wof:placetype":"locality"
},
  "geometry": {"coordinates":[46.98333,31.55],"type":"Point"}
}