{
  "type": "Feature",
  "properties": {
    "gn:admin1_code":"6.0",
    "gn:admin2_code":"99358.0",
    "gn:asciiname":"Ishan Jihan",
    "gn:country_code":"IQ",
    "gn:dem":25,
    "gn:feature_class":"P",
    "gn:feature_code":"PPL",
    "gn:name":"\u012ash\u0101n J\u012b\u1e29\u0101n",
    "gn:population":0,
    "gn:timezone":"Asia/Baghdad",
    "iso:country":"IQ",
    "name:ara_x_preferred":[
        "\u0627\u064a\u0634\u0627\u0646 \u062c\u064a\u062d\u0627\u0646"
    ],
    "name:ara_x_variant":[
        "\u012ash\u0101n J\u012b\u1e29\u0101n"
    ],
    "wof:name":"Ishan Jihan",
    "wof:placetype":"locality"
},
  "geometry": {"coordinates":[44.92262,32.44285],"type":"Point"}
}