{
  "type": "Feature",
  "properties": {
    "gn:admin1_code":"4.0",
    "gn:admin2_code":"6850588.0",
    "gn:asciiname":"Salman an Najjar",
    "gn:cc2":"IQ",
    "gn:country_code":"IQ",
    "gn:dem":15,
    "gn:feature_class":"P",
    "gn:feature_code":"PPL",
    "gn:name":"Salm\u0101n an Najj\u0101r",
    "gn:population":0,
    "gn:timezone":"Asia/Baghdad",
    "iso:country":"IQ",
    "name:und_x_variant":[
        "Salman an Najj",
        "S\u0101lman an Naj\u0101r",
        "Salm\u0101n an Najj\u0101r"
    ],
    "wof:name":"Salman an Najjar",
    "wof:placetype":"locality"
},
  "geometry": {"coordinates":[44.81889,31.49278],"type":"Point"}
}