{
  "type": "Feature",
  "properties": {
    "gn:admin1_code":"9.0",
    "gn:admin2_code":"98700.0",
    "gn:asciiname":"'Uklat az Zarrak",
    "gn:country_code":"IQ",
    "gn:dem":12,
    "gn:feature_class":"P",
    "gn:feature_code":"PPL",
    "gn:name":"\u2018Uklat az Zarr\u0101k",
    "gn:population":0,
    "gn:timezone":"Asia/Baghdad",
    "iso:country":"IQ",
    "name:ara_x_preferred":[
        "\u0639\u06a9\u0644\u0629 \u0627\u0644\u0632\u0631\u0627\u0643"
    ],
    "name:und_x_variant":[
        "\u2018Uklat az Zarr\u0101k"
    ],
    "wof:name":"'Uklat az Zarrak",
    "wof:placetype":"locality"
},
  "geometry": {"coordinates":[46.04035,31.67542000000001],"type":"Point"}
}