{
  "type": "Feature",
  "properties": {
    "gn:admin1_code":"15.0",
    "gn:admin2_code":"9166608.0",
    "gn:asciiname":"Athari al Mushayrifah",
    "gn:country_code":"IQ",
    "gn:dem":313,
    "gn:feature_class":"P",
    "gn:feature_code":"PPL",
    "gn:name":"Athar\u012b al Mushayrifah",
    "gn:population":0,
    "gn:timezone":"Asia/Baghdad",
    "iso:country":"IQ",
    "name:ara_x_preferred":[
        "\u0627\u062b\u0631\u064a \u0627\u0644\u0645\u0634\u064a\u0631\u0641\u0647"
    ],
    "name:und_x_variant":[
        "Athar\u012b al Mushayrifah"
    ],
    "wof:name":"Athari al Mushayrifah",
    "wof:placetype":"locality"
},
  "geometry": {"coordinates":[42.05109,35.9609],"type":"Point"}
}