{
  "type": "Feature",
  "properties": {
    "gn:admin1_code":"5.0",
    "gn:admin2_code":"9166600.0",
    "gn:asciiname":"Ayaquwah Kusa",
    "gn:country_code":"IQ",
    "gn:dem":728,
    "gn:feature_class":"P",
    "gn:feature_code":"PPL",
    "gn:name":"Ay\u0101quwah K\u016bs\u0101",
    "gn:population":0,
    "gn:timezone":"Asia/Baghdad",
    "iso:country":"IQ",
    "name:ara_x_preferred":[
        "\u0627\u064a\u0627\u0642\u0648\u0629 \u0643\u0648\u0633\u0627"
    ],
    "name:kur_x_preferred":[
        "Yaqwe Kose"
    ],
    "name:kur_x_variant":[
        "\u064a\u0627\u0642\u0648\u06d5 \u0643\u06c6\u0633\u06d5"
    ],
    "name:und_x_variant":[
        "Ay\u0101quwah K\u016bs\u0101",
        "Y\u0101quwah K\u016bs\u0101",
        "Yaqua Kosa",
        "\u064a\u0627\u0642\u0648\u0647 \u0643\u0648\u0633\u0627"
    ],
    "wof:name":"Ayaquwah Kusa",
    "wof:placetype":"locality"
},
  "geometry": {"coordinates":[45.41162,35.02563],"type":"Point"}
}