{
  "type": "Feature",
  "properties": {
    "gn:admin1_code":"10.0",
    "gn:admin2_code":"99170.0",
    "gn:asciiname":"Dur Muwazafi Mazra'at an Nay",
    "gn:country_code":"IQ",
    "gn:dem":55,
    "gn:feature_class":"P",
    "gn:feature_code":"PPL",
    "gn:name":"D\u016br Muwaz\u0327af\u012b Mazra\u2018at an N\u0101y",
    "gn:population":0,
    "gn:timezone":"Asia/Baghdad",
    "iso:country":"IQ",
    "name:ara_x_preferred":[
        "\u062f\u0648\u0631 \u0645\u0648\u0638\u0641\u064a \u0645\u0632\u0631\u0639\u0629 \u0627\u0644\u0646\u0627\u064a"
    ],
    "name:und_x_variant":[
        "D\u016br Muwaz\u0327af\u012b Mazra\u2018at an N\u0101y"
    ],
    "wof:name":"Dur Muwazafi Mazra'at an Nay",
    "wof:placetype":"locality"
},
  "geometry": {"coordinates":[44.42878,34.01318],"type":"Point"}
}