{
  "type": "Feature",
  "properties": {
    "gn:admin1_code":"7.0",
    "gn:admin2_code":"9166569.0",
    "gn:asciiname":"'Ubayd al Mansi",
    "gn:country_code":"IQ",
    "gn:dem":39,
    "gn:feature_class":"P",
    "gn:feature_code":"PPL",
    "gn:name":"\u2018Ubayd al Mans\u012b",
    "gn:population":0,
    "gn:timezone":"Asia/Baghdad",
    "iso:country":"IQ",
    "name:ara_x_preferred":[
        "\u0639\u0628\u064a\u062f \u0627\u0644\u0645\u0646\u0633\u064a"
    ],
    "name:und_x_variant":[
        "\u2018Ubayd al Mans\u012b"
    ],
    "wof:name":"'Ubayd al Mansi",
    "wof:placetype":"locality"
},
  "geometry": {"coordinates":[44.26593,33.69835],"type":"Point"}
}