{
  "type": "Feature",
  "properties": {
    "gn:admin1_code":"5.0",
    "gn:admin2_code":"98464.0",
    "gn:asciiname":"Sawlah",
    "gn:country_code":"IQ",
    "gn:dem":803,
    "gn:feature_class":"P",
    "gn:feature_code":"PPL",
    "gn:name":"Sawlah",
    "gn:population":0,
    "gn:timezone":"Asia/Baghdad",
    "iso:country":"IQ",
    "name:ara_x_preferred":[
        "\u0633\u0648\u0644\u0629"
    ],
    "name:kur_x_preferred":[
        "So\u0142ey Sh\u00eax Qadr"
    ],
    "name:kur_x_variant":[
        "So\u0142e",
        "\u0633\u06c6\u06b5\u06d5\u0649 \u0634\u06ce\u062e \u0642\u0627\u062f\u0631",
        "\u0633\u06c6\u06b5\u06d5"
    ],
    "name:und_x_variant":[
        "S\u014dla",
        "Solia",
        "Sawlah",
        "Solla"
    ],
    "wof:name":"Sawlah",
    "wof:placetype":"locality"
},
  "geometry": {"coordinates":[45.22728,35.46148],"type":"Point"}
}