{
  "type": "Feature",
  "properties": {
    "gn:admin1_code":"5.0",
    "gn:admin2_code":"91176.0",
    "gn:asciiname":"'Isaway 'Ulya",
    "gn:country_code":"IQ",
    "gn:dem":907,
    "gn:feature_class":"P",
    "gn:feature_code":"PPL",
    "gn:name":"\u2018\u012as\u0101way \u2018Uly\u0101",
    "gn:population":0,
    "gn:timezone":"Asia/Baghdad",
    "iso:country":"IQ",
    "name:ara_x_preferred":[
        "\u0639\u064a\u0633\u0627\u0648\u064a \u0639\u0644\u064a\u0627"
    ],
    "name:kur_x_preferred":[
        "\u2018\u00cesawa"
    ],
    "name:kur_x_variant":[
        "\u0639\u064a\u0633\u0627\u0648\u0627"
    ],
    "name:und_x_variant":[
        "\u2018\u012as\u0101way \u2018Uly\u0101",
        "Isawa"
    ],
    "wof:name":"'Isaway 'Ulya",
    "wof:placetype":"locality"
},
  "geometry": {"coordinates":[45.40131,35.9509],"type":"Point"}
}