{
  "type": "Feature",
  "properties": {
    "gn:admin1_code":"15.0",
    "gn:admin2_code":"9166649.0",
    "gn:asciiname":"Qaryat 'Awsajah Gharbi",
    "gn:country_code":"IQ",
    "gn:dem":188,
    "gn:feature_class":"P",
    "gn:feature_code":"PPL",
    "gn:name":"Qaryat \u2018Awsajah Gharb\u012b",
    "gn:population":0,
    "gn:timezone":"Asia/Baghdad",
    "iso:country":"IQ",
    "name:ara_x_preferred":[
        "\u0642\u0631\u064a\u0629 \u0639\u0648\u0633\u062c\u0629 \u063a\u0631\u0628\u064a"
    ],
    "name:und_x_variant":[
        "Ausiyah",
        "\u2018Aws\u012byah al Gharb\u012byah",
        "\u2018Aws\u012byah",
        "Qaryat \u2018Awsajah Gharb\u012b"
    ],
    "wof:name":"Qaryat 'Awsajah Gharbi",
    "wof:placetype":"locality"
},
  "geometry": {"coordinates":[43.30929,35.78371],"type":"Point"}
}