{
  "type": "Feature",
  "properties": {
    "gn:admin1_code":"6.0",
    "gn:admin2_code":"99358.0",
    "gn:asciiname":"Hasan Khudayr",
    "gn:country_code":"IQ",
    "gn:dem":29,
    "gn:feature_class":"P",
    "gn:feature_code":"PPL",
    "gn:name":"\u1e28asan Khu\u1e11ayr",
    "gn:population":0,
    "gn:timezone":"Asia/Baghdad",
    "iso:country":"IQ",
    "name:ara_x_preferred":[
        "\u062d\u0633\u0646 \u062e\u0636\u064a\u0631"
    ],
    "name:und_x_variant":[
        "\u1e28asan Khu\u1e11ayr"
    ],
    "wof:name":"Hasan Khudayr",
    "wof:placetype":"locality"
},
  "geometry": {"coordinates":[44.77249000000001,32.31734],"type":"Point"}
}