{
  "type": "Feature",
  "properties": {
    "gn:admin1_code":"4.0",
    "gn:admin2_code":"6850588.0",
    "gn:asciiname":"Al Jadidah",
    "gn:country_code":"IQ",
    "gn:dem":20,
    "gn:feature_class":"P",
    "gn:feature_code":"PPL",
    "gn:name":"Al Jad\u012bdah",
    "gn:population":0,
    "gn:timezone":"Asia/Baghdad",
    "iso:country":"IQ",
    "name:ara_x_preferred":[
        "\u0627\u0644\u062c\u062f\u064a\u062f\u0629"
    ],
    "name:und_x_variant":[
        "Al Jad\u012bdah"
    ],
    "wof:name":"Al Jadidah",
    "wof:placetype":"locality"
},
  "geometry": {"coordinates":[44.9657,31.80214],"type":"Point"}
}