{
  "type": "Feature",
  "properties": {
    "gn:admin1_code":"15.0",
    "gn:admin2_code":"98820.0",
    "gn:asciiname":"Hishtikah",
    "gn:country_code":"IQ",
    "gn:dem":840,
    "gn:feature_class":"P",
    "gn:feature_code":"PPL",
    "gn:name":"H\u012bshtikah",
    "gn:population":0,
    "gn:timezone":"Asia/Baghdad",
    "iso:country":"IQ",
    "name:ara_x_preferred":[
        "\u0647\u064a\u0634\u062a\u0643\u0629"
    ],
    "name:kur_x_preferred":[
        "Hishtke"
    ],
    "name:kur_x_variant":[
        "\u0647\u0634\u062a\u0643\u06d5",
        "Heshtika",
        "\u0647\u06d5\u0634\u062a\u0643\u0627"
    ],
    "name:und_x_variant":[
        "Hishtkah",
        "Hishtka",
        "H\u012bshtikah",
        "Hashtka"
    ],
    "wof:name":"Hishtikah",
    "wof:placetype":"locality"
},
  "geometry": {"coordinates":[43.93032,36.78437],"type":"Point"}
}