{
  "type": "Feature",
  "properties": {
    "gn:admin1_code":"10.0",
    "gn:admin2_code":"99063.0",
    "gn:asciiname":"Qaryat al Ji'ar",
    "gn:country_code":"IQ",
    "gn:dem":61,
    "gn:feature_class":"P",
    "gn:feature_code":"PPL",
    "gn:name":"Qaryat al Ji\u2018\u0101r",
    "gn:population":0,
    "gn:timezone":"Asia/Baghdad",
    "iso:country":"IQ",
    "name:ara_x_preferred":[
        "\u0642\u0631\u064a\u0629 \u0627\u0644\u062c\u0639\u0627\u0631"
    ],
    "name:und_x_variant":[
        "Qaryat al Ji\u2018\u0101r"
    ],
    "wof:name":"Qaryat al Ji'ar",
    "wof:placetype":"locality"
},
  "geometry": {"coordinates":[44.93485,33.96572],"type":"Point"}
}