{
  "type": "Feature",
  "properties": {
    "gn:admin1_code":"10.0",
    "gn:admin2_code":"9166680.0",
    "gn:asciiname":"Anusayf al Jasim",
    "gn:country_code":"IQ",
    "gn:dem":39,
    "gn:feature_class":"P",
    "gn:feature_code":"PPL",
    "gn:name":"Anu\u015fayf al J\u0101sim",
    "gn:population":0,
    "gn:timezone":"Asia/Baghdad",
    "iso:country":"IQ",
    "name:ara_x_preferred":[
        "\u0627\u0646\u0635\u064a\u0641 \u0627\u0644\u062c\u0627\u0633\u0645"
    ],
    "name:und_x_variant":[
        "Anu\u015fayf al J\u0101sim"
    ],
    "wof:name":"Anusayf al Jasim",
    "wof:placetype":"locality"
},
  "geometry": {"coordinates":[45.40003,33.41905999999999],"type":"Point"}
}