{
  "type": "Feature",
  "properties": {
    "gn:admin1_code":"15.0",
    "gn:admin2_code":"9166618.0",
    "gn:asciiname":"Nizar Sayyid Muhammad",
    "gn:country_code":"IQ",
    "gn:dem":317,
    "gn:feature_class":"P",
    "gn:feature_code":"PPL",
    "gn:name":"Niz\u0101r Sayyid Mu\u1e29ammad",
    "gn:population":0,
    "gn:timezone":"Asia/Baghdad",
    "iso:country":"IQ",
    "name:ara_x_preferred":[
        "\u0646\u0632\u0627\u0631 \u0633\u064a\u062f \u0645\u062d\u0645\u062f"
    ],
    "name:kur_x_preferred":[
        "Nzar Seyd Mu\u1e27emed"
    ],
    "name:kur_x_variant":[
        "\u0646\u0632\u0627\u0631 \u0633\u06d5\u064a\u062f \u0645\u0648\u062d\u06d5\u0645\u06d5\u062f"
    ],
    "name:und_x_variant":[
        "Nizar Said Muhammed",
        "Niz\u0101r Sayyid Mu\u1e29ammad"
    ],
    "wof:name":"Nizar Sayyid Muhammad",
    "wof:placetype":"locality"
},
  "geometry": {"coordinates":[43.06304,36.54654],"type":"Point"}
}