{
  "type": "Feature",
  "properties": {
    "iso:country":"IQ",
    "ne:ADM0CAP":0.0,
    "ne:ADM0NAME":"Iraq",
    "ne:ADM0_A3":"IRQ",
    "ne:ADM1NAME":"Wasit",
    "ne:ADMIN1_COD":16,
    "ne:CAPALT":0,
    "ne:CHANGED":0,
    "ne:CHECKME":0,
    "ne:COMPARE":0,
    "ne:DIFFASCII":0,
    "ne:ELEVATION":0.0,
    "ne:FEATURECLA":"Admin-1 capital",
    "ne:FEATURE_CL":"P",
    "ne:FEATURE_CO":"PPL",
    "ne:GEONAMEID":99131,
    "ne:GEONAMESNO":"Geonames ascii name + lat.d + long.d matching.",
    "ne:GN_ASCII":"Al Kut",
    "ne:GN_POP":315162,
    "ne:GTOPO30":23.0,
    "ne:ISO_A2":"IQ",
    "ne:LABELRANK":5,
    "ne:LATITUDE":32.490716,
    "ne:LONGITUDE":45.83037,
    "ne:LS_MATCH":1,
    "ne:LS_NAME":"Al Kut",
    "ne:MAX_AREAKM":32.0,
    "ne:MAX_AREAMI":12.0,
    "ne:MAX_BBXMAX":45.858333,
    "ne:MAX_BBXMIN":45.783333,
    "ne:MAX_BBYMAX":32.55,
    "ne:MAX_BBYMIN":32.466667,
    "ne:MAX_NATSCA":20.0,
    "ne:MAX_PERKM":41.0,
    "ne:MAX_PERMI":26.0,
    "ne:MAX_POP10":321521,
    "ne:MAX_POP20":321521,
    "ne:MAX_POP300":0,
    "ne:MAX_POP310":0,
    "ne:MAX_POP50":0,
    "ne:MEAN_BBXC":45.822348,
    "ne:MEAN_BBYC":32.513258,
    "ne:MEGACITY":0,
    "ne:MIN_AREAKM":32.0,
    "ne:MIN_AREAMI":12.0,
    "ne:MIN_BBXMAX":45.858333,
    "ne:MIN_BBXMIN":45.783333,
    "ne:MIN_BBYMAX":32.55,
    "ne:MIN_BBYMIN":32.466667,
    "ne:MIN_PERKM":41.0,
    "ne:MIN_PERMI":26.0,
    "ne:NAME":"Al Kut",
    "ne:NAMEALT":"Al-Kut",
    "ne:NAMEASCII":"Al Kut",
    "ne:NAMEDIFF":0,
    "ne:NATSCALE":20,
    "ne:POP1950":0,
    "ne:POP1955":0,
    "ne:POP1960":0,
    "ne:POP1965":0,
    "ne:POP1970":0,
    "ne:POP1975":0,
    "ne:POP1980":0,
    "ne:POP1985":0,
    "ne:POP1990":0,
    "ne:POP1995":0,
    "ne:POP2000":0,
    "ne:POP2005":0,
    "ne:POP2010":0,
    "ne:POP2015":0,
    "ne:POP2020":0,
    "ne:POP2025":0,
    "ne:POP2050":0,
    "ne:POP_MAX":321521,
    "ne:POP_MIN":315162,
    "ne:POP_OTHER":0,
    "ne:RANK_MAX":10,
    "ne:RANK_MIN":10,
    "ne:SCALERANK":7,
    "ne:SOV0NAME":"Iraq",
    "ne:SOV_A3":"IRQ",
    "ne:TIMEZONE":"Asia/Baghdad",
    "ne:UN_FID":0,
    "ne:UN_LAT":0.0,
    "ne:UN_LONG":0.0,
    "ne:WORLDCITY":0,
    "ne:min_zoom":6.1,
    "wof:name":"Al Kut",
    "wof:placetype":"locality"
},
  "geometry": {"coordinates":[45.8303702380266,32.49071575828452],"type":"Point"}
}