{
  "type": "Feature",
  "properties": {
    "gn:admin1_code":"10.0",
    "gn:admin2_code":"9166680.0",
    "gn:asciiname":"Sulayman Al 'Udwan",
    "gn:country_code":"IQ",
    "gn:dem":36,
    "gn:feature_class":"P",
    "gn:feature_code":"PPL",
    "gn:name":"Sulaym\u0101n \u0100l \u2018Udw\u0101n",
    "gn:population":0,
    "gn:timezone":"Asia/Baghdad",
    "iso:country":"IQ",
    "name:ara_x_preferred":[
        "\u0633\u0644\u064a\u0645\u0627\u0646 \u0622\u0644 \u0639\u062f\u0648\u0627\u0646"
    ],
    "name:und_x_variant":[
        "Sulaym\u0101n \u0101l \u2018Adw\u0101n",
        "Sulaym\u0101n \u0100l \u2018Udw\u0101n"
    ],
    "wof:name":"Sulayman Al 'Udwan",
    "wof:placetype":"locality"
},
  "geometry": {"coordinates":[45.18359,33.59288],"type":"Point"}
}