{
  "type": "Feature",
  "properties": {
    "gn:admin1_code":"6.0",
    "gn:admin2_code":"99358.0",
    "gn:asciiname":"Sawadi Hassun",
    "gn:country_code":"IQ",
    "gn:dem":27,
    "gn:feature_class":"P",
    "gn:feature_code":"PPL",
    "gn:name":"Saw\u0101d\u012b \u1e28ass\u016bn",
    "gn:population":0,
    "gn:timezone":"Asia/Baghdad",
    "iso:country":"IQ",
    "name:ara_x_preferred":[
        "\u0633\u0648\u0627\u062f\u064a \u062d\u0633\u0648\u0646"
    ],
    "name:und_x_variant":[
        "Saw\u0101d\u012b \u1e28ass\u016bn"
    ],
    "wof:name":"Sawadi Hassun",
    "wof:placetype":"locality"
},
  "geometry": {"coordinates":[44.53562,32.22298],"type":"Point"}
}