{
  "type": "Feature",
  "properties": {
    "gn:admin1_code":"5.0",
    "gn:admin2_code":"97416.0",
    "gn:asciiname":"Drawzinah",
    "gn:country_code":"IQ",
    "gn:dem":667,
    "gn:feature_class":"P",
    "gn:feature_code":"PPL",
    "gn:name":"Drawzinah",
    "gn:population":0,
    "gn:timezone":"Asia/Baghdad",
    "iso:country":"IQ",
    "name:kur_x_preferred":[
        "Drozne"
    ],
    "name:kur_x_variant":[
        "\u062f\u0631\u06c6\u0632\u0646\u06d5"
    ],
    "name:und_x_variant":[
        "D\u0101r\u016bzahnah",
        "Drawzinah",
        "Daruzanah",
        "Drozna"
    ],
    "wof:name":"Drawzinah",
    "wof:placetype":"locality"
},
  "geometry": {"coordinates":[45.28333,35.11667],"type":"Point"}
}