{
  "type": "Feature",
  "properties": {
    "gn:admin1_code":"3.0",
    "gn:admin2_code":"9166568.0",
    "gn:asciiname":"Khara'ib Abu Tabikh",
    "gn:country_code":"IQ",
    "gn:dem":14,
    "gn:feature_class":"P",
    "gn:feature_code":"PPL",
    "gn:name":"Khar\u0101\u2019ib Ab\u016b Tab\u012bkh",
    "gn:population":0,
    "gn:timezone":"Asia/Baghdad",
    "iso:country":"IQ",
    "name:und_x_variant":[
        "Khar\u0101\u2019ib Ab\u016b Tab\u012bkh"
    ],
    "wof:name":"Khara'ib Abu Tabikh",
    "wof:placetype":"locality"
},
  "geometry": {"coordinates":[45.04083,31.43],"type":"Point"}
}