{
  "type": "Feature",
  "properties": {
    "gn:admin1_code":"5.0",
    "gn:admin2_code":"98464.0",
    "gn:asciiname":"Kharajiyah",
    "gn:country_code":"IQ",
    "gn:dem":829,
    "gn:feature_class":"P",
    "gn:feature_code":"PPL",
    "gn:name":"Khar\u0101j\u012byah",
    "gn:population":0,
    "gn:timezone":"Asia/Baghdad",
    "iso:country":"IQ",
    "name:ara_x_preferred":[
        "\u062e\u0631\u0627\u062c\u064a\u0629"
    ],
    "name:kur_x_preferred":[
        "Xeracyan"
    ],
    "name:kur_x_variant":[
        "\u062e\u06d5\u0631\u0627\u062c\u064a\u0627\u0646"
    ],
    "name:und_x_variant":[
        "Khar\u0101ji\u0101m",
        "Khar\u0101j\u012byah",
        "Khar\u0101ji\u0101n",
        "Kharajian",
        "Khrinij\u0101n"
    ],
    "wof:name":"Kharajiyah",
    "wof:placetype":"locality"
},
  "geometry": {"coordinates":[45.56707,35.46597],"type":"Point"}
}