{
  "type": "Feature",
  "properties": {
    "gn:admin1_code":"6.0",
    "gn:admin2_code":"6818313.0",
    "gn:asciiname":"Qaryat Rubar",
    "gn:country_code":"IQ",
    "gn:dem":31,
    "gn:feature_class":"P",
    "gn:feature_code":"PPL",
    "gn:name":"Qaryat Rub\u0101r",
    "gn:population":0,
    "gn:timezone":"Asia/Baghdad",
    "iso:country":"IQ",
    "name:ara_x_preferred":[
        "\u0642\u0631\u064a\u0629 \u0631\u0628\u0627\u0631"
    ],
    "name:und_x_variant":[
        "Qaryat Rub\u0101r"
    ],
    "wof:name":"Qaryat Rubar",
    "wof:placetype":"locality"
},
  "geometry": {"coordinates":[44.4201,32.78319],"type":"Point"}
}