{
  "type": "Feature",
  "properties": {
    "gn:admin1_code":"10.0",
    "gn:admin2_code":"9166680.0",
    "gn:asciiname":"Shamdalah",
    "gn:country_code":"IQ",
    "gn:dem":139,
    "gn:feature_class":"P",
    "gn:feature_code":"PPL",
    "gn:name":"Shamd\u0101lah",
    "gn:population":0,
    "gn:timezone":"Asia/Baghdad",
    "iso:country":"IQ",
    "name:ara_x_preferred":[
        "\u0634\u0645\u062f\u0627\u0644\u0629"
    ],
    "name:und_x_variant":[
        "Shamd\u0101lah"
    ],
    "wof:name":"Shamdalah",
    "wof:placetype":"locality"
},
  "geometry": {"coordinates":[45.56317,33.76638],"type":"Point"}
}