{
  "type": "Feature",
  "properties": {
    "gn:admin1_code":"18.0",
    "gn:admin2_code":"6783103.0",
    "gn:asciiname":"'Arab Muhammad al Hassan",
    "gn:country_code":"IQ",
    "gn:dem":82,
    "gn:feature_class":"P",
    "gn:feature_code":"PPL",
    "gn:name":"\u2018Arab Mu\u1e29ammad al \u1e28ass\u0101n",
    "gn:population":0,
    "gn:timezone":"Asia/Baghdad",
    "iso:country":"IQ",
    "name:ara_x_preferred":[
        "\u0639\u0631\u0628 \u0645\u062d\u0645\u062f \u0627\u0644\u062d\u0633\u0627\u0646"
    ],
    "name:und_x_variant":[
        "\u2018Arab Mu\u1e29ammad al \u1e28ass\u0101n"
    ],
    "wof:name":"'Arab Muhammad al Hassan",
    "wof:placetype":"locality"
},
  "geometry": {"coordinates":[44.35793,34.44306],"type":"Point"}
}