{
  "type": "Feature",
  "properties": {
    "gn:admin1_code":"14.0",
    "gn:admin2_code":"99305.0",
    "gn:asciiname":"Latif Qamandar",
    "gn:country_code":"IQ",
    "gn:dem":10,
    "gn:feature_class":"P",
    "gn:feature_code":"PPL",
    "gn:name":"La\u0163\u012bf Qamand\u0101r",
    "gn:population":0,
    "gn:timezone":"Asia/Baghdad",
    "iso:country":"IQ",
    "name:ara_x_preferred":[
        "\u0644\u0637\u064a\u0641 \u0642\u0645\u0646\u062f\u0627\u0631"
    ],
    "name:und_x_variant":[
        "La\u0163\u012bf Qamand\u0101r"
    ],
    "wof:name":"Latif Qamandar",
    "wof:placetype":"locality"
},
  "geometry": {"coordinates":[46.7073,32.28815],"type":"Point"}
}