{
  "type": "Feature",
  "properties": {
    "gn:admin1_code":"15.0",
    "gn:admin2_code":"98820.0",
    "gn:asciiname":"Giluk",
    "gn:country_code":"IQ",
    "gn:dem":600,
    "gn:feature_class":"P",
    "gn:feature_code":"PPL",
    "gn:name":"Gil\u016bk",
    "gn:population":0,
    "gn:timezone":"Asia/Baghdad",
    "iso:country":"IQ",
    "name:ara_x_preferred":[
        "Gl\u016bk"
    ],
    "name:ara_x_variant":[
        "Gil\u016bk",
        "\u06af\u0644\u0648\u0643"
    ],
    "name:kur_x_preferred":[
        "Kan\u00ee Di\u1e5f"
    ],
    "name:kur_x_variant":[
        "Giluk",
        "\u0643\u0627\u0646\u0649 \u062f\u0695",
        "Geluk Mam Gird",
        "\u06af\u06d5\u0644\u0648\u0643 \u0645\u0627\u0645 \u06af\u0631\u062f"
    ],
    "name:und_x_variant":[
        "Kil\u014dk",
        "\u06af\u0644\u0648\u0643",
        "Qaryat Kil\u016bk",
        "\u0642\u0631\u064a\u0629 \u0643\u0644\u0648\u0643",
        "Gl\u016bk",
        "Kani Dir",
        "Gluk"
    ],
    "wof:name":"Giluk",
    "wof:placetype":"locality"
},
  "geometry": {"coordinates":[44.03685,36.72675],"type":"Point"}
}