{
  "type": "Feature",
  "properties": {
    "gn:admin1_code":"18.0",
    "gn:admin2_code":"6872046.0",
    "gn:asciiname":"Mahmud Ibrahim",
    "gn:country_code":"IQ",
    "gn:dem":151,
    "gn:feature_class":"P",
    "gn:feature_code":"PPL",
    "gn:name":"Ma\u1e29m\u016bd Ibrah\u012bm",
    "gn:population":0,
    "gn:timezone":"Asia/Baghdad",
    "iso:country":"IQ",
    "name:ara_x_preferred":[
        "\u0645\u062d\u0645\u0648\u062f \u0627\u0628\u0631\u0647\u064a\u0645"
    ],
    "name:und_x_variant":[
        "Ma\u1e29m\u016bd Ibrah\u012bm"
    ],
    "wof:name":"Mahmud Ibrahim",
    "wof:placetype":"locality"
},
  "geometry": {"coordinates":[43.38553,35.1913],"type":"Point"}
}