{
  "type": "Feature",
  "properties": {
    "gn:admin1_code":"1.0",
    "gn:admin2_code":"9166576.0",
    "gn:asciiname":"Al Muhadah",
    "gn:country_code":"IQ",
    "gn:dem":173,
    "gn:feature_class":"P",
    "gn:feature_code":"PPL",
    "gn:name":"Al Mu\u1e29\u0101\u1e11ah",
    "gn:population":0,
    "gn:timezone":"Asia/Baghdad",
    "iso:country":"IQ",
    "name:ara_x_preferred":[
        "\u0627\u0644\u0645\u062d\u0627\u0636\u0629"
    ],
    "name:und_x_variant":[
        "Al Mu\u1e29\u0101\u1e11ah"
    ],
    "wof:name":"Al Muhadah",
    "wof:placetype":"locality"
},
  "geometry": {"coordinates":[41.2188,34.43065],"type":"Point"}
}