{
  "type": "Feature",
  "properties": {
    "gn:admin1_code":"5.0",
    "gn:admin2_code":"97416.0",
    "gn:asciiname":"Kalak Paynj",
    "gn:country_code":"IQ",
    "gn:dem":657,
    "gn:feature_class":"P",
    "gn:feature_code":"PPL",
    "gn:name":"Kalak Paynj",
    "gn:population":0,
    "gn:timezone":"Asia/Baghdad",
    "iso:country":"IQ",
    "name:ara_x_preferred":[
        "\u0643\u0644\u0643 \u067e\u064a\u0646\u062c"
    ],
    "name:und_x_variant":[
        "Kalak Banj",
        "\u0643\u0644\u0643 \u0628\u0646\u062c"
    ],
    "wof:name":"Kalak Paynj",
    "wof:placetype":"locality"
},
  "geometry": {"coordinates":[45.22522,35.15204],"type":"Point"}
}