{
  "type": "Feature",
  "properties": {
    "gn:admin1_code":"13.0",
    "gn:asciiname":"Qaryat Tall al Ajwad",
    "gn:country_code":"IQ",
    "gn:dem":184,
    "gn:feature_class":"P",
    "gn:feature_code":"PPL",
    "gn:name":"Qaryat Tall al Ajwad",
    "gn:population":0,
    "gn:timezone":"Asia/Baghdad",
    "iso:country":"IQ",
    "name:ara_x_preferred":[
        "\u0642\u0631\u064a\u0629 \u062a\u0644 \u0627\u0644\u0627\u062c\u0648\u062f"
    ],
    "name:ara_x_variant":[
        "\u062a\u0644 \u0627\u0644\u0633\u0645\u0631"
    ],
    "name:und_x_variant":[
        "\u015eal\u012b\u1e29",
        "Qaryat Tall al Ajwad",
        "Tall as Sumar"
    ],
    "wof:name":"Qaryat Tall al Ajwad",
    "wof:placetype":"locality"
},
  "geometry": {"coordinates":[43.58818,35.46657000000001],"type":"Point"}
}