{
  "type": "Feature",
  "properties": {
    "gn:admin1_code":"5.0",
    "gn:admin2_code":"97416.0",
    "gn:asciiname":"'Askar",
    "gn:country_code":"IQ",
    "gn:dem":588,
    "gn:feature_class":"P",
    "gn:feature_code":"PPL",
    "gn:name":"\u2018Askar",
    "gn:population":0,
    "gn:timezone":"Asia/Baghdad",
    "iso:country":"IQ",
    "name:ara_x_preferred":[
        "\u0639\u0633\u0643\u0631"
    ],
    "name:und_x_variant":[
        "\u2018Askar"
    ],
    "wof:name":"'Askar",
    "wof:placetype":"locality"
},
  "geometry": {"coordinates":[44.91096,35.82745],"type":"Point"}
}