{
  "type": "Feature",
  "properties": {
    "gn:admin1_code":"6.0",
    "gn:admin2_code":"6818313.0",
    "gn:asciiname":"'Arab Khudayr an Nasar",
    "gn:country_code":"IQ",
    "gn:dem":31,
    "gn:feature_class":"P",
    "gn:feature_code":"PPL",
    "gn:name":"\u2018Arab Khu\u1e11ayr an Na\u015f\u0101r",
    "gn:population":0,
    "gn:timezone":"Asia/Baghdad",
    "iso:country":"IQ",
    "name:ara_x_preferred":[
        "\u0639\u0631\u0628 \u062e\u0636\u064a\u0631 \u0627\u0644\u0646\u0635\u0627\u0631"
    ],
    "name:und_x_variant":[
        "\u2018Arab Khu\u1e11ayr an Na\u015f\u0101r"
    ],
    "wof:name":"'Arab Khudayr an Nasar",
    "wof:placetype":"locality"
},
  "geometry": {"coordinates":[44.29622,32.86529],"type":"Point"}
}