{
  "type": "Feature",
  "properties": {
    "gn:admin1_code":"12.0",
    "gn:admin2_code":"99345.0",
    "gn:asciiname":"Qaryat Nasir Agha",
    "gn:country_code":"IQ",
    "gn:dem":28,
    "gn:feature_class":"P",
    "gn:feature_code":"PPL",
    "gn:name":"Qaryat N\u0101\u015fir \u0100gh\u0101",
    "gn:population":0,
    "gn:timezone":"Asia/Baghdad",
    "iso:country":"IQ",
    "name:ara_x_preferred":[
        "\u0642\u0631\u064a\u0629 \u0646\u0627\u0635\u0631 \u0627\u063a\u0627"
    ],
    "name:und_x_variant":[
        "Qaryat N\u0101\u015fr \u0100gh\u0101",
        "Qaryat N\u0101\u015fir \u0100gh\u0101"
    ],
    "wof:name":"Qaryat Nasir Agha",
    "wof:placetype":"locality"
},
  "geometry": {"coordinates":[44.15649000000001,32.58848],"type":"Point"}
}