{
  "type": "Feature",
  "properties": {
    "gn:admin1_code":"15.0",
    "gn:admin2_code":"9166618.0",
    "gn:asciiname":"Qaryat 'Ammar Bayt",
    "gn:country_code":"IQ",
    "gn:dem":279,
    "gn:feature_class":"P",
    "gn:feature_code":"PPL",
    "gn:name":"Qaryat \u2018Amm\u0101r Bayt",
    "gn:population":0,
    "gn:timezone":"Asia/Baghdad",
    "iso:country":"IQ",
    "name:ara_x_preferred":[
        "\u0642\u0631\u064a\u0629 \u0639\u0645\u0627\u0631 \u0628\u064a\u062a"
    ],
    "name:kur_x_preferred":[
        "Xerab B\u00eat"
    ],
    "name:kur_x_variant":[
        "\u062e\u06d5\u0631\u0627\u0628 \u0628\u06ce\u062a"
    ],
    "name:und_x_variant":[
        "Kharab Bet",
        "Qaryat \u2018Amm\u0101r Bayt"
    ],
    "wof:name":"Qaryat 'Ammar Bayt",
    "wof:placetype":"locality"
},
  "geometry": {"coordinates":[42.94837,36.53476],"type":"Point"}
}