{
  "type": "Feature",
  "properties": {
    "gn:admin1_code":"11.0",
    "gn:admin2_code":"95444.0",
    "gn:asciiname":"Chimkah",
    "gn:country_code":"IQ",
    "gn:dem":335,
    "gn:feature_class":"P",
    "gn:feature_code":"PPL",
    "gn:name":"Chimkah",
    "gn:population":0,
    "gn:timezone":"Asia/Baghdad",
    "iso:country":"IQ",
    "name:ara_x_preferred":[
        "\u0686\u0645\u0643\u0629"
    ],
    "name:kur_x_preferred":[
        "Chimke"
    ],
    "name:kur_x_variant":[
        "\u0686\u0645\u0643\u06d5"
    ],
    "name:und_x_variant":[
        "Jam\u012bkah",
        "Jimka",
        "Jimkah",
        "Chimka",
        "Chimkah"
    ],
    "wof:name":"Chimkah",
    "wof:placetype":"locality"
},
  "geometry": {"coordinates":[43.84256,36.14094],"type":"Point"}
}