{
  "type": "Feature",
  "properties": {
    "gn:admin1_code":"11.0",
    "gn:admin2_code":"9166534.0",
    "gn:asciiname":"Kolanok",
    "gn:country_code":"IQ",
    "gn:dem":1091,
    "gn:feature_class":"P",
    "gn:feature_code":"PPL",
    "gn:name":"Kolanok",
    "gn:population":0,
    "gn:timezone":"Asia/Baghdad",
    "iso:country":"IQ",
    "name:kur_x_preferred":[
        "Kolanok"
    ],
    "name:kur_x_variant":[
        "\u0643\u06c6\u0644\u0627\u0646\u06c6\u0643"
    ],
    "name:und_x_variant":[
        "Gulanok"
    ],
    "wof:name":"Kolanok",
    "wof:placetype":"locality"
},
  "geometry": {"coordinates":[44.1644,36.90322000000001],"type":"Point"}
}