{
  "type": "Feature",
  "properties": {
    "gn:admin1_code":"16.0",
    "gn:admin2_code":"9166961.0",
    "gn:asciiname":"Barhujah",
    "gn:country_code":"IQ",
    "gn:dem":24,
    "gn:feature_class":"P",
    "gn:feature_code":"PPL",
    "gn:name":"Barh\u016bjah",
    "gn:population":0,
    "gn:timezone":"Asia/Baghdad",
    "iso:country":"IQ",
    "name:ara_x_preferred":[
        "\u0628\u0631\u0647\u0648\u062c\u0647"
    ],
    "name:und_x_variant":[
        "Barh\u016bjah"
    ],
    "wof:name":"Barhujah",
    "wof:placetype":"locality"
},
  "geometry": {"coordinates":[45.37789,32.66044],"type":"Point"}
}