{
  "type": "Feature",
  "properties": {
    "gn:admin1_code":"8.0",
    "gn:admin2_code":"97269.0",
    "gn:asciiname":"Kirbitah",
    "gn:country_code":"IQ",
    "gn:dem":823,
    "gn:feature_class":"P",
    "gn:feature_code":"PPL",
    "gn:name":"K\u012brbitah",
    "gn:population":0,
    "gn:timezone":"Asia/Baghdad",
    "iso:country":"IQ",
    "name:ara_x_preferred":[
        "\u0643\u064a\u0631\u0628\u062a\u0629"
    ],
    "name:kur_x_preferred":[
        "G\u00eerbina"
    ],
    "name:kur_x_variant":[
        "\u06af\u064a\u0631\u0628\u0646\u0627",
        "Gir\u00ea Pit\u00ea",
        "\u06af\u0631\u06ce \u067e\u062a\u06ce"
    ],
    "name:und_x_variant":[
        "Gir\u0113pit\u012b",
        "K\u012brbitah",
        "Gre Pite",
        "Girbna",
        "Grepete"
    ],
    "wof:name":"Kirbitah",
    "wof:placetype":"locality"
},
  "geometry": {"coordinates":[43.06674,36.99416],"type":"Point"}
}