{
  "type": "Feature",
  "properties": {
    "gn:admin1_code":"13.0",
    "gn:admin2_code":"6770659.0",
    "gn:asciiname":"Qaryat as Sa'duniyah",
    "gn:country_code":"IQ",
    "gn:dem":182,
    "gn:feature_class":"P",
    "gn:feature_code":"PPL",
    "gn:name":"Qaryat as Sa\u2018d\u016bn\u012byah",
    "gn:population":0,
    "gn:timezone":"Asia/Baghdad",
    "iso:country":"IQ",
    "name:ara_x_preferred":[
        "\u0642\u0631\u064a\u0629 \u0627\u0644\u0633\u0639\u062f\u0648\u0646\u064a\u0629"
    ],
    "name:und_x_variant":[
        "Qaryat as Sa\u2018d\u016bn\u012byah"
    ],
    "wof:name":"Qaryat as Sa'duniyah",
    "wof:placetype":"locality"
},
  "geometry": {"coordinates":[43.89505,35.2086],"type":"Point"}
}