{
  "type": "Feature",
  "properties": {
    "gn:admin1_code":"6.0",
    "gn:admin2_code":"6818313.0",
    "gn:asciiname":"Qaryat Dabiyat al Imam",
    "gn:country_code":"IQ",
    "gn:dem":29,
    "gn:feature_class":"P",
    "gn:feature_code":"PPL",
    "gn:name":"Qaryat \u1e10\u0101b\u012byat al Im\u0101m",
    "gn:population":0,
    "gn:timezone":"Asia/Baghdad",
    "iso:country":"IQ",
    "name:ara_x_preferred":[
        "\u0642\u0631\u064a\u0629 \u0636\u0627\u0628\u064a\u0629 \u0627\u0644\u0627\u0645\u0627\u0645"
    ],
    "name:und_x_variant":[
        "Qaryat \u1e10\u0101b\u012byat al Im\u0101m"
    ],
    "wof:name":"Qaryat Dabiyat al Imam",
    "wof:placetype":"locality"
},
  "geometry": {"coordinates":[44.58849,32.79852],"type":"Point"}
}