{
  "type": "Feature",
  "properties": {
    "gn:admin1_code":"9.0",
    "gn:admin2_code":"98700.0",
    "gn:asciiname":"Ar Rifa'i",
    "gn:country_code":"IQ",
    "gn:dem":13,
    "gn:feature_class":"P",
    "gn:feature_code":"PPLA2",
    "gn:name":"Ar Rif\u0101\u2018\u012b",
    "gn:population":0,
    "gn:timezone":"Asia/Baghdad",
    "iso:country":"IQ",
    "name:ara_x_preferred":[
        "\u0627\u0644\u0631\u0641\u0627\u0639\u064a"
    ],
    "name:ara_x_variant":[
        "Ar Rif\u0101\u2018\u012b"
    ],
    "name:und_x_variant":[
        "Refai",
        "Al Karr\u0101d\u012b",
        "Karradi",
        "Al-Refai"
    ],
    "wof:name":"Ar Rifa'i",
    "wof:placetype":"locality"
},
  "geometry": {"coordinates":[46.10778,31.72079],"type":"Point"}
}