{
  "type": "Feature",
  "properties": {
    "gn:admin1_code":"5.0",
    "gn:admin2_code":"91176.0",
    "gn:asciiname":"Barah al Kubra",
    "gn:country_code":"IQ",
    "gn:dem":1463,
    "gn:feature_class":"P",
    "gn:feature_code":"PPL",
    "gn:name":"B\u0101rah al Kubr\u00e1",
    "gn:population":0,
    "gn:timezone":"Asia/Baghdad",
    "iso:country":"IQ",
    "name:ara_x_preferred":[
        "\u0628\u0627\u0631\u0647 \u0627\u0644\u0643\u0628\u0631\u0649"
    ],
    "name:fas_x_preferred":[
        "\u0628\u0627\u0631\u06af\u0648\u0631\u0647"
    ],
    "name:kur_x_preferred":[
        "Bar\u00ee Gewre"
    ],
    "name:kur_x_variant":[
        "\u0628\u0627\u0631\u0649 \u06af\u06d5\u0648\u0631\u06d5"
    ],
    "name:und_x_variant":[
        "B\u0101r\u012b K\u016brah",
        "B\u0101rah al Kubr\u00e1",
        "B\u0101re-\u012b Gawra",
        "Bary Gawra"
    ],
    "wof:name":"Barah al Kubra",
    "wof:placetype":"locality"
},
  "geometry": {"coordinates":[45.69334,35.86281],"type":"Point"}
}