{
  "type": "Feature",
  "properties": {
    "gn:admin1_code":"14.0",
    "gn:admin2_code":"99097.0",
    "gn:asciiname":"Salaf Faysal al Khalaf",
    "gn:country_code":"IQ",
    "gn:dem":8,
    "gn:feature_class":"P",
    "gn:feature_code":"PPL",
    "gn:name":"Salaf Fay\u015fal al Khalaf",
    "gn:population":0,
    "gn:timezone":"Asia/Baghdad",
    "iso:country":"IQ",
    "name:ara_x_preferred":[
        "\u0633\u0644\u0641 \u0641\u064a\u0635\u0644 \u0627\u0644\u062e\u0644\u0641"
    ],
    "name:und_x_variant":[
        "Fay\u015fal al Khal\u012bfah",
        "Faisal al Khal\u012bfa",
        "Fay\u015fal al Khalaf",
        "Salaf Fay\u015fal al Khalaf"
    ],
    "wof:name":"Salaf Faysal al Khalaf",
    "wof:placetype":"locality"
},
  "geometry": {"coordinates":[47.13661,31.64083],"type":"Point"}
}