{
  "type": "Feature",
  "properties": {
    "gn:admin1_code":"18.0",
    "gn:admin2_code":"6805736.0",
    "gn:asciiname":"'Arab Salih Muhammad",
    "gn:country_code":"IQ",
    "gn:dem":48,
    "gn:feature_class":"P",
    "gn:feature_code":"PPL",
    "gn:name":"\u2018Arab \u015e\u0101lih Mu\u1e29ammad",
    "gn:population":0,
    "gn:timezone":"Asia/Baghdad",
    "iso:country":"IQ",
    "name:ara_x_preferred":[
        "\u0639\u0631\u0628 \u0635\u0627\u0644\u062d \u0645\u062d\u0645\u062f"
    ],
    "name:und_x_variant":[
        "\u2018Arab \u015e\u0101lih Mu\u1e29ammad"
    ],
    "wof:name":"'Arab Salih Muhammad",
    "wof:placetype":"locality"
},
  "geometry": {"coordinates":[44.11977,33.99014],"type":"Point"}
}