{
  "type": "Feature",
  "properties": {
    "gn:admin1_code":"16.0",
    "gn:admin2_code":"98197.0",
    "gn:asciiname":"Shaykh Nuwayr",
    "gn:cc2":"IQ",
    "gn:country_code":"IQ",
    "gn:dem":15,
    "gn:feature_class":"P",
    "gn:feature_code":"PPL",
    "gn:name":"Shaykh Nuwayr",
    "gn:population":0,
    "gn:timezone":"Asia/Baghdad",
    "iso:country":"IQ",
    "name:und_x_variant":[
        "Shaikh Nuwair",
        "Shaykh Nuwayr"
    ],
    "wof:name":"Shaykh Nuwayr",
    "wof:placetype":"locality"
},
  "geometry": {"coordinates":[46.06667,32.65361],"type":"Point"}
}