{
  "type": "Feature",
  "properties": {
    "gn:admin1_code":"6.0",
    "gn:admin2_code":"6818313.0",
    "gn:asciiname":"Sabbar Salman",
    "gn:country_code":"IQ",
    "gn:dem":27,
    "gn:feature_class":"P",
    "gn:feature_code":"PPL",
    "gn:name":"\u015eabb\u0101r Salm\u0101n",
    "gn:population":0,
    "gn:timezone":"Asia/Baghdad",
    "iso:country":"IQ",
    "name:ara_x_preferred":[
        "\u0635\u0628\u0627\u0631 \u0633\u0644\u0645\u0627\u0646"
    ],
    "name:und_x_variant":[
        "\u015eabb\u0101r Salm\u0101n"
    ],
    "wof:name":"Sabbar Salman",
    "wof:placetype":"locality"
},
  "geometry": {"coordinates":[44.85029,32.6911],"type":"Point"}
}