{
  "type": "Feature",
  "properties": {
    "gn:admin1_code":"7.0",
    "gn:admin2_code":"99101.0",
    "gn:asciiname":"Khalaf Dawud",
    "gn:country_code":"IQ",
    "gn:dem":34,
    "gn:feature_class":"P",
    "gn:feature_code":"PPL",
    "gn:name":"Khalaf D\u0101wud",
    "gn:population":0,
    "gn:timezone":"Asia/Baghdad",
    "iso:country":"IQ",
    "name:ara_x_preferred":[
        "\u062e\u0644\u0641 \u062f\u0627\u0648\u062f"
    ],
    "name:und_x_variant":[
        "Khalaf D\u0101wud"
    ],
    "wof:name":"Khalaf Dawud",
    "wof:placetype":"locality"
},
  "geometry": {"coordinates":[44.48571,33.1536],"type":"Point"}
}