{
  "type": "Feature",
  "properties": {
    "gn:admin1_code":"14.0",
    "gn:admin2_code":"99097.0",
    "gn:asciiname":"Umm Durayj",
    "gn:cc2":"IQ",
    "gn:country_code":"IQ",
    "gn:dem":4,
    "gn:feature_class":"P",
    "gn:feature_code":"PPL",
    "gn:name":"Umm Durayj",
    "gn:population":0,
    "gn:timezone":"Asia/Baghdad",
    "iso:country":"IQ",
    "name:und_x_variant":[
        "Umm Idrich",
        "Umm Durayj"
    ],
    "wof:name":"Umm Durayj",
    "wof:placetype":"locality"
},
  "geometry": {"coordinates":[47.28333,31.38333],"type":"Point"}
}