{
  "type": "Feature",
  "properties": {
    "gn:admin1_code":"5.0",
    "gn:admin2_code":"9166596.0",
    "gn:asciiname":"Haji Awa",
    "gn:country_code":"IQ",
    "gn:dem":799,
    "gn:feature_class":"P",
    "gn:feature_code":"PPL",
    "gn:name":"\u1e28\u0101j\u012b \u0100w\u0101",
    "gn:population":0,
    "gn:timezone":"Asia/Baghdad",
    "iso:country":"IQ",
    "name:ara_x_preferred":[
        "\u062d\u0627\u062c\u064a \u0622\u0648\u0627"
    ],
    "name:und_x_variant":[
        "\u1e28\u0101jj\u012b \u0100w\u0101",
        "H\u0101j\u012b\u0101w\u0101"
    ],
    "wof:name":"Haji Awa",
    "wof:placetype":"locality"
},
  "geometry": {"coordinates":[45.10756,35.8266],"type":"Point"}
}