{
  "type": "Feature",
  "properties": {
    "gn:admin1_code":"5.0",
    "gn:admin2_code":"91176.0",
    "gn:asciiname":"Suwayralah",
    "gn:country_code":"IQ",
    "gn:dem":1129,
    "gn:feature_class":"P",
    "gn:feature_code":"PPL",
    "gn:name":"Suwayralah",
    "gn:population":0,
    "gn:timezone":"Asia/Baghdad",
    "iso:country":"IQ",
    "name:ara_x_preferred":[
        "\u0633\u0648\u064a\u0631\u0644\u0629"
    ],
    "name:kur_x_preferred":[
        "Sw\u00eare\u0142e"
    ],
    "name:kur_x_variant":[
        "\u0633\u0648\u06ce\u0631\u06d5\u06b5\u06d5"
    ],
    "name:und_x_variant":[
        "Swerala"
    ],
    "wof:name":"Suwayralah",
    "wof:placetype":"locality"
},
  "geometry": {"coordinates":[45.61809,35.65237],"type":"Point"}
}