{
  "type": "Feature",
  "properties": {
    "gn:admin1_code":"9.0",
    "gn:admin2_code":"98623.0",
    "gn:asciiname":"Sayyid 'Abd al Husayn",
    "gn:country_code":"IQ",
    "gn:dem":5,
    "gn:feature_class":"P",
    "gn:feature_code":"PPL",
    "gn:name":"Sayyid \u2018Abd al \u1e28usayn",
    "gn:population":0,
    "gn:timezone":"Asia/Baghdad",
    "iso:country":"IQ",
    "name:ara_x_preferred":[
        "\u0633\u064a\u062f \u0639\u0628\u062f \u0627\u0644\u062d\u0633\u064a\u0646"
    ],
    "name:und_x_variant":[
        "Sayyid \u2018Abd al \u1e28asan",
        "Saiyid Abd al Hasan",
        "\u2018Abd al \u1e28usayn",
        "Sayyid \u2018Abd al \u1e28usayn"
    ],
    "wof:name":"Sayyid 'Abd al Husayn",
    "wof:placetype":"locality"
},
  "geometry": {"coordinates":[46.50288,31.26708],"type":"Point"}
}