{
  "type": "Feature",
  "properties": {
    "gn:admin1_code":"4.0",
    "gn:admin2_code":"98634.0",
    "gn:asciiname":"Al Mutlak",
    "gn:country_code":"IQ",
    "gn:dem":19,
    "gn:feature_class":"P",
    "gn:feature_code":"PPL",
    "gn:name":"\u0100l Mu\u0163lak",
    "gn:population":0,
    "gn:timezone":"Asia/Baghdad",
    "iso:country":"IQ",
    "name:ara_x_preferred":[
        "\u0627\u0644 \u0645\u0637\u0644\u0643"
    ],
    "name:und_x_variant":[
        "\u0100l Mu\u0163lak"
    ],
    "wof:name":"Al Mutlak",
    "wof:placetype":"locality"
},
  "geometry": {"coordinates":[44.66847,31.71976],"type":"Point"}
}