{
  "type": "Feature",
  "properties": {
    "gn:admin1_code":"14.0",
    "gn:admin2_code":"9166557.0",
    "gn:asciiname":"'Arab al Fu'adiyah",
    "gn:country_code":"IQ",
    "gn:dem":7,
    "gn:feature_class":"P",
    "gn:feature_code":"PPL",
    "gn:name":"\u2018Arab al Fu\u2019\u0101d\u012byah",
    "gn:population":0,
    "gn:timezone":"Asia/Baghdad",
    "iso:country":"IQ",
    "name:und_x_variant":[
        "\u2018Arab al Fuw\u0101diya",
        "\u2018Arab al Fu\u2019\u0101d\u012byah"
    ],
    "wof:name":"'Arab al Fu'adiyah",
    "wof:placetype":"locality"
},
  "geometry": {"coordinates":[47.33333,31.71667],"type":"Point"}
}