{
  "type": "Feature",
  "properties": {
    "gn:admin1_code":"5.0",
    "gn:admin2_code":"9166594.0",
    "gn:asciiname":"Saytalan al 'Ulya",
    "gn:country_code":"IQ",
    "gn:dem":809,
    "gn:feature_class":"P",
    "gn:feature_code":"PPL",
    "gn:name":"Say\u0163al\u0101n al \u2018Uly\u0101",
    "gn:population":0,
    "gn:timezone":"Asia/Baghdad",
    "iso:country":"IQ",
    "name:ara_x_preferred":[
        "\u0633\u064a\u0637\u0644\u0627\u0646 \u0627\u0644\u0639\u0644\u064a\u0627"
    ],
    "name:kur_x_preferred":[
        "S\u00eatelan\u00ee Ser\u00fb"
    ],
    "name:kur_x_variant":[
        "S\u00eate\u0142an",
        "\u0633\u06ce\u062a\u06d5\u0644\u0627\u0646\u0649 \u0633\u06d5\u0631\u0648\u0648",
        "\u0633\u06ce\u062a\u06d5\u06b5\u0627\u0646"
    ],
    "name:und_x_variant":[
        "Say\u0163al\u0101n al \u2018Uly\u0101",
        "S\u0113tal\u0101n-i Zh\u016br\u016b",
        "Setalan"
    ],
    "wof:name":"Saytalan al 'Ulya",
    "wof:placetype":"locality"
},
  "geometry": {"coordinates":[45.5915,35.26475999999999],"type":"Point"}
}