{
  "type": "Feature",
  "properties": {
    "gn:admin1_code":"9.0",
    "gn:admin2_code":"98700.0",
    "gn:asciiname":"Qaryat Hamid",
    "gn:country_code":"IQ",
    "gn:dem":9,
    "gn:feature_class":"P",
    "gn:feature_code":"PPL",
    "gn:name":"Qaryat \u1e28am\u012bd",
    "gn:population":0,
    "gn:timezone":"Asia/Baghdad",
    "iso:country":"IQ",
    "name:ara_x_preferred":[
        "\u0642\u0631\u064a\u0629 \u062d\u0645\u064a\u062f"
    ],
    "name:und_x_variant":[
        "Qaryat \u1e28am\u012bd"
    ],
    "wof:name":"Qaryat Hamid",
    "wof:placetype":"locality"
},
  "geometry": {"coordinates":[46.13972,31.63538],"type":"Point"}
}