{
  "type": "Feature",
  "properties": {
    "gn:admin1_code":"3.0",
    "gn:admin2_code":"98532.0",
    "gn:asciiname":"Nazim",
    "gn:cc2":"IQ",
    "gn:country_code":"IQ",
    "gn:dem":9,
    "gn:feature_class":"P",
    "gn:feature_code":"PPL",
    "gn:name":"N\u0101z\u0327im",
    "gn:population":0,
    "gn:timezone":"Asia/Baghdad",
    "iso:country":"IQ",
    "name:ara_x_preferred":[
        "N\u0101z\u0327im"
    ],
    "name:und_x_variant":[
        "Nadhim"
    ],
    "wof:name":"Nazim",
    "wof:placetype":"locality"
},
  "geometry": {"coordinates":[45.33333,31.31667],"type":"Point"}
}