{
  "type": "Feature",
  "properties": {
    "gn:admin1_code":"9.0",
    "gn:admin2_code":"98623.0",
    "gn:asciiname":"Kalhah",
    "gn:country_code":"IQ",
    "gn:dem":8,
    "gn:feature_class":"P",
    "gn:feature_code":"PPL",
    "gn:name":"Kal\u1e29ah",
    "gn:population":0,
    "gn:timezone":"Asia/Baghdad",
    "iso:country":"IQ",
    "name:ara_x_preferred":[
        "\u0643\u0644\u062d\u0647"
    ],
    "name:und_x_variant":[
        "S\u0101kit Umm al Mushattat",
        "S\u0101kit",
        "S\u0101chit",
        "\u015eashid",
        "S\u0101jit",
        "Qahah",
        "Kal\u1e29ah"
    ],
    "wof:name":"Kalhah",
    "wof:placetype":"locality"
},
  "geometry": {"coordinates":[46.45269,31.41901],"type":"Point"}
}