{
  "type": "Feature",
  "properties": {
    "gn:admin1_code":"8.0",
    "gn:admin2_code":"89569.0",
    "gn:asciiname":"Terik 'Ereb",
    "gn:country_code":"IQ",
    "gn:dem":540,
    "gn:feature_class":"P",
    "gn:feature_code":"PPL",
    "gn:name":"T\u00earik \u2018Ereb",
    "gn:population":0,
    "gn:timezone":"Asia/Baghdad",
    "iso:country":"IQ",
    "name:ara_x_preferred":[
        "\u062a\u064a\u0631\u0643 \u0639\u0631\u0628"
    ],
    "name:kur_x_preferred":[
        "T\u00earik \u2018Ereb"
    ],
    "name:kur_x_variant":[
        "\u062a\u06ce\u0631\u0643 \u0639\u06d5\u0631\u06d5\u0628"
    ],
    "name:und_x_variant":[
        "Tayrik \u2018Arab",
        "T\u0113rik \u1e28asan",
        "Terk Arab",
        "Terik Arab"
    ],
    "wof:name":"Terik 'Ereb",
    "wof:placetype":"locality"
},
  "geometry": {"coordinates":[42.79974,37.12832],"type":"Point"}
}