{
  "type": "Feature",
  "properties": {
    "gn:admin1_code":"14.0",
    "gn:admin2_code":"99610.0",
    "gn:asciiname":"Salaf Muhammad Husayn",
    "gn:country_code":"IQ",
    "gn:dem":9,
    "gn:feature_class":"P",
    "gn:feature_code":"PPL",
    "gn:name":"Salaf Mu\u1e29ammad \u1e28usayn",
    "gn:population":0,
    "gn:timezone":"Asia/Baghdad",
    "iso:country":"IQ",
    "name:ara_x_preferred":[
        "\u0633\u0644\u0641 \u0645\u062d\u0645\u062f \u062d\u0633\u064a\u0646"
    ],
    "name:und_x_variant":[
        "Salaf Mu\u1e29ammad \u1e28usayn"
    ],
    "wof:name":"Salaf Muhammad Husayn",
    "wof:placetype":"locality"
},
  "geometry": {"coordinates":[46.92621,31.91414],"type":"Point"}
}