{
  "type": "Feature",
  "properties": {
    "gn:admin1_code":"10.0",
    "gn:admin2_code":"94590.0",
    "gn:asciiname":"Qaryat ar Rashad",
    "gn:country_code":"IQ",
    "gn:dem":56,
    "gn:feature_class":"P",
    "gn:feature_code":"PPL",
    "gn:name":"Qaryat ar Rash\u0101d",
    "gn:population":0,
    "gn:timezone":"Asia/Baghdad",
    "iso:country":"IQ",
    "name:ara_x_preferred":[
        "\u0642\u0631\u064a\u0629 \u0627\u0644\u0631\u0634\u0627\u062f"
    ],
    "name:und_x_variant":[
        "Mu\u1e29ammad \u1e28usayn Jaw\u0101d",
        "\u0645\u062d\u0645\u062f \u062d\u0633\u064a\u0646 \u062c\u0648\u0627\u062f",
        "Qaryat ar Rash\u0101d"
    ],
    "wof:name":"Qaryat ar Rashad",
    "wof:placetype":"locality"
},
  "geometry": {"coordinates":[45.02517,33.97490999999999],"type":"Point"}
}