{
  "type": "Feature",
  "properties": {
    "gn:admin1_code":"6.0",
    "gn:admin2_code":"99040.0",
    "gn:asciiname":"'Arab Fatah Kamar",
    "gn:country_code":"IQ",
    "gn:dem":35,
    "gn:feature_class":"P",
    "gn:feature_code":"PPL",
    "gn:name":"\u2018Arab Fat\u0101\u1e29 Kamar",
    "gn:population":0,
    "gn:timezone":"Asia/Baghdad",
    "iso:country":"IQ",
    "name:ara_x_preferred":[
        "\u0639\u0631\u0628 \u0641\u062a\u0627\u062d \u0643\u0645\u0631"
    ],
    "name:und_x_variant":[
        "\u2018Arab Fat\u0101\u1e29 Kamar"
    ],
    "wof:name":"'Arab Fatah Kamar",
    "wof:placetype":"locality"
},
  "geometry": {"coordinates":[44.36382,32.61283],"type":"Point"}
}