{
  "type": "Feature",
  "properties": {
    "gn:admin1_code":"10.0",
    "gn:admin2_code":"99063.0",
    "gn:asciiname":"Wasmi Muslih",
    "gn:country_code":"IQ",
    "gn:dem":60,
    "gn:feature_class":"P",
    "gn:feature_code":"PPL",
    "gn:name":"Wasm\u012b Mu\u015fli\u1e29",
    "gn:population":0,
    "gn:timezone":"Asia/Baghdad",
    "iso:country":"IQ",
    "name:ara_x_preferred":[
        "\u0648\u0633\u0645\u064a \u0645\u0635\u0644\u062d"
    ],
    "name:und_x_variant":[
        "Wasm\u012b Mu\u015fli\u1e29"
    ],
    "wof:name":"Wasmi Muslih",
    "wof:placetype":"locality"
},
  "geometry": {"coordinates":[44.92241,33.92106],"type":"Point"}
}