{
  "type": "Feature",
  "properties": {
    "gn:admin1_code":"13.0",
    "gn:admin2_code":"94786.0",
    "gn:asciiname":"Qarah Naw",
    "gn:country_code":"IQ",
    "gn:dem":399,
    "gn:feature_class":"P",
    "gn:feature_code":"PPL",
    "gn:name":"Qarah N\u0101w",
    "gn:population":0,
    "gn:timezone":"Asia/Baghdad",
    "iso:country":"IQ",
    "name:ara_x_preferred":[
        "\u0642\u0631\u0647 \u0646\u0627\u0648"
    ],
    "name:und_x_variant":[
        "Kar\u0101wah",
        "Qarah N\u0101w",
        "Karawa",
        "Qaran\u0101w"
    ],
    "wof:name":"Qarah Naw",
    "wof:placetype":"locality"
},
  "geometry": {"coordinates":[44.60009,35.86145],"type":"Point"}
}