{
  "type": "Feature",
  "properties": {
    "gn:admin1_code":"7.0",
    "gn:admin2_code":"99101.0",
    "gn:asciiname":"Qaryat Fuhayl Umm al Khayr",
    "gn:country_code":"IQ",
    "gn:dem":39,
    "gn:feature_class":"P",
    "gn:feature_code":"PPL",
    "gn:name":"Qaryat Fu\u1e29ayl Umm al Khayr",
    "gn:population":0,
    "gn:timezone":"Asia/Baghdad",
    "iso:country":"IQ",
    "name:ara_x_preferred":[
        "\u0642\u0631\u064a\u0629 \u0641\u062d\u064a\u0644 \u0627\u0645 \u0627\u0644\u062e\u064a\u0631"
    ],
    "name:und_x_variant":[
        "Qaryat Fu\u1e29ayl Umm al Khayr"
    ],
    "wof:name":"Qaryat Fuhayl Umm al Khayr",
    "wof:placetype":"locality"
},
  "geometry": {"coordinates":[44.17111,32.99444],"type":"Point"}
}