{
  "type": "Feature",
  "properties": {
    "gn:admin1_code":"18.0",
    "gn:admin2_code":"6872046.0",
    "gn:asciiname":"Shams Jamil",
    "gn:country_code":"IQ",
    "gn:dem":145,
    "gn:feature_class":"P",
    "gn:feature_code":"PPL",
    "gn:name":"Shams Jam\u012bl",
    "gn:population":0,
    "gn:timezone":"Asia/Baghdad",
    "iso:country":"IQ",
    "name:ara_x_preferred":[
        "\u0634\u0645\u0633 \u062c\u0645\u064a\u0644"
    ],
    "name:und_x_variant":[
        "Shams Jam\u012bl"
    ],
    "wof:name":"Shams Jamil",
    "wof:placetype":"locality"
},
  "geometry": {"coordinates":[43.3335,34.86013],"type":"Point"}
}