{
  "type": "Feature",
  "properties": {
    "gn:admin1_code":"7.0",
    "gn:admin2_code":"9166545.0",
    "gn:asciiname":"Salman 'Ali",
    "gn:country_code":"IQ",
    "gn:dem":38,
    "gn:feature_class":"P",
    "gn:feature_code":"PPL",
    "gn:name":"Salm\u0101n \u2018Al\u012b",
    "gn:population":0,
    "gn:timezone":"Asia/Baghdad",
    "iso:country":"IQ",
    "name:ara_x_preferred":[
        "\u0633\u0644\u0645\u0627\u0646 \u0639\u0644\u064a"
    ],
    "name:und_x_variant":[
        "Salm\u0101n \u2018Al\u012b"
    ],
    "wof:name":"Salman 'Ali",
    "wof:placetype":"locality"
},
  "geometry": {"coordinates":[44.4789,33.2027],"type":"Point"}
}