{
  "type": "Feature",
  "properties": {
    "gn:admin1_code":"7.0",
    "gn:admin2_code":"9166545.0",
    "gn:asciiname":"Shukur Husayn",
    "gn:country_code":"IQ",
    "gn:dem":33,
    "gn:feature_class":"P",
    "gn:feature_code":"PPL",
    "gn:name":"Shuk\u016br \u1e28usayn",
    "gn:population":0,
    "gn:timezone":"Asia/Baghdad",
    "iso:country":"IQ",
    "name:ara_x_preferred":[
        "\u0634\u0643\u0648\u0631 \u062d\u0633\u064a\u0646"
    ],
    "name:und_x_variant":[
        "Shuk\u016br \u1e28usayn"
    ],
    "wof:name":"Shukur Husayn",
    "wof:placetype":"locality"
},
  "geometry": {"coordinates":[44.27646,33.21944000000001],"type":"Point"}
}