{
  "type": "Feature",
  "properties": {
    "gn:admin1_code":"2.0",
    "gn:admin2_code":"98994.0",
    "gn:asciiname":"Al Uthaylat",
    "gn:cc2":"IQ",
    "gn:country_code":"IQ",
    "gn:dem":5,
    "gn:feature_class":"P",
    "gn:feature_code":"PPL",
    "gn:name":"Al U\u0163\u1e29ayl\u0101t",
    "gn:population":0,
    "gn:timezone":"Asia/Baghdad",
    "iso:country":"IQ",
    "name:und_x_variant":[
        "Al Ithsil\u0101t",
        "Al U\u0163\u1e29ayl\u0101t"
    ],
    "wof:name":"Al Uthaylat",
    "wof:placetype":"locality"
},
  "geometry": {"coordinates":[47.43944000000001,31.16944],"type":"Point"}
}