{
  "type": "Feature",
  "properties": {
    "gn:admin1_code":"4.0",
    "gn:asciiname":"Qaryat Al Fuqaytir",
    "gn:country_code":"IQ",
    "gn:dem":24,
    "gn:feature_class":"P",
    "gn:feature_code":"PPL",
    "gn:name":"Qaryat \u0100l Fuqay\u0163ir",
    "gn:population":0,
    "gn:timezone":"Asia/Baghdad",
    "iso:country":"IQ",
    "name:ara_x_preferred":[
        "\u0642\u0631\u064a\u0629 \u0622\u0644 \u0641\u0642\u064a\u0637\u0631"
    ],
    "name:und_x_variant":[
        "Qaryat \u0100l Fuqay\u0163ir"
    ],
    "wof:name":"Qaryat Al Fuqaytir",
    "wof:placetype":"locality"
},
  "geometry": {"coordinates":[44.66582,32.1461],"type":"Point"}
}