{
  "type": "Feature",
  "properties": {
    "gn:admin1_code":"6.0",
    "gn:admin2_code":"6818313.0",
    "gn:asciiname":"'Arab Nayif",
    "gn:country_code":"IQ",
    "gn:dem":28,
    "gn:feature_class":"P",
    "gn:feature_code":"PPL",
    "gn:name":"\u2018Arab N\u0101yif",
    "gn:population":0,
    "gn:timezone":"Asia/Baghdad",
    "iso:country":"IQ",
    "name:ara_x_preferred":[
        "\u0639\u0631\u0628 \u0646\u0627\u064a\u0641"
    ],
    "name:und_x_variant":[
        "\u2018Arab N\u0101yif"
    ],
    "wof:name":"'Arab Nayif",
    "wof:placetype":"locality"
},
  "geometry": {"coordinates":[44.74178,32.47859],"type":"Point"}
}