{
  "type": "Feature",
  "properties": {
    "gn:admin1_code":"13.0",
    "gn:admin2_code":"6770659.0",
    "gn:asciiname":"Qaryat Saray",
    "gn:country_code":"IQ",
    "gn:dem":177,
    "gn:feature_class":"P",
    "gn:feature_code":"PPL",
    "gn:name":"Qaryat Sar\u0101y",
    "gn:population":0,
    "gn:timezone":"Asia/Baghdad",
    "iso:country":"IQ",
    "name:ara_x_preferred":[
        "\u0642\u0631\u064a\u0629 \u0633\u0631\u0627\u064a"
    ],
    "name:und_x_variant":[
        "Qaryat Sar\u0101y"
    ],
    "wof:name":"Qaryat Saray",
    "wof:placetype":"locality"
},
  "geometry": {"coordinates":[43.75106,35.17416],"type":"Point"}
}