{
  "type": "Feature",
  "properties": {
    "gn:admin1_code":"1.0",
    "gn:admin2_code":"99455.0",
    "gn:asciiname":"Husayn 'Ali Hamud",
    "gn:country_code":"IQ",
    "gn:dem":34,
    "gn:feature_class":"P",
    "gn:feature_code":"PPL",
    "gn:name":"\u1e28usayn \u2018Al\u012b \u1e28am\u016bd",
    "gn:population":0,
    "gn:timezone":"Asia/Baghdad",
    "iso:country":"IQ",
    "name:ara_x_preferred":[
        "\u062d\u0633\u064a\u0646 \u0639\u0644\u064a \u062d\u0645\u0648\u062f"
    ],
    "name:und_x_variant":[
        "\u1e28usayn \u2018Al\u012b \u1e28am\u016bd"
    ],
    "wof:name":"Husayn 'Ali Hamud",
    "wof:placetype":"locality"
},
  "geometry": {"coordinates":[44.08463,33.50487],"type":"Point"}
}