{
  "type": "Feature",
  "properties": {
    "gn:admin1_code":"5.0",
    "gn:admin2_code":"9166600.0",
    "gn:asciiname":"Qal`at Tapzah",
    "gn:cc2":"IQ",
    "gn:country_code":"IQ",
    "gn:dem":640,
    "gn:feature_class":"P",
    "gn:feature_code":"PPL",
    "gn:name":"Qal`at Tapzah",
    "gn:population":0,
    "gn:timezone":"Asia/Baghdad",
    "iso:country":"IQ",
    "name:und_x_variant":[
        "Qal`a Tapza",
        "Qal`at \u0162abzah"
    ],
    "wof:name":"Qal`at Tapzah",
    "wof:placetype":"locality"
},
  "geometry": {"coordinates":[45.43333,34.98333],"type":"Point"}
}