{
  "type": "Feature",
  "properties": {
    "gn:admin1_code":"18.0",
    "gn:admin2_code":"6783103.0",
    "gn:asciiname":"'Abd ar Rahman Hamid",
    "gn:country_code":"IQ",
    "gn:dem":82,
    "gn:feature_class":"P",
    "gn:feature_code":"PPL",
    "gn:name":"\u2018Abd ar Ra\u1e29man \u1e28am\u012bd",
    "gn:population":0,
    "gn:timezone":"Asia/Baghdad",
    "iso:country":"IQ",
    "name:ara_x_preferred":[
        "\u0639\u0628\u062f \u0627\u0644\u0631\u062d\u0645\u0646 \u062d\u0645\u064a\u062f"
    ],
    "name:und_x_variant":[
        "\u2018Abd ar Ra\u1e29man \u1e28am\u012bd"
    ],
    "wof:name":"'Abd ar Rahman Hamid",
    "wof:placetype":"locality"
},
  "geometry": {"coordinates":[43.78898,34.35804],"type":"Point"}
}