{
  "type": "Feature",
  "properties": {
    "gn:admin1_code":"4.0",
    "gn:admin2_code":"99763.0",
    "gn:asciiname":"Tahir Mayi'",
    "gn:country_code":"IQ",
    "gn:dem":26,
    "gn:feature_class":"P",
    "gn:feature_code":"PPL",
    "gn:name":"\u0162\u0101hir M\u0101yi\u2018",
    "gn:population":0,
    "gn:timezone":"Asia/Baghdad",
    "iso:country":"IQ",
    "name:ara_x_preferred":[
        "\u0637\u0627\u0647\u0631 \u0645\u0627\u064a\u0639"
    ],
    "name:ara_x_variant":[
        "\u0162\u0101hir M\u0101yi\u2018"
    ],
    "wof:name":"Tahir Mayi'",
    "wof:placetype":"locality"
},
  "geometry": {"coordinates":[44.61131,32.09332],"type":"Point"}
}