{
  "type": "Feature",
  "properties": {
    "gn:admin1_code":"15.0",
    "gn:admin2_code":"99414.0",
    "gn:asciiname":"Tall ad Dabaghah",
    "gn:country_code":"IQ",
    "gn:dem":200,
    "gn:feature_class":"P",
    "gn:feature_code":"PPL",
    "gn:name":"Tall ad Dab\u0101ghah",
    "gn:population":0,
    "gn:timezone":"Asia/Baghdad",
    "iso:country":"IQ",
    "name:ara_x_preferred":[
        "\u062a\u0644 \u0627\u0644\u062f\u0628\u0627\u063a\u0629"
    ],
    "name:und_x_variant":[
        "Tall ad Dab\u0101ghah"
    ],
    "wof:name":"Tall ad Dabaghah",
    "wof:placetype":"locality"
},
  "geometry": {"coordinates":[42.53839,35.47876],"type":"Point"}
}