{
  "type": "Feature",
  "properties": {
    "gn:admin1_code":"14.0",
    "gn:admin2_code":"99097.0",
    "gn:asciiname":"'Ataq",
    "gn:country_code":"IQ",
    "gn:dem":11,
    "gn:feature_class":"P",
    "gn:feature_code":"PPL",
    "gn:name":"\u2018Ataq",
    "gn:population":0,
    "gn:timezone":"Asia/Baghdad",
    "iso:country":"IQ",
    "name:und_x_variant":[
        "\u2018Ataq"
    ],
    "wof:name":"'Ataq",
    "wof:placetype":"locality"
},
  "geometry": {"coordinates":[47.17167,31.67722],"type":"Point"}
}