{
  "type": "Feature",
  "properties": {
    "gn:admin1_code":"7.0",
    "gn:admin2_code":"99101.0",
    "gn:asciiname":"Nur Kati'",
    "gn:country_code":"IQ",
    "gn:dem":36,
    "gn:feature_class":"P",
    "gn:feature_code":"PPL",
    "gn:name":"N\u016br K\u0101\u0163i\u2018",
    "gn:population":0,
    "gn:timezone":"Asia/Baghdad",
    "iso:country":"IQ",
    "name:ara_x_preferred":[
        "\u0646\u0648\u0631 \u0643\u0627\u0637\u0639"
    ],
    "name:ara_x_variant":[
        "N\u016br K\u0101\u0163i\u2018"
    ],
    "wof:name":"Nur Kati'",
    "wof:placetype":"locality"
},
  "geometry": {"coordinates":[44.33761,32.98971],"type":"Point"}
}