{
  "type": "Feature",
  "properties": {
    "gn:admin1_code":"13.0",
    "gn:admin2_code":"9166581.0",
    "gn:asciiname":"`Uthman Lakah",
    "gn:country_code":"IQ",
    "gn:dem":631,
    "gn:feature_class":"P",
    "gn:feature_code":"PPL",
    "gn:name":"\u2018Uthm\u0101n Lakah",
    "gn:population":0,
    "gn:timezone":"Asia/Baghdad",
    "iso:country":"IQ",
    "name:ara_x_preferred":[
        "\u0639\u062b\u0645\u0627\u0646 \u0644\u0643\u0647"
    ],
    "name:und_x_variant":[
        "\u2018Uthm\u0101n Laka",
        "\u2018Uthm\u0101n Lah",
        "Uthm\u0101n La ah",
        "\u2018Uthm\u0101n L\u0101kah",
        "\u2018Uthm\u0101n Lakah"
    ],
    "wof:name":"`Uthman Lakah",
    "wof:placetype":"locality"
},
  "geometry": {"coordinates":[44.6869,35.36209],"type":"Point"}
}