{
  "type": "Feature",
  "properties": {
    "gn:admin1_code":"5.0",
    "gn:admin2_code":"91176.0",
    "gn:asciiname":"Darawiyah",
    "gn:country_code":"IQ",
    "gn:dem":1091,
    "gn:feature_class":"P",
    "gn:feature_code":"PPL",
    "gn:name":"Daraw\u012byah",
    "gn:population":0,
    "gn:timezone":"Asia/Baghdad",
    "iso:country":"IQ",
    "name:ara_x_preferred":[
        "\u062f\u0631\u0648\u064a\u0629"
    ],
    "name:kur_x_preferred":[
        "Derewye"
    ],
    "name:kur_x_variant":[
        "Der\u00fbye",
        "\u062f\u06d5\u0631\u06d5\u0648\u064a\u06d5",
        "\u062f\u06d5\u0631\u0648\u0648\u064a\u06d5"
    ],
    "name:und_x_variant":[
        "Daraw\u012byah",
        "Daraw\u012bya",
        "Darooya",
        "\u062f\u0631\u0648\u064a\u06d5"
    ],
    "wof:name":"Darawiyah",
    "wof:placetype":"locality"
},
  "geometry": {"coordinates":[45.75221,35.76279],"type":"Point"}
}