{
  "type": "Feature",
  "properties": {
    "gn:admin1_code":"7.0",
    "gn:admin2_code":"99101.0",
    "gn:asciiname":"Qaryat Ahmad as Salman",
    "gn:country_code":"IQ",
    "gn:dem":33,
    "gn:feature_class":"P",
    "gn:feature_code":"PPL",
    "gn:name":"Qaryat A\u1e29mad as Salm\u0101n",
    "gn:population":0,
    "gn:timezone":"Asia/Baghdad",
    "iso:country":"IQ",
    "name:ara_x_preferred":[
        "\u0642\u0631\u064a\u0629 \u0627\u062d\u0645\u062f \u0627\u0644\u0633\u0644\u0645\u0627\u0646"
    ],
    "name:und_x_variant":[
        "Qaryat A\u1e29mad as Salm\u0101n"
    ],
    "wof:name":"Qaryat Ahmad as Salman",
    "wof:placetype":"locality"
},
  "geometry": {"coordinates":[44.31009,33.20524],"type":"Point"}
}