{
  "type": "Feature",
  "properties": {
    "gn:admin1_code":"17.0",
    "gn:admin2_code":"9166629.0",
    "gn:asciiname":"Hamzat Muhammad",
    "gn:country_code":"IQ",
    "gn:dem":24,
    "gn:feature_class":"P",
    "gn:feature_code":"PPL",
    "gn:name":"\u1e28amzat Mu\u1e29ammad",
    "gn:population":0,
    "gn:timezone":"Asia/Baghdad",
    "iso:country":"IQ",
    "name:ara_x_preferred":[
        "\u062d\u0645\u0632\u0629 \u0645\u062d\u0645\u062f"
    ],
    "name:und_x_variant":[
        "\u1e28amzat Mu\u1e29ammad"
    ],
    "wof:name":"Hamzat Muhammad",
    "wof:placetype":"locality"
},
  "geometry": {"coordinates":[44.55351,32.14348],"type":"Point"}
}