{
  "type": "Feature",
  "properties": {
    "gn:admin1_code":"5.0",
    "gn:admin2_code":"91176.0",
    "gn:asciiname":"Shanakhsay",
    "gn:country_code":"IQ",
    "gn:dem":1081,
    "gn:feature_class":"P",
    "gn:feature_code":"PPL",
    "gn:name":"Sh\u0101n\u0101khsay",
    "gn:population":0,
    "gn:timezone":"Asia/Baghdad",
    "iso:country":"IQ",
    "name:ara_x_preferred":[
        "\u0634\u0627\u0646\u0627\u062e\u0633\u064a"
    ],
    "name:kur_x_preferred":[
        "Shanaxs\u00ea"
    ],
    "name:kur_x_variant":[
        "\u0634\u0627\u0646\u0627\u062e\u0633\u06ce"
    ],
    "name:und_x_variant":[
        "Sh\u0101n\u0101 Khas",
        "Sh\u0101nakhs\u0113",
        "Sh\u0101nakhsay",
        "\u0634\u0627\u0646\u062e\u0633\u064a",
        "Sh\u0101n\u0101khsa",
        "Sh\u0101n\u0101khsay",
        "\u0634\u0627\u0646\u0627\u062e\u0633\u064a",
        "Shanakhse"
    ],
    "wof:name":"Shanakhsay",
    "wof:placetype":"locality"
},
  "geometry": {"coordinates":[45.52146,35.97732],"type":"Point"}
}