{
  "type": "Feature",
  "properties": {
    "gn:admin1_code":"11.0",
    "gn:admin2_code":"9166586.0",
    "gn:asciiname":"Konakhan",
    "gn:country_code":"IQ",
    "gn:dem":1159,
    "gn:feature_class":"P",
    "gn:feature_code":"PPL",
    "gn:name":"K\u014dnakh\u0101n",
    "gn:population":0,
    "gn:timezone":"Asia/Baghdad",
    "iso:country":"IQ",
    "wof:name":"Konakhan",
    "wof:placetype":"locality"
},
  "geometry": {"coordinates":[44.88389,36.63806],"type":"Point"}
}