{
  "type": "Feature",
  "properties": {
    "gn:admin1_code":"5.0",
    "gn:admin2_code":"9166684.0",
    "gn:asciiname":"Yasamal",
    "gn:country_code":"IQ",
    "gn:dem":1323,
    "gn:feature_class":"P",
    "gn:feature_code":"PPL",
    "gn:name":"Yasamal",
    "gn:population":0,
    "gn:timezone":"Asia/Baghdad",
    "iso:country":"IQ",
    "name:ara_x_preferred":[
        "Y\u0101s\u0101m\u0101l"
    ],
    "name:ara_x_variant":[
        "\u06cc\u0627\u0633\u0627\u0645\u0627\u0644"
    ],
    "name:kur_x_preferred":[
        "Yasama\u0142"
    ],
    "name:kur_x_variant":[
        "\u064a\u0627\u0633\u0627\u0645\u0627\u06b5"
    ],
    "name:und_x_variant":[
        "Y\u0101sahm\u0101l",
        "\u064a\u0627\u0633\u0629\u0645\u0627\u0644",
        "\u06cc\u0627\u0633\u0627\u0645\u0627\u0644",
        "Yasamal"
    ],
    "wof:name":"Yasamal",
    "wof:placetype":"locality"
},
  "geometry": {"coordinates":[45.88245,35.55491],"type":"Point"}
}