{
  "type": "Feature",
  "properties": {
    "gn:admin1_code":"7.0",
    "gn:admin2_code":"99173.0",
    "gn:asciiname":"Mukhlif Muhammad 'Abd",
    "gn:country_code":"IQ",
    "gn:dem":36,
    "gn:feature_class":"P",
    "gn:feature_code":"PPL",
    "gn:name":"Mukhlif Mu\u1e29ammad \u2018Abd",
    "gn:population":0,
    "gn:timezone":"Asia/Baghdad",
    "iso:country":"IQ",
    "name:ara_x_preferred":[
        "\u0645\u062e\u0644\u0641 \u0645\u062d\u0645\u062f \u0639\u0628\u062f"
    ],
    "name:und_x_variant":[
        "Mukhlif Mu\u1e29ammad \u2018Abd"
    ],
    "wof:name":"Mukhlif Muhammad 'Abd",
    "wof:placetype":"locality"
},
  "geometry": {"coordinates":[44.16931,33.55996],"type":"Point"}
}