{
  "type": "Feature",
  "properties": {
    "gn:admin1_code":"4.0",
    "gn:admin2_code":"99763.0",
    "gn:asciiname":"Qaryat Ishan al 'Akar",
    "gn:country_code":"IQ",
    "gn:dem":26,
    "gn:feature_class":"P",
    "gn:feature_code":"PPL",
    "gn:name":"Qaryat \u012ash\u0101n al \u2018Akar",
    "gn:population":0,
    "gn:timezone":"Asia/Baghdad",
    "iso:country":"IQ",
    "name:ara_x_preferred":[
        "\u0642\u0631\u064a\u0629 \u0627\u064a\u0634\u0627\u0646 \u0627\u0644\u0639\u0643\u0631"
    ],
    "name:und_x_variant":[
        "Qaryat \u012ash\u0101n al \u2018Akar"
    ],
    "wof:name":"Qaryat Ishan al 'Akar",
    "wof:placetype":"locality"
},
  "geometry": {"coordinates":[44.56426,32.03849],"type":"Point"}
}