{
  "type": "Feature",
  "properties": {
    "gn:admin1_code":"5.0",
    "gn:admin2_code":"92743.0",
    "gn:asciiname":"Koles",
    "gn:country_code":"IQ",
    "gn:dem":1148,
    "gn:feature_class":"P",
    "gn:feature_code":"PPL",
    "gn:name":"Ko\u0142es",
    "gn:population":0,
    "gn:timezone":"Asia/Baghdad",
    "iso:country":"IQ",
    "name:kur_x_preferred":[
        "Ko\u0142es"
    ],
    "name:kur_x_variant":[
        "\u0643\u06c6\u06b5\u06d5\u0633"
    ],
    "name:und_x_variant":[
        "Kolas"
    ],
    "wof:name":"Koles",
    "wof:placetype":"locality"
},
  "geometry": {"coordinates":[45.27072,36.2057],"type":"Point"}
}