{
  "type": "Feature",
  "properties": {
    "gn:admin1_code":"6.0",
    "gn:admin2_code":"99348.0",
    "gn:asciiname":"Al Majanim",
    "gn:country_code":"IQ",
    "gn:dem":27,
    "gn:feature_class":"P",
    "gn:feature_code":"PPL",
    "gn:name":"Al Maj\u0101n\u012bm",
    "gn:population":0,
    "gn:timezone":"Asia/Baghdad",
    "iso:country":"IQ",
    "name:ara_x_preferred":[
        "\u0627\u0644\u0645\u062c\u0627\u0646\u064a\u0645"
    ],
    "name:und_x_variant":[
        "Al Maj\u0101n\u012bm"
    ],
    "wof:name":"Al Majanim",
    "wof:placetype":"locality"
},
  "geometry": {"coordinates":[44.38511,32.18778],"type":"Point"}
}