{
  "type": "Feature",
  "properties": {
    "gn:admin1_code":"15.0",
    "gn:admin2_code":"9166620.0",
    "gn:asciiname":"Al `Ibrah",
    "gn:country_code":"IQ",
    "gn:dem":372,
    "gn:feature_class":"P",
    "gn:feature_code":"PPL",
    "gn:name":"Al \u2018Ibrah",
    "gn:population":0,
    "gn:timezone":"Asia/Baghdad",
    "iso:country":"IQ",
    "name:ara_x_preferred":[
        "\u0627\u0644\u0639\u0628\u0631\u0629"
    ],
    "name:ara_x_variant":[
        "\u0627\u0644\u0639\u0628\u0631\u0629 - \u0627\u0644\u0639\u0638\u0645\u0649"
    ],
    "name:kur_x_preferred":[
        "\u2018Bre"
    ],
    "name:kur_x_variant":[
        "\u0639\u0628\u0631\u06d5"
    ],
    "name:und_x_variant":[
        "Ibr\u0101t al Kab\u012br\u0101",
        "Ibr\u0101t al Kab\u012brah",
        "Ebra",
        "Al \u2018Ibrah",
        "Al \u2018Ibrah - Al \u2018Uz\u0327m\u00e1"
    ],
    "wof:name":"Al `Ibrah",
    "wof:placetype":"locality"
},
  "geometry": {"coordinates":[42.27388,36.3909],"type":"Point"}
}