{
  "type": "Feature",
  "properties": {
    "gn:admin1_code":"6.0",
    "gn:admin2_code":"6818313.0",
    "gn:asciiname":"Jasim Muhammad",
    "gn:country_code":"IQ",
    "gn:dem":30,
    "gn:feature_class":"P",
    "gn:feature_code":"PPL",
    "gn:name":"J\u0101sim Mu\u1e29ammad",
    "gn:population":0,
    "gn:timezone":"Asia/Baghdad",
    "iso:country":"IQ",
    "name:ara_x_preferred":[
        "\u062c\u0627\u0633\u0645 \u0645\u062d\u0645\u062f"
    ],
    "name:und_x_variant":[
        "J\u0101sim Mu\u1e29ammad"
    ],
    "wof:name":"Jasim Muhammad",
    "wof:placetype":"locality"
},
  "geometry": {"coordinates":[44.64588,32.78274],"type":"Point"}
}