{
  "type": "Feature",
  "properties": {
    "gn:admin1_code":"10.0",
    "gn:admin2_code":"99170.0",
    "gn:asciiname":"Qaryat Tali'at Dhiyabah",
    "gn:country_code":"IQ",
    "gn:dem":66,
    "gn:feature_class":"P",
    "gn:feature_code":"PPL",
    "gn:name":"Qaryat \u0162\u0101li\u2018at Dhiy\u0101bah",
    "gn:population":0,
    "gn:timezone":"Asia/Baghdad",
    "iso:country":"IQ",
    "name:ara_x_preferred":[
        "\u0642\u0631\u064a\u0629 \u0637\u0627\u0644\u0639\u0629 \u0630\u064a\u0627\u0628\u0629"
    ],
    "name:und_x_variant":[
        "Qaryat \u0162\u0101li\u2018at Dhiy\u0101bah"
    ],
    "wof:name":"Qaryat Tali'at Dhiyabah",
    "wof:placetype":"locality"
},
  "geometry": {"coordinates":[44.36106,34.14628],"type":"Point"}
}