{
  "type": "Feature",
  "properties": {
    "gn:admin1_code":"11.0",
    "gn:admin2_code":"9166586.0",
    "gn:asciiname":"Markah",
    "gn:country_code":"IQ",
    "gn:dem":1203,
    "gn:feature_class":"P",
    "gn:feature_code":"PPL",
    "gn:name":"Markah",
    "gn:population":0,
    "gn:timezone":"Asia/Baghdad",
    "iso:country":"IQ",
    "name:ara_x_preferred":[
        "\u0645\u0631\u0643\u0629"
    ],
    "name:kur_x_preferred":[
        "M\u00earge"
    ],
    "name:kur_x_variant":[
        "\u0645\u06ce\u0631\u06af\u06d5"
    ],
    "name:und_x_variant":[
        "M\u0113rga",
        "Merga",
        "Merga Upper"
    ],
    "wof:name":"Markah",
    "wof:placetype":"locality"
},
  "geometry": {"coordinates":[44.83784,36.59167],"type":"Point"}
}