{
  "type": "Feature",
  "properties": {
    "gn:admin1_code":"17.0",
    "gn:admin2_code":"9166629.0",
    "gn:asciiname":"Judat Salih",
    "gn:country_code":"IQ",
    "gn:dem":24,
    "gn:feature_class":"P",
    "gn:feature_code":"PPL",
    "gn:name":"J\u016bdat \u015e\u0101li\u1e29",
    "gn:population":0,
    "gn:timezone":"Asia/Baghdad",
    "iso:country":"IQ",
    "name:ara_x_preferred":[
        "\u062c\u0648\u062f\u0629 \u0635\u0627\u0644\u062d"
    ],
    "name:und_x_variant":[
        "J\u016bdat \u015e\u0101li\u1e29"
    ],
    "wof:name":"Judat Salih",
    "wof:placetype":"locality"
},
  "geometry": {"coordinates":[44.57702000000001,32.12028],"type":"Point"}
}