{
  "type": "Feature",
  "properties": {
    "gn:admin1_code":"18.0",
    "gn:admin2_code":"6783103.0",
    "gn:asciiname":"Husayn Shalal",
    "gn:country_code":"IQ",
    "gn:dem":79,
    "gn:feature_class":"P",
    "gn:feature_code":"PPL",
    "gn:name":"\u1e28usayn Shal\u0101l",
    "gn:population":0,
    "gn:timezone":"Asia/Baghdad",
    "iso:country":"IQ",
    "name:ara_x_preferred":[
        "\u062d\u0633\u064a\u0646 \u0634\u0644\u0627\u0644"
    ],
    "name:und_x_variant":[
        "\u1e28usayn Shal\u0101l"
    ],
    "wof:name":"Husayn Shalal",
    "wof:placetype":"locality"
},
  "geometry": {"coordinates":[43.93648,34.31561],"type":"Point"}
}