{
  "type": "Feature",
  "properties": {
    "gn:admin1_code":"7.0",
    "gn:admin2_code":"99101.0",
    "gn:asciiname":"'Arab 'Imran 'Abd al 'Abbas",
    "gn:country_code":"IQ",
    "gn:dem":36,
    "gn:feature_class":"P",
    "gn:feature_code":"PPL",
    "gn:name":"\u2018Arab \u2018Imr\u0101n \u2018Abd al \u2018Abb\u0101s",
    "gn:population":0,
    "gn:timezone":"Asia/Baghdad",
    "iso:country":"IQ",
    "name:ara_x_preferred":[
        "\u0639\u0631\u0628 \u0639\u0645\u0631\u0627\u0646 \u0639\u0628\u062f \u0627\u0644\u0639\u0628\u0627\u0633"
    ],
    "name:und_x_variant":[
        "\u2018Arab \u2018Imr\u0101n \u2018Abd al \u2018Abb\u0101s"
    ],
    "wof:name":"'Arab 'Imran 'Abd al 'Abbas",
    "wof:placetype":"locality"
},
  "geometry": {"coordinates":[44.29335,33.11128],"type":"Point"}
}