{
  "type": "Feature",
  "properties": {
    "gn:admin1_code":"12.0",
    "gn:admin2_code":"99345.0",
    "gn:asciiname":"'Arab 'Abbas Hasan",
    "gn:country_code":"IQ",
    "gn:dem":39,
    "gn:feature_class":"P",
    "gn:feature_code":"PPL",
    "gn:name":"\u2018Arab \u2018Abb\u0101s \u1e28asan",
    "gn:population":0,
    "gn:timezone":"Asia/Baghdad",
    "iso:country":"IQ",
    "name:ara_x_preferred":[
        "\u0639\u0631\u0628 \u0639\u0628\u0627\u0633 \u062d\u0633\u0646"
    ],
    "name:und_x_variant":[
        "\u2018Abb\u0101s",
        "\u2018Arab \u2018Abb\u0101s \u1e28asan"
    ],
    "wof:name":"'Arab 'Abbas Hasan",
    "wof:placetype":"locality"
},
  "geometry": {"coordinates":[44.20776,32.68125999999999],"type":"Point"}
}