{
  "type": "Feature",
  "properties": {
    "gn:admin1_code":"17.0",
    "gn:admin2_code":"9166629.0",
    "gn:asciiname":"'Abbas Dhiyab",
    "gn:country_code":"IQ",
    "gn:dem":23,
    "gn:feature_class":"P",
    "gn:feature_code":"PPL",
    "gn:name":"\u2018Abb\u0101s Dhiy\u0101b",
    "gn:population":0,
    "gn:timezone":"Asia/Baghdad",
    "iso:country":"IQ",
    "name:ara_x_preferred":[
        "\u0639\u0628\u0627\u0633 \u0630\u064a\u0627\u0628"
    ],
    "name:ara_x_variant":[
        "\u2018Abb\u0101s Dhiy\u0101b"
    ],
    "wof:name":"'Abbas Dhiyab",
    "wof:placetype":"locality"
},
  "geometry": {"coordinates":[44.57661,32.13034],"type":"Point"}
}