{
  "type": "Feature",
  "properties": {
    "gn:admin1_code":"7.0",
    "gn:admin2_code":"99101.0",
    "gn:asciiname":"Ash Shuhada'",
    "gn:country_code":"IQ",
    "gn:dem":34,
    "gn:feature_class":"P",
    "gn:feature_code":"PPL",
    "gn:name":"Ash Shuhad\u0101\u2019",
    "gn:population":0,
    "gn:timezone":"Asia/Baghdad",
    "iso:country":"IQ",
    "name:ara_x_preferred":[
        "\u0642\u0631\u064a\u0629 \u0634\u064a\u0627\u0639 \u062d\u0633\u064a\u0646 \u0639\u0644\u064a"
    ],
    "name:ara_x_variant":[
        "\u0627\u0644\u0634\u0647\u062f\u0627\u0621",
        "\u062d\u064a \u0627\u0644\u0634\u0647\u062f\u0627\u0621"
    ],
    "name:und_x_variant":[
        "Qaryat Shay\u0101\u2018 \u1e28usayn \u2018Al\u012b",
        "Ash Shuhad\u0101\u2019",
        "\u1e28ayy ash Shuhad\u0101\u2019"
    ],
    "wof:name":"Ash Shuhada'",
    "wof:placetype":"locality"
},
  "geometry": {"coordinates":[44.34024,33.05256],"type":"Point"}
}