{
  "type": "Feature",
  "properties": {
    "gn:admin1_code":"10.0",
    "gn:admin2_code":"99063.0",
    "gn:asciiname":"Qulay'ah",
    "gn:country_code":"IQ",
    "gn:dem":51,
    "gn:feature_class":"P",
    "gn:feature_code":"PPL",
    "gn:name":"Qulay\u2018ah",
    "gn:population":0,
    "gn:timezone":"Asia/Baghdad",
    "iso:country":"IQ",
    "name:ara_x_preferred":[
        "\u0642\u0644\u064a\u0639\u0629"
    ],
    "name:und_x_variant":[
        "\u2018Arab al Qay\u2018\u012byah",
        "Al Qulay\u2018ah",
        "\u2018Arab al Qal\u2018ia",
        "\u2018Arab al Qulay\u2018ah",
        "Qulay\u2018ah"
    ],
    "wof:name":"Qulay'ah",
    "wof:placetype":"locality"
},
  "geometry": {"coordinates":[44.7247,33.95382],"type":"Point"}
}