{
  "type": "Feature",
  "properties": {
    "gn:admin1_code":"6.0",
    "gn:admin2_code":"6818313.0",
    "gn:asciiname":"Hadi Jayid",
    "gn:country_code":"IQ",
    "gn:dem":36,
    "gn:feature_class":"P",
    "gn:feature_code":"PPL",
    "gn:name":"H\u0101d\u012b J\u0101yid",
    "gn:population":0,
    "gn:timezone":"Asia/Baghdad",
    "iso:country":"IQ",
    "name:ara_x_preferred":[
        "\u0647\u0627\u062f\u064a \u062c\u0627\u064a\u062f"
    ],
    "name:ara_x_variant":[
        "H\u0101d\u012b J\u0101yid"
    ],
    "wof:name":"Hadi Jayid",
    "wof:placetype":"locality"
},
  "geometry": {"coordinates":[44.21424,32.88128],"type":"Point"}
}