{
  "type": "Feature",
  "properties": {
    "gn:admin1_code":"1.0",
    "gn:admin2_code":"6765480.0",
    "gn:asciiname":"Qaryat Sarwinah",
    "gn:country_code":"IQ",
    "gn:dem":112,
    "gn:feature_class":"P",
    "gn:feature_code":"PPL",
    "gn:name":"Qaryat \u015earw\u012bnah",
    "gn:population":0,
    "gn:timezone":"Asia/Baghdad",
    "iso:country":"IQ",
    "name:ara_x_preferred":[
        "\u0642\u0631\u064a\u0629 \u0635\u0631\u0648\u064a\u0646\u0629"
    ],
    "name:und_x_variant":[
        "Qaryat \u015earw\u012bnah"
    ],
    "wof:name":"Qaryat Sarwinah",
    "wof:placetype":"locality"
},
  "geometry": {"coordinates":[42.37434,34.10334],"type":"Point"}
}