{
  "type": "Feature",
  "properties": {
    "gn:admin1_code":"5.0",
    "gn:admin2_code":"96204.0",
    "gn:asciiname":"Disur",
    "gn:country_code":"IQ",
    "gn:dem":1696,
    "gn:feature_class":"P",
    "gn:feature_code":"PPL",
    "gn:name":"Dis\u016br",
    "gn:population":0,
    "gn:timezone":"Asia/Baghdad",
    "iso:country":"IQ",
    "name:ara_x_preferred":[
        "Dis\u016br"
    ],
    "name:ara_x_variant":[
        "\u062f\u0633\u0648\u0631"
    ],
    "wof:name":"Disur",
    "wof:placetype":"locality"
},
  "geometry": {"coordinates":[46.18996,35.18481],"type":"Point"}
}