{
  "type": "Feature",
  "properties": {
    "gn:admin1_code":"6.0",
    "gn:admin2_code":"6818313.0",
    "gn:asciiname":"Tall Abu Shajar",
    "gn:country_code":"IQ",
    "gn:dem":26,
    "gn:feature_class":"P",
    "gn:feature_code":"PPL",
    "gn:name":"Tall Ab\u016b Shajar",
    "gn:population":0,
    "gn:timezone":"Asia/Baghdad",
    "iso:country":"IQ",
    "name:ara_x_preferred":[
        "\u062a\u0644 \u0627\u0628\u0648 \u0634\u062c\u0631"
    ],
    "name:und_x_variant":[
        "Tall Ab\u016b Shajar"
    ],
    "wof:name":"Tall Abu Shajar",
    "wof:placetype":"locality"
},
  "geometry": {"coordinates":[44.74131,32.47959],"type":"Point"}
}