{
  "type": "Feature",
  "properties": {
    "gn:admin1_code":"5.0",
    "gn:admin2_code":"91176.0",
    "gn:asciiname":"Dawlbayshk",
    "gn:country_code":"IQ",
    "gn:dem":877,
    "gn:feature_class":"P",
    "gn:feature_code":"PPL",
    "gn:name":"Dawlbayshk",
    "gn:population":0,
    "gn:timezone":"Asia/Baghdad",
    "iso:country":"IQ",
    "name:ara_x_preferred":[
        "\u062f\u0648\u0644\u0628\u064a\u0634\u0643"
    ],
    "name:kur_x_preferred":[
        "Do\u0142 B\u00eashk\u00ee Mam Xosh\u00ee"
    ],
    "name:kur_x_variant":[
        "Do\u0142 B\u00eashk",
        "\u062f\u06c6\u06b5 \u0628\u06ce\u0634\u0643\u0649 \u0645\u0627\u0645 \u062e\u06c6\u0634\u0649",
        "\u062f\u06c6\u06b5 \u0628\u06ce\u0634\u0643"
    ],
    "name:und_x_variant":[
        "Dolb\u0113shik",
        "Dol Beshk"
    ],
    "wof:name":"Dawlbayshk",
    "wof:placetype":"locality"
},
  "geometry": {"coordinates":[45.40722,35.83139],"type":"Point"}
}