{
  "type": "Feature",
  "properties": {
    "gn:admin1_code":"4.0",
    "gn:admin2_code":"6850588.0",
    "gn:asciiname":"Salman al Jabbar",
    "gn:country_code":"IQ",
    "gn:dem":16,
    "gn:feature_class":"P",
    "gn:feature_code":"PPL",
    "gn:name":"Salm\u0101n al Jabb\u0101r",
    "gn:population":0,
    "gn:timezone":"Asia/Baghdad",
    "iso:country":"IQ",
    "name:und_x_variant":[
        "Salm\u0101n al Jabb\u0101r"
    ],
    "wof:name":"Salman al Jabbar",
    "wof:placetype":"locality"
},
  "geometry": {"coordinates":[44.86667,31.48333],"type":"Point"}
}