{
  "type": "Feature",
  "properties": {
    "gn:admin1_code":"8.0",
    "gn:admin2_code":"99612.0",
    "gn:asciiname":"Atush",
    "gn:country_code":"IQ",
    "gn:dem":1202,
    "gn:feature_class":"P",
    "gn:feature_code":"PPL",
    "gn:name":"Atush",
    "gn:population":0,
    "gn:timezone":"Asia/Baghdad",
    "iso:country":"IQ",
    "name:ara_x_preferred":[
        "\u0623\u062a\u0648\u0634"
    ],
    "name:ara_x_variant":[
        "At\u016bsh"
    ],
    "name:kur_x_preferred":[
        "Etush"
    ],
    "name:kur_x_variant":[
        "\u0626\u06d5\u062a\u0648\u0634",
        "Atush",
        "\u0626\u0627\u062a\u0648\u0634",
        "Atosh",
        "\u0626\u0627\u062a\u06c6\u0634"
    ],
    "name:und_x_variant":[
        "At\u014dsh"
    ],
    "wof:name":"Atush",
    "wof:placetype":"locality"
},
  "geometry": {"coordinates":[43.48698,36.93337],"type":"Point"}
}