{
  "type": "Feature",
  "properties": {
    "gn:admin1_code":"2.0",
    "gn:admin2_code":"99534.0",
    "gn:asciiname":"Hayy al Yarmuk",
    "gn:country_code":"IQ",
    "gn:dem":5,
    "gn:feature_class":"P",
    "gn:feature_code":"PPL",
    "gn:name":"\u1e28ayy al Yarm\u016bk",
    "gn:population":0,
    "gn:timezone":"Asia/Baghdad",
    "iso:country":"IQ",
    "name:und_x_variant":[
        "\u1e28ayy al Yarm\u016bk"
    ],
    "wof:name":"Hayy al Yarmuk",
    "wof:placetype":"locality"
},
  "geometry": {"coordinates":[47.78232,30.46879],"type":"Point"}
}