{
  "type": "Feature",
  "properties": {
    "gn:admin1_code":"6.0",
    "gn:admin2_code":"99358.0",
    "gn:asciiname":"Al Matariyah",
    "gn:country_code":"IQ",
    "gn:dem":26,
    "gn:feature_class":"P",
    "gn:feature_code":"PPL",
    "gn:name":"Al Ma\u0163ar\u012byah",
    "gn:population":0,
    "gn:timezone":"Asia/Baghdad",
    "iso:country":"IQ",
    "name:ara_x_preferred":[
        "\u0627\u0644\u0645\u0637\u0631\u064a\u0629"
    ],
    "name:und_x_variant":[
        "Al Ma\u0163ar\u012byah"
    ],
    "wof:name":"Al Matariyah",
    "wof:placetype":"locality"
},
  "geometry": {"coordinates":[44.64435,32.30231],"type":"Point"}
}