{
  "type": "Feature",
  "properties": {
    "gn:admin1_code":"1.0",
    "gn:admin2_code":"98718.0",
    "gn:asciiname":"Hadir Jasim",
    "gn:country_code":"IQ",
    "gn:dem":61,
    "gn:feature_class":"P",
    "gn:feature_code":"PPL",
    "gn:name":"\u1e28\u0101\u1e11ir J\u0101sim",
    "gn:population":0,
    "gn:timezone":"Asia/Baghdad",
    "iso:country":"IQ",
    "name:ara_x_preferred":[
        "\u062d\u0627\u0636\u0631 \u062c\u0627\u0633\u0645"
    ],
    "name:ara_x_variant":[
        "\u1e28\u0101\u1e11ir J\u0101sim"
    ],
    "wof:name":"Hadir Jasim",
    "wof:placetype":"locality"
},
  "geometry": {"coordinates":[43.07613,33.45849],"type":"Point"}
}