{
  "type": "Feature",
  "properties": {
    "gn:admin1_code":"16.0",
    "gn:admin2_code":"98460.0",
    "gn:asciiname":"Sayyid Yahya",
    "gn:country_code":"IQ",
    "gn:dem":24,
    "gn:feature_class":"P",
    "gn:feature_code":"PPL",
    "gn:name":"Sayyid Ya\u1e29y\u00e1",
    "gn:population":0,
    "gn:timezone":"Asia/Baghdad",
    "iso:country":"IQ",
    "name:ara_x_preferred":[
        "\u0633\u064a\u062f \u064a\u062d\u064a\u0649"
    ],
    "name:und_x_variant":[
        "Sayyid Ya\u1e29y\u00e1"
    ],
    "wof:name":"Sayyid Yahya",
    "wof:placetype":"locality"
},
  "geometry": {"coordinates":[45.3772,32.62437],"type":"Point"}
}