{
  "type": "Feature",
  "properties": {
    "gn:admin1_code":"5.0",
    "gn:admin2_code":"91176.0",
    "gn:asciiname":"Kani Shuwan",
    "gn:country_code":"IQ",
    "gn:dem":1330,
    "gn:feature_class":"P",
    "gn:feature_code":"PPL",
    "gn:name":"K\u0101n\u012b Shuw\u0101n",
    "gn:population":0,
    "gn:timezone":"Asia/Baghdad",
    "iso:country":"IQ",
    "name:ara_x_preferred":[
        "K\u0101n\u012b Shuw\u0101n"
    ],
    "name:ara_x_variant":[
        "\u0643\u0627\u0646\u064a \u0634\u0648\u0627\u0646"
    ],
    "name:kur_x_preferred":[
        "Kan\u00ee Shwan"
    ],
    "name:kur_x_variant":[
        "\u0643\u0627\u0646\u0649 \u0634\u0648\u0627\u0646"
    ],
    "name:und_x_variant":[
        "Kani Shwan"
    ],
    "wof:name":"Kani Shuwan",
    "wof:placetype":"locality"
},
  "geometry": {"coordinates":[45.59009,35.8152],"type":"Point"}
}