{
  "type": "Feature",
  "properties": {
    "gn:admin1_code":"10.0",
    "gn:admin2_code":"9166680.0",
    "gn:asciiname":"'Arab Majid al Hindi",
    "gn:country_code":"IQ",
    "gn:dem":42,
    "gn:feature_class":"P",
    "gn:feature_code":"PPL",
    "gn:name":"\u2018Arab M\u0101jid al Hind\u012b",
    "gn:population":0,
    "gn:timezone":"Asia/Baghdad",
    "iso:country":"IQ",
    "name:ara_x_preferred":[
        "\u0639\u0631\u0628 \u0645\u0627\u062c\u062f \u0627\u0644\u0647\u0646\u062f\u064a"
    ],
    "name:und_x_variant":[
        "\u2018Arab M\u0101jid al Hind\u012b"
    ],
    "wof:name":"'Arab Majid al Hindi",
    "wof:placetype":"locality"
},
  "geometry": {"coordinates":[45.03061,33.71],"type":"Point"}
}