{
  "type": "Feature",
  "properties": {
    "gn:admin1_code":"6.0",
    "gn:admin2_code":"6818313.0",
    "gn:asciiname":"Qal'at 'Umar az Zunbur",
    "gn:country_code":"IQ",
    "gn:dem":29,
    "gn:feature_class":"P",
    "gn:feature_code":"PPL",
    "gn:name":"Qal\u2018at \u2018Umar az Zunb\u016br",
    "gn:population":0,
    "gn:timezone":"Asia/Baghdad",
    "iso:country":"IQ",
    "name:und_x_variant":[
        "Qal\u2018at \u2018Umar az Zunb\u016br"
    ],
    "wof:name":"Qal'at 'Umar az Zunbur",
    "wof:placetype":"locality"
},
  "geometry": {"coordinates":[44.53028,32.69889000000001],"type":"Point"}
}