{
  "type": "Feature",
  "properties": {
    "gn:admin1_code":"10.0",
    "gn:admin2_code":"9166680.0",
    "gn:asciiname":"Dada Wali",
    "gn:country_code":"IQ",
    "gn:dem":41,
    "gn:feature_class":"P",
    "gn:feature_code":"PPL",
    "gn:name":"D\u0101d\u0101 W\u0101l\u012b",
    "gn:population":0,
    "gn:timezone":"Asia/Baghdad",
    "iso:country":"IQ",
    "name:ara_x_preferred":[
        "\u062f\u0627\u062f\u0627 \u0648\u0627\u0644\u064a"
    ],
    "name:ara_x_variant":[
        "D\u0101d\u0101 W\u0101l\u012b"
    ],
    "wof:name":"Dada Wali",
    "wof:placetype":"locality"
},
  "geometry": {"coordinates":[45.08757,33.68198],"type":"Point"}
}