{
  "type": "Feature",
  "properties": {
    "gn:admin1_code":"10.0",
    "gn:admin2_code":"94590.0",
    "gn:asciiname":"Chiya Sarkh",
    "gn:country_code":"IQ",
    "gn:dem":363,
    "gn:feature_class":"P",
    "gn:feature_code":"PPL",
    "gn:name":"Chiy\u0101 Sarkh",
    "gn:population":0,
    "gn:timezone":"Asia/Baghdad",
    "iso:country":"IQ",
    "name:ara_x_preferred":[
        "\u0686\u064a\u0627 \u0633\u0631\u062e"
    ],
    "name:fas_x_preferred":[
        "Ch\u012b\u0101 Sorkh"
    ],
    "name:fas_x_variant":[
        "\u0686\u064a\u0627\u0633\u0631\u062e"
    ],
    "name:und_x_variant":[
        "Ch\u012b\u0101 Surkh",
        "Chah-i-Surkh",
        "Ch\u012b\u0101 Sarkh",
        "Chiy\u0101 Sarkh"
    ],
    "wof:name":"Chiya Sarkh",
    "wof:placetype":"locality"
},
  "geometry": {"coordinates":[45.57995,34.66728],"type":"Point"}
}