{
  "type": "Feature",
  "properties": {
    "gn:admin1_code":"5.0",
    "gn:admin2_code":"91176.0",
    "gn:asciiname":"Qawchi Birdug",
    "gn:country_code":"IQ",
    "gn:dem":1330,
    "gn:feature_class":"P",
    "gn:feature_code":"PPL",
    "gn:name":"Qawch\u012b Bird\u016bg",
    "gn:population":0,
    "gn:timezone":"Asia/Baghdad",
    "iso:country":"IQ",
    "name:ara_x_preferred":[
        "\u0642\u0648\u0686\u064a \u0628\u0631\u062f\u0648\u06af"
    ],
    "name:kur_x_preferred":[
        "Koch\u00ee Brdug"
    ],
    "name:kur_x_variant":[
        "Qoch\u00ee Brdug",
        "\u0643\u06c6\u0686\u0649 \u0628\u0631\u062f\u0648\u06af",
        "\u0642\u06c6\u0686\u0649 \u0628\u0631\u062f\u0648\u06af"
    ],
    "name:und_x_variant":[
        "Q\u016bkh\u012b Bar\u016bdak",
        "\u0642\u0648\u062e\u064a \u0628\u0631\u0648\u062f\u0643",
        "Qawch\u012b Bird\u016bg",
        "Qoche Brdog"
    ],
    "wof:name":"Qawchi Birdug",
    "wof:placetype":"locality"
},
  "geometry": {"coordinates":[45.61721,35.83],"type":"Point"}
}