{
  "type": "Feature",
  "properties": {
    "gn:admin1_code":"18.0",
    "gn:admin2_code":"6783103.0",
    "gn:asciiname":"Muhammad al 'Arabi",
    "gn:country_code":"IQ",
    "gn:dem":66,
    "gn:feature_class":"P",
    "gn:feature_code":"PPL",
    "gn:name":"Mu\u1e29ammad al \u2018Arab\u012b",
    "gn:population":0,
    "gn:timezone":"Asia/Baghdad",
    "iso:country":"IQ",
    "name:ara_x_preferred":[
        "\u0645\u062d\u0645\u062f \u0627\u0644\u0639\u0631\u0628\u064a"
    ],
    "name:und_x_variant":[
        "Mu\u1e29ammad al \u2018Arab\u012b"
    ],
    "wof:name":"Muhammad al 'Arabi",
    "wof:placetype":"locality"
},
  "geometry": {"coordinates":[44.00255,34.26722],"type":"Point"}
}