{
  "type": "Feature",
  "properties": {
    "gn:admin1_code":"5.0",
    "gn:admin2_code":"91176.0",
    "gn:asciiname":"Daralah",
    "gn:country_code":"IQ",
    "gn:dem":906,
    "gn:feature_class":"P",
    "gn:feature_code":"PPL",
    "gn:name":"Daralah",
    "gn:population":0,
    "gn:timezone":"Asia/Baghdad",
    "iso:country":"IQ",
    "name:ara_x_preferred":[
        "\u062f\u0631\u0644\u0647"
    ],
    "name:kur_x_preferred":[
        "Dere\u0142e"
    ],
    "name:kur_x_variant":[
        "Dre\u0142ey Kon",
        "\u062f\u06d5\u0631\u06d5\u06b5\u06d5",
        "\u062f\u0631\u06d5\u06b5\u06d5\u0649 \u0643\u06c6\u0646"
    ],
    "name:und_x_variant":[
        "Darala",
        "Dr\u012b",
        "\u062f\u0631\u0644\u0629"
    ],
    "wof:name":"Daralah",
    "wof:placetype":"locality"
},
  "geometry": {"coordinates":[45.50862,35.71889],"type":"Point"}
}