{
  "type": "Feature",
  "properties": {
    "gn:admin1_code":"9.0",
    "gn:admin2_code":"98623.0",
    "gn:asciiname":"Salim",
    "gn:country_code":"IQ",
    "gn:dem":7,
    "gn:feature_class":"P",
    "gn:feature_code":"PPL",
    "gn:name":"S\u0101lim",
    "gn:population":0,
    "gn:timezone":"Asia/Baghdad",
    "iso:country":"IQ",
    "name:ara_x_preferred":[
        "S\u0101lim"
    ],
    "name:ita_x_preferred":[
        "Salim"
    ],
    "wof:name":"Salim",
    "wof:placetype":"locality"
},
  "geometry": {"coordinates":[46.26917,31.34861],"type":"Point"}
}