{
  "type": "Feature",
  "properties": {
    "gn:admin1_code":"7.0",
    "gn:admin2_code":"99173.0",
    "gn:asciiname":"Tawfiq Husayn al Kazim",
    "gn:country_code":"IQ",
    "gn:dem":43,
    "gn:feature_class":"P",
    "gn:feature_code":"PPL",
    "gn:name":"Tawf\u012bq \u1e28usayn al K\u0101z\u0327im",
    "gn:population":0,
    "gn:timezone":"Asia/Baghdad",
    "iso:country":"IQ",
    "name:und_x_variant":[
        "Tawf\u012bq \u1e28usayn al K\u0101z\u0327im"
    ],
    "wof:name":"Tawfiq Husayn al Kazim",
    "wof:placetype":"locality"
},
  "geometry": {"coordinates":[44.33652,33.43999],"type":"Point"}
}