{
  "type": "Feature",
  "properties": {
    "gn:admin1_code":"9.0",
    "gn:admin2_code":"98623.0",
    "gn:asciiname":"Musa al Matar",
    "gn:country_code":"IQ",
    "gn:dem":9,
    "gn:feature_class":"P",
    "gn:feature_code":"PPL",
    "gn:name":"M\u016bs\u00e1 al Ma\u0163ar",
    "gn:population":0,
    "gn:timezone":"Asia/Baghdad",
    "iso:country":"IQ",
    "name:ara_x_preferred":[
        "\u0645\u0648\u0633\u0649 \u0627\u0644\u0645\u0637\u0631"
    ],
    "name:und_x_variant":[
        "\u1e28usayn al Mu\u0163\u0101",
        "\u1e28usayn al Ma\u0163ar",
        "Husain al Mata",
        "M\u016bs\u00e1 al Ma\u0163ar"
    ],
    "wof:name":"Musa al Matar",
    "wof:placetype":"locality"
},
  "geometry": {"coordinates":[46.2092,31.30741],"type":"Point"}
}