{
  "type": "Feature",
  "properties": {
    "gn:admin1_code":"4.0",
    "gn:admin2_code":"98634.0",
    "gn:asciiname":"Jiyad",
    "gn:country_code":"IQ",
    "gn:dem":18,
    "gn:feature_class":"P",
    "gn:feature_code":"PPL",
    "gn:name":"Jiy\u0101d",
    "gn:population":0,
    "gn:timezone":"Asia/Baghdad",
    "iso:country":"IQ",
    "name:ara_x_preferred":[
        "\u062c\u064a\u0627\u062f"
    ],
    "name:ara_x_variant":[
        "Jiy\u0101d"
    ],
    "wof:name":"Jiyad",
    "wof:placetype":"locality"
},
  "geometry": {"coordinates":[44.63344,31.63576],"type":"Point"}
}