{
  "type": "Feature",
  "properties": {
    "gn:admin1_code":"6.0",
    "gn:admin2_code":"99358.0",
    "gn:asciiname":"'Abbas Muhammad",
    "gn:country_code":"IQ",
    "gn:dem":29,
    "gn:feature_class":"P",
    "gn:feature_code":"PPL",
    "gn:name":"\u2018Abb\u0101s Mu\u1e29ammad",
    "gn:population":0,
    "gn:timezone":"Asia/Baghdad",
    "iso:country":"IQ",
    "name:ara_x_preferred":[
        "\u0639\u0628\u0627\u0633 \u0645\u062d\u0645\u062f"
    ],
    "name:und_x_variant":[
        "\u2018Abb\u0101s Mu\u1e29ammad"
    ],
    "wof:name":"'Abbas Muhammad",
    "wof:placetype":"locality"
},
  "geometry": {"coordinates":[44.73461,32.37269000000001],"type":"Point"}
}