{
  "type": "Feature",
  "properties": {
    "gn:admin1_code":"9.0",
    "gn:admin2_code":"98700.0",
    "gn:asciiname":"Dayf as Sajit",
    "gn:country_code":"IQ",
    "gn:dem":12,
    "gn:feature_class":"P",
    "gn:feature_code":"PPL",
    "gn:name":"\u1e10ayf as S\u0101jit",
    "gn:population":0,
    "gn:timezone":"Asia/Baghdad",
    "iso:country":"IQ",
    "name:ara_x_preferred":[
        "\u0636\u064a\u0641 \u0627\u0644\u0633\u0627\u062c\u062a"
    ],
    "name:und_x_variant":[
        "\u1e10ayf as S\u0101jit"
    ],
    "wof:name":"Dayf as Sajit",
    "wof:placetype":"locality"
},
  "geometry": {"coordinates":[46.05702,31.96977],"type":"Point"}
}