{
  "type": "Feature",
  "properties": {
    "gn:admin1_code":"10.0",
    "gn:admin2_code":"99063.0",
    "gn:asciiname":"Shaykh Zanki",
    "gn:country_code":"IQ",
    "gn:dem":46,
    "gn:feature_class":"P",
    "gn:feature_code":"PPL",
    "gn:name":"Shaykh Zank\u012b",
    "gn:population":0,
    "gn:timezone":"Asia/Baghdad",
    "iso:country":"IQ",
    "name:ara_x_preferred":[
        "\u0634\u064a\u062e \u0632\u0646\u0643\u064a"
    ],
    "name:und_x_variant":[
        "Shaykh Zank\u012b"
    ],
    "wof:name":"Shaykh Zanki",
    "wof:placetype":"locality"
},
  "geometry": {"coordinates":[44.66199,33.66435],"type":"Point"}
}