{
  "type": "Feature",
  "properties": {
    "gn:admin1_code":"6.0",
    "gn:admin2_code":"99358.0",
    "gn:asciiname":"Qaryat Shadhan Jalab",
    "gn:country_code":"IQ",
    "gn:dem":24,
    "gn:feature_class":"P",
    "gn:feature_code":"PPL",
    "gn:name":"Qaryat Shadh\u0101n Jalab",
    "gn:population":0,
    "gn:timezone":"Asia/Baghdad",
    "iso:country":"IQ",
    "name:ara_x_preferred":[
        "\u0642\u0631\u064a\u0629 \u0634\u062f\u0647\u0627\u0646 \u062c\u0644\u0628"
    ],
    "name:und_x_variant":[
        "Qaryat Shadh\u0101n Jalab"
    ],
    "wof:name":"Qaryat Shadhan Jalab",
    "wof:placetype":"locality"
},
  "geometry": {"coordinates":[44.68099,32.1944],"type":"Point"}
}