{
  "type": "Feature",
  "properties": {
    "gn:admin1_code":"5.0",
    "gn:admin2_code":"96204.0",
    "gn:asciiname":"Jalilah",
    "gn:country_code":"IQ",
    "gn:dem":855,
    "gn:feature_class":"P",
    "gn:feature_code":"PPL",
    "gn:name":"Jal\u012blah",
    "gn:population":0,
    "gn:timezone":"Asia/Baghdad",
    "iso:country":"IQ",
    "name:ara_x_preferred":[
        "\u062c\u0644\u064a\u0644\u0629"
    ],
    "name:kur_x_preferred":[
        "Cel\u00eele"
    ],
    "name:kur_x_variant":[
        "\u062c\u06d5\u0644\u064a\u0644\u06d5"
    ],
    "name:und_x_variant":[
        "Jalila",
        "Jal\u012blah",
        "Jaleela"
    ],
    "wof:name":"Jalilah",
    "wof:placetype":"locality"
},
  "geometry": {"coordinates":[46.02629,35.18858],"type":"Point"}
}