{
  "type": "Feature",
  "properties": {
    "gn:admin1_code":"6.0",
    "gn:admin2_code":"99358.0",
    "gn:asciiname":"Turad Hizam",
    "gn:country_code":"IQ",
    "gn:dem":25,
    "gn:feature_class":"P",
    "gn:feature_code":"PPL",
    "gn:name":"\u0162ur\u0101d \u1e28iz\u0101m",
    "gn:population":0,
    "gn:timezone":"Asia/Baghdad",
    "iso:country":"IQ",
    "name:ara_x_preferred":[
        "\u0637\u0631\u0627\u062f \u062d\u0632\u0627\u0645"
    ],
    "name:ara_x_variant":[
        "\u0162ur\u0101d \u1e28iz\u0101m"
    ],
    "wof:name":"Turad Hizam",
    "wof:placetype":"locality"
},
  "geometry": {"coordinates":[44.92761,32.44413],"type":"Point"}
}