{
  "type": "Feature",
  "properties": {
    "gn:admin1_code":"4.0",
    "gn:admin2_code":"99763.0",
    "gn:asciiname":"Salaf Albu Husayn",
    "gn:country_code":"IQ",
    "gn:dem":21,
    "gn:feature_class":"P",
    "gn:feature_code":"PPLL",
    "gn:name":"Salaf \u0100lb\u016b \u1e28usayn",
    "gn:population":0,
    "gn:timezone":"Asia/Baghdad",
    "iso:country":"IQ",
    "name:ara_x_preferred":[
        "\u0633\u0644\u0641 \u0627\u0644\u0628\u0648 \u062d\u0633\u064a\u0646"
    ],
    "name:und_x_variant":[
        "Salaf \u0100lb\u016b \u1e28usayn"
    ],
    "wof:name":"Salaf Albu Husayn",
    "wof:placetype":"locality"
},
  "geometry": {"coordinates":[45.01318,32.09745],"type":"Point"}
}