{
  "type": "Feature",
  "properties": {
    "gn:admin1_code":"5.0",
    "gn:admin2_code":"92743.0",
    "gn:asciiname":"Shaykh `Awdalan",
    "gn:country_code":"IQ",
    "gn:dem":1347,
    "gn:feature_class":"P",
    "gn:feature_code":"PPL",
    "gn:name":"Shaykh \u2018Awd\u0101l\u0101n",
    "gn:population":0,
    "gn:timezone":"Asia/Baghdad",
    "iso:country":"IQ",
    "name:ara_x_preferred":[
        "\u0634\u064a\u062e \u0639\u0648\u062f\u0627\u0644\u0627\u0646"
    ],
    "name:kur_x_preferred":[
        "Sh\u00eax \u2018Ewda\u0142an"
    ],
    "name:kur_x_variant":[
        "\u0634\u06ce\u062e \u0639\u06d5\u0648\u062f\u0627\u06b5\u0627\u0646",
        "Sh\u00eax \u2018Awda\u0142an",
        "\u0634\u06ce\u062e \u0639\u0627\u0648\u062f\u0627\u06b5\u0627\u0646"
    ],
    "name:und_x_variant":[
        "Awadalan",
        "Shaykh \u2018Awd\u0101l\u0101n",
        "Shaykh Awad\u0101l\u0101n",
        "Shekh Awdalan"
    ],
    "wof:name":"Shaykh `Awdalan",
    "wof:placetype":"locality"
},
  "geometry": {"coordinates":[45.21928,36.23407],"type":"Point"}
}