{
  "type": "Feature",
  "properties": {
    "gn:admin1_code":"14.0",
    "gn:admin2_code":"99610.0",
    "gn:asciiname":"As Saglawiyah",
    "gn:country_code":"IQ",
    "gn:dem":8,
    "gn:feature_class":"P",
    "gn:feature_code":"PPL",
    "gn:name":"A\u015f \u015eagl\u0101w\u012byah",
    "gn:population":0,
    "gn:timezone":"Asia/Baghdad",
    "iso:country":"IQ",
    "name:ara_x_preferred":[
        "\u0627\u0627\u0644\u0635\u06af\u0644\u0627\u0648\u064a\u0647"
    ],
    "name:und_x_variant":[
        "A\u015f \u015eagl\u0101w\u012byah"
    ],
    "wof:name":"As Saglawiyah",
    "wof:placetype":"locality"
},
  "geometry": {"coordinates":[46.97137,31.84817],"type":"Point"}
}