{
  "type": "Feature",
  "properties": {
    "gn:admin1_code":"7.0",
    "gn:admin2_code":"9166545.0",
    "gn:asciiname":"Khalil Mansur",
    "gn:country_code":"IQ",
    "gn:dem":36,
    "gn:feature_class":"P",
    "gn:feature_code":"PPL",
    "gn:name":"Khal\u012bl Man\u015f\u016br",
    "gn:population":0,
    "gn:timezone":"Asia/Baghdad",
    "iso:country":"IQ",
    "name:ara_x_preferred":[
        "\u062e\u0644\u064a\u0644 \u0645\u0646\u0635\u0648\u0631"
    ],
    "name:und_x_variant":[
        "Khal\u012bl Man\u015f\u016br"
    ],
    "wof:name":"Khalil Mansur",
    "wof:placetype":"locality"
},
  "geometry": {"coordinates":[44.39876,33.18627],"type":"Point"}
}