{
  "type": "Feature",
  "properties": {
    "gn:admin1_code":"16.0",
    "gn:admin2_code":"99132.0",
    "gn:asciiname":"Al 'Abid",
    "gn:country_code":"IQ",
    "gn:dem":19,
    "gn:feature_class":"P",
    "gn:feature_code":"PPL",
    "gn:name":"Al \u2018\u0100bid",
    "gn:population":0,
    "gn:timezone":"Asia/Baghdad",
    "iso:country":"IQ",
    "name:ara_x_preferred":[
        "\u0627\u0644\u0639\u0627\u0628\u062f"
    ],
    "name:ara_x_variant":[
        "Al \u2018\u0100bid"
    ],
    "wof:name":"Al 'Abid",
    "wof:placetype":"locality"
},
  "geometry": {"coordinates":[45.69749,32.43062],"type":"Point"}
}