{
  "type": "Feature",
  "properties": {
    "gn:admin1_code":"7.0",
    "gn:admin2_code":"9166569.0",
    "gn:asciiname":"'Arab Siham Yusif",
    "gn:country_code":"IQ",
    "gn:dem":38,
    "gn:feature_class":"P",
    "gn:feature_code":"PPL",
    "gn:name":"\u2018Arab Sih\u0101m Y\u016bsif",
    "gn:population":0,
    "gn:timezone":"Asia/Baghdad",
    "iso:country":"IQ",
    "name:ara_x_preferred":[
        "\u0639\u0631\u0628 \u0633\u0647\u0627\u0645 \u064a\u0648\u0633\u0641"
    ],
    "name:und_x_variant":[
        "\u2018Arab Sih\u0101m Y\u016bsif"
    ],
    "wof:name":"'Arab Siham Yusif",
    "wof:placetype":"locality"
},
  "geometry": {"coordinates":[44.30924,33.58237],"type":"Point"}
}