{
  "type": "Feature",
  "properties": {
    "gn:admin1_code":"14.0",
    "gn:admin2_code":"99097.0",
    "gn:asciiname":"Amhuwar",
    "gn:country_code":"IQ",
    "gn:dem":5,
    "gn:feature_class":"P",
    "gn:feature_code":"PPL",
    "gn:name":"Amh\u016bwar",
    "gn:population":0,
    "gn:timezone":"Asia/Baghdad",
    "iso:country":"IQ",
    "name:ara_x_preferred":[
        "\u0627\u0645\u0647\u0648\u0648\u0631"
    ],
    "name:und_x_variant":[
        "Mah\u016bdar",
        "Amh\u016bwar"
    ],
    "wof:name":"Amhuwar",
    "wof:placetype":"locality"
},
  "geometry": {"coordinates":[47.19492,31.46185],"type":"Point"}
}