{
  "type": "Feature",
  "properties": {
    "gn:admin1_code":"5.0",
    "gn:admin2_code":"9166684.0",
    "gn:asciiname":"Bralah",
    "gn:country_code":"IQ",
    "gn:dem":1299,
    "gn:feature_class":"P",
    "gn:feature_code":"PPL",
    "gn:name":"Br\u0101lah",
    "gn:population":0,
    "gn:timezone":"Asia/Baghdad",
    "iso:country":"IQ",
    "name:ara_x_preferred":[
        "\u0628\u0631\u0627\u0644\u0647"
    ],
    "name:kur_x_preferred":[
        "Birale"
    ],
    "name:kur_x_variant":[
        "\u0628\u0631\u0627\u0644\u06d5"
    ],
    "name:und_x_variant":[
        "Birala",
        "B\u012br\u0101lah",
        "Brala",
        "Bir\u0101lah"
    ],
    "wof:name":"Bralah",
    "wof:placetype":"locality"
},
  "geometry": {"coordinates":[46.02362,35.73161],"type":"Point"}
}