{
  "type": "Feature",
  "properties": {
    "gn:admin1_code":"7.0",
    "gn:admin2_code":"9166542.0",
    "gn:asciiname":"Hamad ad Dari",
    "gn:country_code":"IQ",
    "gn:dem":40,
    "gn:feature_class":"P",
    "gn:feature_code":"PPLL",
    "gn:name":"\u1e28amad a\u1e11 \u1e10\u0101r\u012b",
    "gn:population":0,
    "gn:timezone":"Asia/Baghdad",
    "iso:country":"IQ",
    "name:ara_x_preferred":[
        "\u062d\u0645\u062f \u0627\u0644\u0636\u0627\u0631\u064a"
    ],
    "name:und_x_variant":[
        "\u1e28amad a\u1e11 \u1e10\u0101r\u012b"
    ],
    "wof:name":"Hamad ad Dari",
    "wof:placetype":"locality"
},
  "geometry": {"coordinates":[44.06041,33.32598],"type":"Point"}
}