{
  "type": "Feature",
  "properties": {
    "gn:admin1_code":"16.0",
    "gn:admin2_code":"98460.0",
    "gn:asciiname":"Kashash Murad",
    "gn:country_code":"IQ",
    "gn:dem":30,
    "gn:feature_class":"P",
    "gn:feature_code":"PPL",
    "gn:name":"Kash\u0101sh Mur\u0101d",
    "gn:population":0,
    "gn:timezone":"Asia/Baghdad",
    "iso:country":"IQ",
    "name:ara_x_preferred":[
        "\u0643\u0634\u0627\u0634 \u0645\u0631\u0627\u062f"
    ],
    "name:und_x_variant":[
        "Kash\u0101sh Mur\u0101d"
    ],
    "wof:name":"Kashash Murad",
    "wof:placetype":"locality"
},
  "geometry": {"coordinates":[44.83496,32.83823],"type":"Point"}
}