{
  "type": "Feature",
  "properties": {
    "gn:admin1_code":"5.0",
    "gn:admin2_code":"9166596.0",
    "gn:asciiname":"Wija",
    "gn:country_code":"IQ",
    "gn:dem":580,
    "gn:feature_class":"P",
    "gn:feature_code":"PPL",
    "gn:name":"W\u012bj\u0101",
    "gn:population":0,
    "gn:timezone":"Asia/Baghdad",
    "iso:country":"IQ",
    "name:ara_x_preferred":[
        "W\u012bj\u0101"
    ],
    "name:ara_x_variant":[
        "\u0648\u064a\u062c\u0627"
    ],
    "wof:name":"Wija",
    "wof:placetype":"locality"
},
  "geometry": {"coordinates":[44.79999,36.11354],"type":"Point"}
}