{
  "type": "Feature",
  "properties": {
    "gn:admin1_code":"15.0",
    "gn:admin2_code":"90392.0",
    "gn:asciiname":"Ash Shawr",
    "gn:country_code":"IQ",
    "gn:dem":453,
    "gn:feature_class":"P",
    "gn:feature_code":"PPL",
    "gn:name":"Ash Shawr",
    "gn:population":0,
    "gn:timezone":"Asia/Baghdad",
    "iso:country":"IQ",
    "name:ara_x_preferred":[
        "\u0627\u0644\u0634\u0648\u0631"
    ],
    "name:kur_x_preferred":[
        "Shor"
    ],
    "name:kur_x_variant":[
        "\u0634\u06c6\u0631"
    ],
    "name:nno_x_preferred":[
        "Ash Shawr"
    ],
    "name:und_x_variant":[
        "Tel ash Shaur",
        "Tall ash Shawr",
        "\u062a\u0644 \u0627\u0644\u0634\u0648\u0631",
        "Ash Shawr"
    ],
    "wof:name":"Ash Shawr",
    "wof:placetype":"locality"
},
  "geometry": {"coordinates":[42.14333,36.50232000000001],"type":"Point"}
}