{
  "type": "Feature",
  "properties": {
    "gn:admin1_code":"16.0",
    "gn:admin2_code":"98460.0",
    "gn:asciiname":"Sajit 'Abbas",
    "gn:country_code":"IQ",
    "gn:dem":27,
    "gn:feature_class":"P",
    "gn:feature_code":"PPL",
    "gn:name":"S\u0101jit \u2018Abb\u0101s",
    "gn:population":0,
    "gn:timezone":"Asia/Baghdad",
    "iso:country":"IQ",
    "name:ara_x_preferred":[
        "\u0633\u0627\u062c\u062a \u0639\u0628\u0627\u0633"
    ],
    "name:ara_x_variant":[
        "S\u0101jit \u2018Abb\u0101s"
    ],
    "wof:name":"Sajit 'Abbas",
    "wof:placetype":"locality"
},
  "geometry": {"coordinates":[44.56627,32.82374],"type":"Point"}
}