{
  "type": "Feature",
  "properties": {
    "gn:admin1_code":"1.0",
    "gn:admin2_code":"6765480.0",
    "gn:asciiname":"Albu Habbat",
    "gn:country_code":"IQ",
    "gn:dem":112,
    "gn:feature_class":"P",
    "gn:feature_code":"PPL",
    "gn:name":"\u0100lb\u016b \u1e28abb\u0101t",
    "gn:population":0,
    "gn:timezone":"Asia/Baghdad",
    "iso:country":"IQ",
    "name:ara_x_preferred":[
        "\u0627\u0644\u0628\u0648 \u062d\u0628\u0627\u062a"
    ],
    "name:und_x_variant":[
        "\u0100lb\u016b \u1e28abb\u0101t"
    ],
    "wof:name":"Albu Habbat",
    "wof:placetype":"locality"
},
  "geometry": {"coordinates":[42.4444,34.00628],"type":"Point"}
}