{
  "type": "Feature",
  "properties": {
    "gn:admin1_code":"1.0",
    "gn:admin2_code":"6765480.0",
    "gn:asciiname":"Qaryat 'Anayat al 'Ulya",
    "gn:country_code":"IQ",
    "gn:dem":85,
    "gn:feature_class":"P",
    "gn:feature_code":"PPL",
    "gn:name":"Qaryat \u2018An\u0101yat al \u2018Uly\u0101",
    "gn:population":0,
    "gn:timezone":"Asia/Baghdad",
    "iso:country":"IQ",
    "name:ara_x_preferred":[
        "\u0642\u0631\u064a\u0629 \u0639\u0646\u0627\u064a\u0629 \u0627\u0644\u0639\u0644\u064a\u0627"
    ],
    "name:und_x_variant":[
        "Qaryat \u2018An\u0101yat al \u2018Uly\u0101"
    ],
    "wof:name":"Qaryat 'Anayat al 'Ulya",
    "wof:placetype":"locality"
},
  "geometry": {"coordinates":[42.52913,34.00182],"type":"Point"}
}