{
  "type": "Feature",
  "properties": {
    "gn:admin1_code":"9.0",
    "gn:admin2_code":"98855.0",
    "gn:asciiname":"Jama'at al Kharitah",
    "gn:country_code":"IQ",
    "gn:dem":8,
    "gn:feature_class":"P",
    "gn:feature_code":"PPL",
    "gn:name":"Jam\u0101\u2018at al Khar\u012b\u0163ah",
    "gn:population":0,
    "gn:timezone":"Asia/Baghdad",
    "iso:country":"IQ",
    "name:und_x_variant":[
        "Jam\u0101\u2018at al Khar\u012bta",
        "Jam\u0101\u2018at al Khar\u012b\u0163ah"
    ],
    "wof:name":"Jama'at al Kharitah",
    "wof:placetype":"locality"
},
  "geometry": {"coordinates":[45.83333,31.11667000000001],"type":"Point"}
}