{
  "type": "Feature",
  "properties": {
    "gn:admin1_code":"15.0",
    "gn:admin2_code":"98820.0",
    "gn:asciiname":"Artun",
    "gn:country_code":"IQ",
    "gn:dem":778,
    "gn:feature_class":"P",
    "gn:feature_code":"PPL",
    "gn:name":"Art\u016bn",
    "gn:population":0,
    "gn:timezone":"Asia/Baghdad",
    "iso:country":"IQ",
    "name:ara_x_preferred":[
        "\u0623\u0631\u062a\u0648\u0646"
    ],
    "name:ara_x_variant":[
        "Art\u016bn"
    ],
    "name:kur_x_preferred":[
        "Artun"
    ],
    "name:kur_x_variant":[
        "Ertun",
        "\u0626\u06d5\u0631\u062a\u0648\u0646",
        "Art\u00een",
        "Ert\u00een J\u00fbr\u00ee",
        "\u0626\u0627\u0631\u062a\u064a\u0646",
        "\u0626\u06d5\u0631\u062a\u064a\u0646 \u0698\u0648\u0648\u0631\u0649"
    ],
    "name:und_x_variant":[
        "Artin Upper"
    ],
    "wof:name":"Artun",
    "wof:placetype":"locality"
},
  "geometry": {"coordinates":[43.84056,36.86228],"type":"Point"}
}