{
  "type": "Feature",
  "properties": {
    "gn:admin1_code":"18.0",
    "gn:admin2_code":"6872046.0",
    "gn:asciiname":"Ziban",
    "gn:country_code":"IQ",
    "gn:dem":106,
    "gn:feature_class":"P",
    "gn:feature_code":"PPL",
    "gn:name":"Z\u012bb\u0101n",
    "gn:population":0,
    "gn:timezone":"Asia/Baghdad",
    "iso:country":"IQ",
    "name:ara_x_preferred":[
        "\u0632\u064a\u0628\u0627\u0646"
    ],
    "name:ara_x_variant":[
        "Z\u012bb\u0101n"
    ],
    "wof:name":"Ziban",
    "wof:placetype":"locality"
},
  "geometry": {"coordinates":[43.01596,34.84832],"type":"Point"}
}