{
  "type": "Feature",
  "properties": {
    "gn:admin1_code":"9.0",
    "gn:admin2_code":"98623.0",
    "gn:asciiname":"Ash Shaykh Nayif al Mashshay",
    "gn:country_code":"IQ",
    "gn:dem":9,
    "gn:feature_class":"P",
    "gn:feature_code":"PPL",
    "gn:name":"Ash Shaykh N\u0101yif al Mashsh\u0101y",
    "gn:population":0,
    "gn:timezone":"Asia/Baghdad",
    "iso:country":"IQ",
    "name:ara_x_preferred":[
        "\u0627\u0644\u0634\u064a\u062e \u0646\u0627\u064a\u0641 \u0627\u0644\u0645\u0634\u0627\u064a"
    ],
    "name:und_x_variant":[
        "Al \u2018Am\u012br",
        "Shaykh Sh\u0101\u012bf al Mash\u0101\u012b",
        "Ash Shaykh N\u0101yif al Mashsh\u0101y"
    ],
    "wof:name":"Ash Shaykh Nayif al Mashshay",
    "wof:placetype":"locality"
},
  "geometry": {"coordinates":[46.4853,31.35845],"type":"Point"}
}