{
  "type": "Feature",
  "properties": {
    "gn:admin1_code":"8.0",
    "gn:admin2_code":"97269.0",
    "gn:asciiname":"Barushki",
    "gn:country_code":"IQ",
    "gn:dem":841,
    "gn:feature_class":"P",
    "gn:feature_code":"PPL",
    "gn:name":"Bar\u016bshk\u012b",
    "gn:population":0,
    "gn:timezone":"Asia/Baghdad",
    "iso:country":"IQ",
    "name:ara_x_preferred":[
        "\u0628\u0631\u0648\u0634\u0643\u064a"
    ],
    "name:kur_x_preferred":[
        "Birushk\u00ee"
    ],
    "name:kur_x_variant":[
        "\u0628\u0631\u0648\u0634\u0643\u0649",
        "Be\u1e5fushka Se\u2018d\u00een\u00ee",
        "\u0628\u06d5\u0695\u0648\u0634\u0643\u0627 \u0633\u06d5\u0639\u062f\u064a\u0646\u0649",
        "Berushka Se\u2018d\u00een\u00ee",
        "\u0628\u06d5\u0631\u0648\u0634\u0643\u0627 \u0633\u06d5\u0639\u062f\u064a\u0646\u0649"
    ],
    "name:und_x_variant":[
        "Bar\u016bshk\u012b",
        "Broshki",
        "Bar\u014dshk\u012b",
        "Bir\u016bshk\u012b",
        "Barushka Saadini",
        "Baroshke",
        "Baroshka Saadoni"
    ],
    "wof:name":"Barushki",
    "wof:placetype":"locality"
},
  "geometry": {"coordinates":[43.08084,37.06744000000001],"type":"Point"}
}