{
  "type": "Feature",
  "properties": {
    "gn:admin1_code":"18.0",
    "gn:admin2_code":"6872046.0",
    "gn:asciiname":"'Abd Shalash",
    "gn:country_code":"IQ",
    "gn:dem":102,
    "gn:feature_class":"P",
    "gn:feature_code":"PPL",
    "gn:name":"\u2018Abd Shal\u0101sh",
    "gn:population":0,
    "gn:timezone":"Asia/Baghdad",
    "iso:country":"IQ",
    "name:ara_x_preferred":[
        "\u0639\u0628\u062f \u0634\u0644\u0627\u0634"
    ],
    "name:und_x_variant":[
        "\u2018Abd Shal\u0101sh"
    ],
    "wof:name":"'Abd Shalash",
    "wof:placetype":"locality"
},
  "geometry": {"coordinates":[43.12798,34.70399],"type":"Point"}
}