{
  "type": "Feature",
  "properties": {
    "gn:admin1_code":"6.0",
    "gn:admin2_code":"99358.0",
    "gn:asciiname":"Hasan ad Duhaym",
    "gn:country_code":"IQ",
    "gn:dem":27,
    "gn:feature_class":"P",
    "gn:feature_code":"PPL",
    "gn:name":"\u1e28asan ad Duhaym",
    "gn:population":0,
    "gn:timezone":"Asia/Baghdad",
    "iso:country":"IQ",
    "name:ara_x_preferred":[
        "\u062d\u0633\u0646 \u0627\u0644\u062f\u0647\u064a\u0645"
    ],
    "name:und_x_variant":[
        "\u1e28asan ad Duhaym"
    ],
    "wof:name":"Hasan ad Duhaym",
    "wof:placetype":"locality"
},
  "geometry": {"coordinates":[44.52168,32.31309],"type":"Point"}
}