{
  "type": "Feature",
  "properties": {
    "gn:admin1_code":"14.0",
    "gn:admin2_code":"99610.0",
    "gn:asciiname":"Salaf ash Shuwayti",
    "gn:country_code":"IQ",
    "gn:dem":7,
    "gn:feature_class":"P",
    "gn:feature_code":"PPL",
    "gn:name":"Salaf ash Shuway\u0163\u012b",
    "gn:population":0,
    "gn:timezone":"Asia/Baghdad",
    "iso:country":"IQ",
    "name:ara_x_preferred":[
        "\u0633\u0644\u0641 \u0627\u0644\u0634\u0648\u064a\u0637\u064a"
    ],
    "name:und_x_variant":[
        "Salaf ash Shuway\u0163\u012b",
        "Ash Shuway\u0163\u012b"
    ],
    "wof:name":"Salaf ash Shuwayti",
    "wof:placetype":"locality"
},
  "geometry": {"coordinates":[47.52617,31.77398],"type":"Point"}
}