{
  "type": "Feature",
  "properties": {
    "gn:admin1_code":"1.0",
    "gn:admin2_code":"9166650.0",
    "gn:asciiname":"Al 'Awinah",
    "gn:country_code":"IQ",
    "gn:dem":210,
    "gn:feature_class":"P",
    "gn:feature_code":"PPL",
    "gn:name":"Al \u2018Aw\u012bnah",
    "gn:population":0,
    "gn:timezone":"Asia/Baghdad",
    "iso:country":"IQ",
    "name:ara_x_preferred":[
        "\u0627\u0644\u0639\u0648\u064a\u0646\u0629"
    ],
    "name:und_x_variant":[
        "Al \u2018Aw\u012bnah"
    ],
    "wof:name":"Al 'Awinah",
    "wof:placetype":"locality"
},
  "geometry": {"coordinates":[41.34526,35.02961],"type":"Point"}
}