{
  "type": "Feature",
  "properties": {
    "gn:admin1_code":"10.0",
    "gn:admin2_code":"9166680.0",
    "gn:asciiname":"Durayz Kazim Jawad",
    "gn:country_code":"IQ",
    "gn:dem":37,
    "gn:feature_class":"P",
    "gn:feature_code":"PPL",
    "gn:name":"Durayz K\u0101z\u0327im Jaw\u0101d",
    "gn:population":0,
    "gn:timezone":"Asia/Baghdad",
    "iso:country":"IQ",
    "name:ara_x_preferred":[
        "\u062f\u0631\u064a\u0632 \u0643\u0627\u0638\u0645 \u062c\u0648\u0627\u062f"
    ],
    "name:und_x_variant":[
        "Durayz K\u0101z\u0327im Jaw\u0101d"
    ],
    "wof:name":"Durayz Kazim Jawad",
    "wof:placetype":"locality"
},
  "geometry": {"coordinates":[45.13333,33.53496],"type":"Point"}
}