{
  "type": "Feature",
  "properties": {
    "gn:admin1_code":"15.0",
    "gn:admin2_code":"98820.0",
    "gn:asciiname":"Saygirik",
    "gn:country_code":"IQ",
    "gn:dem":401,
    "gn:feature_class":"P",
    "gn:feature_code":"PPL",
    "gn:name":"Sayg\u012brik",
    "gn:population":0,
    "gn:timezone":"Asia/Baghdad",
    "iso:country":"IQ",
    "name:ara_x_preferred":[
        "\u0633\u064a\u06af\u064a\u0631\u0643"
    ],
    "name:kur_x_preferred":[
        "Ser Bgrk"
    ],
    "name:kur_x_variant":[
        "\u0633\u06d5\u0631 \u0628\u06af\u0631\u0643"
    ],
    "name:und_x_variant":[
        "Sigirk",
        "Sar Bgirk",
        "Sar Bigirk",
        "Sayg\u012brik"
    ],
    "wof:name":"Saygirik",
    "wof:placetype":"locality"
},
  "geometry": {"coordinates":[43.66844,36.62961],"type":"Point"}
}