{
  "type": "Feature",
  "properties": {
    "gn:admin1_code":"6.0",
    "gn:admin2_code":"99358.0",
    "gn:asciiname":"Hasan Mujid",
    "gn:country_code":"IQ",
    "gn:dem":26,
    "gn:feature_class":"P",
    "gn:feature_code":"PPL",
    "gn:name":"\u1e28asan M\u016bjid",
    "gn:population":0,
    "gn:timezone":"Asia/Baghdad",
    "iso:country":"IQ",
    "name:ara_x_preferred":[
        "\u062d\u0633\u0646 \u0645\u0648\u062c\u062f"
    ],
    "name:und_x_variant":[
        "\u1e28asan M\u016bjid"
    ],
    "wof:name":"Hasan Mujid",
    "wof:placetype":"locality"
},
  "geometry": {"coordinates":[44.97779,32.46052],"type":"Point"}
}