{
  "type": "Feature",
  "properties": {
    "gn:admin1_code":"18.0",
    "gn:admin2_code":"9166616.0",
    "gn:asciiname":"Majid Fayhan",
    "gn:country_code":"IQ",
    "gn:dem":38,
    "gn:feature_class":"P",
    "gn:feature_code":"PPL",
    "gn:name":"Maj\u012bd Fay\u1e29\u0101n",
    "gn:population":0,
    "gn:timezone":"Asia/Baghdad",
    "iso:country":"IQ",
    "name:ara_x_preferred":[
        "\u0645\u062c\u064a\u062f \u0641\u064a\u062d\u0627\u0646"
    ],
    "name:und_x_variant":[
        "Maj\u012bd Fay\u1e29\u0101n"
    ],
    "wof:name":"Majid Fayhan",
    "wof:placetype":"locality"
},
  "geometry": {"coordinates":[44.01169,33.66833],"type":"Point"}
}