{
  "type": "Feature",
  "properties": {
    "gn:admin1_code":"4.0",
    "gn:admin2_code":"98634.0",
    "gn:asciiname":"Ar Radad ar Ra'isi",
    "gn:country_code":"IQ",
    "gn:dem":21,
    "gn:feature_class":"P",
    "gn:feature_code":"PPL",
    "gn:name":"Ar Rad\u0101d ar Ra\u2019\u012bs\u012b",
    "gn:population":0,
    "gn:timezone":"Asia/Baghdad",
    "iso:country":"IQ",
    "name:ara_x_preferred":[
        "\u0627\u0644\u0631\u062f\u0627\u062f \u0627\u0644\u0631\u0626\u064a\u0633\u064a"
    ],
    "name:und_x_variant":[
        "Ar Rad\u0101d ar Ra\u2019\u012bs\u012b"
    ],
    "wof:name":"Ar Radad ar Ra'isi",
    "wof:placetype":"locality"
},
  "geometry": {"coordinates":[44.64345,31.81046],"type":"Point"}
}