{
  "type": "Feature",
  "properties": {
    "gn:admin1_code":"11.0",
    "gn:admin2_code":"9166592.0",
    "gn:asciiname":"Qesrok",
    "gn:country_code":"IQ",
    "gn:dem":397,
    "gn:feature_class":"P",
    "gn:feature_code":"PPL",
    "gn:name":"Qesrok",
    "gn:population":0,
    "gn:timezone":"Asia/Baghdad",
    "iso:country":"IQ",
    "name:kur_x_preferred":[
        "Qesrok"
    ],
    "name:kur_x_variant":[
        "\u0642\u06d5\u0633\u0631\u06c6\u0643"
    ],
    "name:und_x_variant":[
        "Qasrok"
    ],
    "wof:name":"Qesrok",
    "wof:placetype":"locality"
},
  "geometry": {"coordinates":[44.30696,36.74138],"type":"Point"}
}