{
  "type": "Feature",
  "properties": {
    "gn:admin1_code":"7.0",
    "gn:admin2_code":"99101.0",
    "gn:asciiname":"Hasan 'Abd 'Ali",
    "gn:country_code":"IQ",
    "gn:dem":31,
    "gn:feature_class":"P",
    "gn:feature_code":"PPL",
    "gn:name":"\u1e28asan \u2018Abd \u2018Al\u012b",
    "gn:population":0,
    "gn:timezone":"Asia/Baghdad",
    "iso:country":"IQ",
    "name:ara_x_preferred":[
        "\u062d\u0633\u0646 \u0639\u0628\u062f \u0639\u0644\u064a"
    ],
    "name:und_x_variant":[
        "\u1e28asan \u2018Abd \u2018Al\u012b"
    ],
    "wof:name":"Hasan 'Abd 'Ali",
    "wof:placetype":"locality"
},
  "geometry": {"coordinates":[44.43137,33.17589],"type":"Point"}
}