{
  "type": "Feature",
  "properties": {
    "gn:admin1_code":"8.0",
    "gn:admin2_code":"97269.0",
    "gn:asciiname":"Pirah Khak",
    "gn:country_code":"IQ",
    "gn:dem":833,
    "gn:feature_class":"P",
    "gn:feature_code":"PPL",
    "gn:name":"P\u012brah Kh\u0101k",
    "gn:population":0,
    "gn:timezone":"Asia/Baghdad",
    "iso:country":"IQ",
    "name:ara_x_preferred":[
        "\u067e\u064a\u0631\u062e\u062a"
    ],
    "name:ara_x_variant":[
        "\u067e\u064a\u0631\u06d5 \u062e\u0627\u0643"
    ],
    "name:kur_x_preferred":[
        "Siprexit"
    ],
    "name:kur_x_variant":[
        "\u0633\u067e\u0631\u06d5\u062e\u062a",
        "P\u00eerefat",
        "\u067e\u064a\u0631\u06d5\u0641\u0627\u062a"
    ],
    "name:und_x_variant":[
        "P\u012brah Kh\u0101k",
        "Sprakht",
        "P\u012braf\u0101t",
        "P\u012brakhat",
        "Pirafat"
    ],
    "wof:name":"Pirah Khak",
    "wof:placetype":"locality"
},
  "geometry": {"coordinates":[42.96198,36.95955],"type":"Point"}
}