{
  "type": "Feature",
  "properties": {
    "gn:admin1_code":"10.0",
    "gn:admin2_code":"9166680.0",
    "gn:asciiname":"'Abbas as Salih",
    "gn:country_code":"IQ",
    "gn:dem":45,
    "gn:feature_class":"P",
    "gn:feature_code":"PPL",
    "gn:name":"\u2018Abb\u0101s as S\u0101lih",
    "gn:population":0,
    "gn:timezone":"Asia/Baghdad",
    "iso:country":"IQ",
    "name:und_x_variant":[
        "\u2018Abb\u0101s as S\u0101lih"
    ],
    "wof:name":"'Abbas as Salih",
    "wof:placetype":"locality"
},
  "geometry": {"coordinates":[44.76667,33.71667],"type":"Point"}
}