{
  "type": "Feature",
  "properties": {
    "gn:admin1_code":"7.0",
    "gn:admin2_code":"99101.0",
    "gn:asciiname":"Hamzat al Muhammad",
    "gn:country_code":"IQ",
    "gn:dem":35,
    "gn:feature_class":"P",
    "gn:feature_code":"PPL",
    "gn:name":"\u1e28amzat al Mu\u1e29ammad",
    "gn:population":0,
    "gn:timezone":"Asia/Baghdad",
    "iso:country":"IQ",
    "name:ara_x_preferred":[
        "\u062d\u0645\u0632\u0629 \u0627\u0644\u0645\u062d\u0645\u062f"
    ],
    "name:und_x_variant":[
        "\u1e28amzat al Mu\u1e29ammad"
    ],
    "wof:name":"Hamzat al Muhammad",
    "wof:placetype":"locality"
},
  "geometry": {"coordinates":[44.25046,33.00689000000001],"type":"Point"}
}