{
  "type": "Feature",
  "properties": {
    "gn:admin1_code":"7.0",
    "gn:admin2_code":"9166545.0",
    "gn:asciiname":"Muhammad 'Ali",
    "gn:country_code":"IQ",
    "gn:dem":37,
    "gn:feature_class":"P",
    "gn:feature_code":"PPL",
    "gn:name":"Mu\u1e29ammad \u2018Al\u012b",
    "gn:population":0,
    "gn:timezone":"Asia/Baghdad",
    "iso:country":"IQ",
    "name:ara_x_preferred":[
        "\u0645\u062d\u0645\u062f \u0639\u0644\u064a"
    ],
    "name:und_x_variant":[
        "Mu\u1e29ammad \u2018Al\u012b"
    ],
    "wof:name":"Muhammad 'Ali",
    "wof:placetype":"locality"
},
  "geometry": {"coordinates":[44.48107,33.20326],"type":"Point"}
}