{
  "type": "Feature",
  "properties": {
    "gn:admin1_code":"15.0",
    "gn:admin2_code":"9166620.0",
    "gn:asciiname":"Tall Ghazal",
    "gn:country_code":"IQ",
    "gn:dem":268,
    "gn:feature_class":"P",
    "gn:feature_code":"PPLF",
    "gn:name":"Tall Ghaz\u0101l",
    "gn:population":0,
    "gn:timezone":"Asia/Baghdad",
    "iso:country":"IQ",
    "name:ara_x_preferred":[
        "\u062a\u0644 \u063a\u0632\u0627\u0644"
    ],
    "name:und_x_variant":[
        "Tall Ghaz\u0101l"
    ],
    "wof:name":"Tall Ghazal",
    "wof:placetype":"locality"
},
  "geometry": {"coordinates":[42.36978,36.1754],"type":"Point"}
}