{
  "type": "Feature",
  "properties": {
    "gn:admin1_code":"11.0",
    "gn:admin2_code":"93817.0",
    "gn:asciiname":"Xurmle",
    "gn:country_code":"IQ",
    "gn:dem":334,
    "gn:feature_class":"P",
    "gn:feature_code":"PPL",
    "gn:name":"Xurmle",
    "gn:population":0,
    "gn:timezone":"Asia/Baghdad",
    "iso:country":"IQ",
    "name:ara_x_preferred":[
        "\u062e\u0648\u0631\u0645\u0644\u0629"
    ],
    "name:kur_x_preferred":[
        "Khurimla"
    ],
    "name:kur_x_variant":[
        "Xurmle",
        "\u062e\u0648\u0631\u0645\u0644\u06d5"
    ],
    "name:und_x_variant":[
        "Kh\u016brm\u012blah",
        "Khurmela",
        "Khurmala",
        "Kh\u016brm\u0101lah",
        "Kh\u016brmalah"
    ],
    "wof:name":"Xurmle",
    "wof:placetype":"locality"
},
  "geometry": {"coordinates":[43.74871,35.91664],"type":"Point"}
}