{
  "type": "Feature",
  "properties": {
    "gn:admin1_code":"11.0",
    "gn:admin2_code":"93817.0",
    "gn:asciiname":"Qaryat Quh",
    "gn:country_code":"IQ",
    "gn:dem":213,
    "gn:feature_class":"P",
    "gn:feature_code":"PPL",
    "gn:name":"Qaryat Q\u016b\u1e29",
    "gn:population":0,
    "gn:timezone":"Asia/Baghdad",
    "iso:country":"IQ",
    "name:ara_x_preferred":[
        "\u0642\u0631\u064a\u0629 \u0642\u0648\u062d"
    ],
    "name:und_x_variant":[
        "Qaryat Q\u016b\u1e29"
    ],
    "wof:name":"Qaryat Quh",
    "wof:placetype":"locality"
},
  "geometry": {"coordinates":[43.45244,35.64528],"type":"Point"}
}