{
  "type": "Feature",
  "properties": {
    "gn:admin1_code":"4.0",
    "gn:admin2_code":"98634.0",
    "gn:asciiname":"Al Kuhayfat",
    "gn:country_code":"IQ",
    "gn:dem":20,
    "gn:feature_class":"P",
    "gn:feature_code":"PPL",
    "gn:name":"Al Ku\u1e29ayf\u0101t",
    "gn:population":0,
    "gn:timezone":"Asia/Baghdad",
    "iso:country":"IQ",
    "name:ara_x_preferred":[
        "\u0627\u0644\u0643\u062d\u064a\u0641\u0627\u062a"
    ],
    "name:und_x_variant":[
        "Al Ku\u1e29ayf\u0101t"
    ],
    "wof:name":"Al Kuhayfat",
    "wof:placetype":"locality"
},
  "geometry": {"coordinates":[44.55258,31.65658],"type":"Point"}
}