{
  "type": "Feature",
  "properties": {
    "gn:admin1_code":"8.0",
    "gn:admin2_code":"99612.0",
    "gn:asciiname":"Tinay",
    "gn:country_code":"IQ",
    "gn:dem":1011,
    "gn:feature_class":"P",
    "gn:feature_code":"PPL",
    "gn:name":"T\u012bnay",
    "gn:population":0,
    "gn:timezone":"Asia/Baghdad",
    "iso:country":"IQ",
    "name:ara_x_preferred":[
        "\u062a\u064a\u0646\u064a"
    ],
    "name:kur_x_preferred":[
        "Tan\u00ee"
    ],
    "name:kur_x_variant":[
        "\u062a\u0627\u0646\u0649",
        "Tin\u00ea",
        "\u062a\u0646\u06ce",
        "Gund\u00ee Tina",
        "\u06af\u0648\u0646\u062f\u0649 \u062a\u0646\u0627"
    ],
    "name:und_x_variant":[
        "T\u0101n\u012b",
        "Tany",
        "T\u012bnay",
        "Tina"
    ],
    "wof:name":"Tinay",
    "wof:placetype":"locality"
},
  "geometry": {"coordinates":[43.23794,37.09875],"type":"Point"}
}