{
  "type": "Feature",
  "properties": {
    "gn:admin1_code":"10.0",
    "gn:admin2_code":"9166680.0",
    "gn:asciiname":"'Isa al Husayn",
    "gn:country_code":"IQ",
    "gn:dem":99,
    "gn:feature_class":"P",
    "gn:feature_code":"PPL",
    "gn:name":"\u2018\u012as\u00e1 al \u1e28usayn",
    "gn:population":0,
    "gn:timezone":"Asia/Baghdad",
    "iso:country":"IQ",
    "name:ara_x_preferred":[
        "\u0639\u064a\u0633\u0649 \u0627\u0644\u062d\u0633\u064a\u0646"
    ],
    "name:und_x_variant":[
        "\u2018\u012as\u00e1 al \u1e28usayn"
    ],
    "wof:name":"'Isa al Husayn",
    "wof:placetype":"locality"
},
  "geometry": {"coordinates":[45.31436,33.93396],"type":"Point"}
}