{
  "type": "Feature",
  "properties": {
    "gn:admin1_code":"4.0",
    "gn:admin2_code":"99737.0",
    "gn:asciiname":"Qaryat ad Dar'iyah",
    "gn:country_code":"IQ",
    "gn:dem":23,
    "gn:feature_class":"P",
    "gn:feature_code":"PPL",
    "gn:name":"Qaryat ad Dar\u2018\u012byah",
    "gn:population":0,
    "gn:timezone":"Asia/Baghdad",
    "iso:country":"IQ",
    "name:ara_x_preferred":[
        "\u0642\u0631\u064a\u0629 \u0627\u0644\u062f\u0631\u0639\u064a\u0629"
    ],
    "name:und_x_variant":[
        "Qaryat ad Dar\u2018\u012byah"
    ],
    "wof:name":"Qaryat ad Dar'iyah",
    "wof:placetype":"locality"
},
  "geometry": {"coordinates":[45.14009,32.15004],"type":"Point"}
}