{
  "type": "Feature",
  "properties": {
    "gn:admin1_code":"1.0",
    "gn:admin2_code":"9166650.0",
    "gn:asciiname":"Al Ibrahimiyah",
    "gn:country_code":"IQ",
    "gn:dem":157,
    "gn:feature_class":"P",
    "gn:feature_code":"PPL",
    "gn:name":"Al Ibr\u0101h\u012bm\u012byah",
    "gn:population":0,
    "gn:timezone":"Asia/Baghdad",
    "iso:country":"IQ",
    "name:ara_x_preferred":[
        "\u0627\u0644\u0623\u0628\u0631\u0627\u0647\u064a\u0645\u064a\u0629"
    ],
    "name:und_x_variant":[
        "Al Ibr\u0101h\u012bm\u012byah"
    ],
    "wof:name":"Al Ibrahimiyah",
    "wof:placetype":"locality"
},
  "geometry": {"coordinates":[41.59577,34.4745],"type":"Point"}
}