{
  "type": "Feature",
  "properties": {
    "gn:admin1_code":"3.0",
    "gn:admin2_code":"9166568.0",
    "gn:asciiname":"Sultan al Mahdi",
    "gn:country_code":"IQ",
    "gn:dem":17,
    "gn:feature_class":"P",
    "gn:feature_code":"PPL",
    "gn:name":"Sul\u0163\u0101n al Mahd\u012b",
    "gn:population":0,
    "gn:timezone":"Asia/Baghdad",
    "iso:country":"IQ",
    "name:ara_x_preferred":[
        "\u0633\u0644\u0637\u0627\u0646 \u0627\u0644\u0645\u0647\u062f\u064a"
    ],
    "name:und_x_variant":[
        "Sul\u0163\u0101n al Mahd\u012b"
    ],
    "wof:name":"Sultan al Mahdi",
    "wof:placetype":"locality"
},
  "geometry": {"coordinates":[45.23091,31.48436],"type":"Point"}
}