{
  "type": "Feature",
  "properties": {
    "gn:admin1_code":"14.0",
    "gn:admin2_code":"99610.0",
    "gn:asciiname":"Jabar ath Thamir",
    "gn:country_code":"IQ",
    "gn:dem":9,
    "gn:feature_class":"P",
    "gn:feature_code":"PPL",
    "gn:name":"Jab\u0101r ath Th\u0101mir",
    "gn:population":0,
    "gn:timezone":"Asia/Baghdad",
    "iso:country":"IQ",
    "name:ara_x_preferred":[
        "\u062c\u0628\u0627\u0631 \u0627\u0644\u062b\u0627\u0645\u0631"
    ],
    "name:und_x_variant":[
        "Jab\u0101r ath Th\u0101mir"
    ],
    "wof:name":"Jabar ath Thamir",
    "wof:placetype":"locality"
},
  "geometry": {"coordinates":[47.33807,31.81302],"type":"Point"}
}