{
  "type": "Feature",
  "properties": {
    "gn:admin1_code":"15.0",
    "gn:admin2_code":"9166608.0",
    "gn:asciiname":"'Ajil",
    "gn:country_code":"IQ",
    "gn:dem":278,
    "gn:feature_class":"P",
    "gn:feature_code":"PPL",
    "gn:name":"\u2018Aj\u012bl",
    "gn:population":0,
    "gn:timezone":"Asia/Baghdad",
    "iso:country":"IQ",
    "name:ara_x_preferred":[
        "\u0639\u062c\u064a\u0644"
    ],
    "name:ara_x_variant":[
        "\u2018Aj\u012bl"
    ],
    "wof:name":"'Ajil",
    "wof:placetype":"locality"
},
  "geometry": {"coordinates":[41.70449,35.90812000000001],"type":"Point"}
}