{
  "type": "Feature",
  "properties": {
    "gn:admin1_code":"10.0",
    "gn:admin2_code":"9166680.0",
    "gn:asciiname":"Hasan",
    "gn:country_code":"IQ",
    "gn:dem":61,
    "gn:feature_class":"P",
    "gn:feature_code":"PPL",
    "gn:name":"\u1e28asan",
    "gn:population":0,
    "gn:timezone":"Asia/Baghdad",
    "iso:country":"IQ",
    "name:und_x_variant":[
        "\u1e28asan"
    ],
    "wof:name":"Hasan",
    "wof:placetype":"locality"
},
  "geometry": {"coordinates":[45.51667,33.56667],"type":"Point"}
}