{
  "type": "Feature",
  "properties": {
    "gn:admin1_code":"6.0",
    "gn:admin2_code":"6818313.0",
    "gn:asciiname":"Haybis Matar",
    "gn:country_code":"IQ",
    "gn:dem":29,
    "gn:feature_class":"P",
    "gn:feature_code":"PPL",
    "gn:name":"\u1e28aybis Ma\u0163ar",
    "gn:population":0,
    "gn:timezone":"Asia/Baghdad",
    "iso:country":"IQ",
    "name:ara_x_preferred":[
        "\u062d\u064a\u0628\u0633 \u0645\u0637\u0631"
    ],
    "name:und_x_variant":[
        "\u1e28aybis Ma\u0163ar"
    ],
    "wof:name":"Haybis Matar",
    "wof:placetype":"locality"
},
  "geometry": {"coordinates":[44.70105,32.67049],"type":"Point"}
}