{
  "type": "Feature",
  "properties": {
    "gn:admin1_code":"15.0",
    "gn:admin2_code":"98820.0",
    "gn:asciiname":"Navdar",
    "gn:country_code":"IQ",
    "gn:dem":518,
    "gn:feature_class":"P",
    "gn:feature_code":"PPL",
    "gn:name":"Navdar",
    "gn:population":0,
    "gn:timezone":"Asia/Baghdad",
    "iso:country":"IQ",
    "name:kur_x_preferred":[
        "Navdar"
    ],
    "name:kur_x_variant":[
        "\u0646\u0627\u06a4\u062f\u0627\u0631"
    ],
    "wof:name":"Navdar",
    "wof:placetype":"locality"
},
  "geometry": {"coordinates":[44.0958,36.85202],"type":"Point"}
}