{
  "type": "Feature",
  "properties": {
    "gn:admin1_code":"11.0",
    "gn:admin2_code":"9166592.0",
    "gn:asciiname":"Dostana",
    "gn:country_code":"IQ",
    "gn:dem":1382,
    "gn:feature_class":"P",
    "gn:feature_code":"PPL",
    "gn:name":"Dostana",
    "gn:population":0,
    "gn:timezone":"Asia/Baghdad",
    "iso:country":"IQ",
    "name:deu_x_preferred":[
        "Dostana"
    ],
    "name:kur_x_preferred":[
        "Dostana"
    ],
    "name:kur_x_variant":[
        "\u062f\u06c6\u0633\u062a\u0627\u0646\u0627"
    ],
    "name:und_x_variant":[
        "Dostana Boley"
    ],
    "wof:name":"Dostana",
    "wof:placetype":"locality"
},
  "geometry": {"coordinates":[44.72108,36.77733],"type":"Point"}
}