{
  "type": "Feature",
  "properties": {
    "gn:admin1_code":"5.0",
    "gn:admin2_code":"91176.0",
    "gn:asciiname":"Mashan al 'Ulya",
    "gn:country_code":"IQ",
    "gn:dem":1028,
    "gn:feature_class":"P",
    "gn:feature_code":"PPL",
    "gn:name":"M\u0101sh\u0101n al \u2018Uly\u0101",
    "gn:population":0,
    "gn:timezone":"Asia/Baghdad",
    "iso:country":"IQ",
    "name:ara_x_preferred":[
        "\u0645\u0627\u0634\u0627\u0646 \u0627\u0644\u0639\u0644\u064a\u0627"
    ],
    "name:kur_x_preferred":[
        "Mashan"
    ],
    "name:kur_x_variant":[
        "\u0645\u0627\u0634\u0627\u0646"
    ],
    "name:und_x_variant":[
        "M\u0101sh\u0101n al \u2018Uly\u0101",
        "M\u0101sh\u0101n"
    ],
    "wof:name":"Mashan al 'Ulya",
    "wof:placetype":"locality"
},
  "geometry": {"coordinates":[45.51469,35.98523],"type":"Point"}
}