{
  "type": "Feature",
  "properties": {
    "gn:admin1_code":"1.0",
    "gn:admin2_code":"99455.0",
    "gn:asciiname":"Qaryat 'Abd al Fayyad",
    "gn:country_code":"IQ",
    "gn:dem":43,
    "gn:feature_class":"P",
    "gn:feature_code":"PPL",
    "gn:name":"Qaryat \u2018Abd al Fayy\u0101\u1e11",
    "gn:population":0,
    "gn:timezone":"Asia/Baghdad",
    "iso:country":"IQ",
    "name:ara_x_preferred":[
        "\u0642\u0631\u064a\u0629 \u0639\u064a\u062f \u0627\u0644\u0641\u064a\u0627\u0636"
    ],
    "name:ara_x_variant":[
        "\u0642\u0631\u064a\u0629 \u0639\u0628\u062f \u0627\u0644\u0641\u064a\u0627\u0636"
    ],
    "name:und_x_variant":[
        "Qaryat \u2018\u012ad al Fayy\u0101\u1e11",
        "Qaryat \u2018Abd al Fayy\u0101\u1e11"
    ],
    "wof:name":"Qaryat 'Abd al Fayyad",
    "wof:placetype":"locality"
},
  "geometry": {"coordinates":[43.91609,33.38997],"type":"Point"}
}