{
  "type": "Feature",
  "properties": {
    "gn:admin1_code":"4.0",
    "gn:admin2_code":"99763.0",
    "gn:asciiname":"Jabr Hassan",
    "gn:country_code":"IQ",
    "gn:dem":23,
    "gn:feature_class":"P",
    "gn:feature_code":"PPL",
    "gn:name":"Jabr \u1e28ass\u0101n",
    "gn:population":0,
    "gn:timezone":"Asia/Baghdad",
    "iso:country":"IQ",
    "name:ara_x_preferred":[
        "\u062c\u0628\u0631 \u062d\u0633\u0627\u0646"
    ],
    "name:und_x_variant":[
        "Jabr \u1e28ass\u0101n"
    ],
    "wof:name":"Jabr Hassan",
    "wof:placetype":"locality"
},
  "geometry": {"coordinates":[44.70799,32.07365],"type":"Point"}
}