{
  "type": "Feature",
  "properties": {
    "gn:admin1_code":"14.0",
    "gn:admin2_code":"99097.0",
    "gn:asciiname":"Sayyadah",
    "gn:cc2":"IQ",
    "gn:country_code":"IQ",
    "gn:dem":11,
    "gn:feature_class":"P",
    "gn:feature_code":"PPL",
    "gn:name":"Sayy\u0101dah",
    "gn:population":0,
    "gn:timezone":"Asia/Baghdad",
    "iso:country":"IQ",
    "name:und_x_variant":[
        "Saiy\u0101dah",
        "Sayy\u0101dah"
    ],
    "wof:name":"Sayyadah",
    "wof:placetype":"locality"
},
  "geometry": {"coordinates":[47.19417,31.61611],"type":"Point"}
}