{
  "type": "Feature",
  "properties": {
    "gn:admin1_code":"15.0",
    "gn:admin2_code":"9166620.0",
    "gn:asciiname":"Shananik",
    "gn:country_code":"IQ",
    "gn:dem":428,
    "gn:feature_class":"P",
    "gn:feature_code":"PPL",
    "gn:name":"Shan\u0101n\u012bk",
    "gn:population":0,
    "gn:timezone":"Asia/Baghdad",
    "iso:country":"IQ",
    "name:ara_x_preferred":[
        "\u0634\u0646\u0627\u0646\u064a\u0643"
    ],
    "name:kur_x_preferred":[
        "\u1e26enank"
    ],
    "name:kur_x_variant":[
        "\u062d\u06d5\u0646\u0627\u0646\u0643"
    ],
    "name:und_x_variant":[
        "Hananik",
        "Shan\u0101n\u012bk"
    ],
    "wof:name":"Shananik",
    "wof:placetype":"locality"
},
  "geometry": {"coordinates":[41.88214,36.53075],"type":"Point"}
}