{
  "type": "Feature",
  "properties": {
    "gn:admin1_code":"18.0",
    "gn:admin2_code":"6804454.0",
    "gn:asciiname":"Muhammad Hamud",
    "gn:country_code":"IQ",
    "gn:dem":151,
    "gn:feature_class":"P",
    "gn:feature_code":"PPL",
    "gn:name":"Mu\u1e29ammad \u1e28am\u016bd",
    "gn:population":0,
    "gn:timezone":"Asia/Baghdad",
    "iso:country":"IQ",
    "name:ara_x_preferred":[
        "\u0645\u062d\u0645\u062f \u062d\u0645\u0648\u062f"
    ],
    "name:und_x_variant":[
        "Mu\u1e29ammad \u1e28am\u016bd"
    ],
    "wof:name":"Muhammad Hamud",
    "wof:placetype":"locality"
},
  "geometry": {"coordinates":[43.27192,35.50581],"type":"Point"}
}