{
  "type": "Feature",
  "properties": {
    "gn:admin1_code":"7.0",
    "gn:admin2_code":"99173.0",
    "gn:asciiname":"Khalaf Muhammad Nayif",
    "gn:country_code":"IQ",
    "gn:dem":39,
    "gn:feature_class":"P",
    "gn:feature_code":"PPL",
    "gn:name":"Khalaf Mu\u1e29ammad N\u0101yif",
    "gn:population":0,
    "gn:timezone":"Asia/Baghdad",
    "iso:country":"IQ",
    "name:ara_x_preferred":[
        "\u062e\u0644\u0641 \u0645\u062d\u0645\u062f \u0646\u0627\u064a\u0641"
    ],
    "name:und_x_variant":[
        "Khalaf Mu\u1e29ammad N\u0101yif"
    ],
    "wof:name":"Khalaf Muhammad Nayif",
    "wof:placetype":"locality"
},
  "geometry": {"coordinates":[44.22953,33.51211],"type":"Point"}
}