{
  "type": "Feature",
  "properties": {
    "gn:admin1_code":"1.0",
    "gn:admin2_code":"99455.0",
    "gn:asciiname":"Al Karmah",
    "gn:country_code":"IQ",
    "gn:dem":37,
    "gn:feature_class":"P",
    "gn:feature_code":"PPL",
    "gn:name":"Al Karmah",
    "gn:population":0,
    "gn:timezone":"Asia/Baghdad",
    "iso:country":"IQ",
    "name:und_x_variant":[
        "Karma",
        "Al Karmah"
    ],
    "wof:name":"Al Karmah",
    "wof:placetype":"locality"
},
  "geometry": {"coordinates":[43.93333,33.58333],"type":"Point"}
}