{
  "type": "Feature",
  "properties": {
    "gn:admin1_code":"8.0",
    "gn:admin2_code":"9166607.0",
    "gn:asciiname":"Rikava Dena",
    "gn:country_code":"IQ",
    "gn:dem":485,
    "gn:feature_class":"P",
    "gn:feature_code":"PPL",
    "gn:name":"Rikava Dena",
    "gn:population":0,
    "gn:timezone":"Asia/Baghdad",
    "iso:country":"IQ",
    "name:ara_x_preferred":[
        "\u0631\u0643\u0627\u0628\u0647 \u062f\u0646\u0627\u062f\u064a"
    ],
    "name:kur_x_preferred":[
        "Rikava"
    ],
    "name:kur_x_variant":[
        "\u0695\u0643\u0627\u06a4\u0627",
        "Rikava Dena",
        "\u0631\u0643\u0627\u06a4\u0627 \u062f\u06d5\u0646\u0627"
    ],
    "name:und_x_variant":[
        "Rak\u0101bah Dan\u0101d\u012b",
        "Rik\u0101bah Dan\u0101d\u012b",
        "Rkava"
    ],
    "wof:name":"Rikava Dena",
    "wof:placetype":"locality"
},
  "geometry": {"coordinates":[42.98481,36.76975],"type":"Point"}
}