{
  "type": "Feature",
  "properties": {
    "gn:admin1_code":"4.0",
    "gn:admin2_code":"99737.0",
    "gn:asciiname":"Maftul Abu 'Uwayjilah",
    "gn:country_code":"IQ",
    "gn:dem":12,
    "gn:feature_class":"P",
    "gn:feature_code":"PPL",
    "gn:name":"Maft\u016bl Ab\u016b \u2018Uwayj\u012blah",
    "gn:population":0,
    "gn:timezone":"Asia/Baghdad",
    "iso:country":"IQ",
    "name:ara_x_preferred":[
        "\u0645\u0641\u062a\u0648\u0644 \u0627\u0628\u0648 \u0639\u0648\u064a\u062c\u064a\u0644\u0629"
    ],
    "name:und_x_variant":[
        "Maft\u016bl Ab\u016b \u2018Uwayj\u012blah"
    ],
    "wof:name":"Maftul Abu 'Uwayjilah",
    "wof:placetype":"locality"
},
  "geometry": {"coordinates":[45.41309,31.86098],"type":"Point"}
}