{
  "type": "Feature",
  "properties": {
    "gn:admin1_code":"17.0",
    "gn:admin2_code":"9166552.0",
    "gn:asciiname":"Al Ghazalat",
    "gn:country_code":"IQ",
    "gn:dem":21,
    "gn:feature_class":"P",
    "gn:feature_code":"PPL",
    "gn:name":"Al Ghaz\u0101l\u0101t",
    "gn:population":0,
    "gn:timezone":"Asia/Baghdad",
    "iso:country":"IQ",
    "name:ara_x_preferred":[
        "\u0627\u0644\u063a\u0632\u0627\u0644\u0627\u062a"
    ],
    "name:und_x_variant":[
        "Al Ghaz\u0101l\u0101t"
    ],
    "wof:name":"Al Ghazalat",
    "wof:placetype":"locality"
},
  "geometry": {"coordinates":[44.46362,31.70375],"type":"Point"}
}