{
  "type": "Feature",
  "properties": {
    "gn:admin1_code":"8.0",
    "gn:admin2_code":"9166607.0",
    "gn:asciiname":"Shazi",
    "gn:country_code":"IQ",
    "gn:dem":603,
    "gn:feature_class":"P",
    "gn:feature_code":"PPL",
    "gn:name":"Shaz\u012b",
    "gn:population":0,
    "gn:timezone":"Asia/Baghdad",
    "iso:country":"IQ",
    "name:ara_x_preferred":[
        "\u0634\u0632\u064a"
    ],
    "name:kur_x_preferred":[
        "Shir\u00ee"
    ],
    "name:kur_x_variant":[
        "\u0634\u0631\u0649",
        "S\u00eac\u00ea",
        "\u0633\u06ce\u062c\u06ce"
    ],
    "name:und_x_variant":[
        "Sh\u0113z\u012b",
        "Shry",
        "Shaz\u012b",
        "Seje"
    ],
    "wof:name":"Shazi",
    "wof:placetype":"locality"
},
  "geometry": {"coordinates":[42.88081,36.91252],"type":"Point"}
}