{
  "type": "Feature",
  "properties": {
    "gn:admin1_code":"15.0",
    "gn:admin2_code":"99414.0",
    "gn:asciiname":"Umm Aksur",
    "gn:country_code":"IQ",
    "gn:dem":250,
    "gn:feature_class":"P",
    "gn:feature_code":"PPL",
    "gn:name":"Umm Aks\u016br",
    "gn:population":0,
    "gn:timezone":"Asia/Baghdad",
    "iso:country":"IQ",
    "name:ara_x_preferred":[
        "\u0627\u0645 \u0627\u0643\u0633\u0648\u0631"
    ],
    "name:ara_x_variant":[
        "Umm Aks\u016br"
    ],
    "wof:name":"Umm Aksur",
    "wof:placetype":"locality"
},
  "geometry": {"coordinates":[42.96097,35.82044000000001],"type":"Point"}
}