{
  "type": "Feature",
  "properties": {
    "gn:admin1_code":"5.0",
    "gn:admin2_code":"98464.0",
    "gn:asciiname":"Hanjirah",
    "gn:country_code":"IQ",
    "gn:dem":895,
    "gn:feature_class":"P",
    "gn:feature_code":"PPL",
    "gn:name":"Hanj\u012brah",
    "gn:population":0,
    "gn:timezone":"Asia/Baghdad",
    "iso:country":"IQ",
    "name:ara_x_preferred":[
        "\u0647\u0646\u062c\u064a\u0631\u0629"
    ],
    "name:und_x_variant":[
        "Hanj\u012brah",
        "Hanj\u012bra"
    ],
    "wof:name":"Hanjirah",
    "wof:placetype":"locality"
},
  "geometry": {"coordinates":[45.10662,35.53661],"type":"Point"}
}