{
  "type": "Feature",
  "properties": {
    "gn:admin1_code":"11.0",
    "gn:admin2_code":"95444.0",
    "gn:asciiname":"Bayrzin",
    "gn:country_code":"IQ",
    "gn:dem":490,
    "gn:feature_class":"P",
    "gn:feature_code":"PPL",
    "gn:name":"Bayrz\u012bn",
    "gn:population":0,
    "gn:timezone":"Asia/Baghdad",
    "iso:country":"IQ",
    "name:ara_x_preferred":[
        "\u0628\u064a\u0631\u0632\u064a\u0646"
    ],
    "name:kur_x_preferred":[
        "P\u00earzin"
    ],
    "name:kur_x_variant":[
        "\u0628\u06ce\u0631\u0632\u0646"
    ],
    "name:und_x_variant":[
        "Ber Zin",
        "P\u012brz\u012bn",
        "Bayrz\u012bn"
    ],
    "wof:name":"Bayrzin",
    "wof:placetype":"locality"
},
  "geometry": {"coordinates":[44.07225,36.26709],"type":"Point"}
}