{
  "type": "Feature",
  "properties": {
    "gn:admin1_code":"7.0",
    "gn:admin2_code":"99101.0",
    "gn:asciiname":"'Arab 'Id Abrahi",
    "gn:country_code":"IQ",
    "gn:dem":33,
    "gn:feature_class":"P",
    "gn:feature_code":"PPL",
    "gn:name":"\u2018Arab \u2018\u012ad Abrah\u012b",
    "gn:population":0,
    "gn:timezone":"Asia/Baghdad",
    "iso:country":"IQ",
    "name:ara_x_preferred":[
        "\u0639\u0631\u0628 \u0639\u064a\u062f \u0627\u0628\u0631\u0647\u064a"
    ],
    "name:und_x_variant":[
        "\u2018Arab \u2018\u012ad Abrah\u012b"
    ],
    "wof:name":"'Arab 'Id Abrahi",
    "wof:placetype":"locality"
},
  "geometry": {"coordinates":[44.34103,33.14149],"type":"Point"}
}