{
  "type": "Feature",
  "properties": {
    "gn:admin1_code":"13.0",
    "gn:admin2_code":"6770659.0",
    "gn:asciiname":"Qaryat Sab` Tulul",
    "gn:country_code":"IQ",
    "gn:dem":197,
    "gn:feature_class":"P",
    "gn:feature_code":"PPL",
    "gn:name":"Qaryat Sab\u2018 Tul\u016bl",
    "gn:population":0,
    "gn:timezone":"Asia/Baghdad",
    "iso:country":"IQ",
    "name:ara_x_preferred":[
        "\u0642\u0631\u064a\u0629 \u0633\u0628\u0639 \u062a\u0644\u0648\u0644"
    ],
    "name:und_x_variant":[
        "Qaryat Sab\u2018 Tul\u016bl"
    ],
    "wof:name":"Qaryat Sab` Tulul",
    "wof:placetype":"locality"
},
  "geometry": {"coordinates":[43.9418,35.30346],"type":"Point"}
}