{
  "type": "Feature",
  "properties": {
    "gn:admin1_code":"5.0",
    "gn:admin2_code":"9166596.0",
    "gn:asciiname":"Shaykh Bagh",
    "gn:country_code":"IQ",
    "gn:dem":1519,
    "gn:feature_class":"P",
    "gn:feature_code":"PPL",
    "gn:name":"Shaykh B\u0101gh",
    "gn:population":0,
    "gn:timezone":"Asia/Baghdad",
    "iso:country":"IQ",
    "name:ara_x_preferred":[
        "\u0634\u064a\u062e \u0628\u0627\u063a"
    ],
    "name:und_x_variant":[
        "Shaykh B\u0101gh",
        "Shaykh B\u0101kh",
        "Tal\u0101n",
        "\u062a\u0644\u0627\u0646"
    ],
    "wof:name":"Shaykh Bagh",
    "wof:placetype":"locality"
},
  "geometry": {"coordinates":[45.10361,35.88607000000001],"type":"Point"}
}