{
  "type": "Feature",
  "properties": {
    "gn:admin1_code":"10.0",
    "gn:admin2_code":"9166680.0",
    "gn:asciiname":"Ba Faraj",
    "gn:country_code":"IQ",
    "gn:dem":29,
    "gn:feature_class":"P",
    "gn:feature_code":"PPL",
    "gn:name":"Ba Faraj",
    "gn:population":0,
    "gn:timezone":"Asia/Baghdad",
    "iso:country":"IQ",
    "wof:name":"Ba Faraj",
    "wof:placetype":"locality"
},
  "geometry": {"coordinates":[45.28333,33.45],"type":"Point"}
}