{
  "type": "Feature",
  "properties": {
    "gn:admin1_code":"1.0",
    "gn:admin2_code":"98678.0",
    "gn:asciiname":"Qaryat Abu Ghar",
    "gn:country_code":"IQ",
    "gn:dem":349,
    "gn:feature_class":"P",
    "gn:feature_code":"PPL",
    "gn:name":"Qaryat Ab\u016b Gh\u0101r",
    "gn:population":0,
    "gn:timezone":"Asia/Baghdad",
    "iso:country":"IQ",
    "name:ara_x_preferred":[
        "\u0642\u0631\u064a\u0629 \u0627\u0628\u0648 \u063a\u0627\u0631"
    ],
    "name:und_x_variant":[
        "Qaryat Ab\u016b Gh\u0101r"
    ],
    "wof:name":"Qaryat Abu Ghar",
    "wof:placetype":"locality"
},
  "geometry": {"coordinates":[42.02561,32.34975],"type":"Point"}
}