{
  "type": "Feature",
  "properties": {
    "gn:admin1_code":"15.0",
    "gn:admin2_code":"9166649.0",
    "gn:asciiname":"Qaryat al Hawd",
    "gn:country_code":"IQ",
    "gn:dem":208,
    "gn:feature_class":"P",
    "gn:feature_code":"PPL",
    "gn:name":"Qaryat al \u1e28awd",
    "gn:population":0,
    "gn:timezone":"Asia/Baghdad",
    "iso:country":"IQ",
    "name:ara_x_preferred":[
        "\u0642\u0631\u064a\u0629 \u0627\u0644\u062d\u0648\u062f"
    ],
    "name:und_x_variant":[
        "Al \u1e28awd",
        "Hawd",
        "Al \u1e28awd at Ta\u1e29t\u0101n\u012b",
        "Al \u1e28aws",
        "\u0627\u0644\u062d\u0648\u062f \u0627\u0644\u062a\u062d\u062a\u0627\u0646\u064a",
        "Qaryat al \u1e28awd"
    ],
    "wof:name":"Qaryat al Hawd",
    "wof:placetype":"locality"
},
  "geometry": {"coordinates":[43.29968,35.86526],"type":"Point"}
}