{
  "type": "Feature",
  "properties": {
    "gn:admin1_code":"17.0",
    "gn:admin2_code":"9166629.0",
    "gn:asciiname":"Sayyid Mahdi",
    "gn:country_code":"IQ",
    "gn:dem":26,
    "gn:feature_class":"P",
    "gn:feature_code":"PPL",
    "gn:name":"Sayyid Mahd\u012b",
    "gn:population":0,
    "gn:timezone":"Asia/Baghdad",
    "iso:country":"IQ",
    "name:ara_x_preferred":[
        "\u0633\u064a\u062f \u0645\u0647\u062f\u064a"
    ],
    "name:und_x_variant":[
        "Sayyid Mahd\u012b"
    ],
    "wof:name":"Sayyid Mahdi",
    "wof:placetype":"locality"
},
  "geometry": {"coordinates":[44.53607,32.0697],"type":"Point"}
}