{
  "type": "Feature",
  "properties": {
    "gn:admin1_code":"5.0",
    "gn:admin2_code":"9166600.0",
    "gn:asciiname":"Qulijan Rudu",
    "gn:country_code":"IQ",
    "gn:dem":616,
    "gn:feature_class":"P",
    "gn:feature_code":"PPL",
    "gn:name":"Q\u016bl\u012bj\u0101n R\u016bd\u016b",
    "gn:population":0,
    "gn:timezone":"Asia/Baghdad",
    "iso:country":"IQ",
    "name:ara_x_preferred":[
        "Q\u016bl\u012bj\u0101n R\u016br\u016b"
    ],
    "name:ara_x_variant":[
        "\u0642\u0648\u0644\u064a\u062c\u0627\u0646 \u0631\u0648\u0631\u0648"
    ],
    "name:kur_x_preferred":[
        "Qol\u00eecan Serhed"
    ],
    "name:kur_x_variant":[
        "\u0642\u06c6\u0644\u064a\u062c\u0627\u0646 \u0633\u06d5\u0631\u06be\u06d5\u062f"
    ],
    "name:und_x_variant":[
        "Q\u016bl\u012bj\u0101n R\u016bd\u016b",
        "\u0642\u0648\u0644\u064a\u062c\u0627\u0646 \u0631\u0648\u062f\u0648"
    ],
    "wof:name":"Qulijan Rudu",
    "wof:placetype":"locality"
},
  "geometry": {"coordinates":[45.21877,35.01483],"type":"Point"}
}