{
  "type": "Feature",
  "properties": {
    "gn:admin1_code":"5.0",
    "gn:admin2_code":"96204.0",
    "gn:asciiname":"Mashru' Dujaynah",
    "gn:country_code":"IQ",
    "gn:dem":521,
    "gn:feature_class":"P",
    "gn:feature_code":"PPL",
    "gn:name":"Mashr\u016b\u2018 Dujaynah",
    "gn:population":0,
    "gn:timezone":"Asia/Baghdad",
    "iso:country":"IQ",
    "name:ara_x_preferred":[
        "\u0645\u0634\u0631\u0648\u0639 \u062f\u062c\u064a\u0646\u0629"
    ],
    "name:fas_x_preferred":[
        "\u062f\u0648\u062c\u06cc\u0644\u0647"
    ],
    "name:fas_x_variant":[
        "D\u016bjaylah"
    ],
    "name:und_x_variant":[
        "Dujaylah",
        "Mashr\u016b\u2018 Dujaynah",
        "Dowjaylah"
    ],
    "wof:name":"Mashru' Dujaynah",
    "wof:placetype":"locality"
},
  "geometry": {"coordinates":[45.94472,35.25118],"type":"Point"}
}