{
  "type": "Feature",
  "properties": {
    "gn:admin1_code":"18.0",
    "gn:admin2_code":"6872046.0",
    "gn:asciiname":"'Aydaliyat",
    "gn:country_code":"IQ",
    "gn:dem":147,
    "gn:feature_class":"P",
    "gn:feature_code":"PPL",
    "gn:name":"\u2018\u0100ydal\u012by\u0101t",
    "gn:population":0,
    "gn:timezone":"Asia/Baghdad",
    "iso:country":"IQ",
    "name:ara_x_preferred":[
        "\u0639\u0627\u064a\u062f\u0644\u064a\u0627\u062a"
    ],
    "name:und_x_variant":[
        "\u2018\u0100ydal\u012by\u0101t"
    ],
    "wof:name":"'Aydaliyat",
    "wof:placetype":"locality"
},
  "geometry": {"coordinates":[43.09197,35.18108],"type":"Point"}
}