{
  "type": "Feature",
  "properties": {
    "gn:admin1_code":"11.0",
    "gn:admin2_code":"93817.0",
    "gn:asciiname":"Qaryat Wadi al `Azzab",
    "gn:country_code":"IQ",
    "gn:dem":222,
    "gn:feature_class":"P",
    "gn:feature_code":"PPL",
    "gn:name":"Qaryat W\u0101d\u012b al \u2018Azz\u0101b",
    "gn:population":0,
    "gn:timezone":"Asia/Baghdad",
    "iso:country":"IQ",
    "name:ara_x_preferred":[
        "\u0642\u0631\u064a\u0629 \u0648\u0627\u062f\u064a \u0627\u0644\u0639\u0632\u0627\u0628"
    ],
    "name:kur_x_preferred":[
        "Wad\u00ee Elghurab"
    ],
    "name:kur_x_variant":[
        "\u0648\u0627\u062f\u0649 \u0626\u06d5\u0644\u063a\u0648\u0631\u0627\u0628"
    ],
    "name:und_x_variant":[
        "W\u0101d\u012b al Ghur\u0101b",
        "Wady Al Ghurab",
        "Qaryat W\u0101d\u012b al \u2018Az\u0101b",
        "Qaryat W\u0101d\u012b al \u2018Azz\u0101b"
    ],
    "wof:name":"Qaryat Wadi al `Azzab",
    "wof:placetype":"locality"
},
  "geometry": {"coordinates":[43.44268,35.89745],"type":"Point"}
}