{
  "type": "Feature",
  "properties": {
    "gn:admin1_code":"7.0",
    "gn:asciiname":"Rashid `Uwayd",
    "gn:country_code":"IQ",
    "gn:dem":35,
    "gn:feature_class":"P",
    "gn:feature_code":"PPL",
    "gn:name":"R\u0101shid \u2018Uwayd",
    "gn:population":0,
    "gn:timezone":"Asia/Baghdad",
    "iso:country":"IQ",
    "name:ara_x_preferred":[
        "\u0631\u0627\u0634\u062f \u0639\u0648\u064a\u062f"
    ],
    "name:und_x_variant":[
        "R\u0101shid \u2018Uwayd"
    ],
    "wof:name":"Rashid `Uwayd",
    "wof:placetype":"locality"
},
  "geometry": {"coordinates":[44.37838,32.89757],"type":"Point"}
}