{
  "type": "Feature",
  "properties": {
    "gn:admin1_code":"7.0",
    "gn:admin2_code":"99173.0",
    "gn:asciiname":"Salih al Muhammad",
    "gn:country_code":"IQ",
    "gn:dem":44,
    "gn:feature_class":"P",
    "gn:feature_code":"PPL",
    "gn:name":"\u015e\u0101li\u1e29 al Mu\u1e29ammad",
    "gn:population":0,
    "gn:timezone":"Asia/Baghdad",
    "iso:country":"IQ",
    "name:und_x_variant":[
        "\u015e\u0101li\u1e29 al Mu\u1e29ammad"
    ],
    "wof:name":"Salih al Muhammad",
    "wof:placetype":"locality"
},
  "geometry": {"coordinates":[44.33113,33.44599],"type":"Point"}
}