{
  "type": "Feature",
  "properties": {
    "gn:admin1_code":"5.0",
    "gn:admin2_code":"91176.0",
    "gn:asciiname":"Ranginah",
    "gn:country_code":"IQ",
    "gn:dem":1322,
    "gn:feature_class":"P",
    "gn:feature_code":"PPL",
    "gn:name":"Rang\u012bnah",
    "gn:population":0,
    "gn:timezone":"Asia/Baghdad",
    "iso:country":"IQ",
    "name:ara_x_preferred":[
        "Rin Bin\u0101h"
    ],
    "name:ara_x_variant":[
        "\u0631\u0646\u06af\u064a\u0646\u0629"
    ],
    "name:fas_x_preferred":[
        "\u0631\u0646\u06af\u0646\u0647"
    ],
    "name:kur_x_preferred":[
        "\u1e5eeng\u00eene"
    ],
    "name:kur_x_variant":[
        "\u0695\u06d5\u0646\u06af\u064a\u0646\u06d5"
    ],
    "name:und_x_variant":[
        "B\u0101nj\u012bnah",
        "Rang\u0113na",
        "Rangina",
        "\u0631\u0646 \u0628\u0646\u0627\u0647",
        "Ranganah",
        "Rang\u012bnah"
    ],
    "wof:name":"Ranginah",
    "wof:placetype":"locality"
},
  "geometry": {"coordinates":[45.8041,35.70922],"type":"Point"}
}