{
  "type": "Feature",
  "properties": {
    "gn:admin1_code":"15.0",
    "gn:admin2_code":"9166541.0",
    "gn:asciiname":"Qaryat Qawlan Tabbah",
    "gn:country_code":"IQ",
    "gn:dem":268,
    "gn:feature_class":"P",
    "gn:feature_code":"PPL",
    "gn:name":"Qaryat Qawl\u0101n Tabbah",
    "gn:population":0,
    "gn:timezone":"Asia/Baghdad",
    "iso:country":"IQ",
    "name:ara_x_preferred":[
        "\u0642\u0631\u064a\u0629 \u0642\u0648\u0644\u0627\u0646 \u062a\u0628\u0647"
    ],
    "name:und_x_variant":[
        "Qaryat Qawl\u0101n Tabah"
    ],
    "wof:name":"Qaryat Qawlan Tabbah",
    "wof:placetype":"locality"
},
  "geometry": {"coordinates":[43.23004,36.38341],"type":"Point"}
}