{
  "type": "Feature",
  "properties": {
    "gn:admin1_code":"15.0",
    "gn:admin2_code":"9166649.0",
    "gn:asciiname":"Ash Shakk",
    "gn:country_code":"IQ",
    "gn:dem":293,
    "gn:feature_class":"P",
    "gn:feature_code":"PPL",
    "gn:name":"Ash Shakk",
    "gn:population":0,
    "gn:timezone":"Asia/Baghdad",
    "iso:country":"IQ",
    "name:ara_x_preferred":[
        "\u0627\u0644\u0634\u0643"
    ],
    "name:und_x_variant":[
        "Shaikh",
        "Ash Shakk",
        "Shaykh"
    ],
    "wof:name":"Ash Shakk",
    "wof:placetype":"locality"
},
  "geometry": {"coordinates":[42.97122,36.04888],"type":"Point"}
}