{
  "type": "Feature",
  "properties": {
    "gn:admin1_code":"18.0",
    "gn:admin2_code":"9166616.0",
    "gn:asciiname":"'Abud Sa'id",
    "gn:country_code":"IQ",
    "gn:dem":41,
    "gn:feature_class":"P",
    "gn:feature_code":"PPL",
    "gn:name":"\u2018Ab\u016bd Sa\u2018\u012bd",
    "gn:population":0,
    "gn:timezone":"Asia/Baghdad",
    "iso:country":"IQ",
    "name:ara_x_preferred":[
        "\u0639\u0628\u0648\u062f \u0633\u0639\u064a\u062f"
    ],
    "name:und_x_variant":[
        "\u2018Ab\u016bd Sa\u2018\u012bd"
    ],
    "wof:name":"'Abud Sa'id",
    "wof:placetype":"locality"
},
  "geometry": {"coordinates":[44.32194000000001,33.84741],"type":"Point"}
}