{
  "type": "Feature",
  "properties": {
    "gn:admin1_code":"5.0",
    "gn:admin2_code":"92051.0",
    "gn:asciiname":"Tirshawe",
    "gn:country_code":"IQ",
    "gn:dem":582,
    "gn:feature_class":"P",
    "gn:feature_code":"PPL",
    "gn:name":"T\u00eershawe",
    "gn:population":0,
    "gn:timezone":"Asia/Baghdad",
    "iso:country":"IQ",
    "name:ara_x_preferred":[
        "\u062a\u0631\u0634\u0627\u0648\u0629"
    ],
    "name:kur_x_preferred":[
        "\u062a\u064a\u0631\u0634\u0627\u0648\u06d5"
    ],
    "name:kur_x_variant":[
        "Tirshawa",
        "T\u00eershawe"
    ],
    "name:und_x_variant":[
        "Tirsh\u0101wa",
        "Tirsh\u0101wah",
        "Trshawa"
    ],
    "wof:name":"Tirshawe",
    "wof:placetype":"locality"
},
  "geometry": {"coordinates":[44.76192,36.26942],"type":"Point"}
}