{
  "type": "Feature",
  "properties": {
    "gn:admin1_code":"15.0",
    "gn:admin2_code":"9166608.0",
    "gn:asciiname":"Wasmi al Maruki",
    "gn:country_code":"IQ",
    "gn:dem":310,
    "gn:feature_class":"P",
    "gn:feature_code":"PPL",
    "gn:name":"Wasm\u012b al Mar\u016bk\u012b",
    "gn:population":0,
    "gn:timezone":"Asia/Baghdad",
    "iso:country":"IQ",
    "name:ara_x_preferred":[
        "\u0648\u0633\u0645\u064a \u0627\u0644\u0645\u0631\u0648\u0643\u064a"
    ],
    "name:und_x_variant":[
        "Wasm\u012b al Mar\u016bk\u012b"
    ],
    "wof:name":"Wasmi al Maruki",
    "wof:placetype":"locality"
},
  "geometry": {"coordinates":[41.51392,36.01973],"type":"Point"}
}