{
  "type": "Feature",
  "properties": {
    "gn:admin1_code":"6.0",
    "gn:admin2_code":"99358.0",
    "gn:asciiname":"Fahd al Hammudi",
    "gn:country_code":"IQ",
    "gn:dem":25,
    "gn:feature_class":"P",
    "gn:feature_code":"PPL",
    "gn:name":"Fahd al \u1e28amm\u016bd\u012b",
    "gn:population":0,
    "gn:timezone":"Asia/Baghdad",
    "iso:country":"IQ",
    "name:ara_x_preferred":[
        "\u0641\u0647\u062f \u0627\u0644\u062d\u0645\u0648\u062f\u064a"
    ],
    "name:und_x_variant":[
        "Fahd al \u1e28amm\u016bd\u012b"
    ],
    "wof:name":"Fahd al Hammudi",
    "wof:placetype":"locality"
},
  "geometry": {"coordinates":[44.84099000000001,32.24923],"type":"Point"}
}