{
  "type": "Feature",
  "properties": {
    "gn:admin1_code":"15.0",
    "gn:admin2_code":"9166618.0",
    "gn:asciiname":"Qarah Kharb",
    "gn:country_code":"IQ",
    "gn:dem":287,
    "gn:feature_class":"P",
    "gn:feature_code":"PPL",
    "gn:name":"Qarah Kharb",
    "gn:population":0,
    "gn:timezone":"Asia/Baghdad",
    "iso:country":"IQ",
    "name:ara_x_preferred":[
        "\u0642\u0631\u0647 \u062e\u0631\u0628"
    ],
    "name:kur_x_preferred":[
        "Qere Xerb"
    ],
    "name:kur_x_variant":[
        "\u0642\u06d5\u0631\u06d5 \u062e\u06d5\u0631\u0628"
    ],
    "name:und_x_variant":[
        "Ghuzayl",
        "Qarah Kharb",
        "Qara Kharb"
    ],
    "wof:name":"Qarah Kharb",
    "wof:placetype":"locality"
},
  "geometry": {"coordinates":[43.00777,36.51791],"type":"Point"}
}