{
  "type": "Feature",
  "properties": {
    "gn:admin1_code":"1.0",
    "gn:asciiname":"Nayif al `Ajil",
    "gn:country_code":"IQ",
    "gn:dem":42,
    "gn:feature_class":"P",
    "gn:feature_code":"PPL",
    "gn:name":"N\u0101yif al \u2018Aj\u012bl",
    "gn:population":0,
    "gn:timezone":"Asia/Baghdad",
    "iso:country":"IQ",
    "name:und_x_variant":[
        "Nayef al \u2018Aj\u012bl",
        "N\u0101\u2019if al \u2018Aj\u012bl",
        "N\u0101yif al \u2018Aj\u012bl"
    ],
    "wof:name":"Nayif al `Ajil",
    "wof:placetype":"locality"
},
  "geometry": {"coordinates":[44.16712,33.00897],"type":"Point"}
}