{
  "type": "Feature",
  "properties": {
    "gn:admin1_code":"2.0",
    "gn:admin2_code":"9166549.0",
    "gn:asciiname":"Kut Bu Ghaymish",
    "gn:country_code":"IQ",
    "gn:dem":2,
    "gn:feature_class":"P",
    "gn:feature_code":"PPL",
    "gn:name":"K\u016bt B\u016b Ghaym\u012bsh",
    "gn:population":0,
    "gn:timezone":"Asia/Baghdad",
    "iso:country":"IQ",
    "name:und_x_variant":[
        "K\u016bt B\u016b Ghaym\u012bsh"
    ],
    "wof:name":"Kut Bu Ghaymish",
    "wof:placetype":"locality"
},
  "geometry": {"coordinates":[48.42417,30.03139],"type":"Point"}
}