{
  "type": "Feature",
  "properties": {
    "gn:admin1_code":"14.0",
    "gn:admin2_code":"99610.0",
    "gn:asciiname":"Abd al Wahhab",
    "gn:country_code":"IQ",
    "gn:dem":7,
    "gn:feature_class":"P",
    "gn:feature_code":"PPL",
    "gn:name":"Abd al Wahh\u0101b",
    "gn:population":0,
    "gn:timezone":"Asia/Baghdad",
    "iso:country":"IQ",
    "name:ara_x_preferred":[
        "\u0639\u0628\u062f \u0627\u0644\u0648\u0647\u0627\u0628"
    ],
    "name:und_x_variant":[
        "Abd al Wahh\u0101b"
    ],
    "wof:name":"Abd al Wahhab",
    "wof:placetype":"locality"
},
  "geometry": {"coordinates":[46.88163,31.95585],"type":"Point"}
}