{
  "type": "Feature",
  "properties": {
    "gn:admin1_code":"10.0",
    "gn:admin2_code":"97988.0",
    "gn:asciiname":"Al Hulfayah",
    "gn:country_code":"IQ",
    "gn:dem":39,
    "gn:feature_class":"P",
    "gn:feature_code":"PPL",
    "gn:name":"Al \u1e28ulf\u0101yah",
    "gn:population":0,
    "gn:timezone":"Asia/Baghdad",
    "iso:country":"IQ",
    "name:ara_x_preferred":[
        "\u0627\u0644\u062d\u0644\u0641\u0627\u064a\u0629"
    ],
    "name:und_x_variant":[
        "Al \u1e28ulf\u0101yah"
    ],
    "wof:name":"Al Hulfayah",
    "wof:placetype":"locality"
},
  "geometry": {"coordinates":[44.51335,33.60402],"type":"Point"}
}