{
  "type": "Feature",
  "properties": {
    "gn:admin1_code":"16.0",
    "gn:admin2_code":"99132.0",
    "gn:asciiname":"Tulul ar Ramayli",
    "gn:country_code":"IQ",
    "gn:dem":20,
    "gn:feature_class":"P",
    "gn:feature_code":"PPL",
    "gn:name":"Tul\u016bl ar Ramayl\u012b",
    "gn:population":0,
    "gn:timezone":"Asia/Baghdad",
    "iso:country":"IQ",
    "name:ara_x_preferred":[
        "\u062a\u0644\u0648\u0644 \u0627\u0644\u0631\u0645\u064a\u0644\u064a"
    ],
    "name:und_x_variant":[
        "Tul\u016bl ar Ramayl\u012b"
    ],
    "wof:name":"Tulul ar Ramayli",
    "wof:placetype":"locality"
},
  "geometry": {"coordinates":[45.98271,32.59955],"type":"Point"}
}