{
  "type": "Feature",
  "properties": {
    "gn:admin1_code":"5.0",
    "gn:admin2_code":"9166594.0",
    "gn:asciiname":"Bakhshi Muhammad 'Abd al Qadr",
    "gn:country_code":"IQ",
    "gn:dem":573,
    "gn:feature_class":"P",
    "gn:feature_code":"PPL",
    "gn:name":"Bakhsh\u012b Mu\u1e29ammad \u2018Abd al Q\u0101dr",
    "gn:population":0,
    "gn:timezone":"Asia/Baghdad",
    "iso:country":"IQ",
    "name:ara_x_preferred":[
        "\u064a\u062e\u0634\u064a \u0645\u062d\u0645\u062f \u0639\u0628\u062f \u0627\u0644\u0642\u0627\u062f\u0631"
    ],
    "name:kur_x_preferred":[
        "Paxsh\u00ee"
    ],
    "name:kur_x_variant":[
        "\u067e\u0627\u062e\u0634\u0649"
    ],
    "name:und_x_variant":[
        "Chwukh",
        "Bakhsh\u012b Mu\u1e29ammad \u2018Abd al Q\u0101dr",
        "\u0628\u062e\u0634\u064a \u0645\u062d\u0645\u062f \u0639\u0628\u062f \u0627\u0644\u0642\u0627\u062f\u0631",
        "Yakhsh\u012b",
        "Yakhsh\u012b Mu\u1e29ammad \u2018Abd al Q\u0101dr"
    ],
    "wof:name":"Bakhshi Muhammad 'Abd al Qadr",
    "wof:placetype":"locality"
},
  "geometry": {"coordinates":[45.69455,35.29777],"type":"Point"}
}