{
  "type": "Feature",
  "properties": {
    "gn:admin1_code":"18.0",
    "gn:admin2_code":"6805736.0",
    "gn:asciiname":"Qaryat Khalaf al Khatir",
    "gn:country_code":"IQ",
    "gn:dem":54,
    "gn:feature_class":"P",
    "gn:feature_code":"PPL",
    "gn:name":"Qaryat Khalaf al Kh\u0101\u0163ir",
    "gn:population":0,
    "gn:timezone":"Asia/Baghdad",
    "iso:country":"IQ",
    "name:ara_x_preferred":[
        "\u0642\u0631\u064a\u0629 \u062e\u0644\u0641 \u0627\u0644\u062e\u0627\u0637\u0631"
    ],
    "name:und_x_variant":[
        "Qaryat Khalaf al Kh\u0101\u0163ir"
    ],
    "wof:name":"Qaryat Khalaf al Khatir",
    "wof:placetype":"locality"
},
  "geometry": {"coordinates":[44.06121,34.05495999999999],"type":"Point"}
}