{
  "type": "Feature",
  "properties": {
    "gn:admin1_code":"5.0",
    "gn:admin2_code":"97416.0",
    "gn:asciiname":"Kalahrashi Muhammad Sulayman",
    "gn:country_code":"IQ",
    "gn:dem":701,
    "gn:feature_class":"P",
    "gn:feature_code":"PPL",
    "gn:name":"Kalahrash\u012b Mu\u1e29ammad Sulaym\u0101n",
    "gn:population":0,
    "gn:timezone":"Asia/Baghdad",
    "iso:country":"IQ",
    "name:ara_x_preferred":[
        "\u0643\u0644\u0629 \u0631\u0634\u064a \u0645\u062d\u0645\u062f \u0633\u0644\u064a\u0645\u0627\u0646"
    ],
    "name:kur_x_preferred":[
        "Kele \u1e5eesh\u00ee"
    ],
    "name:kur_x_variant":[
        "\u0643\u06d5\u0644\u06d5 \u0695\u06d5\u0634\u0649 \u0628\u0686\u0648\u0643",
        "\u0643\u06d5\u0644\u06d5 \u0695\u06d5\u0634\u0649",
        "Kele \u1e5eesh\u00ee Bchuk"
    ],
    "name:und_x_variant":[
        "Kalahrash\u012b Mu\u1e29ammad Sulaym\u0101n",
        "Kalarash-i \u1e28ama Sl\u0113m\u0101n",
        "Kalarashi Hama Sleman"
    ],
    "wof:name":"Kalahrashi Muhammad Sulayman",
    "wof:placetype":"locality"
},
  "geometry": {"coordinates":[45.15785,35.33638],"type":"Point"}
}