{
  "type": "Feature",
  "properties": {
    "gn:admin1_code":"6.0",
    "gn:admin2_code":"99358.0",
    "gn:asciiname":"Salim Habib",
    "gn:country_code":"IQ",
    "gn:dem":25,
    "gn:feature_class":"P",
    "gn:feature_code":"PPL",
    "gn:name":"S\u0101lim \u1e28ab\u012bb",
    "gn:population":0,
    "gn:timezone":"Asia/Baghdad",
    "iso:country":"IQ",
    "name:ara_x_preferred":[
        "\u0633\u0627\u0644\u0645 \u062d\u0628\u064a\u0628"
    ],
    "name:und_x_variant":[
        "S\u0101lim \u1e28ab\u012bb"
    ],
    "wof:name":"Salim Habib",
    "wof:placetype":"locality"
},
  "geometry": {"coordinates":[44.9875,32.4364],"type":"Point"}
}