{
  "type": "Feature",
  "properties": {
    "gn:admin1_code":"11.0",
    "gn:admin2_code":"95444.0",
    "gn:asciiname":"Kirdrash",
    "gn:country_code":"IQ",
    "gn:dem":768,
    "gn:feature_class":"P",
    "gn:feature_code":"PPL",
    "gn:name":"Kirdrash",
    "gn:population":0,
    "gn:timezone":"Asia/Baghdad",
    "iso:country":"IQ",
    "name:ara_x_preferred":[
        "\u0643\u0631\u062f\u0631\u0634"
    ],
    "name:kur_x_preferred":[
        "Gird\u00eesh"
    ],
    "name:kur_x_variant":[
        "\u06af\u0631\u062f\u064a\u0634"
    ],
    "name:und_x_variant":[
        "Girdesh",
        "G\u012brd\u012bsh",
        "Kirdrash"
    ],
    "wof:name":"Kirdrash",
    "wof:placetype":"locality"
},
  "geometry": {"coordinates":[44.2306,36.12478],"type":"Point"}
}