{
  "type": "Feature",
  "properties": {
    "gn:admin1_code":"10.0",
    "gn:admin2_code":"97988.0",
    "gn:asciiname":"Qaryat al Amiriyah",
    "gn:country_code":"IQ",
    "gn:dem":44,
    "gn:feature_class":"P",
    "gn:feature_code":"PPL",
    "gn:name":"Qaryat al Am\u012br\u012byah",
    "gn:population":0,
    "gn:timezone":"Asia/Baghdad",
    "iso:country":"IQ",
    "name:ara_x_preferred":[
        "\u0642\u0631\u064a\u0629 \u0627\u0644\u0627\u0645\u064a\u0631\u064a\u0629"
    ],
    "name:und_x_variant":[
        "Qaryat al Am\u012br\u012byah"
    ],
    "wof:name":"Qaryat al Amiriyah",
    "wof:placetype":"locality"
},
  "geometry": {"coordinates":[44.5308,33.66918],"type":"Point"}
}