{
  "type": "Feature",
  "properties": {
    "gn:admin1_code":"11.0",
    "gn:admin2_code":"93817.0",
    "gn:asciiname":"Kulkatish",
    "gn:country_code":"IQ",
    "gn:dem":210,
    "gn:feature_class":"P",
    "gn:feature_code":"PPL",
    "gn:name":"K\u016blkat\u012bsh",
    "gn:population":0,
    "gn:timezone":"Asia/Baghdad",
    "iso:country":"IQ",
    "name:ara_x_preferred":[
        "\u0643\u0648\u0644\u0643\u062a\u064a\u0634"
    ],
    "name:kur_x_preferred":[
        "Gul Kishmish"
    ],
    "name:kur_x_variant":[
        "Gu\u0142 Kshm\u00eesh",
        "\u06af\u0648\u06b5 \u0643\u0634\u0645\u064a\u0634"
    ],
    "name:und_x_variant":[
        "Ak\u016bl K\u0101tish\u012b",
        "K\u016bl K\u0101tish",
        "K\u016bl K\u0101m\u012bshah",
        "\u0643\u0648\u0644 \u0643\u0627\u0645\u064a\u0634\u0647",
        "K\u016blkat\u012bsh",
        "Gul Kishmish"
    ],
    "wof:name":"Kulkatish",
    "wof:placetype":"locality"
},
  "geometry": {"coordinates":[43.58571,35.62079],"type":"Point"}
}