{
  "type": "Feature",
  "properties": {
    "gn:admin1_code":"18.0",
    "gn:admin2_code":"90148.0",
    "gn:asciiname":"Khalaf as Suwadi",
    "gn:country_code":"IQ",
    "gn:dem":122,
    "gn:feature_class":"P",
    "gn:feature_code":"PPL",
    "gn:name":"Khalaf as Suw\u0101d\u012b",
    "gn:population":0,
    "gn:timezone":"Asia/Baghdad",
    "iso:country":"IQ",
    "name:ara_x_preferred":[
        "\u062e\u0644\u0641 \u0627\u0644\u0633\u0648\u0627\u062f\u064a"
    ],
    "name:und_x_variant":[
        "Khalaf as Suw\u0101d\u012b"
    ],
    "wof:name":"Khalaf as Suwadi",
    "wof:placetype":"locality"
},
  "geometry": {"coordinates":[43.47378,34.90094],"type":"Point"}
}