{
  "type": "Feature",
  "properties": {
    "gn:admin1_code":"15.0",
    "gn:admin2_code":"9166541.0",
    "gn:asciiname":"Kuwaylan Bulan",
    "gn:country_code":"IQ",
    "gn:dem":335,
    "gn:feature_class":"P",
    "gn:feature_code":"PPL",
    "gn:name":"Kuwayl\u0101n B\u016bl\u0101n",
    "gn:population":0,
    "gn:timezone":"Asia/Baghdad",
    "iso:country":"IQ",
    "name:ara_x_preferred":[
        "\u0643\u0648\u064a\u0644\u0627\u0646 \u0628\u0648\u0644\u0627\u0646"
    ],
    "name:kur_x_preferred":[
        "Bw\u00eelan"
    ],
    "name:kur_x_variant":[
        "\u0628\u0648\u064a\u0644\u0627\u0646"
    ],
    "name:und_x_variant":[
        "Buailan",
        "Kuwayl\u0101n B\u016bl\u0101n"
    ],
    "wof:name":"Kuwaylan Bulan",
    "wof:placetype":"locality"
},
  "geometry": {"coordinates":[43.65151,36.35113],"type":"Point"}
}