{
  "type": "Feature",
  "properties": {
    "gn:admin1_code":"5.0",
    "gn:admin2_code":"97416.0",
    "gn:asciiname":"'Gulbakh-i Khwaru",
    "gn:country_code":"IQ",
    "gn:dem":513,
    "gn:feature_class":"P",
    "gn:feature_code":"PPL",
    "gn:name":"\u2018Gulb\u0101kh-i Khw\u0101r\u016b",
    "gn:population":0,
    "gn:timezone":"Asia/Baghdad",
    "iso:country":"IQ",
    "name:ara_x_preferred":[
        "\u2018Gulb\u0101kh-i Khw\u0101r\u016b"
    ],
    "wof:name":"'Gulbakh-i Khwaru",
    "wof:placetype":"locality"
},
  "geometry": {"coordinates":[44.98333,35.23333],"type":"Point"}
}