{
  "type": "Feature",
  "properties": {
    "gn:admin1_code":"15.0",
    "gn:admin2_code":"9166620.0",
    "gn:asciiname":"Qazal Kand",
    "gn:country_code":"IQ",
    "gn:dem":521,
    "gn:feature_class":"P",
    "gn:feature_code":"PPL",
    "gn:name":"Qazal Kand",
    "gn:population":0,
    "gn:timezone":"Asia/Baghdad",
    "iso:country":"IQ",
    "name:ara_x_preferred":[
        "\u0642\u0632\u0644 \u0643\u0646\u062f"
    ],
    "name:kur_x_preferred":[
        "Qizil Kand"
    ],
    "name:kur_x_variant":[
        "\u0642\u0632\u0644 \u0643\u06d5\u0646\u062f"
    ],
    "name:und_x_variant":[
        "Qizil K\u0101nah",
        "Qazal Kand"
    ],
    "wof:name":"Qazal Kand",
    "wof:placetype":"locality"
},
  "geometry": {"coordinates":[41.79178,36.31666],"type":"Point"}
}