{
  "type": "Feature",
  "properties": {
    "gn:admin1_code":"7.0",
    "gn:admin2_code":"9166569.0",
    "gn:asciiname":"Fayyad 'Abd",
    "gn:country_code":"IQ",
    "gn:dem":39,
    "gn:feature_class":"P",
    "gn:feature_code":"PPL",
    "gn:name":"Fayy\u0101\u1e11 \u2018Abd",
    "gn:population":0,
    "gn:timezone":"Asia/Baghdad",
    "iso:country":"IQ",
    "name:ara_x_preferred":[
        "\u0641\u064a\u0627\u0636 \u0639\u0628\u062f"
    ],
    "name:und_x_variant":[
        "Fayy\u0101\u1e11 \u2018Abd"
    ],
    "wof:name":"Fayyad 'Abd",
    "wof:placetype":"locality"
},
  "geometry": {"coordinates":[44.19178,33.63058],"type":"Point"}
}