{
  "type": "Feature",
  "properties": {
    "gn:admin1_code":"18.0",
    "gn:admin2_code":"6804454.0",
    "gn:asciiname":"Qaryat al Jajaniyah",
    "gn:country_code":"IQ",
    "gn:dem":192,
    "gn:feature_class":"P",
    "gn:feature_code":"PPL",
    "gn:name":"Qaryat al J\u0101j\u0101n\u012byah",
    "gn:population":0,
    "gn:timezone":"Asia/Baghdad",
    "iso:country":"IQ",
    "name:ara_x_preferred":[
        "\u0642\u0631\u064a\u0629 \u0627\u0644\u062c\u0627\u062c\u0627\u0646\u064a\u0629"
    ],
    "name:und_x_variant":[
        "Qaryat al J\u0101j\u0101n\u012byah"
    ],
    "wof:name":"Qaryat al Jajaniyah",
    "wof:placetype":"locality"
},
  "geometry": {"coordinates":[42.99775,35.46236],"type":"Point"}
}