{
  "type": "Feature",
  "properties": {
    "gn:admin1_code":"3.0",
    "gn:admin2_code":"9166626.0",
    "gn:asciiname":"As Sarhah",
    "gn:country_code":"IQ",
    "gn:dem":8,
    "gn:feature_class":"P",
    "gn:feature_code":"PPL",
    "gn:name":"As Sar\u1e29ah",
    "gn:population":0,
    "gn:timezone":"Asia/Baghdad",
    "iso:country":"IQ",
    "name:ara_x_preferred":[
        "\u0627\u0644\u0633\u0631\u062d\u0629"
    ],
    "name:und_x_variant":[
        "As Sar\u1e29ah"
    ],
    "wof:name":"As Sarhah",
    "wof:placetype":"locality"
},
  "geometry": {"coordinates":[45.64146,31.18287],"type":"Point"}
}