{
  "type": "Feature",
  "properties": {
    "gn:admin1_code":"7.0",
    "gn:admin2_code":"99101.0",
    "gn:asciiname":"Salman Kazim",
    "gn:country_code":"IQ",
    "gn:dem":34,
    "gn:feature_class":"P",
    "gn:feature_code":"PPL",
    "gn:name":"Salm\u0101n K\u0101z\u0327im",
    "gn:population":0,
    "gn:timezone":"Asia/Baghdad",
    "iso:country":"IQ",
    "name:ara_x_preferred":[
        "\u0633\u0644\u0645\u0627\u0646 \u0643\u0627\u0638\u0645"
    ],
    "name:und_x_variant":[
        "Salm\u0101n K\u0101z\u0327im"
    ],
    "wof:name":"Salman Kazim",
    "wof:placetype":"locality"
},
  "geometry": {"coordinates":[44.4061,33.13225],"type":"Point"}
}