{
  "type": "Feature",
  "properties": {
    "gn:admin1_code":"18.0",
    "gn:admin2_code":"9166598.0",
    "gn:asciiname":"Qushlan",
    "gn:country_code":"IQ",
    "gn:dem":275,
    "gn:feature_class":"P",
    "gn:feature_code":"PPL",
    "gn:name":"Q\u016bshl\u0101n",
    "gn:population":0,
    "gn:timezone":"Asia/Baghdad",
    "iso:country":"IQ",
    "name:ara_x_preferred":[
        "\u0642\u0648\u0634\u0644\u0627\u0646"
    ],
    "name:ara_x_variant":[
        "Q\u016bshl\u0101n"
    ],
    "name:und_x_variant":[
        "Qush\u0101l\u0101n"
    ],
    "wof:name":"Qushlan",
    "wof:placetype":"locality"
},
  "geometry": {"coordinates":[44.67837,34.9892],"type":"Point"}
}