{
  "type": "Feature",
  "properties": {
    "gn:admin1_code":"5.0",
    "gn:admin2_code":"98464.0",
    "gn:asciiname":"Zirkuwayz",
    "gn:country_code":"IQ",
    "gn:dem":947,
    "gn:feature_class":"P",
    "gn:feature_code":"PPL",
    "gn:name":"Zirkuwayz",
    "gn:population":0,
    "gn:timezone":"Asia/Baghdad",
    "iso:country":"IQ",
    "name:ara_x_preferred":[
        "\u0632\u0631\u0643\u0648\u064a\u0632"
    ],
    "name:kur_x_preferred":[
        "Z\u1e5fgw\u00eaz"
    ],
    "name:kur_x_variant":[
        "\u0632\u0695\u06af\u0648\u06ce\u0632"
    ],
    "name:und_x_variant":[
        "Zergwez"
    ],
    "wof:name":"Zirkuwayz",
    "wof:placetype":"locality"
},
  "geometry": {"coordinates":[45.42665,35.42514],"type":"Point"}
}