{
  "type": "Feature",
  "properties": {
    "gn:admin1_code":"4.0",
    "gn:admin2_code":"6850588.0",
    "gn:asciiname":"Muhsin Na'man",
    "gn:country_code":"IQ",
    "gn:dem":15,
    "gn:feature_class":"P",
    "gn:feature_code":"PPL",
    "gn:name":"Mu\u1e29sin Na\u2018m\u0101n",
    "gn:population":0,
    "gn:timezone":"Asia/Baghdad",
    "iso:country":"IQ",
    "name:ara_x_preferred":[
        "\u0645\u062d\u0633\u0646 \u0646\u0639\u0645\u0627\u0646"
    ],
    "name:und_x_variant":[
        "Muhsin \u0101l Nom\u0101n",
        "Mu\u1e29sin \u0100l Nu\u2018m\u0101n",
        "Mu\u1e29sin Na\u2018m\u0101n"
    ],
    "wof:name":"Muhsin Na'man",
    "wof:placetype":"locality"
},
  "geometry": {"coordinates":[44.87114,31.47336],"type":"Point"}
}