{
  "type": "Feature",
  "properties": {
    "gn:admin1_code":"3.0",
    "gn:admin2_code":"9166568.0",
    "gn:asciiname":"Hajiyat Bani Huchaym",
    "gn:country_code":"IQ",
    "gn:dem":15,
    "gn:feature_class":"P",
    "gn:feature_code":"PPL",
    "gn:name":"\u1e28\u0101j\u012byat Ban\u012b \u1e28uchaym",
    "gn:population":0,
    "gn:timezone":"Asia/Baghdad",
    "iso:country":"IQ",
    "name:ara_x_preferred":[
        "\u062d\u0627\u062c\u064a\u0629 \u0628\u0646\u064a \u062d\u0686\u064a\u0645"
    ],
    "name:und_x_variant":[
        "\u1e28\u0101j\u012byat Ban\u012b \u1e28uchaym"
    ],
    "wof:name":"Hajiyat Bani Huchaym",
    "wof:placetype":"locality"
},
  "geometry": {"coordinates":[45.22469,31.45088],"type":"Point"}
}