{
  "type": "Feature",
  "properties": {
    "gn:admin1_code":"7.0",
    "gn:admin2_code":"99173.0",
    "gn:asciiname":"Ash Shaykh Ahmad",
    "gn:cc2":"IQ",
    "gn:country_code":"IQ",
    "gn:dem":38,
    "gn:feature_class":"P",
    "gn:feature_code":"PPL",
    "gn:name":"Ash Shaykh A\u1e29mad",
    "gn:population":0,
    "gn:timezone":"Asia/Baghdad",
    "iso:country":"IQ",
    "name:und_x_variant":[
        "Ash Shaikh Ahmad",
        "Ash Shaykh A\u1e29mad"
    ],
    "wof:name":"Ash Shaykh Ahmad",
    "wof:placetype":"locality"
},
  "geometry": {"coordinates":[44.28333,33.48333],"type":"Point"}
}