{
  "type": "Feature",
  "properties": {
    "gn:admin1_code":"15.0",
    "gn:admin2_code":"90392.0",
    "gn:asciiname":"Hamruk",
    "gn:country_code":"IQ",
    "gn:dem":454,
    "gn:feature_class":"P",
    "gn:feature_code":"PPL",
    "gn:name":"\u1e28amr\u016bk",
    "gn:population":0,
    "gn:timezone":"Asia/Baghdad",
    "iso:country":"IQ",
    "name:ara_x_preferred":[
        "\u062d\u0645\u0631\u0648\u0643"
    ],
    "name:kur_x_preferred":[
        "\u1e26efrok"
    ],
    "name:kur_x_variant":[
        "\u062d\u06d5\u0641\u0631\u06c6\u0643"
    ],
    "name:und_x_variant":[
        "Hafruk",
        "Khamr\u016bk",
        "\u1e28amr\u016bk"
    ],
    "wof:name":"Hamruk",
    "wof:placetype":"locality"
},
  "geometry": {"coordinates":[42.67963,36.65551],"type":"Point"}
}