{
  "type": "Feature",
  "properties": {
    "gn:admin1_code":"17.0",
    "gn:admin2_code":"98861.0",
    "gn:asciiname":"'Arab ar Ruhaymah",
    "gn:country_code":"IQ",
    "gn:dem":38,
    "gn:feature_class":"P",
    "gn:feature_code":"PPL",
    "gn:name":"\u2018Arab ar Ru\u1e29aymah",
    "gn:population":0,
    "gn:timezone":"Asia/Baghdad",
    "iso:country":"IQ",
    "name:ara_x_preferred":[
        "\u0639\u0631\u0628 \u0627\u0644\u0631\u062d\u064a\u0645\u0647"
    ],
    "name:und_x_variant":[
        "Ruhaima",
        "\u2018Arab ar Ruhaima",
        "Ar Ru\u1e29aymah",
        "\u2018Arab ar Ru\u1e29aymah"
    ],
    "wof:name":"'Arab ar Ruhaymah",
    "wof:placetype":"locality"
},
  "geometry": {"coordinates":[44.10275,31.95791],"type":"Point"}
}