{
  "type": "Feature",
  "properties": {
    "gn:admin1_code":"5.0",
    "gn:admin2_code":"98464.0",
    "gn:asciiname":"Bah Bi",
    "gn:country_code":"IQ",
    "gn:dem":878,
    "gn:feature_class":"P",
    "gn:feature_code":"PPL",
    "gn:name":"Bah B\u012b",
    "gn:population":0,
    "gn:timezone":"Asia/Baghdad",
    "iso:country":"IQ",
    "name:ara_x_preferred":[
        "\u0628\u0628\u064a"
    ],
    "name:und_x_variant":[
        "Babay",
        "Bap\u0113"
    ],
    "wof:name":"Bah Bi",
    "wof:placetype":"locality"
},
  "geometry": {"coordinates":[45.22848,35.57246],"type":"Point"}
}