{
  "type": "Feature",
  "properties": {
    "gn:admin1_code":"2.0",
    "gn:admin2_code":"9166563.0",
    "gn:asciiname":"'Ali al Hasan",
    "gn:country_code":"IQ",
    "gn:dem":4,
    "gn:feature_class":"P",
    "gn:feature_code":"PPL",
    "gn:name":"\u2018Al\u012b al \u1e28asan",
    "gn:population":0,
    "gn:timezone":"Asia/Baghdad",
    "iso:country":"IQ",
    "name:und_x_variant":[
        "\u2018Al\u012b al \u1e28asan"
    ],
    "wof:name":"'Ali al Hasan",
    "wof:placetype":"locality"
},
  "geometry": {"coordinates":[47.28333,30.93333],"type":"Point"}
}