{
  "type": "Feature",
  "properties": {
    "gn:admin1_code":"13.0",
    "gn:admin2_code":"94786.0",
    "gn:asciiname":"Shawraw",
    "gn:country_code":"IQ",
    "gn:dem":351,
    "gn:feature_class":"P",
    "gn:feature_code":"PPL",
    "gn:name":"Shawr\u0101w",
    "gn:population":0,
    "gn:timezone":"Asia/Baghdad",
    "iso:country":"IQ",
    "name:ara_x_preferred":[
        "\u0634\u0648\u0631\u0627\u0648"
    ],
    "name:kur_x_preferred":[
        "Suara"
    ],
    "name:kur_x_variant":[
        "Suare",
        "\u0633\u0648\u0627\u0631\u06d5"
    ],
    "name:und_x_variant":[
        "Shar\u0101u",
        "Sharaw",
        "Shawr\u0101w",
        "Suara"
    ],
    "wof:name":"Shawraw",
    "wof:placetype":"locality"
},
  "geometry": {"coordinates":[44.37227,35.50925],"type":"Point"}
}