{
  "type": "Feature",
  "properties": {
    "gn:admin1_code":"4.0",
    "gn:admin2_code":"99763.0",
    "gn:asciiname":"Muhsin Karkash",
    "gn:country_code":"IQ",
    "gn:dem":20,
    "gn:feature_class":"P",
    "gn:feature_code":"PPL",
    "gn:name":"Mu\u1e29sin Karkash",
    "gn:population":0,
    "gn:timezone":"Asia/Baghdad",
    "iso:country":"IQ",
    "name:ara_x_preferred":[
        "\u0645\u062d\u0633\u0646 \u0643\u0631\u0643\u0634"
    ],
    "name:und_x_variant":[
        "Mu\u1e29sin Karkash"
    ],
    "wof:name":"Muhsin Karkash",
    "wof:placetype":"locality"
},
  "geometry": {"coordinates":[44.78506,31.8086],"type":"Point"}
}