{
  "type": "Feature",
  "properties": {
    "gn:admin1_code":"18.0",
    "gn:admin2_code":"6805736.0",
    "gn:asciiname":"'Ali Za'in",
    "gn:country_code":"IQ",
    "gn:dem":47,
    "gn:feature_class":"P",
    "gn:feature_code":"PPL",
    "gn:name":"\u2018Al\u012b Z\u0327a\u2018\u012bn",
    "gn:population":0,
    "gn:timezone":"Asia/Baghdad",
    "iso:country":"IQ",
    "name:ara_x_preferred":[
        "\u0639\u0644\u064a \u0638\u0639\u064a\u0646"
    ],
    "name:und_x_variant":[
        "\u2018Al\u012b Z\u0327a\u2018\u012bn"
    ],
    "wof:name":"'Ali Za'in",
    "wof:placetype":"locality"
},
  "geometry": {"coordinates":[44.04015,33.92002],"type":"Point"}
}