{
  "type": "Feature",
  "properties": {
    "gn:admin1_code":"18.0",
    "gn:admin2_code":"6872046.0",
    "gn:asciiname":"'Abud 'Abid",
    "gn:country_code":"IQ",
    "gn:dem":68,
    "gn:feature_class":"P",
    "gn:feature_code":"PPL",
    "gn:name":"\u2018Ab\u016bd \u2018\u0100bid",
    "gn:population":0,
    "gn:timezone":"Asia/Baghdad",
    "iso:country":"IQ",
    "name:ara_x_preferred":[
        "\u0639\u0628\u0648\u062f \u0639\u0627\u0628\u062f"
    ],
    "name:ara_x_variant":[
        "\u2018Ab\u016bd \u2018\u0100bid"
    ],
    "wof:name":"'Abud 'Abid",
    "wof:placetype":"locality"
},
  "geometry": {"coordinates":[43.08649000000001,34.61014],"type":"Point"}
}