{
  "type": "Feature",
  "properties": {
    "gn:admin1_code":"6.0",
    "gn:admin2_code":"99358.0",
    "gn:asciiname":"Hajj Ma'arij 'Akrab",
    "gn:country_code":"IQ",
    "gn:dem":26,
    "gn:feature_class":"P",
    "gn:feature_code":"PPL",
    "gn:name":"\u1e28\u0101jj Ma\u2018\u0101rij \u2018Akrab",
    "gn:population":0,
    "gn:timezone":"Asia/Baghdad",
    "iso:country":"IQ",
    "name:ara_x_preferred":[
        "\u062d\u0627\u062c \u0645\u0639\u0627\u0631\u062c \u0639\u0643\u0631\u0628"
    ],
    "name:und_x_variant":[
        "\u1e28\u0101jj Ma\u2018\u0101rij \u2018Akrab"
    ],
    "wof:name":"Hajj Ma'arij 'Akrab",
    "wof:placetype":"locality"
},
  "geometry": {"coordinates":[44.6967,32.24037],"type":"Point"}
}