{
  "type": "Feature",
  "properties": {
    "gn:admin1_code":"7.0",
    "gn:admin2_code":"9166545.0",
    "gn:asciiname":"Qaryat Hish al Ula",
    "gn:country_code":"IQ",
    "gn:dem":37,
    "gn:feature_class":"P",
    "gn:feature_code":"PPL",
    "gn:name":"Qaryat H\u012bsh al \u016al\u00e1",
    "gn:population":0,
    "gn:timezone":"Asia/Baghdad",
    "iso:country":"IQ",
    "name:ara_x_preferred":[
        "\u0642\u0631\u064a\u0629 \u0647\u064a\u0634 \u0623\u0644\u0623\u0648\u0644\u0649"
    ],
    "name:und_x_variant":[
        "Qaryat H\u012bsh al \u016al\u00e1"
    ],
    "wof:name":"Qaryat Hish al Ula",
    "wof:placetype":"locality"
},
  "geometry": {"coordinates":[44.38135,33.21955],"type":"Point"}
}