{
  "type": "Feature",
  "properties": {
    "gn:admin1_code":"6.0",
    "gn:admin2_code":"99358.0",
    "gn:asciiname":"Shallal Muhammad",
    "gn:country_code":"IQ",
    "gn:dem":27,
    "gn:feature_class":"P",
    "gn:feature_code":"PPL",
    "gn:name":"Shall\u0101l Mu\u1e29ammad",
    "gn:population":0,
    "gn:timezone":"Asia/Baghdad",
    "iso:country":"IQ",
    "name:ara_x_preferred":[
        "\u0634\u0644\u0627\u0644 \u0645\u062d\u0645\u062f"
    ],
    "name:und_x_variant":[
        "Shall\u0101l Mu\u1e29ammad"
    ],
    "wof:name":"Shallal Muhammad",
    "wof:placetype":"locality"
},
  "geometry": {"coordinates":[44.88543,32.26794],"type":"Point"}
}