{
  "type": "Feature",
  "properties": {
    "gn:admin1_code":"18.0",
    "gn:admin2_code":"90148.0",
    "gn:asciiname":"Raml Ahmad",
    "gn:country_code":"IQ",
    "gn:dem":124,
    "gn:feature_class":"P",
    "gn:feature_code":"PPL",
    "gn:name":"Raml A\u1e29mad",
    "gn:population":0,
    "gn:timezone":"Asia/Baghdad",
    "iso:country":"IQ",
    "name:ara_x_preferred":[
        "\u0631\u0645\u0644 \u0627\u062d\u0645\u062f"
    ],
    "name:und_x_variant":[
        "Raml A\u1e29mad"
    ],
    "wof:name":"Raml Ahmad",
    "wof:placetype":"locality"
},
  "geometry": {"coordinates":[43.48195,34.5275],"type":"Point"}
}