{
  "type": "Feature",
  "properties": {
    "gn:admin1_code":"10.0",
    "gn:admin2_code":"99063.0",
    "gn:asciiname":"Kazim ad Dahshan",
    "gn:country_code":"IQ",
    "gn:dem":45,
    "gn:feature_class":"P",
    "gn:feature_code":"PPL",
    "gn:name":"K\u0101z\u0327im ad Dahshan",
    "gn:population":0,
    "gn:timezone":"Asia/Baghdad",
    "iso:country":"IQ",
    "name:ara_x_preferred":[
        "\u0643\u0627\u0638\u0645 \u0627\u0644\u062f\u0647\u0634\u0646"
    ],
    "name:und_x_variant":[
        "K\u0101z\u0327im ad Dahshan"
    ],
    "wof:name":"Kazim ad Dahshan",
    "wof:placetype":"locality"
},
  "geometry": {"coordinates":[44.56894000000001,33.72501],"type":"Point"}
}