{
  "type": "Feature",
  "properties": {
    "gn:admin1_code":"13.0",
    "gn:asciiname":"Sartu",
    "gn:country_code":"IQ",
    "gn:dem":279,
    "gn:feature_class":"P",
    "gn:feature_code":"PPL",
    "gn:name":"Sart\u016b",
    "gn:population":0,
    "gn:timezone":"Asia/Baghdad",
    "iso:country":"IQ",
    "name:ara_x_preferred":[
        "\u0633\u0631\u062a\u0648"
    ],
    "name:kur_x_preferred":[
        "Sert\u00fb"
    ],
    "name:kur_x_variant":[
        "Sartoo",
        "\u0633\u06d5\u0631\u062a\u0648\u0648"
    ],
    "name:und_x_variant":[
        "Sarl\u016b",
        "Sart\u016b"
    ],
    "wof:name":"Sartu",
    "wof:placetype":"locality"
},
  "geometry": {"coordinates":[44.04587,35.70767],"type":"Point"}
}