{
  "type": "Feature",
  "properties": {
    "gn:admin1_code":"6.0",
    "gn:admin2_code":"99358.0",
    "gn:asciiname":"Al Mazhar",
    "gn:country_code":"IQ",
    "gn:dem":29,
    "gn:feature_class":"P",
    "gn:feature_code":"PPLL",
    "gn:name":"\u0100l Maz\u0327har",
    "gn:population":0,
    "gn:timezone":"Asia/Baghdad",
    "iso:country":"IQ",
    "name:ara_x_preferred":[
        "\u0627\u0644 \u0645\u0638\u0647\u0631"
    ],
    "name:und_x_variant":[
        "\u0100l Maz\u0327har"
    ],
    "wof:name":"Al Mazhar",
    "wof:placetype":"locality"
},
  "geometry": {"coordinates":[44.79427,32.26741],"type":"Point"}
}