{
  "type": "Feature",
  "properties": {
    "gn:admin1_code":"4.0",
    "gn:admin2_code":"6850588.0",
    "gn:asciiname":"Murayhij Al Hajj Hamy",
    "gn:cc2":"IQ",
    "gn:country_code":"IQ",
    "gn:dem":15,
    "gn:feature_class":"P",
    "gn:feature_code":"PPL",
    "gn:name":"Murayhij \u0100l \u1e28\u0101jj \u1e28amy",
    "gn:population":0,
    "gn:timezone":"Asia/Baghdad",
    "iso:country":"IQ",
    "name:und_x_variant":[
        "Mohij \u0101l H\u0101j Hami",
        "Murayhij \u0100l \u1e28\u0101jj \u1e28amy"
    ],
    "wof:name":"Murayhij Al Hajj Hamy",
    "wof:placetype":"locality"
},
  "geometry": {"coordinates":[44.93333,31.43333],"type":"Point"}
}