{
  "type": "Feature",
  "properties": {
    "gn:admin1_code":"10.0",
    "gn:admin2_code":"94296.0",
    "gn:asciiname":"Balakah",
    "gn:country_code":"IQ",
    "gn:dem":293,
    "gn:feature_class":"P",
    "gn:feature_code":"PPL",
    "gn:name":"Balakah",
    "gn:population":0,
    "gn:timezone":"Asia/Baghdad",
    "iso:country":"IQ",
    "name:ara_x_preferred":[
        "\u0628\u0644\u0643\u0629"
    ],
    "name:und_x_variant":[
        "Balakah a\u015f \u015eughr\u00e1",
        "Balaga-i Pich\u016bk",
        "Balakah"
    ],
    "wof:name":"Balakah",
    "wof:placetype":"locality"
},
  "geometry": {"coordinates":[44.88542,34.79257],"type":"Point"}
}