{
  "type": "Feature",
  "properties": {
    "gn:admin1_code":"9.0",
    "gn:admin2_code":"98623.0",
    "gn:asciiname":"'Arab Hajj Muhsin",
    "gn:country_code":"IQ",
    "gn:dem":8,
    "gn:feature_class":"P",
    "gn:feature_code":"PPLL",
    "gn:name":"\u2018Arab H\u0101jj Mu\u1e29sin",
    "gn:population":0,
    "gn:timezone":"Asia/Baghdad",
    "iso:country":"IQ",
    "name:ara_x_preferred":[
        "\u0639\u0631\u0628 \u062d\u0627\u062c \u0645\u062d\u0633\u0646"
    ],
    "name:und_x_variant":[
        "\u2018Arab H\u0101jj Mu\u1e29sin"
    ],
    "wof:name":"'Arab Hajj Muhsin",
    "wof:placetype":"locality"
},
  "geometry": {"coordinates":[46.28616,31.21885],"type":"Point"}
}