{
  "type": "Feature",
  "properties": {
    "gn:admin1_code":"15.0",
    "gn:admin2_code":"90392.0",
    "gn:asciiname":"Buwayr",
    "gn:cc2":"IQ",
    "gn:country_code":"IQ",
    "gn:dem":262,
    "gn:feature_class":"P",
    "gn:feature_code":"PPL",
    "gn:name":"Buwayr",
    "gn:population":0,
    "gn:timezone":"Asia/Baghdad",
    "iso:country":"IQ",
    "name:und_x_variant":[
        "Buwair",
        "Buwayr"
    ],
    "wof:name":"Buwayr",
    "wof:placetype":"locality"
},
  "geometry": {"coordinates":[42.51667,36.16722],"type":"Point"}
}