{
  "type": "Feature",
  "properties": {
    "gn:admin1_code":"7.0",
    "gn:admin2_code":"99101.0",
    "gn:asciiname":"Khudayr Hasan",
    "gn:country_code":"IQ",
    "gn:dem":33,
    "gn:feature_class":"P",
    "gn:feature_code":"PPL",
    "gn:name":"Khu\u1e11ayr \u1e28asan",
    "gn:population":0,
    "gn:timezone":"Asia/Baghdad",
    "iso:country":"IQ",
    "name:ara_x_preferred":[
        "\u062e\u0636\u064a\u0631 \u062d\u0633\u0646"
    ],
    "name:und_x_variant":[
        "Khu\u1e11ayr \u1e28asan"
    ],
    "wof:name":"Khudayr Hasan",
    "wof:placetype":"locality"
},
  "geometry": {"coordinates":[44.49622,33.12578],"type":"Point"}
}