{
  "type": "Feature",
  "properties": {
    "gn:admin1_code":"7.0",
    "gn:admin2_code":"99101.0",
    "gn:asciiname":"'Arab Khalil 'Inad",
    "gn:country_code":"IQ",
    "gn:dem":31,
    "gn:feature_class":"P",
    "gn:feature_code":"PPL",
    "gn:name":"\u2018Arab Khal\u012bl \u2018In\u0101d",
    "gn:population":0,
    "gn:timezone":"Asia/Baghdad",
    "iso:country":"IQ",
    "name:ara_x_preferred":[
        "\u0639\u0631\u0628 \u062e\u0644\u064a\u0644 \u0639\u0646\u0627\u062f"
    ],
    "name:und_x_variant":[
        "\u2018Arab Khal\u012bl \u2018In\u0101d"
    ],
    "wof:name":"'Arab Khalil 'Inad",
    "wof:placetype":"locality"
},
  "geometry": {"coordinates":[44.53347,32.96941],"type":"Point"}
}