{
  "type": "Feature",
  "properties": {
    "gn:admin1_code":"1.0",
    "gn:admin2_code":"98718.0",
    "gn:asciiname":"Albu Kan'an",
    "gn:country_code":"IQ",
    "gn:dem":47,
    "gn:feature_class":"P",
    "gn:feature_code":"PPL",
    "gn:name":"\u0100lb\u016b Kan\u2018\u0101n",
    "gn:population":0,
    "gn:timezone":"Asia/Baghdad",
    "iso:country":"IQ",
    "name:ara_x_preferred":[
        "\u0622\u0644\u0628\u0648 \u0643\u0646\u0639\u0627\u0646"
    ],
    "name:und_x_variant":[
        "\u0100lb\u016b Kan\u2018\u0101n"
    ],
    "wof:name":"Albu Kan'an",
    "wof:placetype":"locality"
},
  "geometry": {"coordinates":[43.46214000000001,33.44386],"type":"Point"}
}