{
  "type": "Feature",
  "properties": {
    "gn:admin1_code":"15.0",
    "gn:admin2_code":"90392.0",
    "gn:asciiname":"Tall 'Uwaynat",
    "gn:country_code":"IQ",
    "gn:dem":342,
    "gn:feature_class":"P",
    "gn:feature_code":"PPL",
    "gn:name":"Tall \u2018Uwayn\u0101t",
    "gn:population":0,
    "gn:timezone":"Asia/Baghdad",
    "iso:country":"IQ",
    "name:ara_x_preferred":[
        "\u062a\u0644 \u0639\u0648\u064a\u0646\u0627\u062a"
    ],
    "name:kur_x_preferred":[
        "Tel \u2018Uw\u00eenat"
    ],
    "name:kur_x_variant":[
        "\u062a\u06d5\u0644 \u0639\u0648\u064a\u0646\u0627\u062a"
    ],
    "name:und_x_variant":[
        "Tall \u2018Umwayn\u0101t",
        "Tall Awainat",
        "Tel el Uwainat",
        "Tel Uwainat",
        "Tal Awinat",
        "Tel Uwanat",
        "Tall \u2018Uwayn\u0101t"
    ],
    "wof:name":"Tall 'Uwaynat",
    "wof:placetype":"locality"
},
  "geometry": {"coordinates":[42.39579000000001,36.6802],"type":"Point"}
}