{
  "type": "Feature",
  "properties": {
    "gn:admin1_code":"3.0",
    "gn:admin2_code":"9166568.0",
    "gn:asciiname":"Dhi Qar",
    "gn:cc2":"IQ",
    "gn:country_code":"IQ",
    "gn:dem":13,
    "gn:feature_class":"P",
    "gn:feature_code":"PPL",
    "gn:name":"Dh\u012b Q\u0101r",
    "gn:population":0,
    "gn:timezone":"Asia/Baghdad",
    "iso:country":"IQ",
    "name:ara_x_preferred":[
        "Dh\u012b Q\u0101r"
    ],
    "name:und_x_variant":[
        "Thi Qar"
    ],
    "wof:name":"Dhi Qar",
    "wof:placetype":"locality"
},
  "geometry": {"coordinates":[45.1025,31.46444],"type":"Point"}
}