{
  "type": "Feature",
  "properties": {
    "gn:admin1_code":"4.0",
    "gn:admin2_code":"99737.0",
    "gn:asciiname":"Albu Idam",
    "gn:country_code":"IQ",
    "gn:dem":23,
    "gn:feature_class":"P",
    "gn:feature_code":"PPL",
    "gn:name":"\u0100lb\u016b \u012ad\u0101m",
    "gn:population":0,
    "gn:timezone":"Asia/Baghdad",
    "iso:country":"IQ",
    "name:ara_x_preferred":[
        "\u0627\u0644\u0628\u0648 \u0627\u064a\u062f\u0627\u0645"
    ],
    "name:ara_x_variant":[
        "\u0100lb\u016b \u012ad\u0101m"
    ],
    "name:und_x_variant":[
        "Ab\u016b Y\u0101m"
    ],
    "wof:name":"Albu Idam",
    "wof:placetype":"locality"
},
  "geometry": {"coordinates":[45.11355,32.08293],"type":"Point"}
}