{
  "type": "Feature",
  "properties": {
    "gn:admin1_code":"5.0",
    "gn:admin2_code":"97416.0",
    "gn:asciiname":"Buknah",
    "gn:country_code":"IQ",
    "gn:dem":715,
    "gn:feature_class":"P",
    "gn:feature_code":"PPL",
    "gn:name":"B\u016bknah",
    "gn:population":0,
    "gn:timezone":"Asia/Baghdad",
    "iso:country":"IQ",
    "name:ara_x_preferred":[
        "\u0628\u0648\u0643\u0646\u0647"
    ],
    "name:und_x_variant":[
        "B\u016bknah",
        "\u0628\u0648\u0643\u0646\u0629"
    ],
    "wof:name":"Buknah",
    "wof:placetype":"locality"
},
  "geometry": {"coordinates":[44.92891,35.77073],"type":"Point"}
}