{
  "type": "Feature",
  "properties": {
    "gn:admin1_code":"10.0",
    "gn:admin2_code":"9166680.0",
    "gn:asciiname":"Qaryat 'Abd al Hasan al Bawi",
    "gn:country_code":"IQ",
    "gn:dem":49,
    "gn:feature_class":"P",
    "gn:feature_code":"PPL",
    "gn:name":"Qaryat \u2018Abd al \u1e28asan al B\u0101w\u012b",
    "gn:population":0,
    "gn:timezone":"Asia/Baghdad",
    "iso:country":"IQ",
    "name:ara_x_preferred":[
        "\u0642\u0631\u064a\u0629 \u0639\u0628\u062f \u0627\u0644\u062d\u0633\u0646 \u0627\u0644\u0628\u0627\u0648\u064a"
    ],
    "name:und_x_variant":[
        "Qaryat \u2018Abd al \u1e28asan",
        "\u0642\u0631\u064a\u0629 \u0639\u0628\u062f \u0627\u0644\u062d\u0633\u0646",
        "Qaryat \u2018Abd al \u1e28asan al B\u0101w\u012b"
    ],
    "wof:name":"Qaryat 'Abd al Hasan al Bawi",
    "wof:placetype":"locality"
},
  "geometry": {"coordinates":[44.83711,33.77656],"type":"Point"}
}