{
  "type": "Feature",
  "properties": {
    "gn:admin1_code":"8.0",
    "gn:admin2_code":"9166607.0",
    "gn:asciiname":"Basitkat al 'Ulya",
    "gn:country_code":"IQ",
    "gn:dem":531,
    "gn:feature_class":"P",
    "gn:feature_code":"PPL",
    "gn:name":"B\u0101sitkat al \u2018Uly\u0101",
    "gn:population":0,
    "gn:timezone":"Asia/Baghdad",
    "iso:country":"IQ",
    "name:ara_x_preferred":[
        "\u0628\u0627\u0633\u062a\u0643\u0629 \u0627\u0644\u0639\u0644\u064a\u0627"
    ],
    "name:kur_x_preferred":[
        "Bastikey Ba\u0142a"
    ],
    "name:kur_x_variant":[
        "\u0628\u0627\u0633\u062a\u0643\u06d5\u0649 \u0628\u0627\u06b5\u0627",
        "Bastik\u00ea J\u00fbr\u00ee",
        "\u0628\u0627\u0633\u062a\u0643\u06ce \u0698\u0648\u0648\u0631\u0649"
    ],
    "name:und_x_variant":[
        "B\u0101st\u012bka B\u0101l\u0101",
        "Basitka",
        "Basitkah",
        "B\u0101sit\u012bkah \u2018Uly\u0101",
        "Bastka",
        "B\u0101st\u012bkah B\u0101l\u0101",
        "B\u0101stikah al \u2018Uly\u0101",
        "Basitke Upper"
    ],
    "wof:name":"Basitkat al 'Ulya",
    "wof:placetype":"locality"
},
  "geometry": {"coordinates":[42.7212,36.95894000000001],"type":"Point"}
}