{
  "type": "Feature",
  "properties": {
    "gn:admin1_code":"5.0",
    "gn:admin2_code":"9166596.0",
    "gn:asciiname":"Susi Kun",
    "gn:country_code":"IQ",
    "gn:dem":744,
    "gn:feature_class":"P",
    "gn:feature_code":"PPL",
    "gn:name":"S\u016bs\u012b K\u016bn",
    "gn:population":0,
    "gn:timezone":"Asia/Baghdad",
    "iso:country":"IQ",
    "name:ara_x_preferred":[
        "\u0633\u0648\u0633\u064a \u0643\u0648\u0646"
    ],
    "name:und_x_variant":[
        "Susa",
        "S\u016bs\u0113-i K\u014dn",
        "S\u016bsah K\u016bn",
        "S\u016bsay K\u016bn",
        "S\u016bsah"
    ],
    "wof:name":"Susi Kun",
    "wof:placetype":"locality"
},
  "geometry": {"coordinates":[45.11008,35.76547],"type":"Point"}
}