{
  "type": "Feature",
  "properties": {
    "gn:admin1_code":"6.0",
    "gn:admin2_code":"99358.0",
    "gn:asciiname":"Qaryat as Salt",
    "gn:country_code":"IQ",
    "gn:dem":26,
    "gn:feature_class":"P",
    "gn:feature_code":"PPL",
    "gn:name":"Qaryat as Sal\u0163",
    "gn:population":0,
    "gn:timezone":"Asia/Baghdad",
    "iso:country":"IQ",
    "name:ara_x_preferred":[
        "\u0642\u0631\u064a\u0629 \u0627\u0644\u0633\u0644\u0637"
    ],
    "name:und_x_variant":[
        "Qaryat as Sal\u0163"
    ],
    "wof:name":"Qaryat as Salt",
    "wof:placetype":"locality"
},
  "geometry": {"coordinates":[44.62028,32.31294],"type":"Point"}
}