{
  "type": "Feature",
  "properties": {
    "gn:admin1_code":"13.0",
    "gn:admin2_code":"94786.0",
    "gn:asciiname":"Khuwayshijah",
    "gn:country_code":"IQ",
    "gn:dem":183,
    "gn:feature_class":"P",
    "gn:feature_code":"PPL",
    "gn:name":"Khuwaysh\u012bjah",
    "gn:population":0,
    "gn:timezone":"Asia/Baghdad",
    "iso:country":"IQ",
    "name:ara_x_preferred":[
        "\u062e\u0648\u064a\u0634\u064a\u062c\u0629"
    ],
    "name:und_x_variant":[
        "Khw\u0101\u012bshijah",
        "Khuwaysh\u012byah",
        "Khuwayshijah",
        "\u062e\u0648\u064a\u0634\u062c\u0629",
        "Khuwaysh\u012bjah"
    ],
    "wof:name":"Khuwayshijah",
    "wof:placetype":"locality"
},
  "geometry": {"coordinates":[44.05376,35.15488],"type":"Point"}
}