{
  "type": "Feature",
  "properties": {
    "gn:admin1_code":"18.0",
    "gn:admin2_code":"90148.0",
    "gn:asciiname":"'Arab Khalaf an Nazal",
    "gn:country_code":"IQ",
    "gn:dem":156,
    "gn:feature_class":"P",
    "gn:feature_code":"PPL",
    "gn:name":"\u2018Arab Khalaf an Naz\u0101l",
    "gn:population":0,
    "gn:timezone":"Asia/Baghdad",
    "iso:country":"IQ",
    "name:ara_x_preferred":[
        "\u0639\u0631\u0628 \u062e\u0644\u0641 \u0627\u0644\u0646\u0632\u0627\u0644"
    ],
    "name:und_x_variant":[
        "\u2018Arab Khalaf an Naz\u0101l"
    ],
    "wof:name":"'Arab Khalaf an Nazal",
    "wof:placetype":"locality"
},
  "geometry": {"coordinates":[43.81442,34.86954],"type":"Point"}
}