{
  "type": "Feature",
  "properties": {
    "gn:admin1_code":"7.0",
    "gn:admin2_code":"99101.0",
    "gn:asciiname":"Zaydan al Khalaf",
    "gn:country_code":"IQ",
    "gn:dem":36,
    "gn:feature_class":"P",
    "gn:feature_code":"PPL",
    "gn:name":"Zayd\u0101n al Khalaf",
    "gn:population":0,
    "gn:timezone":"Asia/Baghdad",
    "iso:country":"IQ",
    "name:und_x_variant":[
        "Zaid\u0101n",
        "Zayd\u0101n",
        "Zayd\u0101n al Khalaf"
    ],
    "wof:name":"Zaydan al Khalaf",
    "wof:placetype":"locality"
},
  "geometry": {"coordinates":[44.46367,33.12211],"type":"Point"}
}