{
  "type": "Feature",
  "properties": {
    "gn:admin1_code":"3.0",
    "gn:admin2_code":"9166568.0",
    "gn:asciiname":"Tashshash ash Shayil",
    "gn:country_code":"IQ",
    "gn:dem":15,
    "gn:feature_class":"P",
    "gn:feature_code":"PPL",
    "gn:name":"\u0162ashsh\u0101sh ash Sh\u0101yil",
    "gn:population":0,
    "gn:timezone":"Asia/Baghdad",
    "iso:country":"IQ",
    "name:ara_x_preferred":[
        "\u0637\u0634\u0627\u0634 \u0627\u0644\u0634\u0627\u064a\u0644"
    ],
    "name:und_x_variant":[
        "\u0162ashsh\u0101sh ash Sh\u0101yil"
    ],
    "wof:name":"Tashshash ash Shayil",
    "wof:placetype":"locality"
},
  "geometry": {"coordinates":[45.14738,31.50359000000001],"type":"Point"}
}