{
  "type": "Feature",
  "properties": {
    "gn:admin1_code":"5.0",
    "gn:admin2_code":"92051.0",
    "gn:asciiname":"Shirut",
    "gn:country_code":"IQ",
    "gn:dem":1046,
    "gn:feature_class":"P",
    "gn:feature_code":"PPL",
    "gn:name":"Sh\u012br\u016bt",
    "gn:population":0,
    "gn:timezone":"Asia/Baghdad",
    "iso:country":"IQ",
    "name:ara_x_preferred":[
        "\u0634\u064a\u0631\u0648\u062a"
    ],
    "name:und_x_variant":[
        "Sh\u012br\u016bt"
    ],
    "wof:name":"Shirut",
    "wof:placetype":"locality"
},
  "geometry": {"coordinates":[44.80147,36.39447],"type":"Point"}
}