{
  "type": "Feature",
  "properties": {
    "gn:admin1_code":"10.0",
    "gn:admin2_code":"9166680.0",
    "gn:asciiname":"'Amir al Wajihi",
    "gn:country_code":"IQ",
    "gn:dem":45,
    "gn:feature_class":"P",
    "gn:feature_code":"PPL",
    "gn:name":"\u2018\u0100mir al Waj\u012bh\u012b",
    "gn:population":0,
    "gn:timezone":"Asia/Baghdad",
    "iso:country":"IQ",
    "name:ara_x_preferred":[
        "\u0639\u0627\u0645\u0631 \u0627\u0644\u0648\u062c\u064a\u0647\u064a"
    ],
    "name:und_x_variant":[
        "\u2018\u0100mir al Waj\u012bh\u012b"
    ],
    "wof:name":"'Amir al Wajihi",
    "wof:placetype":"locality"
},
  "geometry": {"coordinates":[44.78076,33.63034],"type":"Point"}
}