{
  "type": "Feature",
  "properties": {
    "gn:admin1_code":"1.0",
    "gn:admin2_code":"9166579.0",
    "gn:asciiname":"Qaryat ad Dikani",
    "gn:country_code":"IQ",
    "gn:dem":124,
    "gn:feature_class":"P",
    "gn:feature_code":"PPL",
    "gn:name":"Qaryat ad D\u012bk\u0101n\u012b",
    "gn:population":0,
    "gn:timezone":"Asia/Baghdad",
    "iso:country":"IQ",
    "name:ara_x_preferred":[
        "\u0642\u0631\u064a\u0629 \u0627\u0644\u062f\u064a\u0643\u0627\u0646\u064a"
    ],
    "name:und_x_variant":[
        "Qaryat ad D\u012bk\u0101n\u012b"
    ],
    "wof:name":"Qaryat ad Dikani",
    "wof:placetype":"locality"
},
  "geometry": {"coordinates":[42.90706,34.38887],"type":"Point"}
}