{
  "type": "Feature",
  "properties": {
    "gn:admin1_code":"4.0",
    "gn:admin2_code":"98634.0",
    "gn:asciiname":"Ad Duraghi",
    "gn:country_code":"IQ",
    "gn:dem":24,
    "gn:feature_class":"P",
    "gn:feature_code":"PPL",
    "gn:name":"Ad Dur\u0101gh\u012b",
    "gn:population":0,
    "gn:timezone":"Asia/Baghdad",
    "iso:country":"IQ",
    "name:ara_x_preferred":[
        "\u0627\u0644\u062f\u0631\u0627\u063a\u064a"
    ],
    "name:ara_x_variant":[
        "Ad Dur\u0101gh\u012b"
    ],
    "wof:name":"Ad Duraghi",
    "wof:placetype":"locality"
},
  "geometry": {"coordinates":[44.65246,31.86653],"type":"Point"}
}