{
  "type": "Feature",
  "properties": {
    "gn:admin1_code":"9.0",
    "gn:admin2_code":"98855.0",
    "gn:asciiname":"Al Nasr Allah",
    "gn:country_code":"IQ",
    "gn:dem":6,
    "gn:feature_class":"P",
    "gn:feature_code":"PPL",
    "gn:name":"\u0100l Na\u015fr All\u0101h",
    "gn:population":0,
    "gn:timezone":"Asia/Baghdad",
    "iso:country":"IQ",
    "name:ara_x_preferred":[
        "\u0627\u0644 \u0646\u0635\u0631 \u0627\u0644\u0644\u0647"
    ],
    "name:und_x_variant":[
        "Sulaim\u0101n an Nasrullah",
        "Na\u015fr All\u0101h",
        "Sulaym\u0101n Na\u015fr All\u0101h",
        "Salm\u0101n an Na\u015fr All\u0101h",
        "\u0100l Na\u015fr All\u0101h"
    ],
    "wof:name":"Al Nasr Allah",
    "wof:placetype":"locality"
},
  "geometry": {"coordinates":[46.58031,31.22519],"type":"Point"}
}