{
  "type": "Feature",
  "properties": {
    "gn:admin1_code":"6.0",
    "gn:admin2_code":"6818313.0",
    "gn:asciiname":"'Arab Jubur",
    "gn:country_code":"IQ",
    "gn:dem":32,
    "gn:feature_class":"P",
    "gn:feature_code":"PPL",
    "gn:name":"\u2018Arab Jub\u016br",
    "gn:population":0,
    "gn:timezone":"Asia/Baghdad",
    "iso:country":"IQ",
    "name:ara_x_preferred":[
        "\u0639\u0631\u0628 \u062c\u0628\u0648\u0631"
    ],
    "name:und_x_variant":[
        "\u2018Arab Jub\u016br"
    ],
    "wof:name":"'Arab Jubur",
    "wof:placetype":"locality"
},
  "geometry": {"coordinates":[44.44046,32.7246],"type":"Point"}
}