{
  "type": "Feature",
  "properties": {
    "gn:admin1_code":"7.0",
    "gn:admin2_code":"99101.0",
    "gn:asciiname":"Al Mahmudiyah",
    "gn:country_code":"IQ",
    "gn:dem":34,
    "gn:feature_class":"P",
    "gn:feature_code":"PPLA2",
    "gn:name":"Al Ma\u1e29m\u016bd\u012byah",
    "gn:population":0,
    "gn:timezone":"Asia/Baghdad",
    "iso:country":"IQ",
    "name:ara_x_preferred":[
        "\u0627\u0644\u0645\u062d\u0645\u0648\u062f\u064a\u0629"
    ],
    "name:und_x_variant":[
        "Mahmudie",
        "Al Mahm\u016bd\u012bya",
        "Mahmudiyeh",
        "Mahm\u016bd\u012bya",
        "Al Ma\u1e29m\u016bd\u012byah"
    ],
    "wof:name":"Al Mahmudiyah",
    "wof:placetype":"locality"
},
  "geometry": {"coordinates":[44.36564,33.06221],"type":"Point"}
}