{
  "type": "Feature",
  "properties": {
    "gn:admin1_code":"5.0",
    "gn:admin2_code":"96204.0",
    "gn:asciiname":"Wuluwr",
    "gn:country_code":"IQ",
    "gn:dem":536,
    "gn:feature_class":"P",
    "gn:feature_code":"PPL",
    "gn:name":"Wuluwr",
    "gn:population":0,
    "gn:timezone":"Asia/Baghdad",
    "iso:country":"IQ",
    "name:ara_x_preferred":[
        "\u0648\u0644\u0648\u0631"
    ],
    "name:kur_x_preferred":[
        "\u00dbl\u00fbr"
    ],
    "name:kur_x_variant":[
        "Wilwer",
        "\u0648\u0648\u0644\u0648\u0648\u0631",
        "\u0648\u0644\u0648\u06d5\u0631"
    ],
    "name:und_x_variant":[
        "Ulwur",
        "Wuluwr",
        "Walwar",
        "Wlwar"
    ],
    "wof:name":"Wuluwr",
    "wof:placetype":"locality"
},
  "geometry": {"coordinates":[45.75067,35.11407],"type":"Point"}
}