{
  "type": "Feature",
  "properties": {
    "gn:admin1_code":"15.0",
    "gn:admin2_code":"9166608.0",
    "gn:asciiname":"Tawilah",
    "gn:country_code":"IQ",
    "gn:dem":301,
    "gn:feature_class":"P",
    "gn:feature_code":"PPL",
    "gn:name":"\u0162aw\u012blah",
    "gn:population":0,
    "gn:timezone":"Asia/Baghdad",
    "iso:country":"IQ",
    "name:ara_x_preferred":[
        "\u0637\u0648\u064a\u0644\u0629"
    ],
    "name:und_x_variant":[
        "\u0162aw\u012blah"
    ],
    "wof:name":"Tawilah",
    "wof:placetype":"locality"
},
  "geometry": {"coordinates":[41.60626,35.99695999999999],"type":"Point"}
}