{
  "type": "Feature",
  "properties": {
    "gn:admin1_code":"2.0",
    "gn:admin2_code":"9166563.0",
    "gn:asciiname":"Abu Malih",
    "gn:country_code":"IQ",
    "gn:dem":2,
    "gn:feature_class":"P",
    "gn:feature_code":"PPL",
    "gn:name":"Ab\u016b Mal\u012b\u1e29",
    "gn:population":0,
    "gn:timezone":"Asia/Baghdad",
    "iso:country":"IQ",
    "name:ara_x_preferred":[
        "\u0627\u0628\u0648 \u0645\u0644\u064a\u062d"
    ],
    "name:und_x_variant":[
        "Ab\u016b Mal\u012b\u1e29"
    ],
    "wof:name":"Abu Malih",
    "wof:placetype":"locality"
},
  "geometry": {"coordinates":[47.35943,31.16856],"type":"Point"}
}