{
  "type": "Feature",
  "properties": {
    "gn:admin1_code":"9.0",
    "gn:admin2_code":"90509.0",
    "gn:asciiname":"Wardawi Naji",
    "gn:country_code":"IQ",
    "gn:dem":5,
    "gn:feature_class":"P",
    "gn:feature_code":"PPLL",
    "gn:name":"Wardawi Naji",
    "gn:population":0,
    "gn:timezone":"Asia/Baghdad",
    "iso:country":"IQ",
    "wof:name":"Wardawi Naji",
    "wof:placetype":"locality"
},
  "geometry": {"coordinates":[46.5725,30.90111],"type":"Point"}
}