{
  "type": "Feature",
  "properties": {
    "gn:admin1_code":"8.0",
    "gn:admin2_code":"89569.0",
    "gn:asciiname":"Misilmah",
    "gn:country_code":"IQ",
    "gn:dem":517,
    "gn:feature_class":"P",
    "gn:feature_code":"PPLF",
    "gn:name":"Misilmah",
    "gn:population":0,
    "gn:timezone":"Asia/Baghdad",
    "iso:country":"IQ",
    "name:ara_x_preferred":[
        "\u0645\u0633\u0644\u0645\u0629"
    ],
    "name:kur_x_preferred":[
        "Msilmet"
    ],
    "name:kur_x_variant":[
        "\u0645\u0633\u0644\u0645\u06d5\u062a",
        "Chem Misilmet",
        "\u0686\u06d5\u0645 \u0645\u0633\u0644\u0645\u06d5\u062a"
    ],
    "name:und_x_variant":[
        "Mslma",
        "Misilmah",
        "Cham Misilmat"
    ],
    "wof:name":"Misilmah",
    "wof:placetype":"locality"
},
  "geometry": {"coordinates":[42.81236,37.0643],"type":"Point"}
}