{
  "type": "Feature",
  "properties": {
    "gn:admin1_code":"11.0",
    "gn:admin2_code":"93817.0",
    "gn:asciiname":"Qaryat 'Ayn Kawah",
    "gn:country_code":"IQ",
    "gn:dem":199,
    "gn:feature_class":"P",
    "gn:feature_code":"PPL",
    "gn:name":"Qaryat \u2018Ayn K\u0101wah",
    "gn:population":0,
    "gn:timezone":"Asia/Baghdad",
    "iso:country":"IQ",
    "name:ara_x_preferred":[
        "\u0642\u0631\u064a\u0629 \u0639\u064a\u0646 \u0643\u0627\u0648\u0647"
    ],
    "name:und_x_variant":[
        "Ankawa",
        "\u2018Ank\u0101wah",
        "\u2018Aynk\u0101wah",
        "Qaryat \u2018Ayn K\u0101wah"
    ],
    "wof:name":"Qaryat 'Ayn Kawah",
    "wof:placetype":"locality"
},
  "geometry": {"coordinates":[43.39701,35.65541],"type":"Point"}
}