{
  "type": "Feature",
  "properties": {
    "gn:admin1_code":"18.0",
    "gn:admin2_code":"6872046.0",
    "gn:asciiname":"Qaryat Samuhah",
    "gn:country_code":"IQ",
    "gn:dem":147,
    "gn:feature_class":"P",
    "gn:feature_code":"PPL",
    "gn:name":"Qaryat Sam\u016b\u1e29ah",
    "gn:population":0,
    "gn:timezone":"Asia/Baghdad",
    "iso:country":"IQ",
    "name:ara_x_preferred":[
        "\u0642\u0631\u064a\u0629 \u0633\u0645\u0648\u062d\u0647"
    ],
    "name:und_x_variant":[
        "Qaryat Sam\u016b\u1e29ah"
    ],
    "wof:name":"Qaryat Samuhah",
    "wof:placetype":"locality"
},
  "geometry": {"coordinates":[43.29282,34.75582],"type":"Point"}
}