{
  "type": "Feature",
  "properties": {
    "gn:admin1_code":"2.0",
    "gn:admin2_code":"9166549.0",
    "gn:asciiname":"Al Dowreh",
    "gn:country_code":"IQ",
    "gn:dem":0,
    "gn:feature_class":"P",
    "gn:feature_code":"PPL",
    "gn:name":"Al Dowreh",
    "gn:population":0,
    "gn:timezone":"Asia/Baghdad",
    "iso:country":"IQ",
    "name:fas_x_preferred":[
        "\u0627\u0644\u062f\u0648\u0631\u0647"
    ],
    "wof:name":"Al Dowreh",
    "wof:placetype":"locality"
},
  "geometry": {"coordinates":[48.372,30.1486],"type":"Point"}
}