{
  "type": "Feature",
  "properties": {
    "gn:admin1_code":"11.0",
    "gn:admin2_code":"9166592.0",
    "gn:asciiname":"Paras",
    "gn:country_code":"IQ",
    "gn:dem":1488,
    "gn:feature_class":"P",
    "gn:feature_code":"PPL",
    "gn:name":"Paras",
    "gn:population":0,
    "gn:timezone":"Asia/Baghdad",
    "iso:country":"IQ",
    "name:ceb_x_preferred":[
        "Paras"
    ],
    "name:fin_x_preferred":[
        "Paras"
    ],
    "name:fra_x_preferred":[
        "Paras"
    ],
    "name:ind_x_preferred":[
        "Paras"
    ],
    "name:kur_x_preferred":[
        "\u067e\u0627\u0631\u0627\u0633"
    ],
    "name:mar_x_preferred":[
        "\u092a\u093e\u0930\u0938"
    ],
    "name:nld_x_preferred":[
        "Paras"
    ],
    "name:rus_x_preferred":[
        "\u041f\u0430\u0440\u0430\u0441"
    ],
    "name:srp_x_preferred":[
        "\u041f\u0430\u0440\u0430\u0441"
    ],
    "name:swe_x_preferred":[
        "Paras"
    ],
    "wof:name":"Paras",
    "wof:placetype":"locality"
},
  "geometry": {"coordinates":[44.61667,37.03333],"type":"Point"}
}