{
  "type": "Feature",
  "properties": {
    "gn:admin1_code":"17.0",
    "gn:admin2_code":"9166629.0",
    "gn:asciiname":"'Abd Zayd Wawi",
    "gn:country_code":"IQ",
    "gn:dem":26,
    "gn:feature_class":"P",
    "gn:feature_code":"PPL",
    "gn:name":"\u2018Abd Zayd W\u0101w\u012b",
    "gn:population":0,
    "gn:timezone":"Asia/Baghdad",
    "iso:country":"IQ",
    "name:ara_x_preferred":[
        "\u0639\u0628\u062f \u0632\u064a\u062f \u0648\u0627\u0648\u064a"
    ],
    "name:und_x_variant":[
        "\u2018Abd Zayd W\u0101w\u012b"
    ],
    "wof:name":"'Abd Zayd Wawi",
    "wof:placetype":"locality"
},
  "geometry": {"coordinates":[44.54919,32.07638],"type":"Point"}
}