{
  "type": "Feature",
  "properties": {
    "gn:admin1_code":"6.0",
    "gn:admin2_code":"6818313.0",
    "gn:asciiname":"'Arab Ahmad al 'Ali",
    "gn:country_code":"IQ",
    "gn:dem":30,
    "gn:feature_class":"P",
    "gn:feature_code":"PPL",
    "gn:name":"\u2018Arab A\u1e29mad al \u2018Al\u012b",
    "gn:population":0,
    "gn:timezone":"Asia/Baghdad",
    "iso:country":"IQ",
    "name:ara_x_preferred":[
        "\u0639\u0631\u0628 \u0627\u062d\u0645\u062f \u0627\u0644\u0639\u0644\u064a"
    ],
    "name:und_x_variant":[
        "\u2018Arab A\u1e29mad al \u2018Al\u012b"
    ],
    "wof:name":"'Arab Ahmad al 'Ali",
    "wof:placetype":"locality"
},
  "geometry": {"coordinates":[44.52837,32.82678],"type":"Point"}
}