{
  "type": "Feature",
  "properties": {
    "gn:admin1_code":"4.0",
    "gn:admin2_code":"98634.0",
    "gn:asciiname":"Kur Tabuq",
    "gn:country_code":"IQ",
    "gn:dem":17,
    "gn:feature_class":"P",
    "gn:feature_code":"PPL",
    "gn:name":"K\u016br \u0162\u0101b\u016bq",
    "gn:population":0,
    "gn:timezone":"Asia/Baghdad",
    "iso:country":"IQ",
    "name:ara_x_preferred":[
        "\u0643\u0648\u0631 \u0637\u0627\u0628\u0648\u0642"
    ],
    "name:ara_x_variant":[
        "K\u016br \u0162\u0101b\u016bq"
    ],
    "wof:name":"Kur Tabuq",
    "wof:placetype":"locality"
},
  "geometry": {"coordinates":[44.69738,31.73015],"type":"Point"}
}