{
  "type": "Feature",
  "properties": {
    "gn:admin1_code":"1.0",
    "gn:admin2_code":"98718.0",
    "gn:asciiname":"Albu 'Ali",
    "gn:country_code":"IQ",
    "gn:dem":53,
    "gn:feature_class":"P",
    "gn:feature_code":"PPL",
    "gn:name":"\u0100lb\u016b \u2018Al\u012b",
    "gn:population":0,
    "gn:timezone":"Asia/Baghdad",
    "iso:country":"IQ",
    "name:ara_x_preferred":[
        "\u0627\u0644\u0628\u0648 \u0639\u0644\u064a"
    ],
    "name:ara_x_variant":[
        "\u0100lb\u016b \u2018Al\u012b"
    ],
    "name:und_x_variant":[
        "Qaryat Ab\u016b \u2018Al\u012b",
        "Qaryat \u0100lb\u016b \u2018Al\u012b",
        "\u0642\u0631\u064a\u0629 \u0627\u0644\u0628\u0648 \u0639\u0644\u064a"
    ],
    "wof:name":"Albu 'Ali",
    "wof:placetype":"locality"
},
  "geometry": {"coordinates":[43.22121,33.48967],"type":"Point"}
}