{
  "type": "Feature",
  "properties": {
    "gn:admin1_code":"15.0",
    "gn:admin2_code":"9166608.0",
    "gn:asciiname":"Athari al Awayt",
    "gn:country_code":"IQ",
    "gn:dem":276,
    "gn:feature_class":"P",
    "gn:feature_code":"PPL",
    "gn:name":"Athar\u012b al Away\u0163",
    "gn:population":0,
    "gn:timezone":"Asia/Baghdad",
    "iso:country":"IQ",
    "name:ara_x_preferred":[
        "\u0627\u062b\u0631\u064a \u0627\u0644\u0627\u0648\u064a\u0637"
    ],
    "name:und_x_variant":[
        "Athar\u012b al Away\u0163"
    ],
    "wof:name":"Athari al Awayt",
    "wof:placetype":"locality"
},
  "geometry": {"coordinates":[42.09079000000001,35.85077000000001],"type":"Point"}
}