{
  "type": "Feature",
  "properties": {
    "gn:admin1_code":"10.0",
    "gn:admin2_code":"94590.0",
    "gn:asciiname":"Kalhuri",
    "gn:country_code":"IQ",
    "gn:dem":162,
    "gn:feature_class":"P",
    "gn:feature_code":"PPL",
    "gn:name":"K\u0101lh\u016br\u012b",
    "gn:population":0,
    "gn:timezone":"Asia/Baghdad",
    "iso:country":"IQ",
    "name:ara_x_preferred":[
        "\u0643\u0627\u0644\u0647\u0648\u0631\u064a"
    ],
    "name:ara_x_variant":[
        "K\u0101lh\u016br\u012b"
    ],
    "wof:name":"Kalhuri",
    "wof:placetype":"locality"
},
  "geometry": {"coordinates":[45.32787,34.32112],"type":"Point"}
}