{
  "type": "Feature",
  "properties": {
    "gn:admin1_code":"4.0",
    "gn:admin2_code":"99763.0",
    "gn:asciiname":"Khirbat Jaza' Jabr",
    "gn:country_code":"IQ",
    "gn:dem":23,
    "gn:feature_class":"P",
    "gn:feature_code":"PPL",
    "gn:name":"Khirbat Jaz\u0101\u2018 Jabr",
    "gn:population":0,
    "gn:timezone":"Asia/Baghdad",
    "iso:country":"IQ",
    "name:ara_x_preferred":[
        "\u062e\u0631\u0628\u0629 \u062c\u0632\u0627\u0639 \u062c\u0628\u0631"
    ],
    "name:und_x_variant":[
        "Khirbat Jaz\u0101\u2018 Jabr"
    ],
    "wof:name":"Khirbat Jaza' Jabr",
    "wof:placetype":"locality"
},
  "geometry": {"coordinates":[44.69754,31.9761],"type":"Point"}
}