{
  "type": "Feature",
  "properties": {
    "gn:admin1_code":"4.0",
    "gn:admin2_code":"99763.0",
    "gn:asciiname":"Qaryat Jardagh",
    "gn:country_code":"IQ",
    "gn:dem":23,
    "gn:feature_class":"P",
    "gn:feature_code":"PPL",
    "gn:name":"Qaryat Jard\u0101gh",
    "gn:population":0,
    "gn:timezone":"Asia/Baghdad",
    "iso:country":"IQ",
    "name:ara_x_preferred":[
        "\u0642\u0631\u064a\u0629 \u062c\u0631\u062f\u0627\u063a"
    ],
    "name:und_x_variant":[
        "Qaryat Jard\u0101gh"
    ],
    "wof:name":"Qaryat Jardagh",
    "wof:placetype":"locality"
},
  "geometry": {"coordinates":[45.0332,32.15753],"type":"Point"}
}