{
  "type": "Feature",
  "properties": {
    "gn:admin1_code":"7.0",
    "gn:admin2_code":"99101.0",
    "gn:asciiname":"Jurayy Hasan",
    "gn:country_code":"IQ",
    "gn:dem":32,
    "gn:feature_class":"P",
    "gn:feature_code":"PPL",
    "gn:name":"Jurayy \u1e28asan",
    "gn:population":0,
    "gn:timezone":"Asia/Baghdad",
    "iso:country":"IQ",
    "name:ara_x_preferred":[
        "\u062c\u0631\u064a \u062d\u0633\u0646"
    ],
    "name:und_x_variant":[
        "Jurayy \u1e28asan"
    ],
    "wof:name":"Jurayy Hasan",
    "wof:placetype":"locality"
},
  "geometry": {"coordinates":[44.5064,32.89604],"type":"Point"}
}