{
  "type": "Feature",
  "properties": {
    "gn:admin1_code":"1.0",
    "gn:admin2_code":"98718.0",
    "gn:asciiname":"Hawijat at Tarabishah",
    "gn:country_code":"IQ",
    "gn:dem":57,
    "gn:feature_class":"P",
    "gn:feature_code":"PPL",
    "gn:name":"\u1e28aw\u012bjat a\u0163 \u0162ar\u0101bishah",
    "gn:population":0,
    "gn:timezone":"Asia/Baghdad",
    "iso:country":"IQ",
    "name:ara_x_preferred":[
        "\u062d\u0648\u064a\u062c\u0629 \u0627\u0644\u0637\u0631\u0627\u0628\u0634\u0629"
    ],
    "name:und_x_variant":[
        "\u1e28aw\u012bjat a\u0163 \u0162ar\u0101bishah"
    ],
    "wof:name":"Hawijat at Tarabishah",
    "wof:placetype":"locality"
},
  "geometry": {"coordinates":[43.07698,33.53213],"type":"Point"}
}