{
  "type": "Feature",
  "properties": {
    "gn:admin1_code":"9.0",
    "gn:admin2_code":"98700.0",
    "gn:asciiname":"Umm al Hamud",
    "gn:country_code":"IQ",
    "gn:dem":7,
    "gn:feature_class":"P",
    "gn:feature_code":"PPL",
    "gn:name":"Umm al \u1e28am\u016bd",
    "gn:population":0,
    "gn:timezone":"Asia/Baghdad",
    "iso:country":"IQ",
    "name:und_x_variant":[
        "Umm al \u1e28am\u016bd"
    ],
    "wof:name":"Umm al Hamud",
    "wof:placetype":"locality"
},
  "geometry": {"coordinates":[45.85,31.51667],"type":"Point"}
}