{
  "type": "Feature",
  "properties": {
    "gn:admin1_code":"10.0",
    "gn:admin2_code":"97988.0",
    "gn:asciiname":"Qaryat al Intisar",
    "gn:country_code":"IQ",
    "gn:dem":43,
    "gn:feature_class":"P",
    "gn:feature_code":"PPL",
    "gn:name":"Qaryat al Inti\u015f\u0101r",
    "gn:population":0,
    "gn:timezone":"Asia/Baghdad",
    "iso:country":"IQ",
    "name:ara_x_preferred":[
        "\u0642\u0631\u064a\u0629 \u0627\u0644\u0627\u0646\u062a\u0635\u0627\u0631"
    ],
    "name:und_x_variant":[
        "Qaryat al Inti\u015f\u0101r"
    ],
    "wof:name":"Qaryat al Intisar",
    "wof:placetype":"locality"
},
  "geometry": {"coordinates":[44.5564,33.58156],"type":"Point"}
}