{
  "type": "Feature",
  "properties": {
    "gn:admin1_code":"11.0",
    "gn:admin2_code":"95444.0",
    "gn:asciiname":"Sudash",
    "gn:country_code":"IQ",
    "gn:dem":372,
    "gn:feature_class":"P",
    "gn:feature_code":"PPL",
    "gn:name":"S\u016bd\u0101sh",
    "gn:population":0,
    "gn:timezone":"Asia/Baghdad",
    "iso:country":"IQ",
    "name:ara_x_preferred":[
        "\u0633\u0648\u062f\u0627\u0634"
    ],
    "name:ara_x_variant":[
        "S\u016bd\u0101sh"
    ],
    "wof:name":"Sudash",
    "wof:placetype":"locality"
},
  "geometry": {"coordinates":[43.86386,36.17409],"type":"Point"}
}