{
  "type": "Feature",
  "properties": {
    "gn:admin1_code":"10.0",
    "gn:admin2_code":"94590.0",
    "gn:asciiname":"Qaryat al Jazirah ath Thaniyah",
    "gn:country_code":"IQ",
    "gn:dem":63,
    "gn:feature_class":"P",
    "gn:feature_code":"PPL",
    "gn:name":"Qaryat al Jaz\u012brah ath Th\u0101niyah",
    "gn:population":0,
    "gn:timezone":"Asia/Baghdad",
    "iso:country":"IQ",
    "name:ara_x_preferred":[
        "\u0642\u0631\u064a\u0629 \u0627\u0644\u062c\u0632\u064a\u0631\u0629 \u0627\u0644\u062b\u0627\u0646\u064a\u0629"
    ],
    "name:und_x_variant":[
        "Al Jaz\u012brah ath Th\u0101niyah",
        "\u0627\u0644\u062c\u0632\u064a\u0631\u0629 \u0627\u0644\u062b\u0627\u0646\u064a\u0629",
        "Qaryat al Jaz\u012brah ath Th\u0101niyah"
    ],
    "wof:name":"Qaryat al Jazirah ath Thaniyah",
    "wof:placetype":"locality"
},
  "geometry": {"coordinates":[44.94125,33.99864],"type":"Point"}
}