{
  "type": "Feature",
  "properties": {
    "gn:admin1_code":"5.0",
    "gn:admin2_code":"96204.0",
    "gn:asciiname":"Kundah",
    "gn:country_code":"IQ",
    "gn:dem":673,
    "gn:feature_class":"P",
    "gn:feature_code":"PPL",
    "gn:name":"K\u016bndah",
    "gn:population":0,
    "gn:timezone":"Asia/Baghdad",
    "iso:country":"IQ",
    "name:ara_x_preferred":[
        "\u0643\u0648\u0646\u062f\u0647"
    ],
    "name:fas_x_preferred":[
        "\u06af\u0646\u0647"
    ],
    "name:kur_x_preferred":[
        "Gune"
    ],
    "name:kur_x_variant":[
        "\u06af\u0648\u0646\u0647"
    ],
    "name:und_x_variant":[
        "Gunda",
        "K\u016bndah",
        "Gonah",
        "Guna"
    ],
    "wof:name":"Kundah",
    "wof:placetype":"locality"
},
  "geometry": {"coordinates":[45.90479000000001,35.1489],"type":"Point"}
}