{
  "type": "Feature",
  "properties": {
    "gn:admin1_code":"6.0",
    "gn:admin2_code":"99348.0",
    "gn:asciiname":"Qaryat az Zaynabiyah",
    "gn:country_code":"IQ",
    "gn:dem":27,
    "gn:feature_class":"P",
    "gn:feature_code":"PPL",
    "gn:name":"Qaryat az Zaynab\u012byah",
    "gn:population":0,
    "gn:timezone":"Asia/Baghdad",
    "iso:country":"IQ",
    "name:ara_x_preferred":[
        "\u0642\u0631\u064a\u0629 \u0627\u0644\u0632\u064a\u0646\u0628\u064a\u0629"
    ],
    "name:und_x_variant":[
        "Qaryat az Zaynab\u012byah"
    ],
    "wof:name":"Qaryat az Zaynabiyah",
    "wof:placetype":"locality"
},
  "geometry": {"coordinates":[44.43356,32.27488],"type":"Point"}
}