{
  "type": "Feature",
  "properties": {
    "gn:admin1_code":"6.0",
    "gn:admin2_code":"6818313.0",
    "gn:asciiname":"Ahmad Muhsin",
    "gn:country_code":"IQ",
    "gn:dem":31,
    "gn:feature_class":"P",
    "gn:feature_code":"PPL",
    "gn:name":"A\u1e29mad Mu\u1e29sin",
    "gn:population":0,
    "gn:timezone":"Asia/Baghdad",
    "iso:country":"IQ",
    "name:ara_x_preferred":[
        "\u0627\u062d\u0645\u062f \u0645\u062d\u0633\u0646"
    ],
    "name:und_x_variant":[
        "A\u1e29mad Mu\u1e29sin"
    ],
    "wof:name":"Ahmad Muhsin",
    "wof:placetype":"locality"
},
  "geometry": {"coordinates":[44.4857,32.77542],"type":"Point"}
}