{
  "type": "Feature",
  "properties": {
    "gn:admin1_code":"15.0",
    "gn:admin2_code":"9166620.0",
    "gn:asciiname":"Al Majnuniyah",
    "gn:country_code":"IQ",
    "gn:dem":447,
    "gn:feature_class":"P",
    "gn:feature_code":"PPL",
    "gn:name":"Al Majn\u016bn\u012byah",
    "gn:population":0,
    "gn:timezone":"Asia/Baghdad",
    "iso:country":"IQ",
    "name:ara_x_preferred":[
        "\u0627\u0644\u0645\u062c\u0646\u0648\u0646\u064a\u0629"
    ],
    "name:und_x_variant":[
        "Majn\u016bn\u012byah",
        "Al Majn\u016bn\u012byah"
    ],
    "wof:name":"Al Majnuniyah",
    "wof:placetype":"locality"
},
  "geometry": {"coordinates":[41.59197,36.28605],"type":"Point"}
}