{
  "type": "Feature",
  "properties": {
    "gn:admin1_code":"15.0",
    "gn:admin2_code":"9166620.0",
    "gn:asciiname":"Al Qamishliyah",
    "gn:country_code":"IQ",
    "gn:dem":285,
    "gn:feature_class":"P",
    "gn:feature_code":"PPL",
    "gn:name":"Al Q\u0101mishl\u012byah",
    "gn:population":0,
    "gn:timezone":"Asia/Baghdad",
    "iso:country":"IQ",
    "name:ara_x_preferred":[
        "\u0627\u0644\u0642\u0627\u0645\u0634\u0644\u064a\u0629"
    ],
    "name:und_x_variant":[
        "Qamush\u012bya",
        "O\u0101mush\u012byah",
        "Q\u0101mish\u012byah",
        "Al Q\u0101mishl\u012byah"
    ],
    "wof:name":"Al Qamishliyah",
    "wof:placetype":"locality"
},
  "geometry": {"coordinates":[42.26718,36.18952],"type":"Point"}
}