{
  "type": "Feature",
  "properties": {
    "gn:admin1_code":"16.0",
    "gn:admin2_code":"99132.0",
    "gn:asciiname":"Kazim 'Abud",
    "gn:country_code":"IQ",
    "gn:dem":11,
    "gn:feature_class":"P",
    "gn:feature_code":"PPL",
    "gn:name":"K\u0101z\u0327im \u2018Ab\u016bd",
    "gn:population":0,
    "gn:timezone":"Asia/Baghdad",
    "iso:country":"IQ",
    "name:ara_x_preferred":[
        "K\u0101z\u0327im \u2018Ab\u016bd"
    ],
    "name:ara_x_variant":[
        "\u0643\u0627\u0638\u0645 \u0639\u0628\u0648\u062f"
    ],
    "wof:name":"Kazim 'Abud",
    "wof:placetype":"locality"
},
  "geometry": {"coordinates":[46.41678,32.50065],"type":"Point"}
}