{
  "type": "Feature",
  "properties": {
    "gn:admin1_code":"3.0",
    "gn:admin2_code":"9166568.0",
    "gn:asciiname":"Khanjar",
    "gn:country_code":"IQ",
    "gn:dem":16,
    "gn:feature_class":"P",
    "gn:feature_code":"PPL",
    "gn:name":"Khanjar",
    "gn:population":0,
    "gn:timezone":"Asia/Baghdad",
    "iso:country":"IQ",
    "name:ara_x_preferred":[
        "\u062e\u0646\u062c\u0631"
    ],
    "name:ces_x_preferred":[
        "Chand\u017ear"
    ],
    "name:deu_x_preferred":[
        "Handschar"
    ],
    "name:fra_x_preferred":[
        "Kandjar"
    ],
    "name:hrv_x_preferred":[
        "Hand\u017ear"
    ],
    "name:hun_x_preferred":[
        "Handzs\u00e1r"
    ],
    "name:ind_x_preferred":[
        "Khanjar"
    ],
    "name:ita_x_preferred":[
        "Khanjar"
    ],
    "name:kor_x_preferred":[
        "\uce78\uc790\ub974"
    ],
    "name:lit_x_preferred":[
        "Chand\u017earas"
    ],
    "name:nld_x_preferred":[
        "Khanjar"
    ],
    "name:pol_x_preferred":[
        "Hand\u017car"
    ],
    "name:rus_x_preferred":[
        "\u0425\u0430\u043d\u0434\u0436\u0430\u0440"
    ],
    "name:slv_x_preferred":[
        "Hand\u017ear"
    ],
    "name:spa_x_preferred":[
        "Janyar"
    ],
    "name:srp_x_preferred":[
        "\u0425\u0430\u043d\u045f\u0430\u0440"
    ],
    "name:ukr_x_preferred":[
        "\u0425\u0430\u043d\u0434\u0436\u0430\u0440"
    ],
    "wof:name":"Khanjar",
    "wof:placetype":"locality"
},
  "geometry": {"coordinates":[45.25341,31.55503],"type":"Point"}
}