{
  "type": "Feature",
  "properties": {
    "gn:admin1_code":"16.0",
    "gn:admin2_code":"9166961.0",
    "gn:asciiname":"Rahim Mustafa",
    "gn:country_code":"IQ",
    "gn:dem":35,
    "gn:feature_class":"P",
    "gn:feature_code":"PPLL",
    "gn:name":"Ra\u1e29\u012bm Mu\u015f\u0163af\u00e1",
    "gn:population":0,
    "gn:timezone":"Asia/Baghdad",
    "iso:country":"IQ",
    "name:ara_x_preferred":[
        "\u0631\u062d\u064a\u0645 \u0645\u0635\u0637\u0641\u0649"
    ],
    "name:und_x_variant":[
        "Ra\u1e29\u012bm Mu\u015f\u0163af\u00e1"
    ],
    "wof:name":"Rahim Mustafa",
    "wof:placetype":"locality"
},
  "geometry": {"coordinates":[44.71173,32.97499000000001],"type":"Point"}
}