{
  "type": "Feature",
  "properties": {
    "gn:admin1_code":"2.0",
    "gn:admin2_code":"9166563.0",
    "gn:asciiname":"Al Barz",
    "gn:country_code":"IQ",
    "gn:dem":4,
    "gn:feature_class":"P",
    "gn:feature_code":"PPL",
    "gn:name":"Al Barz",
    "gn:population":0,
    "gn:timezone":"Asia/Baghdad",
    "iso:country":"IQ",
    "name:ara_x_preferred":[
        "\u0627\u0644\u0628\u0631\u0632"
    ],
    "name:und_x_variant":[
        "Barriz",
        "B\u0101r\u012bz",
        "Al Barz"
    ],
    "wof:name":"Al Barz",
    "wof:placetype":"locality"
},
  "geometry": {"coordinates":[47.38457,31.06351],"type":"Point"}
}