{
  "type": "Feature",
  "properties": {
    "gn:admin1_code":"11.0",
    "gn:admin2_code":"9166592.0",
    "gn:asciiname":"Sarroo",
    "gn:country_code":"IQ",
    "gn:dem":1014,
    "gn:feature_class":"P",
    "gn:feature_code":"PPL",
    "gn:name":"Sarroo",
    "gn:population":0,
    "gn:timezone":"Asia/Baghdad",
    "iso:country":"IQ",
    "name:kur_x_preferred":[
        "Ser Zaw\u00ee"
    ],
    "name:kur_x_variant":[
        "\u0633\u06d5\u0631 \u0632\u06d5\u0648\u0649",
        "Ser\u1e5fo",
        "\u0633\u06d5\u0631\u0695\u06c6"
    ],
    "name:und_x_variant":[
        "Sarr\u016b",
        "Sarroo",
        "Saru",
        "S\u012br\u014d"
    ],
    "wof:name":"Sarroo",
    "wof:placetype":"locality"
},
  "geometry": {"coordinates":[44.63455,36.89645],"type":"Point"}
}