{
  "type": "Feature",
  "properties": {
    "gn:admin1_code":"9.0",
    "gn:admin2_code":"98855.0",
    "gn:asciiname":"Sanshit an Nahar",
    "gn:cc2":"IQ",
    "gn:country_code":"IQ",
    "gn:dem":6,
    "gn:feature_class":"P",
    "gn:feature_code":"PPL",
    "gn:name":"Sanshit an Nah\u0101r",
    "gn:population":0,
    "gn:timezone":"Asia/Baghdad",
    "iso:country":"IQ",
    "name:und_x_variant":[
        "An Nahr",
        "S\u0101kit an Nah\u0101r",
        "An Nah\u0101r",
        "Sanchit an Nah\u0101r",
        "Sanshit an Nah\u0101r"
    ],
    "wof:name":"Sanshit an Nahar",
    "wof:placetype":"locality"
},
  "geometry": {"coordinates":[46.58861,31.26667],"type":"Point"}
}