{
  "type": "Feature",
  "properties": {
    "gn:admin1_code":"15.0",
    "gn:admin2_code":"9166541.0",
    "gn:asciiname":"Qaryat Badanat al `Ulya",
    "gn:country_code":"IQ",
    "gn:dem":281,
    "gn:feature_class":"P",
    "gn:feature_code":"PPL",
    "gn:name":"Qaryat Badanat al \u2018Uly\u0101",
    "gn:population":0,
    "gn:timezone":"Asia/Baghdad",
    "iso:country":"IQ",
    "name:ara_x_preferred":[
        "\u0642\u0631\u064a\u0629 \u0628\u062f\u0646\u0629 \u0627\u0644\u0639\u0644\u064a\u0627"
    ],
    "name:und_x_variant":[
        "Bed\u0101na",
        "B\u012bd\u0101nah",
        "Bed\u0101nah",
        "Qaryat Badanah al \u2018Uly\u0101"
    ],
    "wof:name":"Qaryat Badanat al `Ulya",
    "wof:placetype":"locality"
},
  "geometry": {"coordinates":[43.47595,36.30025],"type":"Point"}
}