{
  "type": "Feature",
  "properties": {
    "gn:admin1_code":"4.0",
    "gn:admin2_code":"98634.0",
    "gn:asciiname":"'Ulaywi Al Furaym",
    "gn:country_code":"IQ",
    "gn:dem":17,
    "gn:feature_class":"P",
    "gn:feature_code":"PPL",
    "gn:name":"\u2018Ulayw\u012b \u0100l Furaym",
    "gn:population":0,
    "gn:timezone":"Asia/Baghdad",
    "iso:country":"IQ",
    "name:ara_x_preferred":[
        "\u0639\u0644\u064a\u0648\u064a \u0627\u0644 \u0641\u0631\u064a\u0645"
    ],
    "name:und_x_variant":[
        "\u2018Ulayw\u012b \u0100l Furaym"
    ],
    "wof:name":"'Ulaywi Al Furaym",
    "wof:placetype":"locality"
},
  "geometry": {"coordinates":[44.65047,31.67195],"type":"Point"}
}