{
  "type": "Feature",
  "properties": {
    "gn:admin1_code":"1.0",
    "gn:admin2_code":"98678.0",
    "gn:asciiname":"Qaryat al Habbariyah",
    "gn:country_code":"IQ",
    "gn:dem":315,
    "gn:feature_class":"P",
    "gn:feature_code":"PPL",
    "gn:name":"Qaryat al Habb\u0101r\u012byah",
    "gn:population":0,
    "gn:timezone":"Asia/Baghdad",
    "iso:country":"IQ",
    "name:ara_x_preferred":[
        "\u0642\u0631\u064a\u0629 \u0627\u0644\u0647\u0628\u0627\u0631\u064a\u0629"
    ],
    "name:und_x_variant":[
        "Habariyah",
        "Al Habb\u0101r\u012byah",
        "Qaryat al Habb\u0101r\u012byah"
    ],
    "wof:name":"Qaryat al Habbariyah",
    "wof:placetype":"locality"
},
  "geometry": {"coordinates":[42.20859,32.28089],"type":"Point"}
}