{
  "type": "Feature",
  "properties": {
    "gn:admin1_code":"16.0",
    "gn:admin2_code":"9166961.0",
    "gn:asciiname":"Nasif Jasim",
    "gn:country_code":"IQ",
    "gn:dem":28,
    "gn:feature_class":"P",
    "gn:feature_code":"PPL",
    "gn:name":"Na\u015f\u012bf J\u0101sim",
    "gn:population":0,
    "gn:timezone":"Asia/Baghdad",
    "iso:country":"IQ",
    "name:ara_x_preferred":[
        "\u0646\u0635\u064a\u0641 \u062c\u0627\u0633\u0645"
    ],
    "name:und_x_variant":[
        "Na\u015f\u012bf J\u0101sim"
    ],
    "wof:name":"Nasif Jasim",
    "wof:placetype":"locality"
},
  "geometry": {"coordinates":[44.93255,32.94464],"type":"Point"}
}