{
  "type": "Feature",
  "properties": {
    "gn:admin1_code":"8.0",
    "gn:admin2_code":"89569.0",
    "gn:asciiname":"Zaxu",
    "gn:country_code":"IQ",
    "gn:dem":437,
    "gn:feature_class":"P",
    "gn:feature_code":"PPLA2",
    "gn:name":"Zaxu",
    "gn:population":0,
    "gn:timezone":"Asia/Baghdad",
    "iso:country":"IQ",
    "name:ara_x_preferred":[
        "\u0632\u0627\u062e\u0648"
    ],
    "name:ara_x_variant":[
        "\u0642\u0636\u0627\u0621 \u0632\u0627\u062e\u0648"
    ],
    "name:kur_x_preferred":[
        "Zaxu"
    ],
    "name:kur_x_variant":[
        "Zaxo",
        "\u0632\u0627\u062e\u06c6"
    ],
    "name:und_x_variant":[
        "Z\u0101kh\u016b",
        "Zakho",
        "Zakhu",
        "Qa\u1e11\u0101\u2019 Z\u0101kh\u016b",
        "Z\u0101kh\u016b Qadh\u0101\u2019"
    ],
    "wof:name":"Zaxu",
    "wof:placetype":"locality"
},
  "geometry": {"coordinates":[42.68187,37.14246],"type":"Point"}
}