{
  "type": "Feature",
  "properties": {
    "gn:admin1_code":"8.0",
    "gn:admin2_code":"89569.0",
    "gn:asciiname":"Zaxu",
    "gn:country_code":"IQ",
    "gn:dem":437,
    "gn:feature_class":"P",
    "gn:feature_code":"PPLA2",
    "gn:name":"Zaxu",
    "gn:population":0,
    "gn:timezone":"Asia/Baghdad",
    "iso:country":"IQ",
    "name:ara_x_preferred":[
        "\u0632\u0627\u062e\u0648"
    ],
    "name:ara_x_variant":[
        "\u0642\u0636\u0627\u0621 \u0632\u0627\u062e\u0648"
    ],
    "name:arc_x_preferred":[
        "\u0719\u071f\u0718"
    ],
    "name:arz_x_preferred":[
        "\u0632\u0627\u062e\u0648"
    ],
    "name:aze_x_preferred":[
        "Zaxo"
    ],
    "name:bel_x_preferred":[
        "\u0417\u0430\u0445\u0443"
    ],
    "name:cat_x_preferred":[
        "Zakho"
    ],
    "name:ceb_x_preferred":[
        "Zaxo"
    ],
    "name:ckb_x_preferred":[
        "\u0632\u0627\u062e\u06c6"
    ],
    "name:deu_x_preferred":[
        "Zaxo"
    ],
    "name:ell_x_preferred":[
        "\u0396\u03ac\u03c7\u03bf"
    ],
    "name:epo_x_preferred":[
        "Za\u0125o"
    ],
    "name:est_x_preferred":[
        "Z\u0101kh\u016b"
    ],
    "name:fas_x_preferred":[
        "\u0632\u0627\u062e\u0648"
    ],
    "name:fra_x_preferred":[
        "Zakho"
    ],
    "name:glg_x_preferred":[
        "Zaxo"
    ],
    "name:heb_x_preferred":[
        "\u05d6\u05d0\u05db\u05d5"
    ],
    "name:hun_x_preferred":[
        "Zah\u00f3"
    ],
    "name:ita_x_preferred":[
        "Zakho"
    ],
    "name:jpn_x_preferred":[
        "\u30b6\u30fc\u30db\u30fc"
    ],
    "name:kaz_x_preferred":[
        "\u0417\u0430\u0445\u0443"
    ],
    "name:kur_x_preferred":[
        "Zaxu"
    ],
    "name:kur_x_variant":[
        "Zaxo",
        "\u0632\u0627\u062e\u06c6"
    ],
    "name:mzn_x_preferred":[
        "\u0632\u0627\u062e\u0648"
    ],
    "name:nld_x_preferred":[
        "Zakho"
    ],
    "name:nor_x_preferred":[
        "Zakho"
    ],
    "name:pnb_x_preferred":[
        "\u0632\u0627\u062e\u0648"
    ],
    "name:pol_x_preferred":[
        "Zachu"
    ],
    "name:por_x_preferred":[
        "Zakho"
    ],
    "name:ron_x_preferred":[
        "Zakho"
    ],
    "name:rus_x_preferred":[
        "\u0417\u0430\u0445\u0443"
    ],
    "name:spa_x_preferred":[
        "Zakho"
    ],
    "name:sqi_x_preferred":[
        "Zaho"
    ],
    "name:swe_x_preferred":[
        "Zakho"
    ],
    "name:tur_x_preferred":[
        "Zaho"
    ],
    "name:ukr_x_preferred":[
        "\u0417\u0430\u0445\u0443"
    ],
    "name:und_x_variant":[
        "Zakhu",
        "Qa\u1e11\u0101\u2019 Z\u0101kh\u016b",
        "Z\u0101kh\u016b Qadh\u0101\u2019"
    ],
    "name:urd_x_preferred":[
        "\u0632\u0627\u062e\u0648"
    ],
    "wof:name":"Zaxu",
    "wof:placetype":"locality"
},
  "geometry": {"coordinates":[42.68187,37.14246],"type":"Point"}
}