{
  "type": "Feature",
  "properties": {
    "gn:admin1_code":"1.0",
    "gn:admin2_code":"6765480.0",
    "gn:asciiname":"Qaryat Sadr Zaghdan",
    "gn:country_code":"IQ",
    "gn:dem":103,
    "gn:feature_class":"P",
    "gn:feature_code":"PPL",
    "gn:name":"Qaryat \u015eadr Zaghd\u0101n",
    "gn:population":0,
    "gn:timezone":"Asia/Baghdad",
    "iso:country":"IQ",
    "name:ara_x_preferred":[
        "\u0642\u0631\u064a\u0629 \u0635\u062f\u0631 \u0632\u063a\u062f\u0627\u0646"
    ],
    "name:und_x_variant":[
        "Qaryat \u015eadr Zaghd\u0101n"
    ],
    "wof:name":"Qaryat Sadr Zaghdan",
    "wof:placetype":"locality"
},
  "geometry": {"coordinates":[42.41204000000001,34.04143],"type":"Point"}
}