{
  "type": "Feature",
  "properties": {
    "gn:admin1_code":"4.0",
    "gn:admin2_code":"98634.0",
    "gn:asciiname":"Al Nabhan",
    "gn:country_code":"IQ",
    "gn:dem":21,
    "gn:feature_class":"P",
    "gn:feature_code":"PPL",
    "gn:name":"\u0100l Nabh\u0101n",
    "gn:population":0,
    "gn:timezone":"Asia/Baghdad",
    "iso:country":"IQ",
    "name:ara_x_preferred":[
        "\u0627\u0644 \u0646\u0628\u0647\u0627\u0646"
    ],
    "name:und_x_variant":[
        "\u0100l Nabh\u0101n"
    ],
    "wof:name":"Al Nabhan",
    "wof:placetype":"locality"
},
  "geometry": {"coordinates":[44.61739,31.72837],"type":"Point"}
}