{
  "type": "Feature",
  "properties": {
    "gn:admin1_code":"3.0",
    "gn:admin2_code":"9166626.0",
    "gn:asciiname":"Ad Darraji",
    "gn:country_code":"IQ",
    "gn:dem":8,
    "gn:feature_class":"P",
    "gn:feature_code":"PPL",
    "gn:name":"Ad Darr\u0101j\u012b",
    "gn:population":0,
    "gn:timezone":"Asia/Baghdad",
    "iso:country":"IQ",
    "name:ara_x_preferred":[
        "\u0627\u0644\u062f\u0631\u0627\u062c\u064a"
    ],
    "name:und_x_variant":[
        "Ad Darr\u0101j\u012b"
    ],
    "wof:name":"Ad Darraji",
    "wof:placetype":"locality"
},
  "geometry": {"coordinates":[45.7474,31.17236],"type":"Point"}
}