{
  "type": "Feature",
  "properties": {
    "gn:admin1_code":"15.0",
    "gn:admin2_code":"9166608.0",
    "gn:asciiname":"Sayjan as Sakr",
    "gn:country_code":"IQ",
    "gn:dem":301,
    "gn:feature_class":"P",
    "gn:feature_code":"PPL",
    "gn:name":"Sayj\u0101n a\u015f \u015eakr",
    "gn:population":0,
    "gn:timezone":"Asia/Baghdad",
    "iso:country":"IQ",
    "name:ara_x_preferred":[
        "\u0633\u064a\u062c\u0627\u0646 \u0627\u0644\u0635\u0643\u0631"
    ],
    "name:und_x_variant":[
        "Sayj\u0101n a\u015f \u015eakr"
    ],
    "wof:name":"Sayjan as Sakr",
    "wof:placetype":"locality"
},
  "geometry": {"coordinates":[41.74263,36.00363],"type":"Point"}
}