{
  "type": "Feature",
  "properties": {
    "gn:admin1_code":"10.0",
    "gn:admin2_code":"94590.0",
    "gn:asciiname":"Tiran Agha Namiq",
    "gn:country_code":"IQ",
    "gn:dem":203,
    "gn:feature_class":"P",
    "gn:feature_code":"PPL",
    "gn:name":"T\u012br\u0101n \u0100gh\u0101 N\u0101miq",
    "gn:population":0,
    "gn:timezone":"Asia/Baghdad",
    "iso:country":"IQ",
    "name:ara_x_preferred":[
        "\u062a\u064a\u0631\u0627\u0646 \u0622\u063a\u0627 \u0646\u0627\u0645\u0642"
    ],
    "name:kur_x_preferred":[
        "T\u00eeran Agha\u00ee Namq"
    ],
    "name:kur_x_variant":[
        "T\u00eeran Agha",
        "\u062a\u064a\u0631\u0627\u0646 \u0626\u0627\u063a\u0627\u0649 \u0646\u0627\u0645\u0642",
        "\u062a\u064a\u0631\u0627\u0646 \u0626\u0627\u063a\u0627"
    ],
    "name:und_x_variant":[
        "Tayr\u0101n-i N\u0101miq \u0100gh\u0101",
        "T\u012br\u0101n \u0100gh\u0101 N\u0101miq",
        "Tir\u0101n \u0100gh\u0101",
        "Teran Agha"
    ],
    "wof:name":"Tiran Agha Namiq",
    "wof:placetype":"locality"
},
  "geometry": {"coordinates":[45.36452,34.62732],"type":"Point"}
}