{
  "type": "Feature",
  "properties": {
    "gn:admin1_code":"11.0",
    "gn:admin2_code":"9166588.0",
    "gn:asciiname":"Banat Kalan",
    "gn:country_code":"IQ",
    "gn:dem":531,
    "gn:feature_class":"P",
    "gn:feature_code":"PPL",
    "gn:name":"B\u0101nat Kal\u0101n",
    "gn:population":0,
    "gn:timezone":"Asia/Baghdad",
    "iso:country":"IQ",
    "name:ara_x_preferred":[
        "\u0628\u0627\u0646\u0629 \u0643\u0644\u0627\u0646"
    ],
    "name:und_x_variant":[
        "B\u0101nah Kal\u0101n",
        "B\u0101nat Kal\u0101n"
    ],
    "wof:name":"Banat Kalan",
    "wof:placetype":"locality"
},
  "geometry": {"coordinates":[44.70946,35.95979000000001],"type":"Point"}
}