{
  "type": "Feature",
  "properties": {
    "gn:admin1_code":"10.0",
    "gn:admin2_code":"9166680.0",
    "gn:asciiname":"Imam al Abyad",
    "gn:cc2":"IQ",
    "gn:country_code":"IQ",
    "gn:dem":43,
    "gn:feature_class":"P",
    "gn:feature_code":"PPL",
    "gn:name":"Im\u0101m al Abya\u1e11",
    "gn:population":0,
    "gn:timezone":"Asia/Baghdad",
    "iso:country":"IQ",
    "name:und_x_variant":[
        "Imam Abyadh",
        "Im\u0101m al Abya\u1e11"
    ],
    "wof:name":"Imam al Abyad",
    "wof:placetype":"locality"
},
  "geometry": {"coordinates":[44.76667,33.58333],"type":"Point"}
}