{
  "type": "Feature",
  "properties": {
    "gn:admin1_code":"5.0",
    "gn:admin2_code":"9166596.0",
    "gn:asciiname":"Dawlkan",
    "gn:country_code":"IQ",
    "gn:dem":706,
    "gn:feature_class":"P",
    "gn:feature_code":"PPL",
    "gn:name":"Dawlk\u0101n",
    "gn:population":0,
    "gn:timezone":"Asia/Baghdad",
    "iso:country":"IQ",
    "name:ara_x_preferred":[
        "\u062f\u0648\u0644\u0643\u0627\u0646"
    ],
    "name:und_x_variant":[
        "Dawlk\u0101n"
    ],
    "wof:name":"Dawlkan",
    "wof:placetype":"locality"
},
  "geometry": {"coordinates":[45.09293,35.81702999999999],"type":"Point"}
}