{
  "type": "Feature",
  "properties": {
    "gn:admin1_code":"18.0",
    "gn:admin2_code":"91594.0",
    "gn:asciiname":"Muhsin al 'Abd Allah",
    "gn:country_code":"IQ",
    "gn:dem":92,
    "gn:feature_class":"P",
    "gn:feature_code":"PPL",
    "gn:name":"Mu\u1e29sin al \u2018Abd All\u0101h",
    "gn:population":0,
    "gn:timezone":"Asia/Baghdad",
    "iso:country":"IQ",
    "name:ara_x_preferred":[
        "\u0645\u062d\u0633\u0646 \u0627\u0644\u0639\u0628\u062f \ufdf2"
    ],
    "name:und_x_variant":[
        "Mu\u1e29sin al \u2018Abd All\u0101h"
    ],
    "wof:name":"Muhsin al 'Abd Allah",
    "wof:placetype":"locality"
},
  "geometry": {"coordinates":[43.63994,34.28583],"type":"Point"}
}