{
  "type": "Feature",
  "properties": {
    "gn:admin1_code":"11.0",
    "gn:admin2_code":"9166588.0",
    "gn:asciiname":"Shaykh Rawwan",
    "gn:country_code":"IQ",
    "gn:dem":669,
    "gn:feature_class":"P",
    "gn:feature_code":"PPL",
    "gn:name":"Shaykh Raww\u0101n",
    "gn:population":0,
    "gn:timezone":"Asia/Baghdad",
    "iso:country":"IQ",
    "name:ara_x_preferred":[
        "\u0634\u064a\u062e \u0631\u0648\u0627\u0646"
    ],
    "name:kur_x_preferred":[
        "\u0634\u06ce\u062e \u0626\u0627\u0648\u062f\u0627\u06b5\u0627\u0646"
    ],
    "name:kur_x_variant":[
        "Sh\u00eax Awda\u0142an",
        "Sh\u00eaxerwan",
        "\u0634\u06ce\u062e\u06d5\u0631\u0648\u0627\u0646"
    ],
    "name:und_x_variant":[
        "Shaykh Ard\u0101n",
        "Shekh Awdalan",
        "Shaykh Raww\u0101n",
        "\u0634\u064a\u062e \u0631\u0648\u0627\u0646",
        "Shekharwan"
    ],
    "wof:name":"Shaykh Rawwan",
    "wof:placetype":"locality"
},
  "geometry": {"coordinates":[44.54608,36.08443],"type":"Point"}
}