{
  "type": "Feature",
  "properties": {
    "gn:admin1_code":"7.0",
    "gn:admin2_code":"99101.0",
    "gn:asciiname":"Rashid Farhan 'Udwan",
    "gn:country_code":"IQ",
    "gn:dem":35,
    "gn:feature_class":"P",
    "gn:feature_code":"PPL",
    "gn:name":"Rash\u012bd Far\u1e29\u0101n \u2018Udw\u0101n",
    "gn:population":0,
    "gn:timezone":"Asia/Baghdad",
    "iso:country":"IQ",
    "name:ara_x_preferred":[
        "\u0631\u0634\u064a\u062f \u0641\u0631\u062d\u0627\u0646 \u0639\u062f\u0648\u0627\u0646"
    ],
    "name:und_x_variant":[
        "Rash\u012bd Far\u1e29\u0101n \u2018Udw\u0101n"
    ],
    "wof:name":"Rashid Farhan 'Udwan",
    "wof:placetype":"locality"
},
  "geometry": {"coordinates":[44.38899,33.14338],"type":"Point"}
}