{
  "type": "Feature",
  "properties": {
    "gn:admin1_code":"18.0",
    "gn:admin2_code":"9167093.0",
    "gn:asciiname":"'Arab Majbal Madi",
    "gn:country_code":"IQ",
    "gn:dem":67,
    "gn:feature_class":"P",
    "gn:feature_code":"PPL",
    "gn:name":"\u2018Arab Majbal M\u0101\u1e11\u012b",
    "gn:population":0,
    "gn:timezone":"Asia/Baghdad",
    "iso:country":"IQ",
    "name:ara_x_preferred":[
        "\u0639\u0631\u0628 \u0645\u062c\u0628\u0644 \u0645\u0627\u0636\u064a"
    ],
    "name:und_x_variant":[
        "\u2018Arab Majbal M\u0101\u1e11\u012b"
    ],
    "wof:name":"'Arab Majbal Madi",
    "wof:placetype":"locality"
},
  "geometry": {"coordinates":[43.83605,34.06949],"type":"Point"}
}