{
  "type": "Feature",
  "properties": {
    "gn:admin1_code":"7.0",
    "gn:admin2_code":"99101.0",
    "gn:asciiname":"Majid Mukhlif",
    "gn:country_code":"IQ",
    "gn:dem":31,
    "gn:feature_class":"P",
    "gn:feature_code":"PPL",
    "gn:name":"Maj\u012bd Mukhlif",
    "gn:population":0,
    "gn:timezone":"Asia/Baghdad",
    "iso:country":"IQ",
    "name:ara_x_preferred":[
        "\u0645\u062c\u064a\u062f \u0645\u062e\u0644\u0641"
    ],
    "name:und_x_variant":[
        "Maj\u012bd Mukhlif"
    ],
    "wof:name":"Majid Mukhlif",
    "wof:placetype":"locality"
},
  "geometry": {"coordinates":[44.36178,32.91854],"type":"Point"}
}