{
  "type": "Feature",
  "properties": {
    "gn:admin1_code":"15.0",
    "gn:admin2_code":"9166608.0",
    "gn:asciiname":"Muhammad 'Abd al 'Aziz",
    "gn:country_code":"IQ",
    "gn:dem":304,
    "gn:feature_class":"P",
    "gn:feature_code":"PPL",
    "gn:name":"Mu\u1e29ammad \u2018Abd al \u2018Az\u012bz",
    "gn:population":0,
    "gn:timezone":"Asia/Baghdad",
    "iso:country":"IQ",
    "name:ara_x_preferred":[
        "\u0645\u062d\u0645\u062f \u0639\u0628\u062f \u0627\u0644\u0639\u0632\u064a\u0632"
    ],
    "name:und_x_variant":[
        "Mu\u1e29ammad \u2018Abd al \u2018Az\u012bz"
    ],
    "wof:name":"Muhammad 'Abd al 'Aziz",
    "wof:placetype":"locality"
},
  "geometry": {"coordinates":[41.71796,36.01152000000001],"type":"Point"}
}