{
  "type": "Feature",
  "properties": {
    "gn:admin1_code":"5.0",
    "gn:admin2_code":"98464.0",
    "gn:asciiname":"Mir Yasin",
    "gn:country_code":"IQ",
    "gn:dem":1239,
    "gn:feature_class":"P",
    "gn:feature_code":"PPL",
    "gn:name":"M\u012br Y\u0101s\u012bn",
    "gn:population":0,
    "gn:timezone":"Asia/Baghdad",
    "iso:country":"IQ",
    "name:ara_x_preferred":[
        "M\u012br Y\u0101s\u012bn"
    ],
    "name:ara_x_variant":[
        "\u0645\u064a\u0631 \u064a\u0627\u0633\u064a\u0646"
    ],
    "name:kur_x_preferred":[
        "M\u00eer Yas\u00ee"
    ],
    "name:kur_x_variant":[
        "M\u00eer Yas\u00ee Ser\u00fb",
        "\u0645\u064a\u0631 \u064a\u0627\u0633\u0649",
        "\u0645\u064a\u0631 \u064a\u0627\u0633\u0649 \u0633\u06d5\u0631\u0648\u0648"
    ],
    "name:und_x_variant":[
        "M\u012br Y\u0101s\u012bn-i Zh\u016br\u016b",
        "M\u012br Y\u0101s\u012bn al \u2018Uly\u00e1",
        "M\u012br Y\u0101s\u012bn-i Khw\u0101r\u012b",
        "M\u012br Y\u0101s\u012bn-i Khw\u0101r\u016b",
        "Meer Yasi"
    ],
    "wof:name":"Mir Yasin",
    "wof:placetype":"locality"
},
  "geometry": {"coordinates":[45.50816,35.31606],"type":"Point"}
}