{
  "type": "Feature",
  "properties": {
    "gn:admin1_code":"4.0",
    "gn:admin2_code":"98634.0",
    "gn:asciiname":"An Naghshuraydisiyah",
    "gn:country_code":"IQ",
    "gn:dem":20,
    "gn:feature_class":"P",
    "gn:feature_code":"PPL",
    "gn:name":"An Naghshuraydis\u012byah",
    "gn:population":0,
    "gn:timezone":"Asia/Baghdad",
    "iso:country":"IQ",
    "name:ara_x_preferred":[
        "\u0627\u0644\u0646\u063a\u0634\u0631\u064a\u062f\u0633\u064a\u0629"
    ],
    "name:und_x_variant":[
        "An Naghshuraydis\u012byah"
    ],
    "wof:name":"An Naghshuraydisiyah",
    "wof:placetype":"locality"
},
  "geometry": {"coordinates":[44.56545,31.68668],"type":"Point"}
}