{
  "type": "Feature",
  "properties": {
    "gn:admin1_code":"13.0",
    "gn:admin2_code":"6770659.0",
    "gn:asciiname":"Qaryat Albu Sayf",
    "gn:country_code":"IQ",
    "gn:dem":173,
    "gn:feature_class":"P",
    "gn:feature_code":"PPLL",
    "gn:name":"Qaryat \u0100lb\u016b Sayf",
    "gn:population":0,
    "gn:timezone":"Asia/Baghdad",
    "iso:country":"IQ",
    "name:ara_x_preferred":[
        "\u0642\u0631\u064a\u0629 \u0627\u0644\u0628\u0648 \u0633\u064a\u0641"
    ],
    "name:und_x_variant":[
        "Qaryat \u0100lb\u016b Sayf"
    ],
    "wof:name":"Qaryat Albu Sayf",
    "wof:placetype":"locality"
},
  "geometry": {"coordinates":[43.74998,35.14123],"type":"Point"}
}