{
  "type": "Feature",
  "properties": {
    "gn:admin1_code":"18.0",
    "gn:admin2_code":"9166598.0",
    "gn:asciiname":"Qaryat Khashamilah",
    "gn:country_code":"IQ",
    "gn:dem":170,
    "gn:feature_class":"P",
    "gn:feature_code":"PPL",
    "gn:name":"Qaryat Khash\u0101milah",
    "gn:population":0,
    "gn:timezone":"Asia/Baghdad",
    "iso:country":"IQ",
    "name:ara_x_preferred":[
        "\u0642\u0631\u064a\u0629 \u062e\u0634\u0627\u0645\u0644\u0629"
    ],
    "name:und_x_variant":[
        "Qaryat Khash\u0101milah"
    ],
    "wof:name":"Qaryat Khashamilah",
    "wof:placetype":"locality"
},
  "geometry": {"coordinates":[44.47341,34.85703],"type":"Point"}
}