{
  "type": "Feature",
  "properties": {
    "gn:admin1_code":"1.0",
    "gn:admin2_code":"9166650.0",
    "gn:asciiname":"Shabalah",
    "gn:country_code":"IQ",
    "gn:dem":151,
    "gn:feature_class":"P",
    "gn:feature_code":"PPL",
    "gn:name":"Shab\u0101lah",
    "gn:population":0,
    "gn:timezone":"Asia/Baghdad",
    "iso:country":"IQ",
    "name:ara_x_preferred":[
        "\u0634\u0628\u0627\u0644\u0629"
    ],
    "name:und_x_variant":[
        "Shab\u0101lah"
    ],
    "wof:name":"Shabalah",
    "wof:placetype":"locality"
},
  "geometry": {"coordinates":[41.8278,34.50632],"type":"Point"}
}