{
  "type": "Feature",
  "properties": {
    "gn:admin1_code":"7.0",
    "gn:admin2_code":"9179819.0",
    "gn:asciiname":"Qaryat al Wardi",
    "gn:country_code":"IQ",
    "gn:dem":34,
    "gn:feature_class":"P",
    "gn:feature_code":"PPL",
    "gn:name":"Qaryat al Ward\u012b",
    "gn:population":0,
    "gn:timezone":"Asia/Baghdad",
    "iso:country":"IQ",
    "name:ara_x_preferred":[
        "\u0642\u0631\u064a\u0629 \u0627\u0644\u0648\u0631\u062f\u064a"
    ],
    "name:und_x_variant":[
        "Qaryat al Ward\u012b"
    ],
    "wof:name":"Qaryat al Wardi",
    "wof:placetype":"locality"
},
  "geometry": {"coordinates":[44.53788,33.1899],"type":"Point"}
}