{
  "type": "Feature",
  "properties": {
    "gn:admin1_code":"6.0",
    "gn:admin2_code":"6818313.0",
    "gn:asciiname":"Wardiyat al 'Arab",
    "gn:country_code":"IQ",
    "gn:dem":35,
    "gn:feature_class":"P",
    "gn:feature_code":"PPL",
    "gn:name":"Ward\u012byat al \u2018Arab",
    "gn:population":0,
    "gn:timezone":"Asia/Baghdad",
    "iso:country":"IQ",
    "name:ara_x_preferred":[
        "\u0648\u0631\u062f\u064a\u0629 \u0627\u0644\u0639\u0631\u0628"
    ],
    "name:und_x_variant":[
        "Ward\u012byat al \u2018Arab"
    ],
    "wof:name":"Wardiyat al 'Arab",
    "wof:placetype":"locality"
},
  "geometry": {"coordinates":[44.4925,32.4821],"type":"Point"}
}