{
  "type": "Feature",
  "properties": {
    "gn:admin1_code":"2.0",
    "gn:admin2_code":"98994.0",
    "gn:asciiname":"Qaryat ash Sharamkhah",
    "gn:country_code":"IQ",
    "gn:dem":5,
    "gn:feature_class":"P",
    "gn:feature_code":"PPL",
    "gn:name":"Qaryat ash Shar\u0101mkhah",
    "gn:population":0,
    "gn:timezone":"Asia/Baghdad",
    "iso:country":"IQ",
    "name:ara_x_preferred":[
        "\u0642\u0631\u064a\u0629 \u0627\u0644\u0634\u0631\u0627\u0645\u062e\u0629"
    ],
    "name:und_x_variant":[
        "Qaryat ash Shar\u0101mkhah"
    ],
    "wof:name":"Qaryat ash Sharamkhah",
    "wof:placetype":"locality"
},
  "geometry": {"coordinates":[47.57213,30.83572],"type":"Point"}
}