{
  "type": "Feature",
  "properties": {
    "gn:admin1_code":"7.0",
    "gn:admin2_code":"99101.0",
    "gn:asciiname":"Salih Dha'ar",
    "gn:country_code":"IQ",
    "gn:dem":35,
    "gn:feature_class":"P",
    "gn:feature_code":"PPL",
    "gn:name":"\u015e\u0101li\u1e29 Dha\u2018\u0101r",
    "gn:population":0,
    "gn:timezone":"Asia/Baghdad",
    "iso:country":"IQ",
    "name:ara_x_preferred":[
        "\u0635\u0627\u0644\u062d \u0630\u0639\u0627\u0631"
    ],
    "name:und_x_variant":[
        "\u015e\u0101li\u1e29 Dha\u2018\u0101r"
    ],
    "wof:name":"Salih Dha'ar",
    "wof:placetype":"locality"
},
  "geometry": {"coordinates":[44.4083,33.05837],"type":"Point"}
}