{
  "type": "Feature",
  "properties": {
    "gn:admin1_code":"15.0",
    "gn:admin2_code":"98820.0",
    "gn:asciiname":"Tall Asmawah",
    "gn:country_code":"IQ",
    "gn:dem":987,
    "gn:feature_class":"P",
    "gn:feature_code":"PPL",
    "gn:name":"Tall Asm\u0101wah",
    "gn:population":0,
    "gn:timezone":"Asia/Baghdad",
    "iso:country":"IQ",
    "name:und_x_variant":[
        "Tall Asm\u0101wah"
    ],
    "wof:name":"Tall Asmawah",
    "wof:placetype":"locality"
},
  "geometry": {"coordinates":[43.68013,36.81967],"type":"Point"}
}