{
  "type": "Feature",
  "properties": {
    "gn:admin1_code":"7.0",
    "gn:admin2_code":"99173.0",
    "gn:asciiname":"Khalifah al Ja'atah",
    "gn:country_code":"IQ",
    "gn:dem":41,
    "gn:feature_class":"P",
    "gn:feature_code":"PPL",
    "gn:name":"Khal\u012bfah al Ja\u2018\u0101\u0163ah",
    "gn:population":0,
    "gn:timezone":"Asia/Baghdad",
    "iso:country":"IQ",
    "name:und_x_variant":[
        "Khal\u012bfah al Ja\u2018\u0101\u0163ah"
    ],
    "wof:name":"Khalifah al Ja'atah",
    "wof:placetype":"locality"
},
  "geometry": {"coordinates":[44.2945,33.46904],"type":"Point"}
}