{
  "type": "Feature",
  "properties": {
    "gn:admin1_code":"7.0",
    "gn:admin2_code":"99173.0",
    "gn:asciiname":"Hamamiyat",
    "gn:country_code":"IQ",
    "gn:dem":38,
    "gn:feature_class":"P",
    "gn:feature_code":"PPL",
    "gn:name":"\u1e28am\u0101m\u012byat",
    "gn:population":0,
    "gn:timezone":"Asia/Baghdad",
    "iso:country":"IQ",
    "name:ara_x_preferred":[
        "\u0627\u0644\u062d\u0645\u0627\u0645\u064a\u0627\u062a"
    ],
    "name:fas_x_preferred":[
        "\u0627\u0644\u062d\u0645\u0627\u0645\u06cc\u0627\u062a"
    ],
    "name:pol_x_preferred":[
        "Al-Hamamijjat"
    ],
    "name:und_x_variant":[
        "Ham\u0101mi\u0101l",
        "Ham\u0101mi\u0101t",
        "\u1e28am\u0101my\u0101l",
        "\u1e28am\u0101m\u012byat"
    ],
    "name:vie_x_preferred":[
        "Hamamiyat"
    ],
    "wof:name":"Hamamiyat",
    "wof:placetype":"locality"
},
  "geometry": {"coordinates":[44.20139,33.50861],"type":"Point"}
}