{
  "type": "Feature",
  "properties": {
    "gn:admin1_code":"16.0",
    "gn:admin2_code":"99351.0",
    "gn:asciiname":"Jamil Shahir Bani",
    "gn:country_code":"IQ",
    "gn:dem":13,
    "gn:feature_class":"P",
    "gn:feature_code":"PPL",
    "gn:name":"Jam\u012bl Shahir B\u0101n\u012b",
    "gn:population":0,
    "gn:timezone":"Asia/Baghdad",
    "iso:country":"IQ",
    "name:ara_x_preferred":[
        "\u062c\u0645\u064a\u0644 \u0634\u0647\u0631 \u0628\u0627\u0646\u064a"
    ],
    "name:und_x_variant":[
        "Jam\u012bl Shahir B\u0101n\u012b"
    ],
    "wof:name":"Jamil Shahir Bani",
    "wof:placetype":"locality"
},
  "geometry": {"coordinates":[46.18176,32.22308],"type":"Point"}
}