{
  "type": "Feature",
  "properties": {
    "gn:admin1_code":"6.0",
    "gn:admin2_code":"99348.0",
    "gn:asciiname":"Qaryat ar Raghliyah",
    "gn:country_code":"IQ",
    "gn:dem":30,
    "gn:feature_class":"P",
    "gn:feature_code":"PPL",
    "gn:name":"Qaryat ar Raghl\u012byah",
    "gn:population":0,
    "gn:timezone":"Asia/Baghdad",
    "iso:country":"IQ",
    "name:ara_x_preferred":[
        "\u0642\u0631\u064a\u0629 \u0627\u0644\u0631\u063a\u0644\u064a\u0629"
    ],
    "name:und_x_variant":[
        "Qaryat ar Raghl\u012byah"
    ],
    "wof:name":"Qaryat ar Raghliyah",
    "wof:placetype":"locality"
},
  "geometry": {"coordinates":[44.30074000000001,32.52941],"type":"Point"}
}