{
  "type": "Feature",
  "properties": {
    "gn:admin1_code":"10.0",
    "gn:admin2_code":"94590.0",
    "gn:asciiname":"'Ali al Wafay",
    "gn:country_code":"IQ",
    "gn:dem":65,
    "gn:feature_class":"P",
    "gn:feature_code":"PPLL",
    "gn:name":"\u2018Al\u012b al Waf\u0101y",
    "gn:population":0,
    "gn:timezone":"Asia/Baghdad",
    "iso:country":"IQ",
    "name:ara_x_preferred":[
        "\u0639\u0644\u064a \u0627\u0644\u0648\u0641\u0627\u064a"
    ],
    "name:und_x_variant":[
        "\u2018Al\u012b al Waf\u0101y"
    ],
    "wof:name":"'Ali al Wafay",
    "wof:placetype":"locality"
},
  "geometry": {"coordinates":[44.97454000000001,34.00980999999999],"type":"Point"}
}