{
  "type": "Feature",
  "properties": {
    "gn:admin1_code":"9.0",
    "gn:admin2_code":"99185.0",
    "gn:asciiname":"Dur Siyadin as Samak",
    "gn:country_code":"IQ",
    "gn:dem":2,
    "gn:feature_class":"P",
    "gn:feature_code":"PPL",
    "gn:name":"D\u016br \u015eiy\u0101d\u012bn as Samak",
    "gn:population":0,
    "gn:timezone":"Asia/Baghdad",
    "iso:country":"IQ",
    "name:ara_x_preferred":[
        "\u062f\u0648\u0631 \u0635\u064a\u0627\u062f\u064a\u0646 \u0627\u0644\u0633\u0645\u0643"
    ],
    "name:und_x_variant":[
        "D\u016br \u015eiy\u0101d\u012bn as Samak"
    ],
    "wof:name":"Dur Siyadin as Samak",
    "wof:placetype":"locality"
},
  "geometry": {"coordinates":[47.09792,30.87903],"type":"Point"}
}