{
  "type": "Feature",
  "properties": {
    "gn:admin1_code":"10.0",
    "gn:admin2_code":"94590.0",
    "gn:asciiname":"Sunkar",
    "gn:country_code":"IQ",
    "gn:dem":58,
    "gn:feature_class":"P",
    "gn:feature_code":"PPL",
    "gn:name":"Sunkar",
    "gn:population":0,
    "gn:timezone":"Asia/Baghdad",
    "iso:country":"IQ",
    "name:ara_x_preferred":[
        "\u0633\u0646\u0643\u0631"
    ],
    "name:und_x_variant":[
        "Sulaim\u0101ni",
        "Sulaym\u0101n\u012byah",
        "Sulaym\u0101n\u012b",
        "Sunkar"
    ],
    "wof:name":"Sunkar",
    "wof:placetype":"locality"
},
  "geometry": {"coordinates":[44.8165,34.04334],"type":"Point"}
}