{
  "type": "Feature",
  "properties": {
    "gn:admin1_code":"13.0",
    "gn:asciiname":"Barkan",
    "gn:country_code":"IQ",
    "gn:dem":276,
    "gn:feature_class":"P",
    "gn:feature_code":"PPL",
    "gn:name":"Barkan",
    "gn:population":0,
    "gn:timezone":"Asia/Baghdad",
    "iso:country":"IQ",
    "name:ara_x_preferred":[
        "\u0628\u0631\u0643\u0646"
    ],
    "name:ara_x_variant":[
        "\u0628\u0631\u0643\u0627\u0646"
    ],
    "name:ces_x_preferred":[
        "Barkan"
    ],
    "name:fas_x_preferred":[
        "\u0628\u0631\u06a9\u0627\u0646"
    ],
    "name:heb_x_preferred":[
        "\u05d1\u05e8\u05e7\u05df"
    ],
    "name:kur_x_preferred":[
        "Berk\u00een"
    ],
    "name:kur_x_variant":[
        "\u0628\u06d5\u0631\u0643\u064a\u0646"
    ],
    "name:nno_x_preferred":[
        "Barkan"
    ],
    "name:pol_x_preferred":[
        "Barkan"
    ],
    "name:rus_x_preferred":[
        "\u0411\u0430\u0440\u043a\u0430\u043d"
    ],
    "name:und_x_variant":[
        "B\u016blikhtir",
        "\u0628\u0648 \u0644\u062e\u062a\u0631",
        "Barkin"
    ],
    "wof:name":"Barkan",
    "wof:placetype":"locality"
},
  "geometry": {"coordinates":[44.09596,35.71508],"type":"Point"}
}