{
  "type": "Feature",
  "properties": {
    "gn:admin1_code":"15.0",
    "gn:admin2_code":"9166541.0",
    "gn:asciiname":"Kuwikin",
    "gn:country_code":"IQ",
    "gn:dem":436,
    "gn:feature_class":"P",
    "gn:feature_code":"PPL",
    "gn:name":"Kuw\u012bkin",
    "gn:population":0,
    "gn:timezone":"Asia/Baghdad",
    "iso:country":"IQ",
    "name:ara_x_preferred":[
        "\u0643\u0648\u064a\u0643\u0646"
    ],
    "name:ara_x_variant":[
        "Kuw\u012bkin"
    ],
    "name:kur_x_preferred":[
        "Kuw\u00eekn"
    ],
    "name:und_x_variant":[
        "Kuikn"
    ],
    "wof:name":"Kuwikin",
    "wof:placetype":"locality"
},
  "geometry": {"coordinates":[43.32634,36.5596],"type":"Point"}
}