{
  "type": "Feature",
  "properties": {
    "gn:admin1_code":"11.0",
    "gn:admin2_code":"93817.0",
    "gn:asciiname":"Qaryat Ghadir ash Shawk",
    "gn:country_code":"IQ",
    "gn:dem":188,
    "gn:feature_class":"P",
    "gn:feature_code":"PPL",
    "gn:name":"Qaryat Ghad\u012br ash Shawk",
    "gn:population":0,
    "gn:timezone":"Asia/Baghdad",
    "iso:country":"IQ",
    "name:ara_x_preferred":[
        "\u0642\u0631\u064a\u0629 \u063a\u062f\u064a\u0631 \u0627\u0644\u0634\u0648\u0643"
    ],
    "name:und_x_variant":[
        "Qaryat Ghad\u012br ash Shawk"
    ],
    "wof:name":"Qaryat Ghadir ash Shawk",
    "wof:placetype":"locality"
},
  "geometry": {"coordinates":[43.41163,35.45064],"type":"Point"}
}