{
  "type": "Feature",
  "properties": {
    "gn:admin1_code":"7.0",
    "gn:admin2_code":"99101.0",
    "gn:asciiname":"Hamud al 'Abbas",
    "gn:country_code":"IQ",
    "gn:dem":38,
    "gn:feature_class":"P",
    "gn:feature_code":"PPL",
    "gn:name":"\u1e28am\u016bd al \u2018Abb\u0101s",
    "gn:population":0,
    "gn:timezone":"Asia/Baghdad",
    "iso:country":"IQ",
    "name:ara_x_preferred":[
        "\u062d\u0645\u0648\u062f \u0627\u0644\u0639\u0628\u0627\u0633"
    ],
    "name:und_x_variant":[
        "\u1e28amm\u016bd al \u2018Abb\u0101s",
        "\u1e28am\u016bd al \u2018Abb\u0101s"
    ],
    "wof:name":"Hamud al 'Abbas",
    "wof:placetype":"locality"
},
  "geometry": {"coordinates":[44.38068,32.9105],"type":"Point"}
}