{
  "type": "Feature",
  "properties": {
    "gn:admin1_code":"15.0",
    "gn:admin2_code":"98820.0",
    "gn:asciiname":"Kawmah Zard",
    "gn:country_code":"IQ",
    "gn:dem":398,
    "gn:feature_class":"P",
    "gn:feature_code":"PPL",
    "gn:name":"Kawmah Zard",
    "gn:population":0,
    "gn:timezone":"Asia/Baghdad",
    "iso:country":"IQ",
    "name:ara_x_preferred":[
        "\u0643\u0648\u0645\u0629 \u0632\u0631\u062f"
    ],
    "name:kur_x_preferred":[
        "Gome Zerd"
    ],
    "name:kur_x_variant":[
        "\u06af\u06c6\u0645\u06d5 \u0632\u06d5\u0631\u062f"
    ],
    "name:und_x_variant":[
        "G\u016bmah Zard",
        "Goma Zard",
        "Kawmah Zard"
    ],
    "wof:name":"Kawmah Zard",
    "wof:placetype":"locality"
},
  "geometry": {"coordinates":[43.68234,36.43476],"type":"Point"}
}