{
  "type": "Feature",
  "properties": {
    "gn:admin1_code":"5.0",
    "gn:admin2_code":"97416.0",
    "gn:asciiname":"Khewlanaka",
    "gn:country_code":"IQ",
    "gn:dem":586,
    "gn:feature_class":"P",
    "gn:feature_code":"PPL",
    "gn:name":"Khewlan\u0101ka",
    "gn:population":0,
    "gn:timezone":"Asia/Baghdad",
    "iso:country":"IQ",
    "name:kur_x_preferred":[
        "X\u00eawl\u00ean"
    ],
    "name:kur_x_variant":[
        "Xw\u00eal\u00eaneke",
        "\u062e\u06ce\u0648\u0644\u06ce\u0646",
        "\u062e\u0648\u06ce\u0644\u06ce\u0646\u06d5\u0643\u06d5"
    ],
    "name:und_x_variant":[
        "Khewlan\u0101ka",
        "Khwelenaka"
    ],
    "wof:name":"Khewlanaka",
    "wof:placetype":"locality"
},
  "geometry": {"coordinates":[45.00278,35.36555999999999],"type":"Point"}
}