{
  "type": "Feature",
  "properties": {
    "gn:admin1_code":"5.0",
    "gn:admin2_code":"91176.0",
    "gn:asciiname":"Ulaghlu",
    "gn:country_code":"IQ",
    "gn:dem":1081,
    "gn:feature_class":"P",
    "gn:feature_code":"PPL",
    "gn:name":"Ul\u0101ghl\u016b",
    "gn:population":0,
    "gn:timezone":"Asia/Baghdad",
    "iso:country":"IQ",
    "name:ara_x_preferred":[
        "Ul\u0101ghl\u016b"
    ],
    "name:ara_x_variant":[
        "\u0627\u0648\u0644\u0627\u063a\u0644\u0648"
    ],
    "name:und_x_variant":[
        "\u016al\u0101ghl\u016b"
    ],
    "wof:name":"Ulaghlu",
    "wof:placetype":"locality"
},
  "geometry": {"coordinates":[45.36981,35.83099],"type":"Point"}
}