{
  "type": "Feature",
  "properties": {
    "gn:admin1_code":"7.0",
    "gn:admin2_code":"99101.0",
    "gn:asciiname":"Fadil Nusayf",
    "gn:country_code":"IQ",
    "gn:dem":32,
    "gn:feature_class":"P",
    "gn:feature_code":"PPL",
    "gn:name":"F\u0101\u1e11il Nu\u015fayf",
    "gn:population":0,
    "gn:timezone":"Asia/Baghdad",
    "iso:country":"IQ",
    "name:ara_x_preferred":[
        "\u0641\u0627\u0636\u0644 \u0646\u0635\u064a\u0641"
    ],
    "name:und_x_variant":[
        "F\u0101\u1e11il Nu\u015fayf"
    ],
    "wof:name":"Fadil Nusayf",
    "wof:placetype":"locality"
},
  "geometry": {"coordinates":[44.50645,32.94035],"type":"Point"}
}