{
  "type": "Feature",
  "properties": {
    "gn:admin1_code":"10.0",
    "gn:admin2_code":"94296.0",
    "gn:asciiname":"Saray Sharqi",
    "gn:country_code":"IQ",
    "gn:dem":127,
    "gn:feature_class":"P",
    "gn:feature_code":"PPL",
    "gn:name":"Sar\u0101y Sharq\u012b",
    "gn:population":0,
    "gn:timezone":"Asia/Baghdad",
    "iso:country":"IQ",
    "name:und_x_variant":[
        "Sar\u0101y Sharq\u012b",
        "Sar\u0101m\u012b Sharq\u012b",
        "Sar \u2018Al\u012b Sharq\u012b"
    ],
    "wof:name":"Saray Sharqi",
    "wof:placetype":"locality"
},
  "geometry": {"coordinates":[44.90333,34.44029],"type":"Point"}
}