{
  "type": "Feature",
  "properties": {
    "gn:admin1_code":"5.0",
    "gn:admin2_code":"91176.0",
    "gn:asciiname":"Chinaran",
    "gn:country_code":"IQ",
    "gn:dem":1152,
    "gn:feature_class":"P",
    "gn:feature_code":"PPL",
    "gn:name":"Chin\u0101r\u0101n",
    "gn:population":0,
    "gn:timezone":"Asia/Baghdad",
    "iso:country":"IQ",
    "name:ara_x_preferred":[
        "Chin\u0101r\u0101n"
    ],
    "name:ara_x_variant":[
        "\u0686\u0646\u0627\u0631\u0627\u0646"
    ],
    "name:kur_x_preferred":[
        "Chnaran"
    ],
    "name:kur_x_variant":[
        "Chnarey Sh\u00eax Let\u00eef",
        "\u0686\u0646\u0627\u0631\u06d5\u0649 \u0634\u06ce\u062e \u0644\u06d5\u062a\u064a\u0641"
    ],
    "wof:name":"Chinaran",
    "wof:placetype":"locality"
},
  "geometry": {"coordinates":[45.76173,35.61197],"type":"Point"}
}