{
  "type": "Feature",
  "properties": {
    "gn:admin1_code":"17.0",
    "gn:admin2_code":"9166629.0",
    "gn:asciiname":"Qaryat at Tarman",
    "gn:country_code":"IQ",
    "gn:dem":24,
    "gn:feature_class":"P",
    "gn:feature_code":"PPL",
    "gn:name":"Qaryat at Tarman",
    "gn:population":0,
    "gn:timezone":"Asia/Baghdad",
    "iso:country":"IQ",
    "name:ara_x_preferred":[
        "\u0642\u0631\u064a\u0629 \u0627\u0644\u062a\u0631\u0645\u0646"
    ],
    "wof:name":"Qaryat at Tarman",
    "wof:placetype":"locality"
},
  "geometry": {"coordinates":[44.42373,32.13477],"type":"Point"}
}