{
  "type": "Feature",
  "properties": {
    "gn:admin1_code":"1.0",
    "gn:admin2_code":"99455.0",
    "gn:asciiname":"Badawi at Talab",
    "gn:country_code":"IQ",
    "gn:dem":38,
    "gn:feature_class":"P",
    "gn:feature_code":"PPL",
    "gn:name":"Badaw\u012b a\u0163 \u0162alab",
    "gn:population":0,
    "gn:timezone":"Asia/Baghdad",
    "iso:country":"IQ",
    "name:ara_x_preferred":[
        "\u0628\u062f\u0648\u064a \u0627\u0644\u0637\u0644\u0628"
    ],
    "name:und_x_variant":[
        "Badaw\u012b a\u0163 \u0162alab"
    ],
    "wof:name":"Badawi at Talab",
    "wof:placetype":"locality"
},
  "geometry": {"coordinates":[43.93504,33.57553],"type":"Point"}
}