{
  "type": "Feature",
  "properties": {
    "gn:admin1_code":"14.0",
    "gn:admin2_code":"99097.0",
    "gn:asciiname":"Mawla",
    "gn:cc2":"IQ",
    "gn:country_code":"IQ",
    "gn:dem":7,
    "gn:feature_class":"P",
    "gn:feature_code":"PPL",
    "gn:name":"Mawl\u00e1",
    "gn:population":0,
    "gn:timezone":"Asia/Baghdad",
    "iso:country":"IQ",
    "name:und_x_variant":[
        "Maula",
        "Mawl\u00e1"
    ],
    "wof:name":"Mawla",
    "wof:placetype":"locality"
},
  "geometry": {"coordinates":[47.17167,31.4875],"type":"Point"}
}