{
  "type": "Feature",
  "properties": {
    "gn:admin1_code":"14.0",
    "gn:admin2_code":"99097.0",
    "gn:asciiname":"Mawla",
    "gn:cc2":"IQ",
    "gn:country_code":"IQ",
    "gn:dem":7,
    "gn:feature_class":"P",
    "gn:feature_code":"PPL",
    "gn:name":"Mawl\u00e1",
    "gn:population":0,
    "gn:timezone":"Asia/Baghdad",
    "iso:country":"IQ",
    "name:ara_x_preferred":[
        "\u0645\u0648\u0644\u0649"
    ],
    "name:azb_x_preferred":[
        "\u0645\u0648\u0644\u06cc"
    ],
    "name:cat_x_preferred":[
        "Mawla"
    ],
    "name:deu_x_preferred":[
        "Mawla"
    ],
    "name:fas_x_preferred":[
        "\u0645\u0648\u0644\u06cc"
    ],
    "name:ita_x_preferred":[
        "Mawl\u0101"
    ],
    "name:rus_x_preferred":[
        "\u041c\u0430\u0432\u043b\u0430"
    ],
    "name:spa_x_preferred":[
        "Mawla"
    ],
    "name:und_x_variant":[
        "Maula",
        "Mawl\u00e1"
    ],
    "wof:name":"Mawla",
    "wof:placetype":"locality"
},
  "geometry": {"coordinates":[47.17167,31.4875],"type":"Point"}
}