{
  "type": "Feature",
  "properties": {
    "gn:admin1_code":"2.0",
    "gn:admin2_code":"100049.0",
    "gn:asciiname":"Qaryat at Tawilah",
    "gn:country_code":"IQ",
    "gn:dem":0,
    "gn:feature_class":"P",
    "gn:feature_code":"PPL",
    "gn:name":"Qaryat a\u0163 \u0162aw\u012blah",
    "gn:population":0,
    "gn:timezone":"Asia/Baghdad",
    "iso:country":"IQ",
    "name:ara_x_preferred":[
        "\u0642\u0631\u064a\u0629 \u0627\u0644\u0637\u0648\u064a\u0644\u0629"
    ],
    "name:und_x_variant":[
        "Qaryat a\u0163 \u0162aw\u012blah"
    ],
    "wof:name":"Qaryat at Tawilah",
    "wof:placetype":"locality"
},
  "geometry": {"coordinates":[48.04094,30.46389000000001],"type":"Point"}
}