{
  "type": "Feature",
  "properties": {
    "gn:admin1_code":"1.0",
    "gn:admin2_code":"6765480.0",
    "gn:asciiname":"Tartasah",
    "gn:cc2":"IQ",
    "gn:country_code":"IQ",
    "gn:dem":138,
    "gn:feature_class":"P",
    "gn:feature_code":"PPL",
    "gn:name":"Tart\u0101sah",
    "gn:population":0,
    "gn:timezone":"Asia/Baghdad",
    "iso:country":"IQ",
    "name:und_x_variant":[
        "Tartasa"
    ],
    "wof:name":"Tartasah",
    "wof:placetype":"locality"
},
  "geometry": {"coordinates":[42.3775,34.3175],"type":"Point"}
}