{
  "type": "Feature",
  "properties": {
    "gn:admin1_code":"6.0",
    "gn:admin2_code":"6818313.0",
    "gn:asciiname":"Ghafil Hamid",
    "gn:country_code":"IQ",
    "gn:dem":27,
    "gn:feature_class":"P",
    "gn:feature_code":"PPL",
    "gn:name":"Gh\u0101fil \u1e28am\u012bd",
    "gn:population":0,
    "gn:timezone":"Asia/Baghdad",
    "iso:country":"IQ",
    "name:ara_x_preferred":[
        "\u063a\u0627\u0641\u0644 \u062d\u0645\u064a\u062f"
    ],
    "name:und_x_variant":[
        "Gh\u0101fil \u1e28am\u012bd"
    ],
    "wof:name":"Ghafil Hamid",
    "wof:placetype":"locality"
},
  "geometry": {"coordinates":[44.70506,32.60062],"type":"Point"}
}