{
  "type": "Feature",
  "properties": {
    "gn:admin1_code":"18.0",
    "gn:admin2_code":"91594.0",
    "gn:asciiname":"'Arab Salih al Wali",
    "gn:country_code":"IQ",
    "gn:dem":78,
    "gn:feature_class":"P",
    "gn:feature_code":"PPLL",
    "gn:name":"\u2018Arab \u015e\u0101li\u1e29 al Wal\u012b",
    "gn:population":0,
    "gn:timezone":"Asia/Baghdad",
    "iso:country":"IQ",
    "name:ara_x_preferred":[
        "\u0639\u0631\u0628 \u0635\u0627\u0644\u062d \u0627\u0644\u0648\u0644\u064a"
    ],
    "name:und_x_variant":[
        "\u2018Arab \u015e\u0101li\u1e29 al Wal\u012b"
    ],
    "wof:name":"'Arab Salih al Wali",
    "wof:placetype":"locality"
},
  "geometry": {"coordinates":[43.7371,34.42082],"type":"Point"}
}