{
  "type": "Feature",
  "properties": {
    "gn:admin1_code":"7.0",
    "gn:admin2_code":"99101.0",
    "gn:asciiname":"Zaydan 'Alwan",
    "gn:country_code":"IQ",
    "gn:dem":34,
    "gn:feature_class":"P",
    "gn:feature_code":"PPL",
    "gn:name":"Zayd\u0101n \u2018Alw\u0101n",
    "gn:population":0,
    "gn:timezone":"Asia/Baghdad",
    "iso:country":"IQ",
    "name:ara_x_preferred":[
        "\u0632\u064a\u062f\u0627\u0646 \u0639\u0644\u0648\u0627\u0646"
    ],
    "name:und_x_variant":[
        "Zayd\u0101n \u2018Alw\u0101n"
    ],
    "wof:name":"Zaydan 'Alwan",
    "wof:placetype":"locality"
},
  "geometry": {"coordinates":[44.45703,33.12475],"type":"Point"}
}