{
  "type": "Feature",
  "properties": {
    "gn:admin1_code":"5.0",
    "gn:admin2_code":"9166684.0",
    "gn:asciiname":"Suwayraw",
    "gn:country_code":"IQ",
    "gn:dem":1245,
    "gn:feature_class":"P",
    "gn:feature_code":"PPL",
    "gn:name":"Suwayr\u0101w",
    "gn:population":0,
    "gn:timezone":"Asia/Baghdad",
    "iso:country":"IQ",
    "name:ara_x_preferred":[
        "\u0633\u0648\u064a\u0631\u0627\u0648"
    ],
    "name:fas_x_preferred":[
        "S\u016br\u0101v"
    ],
    "name:kur_x_preferred":[
        "Suraw"
    ],
    "name:kur_x_variant":[
        "\u0633\u0648\u0631\u0627\u0648"
    ],
    "name:und_x_variant":[
        "S\u016br\u0101wah",
        "Suwayr\u0101w",
        "S\u016br\u0101wa",
        "Suwayr\u0101w\u0101",
        "\u0633\u0648\u064a\u0631\u0627\u0648\u0627"
    ],
    "wof:name":"Suwayraw",
    "wof:placetype":"locality"
},
  "geometry": {"coordinates":[46.01059,35.74816],"type":"Point"}
}