{
  "type": "Feature",
  "properties": {
    "gn:admin1_code":"6.0",
    "gn:admin2_code":"99358.0",
    "gn:asciiname":"Qaryat Albu Diba'",
    "gn:country_code":"IQ",
    "gn:dem":28,
    "gn:feature_class":"P",
    "gn:feature_code":"PPL",
    "gn:name":"Qaryat \u0100lb\u016b \u1e10ib\u0101\u2018",
    "gn:population":0,
    "gn:timezone":"Asia/Baghdad",
    "iso:country":"IQ",
    "name:ara_x_preferred":[
        "\u0642\u0631\u064a\u0629 \u0627\u0644\u0628\u0648 \u0636\u0628\u0627\u0639"
    ],
    "name:und_x_variant":[
        "Qaryat \u0100lb\u016b \u1e10ib\u0101\u2018"
    ],
    "wof:name":"Qaryat Albu Diba'",
    "wof:placetype":"locality"
},
  "geometry": {"coordinates":[44.52828,32.35706],"type":"Point"}
}