{
  "type": "Feature",
  "properties": {
    "gn:admin1_code":"18.0",
    "gn:admin2_code":"91594.0",
    "gn:asciiname":"Salman Sa'ud",
    "gn:country_code":"IQ",
    "gn:dem":105,
    "gn:feature_class":"P",
    "gn:feature_code":"PPL",
    "gn:name":"Salm\u0101n Sa\u2018\u016bd",
    "gn:population":0,
    "gn:timezone":"Asia/Baghdad",
    "iso:country":"IQ",
    "name:ara_x_preferred":[
        "\u0633\u0644\u0645\u0627\u0646 \u0633\u0639\u0648\u062f"
    ],
    "name:und_x_variant":[
        "Salm\u0101n Sa\u2018\u016bd"
    ],
    "wof:name":"Salman Sa'ud",
    "wof:placetype":"locality"
},
  "geometry": {"coordinates":[43.43956,34.24634],"type":"Point"}
}