{
  "type": "Feature",
  "properties": {
    "gn:admin1_code":"3.0",
    "gn:admin2_code":"98532.0",
    "gn:asciiname":"Muhammad al Hasan",
    "gn:country_code":"IQ",
    "gn:dem":13,
    "gn:feature_class":"P",
    "gn:feature_code":"PPL",
    "gn:name":"Mu\u1e29ammad al \u1e28asan",
    "gn:population":0,
    "gn:timezone":"Asia/Baghdad",
    "iso:country":"IQ",
    "name:und_x_variant":[
        "Mu\u1e29ammad al \u1e28asan"
    ],
    "wof:name":"Muhammad al Hasan",
    "wof:placetype":"locality"
},
  "geometry": {"coordinates":[45.2975,31.26917000000001],"type":"Point"}
}