{
  "type": "Feature",
  "properties": {
    "gn:admin1_code":"5.0",
    "gn:admin2_code":"97416.0",
    "gn:asciiname":"Nurah",
    "gn:country_code":"IQ",
    "gn:dem":623,
    "gn:feature_class":"P",
    "gn:feature_code":"PPL",
    "gn:name":"N\u016brah",
    "gn:population":0,
    "gn:timezone":"Asia/Baghdad",
    "iso:country":"IQ",
    "name:ara_x_preferred":[
        "\u0646\u0648\u0631\u0629"
    ],
    "name:und_x_variant":[
        "Nura",
        "N\u016brah"
    ],
    "wof:name":"Nurah",
    "wof:placetype":"locality"
},
  "geometry": {"coordinates":[44.87957,35.45551],"type":"Point"}
}