{
  "type": "Feature",
  "properties": {
    "gn:admin1_code":"13.0",
    "gn:admin2_code":"9166581.0",
    "gn:asciiname":"Qazan Bulagh",
    "gn:country_code":"IQ",
    "gn:dem":362,
    "gn:feature_class":"P",
    "gn:feature_code":"PPL",
    "gn:name":"Q\u0101z\u0101n B\u016bl\u0101gh",
    "gn:population":0,
    "gn:timezone":"Asia/Baghdad",
    "iso:country":"IQ",
    "name:ara_x_preferred":[
        "Q\u0101z\u0101n B\u016bl\u0101gh"
    ],
    "name:ara_x_variant":[
        "\u0642\u0627\u0632\u0627\u0646 \u0628\u0648\u0644\u0627\u063a"
    ],
    "name:und_x_variant":[
        "Q\u0101z\u0101n B\u016bl\u0101q"
    ],
    "wof:name":"Qazan Bulagh",
    "wof:placetype":"locality"
},
  "geometry": {"coordinates":[44.50549,35.37576],"type":"Point"}
}