{
  "type": "Feature",
  "properties": {
    "gn:admin1_code":"18.0",
    "gn:admin2_code":"6805736.0",
    "gn:asciiname":"Hammud al Uhaywir",
    "gn:country_code":"IQ",
    "gn:dem":48,
    "gn:feature_class":"P",
    "gn:feature_code":"PPL",
    "gn:name":"\u1e28amm\u016bd al U\u1e29aywir",
    "gn:population":0,
    "gn:timezone":"Asia/Baghdad",
    "iso:country":"IQ",
    "name:und_x_variant":[
        "\u1e28amm\u016bd al U\u1e29aywir"
    ],
    "wof:name":"Hammud al Uhaywir",
    "wof:placetype":"locality"
},
  "geometry": {"coordinates":[44.14722,34.0575],"type":"Point"}
}