{
  "type": "Feature",
  "properties": {
    "gn:admin1_code":"13.0",
    "gn:admin2_code":"9166581.0",
    "gn:asciiname":"Kilisah",
    "gn:country_code":"IQ",
    "gn:dem":229,
    "gn:feature_class":"P",
    "gn:feature_code":"PPL",
    "gn:name":"Kil\u012bsah",
    "gn:population":0,
    "gn:timezone":"Asia/Baghdad",
    "iso:country":"IQ",
    "name:ara_x_preferred":[
        "\u0643\u0644\u064a\u0633\u0629"
    ],
    "name:und_x_variant":[
        "Kilish\u0101h",
        "Kil\u012bsh\u0101n",
        "\u0643\u0644\u064a\u0633\u0647",
        "Kil\u012bsah"
    ],
    "wof:name":"Kilisah",
    "wof:placetype":"locality"
},
  "geometry": {"coordinates":[44.44225,35.15969],"type":"Point"}
}