{
  "type": "Feature",
  "properties": {
    "gn:admin1_code":"18.0",
    "gn:admin2_code":"6872046.0",
    "gn:asciiname":"Qaryat Albu 'Ubayd",
    "gn:country_code":"IQ",
    "gn:dem":121,
    "gn:feature_class":"P",
    "gn:feature_code":"PPL",
    "gn:name":"Qaryat \u0100lb\u016b \u2018Ubayd",
    "gn:population":0,
    "gn:timezone":"Asia/Baghdad",
    "iso:country":"IQ",
    "name:ara_x_preferred":[
        "\u0642\u0631\u064a\u0629 \u0627\u0644\u0628\u0648 \u0639\u0628\u064a\u062f"
    ],
    "name:und_x_variant":[
        "Qaryat \u0100lb\u016b \u2018Ubayd"
    ],
    "wof:name":"Qaryat Albu 'Ubayd",
    "wof:placetype":"locality"
},
  "geometry": {"coordinates":[43.03345,35.1748],"type":"Point"}
}