{
  "type": "Feature",
  "properties": {
    "gn:admin1_code":"7.0",
    "gn:admin2_code":"9166545.0",
    "gn:asciiname":"Qaryat Abu Dashir al Ula",
    "gn:country_code":"IQ",
    "gn:dem":35,
    "gn:feature_class":"P",
    "gn:feature_code":"PPL",
    "gn:name":"Qaryat Ab\u016b Dash\u012br al \u016al\u00e1",
    "gn:population":0,
    "gn:timezone":"Asia/Baghdad",
    "iso:country":"IQ",
    "name:ara_x_preferred":[
        "\u0642\u0631\u064a\u0629 \u0627\u0628\u0648 \u062f\u0634\u064a\u0631 \u0627\u0644\u0627\u0648\u0644\u0649"
    ],
    "name:und_x_variant":[
        "Qaryat Ab\u016b Dash\u012br al \u016al\u00e1"
    ],
    "wof:name":"Qaryat Abu Dashir al Ula",
    "wof:placetype":"locality"
},
  "geometry": {"coordinates":[44.37046,33.22497],"type":"Point"}
}