{
  "type": "Feature",
  "properties": {
    "gn:admin1_code":"10.0",
    "gn:admin2_code":"99063.0",
    "gn:asciiname":"Latif al Mashi",
    "gn:country_code":"IQ",
    "gn:dem":51,
    "gn:feature_class":"P",
    "gn:feature_code":"PPL",
    "gn:name":"La\u0163\u012bf al M\u0101sh\u012b",
    "gn:population":0,
    "gn:timezone":"Asia/Baghdad",
    "iso:country":"IQ",
    "name:und_x_variant":[
        "La\u0163\u012bf al M\u0101sh\u012b"
    ],
    "wof:name":"Latif al Mashi",
    "wof:placetype":"locality"
},
  "geometry": {"coordinates":[44.81667,33.96667],"type":"Point"}
}