{
  "type": "Feature",
  "properties": {
    "gn:admin1_code":"6.0",
    "gn:admin2_code":"99358.0",
    "gn:asciiname":"Hamzat Husayn Jayad",
    "gn:country_code":"IQ",
    "gn:dem":25,
    "gn:feature_class":"P",
    "gn:feature_code":"PPL",
    "gn:name":"\u1e28amzat \u1e28usayn Jay\u0101d",
    "gn:population":0,
    "gn:timezone":"Asia/Baghdad",
    "iso:country":"IQ",
    "name:ara_x_preferred":[
        "\u062d\u0645\u0632\u0629 \u062d\u0633\u064a\u0646 \u062c\u064a\u0627\u062f"
    ],
    "name:und_x_variant":[
        "\u1e28amzat \u1e28usayn Jay\u0101d"
    ],
    "wof:name":"Hamzat Husayn Jayad",
    "wof:placetype":"locality"
},
  "geometry": {"coordinates":[44.66389,32.21939],"type":"Point"}
}