{
  "type": "Feature",
  "properties": {
    "gn:admin1_code":"11.0",
    "gn:admin2_code":"9166591.0",
    "gn:asciiname":"Yusif",
    "gn:country_code":"IQ",
    "gn:dem":250,
    "gn:feature_class":"P",
    "gn:feature_code":"PPL",
    "gn:name":"Yusif",
    "gn:population":0,
    "gn:timezone":"Asia/Baghdad",
    "iso:country":"IQ",
    "name:ara_x_preferred":[
        "\u064a\u0648\u0633\u0641 \u0645\u0631\u064a\u0627\u0646"
    ],
    "name:kur_x_preferred":[
        "Yusif"
    ],
    "name:kur_x_variant":[
        "\u064a\u0648\u0633\u0641"
    ],
    "name:und_x_variant":[
        "Yusif Mily\u0101n",
        "Y\u016bsuf Milian",
        "Yosif",
        "Y\u016bsuf Mily\u0101n",
        "Y\u016bsuf Mary\u0101n"
    ],
    "wof:name":"Yusif",
    "wof:placetype":"locality"
},
  "geometry": {"coordinates":[43.90342,36.50002],"type":"Point"}
}