{
  "type": "Feature",
  "properties": {
    "gn:admin1_code":"18.0",
    "gn:admin2_code":"6783103.0",
    "gn:asciiname":"Salim Hamash",
    "gn:country_code":"IQ",
    "gn:dem":79,
    "gn:feature_class":"P",
    "gn:feature_code":"PPL",
    "gn:name":"S\u0101lim \u1e28am\u0101sh",
    "gn:population":0,
    "gn:timezone":"Asia/Baghdad",
    "iso:country":"IQ",
    "name:ara_x_preferred":[
        "\u0633\u0627\u0644\u0645 \u062d\u0645\u0627\u0634"
    ],
    "name:und_x_variant":[
        "S\u0101lim \u1e28am\u0101sh"
    ],
    "wof:name":"Salim Hamash",
    "wof:placetype":"locality"
},
  "geometry": {"coordinates":[43.83485,34.29307],"type":"Point"}
}