{
  "type": "Feature",
  "properties": {
    "gn:admin1_code":"10.0",
    "gn:admin2_code":"99063.0",
    "gn:asciiname":"Qaryat Tall Kadar",
    "gn:country_code":"IQ",
    "gn:dem":53,
    "gn:feature_class":"P",
    "gn:feature_code":"PPL",
    "gn:name":"Qaryat Tall Kad\u0101r",
    "gn:population":0,
    "gn:timezone":"Asia/Baghdad",
    "iso:country":"IQ",
    "name:ara_x_preferred":[
        "\u0642\u0631\u064a\u0629 \u062a\u0644 \u0643\u062f\u0627\u0631"
    ],
    "name:und_x_variant":[
        "Tilakd\u0101r",
        "Qaryat Tall Kad\u0101r"
    ],
    "wof:name":"Qaryat Tall Kadar",
    "wof:placetype":"locality"
},
  "geometry": {"coordinates":[44.95202000000001,33.88912],"type":"Point"}
}