{
  "type": "Feature",
  "properties": {
    "gn:admin1_code":"9.0",
    "gn:admin2_code":"98700.0",
    "gn:asciiname":"Faysal 'Anad",
    "gn:country_code":"IQ",
    "gn:dem":9,
    "gn:feature_class":"P",
    "gn:feature_code":"PPL",
    "gn:name":"Fay\u015fal \u2018An\u0101d",
    "gn:population":0,
    "gn:timezone":"Asia/Baghdad",
    "iso:country":"IQ",
    "name:ara_x_preferred":[
        "\u0641\u064a\u0635\u0644 \u0639\u0646\u0627\u062f"
    ],
    "name:und_x_variant":[
        "Fay\u015fal \u2018An\u0101d"
    ],
    "wof:name":"Faysal 'Anad",
    "wof:placetype":"locality"
},
  "geometry": {"coordinates":[46.29865,31.73326],"type":"Point"}
}