{
  "type": "Feature",
  "properties": {
    "gn:admin1_code":"15.0",
    "gn:admin2_code":"98612.0",
    "gn:asciiname":"Nayrwak",
    "gn:country_code":"IQ",
    "gn:dem":441,
    "gn:feature_class":"P",
    "gn:feature_code":"PPL",
    "gn:name":"Nayrwak",
    "gn:population":0,
    "gn:timezone":"Asia/Baghdad",
    "iso:country":"IQ",
    "name:ara_x_preferred":[
        "\u0646\u064a\u0631\u0648\u0643"
    ],
    "name:kur_x_preferred":[
        "B\u00eerok"
    ],
    "name:kur_x_variant":[
        "\u0628\u064a\u0631\u06c6\u0643",
        "N\u00earwek",
        "\u0646\u06ce\u0631\u0648\u06d5\u0643"
    ],
    "name:und_x_variant":[
        "Nir\u014dk",
        "B\u012br\u014dk",
        "Birok",
        "Nayrwak",
        "Nerwak"
    ],
    "wof:name":"Nayrwak",
    "wof:placetype":"locality"
},
  "geometry": {"coordinates":[43.6453,36.80665],"type":"Point"}
}