{
  "type": "Feature",
  "properties": {
    "gn:admin1_code":"9.0",
    "gn:admin2_code":"98700.0",
    "gn:asciiname":"Jabr Albu Hayf wa 'Arab al Yusif",
    "gn:country_code":"IQ",
    "gn:dem":11,
    "gn:feature_class":"P",
    "gn:feature_code":"PPLL",
    "gn:name":"Jabr \u0100lb\u016b Hayf wa \u2018Arab al Y\u016bsif",
    "gn:population":0,
    "gn:timezone":"Asia/Baghdad",
    "iso:country":"IQ",
    "name:ara_x_preferred":[
        "\u062c\u0628\u0631 \u0627\u0644\u0628\u0648 \u0647\u064a\u0641 \u0648\u0639\u0631\u0628 \u0627\u0644\u064a\u0648\u0633\u0641"
    ],
    "name:und_x_variant":[
        "Jabr \u0100lb\u016b Hayf wa \u2018Arab al Y\u016bsif"
    ],
    "wof:name":"Jabr Albu Hayf wa 'Arab al Yusif",
    "wof:placetype":"locality"
},
  "geometry": {"coordinates":[46.2067,31.86994],"type":"Point"}
}