{
  "type": "Feature",
  "properties": {
    "gn:admin1_code":"9.0",
    "gn:admin2_code":"98623.0",
    "gn:asciiname":"'Abd al Wahid Ahsayn",
    "gn:country_code":"IQ",
    "gn:dem":10,
    "gn:feature_class":"P",
    "gn:feature_code":"PPL",
    "gn:name":"\u2018Abd al W\u0101\u1e29id A\u1e29sayn",
    "gn:population":0,
    "gn:timezone":"Asia/Baghdad",
    "iso:country":"IQ",
    "name:ara_x_preferred":[
        "\u0639\u0628\u062f \u0627\u0644\u0648\u0627\u062d\u062f \u0627\u062d\u0633\u064a\u0646"
    ],
    "name:und_x_variant":[
        "\u2018Abd al W\u0101\u1e29id A\u1e29sayn"
    ],
    "wof:name":"'Abd al Wahid Ahsayn",
    "wof:placetype":"locality"
},
  "geometry": {"coordinates":[46.1341,31.49299],"type":"Point"}
}