{
  "type": "Feature",
  "properties": {
    "gn:admin1_code":"11.0",
    "gn:admin2_code":"95444.0",
    "gn:asciiname":"Halawad",
    "gn:country_code":"IQ",
    "gn:dem":308,
    "gn:feature_class":"P",
    "gn:feature_code":"PPL",
    "gn:name":"\u1e28al\u0101wad",
    "gn:population":0,
    "gn:timezone":"Asia/Baghdad",
    "iso:country":"IQ",
    "name:ara_x_preferred":[
        "\u062d\u0644\u0627\u0648\u062f"
    ],
    "name:und_x_variant":[
        "Helawa",
        "Hal\u0101wah",
        "\u1e28al\u0101wad"
    ],
    "wof:name":"Halawad",
    "wof:placetype":"locality"
},
  "geometry": {"coordinates":[43.79088,35.9958],"type":"Point"}
}