{
  "type": "Feature",
  "properties": {
    "gn:admin1_code":"4.0",
    "gn:admin2_code":"98634.0",
    "gn:asciiname":"'Aziz Hasun",
    "gn:country_code":"IQ",
    "gn:dem":20,
    "gn:feature_class":"P",
    "gn:feature_code":"PPL",
    "gn:name":"\u2018Az\u012bz \u1e28as\u016bn",
    "gn:population":0,
    "gn:timezone":"Asia/Baghdad",
    "iso:country":"IQ",
    "name:ara_x_preferred":[
        "\u0639\u0632\u064a\u0632 \u062d\u0633\u0648\u0646"
    ],
    "name:und_x_variant":[
        "\u2018Az\u012bz \u1e28as\u016bn"
    ],
    "wof:name":"'Aziz Hasun",
    "wof:placetype":"locality"
},
  "geometry": {"coordinates":[44.62577,31.76226],"type":"Point"}
}