{
  "type": "Feature",
  "properties": {
    "gn:admin1_code":"4.0",
    "gn:admin2_code":"99763.0",
    "gn:asciiname":"Al Kuwam",
    "gn:country_code":"IQ",
    "gn:dem":27,
    "gn:feature_class":"P",
    "gn:feature_code":"PPL",
    "gn:name":"Al K\u016bw\u0101m",
    "gn:population":0,
    "gn:timezone":"Asia/Baghdad",
    "iso:country":"IQ",
    "name:ara_x_preferred":[
        "\u0627\u0644\u0643\u0648\u0627\u0645"
    ],
    "name:ara_x_variant":[
        "Al K\u016bw\u0101m"
    ],
    "wof:name":"Al Kuwam",
    "wof:placetype":"locality"
},
  "geometry": {"coordinates":[44.80569000000001,32.14322],"type":"Point"}
}