{
  "type": "Feature",
  "properties": {
    "gn:admin1_code":"13.0",
    "gn:admin2_code":"6770659.0",
    "gn:asciiname":"Qaryat `Ilushah",
    "gn:country_code":"IQ",
    "gn:dem":193,
    "gn:feature_class":"P",
    "gn:feature_code":"PPL",
    "gn:name":"Qaryat \u2018Il\u016bshah",
    "gn:population":0,
    "gn:timezone":"Asia/Baghdad",
    "iso:country":"IQ",
    "name:ara_x_preferred":[
        "\u0642\u0631\u064a\u0629 \u0639\u0644\u0648\u0634\u0629"
    ],
    "name:und_x_variant":[
        "Qaryat \u2018Il\u016bshah"
    ],
    "wof:name":"Qaryat `Ilushah",
    "wof:placetype":"locality"
},
  "geometry": {"coordinates":[43.76794,35.42013],"type":"Point"}
}