{
  "type": "Feature",
  "properties": {
    "gn:admin1_code":"9.0",
    "gn:admin2_code":"98855.0",
    "gn:asciiname":"'Abudah",
    "gn:country_code":"IQ",
    "gn:dem":7,
    "gn:feature_class":"P",
    "gn:feature_code":"PPL",
    "gn:name":"\u2018\u0100b\u016bdah",
    "gn:population":0,
    "gn:timezone":"Asia/Baghdad",
    "iso:country":"IQ",
    "name:und_x_variant":[
        "\u2018\u0100b\u016bdah"
    ],
    "wof:name":"'Abudah",
    "wof:placetype":"locality"
},
  "geometry": {"coordinates":[46.38694,31.13639],"type":"Point"}
}