{
  "type": "Feature",
  "properties": {
    "gn:admin1_code":"18.0",
    "gn:admin2_code":"6783103.0",
    "gn:asciiname":"Khalaf al Hasan",
    "gn:country_code":"IQ",
    "gn:dem":81,
    "gn:feature_class":"P",
    "gn:feature_code":"PPL",
    "gn:name":"Khalaf al \u1e28asan",
    "gn:population":0,
    "gn:timezone":"Asia/Baghdad",
    "iso:country":"IQ",
    "name:ara_x_preferred":[
        "\u062e\u0644\u0641 \u0627\u0644\u062d\u0633\u0646"
    ],
    "name:und_x_variant":[
        "Khalaf al \u1e28asan"
    ],
    "wof:name":"Khalaf al Hasan",
    "wof:placetype":"locality"
},
  "geometry": {"coordinates":[43.9337,34.58212],"type":"Point"}
}