{
  "type": "Feature",
  "properties": {
    "gn:admin1_code":"8.0",
    "gn:admin2_code":"97269.0",
    "gn:asciiname":"Banah Surah",
    "gn:country_code":"IQ",
    "gn:dem":817,
    "gn:feature_class":"P",
    "gn:feature_code":"PPL",
    "gn:name":"B\u0101nah S\u016brah",
    "gn:population":0,
    "gn:timezone":"Asia/Baghdad",
    "iso:country":"IQ",
    "name:ara_x_preferred":[
        "\u0628\u0627\u0646\u0647 \u0633\u0648\u0631\u0647"
    ],
    "name:kur_x_preferred":[
        "Bene Sure"
    ],
    "name:kur_x_variant":[
        "\u0628\u06d5\u0646\u06d5 \u0633\u0648\u0631\u06d5",
        "Bane S\u00fbra",
        "\u0628\u0627\u0646\u0647 \u0633\u0648\u0648\u0631\u0627"
    ],
    "name:und_x_variant":[
        "Banasor",
        "Bin\u0101s\u016brah",
        "Bana Sura",
        "B\u0101nah S\u016brah",
        "Banasura",
        "Banesora"
    ],
    "wof:name":"Banah Surah",
    "wof:placetype":"locality"
},
  "geometry": {"coordinates":[43.01683,37.01505],"type":"Point"}
}