{
  "type": "Feature",
  "properties": {
    "gn:admin1_code":"7.0",
    "gn:admin2_code":"9179819.0",
    "gn:asciiname":"Qaryat al Ja'arah",
    "gn:country_code":"IQ",
    "gn:dem":34,
    "gn:feature_class":"P",
    "gn:feature_code":"PPL",
    "gn:name":"Qaryat al Ja\u2018\u0101rah",
    "gn:population":0,
    "gn:timezone":"Asia/Baghdad",
    "iso:country":"IQ",
    "name:ara_x_preferred":[
        "\u0642\u0631\u064a\u0629 \u0627\u0644\u062c\u0639\u0627\u0631\u0629"
    ],
    "name:und_x_variant":[
        "Qaryat al Ja\u2018\u0101rah"
    ],
    "wof:name":"Qaryat al Ja'arah",
    "wof:placetype":"locality"
},
  "geometry": {"coordinates":[44.55479,33.16901],"type":"Point"}
}