{
  "type": "Feature",
  "properties": {
    "gn:admin1_code":"8.0",
    "gn:admin2_code":"99612.0",
    "gn:asciiname":"Zatuwi al 'Ulya",
    "gn:country_code":"IQ",
    "gn:dem":1851,
    "gn:feature_class":"P",
    "gn:feature_code":"PPL",
    "gn:name":"Zatuw\u012b al \u2018Uly\u0101",
    "gn:population":0,
    "gn:timezone":"Asia/Baghdad",
    "iso:country":"IQ",
    "name:ara_x_preferred":[
        "\u0632\u062a\u0648\u064a \u0627\u0644\u0639\u0644\u064a\u0627"
    ],
    "name:kur_x_preferred":[
        "Z\u00eaw\u00ea"
    ],
    "name:kur_x_variant":[
        "\u0632\u06ce\u0648\u06ce",
        "Z\u00eawa Ser\u00ee",
        "\u0632\u06ce\u0648\u0627 \u0633\u06d5\u0631\u0649"
    ],
    "name:und_x_variant":[
        "Ziwi",
        "Zatuw\u012b al \u2018Uly\u0101",
        "Saywah Sar\u012b",
        "Dzgah"
    ],
    "wof:name":"Zatuwi al 'Ulya",
    "wof:placetype":"locality"
},
  "geometry": {"coordinates":[43.72998,37.20336],"type":"Point"}
}