{
  "type": "Feature",
  "properties": {
    "gn:admin1_code":"15.0",
    "gn:admin2_code":"9166649.0",
    "gn:asciiname":"Abu Fishkah",
    "gn:country_code":"IQ",
    "gn:dem":330,
    "gn:feature_class":"P",
    "gn:feature_code":"PPL",
    "gn:name":"Ab\u016b Fishkah",
    "gn:population":0,
    "gn:timezone":"Asia/Baghdad",
    "iso:country":"IQ",
    "name:ara_x_preferred":[
        "\u0627\u0628\u0648 \u0641\u0634\u0643\u0629"
    ],
    "name:und_x_variant":[
        "Ab\u016b Fishkah"
    ],
    "wof:name":"Abu Fishkah",
    "wof:placetype":"locality"
},
  "geometry": {"coordinates":[42.83257,36.21515],"type":"Point"}
}