{
  "type": "Feature",
  "properties": {
    "gn:admin1_code":"4.0",
    "gn:admin2_code":"98634.0",
    "gn:asciiname":"Husayn Hajji Farhan",
    "gn:country_code":"IQ",
    "gn:dem":27,
    "gn:feature_class":"P",
    "gn:feature_code":"PPL",
    "gn:name":"\u1e28usayn \u1e28ajj\u012b Far\u1e29\u0101n",
    "gn:population":0,
    "gn:timezone":"Asia/Baghdad",
    "iso:country":"IQ",
    "name:ara_x_preferred":[
        "\u062d\u0633\u064a\u0646 \u062d\u062c\u064a \u0641\u0631\u062d\u0627\u0646"
    ],
    "name:und_x_variant":[
        "\u1e28usayn \u1e28ajj\u012b Far\u1e29\u0101n"
    ],
    "wof:name":"Husayn Hajji Farhan",
    "wof:placetype":"locality"
},
  "geometry": {"coordinates":[44.54117,32.00279],"type":"Point"}
}