{
  "type": "Feature",
  "properties": {
    "gn:admin1_code":"15.0",
    "gn:admin2_code":"9166608.0",
    "gn:asciiname":"Al Mashraf",
    "gn:country_code":"IQ",
    "gn:dem":273,
    "gn:feature_class":"P",
    "gn:feature_code":"PPL",
    "gn:name":"Al Mashraf",
    "gn:population":0,
    "gn:timezone":"Asia/Baghdad",
    "iso:country":"IQ",
    "name:ara_x_preferred":[
        "\u0627\u0644\u0645\u0634\u0631\u0641"
    ],
    "wof:name":"Al Mashraf",
    "wof:placetype":"locality"
},
  "geometry": {"coordinates":[42.09106,35.83296],"type":"Point"}
}