{
  "type": "Feature",
  "properties": {
    "gn:admin1_code":"17.0",
    "gn:admin2_code":"9166552.0",
    "gn:asciiname":"Al Mayi'",
    "gn:country_code":"IQ",
    "gn:dem":17,
    "gn:feature_class":"P",
    "gn:feature_code":"PPL",
    "gn:name":"\u0100l M\u0101yi\u2018",
    "gn:population":0,
    "gn:timezone":"Asia/Baghdad",
    "iso:country":"IQ",
    "name:ara_x_preferred":[
        "\u0627\u0644 \u0645\u0627\u064a\u0639"
    ],
    "name:ara_x_variant":[
        "\u0100l M\u0101yi\u2018"
    ],
    "wof:name":"Al Mayi'",
    "wof:placetype":"locality"
},
  "geometry": {"coordinates":[44.53111,31.6434],"type":"Point"}
}