{
  "type": "Feature",
  "properties": {
    "gn:admin1_code":"5.0",
    "gn:admin2_code":"98464.0",
    "gn:asciiname":"Hamawand",
    "gn:country_code":"IQ",
    "gn:dem":876,
    "gn:feature_class":"P",
    "gn:feature_code":"PPL",
    "gn:name":"Ham\u0101wand",
    "gn:population":0,
    "gn:timezone":"Asia/Baghdad",
    "iso:country":"IQ",
    "name:ara_x_preferred":[
        "\u0647\u0645\u0627\u0648\u0646\u062f"
    ],
    "name:und_x_variant":[
        "Ham\u0101wand"
    ],
    "wof:name":"Hamawand",
    "wof:placetype":"locality"
},
  "geometry": {"coordinates":[45.02959,35.63235],"type":"Point"}
}