{
  "type": "Feature",
  "properties": {
    "gn:admin1_code":"15.0",
    "gn:admin2_code":"9166541.0",
    "gn:asciiname":"Qaryat Bahzani",
    "gn:country_code":"IQ",
    "gn:dem":361,
    "gn:feature_class":"P",
    "gn:feature_code":"PPL",
    "gn:name":"Qaryat Ba\u1e29z\u0101n\u012b",
    "gn:population":0,
    "gn:timezone":"Asia/Baghdad",
    "iso:country":"IQ",
    "name:ara_x_preferred":[
        "\u0642\u0631\u064a\u0629 \u0628\u062d\u0632\u0627\u0646\u064a"
    ],
    "name:ara_x_variant":[
        "\u0628\u062d\u0632\u0627\u0646\u064a"
    ],
    "name:deu_x_preferred":[
        "Bahzani"
    ],
    "name:und_x_variant":[
        "Bahz\u0101n",
        "Bahzani",
        "Qaryat Ba\u1e29z\u0101n\u012b"
    ],
    "wof:name":"Qaryat Bahzani",
    "wof:placetype":"locality"
},
  "geometry": {"coordinates":[43.33903,36.46052],"type":"Point"}
}