{
  "type": "Feature",
  "properties": {
    "gn:admin1_code":"8.0",
    "gn:admin2_code":"9166607.0",
    "gn:asciiname":"Muqbilah",
    "gn:country_code":"IQ",
    "gn:dem":485,
    "gn:feature_class":"P",
    "gn:feature_code":"PPL",
    "gn:name":"Muqbilah",
    "gn:population":0,
    "gn:timezone":"Asia/Baghdad",
    "iso:country":"IQ",
    "name:ara_x_preferred":[
        "\u0645\u0642\u0628\u0644\u0629"
    ],
    "name:kur_x_preferred":[
        "Muqbil\u00ea"
    ],
    "name:kur_x_variant":[
        "\u0645\u0648\u0642\u0628\u0644\u06ce"
    ],
    "name:und_x_variant":[
        "Muqbal",
        "Muqble",
        "Muqbilah",
        "Muqible"
    ],
    "wof:name":"Muqbilah",
    "wof:placetype":"locality"
},
  "geometry": {"coordinates":[42.73342,36.91444],"type":"Point"}
}