{
  "type": "Feature",
  "properties": {
    "gn:admin1_code":"13.0",
    "gn:admin2_code":"9166581.0",
    "gn:asciiname":"Yahyawa",
    "gn:country_code":"IQ",
    "gn:dem":344,
    "gn:feature_class":"P",
    "gn:feature_code":"PPL",
    "gn:name":"Yahyawa",
    "gn:population":0,
    "gn:timezone":"Asia/Baghdad",
    "iso:country":"IQ",
    "wof:name":"Yahyawa",
    "wof:placetype":"locality"
},
  "geometry": {"coordinates":[44.58232,35.26938],"type":"Point"}
}