{
  "type": "Feature",
  "properties": {
    "gn:admin1_code":"1.0",
    "gn:admin2_code":"98718.0",
    "gn:asciiname":"Hamad al 'Uwayd",
    "gn:country_code":"IQ",
    "gn:dem":50,
    "gn:feature_class":"P",
    "gn:feature_code":"PPL",
    "gn:name":"\u1e28amad al \u2018Uwayd",
    "gn:population":0,
    "gn:timezone":"Asia/Baghdad",
    "iso:country":"IQ",
    "name:ara_x_preferred":[
        "\u062d\u0645\u062f \u0627\u0644\u0639\u0648\u064a\u062f"
    ],
    "name:und_x_variant":[
        "\u1e28amad al \u2018Uwayd"
    ],
    "wof:name":"Hamad al 'Uwayd",
    "wof:placetype":"locality"
},
  "geometry": {"coordinates":[43.39997,33.46096],"type":"Point"}
}