{
  "type": "Feature",
  "properties": {
    "gn:admin1_code":"11.0",
    "gn:admin2_code":"9166592.0",
    "gn:asciiname":"Minah",
    "gn:country_code":"IQ",
    "gn:dem":778,
    "gn:feature_class":"P",
    "gn:feature_code":"PPL",
    "gn:name":"M\u012bnah",
    "gn:population":0,
    "gn:timezone":"Asia/Baghdad",
    "iso:country":"IQ",
    "name:ara_x_preferred":[
        "\u0645\u064a\u0646\u0629"
    ],
    "name:kur_x_preferred":[
        "M\u00eena Xwar\u00fb"
    ],
    "name:kur_x_variant":[
        "\u0645\u064a\u0646\u0627 \u062e\u0648\u0627\u0631\u0648\u0648"
    ],
    "name:und_x_variant":[
        "M\u012bnah",
        "M\u012bn\u0101",
        "Mina Lower"
    ],
    "wof:name":"Minah",
    "wof:placetype":"locality"
},
  "geometry": {"coordinates":[44.54199000000001,36.86609],"type":"Point"}
}