{
  "type": "Feature",
  "properties": {
    "gn:admin1_code":"15.0",
    "gn:admin2_code":"9166608.0",
    "gn:asciiname":"Umm Zahir",
    "gn:country_code":"IQ",
    "gn:dem":298,
    "gn:feature_class":"P",
    "gn:feature_code":"PPL",
    "gn:name":"Umm Z\u0327\u0101hir",
    "gn:population":0,
    "gn:timezone":"Asia/Baghdad",
    "iso:country":"IQ",
    "name:ara_x_preferred":[
        "\u0627\u0645 \u0638\u0627\u0647\u0631"
    ],
    "name:ara_x_variant":[
        "Umm Z\u0327\u0101hir"
    ],
    "wof:name":"Umm Zahir",
    "wof:placetype":"locality"
},
  "geometry": {"coordinates":[41.95915,35.92297],"type":"Point"}
}