{
  "type": "Feature",
  "properties": {
    "gn:admin1_code":"18.0",
    "gn:admin2_code":"90148.0",
    "gn:asciiname":"Qaryat Muhammad al 'Ali",
    "gn:country_code":"IQ",
    "gn:dem":173,
    "gn:feature_class":"P",
    "gn:feature_code":"PPL",
    "gn:name":"Qaryat Mu\u1e29ammad al \u2018Al\u012b",
    "gn:population":0,
    "gn:timezone":"Asia/Baghdad",
    "iso:country":"IQ",
    "name:ara_x_preferred":[
        "\u0642\u0631\u064a\u0629 \u0645\u062d\u0645\u062f \u0627\u0644\u0639\u0644\u064a"
    ],
    "name:und_x_variant":[
        "Qaryat Mu\u1e29ammad al \u2018Al\u012b"
    ],
    "wof:name":"Qaryat Muhammad al 'Ali",
    "wof:placetype":"locality"
},
  "geometry": {"coordinates":[43.82183,34.88406],"type":"Point"}
}