{
  "type": "Feature",
  "properties": {
    "gn:admin1_code":"10.0",
    "gn:admin2_code":"94590.0",
    "gn:asciiname":"'Ayn al Hilal al Jadidah",
    "gn:country_code":"IQ",
    "gn:dem":227,
    "gn:feature_class":"P",
    "gn:feature_code":"PPL",
    "gn:name":"\u2018Ayn al Hil\u0101l al Jad\u012bdah",
    "gn:population":0,
    "gn:timezone":"Asia/Baghdad",
    "iso:country":"IQ",
    "name:ara_x_preferred":[
        "\u0639\u064a\u0646 \u0627\u0644\u0647\u0644\u0627\u0644 \u0627\u0644\u062c\u062f\u064a\u062f\u0629"
    ],
    "name:und_x_variant":[
        "\u2018Ayn al Hil\u0101l al Jad\u012bdah"
    ],
    "wof:name":"'Ayn al Hilal al Jadidah",
    "wof:placetype":"locality"
},
  "geometry": {"coordinates":[45.27464000000001,34.2561],"type":"Point"}
}