{
  "type": "Feature",
  "properties": {
    "gn:admin1_code":"1.0",
    "gn:admin2_code":"99455.0",
    "gn:asciiname":"Mahmud Radi",
    "gn:country_code":"IQ",
    "gn:dem":34,
    "gn:feature_class":"P",
    "gn:feature_code":"PPL",
    "gn:name":"Ma\u1e29m\u016bd R\u0101\u1e11\u012b",
    "gn:population":0,
    "gn:timezone":"Asia/Baghdad",
    "iso:country":"IQ",
    "name:ara_x_preferred":[
        "\u0645\u062d\u0645\u0648\u062f \u0631\u0627\u0636\u064a"
    ],
    "name:und_x_variant":[
        "Ma\u1e29m\u016bd R\u0101\u1e11\u012b"
    ],
    "wof:name":"Mahmud Radi",
    "wof:placetype":"locality"
},
  "geometry": {"coordinates":[44.10529,33.51469],"type":"Point"}
}