{
  "type": "Feature",
  "properties": {
    "gn:admin1_code":"6.0",
    "gn:admin2_code":"99040.0",
    "gn:asciiname":"Al 'Ashur",
    "gn:country_code":"IQ",
    "gn:dem":33,
    "gn:feature_class":"P",
    "gn:feature_code":"PPL",
    "gn:name":"Al \u2018\u0100sh\u016br",
    "gn:population":0,
    "gn:timezone":"Asia/Baghdad",
    "iso:country":"IQ",
    "name:ara_x_preferred":[
        "\u0627\u0644\u0639\u0627\u0634\u0648\u0631"
    ],
    "name:ara_x_variant":[
        "Al \u2018\u0100sh\u016br"
    ],
    "wof:name":"Al 'Ashur",
    "wof:placetype":"locality"
},
  "geometry": {"coordinates":[44.36741,32.57002],"type":"Point"}
}