{
  "type": "Feature",
  "properties": {
    "gn:admin1_code":"5.0",
    "gn:admin2_code":"92051.0",
    "gn:asciiname":"Shiwah",
    "gn:country_code":"IQ",
    "gn:dem":850,
    "gn:feature_class":"P",
    "gn:feature_code":"PPL",
    "gn:name":"Sh\u012bwah",
    "gn:population":0,
    "gn:timezone":"Asia/Baghdad",
    "iso:country":"IQ",
    "name:kur_x_preferred":[
        "Ch\u00eawey Ser\u00fb"
    ],
    "name:kur_x_variant":[
        "\u0686\u06ce\u0648\u06d5\u0649 \u0633\u06d5\u0631\u0648\u0648"
    ],
    "name:und_x_variant":[
        "Sh\u012bwah",
        "Sh\u012bwa-i Zh\u016br\u016b",
        "Chewa Upper",
        "Chewa"
    ],
    "wof:name":"Shiwah",
    "wof:placetype":"locality"
},
  "geometry": {"coordinates":[44.57605,36.34227],"type":"Point"}
}