{
  "type": "Feature",
  "properties": {
    "gn:admin1_code":"18.0",
    "gn:admin2_code":"90148.0",
    "gn:asciiname":"Khitab 'Abd Allah",
    "gn:country_code":"IQ",
    "gn:dem":91,
    "gn:feature_class":"P",
    "gn:feature_code":"PPL",
    "gn:name":"Khi\u0163\u0101b \u2018Abd All\u0101h",
    "gn:population":0,
    "gn:timezone":"Asia/Baghdad",
    "iso:country":"IQ",
    "name:ara_x_preferred":[
        "\u062e\u0637\u0627\u0628 \u0639\u0628\u062f \u0627\u0644\u0644\u0647"
    ],
    "name:ara_x_variant":[
        "Khi\u0163\u0101b \u2018Abd All\u0101h"
    ],
    "name:und_x_variant":[
        "Kha\u0163\u0163\u0101b \u2018Abd All\u0101h"
    ],
    "wof:name":"Khitab 'Abd Allah",
    "wof:placetype":"locality"
},
  "geometry": {"coordinates":[43.87551,34.59769],"type":"Point"}
}