{
  "type": "Feature",
  "properties": {
    "gn:admin1_code":"5.0",
    "gn:admin2_code":"97416.0",
    "gn:asciiname":"Mir Isma'il",
    "gn:country_code":"IQ",
    "gn:dem":612,
    "gn:feature_class":"P",
    "gn:feature_code":"PPL",
    "gn:name":"M\u012br Ism\u0101\u2018\u012bl",
    "gn:population":0,
    "gn:timezone":"Asia/Baghdad",
    "iso:country":"IQ",
    "name:ara_x_preferred":[
        "M\u012br Ism\u0101\u2018\u012bl"
    ],
    "name:ara_x_variant":[
        "\u0645\u064a\u0631 \u0627\u0633\u0645\u0627\u0639\u064a\u0644"
    ],
    "name:kur_x_preferred":[
        "M\u00eer \u00cesma\u2018\u00eel"
    ],
    "name:kur_x_variant":[
        "\u0645\u064a\u0631 \u0626\u064a\u0633\u0645\u0627\u0639\u064a\u0644"
    ],
    "name:und_x_variant":[
        "Meer Ismaeel"
    ],
    "wof:name":"Mir Isma'il",
    "wof:placetype":"locality"
},
  "geometry": {"coordinates":[45.04366,35.29146],"type":"Point"}
}