{
  "type": "Feature",
  "properties": {
    "gn:admin1_code":"3.0",
    "gn:admin2_code":"98532.0",
    "gn:asciiname":"Farhud",
    "gn:country_code":"IQ",
    "gn:dem":14,
    "gn:feature_class":"P",
    "gn:feature_code":"PPL",
    "gn:name":"Farh\u016bd",
    "gn:population":0,
    "gn:timezone":"Asia/Baghdad",
    "iso:country":"IQ",
    "name:ara_x_preferred":[
        "\u0641\u0631\u0647\u0648\u062f"
    ],
    "name:und_x_variant":[
        "Farh\u016bd"
    ],
    "wof:name":"Farhud",
    "wof:placetype":"locality"
},
  "geometry": {"coordinates":[45.42372,31.34398],"type":"Point"}
}