{
  "type": "Feature",
  "properties": {
    "gn:admin1_code":"3.0",
    "gn:admin2_code":"98532.0",
    "gn:asciiname":"Farhud",
    "gn:country_code":"IQ",
    "gn:dem":14,
    "gn:feature_class":"P",
    "gn:feature_code":"PPL",
    "gn:name":"Farh\u016bd",
    "gn:population":0,
    "gn:timezone":"Asia/Baghdad",
    "iso:country":"IQ",
    "name:als_x_preferred":[
        "Farhud"
    ],
    "name:ara_x_preferred":[
        "\u0641\u0631\u0647\u0648\u062f"
    ],
    "name:ara_x_variant":[
        "\u0627\u0644\u0641\u0631\u0647\u0648\u062f"
    ],
    "name:bul_x_preferred":[
        "\u0411\u0430\u0433\u0434\u0430\u0434\u0441\u043a\u0438 \u043f\u043e\u0433\u0440\u043e\u043c"
    ],
    "name:deu_x_preferred":[
        "Farhud"
    ],
    "name:fas_x_preferred":[
        "\u0641\u0631\u0647\u0648\u062f"
    ],
    "name:fra_x_preferred":[
        "Farhoud"
    ],
    "name:heb_x_preferred":[
        "\u05d4\u05e4\u05e8\u05d4\u05d5\u05d3"
    ],
    "name:lad_x_preferred":[
        "Farhud"
    ],
    "name:nld_x_preferred":[
        "Farhud"
    ],
    "name:pol_x_preferred":[
        "Farhud"
    ],
    "name:ron_x_preferred":[
        "Farhud"
    ],
    "name:swe_x_preferred":[
        "Farhud"
    ],
    "name:tur_x_preferred":[
        "Farhud"
    ],
    "name:und_x_variant":[
        "Farh\u016bd"
    ],
    "name:zea_x_preferred":[
        "Farhud"
    ],
    "wof:name":"Farhud",
    "wof:placetype":"locality"
},
  "geometry": {"coordinates":[45.42372,31.34398],"type":"Point"}
}