{
  "type": "Feature",
  "properties": {
    "gn:admin1_code":"8.0",
    "gn:admin2_code":"99612.0",
    "gn:asciiname":"Mirah Kirah",
    "gn:country_code":"IQ",
    "gn:dem":682,
    "gn:feature_class":"P",
    "gn:feature_code":"PPL",
    "gn:name":"M\u012brah Kirah",
    "gn:population":0,
    "gn:timezone":"Asia/Baghdad",
    "iso:country":"IQ",
    "name:kur_x_preferred":[
        "M\u00eera Kira"
    ],
    "name:kur_x_variant":[
        "\u0645\u064a\u0631\u0627 \u0643\u0631\u0627",
        "M\u00eakera",
        "\u0645\u06ce\u0643\u06d5\u0631\u0627"
    ],
    "name:und_x_variant":[
        "Mira Kra",
        "M\u0113rakira",
        "\u0645\u064a\u0631\u0647 \u0643\u0631\u0647",
        "M\u012brah Kirah"
    ],
    "wof:name":"Mirah Kirah",
    "wof:placetype":"locality"
},
  "geometry": {"coordinates":[43.55257,37.06356],"type":"Point"}
}