{
  "type": "Feature",
  "properties": {
    "gn:admin1_code":"7.0",
    "gn:admin2_code":"9166542.0",
    "gn:asciiname":"Ar Radwaniyah",
    "gn:country_code":"IQ",
    "gn:dem":38,
    "gn:feature_class":"P",
    "gn:feature_code":"PPL",
    "gn:name":"Ar Radwaniyah",
    "gn:population":0,
    "gn:timezone":"Asia/Baghdad",
    "iso:country":"IQ",
    "name:ara_x_preferred":[
        "\u062d\u064a \u0627\u0644\u0631\u0636\u0648\u0627\u0646"
    ],
    "name:und_x_variant":[
        "\u1e28ayy ar Ra\u1e11w\u0101n",
        "Ar Radwaniyah"
    ],
    "wof:name":"Ar Radwaniyah",
    "wof:placetype":"locality"
},
  "geometry": {"coordinates":[44.087,33.29581],"type":"Point"}
}