{
  "type": "Feature",
  "properties": {
    "gn:admin1_code":"6.0",
    "gn:admin2_code":"6818313.0",
    "gn:asciiname":"Al Naji",
    "gn:country_code":"IQ",
    "gn:dem":26,
    "gn:feature_class":"P",
    "gn:feature_code":"PPL",
    "gn:name":"\u0100l N\u0101j\u012b",
    "gn:population":0,
    "gn:timezone":"Asia/Baghdad",
    "iso:country":"IQ",
    "name:ara_x_preferred":[
        "\u0622\u0644 \u0646\u0627\u062c\u064a"
    ],
    "name:ara_x_variant":[
        "\u0100l N\u0101j\u012b"
    ],
    "wof:name":"Al Naji",
    "wof:placetype":"locality"
},
  "geometry": {"coordinates":[44.73136,32.45145],"type":"Point"}
}