{
  "type": "Feature",
  "properties": {
    "gn:admin1_code":"6.0",
    "gn:admin2_code":"99348.0",
    "gn:asciiname":"Qaryat 'Awfi",
    "gn:country_code":"IQ",
    "gn:dem":32,
    "gn:feature_class":"P",
    "gn:feature_code":"PPL",
    "gn:name":"Qaryat \u2018Awf\u012b",
    "gn:population":0,
    "gn:timezone":"Asia/Baghdad",
    "iso:country":"IQ",
    "name:ara_x_preferred":[
        "\u0642\u0631\u064a\u0629 \u0639\u0648\u0641\u064a"
    ],
    "name:und_x_variant":[
        "Qaryat \u2018Awf\u012b"
    ],
    "wof:name":"Qaryat 'Awfi",
    "wof:placetype":"locality"
},
  "geometry": {"coordinates":[44.32399,32.43686],"type":"Point"}
}