{
  "type": "Feature",
  "properties": {
    "gn:admin1_code":"15.0",
    "gn:admin2_code":"98612.0",
    "gn:asciiname":"Naychirvan",
    "gn:country_code":"IQ",
    "gn:dem":773,
    "gn:feature_class":"P",
    "gn:feature_code":"PPL",
    "gn:name":"Naychirv\u0101n",
    "gn:population":0,
    "gn:timezone":"Asia/Baghdad",
    "iso:country":"IQ",
    "name:kur_x_preferred":[
        "N\u00each\u00eerevan"
    ],
    "name:kur_x_variant":[
        "\u0646\u06ce\u0686\u064a\u0631\u06d5\u06a4\u0627\u0646"
    ],
    "name:und_x_variant":[
        "Naychir\u012bv\u0101n",
        "Neichirvan",
        "Naychirv\u0101n"
    ],
    "wof:name":"Naychirvan",
    "wof:placetype":"locality"
},
  "geometry": {"coordinates":[43.43771,36.78989],"type":"Point"}
}