{
  "type": "Feature",
  "properties": {
    "gn:admin1_code":"11.0",
    "gn:admin2_code":"9166591.0",
    "gn:asciiname":"Jamakah Zura",
    "gn:country_code":"IQ",
    "gn:dem":280,
    "gn:feature_class":"P",
    "gn:feature_code":"PPL",
    "gn:name":"Jamakah Z\u016br\u00e1",
    "gn:population":0,
    "gn:timezone":"Asia/Baghdad",
    "iso:country":"IQ",
    "name:ara_x_preferred":[
        "\u062c\u0645\u0643\u0647 \u0632\u0648\u0631\u0649"
    ],
    "name:kur_x_preferred":[
        "Chemekey Ser\u00fb"
    ],
    "name:kur_x_variant":[
        "\u0686\u06d5\u0645\u06d5\u0643\u06d5\u0649 \u0633\u06d5\u0631\u0648\u0648"
    ],
    "name:und_x_variant":[
        "Jamaka Zhori",
        "Jamakah Z\u016br\u00e1",
        "Chamaka Upper"
    ],
    "wof:name":"Jamakah Zura",
    "wof:placetype":"locality"
},
  "geometry": {"coordinates":[43.98845,36.58526],"type":"Point"}
}