{
  "type": "Feature",
  "properties": {
    "gn:admin1_code":"5.0",
    "gn:admin2_code":"9166600.0",
    "gn:asciiname":"Qulajah",
    "gn:country_code":"IQ",
    "gn:dem":504,
    "gn:feature_class":"P",
    "gn:feature_code":"PPL",
    "gn:name":"Qul\u0101jah",
    "gn:population":0,
    "gn:timezone":"Asia/Baghdad",
    "iso:country":"IQ",
    "name:ara_x_preferred":[
        "\u0642\u0644\u0627\u062c\u0629"
    ],
    "name:kur_x_preferred":[
        "Gu\u0142e Co"
    ],
    "name:kur_x_variant":[
        "Ku\u0142e Co",
        "\u06af\u0648\u06b5\u06d5 \u062c\u06c6",
        "\u0643\u0648\u06b5\u06d5 \u062c\u06c6"
    ],
    "name:und_x_variant":[
        "K\u016blahjn\u0308",
        "Qul\u0101jah",
        "Kulaj\u014d",
        "Qal\u0101jah",
        "Kula Jo"
    ],
    "wof:name":"Qulajah",
    "wof:placetype":"locality"
},
  "geometry": {"coordinates":[45.14194000000001,34.85225],"type":"Point"}
}