{
  "type": "Feature",
  "properties": {
    "gn:admin1_code":"13.0",
    "gn:asciiname":"Khazir",
    "gn:country_code":"IQ",
    "gn:dem":203,
    "gn:feature_class":"P",
    "gn:feature_code":"PPL",
    "gn:name":"Kh\u0101zir",
    "gn:population":0,
    "gn:timezone":"Asia/Baghdad",
    "iso:country":"IQ",
    "name:ara_x_preferred":[
        "\u062e\u0627\u0632\u0631"
    ],
    "name:ara_x_variant":[
        "Kh\u0101zir"
    ],
    "name:kur_x_preferred":[
        "Xazer"
    ],
    "name:kur_x_variant":[
        "Khazar",
        "\u062e\u0627\u0632\u06d5\u0631"
    ],
    "name:und_x_variant":[
        "Khadir",
        "Kha\u1e11r"
    ],
    "wof:name":"Khazir",
    "wof:placetype":"locality"
},
  "geometry": {"coordinates":[43.83989,35.52942],"type":"Point"}
}