{
  "type": "Feature",
  "properties": {
    "gn:admin1_code":"6.0",
    "gn:admin2_code":"6818313.0",
    "gn:asciiname":"Jawad Husayn",
    "gn:country_code":"IQ",
    "gn:dem":27,
    "gn:feature_class":"P",
    "gn:feature_code":"PPL",
    "gn:name":"Jaw\u0101d \u1e28usayn",
    "gn:population":0,
    "gn:timezone":"Asia/Baghdad",
    "iso:country":"IQ",
    "name:ara_x_preferred":[
        "\u062c\u0648\u0627\u062f \u062d\u0633\u064a\u0646"
    ],
    "name:und_x_variant":[
        "Jaw\u0101d \u1e28usayn"
    ],
    "wof:name":"Jawad Husayn",
    "wof:placetype":"locality"
},
  "geometry": {"coordinates":[44.75208,32.68108],"type":"Point"}
}