{
  "type": "Feature",
  "properties": {
    "gn:admin1_code":"2.0",
    "gn:admin2_code":"100049.0",
    "gn:asciiname":"Qaryat al Mutaw'ah",
    "gn:country_code":"IQ",
    "gn:dem":0,
    "gn:feature_class":"P",
    "gn:feature_code":"PPL",
    "gn:name":"Qaryat al Mu\u0163aw\u2018ah",
    "gn:population":0,
    "gn:timezone":"Asia/Baghdad",
    "iso:country":"IQ",
    "name:ara_x_preferred":[
        "\u0642\u0631\u064a\u0629 \u0627\u0644\u0645\u0637\u0648\u0639\u0629"
    ],
    "name:fas_x_preferred":[
        "Al Ma\u0163\u016b\u2018ah"
    ],
    "name:und_x_variant":[
        "Qaryat al Mu\u0163aww\u0131\u2018ah",
        "Qaryat al Mu\u0163aw\u2018ah"
    ],
    "wof:name":"Qaryat al Mutaw'ah",
    "wof:placetype":"locality"
},
  "geometry": {"coordinates":[48.17366,30.3892],"type":"Point"}
}