{
  "type": "Feature",
  "properties": {
    "gn:admin1_code":"16.0",
    "gn:admin2_code":"99132.0",
    "gn:asciiname":"Qaryat al Qudah",
    "gn:country_code":"IQ",
    "gn:dem":11,
    "gn:feature_class":"P",
    "gn:feature_code":"PPL",
    "gn:name":"Qaryat al Q\u016bdah",
    "gn:population":0,
    "gn:timezone":"Asia/Baghdad",
    "iso:country":"IQ",
    "name:ara_x_preferred":[
        "\u0642\u0631\u064a\u0629 \u0627\u0644\u0642\u0648\u062f\u0629"
    ],
    "name:und_x_variant":[
        "Qaryat al Q\u016bdah"
    ],
    "wof:name":"Qaryat al Qudah",
    "wof:placetype":"locality"
},
  "geometry": {"coordinates":[46.37822,32.50475],"type":"Point"}
}