{
  "type": "Feature",
  "properties": {
    "gn:admin1_code":"7.0",
    "gn:admin2_code":"99101.0",
    "gn:asciiname":"Ahmad Daydan",
    "gn:country_code":"IQ",
    "gn:dem":32,
    "gn:feature_class":"P",
    "gn:feature_code":"PPL",
    "gn:name":"A\u1e29mad \u1e10ayd\u0101n",
    "gn:population":0,
    "gn:timezone":"Asia/Baghdad",
    "iso:country":"IQ",
    "name:ara_x_preferred":[
        "\u0623\u062d\u0645\u062f \u0636\u064a\u062f\u0627\u0646"
    ],
    "name:und_x_variant":[
        "A\u1e29mad \u1e10ayd\u0101n"
    ],
    "wof:name":"Ahmad Daydan",
    "wof:placetype":"locality"
},
  "geometry": {"coordinates":[44.48401,33.13946],"type":"Point"}
}