{
  "type": "Feature",
  "properties": {
    "gn:admin1_code":"10.0",
    "gn:admin2_code":"9166680.0",
    "gn:asciiname":"Qaryat Husayn Salman",
    "gn:country_code":"IQ",
    "gn:dem":45,
    "gn:feature_class":"P",
    "gn:feature_code":"PPL",
    "gn:name":"Qaryat \u1e28usayn Salm\u0101n",
    "gn:population":0,
    "gn:timezone":"Asia/Baghdad",
    "iso:country":"IQ",
    "name:ara_x_preferred":[
        "\u0642\u0631\u064a\u0629 \u062d\u0633\u064a\u0646 \u0633\u0644\u0645\u0627\u0646"
    ],
    "name:und_x_variant":[
        "Qaryat \u1e28usayn Salm\u0101n"
    ],
    "wof:name":"Qaryat Husayn Salman",
    "wof:placetype":"locality"
},
  "geometry": {"coordinates":[44.89312,33.78354],"type":"Point"}
}