{
  "type": "Feature",
  "properties": {
    "gn:admin1_code":"7.0",
    "gn:admin2_code":"99101.0",
    "gn:asciiname":"'Abd Zaydan",
    "gn:country_code":"IQ",
    "gn:dem":31,
    "gn:feature_class":"P",
    "gn:feature_code":"PPL",
    "gn:name":"\u2018Abd Zayd\u0101n",
    "gn:population":0,
    "gn:timezone":"Asia/Baghdad",
    "iso:country":"IQ",
    "name:ara_x_preferred":[
        "\u0639\u0628\u062f \u0632\u064a\u062f\u0627\u0646"
    ],
    "name:und_x_variant":[
        "\u2018Abd Zayd\u0101n"
    ],
    "wof:name":"'Abd Zaydan",
    "wof:placetype":"locality"
},
  "geometry": {"coordinates":[44.47963,32.8559],"type":"Point"}
}