{
  "type": "Feature",
  "properties": {
    "gn:admin1_code":"11.0",
    "gn:admin2_code":"9166534.0",
    "gn:asciiname":"Tanki",
    "gn:country_code":"IQ",
    "gn:dem":1215,
    "gn:feature_class":"P",
    "gn:feature_code":"PPL",
    "gn:name":"T\u0101nk\u012b",
    "gn:population":0,
    "gn:timezone":"Asia/Baghdad",
    "iso:country":"IQ",
    "name:ara_x_preferred":[
        "T\u0101nk\u012b"
    ],
    "name:ara_x_variant":[
        "\u062a\u0627\u0646\u0643\u064a"
    ],
    "name:kur_x_preferred":[
        "Tatk\u00ea"
    ],
    "name:kur_x_variant":[
        "\u062a\u0627\u062a\u0643\u06ce",
        "Tank\u00ee",
        "\u062a\u0627\u0646\u0643\u0649"
    ],
    "name:und_x_variant":[
        "Tatk\u012b",
        "Tanky",
        "Tatke"
    ],
    "wof:name":"Tanki",
    "wof:placetype":"locality"
},
  "geometry": {"coordinates":[44.16556,36.97931],"type":"Point"}
}