{
  "type": "Feature",
  "properties": {
    "gn:admin1_code":"7.0",
    "gn:admin2_code":"99101.0",
    "gn:asciiname":"Salman al Mudallil",
    "gn:country_code":"IQ",
    "gn:dem":32,
    "gn:feature_class":"P",
    "gn:feature_code":"PPL",
    "gn:name":"Salm\u0101n al Mudallil",
    "gn:population":0,
    "gn:timezone":"Asia/Baghdad",
    "iso:country":"IQ",
    "name:und_x_variant":[
        "Salm\u0101n al Mudallil"
    ],
    "wof:name":"Salman al Mudallil",
    "wof:placetype":"locality"
},
  "geometry": {"coordinates":[44.41667,32.95],"type":"Point"}
}