{
  "type": "Feature",
  "properties": {
    "gn:admin1_code":"4.0",
    "gn:admin2_code":"99763.0",
    "gn:asciiname":"'Atiyah Zaydan",
    "gn:country_code":"IQ",
    "gn:dem":25,
    "gn:feature_class":"P",
    "gn:feature_code":"PPL",
    "gn:name":"\u2018A\u0163\u012byah Zayd\u0101n",
    "gn:population":0,
    "gn:timezone":"Asia/Baghdad",
    "iso:country":"IQ",
    "name:ara_x_preferred":[
        "\u0639\u0637\u064a\u0629 \u0632\u064a\u062f\u0627\u0646"
    ],
    "name:und_x_variant":[
        "\u2018A\u0163\u012byah Zayd\u0101n"
    ],
    "wof:name":"'Atiyah Zaydan",
    "wof:placetype":"locality"
},
  "geometry": {"coordinates":[44.6223,32.08749],"type":"Point"}
}