{
  "type": "Feature",
  "properties": {
    "gn:admin1_code":"5.0",
    "gn:admin2_code":"91176.0",
    "gn:asciiname":"Sulaymanah",
    "gn:country_code":"IQ",
    "gn:dem":856,
    "gn:feature_class":"P",
    "gn:feature_code":"PPL",
    "gn:name":"Sulaym\u0101nah",
    "gn:population":0,
    "gn:timezone":"Asia/Baghdad",
    "iso:country":"IQ",
    "name:ara_x_preferred":[
        "\u0633\u0644\u064a\u0645\u0627\u0646\u0629"
    ],
    "name:fas_x_preferred":[
        "\u0633\u06cc\u0645\u0627\u0646\u0647"
    ],
    "name:fas_x_variant":[
        "S\u012bm\u0101neh"
    ],
    "name:kur_x_preferred":[
        "Sl\u00eamane"
    ],
    "name:kur_x_variant":[
        "\u0633\u0644\u06ce\u0645\u0627\u0646\u06d5"
    ],
    "name:und_x_variant":[
        "Si\u0113m\u0101na",
        "Sulaym\u0101niyah",
        "\u0633\u0644\u064a\u0645\u0627\u0646\u064a\u0629",
        "Slemana",
        "Sulaym\u0101nah",
        "\u0633\u0644\u064a\u0645\u0627\u0646\u0629"
    ],
    "wof:name":"Sulaymanah",
    "wof:placetype":"locality"
},
  "geometry": {"coordinates":[45.76746,35.49825999999999],"type":"Point"}
}