{
  "type": "Feature",
  "properties": {
    "gn:admin1_code":"12.0",
    "gn:admin2_code":"99345.0",
    "gn:asciiname":"Qaryat Kafr Qasim",
    "gn:country_code":"IQ",
    "gn:dem":34,
    "gn:feature_class":"P",
    "gn:feature_code":"PPL",
    "gn:name":"Qaryat Kafr Q\u0101sim",
    "gn:population":0,
    "gn:timezone":"Asia/Baghdad",
    "iso:country":"IQ",
    "name:ara_x_preferred":[
        "\u0642\u0631\u064a\u0629 \u0643\u0641\u0631 \u0642\u0627\u0633\u0645"
    ],
    "name:und_x_variant":[
        "Qaryat Kafr Q\u0101sim"
    ],
    "wof:name":"Qaryat Kafr Qasim",
    "wof:placetype":"locality"
},
  "geometry": {"coordinates":[44.17908,32.61428],"type":"Point"}
}