{
  "type": "Feature",
  "properties": {
    "gn:admin1_code":"11.0",
    "gn:admin2_code":"93817.0",
    "gn:asciiname":"Likjah",
    "gn:country_code":"IQ",
    "gn:dem":202,
    "gn:feature_class":"P",
    "gn:feature_code":"PPL",
    "gn:name":"Likjah",
    "gn:population":0,
    "gn:timezone":"Asia/Baghdad",
    "iso:country":"IQ",
    "name:ara_x_preferred":[
        "\u0644\u0643\u062c\u0629"
    ],
    "name:kur_x_preferred":[
        "Likche"
    ],
    "name:kur_x_variant":[
        "Likcha",
        "\u0644\u0643\u0686\u06d5"
    ],
    "name:und_x_variant":[
        "L\u0101kchah",
        "Likjah",
        "Malm\u0101j\u012br",
        "Al M\u0101j\u012bra",
        "Al M\u0101j\u012br"
    ],
    "wof:name":"Likjah",
    "wof:placetype":"locality"
},
  "geometry": {"coordinates":[43.60265,35.59036],"type":"Point"}
}