{
  "type": "Feature",
  "properties": {
    "gn:admin1_code":"14.0",
    "gn:admin2_code":"92536.0",
    "gn:asciiname":"Sa'i",
    "gn:country_code":"IQ",
    "gn:dem":6,
    "gn:feature_class":"P",
    "gn:feature_code":"PPL",
    "gn:name":"S\u0101\u2018\u012b",
    "gn:population":0,
    "gn:timezone":"Asia/Baghdad",
    "iso:country":"IQ",
    "name:ara_x_preferred":[
        "S\u0101\u2018\u012b"
    ],
    "wof:name":"Sa'i",
    "wof:placetype":"locality"
},
  "geometry": {"coordinates":[47.38333,31.51667],"type":"Point"}
}