{
  "type": "Feature",
  "properties": {
    "gn:admin1_code":"15.0",
    "gn:admin2_code":"90392.0",
    "gn:asciiname":"Qaryat Kharabat Tibin",
    "gn:country_code":"IQ",
    "gn:dem":367,
    "gn:feature_class":"P",
    "gn:feature_code":"PPL",
    "gn:name":"Qaryat Khar\u0101bat Tibin",
    "gn:population":0,
    "gn:timezone":"Asia/Baghdad",
    "iso:country":"IQ",
    "name:ara_x_preferred":[
        "\u0642\u0631\u064a\u0629 \u062e\u0631\u0627\u0628\u0629 \u062a\u0628\u0646"
    ],
    "name:und_x_variant":[
        "Qaryat Khar\u0101bat Tibn"
    ],
    "wof:name":"Qaryat Kharabat Tibin",
    "wof:placetype":"locality"
},
  "geometry": {"coordinates":[42.47082,36.74617],"type":"Point"}
}