{
  "type": "Feature",
  "properties": {
    "gn:admin1_code":"7.0",
    "gn:admin2_code":"9166569.0",
    "gn:asciiname":"Nasir Shahir",
    "gn:country_code":"IQ",
    "gn:dem":40,
    "gn:feature_class":"P",
    "gn:feature_code":"PPL",
    "gn:name":"N\u0101\u015fir Sh\u0101hir",
    "gn:population":0,
    "gn:timezone":"Asia/Baghdad",
    "iso:country":"IQ",
    "name:ara_x_preferred":[
        "\u0646\u0627\u0635\u0631 \u0634\u0627\u0647\u0631"
    ],
    "name:ara_x_variant":[
        "N\u0101\u015fir Sh\u0101hir"
    ],
    "wof:name":"Nasir Shahir",
    "wof:placetype":"locality"
},
  "geometry": {"coordinates":[44.22845,33.74123],"type":"Point"}
}