{
  "type": "Feature",
  "properties": {
    "gn:admin1_code":"6.0",
    "gn:admin2_code":"6818313.0",
    "gn:asciiname":"Da'bul ar Rayyas",
    "gn:country_code":"IQ",
    "gn:dem":31,
    "gn:feature_class":"P",
    "gn:feature_code":"PPL",
    "gn:name":"Da\u2018b\u016bl ar Rayy\u0101s",
    "gn:population":0,
    "gn:timezone":"Asia/Baghdad",
    "iso:country":"IQ",
    "name:ara_x_preferred":[
        "\u062f\u0639\u0628\u0648\u0644 \u0627\u0644\u0631\u064a\u0627\u0633"
    ],
    "name:und_x_variant":[
        "Da\u2018b\u016bl ar Rayy\u0101s"
    ],
    "wof:name":"Da'bul ar Rayyas",
    "wof:placetype":"locality"
},
  "geometry": {"coordinates":[44.51675,32.49155],"type":"Point"}
}