{
  "type": "Feature",
  "properties": {
    "gn:admin1_code":"15.0",
    "gn:admin2_code":"98820.0",
    "gn:asciiname":"Bujil",
    "gn:country_code":"IQ",
    "gn:dem":613,
    "gn:feature_class":"P",
    "gn:feature_code":"PPL",
    "gn:name":"B\u016bj\u012bl",
    "gn:population":0,
    "gn:timezone":"Asia/Baghdad",
    "iso:country":"IQ",
    "name:ara_x_preferred":[
        "\u0628\u0648\u062c\u064a\u0644"
    ],
    "name:ara_x_variant":[
        "\u0628\u062c\u064a\u0644"
    ],
    "name:kur_x_colloquial":[
        "\u0628\u062c\u06cc\u0644"
    ],
    "name:kur_x_historical":[
        "\u0628\u062c\u06cc\u0644"
    ],
    "name:kur_x_preferred":[
        "\u0628\u062c\u06cc\u0644"
    ],
    "name:kur_x_variant":[
        "Bic\u00eal",
        "Bic\u00eel",
        "Nehle",
        "\u0628\u062c\u06ce\u0644",
        "\u0646\u06d5\u06be\u0644\u06d5"
    ],
    "name:und_x_variant":[
        "B\u016bj\u012bl",
        "Buj\u012bl",
        "Bjil",
        "Bjel",
        "Bujil"
    ],
    "wof:name":"Bujil",
    "wof:placetype":"locality"
},
  "geometry": {"coordinates":[44.01492,36.72619],"type":"Point"}
}