{
  "type": "Feature",
  "properties": {
    "gn:admin1_code":"5.0",
    "gn:admin2_code":"98464.0",
    "gn:asciiname":"Ribatah",
    "gn:cc2":"IQ",
    "gn:country_code":"IQ",
    "gn:dem":932,
    "gn:feature_class":"P",
    "gn:feature_code":"PPL",
    "gn:name":"Rib\u0101\u0163ah",
    "gn:population":0,
    "gn:timezone":"Asia/Baghdad",
    "iso:country":"IQ",
    "name:und_x_variant":[
        "Rib\u0101ta",
        "Raba\u0163a",
        "Rib\u0101\u0163ah"
    ],
    "wof:name":"Ribatah",
    "wof:placetype":"locality"
},
  "geometry": {"coordinates":[45.46667,35.35],"type":"Point"}
}