{
  "type": "Feature",
  "properties": {
    "gn:admin1_code":"15.0",
    "gn:admin2_code":"90392.0",
    "gn:asciiname":"Raffan al `Ulya",
    "gn:country_code":"IQ",
    "gn:dem":307,
    "gn:feature_class":"P",
    "gn:feature_code":"PPL",
    "gn:name":"Raffan al `Uly\u0101",
    "gn:population":0,
    "gn:timezone":"Asia/Baghdad",
    "iso:country":"IQ",
    "wof:name":"Raffan al `Ulya",
    "wof:placetype":"locality"
},
  "geometry": {"coordinates":[42.78333,36.71667],"type":"Point"}
}