{
  "type": "Feature",
  "properties": {
    "gn:admin1_code":"11.0",
    "gn:admin2_code":"9166534.0",
    "gn:asciiname":"Birnah",
    "gn:country_code":"IQ",
    "gn:dem":1251,
    "gn:feature_class":"P",
    "gn:feature_code":"PPL",
    "gn:name":"Birnah",
    "gn:population":0,
    "gn:timezone":"Asia/Baghdad",
    "iso:country":"IQ",
    "name:ara_x_preferred":[
        "\u0628\u0631\u0646\u0647"
    ],
    "name:kur_x_preferred":[
        "B\u1e5fne"
    ],
    "name:kur_x_variant":[
        "\u0628\u0695\u0646\u06d5",
        "B\u00eaz\u00eene",
        "\u0628\u06ce\u0632\u064a\u0646\u06d5"
    ],
    "name:und_x_variant":[
        "Bizna",
        "Biz\u012bnah",
        "Birnah",
        "Birna"
    ],
    "wof:name":"Birnah",
    "wof:placetype":"locality"
},
  "geometry": {"coordinates":[44.17278,37.17006],"type":"Point"}
}