{
  "type": "Feature",
  "properties": {
    "gn:admin1_code":"13.0",
    "gn:admin2_code":"94786.0",
    "gn:asciiname":"Habah",
    "gn:country_code":"IQ",
    "gn:dem":572,
    "gn:feature_class":"P",
    "gn:feature_code":"PPL",
    "gn:name":"Habah",
    "gn:population":0,
    "gn:timezone":"Asia/Baghdad",
    "iso:country":"IQ",
    "name:ara_x_preferred":[
        "\u0647\u0628\u0629"
    ],
    "name:und_x_variant":[
        "Haybah",
        "Habah",
        "Heba"
    ],
    "wof:name":"Habah",
    "wof:placetype":"locality"
},
  "geometry": {"coordinates":[44.57918,35.54916],"type":"Point"}
}