{
  "type": "Feature",
  "properties": {
    "gn:admin1_code":"1.0",
    "gn:admin2_code":"99455.0",
    "gn:asciiname":"Salman al 'Ayid",
    "gn:country_code":"IQ",
    "gn:dem":45,
    "gn:feature_class":"P",
    "gn:feature_code":"PPL",
    "gn:name":"Salm\u0101n al \u2018Ayid",
    "gn:population":0,
    "gn:timezone":"Asia/Baghdad",
    "iso:country":"IQ",
    "name:und_x_variant":[
        "Salm\u0101n al \u2018Ayid"
    ],
    "wof:name":"Salman al 'Ayid",
    "wof:placetype":"locality"
},
  "geometry": {"coordinates":[43.62861,33.39444],"type":"Point"}
}