{
  "type": "Feature",
  "properties": {
    "gn:admin1_code":"6.0",
    "gn:admin2_code":"99358.0",
    "gn:asciiname":"Al Hadi Mutashshir Husayn",
    "gn:country_code":"IQ",
    "gn:dem":27,
    "gn:feature_class":"P",
    "gn:feature_code":"PPL",
    "gn:name":"Al \u1e28\u0101d\u012b Mu\u0163ashshir \u1e28usayn",
    "gn:population":0,
    "gn:timezone":"Asia/Baghdad",
    "iso:country":"IQ",
    "name:ara_x_preferred":[
        "\u0627\u0644\u0647\u0627\u062f\u064a \u0645\u0637\u0634\u0631 \u062d\u0633\u064a\u0646"
    ],
    "name:und_x_variant":[
        "Al \u1e28\u0101d\u012b Mu\u0163ashshir \u1e28usayn"
    ],
    "wof:name":"Al Hadi Mutashshir Husayn",
    "wof:placetype":"locality"
},
  "geometry": {"coordinates":[44.78082,32.28004],"type":"Point"}
}