{
  "type": "Feature",
  "properties": {
    "gn:admin1_code":"15.0",
    "gn:admin2_code":"9166541.0",
    "gn:asciiname":"Mansuriyat as Salamiyah",
    "gn:country_code":"IQ",
    "gn:dem":217,
    "gn:feature_class":"P",
    "gn:feature_code":"PPL",
    "gn:name":"Man\u015f\u016br\u012byat as Sal\u0101m\u012byah",
    "gn:population":0,
    "gn:timezone":"Asia/Baghdad",
    "iso:country":"IQ",
    "name:ara_x_preferred":[
        "\u0645\u0646\u0635\u0648\u0631\u064a\u0629 \u0627\u0644\u0633\u0644\u0627\u0645\u064a\u0629"
    ],
    "name:und_x_variant":[
        "Man\u015f\u016br\u012byat as Sal\u0101m\u012byah"
    ],
    "wof:name":"Mansuriyat as Salamiyah",
    "wof:placetype":"locality"
},
  "geometry": {"coordinates":[43.31557,36.14417],"type":"Point"}
}