{
  "type": "Feature",
  "properties": {
    "gn:admin1_code":"18.0",
    "gn:admin2_code":"6783103.0",
    "gn:asciiname":"Hasan Khalaf",
    "gn:country_code":"IQ",
    "gn:dem":63,
    "gn:feature_class":"P",
    "gn:feature_code":"PPL",
    "gn:name":"\u1e28asan Khalaf",
    "gn:population":0,
    "gn:timezone":"Asia/Baghdad",
    "iso:country":"IQ",
    "name:ara_x_preferred":[
        "\u062d\u0633\u0646 \u062e\u0644\u0641"
    ],
    "name:und_x_variant":[
        "\u1e28asan Khalaf"
    ],
    "wof:name":"Hasan Khalaf",
    "wof:placetype":"locality"
},
  "geometry": {"coordinates":[43.93861,34.09192],"type":"Point"}
}