{
  "type": "Feature",
  "properties": {
    "gn:admin1_code":"7.0",
    "gn:admin2_code":"9166545.0",
    "gn:asciiname":"Majid Hamid",
    "gn:country_code":"IQ",
    "gn:dem":34,
    "gn:feature_class":"P",
    "gn:feature_code":"PPL",
    "gn:name":"Maj\u012bd \u1e28am\u012bd",
    "gn:population":0,
    "gn:timezone":"Asia/Baghdad",
    "iso:country":"IQ",
    "name:ara_x_preferred":[
        "\u0645\u062c\u064a\u062f \u062d\u0645\u064a\u062f"
    ],
    "name:und_x_variant":[
        "Maj\u012bd \u1e28am\u012bd"
    ],
    "wof:name":"Majid Hamid",
    "wof:placetype":"locality"
},
  "geometry": {"coordinates":[44.39334,33.17708],"type":"Point"}
}