{
  "type": "Feature",
  "properties": {
    "gn:admin1_code":"10.0",
    "gn:admin2_code":"9166680.0",
    "gn:asciiname":"Qaryat Tamuz",
    "gn:country_code":"IQ",
    "gn:dem":35,
    "gn:feature_class":"P",
    "gn:feature_code":"PPL",
    "gn:name":"Qaryat Tam\u016bz",
    "gn:population":0,
    "gn:timezone":"Asia/Baghdad",
    "iso:country":"IQ",
    "name:ara_x_preferred":[
        "\u0642\u0631\u064a\u0629 \u062a\u0645\u0648\u0632"
    ],
    "name:und_x_variant":[
        "Qaryat Tam\u016bz"
    ],
    "wof:name":"Qaryat Tamuz",
    "wof:placetype":"locality"
},
  "geometry": {"coordinates":[44.99582,33.49757],"type":"Point"}
}