{
  "type": "Feature",
  "properties": {
    "gn:admin1_code":"4.0",
    "gn:admin2_code":"98634.0",
    "gn:asciiname":"Tawqan",
    "gn:country_code":"IQ",
    "gn:dem":18,
    "gn:feature_class":"P",
    "gn:feature_code":"PPL",
    "gn:name":"\u0162awq\u0101n",
    "gn:population":0,
    "gn:timezone":"Asia/Baghdad",
    "iso:country":"IQ",
    "name:und_x_variant":[
        "Tarq\u0101n",
        "\u0162awg\u0101n",
        "\u0162awq\u0101n"
    ],
    "wof:name":"Tawqan",
    "wof:placetype":"locality"
},
  "geometry": {"coordinates":[44.6125,31.70083],"type":"Point"}
}