{
  "type": "Feature",
  "properties": {
    "gn:admin1_code":"16.0",
    "gn:admin2_code":"99351.0",
    "gn:asciiname":"Hamid Bayg",
    "gn:country_code":"IQ",
    "gn:dem":16,
    "gn:feature_class":"P",
    "gn:feature_code":"PPL",
    "gn:name":"\u1e28\u0101mid Bayg",
    "gn:population":0,
    "gn:timezone":"Asia/Baghdad",
    "iso:country":"IQ",
    "name:ara_x_preferred":[
        "\u062d\u0627\u0645\u062f \u0628\u06af"
    ],
    "name:und_x_variant":[
        "\u1e28\u0101mid Bak",
        "\u1e28\u0101mid Bayg"
    ],
    "wof:name":"Hamid Bayg",
    "wof:placetype":"locality"
},
  "geometry": {"coordinates":[45.9575,32.17951],"type":"Point"}
}