{
  "type": "Feature",
  "properties": {
    "gn:admin1_code":"15.0",
    "gn:admin2_code":"98820.0",
    "gn:asciiname":"Kirah",
    "gn:country_code":"IQ",
    "gn:dem":812,
    "gn:feature_class":"P",
    "gn:feature_code":"PPL",
    "gn:name":"K\u012brah",
    "gn:population":0,
    "gn:timezone":"Asia/Baghdad",
    "iso:country":"IQ",
    "name:ara_x_preferred":[
        "\u0643\u064a\u0631\u0629"
    ],
    "name:kur_x_preferred":[
        "G\u00eere"
    ],
    "name:kur_x_variant":[
        "Gira",
        "\u06af\u064a\u0631\u06d5"
    ],
    "name:und_x_variant":[
        "G\u012brah",
        "K\u012brah",
        "\u06af\u064a\u0631\u0647",
        "Gira"
    ],
    "wof:name":"Kirah",
    "wof:placetype":"locality"
},
  "geometry": {"coordinates":[43.85724,36.8505],"type":"Point"}
}