{
  "type": "Feature",
  "properties": {
    "gn:admin1_code":"7.0",
    "gn:admin2_code":"9166569.0",
    "gn:asciiname":"Yusif 'Abd ar Rida",
    "gn:country_code":"IQ",
    "gn:dem":37,
    "gn:feature_class":"P",
    "gn:feature_code":"PPL",
    "gn:name":"Y\u016bsif \u2018Abd ar Ri\u1e11\u0101",
    "gn:population":0,
    "gn:timezone":"Asia/Baghdad",
    "iso:country":"IQ",
    "name:ara_x_preferred":[
        "\u064a\u0648\u0633\u0641 \u0639\u0628\u062f \u0627\u0644\u0631\u0636\u0627"
    ],
    "name:und_x_variant":[
        "Y\u016bsif \u2018Abd ar Ri\u1e11\u0101"
    ],
    "wof:name":"Yusif 'Abd ar Rida",
    "wof:placetype":"locality"
},
  "geometry": {"coordinates":[44.29159,33.64183],"type":"Point"}
}