{
  "type": "Feature",
  "properties": {
    "gn:admin1_code":"6.0",
    "gn:admin2_code":"6818313.0",
    "gn:asciiname":"Qaryat al Imam an Namudhajiyah",
    "gn:country_code":"IQ",
    "gn:dem":28,
    "gn:feature_class":"P",
    "gn:feature_code":"PPL",
    "gn:name":"Qaryat al Im\u0101m an Nam\u016bdhaj\u012byah",
    "gn:population":0,
    "gn:timezone":"Asia/Baghdad",
    "iso:country":"IQ",
    "name:ara_x_preferred":[
        "\u0642\u0631\u064a\u0629 \u0627\u0644\u0627\u0645\u0627\u0645 \u0627\u0644\u0646\u0645\u0648\u0630\u062c\u064a\u0629"
    ],
    "name:und_x_variant":[
        "Qaryat al Im\u0101m an Nam\u016bdhaj\u012byah"
    ],
    "wof:name":"Qaryat al Imam an Namudhajiyah",
    "wof:placetype":"locality"
},
  "geometry": {"coordinates":[44.59383,32.78585],"type":"Point"}
}