{
  "type": "Feature",
  "properties": {
    "gn:admin1_code":"10.0",
    "gn:admin2_code":"94590.0",
    "gn:asciiname":"Mardan Qasim",
    "gn:country_code":"IQ",
    "gn:dem":154,
    "gn:feature_class":"P",
    "gn:feature_code":"PPL",
    "gn:name":"Mard\u0101n Q\u0101sim",
    "gn:population":0,
    "gn:timezone":"Asia/Baghdad",
    "iso:country":"IQ",
    "name:ara_x_preferred":[
        "\u0645\u0631\u062f\u0627\u0646 \u0642\u0627\u0633\u0645"
    ],
    "name:fas_x_preferred":[
        "\u0645\u0631\u062f\u0627\u0646"
    ],
    "name:fas_x_variant":[
        "Mard\u0101n"
    ],
    "name:und_x_variant":[
        "Mard\u0101n Q\u0101sim"
    ],
    "wof:name":"Mardan Qasim",
    "wof:placetype":"locality"
},
  "geometry": {"coordinates":[45.3032,34.36618],"type":"Point"}
}