{
  "type": "Feature",
  "properties": {
    "gn:admin1_code":"10.0",
    "gn:admin2_code":"94590.0",
    "gn:asciiname":"Muslih al Husayn",
    "gn:country_code":"IQ",
    "gn:dem":108,
    "gn:feature_class":"P",
    "gn:feature_code":"PPL",
    "gn:name":"Mu\u015fli\u1e29 al \u1e28usayn",
    "gn:population":0,
    "gn:timezone":"Asia/Baghdad",
    "iso:country":"IQ",
    "name:ara_x_preferred":[
        "\u0645\u0635\u0644\u062d \u0627\u0644\u062d\u0633\u064a\u0646"
    ],
    "name:und_x_variant":[
        "Qaryat Mu\u015fli\u1e29",
        "\u0642\u0631\u064a\u0629 \u0645\u0635\u0644\u062d",
        "Mu\u015fli\u1e29 al \u1e28usayn"
    ],
    "wof:name":"Muslih al Husayn",
    "wof:placetype":"locality"
},
  "geometry": {"coordinates":[45.1741,34.01833],"type":"Point"}
}