{
  "type": "Feature",
  "properties": {
    "gn:admin1_code":"7.0",
    "gn:admin2_code":"9166545.0",
    "gn:asciiname":"'Aziz Dahwi",
    "gn:country_code":"IQ",
    "gn:dem":37,
    "gn:feature_class":"P",
    "gn:feature_code":"PPL",
    "gn:name":"\u2018Az\u012bz Dahw\u012b",
    "gn:population":0,
    "gn:timezone":"Asia/Baghdad",
    "iso:country":"IQ",
    "name:ara_x_preferred":[
        "\u0639\u0632\u064a\u0632 \u062f\u0647\u0648\u064a"
    ],
    "name:und_x_variant":[
        "\u2018Az\u012bz Dahw\u012b"
    ],
    "wof:name":"'Aziz Dahwi",
    "wof:placetype":"locality"
},
  "geometry": {"coordinates":[44.48157,33.22533],"type":"Point"}
}