{
  "type": "Feature",
  "properties": {
    "gn:admin1_code":"14.0",
    "gn:admin2_code":"9166557.0",
    "gn:asciiname":"Nazl Ruwayj Bin Shahid",
    "gn:country_code":"IQ",
    "gn:dem":8,
    "gn:feature_class":"P",
    "gn:feature_code":"PPL",
    "gn:name":"Nazl Ruwayj Bin Shah\u012bd",
    "gn:population":0,
    "gn:timezone":"Asia/Baghdad",
    "iso:country":"IQ",
    "name:ara_x_preferred":[
        "\u0646\u0632\u0644 \u0631\u0648\u064a\u062c \u0628\u0646 \u0634\u0647\u064a\u062f"
    ],
    "name:und_x_variant":[
        "Nazl Ruwayj Bin Shah\u012bd"
    ],
    "wof:name":"Nazl Ruwayj Bin Shahid",
    "wof:placetype":"locality"
},
  "geometry": {"coordinates":[47.33738,31.61988],"type":"Point"}
}