{
  "type": "Feature",
  "properties": {
    "gn:admin1_code":"18.0",
    "gn:admin2_code":"6783103.0",
    "gn:asciiname":"'Abd Allah ad Dahur",
    "gn:country_code":"IQ",
    "gn:dem":56,
    "gn:feature_class":"P",
    "gn:feature_code":"PPL",
    "gn:name":"\u2018Abd All\u0101h ad D\u0101h\u016br",
    "gn:population":0,
    "gn:timezone":"Asia/Baghdad",
    "iso:country":"IQ",
    "name:und_x_variant":[
        "\u2018Abd All\u0101h ad D\u0101h\u016br"
    ],
    "wof:name":"'Abd Allah ad Dahur",
    "wof:placetype":"locality"
},
  "geometry": {"coordinates":[44.31944,34.1125],"type":"Point"}
}