{
  "type": "Feature",
  "properties": {
    "gn:admin1_code":"10.0",
    "gn:admin2_code":"9166680.0",
    "gn:asciiname":"Nahiyat Kan'an",
    "gn:country_code":"IQ",
    "gn:dem":52,
    "gn:feature_class":"P",
    "gn:feature_code":"PPL",
    "gn:name":"N\u0101\u1e29iyat Kan\u2018\u0101n",
    "gn:population":0,
    "gn:timezone":"Asia/Baghdad",
    "iso:country":"IQ",
    "name:ara_x_preferred":[
        "\u0646\u0627\u062d\u064a\u0629 \u0643\u0646\u0639\u0627\u0646"
    ],
    "name:ara_x_variant":[
        "\u0643\u0646\u0639\u0627\u0646"
    ],
    "name:und_x_variant":[
        "Mahr\u016bt",
        "Marut Post",
        "Kan\u2018\u0101n",
        "N\u0101\u1e29iyat Kan\u2018\u0101n"
    ],
    "wof:name":"Nahiyat Kan'an",
    "wof:placetype":"locality"
},
  "geometry": {"coordinates":[44.8053,33.69238],"type":"Point"}
}