{
  "type": "Feature",
  "properties": {
    "gn:admin1_code":"5.0",
    "gn:admin2_code":"98464.0",
    "gn:asciiname":"Baruwi Bichuk",
    "gn:country_code":"IQ",
    "gn:dem":913,
    "gn:feature_class":"P",
    "gn:feature_code":"PPL",
    "gn:name":"Baruw\u012b Bich\u016bk",
    "gn:population":0,
    "gn:timezone":"Asia/Baghdad",
    "iso:country":"IQ",
    "name:ara_x_preferred":[
        "\u0628\u0627\u0631\u0648\u064a \u0628\u0686\u0648\u0643"
    ],
    "name:kur_x_preferred":[
        "Ba\u1e5foyy Bichuk"
    ],
    "name:kur_x_variant":[
        "\u0628\u0627\u0695\u06c6\u064a\u0649 \u0628\u0686\u0648\u0643"
    ],
    "name:und_x_variant":[
        "Bar\u016b\u012b Fich\u016bk",
        "Baruw\u012b Bich\u016bk",
        "Bar\u016b\u012b Pich\u016bk",
        "B\u0101raw\u012b Bij\u016bk",
        "Baroye",
        "\u0628\u0627\u0631\u0648\u064a \u0628\u062c\u0648\u0643"
    ],
    "wof:name":"Baruwi Bichuk",
    "wof:placetype":"locality"
},
  "geometry": {"coordinates":[45.27431,35.4811],"type":"Point"}
}