{
  "type": "Feature",
  "properties": {
    "gn:admin1_code":"10.0",
    "gn:admin2_code":"9166680.0",
    "gn:asciiname":"'Uthalat al Hasu",
    "gn:country_code":"IQ",
    "gn:dem":37,
    "gn:feature_class":"P",
    "gn:feature_code":"PPL",
    "gn:name":"\u2018Uth\u0101lat al \u1e28a\u015f\u016b",
    "gn:population":0,
    "gn:timezone":"Asia/Baghdad",
    "iso:country":"IQ",
    "name:ara_x_preferred":[
        "\u0639\u062b\u0627\u0644\u0629 \u0627\u0644\u062d\u0635\u0648"
    ],
    "name:und_x_variant":[
        "\u2018Uth\u0101lat al \u1e28a\u015f\u016b"
    ],
    "wof:name":"'Uthalat al Hasu",
    "wof:placetype":"locality"
},
  "geometry": {"coordinates":[45.07562,33.5306],"type":"Point"}
}