{
  "type": "Feature",
  "properties": {
    "gn:admin1_code":"10.0",
    "gn:admin2_code":"94296.0",
    "gn:asciiname":"Tapan",
    "gn:country_code":"IQ",
    "gn:dem":148,
    "gn:feature_class":"P",
    "gn:feature_code":"PPL",
    "gn:name":"Tap\u0101n",
    "gn:population":0,
    "gn:timezone":"Asia/Baghdad",
    "iso:country":"IQ",
    "name:ara_x_preferred":[
        "\u062a\u067e\u0627\u0646"
    ],
    "name:aze_x_preferred":[
        "Tapan"
    ],
    "name:ceb_x_preferred":[
        "Tapan"
    ],
    "name:ind_x_preferred":[
        "Tapan"
    ],
    "name:kat_x_preferred":[
        "\u10d7\u10d0\u10e4\u10d0\u10dc\u10d8"
    ],
    "name:nld_x_preferred":[
        "Tapan"
    ],
    "name:swe_x_preferred":[
        "Tapan"
    ],
    "name:und_x_variant":[
        "Tap\u0101n"
    ],
    "wof:name":"Tapan",
    "wof:placetype":"locality"
},
  "geometry": {"coordinates":[45.12663,34.46582],"type":"Point"}
}