{
  "type": "Feature",
  "properties": {
    "gn:admin1_code":"1.0",
    "gn:admin2_code":"99455.0",
    "gn:asciiname":"Qaryat al Lifiyah",
    "gn:country_code":"IQ",
    "gn:dem":41,
    "gn:feature_class":"P",
    "gn:feature_code":"PPL",
    "gn:name":"Qaryat al L\u012bf\u012byah",
    "gn:population":0,
    "gn:timezone":"Asia/Baghdad",
    "iso:country":"IQ",
    "name:ara_x_preferred":[
        "\u0642\u0631\u064a\u0629 \u0627\u0644\u0644\u064a\u0641\u064a\u0629"
    ],
    "name:und_x_variant":[
        "Qaryat al L\u012bf\u012byah"
    ],
    "wof:name":"Qaryat al Lifiyah",
    "wof:placetype":"locality"
},
  "geometry": {"coordinates":[43.85413,33.3977],"type":"Point"}
}