{
  "type": "Feature",
  "properties": {
    "gn:admin1_code":"18.0",
    "gn:admin2_code":"6805736.0",
    "gn:asciiname":"'Ali al Hammud",
    "gn:country_code":"IQ",
    "gn:dem":35,
    "gn:feature_class":"P",
    "gn:feature_code":"PPL",
    "gn:name":"\u2018Al\u012b al \u1e28amm\u016bd",
    "gn:population":0,
    "gn:timezone":"Asia/Baghdad",
    "iso:country":"IQ",
    "name:und_x_variant":[
        "Bust\u0101n A\u1e29mad al \u2018Al\u012b",
        "\u2018Al\u012b al \u1e28amm\u016bd"
    ],
    "wof:name":"'Ali al Hammud",
    "wof:placetype":"locality"
},
  "geometry": {"coordinates":[44.27306,34.01722],"type":"Point"}
}