{
  "type": "Feature",
  "properties": {
    "gn:admin1_code":"15.0",
    "gn:admin2_code":"90392.0",
    "gn:asciiname":"'Alganah",
    "gn:country_code":"IQ",
    "gn:dem":374,
    "gn:feature_class":"P",
    "gn:feature_code":"PPL",
    "gn:name":"\u2018Alg\u0101nah",
    "gn:population":0,
    "gn:timezone":"Asia/Baghdad",
    "iso:country":"IQ",
    "name:ara_x_preferred":[
        "\u0639\u0644\u06af\u0627\u0646\u0629"
    ],
    "name:kur_x_preferred":[
        "Elgene"
    ],
    "name:kur_x_variant":[
        "\u0626\u06d5\u0644\u06af\u06d5\u0646\u06d5"
    ],
    "name:und_x_variant":[
        "Algana",
        "Al Qan\u0101t",
        "\u2018Alg\u0101nah"
    ],
    "wof:name":"'Alganah",
    "wof:placetype":"locality"
},
  "geometry": {"coordinates":[42.12625,36.67483],"type":"Point"}
}