{
  "type": "Feature",
  "properties": {
    "gn:admin1_code":"10.0",
    "gn:admin2_code":"99063.0",
    "gn:asciiname":"Qaryat al Khaylaniyah",
    "gn:country_code":"IQ",
    "gn:dem":59,
    "gn:feature_class":"P",
    "gn:feature_code":"PPL",
    "gn:name":"Qaryat al Khayl\u0101n\u012byah",
    "gn:population":0,
    "gn:timezone":"Asia/Baghdad",
    "iso:country":"IQ",
    "name:ara_x_preferred":[
        "\u0642\u0631\u064a\u0629 \u0627\u0644\u062e\u064a\u0644\u0627\u0646\u064a\u0629"
    ],
    "name:und_x_variant":[
        "Qaryat al Khayl\u0101n\u012byah"
    ],
    "wof:name":"Qaryat al Khaylaniyah",
    "wof:placetype":"locality"
},
  "geometry": {"coordinates":[44.89768,33.98687],"type":"Point"}
}