{
  "type": "Feature",
  "properties": {
    "gn:admin1_code":"14.0",
    "gn:admin2_code":"9166557.0",
    "gn:asciiname":"Salaf al 'Adl",
    "gn:country_code":"IQ",
    "gn:dem":9,
    "gn:feature_class":"P",
    "gn:feature_code":"PPL",
    "gn:name":"Salaf al \u2018Adl",
    "gn:population":0,
    "gn:timezone":"Asia/Baghdad",
    "iso:country":"IQ",
    "name:ara_x_preferred":[
        "\u0633\u0644\u0641 \u0627\u0644\u0639\u062f\u0644"
    ],
    "name:und_x_variant":[
        "Salaf al \u2018Adl"
    ],
    "wof:name":"Salaf al 'Adl",
    "wof:placetype":"locality"
},
  "geometry": {"coordinates":[47.4217,31.59919],"type":"Point"}
}