{
  "type": "Feature",
  "properties": {
    "gn:admin1_code":"17.0",
    "gn:admin2_code":"9166629.0",
    "gn:asciiname":"'Awni 'Ali",
    "gn:country_code":"IQ",
    "gn:dem":25,
    "gn:feature_class":"P",
    "gn:feature_code":"PPL",
    "gn:name":"\u2018Awn\u012b \u2018Al\u012b",
    "gn:population":0,
    "gn:timezone":"Asia/Baghdad",
    "iso:country":"IQ",
    "name:ara_x_preferred":[
        "\u0639\u0648\u0646\u064a \u0639\u0644\u064a"
    ],
    "name:ara_x_variant":[
        "\u2018Awn\u012b \u2018Al\u012b"
    ],
    "wof:name":"'Awni 'Ali",
    "wof:placetype":"locality"
},
  "geometry": {"coordinates":[44.55432,32.06464],"type":"Point"}
}