{
  "type": "Feature",
  "properties": {
    "gn:admin1_code":"3.0",
    "gn:admin2_code":"9166568.0",
    "gn:asciiname":"Albu Khudayr",
    "gn:country_code":"IQ",
    "gn:dem":14,
    "gn:feature_class":"P",
    "gn:feature_code":"PPL",
    "gn:name":"\u0100lb\u016b Khu\u1e11ayr",
    "gn:population":0,
    "gn:timezone":"Asia/Baghdad",
    "iso:country":"IQ",
    "name:ara_x_preferred":[
        "\u0627\u0644\u0628\u0648 \u062e\u0636\u064a\u0631"
    ],
    "name:und_x_variant":[
        "\u0100lb\u016b Khu\u1e11ayr"
    ],
    "wof:name":"Albu Khudayr",
    "wof:placetype":"locality"
},
  "geometry": {"coordinates":[45.2578,31.4896],"type":"Point"}
}