{
  "type": "Feature",
  "properties": {
    "gn:admin1_code":"6.0",
    "gn:admin2_code":"6818313.0",
    "gn:asciiname":"Qaryat ar Rashayid",
    "gn:country_code":"IQ",
    "gn:dem":33,
    "gn:feature_class":"P",
    "gn:feature_code":"PPL",
    "gn:name":"Qaryat ar Rash\u0101yid",
    "gn:population":0,
    "gn:timezone":"Asia/Baghdad",
    "iso:country":"IQ",
    "name:ara_x_preferred":[
        "\u0642\u0631\u064a\u0629 \u0627\u0644\u0631\u0634\u0627\u064a\u062f"
    ],
    "name:und_x_variant":[
        "Qaryat ar Rash\u0101yid"
    ],
    "wof:name":"Qaryat ar Rashayid",
    "wof:placetype":"locality"
},
  "geometry": {"coordinates":[44.76615,32.74565],"type":"Point"}
}