{
  "type": "Feature",
  "properties": {
    "gn:admin1_code":"5.0",
    "gn:admin2_code":"97416.0",
    "gn:asciiname":"Garawi",
    "gn:country_code":"IQ",
    "gn:dem":577,
    "gn:feature_class":"P",
    "gn:feature_code":"PPL",
    "gn:name":"Gar\u0101w\u012b",
    "gn:population":0,
    "gn:timezone":"Asia/Baghdad",
    "iso:country":"IQ",
    "name:kur_x_preferred":[
        "Ge\u1e5faw\u00ea"
    ],
    "name:kur_x_variant":[
        "Ge\u1e5faw\u00ee",
        "\u06af\u06d5\u0695\u0627\u0648\u06ce",
        "\u06af\u06d5\u0695\u0627\u0648\u0649"
    ],
    "name:und_x_variant":[
        "Jar\u0101w\u012b",
        "Gar\u0101w\u012b",
        "Garawi"
    ],
    "wof:name":"Garawi",
    "wof:placetype":"locality"
},
  "geometry": {"coordinates":[45.02639,35.29028],"type":"Point"}
}