{
  "type": "Feature",
  "properties": {
    "gn:admin1_code":"7.0",
    "gn:admin2_code":"99101.0",
    "gn:asciiname":"'Arab Suwaydi",
    "gn:country_code":"IQ",
    "gn:dem":35,
    "gn:feature_class":"P",
    "gn:feature_code":"PPL",
    "gn:name":"\u2018Arab Suwayd\u012b",
    "gn:population":0,
    "gn:timezone":"Asia/Baghdad",
    "iso:country":"IQ",
    "name:ara_x_preferred":[
        "\u0639\u0631\u0628 \u0633\u0648\u064a\u062f\u064a"
    ],
    "name:und_x_variant":[
        "\u2018Arab Suwayd\u012b"
    ],
    "wof:name":"'Arab Suwaydi",
    "wof:placetype":"locality"
},
  "geometry": {"coordinates":[44.34266,33.11712],"type":"Point"}
}