{
  "type": "Feature",
  "properties": {
    "gn:admin1_code":"13.0",
    "gn:admin2_code":"6770659.0",
    "gn:asciiname":"Qaryat 'Abd Allah al Basil",
    "gn:country_code":"IQ",
    "gn:dem":182,
    "gn:feature_class":"P",
    "gn:feature_code":"PPL",
    "gn:name":"Qaryat \u2018Abd All\u0101h al B\u0101s\u012bl",
    "gn:population":0,
    "gn:timezone":"Asia/Baghdad",
    "iso:country":"IQ",
    "name:ara_x_preferred":[
        "\u0642\u0631\u064a\u0629 \u0639\u0628\u062f \ufdf2 \u0627\u0644\u0628\u0627\u0633\u064a\u0644"
    ],
    "name:und_x_variant":[
        "Qaryat \u2018Abd All\u0101h al B\u0101s\u012bl"
    ],
    "wof:name":"Qaryat 'Abd Allah al Basil",
    "wof:placetype":"locality"
},
  "geometry": {"coordinates":[43.83656,35.15303],"type":"Point"}
}