{
  "type": "Feature",
  "properties": {
    "gn:admin1_code":"5.0",
    "gn:admin2_code":"9166596.0",
    "gn:asciiname":"Jba Quliyan",
    "gn:country_code":"IQ",
    "gn:dem":993,
    "gn:feature_class":"P",
    "gn:feature_code":"PPL",
    "gn:name":"Jba Quliyan",
    "gn:population":0,
    "gn:timezone":"Asia/Baghdad",
    "iso:country":"IQ",
    "wof:name":"Jba Quliyan",
    "wof:placetype":"locality"
},
  "geometry": {"coordinates":[44.80973,36.04335],"type":"Point"}
}