{
  "type": "Feature",
  "properties": {
    "gn:admin1_code":"12.0",
    "gn:admin2_code":"99345.0",
    "gn:asciiname":"Qaryat al 'Abbas Sharakh",
    "gn:country_code":"IQ",
    "gn:dem":30,
    "gn:feature_class":"P",
    "gn:feature_code":"PPL",
    "gn:name":"Qaryat al \u2018Abb\u0101s Sharakh",
    "gn:population":0,
    "gn:timezone":"Asia/Baghdad",
    "iso:country":"IQ",
    "name:und_x_variant":[
        "Qaryat al \u2018Abb\u0101s Sharakh"
    ],
    "wof:name":"Qaryat al 'Abbas Sharakh",
    "wof:placetype":"locality"
},
  "geometry": {"coordinates":[44.14778,32.5525],"type":"Point"}
}