{
  "type": "Feature",
  "properties": {
    "gn:admin1_code":"11.0",
    "gn:admin2_code":"9166588.0",
    "gn:asciiname":"Shiwah Jan",
    "gn:country_code":"IQ",
    "gn:dem":515,
    "gn:feature_class":"P",
    "gn:feature_code":"PPL",
    "gn:name":"Sh\u012bwah J\u0101n",
    "gn:population":0,
    "gn:timezone":"Asia/Baghdad",
    "iso:country":"IQ",
    "name:ara_x_preferred":[
        "\u0634\u064a\u0648\u0647 \u062c\u0627\u0646"
    ],
    "name:und_x_variant":[
        "Sh\u012bwah S\u016br",
        "Sh\u012bwah J\u0101n"
    ],
    "wof:name":"Shiwah Jan",
    "wof:placetype":"locality"
},
  "geometry": {"coordinates":[44.71184,35.93273],"type":"Point"}
}