{
  "type": "Feature",
  "properties": {
    "gn:admin1_code":"5.0",
    "gn:admin2_code":"92051.0",
    "gn:asciiname":"Barawjah",
    "gn:country_code":"IQ",
    "gn:dem":1291,
    "gn:feature_class":"P",
    "gn:feature_code":"PPL",
    "gn:name":"Barawjah",
    "gn:population":0,
    "gn:timezone":"Asia/Baghdad",
    "iso:country":"IQ",
    "name:ara_x_preferred":[
        "\u0628\u0631\u0648\u062c\u0629"
    ],
    "name:kur_x_preferred":[
        "\u0628\u06d5\u0695\u06c6\u0698\u06d5"
    ],
    "name:kur_x_variant":[
        "Barozha",
        "Be\u1e5foje"
    ],
    "name:und_x_variant":[
        "B\u0101r\u016bzh",
        "Bar\u014dzha",
        "Barawjah",
        "Barozh"
    ],
    "wof:name":"Barawjah",
    "wof:placetype":"locality"
},
  "geometry": {"coordinates":[44.65561,36.37781],"type":"Point"}
}