{
  "type": "Feature",
  "properties": {
    "gn:admin1_code":"11.0",
    "gn:admin2_code":"9166534.0",
    "gn:asciiname":"Herda",
    "gn:country_code":"IQ",
    "gn:dem":516,
    "gn:feature_class":"P",
    "gn:feature_code":"PPL",
    "gn:name":"Herda",
    "gn:population":0,
    "gn:timezone":"Asia/Baghdad",
    "iso:country":"IQ",
    "name:kur_x_preferred":[
        "Herda"
    ],
    "name:kur_x_variant":[
        "\u06be\u06d5\u0631\u062f\u0627"
    ],
    "name:und_x_variant":[
        "Hardan"
    ],
    "wof:name":"Herda",
    "wof:placetype":"locality"
},
  "geometry": {"coordinates":[43.92331,36.98332],"type":"Point"}
}