{
  "type": "Feature",
  "properties": {
    "gn:admin1_code":"11.0",
    "gn:admin2_code":"93817.0",
    "gn:asciiname":"Du Shwan",
    "gn:country_code":"IQ",
    "gn:dem":304,
    "gn:feature_class":"P",
    "gn:feature_code":"PPL",
    "gn:name":"Du Shwan",
    "gn:population":0,
    "gn:timezone":"Asia/Baghdad",
    "iso:country":"IQ",
    "name:ara_x_preferred":[
        "\u0631\u0648\u0634\u0648\u0627\u0646"
    ],
    "name:ara_x_variant":[
        "R\u016bshw\u0101n"
    ],
    "name:kur_x_preferred":[
        "Du Shwan"
    ],
    "name:kur_x_variant":[
        "\u062f\u0648 \u0634\u0648\u0627\u0646"
    ],
    "name:und_x_variant":[
        "D\u016bshw\u0101n"
    ],
    "wof:name":"Du Shwan",
    "wof:placetype":"locality"
},
  "geometry": {"coordinates":[43.68238,35.84408],"type":"Point"}
}