{
  "type": "Feature",
  "properties": {
    "gn:admin1_code":"11.0",
    "gn:admin2_code":"9166592.0",
    "gn:asciiname":"Kewne Gund",
    "gn:country_code":"IQ",
    "gn:dem":739,
    "gn:feature_class":"P",
    "gn:feature_code":"PPL",
    "gn:name":"Kewne Gund",
    "gn:population":0,
    "gn:timezone":"Asia/Baghdad",
    "iso:country":"IQ",
    "name:ara_x_preferred":[
        "\u0643\u0648\u0646\u0629 \u0643\u0648\u0646\u062f"
    ],
    "name:kur_x_preferred":[
        "Kewne Gund"
    ],
    "name:kur_x_variant":[
        "\u0643\u06d5\u0648\u0646\u06d5 \u06af\u0648\u0646\u062f"
    ],
    "name:und_x_variant":[
        "Ka\u016bna K\u016bnd",
        "K\u014dnagund",
        "K\u016bnah K\u016bnd",
        "K\u0101wnag\u016bnd",
        "Kawna Gund"
    ],
    "wof:name":"Kewne Gund",
    "wof:placetype":"locality"
},
  "geometry": {"coordinates":[44.52594000000001,36.74364],"type":"Point"}
}