{
  "type": "Feature",
  "properties": {
    "gn:admin1_code":"11.0",
    "gn:admin2_code":"9166588.0",
    "gn:asciiname":"Aylanja'",
    "gn:country_code":"IQ",
    "gn:dem":412,
    "gn:feature_class":"P",
    "gn:feature_code":"PPL",
    "gn:name":"Aylanj\u0101\u2018",
    "gn:population":0,
    "gn:timezone":"Asia/Baghdad",
    "iso:country":"IQ",
    "name:ara_x_preferred":[
        "\u0627\u064a\u0644\u0646\u062c\u0627\u0639"
    ],
    "name:und_x_variant":[
        "Aylanj\u0101\u2018"
    ],
    "wof:name":"Aylanja'",
    "wof:placetype":"locality"
},
  "geometry": {"coordinates":[44.54572,35.95664],"type":"Point"}
}