{
  "type": "Feature",
  "properties": {
    "gn:admin1_code":"6.0",
    "gn:admin2_code":"99358.0",
    "gn:asciiname":"'Abd al Hasan Kazim",
    "gn:country_code":"IQ",
    "gn:dem":26,
    "gn:feature_class":"P",
    "gn:feature_code":"PPL",
    "gn:name":"\u2018Abd al \u1e28asan K\u0101z\u0327im",
    "gn:population":0,
    "gn:timezone":"Asia/Baghdad",
    "iso:country":"IQ",
    "name:ara_x_preferred":[
        "\u0639\u0628\u062f \u0627\u0644\u062d\u0633\u0646 \u0643\u0627\u0638\u0645"
    ],
    "name:und_x_variant":[
        "\u2018Abd al \u1e28asan K\u0101z\u0327im"
    ],
    "wof:name":"'Abd al Hasan Kazim",
    "wof:placetype":"locality"
},
  "geometry": {"coordinates":[44.8297,32.27535],"type":"Point"}
}