{
  "type": "Feature",
  "properties": {
    "gn:admin1_code":"10.0",
    "gn:admin2_code":"9166680.0",
    "gn:asciiname":"Kazim ad Dawud",
    "gn:cc2":"IQ",
    "gn:country_code":"IQ",
    "gn:dem":43,
    "gn:feature_class":"P",
    "gn:feature_code":"PPL",
    "gn:name":"K\u0101z\u0327im ad D\u0101w\u016bd",
    "gn:population":0,
    "gn:timezone":"Asia/Baghdad",
    "iso:country":"IQ",
    "name:und_x_variant":[
        "K\u0101zim ad D\u0101\u016bd",
        "K\u0101z\u0327\u012bm",
        "K\u0101z\u0327im ad D\u0101wir",
        "K\u0101z\u0327im ad D\u0101w\u016bd"
    ],
    "wof:name":"Kazim ad Dawud",
    "wof:placetype":"locality"
},
  "geometry": {"coordinates":[44.88333,33.78333],"type":"Point"}
}