{
  "type": "Feature",
  "properties": {
    "gn:admin1_code":"6.0",
    "gn:admin2_code":"6818313.0",
    "gn:asciiname":"'Arab Hasan 'Abbud",
    "gn:country_code":"IQ",
    "gn:dem":29,
    "gn:feature_class":"P",
    "gn:feature_code":"PPL",
    "gn:name":"\u2018Arab \u1e28asan \u2018Abb\u016bd",
    "gn:population":0,
    "gn:timezone":"Asia/Baghdad",
    "iso:country":"IQ",
    "name:ara_x_preferred":[
        "\u0639\u0631\u0628 \u062d\u0633\u0646 \u0639\u0628\u0648\u062f"
    ],
    "name:und_x_variant":[
        "\u2018Arab \u1e28asan \u2018Abb\u016bd"
    ],
    "wof:name":"'Arab Hasan 'Abbud",
    "wof:placetype":"locality"
},
  "geometry": {"coordinates":[44.78113,32.67833],"type":"Point"}
}