{
  "type": "Feature",
  "properties": {
    "gn:admin1_code":"18.0",
    "gn:admin2_code":"90148.0",
    "gn:asciiname":"Jasim al Hasan",
    "gn:country_code":"IQ",
    "gn:dem":105,
    "gn:feature_class":"P",
    "gn:feature_code":"PPL",
    "gn:name":"J\u0101sim al \u1e28asan",
    "gn:population":0,
    "gn:timezone":"Asia/Baghdad",
    "iso:country":"IQ",
    "name:ara_x_preferred":[
        "\u062c\u0627\u0633\u0645 \u0627\u0644\u062d\u0633\u0646"
    ],
    "name:und_x_variant":[
        "J\u0101sim al \u1e28asan"
    ],
    "wof:name":"Jasim al Hasan",
    "wof:placetype":"locality"
},
  "geometry": {"coordinates":[43.64773,34.46808],"type":"Point"}
}