{
  "type": "Feature",
  "properties": {
    "gn:admin1_code":"18.0",
    "gn:admin2_code":"6783103.0",
    "gn:asciiname":"Hamad al Makhlaf",
    "gn:country_code":"IQ",
    "gn:dem":78,
    "gn:feature_class":"P",
    "gn:feature_code":"PPL",
    "gn:name":"\u1e28amad al Makhlaf",
    "gn:population":0,
    "gn:timezone":"Asia/Baghdad",
    "iso:country":"IQ",
    "name:ara_x_preferred":[
        "\u062d\u0645\u062f \u0627\u0644\u0645\u062e\u0644\u0641"
    ],
    "name:und_x_variant":[
        "\u1e28amad al Makhlaf"
    ],
    "wof:name":"Hamad al Makhlaf",
    "wof:placetype":"locality"
},
  "geometry": {"coordinates":[43.95285,34.44014],"type":"Point"}
}