{
  "type": "Feature",
  "properties": {
    "gn:admin1_code":"11.0",
    "gn:admin2_code":"9166534.0",
    "gn:asciiname":"Klkamu",
    "gn:country_code":"IQ",
    "gn:dem":1022,
    "gn:feature_class":"P",
    "gn:feature_code":"PPL",
    "gn:name":"Klkamu",
    "gn:population":0,
    "gn:timezone":"Asia/Baghdad",
    "iso:country":"IQ",
    "wof:name":"Klkamu",
    "wof:placetype":"locality"
},
  "geometry": {"coordinates":[44.20273,36.98504000000001],"type":"Point"}
}