{
  "type": "Feature",
  "properties": {
    "gn:admin1_code":"5.0",
    "gn:admin2_code":"9166684.0",
    "gn:asciiname":"Kani Sayf",
    "gn:country_code":"IQ",
    "gn:dem":1459,
    "gn:feature_class":"P",
    "gn:feature_code":"PPL",
    "gn:name":"K\u0101n\u012b Sayf",
    "gn:population":0,
    "gn:timezone":"Asia/Baghdad",
    "iso:country":"IQ",
    "name:ara_x_preferred":[
        "\u0643\u0627\u0646\u064a \u0633\u064a\u0641"
    ],
    "name:fas_x_preferred":[
        "\u06a9\u0627\u0646\u06cc \u0633\u0641\u06cc\u062f"
    ],
    "name:fas_x_variant":[
        "K\u0101n\u012b Sef\u012bd"
    ],
    "name:kur_x_preferred":[
        "Kan\u00ee S\u00eaf\u00ee S\u00eax \u1e26amd"
    ],
    "name:kur_x_variant":[
        "\u0643\u0627\u0646\u0649 \u0633\u06ce\u0641\u0649 \u0634\u06ce\u062e \u062d\u0627\u0645\u062f"
    ],
    "name:und_x_variant":[
        "K\u0101n\u012b Sayf"
    ],
    "wof:name":"Kani Sayf",
    "wof:placetype":"locality"
},
  "geometry": {"coordinates":[45.96546,35.5028],"type":"Point"}
}