{
  "type": "Feature",
  "properties": {
    "gn:admin1_code":"13.0",
    "gn:admin2_code":"6770659.0",
    "gn:asciiname":"Garhat Ghazan",
    "gn:country_code":"IQ",
    "gn:dem":185,
    "gn:feature_class":"P",
    "gn:feature_code":"PPL",
    "gn:name":"Gar\u1e29at Gh\u0101z\u0101n",
    "gn:population":0,
    "gn:timezone":"Asia/Baghdad",
    "iso:country":"IQ",
    "name:ara_x_preferred":[
        "\u06af\u0631\u062d\u0629 \u063a\u0627\u0632\u0627\u0646"
    ],
    "name:und_x_variant":[
        "Gar\u1e29at Gh\u0101z\u0101n"
    ],
    "wof:name":"Garhat Ghazan",
    "wof:placetype":"locality"
},
  "geometry": {"coordinates":[44.01124,35.19523],"type":"Point"}
}