{
  "type": "Feature",
  "properties": {
    "gn:admin1_code":"9.0",
    "gn:admin2_code":"98700.0",
    "gn:asciiname":"'Arab Najib as Sayjar",
    "gn:country_code":"IQ",
    "gn:dem":10,
    "gn:feature_class":"P",
    "gn:feature_code":"PPL",
    "gn:name":"\u2018Arab Naj\u012bb as Sayjar",
    "gn:population":0,
    "gn:timezone":"Asia/Baghdad",
    "iso:country":"IQ",
    "name:ara_x_preferred":[
        "\u0639\u0631\u0628 \u0646\u062c\u064a\u0628 \u0627\u0644\u0633\u064a\u062c\u0631"
    ],
    "name:und_x_variant":[
        "\u2018Arab Naj\u012bb as Sayjar"
    ],
    "wof:name":"'Arab Najib as Sayjar",
    "wof:placetype":"locality"
},
  "geometry": {"coordinates":[45.97067,31.61657],"type":"Point"}
}