{
  "type": "Feature",
  "properties": {
    "gn:admin1_code":"15.0",
    "gn:admin2_code":"9166618.0",
    "gn:asciiname":"Shaykh Muhammad",
    "gn:country_code":"IQ",
    "gn:dem":239,
    "gn:feature_class":"P",
    "gn:feature_code":"PPL",
    "gn:name":"Shaykh Mu\u1e29ammad",
    "gn:population":0,
    "gn:timezone":"Asia/Baghdad",
    "iso:country":"IQ",
    "name:ara_x_preferred":[
        "\u0634\u064a\u062e \u0645\u062d\u0645\u062f"
    ],
    "name:und_x_variant":[
        "Shaikh Muhammad",
        "Shaykh Mu\u1e29ammad"
    ],
    "wof:name":"Shaykh Muhammad",
    "wof:placetype":"locality"
},
  "geometry": {"coordinates":[42.98353,36.42388],"type":"Point"}
}