{
  "type": "Feature",
  "properties": {
    "gn:admin1_code":"6.0",
    "gn:admin2_code":"99358.0",
    "gn:asciiname":"Qal'at Shaykh 'Abdal",
    "gn:country_code":"IQ",
    "gn:dem":27,
    "gn:feature_class":"P",
    "gn:feature_code":"PPL",
    "gn:name":"Qal\u2018at Shaykh \u2018Abd\u0101l",
    "gn:population":0,
    "gn:timezone":"Asia/Baghdad",
    "iso:country":"IQ",
    "name:und_x_variant":[
        "Qal\u2018at Shaykh \u2018Abd\u0101l"
    ],
    "wof:name":"Qal'at Shaykh 'Abdal",
    "wof:placetype":"locality"
},
  "geometry": {"coordinates":[44.75556,32.40583],"type":"Point"}
}