{
  "type": "Feature",
  "properties": {
    "gn:admin1_code":"5.0",
    "gn:asciiname":"Shkawe",
    "gn:country_code":"IQ",
    "gn:dem":1077,
    "gn:feature_class":"P",
    "gn:feature_code":"PPL",
    "gn:name":"Shkawe",
    "gn:population":0,
    "gn:timezone":"Asia/Baghdad",
    "iso:country":"IQ",
    "name:kur_x_preferred":[
        "Shkawe"
    ],
    "name:kur_x_variant":[
        "\u0634\u0643\u0627\u0648\u06d5"
    ],
    "name:und_x_variant":[
        "Pshk Awa"
    ],
    "wof:name":"Shkawe",
    "wof:placetype":"locality"
},
  "geometry": {"coordinates":[45.2573,36.30411],"type":"Point"}
}