{
  "type": "Feature",
  "properties": {
    "gn:admin1_code":"7.0",
    "gn:admin2_code":"99173.0",
    "gn:asciiname":"Taha Latif 'Ali",
    "gn:country_code":"IQ",
    "gn:dem":34,
    "gn:feature_class":"P",
    "gn:feature_code":"PPL",
    "gn:name":"\u0162\u0101h\u0101 La\u0163\u012bf \u2018Al\u012b",
    "gn:population":0,
    "gn:timezone":"Asia/Baghdad",
    "iso:country":"IQ",
    "name:ara_x_preferred":[
        "\u0637\u0647 \u0644\u0637\u064a\u0641 \u0639\u0644\u064a"
    ],
    "name:und_x_variant":[
        "\u0162\u0101h\u0101 La\u0163\u012bf \u2018Al\u012b"
    ],
    "wof:name":"Taha Latif 'Ali",
    "wof:placetype":"locality"
},
  "geometry": {"coordinates":[44.19323,33.50169],"type":"Point"}
}