{
  "type": "Feature",
  "properties": {
    "gn:admin1_code":"17.0",
    "gn:admin2_code":"9166629.0",
    "gn:asciiname":"Qaryat as Sakyan",
    "gn:country_code":"IQ",
    "gn:dem":26,
    "gn:feature_class":"P",
    "gn:feature_code":"PPL",
    "gn:name":"Qaryat a\u015f \u015eaky\u0101n",
    "gn:population":0,
    "gn:timezone":"Asia/Baghdad",
    "iso:country":"IQ",
    "name:ara_x_preferred":[
        "\u0642\u0631\u064a\u0629 \u0627\u0644\u0635\u0643\u064a\u0627\u0646"
    ],
    "name:und_x_variant":[
        "Qaryat a\u015f \u015eaky\u0101n"
    ],
    "wof:name":"Qaryat as Sakyan",
    "wof:placetype":"locality"
},
  "geometry": {"coordinates":[44.56835,32.05722],"type":"Point"}
}