{
  "type": "Feature",
  "properties": {
    "gn:admin1_code":"15.0",
    "gn:admin2_code":"98820.0",
    "gn:asciiname":"Galuk Mam Sak",
    "gn:country_code":"IQ",
    "gn:dem":652,
    "gn:feature_class":"P",
    "gn:feature_code":"PPL",
    "gn:name":"Gal\u016bk M\u0101m S\u0101k",
    "gn:population":0,
    "gn:timezone":"Asia/Baghdad",
    "iso:country":"IQ",
    "name:ara_x_preferred":[
        "\u06af\u0644\u0648\u0643 \u0645\u0627\u0645 \u0633\u0627\u0643"
    ],
    "name:kur_x_preferred":[
        "Geluk Mam Sakj\u00fbr\u00ee"
    ],
    "name:kur_x_variant":[
        "Geluk Mam Sak J\u00fbr\u00ee",
        "\u06af\u06d5\u0644\u0648\u0643 \u0645\u0627\u0645 \u0633\u0627\u0643\u0698\u0648\u0648\u0631\u0649",
        "\u06af\u06d5\u0644\u0648\u0643 \u0645\u0627\u0645 \u0633\u0627\u0643 \u0698\u0648\u0648\u0631\u0649"
    ],
    "name:und_x_variant":[
        "Gal\u016bk",
        "Gal\u016bk M\u0101m S\u0101k",
        "Kal\u016bk",
        "\u0643\u0644\u0648\u0643",
        "Galuk Mam Sak Upper"
    ],
    "wof:name":"Galuk Mam Sak",
    "wof:placetype":"locality"
},
  "geometry": {"coordinates":[44.19332,36.68274],"type":"Point"}
}