{
  "type": "Feature",
  "properties": {
    "gn:admin1_code":"7.0",
    "gn:admin2_code":"9179819.0",
    "gn:asciiname":"Qaryat al Basmayah",
    "gn:country_code":"IQ",
    "gn:dem":34,
    "gn:feature_class":"P",
    "gn:feature_code":"PPL",
    "gn:name":"Qaryat al Basm\u0101yah",
    "gn:population":0,
    "gn:timezone":"Asia/Baghdad",
    "iso:country":"IQ",
    "name:ara_x_preferred":[
        "\u0642\u0631\u064a\u0629 \u0627\u0644\u0628\u0633\u0645\u0627\u064a\u0629"
    ],
    "name:und_x_variant":[
        "Qaryat al Basm\u0101yah"
    ],
    "wof:name":"Qaryat al Basmayah",
    "wof:placetype":"locality"
},
  "geometry": {"coordinates":[44.59618,33.24602],"type":"Point"}
}