{
  "type": "Feature",
  "properties": {
    "gn:admin1_code":"7.0",
    "gn:admin2_code":"99101.0",
    "gn:asciiname":"Qaryat al Jasiyah",
    "gn:country_code":"IQ",
    "gn:dem":37,
    "gn:feature_class":"P",
    "gn:feature_code":"PPL",
    "gn:name":"Qaryat al Jas\u012byah",
    "gn:population":0,
    "gn:timezone":"Asia/Baghdad",
    "iso:country":"IQ",
    "name:ara_x_preferred":[
        "\u0642\u0631\u064a\u0629 \u0627\u0644\u062c\u0633\u064a\u0629"
    ],
    "name:und_x_variant":[
        "Qaryat al Jas\u012byah"
    ],
    "wof:name":"Qaryat al Jasiyah",
    "wof:placetype":"locality"
},
  "geometry": {"coordinates":[44.28716,33.03413],"type":"Point"}
}