{
  "type": "Feature",
  "properties": {
    "gn:admin1_code":"10.0",
    "gn:admin2_code":"94590.0",
    "gn:asciiname":"Suwayhah",
    "gn:country_code":"IQ",
    "gn:dem":58,
    "gn:feature_class":"P",
    "gn:feature_code":"PPL",
    "gn:name":"Suway\u1e29ah",
    "gn:population":0,
    "gn:timezone":"Asia/Baghdad",
    "iso:country":"IQ",
    "name:ara_x_preferred":[
        "\u0633\u0648\u064a\u062d\u0629"
    ],
    "name:und_x_variant":[
        "Suweja",
        "Suwayjat Zumb\u016br",
        "Suwayjah Zamb\u016bri",
        "S\u016bwaija Zmb\u016br",
        "Suwayjat Zunb\u016br",
        "Suway\u1e29ah"
    ],
    "wof:name":"Suwayhah",
    "wof:placetype":"locality"
},
  "geometry": {"coordinates":[44.78017,34.06407],"type":"Point"}
}