{
  "type": "Feature",
  "properties": {
    "gn:admin1_code":"4.0",
    "gn:admin2_code":"99763.0",
    "gn:asciiname":"Salman Al 'Ubayd",
    "gn:country_code":"IQ",
    "gn:dem":20,
    "gn:feature_class":"P",
    "gn:feature_code":"PPL",
    "gn:name":"Salm\u0101n \u0100l \u2018Ubayd",
    "gn:population":0,
    "gn:timezone":"Asia/Baghdad",
    "iso:country":"IQ",
    "name:ara_x_preferred":[
        "\u0633\u0644\u0645\u0627\u0646 \u0627\u0644 \u0639\u0628\u064a\u062f"
    ],
    "name:und_x_variant":[
        "Salm\u0101n \u0100l \u2018Ubayd"
    ],
    "wof:name":"Salman Al 'Ubayd",
    "wof:placetype":"locality"
},
  "geometry": {"coordinates":[44.7757,31.79597],"type":"Point"}
}