{
  "type": "Feature",
  "properties": {
    "gn:admin1_code":"5.0",
    "gn:admin2_code":"96204.0",
    "gn:asciiname":"Muwan Muhammad Hasan",
    "gn:country_code":"IQ",
    "gn:dem":529,
    "gn:feature_class":"P",
    "gn:feature_code":"PPL",
    "gn:name":"Muw\u0101n Mu\u1e29ammad \u1e28asan",
    "gn:population":0,
    "gn:timezone":"Asia/Baghdad",
    "iso:country":"IQ",
    "name:ara_x_preferred":[
        "\u0645\u0648\u0627\u0646 \u0645\u062d\u0645\u062f \u062d\u0633\u0646"
    ],
    "name:kur_x_preferred":[
        "Mwan \u1e26eme \u1e26esen"
    ],
    "name:kur_x_variant":[
        "Muwan\u00ee \u1e26eme \u1e26esen",
        "\u0645\u0648\u0627\u0646 \u062d\u06d5\u0645\u06d5 \u062d\u06d5\u0633\u06d5\u0646",
        "\u0645\u0648\u0648\u0627\u0646\u0649 \u062d\u06d5\u0645\u06d5 \u062d\u06d5\u0633\u06d5\u0646"
    ],
    "name:und_x_variant":[
        "M\u016b\u0101n",
        "Muw\u0101n-i",
        "Muw\u0101n",
        "Muw\u0101n Mu\u1e29ammad \u1e28asan",
        "Muw\u0101n-i \u1e28ama \u1e28asan \u015e\u014df\u012b",
        "Hama Hasan"
    ],
    "wof:name":"Muwan Muhammad Hasan",
    "wof:placetype":"locality"
},
  "geometry": {"coordinates":[45.71967,35.36722],"type":"Point"}
}