{
  "type": "Feature",
  "properties": {
    "gn:admin1_code":"11.0",
    "gn:admin2_code":"9166591.0",
    "gn:asciiname":"Shaykh Himundiyan",
    "gn:country_code":"IQ",
    "gn:dem":627,
    "gn:feature_class":"P",
    "gn:feature_code":"PPL",
    "gn:name":"Shaykh \u1e28im\u016bndiy\u0101n",
    "gn:population":0,
    "gn:timezone":"Asia/Baghdad",
    "iso:country":"IQ",
    "name:ara_x_preferred":[
        "\u0634\u064a\u062e \u062d\u0645\u0648\u0646\u062f\u064a\u0627\u0646"
    ],
    "name:kur_x_preferred":[
        "Sh\u00eax \u1e26mund\u00eean"
    ],
    "name:kur_x_variant":[
        "\u0634\u06ce\u062e \u062d\u0645\u0648\u0646\u062f\u064a\u0627\u0646"
    ],
    "name:und_x_variant":[
        "Shaykh Ma\u1e29m\u016bd\u012by\u0101n",
        "Sheikh Hmundian",
        "Shaykh \u1e28im\u016bndiy\u0101n"
    ],
    "wof:name":"Shaykh Himundiyan",
    "wof:placetype":"locality"
},
  "geometry": {"coordinates":[44.16857,36.4523],"type":"Point"}
}