{
  "type": "Feature",
  "properties": {
    "gn:admin1_code":"11.0",
    "gn:admin2_code":"95444.0",
    "gn:asciiname":"Qalan Jawghan",
    "gn:country_code":"IQ",
    "gn:dem":345,
    "gn:feature_class":"P",
    "gn:feature_code":"PPL",
    "gn:name":"Qal\u0101n Jawgh\u0101n",
    "gn:population":0,
    "gn:timezone":"Asia/Baghdad",
    "iso:country":"IQ",
    "name:ara_x_preferred":[
        "\u0642\u0644\u0627\u0646 \u062c\u0648\u063a\u0627\u0646"
    ],
    "name:kur_x_preferred":[
        "Qe\u0142a Choghan"
    ],
    "name:kur_x_variant":[
        "\u0642\u06d5\u06b5\u0627 \u0686\u06c6\u063a\u0627\u0646"
    ],
    "name:und_x_variant":[
        "Qal\u0101nchog\u0101n",
        "Qal\u0101nch\u016bgh\u0101n",
        "Qala Choghan",
        "Qal\u0101n Jawgh\u0101n"
    ],
    "wof:name":"Qalan Jawghan",
    "wof:placetype":"locality"
},
  "geometry": {"coordinates":[43.8942,36.2826],"type":"Point"}
}