{
  "type": "Feature",
  "properties": {
    "gn:admin1_code":"9.0",
    "gn:admin2_code":"99185.0",
    "gn:asciiname":"Al 'Umaydah",
    "gn:country_code":"IQ",
    "gn:dem":2,
    "gn:feature_class":"P",
    "gn:feature_code":"PPL",
    "gn:name":"Al \u2018Umaydah",
    "gn:population":0,
    "gn:timezone":"Asia/Baghdad",
    "iso:country":"IQ",
    "name:ara_x_preferred":[
        "\u0627\u0644\u0639\u0645\u064a\u062f\u0647"
    ],
    "name:und_x_variant":[
        "Al \u2018Umaydah"
    ],
    "wof:name":"Al 'Umaydah",
    "wof:placetype":"locality"
},
  "geometry": {"coordinates":[46.92463,30.96536],"type":"Point"}
}