{
  "type": "Feature",
  "properties": {
    "gn:admin1_code":"5.0",
    "gn:admin2_code":"92051.0",
    "gn:asciiname":"Topawe",
    "gn:country_code":"IQ",
    "gn:dem":512,
    "gn:feature_class":"P",
    "gn:feature_code":"PPL",
    "gn:name":"Topawe",
    "gn:population":0,
    "gn:timezone":"Asia/Baghdad",
    "iso:country":"IQ",
    "name:kur_x_preferred":[
        "Topawe"
    ],
    "name:kur_x_variant":[
        "\u062a\u06c6\u067e\u0627\u0648\u06d5"
    ],
    "name:und_x_variant":[
        "Tawp\u0101wah",
        "N\u014db\u0101wa",
        "Topawa"
    ],
    "wof:name":"Topawe",
    "wof:placetype":"locality"
},
  "geometry": {"coordinates":[44.92502,36.21852],"type":"Point"}
}