{
  "type": "Feature",
  "properties": {
    "gn:admin1_code":"1.0",
    "gn:admin2_code":"99455.0",
    "gn:asciiname":"Husayn 'Ali Jazza'",
    "gn:country_code":"IQ",
    "gn:dem":35,
    "gn:feature_class":"P",
    "gn:feature_code":"PPL",
    "gn:name":"\u1e28usayn \u2018Al\u012b Jazz\u0101\u2018",
    "gn:population":0,
    "gn:timezone":"Asia/Baghdad",
    "iso:country":"IQ",
    "name:ara_x_preferred":[
        "\u062d\u0633\u064a\u0646 \u0639\u0644\u064a \u062c\u0632\u0627\u0639"
    ],
    "name:und_x_variant":[
        "\u1e28usayn \u2018Al\u012b Jazz\u0101\u2018"
    ],
    "wof:name":"Husayn 'Ali Jazza'",
    "wof:placetype":"locality"
},
  "geometry": {"coordinates":[44.03737,33.61538],"type":"Point"}
}