{
  "type": "Feature",
  "properties": {
    "gn:gn_country":"IQ",
    "gn:gn_fcode":"PPLX",
    "gn:gn_pop":0,
    "iso:country":"IQ",
    "name:ara_x_colloquial":[
        "Al Jazirah"
    ],
    "name:ara_x_preferred":[
        "Al Jaz\u012brah"
    ],
    "name:unk_x_variant":[
        "Al Jaz\u012brah",
        "Jiz\u012bra"
    ],
    "qs_pg:aaroncc":"IQ",
    "qs_pg:gn_country":"IQ",
    "qs_pg:gn_fcode":"PPLX",
    "qs_pg:gn_pop":0,
    "qs_pg:name":"Al Jaz\u012brah",
    "qs_pg:name_adm0":"Iraq",
    "qs_pg:name_adm1":"\u0628\u063a\u062f\u0627\u062f",
    "qs_pg:photos":4,
    "qs_pg:photos_1k":1,
    "qs_pg:photos_9k":1,
    "qs_pg:photos_9r":1,
    "qs_pg:photos_all":4,
    "qs_pg:photos_sr":1,
    "qs_pg:pop_sr":0,
    "qs_pg:qs_pg_placetype":"neighbourhood",
    "qs_pg:qs_pg_placetype_gp":"Suburb",
    "qs_pg:woe_adm0":23424855,
    "woe:adm0_id":23424855,
    "woe:name_adm0":"Iraq",
    "woe:name_adm1":"\u0628\u063a\u062f\u0627\u062f",
    "woe:placetype":"Suburb",
    "wof:name":"Al Jaz\u012brah",
    "wof:placetype":"neighbourhood"
},
  "geometry": {"coordinates":[44.40583,33.26583],"type":"Point"}
}