{
  "type": "Feature",
  "properties": {
    "gn:admin1_code":"10.0",
    "gn:admin2_code":"99063.0",
    "gn:asciiname":"'Urkub al Yahudi",
    "gn:country_code":"IQ",
    "gn:dem":50,
    "gn:feature_class":"P",
    "gn:feature_code":"PPL",
    "gn:name":"\u2018Urk\u016bb al Yah\u016bd\u012b",
    "gn:population":0,
    "gn:timezone":"Asia/Baghdad",
    "iso:country":"IQ",
    "name:ara_x_preferred":[
        "\u0639\u0631\u0643\u0648\u0628 \u0627\u0644\u064a\u0647\u0648\u062f\u064a"
    ],
    "name:und_x_variant":[
        "\u2018Urk\u016bb al Yah\u016bd\u012b"
    ],
    "wof:name":"'Urkub al Yahudi",
    "wof:placetype":"locality"
},
  "geometry": {"coordinates":[44.83891,33.853],"type":"Point"}
}