{
  "type": "Feature",
  "properties": {
    "gn:admin1_code":"2.0",
    "gn:asciiname":"Abu Bushayr",
    "gn:country_code":"IQ",
    "gn:dem":4,
    "gn:feature_class":"P",
    "gn:feature_code":"PPL",
    "gn:name":"Ab\u016b Bushayr",
    "gn:population":0,
    "gn:timezone":"Asia/Baghdad",
    "iso:country":"IQ",
    "name:und_x_variant":[
        "Ab\u016b Bushayr"
    ],
    "wof:name":"Abu Bushayr",
    "wof:placetype":"locality"
},
  "geometry": {"coordinates":[47.78556,30.57528],"type":"Point"}
}