{
  "type": "Feature",
  "properties": {
    "gn:admin1_code":"5.0",
    "gn:admin2_code":"92743.0",
    "gn:asciiname":"Qula Shar",
    "gn:country_code":"IQ",
    "gn:dem":947,
    "gn:feature_class":"P",
    "gn:feature_code":"PPL",
    "gn:name":"Qula Shar",
    "gn:population":0,
    "gn:timezone":"Asia/Baghdad",
    "iso:country":"IQ",
    "wof:name":"Qula Shar",
    "wof:placetype":"locality"
},
  "geometry": {"coordinates":[45.22507,36.13417000000001],"type":"Point"}
}