{
  "type": "Feature",
  "properties": {
    "gn:admin1_code":"15.0",
    "gn:admin2_code":"90392.0",
    "gn:asciiname":"Qaryat Buthah",
    "gn:country_code":"IQ",
    "gn:dem":362,
    "gn:feature_class":"P",
    "gn:feature_code":"PPL",
    "gn:name":"Qaryat B\u016bthah",
    "gn:population":0,
    "gn:timezone":"Asia/Baghdad",
    "iso:country":"IQ",
    "name:ara_x_preferred":[
        "\u0642\u0631\u064a\u0629 \u0628\u0648\u062b\u0629"
    ],
    "name:und_x_variant":[
        "Qaryat B\u016bthah"
    ],
    "wof:name":"Qaryat Buthah",
    "wof:placetype":"locality"
},
  "geometry": {"coordinates":[42.25775,36.7255],"type":"Point"}
}