{
  "type": "Feature",
  "properties": {
    "gn:admin1_code":"1.0",
    "gn:admin2_code":"99455.0",
    "gn:asciiname":"Albu 'Isa",
    "gn:country_code":"IQ",
    "gn:dem":36,
    "gn:feature_class":"P",
    "gn:feature_code":"PPL",
    "gn:name":"\u0100lb\u016b \u2018\u012as\u00e1",
    "gn:population":0,
    "gn:timezone":"Asia/Baghdad",
    "iso:country":"IQ",
    "name:ara_x_preferred":[
        "\u0627\u0644\u0628\u0648 \u0639\u064a\u0633\u0649"
    ],
    "name:ara_x_variant":[
        "\u0100lb\u016b \u2018\u012as\u00e1"
    ],
    "name:und_x_variant":[
        "\u0100lb\u016b Duluf",
        "\u0627\u0644\u0628\u0648 \u062f\u0644\u0641"
    ],
    "wof:name":"Albu 'Isa",
    "wof:placetype":"locality"
},
  "geometry": {"coordinates":[44.0252,33.52058],"type":"Point"}
}