{
  "type": "Feature",
  "properties": {
    "gn:admin1_code":"4.0",
    "gn:admin2_code":"6850588.0",
    "gn:asciiname":"Ishan Hambul",
    "gn:country_code":"IQ",
    "gn:dem":17,
    "gn:feature_class":"P",
    "gn:feature_code":"PPL",
    "gn:name":"\u012ash\u0101n Hambul",
    "gn:population":0,
    "gn:timezone":"Asia/Baghdad",
    "iso:country":"IQ",
    "name:ara_x_preferred":[
        "\u0627\u064a\u0634\u0627\u0646 \u0647\u0645\u0628\u0644"
    ],
    "name:und_x_variant":[
        "\u012ash\u0101n Hambul"
    ],
    "wof:name":"Ishan Hambul",
    "wof:placetype":"locality"
},
  "geometry": {"coordinates":[44.90366,31.76453],"type":"Point"}
}