{
  "type": "Feature",
  "properties": {
    "gn:admin1_code":"17.0",
    "gn:admin2_code":"9166629.0",
    "gn:asciiname":"Husayn al 'Ali",
    "gn:country_code":"IQ",
    "gn:dem":26,
    "gn:feature_class":"P",
    "gn:feature_code":"PPL",
    "gn:name":"\u1e28usayn al \u2018Al\u012b",
    "gn:population":0,
    "gn:timezone":"Asia/Baghdad",
    "iso:country":"IQ",
    "name:ara_x_preferred":[
        "\u062d\u0633\u064a\u0646 \u0627\u0644\u0639\u0644\u064a"
    ],
    "name:und_x_variant":[
        "\u1e28usayn al \u2018Al\u012b"
    ],
    "wof:name":"Husayn al 'Ali",
    "wof:placetype":"locality"
},
  "geometry": {"coordinates":[44.51963,32.06816],"type":"Point"}
}