{
  "type": "Feature",
  "properties": {
    "gn:admin1_code":"16.0",
    "gn:admin2_code":"99351.0",
    "gn:asciiname":"Miyah",
    "gn:country_code":"IQ",
    "gn:dem":17,
    "gn:feature_class":"P",
    "gn:feature_code":"PPL",
    "gn:name":"Miy\u0101\u1e29",
    "gn:population":0,
    "gn:timezone":"Asia/Baghdad",
    "iso:country":"IQ",
    "name:ara_x_preferred":[
        "\u0645\u064a\u0627\u062d"
    ],
    "name:ara_x_variant":[
        "Miy\u0101\u1e29"
    ],
    "wof:name":"Miyah",
    "wof:placetype":"locality"
},
  "geometry": {"coordinates":[45.9932,32.05972],"type":"Point"}
}