{
  "type": "Feature",
  "properties": {
    "gn:admin1_code":"3.0",
    "gn:admin2_code":"98532.0",
    "gn:asciiname":"Qaryat Bani Huchaym",
    "gn:country_code":"IQ",
    "gn:dem":12,
    "gn:feature_class":"P",
    "gn:feature_code":"PPLL",
    "gn:name":"Qaryat Ban\u012b \u1e28uchaym",
    "gn:population":0,
    "gn:timezone":"Asia/Baghdad",
    "iso:country":"IQ",
    "name:ara_x_preferred":[
        "\u0642\u0631\u064a\u0629 \u0628\u0646\u064a \u062d\u0686\u064a\u0645"
    ],
    "name:und_x_variant":[
        "Qaryat Ban\u012b \u1e28uchaym"
    ],
    "wof:name":"Qaryat Bani Huchaym",
    "wof:placetype":"locality"
},
  "geometry": {"coordinates":[45.41519,31.2786],"type":"Point"}
}