{
  "type": "Feature",
  "properties": {
    "gn:admin1_code":"16.0",
    "gn:admin2_code":"98460.0",
    "gn:asciiname":"Hadi",
    "gn:country_code":"IQ",
    "gn:dem":26,
    "gn:feature_class":"P",
    "gn:feature_code":"PPL",
    "gn:name":"H\u0101d\u012b",
    "gn:population":0,
    "gn:timezone":"Asia/Baghdad",
    "iso:country":"IQ",
    "name:ara_x_preferred":[
        "\u0647\u0627\u062f\u064a"
    ],
    "name:ara_x_variant":[
        "H\u0101d\u012b"
    ],
    "wof:name":"Hadi",
    "wof:placetype":"locality"
},
  "geometry": {"coordinates":[45.05134,32.81828],"type":"Point"}
}