{
  "type": "Feature",
  "properties": {
    "gn:admin1_code":"14.0",
    "gn:admin2_code":"99610.0",
    "gn:asciiname":"Salaf Mulla Farhan",
    "gn:country_code":"IQ",
    "gn:dem":6,
    "gn:feature_class":"P",
    "gn:feature_code":"PPL",
    "gn:name":"Salaf Mull\u0101 Far\u1e29\u0101n",
    "gn:population":0,
    "gn:timezone":"Asia/Baghdad",
    "iso:country":"IQ",
    "name:ara_x_preferred":[
        "\u0633\u0644\u0641 \u0645\u0644\u0627 \u0641\u0631\u062d\u0627\u0646"
    ],
    "name:und_x_variant":[
        "Far\u1e29\u0101n",
        "Salaf Mull\u0101 Far\u1e29\u0101n"
    ],
    "wof:name":"Salaf Mulla Farhan",
    "wof:placetype":"locality"
},
  "geometry": {"coordinates":[47.16274,31.76541],"type":"Point"}
}