{
  "type": "Feature",
  "properties": {
    "gn:admin1_code":"10.0",
    "gn:admin2_code":"99063.0",
    "gn:asciiname":"'Arab Hamzah",
    "gn:country_code":"IQ",
    "gn:dem":51,
    "gn:feature_class":"P",
    "gn:feature_code":"PPL",
    "gn:name":"\u2018Arab \u1e28amzah",
    "gn:population":0,
    "gn:timezone":"Asia/Baghdad",
    "iso:country":"IQ",
    "name:ara_x_preferred":[
        "\u0639\u0631\u0628 \u062d\u0645\u0632\u0647"
    ],
    "name:und_x_variant":[
        "\u2018Arab \u1e28amzah"
    ],
    "wof:name":"'Arab Hamzah",
    "wof:placetype":"locality"
},
  "geometry": {"coordinates":[44.79935,33.81253],"type":"Point"}
}