{
  "type": "Feature",
  "properties": {
    "gn:admin1_code":"18.0",
    "gn:admin2_code":"6805736.0",
    "gn:asciiname":"'Aziz ad Dawan",
    "gn:country_code":"IQ",
    "gn:dem":55,
    "gn:feature_class":"P",
    "gn:feature_code":"PPL",
    "gn:name":"\u2018Az\u012bz ad Daw\u0101n",
    "gn:population":0,
    "gn:timezone":"Asia/Baghdad",
    "iso:country":"IQ",
    "name:ara_x_preferred":[
        "\u0639\u0632\u064a\u0632 \u0627\u0644\u062f\u0648\u0627\u0646"
    ],
    "name:und_x_variant":[
        "\u2018Az\u012bz ad Daw\u0101n"
    ],
    "wof:name":"'Aziz ad Dawan",
    "wof:placetype":"locality"
},
  "geometry": {"coordinates":[43.9291,33.99063],"type":"Point"}
}