{
  "type": "Feature",
  "properties": {
    "gn:admin1_code":"2.0",
    "gn:admin2_code":"98247.0",
    "gn:asciiname":"Dirhamiyah",
    "gn:country_code":"IQ",
    "gn:dem":17,
    "gn:feature_class":"P",
    "gn:feature_code":"PPL",
    "gn:name":"Dirham\u012byah",
    "gn:population":0,
    "gn:timezone":"Asia/Baghdad",
    "iso:country":"IQ",
    "name:und_x_variant":[
        "Dirham\u012byah"
    ],
    "wof:name":"Dirhamiyah",
    "wof:placetype":"locality"
},
  "geometry": {"coordinates":[47.7211,30.33341],"type":"Point"}
}