{
  "type": "Feature",
  "properties": {
    "gn:admin1_code":"7.0",
    "gn:admin2_code":"9166569.0",
    "gn:asciiname":"'Abd Khalaf",
    "gn:country_code":"IQ",
    "gn:dem":38,
    "gn:feature_class":"P",
    "gn:feature_code":"PPL",
    "gn:name":"\u2018Abd Khalaf",
    "gn:population":0,
    "gn:timezone":"Asia/Baghdad",
    "iso:country":"IQ",
    "name:ara_x_preferred":[
        "\u0639\u0628\u062f \u062e\u0644\u0641"
    ],
    "name:und_x_variant":[
        "\u2018Abd Khalaf"
    ],
    "wof:name":"'Abd Khalaf",
    "wof:placetype":"locality"
},
  "geometry": {"coordinates":[44.16074,33.6253],"type":"Point"}
}