{
  "type": "Feature",
  "properties": {
    "gn:admin1_code":"15.0",
    "gn:admin2_code":"99414.0",
    "gn:asciiname":"Qaryat Muwaylah ash Shimali",
    "gn:country_code":"IQ",
    "gn:dem":225,
    "gn:feature_class":"P",
    "gn:feature_code":"PPL",
    "gn:name":"Qaryat Muwayla\u1e29 ash Shim\u0101l\u012b",
    "gn:population":0,
    "gn:timezone":"Asia/Baghdad",
    "iso:country":"IQ",
    "name:ara_x_preferred":[
        "\u0642\u0631\u064a\u0629 \u0645\u0648\u064a\u0644\u062d \u0627\u0644\u0634\u0645\u0627\u0644\u064a"
    ],
    "name:und_x_variant":[
        "Qaryat Muwayla\u1e29 ash Shim\u0101l\u012b"
    ],
    "wof:name":"Qaryat Muwaylah ash Shimali",
    "wof:placetype":"locality"
},
  "geometry": {"coordinates":[43.00119,35.78596],"type":"Point"}
}