{
  "type": "Feature",
  "properties": {
    "gn:admin1_code":"15.0",
    "gn:admin2_code":"90392.0",
    "gn:asciiname":"Mamil Hilum",
    "gn:country_code":"IQ",
    "gn:dem":454,
    "gn:feature_class":"P",
    "gn:feature_code":"PPL",
    "gn:name":"M\u0101mil \u1e28il\u016bm",
    "gn:population":0,
    "gn:timezone":"Asia/Baghdad",
    "iso:country":"IQ",
    "name:ara_x_preferred":[
        "\u0645\u0627\u0645\u0644 \u062d\u0644\u0648\u0645"
    ],
    "name:kur_x_preferred":[
        "Maml \u1e26lum"
    ],
    "name:und_x_variant":[
        "M\u0101mil \u1e28all\u016bm",
        "M\u0101mil \u1e28ul\u016bm"
    ],
    "wof:name":"Mamil Hilum",
    "wof:placetype":"locality"
},
  "geometry": {"coordinates":[42.29364,36.53331],"type":"Point"}
}