{
  "type": "Feature",
  "properties": {
    "gn:admin1_code":"1.0",
    "gn:admin2_code":"9166579.0",
    "gn:asciiname":"Al Ma'murah",
    "gn:country_code":"IQ",
    "gn:dem":82,
    "gn:feature_class":"P",
    "gn:feature_code":"PPL",
    "gn:name":"Al Ma\u2018m\u016brah",
    "gn:population":0,
    "gn:timezone":"Asia/Baghdad",
    "iso:country":"IQ",
    "name:ara_x_preferred":[
        "\u0627\u0644\u0645\u0639\u0645\u0648\u0631\u0629"
    ],
    "name:und_x_variant":[
        "Al Ma\u2018m\u016brah"
    ],
    "wof:name":"Al Ma'murah",
    "wof:placetype":"locality"
},
  "geometry": {"coordinates":[42.78516,33.61538],"type":"Point"}
}