{
  "type": "Feature",
  "properties": {
    "gn:admin1_code":"4.0",
    "gn:admin2_code":"99763.0",
    "gn:asciiname":"Kazim as Salamah",
    "gn:country_code":"IQ",
    "gn:dem":25,
    "gn:feature_class":"P",
    "gn:feature_code":"PPL",
    "gn:name":"K\u0101z\u0327im as Sal\u0101mah",
    "gn:population":0,
    "gn:timezone":"Asia/Baghdad",
    "iso:country":"IQ",
    "name:ara_x_preferred":[
        "\u0643\u0627\u0638\u0645 \u0627\u0644\u0633\u0644\u0627\u0645\u0629"
    ],
    "name:und_x_variant":[
        "K\u0101z\u0327im as Sal\u0101mah"
    ],
    "wof:name":"Kazim as Salamah",
    "wof:placetype":"locality"
},
  "geometry": {"coordinates":[44.562,31.99521],"type":"Point"}
}