{
  "type": "Feature",
  "properties": {
    "gn:admin1_code":"17.0",
    "gn:admin2_code":"9166552.0",
    "gn:asciiname":"Al Far'awn ash Shimali",
    "gn:country_code":"IQ",
    "gn:dem":25,
    "gn:feature_class":"P",
    "gn:feature_code":"PPL",
    "gn:name":"\u0100l Far\u2018awn ash Shim\u0101l\u012b",
    "gn:population":0,
    "gn:timezone":"Asia/Baghdad",
    "iso:country":"IQ",
    "name:ara_x_preferred":[
        "\u0627\u0644 \u0641\u0631\u0639\u0648\u0646 \u0627\u0644\u0634\u0645\u0627\u0644\u064a"
    ],
    "name:und_x_variant":[
        "\u0100l Far\u2018awn ash Shim\u0101l\u012b"
    ],
    "wof:name":"Al Far'awn ash Shimali",
    "wof:placetype":"locality"
},
  "geometry": {"coordinates":[44.50553,31.88416],"type":"Point"}
}