{
  "type": "Feature",
  "properties": {
    "gn:admin1_code":"4.0",
    "gn:admin2_code":"98634.0",
    "gn:asciiname":"Manazil Jari",
    "gn:country_code":"IQ",
    "gn:dem":20,
    "gn:feature_class":"P",
    "gn:feature_code":"PPL",
    "gn:name":"Man\u0101zil Jar\u012b",
    "gn:population":0,
    "gn:timezone":"Asia/Baghdad",
    "iso:country":"IQ",
    "name:und_x_variant":[
        "Man\u0101zil Jar\u012b"
    ],
    "wof:name":"Manazil Jari",
    "wof:placetype":"locality"
},
  "geometry": {"coordinates":[44.5925,31.70194],"type":"Point"}
}