{
  "type": "Feature",
  "properties": {
    "gn:admin1_code":"6.0",
    "gn:admin2_code":"6818313.0",
    "gn:asciiname":"Qaryat 'Ubayd Husayn",
    "gn:country_code":"IQ",
    "gn:dem":28,
    "gn:feature_class":"P",
    "gn:feature_code":"PPL",
    "gn:name":"Qaryat \u2018Ubayd \u1e28usayn",
    "gn:population":0,
    "gn:timezone":"Asia/Baghdad",
    "iso:country":"IQ",
    "name:ara_x_preferred":[
        "\u0642\u0631\u064a\u0629 \u0639\u0628\u064a\u062f \u062d\u0633\u064a\u0646"
    ],
    "name:und_x_variant":[
        "Qaryat \u2018Ubayd \u1e28usayn"
    ],
    "wof:name":"Qaryat 'Ubayd Husayn",
    "wof:placetype":"locality"
},
  "geometry": {"coordinates":[44.4612,32.52108],"type":"Point"}
}