{
  "type": "Feature",
  "properties": {
    "gn:admin1_code":"5.0",
    "gn:admin2_code":"96204.0",
    "gn:asciiname":"Dawli Nawhad",
    "gn:country_code":"IQ",
    "gn:dem":502,
    "gn:feature_class":"P",
    "gn:feature_code":"PPL",
    "gn:name":"Dawl\u012b N\u0101whad",
    "gn:population":0,
    "gn:timezone":"Asia/Baghdad",
    "iso:country":"IQ",
    "name:ara_x_preferred":[
        "\u062f\u0648\u0644\u064a \u0646\u0627\u0648\u06be\u062f"
    ],
    "name:kur_x_preferred":[
        "Do\u0142\u00ee Naw Hedulu\u1e5f"
    ],
    "name:kur_x_variant":[
        "\u062f\u06c6\u06b5\u0649 \u0646\u0627\u0648 \u06be\u06d5\u062f\u0648\u0644\u0648\u0695"
    ],
    "name:und_x_variant":[
        "Dawl\u012b N\u0101whad",
        "Doli Naw Hadulor"
    ],
    "wof:name":"Dawli Nawhad",
    "wof:placetype":"locality"
},
  "geometry": {"coordinates":[45.76694000000001,35.13437],"type":"Point"}
}