{
  "type": "Feature",
  "properties": {
    "gn:admin1_code":"5.0",
    "gn:admin2_code":"92051.0",
    "gn:asciiname":"Asterilan",
    "gn:country_code":"IQ",
    "gn:dem":615,
    "gn:feature_class":"P",
    "gn:feature_code":"PPL",
    "gn:name":"Ast\u0113r\u012bl\u0101n",
    "gn:population":0,
    "gn:timezone":"Asia/Baghdad",
    "iso:country":"IQ",
    "name:ara_x_preferred":[
        "Ast\u0113r\u012bl\u0101n"
    ],
    "wof:name":"Asterilan",
    "wof:placetype":"locality"
},
  "geometry": {"coordinates":[44.80861,36.25694],"type":"Point"}
}