{
  "type": "Feature",
  "properties": {
    "gn:admin1_code":"3.0",
    "gn:admin2_code":"9166568.0",
    "gn:asciiname":"Albu Nasr",
    "gn:country_code":"IQ",
    "gn:dem":16,
    "gn:feature_class":"P",
    "gn:feature_code":"PPL",
    "gn:name":"\u0100lb\u016b Na\u015fr",
    "gn:population":0,
    "gn:timezone":"Asia/Baghdad",
    "iso:country":"IQ",
    "name:ara_x_preferred":[
        "\u0627\u0644\u0628\u0648 \u0646\u0635\u0631"
    ],
    "name:und_x_variant":[
        "\u0100lb\u016b Na\u015fr"
    ],
    "wof:name":"Albu Nasr",
    "wof:placetype":"locality"
},
  "geometry": {"coordinates":[45.10317,31.46544],"type":"Point"}
}