{
  "type": "Feature",
  "properties": {
    "gn:admin1_code":"6.0",
    "gn:admin2_code":"6818313.0",
    "gn:asciiname":"Husayn Juwayd",
    "gn:country_code":"IQ",
    "gn:dem":30,
    "gn:feature_class":"P",
    "gn:feature_code":"PPL",
    "gn:name":"\u1e28usayn Juwayd",
    "gn:population":0,
    "gn:timezone":"Asia/Baghdad",
    "iso:country":"IQ",
    "name:ara_x_preferred":[
        "\u062d\u0633\u064a\u0646 \u062c\u0648\u064a\u062f"
    ],
    "name:und_x_variant":[
        "\u1e28usayn Juwayd"
    ],
    "wof:name":"Husayn Juwayd",
    "wof:placetype":"locality"
},
  "geometry": {"coordinates":[44.67027,32.77611],"type":"Point"}
}