{
  "type": "Feature",
  "properties": {
    "gn:admin1_code":"5.0",
    "gn:admin2_code":"97416.0",
    "gn:asciiname":"Jinkani",
    "gn:country_code":"IQ",
    "gn:dem":578,
    "gn:feature_class":"P",
    "gn:feature_code":"PPL",
    "gn:name":"J\u012bnkan\u012b",
    "gn:population":0,
    "gn:timezone":"Asia/Baghdad",
    "iso:country":"IQ",
    "name:ara_x_preferred":[
        "\u062c\u064a\u0646\u0643\u0646\u064a"
    ],
    "name:und_x_variant":[
        "J\u012bnkan\u012b",
        "Chingn\u012b",
        "Ch\u012bngan\u012b",
        "\u0686\u064a\u0646\u06af\u0646\u064a"
    ],
    "wof:name":"Jinkani",
    "wof:placetype":"locality"
},
  "geometry": {"coordinates":[44.90713,35.34348],"type":"Point"}
}