{
  "type": "Feature",
  "properties": {
    "gn:admin1_code":"11.0",
    "gn:admin2_code":"93817.0",
    "gn:asciiname":"Qaryat Hushtir Laluk",
    "gn:country_code":"IQ",
    "gn:dem":220,
    "gn:feature_class":"P",
    "gn:feature_code":"PPL",
    "gn:name":"Qaryat H\u016bshtir Lal\u016bk",
    "gn:population":0,
    "gn:timezone":"Asia/Baghdad",
    "iso:country":"IQ",
    "name:ara_x_preferred":[
        "\u0642\u0631\u064a\u0629 \u0647\u0648\u0634\u062a\u0631 \u0644\u0627\u0644\u0648\u0643"
    ],
    "name:kur_x_preferred":[
        "\u1e26ushtr Aluk"
    ],
    "name:kur_x_variant":[
        "\u062d\u0648\u0634\u062a\u0631 \u0626\u0627\u0644\u0648\u0643"
    ],
    "name:und_x_variant":[
        "Hushtr Aluk",
        "Qaryat H\u016bshtir Lal\u016bk"
    ],
    "wof:name":"Qaryat Hushtir Laluk",
    "wof:placetype":"locality"
},
  "geometry": {"coordinates":[43.44627,35.67089],"type":"Point"}
}