{
  "type": "Feature",
  "properties": {
    "gn:admin1_code":"10.0",
    "gn:admin2_code":"9166680.0",
    "gn:asciiname":"Qaryat Ibrahim",
    "gn:country_code":"IQ",
    "gn:dem":46,
    "gn:feature_class":"P",
    "gn:feature_code":"PPL",
    "gn:name":"Qaryat Ibr\u0101h\u012bm",
    "gn:population":0,
    "gn:timezone":"Asia/Baghdad",
    "iso:country":"IQ",
    "name:ara_x_preferred":[
        "\u0642\u0631\u064a\u0629 \u0627\u0628\u0631\u0627\u0647\u064a\u0645"
    ],
    "name:und_x_variant":[
        "Qaryat Ibr\u0101h\u012bm"
    ],
    "wof:name":"Qaryat Ibrahim",
    "wof:placetype":"locality"
},
  "geometry": {"coordinates":[44.82917,33.68761],"type":"Point"}
}