{
  "type": "Feature",
  "properties": {
    "gn:admin1_code":"11.0",
    "gn:admin2_code":"9166592.0",
    "gn:asciiname":"Warah Sinan",
    "gn:country_code":"IQ",
    "gn:dem":968,
    "gn:feature_class":"P",
    "gn:feature_code":"PPL",
    "gn:name":"Warah Sin\u0101n",
    "gn:population":0,
    "gn:timezone":"Asia/Baghdad",
    "iso:country":"IQ",
    "name:ara_x_preferred":[
        "\u0648\u0631\u0647 \u0633\u0646\u0627\u0646"
    ],
    "name:kur_x_preferred":[
        "Dara S\u00eenan"
    ],
    "name:kur_x_variant":[
        "\u062f\u0627\u0631\u0627 \u0633\u064a\u0646\u0627\u0646"
    ],
    "name:und_x_variant":[
        "Warah Sin\u0101n",
        "Dara Senan"
    ],
    "wof:name":"Warah Sinan",
    "wof:placetype":"locality"
},
  "geometry": {"coordinates":[44.53988,36.92157],"type":"Point"}
}