{
  "type": "Feature",
  "properties": {
    "gn:admin1_code":"7.0",
    "gn:admin2_code":"99173.0",
    "gn:asciiname":"Husayn Suhayl",
    "gn:country_code":"IQ",
    "gn:dem":36,
    "gn:feature_class":"P",
    "gn:feature_code":"PPL",
    "gn:name":"\u1e28usayn Suhayl",
    "gn:population":0,
    "gn:timezone":"Asia/Baghdad",
    "iso:country":"IQ",
    "name:ara_x_preferred":[
        "\u062d\u0633\u064a\u0646 \u0633\u0647\u064a\u0644"
    ],
    "name:und_x_variant":[
        "\u1e28usayn Suhayl"
    ],
    "wof:name":"Husayn Suhayl",
    "wof:placetype":"locality"
},
  "geometry": {"coordinates":[44.19485,33.46922],"type":"Point"}
}