{
  "type": "Feature",
  "properties": {
    "gn:admin1_code":"18.0",
    "gn:admin2_code":"91594.0",
    "gn:asciiname":"'Arab Muhammad al 'Abd",
    "gn:country_code":"IQ",
    "gn:dem":75,
    "gn:feature_class":"P",
    "gn:feature_code":"PPLL",
    "gn:name":"\u2018Arab Mu\u1e29ammad al \u2018Abd",
    "gn:population":0,
    "gn:timezone":"Asia/Baghdad",
    "iso:country":"IQ",
    "name:ara_x_preferred":[
        "\u0639\u0631\u0628 \u0645\u062d\u0645\u062f \u0627\u0644\u0639\u0628\u062f"
    ],
    "name:und_x_variant":[
        "\u2018Arab Mu\u1e29ammad al \u2018Abd"
    ],
    "wof:name":"'Arab Muhammad al 'Abd",
    "wof:placetype":"locality"
},
  "geometry": {"coordinates":[43.74202,34.36691],"type":"Point"}
}