{
  "type": "Feature",
  "properties": {
    "gn:admin1_code":"17.0",
    "gn:admin2_code":"9166629.0",
    "gn:asciiname":"Qal'at Dighayim",
    "gn:country_code":"IQ",
    "gn:dem":27,
    "gn:feature_class":"P",
    "gn:feature_code":"PPL",
    "gn:name":"Qal\u2018at Dighayim",
    "gn:population":0,
    "gn:timezone":"Asia/Baghdad",
    "iso:country":"IQ",
    "name:ara_x_preferred":[
        "\u0642\u0644\u0639\u0629 \u0648\u063a\u064a\u0645"
    ],
    "name:und_x_variant":[
        "Qal\u2018at Dighayim"
    ],
    "wof:name":"Qal'at Dighayim",
    "wof:placetype":"locality"
},
  "geometry": {"coordinates":[44.42822,31.99374000000001],"type":"Point"}
}