{
  "type": "Feature",
  "properties": {
    "gn:admin1_code":"18.0",
    "gn:admin2_code":"91594.0",
    "gn:asciiname":"Jaddu' Salman",
    "gn:country_code":"IQ",
    "gn:dem":84,
    "gn:feature_class":"P",
    "gn:feature_code":"PPL",
    "gn:name":"Jadd\u016b\u2018 Salm\u0101n",
    "gn:population":0,
    "gn:timezone":"Asia/Baghdad",
    "iso:country":"IQ",
    "name:ara_x_preferred":[
        "\u062c\u062f\u0648\u0639 \u0633\u0644\u0645\u0627\u0646"
    ],
    "name:und_x_variant":[
        "Jadd\u016b\u2018 Salm\u0101n"
    ],
    "wof:name":"Jaddu' Salman",
    "wof:placetype":"locality"
},
  "geometry": {"coordinates":[43.65787,34.2026],"type":"Point"}
}