{
  "type": "Feature",
  "properties": {
    "gn:admin1_code":"11.0",
    "gn:admin2_code":"9166592.0",
    "gn:asciiname":"Gird Xiwet",
    "gn:country_code":"IQ",
    "gn:dem":565,
    "gn:feature_class":"P",
    "gn:feature_code":"PPL",
    "gn:name":"Gird X\u00eewet",
    "gn:population":0,
    "gn:timezone":"Asia/Baghdad",
    "iso:country":"IQ",
    "name:kur_x_preferred":[
        "Gird X\u00eewet"
    ],
    "name:kur_x_variant":[
        "\u06af\u0631\u062f \u062e\u064a\u0648\u06d5\u062a"
    ],
    "name:und_x_variant":[
        "Grd Khiwat"
    ],
    "wof:name":"Gird Xiwet",
    "wof:placetype":"locality"
},
  "geometry": {"coordinates":[44.49419,36.67828],"type":"Point"}
}