{
  "type": "Feature",
  "properties": {
    "gn:admin1_code":"16.0",
    "gn:admin2_code":"98460.0",
    "gn:asciiname":"Nu'man",
    "gn:country_code":"IQ",
    "gn:dem":26,
    "gn:feature_class":"P",
    "gn:feature_code":"PPL",
    "gn:name":"Nu\u2018m\u0101n",
    "gn:population":0,
    "gn:timezone":"Asia/Baghdad",
    "iso:country":"IQ",
    "name:ara_x_preferred":[
        "Nu\u2018m\u0101n"
    ],
    "wof:name":"Nu'man",
    "wof:placetype":"locality"
},
  "geometry": {"coordinates":[45.40444,32.60833],"type":"Point"}
}