{
  "type": "Feature",
  "properties": {
    "gn:admin1_code":"11.0",
    "gn:admin2_code":"93817.0",
    "gn:asciiname":"Kird Kalikhah",
    "gn:country_code":"IQ",
    "gn:dem":197,
    "gn:feature_class":"P",
    "gn:feature_code":"PPL",
    "gn:name":"Kird Kal\u012bkhah",
    "gn:population":0,
    "gn:timezone":"Asia/Baghdad",
    "iso:country":"IQ",
    "name:ara_x_preferred":[
        "\u0643\u0631\u062f \u0643\u0644\u064a\u062e\u0629"
    ],
    "name:und_x_variant":[
        "Kird Kal\u012bkhah"
    ],
    "wof:name":"Kird Kalikhah",
    "wof:placetype":"locality"
},
  "geometry": {"coordinates":[43.6271,35.54389000000001],"type":"Point"}
}