{
  "type": "Feature",
  "properties": {
    "gn:admin1_code":"15.0",
    "gn:admin2_code":"9166649.0",
    "gn:asciiname":"Tall ar Rayyis",
    "gn:country_code":"IQ",
    "gn:dem":251,
    "gn:feature_class":"P",
    "gn:feature_code":"PPL",
    "gn:name":"Tall ar Rayyis",
    "gn:population":0,
    "gn:timezone":"Asia/Baghdad",
    "iso:country":"IQ",
    "name:ara_x_preferred":[
        "\u062a\u0644 \u0627\u0644\u0631\u064a\u0633"
    ],
    "wof:name":"Tall ar Rayyis",
    "wof:placetype":"locality"
},
  "geometry": {"coordinates":[42.96686,36.41519],"type":"Point"}
}