{
  "type": "Feature",
  "properties": {
    "gn:admin1_code":"13.0",
    "gn:admin2_code":"6770659.0",
    "gn:asciiname":"Hamad Sharaji",
    "gn:country_code":"IQ",
    "gn:dem":174,
    "gn:feature_class":"P",
    "gn:feature_code":"PPL",
    "gn:name":"\u1e28amad Sharaj\u012b",
    "gn:population":0,
    "gn:timezone":"Asia/Baghdad",
    "iso:country":"IQ",
    "name:ara_x_preferred":[
        "\u062d\u0645\u062f \u0634\u0631\u062c\u064a"
    ],
    "name:und_x_variant":[
        "\u1e28amad Sharaj\u012b"
    ],
    "wof:name":"Hamad Sharaji",
    "wof:placetype":"locality"
},
  "geometry": {"coordinates":[43.72638,35.15532],"type":"Point"}
}