{
  "type": "Feature",
  "properties": {
    "gn:admin1_code":"16.0",
    "gn:admin2_code":"9166961.0",
    "gn:asciiname":"Qaryat at Tanmiyah",
    "gn:country_code":"IQ",
    "gn:dem":28,
    "gn:feature_class":"P",
    "gn:feature_code":"PPL",
    "gn:name":"Qaryat at Tanm\u012byah",
    "gn:population":0,
    "gn:timezone":"Asia/Baghdad",
    "iso:country":"IQ",
    "name:ara_x_preferred":[
        "\u0642\u0631\u064a\u0629 \u0627\u0644\u062a\u0646\u0645\u064a\u0629"
    ],
    "name:und_x_variant":[
        "Qaryat at Tanm\u012byah"
    ],
    "wof:name":"Qaryat at Tanmiyah",
    "wof:placetype":"locality"
},
  "geometry": {"coordinates":[44.80673,33.01564],"type":"Point"}
}