{
  "type": "Feature",
  "properties": {
    "gn:admin1_code":"10.0",
    "gn:admin2_code":"99063.0",
    "gn:asciiname":"Qaryat al Bazul",
    "gn:country_code":"IQ",
    "gn:dem":59,
    "gn:feature_class":"P",
    "gn:feature_code":"PPL",
    "gn:name":"Qaryat al B\u0101z\u016bl",
    "gn:population":0,
    "gn:timezone":"Asia/Baghdad",
    "iso:country":"IQ",
    "name:ara_x_preferred":[
        "\u0642\u0631\u064a\u0629 \u0627\u0644\u0628\u0627\u0632\u0648\u0644"
    ],
    "name:und_x_variant":[
        "Qaryat al B\u0101z\u016bl"
    ],
    "wof:name":"Qaryat al Bazul",
    "wof:placetype":"locality"
},
  "geometry": {"coordinates":[44.89545,33.98461],"type":"Point"}
}