{
  "type": "Feature",
  "properties": {
    "gn:admin1_code":"5.0",
    "gn:admin2_code":"97416.0",
    "gn:asciiname":"Darwishan Bichuk",
    "gn:country_code":"IQ",
    "gn:dem":693,
    "gn:feature_class":"P",
    "gn:feature_code":"PPL",
    "gn:name":"Darw\u012bsh\u0101n Bich\u016bk",
    "gn:population":0,
    "gn:timezone":"Asia/Baghdad",
    "iso:country":"IQ",
    "name:ara_x_preferred":[
        "\u062f\u0631\u0648\u064a\u0634\u0627\u0646 \u0628\u0686\u0648\u0643"
    ],
    "name:kur_x_preferred":[
        "Derw\u00eashan\u00ee Bichuk"
    ],
    "name:kur_x_variant":[
        "Derw\u00eashan",
        "\u062f\u06d5\u0631\u0648\u06ce\u0634\u0627\u0646\u0649 \u0628\u0686\u0648\u0643",
        "\u062f\u06d5\u0631\u0648\u06ce\u0634\u0627\u0646"
    ],
    "name:und_x_variant":[
        "Darw\u012bsh\u0101n Bich\u016bk",
        "Darw\u0113sh\u0101n-i Pich\u016bk",
        "Darw\u012bsh\u0101n Bij\u016bk",
        "Darweshan",
        "\u062f\u0631\u0648\u064a\u0634\u0627\u0646 \u0628\u062c\u0648\u0643"
    ],
    "wof:name":"Darwishan Bichuk",
    "wof:placetype":"locality"
},
  "geometry": {"coordinates":[45.15777,35.37284000000001],"type":"Point"}
}