{
  "type": "Feature",
  "properties": {
    "gn:admin1_code":"18.0",
    "gn:admin2_code":"6805736.0",
    "gn:asciiname":"'Uday Ramih",
    "gn:country_code":"IQ",
    "gn:dem":49,
    "gn:feature_class":"P",
    "gn:feature_code":"PPL",
    "gn:name":"\u2018Uday Rami\u1e29",
    "gn:population":0,
    "gn:timezone":"Asia/Baghdad",
    "iso:country":"IQ",
    "name:ara_x_preferred":[
        "\u0639\u062f\u064a \u0631\u0645\u062d"
    ],
    "name:und_x_variant":[
        "\u2018Uday Rami\u1e29"
    ],
    "wof:name":"'Uday Ramih",
    "wof:placetype":"locality"
},
  "geometry": {"coordinates":[44.12391,33.97833],"type":"Point"}
}