{
  "type": "Feature",
  "properties": {
    "gn:admin1_code":"16.0",
    "gn:admin2_code":"98197.0",
    "gn:asciiname":"'Ali Hasan",
    "gn:country_code":"IQ",
    "gn:dem":78,
    "gn:feature_class":"P",
    "gn:feature_code":"PPL",
    "gn:name":"\u2018Al\u012b \u1e28asan",
    "gn:population":0,
    "gn:timezone":"Asia/Baghdad",
    "iso:country":"IQ",
    "name:und_x_variant":[
        "\u2018Al\u012b \u1e28asan"
    ],
    "wof:name":"'Ali Hasan",
    "wof:placetype":"locality"
},
  "geometry": {"coordinates":[45.97889,33.12361],"type":"Point"}
}