{
  "type": "Feature",
  "properties": {
    "gn:admin1_code":"5.0",
    "gn:admin2_code":"9166594.0",
    "gn:asciiname":"Birkay",
    "gn:country_code":"IQ",
    "gn:dem":624,
    "gn:feature_class":"P",
    "gn:feature_code":"PPL",
    "gn:name":"B\u012brkay",
    "gn:population":0,
    "gn:timezone":"Asia/Baghdad",
    "iso:country":"IQ",
    "name:ara_x_preferred":[
        "B\u012brk\u012b"
    ],
    "name:ara_x_variant":[
        "\u0628\u064a\u0631\u0643\u064a"
    ],
    "name:kur_x_preferred":[
        "B\u00eerk\u00ea"
    ],
    "name:kur_x_variant":[
        "\u0628\u064a\u0631\u0643\u06ce"
    ],
    "name:und_x_variant":[
        "B\u012brk",
        "B\u012brkis",
        "B\u012brkay",
        "Birke"
    ],
    "wof:name":"Birkay",
    "wof:placetype":"locality"
},
  "geometry": {"coordinates":[45.69898,35.15879],"type":"Point"}
}