{
  "type": "Feature",
  "properties": {
    "iso:country":"IQ",
    "oa:elevation_ft":"719",
    "oa:type":"medium_airport",
    "woe:hierarchy":{
        "country_id":23424855,
        "county_id":55999964,
        "planet_id":1,
        "state_id":2345847
    },
    "wof:name":"Mosul Airport",
    "wof:placetype":"campus"
},
  "geometry": {"coordinates":[43.1475,36.305833333333],"type":"Point"}
}