{
  "type": "Feature",
  "properties": {
    "iso:country":"IQ",
    "name:ara_x_preferred":[
        "\u0645\u0637\u0627\u0631 \u0627\u0644\u0645\u0648\u0635\u0644 \u0627\u0644\u062f\u0648\u0644\u064a"
    ],
    "name:ckb_x_preferred":[
        "\u0641\u0695\u06c6\u06a9\u06d5\u062e\u0627\u0646\u06d5\u06cc \u0646\u06ce\u0648\u062f\u06d5\u0648\u06b5\u06d5\u062a\u06cc\u06cc \u0645\u0648\u0648\u0633\u06b5"
    ],
    "name:cym_x_preferred":[
        "Maes Awyr Rhyngwladol Mosul"
    ],
    "name:deu_x_preferred":[
        "Flughafen Mosul"
    ],
    "name:eng_x_variant":[
        "OSM",
        "ORBM"
    ],
    "name:fas_x_preferred":[
        "\u0641\u0631\u0648\u062f\u06af\u0627\u0647 \u0628\u06cc\u0646\u200c\u0627\u0644\u0645\u0644\u0644\u06cc \u0645\u0648\u0635\u0644"
    ],
    "name:heb_x_preferred":[
        "\u05e0\u05de\u05dc \u05d4\u05ea\u05e2\u05d5\u05e4\u05d4 \u05d4\u05d1\u05d9\u05e0\u05dc\u05d0\u05d5\u05de\u05d9 \u05de\u05d5\u05e1\u05d5\u05dc"
    ],
    "name:jpn_x_preferred":[
        "\u30e2\u30fc\u30b9\u30eb\u56fd\u969b\u7a7a\u6e2f"
    ],
    "name:pol_x_preferred":[
        "Port lotniczy Mosul"
    ],
    "name:ron_x_preferred":[
        "Aeroportul Interna\u021bional Mosul"
    ],
    "name:rus_x_preferred":[
        "\u041c\u043e\u0441\u0443\u043b"
    ],
    "name:tgk_x_preferred":[
        "\u0424\u0443\u0440\u0443\u0434\u0433\u043e\u04b3\u0438 \u0431\u0438\u043d\u200c\u0430\u043b\u043c\u0438\u043b\u0430\u043b\u04e3 \u043c\u0443\u0432\u0441\u0443\u043b"
    ],
    "name:tur_x_preferred":[
        "Musul Havaliman\u0131"
    ],
    "name:zho_x_preferred":[
        "\u6469\u8607\u723e\u570b\u969b\u6a5f\u5834"
    ],
    "oa:elevation_ft":"719",
    "oa:type":"medium_airport",
    "woe:hierarchy":{
        "country_id":23424855,
        "county_id":55999964,
        "planet_id":1,
        "state_id":2345847
    },
    "wof:name":"Mosul Airport",
    "wof:placetype":"campus"
},
  "geometry": {"coordinates":[43.1475,36.305833],"type":"Point"}
}