{
  "type": "Feature",
  "properties": {
    "gn:admin1_code":"15.0",
    "gn:admin2_code":"9166649.0",
    "gn:asciiname":"Qaryat Aknitrah",
    "gn:country_code":"IQ",
    "gn:dem":222,
    "gn:feature_class":"P",
    "gn:feature_code":"PPL",
    "gn:name":"Qaryat Akn\u012b\u0163rah",
    "gn:population":0,
    "gn:timezone":"Asia/Baghdad",
    "iso:country":"IQ",
    "name:ara_x_preferred":[
        "\u0642\u0631\u064a\u0629 \u0627\u0643\u0646\u064a\u0637\u0631\u0629"
    ],
    "name:und_x_variant":[
        "Qaryat Agn\u012b\u0163rah",
        "\u0642\u0631\u064a\u0629 \u0627\u06af\u0646\u064a\u0637\u0631\u0629",
        "Qaryat Akn\u012b\u0163rah"
    ],
    "wof:name":"Qaryat Aknitrah",
    "wof:placetype":"locality"
},
  "geometry": {"coordinates":[43.18024000000001,36.23939],"type":"Point"}
}