{
  "type": "Feature",
  "properties": {
    "gn:admin1_code":"5.0",
    "gn:admin2_code":"97416.0",
    "gn:asciiname":"Shaykh Muhammad al `Ulya",
    "gn:country_code":"IQ",
    "gn:dem":799,
    "gn:feature_class":"P",
    "gn:feature_code":"PPLL",
    "gn:name":"Shaykh Mu\u1e29ammad al \u2018Uly\u0101",
    "gn:population":0,
    "gn:timezone":"Asia/Baghdad",
    "iso:country":"IQ",
    "name:ara_x_preferred":[
        "\u0634\u064a\u062e \u0645\u062d\u0645\u062f \u0627\u0644\u0639\u0644\u064a\u0627"
    ],
    "name:und_x_variant":[
        "Shaykh Mu\u1e29ammad al \u2018Uly\u0101"
    ],
    "wof:name":"Shaykh Muhammad al `Ulya",
    "wof:placetype":"locality"
},
  "geometry": {"coordinates":[44.83541,35.32346],"type":"Point"}
}