{
  "type": "Feature",
  "properties": {
    "gn:admin1_code":"6.0",
    "gn:admin2_code":"99358.0",
    "gn:asciiname":"Qaryat Bukan",
    "gn:country_code":"IQ",
    "gn:dem":24,
    "gn:feature_class":"P",
    "gn:feature_code":"PPL",
    "gn:name":"Qaryat Buk\u0101n",
    "gn:population":0,
    "gn:timezone":"Asia/Baghdad",
    "iso:country":"IQ",
    "name:ara_x_preferred":[
        "\u0642\u0631\u064a\u0629 \u0628\u0643\u0627\u0646"
    ],
    "name:und_x_variant":[
        "Qaryat Buk\u0101n"
    ],
    "wof:name":"Qaryat Bukan",
    "wof:placetype":"locality"
},
  "geometry": {"coordinates":[44.88045,32.31068],"type":"Point"}
}