{
  "type": "Feature",
  "properties": {
    "gn:admin1_code":"14.0",
    "gn:admin2_code":"9166562.0",
    "gn:asciiname":"Tall Abu Dhahab",
    "gn:country_code":"IQ",
    "gn:dem":8,
    "gn:feature_class":"P",
    "gn:feature_code":"PPL",
    "gn:name":"Tall Ab\u016b Dhahab",
    "gn:population":0,
    "gn:timezone":"Asia/Baghdad",
    "iso:country":"IQ",
    "name:ara_x_preferred":[
        "\u062a\u0644 \u0627\u0628\u0648 \u0630\u0647\u0628"
    ],
    "name:und_x_variant":[
        "Tall Ab\u016b Dhahab"
    ],
    "wof:name":"Tall Abu Dhahab",
    "wof:placetype":"locality"
},
  "geometry": {"coordinates":[46.9122,31.63005],"type":"Point"}
}