{
  "type": "Feature",
  "properties": {
    "gn:admin1_code":"12.0",
    "gn:admin2_code":"99345.0",
    "gn:asciiname":"Qaryat as Salamiyah al Gharbiyah",
    "gn:country_code":"IQ",
    "gn:dem":35,
    "gn:feature_class":"P",
    "gn:feature_code":"PPL",
    "gn:name":"Qaryat as Sal\u0101m\u012byah al Gharb\u012byah",
    "gn:population":0,
    "gn:timezone":"Asia/Baghdad",
    "iso:country":"IQ",
    "name:ara_x_preferred":[
        "\u0642\u0631\u064a\u0629 \u0627\u0644\u0633\u0644\u0627\u0645\u064a\u0629 \u0627\u0644\u063a\u0631\u0628\u064a\u0629"
    ],
    "name:und_x_variant":[
        "Qaryat as Sal\u0101m\u012byah al Gharb\u012byah"
    ],
    "wof:name":"Qaryat as Salamiyah al Gharbiyah",
    "wof:placetype":"locality"
},
  "geometry": {"coordinates":[44.18829,32.65673],"type":"Point"}
}