{
  "type": "Feature",
  "properties": {
    "gn:admin1_code":"9.0",
    "gn:admin2_code":"98855.0",
    "gn:asciiname":"'Atshan",
    "gn:country_code":"IQ",
    "gn:dem":6,
    "gn:feature_class":"P",
    "gn:feature_code":"PPL",
    "gn:name":"\u2018A\u0163sh\u0101n",
    "gn:population":0,
    "gn:timezone":"Asia/Baghdad",
    "iso:country":"IQ",
    "name:ara_x_preferred":[
        "\u0639\u0637\u0634\u0627\u0646"
    ],
    "name:ara_x_variant":[
        "\u2018A\u0163sh\u0101n"
    ],
    "wof:name":"'Atshan",
    "wof:placetype":"locality"
},
  "geometry": {"coordinates":[45.95272,31.10111],"type":"Point"}
}