{
  "type": "Feature",
  "properties": {
    "gn:admin1_code":"7.0",
    "gn:admin2_code":"99101.0",
    "gn:asciiname":"Sadum 'Abd",
    "gn:country_code":"IQ",
    "gn:dem":35,
    "gn:feature_class":"P",
    "gn:feature_code":"PPL",
    "gn:name":"Sad\u016bm \u2018Abd",
    "gn:population":0,
    "gn:timezone":"Asia/Baghdad",
    "iso:country":"IQ",
    "name:ara_x_preferred":[
        "\u0633\u062f\u0648\u0645 \u0639\u0628\u062f"
    ],
    "name:und_x_variant":[
        "Sad\u016bm \u2018Abd"
    ],
    "wof:name":"Sadum 'Abd",
    "wof:placetype":"locality"
},
  "geometry": {"coordinates":[44.48046,33.17024],"type":"Point"}
}