{
  "type": "Feature",
  "properties": {
    "gn:admin1_code":"18.0",
    "gn:admin2_code":"91594.0",
    "gn:asciiname":"Hayim Jasim Mut'ab",
    "gn:country_code":"IQ",
    "gn:dem":97,
    "gn:feature_class":"P",
    "gn:feature_code":"PPL",
    "gn:name":"\u1e28\u0101yim J\u0101sim Mut\u2018ab",
    "gn:population":0,
    "gn:timezone":"Asia/Baghdad",
    "iso:country":"IQ",
    "name:ara_x_preferred":[
        "\u062d\u0627\u064a\u0645 \u062c\u0627\u0633\u0645 \u0645\u062a\u0639\u0628"
    ],
    "name:und_x_variant":[
        "\u1e28\u0101yim J\u0101sim Mut\u2018ab"
    ],
    "wof:name":"Hayim Jasim Mut'ab",
    "wof:placetype":"locality"
},
  "geometry": {"coordinates":[43.49503,34.20845],"type":"Point"}
}