{
  "type": "Feature",
  "properties": {
    "gn:admin1_code":"12.0",
    "gn:admin2_code":"99345.0",
    "gn:asciiname":"Nahiyat ar Rajibah",
    "gn:country_code":"IQ",
    "gn:dem":32,
    "gn:feature_class":"P",
    "gn:feature_code":"PPL",
    "gn:name":"N\u0101\u1e29\u012byat ar Raj\u012bbah",
    "gn:population":0,
    "gn:timezone":"Asia/Baghdad",
    "iso:country":"IQ",
    "name:und_x_variant":[
        "N\u0101\u1e29\u012byat ar Raj\u012bbah",
        "Qaryat ar Raj\u012bbah",
        "N\u0101\u1e29iyat ar Raj\u012bbah",
        "\u0646\u0627\u062d\u064a\u0629 \u0627\u0644\u0631\u062c\u064a\u0628\u0629",
        "Ar Raj\u012bbah",
        "\u0627\u0644\u0631\u062c\u064a\u0628\u0629"
    ],
    "wof:name":"Nahiyat ar Rajibah",
    "wof:placetype":"locality"
},
  "geometry": {"coordinates":[44.19984,32.50952],"type":"Point"}
}