{
  "type": "Feature",
  "properties": {
    "gn:admin1_code":"11.0",
    "gn:admin2_code":"9166592.0",
    "gn:asciiname":"Tale Jar",
    "gn:country_code":"IQ",
    "gn:dem":836,
    "gn:feature_class":"P",
    "gn:feature_code":"PPL",
    "gn:name":"Ta\u0142e Ja\u1e5f",
    "gn:population":0,
    "gn:timezone":"Asia/Baghdad",
    "iso:country":"IQ",
    "name:kur_x_preferred":[
        "Ta\u0142e Ja\u1e5f"
    ],
    "name:kur_x_variant":[
        "\u062a\u0627\u06b5\u06d5 \u062c\u0627\u0695"
    ],
    "name:und_x_variant":[
        "Tara Jarr"
    ],
    "wof:name":"Tale Jar",
    "wof:placetype":"locality"
},
  "geometry": {"coordinates":[44.57844,36.87089],"type":"Point"}
}