{
  "type": "Feature",
  "properties": {
    "gn:admin1_code":"6.0",
    "gn:admin2_code":"99358.0",
    "gn:asciiname":"Kazim al Ghadir",
    "gn:country_code":"IQ",
    "gn:dem":27,
    "gn:feature_class":"P",
    "gn:feature_code":"PPL",
    "gn:name":"K\u0101z\u0327im al Ghad\u012br",
    "gn:population":0,
    "gn:timezone":"Asia/Baghdad",
    "iso:country":"IQ",
    "name:ara_x_preferred":[
        "\u0643\u0627\u0638\u0645 \u0627\u0644\u063a\u062f\u064a\u0631"
    ],
    "name:und_x_variant":[
        "K\u0101z\u0327im al Ghad\u012br"
    ],
    "wof:name":"Kazim al Ghadir",
    "wof:placetype":"locality"
},
  "geometry": {"coordinates":[44.84373,32.38345],"type":"Point"}
}