{
  "type": "Feature",
  "properties": {
    "gn:admin1_code":"15.0",
    "gn:admin2_code":"9166649.0",
    "gn:asciiname":"Al 'Asraj",
    "gn:country_code":"IQ",
    "gn:dem":217,
    "gn:feature_class":"P",
    "gn:feature_code":"PPL",
    "gn:name":"Al \u2018Asraj",
    "gn:population":0,
    "gn:timezone":"Asia/Baghdad",
    "iso:country":"IQ",
    "name:ara_x_preferred":[
        "\u0627\u0644\u0639\u0633\u0631\u062c"
    ],
    "name:und_x_variant":[
        "Al \u2018Asraj"
    ],
    "wof:name":"Al 'Asraj",
    "wof:placetype":"locality"
},
  "geometry": {"coordinates":[42.72189,35.90494],"type":"Point"}
}