{
  "type": "Feature",
  "properties": {
    "gn:admin1_code":"5.0",
    "gn:admin2_code":"97416.0",
    "gn:asciiname":"Gurgayi Siwah Sur",
    "gn:country_code":"IQ",
    "gn:dem":698,
    "gn:feature_class":"P",
    "gn:feature_code":"PPL",
    "gn:name":"G\u016brgay\u012b S\u012bwah S\u016br",
    "gn:population":0,
    "gn:timezone":"Asia/Baghdad",
    "iso:country":"IQ",
    "name:ara_x_preferred":[
        "\u06af\u0648\u0631\u06af\u064a\u064a \u0633\u064a\u0648\u0647 \u0633\u0648\u0631"
    ],
    "name:und_x_variant":[
        "K\u016brk\u012b Mu\u1e29ammad Z\u0101r\u012b",
        "Gurgar Muhammad Z\u0101ri",
        "Gurgai Muhammad Z\u0101r",
        "G\u016brgay\u012b S\u012bwah S\u016br",
        "G\u016brg\u0101y Mu\u1e29ammad Z\u0101r\u012b"
    ],
    "wof:name":"Gurgayi Siwah Sur",
    "wof:placetype":"locality"
},
  "geometry": {"coordinates":[44.85017,35.5671],"type":"Point"}
}