{
  "type": "Feature",
  "properties": {
    "gn:admin1_code":"15.0",
    "gn:admin2_code":"9166620.0",
    "gn:asciiname":"Al Buthah",
    "gn:country_code":"IQ",
    "gn:dem":230,
    "gn:feature_class":"P",
    "gn:feature_code":"PPL",
    "gn:name":"Al B\u016bthah",
    "gn:population":0,
    "gn:timezone":"Asia/Baghdad",
    "iso:country":"IQ",
    "name:ara_x_preferred":[
        "\u0627\u0644\u0628\u0648\u062b\u0629"
    ],
    "name:und_x_variant":[
        "Al B\u016bthah"
    ],
    "wof:name":"Al Buthah",
    "wof:placetype":"locality"
},
  "geometry": {"coordinates":[42.46749000000001,36.03184],"type":"Point"}
}