{
  "type": "Feature",
  "properties": {
    "gn:admin1_code":"10.0",
    "gn:admin2_code":"97988.0",
    "gn:asciiname":"Qaryat Jayzan Thuwaylab",
    "gn:country_code":"IQ",
    "gn:dem":43,
    "gn:feature_class":"P",
    "gn:feature_code":"PPL",
    "gn:name":"Qaryat Jayz\u0101n Thuwaylab",
    "gn:population":0,
    "gn:timezone":"Asia/Baghdad",
    "iso:country":"IQ",
    "name:ara_x_preferred":[
        "\u0642\u0631\u064a\u0629 \u062c\u064a\u0632\u0627\u0646 \u062b\u0648\u064a\u0644\u0628"
    ],
    "name:und_x_variant":[
        "Qaryat Jayz\u0101n Thuwaylab"
    ],
    "wof:name":"Qaryat Jayzan Thuwaylab",
    "wof:placetype":"locality"
},
  "geometry": {"coordinates":[44.45045,33.79414000000001],"type":"Point"}
}