{
  "type": "Feature",
  "properties": {
    "gn:admin1_code":"18.0",
    "gn:admin2_code":"6783103.0",
    "gn:asciiname":"'Arab 'Alwan Salim",
    "gn:country_code":"IQ",
    "gn:dem":53,
    "gn:feature_class":"P",
    "gn:feature_code":"PPL",
    "gn:name":"\u2018Arab \u2018Alw\u0101n S\u0101lim",
    "gn:population":0,
    "gn:timezone":"Asia/Baghdad",
    "iso:country":"IQ",
    "name:ara_x_preferred":[
        "\u0639\u0631\u0628 \u0639\u0644\u0648\u0627\u0646 \u0633\u0627\u0644\u0645"
    ],
    "name:und_x_variant":[
        "\u2018Arab \u2018Alw\u0101n S\u0101lim"
    ],
    "wof:name":"'Arab 'Alwan Salim",
    "wof:placetype":"locality"
},
  "geometry": {"coordinates":[44.04408,34.09145],"type":"Point"}
}