{
  "type": "Feature",
  "properties": {
    "gn:admin1_code":"11.0",
    "gn:admin2_code":"95444.0",
    "gn:asciiname":"Kawcha Biyas",
    "gn:country_code":"IQ",
    "gn:dem":372,
    "gn:feature_class":"P",
    "gn:feature_code":"PPL",
    "gn:name":"Kawch\u0101 Biy\u0101s",
    "gn:population":0,
    "gn:timezone":"Asia/Baghdad",
    "iso:country":"IQ",
    "name:ara_x_preferred":[
        "\u0643\u0648\u0686\u0627 \u0628\u064a\u0627\u0633"
    ],
    "name:kur_x_preferred":[
        "Qoche B\u0142bas"
    ],
    "name:kur_x_variant":[
        "\u0642\u06c6\u0686\u06d5 \u0628\u06b5\u0628\u0627\u0633"
    ],
    "name:und_x_variant":[
        "Qojabilb\u0101s",
        "Q\u016bjah Bilb\u0101z",
        "Qocha Blbas",
        "Kawch\u0101 Biy\u0101s"
    ],
    "wof:name":"Kawcha Biyas",
    "wof:placetype":"locality"
},
  "geometry": {"coordinates":[43.99075,36.05183],"type":"Point"}
}