{
  "type": "Feature",
  "properties": {
    "gn:admin1_code":"7.0",
    "gn:admin2_code":"99101.0",
    "gn:asciiname":"'Arab Salman 'Abbas",
    "gn:country_code":"IQ",
    "gn:dem":31,
    "gn:feature_class":"P",
    "gn:feature_code":"PPL",
    "gn:name":"\u2018Arab Salm\u0101n \u2018Abb\u0101s",
    "gn:population":0,
    "gn:timezone":"Asia/Baghdad",
    "iso:country":"IQ",
    "name:ara_x_preferred":[
        "\u0639\u0631\u0628 \u0633\u0644\u0645\u0627\u0646 \u0639\u0628\u0627\u0633"
    ],
    "name:und_x_variant":[
        "\u2018Arab Salm\u0101n \u2018Abb\u0101s"
    ],
    "wof:name":"'Arab Salman 'Abbas",
    "wof:placetype":"locality"
},
  "geometry": {"coordinates":[44.4835,32.92427],"type":"Point"}
}