{
  "type": "Feature",
  "properties": {
    "gn:admin1_code":"11.0",
    "gn:admin2_code":"9166586.0",
    "gn:asciiname":"Zilki",
    "gn:country_code":"IQ",
    "gn:dem":1693,
    "gn:feature_class":"P",
    "gn:feature_code":"PPL",
    "gn:name":"Zilk\u012b",
    "gn:population":0,
    "gn:timezone":"Asia/Baghdad",
    "iso:country":"IQ",
    "name:ara_x_preferred":[
        "Zilk\u012b"
    ],
    "name:ara_x_variant":[
        "\u0632\u0644\u0643\u064a \u0648 \u062c\u0648\u0645\u0629",
        "\u0632\u0644\u0643\u064a"
    ],
    "name:kur_x_preferred":[
        "Zi\u0142ch\u00ea"
    ],
    "name:kur_x_variant":[
        "\u0632\u06b5\u0686\u06ce"
    ],
    "name:und_x_variant":[
        "\u0632\u0644\u0643\u064a",
        "Zilk\u012b Wa J\u016bmah"
    ],
    "wof:name":"Zilki",
    "wof:placetype":"locality"
},
  "geometry": {"coordinates":[44.923,36.49899],"type":"Point"}
}