{
  "type": "Feature",
  "properties": {
    "gn:admin1_code":"8.0",
    "gn:admin2_code":"9166607.0",
    "gn:asciiname":"Drustike",
    "gn:country_code":"IQ",
    "gn:dem":608,
    "gn:feature_class":"P",
    "gn:feature_code":"PPL",
    "gn:name":"Drustike",
    "gn:population":0,
    "gn:timezone":"Asia/Baghdad",
    "iso:country":"IQ",
    "name:ara_x_preferred":[
        "\u062f\u0648\u0633\u062a\u0643\u0629"
    ],
    "name:kur_x_preferred":[
        "Drustike"
    ],
    "name:kur_x_variant":[
        "\u062f\u0631\u0648\u0633\u062a\u0643\u06d5"
    ],
    "name:und_x_variant":[
        "D\u014dstika",
        "Drustka",
        "Drustika",
        "D\u016bstikah"
    ],
    "wof:name":"Drustike",
    "wof:placetype":"locality"
},
  "geometry": {"coordinates":[43.07841,36.8052],"type":"Point"}
}