{
  "type": "Feature",
  "properties": {
    "gn:admin1_code":"5.0",
    "gn:admin2_code":"9166684.0",
    "gn:asciiname":"Baraleh",
    "gn:country_code":"IQ",
    "gn:dem":1284,
    "gn:feature_class":"P",
    "gn:feature_code":"PPL",
    "gn:name":"Bar\u0101leh",
    "gn:population":0,
    "gn:timezone":"Asia/Baghdad",
    "iso:country":"IQ",
    "name:fas_x_preferred":[
        "\u0628\u0631\u0627\u0644\u0647"
    ],
    "wof:name":"Baraleh",
    "wof:placetype":"locality"
},
  "geometry": {"coordinates":[46.0241,35.7316],"type":"Point"}
}