{
  "type": "Feature",
  "properties": {
    "gn:admin1_code":"11.0",
    "gn:admin2_code":"95444.0",
    "gn:asciiname":"Kuran",
    "gn:country_code":"IQ",
    "gn:dem":415,
    "gn:feature_class":"P",
    "gn:feature_code":"PPL",
    "gn:name":"K\u016br\u0101n",
    "gn:population":0,
    "gn:timezone":"Asia/Baghdad",
    "iso:country":"IQ",
    "name:ara_x_preferred":[
        "\u0643\u0648\u0631\u0627\u0646"
    ],
    "name:ara_x_variant":[
        "K\u016br\u0101n"
    ],
    "wof:name":"Kuran",
    "wof:placetype":"locality"
},
  "geometry": {"coordinates":[43.99888,36.22052],"type":"Point"}
}