{
  "type": "Feature",
  "properties": {
    "gn:admin1_code":"15.0",
    "gn:admin2_code":"98820.0",
    "gn:asciiname":"Nazrawah",
    "gn:country_code":"IQ",
    "gn:dem":365,
    "gn:feature_class":"P",
    "gn:feature_code":"PPL",
    "gn:name":"Nazr\u0101wah",
    "gn:population":0,
    "gn:timezone":"Asia/Baghdad",
    "iso:country":"IQ",
    "name:ara_x_preferred":[
        "\u0646\u0632\u0631\u0627\u0648\u0647"
    ],
    "name:kur_x_preferred":[
        "Mizrawa"
    ],
    "name:kur_x_variant":[
        "\u0645\u0632\u0631\u0627\u0648\u0627",
        "Nezrawe",
        "\u0646\u06d5\u0632\u0631\u0627\u0648\u0647"
    ],
    "name:und_x_variant":[
        "Mizr\u0101wa",
        "Nazr\u0101wah",
        "Nazrawa"
    ],
    "wof:name":"Nazrawah",
    "wof:placetype":"locality"
},
  "geometry": {"coordinates":[43.61986,36.55907],"type":"Point"}
}