{
  "type": "Feature",
  "properties": {
    "gn:admin1_code":"9.0",
    "gn:admin2_code":"98700.0",
    "gn:asciiname":"Suwayj ash Shakban",
    "gn:country_code":"IQ",
    "gn:dem":11,
    "gn:feature_class":"P",
    "gn:feature_code":"PPL",
    "gn:name":"Suwayj ash Shakb\u0101n",
    "gn:population":0,
    "gn:timezone":"Asia/Baghdad",
    "iso:country":"IQ",
    "name:ara_x_preferred":[
        "\u0633\u0648\u064a\u062c \u0627\u0644\u0634\u0643\u0628\u0627\u0646"
    ],
    "name:und_x_variant":[
        "Suwaij ash Saqban",
        "Suwayj \u015eakb\u0101n",
        "Suwaik esh Shakban",
        "Suwayk ash Shakb\u0101n",
        "Suwayq a\u015f \u015euqb\u0101n",
        "Suwayj ash Shakb\u0101n"
    ],
    "wof:name":"Suwayj ash Shakban",
    "wof:placetype":"locality"
},
  "geometry": {"coordinates":[46.11736,31.53423],"type":"Point"}
}