{
  "type": "Feature",
  "properties": {
    "gn:admin1_code":"10.0",
    "gn:admin2_code":"9166680.0",
    "gn:asciiname":"Gharah Ghul",
    "gn:country_code":"IQ",
    "gn:dem":32,
    "gn:feature_class":"P",
    "gn:feature_code":"PPL",
    "gn:name":"Gharah Gh\u016bl",
    "gn:population":0,
    "gn:timezone":"Asia/Baghdad",
    "iso:country":"IQ",
    "name:und_x_variant":[
        "Gharah Gh\u016bl"
    ],
    "wof:name":"Gharah Ghul",
    "wof:placetype":"locality"
},
  "geometry": {"coordinates":[45.23333,33.46667],"type":"Point"}
}