{
  "type": "Feature",
  "properties": {
    "gn:admin1_code":"15.0",
    "gn:admin2_code":"98820.0",
    "gn:asciiname":"Barewan Kichke",
    "gn:country_code":"IQ",
    "gn:dem":357,
    "gn:feature_class":"P",
    "gn:feature_code":"PPL",
    "gn:name":"Barewan Kichke",
    "gn:population":0,
    "gn:timezone":"Asia/Baghdad",
    "iso:country":"IQ",
    "name:kur_x_preferred":[
        "Barewan Kichke"
    ],
    "name:kur_x_variant":[
        "\u0628\u0627\u0631\u06d5\u0648\u0627\u0646 \u0643\u0686\u0643\u06d5",
        "Behrawe Nw\u00ea",
        "\u0628\u06d5\u06be\u0631\u0627\u0648\u06d5 \u0646\u0648\u06ce"
    ],
    "name:und_x_variant":[
        "Bahrawa New"
    ],
    "wof:name":"Barewan Kichke",
    "wof:placetype":"locality"
},
  "geometry": {"coordinates":[43.79112,36.51788],"type":"Point"}
}