{
  "type": "Feature",
  "properties": {
    "gn:admin1_code":"9.0",
    "gn:admin2_code":"99185.0",
    "gn:asciiname":"Madar",
    "gn:country_code":"IQ",
    "gn:dem":2,
    "gn:feature_class":"P",
    "gn:feature_code":"PPL",
    "gn:name":"Mad\u0101r",
    "gn:population":0,
    "gn:timezone":"Asia/Baghdad",
    "iso:country":"IQ",
    "name:ceb_x_preferred":[
        "Madar"
    ],
    "name:deu_x_preferred":[
        "Madar"
    ],
    "name:fra_x_preferred":[
        "Madar"
    ],
    "name:rus_x_preferred":[
        "\u041c\u0430\u0434\u0430\u0440"
    ],
    "name:slk_x_preferred":[
        "Madar"
    ],
    "name:swe_x_preferred":[
        "Madar"
    ],
    "name:und_x_variant":[
        "Midar",
        "Mad\u0101r"
    ],
    "wof:name":"Madar",
    "wof:placetype":"locality"
},
  "geometry": {"coordinates":[46.95,30.95],"type":"Point"}
}