{
  "type": "Feature",
  "properties": {
    "gn:admin1_code":"11.0",
    "gn:admin2_code":"95444.0",
    "gn:asciiname":"Awmir Mamakah",
    "gn:country_code":"IQ",
    "gn:dem":314,
    "gn:feature_class":"P",
    "gn:feature_code":"PPL",
    "gn:name":"Awm\u012br M\u0101makah",
    "gn:population":0,
    "gn:timezone":"Asia/Baghdad",
    "iso:country":"IQ",
    "name:ara_x_preferred":[
        "\u0623\u0648\u0645\u064a\u0631 \u0645\u0627\u0645\u0643\u0629"
    ],
    "name:kur_x_preferred":[
        "Omer Mamke"
    ],
    "name:kur_x_variant":[
        "\u0626\u06c6\u0645\u06d5\u0631 \u0645\u0627\u0645\u0643\u06d5"
    ],
    "name:und_x_variant":[
        "Omar Mamka",
        "Awm\u012br M\u0101makah"
    ],
    "wof:name":"Awmir Mamakah",
    "wof:placetype":"locality"
},
  "geometry": {"coordinates":[44.06901,35.86384],"type":"Point"}
}