{
  "type": "Feature",
  "properties": {
    "gn:admin1_code":"5.0",
    "gn:admin2_code":"92051.0",
    "gn:asciiname":"Side Feqire",
    "gn:country_code":"IQ",
    "gn:dem":559,
    "gn:feature_class":"P",
    "gn:feature_code":"PPL",
    "gn:name":"S\u00eede Feq\u00eere",
    "gn:population":0,
    "gn:timezone":"Asia/Baghdad",
    "iso:country":"IQ",
    "name:kur_x_preferred":[
        "S\u00eede Feq\u00eere"
    ],
    "name:kur_x_variant":[
        "\u0633\u064a\u062f\u06d5 \u0641\u06d5\u0642\u064a\u0631\u06d5"
    ],
    "name:und_x_variant":[
        "Saida Faqira"
    ],
    "wof:name":"Side Feqire",
    "wof:placetype":"locality"
},
  "geometry": {"coordinates":[44.90675,36.25246],"type":"Point"}
}