{
  "type": "Feature",
  "properties": {
    "gn:admin1_code":"10.0",
    "gn:admin2_code":"9166680.0",
    "gn:asciiname":"Sharstan",
    "gn:country_code":"IQ",
    "gn:dem":77,
    "gn:feature_class":"P",
    "gn:feature_code":"PPL",
    "gn:name":"Sh\u0101rst\u0101n",
    "gn:population":0,
    "gn:timezone":"Asia/Baghdad",
    "iso:country":"IQ",
    "name:ara_x_preferred":[
        "Sh\u0101rst\u0101n"
    ],
    "wof:name":"Sharstan",
    "wof:placetype":"locality"
},
  "geometry": {"coordinates":[45.75824,33.46175],"type":"Point"}
}