{
  "type": "Feature",
  "properties": {
    "gn:admin1_code":"5.0",
    "gn:admin2_code":"9166600.0",
    "gn:asciiname":"Jirjah Qala",
    "gn:country_code":"IQ",
    "gn:dem":923,
    "gn:feature_class":"P",
    "gn:feature_code":"PPL",
    "gn:name":"Jirjah Qal\u0101",
    "gn:population":0,
    "gn:timezone":"Asia/Baghdad",
    "iso:country":"IQ",
    "name:ara_x_preferred":[
        "\u062c\u0631\u062c\u0647 \u0642\u0644\u0627"
    ],
    "name:kur_x_preferred":[
        "Chirche Qe\u0142a"
    ],
    "name:kur_x_variant":[
        "\u0686\u0631\u0686\u06d5 \u0642\u06d5\u06b5\u0627"
    ],
    "name:und_x_variant":[
        "Ch\u012brghah Qal\u2018ah",
        "Chirgha Qal\u2018a",
        "Ch\u012bchah Qal\u2018ah",
        "Jirjah Qal\u0101",
        "Chirchaqal\u0101",
        "Chircha Qala"
    ],
    "wof:name":"Jirjah Qala",
    "wof:placetype":"locality"
},
  "geometry": {"coordinates":[45.52141,35.10977],"type":"Point"}
}