{
  "type": "Feature",
  "properties": {
    "gn:admin1_code":"11.0",
    "gn:admin2_code":"93817.0",
    "gn:asciiname":"S`dawe",
    "gn:country_code":"IQ",
    "gn:dem":284,
    "gn:feature_class":"P",
    "gn:feature_code":"PPL",
    "gn:name":"S\u2018dawe",
    "gn:population":0,
    "gn:timezone":"Asia/Baghdad",
    "iso:country":"IQ",
    "name:ara_x_preferred":[
        "\u0633\u0639\u062f\u0627\u0648\u0629"
    ],
    "name:ara_x_variant":[
        "\u0633\u062f\u0627\u0648\u0629"
    ],
    "name:kur_x_preferred":[
        "S\u2018dawe"
    ],
    "name:kur_x_variant":[
        "\u0633\u0639\u062f\u0627\u0648\u06d5"
    ],
    "name:und_x_variant":[
        "S\u0101d\u0101wa",
        "S\u0101d\u0101wah",
        "Sidawa",
        "Sa\u2018d\u0101wah",
        "Sad\u0101wah"
    ],
    "wof:name":"S`dawe",
    "wof:placetype":"locality"
},
  "geometry": {"coordinates":[43.75042,36.1005],"type":"Point"}
}