{
  "type": "Feature",
  "properties": {
    "gn:admin1_code":"11.0",
    "gn:admin2_code":"9166534.0",
    "gn:asciiname":"Bile",
    "gn:country_code":"IQ",
    "gn:dem":466,
    "gn:feature_class":"P",
    "gn:feature_code":"PPL",
    "gn:name":"Bile",
    "gn:population":0,
    "gn:timezone":"Asia/Baghdad",
    "iso:country":"IQ",
    "name:ara_x_preferred":[
        "\u0628\u0644\u0647 \u0627\u0644\u0633\u0641\u0644\u0649"
    ],
    "name:kur_x_preferred":[
        "Bile"
    ],
    "name:kur_x_variant":[
        "\u0628\u0644\u0647"
    ],
    "name:und_x_variant":[
        "Bila Zh\u0113n",
        "Bila Zh\u0113r\u012b",
        "Bilah as Sufl\u00e1",
        "Bilah Zayr\u012b",
        "\u0628\u0644\u0647 \u0632\u064a\u0631\u064a",
        "Bila"
    ],
    "wof:name":"Bile",
    "wof:placetype":"locality"
},
  "geometry": {"coordinates":[44.07555,36.86397],"type":"Point"}
}