{
  "type": "Feature",
  "properties": {
    "gn:admin1_code":"6.0",
    "gn:admin2_code":"99358.0",
    "gn:asciiname":"Mushir al 'Umar",
    "gn:country_code":"IQ",
    "gn:dem":26,
    "gn:feature_class":"P",
    "gn:feature_code":"PPL",
    "gn:name":"Mush\u012br al \u2018Umar",
    "gn:population":0,
    "gn:timezone":"Asia/Baghdad",
    "iso:country":"IQ",
    "name:ara_x_preferred":[
        "\u0645\u0634\u064a\u0631 \u0627\u0644\u0639\u0645\u0631"
    ],
    "name:und_x_variant":[
        "Mush\u012bn al \u2018Umar",
        "Qaryat Mush\u012br al \u2018Umar",
        "\u0642\u0631\u064a\u0629 \u0645\u0634\u064a\u0631 \u0639\u0645\u0631",
        "Mush\u012br al \u2018Umar"
    ],
    "wof:name":"Mushir al 'Umar",
    "wof:placetype":"locality"
},
  "geometry": {"coordinates":[44.6553,32.21323],"type":"Point"}
}