{
  "type": "Feature",
  "properties": {
    "gn:admin1_code":"5.0",
    "gn:admin2_code":"9166596.0",
    "gn:asciiname":"Kharluk Khuwaru",
    "gn:country_code":"IQ",
    "gn:dem":786,
    "gn:feature_class":"P",
    "gn:feature_code":"PPL",
    "gn:name":"Kharl\u016bk Khuw\u0101r\u016b",
    "gn:population":0,
    "gn:timezone":"Asia/Baghdad",
    "iso:country":"IQ",
    "name:ara_x_preferred":[
        "\u062e\u0631\u0644\u0648\u0643 \u062e\u0648\u0627\u0631\u0648"
    ],
    "name:und_x_variant":[
        "Kharl\u016bk Khuw\u0101r\u016b",
        "Khardal\u016bk Khuw\u0101r\u016b",
        "\u062e\u0631\u062f\u0644\u0648\u0643 \u062e\u0648\u0627\u0631\u0648"
    ],
    "wof:name":"Kharluk Khuwaru",
    "wof:placetype":"locality"
},
  "geometry": {"coordinates":[45.07921,35.83941],"type":"Point"}
}