{
  "type": "Feature",
  "properties": {
    "gn:admin1_code":"6.0",
    "gn:admin2_code":"6818313.0",
    "gn:asciiname":"Qal'at Bushaytah",
    "gn:country_code":"IQ",
    "gn:dem":33,
    "gn:feature_class":"P",
    "gn:feature_code":"PPL",
    "gn:name":"Qal\u2018at Bushaytah",
    "gn:population":0,
    "gn:timezone":"Asia/Baghdad",
    "iso:country":"IQ",
    "name:und_x_variant":[
        "Qal\u2018at Bushaytah"
    ],
    "wof:name":"Qal'at Bushaytah",
    "wof:placetype":"locality"
},
  "geometry": {"coordinates":[44.45,32.68333],"type":"Point"}
}