{
  "type": "Feature",
  "properties": {
    "gn:admin1_code":"5.0",
    "gn:admin2_code":"98464.0",
    "gn:asciiname":"Al Yakuran",
    "gn:country_code":"IQ",
    "gn:dem":956,
    "gn:feature_class":"P",
    "gn:feature_code":"PPL",
    "gn:name":"Al Yak\u016br\u0101n",
    "gn:population":0,
    "gn:timezone":"Asia/Baghdad",
    "iso:country":"IQ",
    "name:ara_x_preferred":[
        "\u0627\u0644\u064a\u0643\u0648\u0631\u0627\u0646"
    ],
    "name:und_x_variant":[
        "Al\u012bk\u016br\u0101n",
        "Al\u012bg\u014dr\u0101n"
    ],
    "wof:name":"Al Yakuran",
    "wof:placetype":"locality"
},
  "geometry": {"coordinates":[45.11687,35.52395],"type":"Point"}
}