{
  "type": "Feature",
  "properties": {
    "gn:admin1_code":"4.0",
    "gn:admin2_code":"6850588.0",
    "gn:asciiname":"Qal'at Abu Bakurah",
    "gn:country_code":"IQ",
    "gn:dem":18,
    "gn:feature_class":"P",
    "gn:feature_code":"PPL",
    "gn:name":"Qal\u2018at \u0100b\u016b Bak\u016brah",
    "gn:population":0,
    "gn:timezone":"Asia/Baghdad",
    "iso:country":"IQ",
    "name:und_x_variant":[
        "Qal\u2018at \u0100b\u016b Bak\u016brah"
    ],
    "wof:name":"Qal'at Abu Bakurah",
    "wof:placetype":"locality"
},
  "geometry": {"coordinates":[44.96667,31.65],"type":"Point"}
}