{
  "type": "Feature",
  "properties": {
    "gn:admin1_code":"18.0",
    "gn:admin2_code":"6805736.0",
    "gn:asciiname":"Qaryat Bani Sa'd",
    "gn:country_code":"IQ",
    "gn:dem":47,
    "gn:feature_class":"P",
    "gn:feature_code":"PPL",
    "gn:name":"Qaryat Ban\u012b Sa\u2018d",
    "gn:population":0,
    "gn:timezone":"Asia/Baghdad",
    "iso:country":"IQ",
    "name:ara_x_preferred":[
        "\u0642\u0631\u064a\u0629 \u0628\u0646\u064a \u0633\u0639\u062f"
    ],
    "name:und_x_variant":[
        "Khar\u0101\u2019ib Ban\u012b Sa\u2018d",
        "Bani Sa\u2018ad",
        "Ban\u012b Sa\u2018d",
        "Qaryat Ban\u012b Sa\u2018d"
    ],
    "wof:name":"Qaryat Bani Sa'd",
    "wof:placetype":"locality"
},
  "geometry": {"coordinates":[44.20563,33.9861],"type":"Point"}
}