{
  "type": "Feature",
  "properties": {
    "gn:admin1_code":"16.0",
    "gn:admin2_code":"99351.0",
    "gn:asciiname":"Al Basrukiyah",
    "gn:country_code":"IQ",
    "gn:dem":18,
    "gn:feature_class":"P",
    "gn:feature_code":"PPL",
    "gn:name":"Al Basr\u016bk\u012byah",
    "gn:population":0,
    "gn:timezone":"Asia/Baghdad",
    "iso:country":"IQ",
    "name:ara_x_preferred":[
        "\u0627\u0644\u0628\u0633\u0631\u0648\u0643\u064a\u0647"
    ],
    "name:und_x_variant":[
        "Al Basr\u016bk\u012byah"
    ],
    "wof:name":"Al Basrukiyah",
    "wof:placetype":"locality"
},
  "geometry": {"coordinates":[45.76275,32.36059],"type":"Point"}
}