{
  "type": "Feature",
  "properties": {
    "gn:admin1_code":"7.0",
    "gn:admin2_code":"99101.0",
    "gn:asciiname":"Albu 'Amir",
    "gn:country_code":"IQ",
    "gn:dem":39,
    "gn:feature_class":"P",
    "gn:feature_code":"PPL",
    "gn:name":"Alb\u016b \u2018\u0100mir",
    "gn:population":0,
    "gn:timezone":"Asia/Baghdad",
    "iso:country":"IQ",
    "name:ara_x_preferred":[
        "Alb\u016b \u2018\u0100mir"
    ],
    "name:ara_x_variant":[
        "\u0627\u0644\u0628\u0648 \u0639\u0627\u0645\u0631"
    ],
    "wof:name":"Albu 'Amir",
    "wof:placetype":"locality"
},
  "geometry": {"coordinates":[44.18324000000001,33.13237],"type":"Point"}
}