{
  "type": "Feature",
  "properties": {
    "gn:admin1_code":"4.0",
    "gn:admin2_code":"98634.0",
    "gn:asciiname":"'Abd al 'Abbas Al Murad",
    "gn:country_code":"IQ",
    "gn:dem":22,
    "gn:feature_class":"P",
    "gn:feature_code":"PPL",
    "gn:name":"\u2018Abd al \u2018Abb\u0101s \u0100l Mur\u0101d",
    "gn:population":0,
    "gn:timezone":"Asia/Baghdad",
    "iso:country":"IQ",
    "name:ara_x_preferred":[
        "\u0639\u0628\u062f \u0627\u0644\u0639\u0628\u0627\u0633 \u0627\u0644 \u0645\u0631\u0627\u062f"
    ],
    "name:und_x_variant":[
        "\u2018Abd al \u2018Abb\u0101s \u0100l Mur\u0101d"
    ],
    "wof:name":"'Abd al 'Abbas Al Murad",
    "wof:placetype":"locality"
},
  "geometry": {"coordinates":[44.51749,31.91288],"type":"Point"}
}