{
  "type": "Feature",
  "properties": {
    "gn:admin1_code":"18.0",
    "gn:admin2_code":"9166598.0",
    "gn:asciiname":"Albu Kabir",
    "gn:country_code":"IQ",
    "gn:dem":151,
    "gn:feature_class":"P",
    "gn:feature_code":"PPL",
    "gn:name":"Alb\u016b Kab\u012br",
    "gn:population":0,
    "gn:timezone":"Asia/Baghdad",
    "iso:country":"IQ",
    "name:ara_x_preferred":[
        "\u0627\u0644\u0628\u0648 \u0643\u0628\u064a\u0631"
    ],
    "name:und_x_variant":[
        "Alb\u016b Kab\u012br"
    ],
    "wof:name":"Albu Kabir",
    "wof:placetype":"locality"
},
  "geometry": {"coordinates":[44.71159,34.60814],"type":"Point"}
}