{
  "type": "Feature",
  "properties": {
    "gn:admin1_code":"9.0",
    "gn:admin2_code":"98700.0",
    "gn:asciiname":"Qaryat Albu Zamil",
    "gn:country_code":"IQ",
    "gn:dem":8,
    "gn:feature_class":"P",
    "gn:feature_code":"PPL",
    "gn:name":"Qaryat \u0100lb\u016b Z\u0101mil",
    "gn:population":0,
    "gn:timezone":"Asia/Baghdad",
    "iso:country":"IQ",
    "name:ara_x_preferred":[
        "\u0642\u0631\u064a\u0629 \u0627\u0644\u0628\u0648 \u0632\u0627\u0645\u0644"
    ],
    "name:und_x_variant":[
        "Qaryat \u0100lb\u016b Z\u0101mil"
    ],
    "wof:name":"Qaryat Albu Zamil",
    "wof:placetype":"locality"
},
  "geometry": {"coordinates":[46.01256,31.56184],"type":"Point"}
}