{
  "type": "Feature",
  "properties": {
    "gn:admin1_code":"5.0",
    "gn:admin2_code":"91176.0",
    "gn:asciiname":"Musak",
    "gn:country_code":"IQ",
    "gn:dem":1501,
    "gn:feature_class":"P",
    "gn:feature_code":"PPL",
    "gn:name":"M\u016bsak",
    "gn:population":0,
    "gn:timezone":"Asia/Baghdad",
    "iso:country":"IQ",
    "name:ara_x_preferred":[
        "\u0645\u0648\u0633\u0643"
    ],
    "name:fas_x_preferred":[
        "\u0645\u0648\u0633\u06a9"
    ],
    "name:kur_x_preferred":[
        "Musek"
    ],
    "name:kur_x_variant":[
        "\u0645\u0648\u0633\u06d5\u0643"
    ],
    "name:und_x_variant":[
        "M\u016bsak",
        "Moosak"
    ],
    "wof:name":"Musak",
    "wof:placetype":"locality"
},
  "geometry": {"coordinates":[45.65458,35.92420999999999],"type":"Point"}
}