{
  "type": "Feature",
  "properties": {
    "gn:admin1_code":"11.0",
    "gn:admin2_code":"93817.0",
    "gn:asciiname":"Al Kuwayr",
    "gn:country_code":"IQ",
    "gn:dem":247,
    "gn:feature_class":"P",
    "gn:feature_code":"PPL",
    "gn:name":"Al Kuwayr",
    "gn:population":0,
    "gn:timezone":"Asia/Baghdad",
    "iso:country":"IQ",
    "name:ara_x_preferred":[
        "\u0627\u0644\u0643\u0648\u064a\u0631"
    ],
    "name:und_x_variant":[
        "Q\u0101dir\u012byah",
        "Al Kuwayr"
    ],
    "wof:name":"Al Kuwayr",
    "wof:placetype":"locality"
},
  "geometry": {"coordinates":[43.66064,36.12318],"type":"Point"}
}