{
  "type": "Feature",
  "properties": {
    "gn:admin1_code":"5.0",
    "gn:admin2_code":"9166684.0",
    "gn:asciiname":"Dulabi",
    "gn:country_code":"IQ",
    "gn:dem":1280,
    "gn:feature_class":"P",
    "gn:feature_code":"PPL",
    "gn:name":"Dulab\u012b",
    "gn:population":0,
    "gn:timezone":"Asia/Baghdad",
    "iso:country":"IQ",
    "name:ara_x_preferred":[
        "\u062f\u0644\u0628\u064a"
    ],
    "name:fas_x_preferred":[
        "Delab\u012b"
    ],
    "name:fas_x_variant":[
        "\u062f\u0644\u0628\u06cc"
    ],
    "name:kur_x_preferred":[
        "Do\u0142e B\u00ee"
    ],
    "name:kur_x_variant":[
        "\u062f\u06c6\u06b5\u06d5 \u0628\u0649"
    ],
    "name:und_x_variant":[
        "Dulab\u012b",
        "Dol\u0101bi",
        "Dola Bee",
        "\u062f\u0644\u0628\u06cc"
    ],
    "wof:name":"Dulabi",
    "wof:placetype":"locality"
},
  "geometry": {"coordinates":[46.00995,35.78025],"type":"Point"}
}