{
  "type": "Feature",
  "properties": {
    "gn:admin1_code":"18.0",
    "gn:admin2_code":"9166598.0",
    "gn:asciiname":"'Arab Muhammad Dhiyab",
    "gn:country_code":"IQ",
    "gn:dem":101,
    "gn:feature_class":"P",
    "gn:feature_code":"PPLL",
    "gn:name":"\u2018Arab Mu\u1e29ammad Dhiy\u0101b",
    "gn:population":0,
    "gn:timezone":"Asia/Baghdad",
    "iso:country":"IQ",
    "name:ara_x_preferred":[
        "\u0639\u0631\u0628 \u0645\u062d\u0645\u062f \u0630\u064a\u0627\u0628"
    ],
    "name:und_x_variant":[
        "\u2018Arab Mu\u1e29ammad Dhiy\u0101b"
    ],
    "wof:name":"'Arab Muhammad Dhiyab",
    "wof:placetype":"locality"
},
  "geometry": {"coordinates":[44.25064,34.57132],"type":"Point"}
}