{
  "type": "Feature",
  "properties": {
    "gn:admin1_code":"9.0",
    "gn:admin2_code":"98700.0",
    "gn:asciiname":"Sayyid Dakhil",
    "gn:country_code":"IQ",
    "gn:dem":8,
    "gn:feature_class":"P",
    "gn:feature_code":"PPL",
    "gn:name":"Sayyid Dakh\u012bl",
    "gn:population":0,
    "gn:timezone":"Asia/Baghdad",
    "iso:country":"IQ",
    "name:ara_x_preferred":[
        "\u0633\u064a\u062f \u062f\u062e\u064a\u0644"
    ],
    "name:und_x_variant":[
        "Sayyid Dakh\u012bl"
    ],
    "wof:name":"Sayyid Dakhil",
    "wof:placetype":"locality"
},
  "geometry": {"coordinates":[46.15279,31.65739],"type":"Point"}
}