{
  "type": "Feature",
  "properties": {
    "gn:admin1_code":"15.0",
    "gn:admin2_code":"9166620.0",
    "gn:asciiname":"Al 'Abd",
    "gn:country_code":"IQ",
    "gn:dem":237,
    "gn:feature_class":"P",
    "gn:feature_code":"PPL",
    "gn:name":"Al \u2018Abd",
    "gn:population":0,
    "gn:timezone":"Asia/Baghdad",
    "iso:country":"IQ",
    "name:ara_x_preferred":[
        "\u0627\u0644\u0639\u0628\u062f"
    ],
    "name:ara_x_variant":[
        "Al \u2018Abd"
    ],
    "wof:name":"Al 'Abd",
    "wof:placetype":"locality"
},
  "geometry": {"coordinates":[42.37962,35.97631],"type":"Point"}
}