{
  "type": "Feature",
  "properties": {
    "gn:admin1_code":"16.0",
    "gn:admin2_code":"9166961.0",
    "gn:asciiname":"Khattab Chalabi",
    "gn:cc2":"IQ",
    "gn:country_code":"IQ",
    "gn:dem":26,
    "gn:feature_class":"P",
    "gn:feature_code":"PPL",
    "gn:name":"Kha\u0163\u0163\u0101b Chalab\u012b",
    "gn:population":0,
    "gn:timezone":"Asia/Baghdad",
    "iso:country":"IQ",
    "name:und_x_variant":[
        "Khatt\u0101b Chalbi",
        "Kha\u0163\u0163\u0101b Shalab\u012b",
        "Kha\u0163\u0163\u0101b Chalab\u012b"
    ],
    "wof:name":"Khattab Chalabi",
    "wof:placetype":"locality"
},
  "geometry": {"coordinates":[45.18222,32.83861],"type":"Point"}
}