{
  "type": "Feature",
  "properties": {
    "gn:admin1_code":"15.0",
    "gn:admin2_code":"98612.0",
    "gn:asciiname":"Kir Faqir",
    "gn:country_code":"IQ",
    "gn:dem":342,
    "gn:feature_class":"P",
    "gn:feature_code":"PPL",
    "gn:name":"Kir Faq\u012br",
    "gn:population":0,
    "gn:timezone":"Asia/Baghdad",
    "iso:country":"IQ",
    "name:ara_x_preferred":[
        "\u0643\u0631 \u0641\u0642\u064a\u0631"
    ],
    "name:kur_x_preferred":[
        "Gir Feq\u00eer"
    ],
    "name:kur_x_variant":[
        "\u06af\u0631 \u0641\u06d5\u0642\u064a\u0631"
    ],
    "name:und_x_variant":[
        "Gir Faqir",
        "Kir Faq\u012br"
    ],
    "wof:name":"Kir Faqir",
    "wof:placetype":"locality"
},
  "geometry": {"coordinates":[43.45134,36.58406],"type":"Point"}
}