{
  "type": "Feature",
  "properties": {
    "gn:admin1_code":"1.0",
    "gn:admin2_code":"98718.0",
    "gn:asciiname":"Albu Sahl wa Albu Sakr",
    "gn:country_code":"IQ",
    "gn:dem":52,
    "gn:feature_class":"P",
    "gn:feature_code":"PPL",
    "gn:name":"\u0100lb\u016b Sa\u1e29l wa \u0100lb\u016b \u015eakr",
    "gn:population":0,
    "gn:timezone":"Asia/Baghdad",
    "iso:country":"IQ",
    "name:ara_x_preferred":[
        "\u0622\u0644\u0628\u0648 \u0633\u062d\u0644 \u0648\u0622\u0644\u0628\u0648 \u0635\u0643\u0631"
    ],
    "name:und_x_variant":[
        "\u2018Arab \u0100lb\u016b Sa\u1e29l wa \u0100lb\u016b \u015eakr",
        "\u0639\u0631\u0628 \u0622\u0644\u0628\u0648 \u0633\u062d\u0644 \u0648\u0622\u0644\u0628\u0648 \u0635\u0643\u0631",
        "\u0100lb\u016b Sa\u1e29l wa \u0100lb\u016b \u015eakr"
    ],
    "wof:name":"Albu Sahl wa Albu Sakr",
    "wof:placetype":"locality"
},
  "geometry": {"coordinates":[43.36248,33.44765],"type":"Point"}
}