{
  "type": "Feature",
  "properties": {
    "gn:admin1_code":"6.0",
    "gn:admin2_code":"99358.0",
    "gn:asciiname":"Husayn 'Abd",
    "gn:country_code":"IQ",
    "gn:dem":27,
    "gn:feature_class":"P",
    "gn:feature_code":"PPL",
    "gn:name":"\u1e28usayn \u2018Abd",
    "gn:population":0,
    "gn:timezone":"Asia/Baghdad",
    "iso:country":"IQ",
    "name:ara_x_preferred":[
        "\u062d\u0633\u064a\u0646 \u0639\u0628\u062f"
    ],
    "name:und_x_variant":[
        "\u1e28usayn \u2018Abd"
    ],
    "wof:name":"Husayn 'Abd",
    "wof:placetype":"locality"
},
  "geometry": {"coordinates":[44.89736,32.36882],"type":"Point"}
}