{
  "type": "Feature",
  "properties": {
    "gn:admin1_code":"18.0",
    "gn:admin2_code":"91594.0",
    "gn:asciiname":"Fadil Hasan as Salman",
    "gn:country_code":"IQ",
    "gn:dem":95,
    "gn:feature_class":"P",
    "gn:feature_code":"PPL",
    "gn:name":"F\u0101\u1e11il \u1e28asan as Salm\u0101n",
    "gn:population":0,
    "gn:timezone":"Asia/Baghdad",
    "iso:country":"IQ",
    "name:ara_x_preferred":[
        "\u0641\u0627\u0636\u0644 \u062d\u0633\u0646 \u0627\u0644\u0633\u0644\u0645\u0627\u0646"
    ],
    "name:und_x_variant":[
        "F\u0101\u1e11il \u1e28asan as Salm\u0101n"
    ],
    "wof:name":"Fadil Hasan as Salman",
    "wof:placetype":"locality"
},
  "geometry": {"coordinates":[43.67389,34.28907],"type":"Point"}
}