{
  "type": "Feature",
  "properties": {
    "gn:admin1_code":"11.0",
    "gn:admin2_code":"9166534.0",
    "gn:asciiname":"Daw",
    "gn:country_code":"IQ",
    "gn:dem":2028,
    "gn:feature_class":"P",
    "gn:feature_code":"PPL",
    "gn:name":"Daw",
    "gn:population":0,
    "gn:timezone":"Asia/Baghdad",
    "iso:country":"IQ",
    "name:ara_x_preferred":[
        "B\u0113d\u0101r"
    ],
    "name:fra_x_preferred":[
        "Daw"
    ],
    "name:kur_x_preferred":[
        "Daw"
    ],
    "name:kur_x_variant":[
        "\u062f\u0627\u0648"
    ],
    "wof:name":"Daw",
    "wof:placetype":"locality"
},
  "geometry": {"coordinates":[44.23334000000001,37.26417],"type":"Point"}
}