{
  "type": "Feature",
  "properties": {
    "gn:admin1_code":"11.0",
    "gn:admin2_code":"9166592.0",
    "gn:asciiname":"Faqiyan",
    "gn:country_code":"IQ",
    "gn:dem":1177,
    "gn:feature_class":"P",
    "gn:feature_code":"PPL",
    "gn:name":"F\u0101qiy\u0101n",
    "gn:population":0,
    "gn:timezone":"Asia/Baghdad",
    "iso:country":"IQ",
    "name:ara_x_preferred":[
        "F\u0101qiy\u0101n"
    ],
    "name:ara_x_variant":[
        "\u0641\u0627\u0642\u064a\u0627\u0646"
    ],
    "name:kur_x_preferred":[
        "Feq\u00eayan"
    ],
    "name:kur_x_variant":[
        "\u0641\u06d5\u0642\u06ce\u064a\u0627\u0646"
    ],
    "wof:name":"Faqiyan",
    "wof:placetype":"locality"
},
  "geometry": {"coordinates":[44.53801,36.54265],"type":"Point"}
}