{
  "type": "Feature",
  "properties": {
    "gn:admin1_code":"11.0",
    "gn:admin2_code":"9166534.0",
    "gn:asciiname":"Ashtah",
    "gn:country_code":"IQ",
    "gn:dem":516,
    "gn:feature_class":"P",
    "gn:feature_code":"PPL",
    "gn:name":"Ashtah",
    "gn:population":0,
    "gn:timezone":"Asia/Baghdad",
    "iso:country":"IQ",
    "name:ara_x_preferred":[
        "Ast\u0101"
    ],
    "name:ara_x_variant":[
        "\u0672\u0633\u062a\u0627"
    ],
    "name:kur_x_preferred":[
        "Esta"
    ],
    "name:kur_x_variant":[
        "\u0626\u06d5\u0633\u062a\u0627",
        "Asta",
        "\u0626\u0627\u0633\u062a\u0627"
    ],
    "name:und_x_variant":[
        "\u016astah",
        "Ashtah",
        "\u0672\u0634\u062a\u0647"
    ],
    "wof:name":"Ashtah",
    "wof:placetype":"locality"
},
  "geometry": {"coordinates":[44.09771,36.87588],"type":"Point"}
}