{
  "type": "Feature",
  "properties": {
    "gn:admin1_code":"5.0",
    "gn:admin2_code":"91176.0",
    "gn:asciiname":"Yuleh",
    "gn:country_code":"IQ",
    "gn:dem":1061,
    "gn:feature_class":"P",
    "gn:feature_code":"PPL",
    "gn:name":"Y\u016bleh",
    "gn:population":0,
    "gn:timezone":"Asia/Baghdad",
    "iso:country":"IQ",
    "name:fas_x_preferred":[
        "\u06cc\u0648\u0644\u0647"
    ],
    "wof:name":"Yuleh",
    "wof:placetype":"locality"
},
  "geometry": {"coordinates":[45.7653,35.5315],"type":"Point"}
}