{
  "type": "Feature",
  "properties": {
    "gn:admin1_code":"9.0",
    "gn:admin2_code":"99185.0",
    "gn:asciiname":"Al Ma'dan",
    "gn:country_code":"IQ",
    "gn:dem":5,
    "gn:feature_class":"P",
    "gn:feature_code":"PPL",
    "gn:name":"Al Ma\u2018d\u0101n",
    "gn:population":0,
    "gn:timezone":"Asia/Baghdad",
    "iso:country":"IQ",
    "name:ara_x_preferred":[
        "\u0627\u0644\u0645\u0639\u062f\u0627\u0646"
    ],
    "name:und_x_variant":[
        "Al Ma\u2018d\u0101n"
    ],
    "wof:name":"Al Ma'dan",
    "wof:placetype":"locality"
},
  "geometry": {"coordinates":[46.90941,31.04097],"type":"Point"}
}