{
  "type": "Feature",
  "properties": {
    "gn:admin1_code":"14.0",
    "gn:admin2_code":"9166562.0",
    "gn:asciiname":"Salaf Abu 'Arran",
    "gn:country_code":"IQ",
    "gn:dem":7,
    "gn:feature_class":"P",
    "gn:feature_code":"PPL",
    "gn:name":"Salaf Ab\u016b \u2018Arr\u0101n",
    "gn:population":0,
    "gn:timezone":"Asia/Baghdad",
    "iso:country":"IQ",
    "name:ara_x_preferred":[
        "\u0633\u0644\u0641 \u0627\u0628\u0648 \u0639\u0631\u0627\u0646"
    ],
    "name:und_x_variant":[
        "Salaf Ab\u016b \u2018Arr\u0101n"
    ],
    "wof:name":"Salaf Abu 'Arran",
    "wof:placetype":"locality"
},
  "geometry": {"coordinates":[46.97393,31.45933],"type":"Point"}
}