{
  "type": "Feature",
  "properties": {
    "gn:admin1_code":"15.0",
    "gn:admin2_code":"9166620.0",
    "gn:asciiname":"Hazil",
    "gn:country_code":"IQ",
    "gn:dem":299,
    "gn:feature_class":"P",
    "gn:feature_code":"PPL",
    "gn:name":"Haz\u012bl",
    "gn:population":0,
    "gn:timezone":"Asia/Baghdad",
    "iso:country":"IQ",
    "name:ara_x_preferred":[
        "\u0647\u0632\u064a\u0644"
    ],
    "name:ara_x_variant":[
        "\u0647\u0632\u064a\u0644 \u0627\u0644\u0634\u0631\u0642\u064a\u0629"
    ],
    "name:und_x_variant":[
        "Haz\u012bl",
        "Haz\u012bl ash Sharq\u012byah"
    ],
    "wof:name":"Hazil",
    "wof:placetype":"locality"
},
  "geometry": {"coordinates":[42.1064,36.14479],"type":"Point"}
}