{
  "type": "Feature",
  "properties": {
    "iso:country":"IQ",
    "name:und_x_variant":[
        "Kharja"
    ],
    "qs:gn_country":"IQ",
    "qs:gn_fcode":"PPL",
    "qs:gn_pop":0,
    "qs:name":"Al Kha\u1e11r\u0101'",
    "qs:name_adm0":"Iraq",
    "qs:name_adm1":"\u0628\u063a\u062f\u0627\u062f",
    "qs:photos":8,
    "qs:photos_1k":2,
    "qs:photos_9k":1,
    "qs:photos_9r":1,
    "qs:photos_all":8,
    "qs:photos_sr":1,
    "qs:placetype":"Suburb",
    "qs:pop_sr":"0",
    "qs:woe_adm0":23424855,
    "wof:name":"Al Kha\u1e11r\u0101'",
    "wof:placetype":"neighbourhood"
},
  "geometry": {"coordinates":[44.21667,33.98333],"type":"Point"}
}