{
  "type": "Feature",
  "properties": {
    "gn:admin1_code":"14.0",
    "gn:admin2_code":"9166562.0",
    "gn:asciiname":"Al Jirjan",
    "gn:cc2":"IQ",
    "gn:country_code":"IQ",
    "gn:dem":7,
    "gn:feature_class":"P",
    "gn:feature_code":"PPL",
    "gn:name":"Al Jirj\u0101n",
    "gn:population":0,
    "gn:timezone":"Asia/Baghdad",
    "iso:country":"IQ",
    "name:ara_x_preferred":[
        "Al Jirj\u0101n"
    ],
    "name:und_x_variant":[
        "Al Jurj\u0101n"
    ],
    "wof:name":"Al Jirjan",
    "wof:placetype":"locality"
},
  "geometry": {"coordinates":[47.06667,31.78333],"type":"Point"}
}