{
  "type": "Feature",
  "properties": {
    "gn:admin1_code":"6.0",
    "gn:admin2_code":"6818313.0",
    "gn:asciiname":"Hafuk 'Ujayl",
    "gn:country_code":"IQ",
    "gn:dem":33,
    "gn:feature_class":"P",
    "gn:feature_code":"PPL",
    "gn:name":"\u1e28af\u016bk \u2018Ujayl",
    "gn:population":0,
    "gn:timezone":"Asia/Baghdad",
    "iso:country":"IQ",
    "name:ara_x_preferred":[
        "\u062d\u0641\u0648\u0643 \u0639\u062c\u064a\u0644"
    ],
    "name:und_x_variant":[
        "\u1e28af\u016bk \u2018Ujayl"
    ],
    "wof:name":"Hafuk 'Ujayl",
    "wof:placetype":"locality"
},
  "geometry": {"coordinates":[44.61533,32.70474],"type":"Point"}
}