{
  "type": "Feature",
  "properties": {
    "gn:admin1_code":"11.0",
    "gn:admin2_code":"9166592.0",
    "gn:asciiname":"Setkan",
    "gn:country_code":"IQ",
    "gn:dem":1062,
    "gn:feature_class":"P",
    "gn:feature_code":"PPL",
    "gn:name":"S\u00eatkan",
    "gn:population":0,
    "gn:timezone":"Asia/Baghdad",
    "iso:country":"IQ",
    "name:ara_x_preferred":[
        "\u0633\u064a\u062a\u0643\u0627\u0646"
    ],
    "name:kur_x_preferred":[
        "S\u00eatkan"
    ],
    "name:kur_x_variant":[
        "\u0633\u06ce\u062a\u0643\u0627\u0646",
        "S\u00eetkan"
    ],
    "name:und_x_variant":[
        "S\u012bdk\u0101n",
        "Sitk\u0101n",
        "Setkan",
        "Sitkan",
        "Saytk\u0101n"
    ],
    "wof:name":"Setkan",
    "wof:placetype":"locality"
},
  "geometry": {"coordinates":[44.59328,36.68103],"type":"Point"}
}