{
  "type": "Feature",
  "properties": {
    "gn:admin1_code":"1.0",
    "gn:admin2_code":"9166650.0",
    "gn:asciiname":"Ash Shirwaniyah",
    "gn:country_code":"IQ",
    "gn:dem":170,
    "gn:feature_class":"P",
    "gn:feature_code":"PPL",
    "gn:name":"Ash Shirw\u0101n\u012byah",
    "gn:population":0,
    "gn:timezone":"Asia/Baghdad",
    "iso:country":"IQ",
    "name:ara_x_preferred":[
        "\u0627\u0644\u0634\u0631\u0648\u0627\u0646\u064a\u0647"
    ],
    "name:und_x_variant":[
        "Ash Shirw\u0101n\u012byah"
    ],
    "wof:name":"Ash Shirwaniyah",
    "wof:placetype":"locality"
},
  "geometry": {"coordinates":[41.78811,34.48989],"type":"Point"}
}