{
  "type": "Feature",
  "properties": {
    "gn:admin1_code":"15.0",
    "gn:admin2_code":"9166649.0",
    "gn:asciiname":"Qaryat Jaddalat Isma'il",
    "gn:country_code":"IQ",
    "gn:dem":204,
    "gn:feature_class":"P",
    "gn:feature_code":"PPL",
    "gn:name":"Qaryat Jadd\u0101lat Ism\u0101\u2018\u012bl",
    "gn:population":0,
    "gn:timezone":"Asia/Baghdad",
    "iso:country":"IQ",
    "name:ara_x_preferred":[
        "\u0642\u0631\u064a\u0629 \u062c\u062f\u0627\u0644\u0629 \u0627\u0633\u0645\u0627\u0639\u064a\u0644"
    ],
    "name:und_x_variant":[
        "Qaryat Jadd\u0101lat Ism\u0101\u2018\u012bl"
    ],
    "wof:name":"Qaryat Jaddalat Isma'il",
    "wof:placetype":"locality"
},
  "geometry": {"coordinates":[43.0869,35.73879],"type":"Point"}
}