{
  "type": "Feature",
  "properties": {
    "gn:admin1_code":"16.0",
    "gn:admin2_code":"98460.0",
    "gn:asciiname":"Trad al Jiryan",
    "gn:country_code":"IQ",
    "gn:dem":27,
    "gn:feature_class":"P",
    "gn:feature_code":"PPL",
    "gn:name":"\u0162r\u0101d al Jiry\u0101n",
    "gn:population":0,
    "gn:timezone":"Asia/Baghdad",
    "iso:country":"IQ",
    "name:ara_x_preferred":[
        "\u0637\u0631\u0627\u062f \u0627\u0644\u062c\u0631\u064a\u0627\u0646"
    ],
    "name:und_x_variant":[
        "\u0162r\u0101d al Jiry\u0101n"
    ],
    "wof:name":"Trad al Jiryan",
    "wof:placetype":"locality"
},
  "geometry": {"coordinates":[45.29184,32.6666],"type":"Point"}
}