{
  "type": "Feature",
  "properties": {
    "gn:admin1_code":"7.0",
    "gn:admin2_code":"9166545.0",
    "gn:asciiname":"'Arab Ahmad Musa",
    "gn:country_code":"IQ",
    "gn:dem":35,
    "gn:feature_class":"P",
    "gn:feature_code":"PPL",
    "gn:name":"\u2018Arab A\u1e29mad M\u016bs\u00e1",
    "gn:population":0,
    "gn:timezone":"Asia/Baghdad",
    "iso:country":"IQ",
    "name:ara_x_preferred":[
        "\u0639\u0631\u0628 \u0623\u062d\u0645\u062f \u0645\u0648\u0633\u0649"
    ],
    "name:und_x_variant":[
        "\u2018Arab A\u1e29mad M\u016bs\u00e1"
    ],
    "wof:name":"'Arab Ahmad Musa",
    "wof:placetype":"locality"
},
  "geometry": {"coordinates":[44.33974,33.21739],"type":"Point"}
}