{
  "type": "Feature",
  "properties": {
    "gn:admin1_code":"15.0",
    "gn:admin2_code":"9166649.0",
    "gn:asciiname":"Qaryat Kuraydi",
    "gn:country_code":"IQ",
    "gn:dem":208,
    "gn:feature_class":"P",
    "gn:feature_code":"PPL",
    "gn:name":"Qaryat Kurayd\u012b",
    "gn:population":0,
    "gn:timezone":"Asia/Baghdad",
    "iso:country":"IQ",
    "name:ara_x_preferred":[
        "\u0642\u0631\u064a\u0629 \u0643\u0631\u064a\u062f\u064a"
    ],
    "name:und_x_variant":[
        "Qaryat Kurayd\u012b"
    ],
    "wof:name":"Qaryat Kuraydi",
    "wof:placetype":"locality"
},
  "geometry": {"coordinates":[43.1355,35.70159],"type":"Point"}
}