{
  "type": "Feature",
  "properties": {
    "gn:admin1_code":"1.0",
    "gn:admin2_code":"99455.0",
    "gn:asciiname":"'Ali 'Awwad",
    "gn:country_code":"IQ",
    "gn:dem":34,
    "gn:feature_class":"P",
    "gn:feature_code":"PPL",
    "gn:name":"\u2018Al\u012b \u2018Aww\u0101d",
    "gn:population":0,
    "gn:timezone":"Asia/Baghdad",
    "iso:country":"IQ",
    "name:ara_x_preferred":[
        "\u0639\u0644\u064a \u0639\u0648\u0627\u062f"
    ],
    "name:ara_x_variant":[
        "\u2018Al\u012b \u2018Aww\u0101d"
    ],
    "wof:name":"'Ali 'Awwad",
    "wof:placetype":"locality"
},
  "geometry": {"coordinates":[44.02025,33.5228],"type":"Point"}
}