{
  "type": "Feature",
  "properties": {
    "gn:admin1_code":"7.0",
    "gn:admin2_code":"99101.0",
    "gn:asciiname":"Majid ar Rumman",
    "gn:country_code":"IQ",
    "gn:dem":39,
    "gn:feature_class":"P",
    "gn:feature_code":"PPL",
    "gn:name":"Maj\u012bd ar Rumm\u0101n",
    "gn:population":0,
    "gn:timezone":"Asia/Baghdad",
    "iso:country":"IQ",
    "name:ara_x_preferred":[
        "\u0645\u062c\u064a\u062f \u0627\u0644\u0631\u0645\u0627\u0646"
    ],
    "name:und_x_variant":[
        "Maj\u012bd ar Rumm\u0101n"
    ],
    "wof:name":"Majid ar Rumman",
    "wof:placetype":"locality"
},
  "geometry": {"coordinates":[44.31139,33.03211],"type":"Point"}
}