{
  "type": "Feature",
  "properties": {
    "gn:admin1_code":"16.0",
    "gn:admin2_code":"98460.0",
    "gn:asciiname":"Jasim al Hasbun",
    "gn:country_code":"IQ",
    "gn:dem":29,
    "gn:feature_class":"P",
    "gn:feature_code":"PPL",
    "gn:name":"J\u0101sim al \u1e28asb\u016bn",
    "gn:population":0,
    "gn:timezone":"Asia/Baghdad",
    "iso:country":"IQ",
    "name:ara_x_preferred":[
        "\u062c\u0627\u0633\u0645 \u0627\u0644\u062d\u0633\u0628\u0648\u0646"
    ],
    "name:und_x_variant":[
        "J\u0101sim al \u1e28asb\u016bn"
    ],
    "wof:name":"Jasim al Hasbun",
    "wof:placetype":"locality"
},
  "geometry": {"coordinates":[45.00824,32.85292],"type":"Point"}
}