{
  "type": "Feature",
  "properties": {
    "gn:admin1_code":"7.0",
    "gn:admin2_code":"9166542.0",
    "gn:asciiname":"Hadi al 'Afan",
    "gn:country_code":"IQ",
    "gn:dem":40,
    "gn:feature_class":"P",
    "gn:feature_code":"PPL",
    "gn:name":"Had\u012b al \u2018Afan",
    "gn:population":0,
    "gn:timezone":"Asia/Baghdad",
    "iso:country":"IQ",
    "name:ara_x_preferred":[
        "\u0647\u0627\u062f\u064a \u0627\u0644\u0639\u0641\u0646"
    ],
    "name:und_x_variant":[
        "Had\u012b al \u2018Afan"
    ],
    "wof:name":"Hadi al 'Afan",
    "wof:placetype":"locality"
},
  "geometry": {"coordinates":[43.96652,33.26021],"type":"Point"}
}