{
  "type": "Feature",
  "properties": {
    "gn:admin1_code":"15.0",
    "gn:admin2_code":"9166649.0",
    "gn:asciiname":"Khuwaytalah",
    "gn:country_code":"IQ",
    "gn:dem":330,
    "gn:feature_class":"P",
    "gn:feature_code":"PPL",
    "gn:name":"Khuwaytalah",
    "gn:population":0,
    "gn:timezone":"Asia/Baghdad",
    "iso:country":"IQ",
    "name:ara_x_preferred":[
        "\u062e\u0648\u064a\u062a\u0644\u0629"
    ],
    "name:und_x_variant":[
        "Huwaitla",
        "Khuwaitla",
        "\u1e28uwaytilah",
        "Khuwaytalah"
    ],
    "wof:name":"Khuwaytalah",
    "wof:placetype":"locality"
},
  "geometry": {"coordinates":[42.84228,36.2377],"type":"Point"}
}