{
  "type": "Feature",
  "properties": {
    "gn:admin1_code":"13.0",
    "gn:admin2_code":"6770659.0",
    "gn:asciiname":"Qaryat ad Damakah",
    "gn:country_code":"IQ",
    "gn:dem":199,
    "gn:feature_class":"P",
    "gn:feature_code":"PPL",
    "gn:name":"Qaryat ad Dam\u0101kah",
    "gn:population":0,
    "gn:timezone":"Asia/Baghdad",
    "iso:country":"IQ",
    "name:ara_x_preferred":[
        "\u0642\u0631\u064a\u0629 \u0627\u0644\u062f\u0645\u0627\u0643\u0629"
    ],
    "name:und_x_variant":[
        "Qaryat ad Dam\u0101kah"
    ],
    "wof:name":"Qaryat ad Damakah",
    "wof:placetype":"locality"
},
  "geometry": {"coordinates":[43.95892,35.30399],"type":"Point"}
}