{
  "type": "Feature",
  "properties": {
    "gn:admin1_code":"5.0",
    "gn:admin2_code":"92743.0",
    "gn:asciiname":"Gwezle",
    "gn:country_code":"IQ",
    "gn:dem":513,
    "gn:feature_class":"P",
    "gn:feature_code":"PPLL",
    "gn:name":"Gw\u00eaz\u0142e",
    "gn:population":0,
    "gn:timezone":"Asia/Baghdad",
    "iso:country":"IQ",
    "name:ara_x_preferred":[
        "\u0643\u0648\u064a\u0632\u064a\u0629"
    ],
    "name:kur_x_preferred":[
        "Gw\u00eaz\u0142e"
    ],
    "name:kur_x_variant":[
        "Gw\u00eaz\u00eele",
        "\u06af\u0648\u06ce\u0632\u06b5\u0647",
        "\u06af\u0648\u06ce\u0632\u064a\u0644\u06d5"
    ],
    "name:und_x_variant":[
        "Goz\u012bla",
        "Gwezila",
        "Guezeela",
        "Kuwayz\u012byah"
    ],
    "wof:name":"Gwezle",
    "wof:placetype":"locality"
},
  "geometry": {"coordinates":[45.08239,36.16772],"type":"Point"}
}