{
  "type": "Feature",
  "properties": {
    "gn:admin1_code":"6.0",
    "gn:admin2_code":"99358.0",
    "gn:asciiname":"'Inad Fahd",
    "gn:country_code":"IQ",
    "gn:dem":22,
    "gn:feature_class":"P",
    "gn:feature_code":"PPL",
    "gn:name":"\u2018In\u0101d Fahd",
    "gn:population":0,
    "gn:timezone":"Asia/Baghdad",
    "iso:country":"IQ",
    "name:ara_x_preferred":[
        "\u0639\u0646\u0627\u062f \u0641\u0647\u062f"
    ],
    "name:und_x_variant":[
        "\u2018In\u0101d Fahd"
    ],
    "wof:name":"'Inad Fahd",
    "wof:placetype":"locality"
},
  "geometry": {"coordinates":[44.61123,32.21815],"type":"Point"}
}