{
  "type": "Feature",
  "properties": {
    "gn:admin1_code":"6.0",
    "gn:admin2_code":"99040.0",
    "gn:asciiname":"Shakir Mu'in",
    "gn:country_code":"IQ",
    "gn:dem":32,
    "gn:feature_class":"P",
    "gn:feature_code":"PPL",
    "gn:name":"Sh\u0101kir Mu\u2018\u012bn",
    "gn:population":0,
    "gn:timezone":"Asia/Baghdad",
    "iso:country":"IQ",
    "name:ara_x_preferred":[
        "\u0634\u0627\u0643\u0631 \u0645\u0639\u064a\u0646"
    ],
    "name:ara_x_variant":[
        "Sh\u0101kir Mu\u2018\u012bn"
    ],
    "wof:name":"Shakir Mu'in",
    "wof:placetype":"locality"
},
  "geometry": {"coordinates":[44.2259,32.56831],"type":"Point"}
}