{
  "type": "Feature",
  "properties": {
    "gn:admin1_code":"18.0",
    "gn:admin2_code":"91594.0",
    "gn:asciiname":"Muhammad Khalifah",
    "gn:country_code":"IQ",
    "gn:dem":119,
    "gn:feature_class":"P",
    "gn:feature_code":"PPL",
    "gn:name":"Mu\u1e29ammad Khal\u012bfah",
    "gn:population":0,
    "gn:timezone":"Asia/Baghdad",
    "iso:country":"IQ",
    "name:ara_x_preferred":[
        "\u0645\u062d\u0645\u062f \u062e\u0644\u064a\u0641\u0629"
    ],
    "name:und_x_variant":[
        "Mu\u1e29ammad Khal\u012bfah"
    ],
    "wof:name":"Muhammad Khalifah",
    "wof:placetype":"locality"
},
  "geometry": {"coordinates":[43.4073,34.32391],"type":"Point"}
}