{
  "type": "Feature",
  "properties": {
    "gn:admin1_code":"6.0",
    "gn:admin2_code":"99358.0",
    "gn:asciiname":"Khudayr 'Ubays",
    "gn:country_code":"IQ",
    "gn:dem":25,
    "gn:feature_class":"P",
    "gn:feature_code":"PPL",
    "gn:name":"Khu\u1e11ayr \u2018Ubays",
    "gn:population":0,
    "gn:timezone":"Asia/Baghdad",
    "iso:country":"IQ",
    "name:ara_x_preferred":[
        "\u062e\u0636\u064a\u0631 \u0639\u0628\u064a\u0633"
    ],
    "name:und_x_variant":[
        "Khu\u1e11ayr \u2018Ubays"
    ],
    "wof:name":"Khudayr 'Ubays",
    "wof:placetype":"locality"
},
  "geometry": {"coordinates":[44.79031,32.33485],"type":"Point"}
}