{
  "type": "Feature",
  "properties": {
    "gn:admin1_code":"18.0",
    "gn:admin2_code":"6804454.0",
    "gn:asciiname":"Mushayt",
    "gn:country_code":"IQ",
    "gn:dem":233,
    "gn:feature_class":"P",
    "gn:feature_code":"PPL",
    "gn:name":"Mushayt",
    "gn:population":0,
    "gn:timezone":"Asia/Baghdad",
    "iso:country":"IQ",
    "name:ara_x_preferred":[
        "\u0645\u064f\u0634\u064a\u062a"
    ],
    "wof:name":"Mushayt",
    "wof:placetype":"locality"
},
  "geometry": {"coordinates":[43.17542,35.33932],"type":"Point"}
}