{
  "type": "Feature",
  "properties": {
    "gn:admin1_code":"15.0",
    "gn:admin2_code":"9166618.0",
    "gn:asciiname":"Al Qush",
    "gn:country_code":"IQ",
    "gn:dem":530,
    "gn:feature_class":"P",
    "gn:feature_code":"PPL",
    "gn:name":"Al Q\u016bsh",
    "gn:population":0,
    "gn:timezone":"Asia/Baghdad",
    "iso:country":"IQ",
    "name:ara_x_preferred":[
        "\u0627\u0644\u0642\u0648\u0634"
    ],
    "name:ara_x_variant":[
        "Al Q\u016bsh"
    ],
    "name:kur_x_preferred":[
        "Elqush"
    ],
    "name:kur_x_variant":[
        "\u0626\u06d5\u0644\u0642\u0648\u0634"
    ],
    "name:und_x_variant":[
        "Alg\u014dsh",
        "Alqosh",
        "Alqoush"
    ],
    "wof:name":"Al Qush",
    "wof:placetype":"locality"
},
  "geometry": {"coordinates":[43.0967,36.73423],"type":"Point"}
}