{
  "type": "Feature",
  "properties": {
    "gn:admin1_code":"15.0",
    "gn:admin2_code":"9166618.0",
    "gn:asciiname":"Al Qush",
    "gn:country_code":"IQ",
    "gn:dem":530,
    "gn:feature_class":"P",
    "gn:feature_code":"PPL",
    "gn:name":"Al Q\u016bsh",
    "gn:population":0,
    "gn:timezone":"Asia/Baghdad",
    "iso:country":"IQ",
    "name:ara_x_preferred":[
        "\u0627\u0644\u0642\u0648\u0634"
    ],
    "name:ara_x_variant":[
        "Al Q\u016bsh",
        "\u0623\u0644\u0642\u0648\u0634"
    ],
    "name:arc_x_preferred":[
        "\u0710\u0720\u0729\u0718\u072b"
    ],
    "name:ast_x_preferred":[
        "Alqosh"
    ],
    "name:ceb_x_preferred":[
        "Al Q\u016bsh"
    ],
    "name:deu_x_preferred":[
        "Alqosh"
    ],
    "name:fas_x_preferred":[
        "\u0627\u0644\u0642\u0648\u0634"
    ],
    "name:fra_x_preferred":[
        "Alqosh"
    ],
    "name:ita_x_preferred":[
        "Alqosh"
    ],
    "name:kur_x_preferred":[
        "Elqush"
    ],
    "name:kur_x_variant":[
        "\u0626\u06d5\u0644\u0642\u0648\u0634"
    ],
    "name:nor_x_preferred":[
        "Alqosh"
    ],
    "name:pol_x_preferred":[
        "Alkusz"
    ],
    "name:rus_x_preferred":[
        "\u0410\u043b\u044c\u043a\u0430\u0448"
    ],
    "name:spa_x_preferred":[
        "Alqosh"
    ],
    "name:swe_x_preferred":[
        "Alqosh"
    ],
    "name:und_x_variant":[
        "Alg\u014dsh",
        "Alqoush"
    ],
    "name:zho_x_preferred":[
        "\u4e9e\u52d2\u8f9c\u9808"
    ],
    "wof:name":"Al Qush",
    "wof:placetype":"locality"
},
  "geometry": {"coordinates":[43.0967,36.73423],"type":"Point"}
}