{
  "type": "Feature",
  "properties": {
    "gn:admin1_code":"12.0",
    "gn:admin2_code":"99345.0",
    "gn:asciiname":"Qaryat al Hamdaniyah",
    "gn:country_code":"IQ",
    "gn:dem":36,
    "gn:feature_class":"P",
    "gn:feature_code":"PPL",
    "gn:name":"Qaryat al \u1e28amd\u0101n\u012byah",
    "gn:population":0,
    "gn:timezone":"Asia/Baghdad",
    "iso:country":"IQ",
    "name:ara_x_preferred":[
        "\u0642\u0631\u064a\u0629 \u0627\u0644\u062d\u0645\u062f\u0627\u0646\u064a\u0629"
    ],
    "name:und_x_variant":[
        "Qaryat al \u1e28amd\u0101n\u012byah"
    ],
    "wof:name":"Qaryat al Hamdaniyah",
    "wof:placetype":"locality"
},
  "geometry": {"coordinates":[44.21533,32.59445],"type":"Point"}
}