{
  "type": "Feature",
  "properties": {
    "gn:admin1_code":"7.0",
    "gn:admin2_code":"99101.0",
    "gn:asciiname":"'Abd Allah 'Ashiq",
    "gn:country_code":"IQ",
    "gn:dem":34,
    "gn:feature_class":"P",
    "gn:feature_code":"PPL",
    "gn:name":"\u2018Abd All\u0101h \u2018\u0100shiq",
    "gn:population":0,
    "gn:timezone":"Asia/Baghdad",
    "iso:country":"IQ",
    "name:ara_x_preferred":[
        "\u0639\u0628\u062f\u0627\u0644\u0644\u0647 \u0639\u0627\u0634\u0642"
    ],
    "name:ara_x_variant":[
        "\u2018Abd All\u0101h \u2018\u0100shiq"
    ],
    "wof:name":"'Abd Allah 'Ashiq",
    "wof:placetype":"locality"
},
  "geometry": {"coordinates":[44.45568,33.00824],"type":"Point"}
}