{
  "type": "Feature",
  "properties": {
    "gn:admin1_code":"11.0",
    "gn:admin2_code":"9166592.0",
    "gn:asciiname":"Chawnar",
    "gn:country_code":"IQ",
    "gn:dem":810,
    "gn:feature_class":"P",
    "gn:feature_code":"PPL",
    "gn:name":"Chawnar",
    "gn:population":0,
    "gn:timezone":"Asia/Baghdad",
    "iso:country":"IQ",
    "name:ara_x_preferred":[
        "\u0686\u0648\u0646\u0631"
    ],
    "name:kur_x_preferred":[
        "Conere"
    ],
    "name:kur_x_variant":[
        "\u062c\u06c6\u0646\u06d5\u0631\u06d5"
    ],
    "name:und_x_variant":[
        "J\u014dn\u0101ra",
        "Jawnarah",
        "\u062c\u0648\u0646\u0631\u0629"
    ],
    "wof:name":"Chawnar",
    "wof:placetype":"locality"
},
  "geometry": {"coordinates":[44.35851,36.65815],"type":"Point"}
}