{
  "type": "Feature",
  "properties": {
    "gn:admin1_code":"18.0",
    "gn:admin2_code":"6783103.0",
    "gn:asciiname":"'Arab Hamid al Marhun",
    "gn:country_code":"IQ",
    "gn:dem":100,
    "gn:feature_class":"P",
    "gn:feature_code":"PPLL",
    "gn:name":"\u2018Arab \u1e28am\u012bd al Marh\u016bn",
    "gn:population":0,
    "gn:timezone":"Asia/Baghdad",
    "iso:country":"IQ",
    "name:ara_x_preferred":[
        "\u0639\u0631\u0628 \u062d\u0645\u064a\u062f \u0627\u0644\u0645\u0631\u0647\u0648\u0646"
    ],
    "name:und_x_variant":[
        "\u2018Arab \u1e28am\u012bd al Marh\u016bn"
    ],
    "wof:name":"'Arab Hamid al Marhun",
    "wof:placetype":"locality"
},
  "geometry": {"coordinates":[44.49376,34.50192],"type":"Point"}
}