{
  "type": "Feature",
  "properties": {
    "gn:admin1_code":"15.0",
    "gn:admin2_code":"99414.0",
    "gn:asciiname":"'Ubayd as Sayil",
    "gn:country_code":"IQ",
    "gn:dem":251,
    "gn:feature_class":"P",
    "gn:feature_code":"PPL",
    "gn:name":"\u2018Ubayd a\u015f \u015e\u0101yil",
    "gn:population":0,
    "gn:timezone":"Asia/Baghdad",
    "iso:country":"IQ",
    "name:ara_x_preferred":[
        "\u0639\u0628\u064a\u062f \u0627\u0644\u0635\u0627\u064a\u0644"
    ],
    "name:und_x_variant":[
        "\u2018Ubayd a\u015f \u015e\u0101yil"
    ],
    "wof:name":"'Ubayd as Sayil",
    "wof:placetype":"locality"
},
  "geometry": {"coordinates":[43.02409,35.81108],"type":"Point"}
}