{
  "type": "Feature",
  "properties": {
    "gn:admin1_code":"7.0",
    "gn:admin2_code":"99173.0",
    "gn:asciiname":"Husayn as Suhayl",
    "gn:cc2":"IQ",
    "gn:country_code":"IQ",
    "gn:dem":39,
    "gn:feature_class":"P",
    "gn:feature_code":"PPL",
    "gn:name":"\u1e28usayn as Suhayl",
    "gn:population":0,
    "gn:timezone":"Asia/Baghdad",
    "iso:country":"IQ",
    "name:und_x_variant":[
        "Husain as Suhail",
        "\u1e28usayn as Suhayl"
    ],
    "wof:name":"Husayn as Suhayl",
    "wof:placetype":"locality"
},
  "geometry": {"coordinates":[44.30139000000001,33.43667],"type":"Point"}
}