{
  "type": "Feature",
  "properties": {
    "gn:admin1_code":"18.0",
    "gn:admin2_code":"9166616.0",
    "gn:asciiname":"Taba'i",
    "gn:country_code":"IQ",
    "gn:dem":40,
    "gn:feature_class":"P",
    "gn:feature_code":"PPL",
    "gn:name":"Tab\u0101\u2018\u012b",
    "gn:population":0,
    "gn:timezone":"Asia/Baghdad",
    "iso:country":"IQ",
    "name:ara_x_preferred":[
        "\u062a\u0628\u0627\u0639\u064a"
    ],
    "name:und_x_variant":[
        "Tab\u0101\u2018\u012b"
    ],
    "wof:name":"Taba'i",
    "wof:placetype":"locality"
},
  "geometry": {"coordinates":[43.95936,33.72128],"type":"Point"}
}