{
  "type": "Feature",
  "properties": {
    "gn:admin1_code":"8.0",
    "gn:admin2_code":"99612.0",
    "gn:asciiname":"Bibafah",
    "gn:country_code":"IQ",
    "gn:dem":909,
    "gn:feature_class":"P",
    "gn:feature_code":"PPL",
    "gn:name":"B\u012bb\u0101fah",
    "gn:population":0,
    "gn:timezone":"Asia/Baghdad",
    "iso:country":"IQ",
    "name:ara_x_preferred":[
        "\u0628\u064a\u0628\u0627\u0641\u0647"
    ],
    "name:kur_x_preferred":[
        "B\u00eebafe"
    ],
    "name:kur_x_variant":[
        "\u0628\u064a\u0628\u0627\u0641\u06d5",
        "B\u00eebava",
        "\u0628\u064a\u0628\u0627\u06a4\u0627"
    ],
    "name:und_x_variant":[
        "B\u012bb\u0101va",
        "Bibafa",
        "B\u012bb\u0101fa",
        "B\u012bb\u0101fah",
        "Bibava",
        "Bebava"
    ],
    "wof:name":"Bibafah",
    "wof:placetype":"locality"
},
  "geometry": {"coordinates":[43.28042,37.03425],"type":"Point"}
}