{
  "type": "Feature",
  "properties": {
    "gn:admin1_code":"10.0",
    "gn:admin2_code":"9166680.0",
    "gn:asciiname":"Shamar al Janubi",
    "gn:country_code":"IQ",
    "gn:dem":95,
    "gn:feature_class":"P",
    "gn:feature_code":"PPL",
    "gn:name":"Sh\u0101m\u0101r al Jan\u016bb\u012b",
    "gn:population":0,
    "gn:timezone":"Asia/Baghdad",
    "iso:country":"IQ",
    "name:ara_x_preferred":[
        "\u0634\u0627\u0645\u0627\u0631 \u0627\u0644\u062c\u0646\u0648\u0628\u064a"
    ],
    "name:und_x_variant":[
        "Sh\u0101m\u0101r al Jan\u016bb\u012b"
    ],
    "wof:name":"Shamar al Janubi",
    "wof:placetype":"locality"
},
  "geometry": {"coordinates":[45.45844,33.82237],"type":"Point"}
}