{
  "type": "Feature",
  "properties": {
    "gn:admin1_code":"6.0",
    "gn:admin2_code":"99358.0",
    "gn:asciiname":"Qal'at Sanad al Hasan",
    "gn:country_code":"IQ",
    "gn:dem":32,
    "gn:feature_class":"P",
    "gn:feature_code":"PPL",
    "gn:name":"Qal\u2018at Sanad al \u1e28asan",
    "gn:population":0,
    "gn:timezone":"Asia/Baghdad",
    "iso:country":"IQ",
    "name:und_x_variant":[
        "Qal\u2018at Sanad al \u1e28asan"
    ],
    "wof:name":"Qal'at Sanad al Hasan",
    "wof:placetype":"locality"
},
  "geometry": {"coordinates":[44.76361,32.31917],"type":"Point"}
}