{
  "type": "Feature",
  "properties": {
    "gn:admin1_code":"5.0",
    "gn:admin2_code":"97416.0",
    "gn:asciiname":"Kani Karmar",
    "gn:country_code":"IQ",
    "gn:dem":635,
    "gn:feature_class":"P",
    "gn:feature_code":"PPL",
    "gn:name":"K\u0101n\u012b Karmar",
    "gn:population":0,
    "gn:timezone":"Asia/Baghdad",
    "iso:country":"IQ",
    "name:ara_x_preferred":[
        "\u0643\u0627\u0646\u064a \u0643\u0631\u0645\u0631"
    ],
    "name:und_x_variant":[
        "K\u0101n\u012b Karmar",
        "K\u0101ni Gawhar"
    ],
    "wof:name":"Kani Karmar",
    "wof:placetype":"locality"
},
  "geometry": {"coordinates":[44.7375,35.74091],"type":"Point"}
}