{
  "type": "Feature",
  "properties": {
    "gn:admin1_code":"15.0",
    "gn:admin2_code":"9166608.0",
    "gn:asciiname":"Karkah",
    "gn:country_code":"IQ",
    "gn:dem":271,
    "gn:feature_class":"P",
    "gn:feature_code":"PPL",
    "gn:name":"Karkah",
    "gn:population":0,
    "gn:timezone":"Asia/Baghdad",
    "iso:country":"IQ",
    "name:ara_x_preferred":[
        "\u0643\u0631\u0643\u0647"
    ],
    "wof:name":"Karkah",
    "wof:placetype":"locality"
},
  "geometry": {"coordinates":[42.14458,35.83665999999999],"type":"Point"}
}