{
  "type": "Feature",
  "properties": {
    "gn:admin1_code":"11.0",
    "gn:admin2_code":"95444.0",
    "gn:asciiname":"Kawrah Ban",
    "gn:country_code":"IQ",
    "gn:dem":414,
    "gn:feature_class":"P",
    "gn:feature_code":"PPL",
    "gn:name":"Kawrah Ban",
    "gn:population":0,
    "gn:timezone":"Asia/Baghdad",
    "iso:country":"IQ",
    "name:ara_x_preferred":[
        "\u0643\u0648\u0631\u0629 \u0628\u0646"
    ],
    "name:kur_x_preferred":[
        "Gore Ben"
    ],
    "name:kur_x_variant":[
        "\u06af\u06c6\u0631\u06d5 \u0628\u06d5\u0646"
    ],
    "name:und_x_variant":[
        "K\u016br\u0101b\u0101n",
        "Gora Ban",
        "Koraban",
        "Kawrah Ban"
    ],
    "wof:name":"Kawrah Ban",
    "wof:placetype":"locality"
},
  "geometry": {"coordinates":[43.77202,36.22498],"type":"Point"}
}