{
  "type": "Feature",
  "properties": {
    "gn:admin1_code":"8.0",
    "gn:asciiname":"Kani Baskah",
    "gn:country_code":"IQ",
    "gn:dem":816,
    "gn:feature_class":"P",
    "gn:feature_code":"PPL",
    "gn:name":"K\u0101n\u012b Baskah",
    "gn:population":0,
    "gn:timezone":"Asia/Baghdad",
    "iso:country":"IQ",
    "name:und_x_variant":[
        "K\u0101nibaska",
        "K\u0101n\u012b S\u012bkah",
        "K\u0101n\u012b Baskah"
    ],
    "wof:name":"Kani Baskah",
    "wof:placetype":"locality"
},
  "geometry": {"coordinates":[43.28434,36.9208],"type":"Point"}
}