{
  "type": "Feature",
  "properties": {
    "gn:admin1_code":"17.0",
    "gn:admin2_code":"9166629.0",
    "gn:asciiname":"Sayyid Ibrahim",
    "gn:country_code":"IQ",
    "gn:dem":25,
    "gn:feature_class":"P",
    "gn:feature_code":"PPL",
    "gn:name":"Sayyid Ibr\u0101h\u012bm",
    "gn:population":0,
    "gn:timezone":"Asia/Baghdad",
    "iso:country":"IQ",
    "name:und_x_variant":[
        "Saiyid Ibr\u0101him",
        "Sayyid Ibr\u0101h\u012bm"
    ],
    "wof:name":"Sayyid Ibrahim",
    "wof:placetype":"locality"
},
  "geometry": {"coordinates":[44.42111,32.16],"type":"Point"}
}