{
  "type": "Feature",
  "properties": {
    "gn:admin1_code":"7.0",
    "gn:admin2_code":"99173.0",
    "gn:asciiname":"Shakr Hamid al Wajab",
    "gn:country_code":"IQ",
    "gn:dem":44,
    "gn:feature_class":"P",
    "gn:feature_code":"PPL",
    "gn:name":"Sh\u0101kr \u1e28am\u012bd al Wajab",
    "gn:population":0,
    "gn:timezone":"Asia/Baghdad",
    "iso:country":"IQ",
    "name:und_x_variant":[
        "Sh\u0101kr \u1e28am\u012bd al Wajab"
    ],
    "wof:name":"Shakr Hamid al Wajab",
    "wof:placetype":"locality"
},
  "geometry": {"coordinates":[44.33723,33.41167],"type":"Point"}
}