{
  "type": "Feature",
  "properties": {
    "gn:admin1_code":"6.0",
    "gn:admin2_code":"99358.0",
    "gn:asciiname":"Qaryat Jawdat Khalil",
    "gn:country_code":"IQ",
    "gn:dem":27,
    "gn:feature_class":"P",
    "gn:feature_code":"PPL",
    "gn:name":"Qaryat Jawdat Khal\u012bl",
    "gn:population":0,
    "gn:timezone":"Asia/Baghdad",
    "iso:country":"IQ",
    "name:ara_x_preferred":[
        "\u0642\u0631\u064a\u0629 \u062c\u0648\u062f\u0629 \u062e\u0644\u064a\u0644"
    ],
    "name:und_x_variant":[
        "Qaryat Jawdat Khal\u012bl"
    ],
    "wof:name":"Qaryat Jawdat Khalil",
    "wof:placetype":"locality"
},
  "geometry": {"coordinates":[44.87172,32.38805],"type":"Point"}
}