{
  "type": "Feature",
  "properties": {
    "gn:admin1_code":"5.0",
    "gn:admin2_code":"98464.0",
    "gn:asciiname":"Kuchuk Zerguez",
    "gn:cc2":"IQ",
    "gn:country_code":"IQ",
    "gn:dem":914,
    "gn:feature_class":"P",
    "gn:feature_code":"PPL",
    "gn:name":"Kuchuk Zerguez",
    "gn:population":0,
    "gn:timezone":"Asia/Baghdad",
    "iso:country":"IQ",
    "name:und_x_variant":[
        "Kuchik Zerguez"
    ],
    "wof:name":"Kuchuk Zerguez",
    "wof:placetype":"locality"
},
  "geometry": {"coordinates":[45.48333,35.38333],"type":"Point"}
}