{
  "type": "Feature",
  "properties": {
    "gn:admin1_code":"11.0",
    "gn:admin2_code":"9166534.0",
    "gn:asciiname":"Shtaynah",
    "gn:country_code":"IQ",
    "gn:dem":953,
    "gn:feature_class":"P",
    "gn:feature_code":"PPL",
    "gn:name":"Shtaynah",
    "gn:population":0,
    "gn:timezone":"Asia/Baghdad",
    "iso:country":"IQ",
    "name:ara_x_preferred":[
        "\u0634\u062a\u064a\u0646\u06d5"
    ],
    "name:kur_x_preferred":[
        "Sh\u00eatne"
    ],
    "name:kur_x_variant":[
        "\u0634\u06ce\u062a\u0646\u06d5",
        "Sht\u00eene"
    ],
    "name:und_x_variant":[
        "Sh\u0113tna",
        "Shtaynah",
        "Shtina",
        "Shetna"
    ],
    "wof:name":"Shtaynah",
    "wof:placetype":"locality"
},
  "geometry": {"coordinates":[44.44435,36.78527],"type":"Point"}
}