{
  "type": "Feature",
  "properties": {
    "gn:admin1_code":"6.0",
    "gn:admin2_code":"6818313.0",
    "gn:asciiname":"Qaryat Hamzah al Khisarah",
    "gn:country_code":"IQ",
    "gn:dem":37,
    "gn:feature_class":"P",
    "gn:feature_code":"PPL",
    "gn:name":"Qaryat \u1e28amzah al Khis\u0101rah",
    "gn:population":0,
    "gn:timezone":"Asia/Baghdad",
    "iso:country":"IQ",
    "name:ara_x_preferred":[
        "\u0642\u0631\u064a\u0629 \u062d\u0645\u0632\u0647 \u0627\u0644\u062e\u0633\u0627\u0631\u0647"
    ],
    "name:und_x_variant":[
        "Hamza",
        "\u1e28azah",
        "\u1e28amzah",
        "Qaryat \u1e28amzah al Khis\u0101rah"
    ],
    "wof:name":"Qaryat Hamzah al Khisarah",
    "wof:placetype":"locality"
},
  "geometry": {"coordinates":[44.27889,32.81974],"type":"Point"}
}