{
  "type": "Feature",
  "properties": {
    "gn:admin1_code":"10.0",
    "gn:admin2_code":"9166680.0",
    "gn:asciiname":"Ahmad Khamis",
    "gn:country_code":"IQ",
    "gn:dem":46,
    "gn:feature_class":"P",
    "gn:feature_code":"PPL",
    "gn:name":"A\u1e29mad Kham\u012bs",
    "gn:population":0,
    "gn:timezone":"Asia/Baghdad",
    "iso:country":"IQ",
    "name:ara_x_preferred":[
        "\u0627\u062d\u0645\u062f \u062e\u0645\u064a\u0633"
    ],
    "name:und_x_variant":[
        "A\u1e29mad Kham\u012bs"
    ],
    "wof:name":"Ahmad Khamis",
    "wof:placetype":"locality"
},
  "geometry": {"coordinates":[44.84208,33.72393],"type":"Point"}
}