{
  "type": "Feature",
  "properties": {
    "gn:admin1_code":"10.0",
    "gn:admin2_code":"9166680.0",
    "gn:asciiname":"Khalaf 'Alwan al Hayad",
    "gn:country_code":"IQ",
    "gn:dem":95,
    "gn:feature_class":"P",
    "gn:feature_code":"PPL",
    "gn:name":"Khalaf \u2018Alw\u0101n al \u1e28ay\u0101d",
    "gn:population":0,
    "gn:timezone":"Asia/Baghdad",
    "iso:country":"IQ",
    "name:ara_x_preferred":[
        "\u062e\u0644\u0641 \u0639\u0644\u0648\u0627\u0646 \u0627\u0644\u062d\u064a\u0627\u062f"
    ],
    "name:und_x_variant":[
        "Khalaf \u2018Alw\u0101n al \u1e28ay\u0101d"
    ],
    "wof:name":"Khalaf 'Alwan al Hayad",
    "wof:placetype":"locality"
},
  "geometry": {"coordinates":[45.75024000000001,33.52936],"type":"Point"}
}