{
  "type": "Feature",
  "properties": {
    "gn:admin1_code":"15.0",
    "gn:admin2_code":"98820.0",
    "gn:asciiname":"Suse",
    "gn:country_code":"IQ",
    "gn:dem":451,
    "gn:feature_class":"P",
    "gn:feature_code":"PPL",
    "gn:name":"Suse",
    "gn:population":0,
    "gn:timezone":"Asia/Baghdad",
    "iso:country":"IQ",
    "name:deu_x_preferred":[
        "Suse"
    ],
    "name:fra_x_preferred":[
        "Suse"
    ],
    "name:kur_x_preferred":[
        "Sus\u00ea"
    ],
    "name:kur_x_variant":[
        "\u0633\u0648\u0633\u06ce"
    ],
    "name:nep_x_preferred":[
        "\u0938\u0941\u091c\u0947"
    ],
    "wof:name":"Suse",
    "wof:placetype":"locality"
},
  "geometry": {"coordinates":[44.25031,36.7362],"type":"Point"}
}