{
  "type": "Feature",
  "properties": {
    "gn:admin1_code":"18.0",
    "gn:admin2_code":"6805736.0",
    "gn:asciiname":"'Aziz 'Atiyah",
    "gn:country_code":"IQ",
    "gn:dem":47,
    "gn:feature_class":"P",
    "gn:feature_code":"PPL",
    "gn:name":"\u2018Az\u012bz \u2018A\u0163\u012byah",
    "gn:population":0,
    "gn:timezone":"Asia/Baghdad",
    "iso:country":"IQ",
    "name:ara_x_preferred":[
        "\u0639\u0632\u064a\u0632 \u0639\u0637\u064a\u0629"
    ],
    "name:und_x_variant":[
        "\u2018Az\u012bz \u2018A\u0163\u012byah"
    ],
    "wof:name":"'Aziz 'Atiyah",
    "wof:placetype":"locality"
},
  "geometry": {"coordinates":[44.27509000000001,33.95788],"type":"Point"}
}