{
  "type": "Feature",
  "properties": {
    "gn:admin1_code":"8.0",
    "gn:admin2_code":"89569.0",
    "gn:asciiname":"Dar Huzan",
    "gn:country_code":"IQ",
    "gn:dem":508,
    "gn:feature_class":"P",
    "gn:feature_code":"PPL",
    "gn:name":"Dar Huzan",
    "gn:population":0,
    "gn:timezone":"Asia/Baghdad",
    "iso:country":"IQ",
    "name:ara_x_preferred":[
        "\u062f\u0627\u0631 \u0647\u0648\u0632\u0627\u0646"
    ],
    "name:kur_x_preferred":[
        "Dar Hozan"
    ],
    "name:kur_x_variant":[
        "\u062f\u0627\u0631 \u0647\u06c6\u0632\u0627\u0646",
        "Dar Huzan"
    ],
    "name:und_x_variant":[
        "Darhawzan",
        "D\u0101rh\u014dz\u0101n",
        "D\u0101r Hawz\u0101n",
        "Darhuzan"
    ],
    "wof:name":"Dar Huzan",
    "wof:placetype":"locality"
},
  "geometry": {"coordinates":[42.75202,37.17069],"type":"Point"}
}