{
  "type": "Feature",
  "properties": {
    "gn:admin1_code":"13.0",
    "gn:admin2_code":"6770659.0",
    "gn:asciiname":"Qaryat ad Dughaylah",
    "gn:country_code":"IQ",
    "gn:dem":182,
    "gn:feature_class":"P",
    "gn:feature_code":"PPL",
    "gn:name":"Qaryat ad Dughaylah",
    "gn:population":0,
    "gn:timezone":"Asia/Baghdad",
    "iso:country":"IQ",
    "name:ara_x_preferred":[
        "\u0642\u0631\u064a\u0629 \u0627\u0644\u062f\u063a\u064a\u0644\u0629"
    ],
    "name:und_x_variant":[
        "Digail",
        "Dijayl",
        "Duqayl",
        "Dujayl",
        "Qaryat ad Dughaylah"
    ],
    "wof:name":"Qaryat ad Dughaylah",
    "wof:placetype":"locality"
},
  "geometry": {"coordinates":[43.81092,35.24440999999999],"type":"Point"}
}