{
  "type": "Feature",
  "properties": {
    "gn:admin1_code":"10.0",
    "gn:admin2_code":"99063.0",
    "gn:asciiname":"'Abd Allah",
    "gn:country_code":"IQ",
    "gn:dem":54,
    "gn:feature_class":"P",
    "gn:feature_code":"PPL",
    "gn:name":"\u2018Abd All\u0101h",
    "gn:population":0,
    "gn:timezone":"Asia/Baghdad",
    "iso:country":"IQ",
    "name:ara_x_preferred":[
        "\u0639\u0628\u062f \u0627\u0644\u0644\u0647"
    ],
    "name:ara_x_variant":[
        "\u2018Abd All\u0101h"
    ],
    "name:und_x_variant":[
        "Bust\u0101n \u2018Abd All\u0101h",
        "\u2018Abdullah Effendi",
        "\u2018Abd All\u0101h Afand\u012b"
    ],
    "wof:name":"'Abd Allah",
    "wof:placetype":"locality"
},
  "geometry": {"coordinates":[44.70768,33.97422],"type":"Point"}
}