{
  "type": "Feature",
  "properties": {
    "gn:admin1_code":"6.0",
    "gn:admin2_code":"6818313.0",
    "gn:asciiname":"Nasir Haran",
    "gn:country_code":"IQ",
    "gn:dem":30,
    "gn:feature_class":"P",
    "gn:feature_code":"PPL",
    "gn:name":"N\u0101\u015fir \u1e28ar\u0101n",
    "gn:population":0,
    "gn:timezone":"Asia/Baghdad",
    "iso:country":"IQ",
    "name:ara_x_preferred":[
        "\u0646\u0627\u0635\u0631\u062d\u0631\u0627\u0646"
    ],
    "name:und_x_variant":[
        "N\u0101\u015fir \u1e28ar\u0101n"
    ],
    "wof:name":"Nasir Haran",
    "wof:placetype":"locality"
},
  "geometry": {"coordinates":[44.49196,32.82673],"type":"Point"}
}