{
  "type": "Feature",
  "properties": {
    "gn:admin1_code":"5.0",
    "gn:admin2_code":"97416.0",
    "gn:asciiname":"Awah Bawrak",
    "gn:country_code":"IQ",
    "gn:dem":583,
    "gn:feature_class":"P",
    "gn:feature_code":"PPL",
    "gn:name":"Awah Bawrak",
    "gn:population":0,
    "gn:timezone":"Asia/Baghdad",
    "iso:country":"IQ",
    "name:ara_x_preferred":[
        "\u0627\u0648\u0647 \u0628\u0648\u0631\u0643"
    ],
    "name:kur_x_preferred":[
        "Awe Borke"
    ],
    "name:kur_x_variant":[
        "\u0626\u0627\u0648\u06d5 \u0628\u06c6\u0631\u0643\u06d5"
    ],
    "name:und_x_variant":[
        "Awb\u016br\u012b",
        "Awah Bawrak",
        "\u0100wb\u014draka"
    ],
    "wof:name":"Awah Bawrak",
    "wof:placetype":"locality"
},
  "geometry": {"coordinates":[45.02325,35.31688],"type":"Point"}
}