{
  "type": "Feature",
  "properties": {
    "gn:admin1_code":"13.0",
    "gn:admin2_code":"6770659.0",
    "gn:asciiname":"Qaryat Mahuz",
    "gn:country_code":"IQ",
    "gn:dem":195,
    "gn:feature_class":"P",
    "gn:feature_code":"PPL",
    "gn:name":"Qaryat M\u0101\u1e29\u016bz",
    "gn:population":0,
    "gn:timezone":"Asia/Baghdad",
    "iso:country":"IQ",
    "name:ara_x_preferred":[
        "\u0642\u0631\u064a\u0629 \u0645\u0627\u062d\u0648\u0632"
    ],
    "name:ara_x_variant":[
        "\u0645\u0627\u0647\u0648\u0632"
    ],
    "name:kur_x_preferred":[
        "Maho\u1e5f"
    ],
    "name:kur_x_variant":[
        "\u0645\u0627\u0647\u06c6\u0695"
    ],
    "name:und_x_variant":[
        "Tel Mahus",
        "Tall Ma\u1e29\u016bs",
        "Tall M\u0101\u1e29\u016bz",
        "Qaryat M\u0101\u1e29\u016bz",
        "M\u0101\u1e29\u016bz",
        "M\u0101h\u016bs",
        "M\u0101h\u016bz",
        "Mahor"
    ],
    "wof:name":"Qaryat Mahuz",
    "wof:placetype":"locality"
},
  "geometry": {"coordinates":[43.83967,35.49173],"type":"Point"}
}