{
  "type": "Feature",
  "properties": {
    "gn:admin1_code":"18.0",
    "gn:admin2_code":"90148.0",
    "gn:asciiname":"Qaryat al Jisat",
    "gn:country_code":"IQ",
    "gn:dem":105,
    "gn:feature_class":"P",
    "gn:feature_code":"PPL",
    "gn:name":"Qaryat al J\u012bs\u0101t",
    "gn:population":0,
    "gn:timezone":"Asia/Baghdad",
    "iso:country":"IQ",
    "name:ara_x_preferred":[
        "\u0642\u0631\u064a\u0629 \u0627\u0644\u062c\u064a\u0633\u0627\u062a"
    ],
    "name:und_x_variant":[
        "Qaryat al J\u012bs\u0101t"
    ],
    "wof:name":"Qaryat al Jisat",
    "wof:placetype":"locality"
},
  "geometry": {"coordinates":[43.51899,34.87948],"type":"Point"}
}