{
  "type": "Feature",
  "properties": {
    "gn:admin1_code":"7.0",
    "gn:admin2_code":"99101.0",
    "gn:asciiname":"Al Jaybahi",
    "gn:country_code":"IQ",
    "gn:dem":35,
    "gn:feature_class":"P",
    "gn:feature_code":"PPL",
    "gn:name":"Al Jayba\u1e29\u012b",
    "gn:population":0,
    "gn:timezone":"Asia/Baghdad",
    "iso:country":"IQ",
    "name:und_x_variant":[
        "Al Jayba\u1e29\u012b"
    ],
    "wof:name":"Al Jaybahi",
    "wof:placetype":"locality"
},
  "geometry": {"coordinates":[44.41958,33.16589],"type":"Point"}
}