{
  "type": "Feature",
  "properties": {
    "gn:admin1_code":"10.0",
    "gn:admin2_code":"9166680.0",
    "gn:asciiname":"Nasif an Nasir",
    "gn:country_code":"IQ",
    "gn:dem":40,
    "gn:feature_class":"P",
    "gn:feature_code":"PPL",
    "gn:name":"Na\u015f\u012bf an N\u0101\u015fir",
    "gn:population":0,
    "gn:timezone":"Asia/Baghdad",
    "iso:country":"IQ",
    "name:ara_x_preferred":[
        "\u0646\u0635\u064a\u0641 \u0627\u0644\u0646\u0627\u0635\u0631"
    ],
    "name:und_x_variant":[
        "Na\u015f\u012bf an N\u0101\u015fir"
    ],
    "wof:name":"Nasif an Nasir",
    "wof:placetype":"locality"
},
  "geometry": {"coordinates":[45.091,33.61102],"type":"Point"}
}