{
  "type": "Feature",
  "properties": {
    "gn:admin1_code":"2.0",
    "gn:admin2_code":"99534.0",
    "gn:asciiname":"Sayyid Tahir",
    "gn:country_code":"IQ",
    "gn:dem":2,
    "gn:feature_class":"P",
    "gn:feature_code":"PPL",
    "gn:name":"Sayyid \u0162\u0101hir",
    "gn:population":0,
    "gn:timezone":"Asia/Baghdad",
    "iso:country":"IQ",
    "name:und_x_variant":[
        "Sayyid \u0162\u0101hir"
    ],
    "wof:name":"Sayyid Tahir",
    "wof:placetype":"locality"
},
  "geometry": {"coordinates":[47.72528,30.72694000000001],"type":"Point"}
}