{
  "type": "Feature",
  "properties": {
    "gn:admin1_code":"10.0",
    "gn:admin2_code":"99063.0",
    "gn:asciiname":"Ahmad Majid",
    "gn:cc2":"IQ",
    "gn:country_code":"IQ",
    "gn:dem":45,
    "gn:feature_class":"P",
    "gn:feature_code":"PPL",
    "gn:name":"A\u1e29mad Maj\u012bd",
    "gn:population":0,
    "gn:timezone":"Asia/Baghdad",
    "iso:country":"IQ",
    "name:und_x_variant":[
        "Ahad Majid",
        "A\u1e29mad Maj\u012bd"
    ],
    "wof:name":"Ahmad Majid",
    "wof:placetype":"locality"
},
  "geometry": {"coordinates":[44.73333,33.78333],"type":"Point"}
}