{
  "type": "Feature",
  "properties": {
    "gn:admin1_code":"18.0",
    "gn:admin2_code":"9167093.0",
    "gn:asciiname":"Badr 'Awid",
    "gn:country_code":"IQ",
    "gn:dem":77,
    "gn:feature_class":"P",
    "gn:feature_code":"PPL",
    "gn:name":"Badr \u2018Aw\u012bd",
    "gn:population":0,
    "gn:timezone":"Asia/Baghdad",
    "iso:country":"IQ",
    "name:ara_x_preferred":[
        "\u0628\u062f\u0631 \u0639\u0648\u064a\u062f"
    ],
    "name:und_x_variant":[
        "Badr \u2018Aw\u012bd"
    ],
    "wof:name":"Badr 'Awid",
    "wof:placetype":"locality"
},
  "geometry": {"coordinates":[43.64801,34.05899],"type":"Point"}
}