{
  "type": "Feature",
  "properties": {
    "gn:admin1_code":"18.0",
    "gn:admin2_code":"90148.0",
    "gn:asciiname":"Khalil Halihal",
    "gn:country_code":"IQ",
    "gn:dem":138,
    "gn:feature_class":"P",
    "gn:feature_code":"PPL",
    "gn:name":"Khal\u012bl \u1e28al\u012b\u1e29al",
    "gn:population":0,
    "gn:timezone":"Asia/Baghdad",
    "iso:country":"IQ",
    "name:ara_x_preferred":[
        "\u062e\u0644\u064a\u0644 \u062d\u0644\u064a\u062d\u0644"
    ],
    "name:und_x_variant":[
        "Khal\u012bl \u1e28al\u012b\u1e29al"
    ],
    "wof:name":"Khalil Halihal",
    "wof:placetype":"locality"
},
  "geometry": {"coordinates":[43.8364,34.82859000000001],"type":"Point"}
}