{
  "type": "Feature",
  "properties": {
    "gn:admin1_code":"15.0",
    "gn:admin2_code":"9166620.0",
    "gn:asciiname":"Ahuwaydir",
    "gn:country_code":"IQ",
    "gn:dem":340,
    "gn:feature_class":"P",
    "gn:feature_code":"PPL",
    "gn:name":"A\u1e29uwaydir",
    "gn:population":0,
    "gn:timezone":"Asia/Baghdad",
    "iso:country":"IQ",
    "name:ara_x_preferred":[
        "\u0627\u062d\u0648\u064a\u062f\u0631"
    ],
    "name:und_x_variant":[
        "A\u1e29uwaydir"
    ],
    "wof:name":"Ahuwaydir",
    "wof:placetype":"locality"
},
  "geometry": {"coordinates":[41.66985,36.10342],"type":"Point"}
}