{
  "type": "Feature",
  "properties": {
    "gn:admin1_code":"15.0",
    "gn:admin2_code":"90392.0",
    "gn:asciiname":"Shafaq",
    "gn:country_code":"IQ",
    "gn:dem":401,
    "gn:feature_class":"P",
    "gn:feature_code":"PPL",
    "gn:name":"Shafaq",
    "gn:population":0,
    "gn:timezone":"Asia/Baghdad",
    "iso:country":"IQ",
    "name:ara_x_preferred":[
        "\u0634\u0641\u0642"
    ],
    "name:kur_x_preferred":[
        "Shefeq"
    ],
    "name:kur_x_variant":[
        "\u0634\u06d5\u0641\u06d5\u0642"
    ],
    "wof:name":"Shafaq",
    "wof:placetype":"locality"
},
  "geometry": {"coordinates":[42.16312,36.59326],"type":"Point"}
}