{
  "type": "Feature",
  "properties": {
    "gn:admin1_code":"10.0",
    "gn:admin2_code":"97988.0",
    "gn:asciiname":"Hudaydan",
    "gn:country_code":"IQ",
    "gn:dem":41,
    "gn:feature_class":"P",
    "gn:feature_code":"PPL",
    "gn:name":"\u1e28udayd\u0101n",
    "gn:population":0,
    "gn:timezone":"Asia/Baghdad",
    "iso:country":"IQ",
    "name:ara_x_preferred":[
        "\u062d\u062f\u064a\u062f\u0627\u0646"
    ],
    "name:und_x_variant":[
        "Qaryat \u1e28udayd\u0101n",
        "\u0642\u0631\u064a\u0629 \u062d\u062f\u064a\u062f\u0627\u0646",
        "\u1e28udayd\u0101n"
    ],
    "wof:name":"Hudaydan",
    "wof:placetype":"locality"
},
  "geometry": {"coordinates":[44.5028,33.55812],"type":"Point"}
}