{
  "type": "Feature",
  "properties": {
    "gn:admin1_code":"7.0",
    "gn:admin2_code":"9166569.0",
    "gn:asciiname":"Muhammad al 'Awdah",
    "gn:country_code":"IQ",
    "gn:dem":40,
    "gn:feature_class":"P",
    "gn:feature_code":"PPL",
    "gn:name":"Mu\u1e29ammad al \u2018Awdah",
    "gn:population":0,
    "gn:timezone":"Asia/Baghdad",
    "iso:country":"IQ",
    "name:ara_x_preferred":[
        "\u0645\u062d\u0645\u062f \u0627\u0644\u0639\u0648\u062f\u0629"
    ],
    "name:und_x_variant":[
        "Mu\u1e29ammad al \u2018Awdah"
    ],
    "wof:name":"Muhammad al 'Awdah",
    "wof:placetype":"locality"
},
  "geometry": {"coordinates":[44.29166,33.61688],"type":"Point"}
}