{
  "type": "Feature",
  "properties": {
    "gn:admin1_code":"6.0",
    "gn:admin2_code":"6818313.0",
    "gn:asciiname":"'Arab as Sahib Turad",
    "gn:country_code":"IQ",
    "gn:dem":36,
    "gn:feature_class":"P",
    "gn:feature_code":"PPL",
    "gn:name":"\u2018Arab a\u015f \u015e\u0101\u1e29ib \u0162ur\u0101d",
    "gn:population":0,
    "gn:timezone":"Asia/Baghdad",
    "iso:country":"IQ",
    "name:ara_x_preferred":[
        "\u0639\u0631\u0628 \u0627\u0644\u0635\u0627\u062d\u0628 \u0637\u0631\u0627\u062f"
    ],
    "name:und_x_variant":[
        "\u2018Arab a\u015f \u015e\u0101\u1e29ib \u0162ur\u0101d"
    ],
    "wof:name":"'Arab as Sahib Turad",
    "wof:placetype":"locality"
},
  "geometry": {"coordinates":[44.38076,32.82915999999999],"type":"Point"}
}