{
  "type": "Feature",
  "properties": {
    "gn:admin1_code":"10.0",
    "gn:admin2_code":"94296.0",
    "gn:asciiname":"Tall Hanish",
    "gn:country_code":"IQ",
    "gn:dem":173,
    "gn:feature_class":"P",
    "gn:feature_code":"PPL",
    "gn:name":"Tall \u1e28anish",
    "gn:population":0,
    "gn:timezone":"Asia/Baghdad",
    "iso:country":"IQ",
    "name:ara_x_preferred":[
        "\u062a\u0644 \u062d\u0646\u0634"
    ],
    "name:und_x_variant":[
        "Tall \u1e28anish"
    ],
    "wof:name":"Tall Hanish",
    "wof:placetype":"locality"
},
  "geometry": {"coordinates":[44.83186,34.67809],"type":"Point"}
}