{
  "type": "Feature",
  "properties": {
    "gn:admin1_code":"10.0",
    "gn:admin2_code":"94590.0",
    "gn:asciiname":"Qadir Jawamir",
    "gn:country_code":"IQ",
    "gn:dem":126,
    "gn:feature_class":"P",
    "gn:feature_code":"PPL",
    "gn:name":"Q\u0101dir Jaw\u0101m\u012br",
    "gn:population":0,
    "gn:timezone":"Asia/Baghdad",
    "iso:country":"IQ",
    "name:ara_x_preferred":[
        "\u0642\u0627\u062f\u0631 \u062c\u0648\u0627\u0645\u064a\u0631"
    ],
    "name:und_x_variant":[
        "Q\u0101dir Juway\u012bd",
        "\u0642\u0627\u062f\u0631 \u062c\u0648\u064a\u062f",
        "Q\u0101dir Jaw\u0101m\u012br"
    ],
    "wof:name":"Qadir Jawamir",
    "wof:placetype":"locality"
},
  "geometry": {"coordinates":[45.19823,34.10179],"type":"Point"}
}