{
  "type": "Feature",
  "properties": {
    "gn:admin1_code":"16.0",
    "gn:admin2_code":"99132.0",
    "gn:asciiname":"Thamir",
    "gn:country_code":"IQ",
    "gn:dem":15,
    "gn:feature_class":"P",
    "gn:feature_code":"PPL",
    "gn:name":"Th\u0101mir",
    "gn:population":0,
    "gn:timezone":"Asia/Baghdad",
    "iso:country":"IQ",
    "name:ara_x_preferred":[
        "\u062b\u0627\u0645\u0631"
    ],
    "name:ara_x_variant":[
        "Th\u0101mir"
    ],
    "wof:name":"Thamir",
    "wof:placetype":"locality"
},
  "geometry": {"coordinates":[46.11129,32.38659000000001],"type":"Point"}
}