{
  "type": "Feature",
  "properties": {
    "gn:admin1_code":"6.0",
    "gn:admin2_code":"99358.0",
    "gn:asciiname":"Kazim Dahash",
    "gn:country_code":"IQ",
    "gn:dem":26,
    "gn:feature_class":"P",
    "gn:feature_code":"PPL",
    "gn:name":"K\u0101z\u0327im Dahash",
    "gn:population":0,
    "gn:timezone":"Asia/Baghdad",
    "iso:country":"IQ",
    "name:ara_x_preferred":[
        "\u0643\u0627\u0638\u0645 \u062f\u0647\u0634"
    ],
    "name:und_x_variant":[
        "K\u0101z\u0327im Dahash"
    ],
    "wof:name":"Kazim Dahash",
    "wof:placetype":"locality"
},
  "geometry": {"coordinates":[44.93062000000001,32.32725],"type":"Point"}
}