{
  "type": "Feature",
  "properties": {
    "gn:admin1_code":"5.0",
    "gn:admin2_code":"97416.0",
    "gn:asciiname":"Mahmuday",
    "gn:country_code":"IQ",
    "gn:dem":570,
    "gn:feature_class":"P",
    "gn:feature_code":"PPL",
    "gn:name":"Ma\u1e29m\u016bday",
    "gn:population":0,
    "gn:timezone":"Asia/Baghdad",
    "iso:country":"IQ",
    "name:ara_x_preferred":[
        "\u0645\u062d\u0645\u0648\u062f\u064a"
    ],
    "name:und_x_variant":[
        "Ma\u1e29m\u016bday",
        "Me\u1e27mud\u00ea",
        "Mahmoodi",
        "\u0645\u0647 \u062d\u0645\u0648\u062f\u06ce"
    ],
    "wof:name":"Mahmuday",
    "wof:placetype":"locality"
},
  "geometry": {"coordinates":[45.10969,35.41083],"type":"Point"}
}