{
  "type": "Feature",
  "properties": {
    "gn:admin1_code":"6.0",
    "gn:admin2_code":"99358.0",
    "gn:asciiname":"Al Sukaytiri",
    "gn:country_code":"IQ",
    "gn:dem":26,
    "gn:feature_class":"P",
    "gn:feature_code":"PPL",
    "gn:name":"\u0100l Sukay\u0163ir\u012b",
    "gn:population":0,
    "gn:timezone":"Asia/Baghdad",
    "iso:country":"IQ",
    "name:ara_x_preferred":[
        "\u0627\u0644 \u0633\u0643\u064a\u0637\u0631\u064a"
    ],
    "name:und_x_variant":[
        "\u0100l Sukay\u0163ir\u012b"
    ],
    "wof:name":"Al Sukaytiri",
    "wof:placetype":"locality"
},
  "geometry": {"coordinates":[44.59393,32.25498],"type":"Point"}
}