{
  "type": "Feature",
  "properties": {
    "gn:admin1_code":"18.0",
    "gn:admin2_code":"6872046.0",
    "gn:asciiname":"Al Hajj Kazim",
    "gn:country_code":"IQ",
    "gn:dem":127,
    "gn:feature_class":"P",
    "gn:feature_code":"PPL",
    "gn:name":"Al \u1e28\u0101jj K\u0101z\u0327im",
    "gn:population":0,
    "gn:timezone":"Asia/Baghdad",
    "iso:country":"IQ",
    "name:ara_x_preferred":[
        "\u0627\u0644\u062d\u0627\u062c \u0643\u0627\u0638\u0645"
    ],
    "name:ara_x_variant":[
        "Al \u1e28\u0101jj K\u0101z\u0327im"
    ],
    "wof:name":"Al Hajj Kazim",
    "wof:placetype":"locality"
},
  "geometry": {"coordinates":[43.08916,35.08949],"type":"Point"}
}