{
  "type": "Feature",
  "properties": {
    "gn:admin1_code":"11.0",
    "gn:admin2_code":"93817.0",
    "gn:asciiname":"Qawagh",
    "gn:country_code":"IQ",
    "gn:dem":281,
    "gn:feature_class":"P",
    "gn:feature_code":"PPLL",
    "gn:name":"Qawagh",
    "gn:population":0,
    "gn:timezone":"Asia/Baghdad",
    "iso:country":"IQ",
    "name:ara_x_preferred":[
        "\u0642\u0627\u0648\u063a"
    ],
    "name:kur_x_preferred":[
        "Qawagh"
    ],
    "name:kur_x_variant":[
        "\u0642\u0627\u0648\u0627\u063a"
    ],
    "name:und_x_variant":[
        "Q\u0101w\u0101gh",
        "Q\u0101wagh"
    ],
    "wof:name":"Qawagh",
    "wof:placetype":"locality"
},
  "geometry": {"coordinates":[43.69313,36.15187],"type":"Point"}
}