{
  "type": "Feature",
  "properties": {
    "gn:admin1_code":"6.0",
    "gn:admin2_code":"6818313.0",
    "gn:asciiname":"Tu'ays Jadid",
    "gn:country_code":"IQ",
    "gn:dem":26,
    "gn:feature_class":"P",
    "gn:feature_code":"PPL",
    "gn:name":"\u0162u\u2018ays Jad\u012bd",
    "gn:population":0,
    "gn:timezone":"Asia/Baghdad",
    "iso:country":"IQ",
    "name:ara_x_preferred":[
        "\u0637\u0639\u064a\u0633 \u062c\u062f\u064a\u062f"
    ],
    "name:und_x_variant":[
        "\u0162u\u2018ays Jad\u012bd"
    ],
    "wof:name":"Tu'ays Jadid",
    "wof:placetype":"locality"
},
  "geometry": {"coordinates":[44.91071,32.47781],"type":"Point"}
}