{
  "type": "Feature",
  "properties": {
    "gn:admin1_code":"9.0",
    "gn:admin2_code":"90509.0",
    "gn:asciiname":"Bahr",
    "gn:cc2":"IQ",
    "gn:country_code":"IQ",
    "gn:dem":4,
    "gn:feature_class":"P",
    "gn:feature_code":"PPL",
    "gn:name":"Ba\u1e29r",
    "gn:population":0,
    "gn:timezone":"Asia/Baghdad",
    "iso:country":"IQ",
    "name:ceb_x_preferred":[
        "Bahr"
    ],
    "name:deu_x_preferred":[
        "Bahr"
    ],
    "name:fin_x_preferred":[
        "Bahr"
    ],
    "name:fra_x_preferred":[
        "Bahr"
    ],
    "name:pol_x_preferred":[
        "Bahr"
    ],
    "name:por_x_preferred":[
        "Bahr"
    ],
    "name:slv_x_preferred":[
        "Bahr"
    ],
    "name:swe_x_preferred":[
        "Bahr"
    ],
    "name:und_x_variant":[
        "Nahr",
        "Ba\u1e29r"
    ],
    "wof:name":"Bahr",
    "wof:placetype":"locality"
},
  "geometry": {"coordinates":[46.55,30.83333],"type":"Point"}
}