{
  "type": "Feature",
  "properties": {
    "gn:admin1_code":"18.0",
    "gn:admin2_code":"6805736.0",
    "gn:asciiname":"'Ali Faris",
    "gn:country_code":"IQ",
    "gn:dem":55,
    "gn:feature_class":"P",
    "gn:feature_code":"PPL",
    "gn:name":"\u2018Al\u012b F\u0101ris",
    "gn:population":0,
    "gn:timezone":"Asia/Baghdad",
    "iso:country":"IQ",
    "name:ara_x_preferred":[
        "\u0639\u0644\u064a \u0641\u0627\u0631\u0633"
    ],
    "name:ara_x_variant":[
        "\u2018Al\u012b F\u0101ris"
    ],
    "wof:name":"'Ali Faris",
    "wof:placetype":"locality"
},
  "geometry": {"coordinates":[43.94061,33.97692],"type":"Point"}
}