{
  "type": "Feature",
  "properties": {
    "gn:admin1_code":"8.0",
    "gn:admin2_code":"99612.0",
    "gn:asciiname":"Barzanik",
    "gn:country_code":"IQ",
    "gn:dem":872,
    "gn:feature_class":"P",
    "gn:feature_code":"PPLL",
    "gn:name":"Barzanik",
    "gn:population":0,
    "gn:timezone":"Asia/Baghdad",
    "iso:country":"IQ",
    "name:kur_x_preferred":[
        "Barzanik"
    ],
    "name:kur_x_variant":[
        "\u0628\u0627\u0631\u0632\u0627\u0646\u0643"
    ],
    "name:und_x_variant":[
        "Barzank"
    ],
    "wof:name":"Barzanik",
    "wof:placetype":"locality"
},
  "geometry": {"coordinates":[43.14402000000001,37.31151],"type":"Point"}
}