{
  "type": "Feature",
  "properties": {
    "gn:admin1_code":"15.0",
    "gn:admin2_code":"9166620.0",
    "gn:asciiname":"Nukhsat `Awaj",
    "gn:country_code":"IQ",
    "gn:dem":525,
    "gn:feature_class":"P",
    "gn:feature_code":"PPL",
    "gn:name":"Nukhsat \u2018Awaj",
    "gn:population":0,
    "gn:timezone":"Asia/Baghdad",
    "iso:country":"IQ",
    "name:ara_x_preferred":[
        "\u0646\u062e\u0633\u0629 \u0639\u0648\u062c"
    ],
    "name:und_x_variant":[
        "Nukhsat \u2018Awaj"
    ],
    "wof:name":"Nukhsat `Awaj",
    "wof:placetype":"locality"
},
  "geometry": {"coordinates":[41.9162,36.45998],"type":"Point"}
}