{
  "type": "Feature",
  "properties": {
    "gn:admin1_code":"1.0",
    "gn:admin2_code":"98718.0",
    "gn:asciiname":"Habib an Najm",
    "gn:cc2":"IQ",
    "gn:country_code":"IQ",
    "gn:dem":51,
    "gn:feature_class":"P",
    "gn:feature_code":"PPL",
    "gn:name":"\u1e28ab\u012bb an Najm",
    "gn:population":0,
    "gn:timezone":"Asia/Baghdad",
    "iso:country":"IQ",
    "name:und_x_variant":[
        "Hab\u012bb an Naim",
        "\u1e28ab\u012bb an Najm"
    ],
    "wof:name":"Habib an Najm",
    "wof:placetype":"locality"
},
  "geometry": {"coordinates":[43.27778,33.49306],"type":"Point"}
}