{
  "type": "Feature",
  "properties": {
    "gn:admin1_code":"7.0",
    "gn:admin2_code":"9166668.0",
    "gn:asciiname":"Faydi as Salman",
    "gn:country_code":"IQ",
    "gn:dem":39,
    "gn:feature_class":"P",
    "gn:feature_code":"PPL",
    "gn:name":"Fay\u1e11\u012b as Salm\u0101n",
    "gn:population":0,
    "gn:timezone":"Asia/Baghdad",
    "iso:country":"IQ",
    "name:und_x_variant":[
        "Fay\u1e11\u012b as Salm\u0101n"
    ],
    "wof:name":"Faydi as Salman",
    "wof:placetype":"locality"
},
  "geometry": {"coordinates":[44.46213,33.27846],"type":"Point"}
}