{
  "type": "Feature",
  "properties": {
    "gn:admin1_code":"5.0",
    "gn:admin2_code":"9166596.0",
    "gn:asciiname":"Kubah",
    "gn:country_code":"IQ",
    "gn:dem":919,
    "gn:feature_class":"P",
    "gn:feature_code":"PPL",
    "gn:name":"K\u016bbah",
    "gn:population":0,
    "gn:timezone":"Asia/Baghdad",
    "iso:country":"IQ",
    "name:ara_x_preferred":[
        "\u0643\u0648\u0628\u0629"
    ],
    "name:ind_x_preferred":[
        "Kubah"
    ],
    "name:und_x_variant":[
        "Kubbah",
        "K\u016bbah",
        "Gaba"
    ],
    "wof:name":"Kubah",
    "wof:placetype":"locality"
},
  "geometry": {"coordinates":[45.07527,35.72108],"type":"Point"}
}