{
  "type": "Feature",
  "properties": {
    "gn:admin1_code":"10.0",
    "gn:admin2_code":"97988.0",
    "gn:asciiname":"Nasir 'Alaywi",
    "gn:country_code":"IQ",
    "gn:dem":38,
    "gn:feature_class":"P",
    "gn:feature_code":"PPL",
    "gn:name":"N\u0101\u015fir \u2018Alayw\u012b",
    "gn:population":0,
    "gn:timezone":"Asia/Baghdad",
    "iso:country":"IQ",
    "name:ara_x_preferred":[
        "\u0646\u0627\u0635\u0631 \u0639\u0644\u064a\u0648\u064a"
    ],
    "name:und_x_variant":[
        "N\u0101\u015fir \u2018Alayw\u012b"
    ],
    "wof:name":"Nasir 'Alaywi",
    "wof:placetype":"locality"
},
  "geometry": {"coordinates":[44.43135,33.659],"type":"Point"}
}