{
  "type": "Feature",
  "properties": {
    "gn:admin1_code":"2.0",
    "gn:admin2_code":"99534.0",
    "gn:asciiname":"Al Farid",
    "gn:country_code":"IQ",
    "gn:dem":3,
    "gn:feature_class":"P",
    "gn:feature_code":"PPL",
    "gn:name":"Al Far\u012bd",
    "gn:population":0,
    "gn:timezone":"Asia/Baghdad",
    "iso:country":"IQ",
    "name:ara_x_preferred":[
        "\u0627\u0644\u0641\u0631\u064a\u062f"
    ],
    "name:und_x_variant":[
        "Al Far\u012bd"
    ],
    "wof:name":"Al Farid",
    "wof:placetype":"locality"
},
  "geometry": {"coordinates":[47.71507,30.63313],"type":"Point"}
}