{
  "type": "Feature",
  "properties": {
    "gn:admin1_code":"10.0",
    "gn:admin2_code":"99170.0",
    "gn:asciiname":"Qizil",
    "gn:country_code":"IQ",
    "gn:dem":44,
    "gn:feature_class":"P",
    "gn:feature_code":"PPL",
    "gn:name":"Qizil",
    "gn:population":0,
    "gn:timezone":"Asia/Baghdad",
    "iso:country":"IQ",
    "name:uzb_x_preferred":[
        "Qizil"
    ],
    "wof:name":"Qizil",
    "wof:placetype":"locality"
},
  "geometry": {"coordinates":[44.31667,34.08333],"type":"Point"}
}