{
  "type": "Feature",
  "properties": {
    "gn:admin1_code":"10.0",
    "gn:admin2_code":"9166680.0",
    "gn:asciiname":"Muhsin Ibrahim",
    "gn:country_code":"IQ",
    "gn:dem":47,
    "gn:feature_class":"P",
    "gn:feature_code":"PPL",
    "gn:name":"Mu\u1e29sin Ibr\u0101h\u012bm",
    "gn:population":0,
    "gn:timezone":"Asia/Baghdad",
    "iso:country":"IQ",
    "name:ara_x_preferred":[
        "\u0645\u062d\u0633\u0646 \u0627\u0628\u0631\u0627\u0647\u064a\u0645"
    ],
    "name:ara_x_variant":[
        "Mu\u1e29sin Ibr\u0101h\u012bm"
    ],
    "wof:name":"Muhsin Ibrahim",
    "wof:placetype":"locality"
},
  "geometry": {"coordinates":[44.83774,33.69893],"type":"Point"}
}