{
  "type": "Feature",
  "properties": {
    "gn:admin1_code":"6.0",
    "gn:admin2_code":"99040.0",
    "gn:asciiname":"'Abd 'Abd Allah",
    "gn:country_code":"IQ",
    "gn:dem":38,
    "gn:feature_class":"P",
    "gn:feature_code":"PPL",
    "gn:name":"\u2018Abd \u2018Abd All\u0101h",
    "gn:population":0,
    "gn:timezone":"Asia/Baghdad",
    "iso:country":"IQ",
    "name:ara_x_preferred":[
        "\u0639\u0628\u062f \u0639\u0628\u062f \u0627\u0644\u0644\u0647"
    ],
    "name:ara_x_variant":[
        "\u2018Abd \u2018Abd All\u0101h"
    ],
    "wof:name":"'Abd 'Abd Allah",
    "wof:placetype":"locality"
},
  "geometry": {"coordinates":[44.17481,32.97746],"type":"Point"}
}