{
  "type": "Feature",
  "properties": {
    "gn:admin1_code":"16.0",
    "gn:admin2_code":"9166606.0",
    "gn:asciiname":"Muhsin al Harbush",
    "gn:country_code":"IQ",
    "gn:dem":18,
    "gn:feature_class":"P",
    "gn:feature_code":"PPL",
    "gn:name":"Mu\u1e29sin al \u1e28arb\u016bsh",
    "gn:population":0,
    "gn:timezone":"Asia/Baghdad",
    "iso:country":"IQ",
    "name:ara_x_preferred":[
        "\u0645\u062d\u0633\u0646 \u0627\u0644\u062d\u0631\u0628\u0648\u0634"
    ],
    "name:und_x_variant":[
        "Mu\u1e29sin al \u1e28arb\u016bsh"
    ],
    "wof:name":"Muhsin al Harbush",
    "wof:placetype":"locality"
},
  "geometry": {"coordinates":[45.62965,32.48562],"type":"Point"}
}