{
  "type": "Feature",
  "properties": {
    "gn:admin1_code":"18.0",
    "gn:admin2_code":"6872046.0",
    "gn:asciiname":"Hardan Mu'iwif",
    "gn:country_code":"IQ",
    "gn:dem":101,
    "gn:feature_class":"P",
    "gn:feature_code":"PPL",
    "gn:name":"\u1e28ard\u0101n Mu\u2018\u012bwif",
    "gn:population":0,
    "gn:timezone":"Asia/Baghdad",
    "iso:country":"IQ",
    "name:ara_x_preferred":[
        "\u062d\u0631\u062f\u0627\u0646 \u0645\u0639\u064a\u0648\u0641"
    ],
    "name:und_x_variant":[
        "\u1e28ard\u0101n Mu\u2018\u012bwif"
    ],
    "wof:name":"Hardan Mu'iwif",
    "wof:placetype":"locality"
},
  "geometry": {"coordinates":[43.05982,34.87661],"type":"Point"}
}