{
  "type": "Feature",
  "properties": {
    "gn:admin1_code":"16.0",
    "gn:admin2_code":"9166961.0",
    "gn:asciiname":"Qaryat an Nil",
    "gn:country_code":"IQ",
    "gn:dem":28,
    "gn:feature_class":"P",
    "gn:feature_code":"PPL",
    "gn:name":"Qaryat an N\u012bl",
    "gn:population":0,
    "gn:timezone":"Asia/Baghdad",
    "iso:country":"IQ",
    "name:ara_x_preferred":[
        "\u0642\u0631\u064a\u0629 \u0627\u0644\u0646\u064a\u0644"
    ],
    "name:und_x_variant":[
        "Qaryat an N\u012bl"
    ],
    "wof:name":"Qaryat an Nil",
    "wof:placetype":"locality"
},
  "geometry": {"coordinates":[44.96746,32.95307],"type":"Point"}
}