{
  "type": "Feature",
  "properties": {
    "gn:admin1_code":"5.0",
    "gn:admin2_code":"92743.0",
    "gn:asciiname":"Wastah Sammal",
    "gn:country_code":"IQ",
    "gn:dem":672,
    "gn:feature_class":"P",
    "gn:feature_code":"PPL",
    "gn:name":"Wastah Sammal",
    "gn:population":0,
    "gn:timezone":"Asia/Baghdad",
    "iso:country":"IQ",
    "name:ara_x_preferred":[
        "\u0648\u0633\u062a\u0629 \u0633\u0645\u0644"
    ],
    "name:und_x_variant":[
        "Wast\u0101 S\u0113man",
        "Wasta Seman"
    ],
    "wof:name":"Wastah Sammal",
    "wof:placetype":"locality"
},
  "geometry": {"coordinates":[45.15399,36.17962],"type":"Point"}
}