{
  "type": "Feature",
  "properties": {
    "gn:admin1_code":"9.0",
    "gn:admin2_code":"98700.0",
    "gn:asciiname":"Al Hajj Ghulub",
    "gn:country_code":"IQ",
    "gn:dem":10,
    "gn:feature_class":"P",
    "gn:feature_code":"PPL",
    "gn:name":"Al \u1e28\u0101jj Ghul\u016bb",
    "gn:population":0,
    "gn:timezone":"Asia/Baghdad",
    "iso:country":"IQ",
    "name:ara_x_preferred":[
        "\u0627\u0644\u062d\u0627\u062c \u063a\u0644\u0648\u0628"
    ],
    "name:ara_x_variant":[
        "Al \u1e28\u0101jj Ghul\u016bb"
    ],
    "wof:name":"Al Hajj Ghulub",
    "wof:placetype":"locality"
},
  "geometry": {"coordinates":[46.06658,31.54845],"type":"Point"}
}