{
  "type": "Feature",
  "properties": {
    "gn:admin1_code":"11.0",
    "gn:admin2_code":"9166591.0",
    "gn:asciiname":"Mirza Rawstam",
    "gn:country_code":"IQ",
    "gn:dem":726,
    "gn:feature_class":"P",
    "gn:feature_code":"PPL",
    "gn:name":"M\u012brz\u0101 Rawstam",
    "gn:population":0,
    "gn:timezone":"Asia/Baghdad",
    "iso:country":"IQ",
    "name:ara_x_preferred":[
        "\u0645\u064a\u0631\u0632\u0627 \u0631\u0648\u0633\u062a\u0645"
    ],
    "name:kur_x_preferred":[
        "M\u00eerza Rostem"
    ],
    "name:kur_x_variant":[
        "\u0645\u064a\u0631\u0632\u0627 \u0631\u06c6\u0633\u062a\u06d5\u0645"
    ],
    "name:und_x_variant":[
        "P\u012br Rustam",
        "Mirza Rustam",
        "M\u012brz\u0101 Rawstam"
    ],
    "wof:name":"Mirza Rawstam",
    "wof:placetype":"locality"
},
  "geometry": {"coordinates":[44.37674000000001,36.459],"type":"Point"}
}