{
  "type": "Feature",
  "properties": {
    "gn:admin1_code":"18.0",
    "gn:admin2_code":"6872046.0",
    "gn:asciiname":"Abu Jidh'",
    "gn:country_code":"IQ",
    "gn:dem":90,
    "gn:feature_class":"P",
    "gn:feature_code":"PPL",
    "gn:name":"Ab\u016b Jidh\u2019",
    "gn:population":0,
    "gn:timezone":"Asia/Baghdad",
    "iso:country":"IQ",
    "name:ara_x_preferred":[
        "Ab\u016b Jidh\u2019"
    ],
    "wof:name":"Abu Jidh'",
    "wof:placetype":"locality"
},
  "geometry": {"coordinates":[43.14083,34.54],"type":"Point"}
}