{
  "type": "Feature",
  "properties": {
    "gn:admin1_code":"9.0",
    "gn:admin2_code":"98700.0",
    "gn:asciiname":"'Ajil ar Radnan",
    "gn:country_code":"IQ",
    "gn:dem":8,
    "gn:feature_class":"P",
    "gn:feature_code":"PPL",
    "gn:name":"\u2018Aj\u012bl ar Radn\u0101n",
    "gn:population":0,
    "gn:timezone":"Asia/Baghdad",
    "iso:country":"IQ",
    "name:und_x_variant":[
        "Ajil ar Radh\u0101n",
        "\u2018Aj\u012bl ar Raw\u1e11\u0101n",
        "\u2018Aj\u012bl ar Radn\u0101n"
    ],
    "wof:name":"'Ajil ar Radnan",
    "wof:placetype":"locality"
},
  "geometry": {"coordinates":[46.12722,31.56389],"type":"Point"}
}