{
  "type": "Feature",
  "properties": {
    "gn:admin1_code":"6.0",
    "gn:admin2_code":"99358.0",
    "gn:asciiname":"'Abbas al Battan",
    "gn:country_code":"IQ",
    "gn:dem":24,
    "gn:feature_class":"P",
    "gn:feature_code":"PPL",
    "gn:name":"\u2018Abb\u0101s al Ba\u0163\u0163\u0101n",
    "gn:population":0,
    "gn:timezone":"Asia/Baghdad",
    "iso:country":"IQ",
    "name:ara_x_preferred":[
        "\u0639\u0628\u0627\u0633 \u0627\u0644\u0628\u0637\u0627\u0646"
    ],
    "name:und_x_variant":[
        "\u2018Abb\u0101s al Ba\u0163\u0163\u0101n"
    ],
    "wof:name":"'Abbas al Battan",
    "wof:placetype":"locality"
},
  "geometry": {"coordinates":[44.98396,32.34285999999999],"type":"Point"}
}