{
  "type": "Feature",
  "properties": {
    "gn:admin1_code":"18.0",
    "gn:admin2_code":"6872046.0",
    "gn:asciiname":"Muhammad Halifah",
    "gn:country_code":"IQ",
    "gn:dem":142,
    "gn:feature_class":"P",
    "gn:feature_code":"PPL",
    "gn:name":"Mu\u1e29ammad \u1e28al\u012bfah",
    "gn:population":0,
    "gn:timezone":"Asia/Baghdad",
    "iso:country":"IQ",
    "name:ara_x_preferred":[
        "\u0645\u062d\u0645\u062f \u062d\u0644\u064a\u0641\u0647"
    ],
    "name:und_x_variant":[
        "Mu\u1e29ammad \u1e28al\u012bfah"
    ],
    "wof:name":"Muhammad Halifah",
    "wof:placetype":"locality"
},
  "geometry": {"coordinates":[43.30565,34.61812],"type":"Point"}
}