{
  "type": "Feature",
  "properties": {
    "gn:admin1_code":"15.0",
    "gn:admin2_code":"9166649.0",
    "gn:asciiname":"Dallawiyah",
    "gn:country_code":"IQ",
    "gn:dem":296,
    "gn:feature_class":"P",
    "gn:feature_code":"PPL",
    "gn:name":"Dall\u0101w\u012byah",
    "gn:population":0,
    "gn:timezone":"Asia/Baghdad",
    "iso:country":"IQ",
    "name:ara_x_preferred":[
        "\u062f\u0644\u0627\u0648\u064a\u0629"
    ],
    "name:und_x_variant":[
        "Dal\u0101w\u012byah",
        "Dall\u0101w\u012byah"
    ],
    "wof:name":"Dallawiyah",
    "wof:placetype":"locality"
},
  "geometry": {"coordinates":[42.93779,36.02526],"type":"Point"}
}