{
  "type": "Feature",
  "properties": {
    "gn:admin1_code":"11.0",
    "gn:admin2_code":"95444.0",
    "gn:asciiname":"Tatarawah",
    "gn:country_code":"IQ",
    "gn:dem":331,
    "gn:feature_class":"P",
    "gn:feature_code":"PPL",
    "gn:name":"Tatar\u0101wah",
    "gn:population":0,
    "gn:timezone":"Asia/Baghdad",
    "iso:country":"IQ",
    "name:ara_x_preferred":[
        "\u062a\u062a\u0631\u0627\u0648\u0629"
    ],
    "name:kur_x_preferred":[
        "Teterawa"
    ],
    "name:kur_x_variant":[
        "\u062a\u06d5\u062a\u06d5\u0631\u0627\u0648\u0627"
    ],
    "name:und_x_variant":[
        "Tal R\u0101wah",
        "Tan Rawa",
        "Tatar\u0101wah"
    ],
    "wof:name":"Tatarawah",
    "wof:placetype":"locality"
},
  "geometry": {"coordinates":[44.05725,35.88480999999999],"type":"Point"}
}