{
  "type": "Feature",
  "properties": {
    "gn:admin1_code":"18.0",
    "gn:admin2_code":"6783103.0",
    "gn:asciiname":"'Arab Mardas 'Ali",
    "gn:country_code":"IQ",
    "gn:dem":67,
    "gn:feature_class":"P",
    "gn:feature_code":"PPL",
    "gn:name":"\u2018Arab Mard\u0101s \u2018Al\u012b",
    "gn:population":0,
    "gn:timezone":"Asia/Baghdad",
    "iso:country":"IQ",
    "name:ara_x_preferred":[
        "\u0639\u0631\u0628 \u0645\u0631\u062f\u0627\u0633 \u0639\u0644\u064a"
    ],
    "name:und_x_variant":[
        "\u2018Arab Mard\u0101s \u2018Al\u012b"
    ],
    "wof:name":"'Arab Mardas 'Ali",
    "wof:placetype":"locality"
},
  "geometry": {"coordinates":[44.26794,34.33064],"type":"Point"}
}