{
  "type": "Feature",
  "properties": {
    "gn:admin1_code":"18.0",
    "gn:admin2_code":"6805736.0",
    "gn:asciiname":"Qaryat al Khudayrah",
    "gn:country_code":"IQ",
    "gn:dem":42,
    "gn:feature_class":"P",
    "gn:feature_code":"PPL",
    "gn:name":"Qaryat al Khu\u1e11ayrah",
    "gn:population":0,
    "gn:timezone":"Asia/Baghdad",
    "iso:country":"IQ",
    "name:ara_x_preferred":[
        "\u0642\u0631\u064a\u0629 \u0627\u0644\u062e\u0636\u064a\u0631\u0629"
    ],
    "name:und_x_variant":[
        "Qaryat al Khu\u1e11ayrah"
    ],
    "wof:name":"Qaryat al Khudayrah",
    "wof:placetype":"locality"
},
  "geometry": {"coordinates":[44.3573,34.00239000000001],"type":"Point"}
}