{
  "type": "Feature",
  "properties": {
    "gn:admin1_code":"5.0",
    "gn:admin2_code":"98464.0",
    "gn:asciiname":"Qirgah",
    "gn:country_code":"IQ",
    "gn:dem":934,
    "gn:feature_class":"P",
    "gn:feature_code":"PPL",
    "gn:name":"Qirgah",
    "gn:population":0,
    "gn:timezone":"Asia/Baghdad",
    "iso:country":"IQ",
    "name:ara_x_preferred":[
        "\u0642\u0631\u0643\u0629"
    ],
    "name:kur_x_preferred":[
        "Qi\u1e5fge"
    ],
    "name:kur_x_variant":[
        "\u0642\u0695\u06af\u06d5"
    ],
    "name:und_x_variant":[
        "Qirkah",
        "Qirga",
        "Qrga"
    ],
    "wof:name":"Qirgah",
    "wof:placetype":"locality"
},
  "geometry": {"coordinates":[45.48074,35.53449],"type":"Point"}
}