{
  "type": "Feature",
  "properties": {
    "gn:admin1_code":"7.0",
    "gn:admin2_code":"99101.0",
    "gn:asciiname":"'Arab Nayif Husayn",
    "gn:country_code":"IQ",
    "gn:dem":32,
    "gn:feature_class":"P",
    "gn:feature_code":"PPL",
    "gn:name":"\u2018Arab N\u0101yif \u1e28usayn",
    "gn:population":0,
    "gn:timezone":"Asia/Baghdad",
    "iso:country":"IQ",
    "name:ara_x_preferred":[
        "\u0639\u0631\u0628 \u0646\u0627\u064a\u0641 \u062d\u0633\u064a\u0646"
    ],
    "name:und_x_variant":[
        "\u2018Arab N\u0101yif \u1e28usayn"
    ],
    "wof:name":"'Arab Nayif Husayn",
    "wof:placetype":"locality"
},
  "geometry": {"coordinates":[44.48733,32.95764],"type":"Point"}
}