{
  "type": "Feature",
  "properties": {
    "gn:admin1_code":"5.0",
    "gn:admin2_code":"9166596.0",
    "gn:asciiname":"Frizalah",
    "gn:country_code":"IQ",
    "gn:dem":845,
    "gn:feature_class":"P",
    "gn:feature_code":"PPL",
    "gn:name":"Fr\u012bzalah",
    "gn:population":0,
    "gn:timezone":"Asia/Baghdad",
    "iso:country":"IQ",
    "name:ara_x_preferred":[
        "\u0641\u0631\u064a\u0632\u0644\u06d5"
    ],
    "name:kur_x_preferred":[
        "Fr\u00eeze\u0142e"
    ],
    "name:kur_x_variant":[
        "\u0641\u0631\u064a\u0632\u06d5\u06b5\u06d5"
    ],
    "name:und_x_variant":[
        "Fr\u012bzalah",
        "Fr\u012bzala",
        "Freezala",
        "Frizala"
    ],
    "wof:name":"Frizalah",
    "wof:placetype":"locality"
},
  "geometry": {"coordinates":[44.86728,35.98092000000001],"type":"Point"}
}