{
  "type": "Feature",
  "properties": {
    "gn:admin1_code":"6.0",
    "gn:admin2_code":"99358.0",
    "gn:asciiname":"Muhammad al Khashshan",
    "gn:country_code":"IQ",
    "gn:dem":22,
    "gn:feature_class":"P",
    "gn:feature_code":"PPL",
    "gn:name":"Mu\u1e29ammad al Khashsh\u0101n",
    "gn:population":0,
    "gn:timezone":"Asia/Baghdad",
    "iso:country":"IQ",
    "name:ara_x_preferred":[
        "\u0645\u062d\u0645\u062f \u0627\u0644\u062e\u0634\u0627\u0646"
    ],
    "name:und_x_variant":[
        "Mu\u1e29ammad al Khashsh\u0101n"
    ],
    "wof:name":"Muhammad al Khashshan",
    "wof:placetype":"locality"
},
  "geometry": {"coordinates":[44.93019,32.3049],"type":"Point"}
}