{
  "type": "Feature",
  "properties": {
    "gn:admin1_code":"4.0",
    "gn:admin2_code":"99763.0",
    "gn:asciiname":"Muhammad Kazim",
    "gn:country_code":"IQ",
    "gn:dem":24,
    "gn:feature_class":"P",
    "gn:feature_code":"PPL",
    "gn:name":"Mu\u1e29ammad K\u0101z\u0327im",
    "gn:population":0,
    "gn:timezone":"Asia/Baghdad",
    "iso:country":"IQ",
    "name:ara_x_preferred":[
        "\u0645\u062d\u0645\u062f \u0643\u0627\u0638\u0645"
    ],
    "name:und_x_variant":[
        "Mu\u1e29ammad K\u0101z\u0327im"
    ],
    "wof:name":"Muhammad Kazim",
    "wof:placetype":"locality"
},
  "geometry": {"coordinates":[44.6605,32.04269],"type":"Point"}
}