{
  "type": "Feature",
  "properties": {
    "gn:admin1_code":"4.0",
    "gn:admin2_code":"98634.0",
    "gn:asciiname":"Qaryat at Tantur",
    "gn:country_code":"IQ",
    "gn:dem":26,
    "gn:feature_class":"P",
    "gn:feature_code":"PPL",
    "gn:name":"Qaryat a\u0163 \u0162an\u0163\u016br",
    "gn:population":0,
    "gn:timezone":"Asia/Baghdad",
    "iso:country":"IQ",
    "name:ara_x_preferred":[
        "\u0642\u0631\u064a\u0629 \u0627\u0644\u0637\u0646\u0637\u0648\u0631"
    ],
    "name:und_x_variant":[
        "Qaryat a\u0163 \u0162an\u0163\u016br"
    ],
    "wof:name":"Qaryat at Tantur",
    "wof:placetype":"locality"
},
  "geometry": {"coordinates":[44.5405,32.00087],"type":"Point"}
}