{
  "type": "Feature",
  "properties": {
    "gn:admin1_code":"6.0",
    "gn:admin2_code":"99358.0",
    "gn:asciiname":"'Ulaywi Mu'aydi",
    "gn:country_code":"IQ",
    "gn:dem":23,
    "gn:feature_class":"P",
    "gn:feature_code":"PPL",
    "gn:name":"\u2018Ulayw\u012b Mu\u2018ayd\u012b",
    "gn:population":0,
    "gn:timezone":"Asia/Baghdad",
    "iso:country":"IQ",
    "name:ara_x_preferred":[
        "\u0639\u0644\u064a\u0648\u064a \u0645\u0639\u064a\u062f\u064a"
    ],
    "name:und_x_variant":[
        "\u2018Ulayw\u012b Mu\u2018ayd\u012b"
    ],
    "wof:name":"'Ulaywi Mu'aydi",
    "wof:placetype":"locality"
},
  "geometry": {"coordinates":[44.94807,32.31215],"type":"Point"}
}