{
  "type": "Feature",
  "properties": {
    "gn:admin1_code":"10.0",
    "gn:admin2_code":"9166680.0",
    "gn:asciiname":"'Arab Sirhan",
    "gn:country_code":"IQ",
    "gn:dem":94,
    "gn:feature_class":"P",
    "gn:feature_code":"PPL",
    "gn:name":"\u2018Arab Sir\u1e29\u0101n",
    "gn:population":0,
    "gn:timezone":"Asia/Baghdad",
    "iso:country":"IQ",
    "name:ara_x_preferred":[
        "\u0639\u0631\u0628 \u0633\u0631\u062d\u0627\u0646"
    ],
    "name:und_x_variant":[
        "\u2018Arab Sir\u1e29\u0101n"
    ],
    "wof:name":"'Arab Sirhan",
    "wof:placetype":"locality"
},
  "geometry": {"coordinates":[45.60548,33.68343],"type":"Point"}
}