{
  "type": "Feature",
  "properties": {
    "gn:admin1_code":"10.0",
    "gn:admin2_code":"9166680.0",
    "gn:asciiname":"Husayn Nasif",
    "gn:country_code":"IQ",
    "gn:dem":50,
    "gn:feature_class":"P",
    "gn:feature_code":"PPL",
    "gn:name":"\u1e28usayn Na\u015f\u012bf",
    "gn:population":0,
    "gn:timezone":"Asia/Baghdad",
    "iso:country":"IQ",
    "name:ara_x_preferred":[
        "\u062d\u0633\u064a\u0646 \u0646\u0635\u064a\u0641"
    ],
    "name:und_x_variant":[
        "\u1e28usayn Na\u015f\u012bf"
    ],
    "wof:name":"Husayn Nasif",
    "wof:placetype":"locality"
},
  "geometry": {"coordinates":[45.45775,33.51163],"type":"Point"}
}