{
  "type": "Feature",
  "properties": {
    "gn:admin1_code":"13.0",
    "gn:admin2_code":"6770659.0",
    "gn:asciiname":"Qaryat Daqilah",
    "gn:country_code":"IQ",
    "gn:dem":186,
    "gn:feature_class":"P",
    "gn:feature_code":"PPL",
    "gn:name":"Qaryat Daq\u012blah",
    "gn:population":0,
    "gn:timezone":"Asia/Baghdad",
    "iso:country":"IQ",
    "name:ara_x_preferred":[
        "\u0642\u0631\u064a\u0629 \u062f\u0642\u064a\u0644\u0629"
    ],
    "name:und_x_variant":[
        "Qaryat Daq\u012blah"
    ],
    "wof:name":"Qaryat Daqilah",
    "wof:placetype":"locality"
},
  "geometry": {"coordinates":[43.8452,35.26826],"type":"Point"}
}