{
  "type": "Feature",
  "properties": {
    "gn:admin1_code":"5.0",
    "gn:admin2_code":"9166684.0",
    "gn:asciiname":"Gawlay",
    "gn:country_code":"IQ",
    "gn:dem":1289,
    "gn:feature_class":"P",
    "gn:feature_code":"PPL",
    "gn:name":"Gawlay",
    "gn:population":0,
    "gn:timezone":"Asia/Baghdad",
    "iso:country":"IQ",
    "name:ara_x_preferred":[
        "\u06af\u0648\u0644\u064a"
    ],
    "name:kur_x_preferred":[
        "Go\u0142\u00ea"
    ],
    "name:kur_x_variant":[
        "\u06af\u06c6\u06b5\u06ce"
    ],
    "name:und_x_variant":[
        "Makhfar K\u016blah",
        "Kawlah",
        "\u0643\u0648\u0644\u0629",
        "Gola",
        "Gawlay",
        "Gowle"
    ],
    "wof:name":"Gawlay",
    "wof:placetype":"locality"
},
  "geometry": {"coordinates":[45.82822,35.78442000000001],"type":"Point"}
}