{
  "type": "Feature",
  "properties": {
    "gn:admin1_code":"7.0",
    "gn:admin2_code":"9179819.0",
    "gn:asciiname":"Tall al Majaradah",
    "gn:country_code":"IQ",
    "gn:dem":38,
    "gn:feature_class":"P",
    "gn:feature_code":"PPL",
    "gn:name":"Tall al Majaradah",
    "gn:population":0,
    "gn:timezone":"Asia/Baghdad",
    "iso:country":"IQ",
    "name:ara_x_preferred":[
        "\u062a\u0644 \u0627\u0644\u0645\u062c\u0631\u062f\u0629"
    ],
    "wof:name":"Tall al Majaradah",
    "wof:placetype":"locality"
},
  "geometry": {"coordinates":[44.694,33.42023],"type":"Point"}
}