{
  "type": "Feature",
  "properties": {
    "gn:admin1_code":"5.0",
    "gn:admin2_code":"9166594.0",
    "gn:asciiname":"Mijah Kumiri as Sufla",
    "gn:country_code":"IQ",
    "gn:dem":766,
    "gn:feature_class":"P",
    "gn:feature_code":"PPL",
    "gn:name":"Mijah K\u016bm\u012br\u012b as Sufl\u00e1",
    "gn:population":0,
    "gn:timezone":"Asia/Baghdad",
    "iso:country":"IQ",
    "name:ara_x_preferred":[
        "\u0645\u062c\u0629 \u0643\u0648\u0645\u064a\u0631\u064a \u0627\u0644\u0633\u0641\u0644\u0649"
    ],
    "name:kur_x_preferred":[
        "Miche Kw\u00ear\u00ee Bira"
    ],
    "name:kur_x_variant":[
        "\u0645\u0686\u06d5 \u0643\u0648\u06ce\u0631\u0649 \u0628\u0631\u0627"
    ],
    "name:und_x_variant":[
        "Mijah K\u016bm\u012br\u012b as Sufl\u00e1",
        "Macah Kur",
        "Nacah Kur",
        "Mcha Kuer Bra"
    ],
    "wof:name":"Mijah Kumiri as Sufla",
    "wof:placetype":"locality"
},
  "geometry": {"coordinates":[45.58245,35.21621],"type":"Point"}
}