{
  "type": "Feature",
  "properties": {
    "gn:admin1_code":"8.0",
    "gn:admin2_code":"99612.0",
    "gn:asciiname":"Hiran",
    "gn:country_code":"IQ",
    "gn:dem":644,
    "gn:feature_class":"P",
    "gn:feature_code":"PPL",
    "gn:name":"H\u012br\u0101n",
    "gn:population":0,
    "gn:timezone":"Asia/Baghdad",
    "iso:country":"IQ",
    "name:ara_x_preferred":[
        "\u0647\u064a\u0631\u0627\u0646"
    ],
    "name:ara_x_variant":[
        "H\u012br\u0101n"
    ],
    "name:kur_x_preferred":[
        "H\u00eeran"
    ],
    "name:kur_x_variant":[
        "Jul\u00ea",
        "\u0698\u0648\u0644\u06ce"
    ],
    "name:und_x_variant":[
        "H\u0113r\u0101n",
        "Zhule"
    ],
    "wof:name":"Hiran",
    "wof:placetype":"locality"
},
  "geometry": {"coordinates":[43.70445,36.8684],"type":"Point"}
}