{
  "type": "Feature",
  "properties": {
    "gn:admin1_code":"5.0",
    "gn:admin2_code":"92051.0",
    "gn:asciiname":"Mergeser",
    "gn:country_code":"IQ",
    "gn:dem":807,
    "gn:feature_class":"P",
    "gn:feature_code":"PPL",
    "gn:name":"M\u00eargeser",
    "gn:population":0,
    "gn:timezone":"Asia/Baghdad",
    "iso:country":"IQ",
    "name:kur_x_preferred":[
        "M\u00eargeser"
    ],
    "name:kur_x_variant":[
        "\u0645\u06ce\u0631\u06af\u06d5\u0633\u06d5\u0631"
    ],
    "name:und_x_variant":[
        "Mergasar"
    ],
    "wof:name":"Mergeser",
    "wof:placetype":"locality"
},
  "geometry": {"coordinates":[44.59095,36.37126],"type":"Point"}
}