{
  "type": "Feature",
  "properties": {
    "gn:admin1_code":"15.0",
    "gn:admin2_code":"98820.0",
    "gn:asciiname":"Shikefte Mighara",
    "gn:country_code":"IQ",
    "gn:dem":596,
    "gn:feature_class":"P",
    "gn:feature_code":"PPL",
    "gn:name":"Shikefte Mighara",
    "gn:population":0,
    "gn:timezone":"Asia/Baghdad",
    "iso:country":"IQ",
    "name:kur_x_preferred":[
        "Shikefte Mighara"
    ],
    "name:kur_x_variant":[
        "\u0634\u0643\u06d5\u0641\u062a\u06d5 \u0645\u063a\u0627\u0631\u0627",
        "Shikefte Mighare",
        "\u0634\u0643\u06d5\u0641\u062a\u06d5 \u0645\u063a\u0627\u0631\u06d5"
    ],
    "name:und_x_variant":[
        "Shkafta Moghara"
    ],
    "wof:name":"Shikefte Mighara",
    "wof:placetype":"locality"
},
  "geometry": {"coordinates":[43.88739,36.71958],"type":"Point"}
}