{
  "type": "Feature",
  "properties": {
    "gn:admin1_code":"8.0",
    "gn:admin2_code":"99612.0",
    "gn:asciiname":"Cham Sayyidah",
    "gn:country_code":"IQ",
    "gn:dem":819,
    "gn:feature_class":"P",
    "gn:feature_code":"PPL",
    "gn:name":"Cham Sayyidah",
    "gn:population":0,
    "gn:timezone":"Asia/Baghdad",
    "iso:country":"IQ",
    "name:ara_x_preferred":[
        "\u0686\u0645 \u0633\u064a\u062f\u0629"
    ],
    "name:kur_x_preferred":[
        "Chem Seyda"
    ],
    "name:kur_x_variant":[
        "\u0686\u06d5\u0645 \u0633\u06d5\u064a\u062f\u0627",
        "Chem Siyeda",
        "\u0686\u06d5\u0645 \u0633\u064a\u06d5\u062f\u0627",
        "Chem Seyd\u00ea",
        "\u0686\u06d5\u0645 \u0633\u06d5\u064a\u062f\u06ce"
    ],
    "name:und_x_variant":[
        "Chamsa\u2019idah",
        "Cham Saida",
        "Chamsayda",
        "Cham Sayyidah"
    ],
    "wof:name":"Cham Sayyidah",
    "wof:placetype":"locality"
},
  "geometry": {"coordinates":[43.26429,37.1904],"type":"Point"}
}