{
  "type": "Feature",
  "properties": {
    "gn:admin1_code":"6.0",
    "gn:admin2_code":"99358.0",
    "gn:asciiname":"Jalil Wahid Budaywi",
    "gn:country_code":"IQ",
    "gn:dem":28,
    "gn:feature_class":"P",
    "gn:feature_code":"PPL",
    "gn:name":"Jal\u012bl Wa\u1e29\u012bd Budayw\u012b",
    "gn:population":0,
    "gn:timezone":"Asia/Baghdad",
    "iso:country":"IQ",
    "name:ara_x_preferred":[
        "\u062c\u0644\u064a\u0644 \u0648\u062d\u064a\u062f \u0628\u062f\u064a\u0648\u064a"
    ],
    "name:und_x_variant":[
        "Jal\u012bl Wa\u1e29\u012bd Budayw\u012b"
    ],
    "wof:name":"Jalil Wahid Budaywi",
    "wof:placetype":"locality"
},
  "geometry": {"coordinates":[44.76485,32.37849],"type":"Point"}
}