{
  "type": "Feature",
  "properties": {
    "gn:admin1_code":"2.0",
    "gn:admin2_code":"9166549.0",
    "gn:asciiname":"Hajj 'Isa",
    "gn:country_code":"IQ",
    "gn:dem":2,
    "gn:feature_class":"P",
    "gn:feature_code":"PPL",
    "gn:name":"\u1e28\u0101jj \u2018\u012as\u00e1",
    "gn:population":0,
    "gn:timezone":"Asia/Baghdad",
    "iso:country":"IQ",
    "name:ara_x_preferred":[
        "\u1e28\u0101jj \u2018\u012as\u00e1"
    ],
    "wof:name":"Hajj 'Isa",
    "wof:placetype":"locality"
},
  "geometry": {"coordinates":[48.51417,29.94083],"type":"Point"}
}