{
  "type": "Feature",
  "properties": {
    "gn:admin1_code":"4.0",
    "gn:admin2_code":"6850588.0",
    "gn:asciiname":"Al Sabti",
    "gn:country_code":"IQ",
    "gn:dem":16,
    "gn:feature_class":"P",
    "gn:feature_code":"PPL",
    "gn:name":"\u0100l Sabt\u012b",
    "gn:population":0,
    "gn:timezone":"Asia/Baghdad",
    "iso:country":"IQ",
    "name:ara_x_preferred":[
        "\u0627\u0644 \u0633\u0628\u062a\u064a"
    ],
    "name:und_x_variant":[
        "\u0100l Sabt\u012b"
    ],
    "wof:name":"Al Sabti",
    "wof:placetype":"locality"
},
  "geometry": {"coordinates":[44.83677,31.50512],"type":"Point"}
}