{
  "type": "Feature",
  "properties": {
    "gn:admin1_code":"18.0",
    "gn:admin2_code":"6872046.0",
    "gn:asciiname":"Qaryat ad Diyan",
    "gn:country_code":"IQ",
    "gn:dem":62,
    "gn:feature_class":"P",
    "gn:feature_code":"PPL",
    "gn:name":"Qaryat ad Diy\u0101n",
    "gn:population":0,
    "gn:timezone":"Asia/Baghdad",
    "iso:country":"IQ",
    "name:ara_x_preferred":[
        "\u0642\u0631\u064a\u0629 \u0627\u0644\u062f\u064a\u0627\u0646"
    ],
    "name:und_x_variant":[
        "Qaryat ad Diy\u0101n"
    ],
    "wof:name":"Qaryat ad Diyan",
    "wof:placetype":"locality"
},
  "geometry": {"coordinates":[43.06411,34.54197],"type":"Point"}
}