{
  "type": "Feature",
  "properties": {
    "gn:admin1_code":"7.0",
    "gn:admin2_code":"9166545.0",
    "gn:asciiname":"Ghubabah",
    "gn:country_code":"IQ",
    "gn:dem":36,
    "gn:feature_class":"P",
    "gn:feature_code":"PPL",
    "gn:name":"Ghub\u0101bah",
    "gn:population":0,
    "gn:timezone":"Asia/Baghdad",
    "iso:country":"IQ",
    "name:und_x_variant":[
        "Gub\u0101ba",
        "Ghub\u0101bah"
    ],
    "wof:name":"Ghubabah",
    "wof:placetype":"locality"
},
  "geometry": {"coordinates":[44.31694,33.24389],"type":"Point"}
}