{
  "type": "Feature",
  "properties": {
    "gn:admin1_code":"5.0",
    "gn:admin2_code":"98464.0",
    "gn:asciiname":"Gawany",
    "gn:country_code":"IQ",
    "gn:dem":821,
    "gn:feature_class":"P",
    "gn:feature_code":"PPL",
    "gn:name":"Gawany",
    "gn:population":0,
    "gn:timezone":"Asia/Baghdad",
    "iso:country":"IQ",
    "name:ara_x_preferred":[
        "G\u0101w\u0101n\u012b"
    ],
    "name:kur_x_preferred":[
        "Gawan\u00ee"
    ],
    "name:kur_x_variant":[
        "\u06af\u0627\u0648\u0627\u0646\u0649"
    ],
    "name:und_x_variant":[
        "G\u0101w\u0101n\u012b",
        "Gawany",
        "K\u0101w\u0101n\u012b",
        "\u0643\u0627\u0648\u0627\u0646\u064a"
    ],
    "wof:name":"Gawany",
    "wof:placetype":"locality"
},
  "geometry": {"coordinates":[45.24969,35.50348],"type":"Point"}
}