{
  "type": "Feature",
  "properties": {
    "gn:admin1_code":"4.0",
    "gn:admin2_code":"99763.0",
    "gn:asciiname":"Ruwayj 'Atshan",
    "gn:country_code":"IQ",
    "gn:dem":24,
    "gn:feature_class":"P",
    "gn:feature_code":"PPL",
    "gn:name":"Ruwayj \u2018A\u0163sh\u0101n",
    "gn:population":0,
    "gn:timezone":"Asia/Baghdad",
    "iso:country":"IQ",
    "name:ara_x_preferred":[
        "\u0631\u0648\u064a\u062c \u0639\u0637\u0634\u0627\u0646"
    ],
    "name:und_x_variant":[
        "Ruwayj \u2018A\u0163sh\u0101n"
    ],
    "wof:name":"Ruwayj 'Atshan",
    "wof:placetype":"locality"
},
  "geometry": {"coordinates":[44.63668,32.09103],"type":"Point"}
}