{
  "type": "Feature",
  "properties": {
    "gn:admin1_code":"5.0",
    "gn:admin2_code":"9166600.0",
    "gn:asciiname":"Gopan",
    "gn:country_code":"IQ",
    "gn:dem":370,
    "gn:feature_class":"P",
    "gn:feature_code":"PPL",
    "gn:name":"Gopan",
    "gn:population":0,
    "gn:timezone":"Asia/Baghdad",
    "iso:country":"IQ",
    "name:ara_x_preferred":[
        "\u0643\u0648\u067e\u0627\u0646"
    ],
    "name:kur_x_preferred":[
        "Gopan"
    ],
    "name:kur_x_variant":[
        "\u06af\u06c6\u067e\u0627\u0646"
    ],
    "name:und_x_variant":[
        "Gawb\u0101n",
        "Kawp\u0101n",
        "G\u014db\u0101n",
        "Kawb\u0101n",
        "Koban",
        "\u0643\u0648\u0628\u0627\u0646"
    ],
    "wof:name":"Gopan",
    "wof:placetype":"locality"
},
  "geometry": {"coordinates":[45.30259,34.74453],"type":"Point"}
}