{
  "type": "Feature",
  "properties": {
    "gn:admin1_code":"11.0",
    "gn:admin2_code":"95444.0",
    "gn:asciiname":"Rakawah",
    "gn:country_code":"IQ",
    "gn:dem":333,
    "gn:feature_class":"P",
    "gn:feature_code":"PPL",
    "gn:name":"Rak\u0101wah",
    "gn:population":0,
    "gn:timezone":"Asia/Baghdad",
    "iso:country":"IQ",
    "name:ara_x_preferred":[
        "\u0631\u0643\u0627\u0648\u0629"
    ],
    "name:kur_x_preferred":[
        "\u1e5ekawe"
    ],
    "name:kur_x_variant":[
        "\u0695\u0643\u0627\u0648\u06d5"
    ],
    "name:und_x_variant":[
        "Rkawa",
        "Rak\u0101wah"
    ],
    "wof:name":"Rakawah",
    "wof:placetype":"locality"
},
  "geometry": {"coordinates":[43.93104,36.10358],"type":"Point"}
}