{
  "type": "Feature",
  "properties": {
    "gn:admin1_code":"18.0",
    "gn:admin2_code":"90148.0",
    "gn:asciiname":"Jasim Ibrahim",
    "gn:country_code":"IQ",
    "gn:dem":102,
    "gn:feature_class":"P",
    "gn:feature_code":"PPL",
    "gn:name":"J\u0101sim Ibr\u0101h\u012bm",
    "gn:population":0,
    "gn:timezone":"Asia/Baghdad",
    "iso:country":"IQ",
    "name:ara_x_preferred":[
        "\u062c\u0627\u0633\u0645 \u0627\u0628\u0631\u0627\u0647\u064a\u0645"
    ],
    "name:ara_x_variant":[
        "J\u0101sim Ibr\u0101h\u012bm"
    ],
    "wof:name":"Jasim Ibrahim",
    "wof:placetype":"locality"
},
  "geometry": {"coordinates":[43.59338,34.37965],"type":"Point"}
}