{
  "type": "Feature",
  "properties": {
    "gn:admin1_code":"4.0",
    "gn:admin2_code":"98634.0",
    "gn:asciiname":"Ridam Marzuk",
    "gn:country_code":"IQ",
    "gn:dem":25,
    "gn:feature_class":"P",
    "gn:feature_code":"PPL",
    "gn:name":"Rid\u0101m Marz\u016bk",
    "gn:population":0,
    "gn:timezone":"Asia/Baghdad",
    "iso:country":"IQ",
    "name:ara_x_preferred":[
        "\u0631\u062f\u0627\u0645 \u0645\u0631\u0632\u0648\u0643"
    ],
    "name:und_x_variant":[
        "Rid\u0101m Marz\u016bk"
    ],
    "wof:name":"Ridam Marzuk",
    "wof:placetype":"locality"
},
  "geometry": {"coordinates":[44.55046,31.97021],"type":"Point"}
}