{
  "type": "Feature",
  "properties": {
    "gn:admin1_code":"18.0",
    "gn:admin2_code":"6783103.0",
    "gn:asciiname":"Qaryat Musayrah",
    "gn:country_code":"IQ",
    "gn:dem":117,
    "gn:feature_class":"P",
    "gn:feature_code":"PPL",
    "gn:name":"Qaryat Mu\u015fayra\u1e29",
    "gn:population":0,
    "gn:timezone":"Asia/Baghdad",
    "iso:country":"IQ",
    "name:ara_x_preferred":[
        "\u0642\u0631\u064a\u0629 \u0645\u0635\u064a\u0631\u062d"
    ],
    "name:und_x_variant":[
        "Qaryat Mu\u015fayra\u1e29"
    ],
    "wof:name":"Qaryat Musayrah",
    "wof:placetype":"locality"
},
  "geometry": {"coordinates":[44.15586,34.64850999999999],"type":"Point"}
}