{
  "type": "Feature",
  "properties": {
    "gn:admin1_code":"18.0",
    "gn:admin2_code":"6805736.0",
    "gn:asciiname":"'Arab Jasim Muhammad",
    "gn:country_code":"IQ",
    "gn:dem":41,
    "gn:feature_class":"P",
    "gn:feature_code":"PPL",
    "gn:name":"\u2018Arab J\u0101sim Mu\u1e29ammad",
    "gn:population":0,
    "gn:timezone":"Asia/Baghdad",
    "iso:country":"IQ",
    "name:ara_x_preferred":[
        "\u0639\u0631\u0628 \u062c\u0627\u0633\u0645 \u0645\u062d\u0645\u062f"
    ],
    "name:und_x_variant":[
        "\u2018Arab J\u0101sim Mu\u1e29ammad"
    ],
    "wof:name":"'Arab Jasim Muhammad",
    "wof:placetype":"locality"
},
  "geometry": {"coordinates":[44.12599,33.86177],"type":"Point"}
}