{
  "type": "Feature",
  "properties": {
    "gn:admin1_code":"5.0",
    "gn:admin2_code":"96204.0",
    "gn:asciiname":"Chenar",
    "gn:country_code":"IQ",
    "gn:dem":1050,
    "gn:feature_class":"P",
    "gn:feature_code":"PPL",
    "gn:name":"Chen\u0101r",
    "gn:population":0,
    "gn:timezone":"Asia/Baghdad",
    "iso:country":"IQ",
    "name:fas_x_preferred":[
        "\u0686\u0646\u0627\u0631"
    ],
    "wof:name":"Chenar",
    "wof:placetype":"locality"
},
  "geometry": {"coordinates":[46.0322,35.0791],"type":"Point"}
}