{
  "type": "Feature",
  "properties": {
    "gn:admin1_code":"13.0",
    "gn:admin2_code":"9171727.0",
    "gn:asciiname":"Altun Kubri",
    "gn:country_code":"IQ",
    "gn:dem":257,
    "gn:feature_class":"P",
    "gn:feature_code":"PPL",
    "gn:name":"\u0100lt\u016bn K\u016bbr\u012b",
    "gn:population":0,
    "gn:timezone":"Asia/Baghdad",
    "iso:country":"IQ",
    "name:ara_x_preferred":[
        "\u0622\u0644\u062a\u0648\u0646 \u0643\u0648\u0628\u0631\u064a"
    ],
    "name:ara_x_variant":[
        "\u0100lt\u016bn K\u016bbr\u012b",
        "Alt\u016bn K\u016bbr\u012b"
    ],
    "name:kur_x_preferred":[
        "A\u0142t\u00fbn Kopr\u00ee"
    ],
    "name:kur_x_variant":[
        "\u0626\u0627\u06b5\u062a\u0648\u0646 \u0643\u06c6\u067e\u0631\u0649"
    ],
    "name:und_x_variant":[
        "Pird\u0113",
        "Altun Kopru",
        "Keupri",
        "Alt\u016bn K\u016bbr\u012b",
        "Kupri",
        "Altin Kopru",
        "Altun Kupri",
        "Altunkopri",
        "Altuni Kopri",
        "Altoon Kopry"
    ],
    "wof:name":"Altun Kubri",
    "wof:placetype":"locality"
},
  "geometry": {"coordinates":[44.14361,35.75351],"type":"Point"}
}