{
  "type": "Feature",
  "properties": {
    "gn:admin1_code":"6.0",
    "gn:admin2_code":"99358.0",
    "gn:asciiname":"Hulaybah",
    "gn:country_code":"IQ",
    "gn:dem":22,
    "gn:feature_class":"P",
    "gn:feature_code":"PPL",
    "gn:name":"\u1e28ulaybah",
    "gn:population":0,
    "gn:timezone":"Asia/Baghdad",
    "iso:country":"IQ",
    "name:und_x_variant":[
        "\u1e28ulaybah"
    ],
    "wof:name":"Hulaybah",
    "wof:placetype":"locality"
},
  "geometry": {"coordinates":[44.63333,32.23333],"type":"Point"}
}