{
  "type": "Feature",
  "properties": {
    "gn:admin1_code":"9.0",
    "gn:admin2_code":"98700.0",
    "gn:asciiname":"As Sayyid Wafiyah",
    "gn:country_code":"IQ",
    "gn:dem":11,
    "gn:feature_class":"P",
    "gn:feature_code":"PPL",
    "gn:name":"As Sayyid Waf\u012byah",
    "gn:population":0,
    "gn:timezone":"Asia/Baghdad",
    "iso:country":"IQ",
    "name:ara_x_preferred":[
        "\u0627\u0644\u0633\u064a\u062f \u0648\u0641\u064a\u0647"
    ],
    "name:und_x_variant":[
        "As Sayyid Waf\u012byah"
    ],
    "wof:name":"As Sayyid Wafiyah",
    "wof:placetype":"locality"
},
  "geometry": {"coordinates":[46.12159000000001,31.8871],"type":"Point"}
}