{
  "type": "Feature",
  "properties": {
    "gn:admin1_code":"14.0",
    "gn:admin2_code":"99097.0",
    "gn:asciiname":"Abu Samij",
    "gn:country_code":"IQ",
    "gn:dem":6,
    "gn:feature_class":"P",
    "gn:feature_code":"PPL",
    "gn:name":"Ab\u016b Sam\u012bj",
    "gn:population":0,
    "gn:timezone":"Asia/Baghdad",
    "iso:country":"IQ",
    "name:ara_x_preferred":[
        "\u0627\u0628\u0648 \u0633\u0645\u064a\u062c"
    ],
    "name:und_x_variant":[
        "Ab\u016b Sam\u012bj"
    ],
    "wof:name":"Abu Samij",
    "wof:placetype":"locality"
},
  "geometry": {"coordinates":[47.29396,31.42226],"type":"Point"}
}