{
  "type": "Feature",
  "properties": {
    "gn:admin1_code":"5.0",
    "gn:admin2_code":"9166600.0",
    "gn:asciiname":"Karmik",
    "gn:country_code":"IQ",
    "gn:dem":559,
    "gn:feature_class":"P",
    "gn:feature_code":"PPL",
    "gn:name":"Karmik",
    "gn:population":0,
    "gn:timezone":"Asia/Baghdad",
    "iso:country":"IQ",
    "name:ara_x_preferred":[
        "\u0642\u0631\u064a\u0629 \u0643\u0631\u0645\u0643"
    ],
    "name:kur_x_preferred":[
        "\u06af\u06d5\u0631\u0645\u0643"
    ],
    "name:kur_x_variant":[
        "Germk"
    ],
    "name:und_x_variant":[
        "Garmik",
        "Qaryat Karmik",
        "\u0643\u0631\u0645\u0643"
    ],
    "wof:name":"Karmik",
    "wof:placetype":"locality"
},
  "geometry": {"coordinates":[45.34672,34.85995],"type":"Point"}
}