{
  "type": "Feature",
  "properties": {
    "gn:admin1_code":"13.0",
    "gn:admin2_code":"9166581.0",
    "gn:asciiname":"Mamli",
    "gn:country_code":"IQ",
    "gn:dem":474,
    "gn:feature_class":"P",
    "gn:feature_code":"PPL",
    "gn:name":"M\u0101ml\u012b",
    "gn:population":0,
    "gn:timezone":"Asia/Baghdad",
    "iso:country":"IQ",
    "name:ara_x_preferred":[
        "M\u0101ml\u012b"
    ],
    "name:ara_x_variant":[
        "\u0645\u0627\u0645\u0644\u064a"
    ],
    "wof:name":"Mamli",
    "wof:placetype":"locality"
},
  "geometry": {"coordinates":[44.56042,35.41565],"type":"Point"}
}