{
  "type": "Feature",
  "properties": {
    "gn:admin1_code":"6.0",
    "gn:admin2_code":"99358.0",
    "gn:asciiname":"Dayih 'Ubays",
    "gn:country_code":"IQ",
    "gn:dem":26,
    "gn:feature_class":"P",
    "gn:feature_code":"PPL",
    "gn:name":"D\u0101yih \u2018Ubays",
    "gn:population":0,
    "gn:timezone":"Asia/Baghdad",
    "iso:country":"IQ",
    "name:ara_x_preferred":[
        "\u062f\u0627\u064a\u062d \u0639\u0628\u064a\u0633"
    ],
    "name:und_x_variant":[
        "D\u0101yih \u2018Ubays"
    ],
    "wof:name":"Dayih 'Ubays",
    "wof:placetype":"locality"
},
  "geometry": {"coordinates":[44.9278,32.3909],"type":"Point"}
}