{
  "type": "Feature",
  "properties": {
    "gn:admin1_code":"4.0",
    "gn:admin2_code":"6850588.0",
    "gn:asciiname":"As Sayyid 'Usfur",
    "gn:country_code":"IQ",
    "gn:dem":23,
    "gn:feature_class":"P",
    "gn:feature_code":"PPL",
    "gn:name":"As Sayyid \u2018U\u015ff\u016br",
    "gn:population":0,
    "gn:timezone":"Asia/Baghdad",
    "iso:country":"IQ",
    "name:und_x_variant":[
        "Saiyid Zab\u0101r",
        "Saiyid \u2018Asf\u016bl",
        "Saiyid \u2018Asf\u016b",
        "As Sayyid \u2018U\u015ff\u016br"
    ],
    "wof:name":"As Sayyid 'Usfur",
    "wof:placetype":"locality"
},
  "geometry": {"coordinates":[44.95,31.81667],"type":"Point"}
}