{
  "type": "Feature",
  "properties": {
    "gn:admin1_code":"12.0",
    "gn:admin2_code":"94822.0",
    "gn:asciiname":"'Abd al Karam",
    "gn:country_code":"IQ",
    "gn:dem":37,
    "gn:feature_class":"P",
    "gn:feature_code":"PPL",
    "gn:name":"\u2018Abd al Karam",
    "gn:population":0,
    "gn:timezone":"Asia/Baghdad",
    "iso:country":"IQ",
    "name:ara_x_preferred":[
        "\u0639\u0628\u062f \u0627\u0644\u0643\u0631\u0645"
    ],
    "name:und_x_variant":[
        "\u2018Abd al Karam"
    ],
    "wof:name":"'Abd al Karam",
    "wof:placetype":"locality"
},
  "geometry": {"coordinates":[44.12496,32.64979],"type":"Point"}
}