{
  "type": "Feature",
  "properties": {
    "gn:admin1_code":"5.0",
    "gn:admin2_code":"9166596.0",
    "gn:asciiname":"Dalzulzah",
    "gn:country_code":"IQ",
    "gn:dem":578,
    "gn:feature_class":"P",
    "gn:feature_code":"PPL",
    "gn:name":"Dalz\u016blzah",
    "gn:population":0,
    "gn:timezone":"Asia/Baghdad",
    "iso:country":"IQ",
    "name:ara_x_preferred":[
        "\u062f\u0644\u0632\u0648\u0644\u0632\u0629"
    ],
    "name:kur_x_preferred":[
        "D\u00eal\u00eaje"
    ],
    "name:kur_x_variant":[
        "\u062f\u06ce\u0644\u06ce\u0698\u06d5"
    ],
    "name:und_x_variant":[
        "Dalz\u016blzah",
        "D\u0113l\u0113zha",
        "Delizha",
        "Delezha"
    ],
    "wof:name":"Dalzulzah",
    "wof:placetype":"locality"
},
  "geometry": {"coordinates":[45.01811,36.10708],"type":"Point"}
}