{
  "type": "Feature",
  "properties": {
    "gn:admin1_code":"6.0",
    "gn:admin2_code":"6818313.0",
    "gn:asciiname":"Lilu Tarif",
    "gn:country_code":"IQ",
    "gn:dem":28,
    "gn:feature_class":"P",
    "gn:feature_code":"PPL",
    "gn:name":"L\u012bl\u016b \u0162ar\u012bf",
    "gn:population":0,
    "gn:timezone":"Asia/Baghdad",
    "iso:country":"IQ",
    "name:ara_x_preferred":[
        "\u0644\u064a\u0644\u0648 \u0637\u0631\u064a\u0641"
    ],
    "name:und_x_variant":[
        "L\u012bl\u016b \u0162ar\u012bf"
    ],
    "wof:name":"Lilu Tarif",
    "wof:placetype":"locality"
},
  "geometry": {"coordinates":[44.77257,32.44707],"type":"Point"}
}