{
  "type": "Feature",
  "properties": {
    "gn:admin1_code":"18.0",
    "gn:admin2_code":"6805736.0",
    "gn:asciiname":"'Ali al Jafal",
    "gn:country_code":"IQ",
    "gn:dem":49,
    "gn:feature_class":"P",
    "gn:feature_code":"PPL",
    "gn:name":"\u2018Al\u012b al Jaf\u0101l",
    "gn:population":0,
    "gn:timezone":"Asia/Baghdad",
    "iso:country":"IQ",
    "name:ara_x_preferred":[
        "\u0639\u0644\u064a \u0627\u0644\u062c\u0641\u0627\u0644"
    ],
    "name:und_x_variant":[
        "\u2018Al\u012b al Jaf\u0101l"
    ],
    "wof:name":"'Ali al Jafal",
    "wof:placetype":"locality"
},
  "geometry": {"coordinates":[44.00134,33.87808],"type":"Point"}
}