{
  "type": "Feature",
  "properties": {
    "gn:admin1_code":"10.0",
    "gn:admin2_code":"94590.0",
    "gn:asciiname":"Khidr Badr",
    "gn:cc2":"IQ",
    "gn:country_code":"IQ",
    "gn:dem":584,
    "gn:feature_class":"P",
    "gn:feature_code":"PPL",
    "gn:name":"Khi\u1e11r Badr",
    "gn:population":0,
    "gn:timezone":"Asia/Baghdad",
    "iso:country":"IQ",
    "name:und_x_variant":[
        "Khidhr Badr",
        "Khi\u1e11r Badr"
    ],
    "wof:name":"Khidr Badr",
    "wof:placetype":"locality"
},
  "geometry": {"coordinates":[45.73333,34.56667],"type":"Point"}
}