{
  "type": "Feature",
  "properties": {
    "gn:admin1_code":"10.0",
    "gn:admin2_code":"94296.0",
    "gn:asciiname":"Sanajirah",
    "gn:country_code":"IQ",
    "gn:dem":149,
    "gn:feature_class":"P",
    "gn:feature_code":"PPL",
    "gn:name":"San\u0101jirah",
    "gn:population":0,
    "gn:timezone":"Asia/Baghdad",
    "iso:country":"IQ",
    "name:ara_x_preferred":[
        "\u0633\u0646\u0627\u062c\u0631\u0629"
    ],
    "name:und_x_variant":[
        "San\u0101jirah"
    ],
    "wof:name":"Sanajirah",
    "wof:placetype":"locality"
},
  "geometry": {"coordinates":[44.92359,34.59257],"type":"Point"}
}