{
  "type": "Feature",
  "properties": {
    "gn:admin1_code":"18.0",
    "gn:asciiname":"Jaddu` Kazim",
    "gn:country_code":"IQ",
    "gn:dem":35,
    "gn:feature_class":"P",
    "gn:feature_code":"PPL",
    "gn:name":"Jadd\u016b\u2018 K\u0101z\u0327im",
    "gn:population":0,
    "gn:timezone":"Asia/Baghdad",
    "iso:country":"IQ",
    "name:ara_x_preferred":[
        "\u062c\u062f\u0648\u0639 \u0643\u0627\u0638\u0645"
    ],
    "name:und_x_variant":[
        "Jadd\u016b\u2018 K\u0101z\u0327im"
    ],
    "wof:name":"Jaddu` Kazim",
    "wof:placetype":"locality"
},
  "geometry": {"coordinates":[44.14218,33.52843],"type":"Point"}
}