{
  "type": "Feature",
  "properties": {
    "gn:admin1_code":"5.0",
    "gn:admin2_code":"9166596.0",
    "gn:asciiname":"Dermanawe",
    "gn:country_code":"IQ",
    "gn:dem":523,
    "gn:feature_class":"P",
    "gn:feature_code":"PPL",
    "gn:name":"Dermanawe",
    "gn:population":0,
    "gn:timezone":"Asia/Baghdad",
    "iso:country":"IQ",
    "name:kur_x_preferred":[
        "Dermanawe"
    ],
    "name:kur_x_variant":[
        "\u062f\u06d5\u0631\u0645\u0627\u0646\u0627\u0648\u06d5"
    ],
    "name:und_x_variant":[
        "Darmanawa"
    ],
    "wof:name":"Dermanawe",
    "wof:placetype":"locality"
},
  "geometry": {"coordinates":[44.74634,36.14786],"type":"Point"}
}