{
  "type": "Feature",
  "properties": {
    "gn:admin1_code":"16.0",
    "gn:admin2_code":"99132.0",
    "gn:asciiname":"Abu Rumman",
    "gn:country_code":"IQ",
    "gn:dem":16,
    "gn:feature_class":"P",
    "gn:feature_code":"PPL",
    "gn:name":"Ab\u016b Rumm\u0101n",
    "gn:population":0,
    "gn:timezone":"Asia/Baghdad",
    "iso:country":"IQ",
    "name:ara_x_preferred":[
        "\u0627\u0628\u0648 \u0631\u0645\u0627\u0646\u0647"
    ],
    "name:ara_x_variant":[
        "Ab\u016b Rumm\u0101n"
    ],
    "name:und_x_variant":[
        "Ab\u016b Rumm\u0101n",
        "Rumm\u0101nah"
    ],
    "wof:name":"Abu Rumman",
    "wof:placetype":"locality"
},
  "geometry": {"coordinates":[46.03122000000001,32.6123],"type":"Point"}
}