{
  "type": "Feature",
  "properties": {
    "gn:admin1_code":"7.0",
    "gn:admin2_code":"9166542.0",
    "gn:asciiname":"Qaryat ar Rufush",
    "gn:country_code":"IQ",
    "gn:dem":44,
    "gn:feature_class":"P",
    "gn:feature_code":"PPL",
    "gn:name":"Qaryat ar Ruf\u016bsh",
    "gn:population":0,
    "gn:timezone":"Asia/Baghdad",
    "iso:country":"IQ",
    "name:ara_x_preferred":[
        "\u0642\u0631\u064a\u0629 \u0627\u0644\u0631\u0641\u0648\u0634"
    ],
    "name:ara_x_variant":[
        "\u0627\u0644\u0631\u0641\u0648\u0634"
    ],
    "name:und_x_variant":[
        "Qaryat ar Ruf\u016bsh",
        "Ar Ruf\u016bsh"
    ],
    "wof:name":"Qaryat ar Rufush",
    "wof:placetype":"locality"
},
  "geometry": {"coordinates":[43.97109,33.19423],"type":"Point"}
}