{
  "type": "Feature",
  "properties": {
    "gn:admin1_code":"4.0",
    "gn:admin2_code":"98634.0",
    "gn:asciiname":"Sultan Al Zahim",
    "gn:cc2":"IQ",
    "gn:country_code":"IQ",
    "gn:dem":18,
    "gn:feature_class":"P",
    "gn:feature_code":"PPL",
    "gn:name":"Sul\u0163\u0101n \u0100l Za\u1e29\u012bm",
    "gn:population":0,
    "gn:timezone":"Asia/Baghdad",
    "iso:country":"IQ",
    "name:und_x_variant":[
        "Su\u0163\u0101n az Za\u1e29\u012bm",
        "Sul\u0163\u0101n \u0100l Za\u1e29\u012bm"
    ],
    "wof:name":"Sultan Al Zahim",
    "wof:placetype":"locality"
},
  "geometry": {"coordinates":[44.65,31.61667000000001],"type":"Point"}
}