{
  "type": "Feature",
  "properties": {
    "gn:admin1_code":"7.0",
    "gn:admin2_code":"99101.0",
    "gn:asciiname":"Tall 'Idan",
    "gn:country_code":"IQ",
    "gn:dem":42,
    "gn:feature_class":"P",
    "gn:feature_code":"PPL",
    "gn:name":"Tall \u2018\u012ad\u0101n",
    "gn:population":0,
    "gn:timezone":"Asia/Baghdad",
    "iso:country":"IQ",
    "name:ara_x_preferred":[
        "\u062a\u0644 \u0639\u064a\u062f\u0627\u0646"
    ],
    "name:und_x_variant":[
        "Tall Gh\u012bd\u0101n",
        "Tall \u2018\u012ad\u0101n"
    ],
    "wof:name":"Tall 'Idan",
    "wof:placetype":"locality"
},
  "geometry": {"coordinates":[44.08835,33.11012],"type":"Point"}
}