{
  "type": "Feature",
  "properties": {
    "gn:admin1_code":"8.0",
    "gn:admin2_code":"97269.0",
    "gn:asciiname":"Aytut",
    "gn:country_code":"IQ",
    "gn:dem":734,
    "gn:feature_class":"P",
    "gn:feature_code":"PPL",
    "gn:name":"Ayt\u016bt",
    "gn:population":0,
    "gn:timezone":"Asia/Baghdad",
    "iso:country":"IQ",
    "name:ara_x_preferred":[
        "\u0627\u064a\u062a\u0648\u062a"
    ],
    "name:kur_x_preferred":[
        "\u00catut"
    ],
    "name:kur_x_variant":[
        "\u0626\u06ce\u062a\u0648\u062a",
        "\u00cat\u00eet",
        "\u0626\u06ce\u062a\u064a\u062a"
    ],
    "name:und_x_variant":[
        "Ayt\u016bt",
        "Etit"
    ],
    "wof:name":"Aytut",
    "wof:placetype":"locality"
},
  "geometry": {"coordinates":[43.08326,36.84594],"type":"Point"}
}