{
  "type": "Feature",
  "properties": {
    "gn:admin1_code":"8.0",
    "gn:admin2_code":"89569.0",
    "gn:asciiname":"Bayshilk",
    "gn:country_code":"IQ",
    "gn:dem":529,
    "gn:feature_class":"P",
    "gn:feature_code":"PPL",
    "gn:name":"Bayshilk",
    "gn:population":0,
    "gn:timezone":"Asia/Baghdad",
    "iso:country":"IQ",
    "name:ara_x_preferred":[
        "\u0628\u064a\u0634\u0644\u0643"
    ],
    "name:kur_x_preferred":[
        "Pish\u00eelk"
    ],
    "name:kur_x_variant":[
        "\u067e\u0634\u064a\u0644\u0643",
        "B\u00eash\u00eelk",
        "\u0628\u06ce\u0634\u064a\u0644\u0643"
    ],
    "name:und_x_variant":[
        "B\u0113shilki",
        "P\u0113shilk",
        "Pshilk",
        "Bayshilk"
    ],
    "wof:name":"Bayshilk",
    "wof:placetype":"locality"
},
  "geometry": {"coordinates":[42.8198,37.08286],"type":"Point"}
}