{
  "type": "Feature",
  "properties": {
    "gn:admin1_code":"8.0",
    "gn:admin2_code":"97269.0",
    "gn:asciiname":"Kharkhabkah",
    "gn:country_code":"IQ",
    "gn:dem":621,
    "gn:feature_class":"P",
    "gn:feature_code":"PPLL",
    "gn:name":"Kharkhabkah",
    "gn:population":0,
    "gn:timezone":"Asia/Baghdad",
    "iso:country":"IQ",
    "name:ara_x_preferred":[
        "\u062e\u0631\u062e\u0628\u0643\u0647"
    ],
    "name:kur_x_preferred":[
        "Xirxepka"
    ],
    "name:kur_x_variant":[
        "\u062e\u0631\u062e\u06d5\u067e\u0643\u0627",
        "Xerxepka",
        "\u062e\u06d5\u0631\u062e\u06d5\u067e\u0643\u0627"
    ],
    "name:und_x_variant":[
        "Kharkhabk\u0101",
        "Kharkhabkah"
    ],
    "wof:name":"Kharkhabkah",
    "wof:placetype":"locality"
},
  "geometry": {"coordinates":[42.9165,37.08205],"type":"Point"}
}