{
  "type": "Feature",
  "properties": {
    "gn:admin1_code":"13.0",
    "gn:admin2_code":"94786.0",
    "gn:asciiname":"'Umar Mandan",
    "gn:country_code":"IQ",
    "gn:dem":450,
    "gn:feature_class":"P",
    "gn:feature_code":"PPL",
    "gn:name":"\u2018Umar Mand\u0101n",
    "gn:population":0,
    "gn:timezone":"Asia/Baghdad",
    "iso:country":"IQ",
    "name:ara_x_preferred":[
        "\u0639\u0645\u0631 \u0645\u0646\u062f\u0627\u0646"
    ],
    "name:und_x_variant":[
        "\u2018Umar Mand\u0101n"
    ],
    "wof:name":"'Umar Mandan",
    "wof:placetype":"locality"
},
  "geometry": {"coordinates":[44.5547,35.79846],"type":"Point"}
}