{
  "type": "Feature",
  "properties": {
    "gn:admin1_code":"11.0",
    "gn:admin2_code":"9166534.0",
    "gn:asciiname":"Avgirke",
    "gn:country_code":"IQ",
    "gn:dem":1358,
    "gn:feature_class":"P",
    "gn:feature_code":"PPL",
    "gn:name":"Avgirke",
    "gn:population":0,
    "gn:timezone":"Asia/Baghdad",
    "iso:country":"IQ",
    "name:ara_x_preferred":[
        "\u0646\u0648\u0641\u06af\u0631\u0643\u0647"
    ],
    "name:kur_x_preferred":[
        "Nuvgirke"
    ],
    "name:kur_x_variant":[
        "\u0646\u0648\u06a4\u06af\u0631\u0643\u06d5",
        "Avgirke",
        "\u0626\u0627\u06a4\u06af\u0631\u0643\u06d5"
    ],
    "name:und_x_variant":[
        "N\u0101rkurka",
        "Nuvgrka",
        "N\u0101vkurka",
        "N\u016bfgirkah"
    ],
    "wof:name":"Avgirke",
    "wof:placetype":"locality"
},
  "geometry": {"coordinates":[44.08558,37.07109000000001],"type":"Point"}
}