{
  "type": "Feature",
  "properties": {
    "gn:admin1_code":"7.0",
    "gn:admin2_code":"99101.0",
    "gn:asciiname":"'Arab Salih Hulu",
    "gn:country_code":"IQ",
    "gn:dem":30,
    "gn:feature_class":"P",
    "gn:feature_code":"PPL",
    "gn:name":"\u2018Arab \u015e\u0101li\u1e29 \u1e28ul\u016b",
    "gn:population":0,
    "gn:timezone":"Asia/Baghdad",
    "iso:country":"IQ",
    "name:ara_x_preferred":[
        "\u0639\u0631\u0628 \u0635\u0627\u0644\u062d \u062d\u0644\u0648"
    ],
    "name:und_x_variant":[
        "\u2018Arab \u015e\u0101li\u1e29 \u1e28ul\u016b"
    ],
    "wof:name":"'Arab Salih Hulu",
    "wof:placetype":"locality"
},
  "geometry": {"coordinates":[44.46237,32.9236],"type":"Point"}
}