{
  "type": "Feature",
  "properties": {
    "gn:admin1_code":"5.0",
    "gn:admin2_code":"97416.0",
    "gn:asciiname":"Guran",
    "gn:country_code":"IQ",
    "gn:dem":789,
    "gn:feature_class":"P",
    "gn:feature_code":"PPL",
    "gn:name":"G\u016br\u0101n",
    "gn:population":0,
    "gn:timezone":"Asia/Baghdad",
    "iso:country":"IQ",
    "name:ara_x_preferred":[
        "G\u016br\u0101n"
    ],
    "name:ara_x_variant":[
        "\u06af\u0648\u0631\u0627\u0646"
    ],
    "name:nor_x_preferred":[
        "Guran"
    ],
    "wof:name":"Guran",
    "wof:placetype":"locality"
},
  "geometry": {"coordinates":[44.85832,35.36604000000001],"type":"Point"}
}