{
  "type": "Feature",
  "properties": {
    "gn:admin1_code":"9.0",
    "gn:admin2_code":"98700.0",
    "gn:asciiname":"Albu Hamzah",
    "gn:country_code":"IQ",
    "gn:dem":13,
    "gn:feature_class":"P",
    "gn:feature_code":"PPL",
    "gn:name":"\u0100lb\u016b \u1e28amzah",
    "gn:population":0,
    "gn:timezone":"Asia/Baghdad",
    "iso:country":"IQ",
    "name:ara_x_preferred":[
        "\u0627\u0644\u0628\u0648 \u062d\u0645\u0632\u0647"
    ],
    "name:und_x_variant":[
        "Ab\u016b \u1e28amzah",
        "Albu Hamza",
        "Alb\u016b Ramzah",
        "\u0100lb\u016b \u1e28amzah"
    ],
    "wof:name":"Albu Hamzah",
    "wof:placetype":"locality"
},
  "geometry": {"coordinates":[46.09367,31.79622],"type":"Point"}
}