{
  "type": "Feature",
  "properties": {
    "gn:admin1_code":"6.0",
    "gn:admin2_code":"99358.0",
    "gn:asciiname":"Sayyid Musa",
    "gn:country_code":"IQ",
    "gn:dem":23,
    "gn:feature_class":"P",
    "gn:feature_code":"PPL",
    "gn:name":"Sayyid M\u016bs\u00e1",
    "gn:population":0,
    "gn:timezone":"Asia/Baghdad",
    "iso:country":"IQ",
    "name:ara_x_preferred":[
        "\u0633\u064a\u062f \u0645\u0648\u0633\u0649"
    ],
    "name:und_x_variant":[
        "Sayyid M\u016bs\u00e1"
    ],
    "wof:name":"Sayyid Musa",
    "wof:placetype":"locality"
},
  "geometry": {"coordinates":[44.98614,32.37194],"type":"Point"}
}