{
  "type": "Feature",
  "properties": {
    "gn:admin1_code":"14.0",
    "gn:admin2_code":"99305.0",
    "gn:asciiname":"Qaryat al `Umayyah as Saghirah",
    "gn:country_code":"IQ",
    "gn:dem":13,
    "gn:feature_class":"P",
    "gn:feature_code":"PPL",
    "gn:name":"Qaryat al \u2018Umayyah a\u015f \u015eagh\u012brah",
    "gn:population":0,
    "gn:timezone":"Asia/Baghdad",
    "iso:country":"IQ",
    "name:ara_x_preferred":[
        "\u0642\u0631\u064a\u0629 \u0627\u0644\u0639\u0645\u064a\u0629 \u0627\u0644\u0635\u063a\u064a\u0631\u0629"
    ],
    "name:und_x_variant":[
        "Qaryat al \u2018Umayyah a\u015f \u015eagh\u012brah",
        "Qaryat al \u2018Am\u012byah a\u015f \u015eagh\u012brah"
    ],
    "wof:name":"Qaryat al `Umayyah as Saghirah",
    "wof:placetype":"locality"
},
  "geometry": {"coordinates":[46.55089,32.50712],"type":"Point"}
}