{
  "type": "Feature",
  "properties": {
    "gn:admin1_code":"18.0",
    "gn:admin2_code":"6783103.0",
    "gn:asciiname":"Shaman Aswad",
    "gn:country_code":"IQ",
    "gn:dem":113,
    "gn:feature_class":"P",
    "gn:feature_code":"PPL",
    "gn:name":"Sh\u0101m\u0101n Aswad",
    "gn:population":0,
    "gn:timezone":"Asia/Baghdad",
    "iso:country":"IQ",
    "name:ara_x_preferred":[
        "\u0634\u0627\u0645\u0627\u0646 \u0627\u0633\u0648\u062f"
    ],
    "name:und_x_variant":[
        "Sh\u0101m\u0101n Aswad"
    ],
    "wof:name":"Shaman Aswad",
    "wof:placetype":"locality"
},
  "geometry": {"coordinates":[44.14257,34.65382],"type":"Point"}
}