{
  "type": "Feature",
  "properties": {
    "gn:admin1_code":"7.0",
    "gn:admin2_code":"99101.0",
    "gn:asciiname":"Tall al Farkhah",
    "gn:country_code":"IQ",
    "gn:dem":34,
    "gn:feature_class":"P",
    "gn:feature_code":"PPL",
    "gn:name":"Tall al Farkhah",
    "gn:population":0,
    "gn:timezone":"Asia/Baghdad",
    "iso:country":"IQ",
    "name:ara_x_preferred":[
        "\u062a\u0644 \u0627\u0644\u0641\u0631\u062e\u0629"
    ],
    "wof:name":"Tall al Farkhah",
    "wof:placetype":"locality"
},
  "geometry": {"coordinates":[44.3635,33.11019],"type":"Point"}
}