{
  "type": "Feature",
  "properties": {
    "gn:admin1_code":"15.0",
    "gn:admin2_code":"90392.0",
    "gn:asciiname":"Tall Samir",
    "gn:country_code":"IQ",
    "gn:dem":375,
    "gn:feature_class":"P",
    "gn:feature_code":"PPL",
    "gn:name":"Tall Sam\u012br",
    "gn:population":0,
    "gn:timezone":"Asia/Baghdad",
    "iso:country":"IQ",
    "name:ara_x_preferred":[
        "\u062a\u0644 \u0633\u0645\u064a\u0631"
    ],
    "name:kur_x_preferred":[
        "Tel Sem\u00eer"
    ],
    "name:kur_x_variant":[
        "\u062a\u06d5\u0644 \u0633\u06d5\u0645\u064a\u0631"
    ],
    "name:und_x_variant":[
        "Tel Sumayir",
        "Tall Sumayyir",
        "Til Samir",
        "Tall Sam\u012br"
    ],
    "wof:name":"Tall Samir",
    "wof:placetype":"locality"
},
  "geometry": {"coordinates":[42.16638,36.75078],"type":"Point"}
}