{
  "type": "Feature",
  "properties": {
    "gn:admin1_code":"7.0",
    "gn:admin2_code":"99101.0",
    "gn:asciiname":"'Arab Thamir Mujawwal",
    "gn:country_code":"IQ",
    "gn:dem":38,
    "gn:feature_class":"P",
    "gn:feature_code":"PPL",
    "gn:name":"\u2018Arab Th\u0101mir Mujawwal",
    "gn:population":0,
    "gn:timezone":"Asia/Baghdad",
    "iso:country":"IQ",
    "name:ara_x_preferred":[
        "\u0639\u0631\u0628 \u062b\u0627\u0645\u0631 \u0645\u062c\u0648\u0644"
    ],
    "name:und_x_variant":[
        "\u2018Arab Th\u0101mir Mujawl",
        "\u2018Arab Th\u0101mir Mujawwal"
    ],
    "wof:name":"'Arab Thamir Mujawwal",
    "wof:placetype":"locality"
},
  "geometry": {"coordinates":[44.3108,33.01485],"type":"Point"}
}