{
  "type": "Feature",
  "properties": {
    "gn:admin1_code":"7.0",
    "gn:admin2_code":"9166569.0",
    "gn:asciiname":"'Uwayd 'Abd",
    "gn:country_code":"IQ",
    "gn:dem":38,
    "gn:feature_class":"P",
    "gn:feature_code":"PPL",
    "gn:name":"\u2018\u016awayd \u2018Abd",
    "gn:population":0,
    "gn:timezone":"Asia/Baghdad",
    "iso:country":"IQ",
    "name:ara_x_preferred":[
        "\u0639\u0648\u064a\u062f \u0639\u0628\u062f"
    ],
    "name:und_x_variant":[
        "\u2018\u016awayd \u2018Abd Naww\u0101r",
        "\u0639\u0648\u064a\u062f \u0639\u0628\u062f \u0646\u0648\u0627\u0631",
        "\u2018\u016awayd \u2018Abd"
    ],
    "wof:name":"'Uwayd 'Abd",
    "wof:placetype":"locality"
},
  "geometry": {"coordinates":[44.16298,33.6159],"type":"Point"}
}