{
  "type": "Feature",
  "properties": {
    "gn:admin1_code":"3.0",
    "gn:admin2_code":"9166626.0",
    "gn:asciiname":"Huwayshali",
    "gn:country_code":"IQ",
    "gn:dem":8,
    "gn:feature_class":"P",
    "gn:feature_code":"PPL",
    "gn:name":"\u1e28uwayshal\u012b",
    "gn:population":0,
    "gn:timezone":"Asia/Baghdad",
    "iso:country":"IQ",
    "name:ara_x_preferred":[
        "\u062d\u0648\u064a\u0634\u0644\u064a"
    ],
    "name:und_x_variant":[
        "\u1e28uwayshal\u012b"
    ],
    "wof:name":"Huwayshali",
    "wof:placetype":"locality"
},
  "geometry": {"coordinates":[45.76919,31.16704],"type":"Point"}
}