{
  "type": "Feature",
  "properties": {
    "gn:admin1_code":"18.0",
    "gn:admin2_code":"9166616.0",
    "gn:asciiname":"Hamadi Sayab",
    "gn:country_code":"IQ",
    "gn:dem":42,
    "gn:feature_class":"P",
    "gn:feature_code":"PPL",
    "gn:name":"\u1e28am\u0101d\u012b \u015eay\u0101b",
    "gn:population":0,
    "gn:timezone":"Asia/Baghdad",
    "iso:country":"IQ",
    "name:ara_x_preferred":[
        "\u062d\u0645\u0627\u062f\u064a \u0635\u064a\u0627\u0628"
    ],
    "name:und_x_variant":[
        "\u1e28am\u0101d\u012b \u015eay\u0101b"
    ],
    "wof:name":"Hamadi Sayab",
    "wof:placetype":"locality"
},
  "geometry": {"coordinates":[44.37153,33.78651],"type":"Point"}
}