{
  "type": "Feature",
  "properties": {
    "gn:admin1_code":"15.0",
    "gn:admin2_code":"9166620.0",
    "gn:asciiname":"Tall Abu Sanam",
    "gn:country_code":"IQ",
    "gn:dem":270,
    "gn:feature_class":"P",
    "gn:feature_code":"PPL",
    "gn:name":"Tall Ab\u016b San\u0101m",
    "gn:population":0,
    "gn:timezone":"Asia/Baghdad",
    "iso:country":"IQ",
    "name:ara_x_preferred":[
        "\u062a\u0644 \u0627\u0628\u0648 \u0633\u0646\u0627\u0645"
    ],
    "name:und_x_variant":[
        "Tall Sanam",
        "Tall Ab\u016b San\u0101m"
    ],
    "wof:name":"Tall Abu Sanam",
    "wof:placetype":"locality"
},
  "geometry": {"coordinates":[42.32432,36.15987],"type":"Point"}
}