{
  "type": "Feature",
  "properties": {
    "gn:admin1_code":"2.0",
    "gn:admin2_code":"98994.0",
    "gn:asciiname":"Athar ash Shati",
    "gn:country_code":"IQ",
    "gn:dem":6,
    "gn:feature_class":"P",
    "gn:feature_code":"PPL",
    "gn:name":"\u0100th\u0101r ash Sh\u0101\u0163\u012b",
    "gn:population":0,
    "gn:timezone":"Asia/Baghdad",
    "iso:country":"IQ",
    "name:ara_x_preferred":[
        "\u0622\u062b\u0627\u0631 \u0627\u0644\u0634\u0627\u0637\u064a"
    ],
    "name:und_x_variant":[
        "\u0100th\u0101r ash Sh\u0101\u0163\u012b"
    ],
    "wof:name":"Athar ash Shati",
    "wof:placetype":"locality"
},
  "geometry": {"coordinates":[47.42837,31.16897],"type":"Point"}
}