{
  "type": "Feature",
  "properties": {
    "gn:admin1_code":"4.0",
    "gn:admin2_code":"99763.0",
    "gn:asciiname":"'Arar Mazhar",
    "gn:country_code":"IQ",
    "gn:dem":21,
    "gn:feature_class":"P",
    "gn:feature_code":"PPL",
    "gn:name":"\u2018Ar\u0101r Mazhar",
    "gn:population":0,
    "gn:timezone":"Asia/Baghdad",
    "iso:country":"IQ",
    "name:ara_x_preferred":[
        "\u0639\u0631\u0627\u0631 \u0645\u0632\u0647\u0631"
    ],
    "name:und_x_variant":[
        "\u2018Ar\u0101r Mazhar"
    ],
    "wof:name":"'Arar Mazhar",
    "wof:placetype":"locality"
},
  "geometry": {"coordinates":[44.65906,31.87965],"type":"Point"}
}