{
  "type": "Feature",
  "properties": {
    "gn:admin1_code":"10.0",
    "gn:admin2_code":"94590.0",
    "gn:asciiname":"Mishiyaw",
    "gn:country_code":"IQ",
    "gn:dem":514,
    "gn:feature_class":"P",
    "gn:feature_code":"PPL",
    "gn:name":"M\u012bshiy\u0101w",
    "gn:population":0,
    "gn:timezone":"Asia/Baghdad",
    "iso:country":"IQ",
    "name:ara_x_preferred":[
        "\u0645\u064a\u0634\u064a\u0627\u0648"
    ],
    "name:ara_x_variant":[
        "M\u012bshiy\u0101w"
    ],
    "name:und_x_variant":[
        "\u2018Al\u012b Ya\u2018q\u016bb",
        "\u0639\u0644\u064a \u064a\u0639\u0642\u0648\u0628"
    ],
    "wof:name":"Mishiyaw",
    "wof:placetype":"locality"
},
  "geometry": {"coordinates":[45.70172,34.94408],"type":"Point"}
}