{
  "type": "Feature",
  "properties": {
    "gn:admin1_code":"16.0",
    "gn:admin2_code":"98460.0",
    "gn:asciiname":"'Urkub Abu Sudaymah",
    "gn:country_code":"IQ",
    "gn:dem":32,
    "gn:feature_class":"P",
    "gn:feature_code":"PPL",
    "gn:name":"\u2018Urk\u016bb Ab\u016b \u015eudaymah",
    "gn:population":0,
    "gn:timezone":"Asia/Baghdad",
    "iso:country":"IQ",
    "name:ara_x_preferred":[
        "\u0639\u0631\u0643\u0648\u0628 \u0627\u0628\u0648 \u0635\u062f\u064a\u0645\u0629"
    ],
    "name:und_x_variant":[
        "\u2018Urk\u016bb Ab\u016b \u015eudaymah"
    ],
    "wof:name":"'Urkub Abu Sudaymah",
    "wof:placetype":"locality"
},
  "geometry": {"coordinates":[44.70414,32.92435],"type":"Point"}
}