{
  "type": "Feature",
  "properties": {
    "gn:admin1_code":"13.0",
    "gn:admin2_code":"6770659.0",
    "gn:asciiname":"Qaryat Rabid Abu Da'aj",
    "gn:country_code":"IQ",
    "gn:dem":178,
    "gn:feature_class":"P",
    "gn:feature_code":"PPL",
    "gn:name":"Qaryat Rab\u012b\u1e11 Ab\u016b Da\u2018\u0101j",
    "gn:population":0,
    "gn:timezone":"Asia/Baghdad",
    "iso:country":"IQ",
    "name:ara_x_preferred":[
        "\u0642\u0631\u064a\u0629 \u0631\u0628\u064a\u0636 \u0627\u0628\u0648 \u062f\u0639\u0627\u062c"
    ],
    "name:und_x_variant":[
        "Qaryat Rab\u012b\u1e11 Ab\u016b Da\u2018\u0101j"
    ],
    "wof:name":"Qaryat Rabid Abu Da'aj",
    "wof:placetype":"locality"
},
  "geometry": {"coordinates":[43.96842,35.15124],"type":"Point"}
}