{
  "type": "Feature",
  "properties": {
    "gn:admin1_code":"11.0",
    "gn:admin2_code":"9166592.0",
    "gn:asciiname":"Sadar",
    "gn:country_code":"IQ",
    "gn:dem":656,
    "gn:feature_class":"P",
    "gn:feature_code":"PPL",
    "gn:name":"Sadar",
    "gn:population":0,
    "gn:timezone":"Asia/Baghdad",
    "iso:country":"IQ",
    "name:ara_x_preferred":[
        "\u0633\u062f\u0631"
    ],
    "name:ceb_x_preferred":[
        "Sadar"
    ],
    "name:deu_x_preferred":[
        "Sadar"
    ],
    "name:kur_x_preferred":[
        "Sede\u1e5f"
    ],
    "name:kur_x_variant":[
        "\u0633\u06d5\u062f\u06d5\u0695"
    ],
    "name:spa_x_preferred":[
        "Sadar"
    ],
    "wof:name":"Sadar",
    "wof:placetype":"locality"
},
  "geometry": {"coordinates":[44.43901,36.75617],"type":"Point"}
}