{
  "type": "Feature",
  "properties": {
    "gn:admin1_code":"16.0",
    "gn:admin2_code":"9166961.0",
    "gn:asciiname":"Hamid",
    "gn:country_code":"IQ",
    "gn:dem":29,
    "gn:feature_class":"P",
    "gn:feature_code":"PPL",
    "gn:name":"\u1e28\u0101mid",
    "gn:population":0,
    "gn:timezone":"Asia/Baghdad",
    "iso:country":"IQ",
    "name:ara_x_preferred":[
        "\u1e28\u0101mid"
    ],
    "name:ara_x_variant":[
        "\u062d\u0645\u064a\u062f"
    ],
    "name:cat_x_preferred":[
        "H\u00e0mid"
    ],
    "name:deu_x_preferred":[
        "Hamid"
    ],
    "name:rus_x_preferred":[
        "\u0425\u0430\u043c\u0438\u0434"
    ],
    "name:ukr_x_preferred":[
        "\u0425\u0430\u043c\u0435\u0434"
    ],
    "wof:name":"Hamid",
    "wof:placetype":"locality"
},
  "geometry": {"coordinates":[45.04722,32.95],"type":"Point"}
}