{
  "type": "Feature",
  "properties": {
    "gn:admin1_code":"16.0",
    "gn:admin2_code":"9166606.0",
    "gn:asciiname":"Jawdat al 'Ajim",
    "gn:country_code":"IQ",
    "gn:dem":21,
    "gn:feature_class":"P",
    "gn:feature_code":"PPL",
    "gn:name":"Jawdat al \u2018Ajim",
    "gn:population":0,
    "gn:timezone":"Asia/Baghdad",
    "iso:country":"IQ",
    "name:ara_x_preferred":[
        "\u062c\u0648\u062f\u0629 \u0627\u0644\u0639\u062c\u0645"
    ],
    "name:und_x_variant":[
        "Jawdat al \u2018Ajim"
    ],
    "wof:name":"Jawdat al 'Ajim",
    "wof:placetype":"locality"
},
  "geometry": {"coordinates":[45.45193,32.48278],"type":"Point"}
}