{
  "type": "Feature",
  "properties": {
    "gn:admin1_code":"18.0",
    "gn:admin2_code":"6872046.0",
    "gn:asciiname":"Mashrah Mulla Farih",
    "gn:country_code":"IQ",
    "gn:dem":131,
    "gn:feature_class":"P",
    "gn:feature_code":"PPL",
    "gn:name":"Mashra\u1e29 Mull\u0101 Far\u012b\u1e29",
    "gn:population":0,
    "gn:timezone":"Asia/Baghdad",
    "iso:country":"IQ",
    "name:ara_x_preferred":[
        "\u0645\u0634\u0631\u062d \u0645\u0644\u0627 \u0641\u0631\u064a\u062d"
    ],
    "name:und_x_variant":[
        "Mashra\u1e29 Mull\u0101 Far\u012b\u1e29"
    ],
    "wof:name":"Mashrah Mulla Farih",
    "wof:placetype":"locality"
},
  "geometry": {"coordinates":[43.24132,34.50734],"type":"Point"}
}