{
  "type": "Feature",
  "properties": {
    "gn:admin1_code":"10.0",
    "gn:admin2_code":"9166680.0",
    "gn:asciiname":"Al Qadawi",
    "gn:cc2":"IQ",
    "gn:country_code":"IQ",
    "gn:dem":43,
    "gn:feature_class":"P",
    "gn:feature_code":"PPL",
    "gn:name":"Al Qa\u1e11\u0101w\u012b",
    "gn:population":0,
    "gn:timezone":"Asia/Baghdad",
    "iso:country":"IQ",
    "name:und_x_variant":[
        "Al Qadh\u0101wi",
        "\u2018Arab Alwara",
        "Al Qa\u1e11\u0101w\u012b"
    ],
    "wof:name":"Al Qadawi",
    "wof:placetype":"locality"
},
  "geometry": {"coordinates":[44.79389000000001,33.63056],"type":"Point"}
}