{
  "type": "Feature",
  "properties": {
    "gn:admin1_code":"13.0",
    "gn:admin2_code":"9166581.0",
    "gn:asciiname":"Shi Kani",
    "gn:country_code":"IQ",
    "gn:dem":188,
    "gn:feature_class":"P",
    "gn:feature_code":"PPL",
    "gn:name":"Sh\u012b K\u0101n\u012b",
    "gn:population":0,
    "gn:timezone":"Asia/Baghdad",
    "iso:country":"IQ",
    "name:ara_x_preferred":[
        "\u0634\u064a \u0643\u0627\u0646\u064a"
    ],
    "name:ara_x_variant":[
        "Sh\u012b K\u0101n\u012b"
    ],
    "name:und_x_variant":[
        "Shakh\u0101n\u012byah"
    ],
    "wof:name":"Shi Kani",
    "wof:placetype":"locality"
},
  "geometry": {"coordinates":[44.2842,35.08614],"type":"Point"}
}