{
  "type": "Feature",
  "properties": {
    "gn:admin1_code":"5.0",
    "gn:admin2_code":"96204.0",
    "gn:asciiname":"Qurtas",
    "gn:country_code":"IQ",
    "gn:dem":484,
    "gn:feature_class":"P",
    "gn:feature_code":"PPL",
    "gn:name":"Qurt\u0101s",
    "gn:population":0,
    "gn:timezone":"Asia/Baghdad",
    "iso:country":"IQ",
    "name:ara_x_preferred":[
        "Qurt\u0101s"
    ],
    "name:fas_x_preferred":[
        "\u0641\u0648\u0631\u062a\u0627\u0633"
    ],
    "name:fas_x_variant":[
        "F\u016brt\u0101s"
    ],
    "name:kur_x_preferred":[
        "Qurtas"
    ],
    "name:kur_x_variant":[
        "\u0642\u0648\u0631\u062a\u0627\u0633"
    ],
    "wof:name":"Qurtas",
    "wof:placetype":"locality"
},
  "geometry": {"coordinates":[45.883,35.2367],"type":"Point"}
}