{
  "type": "Feature",
  "properties": {
    "gn:admin1_code":"5.0",
    "gn:admin2_code":"92051.0",
    "gn:asciiname":"Serdol",
    "gn:country_code":"IQ",
    "gn:dem":1019,
    "gn:feature_class":"P",
    "gn:feature_code":"PPL",
    "gn:name":"Serdol",
    "gn:population":0,
    "gn:timezone":"Asia/Baghdad",
    "iso:country":"IQ",
    "name:ara_x_preferred":[
        "\u0633\u0631\u062f\u0648\u0644"
    ],
    "name:kur_x_preferred":[
        "\u0633\u06d5\u0631\u062f\u06c6\u06b5"
    ],
    "name:kur_x_variant":[
        "Serdol"
    ],
    "name:und_x_variant":[
        "Sard\u014dl",
        "Sardawl",
        "\u0633\u0631\u062f\u0648\u0644",
        "Sardol"
    ],
    "wof:name":"Serdol",
    "wof:placetype":"locality"
},
  "geometry": {"coordinates":[44.61454000000001,36.31586],"type":"Point"}
}