{
  "type": "Feature",
  "properties": {
    "gn:admin1_code":"13.0",
    "gn:admin2_code":"6770659.0",
    "gn:asciiname":"Tak Tak",
    "gn:country_code":"IQ",
    "gn:dem":149,
    "gn:feature_class":"P",
    "gn:feature_code":"PPL",
    "gn:name":"\u0162ak \u0162ak",
    "gn:population":0,
    "gn:timezone":"Asia/Baghdad",
    "iso:country":"IQ",
    "name:ara_x_preferred":[
        "\u0637\u0643 \u0637\u0643"
    ],
    "name:und_x_variant":[
        "\u0162ak \u0162ak"
    ],
    "wof:name":"Tak Tak",
    "wof:placetype":"locality"
},
  "geometry": {"coordinates":[43.29482,35.44839],"type":"Point"}
}