{
  "type": "Feature",
  "properties": {
    "gn:admin1_code":"11.0",
    "gn:admin2_code":"9166534.0",
    "gn:asciiname":"Khalutah",
    "gn:country_code":"IQ",
    "gn:dem":552,
    "gn:feature_class":"P",
    "gn:feature_code":"PPL",
    "gn:name":"Kh\u0101l\u016btah",
    "gn:population":0,
    "gn:timezone":"Asia/Baghdad",
    "iso:country":"IQ",
    "name:und_x_variant":[
        "Kh\u0101l\u016btah"
    ],
    "wof:name":"Khalutah",
    "wof:placetype":"locality"
},
  "geometry": {"coordinates":[44.2375,36.96722000000001],"type":"Point"}
}