{
  "type": "Feature",
  "properties": {
    "gn:admin1_code":"13.0",
    "gn:admin2_code":"6770659.0",
    "gn:asciiname":"Qaryat al Muradiyah",
    "gn:country_code":"IQ",
    "gn:dem":186,
    "gn:feature_class":"P",
    "gn:feature_code":"PPL",
    "gn:name":"Qaryat al Mur\u0101d\u012byah",
    "gn:population":0,
    "gn:timezone":"Asia/Baghdad",
    "iso:country":"IQ",
    "name:ara_x_preferred":[
        "\u0642\u0631\u064a\u0629 \u0627\u0644\u0645\u0631\u0627\u062f\u064a\u0629"
    ],
    "name:und_x_variant":[
        "Qaryat al Mur\u0101d\u012byah"
    ],
    "wof:name":"Qaryat al Muradiyah",
    "wof:placetype":"locality"
},
  "geometry": {"coordinates":[43.72324,35.17872],"type":"Point"}
}