{
  "type": "Feature",
  "properties": {
    "gn:admin1_code":"18.0",
    "gn:admin2_code":"90148.0",
    "gn:asciiname":"'Awwad Mahmud",
    "gn:country_code":"IQ",
    "gn:dem":109,
    "gn:feature_class":"P",
    "gn:feature_code":"PPL",
    "gn:name":"\u2018Aww\u0101d Ma\u1e29m\u016bd",
    "gn:population":0,
    "gn:timezone":"Asia/Baghdad",
    "iso:country":"IQ",
    "name:ara_x_preferred":[
        "\u0639\u0648\u0627\u062f \u0645\u062d\u0645\u0648\u062f"
    ],
    "name:und_x_variant":[
        "\u2018Aww\u0101d Ma\u1e29m\u016bd"
    ],
    "wof:name":"'Awwad Mahmud",
    "wof:placetype":"locality"
},
  "geometry": {"coordinates":[43.49529,34.95507],"type":"Point"}
}