{
  "type": "Feature",
  "properties": {
    "gn:admin1_code":"5.0",
    "gn:admin2_code":"9166684.0",
    "gn:asciiname":"Bamsar",
    "gn:country_code":"IQ",
    "gn:dem":1370,
    "gn:feature_class":"P",
    "gn:feature_code":"PPL",
    "gn:name":"Bamsar",
    "gn:population":0,
    "gn:timezone":"Asia/Baghdad",
    "iso:country":"IQ",
    "name:fas_x_preferred":[
        "\u0628\u0645\u0633\u0631"
    ],
    "wof:name":"Bamsar",
    "wof:placetype":"locality"
},
  "geometry": {"coordinates":[45.9982,35.8123],"type":"Point"}
}