{
  "type": "Feature",
  "properties": {
    "gn:admin1_code":"15.0",
    "gn:admin2_code":"9166541.0",
    "gn:asciiname":"Qaryat Karamlays",
    "gn:country_code":"IQ",
    "gn:dem":280,
    "gn:feature_class":"P",
    "gn:feature_code":"PPL",
    "gn:name":"Qaryat Karamlays",
    "gn:population":0,
    "gn:timezone":"Asia/Baghdad",
    "iso:country":"IQ",
    "name:ara_x_preferred":[
        "\u0642\u0631\u064a\u0629 \u0643\u0631\u0645\u0644\u064a\u0633"
    ],
    "name:und_x_variant":[
        "Kirmalays",
        "Keramlais",
        "Qaryat Kiraml\u012bs",
        "Qaryat Karamlays",
        "Karamlish",
        "Karemlesh"
    ],
    "wof:name":"Qaryat Karamlays",
    "wof:placetype":"locality"
},
  "geometry": {"coordinates":[43.41369,36.30275],"type":"Point"}
}