{
  "type": "Feature",
  "properties": {
    "gn:admin1_code":"10.0",
    "gn:admin2_code":"94590.0",
    "gn:asciiname":"Shamishir Kul",
    "gn:country_code":"IQ",
    "gn:dem":676,
    "gn:feature_class":"P",
    "gn:feature_code":"PPL",
    "gn:name":"Sham\u012bshir K\u016bl",
    "gn:population":0,
    "gn:timezone":"Asia/Baghdad",
    "iso:country":"IQ",
    "name:ara_x_preferred":[
        "\u0634\u0645\u064a\u0634\u0631 \u0643\u0648\u0644"
    ],
    "name:und_x_variant":[
        "Shim\u012bsh\u0101r K\u016bl",
        "Shamsh\u0113rk\u00fal",
        "Shimsh\u0101rk\u0101l",
        "Shimshar\u012bk\u0101l",
        "Shimsherkul",
        "Sham\u012bshir K\u016bl"
    ],
    "wof:name":"Shamishir Kul",
    "wof:placetype":"locality"
},
  "geometry": {"coordinates":[45.71386,34.99239],"type":"Point"}
}