{
  "type": "Feature",
  "properties": {
    "gn:admin1_code":"15.0",
    "gn:admin2_code":"98820.0",
    "gn:asciiname":"Afrudalkah",
    "gn:country_code":"IQ",
    "gn:dem":780,
    "gn:feature_class":"P",
    "gn:feature_code":"PPL",
    "gn:name":"Afrudalkah",
    "gn:population":0,
    "gn:timezone":"Asia/Baghdad",
    "iso:country":"IQ",
    "name:ara_x_preferred":[
        "\u0623\u0641\u0631\u062f\u0644\u0643\u0629"
    ],
    "name:kur_x_preferred":[
        "\u00cefrolke"
    ],
    "name:kur_x_variant":[
        "\u0626\u064a\u0641\u0631\u06c6\u0644\u0643\u06d5",
        "Avdelka",
        "\u0626\u0627\u06a4\u062f\u06d5\u0644\u0643\u0627"
    ],
    "name:und_x_variant":[
        "Afrolka",
        "Afrudalkah",
        "Avdalka"
    ],
    "wof:name":"Afrudalkah",
    "wof:placetype":"locality"
},
  "geometry": {"coordinates":[43.89131,36.81011],"type":"Point"}
}