{
  "type": "Feature",
  "properties": {
    "gn:admin1_code":"4.0",
    "gn:admin2_code":"6850588.0",
    "gn:asciiname":"Madlul Matarid",
    "gn:country_code":"IQ",
    "gn:dem":17,
    "gn:feature_class":"P",
    "gn:feature_code":"PPL",
    "gn:name":"Madl\u016bl Ma\u0163\u0101rid",
    "gn:population":0,
    "gn:timezone":"Asia/Baghdad",
    "iso:country":"IQ",
    "name:ara_x_preferred":[
        "\u0645\u062f\u0644\u0648\u0644 \u0645\u0637\u0627\u0631\u062f"
    ],
    "name:und_x_variant":[
        "Madl\u016bl Ma\u0163\u0101rid"
    ],
    "wof:name":"Madlul Matarid",
    "wof:placetype":"locality"
},
  "geometry": {"coordinates":[44.94474,31.69473],"type":"Point"}
}