{
  "type": "Feature",
  "properties": {
    "gn:admin1_code":"5.0",
    "gn:admin2_code":"91176.0",
    "gn:asciiname":"Kanarwe",
    "gn:country_code":"IQ",
    "gn:dem":1345,
    "gn:feature_class":"P",
    "gn:feature_code":"PPL",
    "gn:name":"Kanarwe",
    "gn:population":0,
    "gn:timezone":"Asia/Baghdad",
    "iso:country":"IQ",
    "name:kur_x_preferred":[
        "Kenarw\u00ea"
    ],
    "name:kur_x_variant":[
        "Kenar\u00fb",
        "\u0643\u06d5\u0646\u0627\u0631\u0648\u06ce",
        "\u0643\u06d5\u0646\u0627\u0631\u0648\u0648"
    ],
    "name:und_x_variant":[
        "Kan\u0101r\u016b",
        "Kanarwe"
    ],
    "wof:name":"Kanarwe",
    "wof:placetype":"locality"
},
  "geometry": {"coordinates":[45.57444,35.80361],"type":"Point"}
}