{
  "type": "Feature",
  "properties": {
    "gn:admin1_code":"18.0",
    "gn:admin2_code":"6805736.0",
    "gn:asciiname":"Shadhar",
    "gn:country_code":"IQ",
    "gn:dem":54,
    "gn:feature_class":"P",
    "gn:feature_code":"PPL",
    "gn:name":"Shadhar",
    "gn:population":0,
    "gn:timezone":"Asia/Baghdad",
    "iso:country":"IQ",
    "wof:name":"Shadhar",
    "wof:placetype":"locality"
},
  "geometry": {"coordinates":[44.00861,34.05889000000001],"type":"Point"}
}