{
  "type": "Feature",
  "properties": {
    "gn:admin1_code":"16.0",
    "gn:admin2_code":"98460.0",
    "gn:asciiname":"Bid'at Najris",
    "gn:country_code":"IQ",
    "gn:dem":30,
    "gn:feature_class":"P",
    "gn:feature_code":"PPL",
    "gn:name":"Bid\u2018at Najris",
    "gn:population":0,
    "gn:timezone":"Asia/Baghdad",
    "iso:country":"IQ",
    "name:ara_x_preferred":[
        "\u0628\u062f\u0639\u0629 \u0646\u062c\u0631\u0633"
    ],
    "name:und_x_variant":[
        "Bid\u2018at Najris"
    ],
    "wof:name":"Bid'at Najris",
    "wof:placetype":"locality"
},
  "geometry": {"coordinates":[44.82547,32.9127],"type":"Point"}
}