{
  "type": "Feature",
  "properties": {
    "gn:admin1_code":"10.0",
    "gn:admin2_code":"99063.0",
    "gn:asciiname":"Abu Wajh",
    "gn:country_code":"IQ",
    "gn:dem":49,
    "gn:feature_class":"P",
    "gn:feature_code":"PPL",
    "gn:name":"Ab\u016b Wajh",
    "gn:population":0,
    "gn:timezone":"Asia/Baghdad",
    "iso:country":"IQ",
    "name:ara_x_preferred":[
        "\u0627\u0628\u0648 \u0648\u062c\u0647"
    ],
    "name:und_x_variant":[
        "Ab\u016b Wajh"
    ],
    "wof:name":"Abu Wajh",
    "wof:placetype":"locality"
},
  "geometry": {"coordinates":[44.72922,33.85494],"type":"Point"}
}