{
  "type": "Feature",
  "properties": {
    "gn:admin1_code":"16.0",
    "gn:admin2_code":"99132.0",
    "gn:asciiname":"Bayt Shi'ah",
    "gn:country_code":"IQ",
    "gn:dem":10,
    "gn:feature_class":"P",
    "gn:feature_code":"PPL",
    "gn:name":"Bayt Sh\u012b\u2018ah",
    "gn:population":0,
    "gn:timezone":"Asia/Baghdad",
    "iso:country":"IQ",
    "name:und_x_variant":[
        "Bait Sha\u2018e",
        "Bayt Sha\u2018\u012b",
        "Bayt Sh\u012b\u2018ah"
    ],
    "wof:name":"Bayt Shi'ah",
    "wof:placetype":"locality"
},
  "geometry": {"coordinates":[46.46833,32.52833],"type":"Point"}
}