{
  "type": "Feature",
  "properties": {
    "gn:admin1_code":"11.0",
    "gn:admin2_code":"9166586.0",
    "gn:asciiname":"Basan",
    "gn:country_code":"IQ",
    "gn:dem":1337,
    "gn:feature_class":"P",
    "gn:feature_code":"PPL",
    "gn:name":"Basan",
    "gn:population":0,
    "gn:timezone":"Asia/Baghdad",
    "iso:country":"IQ",
    "name:kur_x_preferred":[
        "Basan"
    ],
    "name:kur_x_variant":[
        "\u0628\u0627\u0633\u0627\u0646"
    ],
    "wof:name":"Basan",
    "wof:placetype":"locality"
},
  "geometry": {"coordinates":[44.93534,36.60191],"type":"Point"}
}