{
  "type": "Feature",
  "properties": {
    "gn:admin1_code":"15.0",
    "gn:admin2_code":"99414.0",
    "gn:asciiname":"Abu Rasin",
    "gn:country_code":"IQ",
    "gn:dem":244,
    "gn:feature_class":"P",
    "gn:feature_code":"PPL",
    "gn:name":"Ab\u016b R\u0101s\u012bn",
    "gn:population":0,
    "gn:timezone":"Asia/Baghdad",
    "iso:country":"IQ",
    "name:ara_x_preferred":[
        "\u0627\u0628\u0648 \u0631\u0627\u0633\u064a\u0646"
    ],
    "name:ara_x_variant":[
        "Ab\u016b R\u0101s\u012bn"
    ],
    "wof:name":"Abu Rasin",
    "wof:placetype":"locality"
},
  "geometry": {"coordinates":[42.16562,35.6957],"type":"Point"}
}