{
  "type": "Feature",
  "properties": {
    "gn:admin1_code":"5.0",
    "gn:admin2_code":"97416.0",
    "gn:asciiname":"Qaytul",
    "gn:country_code":"IQ",
    "gn:dem":582,
    "gn:feature_class":"P",
    "gn:feature_code":"PPL",
    "gn:name":"Qayt\u016bl",
    "gn:population":0,
    "gn:timezone":"Asia/Baghdad",
    "iso:country":"IQ",
    "name:ara_x_preferred":[
        "\u0642\u064a\u062a\u0648\u0644"
    ],
    "name:kur_x_preferred":[
        "Qeyt\u00fbl"
    ],
    "name:kur_x_variant":[
        "Qey Twan\u00ee Gewre",
        "\u0642\u06d5\u064a\u062a\u0648\u0648\u0644",
        "\u0642\u06d5\u0649 \u062a\u0648\u0627\u0646\u0649 \u06af\u06d5\u0648\u0631\u06d5"
    ],
    "name:und_x_variant":[
        "Qayt\u016bl",
        "Qaitool"
    ],
    "wof:name":"Qaytul",
    "wof:placetype":"locality"
},
  "geometry": {"coordinates":[45.02526,35.28985],"type":"Point"}
}