{
  "type": "Feature",
  "properties": {
    "gn:admin1_code":"10.0",
    "gn:admin2_code":"9166680.0",
    "gn:asciiname":"Rashid Sa'id",
    "gn:country_code":"IQ",
    "gn:dem":39,
    "gn:feature_class":"P",
    "gn:feature_code":"PPL",
    "gn:name":"Rash\u012bd Sa\u2018\u012bd",
    "gn:population":0,
    "gn:timezone":"Asia/Baghdad",
    "iso:country":"IQ",
    "name:ara_x_preferred":[
        "\u0631\u0634\u064a\u062f \u0633\u0639\u064a\u062f"
    ],
    "name:und_x_variant":[
        "Rash\u012bd Sa\u2018\u012bd"
    ],
    "wof:name":"Rashid Sa'id",
    "wof:placetype":"locality"
},
  "geometry": {"coordinates":[44.90325,33.58979],"type":"Point"}
}