{
  "type": "Feature",
  "properties": {
    "gn:admin1_code":"11.0",
    "gn:admin2_code":"9166534.0",
    "gn:asciiname":"Hupah",
    "gn:country_code":"IQ",
    "gn:dem":884,
    "gn:feature_class":"P",
    "gn:feature_code":"PPL",
    "gn:name":"H\u016bpah",
    "gn:population":0,
    "gn:timezone":"Asia/Baghdad",
    "iso:country":"IQ",
    "name:ara_x_preferred":[
        "\u0647\u0648\u067e\u0647"
    ],
    "name:kur_x_preferred":[
        "Hobe"
    ],
    "name:kur_x_variant":[
        "\u0647\u06c6\u0628\u06d5",
        "H\u00eap\u00ee",
        "\u06be\u06ce\u067e\u0649"
    ],
    "name:und_x_variant":[
        "Hoba",
        "H\u016bp\u0113",
        "H\u016bpah"
    ],
    "wof:name":"Hupah",
    "wof:placetype":"locality"
},
  "geometry": {"coordinates":[44.19673,37.01937],"type":"Point"}
}