{
  "type": "Feature",
  "properties": {
    "gn:admin1_code":"9.0",
    "gn:admin2_code":"98855.0",
    "gn:asciiname":"Al Kuwam",
    "gn:country_code":"IQ",
    "gn:dem":8,
    "gn:feature_class":"P",
    "gn:feature_code":"PPL",
    "gn:name":"Al Kuw\u0101m",
    "gn:population":0,
    "gn:timezone":"Asia/Baghdad",
    "iso:country":"IQ",
    "name:ara_x_preferred":[
        "\u0627\u0644\u0643\u0648\u0627\u0645"
    ],
    "name:ara_x_variant":[
        "Al Kuw\u0101m"
    ],
    "wof:name":"Al Kuwam",
    "wof:placetype":"locality"
},
  "geometry": {"coordinates":[45.82946,31.15309],"type":"Point"}
}