{
  "type": "Feature",
  "properties": {
    "gn:admin1_code":"18.0",
    "gn:admin2_code":"6872046.0",
    "gn:asciiname":"'Ali an Nayif",
    "gn:country_code":"IQ",
    "gn:dem":151,
    "gn:feature_class":"P",
    "gn:feature_code":"PPL",
    "gn:name":"\u2018Al\u012b an N\u0101yif",
    "gn:population":0,
    "gn:timezone":"Asia/Baghdad",
    "iso:country":"IQ",
    "name:ara_x_preferred":[
        "\u0639\u0644\u064a \u0627\u0644\u0646\u0627\u064a\u0641"
    ],
    "name:und_x_variant":[
        "\u2018Al\u012b an N\u0101yif"
    ],
    "wof:name":"'Ali an Nayif",
    "wof:placetype":"locality"
},
  "geometry": {"coordinates":[43.29613,34.74604],"type":"Point"}
}