{
  "type": "Feature",
  "properties": {
    "gn:admin1_code":"16.0",
    "gn:admin2_code":"99351.0",
    "gn:asciiname":"Abija'",
    "gn:country_code":"IQ",
    "gn:dem":15,
    "gn:feature_class":"P",
    "gn:feature_code":"PPL",
    "gn:name":"Ab\u012bja\u2018",
    "gn:population":0,
    "gn:timezone":"Asia/Baghdad",
    "iso:country":"IQ",
    "name:ara_x_preferred":[
        "\u0627\u0628\u064a\u062c\u0639"
    ],
    "name:und_x_variant":[
        "Makhfar Shur\u0163at al Ubayj\u0131\u2018",
        "Al Ubaij\u0131\u2018i",
        "Al \u2018Ubayja\u2018",
        "Al Ubayj\u0131\u2018",
        "Ab\u012bja\u2018"
    ],
    "wof:name":"Abija'",
    "wof:placetype":"locality"
},
  "geometry": {"coordinates":[45.84425,32.0991],"type":"Point"}
}