{
  "type": "Feature",
  "properties": {
    "gn:admin1_code":"11.0",
    "gn:admin2_code":"9166534.0",
    "gn:asciiname":"Hemdan",
    "gn:country_code":"IQ",
    "gn:dem":497,
    "gn:feature_class":"P",
    "gn:feature_code":"PPL",
    "gn:name":"\u1e26emdan",
    "gn:population":0,
    "gn:timezone":"Asia/Baghdad",
    "iso:country":"IQ",
    "name:ara_x_preferred":[
        "\u0647\u0645\u062f\u0648\u0644\u0629"
    ],
    "name:ara_x_variant":[
        "\u062d\u0645\u062f\u0648\u0644\u0647"
    ],
    "name:kur_x_preferred":[
        "\u1e26emdan"
    ],
    "name:kur_x_variant":[
        "\u062d\u06d5\u0645\u062f\u0627\u0646"
    ],
    "name:und_x_variant":[
        "\u1e28amdullah",
        "\u1e28amad\u0101n",
        "Hamdan",
        "\u1e28amd\u016blah",
        "Hamdla",
        "Hamd\u016blah"
    ],
    "wof:name":"Hemdan",
    "wof:placetype":"locality"
},
  "geometry": {"coordinates":[43.98541,36.94972],"type":"Point"}
}