{
  "type": "Feature",
  "properties": {
    "gn:admin1_code":"2.0",
    "gn:admin2_code":"9166563.0",
    "gn:asciiname":"Qasr Bani Malik",
    "gn:country_code":"IQ",
    "gn:dem":6,
    "gn:feature_class":"P",
    "gn:feature_code":"PPL",
    "gn:name":"Qa\u015fr Ban\u012b M\u0101lik",
    "gn:population":0,
    "gn:timezone":"Asia/Baghdad",
    "iso:country":"IQ",
    "name:ara_x_preferred":[
        "\u0642\u0635\u0631 \u0628\u0646\u064a \u0645\u0627\u0644\u0643"
    ],
    "name:und_x_variant":[
        "Qa\u015fr Ban\u012b M\u0101lik"
    ],
    "wof:name":"Qasr Bani Malik",
    "wof:placetype":"locality"
},
  "geometry": {"coordinates":[47.40279,31.21546],"type":"Point"}
}