{
  "type": "Feature",
  "properties": {
    "gn:admin1_code":"4.0",
    "gn:admin2_code":"6850588.0",
    "gn:asciiname":"Al Khalkhal",
    "gn:country_code":"IQ",
    "gn:dem":22,
    "gn:feature_class":"P",
    "gn:feature_code":"PPL",
    "gn:name":"\u0100l Khalkh\u0101l",
    "gn:population":0,
    "gn:timezone":"Asia/Baghdad",
    "iso:country":"IQ",
    "name:ara_x_preferred":[
        "\u0627\u0644 \u062e\u0644\u062e\u0627\u0644"
    ],
    "name:und_x_variant":[
        "Al Mars\u016bl",
        "\u0627\u0644\u0645\u0631\u0633\u0648\u0644",
        "\u0100l Khalkh\u0101l"
    ],
    "wof:name":"Al Khalkhal",
    "wof:placetype":"locality"
},
  "geometry": {"coordinates":[44.89664000000001,31.81946],"type":"Point"}
}