{
  "type": "Feature",
  "properties": {
    "gn:admin1_code":"13.0",
    "gn:admin2_code":"6770659.0",
    "gn:asciiname":"Salih Shihab",
    "gn:country_code":"IQ",
    "gn:dem":180,
    "gn:feature_class":"P",
    "gn:feature_code":"PPL",
    "gn:name":"\u015e\u0101li\u1e29 Shih\u0101b",
    "gn:population":0,
    "gn:timezone":"Asia/Baghdad",
    "iso:country":"IQ",
    "name:ara_x_preferred":[
        "\u0635\u0627\u0644\u062d \u0634\u0647\u0627\u0628"
    ],
    "name:ara_x_variant":[
        "\u015e\u0101li\u1e29 Shih\u0101b"
    ],
    "wof:name":"Salih Shihab",
    "wof:placetype":"locality"
},
  "geometry": {"coordinates":[43.92677,35.17744],"type":"Point"}
}