{
  "type": "Feature",
  "properties": {
    "gn:admin1_code":"2.0",
    "gn:admin2_code":"99534.0",
    "gn:asciiname":"Qaryat al Hillat",
    "gn:country_code":"IQ",
    "gn:dem":2,
    "gn:feature_class":"P",
    "gn:feature_code":"PPL",
    "gn:name":"Qaryat al \u1e28ill\u0101t",
    "gn:population":0,
    "gn:timezone":"Asia/Baghdad",
    "iso:country":"IQ",
    "name:ara_x_preferred":[
        "\u0642\u0631\u064a\u0629 \u0627\u0644\u062d\u0644\u0627\u062a"
    ],
    "name:und_x_variant":[
        "Qaryat al \u1e28ill\u0101t"
    ],
    "wof:name":"Qaryat al Hillat",
    "wof:placetype":"locality"
},
  "geometry": {"coordinates":[47.68053,30.62863],"type":"Point"}
}