{
  "type": "Feature",
  "properties": {
    "gn:admin1_code":"11.0",
    "gn:admin2_code":"93817.0",
    "gn:asciiname":"`Ali Rashsh",
    "gn:country_code":"IQ",
    "gn:dem":244,
    "gn:feature_class":"P",
    "gn:feature_code":"PPL",
    "gn:name":"\u2018Al\u012b Rashsh",
    "gn:population":0,
    "gn:timezone":"Asia/Baghdad",
    "iso:country":"IQ",
    "name:ara_x_preferred":[
        "\u0639\u0644\u064a \u0631\u0634"
    ],
    "name:kur_x_preferred":[
        "\u2018El\u00ee \u1e5eesh"
    ],
    "name:kur_x_variant":[
        "\u0639\u06d5\u0644\u0649 \u0695\u06d5\u0634",
        "Ali Rash"
    ],
    "name:und_x_variant":[
        "\u2018Al\u012b Rashsh",
        "\u2018Al\u012b Rash"
    ],
    "wof:name":"`Ali Rashsh",
    "wof:placetype":"locality"
},
  "geometry": {"coordinates":[43.69903,35.67261],"type":"Point"}
}