{
  "type": "Feature",
  "properties": {
    "gn:admin1_code":"13.0",
    "gn:admin2_code":"6770659.0",
    "gn:asciiname":"Qaryat ad Daghiyah",
    "gn:country_code":"IQ",
    "gn:dem":192,
    "gn:feature_class":"P",
    "gn:feature_code":"PPL",
    "gn:name":"Qaryat ad D\u0101gh\u012byah",
    "gn:population":0,
    "gn:timezone":"Asia/Baghdad",
    "iso:country":"IQ",
    "name:ara_x_preferred":[
        "\u0642\u0631\u064a\u0629 \u0627\u0644\u062f\u0627\u063a\u064a\u0629"
    ],
    "name:und_x_variant":[
        "Qaryat ad D\u0101gh\u012byah"
    ],
    "wof:name":"Qaryat ad Daghiyah",
    "wof:placetype":"locality"
},
  "geometry": {"coordinates":[43.81296,35.47488],"type":"Point"}
}