{
  "type": "Feature",
  "properties": {
    "gn:admin1_code":"5.0",
    "gn:admin2_code":"9166684.0",
    "gn:asciiname":"Owdalan",
    "gn:country_code":"IQ",
    "gn:dem":1524,
    "gn:feature_class":"P",
    "gn:feature_code":"PPL",
    "gn:name":"Owd\u0101l\u0101n",
    "gn:population":0,
    "gn:timezone":"Asia/Baghdad",
    "iso:country":"IQ",
    "name:fas_x_preferred":[
        "\u0627\u0648\u062f\u0627\u0644\u0627\u0646"
    ],
    "wof:name":"Owdalan",
    "wof:placetype":"locality"
},
  "geometry": {"coordinates":[46.1658,35.7766],"type":"Point"}
}