{
  "type": "Feature",
  "properties": {
    "gn:admin1_code":"1.0",
    "gn:admin2_code":"9166579.0",
    "gn:asciiname":"Kurd Hamad Nayif",
    "gn:country_code":"IQ",
    "gn:dem":58,
    "gn:feature_class":"P",
    "gn:feature_code":"PPL",
    "gn:name":"Kurd \u1e28amad N\u0101yif",
    "gn:population":0,
    "gn:timezone":"Asia/Baghdad",
    "iso:country":"IQ",
    "name:ara_x_preferred":[
        "\u06a9\u0631\u062f \u062d\u0645\u062f \u0646\u0627\u064a\u0641"
    ],
    "name:und_x_variant":[
        "Kurd \u1e28amad N\u0101yif"
    ],
    "wof:name":"Kurd Hamad Nayif",
    "wof:placetype":"locality"
},
  "geometry": {"coordinates":[43.04062,33.52909],"type":"Point"}
}