{
  "type": "Feature",
  "properties": {
    "gn:admin1_code":"5.0",
    "gn:admin2_code":"92743.0",
    "gn:asciiname":"Erke",
    "gn:country_code":"IQ",
    "gn:dem":845,
    "gn:feature_class":"P",
    "gn:feature_code":"PPL",
    "gn:name":"Erke",
    "gn:population":0,
    "gn:timezone":"Asia/Baghdad",
    "iso:country":"IQ",
    "name:cat_x_preferred":[
        "Erke"
    ],
    "name:kur_x_preferred":[
        "Warkele"
    ],
    "name:kur_x_variant":[
        "\u0648\u0627\u0631\u0643\u06d5\u0644\u06d5",
        "Erke",
        "\u0626\u06d5\u0631\u0643\u06d5"
    ],
    "name:mkd_x_preferred":[
        "\u0415\u0440\u043a\u0435"
    ],
    "name:oci_x_preferred":[
        "Erke"
    ],
    "name:spa_x_preferred":[
        "Erke"
    ],
    "name:ukr_x_preferred":[
        "\u0415\u0440\u043a\u0435"
    ],
    "name:und_x_variant":[
        "Warkala",
        "Arka Upper"
    ],
    "wof:name":"Erke",
    "wof:placetype":"locality"
},
  "geometry": {"coordinates":[45.18325,36.3605],"type":"Point"}
}