{
  "type": "Feature",
  "properties": {
    "gn:admin1_code":"13.0",
    "gn:admin2_code":"9166581.0",
    "gn:asciiname":"Shurawah",
    "gn:country_code":"IQ",
    "gn:dem":202,
    "gn:feature_class":"P",
    "gn:feature_code":"PPL",
    "gn:name":"Sh\u016br\u0101wah",
    "gn:population":0,
    "gn:timezone":"Asia/Baghdad",
    "iso:country":"IQ",
    "name:ara_x_preferred":[
        "\u0634\u0648\u0631\u0627\u0648\u0629"
    ],
    "name:und_x_variant":[
        "Shor\u0101wa",
        "Shan\u0101d",
        "Sh\u016br\u0101wah",
        "Shenad"
    ],
    "wof:name":"Shurawah",
    "wof:placetype":"locality"
},
  "geometry": {"coordinates":[44.50236,35.07278],"type":"Point"}
}