{
  "type": "Feature",
  "properties": {
    "gn:admin1_code":"1.0",
    "gn:admin2_code":"9166576.0",
    "gn:asciiname":"Al Qa'im",
    "gn:country_code":"IQ",
    "gn:dem":180,
    "gn:feature_class":"P",
    "gn:feature_code":"PPLA2",
    "gn:name":"Al Q\u0101\u2019im",
    "gn:population":0,
    "gn:timezone":"Asia/Baghdad",
    "iso:country":"IQ",
    "name:ara_x_preferred":[
        "\u062d\u0635\u064a\u0628\u0629"
    ],
    "name:ara_x_variant":[
        "\u0627\u0644\u0642\u0627\u0626\u0645",
        "\u0645\u0631\u0643\u0632 \u0642\u0636\u0627\u0621 \u0627\u0644\u0642\u0627\u0626\u0645"
    ],
    "name:dan_x_preferred":[
        "Husaybah"
    ],
    "name:fas_x_preferred":[
        "\u062d\u0635\u06cc\u0628\u0647"
    ],
    "name:fra_x_preferred":[
        "Husaybah"
    ],
    "name:pol_x_preferred":[
        "Husajba"
    ],
    "name:sco_x_preferred":[
        "Husaybah"
    ],
    "name:und_x_variant":[
        "Ka\u015f\u012bbah",
        "Kseba",
        "Qs\u012bb\u0101",
        "Dulaym al \u1e28usaybah",
        "Qu\u015faybah",
        "Hsaiba",
        "\u1e28u\u015faybah",
        "Al Q\u0101\u2019im",
        "El Qa\u2019im",
        "El Kaim",
        "Al-Qaim",
        "Markaz Qa\u1e11\u0101\u2018 al Q\u0101\u2018im"
    ],
    "wof:name":"Al Qa'im",
    "wof:placetype":"locality"
},
  "geometry": {"coordinates":[40.98945,34.39250999999999],"type":"Point"}
}