{
  "type": "Feature",
  "properties": {
    "gn:admin1_code":"10.0",
    "gn:admin2_code":"99063.0",
    "gn:asciiname":"'Ali Mansur",
    "gn:country_code":"IQ",
    "gn:dem":50,
    "gn:feature_class":"P",
    "gn:feature_code":"PPL",
    "gn:name":"\u2018Al\u012b Man\u015f\u016br",
    "gn:population":0,
    "gn:timezone":"Asia/Baghdad",
    "iso:country":"IQ",
    "name:ara_x_preferred":[
        "\u0639\u0644\u064a \u0645\u0646\u0635\u0648\u0631"
    ],
    "name:und_x_variant":[
        "\u2018Al\u012b Man\u015f\u016br"
    ],
    "wof:name":"'Ali Mansur",
    "wof:placetype":"locality"
},
  "geometry": {"coordinates":[45.07642,33.91220999999999],"type":"Point"}
}