{
  "type": "Feature",
  "properties": {
    "gn:admin1_code":"4.0",
    "gn:admin2_code":"99763.0",
    "gn:asciiname":"Jama'at Farhan Al 'Abd Allah",
    "gn:country_code":"IQ",
    "gn:dem":24,
    "gn:feature_class":"P",
    "gn:feature_code":"PPLL",
    "gn:name":"Jam\u0101\u2018at Far\u1e29\u0101n \u0100l \u2018Abd All\u0101h",
    "gn:population":0,
    "gn:timezone":"Asia/Baghdad",
    "iso:country":"IQ",
    "name:ara_x_preferred":[
        "\u062c\u0645\u0627\u0639\u0629 \u0641\u0631\u062d\u0627\u0646 \u0627\u0644 \u0639\u0628\u062f \u0627\u0644\u0644\u0629"
    ],
    "name:und_x_variant":[
        "Jam\u0101\u2018at Far\u1e29\u0101n \u0100l \u2018Abd All\u0101h"
    ],
    "wof:name":"Jama'at Farhan Al 'Abd Allah",
    "wof:placetype":"locality"
},
  "geometry": {"coordinates":[45.07032,32.10457],"type":"Point"}
}