{
  "type": "Feature",
  "properties": {
    "gn:admin1_code":"6.0",
    "gn:admin2_code":"99358.0",
    "gn:asciiname":"'Ubayd Farhan",
    "gn:country_code":"IQ",
    "gn:dem":28,
    "gn:feature_class":"P",
    "gn:feature_code":"PPL",
    "gn:name":"\u2018Ubayd Far\u1e29\u0101n",
    "gn:population":0,
    "gn:timezone":"Asia/Baghdad",
    "iso:country":"IQ",
    "name:ara_x_preferred":[
        "\u0639\u0628\u064a\u062f \u0641\u0631\u062d\u0627\u0646"
    ],
    "name:und_x_variant":[
        "\u2018Ubayd Far\u1e29\u0101n"
    ],
    "wof:name":"'Ubayd Farhan",
    "wof:placetype":"locality"
},
  "geometry": {"coordinates":[44.70124000000001,32.38186],"type":"Point"}
}