{
  "type": "Feature",
  "properties": {
    "gn:admin1_code":"10.0",
    "gn:admin2_code":"9166680.0",
    "gn:asciiname":"Dal'ah Rashid 'Abbas",
    "gn:country_code":"IQ",
    "gn:dem":98,
    "gn:feature_class":"P",
    "gn:feature_code":"PPL",
    "gn:name":"Dal\u2018ah Rash\u012bd \u2018Abb\u0101s",
    "gn:population":0,
    "gn:timezone":"Asia/Baghdad",
    "iso:country":"IQ",
    "name:und_x_variant":[
        "Dal\u2018ah Rash\u012bd \u2018Abb\u0101s"
    ],
    "wof:name":"Dal'ah Rashid 'Abbas",
    "wof:placetype":"locality"
},
  "geometry": {"coordinates":[45.82639,33.4375],"type":"Point"}
}