{
  "type": "Feature",
  "properties": {
    "gn:admin1_code":"7.0",
    "gn:admin2_code":"99101.0",
    "gn:asciiname":"'Arab Dawud Salim al Musa",
    "gn:country_code":"IQ",
    "gn:dem":36,
    "gn:feature_class":"P",
    "gn:feature_code":"PPL",
    "gn:name":"\u2018Arab D\u0101wud Sal\u012bm al M\u016bs\u00e1",
    "gn:population":0,
    "gn:timezone":"Asia/Baghdad",
    "iso:country":"IQ",
    "name:ara_x_preferred":[
        "\u0639\u0631\u0628 \u062f\u0627\u0648\u062f \u0633\u0644\u064a\u0645 \u0627\u0644\u0645\u0648\u0633\u0649"
    ],
    "name:und_x_variant":[
        "\u2018Arab D\u0101wud Sal\u012bm al M\u016bs\u00e1"
    ],
    "wof:name":"'Arab Dawud Salim al Musa",
    "wof:placetype":"locality"
},
  "geometry": {"coordinates":[44.55269000000001,33.12643],"type":"Point"}
}