{
  "type": "Feature",
  "properties": {
    "gn:admin1_code":"4.0",
    "gn:admin2_code":"6850588.0",
    "gn:asciiname":"Hasan Al Jazzar",
    "gn:country_code":"IQ",
    "gn:dem":21,
    "gn:feature_class":"P",
    "gn:feature_code":"PPL",
    "gn:name":"\u1e28asan \u0100l Jazz\u0101r",
    "gn:population":0,
    "gn:timezone":"Asia/Baghdad",
    "iso:country":"IQ",
    "name:ara_x_preferred":[
        "\u062d\u0633\u0646 \u0627\u0644 \u062c\u0632\u0627\u0631"
    ],
    "name:und_x_variant":[
        "\u1e28asan \u0100l Jazz\u0101r"
    ],
    "wof:name":"Hasan Al Jazzar",
    "wof:placetype":"locality"
},
  "geometry": {"coordinates":[44.9697,31.76386],"type":"Point"}
}