{
  "type": "Feature",
  "properties": {
    "gn:admin1_code":"17.0",
    "gn:admin2_code":"9166629.0",
    "gn:asciiname":"Sayyid Khalil",
    "gn:country_code":"IQ",
    "gn:dem":26,
    "gn:feature_class":"P",
    "gn:feature_code":"PPL",
    "gn:name":"Sayyid Khal\u012bl",
    "gn:population":0,
    "gn:timezone":"Asia/Baghdad",
    "iso:country":"IQ",
    "name:ara_x_preferred":[
        "\u0633\u064a\u062f \u062e\u0644\u064a\u0644"
    ],
    "name:und_x_variant":[
        "Sayyid Khal\u012bl"
    ],
    "wof:name":"Sayyid Khalil",
    "wof:placetype":"locality"
},
  "geometry": {"coordinates":[44.51656,32.05761],"type":"Point"}
}