{
  "type": "Feature",
  "properties": {
    "gn:admin1_code":"5.0",
    "gn:admin2_code":"92051.0",
    "gn:asciiname":"Seydawa",
    "gn:country_code":"IQ",
    "gn:dem":573,
    "gn:feature_class":"P",
    "gn:feature_code":"PPL",
    "gn:name":"Seydawa",
    "gn:population":0,
    "gn:timezone":"Asia/Baghdad",
    "iso:country":"IQ",
    "name:ara_x_preferred":[
        "\u0633\u064a\u062f\u0627\u0648\u0629"
    ],
    "name:kur_x_preferred":[
        "\u0633\u06d5\u064a\u062f\u0627\u0648\u0627"
    ],
    "name:kur_x_variant":[
        "Seydawa"
    ],
    "name:und_x_variant":[
        "Sayd\u0101 Faq\u012brah",
        "Sayd\u0101wah",
        "Saidawa"
    ],
    "wof:name":"Seydawa",
    "wof:placetype":"locality"
},
  "geometry": {"coordinates":[44.9002,36.25716],"type":"Point"}
}