{
  "type": "Feature",
  "properties": {
    "gn:admin1_code":"4.0",
    "gn:admin2_code":"99737.0",
    "gn:asciiname":"Qaryat al Kufyaniyah",
    "gn:country_code":"IQ",
    "gn:dem":20,
    "gn:feature_class":"P",
    "gn:feature_code":"PPL",
    "gn:name":"Qaryat al K\u016bfy\u0101n\u012byah",
    "gn:population":0,
    "gn:timezone":"Asia/Baghdad",
    "iso:country":"IQ",
    "name:ara_x_preferred":[
        "\u0642\u0631\u064a\u0629 \u0627\u0644\u0643\u0648\u0641\u064a\u0627\u0646\u064a\u0629"
    ],
    "name:und_x_variant":[
        "Qaryat al K\u016bfy\u0101n\u012byah"
    ],
    "wof:name":"Qaryat al Kufyaniyah",
    "wof:placetype":"locality"
},
  "geometry": {"coordinates":[45.32839,32.0692],"type":"Point"}
}