{
  "type": "Feature",
  "properties": {
    "gn:admin1_code":"9.0",
    "gn:admin2_code":"98855.0",
    "gn:asciiname":"'Ubayd Shurrush",
    "gn:country_code":"IQ",
    "gn:dem":9,
    "gn:feature_class":"P",
    "gn:feature_code":"PPL",
    "gn:name":"\u2018Ubayd Shurrush",
    "gn:population":0,
    "gn:timezone":"Asia/Baghdad",
    "iso:country":"IQ",
    "name:ara_x_preferred":[
        "\u0639\u0628\u064a\u062f \u0634\u0631\u0634"
    ],
    "name:und_x_variant":[
        "\u2018Ubayd Shurrush"
    ],
    "wof:name":"'Ubayd Shurrush",
    "wof:placetype":"locality"
},
  "geometry": {"coordinates":[45.91283,31.11733],"type":"Point"}
}