{
  "type": "Feature",
  "properties": {
    "gn:admin1_code":"6.0",
    "gn:admin2_code":"99358.0",
    "gn:asciiname":"Khassun al Jali",
    "gn:country_code":"IQ",
    "gn:dem":24,
    "gn:feature_class":"P",
    "gn:feature_code":"PPL",
    "gn:name":"Khass\u016bn al J\u0101l\u012b",
    "gn:population":0,
    "gn:timezone":"Asia/Baghdad",
    "iso:country":"IQ",
    "name:ara_x_preferred":[
        "\u062e\u0633\u0648\u0646 \u0627\u0644\u062c\u0627\u0644\u064a"
    ],
    "name:und_x_variant":[
        "Khass\u016bn al J\u0101l\u012b"
    ],
    "wof:name":"Khassun al Jali",
    "wof:placetype":"locality"
},
  "geometry": {"coordinates":[44.9682,32.39592],"type":"Point"}
}