{
  "type": "Feature",
  "properties": {
    "gn:admin1_code":"14.0",
    "gn:admin2_code":"99097.0",
    "gn:asciiname":"Baydhan",
    "gn:country_code":"IQ",
    "gn:dem":7,
    "gn:feature_class":"P",
    "gn:feature_code":"PPL",
    "gn:name":"Baydhan",
    "gn:population":0,
    "gn:timezone":"Asia/Baghdad",
    "iso:country":"IQ",
    "name:und_x_variant":[
        "Bayd\u0101n",
        "Bay\u1e11\u0101t",
        "Baydhan",
        "Baidhan"
    ],
    "wof:name":"Baydhan",
    "wof:placetype":"locality"
},
  "geometry": {"coordinates":[47.23333,31.53333],"type":"Point"}
}