{
  "type": "Feature",
  "properties": {
    "gn:admin1_code":"4.0",
    "gn:admin2_code":"98634.0",
    "gn:asciiname":"Al 'Ubayd",
    "gn:country_code":"IQ",
    "gn:dem":20,
    "gn:feature_class":"P",
    "gn:feature_code":"PPL",
    "gn:name":"Al \u2018Ubayd",
    "gn:population":0,
    "gn:timezone":"Asia/Baghdad",
    "iso:country":"IQ",
    "name:ara_x_preferred":[
        "\u0627\u0644\u0639\u0628\u064a\u062f"
    ],
    "name:und_x_variant":[
        "Al \u2018Ubayd"
    ],
    "wof:name":"Al 'Ubayd",
    "wof:placetype":"locality"
},
  "geometry": {"coordinates":[44.60937,31.82384],"type":"Point"}
}