{
  "type": "Feature",
  "properties": {
    "gn:admin1_code":"13.0",
    "gn:admin2_code":"6770659.0",
    "gn:asciiname":"Qaryat Shawuk",
    "gn:country_code":"IQ",
    "gn:dem":169,
    "gn:feature_class":"P",
    "gn:feature_code":"PPL",
    "gn:name":"Qaryat Sh\u0101w\u016bk",
    "gn:population":0,
    "gn:timezone":"Asia/Baghdad",
    "iso:country":"IQ",
    "name:ara_x_preferred":[
        "\u0642\u0631\u064a\u0629 \u0634\u0627\u0648\u0648\u0643"
    ],
    "name:und_x_variant":[
        "Qaryat Sh\u0101w\u016bk"
    ],
    "wof:name":"Qaryat Shawuk",
    "wof:placetype":"locality"
},
  "geometry": {"coordinates":[43.63383,35.35375],"type":"Point"}
}