{
  "type": "Feature",
  "properties": {
    "gn:admin1_code":"7.0",
    "gn:admin2_code":"99173.0",
    "gn:asciiname":"Tall al Hamrah",
    "gn:country_code":"IQ",
    "gn:dem":41,
    "gn:feature_class":"P",
    "gn:feature_code":"PPL",
    "gn:name":"Tall al \u1e28amrah",
    "gn:population":0,
    "gn:timezone":"Asia/Baghdad",
    "iso:country":"IQ",
    "name:ara_x_preferred":[
        "\u062a\u0644 \u0627\u0644\u062d\u0645\u0631\u0629"
    ],
    "name:und_x_variant":[
        "Tall al \u1e28amrah"
    ],
    "wof:name":"Tall al Hamrah",
    "wof:placetype":"locality"
},
  "geometry": {"coordinates":[44.2355,33.57277],"type":"Point"}
}