{
  "type": "Feature",
  "properties": {
    "gn:admin1_code":"10.0",
    "gn:admin2_code":"99063.0",
    "gn:asciiname":"Albu Udaysh",
    "gn:country_code":"IQ",
    "gn:dem":43,
    "gn:feature_class":"P",
    "gn:feature_code":"PPLL",
    "gn:name":"\u0100lb\u016b Udaysh",
    "gn:population":0,
    "gn:timezone":"Asia/Baghdad",
    "iso:country":"IQ",
    "name:und_x_variant":[
        "\u0100lb\u016b Udaysh"
    ],
    "wof:name":"Albu Udaysh",
    "wof:placetype":"locality"
},
  "geometry": {"coordinates":[44.69972,33.65139],"type":"Point"}
}