{
  "type": "Feature",
  "properties": {
    "gn:admin1_code":"18.0",
    "gn:admin2_code":"9166616.0",
    "gn:asciiname":"Ma'lat 'Attiyah",
    "gn:country_code":"IQ",
    "gn:dem":38,
    "gn:feature_class":"P",
    "gn:feature_code":"PPL",
    "gn:name":"Ma\u2018lat \u2018A\u0163\u0163\u012byah",
    "gn:population":0,
    "gn:timezone":"Asia/Baghdad",
    "iso:country":"IQ",
    "name:ara_x_preferred":[
        "\u0645\u0639\u0644\u0629 \u0639\u0637\u064a\u0629"
    ],
    "name:und_x_variant":[
        "Ma\u2018lat \u2018A\u0163\u0163\u012byah"
    ],
    "wof:name":"Ma'lat 'Attiyah",
    "wof:placetype":"locality"
},
  "geometry": {"coordinates":[44.01597,33.71612],"type":"Point"}
}