{
  "type": "Feature",
  "properties": {
    "gn:admin1_code":"10.0",
    "gn:admin2_code":"9166680.0",
    "gn:asciiname":"'Aziz al Hasan",
    "gn:country_code":"IQ",
    "gn:dem":44,
    "gn:feature_class":"P",
    "gn:feature_code":"PPL",
    "gn:name":"\u2018Az\u012bz al \u1e28asan",
    "gn:population":0,
    "gn:timezone":"Asia/Baghdad",
    "iso:country":"IQ",
    "name:ara_x_preferred":[
        "\u0639\u0632\u064a\u0632 \u0627\u0644\u062d\u0633\u0646"
    ],
    "name:und_x_variant":[
        "\u2018Az\u012bz al \u1e28asn",
        "\u2018Az\u012bz al \u1e28asan"
    ],
    "wof:name":"'Aziz al Hasan",
    "wof:placetype":"locality"
},
  "geometry": {"coordinates":[44.72682,33.60039],"type":"Point"}
}