{
  "type": "Feature",
  "properties": {
    "gn:admin1_code":"18.0",
    "gn:admin2_code":"9166616.0",
    "gn:asciiname":"'Arab Sakran al 'Ali",
    "gn:country_code":"IQ",
    "gn:dem":42,
    "gn:feature_class":"P",
    "gn:feature_code":"PPL",
    "gn:name":"\u2018Arab Sakr\u0101n al \u2018Al\u012b",
    "gn:population":0,
    "gn:timezone":"Asia/Baghdad",
    "iso:country":"IQ",
    "name:ara_x_preferred":[
        "\u0639\u0631\u0628 \u0633\u0643\u0631\u0627\u0646 \u0627\u0644\u0639\u0644\u064a"
    ],
    "name:und_x_variant":[
        "\u2018Arab Sakr\u0101n al \u2018Al\u012b"
    ],
    "wof:name":"'Arab Sakran al 'Ali",
    "wof:placetype":"locality"
},
  "geometry": {"coordinates":[44.22402,33.79415],"type":"Point"}
}