{
  "type": "Feature",
  "properties": {
    "gn:admin1_code":"7.0",
    "gn:admin2_code":"99173.0",
    "gn:asciiname":"Raml 'Abd Nasir",
    "gn:country_code":"IQ",
    "gn:dem":34,
    "gn:feature_class":"P",
    "gn:feature_code":"PPL",
    "gn:name":"Raml \u2018Abd N\u0101sir",
    "gn:population":0,
    "gn:timezone":"Asia/Baghdad",
    "iso:country":"IQ",
    "name:ara_x_preferred":[
        "\u0631\u0645\u0644 \u0639\u0628\u062f \u0646\u0627\u0635\u0631"
    ],
    "name:und_x_variant":[
        "Raml \u2018Abd N\u0101sir"
    ],
    "wof:name":"Raml 'Abd Nasir",
    "wof:placetype":"locality"
},
  "geometry": {"coordinates":[44.18832,33.50841],"type":"Point"}
}