{
  "type": "Feature",
  "properties": {
    "gn:admin1_code":"11.0",
    "gn:admin2_code":"9166588.0",
    "gn:asciiname":"Siktan",
    "gn:country_code":"IQ",
    "gn:dem":723,
    "gn:feature_class":"P",
    "gn:feature_code":"PPL",
    "gn:name":"Siktan",
    "gn:population":0,
    "gn:timezone":"Asia/Baghdad",
    "iso:country":"IQ",
    "name:ara_x_preferred":[
        "Sekt\u0101n"
    ],
    "name:ara_x_variant":[
        "Sikt\u0101n"
    ],
    "name:kur_x_preferred":[
        "Siktan"
    ],
    "name:kur_x_variant":[
        "\u0633\u0643\u062a\u0627\u0646"
    ],
    "name:und_x_variant":[
        "Sakt\u0101n",
        "Sktan"
    ],
    "wof:name":"Siktan",
    "wof:placetype":"locality"
},
  "geometry": {"coordinates":[44.61625,36.23674000000001],"type":"Point"}
}