{
  "type": "Feature",
  "properties": {
    "gn:admin1_code":"8.0",
    "gn:admin2_code":"99612.0",
    "gn:asciiname":"Qasr-e Yokhanna",
    "gn:country_code":"IQ",
    "gn:dem":1222,
    "gn:feature_class":"P",
    "gn:feature_code":"PPL",
    "gn:name":"Qa\u015fr-e Y\u014dkhanna",
    "gn:population":0,
    "gn:timezone":"Asia/Baghdad",
    "iso:country":"IQ",
    "wof:name":"Qasr-e Yokhanna",
    "wof:placetype":"locality"
},
  "geometry": {"coordinates":[43.44431,37.22107000000001],"type":"Point"}
}