{
  "type": "Feature",
  "properties": {
    "gn:admin1_code":"13.0",
    "gn:admin2_code":"6770659.0",
    "gn:asciiname":"Qaryat Marba'",
    "gn:country_code":"IQ",
    "gn:dem":166,
    "gn:feature_class":"P",
    "gn:feature_code":"PPL",
    "gn:name":"Qaryat Marba\u2018",
    "gn:population":0,
    "gn:timezone":"Asia/Baghdad",
    "iso:country":"IQ",
    "name:ara_x_preferred":[
        "\u0642\u0631\u064a\u0629 \u0645\u0631\u0628\u0639"
    ],
    "name:und_x_variant":[
        "Qaryat Marba\u2018"
    ],
    "wof:name":"Qaryat Marba'",
    "wof:placetype":"locality"
},
  "geometry": {"coordinates":[43.55669,35.12727],"type":"Point"}
}