{
  "type": "Feature",
  "properties": {
    "gn:admin1_code":"5.0",
    "gn:admin2_code":"97416.0",
    "gn:asciiname":"Darawar Khuwaru",
    "gn:country_code":"IQ",
    "gn:dem":765,
    "gn:feature_class":"P",
    "gn:feature_code":"PPL",
    "gn:name":"Daraw\u0101r Khuw\u0101r\u016b",
    "gn:population":0,
    "gn:timezone":"Asia/Baghdad",
    "iso:country":"IQ",
    "name:ara_x_preferred":[
        "\u062f\u0631\u0648\u0627\u0631 \u062e\u0648\u0627\u0631\u0648"
    ],
    "name:kur_x_preferred":[
        "Darawey Xwar\u00fb"
    ],
    "name:kur_x_variant":[
        "Dere War",
        "\u062f\u0627\u0631\u0627\u0648\u06d5\u0649 \u062e\u0648\u0627\u0631\u0648\u0648",
        "\u062f\u06d5 \u0631\u06d5 \u0648\u0627\u0631"
    ],
    "name:und_x_variant":[
        "Daraw\u0101r Khuw\u0101r\u016b",
        "Darawar-i Khw\u0101r\u016b",
        "Daraw\u0101r Khuw\u0101r",
        "Darawar",
        "\u062f\u0631\u0648\u0627\u0631 \u062e\u0648\u0627\u0631"
    ],
    "wof:name":"Darawar Khuwaru",
    "wof:placetype":"locality"
},
  "geometry": {"coordinates":[45.36467,35.1298],"type":"Point"}
}