{
  "type": "Feature",
  "properties": {
    "gn:admin1_code":"11.0",
    "gn:admin2_code":"93817.0",
    "gn:asciiname":"Qaryat Tall ar Rim",
    "gn:country_code":"IQ",
    "gn:dem":210,
    "gn:feature_class":"P",
    "gn:feature_code":"PPL",
    "gn:name":"Qaryat Tall ar R\u012bm",
    "gn:population":0,
    "gn:timezone":"Asia/Baghdad",
    "iso:country":"IQ",
    "name:ara_x_preferred":[
        "\u0642\u0631\u064a\u0629 \u062a\u0644 \u0627\u0644\u0632"
    ],
    "name:kur_x_preferred":[
        "Tel R\u00eem"
    ],
    "name:kur_x_variant":[
        "\u062a\u06d5\u0644 \u0631\u064a\u0645"
    ],
    "name:und_x_variant":[
        "Tel ar Rim",
        "Qaryat Tall ar R\u012bm",
        "Tall ar R\u012bm",
        "\u0642\u0631\u064a\u0629 \u062a\u0644 \u0627\u0644\u0631\u064a\u0645",
        "Tal Reem",
        "Qaryat Tall Alz"
    ],
    "wof:name":"Qaryat Tall ar Rim",
    "wof:placetype":"locality"
},
  "geometry": {"coordinates":[43.42673,35.87052],"type":"Point"}
}