{
  "type": "Feature",
  "properties": {
    "gn:admin1_code":"6.0",
    "gn:admin2_code":"99358.0",
    "gn:asciiname":"Matrud Kazim",
    "gn:country_code":"IQ",
    "gn:dem":24,
    "gn:feature_class":"P",
    "gn:feature_code":"PPL",
    "gn:name":"Ma\u0163r\u016bd K\u0101z\u0327im",
    "gn:population":0,
    "gn:timezone":"Asia/Baghdad",
    "iso:country":"IQ",
    "name:ara_x_preferred":[
        "\u0645\u0637\u0631\u0648\u062f \u0643\u0627\u0638\u0645"
    ],
    "name:und_x_variant":[
        "Ma\u0163r\u016bd K\u0101z\u0327im"
    ],
    "wof:name":"Matrud Kazim",
    "wof:placetype":"locality"
},
  "geometry": {"coordinates":[44.86543,32.36838],"type":"Point"}
}