{
  "type": "Feature",
  "properties": {
    "gn:admin1_code":"9.0",
    "gn:admin2_code":"98700.0",
    "gn:asciiname":"Fachhah",
    "gn:country_code":"IQ",
    "gn:dem":13,
    "gn:feature_class":"P",
    "gn:feature_code":"PPL",
    "gn:name":"Fach\u1e29ah",
    "gn:population":0,
    "gn:timezone":"Asia/Baghdad",
    "iso:country":"IQ",
    "name:ara_x_preferred":[
        "\u0641\u0686\u062d\u0647"
    ],
    "name:und_x_variant":[
        "Fash\u0101kh",
        "Fach\u1e29ah"
    ],
    "wof:name":"Fachhah",
    "wof:placetype":"locality"
},
  "geometry": {"coordinates":[46.08543,31.81486],"type":"Point"}
}