{
  "type": "Feature",
  "properties": {
    "gn:admin1_code":"7.0",
    "gn:admin2_code":"9166569.0",
    "gn:asciiname":"'Abd al Latif al Firas",
    "gn:country_code":"IQ",
    "gn:dem":41,
    "gn:feature_class":"P",
    "gn:feature_code":"PPL",
    "gn:name":"\u2018Abd al La\u0163\u012bf al Fir\u0101s",
    "gn:population":0,
    "gn:timezone":"Asia/Baghdad",
    "iso:country":"IQ",
    "name:ara_x_preferred":[
        "\u0639\u0628\u062f \u0627\u0644\u0644\u0637\u064a\u0641 \u0627\u0644\u0641\u0631\u0627\u0633"
    ],
    "name:und_x_variant":[
        "\u2018Abd al La\u0163\u012bf al Fir\u0101s"
    ],
    "wof:name":"'Abd al Latif al Firas",
    "wof:placetype":"locality"
},
  "geometry": {"coordinates":[44.25725,33.66774],"type":"Point"}
}