{
  "type": "Feature",
  "properties": {
    "gn:admin1_code":"18.0",
    "gn:admin2_code":"6804454.0",
    "gn:asciiname":"Qaryat 'Ayn Hayawi ash Shamaliyah",
    "gn:country_code":"IQ",
    "gn:dem":180,
    "gn:feature_class":"P",
    "gn:feature_code":"PPL",
    "gn:name":"Qaryat \u2018Ayn \u1e28ay\u0101w\u012b ash Sham\u0101l\u012byah",
    "gn:population":0,
    "gn:timezone":"Asia/Baghdad",
    "iso:country":"IQ",
    "name:ara_x_preferred":[
        "\u0642\u0631\u064a\u0629 \u0639\u064a\u0646 \u062d\u064a\u0627\u0648\u064a \u0627\u0644\u0634\u0645\u0627\u0644\u064a\u0629"
    ],
    "name:und_x_variant":[
        "\u2018Ayn \u1e28ay\u0101w\u012b ash Sham\u0101l\u012byah",
        "Qaryat \u2018Ayn \u1e28ay\u0101w\u012b ash Sham\u0101l\u012byah"
    ],
    "wof:name":"Qaryat 'Ayn Hayawi ash Shamaliyah",
    "wof:placetype":"locality"
},
  "geometry": {"coordinates":[43.31321,35.54871],"type":"Point"}
}