{
  "type": "Feature",
  "properties": {
    "gn:admin1_code":"5.0",
    "gn:admin2_code":"9166600.0",
    "gn:asciiname":"Kake Bira",
    "gn:country_code":"IQ",
    "gn:dem":607,
    "gn:feature_class":"P",
    "gn:feature_code":"PPL",
    "gn:name":"Kake Bira",
    "gn:population":0,
    "gn:timezone":"Asia/Baghdad",
    "iso:country":"IQ",
    "name:ara_x_preferred":[
        "\u0643\u0627\u0643\u0629 \u0628\u0631\u0627"
    ],
    "name:ara_x_variant":[
        "\u0643\u0627\u0643\u0629 \u0628\u0631\u0629"
    ],
    "name:kur_x_preferred":[
        "Kake Bira"
    ],
    "name:kur_x_variant":[
        "\u0643\u0627\u0643\u06d5 \u0628\u0631\u0627"
    ],
    "name:und_x_variant":[
        "K\u0101kah P\u012brah",
        "K\u0101kah Bir\u0101",
        "Kaka Bira",
        "K\u0101kah Birah",
        "Kaka Bra"
    ],
    "wof:name":"Kake Bira",
    "wof:placetype":"locality"
},
  "geometry": {"coordinates":[45.15663,34.93768],"type":"Point"}
}