{
  "type": "Feature",
  "properties": {
    "gn:admin1_code":"4.0",
    "gn:admin2_code":"98634.0",
    "gn:asciiname":"Abu 'Ujaylah",
    "gn:country_code":"IQ",
    "gn:dem":17,
    "gn:feature_class":"P",
    "gn:feature_code":"PPL",
    "gn:name":"Ab\u016b \u2018\u016ajaylah",
    "gn:population":0,
    "gn:timezone":"Asia/Baghdad",
    "iso:country":"IQ",
    "name:ara_x_preferred":[
        "\u0627\u0628\u0648 \u0639\u0648\u062c\u064a\u0644\u0629"
    ],
    "name:und_x_variant":[
        "Ab\u016b \u2018\u016ajaylah"
    ],
    "wof:name":"Abu 'Ujaylah",
    "wof:placetype":"locality"
},
  "geometry": {"coordinates":[44.54078,31.70245],"type":"Point"}
}