{
  "type": "Feature",
  "properties": {
    "gn:admin1_code":"1.0",
    "gn:admin2_code":"9166576.0",
    "gn:asciiname":"Ar Rumiyah",
    "gn:country_code":"IQ",
    "gn:dem":160,
    "gn:feature_class":"P",
    "gn:feature_code":"PPL",
    "gn:name":"Ar R\u016bm\u012byah",
    "gn:population":0,
    "gn:timezone":"Asia/Baghdad",
    "iso:country":"IQ",
    "name:ara_x_preferred":[
        "\u0627\u0644\u0631\u0648\u0645\u064a\u0629"
    ],
    "name:und_x_variant":[
        "Ar R\u016bm\u012byah"
    ],
    "wof:name":"Ar Rumiyah",
    "wof:placetype":"locality"
},
  "geometry": {"coordinates":[41.25395,34.43846],"type":"Point"}
}