{
  "type": "Feature",
  "properties": {
    "gn:admin1_code":"7.0",
    "gn:admin2_code":"99101.0",
    "gn:asciiname":"Mahdi Jawad",
    "gn:country_code":"IQ",
    "gn:dem":37,
    "gn:feature_class":"P",
    "gn:feature_code":"PPL",
    "gn:name":"Mahd\u012b Jaw\u0101d",
    "gn:population":0,
    "gn:timezone":"Asia/Baghdad",
    "iso:country":"IQ",
    "name:ara_x_preferred":[
        "\u0645\u0647\u062f\u064a \u062c\u0648\u0627\u062f"
    ],
    "name:und_x_variant":[
        "Mahd\u012b Jaw\u0101d"
    ],
    "wof:name":"Mahdi Jawad",
    "wof:placetype":"locality"
},
  "geometry": {"coordinates":[44.32839,32.96749000000001],"type":"Point"}
}