{
  "type": "Feature",
  "properties": {
    "gn:admin1_code":"11.0",
    "gn:admin2_code":"9166591.0",
    "gn:asciiname":"Kawani",
    "gn:country_code":"IQ",
    "gn:dem":954,
    "gn:feature_class":"P",
    "gn:feature_code":"PPL",
    "gn:name":"Kawani",
    "gn:population":0,
    "gn:timezone":"Asia/Baghdad",
    "iso:country":"IQ",
    "name:ara_x_preferred":[
        "\u0643\u0627\u0648\u0627\u0646\u064a"
    ],
    "name:ara_x_variant":[
        "K\u0101w\u0101n\u012b"
    ],
    "name:kur_x_preferred":[
        "Kawan\u00ee"
    ],
    "name:kur_x_variant":[
        "\u0643\u0627\u0648\u0627\u0646\u0649"
    ],
    "name:und_x_variant":[
        "K\u0101w\u0101niy\u0101n"
    ],
    "wof:name":"Kawani",
    "wof:placetype":"locality"
},
  "geometry": {"coordinates":[44.2953,36.41411],"type":"Point"}
}