{
  "type": "Feature",
  "properties": {
    "gn:admin1_code":"9.0",
    "gn:admin2_code":"98700.0",
    "gn:asciiname":"Thujayl Al Nassar",
    "gn:country_code":"IQ",
    "gn:dem":13,
    "gn:feature_class":"P",
    "gn:feature_code":"PPL",
    "gn:name":"Thujayl \u0100l Na\u015f\u015f\u0101r",
    "gn:population":0,
    "gn:timezone":"Asia/Baghdad",
    "iso:country":"IQ",
    "name:ara_x_preferred":[
        "\u062b\u062c\u064a\u0644 \u0622\u0644 \u0646\u0635\u0627\u0631"
    ],
    "name:und_x_variant":[
        "Thujayl \u0100l Na\u015f\u015f\u0101r"
    ],
    "wof:name":"Thujayl Al Nassar",
    "wof:placetype":"locality"
},
  "geometry": {"coordinates":[46.22338,31.99012],"type":"Point"}
}