{
  "type": "Feature",
  "properties": {
    "gn:admin1_code":"10.0",
    "gn:admin2_code":"9166680.0",
    "gn:asciiname":"Qaryat Bayt Rawdan",
    "gn:country_code":"IQ",
    "gn:dem":77,
    "gn:feature_class":"P",
    "gn:feature_code":"PPL",
    "gn:name":"Qaryat Bayt Raw\u1e11\u0101n",
    "gn:population":0,
    "gn:timezone":"Asia/Baghdad",
    "iso:country":"IQ",
    "name:ara_x_preferred":[
        "\u0642\u0631\u064a\u0629 \u0628\u064a\u062a \u0631\u0648\u0636\u0627\u0646"
    ],
    "name:und_x_variant":[
        "Qaryat Bayt Raw\u1e11\u0101n"
    ],
    "wof:name":"Qaryat Bayt Rawdan",
    "wof:placetype":"locality"
},
  "geometry": {"coordinates":[45.34025,33.83955],"type":"Point"}
}