{
  "type": "Feature",
  "properties": {
    "gn:admin1_code":"5.0",
    "gn:admin2_code":"96204.0",
    "gn:asciiname":"Darah Kawlan",
    "gn:country_code":"IQ",
    "gn:dem":656,
    "gn:feature_class":"P",
    "gn:feature_code":"PPL",
    "gn:name":"Darah Kawl\u0101n",
    "gn:population":0,
    "gn:timezone":"Asia/Baghdad",
    "iso:country":"IQ",
    "name:ara_x_preferred":[
        "\u062f\u0631\u0629 \u0643\u0648\u0644\u0627\u0646"
    ],
    "name:fas_x_preferred":[
        "\u062f\u0631\u0651\u0647 \u06af\u0644\u0627\u0646"
    ],
    "name:fas_x_variant":[
        "Darreh Gel\u0101n"
    ],
    "name:kur_x_preferred":[
        "Dere Go\u0142an"
    ],
    "name:kur_x_variant":[
        "Dere Golan",
        "\u062f\u06d5\u0631\u06d5 \u06af\u06c6\u06b5\u0627\u0646",
        "\u062f\u06d5\u0631\u06d5 \u06af\u06c6\u0644\u0627\u0646"
    ],
    "name:und_x_variant":[
        "Dara Gul\u0101n",
        "Darah Kawl\u0101n",
        "Darah K\u016bl\u0101n",
        "\u062f\u0631\u0647 \u0643\u0648\u0644\u0627\u0646",
        "Dara Goulan"
    ],
    "wof:name":"Darah Kawlan",
    "wof:placetype":"locality"
},
  "geometry": {"coordinates":[45.97706,35.37912],"type":"Point"}
}