{
  "type": "Feature",
  "properties": {
    "gn:admin1_code":"17.0",
    "gn:admin2_code":"9166629.0",
    "gn:asciiname":"Qasr Sawadi",
    "gn:country_code":"IQ",
    "gn:dem":26,
    "gn:feature_class":"P",
    "gn:feature_code":"PPL",
    "gn:name":"Qa\u015fr Saw\u0101d\u012b",
    "gn:population":0,
    "gn:timezone":"Asia/Baghdad",
    "iso:country":"IQ",
    "name:ara_x_preferred":[
        "\u0642\u0635\u0631 \u0633\u0648\u0627\u062f\u064a"
    ],
    "name:und_x_variant":[
        "Qa\u015fr Saw\u0101d\u012b"
    ],
    "wof:name":"Qasr Sawadi",
    "wof:placetype":"locality"
},
  "geometry": {"coordinates":[44.59693,32.07247],"type":"Point"}
}