{
  "type": "Feature",
  "properties": {
    "gn:admin1_code":"10.0",
    "gn:admin2_code":"99063.0",
    "gn:asciiname":"Abu Karmah",
    "gn:country_code":"IQ",
    "gn:dem":54,
    "gn:feature_class":"P",
    "gn:feature_code":"PPL",
    "gn:name":"Ab\u016b Karmah",
    "gn:population":0,
    "gn:timezone":"Asia/Baghdad",
    "iso:country":"IQ",
    "name:ara_x_preferred":[
        "\u0627\u0628\u0648 \u0643\u0631\u0645\u0629"
    ],
    "name:und_x_variant":[
        "Qaryat Ab\u016b Karmah",
        "Abu Karma",
        "Ab\u016b Karmah"
    ],
    "wof:name":"Abu Karmah",
    "wof:placetype":"locality"
},
  "geometry": {"coordinates":[44.72452,33.90691],"type":"Point"}
}