{
  "type": "Feature",
  "properties": {
    "gn:admin1_code":"15.0",
    "gn:admin2_code":"9166608.0",
    "gn:asciiname":"Tall ash Shaykh",
    "gn:country_code":"IQ",
    "gn:dem":292,
    "gn:feature_class":"P",
    "gn:feature_code":"PPL",
    "gn:name":"Tall ash Shaykh",
    "gn:population":0,
    "gn:timezone":"Asia/Baghdad",
    "iso:country":"IQ",
    "name:ara_x_preferred":[
        "\u062a\u0644 \u0627\u0644\u0634\u064a\u062e"
    ],
    "wof:name":"Tall ash Shaykh",
    "wof:placetype":"locality"
},
  "geometry": {"coordinates":[41.55424,35.96024],"type":"Point"}
}