{
  "type": "Feature",
  "properties": {
    "gn:admin1_code":"6.0",
    "gn:admin2_code":"6818313.0",
    "gn:asciiname":"'Arab Hani 'Abud",
    "gn:country_code":"IQ",
    "gn:dem":35,
    "gn:feature_class":"P",
    "gn:feature_code":"PPL",
    "gn:name":"\u2018Arab H\u0101n\u012b \u2018Ab\u016bd",
    "gn:population":0,
    "gn:timezone":"Asia/Baghdad",
    "iso:country":"IQ",
    "name:ara_x_preferred":[
        "\u0639\u0631\u0628 \u0647\u0627\u0646\u064a \u0639\u0628\u0648\u062f"
    ],
    "name:und_x_variant":[
        "\u2018Arab H\u0101n\u012b \u2018Ab\u016bd"
    ],
    "wof:name":"'Arab Hani 'Abud",
    "wof:placetype":"locality"
},
  "geometry": {"coordinates":[44.40465,32.86577],"type":"Point"}
}