{
  "type": "Feature",
  "properties": {
    "gn:admin1_code":"18.0",
    "gn:admin2_code":"9167093.0",
    "gn:asciiname":"'Aftan 'Abd Hamad",
    "gn:country_code":"IQ",
    "gn:dem":64,
    "gn:feature_class":"P",
    "gn:feature_code":"PPL",
    "gn:name":"\u2018Aft\u0101n \u2018Abd \u1e28amad",
    "gn:population":0,
    "gn:timezone":"Asia/Baghdad",
    "iso:country":"IQ",
    "name:ara_x_preferred":[
        "\u0639\u0641\u062a\u0627\u0646 \u0639\u0628\u062f \u062d\u0645\u062f"
    ],
    "name:und_x_variant":[
        "\u2018Aft\u0101n \u2018Abd \u1e28amad"
    ],
    "wof:name":"'Aftan 'Abd Hamad",
    "wof:placetype":"locality"
},
  "geometry": {"coordinates":[43.71213,34.03016],"type":"Point"}
}