{
  "type": "Feature",
  "properties": {
    "gn:admin1_code":"18.0",
    "gn:admin2_code":"6805736.0",
    "gn:asciiname":"Latif al Hajj 'Abd",
    "gn:country_code":"IQ",
    "gn:dem":44,
    "gn:feature_class":"P",
    "gn:feature_code":"PPL",
    "gn:name":"La\u0163\u012bf al \u1e28\u0101jj \u2018Abd",
    "gn:population":0,
    "gn:timezone":"Asia/Baghdad",
    "iso:country":"IQ",
    "name:und_x_variant":[
        "La\u0163\u012bf al \u1e28\u0101jj \u2018Abd"
    ],
    "wof:name":"Latif al Hajj 'Abd",
    "wof:placetype":"locality"
},
  "geometry": {"coordinates":[44.34667,34.005],"type":"Point"}
}