{
  "type": "Feature",
  "properties": {
    "gn:admin1_code":"2.0",
    "gn:admin2_code":"98994.0",
    "gn:asciiname":"Tall al Kuwayfah",
    "gn:country_code":"IQ",
    "gn:dem":3,
    "gn:feature_class":"P",
    "gn:feature_code":"PPL",
    "gn:name":"Tall al Kuwayfah",
    "gn:population":0,
    "gn:timezone":"Asia/Baghdad",
    "iso:country":"IQ",
    "name:ara_x_preferred":[
        "\u062a\u0644 \u0627\u0644\u0643\u0648\u064a\u0641\u0629"
    ],
    "wof:name":"Tall al Kuwayfah",
    "wof:placetype":"locality"
},
  "geometry": {"coordinates":[47.4335,31.18868],"type":"Point"}
}