{
  "type": "Feature",
  "properties": {
    "gn:admin1_code":"1.0",
    "gn:admin2_code":"9166579.0",
    "gn:asciiname":"Katbiyah",
    "gn:country_code":"IQ",
    "gn:dem":76,
    "gn:feature_class":"P",
    "gn:feature_code":"PPL",
    "gn:name":"Ka\u0163b\u012byah",
    "gn:population":0,
    "gn:timezone":"Asia/Baghdad",
    "iso:country":"IQ",
    "name:ara_x_preferred":[
        "\u0643\u0637\u0628\u064a\u0629"
    ],
    "name:und_x_variant":[
        "Qaba\u0163\u012byah",
        "Ka\u0163b\u012byah"
    ],
    "wof:name":"Katbiyah",
    "wof:placetype":"locality"
},
  "geometry": {"coordinates":[42.75737,33.84331],"type":"Point"}
}