{
  "type": "Feature",
  "properties": {
    "gn:admin1_code":"16.0",
    "gn:admin2_code":"9166961.0",
    "gn:asciiname":"Muhammad ash Shadid",
    "gn:country_code":"IQ",
    "gn:dem":24,
    "gn:feature_class":"P",
    "gn:feature_code":"PPL",
    "gn:name":"Mu\u1e29ammad ash Shad\u012bd",
    "gn:population":0,
    "gn:timezone":"Asia/Baghdad",
    "iso:country":"IQ",
    "name:ara_x_preferred":[
        "\u0645\u062d\u0645\u062f \u0627\u0644\u0634\u062f\u064a\u062f"
    ],
    "name:und_x_variant":[
        "Muhammad",
        "Mu\u1e29ammad ash Shad\u012bd"
    ],
    "wof:name":"Muhammad ash Shadid",
    "wof:placetype":"locality"
},
  "geometry": {"coordinates":[45.2097,32.76262],"type":"Point"}
}