{
  "type": "Feature",
  "properties": {
    "gn:admin1_code":"16.0",
    "gn:admin2_code":"98460.0",
    "gn:asciiname":"'Ubayd Jabr",
    "gn:country_code":"IQ",
    "gn:dem":28,
    "gn:feature_class":"P",
    "gn:feature_code":"PPL",
    "gn:name":"\u2018Ubayd Jabr",
    "gn:population":0,
    "gn:timezone":"Asia/Baghdad",
    "iso:country":"IQ",
    "name:ara_x_preferred":[
        "\u0639\u0628\u064a\u062f \u062c\u0628\u0631"
    ],
    "name:und_x_variant":[
        "\u2018Ubayd Jabr"
    ],
    "wof:name":"'Ubayd Jabr",
    "wof:placetype":"locality"
},
  "geometry": {"coordinates":[44.85973,32.83552],"type":"Point"}
}