{
  "type": "Feature",
  "properties": {
    "gn:admin1_code":"18.0",
    "gn:admin2_code":"6783103.0",
    "gn:asciiname":"Al Hajj Husayn Khabur",
    "gn:country_code":"IQ",
    "gn:dem":78,
    "gn:feature_class":"P",
    "gn:feature_code":"PPL",
    "gn:name":"Al \u1e28\u0101jj \u1e28usayn Kh\u0101b\u016br",
    "gn:population":0,
    "gn:timezone":"Asia/Baghdad",
    "iso:country":"IQ",
    "name:ara_x_preferred":[
        "\u0627\u0644\u062d\u0627\u062c \u062d\u0633\u064a\u0646 \u062e\u0627\u0628\u0648\u0631"
    ],
    "name:und_x_variant":[
        "Al \u1e28\u0101jj \u1e28usayn Kh\u0101b\u016br"
    ],
    "wof:name":"Al Hajj Husayn Khabur",
    "wof:placetype":"locality"
},
  "geometry": {"coordinates":[43.85968,34.3168],"type":"Point"}
}