{
  "type": "Feature",
  "properties": {
    "gn:admin1_code":"4.0",
    "gn:admin2_code":"98634.0",
    "gn:asciiname":"Al Saduj",
    "gn:country_code":"IQ",
    "gn:dem":20,
    "gn:feature_class":"P",
    "gn:feature_code":"PPL",
    "gn:name":"\u0100l \u015e\u0101d\u016bj",
    "gn:population":0,
    "gn:timezone":"Asia/Baghdad",
    "iso:country":"IQ",
    "name:ara_x_preferred":[
        "\u0627\u0644 \u0635\u0627\u062f\u0648\u062c"
    ],
    "name:ara_x_variant":[
        "\u0100l \u015e\u0101d\u016bj"
    ],
    "wof:name":"Al Saduj",
    "wof:placetype":"locality"
},
  "geometry": {"coordinates":[44.59807,31.81722],"type":"Point"}
}