{
  "type": "Feature",
  "properties": {
    "gn:admin1_code":"6.0",
    "gn:admin2_code":"99358.0",
    "gn:asciiname":"Nuri Kazim",
    "gn:country_code":"IQ",
    "gn:dem":35,
    "gn:feature_class":"P",
    "gn:feature_code":"PPL",
    "gn:name":"N\u016br\u012b K\u0101z\u0327im",
    "gn:population":0,
    "gn:timezone":"Asia/Baghdad",
    "iso:country":"IQ",
    "name:ara_x_preferred":[
        "\u0646\u0648\u0631\u064a \u0643\u0627\u0638\u0645"
    ],
    "name:ara_x_variant":[
        "N\u016br\u012b K\u0101z\u0327im"
    ],
    "wof:name":"Nuri Kazim",
    "wof:placetype":"locality"
},
  "geometry": {"coordinates":[44.50533,32.39983],"type":"Point"}
}