{
  "type": "Feature",
  "properties": {
    "gn:admin1_code":"15.0",
    "gn:admin2_code":"9166618.0",
    "gn:asciiname":"Khirbat 'Umari",
    "gn:country_code":"IQ",
    "gn:dem":352,
    "gn:feature_class":"P",
    "gn:feature_code":"PPL",
    "gn:name":"Khirbat \u2018Umar\u012b",
    "gn:population":0,
    "gn:timezone":"Asia/Baghdad",
    "iso:country":"IQ",
    "name:ara_x_preferred":[
        "\u062e\u0631\u0628\u0647 \u0639\u0645\u0631\u064a"
    ],
    "name:und_x_variant":[
        "Khirbat \u0100mir\u012b",
        "Khirbat \u2018Umar\u012b"
    ],
    "wof:name":"Khirbat 'Umari",
    "wof:placetype":"locality"
},
  "geometry": {"coordinates":[42.97966,36.69784],"type":"Point"}
}