{
  "type": "Feature",
  "properties": {
    "gn:admin1_code":"14.0",
    "gn:admin2_code":"99097.0",
    "gn:asciiname":"Salaf al Hamiliyah",
    "gn:country_code":"IQ",
    "gn:dem":6,
    "gn:feature_class":"P",
    "gn:feature_code":"PPL",
    "gn:name":"Salaf al Ham\u012bl\u012byah",
    "gn:population":0,
    "gn:timezone":"Asia/Baghdad",
    "iso:country":"IQ",
    "name:ara_x_preferred":[
        "\u0633\u0644\u0641 \u0627\u0644\u0647\u0645\u064a\u0644\u064a\u0629"
    ],
    "name:und_x_variant":[
        "Salaf al Ham\u012bl\u012byah"
    ],
    "wof:name":"Salaf al Hamiliyah",
    "wof:placetype":"locality"
},
  "geometry": {"coordinates":[47.26261,31.55837],"type":"Point"}
}