{
  "type": "Feature",
  "properties": {
    "gn:admin1_code":"11.0",
    "gn:admin2_code":"9166588.0",
    "gn:asciiname":"Kirawz",
    "gn:country_code":"IQ",
    "gn:dem":737,
    "gn:feature_class":"P",
    "gn:feature_code":"PPL",
    "gn:name":"Kirawz",
    "gn:population":0,
    "gn:timezone":"Asia/Baghdad",
    "iso:country":"IQ",
    "name:ara_x_preferred":[
        "\u0643\u0631\u0648\u0632"
    ],
    "name:kur_x_preferred":[
        "Ki\u1e5foj"
    ],
    "name:kur_x_variant":[
        "\u0643\u0695\u06c6\u0698"
    ],
    "name:und_x_variant":[
        "Krozh",
        "K\u014dl\u014dsh"
    ],
    "wof:name":"Kirawz",
    "wof:placetype":"locality"
},
  "geometry": {"coordinates":[44.56272,36.15489],"type":"Point"}
}