{
  "type": "Feature",
  "properties": {
    "gn:admin1_code":"5.0",
    "gn:admin2_code":"96204.0",
    "gn:asciiname":"Kawtah",
    "gn:country_code":"IQ",
    "gn:dem":551,
    "gn:feature_class":"P",
    "gn:feature_code":"PPL",
    "gn:name":"K\u0101wtah",
    "gn:population":0,
    "gn:timezone":"Asia/Baghdad",
    "iso:country":"IQ",
    "name:fas_x_preferred":[
        "\u06a9\u062a\u0647"
    ],
    "name:fas_x_variant":[
        "K\u016bteh"
    ],
    "name:kur_x_preferred":[
        "Kewute"
    ],
    "name:kur_x_variant":[
        "\u0643\u06d5\u0648\u0648\u062a\u06d5"
    ],
    "name:und_x_variant":[
        "Kawta",
        "K\u0101wtah"
    ],
    "wof:name":"Kawtah",
    "wof:placetype":"locality"
},
  "geometry": {"coordinates":[45.9241,35.0993],"type":"Point"}
}