{
  "type": "Feature",
  "properties": {
    "gn:admin1_code":"5.0",
    "gn:admin2_code":"97416.0",
    "gn:asciiname":"Jami Raz",
    "gn:country_code":"IQ",
    "gn:dem":539,
    "gn:feature_class":"P",
    "gn:feature_code":"PPL",
    "gn:name":"Jami Raz",
    "gn:population":0,
    "gn:timezone":"Asia/Baghdad",
    "iso:country":"IQ",
    "wof:name":"Jami Raz",
    "wof:placetype":"locality"
},
  "geometry": {"coordinates":[45.21667,35.11667],"type":"Point"}
}