{
  "type": "Feature",
  "properties": {
    "gn:admin1_code":"2.0",
    "gn:admin2_code":"100049.0",
    "gn:asciiname":"Balad Salamah",
    "gn:country_code":"IQ",
    "gn:dem":2,
    "gn:feature_class":"P",
    "gn:feature_code":"PPL",
    "gn:name":"Balad Sal\u0101mah",
    "gn:population":0,
    "gn:timezone":"Asia/Baghdad",
    "iso:country":"IQ",
    "name:ara_x_preferred":[
        "\u0628\u0644\u062f \u0633\u0644\u0627\u0645\u0629"
    ],
    "name:und_x_variant":[
        "Balad Sal\u0101mah"
    ],
    "wof:name":"Balad Salamah",
    "wof:placetype":"locality"
},
  "geometry": {"coordinates":[47.87497000000001,30.45987],"type":"Point"}
}