{
  "type": "Feature",
  "properties": {
    "gn:admin1_code":"13.0",
    "gn:admin2_code":"9166581.0",
    "gn:asciiname":"Qaryat as Sa'idi",
    "gn:country_code":"IQ",
    "gn:dem":173,
    "gn:feature_class":"P",
    "gn:feature_code":"PPL",
    "gn:name":"Qaryat as Sa\u2018\u012bd\u012b",
    "gn:population":0,
    "gn:timezone":"Asia/Baghdad",
    "iso:country":"IQ",
    "name:ara_x_preferred":[
        "\u0642\u0631\u064a\u0629 \u0627\u0644\u0633\u0639\u064a\u062f\u064a"
    ],
    "name:und_x_variant":[
        "Qaryat as Sa\u2018\u012bd\u012b"
    ],
    "wof:name":"Qaryat as Sa'idi",
    "wof:placetype":"locality"
},
  "geometry": {"coordinates":[44.21585,34.97490999999999],"type":"Point"}
}