{
  "type": "Feature",
  "properties": {
    "gn:admin1_code":"6.0",
    "gn:admin2_code":"99348.0",
    "gn:asciiname":"Shakhat ath Thulth",
    "gn:country_code":"IQ",
    "gn:dem":26,
    "gn:feature_class":"P",
    "gn:feature_code":"PPL",
    "gn:name":"Sh\u0101khat ath Thulth",
    "gn:population":0,
    "gn:timezone":"Asia/Baghdad",
    "iso:country":"IQ",
    "name:ara_x_preferred":[
        "\u0634\u0627\u062e\u0629 \u0627\u0644\u062b\u0644\u062b"
    ],
    "name:und_x_variant":[
        "Al \u1e28ajj\u012byah",
        "\u0627\u0644\u062d\u062c\u064a\u0629",
        "Sh\u0101khat ath Thulth"
    ],
    "wof:name":"Shakhat ath Thulth",
    "wof:placetype":"locality"
},
  "geometry": {"coordinates":[44.36395,32.37454],"type":"Point"}
}