{
  "type": "Feature",
  "properties": {
    "gn:admin1_code":"6.0",
    "gn:admin2_code":"99040.0",
    "gn:asciiname":"Qaryat Huwayfat",
    "gn:country_code":"IQ",
    "gn:dem":36,
    "gn:feature_class":"P",
    "gn:feature_code":"PPL",
    "gn:name":"Qaryat \u1e28uwayf\u0101t",
    "gn:population":0,
    "gn:timezone":"Asia/Baghdad",
    "iso:country":"IQ",
    "name:ara_x_preferred":[
        "\u0642\u0631\u064a\u0629 \u062d\u0648\u064a\u0641\u0627\u062a"
    ],
    "name:und_x_variant":[
        "Qaryat \u1e28uwayf\u0101t"
    ],
    "wof:name":"Qaryat Huwayfat",
    "wof:placetype":"locality"
},
  "geometry": {"coordinates":[44.30641,32.76698],"type":"Point"}
}