{
  "type": "Feature",
  "properties": {
    "iso:country":"IQ",
    "qs:gn_pop":0,
    "qs:name":"T'all Al-Lahm",
    "qs:name_adm0":"Iraq",
    "qs:name_adm1":"Dhi Qar",
    "qs:photos":68,
    "qs:photos_1k":14,
    "qs:photos_9k":1,
    "qs:photos_9r":2,
    "qs:photos_all":68,
    "qs:photos_sr":2,
    "qs:placetype":"Town",
    "qs:pop_sr":"0",
    "qs:woe_adm0":23424855,
    "wof:name":"T'all Al-Lahm",
    "wof:placetype":"locality"
},
  "geometry": {"coordinates":[46.106357,30.9627],"type":"Point"}
}