{
  "type": "Feature",
  "properties": {
    "gn:admin1_code":"15.0",
    "gn:admin2_code":"9166608.0",
    "gn:asciiname":"Umm Hijarah",
    "gn:country_code":"IQ",
    "gn:dem":309,
    "gn:feature_class":"P",
    "gn:feature_code":"PPL",
    "gn:name":"Umm \u1e28ij\u0101rah",
    "gn:population":0,
    "gn:timezone":"Asia/Baghdad",
    "iso:country":"IQ",
    "name:ara_x_preferred":[
        "\u0627\u0645 \u062d\u062c\u0627\u0631\u0647"
    ],
    "name:und_x_variant":[
        "Umm \u1e28ij\u0101rah"
    ],
    "wof:name":"Umm Hijarah",
    "wof:placetype":"locality"
},
  "geometry": {"coordinates":[41.99391,36.04974],"type":"Point"}
}