{
  "type": "Feature",
  "properties": {
    "gn:admin1_code":"4.0",
    "gn:admin2_code":"98634.0",
    "gn:asciiname":"Juwar ar Rughliyah",
    "gn:country_code":"IQ",
    "gn:dem":21,
    "gn:feature_class":"P",
    "gn:feature_code":"PPL",
    "gn:name":"Juw\u0101r ar Rughl\u012byah",
    "gn:population":0,
    "gn:timezone":"Asia/Baghdad",
    "iso:country":"IQ",
    "name:ara_x_preferred":[
        "\u062c\u0648\u0627\u0631 \u0627\u0644\u0631\u063a\u0644\u064a\u0629"
    ],
    "name:und_x_variant":[
        "Juw\u0101r ar Rughl\u012byah"
    ],
    "wof:name":"Juwar ar Rughliyah",
    "wof:placetype":"locality"
},
  "geometry": {"coordinates":[44.54621,31.92375],"type":"Point"}
}