{
  "type": "Feature",
  "properties": {
    "gn:admin1_code":"10.0",
    "gn:admin2_code":"9166680.0",
    "gn:asciiname":"Katir as Salman",
    "gn:country_code":"IQ",
    "gn:dem":31,
    "gn:feature_class":"P",
    "gn:feature_code":"PPL",
    "gn:name":"Kat\u012br as Salm\u0101n",
    "gn:population":0,
    "gn:timezone":"Asia/Baghdad",
    "iso:country":"IQ",
    "name:ara_x_preferred":[
        "\u0643\u062a\u064a\u0631 \u0627\u0644\u0633\u0644\u0645\u0627\u0646"
    ],
    "name:und_x_variant":[
        "Kat\u012br as Salm\u0101n"
    ],
    "wof:name":"Katir as Salman",
    "wof:placetype":"locality"
},
  "geometry": {"coordinates":[45.37703,33.34114],"type":"Point"}
}