{
  "type": "Feature",
  "properties": {
    "gn:admin1_code":"13.0",
    "gn:admin2_code":"6770659.0",
    "gn:asciiname":"Qaryat Dukan",
    "gn:country_code":"IQ",
    "gn:dem":183,
    "gn:feature_class":"P",
    "gn:feature_code":"PPL",
    "gn:name":"Qaryat D\u016bk\u0101n",
    "gn:population":0,
    "gn:timezone":"Asia/Baghdad",
    "iso:country":"IQ",
    "name:ara_x_preferred":[
        "\u0642\u0631\u064a\u0629 \u062f\u0648\u0643\u0627\u0646"
    ],
    "name:und_x_variant":[
        "Qaryat D\u016bk\u0101n"
    ],
    "wof:name":"Qaryat Dukan",
    "wof:placetype":"locality"
},
  "geometry": {"coordinates":[43.70081,35.30305],"type":"Point"}
}