{
  "type": "Feature",
  "properties": {
    "gn:admin1_code":"15.0",
    "gn:admin2_code":"98612.0",
    "gn:asciiname":"Shifshirin",
    "gn:country_code":"IQ",
    "gn:dem":402,
    "gn:feature_class":"P",
    "gn:feature_code":"PPL",
    "gn:name":"Shifsh\u012brin",
    "gn:population":0,
    "gn:timezone":"Asia/Baghdad",
    "iso:country":"IQ",
    "name:ara_x_preferred":[
        "\u0634\u0641\u0634\u064a\u0631\u0646"
    ],
    "name:kur_x_preferred":[
        "Sh\u00eev Sh\u00eer\u00een"
    ],
    "name:kur_x_variant":[
        "\u0634\u064a\u06a4 \u0634\u064a\u0631\u064a\u0646"
    ],
    "name:und_x_variant":[
        "Shiv Shirin",
        "Shifsh\u012br\u012bn",
        "Shifsh\u012brin"
    ],
    "wof:name":"Shifshirin",
    "wof:placetype":"locality"
},
  "geometry": {"coordinates":[43.32323,36.65659],"type":"Point"}
}