{
  "type": "Feature",
  "properties": {
    "gn:admin1_code":"16.0",
    "gn:admin2_code":"99132.0",
    "gn:asciiname":"Ibn Ati",
    "gn:cc2":"IQ",
    "gn:country_code":"IQ",
    "gn:dem":17,
    "gn:feature_class":"P",
    "gn:feature_code":"PPL",
    "gn:name":"Ibn \u0100t\u012b",
    "gn:population":0,
    "gn:timezone":"Asia/Baghdad",
    "iso:country":"IQ",
    "name:ara_x_preferred":[
        "Ibn \u0100t\u012b"
    ],
    "name:und_x_variant":[
        "Ibn \u2018\u0100n\u012b"
    ],
    "wof:name":"Ibn Ati",
    "wof:placetype":"locality"
},
  "geometry": {"coordinates":[45.92778,32.38306],"type":"Point"}
}