{
  "type": "Feature",
  "properties": {
    "gn:admin1_code":"5.0",
    "gn:admin2_code":"91176.0",
    "gn:asciiname":"Barda Zard",
    "gn:country_code":"IQ",
    "gn:dem":1068,
    "gn:feature_class":"P",
    "gn:feature_code":"PPL",
    "gn:name":"Barda Zard",
    "gn:population":0,
    "gn:timezone":"Asia/Baghdad",
    "iso:country":"IQ",
    "name:kur_x_preferred":[
        "Berde Zerd"
    ],
    "name:kur_x_variant":[
        "\u0628\u06d5\u0631\u062f\u06d5 \u0632\u06d5\u0631\u062f"
    ],
    "wof:name":"Barda Zard",
    "wof:placetype":"locality"
},
  "geometry": {"coordinates":[45.53111,35.75],"type":"Point"}
}