{
  "type": "Feature",
  "properties": {
    "gn:admin1_code":"6.0",
    "gn:admin2_code":"99358.0",
    "gn:asciiname":"Bayt Hajj 'Isa",
    "gn:country_code":"IQ",
    "gn:dem":29,
    "gn:feature_class":"P",
    "gn:feature_code":"PPL",
    "gn:name":"Bayt \u1e28\u0101jj \u2018\u012as\u00e1",
    "gn:population":0,
    "gn:timezone":"Asia/Baghdad",
    "iso:country":"IQ",
    "name:ara_x_preferred":[
        "\u0628\u064a\u062a \u062d\u0627\u062c \u0639\u064a\u0633\u0649"
    ],
    "name:und_x_variant":[
        "Bayt \u1e28\u0101jj \u2018\u012as\u00e1"
    ],
    "wof:name":"Bayt Hajj 'Isa",
    "wof:placetype":"locality"
},
  "geometry": {"coordinates":[44.70237,32.34471],"type":"Point"}
}