{
  "type": "Feature",
  "properties": {
    "gn:admin1_code":"18.0",
    "gn:admin2_code":"90148.0",
    "gn:asciiname":"Qaryat Ta'an",
    "gn:country_code":"IQ",
    "gn:dem":142,
    "gn:feature_class":"P",
    "gn:feature_code":"PPL",
    "gn:name":"Qaryat \u0162a\u2018\u0101n",
    "gn:population":0,
    "gn:timezone":"Asia/Baghdad",
    "iso:country":"IQ",
    "name:ara_x_preferred":[
        "\u0642\u0631\u064a\u0629 \u0637\u0639\u0627\u0646"
    ],
    "name:und_x_variant":[
        "Qaryat \u0162a\u2018\u0101n"
    ],
    "wof:name":"Qaryat Ta'an",
    "wof:placetype":"locality"
},
  "geometry": {"coordinates":[43.82164,34.84155],"type":"Point"}
}