{
  "type": "Feature",
  "properties": {
    "gn:admin1_code":"5.0",
    "gn:admin2_code":"91176.0",
    "gn:asciiname":"Jamak",
    "gn:country_code":"IQ",
    "gn:dem":1289,
    "gn:feature_class":"P",
    "gn:feature_code":"PPL",
    "gn:name":"Jamak",
    "gn:population":0,
    "gn:timezone":"Asia/Baghdad",
    "iso:country":"IQ",
    "name:ara_x_preferred":[
        "\u062c\u0645\u0643"
    ],
    "name:fas_x_preferred":[
        "\u0686\u0645\u06a9"
    ],
    "name:kur_x_preferred":[
        "Chemik"
    ],
    "name:kur_x_variant":[
        "\u0686\u06d5\u0645\u0643"
    ],
    "name:und_x_variant":[
        "Chamak",
        "\u0686\u0645\u06a9"
    ],
    "wof:name":"Jamak",
    "wof:placetype":"locality"
},
  "geometry": {"coordinates":[45.79237,35.73291],"type":"Point"}
}