{
  "type": "Feature",
  "properties": {
    "gn:admin1_code":"18.0",
    "gn:admin2_code":"6805736.0",
    "gn:asciiname":"Mush'al al Amkhakh",
    "gn:country_code":"IQ",
    "gn:dem":51,
    "gn:feature_class":"P",
    "gn:feature_code":"PPL",
    "gn:name":"Mush\u2018al al Amkh\u0101kh",
    "gn:population":0,
    "gn:timezone":"Asia/Baghdad",
    "iso:country":"IQ",
    "name:ara_x_preferred":[
        "\u0645\u0634\u0639\u0644 \u0627\u0644\u0627\u0645\u062e\u0627\u062e"
    ],
    "name:und_x_variant":[
        "Mush\u2018al al Amkh\u0101kh"
    ],
    "wof:name":"Mush'al al Amkhakh",
    "wof:placetype":"locality"
},
  "geometry": {"coordinates":[43.91487,33.90937],"type":"Point"}
}