{
  "type": "Feature",
  "properties": {
    "gn:admin1_code":"2.0",
    "gn:admin2_code":"98994.0",
    "gn:asciiname":"Qaryat Abu Wawi",
    "gn:country_code":"IQ",
    "gn:dem":3,
    "gn:feature_class":"P",
    "gn:feature_code":"PPL",
    "gn:name":"Qaryat Ab\u016b W\u0101w\u012b",
    "gn:population":0,
    "gn:timezone":"Asia/Baghdad",
    "iso:country":"IQ",
    "name:ara_x_preferred":[
        "\u0642\u0631\u064a\u0629 \u0627\u0628\u0648 \u0648\u0627\u0648\u064a"
    ],
    "name:und_x_variant":[
        "Al Ma\u2018d\u0101n",
        "\u0627\u0644\u0645\u0639\u062f\u0627\u0646",
        "Qaryat Ab\u016b W\u0101w\u012b"
    ],
    "wof:name":"Qaryat Abu Wawi",
    "wof:placetype":"locality"
},
  "geometry": {"coordinates":[47.5281,30.83952],"type":"Point"}
}