{
  "type": "Feature",
  "properties": {
    "gn:admin1_code":"5.0",
    "gn:admin2_code":"96204.0",
    "gn:asciiname":"Hani Danik",
    "gn:country_code":"IQ",
    "gn:dem":1148,
    "gn:feature_class":"P",
    "gn:feature_code":"PPL",
    "gn:name":"H\u0101n\u012b D\u0101nik",
    "gn:population":0,
    "gn:timezone":"Asia/Baghdad",
    "iso:country":"IQ",
    "name:ara_x_preferred":[
        "H\u0101n\u012b D\u0101nik"
    ],
    "name:ara_x_variant":[
        "\u0647\u0627\u0646\u064a \u062f\u0627\u0646\u0643"
    ],
    "name:fas_x_preferred":[
        "\u0647\u0646\u06cc\u062f\u0646\u06cc\u062f"
    ],
    "name:fas_x_variant":[
        "Han\u012bdn\u012bd"
    ],
    "name:kur_x_preferred":[
        "Haney Dn"
    ],
    "name:kur_x_variant":[
        "Haney Deng",
        "\u06be\u0627\u0646\u06d5\u0649 \u062f\u0646",
        "\u06be\u0627\u0646\u06d5\u0649 \u062f\u06d5\u0646\u06af"
    ],
    "name:und_x_variant":[
        "Hanidind",
        "Hanay Dang"
    ],
    "wof:name":"Hani Danik",
    "wof:placetype":"locality"
},
  "geometry": {"coordinates":[46.11145,35.29049000000001],"type":"Point"}
}