{
  "type": "Feature",
  "properties": {
    "gn:admin1_code":"6.0",
    "gn:admin2_code":"6818313.0",
    "gn:asciiname":"Al Qaryah al 'Asriyah",
    "gn:country_code":"IQ",
    "gn:dem":34,
    "gn:feature_class":"P",
    "gn:feature_code":"PPL",
    "gn:name":"Al Qaryah al \u2018A\u015fr\u012byah",
    "gn:population":0,
    "gn:timezone":"Asia/Baghdad",
    "iso:country":"IQ",
    "name:ara_x_preferred":[
        "\u0627\u0644\u0642\u0631\u064a\u0647 \u0627\u0644\u0639\u0635\u0631\u064a\u0629"
    ],
    "name:und_x_variant":[
        "\u2018A\u015fr\u012byah",
        "Asr\u012bya",
        "Al \u2018A\u015fr\u012byah",
        "Al Qaryah al \u2018A\u015fr\u012byah"
    ],
    "wof:name":"Al Qaryah al 'Asriyah",
    "wof:placetype":"locality"
},
  "geometry": {"coordinates":[44.38943,32.88505],"type":"Point"}
}