{
  "type": "Feature",
  "properties": {
    "gn:admin1_code":"10.0",
    "gn:admin2_code":"9166680.0",
    "gn:asciiname":"Kazim 'Ali",
    "gn:country_code":"IQ",
    "gn:dem":47,
    "gn:feature_class":"P",
    "gn:feature_code":"PPL",
    "gn:name":"K\u0101z\u0327im \u2018Al\u012b",
    "gn:population":0,
    "gn:timezone":"Asia/Baghdad",
    "iso:country":"IQ",
    "name:ara_x_preferred":[
        "\u0643\u0627\u0638\u0645 \u0639\u0644\u064a"
    ],
    "name:ara_x_variant":[
        "K\u0101z\u0327im \u2018Al\u012b"
    ],
    "wof:name":"Kazim 'Ali",
    "wof:placetype":"locality"
},
  "geometry": {"coordinates":[44.85125,33.76777],"type":"Point"}
}