{
  "type": "Feature",
  "properties": {
    "gn:admin1_code":"9.0",
    "gn:admin2_code":"98700.0",
    "gn:asciiname":"Al Hadahidah",
    "gn:country_code":"IQ",
    "gn:dem":7,
    "gn:feature_class":"P",
    "gn:feature_code":"PPL",
    "gn:name":"Al \u1e28ad\u0101\u1e29idah",
    "gn:population":0,
    "gn:timezone":"Asia/Baghdad",
    "iso:country":"IQ",
    "name:ara_x_preferred":[
        "\u0627\u0644\u062d\u062f\u0627\u062d\u062f\u0629"
    ],
    "name:und_x_variant":[
        "Al \u1e28ad\u0101\u1e29idah"
    ],
    "wof:name":"Al Hadahidah",
    "wof:placetype":"locality"
},
  "geometry": {"coordinates":[46.0429,31.59398],"type":"Point"}
}