{
  "type": "Feature",
  "properties": {
    "gn:admin1_code":"5.0",
    "gn:admin2_code":"92743.0",
    "gn:asciiname":"Gorran",
    "gn:country_code":"IQ",
    "gn:dem":1108,
    "gn:feature_class":"P",
    "gn:feature_code":"PPL",
    "gn:name":"Gorran",
    "gn:population":0,
    "gn:timezone":"Asia/Baghdad",
    "iso:country":"IQ",
    "wof:name":"Gorran",
    "wof:placetype":"locality"
},
  "geometry": {"coordinates":[45.2529,36.20849000000001],"type":"Point"}
}