{
  "type": "Feature",
  "properties": {
    "gn:admin1_code":"7.0",
    "gn:admin2_code":"99101.0",
    "gn:asciiname":"'Arab 'Isa Jabr",
    "gn:country_code":"IQ",
    "gn:dem":32,
    "gn:feature_class":"P",
    "gn:feature_code":"PPL",
    "gn:name":"\u2018Arab \u2018\u012as\u00e1 Jabr",
    "gn:population":0,
    "gn:timezone":"Asia/Baghdad",
    "iso:country":"IQ",
    "name:ara_x_preferred":[
        "\u0639\u0631\u0628 \u0639\u064a\u0633\u0649 \u062c\u0628\u0631"
    ],
    "name:und_x_variant":[
        "\u2018Arab \u2018\u012as\u00e1 Jabr"
    ],
    "wof:name":"'Arab 'Isa Jabr",
    "wof:placetype":"locality"
},
  "geometry": {"coordinates":[44.41475,32.93941],"type":"Point"}
}