{
  "type": "Feature",
  "properties": {
    "gn:admin1_code":"10.0",
    "gn:admin2_code":"9166680.0",
    "gn:asciiname":"Sa'd al Hasan",
    "gn:country_code":"IQ",
    "gn:dem":42,
    "gn:feature_class":"P",
    "gn:feature_code":"PPL",
    "gn:name":"Sa\u2018d al \u1e28asan",
    "gn:population":0,
    "gn:timezone":"Asia/Baghdad",
    "iso:country":"IQ",
    "name:und_x_variant":[
        "Sa\u2018d al \u1e28asan"
    ],
    "wof:name":"Sa'd al Hasan",
    "wof:placetype":"locality"
},
  "geometry": {"coordinates":[45.08333,33.75],"type":"Point"}
}