{
  "type": "Feature",
  "properties": {
    "gn:admin1_code":"15.0",
    "gn:admin2_code":"9166541.0",
    "gn:asciiname":"Qaryat Kanunah",
    "gn:country_code":"IQ",
    "gn:dem":370,
    "gn:feature_class":"P",
    "gn:feature_code":"PPL",
    "gn:name":"Qaryat K\u0101n\u016bnah",
    "gn:population":0,
    "gn:timezone":"Asia/Baghdad",
    "iso:country":"IQ",
    "name:ara_x_preferred":[
        "\u0642\u0631\u064a\u0629 \u0643\u0627\u0646\u0648\u0646\u0629"
    ],
    "name:und_x_variant":[
        "Qaryat K\u0101n\u016bnah"
    ],
    "wof:name":"Qaryat Kanunah",
    "wof:placetype":"locality"
},
  "geometry": {"coordinates":[43.30743,36.49084000000001],"type":"Point"}
}