{
  "type": "Feature",
  "properties": {
    "gn:admin1_code":"6.0",
    "gn:admin2_code":"99358.0",
    "gn:asciiname":"Turki Mukhif 'Abd",
    "gn:country_code":"IQ",
    "gn:dem":30,
    "gn:feature_class":"P",
    "gn:feature_code":"PPL",
    "gn:name":"Turk\u012b Mukh\u012bf \u2018Abd",
    "gn:population":0,
    "gn:timezone":"Asia/Baghdad",
    "iso:country":"IQ",
    "name:ara_x_preferred":[
        "\u062a\u0631\u0643\u064a \u0645\u062e\u064a\u0641 \u0639\u0628\u062f"
    ],
    "name:ara_x_variant":[
        "Turk\u012b Mukh\u012bf \u2018Abd"
    ],
    "wof:name":"Turki Mukhif 'Abd",
    "wof:placetype":"locality"
},
  "geometry": {"coordinates":[44.52801,32.4288],"type":"Point"}
}