{
  "type": "Feature",
  "properties": {
    "gn:admin1_code":"13.0",
    "gn:admin2_code":"6770659.0",
    "gn:asciiname":"Qaryat as Safrah",
    "gn:country_code":"IQ",
    "gn:dem":187,
    "gn:feature_class":"P",
    "gn:feature_code":"PPL",
    "gn:name":"Qaryat a\u015f \u015eafrah",
    "gn:population":0,
    "gn:timezone":"Asia/Baghdad",
    "iso:country":"IQ",
    "name:ara_x_preferred":[
        "\u0642\u0631\u064a\u0629 \u0627\u0644\u0635\u0641\u0631\u0629"
    ],
    "name:und_x_variant":[
        "Qaryat a\u015f \u015eafrah"
    ],
    "wof:name":"Qaryat as Safrah",
    "wof:placetype":"locality"
},
  "geometry": {"coordinates":[43.79351,35.19899],"type":"Point"}
}