{
  "type": "Feature",
  "properties": {
    "gn:admin1_code":"10.0",
    "gn:admin2_code":"9166680.0",
    "gn:asciiname":"'Abd al Karim",
    "gn:country_code":"IQ",
    "gn:dem":41,
    "gn:feature_class":"P",
    "gn:feature_code":"PPL",
    "gn:name":"\u2018Abd al Kar\u012bm",
    "gn:population":0,
    "gn:timezone":"Asia/Baghdad",
    "iso:country":"IQ",
    "name:und_x_variant":[
        "\u2018Abd al Kar\u012bm"
    ],
    "wof:name":"'Abd al Karim",
    "wof:placetype":"locality"
},
  "geometry": {"coordinates":[45.02942,33.68016],"type":"Point"}
}