{
  "type": "Feature",
  "properties": {
    "gn:admin1_code":"15.0",
    "gn:admin2_code":"9166620.0",
    "gn:asciiname":"Kunruqi",
    "gn:country_code":"IQ",
    "gn:dem":396,
    "gn:feature_class":"P",
    "gn:feature_code":"PPL",
    "gn:name":"Kunr\u016bq\u012b",
    "gn:population":0,
    "gn:timezone":"Asia/Baghdad",
    "iso:country":"IQ",
    "name:ara_x_preferred":[
        "\u0643\u0646\u0631\u0648\u0642\u064a"
    ],
    "name:ara_x_variant":[
        "Kunr\u016bq\u012b"
    ],
    "name:und_x_variant":[
        "Kun Ruv\u012b"
    ],
    "wof:name":"Kunruqi",
    "wof:placetype":"locality"
},
  "geometry": {"coordinates":[41.83207,36.23496],"type":"Point"}
}