{
  "type": "Feature",
  "properties": {
    "gn:admin1_code":"13.0",
    "gn:admin2_code":"94786.0",
    "gn:asciiname":"Juwah Juwah",
    "gn:country_code":"IQ",
    "gn:dem":683,
    "gn:feature_class":"P",
    "gn:feature_code":"PPL",
    "gn:name":"Juwah Juwah",
    "gn:population":0,
    "gn:timezone":"Asia/Baghdad",
    "iso:country":"IQ",
    "name:ara_x_preferred":[
        "\u062c\u0648\u0647 \u062c\u0648\u0647"
    ],
    "name:kur_x_preferred":[
        "Ciwe Ciwe"
    ],
    "name:kur_x_variant":[
        "\u062c\u0648\u06d5 \u062c\u0648\u06d5"
    ],
    "name:und_x_variant":[
        "Juw\u0101jwah",
        "J\u0113waj\u0113wa",
        "Jua Jua",
        "Juwah Juwah"
    ],
    "wof:name":"Juwah Juwah",
    "wof:placetype":"locality"
},
  "geometry": {"coordinates":[44.46759,35.75721],"type":"Point"}
}