{
  "type": "Feature",
  "properties": {
    "gn:admin1_code":"5.0",
    "gn:admin2_code":"97416.0",
    "gn:asciiname":"Kani Mistafa",
    "gn:country_code":"IQ",
    "gn:dem":820,
    "gn:feature_class":"P",
    "gn:feature_code":"PPL",
    "gn:name":"Kani Mistafa",
    "gn:population":0,
    "gn:timezone":"Asia/Baghdad",
    "iso:country":"IQ",
    "name:kur_x_preferred":[
        "Kan\u00ee Mistefa"
    ],
    "name:kur_x_variant":[
        "\u0643\u0627\u0646\u0649 \u0645\u0633\u062a\u06d5\u0641\u0627"
    ],
    "name:und_x_variant":[
        "K\u0101n\u012b Mu\u015f\u0163af\u00e1",
        "Kani Mistafa"
    ],
    "wof:name":"Kani Mistafa",
    "wof:placetype":"locality"
},
  "geometry": {"coordinates":[45.09667,35.49556],"type":"Point"}
}