{
  "type": "Feature",
  "properties": {
    "gn:admin1_code":"12.0",
    "gn:admin2_code":"99345.0",
    "gn:asciiname":"Husayn 'Ali",
    "gn:country_code":"IQ",
    "gn:dem":30,
    "gn:feature_class":"P",
    "gn:feature_code":"PPL",
    "gn:name":"\u1e28usayn \u2018Al\u012b",
    "gn:population":0,
    "gn:timezone":"Asia/Baghdad",
    "iso:country":"IQ",
    "name:ara_x_preferred":[
        "\u062d\u0633\u064a\u0646 \u0639\u0644\u064a"
    ],
    "name:und_x_variant":[
        "\u1e28usayn \u2018Al\u012b"
    ],
    "wof:name":"Husayn 'Ali",
    "wof:placetype":"locality"
},
  "geometry": {"coordinates":[44.173,32.62539],"type":"Point"}
}