{
  "type": "Feature",
  "properties": {
    "gn:admin1_code":"11.0",
    "gn:admin2_code":"9166534.0",
    "gn:asciiname":"Kaniye Linc",
    "gn:country_code":"IQ",
    "gn:dem":887,
    "gn:feature_class":"P",
    "gn:feature_code":"PPL",
    "gn:name":"Kaniye L\u00eenc",
    "gn:population":0,
    "gn:timezone":"Asia/Baghdad",
    "iso:country":"IQ",
    "name:ara_x_preferred":[
        "\u0643\u0627\u0646\u064a \u0644\u0646\u062c\u0647"
    ],
    "name:kur_x_preferred":[
        "Kaniye L\u00eenc"
    ],
    "name:kur_x_variant":[
        "\u0643\u0627\u0646\u064a\u06d5 \u0644\u064a\u0646\u062c",
        "Kan\u00ee Lence",
        "\u0643\u0627\u0646\u0649 \u0644\u06d5\u0646\u062c\u06d5"
    ],
    "name:und_x_variant":[
        "K\u0101ni Linja",
        "K\u0101n\u012b Linj",
        "K\u0101n\u012b Linjah",
        "Kani Lanj",
        "Kani Lanja",
        "K\u0101n\u012b Lanjah"
    ],
    "wof:name":"Kaniye Linc",
    "wof:placetype":"locality"
},
  "geometry": {"coordinates":[44.24731,36.9495],"type":"Point"}
}