{
  "type": "Feature",
  "properties": {
    "gn:admin1_code":"11.0",
    "gn:admin2_code":"9166588.0",
    "gn:asciiname":"Bagh Hanjir",
    "gn:country_code":"IQ",
    "gn:dem":484,
    "gn:feature_class":"P",
    "gn:feature_code":"PPL",
    "gn:name":"B\u0101gh Hanj\u012br",
    "gn:population":0,
    "gn:timezone":"Asia/Baghdad",
    "iso:country":"IQ",
    "name:ara_x_preferred":[
        "\u0628\u0627\u063a \u0647\u0646\u062c\u064a\u0631"
    ],
    "name:und_x_variant":[
        "B\u0101gh Hanj\u012br",
        "B\u0101gh Ajn\u012br"
    ],
    "wof:name":"Bagh Hanjir",
    "wof:placetype":"locality"
},
  "geometry": {"coordinates":[44.63851,35.93425999999999],"type":"Point"}
}