{
  "type": "Feature",
  "properties": {
    "gn:admin1_code":"1.0",
    "gn:admin2_code":"98718.0",
    "gn:asciiname":"Albu Sawdah",
    "gn:country_code":"IQ",
    "gn:dem":50,
    "gn:feature_class":"P",
    "gn:feature_code":"PPL",
    "gn:name":"\u0100lb\u016b Sawdah",
    "gn:population":0,
    "gn:timezone":"Asia/Baghdad",
    "iso:country":"IQ",
    "name:ara_x_preferred":[
        "\u0622\u0644\u0628\u0648 \u0633\u0648\u062f\u0629"
    ],
    "name:und_x_variant":[
        "\u2018Arab \u0100lb\u016b Sawdah",
        "\u0639\u0631\u0628 \u0622\u0644\u0628\u0648 \u0633\u0648\u062f\u0629",
        "\u0100lb\u016b Sawdah"
    ],
    "wof:name":"Albu Sawdah",
    "wof:placetype":"locality"
},
  "geometry": {"coordinates":[43.34239,33.45695],"type":"Point"}
}