{
  "type": "Feature",
  "properties": {
    "gn:admin1_code":"15.0",
    "gn:admin2_code":"90392.0",
    "gn:asciiname":"Qaryat Abu Wakhiyah",
    "gn:country_code":"IQ",
    "gn:dem":371,
    "gn:feature_class":"P",
    "gn:feature_code":"PPL",
    "gn:name":"Qaryat Ab\u016b Wakh\u012byah",
    "gn:population":0,
    "gn:timezone":"Asia/Baghdad",
    "iso:country":"IQ",
    "name:ara_x_preferred":[
        "\u0642\u0631\u064a\u0629 \u0627\u0628\u0648 \u0648\u062e\u064a\u0629"
    ],
    "name:kur_x_preferred":[
        "Ebu Wecnam"
    ],
    "name:kur_x_variant":[
        "\u0626\u06d5\u0628\u0648 \u0648\u06d5\u062c\u0646\u0627\u0645"
    ],
    "name:und_x_variant":[
        "Abu Wajnam",
        "Qaryat Ab\u016b Wakh\u012byah"
    ],
    "wof:name":"Qaryat Abu Wakhiyah",
    "wof:placetype":"locality"
},
  "geometry": {"coordinates":[42.6246,36.69219],"type":"Point"}
}