{
  "type": "Feature",
  "properties": {
    "gn:admin1_code":"9.0",
    "gn:admin2_code":"98855.0",
    "gn:asciiname":"Abu Shambalanah",
    "gn:cc2":"IQ",
    "gn:country_code":"IQ",
    "gn:dem":7,
    "gn:feature_class":"P",
    "gn:feature_code":"PPL",
    "gn:name":"Ab\u016b Shambal\u0101nah",
    "gn:population":0,
    "gn:timezone":"Asia/Baghdad",
    "iso:country":"IQ",
    "name:und_x_variant":[
        "Ab\u016b Shambay\u0101nah",
        "Abu Shimbalana",
        "Ab\u016b Shabb\u0101nah",
        "Ab\u016b Shambal\u0101nah"
    ],
    "wof:name":"Abu Shambalanah",
    "wof:placetype":"locality"
},
  "geometry": {"coordinates":[46.06667,31.08333],"type":"Point"}
}