{
  "type": "Feature",
  "properties": {
    "gn:admin1_code":"8.0",
    "gn:admin2_code":"97269.0",
    "gn:asciiname":"Babuxke Jeri",
    "gn:country_code":"IQ",
    "gn:dem":683,
    "gn:feature_class":"P",
    "gn:feature_code":"PPLL",
    "gn:name":"Babuxk\u00ea J\u00ear\u00ee",
    "gn:population":0,
    "gn:timezone":"Asia/Baghdad",
    "iso:country":"IQ",
    "name:ara_x_preferred":[
        "\u0628\u064a\u0628\u0648\u062e\u0643\u064a"
    ],
    "name:kur_x_preferred":[
        "Babuxk\u00ea J\u00ear\u00ee"
    ],
    "name:kur_x_variant":[
        "\u0628\u0627\u0628\u0648\u062e\u0643\u06ce \u0698\u06ce\u0631\u0649",
        "Bebuxk\u00ea",
        "\u0628\u06d5\u0628\u0648\u062e\u0643\u06ce"
    ],
    "name:und_x_variant":[
        "Bayb\u016bkhkay",
        "Babukhky",
        "Babukhke Lower",
        "B\u0113b\u014dkh\u012b",
        "Baboxki"
    ],
    "wof:name":"Babuxke Jeri",
    "wof:placetype":"locality"
},
  "geometry": {"coordinates":[43.00045,36.99577],"type":"Point"}
}