{
  "type": "Feature",
  "properties": {
    "gn:admin1_code":"10.0",
    "gn:admin2_code":"9166680.0",
    "gn:asciiname":"Muhsin Nasr Allah",
    "gn:country_code":"IQ",
    "gn:dem":44,
    "gn:feature_class":"P",
    "gn:feature_code":"PPL",
    "gn:name":"Mu\u1e29sin Na\u015fr Allah",
    "gn:population":0,
    "gn:timezone":"Asia/Baghdad",
    "iso:country":"IQ",
    "name:ara_x_preferred":[
        "\u0645\u062d\u0633\u0646 \u0646\u0635\u0631 \u0627\u0644\u0644\u0647"
    ],
    "name:und_x_variant":[
        "\u1e28asan Na\u015fr Allah",
        "\u062d\u0633\u0646 \u0646\u0635\u0631\u0627\u0644\u0644\u0647",
        "Mu\u1e29sin Na\u015fr Allah"
    ],
    "wof:name":"Muhsin Nasr Allah",
    "wof:placetype":"locality"
},
  "geometry": {"coordinates":[45.06903,33.84025],"type":"Point"}
}