{
  "type": "Feature",
  "properties": {
    "gn:admin1_code":"5.0",
    "gn:admin2_code":"91176.0",
    "gn:asciiname":"Chinarah",
    "gn:country_code":"IQ",
    "gn:dem":1283,
    "gn:feature_class":"P",
    "gn:feature_code":"PPL",
    "gn:name":"Chin\u0101rah",
    "gn:population":0,
    "gn:timezone":"Asia/Baghdad",
    "iso:country":"IQ",
    "name:ara_x_preferred":[
        "\u0686\u0646\u0627\u0631\u0647"
    ],
    "name:kur_x_preferred":[
        "Chinare"
    ],
    "name:kur_x_variant":[
        "\u0686\u0646\u0627\u0631\u06d5"
    ],
    "name:und_x_variant":[
        "Chin\u0101rah",
        "Chnara",
        "Jin\u0101rah",
        "\u062c\u0646\u0627\u0631\u0647"
    ],
    "wof:name":"Chinarah",
    "wof:placetype":"locality"
},
  "geometry": {"coordinates":[45.73669,35.55044],"type":"Point"}
}