{
  "type": "Feature",
  "properties": {
    "gn:admin1_code":"14.0",
    "gn:admin2_code":"99097.0",
    "gn:asciiname":"Salaf Rumi",
    "gn:country_code":"IQ",
    "gn:dem":9,
    "gn:feature_class":"P",
    "gn:feature_code":"PPL",
    "gn:name":"Salaf R\u016bm\u012b",
    "gn:population":0,
    "gn:timezone":"Asia/Baghdad",
    "iso:country":"IQ",
    "name:ara_x_preferred":[
        "\u0633\u0644\u0641 \u0631\u0648\u0645\u064a"
    ],
    "name:und_x_variant":[
        "Salaf R\u016bm\u012b"
    ],
    "wof:name":"Salaf Rumi",
    "wof:placetype":"locality"
},
  "geometry": {"coordinates":[47.17976,31.69324000000001],"type":"Point"}
}