{
  "type": "Feature",
  "properties": {
    "gn:admin1_code":"10.0",
    "gn:admin2_code":"9166680.0",
    "gn:asciiname":"Janwin Rashid",
    "gn:country_code":"IQ",
    "gn:dem":43,
    "gn:feature_class":"P",
    "gn:feature_code":"PPL",
    "gn:name":"Janw\u012bn Rash\u012bd",
    "gn:population":0,
    "gn:timezone":"Asia/Baghdad",
    "iso:country":"IQ",
    "name:ara_x_preferred":[
        "\u062c\u0646\u0648\u064a\u0646 \u0631\u0634\u064a\u062f"
    ],
    "name:und_x_variant":[
        "Janw\u012bn Rash\u012bd"
    ],
    "wof:name":"Janwin Rashid",
    "wof:placetype":"locality"
},
  "geometry": {"coordinates":[44.89695,33.70578],"type":"Point"}
}