{
  "type": "Feature",
  "properties": {
    "gn:admin1_code":"6.0",
    "gn:admin2_code":"99358.0",
    "gn:asciiname":"'Id Muhammad ar Radi",
    "gn:country_code":"IQ",
    "gn:dem":24,
    "gn:feature_class":"P",
    "gn:feature_code":"PPL",
    "gn:name":"\u2018\u012ad Mu\u1e29ammad ar R\u0101\u1e11\u012b",
    "gn:population":0,
    "gn:timezone":"Asia/Baghdad",
    "iso:country":"IQ",
    "name:ara_x_preferred":[
        "\u0639\u064a\u062f \u0645\u062d\u0645\u062f \u0627\u0644\u0631\u0627\u0636\u064a"
    ],
    "name:und_x_variant":[
        "\u2018\u012ad Mu\u1e29ammad ar R\u0101\u1e11\u012b"
    ],
    "wof:name":"'Id Muhammad ar Radi",
    "wof:placetype":"locality"
},
  "geometry": {"coordinates":[44.57824,32.2796],"type":"Point"}
}