{
  "type": "Feature",
  "properties": {
    "gn:admin1_code":"16.0",
    "gn:admin2_code":"99351.0",
    "gn:asciiname":"Tall Umm 'Itaf",
    "gn:country_code":"IQ",
    "gn:dem":13,
    "gn:feature_class":"P",
    "gn:feature_code":"PPL",
    "gn:name":"Tall Umm \u2018It\u0101f",
    "gn:population":0,
    "gn:timezone":"Asia/Baghdad",
    "iso:country":"IQ",
    "name:ara_x_preferred":[
        "\u062a\u0644 \u0627\u0645 \u0639\u0637\u0627\u0641"
    ],
    "name:und_x_variant":[
        "Tall Umm \u2018It\u0101f"
    ],
    "wof:name":"Tall Umm 'Itaf",
    "wof:placetype":"locality"
},
  "geometry": {"coordinates":[45.88019,31.99638],"type":"Point"}
}