{
  "type": "Feature",
  "properties": {
    "gn:admin1_code":"5.0",
    "gn:admin2_code":"91176.0",
    "gn:asciiname":"Kulard",
    "gn:country_code":"IQ",
    "gn:dem":999,
    "gn:feature_class":"P",
    "gn:feature_code":"PPL",
    "gn:name":"K\u016blard",
    "gn:population":0,
    "gn:timezone":"Asia/Baghdad",
    "iso:country":"IQ",
    "name:ara_x_preferred":[
        "\u0643\u0648\u0644\u0631\u062f"
    ],
    "name:und_x_variant":[
        "K\u014dlarid",
        "K\u016blard",
        "Kolar"
    ],
    "wof:name":"Kulard",
    "wof:placetype":"locality"
},
  "geometry": {"coordinates":[45.38819,35.74903],"type":"Point"}
}