{
  "type": "Feature",
  "properties": {
    "gn:admin1_code":"6.0",
    "gn:admin2_code":"99358.0",
    "gn:asciiname":"'Arab Hajj Salih",
    "gn:country_code":"IQ",
    "gn:dem":27,
    "gn:feature_class":"P",
    "gn:feature_code":"PPLL",
    "gn:name":"\u2018Arab \u1e28\u0101jj \u015e\u0101li\u1e29",
    "gn:population":0,
    "gn:timezone":"Asia/Baghdad",
    "iso:country":"IQ",
    "name:ara_x_preferred":[
        "\u0639\u0631\u0628 \u062d\u0627\u062c \u0635\u0627\u0644\u062d"
    ],
    "name:und_x_variant":[
        "\u2018Arab \u1e28\u0101jj \u015e\u0101li\u1e29"
    ],
    "wof:name":"'Arab Hajj Salih",
    "wof:placetype":"locality"
},
  "geometry": {"coordinates":[44.82377,32.33913],"type":"Point"}
}