{
  "type": "Feature",
  "properties": {
    "gn:admin1_code":"6.0",
    "gn:admin2_code":"99358.0",
    "gn:asciiname":"Muhammad as Sahi",
    "gn:country_code":"IQ",
    "gn:dem":27,
    "gn:feature_class":"P",
    "gn:feature_code":"PPL",
    "gn:name":"Mu\u1e29ammad as Sa\u1e29\u012b",
    "gn:population":0,
    "gn:timezone":"Asia/Baghdad",
    "iso:country":"IQ",
    "name:ara_x_preferred":[
        "\u0645\u062d\u0645\u062f \u0627\u0644\u0633\u062d\u064a"
    ],
    "name:und_x_variant":[
        "Mu\u1e29ammad as Sa\u1e29\u012b"
    ],
    "wof:name":"Muhammad as Sahi",
    "wof:placetype":"locality"
},
  "geometry": {"coordinates":[44.62917,32.40829],"type":"Point"}
}