{
  "type": "Feature",
  "properties": {
    "gn:admin1_code":"18.0",
    "gn:admin2_code":"91594.0",
    "gn:asciiname":"'Ali Husayn",
    "gn:country_code":"IQ",
    "gn:dem":88,
    "gn:feature_class":"P",
    "gn:feature_code":"PPL",
    "gn:name":"\u2018Al\u012b \u1e28usayn",
    "gn:population":0,
    "gn:timezone":"Asia/Baghdad",
    "iso:country":"IQ",
    "name:ara_x_preferred":[
        "\u0639\u0644\u064a \u062d\u0633\u064a\u0646"
    ],
    "name:und_x_variant":[
        "\u2018Al\u012b \u1e28usayn"
    ],
    "wof:name":"'Ali Husayn",
    "wof:placetype":"locality"
},
  "geometry": {"coordinates":[43.72201,34.24539],"type":"Point"}
}