{
  "type": "Feature",
  "properties": {
    "gn:admin1_code":"10.0",
    "gn:admin2_code":"94590.0",
    "gn:asciiname":"Kawrah Shalah",
    "gn:country_code":"IQ",
    "gn:dem":293,
    "gn:feature_class":"P",
    "gn:feature_code":"PPL",
    "gn:name":"Kawrah Shalah",
    "gn:population":0,
    "gn:timezone":"Asia/Baghdad",
    "iso:country":"IQ",
    "name:ara_x_preferred":[
        "\u0643\u0648\u0631\u0629 \u0634\u0644\u0629"
    ],
    "name:kur_x_preferred":[
        "Go\u1e5fe Shel"
    ],
    "name:kur_x_variant":[
        "\u06af\u06c6\u0695\u06d5 \u0634\u06d5\u0644"
    ],
    "name:und_x_variant":[
        "\u2018Gorashala",
        "Gawrah Shalah",
        "Kawrah Shalah",
        "Kurashal",
        "Gora Shal"
    ],
    "wof:name":"Kawrah Shalah",
    "wof:placetype":"locality"
},
  "geometry": {"coordinates":[45.47896,34.71455],"type":"Point"}
}