{
  "type": "Feature",
  "properties": {
    "gn:admin1_code":"4.0",
    "gn:admin2_code":"99763.0",
    "gn:asciiname":"Salman Al Sharmahi",
    "gn:country_code":"IQ",
    "gn:dem":23,
    "gn:feature_class":"P",
    "gn:feature_code":"PPL",
    "gn:name":"Salm\u0101n \u0100l Sharm\u0101h\u012b",
    "gn:population":0,
    "gn:timezone":"Asia/Baghdad",
    "iso:country":"IQ",
    "name:ara_x_preferred":[
        "\u0633\u0644\u0645\u0627\u0646 \u0627\u0644 \u0634\u0631\u0645\u0627\u0647\u064a"
    ],
    "name:und_x_variant":[
        "Salm\u0101n \u0100l Sharm\u0101h\u012b"
    ],
    "wof:name":"Salman Al Sharmahi",
    "wof:placetype":"locality"
},
  "geometry": {"coordinates":[44.95691,31.90987],"type":"Point"}
}