{
  "type": "Feature",
  "properties": {
    "gn:admin1_code":"10.0",
    "gn:admin2_code":"99063.0",
    "gn:asciiname":"Az Zabitiyah",
    "gn:country_code":"IQ",
    "gn:dem":45,
    "gn:feature_class":"P",
    "gn:feature_code":"PPL",
    "gn:name":"Az\u0327 Z\u0327\u0101bi\u0163\u012byah",
    "gn:population":0,
    "gn:timezone":"Asia/Baghdad",
    "iso:country":"IQ",
    "name:ara_x_preferred":[
        "\u0627\u0644\u0638\u0627\u0628\u0637\u064a\u0629"
    ],
    "name:und_x_variant":[
        "Zabt\u012bya",
        "Az\u0327 Z\u0327\u0101bi\u0163\u012byah"
    ],
    "wof:name":"Az Zabitiyah",
    "wof:placetype":"locality"
},
  "geometry": {"coordinates":[44.54722,33.73609],"type":"Point"}
}