{
  "type": "Feature",
  "properties": {
    "gn:admin1_code":"18.0",
    "gn:admin2_code":"6872046.0",
    "gn:asciiname":"Qaryat Umm Dibs",
    "gn:country_code":"IQ",
    "gn:dem":63,
    "gn:feature_class":"P",
    "gn:feature_code":"PPL",
    "gn:name":"Qaryat Umm Dibs",
    "gn:population":0,
    "gn:timezone":"Asia/Baghdad",
    "iso:country":"IQ",
    "name:ara_x_preferred":[
        "\u0642\u0631\u064a\u0629 \u0627\u0645 \u062f\u0628\u0633"
    ],
    "wof:name":"Qaryat Umm Dibs",
    "wof:placetype":"locality"
},
  "geometry": {"coordinates":[43.01857,34.47611],"type":"Point"}
}