{
  "type": "Feature",
  "properties": {
    "gn:admin1_code":"15.0",
    "gn:admin2_code":"9166649.0",
    "gn:asciiname":"'Usaylah",
    "gn:country_code":"IQ",
    "gn:dem":295,
    "gn:feature_class":"P",
    "gn:feature_code":"PPL",
    "gn:name":"\u2018Usaylah",
    "gn:population":0,
    "gn:timezone":"Asia/Baghdad",
    "iso:country":"IQ",
    "name:ara_x_preferred":[
        "\u0639\u0633\u064a\u0644\u0629"
    ],
    "name:und_x_variant":[
        "\u2018Usaylah"
    ],
    "wof:name":"'Usaylah",
    "wof:placetype":"locality"
},
  "geometry": {"coordinates":[42.88008,36.05823],"type":"Point"}
}