{
  "type": "Feature",
  "properties": {
    "gn:admin1_code":"18.0",
    "gn:admin2_code":"9166616.0",
    "gn:asciiname":"Baqir Shalabi",
    "gn:country_code":"IQ",
    "gn:dem":45,
    "gn:feature_class":"P",
    "gn:feature_code":"PPL",
    "gn:name":"B\u0101qir Shalab\u012b",
    "gn:population":0,
    "gn:timezone":"Asia/Baghdad",
    "iso:country":"IQ",
    "name:und_x_variant":[
        "B\u0101qir Shalab\u012b"
    ],
    "wof:name":"Baqir Shalabi",
    "wof:placetype":"locality"
},
  "geometry": {"coordinates":[44.38333,33.81667],"type":"Point"}
}