{
  "type": "Feature",
  "properties": {
    "gn:admin1_code":"17.0",
    "gn:admin2_code":"9166552.0",
    "gn:asciiname":"Al Hirah",
    "gn:country_code":"IQ",
    "gn:dem":25,
    "gn:feature_class":"P",
    "gn:feature_code":"PPL",
    "gn:name":"Al \u1e28\u012brah",
    "gn:population":0,
    "gn:timezone":"Asia/Baghdad",
    "iso:country":"IQ",
    "name:ara_x_preferred":[
        "\u0627\u0644\u062d\u064a\u0631\u0629"
    ],
    "name:aze_x_preferred":[
        "Hiyr\u0259"
    ],
    "name:cat_x_preferred":[
        "Hira"
    ],
    "name:deu_x_preferred":[
        "Al-H\u012bra"
    ],
    "name:fas_x_preferred":[
        "\u062d\u06cc\u0631\u0647"
    ],
    "name:fra_x_preferred":[
        "Al-Hira"
    ],
    "name:hin_x_preferred":[
        "\u0905\u0932-\u0939\u0940\u0930\u093e"
    ],
    "name:ita_x_preferred":[
        "Al-Hira"
    ],
    "name:kat_x_preferred":[
        "\u10d0\u10da-\u10f0\u10d8\u10e0\u10d0"
    ],
    "name:msa_x_preferred":[
        "Hirah"
    ],
    "name:nld_x_preferred":[
        "Hira"
    ],
    "name:nor_x_preferred":[
        "Al-Hira"
    ],
    "name:pol_x_preferred":[
        "Al-Hira"
    ],
    "name:por_x_preferred":[
        "Hira"
    ],
    "name:rus_x_preferred":[
        "\u0425\u0438\u0440\u0430"
    ],
    "name:scn_x_preferred":[
        "Al-Hira"
    ],
    "name:srp_x_preferred":[
        "\u0410\u043b-\u0425\u0438\u0440\u0430"
    ],
    "name:tur_x_preferred":[
        "H\u00eere"
    ],
    "name:ukr_x_preferred":[
        "\u0410\u043b\u044c-\u0425\u0456\u0440\u0430"
    ],
    "name:und_x_variant":[
        "Al \u1e28ayrah",
        "Al \u1e28\u012brah"
    ],
    "name:urd_x_preferred":[
        "\u0627\u0644\u062d\u06cc\u0631\u06c1"
    ],
    "wof:name":"Al Hirah",
    "wof:placetype":"locality"
},
  "geometry": {"coordinates":[44.48674000000001,31.88993],"type":"Point"}
}