{
  "type": "Feature",
  "properties": {
    "gn:admin1_code":"17.0",
    "gn:admin2_code":"9166552.0",
    "gn:asciiname":"Al Hirah",
    "gn:country_code":"IQ",
    "gn:dem":25,
    "gn:feature_class":"P",
    "gn:feature_code":"PPL",
    "gn:name":"Al \u1e28\u012brah",
    "gn:population":0,
    "gn:timezone":"Asia/Baghdad",
    "iso:country":"IQ",
    "name:ara_x_preferred":[
        "\u0627\u0644\u062d\u064a\u0631\u0629"
    ],
    "name:und_x_variant":[
        "Hira",
        "Al \u1e28ayrah",
        "Al \u1e28\u012brah"
    ],
    "wof:name":"Al Hirah",
    "wof:placetype":"locality"
},
  "geometry": {"coordinates":[44.48674000000001,31.88993],"type":"Point"}
}