{
  "type": "Feature",
  "properties": {
    "gn:admin1_code":"10.0",
    "gn:admin2_code":"99170.0",
    "gn:asciiname":"Tahsin Habib",
    "gn:country_code":"IQ",
    "gn:dem":64,
    "gn:feature_class":"P",
    "gn:feature_code":"PPL",
    "gn:name":"Ta\u1e29s\u012bn \u1e28ab\u012bb",
    "gn:population":0,
    "gn:timezone":"Asia/Baghdad",
    "iso:country":"IQ",
    "name:ara_x_preferred":[
        "\u062a\u062d\u0633\u064a\u0646 \u062d\u0628\u064a\u0628"
    ],
    "name:und_x_variant":[
        "Ta\u1e29s\u012bn \u1e28ab\u012bb"
    ],
    "wof:name":"Tahsin Habib",
    "wof:placetype":"locality"
},
  "geometry": {"coordinates":[44.46252,34.1018],"type":"Point"}
}