{
  "type": "Feature",
  "properties": {
    "gn:admin1_code":"15.0",
    "gn:admin2_code":"90392.0",
    "gn:asciiname":"Al Bughah",
    "gn:country_code":"IQ",
    "gn:dem":391,
    "gn:feature_class":"P",
    "gn:feature_code":"PPL",
    "gn:name":"Al B\u016bghah",
    "gn:population":0,
    "gn:timezone":"Asia/Baghdad",
    "iso:country":"IQ",
    "name:ara_x_preferred":[
        "\u0627\u0644\u0628\u0648\u063a\u0629"
    ],
    "name:fas_x_preferred":[
        "\u0628\u0648\u063a\u0647"
    ],
    "name:kur_x_preferred":[
        "Yoghe"
    ],
    "name:kur_x_variant":[
        "\u064a\u06c6\u063a\u06d5"
    ],
    "name:und_x_variant":[
        "Yogha",
        "B\u016bghah",
        "Al B\u016bghah"
    ],
    "wof:name":"Al Bughah",
    "wof:placetype":"locality"
},
  "geometry": {"coordinates":[42.38813,36.59303],"type":"Point"}
}