{
  "type": "Feature",
  "properties": {
    "gn:admin1_code":"9.0",
    "gn:admin2_code":"98855.0",
    "gn:asciiname":"Tall Uzayniyah",
    "gn:country_code":"IQ",
    "gn:dem":5,
    "gn:feature_class":"P",
    "gn:feature_code":"PPL",
    "gn:name":"Tall Uz\u0327ayn\u012byah",
    "gn:population":0,
    "gn:timezone":"Asia/Baghdad",
    "iso:country":"IQ",
    "name:ara_x_preferred":[
        "\u062a\u0644 \u0627\u0638\u064a\u0646\u064a\u0629"
    ],
    "name:und_x_variant":[
        "Tall Uz\u0327ayn\u012byah"
    ],
    "wof:name":"Tall Uzayniyah",
    "wof:placetype":"locality"
},
  "geometry": {"coordinates":[46.2959,31.00716],"type":"Point"}
}