{
  "type": "Feature",
  "properties": {
    "gn:admin1_code":"6.0",
    "gn:admin2_code":"99040.0",
    "gn:asciiname":"Jasim Rashid",
    "gn:country_code":"IQ",
    "gn:dem":34,
    "gn:feature_class":"P",
    "gn:feature_code":"PPL",
    "gn:name":"J\u0101sim R\u0101shid",
    "gn:population":0,
    "gn:timezone":"Asia/Baghdad",
    "iso:country":"IQ",
    "name:ara_x_preferred":[
        "\u062c\u0627\u0633\u0645 \u0631\u0627\u0634\u062f"
    ],
    "name:ara_x_variant":[
        "J\u0101sim R\u0101shid"
    ],
    "wof:name":"Jasim Rashid",
    "wof:placetype":"locality"
},
  "geometry": {"coordinates":[44.32279000000001,32.59646],"type":"Point"}
}