{
  "type": "Feature",
  "properties": {
    "gn:admin1_code":"5.0",
    "gn:admin2_code":"91176.0",
    "gn:asciiname":"Mashan al Wusta",
    "gn:country_code":"IQ",
    "gn:dem":960,
    "gn:feature_class":"P",
    "gn:feature_code":"PPL",
    "gn:name":"M\u0101sh\u0101n al Wus\u0163\u00e1",
    "gn:population":0,
    "gn:timezone":"Asia/Baghdad",
    "iso:country":"IQ",
    "name:ara_x_preferred":[
        "\u0645\u0627\u0634\u0627\u0646 \u0627\u0644\u0648\u0633\u0637\u0649"
    ],
    "name:kur_x_preferred":[
        "Mashan"
    ],
    "name:kur_x_variant":[
        "\u0645\u0627\u0634\u0627\u0646"
    ],
    "name:und_x_variant":[
        "M\u0101sh\u0101n al Wus\u0163\u00e1"
    ],
    "wof:name":"Mashan al Wusta",
    "wof:placetype":"locality"
},
  "geometry": {"coordinates":[45.53003,35.98718],"type":"Point"}
}