{
  "type": "Feature",
  "properties": {
    "gn:admin1_code":"18.0",
    "gn:admin2_code":"6872046.0",
    "gn:asciiname":"Bajjah",
    "gn:country_code":"IQ",
    "gn:dem":167,
    "gn:feature_class":"P",
    "gn:feature_code":"PPL",
    "gn:name":"Bajjah",
    "gn:population":0,
    "gn:timezone":"Asia/Baghdad",
    "iso:country":"IQ",
    "name:ara_x_preferred":[
        "\u0628\u062c\u0651\u0647"
    ],
    "wof:name":"Bajjah",
    "wof:placetype":"locality"
},
  "geometry": {"coordinates":[42.78673,34.92460999999999],"type":"Point"}
}