{
  "type": "Feature",
  "properties": {
    "gn:admin1_code":"10.0",
    "gn:admin2_code":"9166680.0",
    "gn:asciiname":"'Arab al Hazam",
    "gn:country_code":"IQ",
    "gn:dem":92,
    "gn:feature_class":"P",
    "gn:feature_code":"PPL",
    "gn:name":"\u2018Arab al \u1e28az\u0101m",
    "gn:population":0,
    "gn:timezone":"Asia/Baghdad",
    "iso:country":"IQ",
    "name:ara_x_preferred":[
        "\u0639\u0631\u0628 \u0627\u0644\u062d\u0632\u0627\u0645"
    ],
    "name:und_x_variant":[
        "\u2018Arab al \u1e28az\u0101m"
    ],
    "wof:name":"'Arab al Hazam",
    "wof:placetype":"locality"
},
  "geometry": {"coordinates":[45.65274,33.64436],"type":"Point"}
}