{
  "type": "Feature",
  "properties": {
    "gn:admin1_code":"5.0",
    "gn:admin2_code":"96204.0",
    "gn:asciiname":"'Ababayli",
    "gn:country_code":"IQ",
    "gn:dem":993,
    "gn:feature_class":"P",
    "gn:feature_code":"PPL",
    "gn:name":"\u2018Ab\u0101bayl\u012b",
    "gn:population":0,
    "gn:timezone":"Asia/Baghdad",
    "iso:country":"IQ",
    "name:ara_x_preferred":[
        "\u0639\u0628\u0627\u0628\u064a\u0644\u064a"
    ],
    "name:kur_x_preferred":[
        "\u2018Ebabeyl\u00ea"
    ],
    "name:kur_x_variant":[
        "\u0639\u06d5\u0628\u0627\u0628\u06d5\u064a\u0644\u06ce"
    ],
    "name:und_x_variant":[
        "Ab\u0101bayt\u0113",
        "\u0100b\u0101belleh",
        "Ab\u0101b\u012blah",
        "\u2018Ab\u0101bayl\u012b",
        "\u0100b\u0101bell\u012b",
        "Ababayle"
    ],
    "wof:name":"'Ababayli",
    "wof:placetype":"locality"
},
  "geometry": {"coordinates":[46.03246,35.17043],"type":"Point"}
}