{
  "type": "Feature",
  "properties": {
    "gn:admin1_code":"10.0",
    "gn:admin2_code":"94590.0",
    "gn:asciiname":"Kani Shirin",
    "gn:country_code":"IQ",
    "gn:dem":294,
    "gn:feature_class":"P",
    "gn:feature_code":"PPL",
    "gn:name":"K\u0101n\u012b Sh\u012br\u012bn",
    "gn:population":0,
    "gn:timezone":"Asia/Baghdad",
    "iso:country":"IQ",
    "name:ara_x_preferred":[
        "\u0643\u0627\u0646\u064a \u0634\u064a\u0631\u064a\u0646"
    ],
    "name:ara_x_variant":[
        "K\u0101n\u012b Sh\u012br\u012bn"
    ],
    "name:ceb_x_preferred":[
        "K\u0101n\u012b Sh\u012br\u012bn"
    ],
    "name:ckb_x_preferred":[
        "\u06a9\u0627\u0646\u06cc \u0634\u06cc\u0631\u06cc\u0646"
    ],
    "name:fas_x_preferred":[
        "\u06a9\u0627\u0646\u06cc \u0634\u064a\u0631\u064a\u0646"
    ],
    "name:fas_x_variant":[
        "\u06a9\u0627\u0646\u06cc \u0634\u06cc\u0631\u06cc\u0646"
    ],
    "name:swe_x_preferred":[
        "K\u0101n\u012b Sh\u012br\u012bn"
    ],
    "wof:name":"Kani Shirin",
    "wof:placetype":"locality"
},
  "geometry": {"coordinates":[45.53381,34.63669],"type":"Point"}
}