{
  "type": "Feature",
  "properties": {
    "gn:admin1_code":"5.0",
    "gn:admin2_code":"97416.0",
    "gn:asciiname":"Tabah Dayy",
    "gn:country_code":"IQ",
    "gn:dem":714,
    "gn:feature_class":"P",
    "gn:feature_code":"PPL",
    "gn:name":"Tabah Dayy",
    "gn:population":0,
    "gn:timezone":"Asia/Baghdad",
    "iso:country":"IQ",
    "name:ara_x_preferred":[
        "\u062a\u0628\u0647 \u062f\u064a"
    ],
    "wof:name":"Tabah Dayy",
    "wof:placetype":"locality"
},
  "geometry": {"coordinates":[44.84989,35.43396],"type":"Point"}
}