{
  "type": "Feature",
  "properties": {
    "gn:admin1_code":"1.0",
    "gn:admin2_code":"99455.0",
    "gn:asciiname":"Qaryat Tall 'Atas",
    "gn:country_code":"IQ",
    "gn:dem":44,
    "gn:feature_class":"P",
    "gn:feature_code":"PPL",
    "gn:name":"Qaryat Tall \u2018A\u0163\u0101s",
    "gn:population":0,
    "gn:timezone":"Asia/Baghdad",
    "iso:country":"IQ",
    "name:ara_x_preferred":[
        "\u0642\u0631\u064a\u0629 \u062a\u0644 \u0639\u0637\u0627\u0633"
    ],
    "name:und_x_variant":[
        "Qaryat Tall \u2018A\u0163\u0101s"
    ],
    "wof:name":"Qaryat Tall 'Atas",
    "wof:placetype":"locality"
},
  "geometry": {"coordinates":[43.9251,33.18268],"type":"Point"}
}