{
  "type": "Feature",
  "properties": {
    "gn:admin1_code":"18.0",
    "gn:admin2_code":"9166598.0",
    "gn:asciiname":"Qaryat as Sarah",
    "gn:country_code":"IQ",
    "gn:dem":110,
    "gn:feature_class":"P",
    "gn:feature_code":"PPL",
    "gn:name":"Qaryat a\u015f \u015ear\u0101h",
    "gn:population":0,
    "gn:timezone":"Asia/Baghdad",
    "iso:country":"IQ",
    "name:ara_x_preferred":[
        "\u0642\u0631\u064a\u0629 \u0627\u0644\u0635\u0631\u0627\u0629"
    ],
    "name:und_x_variant":[
        "\u0100lb\u016b Sa\u2018\u012bd",
        "\u0627\u0644\u0628\u0648 \u0633\u0639\u064a\u062f",
        "Qaryat a\u015f \u015ear\u0101h"
    ],
    "wof:name":"Qaryat as Sarah",
    "wof:placetype":"locality"
},
  "geometry": {"coordinates":[44.28197,34.59943],"type":"Point"}
}