{
  "type": "Feature",
  "properties": {
    "gn:admin1_code":"5.0",
    "gn:admin2_code":"92743.0",
    "gn:asciiname":"Tutme",
    "gn:country_code":"IQ",
    "gn:dem":945,
    "gn:feature_class":"P",
    "gn:feature_code":"PPL",
    "gn:name":"Tutme",
    "gn:population":0,
    "gn:timezone":"Asia/Baghdad",
    "iso:country":"IQ",
    "name:ara_x_preferred":[
        "\u062a\u0648\u062a\u0645\u0629"
    ],
    "name:kur_x_preferred":[
        "Tutme"
    ],
    "name:kur_x_variant":[
        "\u062a\u0648\u062a\u0645\u06d5"
    ],
    "name:und_x_variant":[
        "Tutma",
        "T\u016btmah",
        "T\u016btama",
        "Tutama"
    ],
    "wof:name":"Tutme",
    "wof:placetype":"locality"
},
  "geometry": {"coordinates":[45.12424,36.34052],"type":"Point"}
}