{
  "type": "Feature",
  "properties": {
    "gn:admin1_code":"13.0",
    "gn:admin2_code":"94786.0",
    "gn:asciiname":"Tappah Kird",
    "gn:country_code":"IQ",
    "gn:dem":709,
    "gn:feature_class":"P",
    "gn:feature_code":"PPL",
    "gn:name":"Tappah Kird",
    "gn:population":0,
    "gn:timezone":"Asia/Baghdad",
    "iso:country":"IQ",
    "name:ara_x_preferred":[
        "\u062a\u0628\u0629 \u0643\u0631\u062f"
    ],
    "name:und_x_variant":[
        "K\u016br Sufl\u00e1",
        "Tappah Qur\u2018\u0101t",
        "Kurr Sufl\u00e1",
        "Tappeh Kur\u0101h",
        "Teppeh Kurah",
        "Tabbah Kurd",
        "Tepe Kur\u0101h",
        "Tappah Kird",
        "Tapakurr"
    ],
    "wof:name":"Tappah Kird",
    "wof:placetype":"locality"
},
  "geometry": {"coordinates":[44.59332,35.70585],"type":"Point"}
}