{
  "type": "Feature",
  "properties": {
    "gn:admin1_code":"15.0",
    "gn:admin2_code":"98820.0",
    "gn:asciiname":"Hukay",
    "gn:country_code":"IQ",
    "gn:dem":595,
    "gn:feature_class":"P",
    "gn:feature_code":"PPL",
    "gn:name":"H\u016bkay",
    "gn:population":0,
    "gn:timezone":"Asia/Baghdad",
    "iso:country":"IQ",
    "name:ara_x_preferred":[
        "\u0647\u0648\u0643\u064a"
    ],
    "name:kur_x_preferred":[
        "Hurk\u00ee"
    ],
    "name:kur_x_variant":[
        "\u0647\u0648\u0631\u0643\u0649",
        "Huw\u00eek\u00ea",
        "\u0647\u0648\u0649\u0643\u06ce"
    ],
    "name:und_x_variant":[
        "Hukah",
        "Hrky",
        "H\u014drki",
        "H\u016bkay"
    ],
    "wof:name":"Hukay",
    "wof:placetype":"locality"
},
  "geometry": {"coordinates":[43.93084,36.89794000000001],"type":"Point"}
}