{
  "type": "Feature",
  "properties": {
    "gn:admin1_code":"15.0",
    "gn:admin2_code":"98612.0",
    "gn:asciiname":"Mayrkabi",
    "gn:country_code":"IQ",
    "gn:dem":664,
    "gn:feature_class":"P",
    "gn:feature_code":"PPL",
    "gn:name":"Mayrkab\u012b",
    "gn:population":0,
    "gn:timezone":"Asia/Baghdad",
    "iso:country":"IQ",
    "name:ara_x_preferred":[
        "\u0645\u064a\u0631\u0643\u0628\u064a"
    ],
    "name:kur_x_preferred":[
        "M\u00eerk\u00ee"
    ],
    "name:kur_x_variant":[
        "\u0645\u064a\u0631\u0643\u0649",
        "M\u00earge Biy\u00ea",
        "\u0645\u06ce\u0631\u06af\u06d5 \u0628\u064a\u06ce"
    ],
    "name:und_x_variant":[
        "Mirky",
        "M\u0113rgabi",
        "Mayrkab\u012b",
        "Merga Bie"
    ],
    "wof:name":"Mayrkabi",
    "wof:placetype":"locality"
},
  "geometry": {"coordinates":[43.56891,36.8175],"type":"Point"}
}