{
  "type": "Feature",
  "properties": {
    "gn:admin1_code":"5.0",
    "gn:admin2_code":"96204.0",
    "gn:asciiname":"Qilrikh as Saghir",
    "gn:country_code":"IQ",
    "gn:dem":514,
    "gn:feature_class":"P",
    "gn:feature_code":"PPL",
    "gn:name":"Qilrikh a\u015f \u015eagh\u012br",
    "gn:population":0,
    "gn:timezone":"Asia/Baghdad",
    "iso:country":"IQ",
    "name:ara_x_preferred":[
        "Qilrikh-i Pich\u016bk"
    ],
    "name:ara_x_variant":[
        "\u0642\u0644\u0631\u062e \u0627\u0644\u0635\u063a\u064a\u0631"
    ],
    "name:fas_x_preferred":[
        "\u0642\u0644\u0631\u062e \u067e\u0686\u0648\u06a9"
    ],
    "name:fas_x_variant":[
        "Qolrokh Pach\u016bk"
    ],
    "name:kur_x_preferred":[
        "Qilrx\u00ee Bichuk"
    ],
    "name:kur_x_variant":[
        "Qilrx",
        "\u0642\u0644\u0631\u062e\u0649 \u0628\u0686\u0648\u0643",
        "\u0642\u0644\u0631\u062e"
    ],
    "name:und_x_variant":[
        "Qilrikh-i Puch\u016bk",
        "Qilrikh a\u015f \u015eagh\u012br",
        "Qilrikh-i Pich\u016bk",
        "Qilrkh"
    ],
    "wof:name":"Qilrikh as Saghir",
    "wof:placetype":"locality"
},
  "geometry": {"coordinates":[45.84459,35.36358],"type":"Point"}
}