{
  "type": "Feature",
  "properties": {
    "gn:admin1_code":"15.0",
    "gn:admin2_code":"9166541.0",
    "gn:asciiname":"Qaryat 'Umar Qabji",
    "gn:country_code":"IQ",
    "gn:dem":307,
    "gn:feature_class":"P",
    "gn:feature_code":"PPL",
    "gn:name":"Qaryat \u2018Umar Q\u0101bj\u012b",
    "gn:population":0,
    "gn:timezone":"Asia/Baghdad",
    "iso:country":"IQ",
    "name:ara_x_preferred":[
        "\u0642\u0631\u064a\u0629 \u0639\u0645\u0631 \u0642\u0627\u0628\u062c\u064a"
    ],
    "name:und_x_variant":[
        "Qaryat \u2018Umar Q\u0101bj\u012b"
    ],
    "wof:name":"Qaryat 'Umar Qabji",
    "wof:placetype":"locality"
},
  "geometry": {"coordinates":[43.2758,36.47935],"type":"Point"}
}