{
  "type": "Feature",
  "properties": {
    "gn:admin1_code":"5.0",
    "gn:admin2_code":"97416.0",
    "gn:asciiname":"Shaykhan",
    "gn:country_code":"IQ",
    "gn:dem":535,
    "gn:feature_class":"P",
    "gn:feature_code":"PPL",
    "gn:name":"Shaykh\u0101n",
    "gn:population":0,
    "gn:timezone":"Asia/Baghdad",
    "iso:country":"IQ",
    "name:ara_x_preferred":[
        "\u0634\u064a\u062e\u0627\u0646"
    ],
    "name:und_x_variant":[
        "Shai Kh\u0101n",
        "Shaykh\u0101n"
    ],
    "wof:name":"Shaykhan",
    "wof:placetype":"locality"
},
  "geometry": {"coordinates":[44.74291,35.82022],"type":"Point"}
}