{
  "type": "Feature",
  "properties": {
    "gn:admin1_code":"6.0",
    "gn:admin2_code":"99358.0",
    "gn:asciiname":"Qaryat Hajj Hasan Murad",
    "gn:country_code":"IQ",
    "gn:dem":24,
    "gn:feature_class":"P",
    "gn:feature_code":"PPL",
    "gn:name":"Qaryat \u1e28\u0101jj \u1e28asan Mur\u0101d",
    "gn:population":0,
    "gn:timezone":"Asia/Baghdad",
    "iso:country":"IQ",
    "name:ara_x_preferred":[
        "\u0642\u0631\u064a\u0629 \u062d\u0627\u062c \u062d\u0633\u0646 \u0645\u0631\u0627\u062f"
    ],
    "name:und_x_variant":[
        "Qaryat \u1e28\u0101jj \u1e28asan Mur\u0101d"
    ],
    "wof:name":"Qaryat Hajj Hasan Murad",
    "wof:placetype":"locality"
},
  "geometry": {"coordinates":[44.68943,32.15879],"type":"Point"}
}