{
  "type": "Feature",
  "properties": {
    "gn:admin1_code":"9.0",
    "gn:admin2_code":"90509.0",
    "gn:asciiname":"Sharqiyah",
    "gn:country_code":"IQ",
    "gn:dem":7,
    "gn:feature_class":"P",
    "gn:feature_code":"PPL",
    "gn:name":"Sharq\u012byah",
    "gn:population":0,
    "gn:timezone":"Asia/Baghdad",
    "iso:country":"IQ",
    "name:ara_x_preferred":[
        "\u0634\u0631\u0642\u064a\u0629"
    ],
    "name:und_x_variant":[
        "Sharq\u012byah"
    ],
    "wof:name":"Sharqiyah",
    "wof:placetype":"locality"
},
  "geometry": {"coordinates":[46.56901,30.85913],"type":"Point"}
}