{
  "type": "Feature",
  "properties": {
    "gn:admin1_code":"5.0",
    "gn:admin2_code":"9166684.0",
    "gn:asciiname":"Jasht",
    "gn:country_code":"IQ",
    "gn:dem":1522,
    "gn:feature_class":"P",
    "gn:feature_code":"PPL",
    "gn:name":"J\u0101sht",
    "gn:population":0,
    "gn:timezone":"Asia/Baghdad",
    "iso:country":"IQ",
    "name:ara_x_preferred":[
        "J\u0101sht"
    ],
    "name:ara_x_variant":[
        "\u062c\u0627\u0634\u062a"
    ],
    "name:kur_x_preferred":[
        "Chaj"
    ],
    "name:kur_x_variant":[
        "Ch\u0101sh",
        "\u0686\u0627\u0698",
        "\u0686\u0627\u0634"
    ],
    "name:und_x_variant":[
        "Ch\u0101sht"
    ],
    "wof:name":"Jasht",
    "wof:placetype":"locality"
},
  "geometry": {"coordinates":[46.16777,35.77489],"type":"Point"}
}