{
  "type": "Feature",
  "properties": {
    "gn:admin1_code":"13.0",
    "gn:admin2_code":"94786.0",
    "gn:asciiname":"Hajji Lar",
    "gn:country_code":"IQ",
    "gn:dem":552,
    "gn:feature_class":"P",
    "gn:feature_code":"PPL",
    "gn:name":"\u1e28\u0101jj\u012b Lar",
    "gn:population":0,
    "gn:timezone":"Asia/Baghdad",
    "iso:country":"IQ",
    "wof:name":"Hajji Lar",
    "wof:placetype":"locality"
},
  "geometry": {"coordinates":[44.57167000000001,35.8225],"type":"Point"}
}