{
  "type": "Feature",
  "properties": {
    "gn:admin1_code":"5.0",
    "gn:admin2_code":"98464.0",
    "gn:asciiname":"Suwayrawah",
    "gn:country_code":"IQ",
    "gn:dem":971,
    "gn:feature_class":"P",
    "gn:feature_code":"PPL",
    "gn:name":"Suwayr\u0101wah",
    "gn:population":0,
    "gn:timezone":"Asia/Baghdad",
    "iso:country":"IQ",
    "name:ara_x_preferred":[
        "\u0633\u0648\u064a\u0631\u0627\u0648\u0647"
    ],
    "name:kur_x_preferred":[
        "Sw\u00earawa"
    ],
    "name:kur_x_variant":[
        "\u0633\u0648\u06ce\u0631\u0627\u0648\u0627"
    ],
    "name:und_x_variant":[
        "Suwayr\u0101wah",
        "S\u00f6r\u0101wa",
        "Swerawa"
    ],
    "wof:name":"Suwayrawah",
    "wof:placetype":"locality"
},
  "geometry": {"coordinates":[45.45307,35.37723],"type":"Point"}
}