{
  "type": "Feature",
  "properties": {
    "gn:admin1_code":"5.0",
    "gn:admin2_code":"98464.0",
    "gn:asciiname":"Tangi Sar",
    "gn:country_code":"IQ",
    "gn:dem":844,
    "gn:feature_class":"P",
    "gn:feature_code":"PPL",
    "gn:name":"Tang\u012b Sar",
    "gn:population":0,
    "gn:timezone":"Asia/Baghdad",
    "iso:country":"IQ",
    "name:ara_x_preferred":[
        "\u062a\u0646\u06af\u064a \u0633\u0631"
    ],
    "name:fas_x_preferred":[
        "\u062a\u0646\u06af\u06cc \u0633\u0631"
    ],
    "name:kur_x_preferred":[
        "Teng\u00eeser"
    ],
    "name:kur_x_variant":[
        "\u062a\u06d5\u0646\u06af\u064a\u0633\u06d5\u0631"
    ],
    "name:und_x_variant":[
        "Tang\u012b Sar",
        "Tangisar",
        "Tank\u012b Sadr",
        "\u062a\u0646\u0643\u064a \u0633\u062f\u0631"
    ],
    "wof:name":"Tangi Sar",
    "wof:placetype":"locality"
},
  "geometry": {"coordinates":[45.29324,35.42787],"type":"Point"}
}