{
  "type": "Feature",
  "properties": {
    "gn:admin1_code":"7.0",
    "gn:admin2_code":"9166542.0",
    "gn:asciiname":"Qaryat Waqti Zayd",
    "gn:country_code":"IQ",
    "gn:dem":36,
    "gn:feature_class":"P",
    "gn:feature_code":"PPL",
    "gn:name":"Qaryat Waqt\u012b Zayd",
    "gn:population":0,
    "gn:timezone":"Asia/Baghdad",
    "iso:country":"IQ",
    "name:ara_x_preferred":[
        "\u0642\u0631\u064a\u0629 \u0648\u0642\u062a\u064a \u0632\u064a\u062f"
    ],
    "name:und_x_variant":[
        "Qaryat Waqt\u012b Zayd"
    ],
    "wof:name":"Qaryat Waqti Zayd",
    "wof:placetype":"locality"
},
  "geometry": {"coordinates":[44.05349,33.39927],"type":"Point"}
}