{
  "type": "Feature",
  "properties": {
    "gn:admin1_code":"16.0",
    "gn:admin2_code":"99132.0",
    "gn:asciiname":"Ad Diya'",
    "gn:country_code":"IQ",
    "gn:dem":14,
    "gn:feature_class":"P",
    "gn:feature_code":"PPL",
    "gn:name":"A\u1e11 \u1e10iy\u0101\u2018",
    "gn:population":0,
    "gn:timezone":"Asia/Baghdad",
    "iso:country":"IQ",
    "name:ara_x_preferred":[
        "\u0627\u0644\u0636\u064a\u0627\u0639"
    ],
    "name:ara_x_variant":[
        "A\u1e11 \u1e10iy\u0101\u2018"
    ],
    "wof:name":"Ad Diya'",
    "wof:placetype":"locality"
},
  "geometry": {"coordinates":[46.0416,32.38632],"type":"Point"}
}