{
  "type": "Feature",
  "properties": {
    "gn:admin1_code":"9.0",
    "gn:admin2_code":"90509.0",
    "gn:asciiname":"'Ashirat al 'Abd",
    "gn:country_code":"IQ",
    "gn:dem":5,
    "gn:feature_class":"P",
    "gn:feature_code":"PPL",
    "gn:name":"\u2018Ash\u012brat al \u2018Abd",
    "gn:population":0,
    "gn:timezone":"Asia/Baghdad",
    "iso:country":"IQ",
    "name:ara_x_preferred":[
        "\u0639\u0634\u064a\u0631\u0629 \u0627\u0644\u0639\u0628\u062f"
    ],
    "name:und_x_variant":[
        "\u2018Ash\u012brat al \u2018Abd"
    ],
    "wof:name":"'Ashirat al 'Abd",
    "wof:placetype":"locality"
},
  "geometry": {"coordinates":[46.50281,30.9754],"type":"Point"}
}