{
  "type": "Feature",
  "properties": {
    "gn:admin1_code":"11.0",
    "gn:admin2_code":"9166534.0",
    "gn:asciiname":"Layluk",
    "gn:country_code":"IQ",
    "gn:dem":781,
    "gn:feature_class":"P",
    "gn:feature_code":"PPL",
    "gn:name":"Layl\u016bk",
    "gn:population":0,
    "gn:timezone":"Asia/Baghdad",
    "iso:country":"IQ",
    "name:ara_x_preferred":[
        "\u0644\u064a\u0644\u0648\u0643"
    ],
    "name:kur_x_preferred":[
        "L\u00ealuk"
    ],
    "name:kur_x_variant":[
        "\u0644\u06ce\u0644\u0648\u0643",
        "L\u00eelok",
        "\u0644\u064a\u0644\u06c6\u0643"
    ],
    "name:und_x_variant":[
        "Layl\u016bk",
        "Layl\u014dk",
        "Lailuk",
        "Layluk"
    ],
    "wof:name":"Layluk",
    "wof:placetype":"locality"
},
  "geometry": {"coordinates":[44.38719,36.80736],"type":"Point"}
}