{
  "type": "Feature",
  "properties": {
    "gn:admin1_code":"10.0",
    "gn:admin2_code":"99063.0",
    "gn:asciiname":"Qaryat al Badiyah",
    "gn:country_code":"IQ",
    "gn:dem":52,
    "gn:feature_class":"P",
    "gn:feature_code":"PPL",
    "gn:name":"Qaryat al B\u0101diyah",
    "gn:population":0,
    "gn:timezone":"Asia/Baghdad",
    "iso:country":"IQ",
    "name:ara_x_preferred":[
        "\u0642\u0631\u064a\u0629 \u0627\u0644\u0628\u0627\u062f\u064a\u0629"
    ],
    "name:und_x_variant":[
        "Qaryat al B\u0101diyah"
    ],
    "wof:name":"Qaryat al Badiyah",
    "wof:placetype":"locality"
},
  "geometry": {"coordinates":[44.88801,33.86568],"type":"Point"}
}