{
  "type": "Feature",
  "properties": {
    "gn:admin1_code":"14.0",
    "gn:admin2_code":"99305.0",
    "gn:asciiname":"'Arab Mahmud al Kabir",
    "gn:country_code":"IQ",
    "gn:dem":13,
    "gn:feature_class":"P",
    "gn:feature_code":"PPL",
    "gn:name":"\u2018Arab Ma\u1e29m\u016bd al Kab\u012br",
    "gn:population":0,
    "gn:timezone":"Asia/Baghdad",
    "iso:country":"IQ",
    "name:ara_x_preferred":[
        "\u0639\u0631\u0628 \u0645\u062d\u0645\u0648\u062f \u0627\u0644\u0643\u0628\u064a\u0631"
    ],
    "name:und_x_variant":[
        "\u2018Arab Ma\u1e29m\u016bd al Kab\u012br"
    ],
    "wof:name":"'Arab Mahmud al Kabir",
    "wof:placetype":"locality"
},
  "geometry": {"coordinates":[46.58465,32.50757],"type":"Point"}
}