{
  "type": "Feature",
  "properties": {
    "gn:admin1_code":"9.0",
    "gn:admin2_code":"98700.0",
    "gn:asciiname":"Falah Thamir",
    "gn:country_code":"IQ",
    "gn:dem":6,
    "gn:feature_class":"P",
    "gn:feature_code":"PPL",
    "gn:name":"Fal\u0101\u1e29 Th\u0101mir",
    "gn:population":0,
    "gn:timezone":"Asia/Baghdad",
    "iso:country":"IQ",
    "name:ara_x_preferred":[
        "\u0641\u0644\u0627\u062d \u062b\u0627\u0645\u0631"
    ],
    "name:und_x_variant":[
        "Fal\u0101\u1e29 Th\u0101mir"
    ],
    "wof:name":"Falah Thamir",
    "wof:placetype":"locality"
},
  "geometry": {"coordinates":[45.95743,31.50538],"type":"Point"}
}