{
  "type": "Feature",
  "properties": {
    "gn:admin1_code":"16.0",
    "gn:admin2_code":"99132.0",
    "gn:asciiname":"Al Faysaliyah",
    "gn:country_code":"IQ",
    "gn:dem":17,
    "gn:feature_class":"P",
    "gn:feature_code":"PPL",
    "gn:name":"Al Fay\u015fal\u012byah",
    "gn:population":0,
    "gn:timezone":"Asia/Baghdad",
    "iso:country":"IQ",
    "name:ara_x_preferred":[
        "\u0627\u0644\u0641\u064a\u0635\u0644\u064a\u0647"
    ],
    "name:und_x_variant":[
        "Faisaliya",
        "Al Fay\u015fal\u012byah"
    ],
    "wof:name":"Al Faysaliyah",
    "wof:placetype":"locality"
},
  "geometry": {"coordinates":[45.80557,32.49019000000001],"type":"Point"}
}