{
  "type": "Feature",
  "properties": {
    "gn:admin1_code":"2.0",
    "gn:admin2_code":"9166549.0",
    "gn:asciiname":"Kut al Khalifah",
    "gn:country_code":"IQ",
    "gn:dem":1,
    "gn:feature_class":"P",
    "gn:feature_code":"PPL",
    "gn:name":"K\u016bt al Khal\u012bfah",
    "gn:population":0,
    "gn:timezone":"Asia/Baghdad",
    "iso:country":"IQ",
    "name:ara_x_preferred":[
        "\u0643\u0648\u062a \u0627\u0644\u062e\u0644\u064a\u0641\u0629"
    ],
    "name:und_x_variant":[
        "K\u016bt Khal\u012bfah",
        "K\u016bt Khal\u012bfa",
        "K\u016bt al Khal\u012bfah"
    ],
    "wof:name":"Kut al Khalifah",
    "wof:placetype":"locality"
},
  "geometry": {"coordinates":[48.38856,30.19597000000001],"type":"Point"}
}