{
  "type": "Feature",
  "properties": {
    "gn:admin1_code":"14.0",
    "gn:admin2_code":"9166557.0",
    "gn:asciiname":"Hamad al Jabr",
    "gn:country_code":"IQ",
    "gn:dem":9,
    "gn:feature_class":"P",
    "gn:feature_code":"PPL",
    "gn:name":"\u1e28amad al Jabr",
    "gn:population":0,
    "gn:timezone":"Asia/Baghdad",
    "iso:country":"IQ",
    "name:ara_x_preferred":[
        "\u062d\u0645\u062f \u0627\u0644\u062c\u0628\u0631"
    ],
    "name:und_x_variant":[
        "\u1e28amad al Jabr"
    ],
    "wof:name":"Hamad al Jabr",
    "wof:placetype":"locality"
},
  "geometry": {"coordinates":[47.32519,31.74671],"type":"Point"}
}