{
  "type": "Feature",
  "properties": {
    "gn:admin1_code":"15.0",
    "gn:admin2_code":"98820.0",
    "gn:asciiname":"Bashqal Rawand",
    "gn:country_code":"IQ",
    "gn:dem":660,
    "gn:feature_class":"P",
    "gn:feature_code":"PPL",
    "gn:name":"Bashq\u0101l Rawand",
    "gn:population":0,
    "gn:timezone":"Asia/Baghdad",
    "iso:country":"IQ",
    "name:ara_x_preferred":[
        "\u0628\u0634\u0642\u0627\u0644 \u0631\u0648\u0646\u062f"
    ],
    "name:kur_x_preferred":[
        "Bshqal"
    ],
    "name:kur_x_variant":[
        "\u0628\u0634\u0642\u0627\u0644",
        "Bashqal \u1e5eawend",
        "\u0628\u0627\u0634\u0642\u0627\u0644 \u0695\u0627\u0648\u06d5\u0646\u062f"
    ],
    "name:und_x_variant":[
        "Bishqal",
        "Bashq\u0101l",
        "Bashq\u0101l Rawand",
        "Bashqal Rawand"
    ],
    "wof:name":"Bashqal Rawand",
    "wof:placetype":"locality"
},
  "geometry": {"coordinates":[43.93131,36.73886],"type":"Point"}
}