{
  "type": "Feature",
  "properties": {
    "gn:admin1_code":"15.0",
    "gn:admin2_code":"9166649.0",
    "gn:asciiname":"Tall 'Abtah ash Shimali",
    "gn:country_code":"IQ",
    "gn:dem":221,
    "gn:feature_class":"P",
    "gn:feature_code":"PPL",
    "gn:name":"Tall \u2018Ab\u0163ah ash Shim\u0101l\u012b",
    "gn:population":0,
    "gn:timezone":"Asia/Baghdad",
    "iso:country":"IQ",
    "name:ara_x_preferred":[
        "\u062a\u0644 \u0639\u0628\u0637\u0629 \u0627\u0644\u0634\u0645\u0627\u0644\u064a"
    ],
    "name:und_x_variant":[
        "Tall \u2018Ab\u0163ah",
        "Tall \u2018Ab\u0163ah ash Shim\u0101l\u012b"
    ],
    "wof:name":"Tall 'Abtah ash Shimali",
    "wof:placetype":"locality"
},
  "geometry": {"coordinates":[42.56476,35.94742],"type":"Point"}
}