{
  "type": "Feature",
  "properties": {
    "gn:admin1_code":"2.0",
    "gn:admin2_code":"100049.0",
    "gn:asciiname":"Ru'ays",
    "gn:country_code":"IQ",
    "gn:dem":1,
    "gn:feature_class":"P",
    "gn:feature_code":"PPL",
    "gn:name":"Ru\u2019ays",
    "gn:population":0,
    "gn:timezone":"Asia/Baghdad",
    "iso:country":"IQ",
    "name:und_x_variant":[
        "Ruways",
        "Ruwais",
        "Ru\u2019ays"
    ],
    "wof:name":"Ru'ays",
    "wof:placetype":"locality"
},
  "geometry": {"coordinates":[48.16667,30.38333],"type":"Point"}
}