{
  "type": "Feature",
  "properties": {
    "gn:admin1_code":"4.0",
    "gn:admin2_code":"98634.0",
    "gn:asciiname":"Al Malihah",
    "gn:country_code":"IQ",
    "gn:dem":22,
    "gn:feature_class":"P",
    "gn:feature_code":"PPL",
    "gn:name":"Al M\u0101li\u1e29ah",
    "gn:population":0,
    "gn:timezone":"Asia/Baghdad",
    "iso:country":"IQ",
    "name:ara_x_preferred":[
        "\u0627\u0644\u0645\u0627\u0644\u062d\u0629"
    ],
    "name:und_x_variant":[
        "Shab\u0101n\u0101t",
        "\u0634\u0628\u0627\u0646\u0627\u062a",
        "Al M\u0101li\u1e29ah"
    ],
    "wof:name":"Al Malihah",
    "wof:placetype":"locality"
},
  "geometry": {"coordinates":[44.53802,31.89164],"type":"Point"}
}