{
  "type": "Feature",
  "properties": {
    "gn:admin1_code":"18.0",
    "gn:admin2_code":"6805736.0",
    "gn:asciiname":"Qasr Farhatiyah",
    "gn:cc2":"IQ",
    "gn:country_code":"IQ",
    "gn:dem":45,
    "gn:feature_class":"P",
    "gn:feature_code":"PPL",
    "gn:name":"Qa\u015fr Farh\u0101t\u012byah",
    "gn:population":0,
    "gn:timezone":"Asia/Baghdad",
    "iso:country":"IQ",
    "name:und_x_variant":[
        "Qasr Farhatiya",
        "Qa\u015fr Farh\u0101t\u012byah"
    ],
    "wof:name":"Qasr Farhatiyah",
    "wof:placetype":"locality"
},
  "geometry": {"coordinates":[44.08333,33.91667],"type":"Point"}
}