{
  "type": "Feature",
  "properties": {
    "gn:admin1_code":"16.0",
    "gn:admin2_code":"98460.0",
    "gn:asciiname":"Qaryat 'Ayid Khulayf",
    "gn:country_code":"IQ",
    "gn:dem":26,
    "gn:feature_class":"P",
    "gn:feature_code":"PPL",
    "gn:name":"Qaryat \u2018\u0100yid Khulayf",
    "gn:population":0,
    "gn:timezone":"Asia/Baghdad",
    "iso:country":"IQ",
    "name:ara_x_preferred":[
        "\u0642\u0631\u064a\u0629 \u0639\u0627\u064a\u062f \u062e\u0644\u064a\u0641"
    ],
    "name:und_x_variant":[
        "Qaryat \u2018\u0100yid Khulayf"
    ],
    "wof:name":"Qaryat 'Ayid Khulayf",
    "wof:placetype":"locality"
},
  "geometry": {"coordinates":[44.93229,32.8275],"type":"Point"}
}