{
  "type": "Feature",
  "properties": {
    "gn:admin1_code":"7.0",
    "gn:admin2_code":"9166569.0",
    "gn:asciiname":"'Abd Allah Mud'af",
    "gn:country_code":"IQ",
    "gn:dem":38,
    "gn:feature_class":"P",
    "gn:feature_code":"PPL",
    "gn:name":"\u2018Abd All\u0101h Mu\u1e11\u2018af",
    "gn:population":0,
    "gn:timezone":"Asia/Baghdad",
    "iso:country":"IQ",
    "name:ara_x_preferred":[
        "\u0639\u0628\u062f \ufdf2 \u0645\u0636\u0639\u0641"
    ],
    "name:und_x_variant":[
        "\u2018Abd All\u0101h Mu\u1e11\u2018af"
    ],
    "wof:name":"'Abd Allah Mud'af",
    "wof:placetype":"locality"
},
  "geometry": {"coordinates":[44.17064,33.72758],"type":"Point"}
}