{
  "type": "Feature",
  "properties": {
    "gn:admin1_code":"13.0",
    "gn:admin2_code":"9171727.0",
    "gn:asciiname":"Hanjirah",
    "gn:country_code":"IQ",
    "gn:dem":320,
    "gn:feature_class":"P",
    "gn:feature_code":"PPL",
    "gn:name":"Hanj\u012brah",
    "gn:population":0,
    "gn:timezone":"Asia/Baghdad",
    "iso:country":"IQ",
    "name:ara_x_preferred":[
        "\u0647\u0646\u062c\u064a\u0631\u0629"
    ],
    "name:kur_x_preferred":[
        "Henc\u00eere"
    ],
    "name:kur_x_variant":[
        "Hanjira",
        "\u0647\u06d5\u0646\u062c\u064a\u0631\u06d5"
    ],
    "name:und_x_variant":[
        "Kuchuk Hanjira",
        "Kuch\u016bk Hanj\u012brah",
        "Hanj\u012brah"
    ],
    "wof:name":"Hanjirah",
    "wof:placetype":"locality"
},
  "geometry": {"coordinates":[44.23215,35.58373],"type":"Point"}
}