{
  "type": "Feature",
  "properties": {
    "gn:admin1_code":"5.0",
    "gn:admin2_code":"9166600.0",
    "gn:asciiname":"Zahardahlikaw",
    "gn:country_code":"IQ",
    "gn:dem":1027,
    "gn:feature_class":"P",
    "gn:feature_code":"PPL",
    "gn:name":"Zahardahl\u012bkaw",
    "gn:population":0,
    "gn:timezone":"Asia/Baghdad",
    "iso:country":"IQ",
    "name:ara_x_preferred":[
        "\u0632\u06d5\u0631\u062f\u0629\u0644\u064a\u0643\u0648"
    ],
    "name:kur_x_preferred":[
        "Zerdel\u00eekaw"
    ],
    "name:kur_x_variant":[
        "\u0632\u06d5\u0631\u062f\u06d5\u0644\u064a\u0643\u0627\u0648"
    ],
    "name:und_x_variant":[
        "Zardalikaw",
        "Zahardahl\u012bkaw",
        "Zardah Likaw",
        "\u0632\u06d5\u0631\u062f\u06d5\u0644\u064a\u0643\u0648"
    ],
    "wof:name":"Zahardahlikaw",
    "wof:placetype":"locality"
},
  "geometry": {"coordinates":[45.47556,35.12789],"type":"Point"}
}