{
  "type": "Feature",
  "properties": {
    "gn:admin1_code":"18.0",
    "gn:admin2_code":"6783103.0",
    "gn:asciiname":"Qaryat Makirah",
    "gn:country_code":"IQ",
    "gn:dem":67,
    "gn:feature_class":"P",
    "gn:feature_code":"PPL",
    "gn:name":"Qaryat Mak\u012brah",
    "gn:population":0,
    "gn:timezone":"Asia/Baghdad",
    "iso:country":"IQ",
    "name:ara_x_preferred":[
        "\u0642\u0631\u064a\u0629 \u0645\u0643\u064a\u0631\u0647"
    ],
    "name:und_x_variant":[
        "Qaryat Mak\u012brah"
    ],
    "wof:name":"Qaryat Makirah",
    "wof:placetype":"locality"
},
  "geometry": {"coordinates":[44.34341,34.16446],"type":"Point"}
}