{
  "type": "Feature",
  "properties": {
    "gn:admin1_code":"18.0",
    "gn:admin2_code":"6783103.0",
    "gn:asciiname":"Ahmad Hasan",
    "gn:country_code":"IQ",
    "gn:dem":78,
    "gn:feature_class":"P",
    "gn:feature_code":"PPL",
    "gn:name":"A\u1e29mad \u1e28asan",
    "gn:population":0,
    "gn:timezone":"Asia/Baghdad",
    "iso:country":"IQ",
    "name:ara_x_preferred":[
        "\u0627\u062d\u0645\u062f \u062d\u0633\u0646"
    ],
    "name:und_x_variant":[
        "A\u1e29mad \u1e28asan"
    ],
    "wof:name":"Ahmad Hasan",
    "wof:placetype":"locality"
},
  "geometry": {"coordinates":[43.95704,34.43185],"type":"Point"}
}