{
  "type": "Feature",
  "properties": {
    "gn:admin1_code":"6.0",
    "gn:admin2_code":"99040.0",
    "gn:asciiname":"'Arab Hatim Musa",
    "gn:country_code":"IQ",
    "gn:dem":33,
    "gn:feature_class":"P",
    "gn:feature_code":"PPL",
    "gn:name":"\u2018Arab \u1e28\u0101tim M\u016bs\u00e1",
    "gn:population":0,
    "gn:timezone":"Asia/Baghdad",
    "iso:country":"IQ",
    "name:ara_x_preferred":[
        "\u0639\u0631\u0628 \u062d\u0627\u062a\u0645 \u0645\u0648\u0633\u0649"
    ],
    "name:und_x_variant":[
        "\u2018Arab \u1e28\u0101tim M\u016bs\u00e1"
    ],
    "wof:name":"'Arab Hatim Musa",
    "wof:placetype":"locality"
},
  "geometry": {"coordinates":[44.41088,32.52059000000001],"type":"Point"}
}