{
  "type": "Feature",
  "properties": {
    "gn:admin1_code":"6.0",
    "gn:admin2_code":"6818313.0",
    "gn:asciiname":"Nabi Ayyub",
    "gn:country_code":"IQ",
    "gn:dem":32,
    "gn:feature_class":"P",
    "gn:feature_code":"PPL",
    "gn:name":"Nab\u012b Ayy\u016bb",
    "gn:population":0,
    "gn:timezone":"Asia/Baghdad",
    "iso:country":"IQ",
    "name:ara_x_preferred":[
        "\u0646\u0628\u064a \u0627\u064a\u0648\u0628"
    ],
    "name:und_x_variant":[
        "Im\u0101m Aiy\u016bb",
        "Im\u0101m Ayy\u016bb",
        "Nab\u012b Ayy\u016bb"
    ],
    "wof:name":"Nabi Ayyub",
    "wof:placetype":"locality"
},
  "geometry": {"coordinates":[44.45606,32.44684],"type":"Point"}
}