{
  "type": "Feature",
  "properties": {
    "gn:admin1_code":"7.0",
    "gn:admin2_code":"99101.0",
    "gn:asciiname":"Karim Muhammad",
    "gn:country_code":"IQ",
    "gn:dem":34,
    "gn:feature_class":"P",
    "gn:feature_code":"PPL",
    "gn:name":"Kar\u012bm Mu\u1e29ammad",
    "gn:population":0,
    "gn:timezone":"Asia/Baghdad",
    "iso:country":"IQ",
    "name:ara_x_preferred":[
        "\u0643\u0631\u064a\u0645 \u0645\u062d\u0645\u062f"
    ],
    "name:und_x_variant":[
        "Kar\u012bm Mu\u1e29ammad"
    ],
    "wof:name":"Karim Muhammad",
    "wof:placetype":"locality"
},
  "geometry": {"coordinates":[44.47685,33.10262],"type":"Point"}
}