{
  "type": "Feature",
  "properties": {
    "gn:admin1_code":"4.0",
    "gn:admin2_code":"6850588.0",
    "gn:asciiname":"Kurd 'Abd Allah",
    "gn:country_code":"IQ",
    "gn:dem":15,
    "gn:feature_class":"P",
    "gn:feature_code":"PPL",
    "gn:name":"Kurd \u2018Abd All\u0101h",
    "gn:population":0,
    "gn:timezone":"Asia/Baghdad",
    "iso:country":"IQ",
    "name:ara_x_preferred":[
        "\u0643\u0631\u062f \u0639\u0628\u062f \ufdf2"
    ],
    "name:ara_x_variant":[
        "Kurd \u2018Abd All\u0101h"
    ],
    "wof:name":"Kurd 'Abd Allah",
    "wof:placetype":"locality"
},
  "geometry": {"coordinates":[44.82242,31.45853],"type":"Point"}
}