{
  "type": "Feature",
  "properties": {
    "gn:admin1_code":"18.0",
    "gn:admin2_code":"6783103.0",
    "gn:asciiname":"Hadi al Fayyad",
    "gn:country_code":"IQ",
    "gn:dem":77,
    "gn:feature_class":"P",
    "gn:feature_code":"PPL",
    "gn:name":"H\u0101d\u012b al Fayy\u0101\u1e11",
    "gn:population":0,
    "gn:timezone":"Asia/Baghdad",
    "iso:country":"IQ",
    "name:ara_x_preferred":[
        "\u0647\u0627\u062f\u064a \u0627\u0644\u0641\u064a\u0627\u0636"
    ],
    "name:und_x_variant":[
        "H\u0101d\u012b al Fayy\u0101\u1e11"
    ],
    "wof:name":"Hadi al Fayyad",
    "wof:placetype":"locality"
},
  "geometry": {"coordinates":[44.48748,34.28993],"type":"Point"}
}