{
  "type": "Feature",
  "properties": {
    "gn:admin1_code":"18.0",
    "gn:admin2_code":"6783103.0",
    "gn:asciiname":"'Arab Shallal Jasim",
    "gn:country_code":"IQ",
    "gn:dem":75,
    "gn:feature_class":"P",
    "gn:feature_code":"PPL",
    "gn:name":"\u2018Arab Shall\u0101l J\u0101sim",
    "gn:population":0,
    "gn:timezone":"Asia/Baghdad",
    "iso:country":"IQ",
    "name:ara_x_preferred":[
        "\u0639\u0631\u0628 \u0634\u0644\u0627\u0644 \u062c\u0627\u0633\u0645"
    ],
    "name:und_x_variant":[
        "\u2018Arab Shall\u0101l J\u0101sim"
    ],
    "wof:name":"'Arab Shallal Jasim",
    "wof:placetype":"locality"
},
  "geometry": {"coordinates":[44.49139,34.28515],"type":"Point"}
}