{
  "type": "Feature",
  "properties": {
    "gn:admin1_code":"6.0",
    "gn:admin2_code":"99358.0",
    "gn:asciiname":"Nayif al Jaryan",
    "gn:country_code":"IQ",
    "gn:dem":28,
    "gn:feature_class":"P",
    "gn:feature_code":"PPLL",
    "gn:name":"N\u0101yif al Jary\u0101n",
    "gn:population":0,
    "gn:timezone":"Asia/Baghdad",
    "iso:country":"IQ",
    "name:ara_x_preferred":[
        "\u0646\u0627\u064a\u0641 \u0627\u0644\u062c\u0631\u064a\u0627\u0646"
    ],
    "name:und_x_variant":[
        "N\u0101yif al Jary\u0101n"
    ],
    "wof:name":"Nayif al Jaryan",
    "wof:placetype":"locality"
},
  "geometry": {"coordinates":[44.78646,32.43518],"type":"Point"}
}