{
  "type": "Feature",
  "properties": {
    "gn:admin1_code":"10.0",
    "gn:admin2_code":"94590.0",
    "gn:asciiname":"Jahanjir",
    "gn:country_code":"IQ",
    "gn:dem":295,
    "gn:feature_class":"P",
    "gn:feature_code":"PPL",
    "gn:name":"Jah\u0101nj\u012br",
    "gn:population":0,
    "gn:timezone":"Asia/Baghdad",
    "iso:country":"IQ",
    "name:kur_x_preferred":[
        "C\u00eehang\u00eer"
    ],
    "name:kur_x_variant":[
        "\u062c\u064a\u0647\u0627\u0646\u06af\u064a\u0631"
    ],
    "name:und_x_variant":[
        "Jeh\u0101ngir",
        "Jah\u0101nj\u012br"
    ],
    "wof:name":"Jahanjir",
    "wof:placetype":"locality"
},
  "geometry": {"coordinates":[45.42762000000001,34.52918],"type":"Point"}
}