{
  "type": "Feature",
  "properties": {
    "gn:admin1_code":"7.0",
    "gn:admin2_code":"9166569.0",
    "gn:asciiname":"'Ali Hurayz",
    "gn:country_code":"IQ",
    "gn:dem":40,
    "gn:feature_class":"P",
    "gn:feature_code":"PPL",
    "gn:name":"\u2018Al\u012b \u1e28urayz",
    "gn:population":0,
    "gn:timezone":"Asia/Baghdad",
    "iso:country":"IQ",
    "name:ara_x_preferred":[
        "\u0639\u0644\u064a \u062d\u0631\u064a\u0632"
    ],
    "name:und_x_variant":[
        "\u2018Al\u012b \u1e28urayz"
    ],
    "wof:name":"'Ali Hurayz",
    "wof:placetype":"locality"
},
  "geometry": {"coordinates":[44.19202,33.60063],"type":"Point"}
}