{
  "type": "Feature",
  "properties": {
    "gn:admin1_code":"7.0",
    "gn:admin2_code":"9166569.0",
    "gn:asciiname":"'Awdah Jasim",
    "gn:country_code":"IQ",
    "gn:dem":39,
    "gn:feature_class":"P",
    "gn:feature_code":"PPL",
    "gn:name":"\u2018Awdah J\u0101sim",
    "gn:population":0,
    "gn:timezone":"Asia/Baghdad",
    "iso:country":"IQ",
    "name:ara_x_preferred":[
        "\u0639\u0648\u062f\u0629 \u062c\u0627\u0633\u0645"
    ],
    "name:und_x_variant":[
        "\u2018Awdah J\u0101sim"
    ],
    "wof:name":"'Awdah Jasim",
    "wof:placetype":"locality"
},
  "geometry": {"coordinates":[44.21119,33.62336],"type":"Point"}
}