{
  "type": "Feature",
  "properties": {
    "gn:admin1_code":"18.0",
    "gn:admin2_code":"6872046.0",
    "gn:asciiname":"Salih Farah",
    "gn:country_code":"IQ",
    "gn:dem":138,
    "gn:feature_class":"P",
    "gn:feature_code":"PPL",
    "gn:name":"\u015e\u0101li\u1e29 Fara\u1e29",
    "gn:population":0,
    "gn:timezone":"Asia/Baghdad",
    "iso:country":"IQ",
    "name:ara_x_preferred":[
        "\u0635\u0627\u0644\u062d \u0641\u0631\u062d"
    ],
    "name:und_x_variant":[
        "\u015e\u0101li\u1e29 Fara\u1e29"
    ],
    "wof:name":"Salih Farah",
    "wof:placetype":"locality"
},
  "geometry": {"coordinates":[43.32297,34.56753],"type":"Point"}
}