{
  "type": "Feature",
  "properties": {
    "gn:admin1_code":"4.0",
    "gn:admin2_code":"99763.0",
    "gn:asciiname":"Da'da' Muhi",
    "gn:country_code":"IQ",
    "gn:dem":23,
    "gn:feature_class":"P",
    "gn:feature_code":"PPL",
    "gn:name":"Da\u2018d\u0101\u2018 Mu\u1e29\u012b",
    "gn:population":0,
    "gn:timezone":"Asia/Baghdad",
    "iso:country":"IQ",
    "name:ara_x_preferred":[
        "\u062f\u0639\u062f\u0627\u0639 \u0645\u062d\u064a"
    ],
    "name:und_x_variant":[
        "Da\u2018d\u0101\u2018 Mu\u1e29\u012b"
    ],
    "wof:name":"Da'da' Muhi",
    "wof:placetype":"locality"
},
  "geometry": {"coordinates":[44.63798,31.93126],"type":"Point"}
}