{
  "type": "Feature",
  "properties": {
    "gn:admin1_code":"11.0",
    "gn:admin2_code":"9166534.0",
    "gn:asciiname":"Dirray",
    "gn:country_code":"IQ",
    "gn:dem":1525,
    "gn:feature_class":"P",
    "gn:feature_code":"PPL",
    "gn:name":"Dirray",
    "gn:population":0,
    "gn:timezone":"Asia/Baghdad",
    "iso:country":"IQ",
    "name:ara_x_preferred":[
        "\u062f\u0631\u0651\u064a"
    ],
    "name:kur_x_preferred":[
        "Di\u1e5f\u00ee"
    ],
    "name:kur_x_variant":[
        "\u062f\u0695\u0649",
        "Di\u1e5f\u00ea",
        "\u062f\u0695\u06ce"
    ],
    "name:und_x_variant":[
        "Dry",
        "Dir\u0113",
        "Dirray"
    ],
    "wof:name":"Dirray",
    "wof:placetype":"locality"
},
  "geometry": {"coordinates":[44.16131,37.22084],"type":"Point"}
}