{
  "type": "Feature",
  "properties": {
    "gn:admin1_code":"5.0",
    "gn:admin2_code":"91176.0",
    "gn:asciiname":"Shirah Barah",
    "gn:country_code":"IQ",
    "gn:dem":751,
    "gn:feature_class":"P",
    "gn:feature_code":"PPL",
    "gn:name":"Sh\u012brah Barah",
    "gn:population":0,
    "gn:timezone":"Asia/Baghdad",
    "iso:country":"IQ",
    "name:ara_x_preferred":[
        "\u0634\u064a\u0631\u0629 \u0628\u0631\u0629"
    ],
    "name:kur_x_preferred":[
        "Sh\u00eere Bere"
    ],
    "name:kur_x_variant":[
        "\u0634\u064a\u0631\u06d5 \u0628\u06d5\u0631\u06d5"
    ],
    "name:und_x_variant":[
        "Sh\u012brah Badah",
        "\u0634\u064a\u0631\u0629 \u0628\u062f\u0629",
        "Sh\u012brah Barah",
        "Shera Bara"
    ],
    "wof:name":"Shirah Barah",
    "wof:placetype":"locality"
},
  "geometry": {"coordinates":[45.73986,35.42694],"type":"Point"}
}