{
  "type": "Feature",
  "properties": {
    "gn:admin1_code":"2.0",
    "gn:admin2_code":"98994.0",
    "gn:asciiname":"Shamli",
    "gn:cc2":"IQ",
    "gn:country_code":"IQ",
    "gn:dem":5,
    "gn:feature_class":"P",
    "gn:feature_code":"PPL",
    "gn:name":"Sh\u0101ml\u012b",
    "gn:population":0,
    "gn:timezone":"Asia/Baghdad",
    "iso:country":"IQ",
    "name:ara_x_preferred":[
        "Sh\u0101ml\u012b"
    ],
    "name:und_x_variant":[
        "Sh\u0101mil"
    ],
    "wof:name":"Shamli",
    "wof:placetype":"locality"
},
  "geometry": {"coordinates":[47.49222,30.93917],"type":"Point"}
}