{
  "type": "Feature",
  "properties": {
    "gn:admin1_code":"2.0",
    "gn:admin2_code":"98994.0",
    "gn:asciiname":"Shamli",
    "gn:cc2":"IQ",
    "gn:country_code":"IQ",
    "gn:dem":5,
    "gn:feature_class":"P",
    "gn:feature_code":"PPL",
    "gn:name":"Sh\u0101ml\u012b",
    "gn:population":0,
    "gn:timezone":"Asia/Baghdad",
    "iso:country":"IQ",
    "name:ara_x_preferred":[
        "Sh\u0101ml\u012b"
    ],
    "name:bih_x_preferred":[
        "\u0936\u093e\u092e\u0932\u0940"
    ],
    "name:bpy_x_preferred":[
        "\u09b6\u09be\u09ae\u09b2\u09bf"
    ],
    "name:cat_x_preferred":[
        "Shamli"
    ],
    "name:ceb_x_preferred":[
        "Sh\u0101mli"
    ],
    "name:fra_x_preferred":[
        "Shamli"
    ],
    "name:guj_x_preferred":[
        "\u0ab6\u0abe\u0aae\u0ab2\u0ac0"
    ],
    "name:hif_x_preferred":[
        "Shamli"
    ],
    "name:hin_x_preferred":[
        "\u0936\u093e\u092e\u0932\u0940"
    ],
    "name:ita_x_preferred":[
        "Shamli"
    ],
    "name:mlg_x_preferred":[
        "Shamli"
    ],
    "name:msa_x_preferred":[
        "Shamli"
    ],
    "name:nld_x_preferred":[
        "Shamli"
    ],
    "name:ori_x_preferred":[
        "\u0b36\u0b3e\u0b2e\u0b33\u0b3f"
    ],
    "name:pnb_x_preferred":[
        "\u0634\u0627\u0645\u0644\u06cc"
    ],
    "name:pol_x_preferred":[
        "Shamli"
    ],
    "name:por_x_preferred":[
        "Shamli"
    ],
    "name:san_x_preferred":[
        "\u0936\u093e\u092e\u0932\u0940"
    ],
    "name:swe_x_preferred":[
        "Shamli"
    ],
    "name:und_x_variant":[
        "Sh\u0101mil"
    ],
    "name:urd_x_preferred":[
        "\u0634\u0627\u0645\u0644\u06cc"
    ],
    "name:vie_x_preferred":[
        "Shamli"
    ],
    "name:zho_x_preferred":[
        "\u65af\u54c8\u59c6\u5229"
    ],
    "wof:name":"Shamli",
    "wof:placetype":"locality"
},
  "geometry": {"coordinates":[47.49222,30.93917],"type":"Point"}
}