{
  "type": "Feature",
  "properties": {
    "gn:admin1_code":"15.0",
    "gn:admin2_code":"99414.0",
    "gn:asciiname":"Bayt Muhammad al Fathwan",
    "gn:country_code":"IQ",
    "gn:dem":230,
    "gn:feature_class":"P",
    "gn:feature_code":"PPL",
    "gn:name":"Bayt Mu\u1e29ammad al Fathw\u0101n",
    "gn:population":0,
    "gn:timezone":"Asia/Baghdad",
    "iso:country":"IQ",
    "name:ara_x_preferred":[
        "\u0628\u064a\u062a \u0645\u062d\u0645\u062f \u0627\u0644\u0641\u062b\u0648\u0627\u0646"
    ],
    "name:und_x_variant":[
        "Bayt Mu\u1e29ammad al Fathw\u0101n"
    ],
    "wof:name":"Bayt Muhammad al Fathwan",
    "wof:placetype":"locality"
},
  "geometry": {"coordinates":[43.01405,35.63435],"type":"Point"}
}