{
  "type": "Feature",
  "properties": {
    "gn:admin1_code":"7.0",
    "gn:asciiname":"`Uwayd Shikhan",
    "gn:country_code":"IQ",
    "gn:dem":34,
    "gn:feature_class":"P",
    "gn:feature_code":"PPL",
    "gn:name":"\u2018Uwayd Sh\u012bkh\u0101n",
    "gn:population":0,
    "gn:timezone":"Asia/Baghdad",
    "iso:country":"IQ",
    "name:ara_x_preferred":[
        "\u0639\u0648\u064a\u062f \u0634\u064a\u062e\u0627\u0646"
    ],
    "name:und_x_variant":[
        "\u2018Uwayd Sh\u012bkh\u0101n"
    ],
    "wof:name":"`Uwayd Shikhan",
    "wof:placetype":"locality"
},
  "geometry": {"coordinates":[44.3801,32.89393],"type":"Point"}
}