{
  "type": "Feature",
  "properties": {
    "gn:admin1_code":"5.0",
    "gn:admin2_code":"9166596.0",
    "gn:asciiname":"Kulkan",
    "gn:country_code":"IQ",
    "gn:dem":576,
    "gn:feature_class":"P",
    "gn:feature_code":"PPL",
    "gn:name":"Kulkan",
    "gn:population":0,
    "gn:timezone":"Asia/Baghdad",
    "iso:country":"IQ",
    "name:kur_x_preferred":[
        "\u0643\u0644\u0643\u0627\u0646"
    ],
    "name:kur_x_variant":[
        "Kilkan",
        "Kulkan",
        "\u0643\u0648\u0644\u0643\u0627\u0646"
    ],
    "name:und_x_variant":[
        "K\u0101lk\u0101n",
        "Kalk\u0101n",
        "Kalkan"
    ],
    "wof:name":"Kulkan",
    "wof:placetype":"locality"
},
  "geometry": {"coordinates":[44.85752,36.08907],"type":"Point"}
}