{
  "type": "Feature",
  "properties": {
    "gn:admin1_code":"11.0",
    "gn:admin2_code":"9166592.0",
    "gn:asciiname":"Sorani Jeri",
    "gn:country_code":"IQ",
    "gn:dem":558,
    "gn:feature_class":"P",
    "gn:feature_code":"PPLL",
    "gn:name":"Soran\u00ee J\u00ear\u00ee",
    "gn:population":0,
    "gn:timezone":"Asia/Baghdad",
    "iso:country":"IQ",
    "name:kur_x_preferred":[
        "Soran\u00ee J\u00ear\u00ee"
    ],
    "name:kur_x_variant":[
        "\u0633\u06c6\u0631\u0627\u0646\u0649 \u0698\u06ce\u0631\u0649"
    ],
    "name:und_x_variant":[
        "Soran Upper"
    ],
    "wof:name":"Sorani Jeri",
    "wof:placetype":"locality"
},
  "geometry": {"coordinates":[44.30325,36.75761],"type":"Point"}
}