{
  "type": "Feature",
  "properties": {
    "gn:admin1_code":"7.0",
    "gn:admin2_code":"99101.0",
    "gn:asciiname":"'Arab Shati Hasan",
    "gn:country_code":"IQ",
    "gn:dem":35,
    "gn:feature_class":"P",
    "gn:feature_code":"PPL",
    "gn:name":"\u2018Arab Sh\u0101\u0163\u012b \u1e28asan",
    "gn:population":0,
    "gn:timezone":"Asia/Baghdad",
    "iso:country":"IQ",
    "name:ara_x_preferred":[
        "\u0639\u0631\u0628 \u0634\u0627\u0637\u064a \u062d\u0633\u0646"
    ],
    "name:und_x_variant":[
        "\u2018Arab Sh\u0101\u0163\u012b \u1e28asan"
    ],
    "wof:name":"'Arab Shati Hasan",
    "wof:placetype":"locality"
},
  "geometry": {"coordinates":[44.34835,33.11607],"type":"Point"}
}