{
  "type": "Feature",
  "properties": {
    "gn:admin1_code":"16.0",
    "gn:admin2_code":"99132.0",
    "gn:asciiname":"Ash Shadi al Awsat",
    "gn:country_code":"IQ",
    "gn:dem":22,
    "gn:feature_class":"P",
    "gn:feature_code":"PPL",
    "gn:name":"Ash Sh\u0101\u1e11\u012b al Awsa\u0163",
    "gn:population":0,
    "gn:timezone":"Asia/Baghdad",
    "iso:country":"IQ",
    "name:ara_x_preferred":[
        "\u0627\u0644\u0634\u0627\u0636\u064a \u0627\u0644\u0623\u0648\u0633\u0637"
    ],
    "name:und_x_variant":[
        "Ash Sh\u0101\u1e11\u012b al Awsa\u0163"
    ],
    "wof:name":"Ash Shadi al Awsat",
    "wof:placetype":"locality"
},
  "geometry": {"coordinates":[45.51232,32.64765],"type":"Point"}
}