{
  "type": "Feature",
  "properties": {
    "gn:admin1_code":"10.0",
    "gn:admin2_code":"9166680.0",
    "gn:asciiname":"'Awad as Suwaylim",
    "gn:country_code":"IQ",
    "gn:dem":59,
    "gn:feature_class":"P",
    "gn:feature_code":"PPL",
    "gn:name":"\u2018Aw\u0101\u1e11 as Suwaylim",
    "gn:population":0,
    "gn:timezone":"Asia/Baghdad",
    "iso:country":"IQ",
    "name:und_x_variant":[
        "\u2018Aw\u0101\u1e11 as Suwaylim"
    ],
    "wof:name":"'Awad as Suwaylim",
    "wof:placetype":"locality"
},
  "geometry": {"coordinates":[45.51667,33.55],"type":"Point"}
}