{
  "type": "Feature",
  "properties": {
    "gn:admin1_code":"4.0",
    "gn:admin2_code":"99763.0",
    "gn:asciiname":"Hunaytil Khadr",
    "gn:country_code":"IQ",
    "gn:dem":22,
    "gn:feature_class":"P",
    "gn:feature_code":"PPL",
    "gn:name":"\u1e28unay\u0163il Kha\u1e11r",
    "gn:population":0,
    "gn:timezone":"Asia/Baghdad",
    "iso:country":"IQ",
    "name:ara_x_preferred":[
        "\u062d\u0646\u064a\u0637\u0644 \u062e\u0636\u0631"
    ],
    "name:und_x_variant":[
        "\u1e28unay\u0163il Kha\u1e11r"
    ],
    "wof:name":"Hunaytil Khadr",
    "wof:placetype":"locality"
},
  "geometry": {"coordinates":[44.96151,31.91723],"type":"Point"}
}