{
  "type": "Feature",
  "properties": {
    "gn:admin1_code":"10.0",
    "gn:admin2_code":"99063.0",
    "gn:asciiname":"Qaryat Salih al Mahdi",
    "gn:country_code":"IQ",
    "gn:dem":49,
    "gn:feature_class":"P",
    "gn:feature_code":"PPL",
    "gn:name":"Qaryat \u015e\u0101li\u1e29 al Mahd\u012b",
    "gn:population":0,
    "gn:timezone":"Asia/Baghdad",
    "iso:country":"IQ",
    "name:ara_x_preferred":[
        "\u0642\u0631\u064a\u0629 \u0635\u0627\u0644\u062d \u0627\u0644\u0645\u0647\u062f\u064a"
    ],
    "name:und_x_variant":[
        "Qaryat \u015e\u0101li\u1e29 al Mahd\u012b"
    ],
    "wof:name":"Qaryat Salih al Mahdi",
    "wof:placetype":"locality"
},
  "geometry": {"coordinates":[45.08412,33.90863],"type":"Point"}
}