{
  "type": "Feature",
  "properties": {
    "gn:admin1_code":"10.0",
    "gn:admin2_code":"9166680.0",
    "gn:asciiname":"Muhammad al Hays",
    "gn:country_code":"IQ",
    "gn:dem":36,
    "gn:feature_class":"P",
    "gn:feature_code":"PPL",
    "gn:name":"Mu\u1e29ammad al Hays",
    "gn:population":0,
    "gn:timezone":"Asia/Baghdad",
    "iso:country":"IQ",
    "name:ara_x_preferred":[
        "\u0645\u062d\u0645\u062f \u0627\u0644\u0647\u064a\u0633"
    ],
    "name:und_x_variant":[
        "Mu\u1e29ammad al Hays"
    ],
    "wof:name":"Muhammad al Hays",
    "wof:placetype":"locality"
},
  "geometry": {"coordinates":[45.35723,33.46226],"type":"Point"}
}