{
  "type": "Feature",
  "properties": {
    "gn:admin1_code":"6.0",
    "gn:admin2_code":"99358.0",
    "gn:asciiname":"Qaryat at Tabu",
    "gn:country_code":"IQ",
    "gn:dem":24,
    "gn:feature_class":"P",
    "gn:feature_code":"PPL",
    "gn:name":"Qaryat a\u0163 \u0162\u0101b\u016b",
    "gn:population":0,
    "gn:timezone":"Asia/Baghdad",
    "iso:country":"IQ",
    "name:ara_x_preferred":[
        "\u0642\u0631\u064a\u0629 \u0627\u0644\u0637\u0627\u0628\u0648"
    ],
    "name:und_x_variant":[
        "Qaryat a\u0163 \u0162\u0101b\u016b"
    ],
    "wof:name":"Qaryat at Tabu",
    "wof:placetype":"locality"
},
  "geometry": {"coordinates":[44.67719,32.2662],"type":"Point"}
}