{
  "type": "Feature",
  "properties": {
    "gn:admin1_code":"5.0",
    "gn:admin2_code":"9166600.0",
    "gn:asciiname":"Xr Punge",
    "gn:country_code":"IQ",
    "gn:dem":325,
    "gn:feature_class":"P",
    "gn:feature_code":"PPL",
    "gn:name":"Xr Punge",
    "gn:population":0,
    "gn:timezone":"Asia/Baghdad",
    "iso:country":"IQ",
    "name:ara_x_preferred":[
        "\u062e\u0631 \u067e\u0648\u0646\u0643\u0644\u0629"
    ],
    "name:ara_x_variant":[
        "\u062e\u0631 \u067e\u0648\u0646\u06af\u0644\u0629"
    ],
    "name:kur_x_preferred":[
        "Xr Punge"
    ],
    "name:kur_x_variant":[
        "\u062e\u0631 \u067e\u0648\u0646\u06af\u06d5"
    ],
    "name:und_x_variant":[
        "Khirr P\u016bnkalah",
        "Khirr P\u016bngalah",
        "Khirpunga"
    ],
    "wof:name":"Xr Punge",
    "wof:placetype":"locality"
},
  "geometry": {"coordinates":[45.20607,34.70803],"type":"Point"}
}