{
  "type": "Feature",
  "properties": {
    "gn:admin1_code":"4.0",
    "gn:admin2_code":"99763.0",
    "gn:asciiname":"Madlul Shukri",
    "gn:country_code":"IQ",
    "gn:dem":24,
    "gn:feature_class":"P",
    "gn:feature_code":"PPL",
    "gn:name":"Madl\u016bl Shukr\u012b",
    "gn:population":0,
    "gn:timezone":"Asia/Baghdad",
    "iso:country":"IQ",
    "name:ara_x_preferred":[
        "\u0645\u062f\u0644\u0648\u0644 \u0634\u0643\u0631\u064a"
    ],
    "name:und_x_variant":[
        "Madl\u016bl Shukr\u012b"
    ],
    "wof:name":"Madlul Shukri",
    "wof:placetype":"locality"
},
  "geometry": {"coordinates":[44.7186,32.08417],"type":"Point"}
}