{
  "type": "Feature",
  "properties": {
    "gn:admin1_code":"14.0",
    "gn:admin2_code":"9166557.0",
    "gn:asciiname":"Finjan",
    "gn:cc2":"IQ",
    "gn:country_code":"IQ",
    "gn:dem":9,
    "gn:feature_class":"P",
    "gn:feature_code":"PPL",
    "gn:name":"Finj\u0101n",
    "gn:population":0,
    "gn:timezone":"Asia/Baghdad",
    "iso:country":"IQ",
    "name:ara_x_preferred":[
        "Finj\u0101n"
    ],
    "name:und_x_variant":[
        "Finj\u0101r",
        "Furayj\u0101n"
    ],
    "wof:name":"Finjan",
    "wof:placetype":"locality"
},
  "geometry": {"coordinates":[47.36111,31.63639],"type":"Point"}
}