{
  "type": "Feature",
  "properties": {
    "gn:admin1_code":"5.0",
    "gn:admin2_code":"92743.0",
    "gn:asciiname":"Gush",
    "gn:country_code":"IQ",
    "gn:dem":789,
    "gn:feature_class":"P",
    "gn:feature_code":"PPL",
    "gn:name":"Gush",
    "gn:population":0,
    "gn:timezone":"Asia/Baghdad",
    "iso:country":"IQ",
    "name:fas_x_preferred":[
        "\u06af\u0648\u0634"
    ],
    "name:heb_x_preferred":[
        "\u05d2\u05d5\u05e9"
    ],
    "name:kur_x_preferred":[
        "Gush"
    ],
    "name:kur_x_variant":[
        "\u06af\u0648\u0634"
    ],
    "name:und_x_variant":[
        "Gush Gush"
    ],
    "wof:name":"Gush",
    "wof:placetype":"locality"
},
  "geometry": {"coordinates":[45.17456,36.19201],"type":"Point"}
}