{
  "type": "Feature",
  "properties": {
    "gn:admin1_code":"16.0",
    "gn:admin2_code":"9166961.0",
    "gn:asciiname":"Tall Jamilah",
    "gn:country_code":"IQ",
    "gn:dem":27,
    "gn:feature_class":"P",
    "gn:feature_code":"PPL",
    "gn:name":"Tall Jam\u012blah",
    "gn:population":0,
    "gn:timezone":"Asia/Baghdad",
    "iso:country":"IQ",
    "name:ara_x_preferred":[
        "\u062a\u0644 \u062c\u0645\u064a\u0644\u0629"
    ],
    "name:und_x_variant":[
        "Tall Jam\u012blah"
    ],
    "wof:name":"Tall Jamilah",
    "wof:placetype":"locality"
},
  "geometry": {"coordinates":[44.90596,32.94239],"type":"Point"}
}