{
  "type": "Feature",
  "properties": {
    "gn:admin1_code":"10.0",
    "gn:admin2_code":"99063.0",
    "gn:asciiname":"Qaryat Mulla Jawad",
    "gn:country_code":"IQ",
    "gn:dem":56,
    "gn:feature_class":"P",
    "gn:feature_code":"PPL",
    "gn:name":"Qaryat Mull\u0101 Jaw\u0101d",
    "gn:population":0,
    "gn:timezone":"Asia/Baghdad",
    "iso:country":"IQ",
    "name:ara_x_preferred":[
        "\u0642\u0631\u064a\u0629 \u0645\u0644\u0627 \u062c\u0648\u0627\u062f"
    ],
    "name:und_x_variant":[
        "Qaryat Mull\u0101 Jaw\u0101d"
    ],
    "wof:name":"Qaryat Mulla Jawad",
    "wof:placetype":"locality"
},
  "geometry": {"coordinates":[44.85863,33.89595],"type":"Point"}
}