{
  "type": "Feature",
  "properties": {
    "gn:admin1_code":"10.0",
    "gn:admin2_code":"94590.0",
    "gn:asciiname":"Amin Agha",
    "gn:country_code":"IQ",
    "gn:dem":187,
    "gn:feature_class":"P",
    "gn:feature_code":"PPL",
    "gn:name":"Am\u012bn \u0100gh\u0101",
    "gn:population":0,
    "gn:timezone":"Asia/Baghdad",
    "iso:country":"IQ",
    "name:ara_x_preferred":[
        "Am\u012bn \u0100gh\u0101"
    ],
    "name:ara_x_variant":[
        "\u0627\u0645\u064a\u0646 \u0622\u063a\u0627"
    ],
    "wof:name":"Amin Agha",
    "wof:placetype":"locality"
},
  "geometry": {"coordinates":[45.2933,34.52892],"type":"Point"}
}