{
  "type": "Feature",
  "properties": {
    "gn:admin1_code":"8.0",
    "gn:admin2_code":"9166607.0",
    "gn:asciiname":"Hamjiky",
    "gn:country_code":"IQ",
    "gn:dem":734,
    "gn:feature_class":"P",
    "gn:feature_code":"PPL",
    "gn:name":"Hamjiky",
    "gn:population":0,
    "gn:timezone":"Asia/Baghdad",
    "iso:country":"IQ",
    "name:ara_x_preferred":[
        "\u062d\u0645\u062c\u064a\u0643\u064a"
    ],
    "name:kur_x_preferred":[
        "\u1e26emc\u00eek\u00ee"
    ],
    "name:kur_x_variant":[
        "\u062d\u06d5\u0645\u062c\u064a\u0643\u0649"
    ],
    "name:und_x_variant":[
        "Hajm\u012bz\u012b",
        "\u0647\u062c\u0645\u064a\u0632\u064a",
        "\u1e28amj\u012bk\u012b"
    ],
    "wof:name":"Hamjiky",
    "wof:placetype":"locality"
},
  "geometry": {"coordinates":[42.87779000000001,36.9355],"type":"Point"}
}