{
  "type": "Feature",
  "properties": {
    "gn:admin1_code":"6.0",
    "gn:admin2_code":"6818313.0",
    "gn:asciiname":"Nasir Muhsin",
    "gn:country_code":"IQ",
    "gn:dem":29,
    "gn:feature_class":"P",
    "gn:feature_code":"PPL",
    "gn:name":"N\u0101\u015fir Mu\u1e29sin",
    "gn:population":0,
    "gn:timezone":"Asia/Baghdad",
    "iso:country":"IQ",
    "name:ara_x_preferred":[
        "\u0646\u0627\u0635\u0631 \u0645\u062d\u0633\u0646"
    ],
    "name:ara_x_variant":[
        "N\u0101\u015fir Mu\u1e29sin"
    ],
    "wof:name":"Nasir Muhsin",
    "wof:placetype":"locality"
},
  "geometry": {"coordinates":[44.68043,32.66925999999999],"type":"Point"}
}