{
  "type": "Feature",
  "properties": {
    "gn:admin1_code":"10.0",
    "gn:admin2_code":"9166680.0",
    "gn:asciiname":"Jasim Khashf",
    "gn:country_code":"IQ",
    "gn:dem":40,
    "gn:feature_class":"P",
    "gn:feature_code":"PPL",
    "gn:name":"J\u0101sim Khashf",
    "gn:population":0,
    "gn:timezone":"Asia/Baghdad",
    "iso:country":"IQ",
    "name:ara_x_preferred":[
        "\u062c\u0627\u0633\u0645 \u062e\u0634\u0641"
    ],
    "name:und_x_variant":[
        "J\u0101sim Khashf"
    ],
    "wof:name":"Jasim Khashf",
    "wof:placetype":"locality"
},
  "geometry": {"coordinates":[44.88117,33.539],"type":"Point"}
}