{
  "type": "Feature",
  "properties": {
    "gn:admin1_code":"5.0",
    "gn:admin2_code":"92743.0",
    "gn:asciiname":"Berbine",
    "gn:country_code":"IQ",
    "gn:dem":891,
    "gn:feature_class":"P",
    "gn:feature_code":"PPL",
    "gn:name":"Berbine",
    "gn:population":0,
    "gn:timezone":"Asia/Baghdad",
    "iso:country":"IQ",
    "name:ara_x_preferred":[
        "\u0628\u0627\u0631\u0628\u0646\u0629"
    ],
    "name:kur_x_preferred":[
        "Berbine"
    ],
    "name:kur_x_variant":[
        "\u0628\u06d5\u0631\u0628\u0646\u06d5"
    ],
    "name:und_x_variant":[
        "B\u0101rbinah",
        "Barb\u0101na",
        "Barbna",
        "Barbana"
    ],
    "wof:name":"Berbine",
    "wof:placetype":"locality"
},
  "geometry": {"coordinates":[45.23148,36.13977],"type":"Point"}
}