{
  "type": "Feature",
  "properties": {
    "gn:admin1_code":"18.0",
    "gn:admin2_code":"6872046.0",
    "gn:asciiname":"Qaryat 'Atiq",
    "gn:country_code":"IQ",
    "gn:dem":135,
    "gn:feature_class":"P",
    "gn:feature_code":"PPL",
    "gn:name":"Qaryat \u2018At\u012bq",
    "gn:population":0,
    "gn:timezone":"Asia/Baghdad",
    "iso:country":"IQ",
    "name:und_x_variant":[
        "Qaryah At\u012bf",
        "Qaryat \u2018A\u0163\u012bj",
        "Qaryat Atif",
        "Qaryat \u2018At\u012bq"
    ],
    "wof:name":"Qaryat 'Atiq",
    "wof:placetype":"locality"
},
  "geometry": {"coordinates":[43.405,35.26306],"type":"Point"}
}