{
  "type": "Feature",
  "properties": {
    "gn:admin1_code":"4.0",
    "gn:admin2_code":"6850588.0",
    "gn:asciiname":"Ahar al 'Awdah",
    "gn:country_code":"IQ",
    "gn:dem":16,
    "gn:feature_class":"P",
    "gn:feature_code":"PPL",
    "gn:name":"Ahar al \u2018Awdah",
    "gn:population":0,
    "gn:timezone":"Asia/Baghdad",
    "iso:country":"IQ",
    "name:ara_x_preferred":[
        "\u0627\u0647\u0631 \u0627\u0644\u0639\u0648\u062f\u0647"
    ],
    "name:und_x_variant":[
        "Ahar al \u2018Awdah"
    ],
    "wof:name":"Ahar al 'Awdah",
    "wof:placetype":"locality"
},
  "geometry": {"coordinates":[44.72292,31.47145],"type":"Point"}
}