{
  "type": "Feature",
  "properties": {
    "gn:admin1_code":"11.0",
    "gn:admin2_code":"9166591.0",
    "gn:asciiname":"Banaman",
    "gn:country_code":"IQ",
    "gn:dem":742,
    "gn:feature_class":"P",
    "gn:feature_code":"PPL",
    "gn:name":"B\u0101n\u0101m\u0101n",
    "gn:population":0,
    "gn:timezone":"Asia/Baghdad",
    "iso:country":"IQ",
    "name:ara_x_preferred":[
        "\u0628\u0627\u0646\u0627\u0645\u0627\u0646"
    ],
    "name:ara_x_variant":[
        "B\u0101n\u0101m\u0101n"
    ],
    "wof:name":"Banaman",
    "wof:placetype":"locality"
},
  "geometry": {"coordinates":[44.18113,36.35572],"type":"Point"}
}