{
  "type": "Feature",
  "properties": {
    "gn:admin1_code":"6.0",
    "gn:admin2_code":"99358.0",
    "gn:asciiname":"Hasan Fursan",
    "gn:country_code":"IQ",
    "gn:dem":26,
    "gn:feature_class":"P",
    "gn:feature_code":"PPL",
    "gn:name":"\u1e28asan Furs\u0101n",
    "gn:population":0,
    "gn:timezone":"Asia/Baghdad",
    "iso:country":"IQ",
    "name:ara_x_preferred":[
        "\u062d\u0633\u0646 \u0641\u0631\u0633\u0627\u0646"
    ],
    "name:und_x_variant":[
        "\u1e28asan Furs\u0101n"
    ],
    "wof:name":"Hasan Fursan",
    "wof:placetype":"locality"
},
  "geometry": {"coordinates":[44.75202,32.32532],"type":"Point"}
}