{
  "type": "Feature",
  "properties": {
    "gn:admin1_code":"18.0",
    "gn:admin2_code":"6783103.0",
    "gn:asciiname":"Qaryat Tall Kusaybah",
    "gn:country_code":"IQ",
    "gn:dem":118,
    "gn:feature_class":"P",
    "gn:feature_code":"PPL",
    "gn:name":"Qaryat Tall Ku\u015faybah",
    "gn:population":0,
    "gn:timezone":"Asia/Baghdad",
    "iso:country":"IQ",
    "name:ara_x_preferred":[
        "\u0642\u0631\u064a\u0629 \u062a\u0644 \u06a9\u0635\u064a\u0628\u0629"
    ],
    "name:und_x_variant":[
        "Qaryat Tall Ku\u015faybah"
    ],
    "wof:name":"Qaryat Tall Kusaybah",
    "wof:placetype":"locality"
},
  "geometry": {"coordinates":[44.067,34.69382],"type":"Point"}
}