{
  "type": "Feature",
  "properties": {
    "gn:admin1_code":"3.0",
    "gn:admin2_code":"9166568.0",
    "gn:asciiname":"Qaryat al Barid",
    "gn:country_code":"IQ",
    "gn:dem":16,
    "gn:feature_class":"P",
    "gn:feature_code":"PPL",
    "gn:name":"Qaryat al B\u0101rid",
    "gn:population":0,
    "gn:timezone":"Asia/Baghdad",
    "iso:country":"IQ",
    "name:ara_x_preferred":[
        "\u0642\u0631\u064a\u0629 \u0627\u0644\u0628\u0627\u0631\u062f"
    ],
    "name:und_x_variant":[
        "Qaryat al B\u0101rid"
    ],
    "wof:name":"Qaryat al Barid",
    "wof:placetype":"locality"
},
  "geometry": {"coordinates":[45.10059,31.42815],"type":"Point"}
}