{
  "type": "Feature",
  "properties": {
    "gn:admin1_code":"14.0",
    "gn:admin2_code":"9166562.0",
    "gn:asciiname":"Tall ash Shaziriyah",
    "gn:country_code":"IQ",
    "gn:dem":8,
    "gn:feature_class":"P",
    "gn:feature_code":"PPL",
    "gn:name":"Tall ash Shaz\u012br\u012byah",
    "gn:population":0,
    "gn:timezone":"Asia/Baghdad",
    "iso:country":"IQ",
    "name:ara_x_preferred":[
        "\u062a\u0644 \u0627\u0644\u0634\u0632\u064a\u0631\u064a\u0647"
    ],
    "name:und_x_variant":[
        "Tall ash Shaz\u012br\u012byah"
    ],
    "wof:name":"Tall ash Shaziriyah",
    "wof:placetype":"locality"
},
  "geometry": {"coordinates":[46.91363,31.68807],"type":"Point"}
}