{
  "type": "Feature",
  "properties": {
    "gn:admin1_code":"14.0",
    "gn:admin2_code":"99097.0",
    "gn:asciiname":"Bustan Salman",
    "gn:country_code":"IQ",
    "gn:dem":8,
    "gn:feature_class":"P",
    "gn:feature_code":"PPL",
    "gn:name":"Bust\u0101n Salm\u0101n",
    "gn:population":0,
    "gn:timezone":"Asia/Baghdad",
    "iso:country":"IQ",
    "name:ara_x_preferred":[
        "\u0628\u0633\u062a\u0627\u0646 \u0633\u0644\u0645\u0627\u0646"
    ],
    "name:und_x_variant":[
        "Bust\u0101n Salm\u0101n"
    ],
    "wof:name":"Bustan Salman",
    "wof:placetype":"locality"
},
  "geometry": {"coordinates":[47.17306,31.48578],"type":"Point"}
}