{
  "type": "Feature",
  "properties": {
    "gn:admin1_code":"3.0",
    "gn:admin2_code":"9166568.0",
    "gn:asciiname":"Qal'at 'Azuz",
    "gn:country_code":"IQ",
    "gn:dem":15,
    "gn:feature_class":"P",
    "gn:feature_code":"PPL",
    "gn:name":"Qal\u2018at \u2018Az\u016bz",
    "gn:population":0,
    "gn:timezone":"Asia/Baghdad",
    "iso:country":"IQ",
    "name:ara_x_preferred":[
        "\u0642\u0644\u0639\u0629 \u0639\u0632\u0648\u0632"
    ],
    "name:und_x_variant":[
        "Qal\u2018at \u2018Az\u016bz"
    ],
    "wof:name":"Qal'at 'Azuz",
    "wof:placetype":"locality"
},
  "geometry": {"coordinates":[45.28198,31.55469],"type":"Point"}
}