{
  "type": "Feature",
  "properties": {
    "gn:admin1_code":"6.0",
    "gn:admin2_code":"6818313.0",
    "gn:asciiname":"Zughayr Hamzah",
    "gn:country_code":"IQ",
    "gn:dem":31,
    "gn:feature_class":"P",
    "gn:feature_code":"PPL",
    "gn:name":"Zughayr \u1e28amzah",
    "gn:population":0,
    "gn:timezone":"Asia/Baghdad",
    "iso:country":"IQ",
    "name:ara_x_preferred":[
        "\u0632\u063a\u064a\u0631 \u062d\u0645\u0632\u0629"
    ],
    "name:und_x_variant":[
        "Zughayr \u1e28amzah"
    ],
    "wof:name":"Zughayr Hamzah",
    "wof:placetype":"locality"
},
  "geometry": {"coordinates":[44.5317,32.61471],"type":"Point"}
}