{
  "type": "Feature",
  "properties": {
    "gn:admin1_code":"10.0",
    "gn:admin2_code":"9166680.0",
    "gn:asciiname":"'Ulaywi Khamis",
    "gn:country_code":"IQ",
    "gn:dem":45,
    "gn:feature_class":"P",
    "gn:feature_code":"PPL",
    "gn:name":"\u2018Ulayw\u012b Kham\u012bs",
    "gn:population":0,
    "gn:timezone":"Asia/Baghdad",
    "iso:country":"IQ",
    "name:ara_x_preferred":[
        "\u0639\u0644\u064a\u0648\u064a \u062e\u0645\u064a\u0633"
    ],
    "name:und_x_variant":[
        "\u2018Ulayw\u012b al Kham\u012bs",
        "\u2018Ulayw\u012b Kham\u012bs"
    ],
    "wof:name":"'Ulaywi Khamis",
    "wof:placetype":"locality"
},
  "geometry": {"coordinates":[44.69598,33.56877],"type":"Point"}
}