{
  "type": "Feature",
  "properties": {
    "gn:admin1_code":"15.0",
    "gn:admin2_code":"9166620.0",
    "gn:asciiname":"'Ayn Fathi",
    "gn:country_code":"IQ",
    "gn:dem":397,
    "gn:feature_class":"P",
    "gn:feature_code":"PPL",
    "gn:name":"\u2018Ayn Fat\u1e29\u012b",
    "gn:population":0,
    "gn:timezone":"Asia/Baghdad",
    "iso:country":"IQ",
    "name:ara_x_preferred":[
        "\u0639\u064a\u0646 \u0641\u062a\u062d\u064a"
    ],
    "name:und_x_variant":[
        "\u2018Ayn Fat\u1e29\u012b"
    ],
    "wof:name":"'Ayn Fathi",
    "wof:placetype":"locality"
},
  "geometry": {"coordinates":[41.95355,36.25089000000001],"type":"Point"}
}