{
  "type": "Feature",
  "properties": {
    "gn:admin1_code":"3.0",
    "gn:admin2_code":"9166626.0",
    "gn:asciiname":"Nayif Al 'Ajil",
    "gn:country_code":"IQ",
    "gn:dem":8,
    "gn:feature_class":"P",
    "gn:feature_code":"PPL",
    "gn:name":"N\u0101yif \u0100l \u2018Aj\u012bl",
    "gn:population":0,
    "gn:timezone":"Asia/Baghdad",
    "iso:country":"IQ",
    "name:ara_x_preferred":[
        "\u0646\u0627\u064a\u0641 \u0622\u0644 \u0639\u062c\u064a\u0644"
    ],
    "name:ara_x_variant":[
        "N\u0101yif \u0100l \u2018Aj\u012bl"
    ],
    "name:und_x_variant":[
        "N\u0101\u2019if",
        "N\u0101\u2019if al \u2018\u0100jil"
    ],
    "wof:name":"Nayif Al 'Ajil",
    "wof:placetype":"locality"
},
  "geometry": {"coordinates":[45.77476,31.15713],"type":"Point"}
}