{
  "type": "Feature",
  "properties": {
    "gn:admin1_code":"10.0",
    "gn:admin2_code":"9166680.0",
    "gn:asciiname":"'Arab al Husayniyah",
    "gn:country_code":"IQ",
    "gn:dem":43,
    "gn:feature_class":"P",
    "gn:feature_code":"PPL",
    "gn:name":"\u2018Arab al \u1e28usayn\u012byah",
    "gn:population":0,
    "gn:timezone":"Asia/Baghdad",
    "iso:country":"IQ",
    "name:ara_x_preferred":[
        "\u0639\u0631\u0628 \u0627\u0644\u062d\u0633\u064a\u0646\u064a\u0629"
    ],
    "name:und_x_variant":[
        "\u2018Arab al \u1e28usayn\u012byah"
    ],
    "wof:name":"'Arab al Husayniyah",
    "wof:placetype":"locality"
},
  "geometry": {"coordinates":[44.62488,33.54711],"type":"Point"}
}