{
  "type": "Feature",
  "properties": {
    "gn:admin1_code":"14.0",
    "gn:admin2_code":"92536.0",
    "gn:asciiname":"Al Hafliyah",
    "gn:country_code":"IQ",
    "gn:dem":6,
    "gn:feature_class":"P",
    "gn:feature_code":"PPL",
    "gn:name":"Al \u1e28afl\u012byah",
    "gn:population":0,
    "gn:timezone":"Asia/Baghdad",
    "iso:country":"IQ",
    "name:ara_x_preferred":[
        "\u0627\u0644\u062d\u0641\u0644\u064a\u0629"
    ],
    "name:und_x_variant":[
        "Al \u1e28afl\u012byah"
    ],
    "wof:name":"Al Hafliyah",
    "wof:placetype":"locality"
},
  "geometry": {"coordinates":[47.33534,31.4926],"type":"Point"}
}