{
  "type": "Feature",
  "properties": {
    "gn:admin1_code":"13.0",
    "gn:admin2_code":"6770659.0",
    "gn:asciiname":"Mashru' al Hawijah",
    "gn:country_code":"IQ",
    "gn:dem":181,
    "gn:feature_class":"P",
    "gn:feature_code":"PPL",
    "gn:name":"Mashr\u016b\u2018 al \u1e28aw\u012bjah",
    "gn:population":0,
    "gn:timezone":"Asia/Baghdad",
    "iso:country":"IQ",
    "name:ara_x_preferred":[
        "\u0645\u0634\u0631\u0648\u0639 \u0627\u0644\u062d\u0648\u064a\u062c\u0629"
    ],
    "name:und_x_variant":[
        "Mashr\u016b\u2018 al \u1e28aw\u012bjah"
    ],
    "wof:name":"Mashru' al Hawijah",
    "wof:placetype":"locality"
},
  "geometry": {"coordinates":[43.88162,35.22029000000001],"type":"Point"}
}