{
  "type": "Feature",
  "properties": {
    "gn:admin1_code":"6.0",
    "gn:admin2_code":"99040.0",
    "gn:asciiname":"Husayn Hamud",
    "gn:country_code":"IQ",
    "gn:dem":36,
    "gn:feature_class":"P",
    "gn:feature_code":"PPL",
    "gn:name":"\u1e28usayn \u1e28am\u016bd",
    "gn:population":0,
    "gn:timezone":"Asia/Baghdad",
    "iso:country":"IQ",
    "name:ara_x_preferred":[
        "\u062d\u0633\u064a\u0646 \u062d\u0645\u0648\u062f"
    ],
    "name:und_x_variant":[
        "\u1e28usayn al \u1e28am\u0101d\u012b",
        "\u1e28usayn \u1e28amm\u016bd",
        "\u1e28usayn \u1e28am\u016bd"
    ],
    "wof:name":"Husayn Hamud",
    "wof:placetype":"locality"
},
  "geometry": {"coordinates":[44.18826,32.88723],"type":"Point"}
}