{
  "type": "Feature",
  "properties": {
    "gn:admin1_code":"7.0",
    "gn:admin2_code":"9179819.0",
    "gn:asciiname":"Rashid Hajji Hamid",
    "gn:country_code":"IQ",
    "gn:dem":32,
    "gn:feature_class":"P",
    "gn:feature_code":"PPL",
    "gn:name":"Rash\u012bd \u1e28\u0101jj\u012b \u1e28am\u012bd",
    "gn:population":0,
    "gn:timezone":"Asia/Baghdad",
    "iso:country":"IQ",
    "name:und_x_variant":[
        "Rash\u012bd H\u0101ji Ham\u012bd",
        "Rash\u012bd \u1e28\u0101jj\u012b \u1e28am\u012bd"
    ],
    "wof:name":"Rashid Hajji Hamid",
    "wof:placetype":"locality"
},
  "geometry": {"coordinates":[44.73333,33.03333],"type":"Point"}
}