{
  "type": "Feature",
  "properties": {
    "gn:admin1_code":"6.0",
    "gn:admin2_code":"99348.0",
    "gn:asciiname":"Hajji 'Abd as Sayyid",
    "gn:country_code":"IQ",
    "gn:dem":31,
    "gn:feature_class":"P",
    "gn:feature_code":"PPL",
    "gn:name":"\u1e28\u0101jj\u012b \u2018Abd as Sayyid",
    "gn:population":0,
    "gn:timezone":"Asia/Baghdad",
    "iso:country":"IQ",
    "name:und_x_variant":[
        "Al \u1e28ajj \u2018Abd as Sayyid",
        "\u1e28\u0101jj\u012b \u2018Abd as Sayyid"
    ],
    "wof:name":"Hajji 'Abd as Sayyid",
    "wof:placetype":"locality"
},
  "geometry": {"coordinates":[44.31667,32.33333],"type":"Point"}
}