{
  "type": "Feature",
  "properties": {
    "gn:admin1_code":"4.0",
    "gn:admin2_code":"99737.0",
    "gn:asciiname":"Maftul Umm Kaynah",
    "gn:country_code":"IQ",
    "gn:dem":14,
    "gn:feature_class":"P",
    "gn:feature_code":"PPL",
    "gn:name":"Maft\u016bl Umm Kaynah",
    "gn:population":0,
    "gn:timezone":"Asia/Baghdad",
    "iso:country":"IQ",
    "name:ara_x_preferred":[
        "\u0645\u0641\u062a\u0648\u0644 \u0627\u0645 \u0643\u064a\u0646\u0629"
    ],
    "name:und_x_variant":[
        "Maft\u016bl Umm Kaynah"
    ],
    "wof:name":"Maftul Umm Kaynah",
    "wof:placetype":"locality"
},
  "geometry": {"coordinates":[45.46019,31.80623],"type":"Point"}
}