{
  "type": "Feature",
  "properties": {
    "gn:admin1_code":"5.0",
    "gn:admin2_code":"9166684.0",
    "gn:asciiname":"Waliyawa",
    "gn:country_code":"IQ",
    "gn:dem":1259,
    "gn:feature_class":"P",
    "gn:feature_code":"PPL",
    "gn:name":"Waliy\u0101wa",
    "gn:population":0,
    "gn:timezone":"Asia/Baghdad",
    "iso:country":"IQ",
    "name:fas_x_preferred":[
        "\u0648\u0644\u06cc\u0627\u0648\u0647"
    ],
    "name:fas_x_variant":[
        "Val\u012b\u0101veh"
    ],
    "name:kur_x_preferred":[
        "A\u0142yawa"
    ],
    "name:kur_x_variant":[
        "\u0626\u0627\u06b5\u064a\u0627\u0648\u0627"
    ],
    "name:und_x_variant":[
        "Waliy\u0101wa"
    ],
    "wof:name":"Waliyawa",
    "wof:placetype":"locality"
},
  "geometry": {"coordinates":[45.982,35.6319],"type":"Point"}
}