{
  "type": "Feature",
  "properties": {
    "gn:admin1_code":"6.0",
    "gn:admin2_code":"6818313.0",
    "gn:asciiname":"Su'aydat",
    "gn:country_code":"IQ",
    "gn:dem":26,
    "gn:feature_class":"P",
    "gn:feature_code":"PPL",
    "gn:name":"Su\u2018ayd\u0101t",
    "gn:population":0,
    "gn:timezone":"Asia/Baghdad",
    "iso:country":"IQ",
    "name:ara_x_preferred":[
        "\u0633\u0639\u064a\u062f\u0627\u062a"
    ],
    "name:und_x_variant":[
        "Su\u2018ayd\u0101t"
    ],
    "wof:name":"Su'aydat",
    "wof:placetype":"locality"
},
  "geometry": {"coordinates":[44.81134,32.4606],"type":"Point"}
}