{
  "type": "Feature",
  "properties": {
    "gn:admin1_code":"18.0",
    "gn:admin2_code":"91594.0",
    "gn:asciiname":"Tayat Muhammad",
    "gn:country_code":"IQ",
    "gn:dem":119,
    "gn:feature_class":"P",
    "gn:feature_code":"PPL",
    "gn:name":"T\u0101yat Mu\u1e29ammad",
    "gn:population":0,
    "gn:timezone":"Asia/Baghdad",
    "iso:country":"IQ",
    "name:ara_x_preferred":[
        "\u062a\u0627\u064a\u0629 \u0645\u062d\u0645\u062f"
    ],
    "name:und_x_variant":[
        "T\u0101yat Mu\u1e29ammad"
    ],
    "wof:name":"Tayat Muhammad",
    "wof:placetype":"locality"
},
  "geometry": {"coordinates":[43.26808,34.31910999999999],"type":"Point"}
}