{
  "type": "Feature",
  "properties": {
    "gn:admin1_code":"6.0",
    "gn:admin2_code":"6818313.0",
    "gn:asciiname":"Talib Kamar",
    "gn:country_code":"IQ",
    "gn:dem":30,
    "gn:feature_class":"P",
    "gn:feature_code":"PPL",
    "gn:name":"\u0162\u0101lib Kamar",
    "gn:population":0,
    "gn:timezone":"Asia/Baghdad",
    "iso:country":"IQ",
    "name:ara_x_preferred":[
        "\u0637\u0627\u0644\u0628 \u0643\u0645\u0631"
    ],
    "name:und_x_variant":[
        "\u0162\u0101lib Kamar"
    ],
    "wof:name":"Talib Kamar",
    "wof:placetype":"locality"
},
  "geometry": {"coordinates":[44.46363,32.64977],"type":"Point"}
}