{
  "type": "Feature",
  "properties": {
    "gn:admin1_code":"4.0",
    "gn:admin2_code":"99763.0",
    "gn:asciiname":"'Abd Nur 'Abd",
    "gn:country_code":"IQ",
    "gn:dem":24,
    "gn:feature_class":"P",
    "gn:feature_code":"PPL",
    "gn:name":"\u2018Abd N\u016br \u2018Abd",
    "gn:population":0,
    "gn:timezone":"Asia/Baghdad",
    "iso:country":"IQ",
    "name:ara_x_preferred":[
        "\u0639\u0628\u062f \u0646\u0648\u0631 \u0639\u0628\u062f"
    ],
    "name:ara_x_variant":[
        "\u2018Abd N\u016br \u2018Abd"
    ],
    "wof:name":"'Abd Nur 'Abd",
    "wof:placetype":"locality"
},
  "geometry": {"coordinates":[44.6281,32.05323],"type":"Point"}
}