{
  "type": "Feature",
  "properties": {
    "gn:admin1_code":"6.0",
    "gn:admin2_code":"99358.0",
    "gn:asciiname":"Husayn Haras",
    "gn:country_code":"IQ",
    "gn:dem":25,
    "gn:feature_class":"P",
    "gn:feature_code":"PPL",
    "gn:name":"\u1e28usayn \u1e28aras",
    "gn:population":0,
    "gn:timezone":"Asia/Baghdad",
    "iso:country":"IQ",
    "name:ara_x_preferred":[
        "\u062d\u0633\u064a\u0646 \u062d\u0631\u0633"
    ],
    "name:und_x_variant":[
        "\u1e28usayn \u1e28aras"
    ],
    "wof:name":"Husayn Haras",
    "wof:placetype":"locality"
},
  "geometry": {"coordinates":[44.96753,32.38543],"type":"Point"}
}