{
  "type": "Feature",
  "properties": {
    "gn:admin1_code":"15.0",
    "gn:admin2_code":"9166620.0",
    "gn:asciiname":"Hariku",
    "gn:country_code":"IQ",
    "gn:dem":457,
    "gn:feature_class":"P",
    "gn:feature_code":"PPL",
    "gn:name":"Har\u012bk\u016b",
    "gn:population":0,
    "gn:timezone":"Asia/Baghdad",
    "iso:country":"IQ",
    "name:ara_x_preferred":[
        "\u0647\u0631\u064a\u0643\u0648"
    ],
    "name:und_x_variant":[
        "Har\u012bk\u016b"
    ],
    "wof:name":"Hariku",
    "wof:placetype":"locality"
},
  "geometry": {"coordinates":[41.9699,36.51538],"type":"Point"}
}