{
  "type": "Feature",
  "properties": {
    "gn:admin1_code":"6.0",
    "gn:admin2_code":"99358.0",
    "gn:asciiname":"Sayyid Badi",
    "gn:country_code":"IQ",
    "gn:dem":26,
    "gn:feature_class":"P",
    "gn:feature_code":"PPL",
    "gn:name":"Sayyid B\u0101d\u012b",
    "gn:population":0,
    "gn:timezone":"Asia/Baghdad",
    "iso:country":"IQ",
    "name:ara_x_preferred":[
        "\u0633\u064a\u062f \u0628\u0627\u062f\u064a"
    ],
    "name:und_x_variant":[
        "Sayyid B\u0101d\u012b"
    ],
    "wof:name":"Sayyid Badi",
    "wof:placetype":"locality"
},
  "geometry": {"coordinates":[44.86043,32.364],"type":"Point"}
}