{
  "type": "Feature",
  "properties": {
    "gn:admin1_code":"7.0",
    "gn:admin2_code":"9166569.0",
    "gn:asciiname":"Ahmad al 'Amari",
    "gn:country_code":"IQ",
    "gn:dem":41,
    "gn:feature_class":"P",
    "gn:feature_code":"PPL",
    "gn:name":"A\u1e29mad al \u2018Am\u0101r\u012b",
    "gn:population":0,
    "gn:timezone":"Asia/Baghdad",
    "iso:country":"IQ",
    "name:ara_x_preferred":[
        "\u0627\u062d\u0645\u062f \u0627\u0644\u0639\u0645\u0627\u0631\u064a"
    ],
    "name:und_x_variant":[
        "A\u1e29mad al \u2018Am\u0101r\u012b"
    ],
    "wof:name":"Ahmad al 'Amari",
    "wof:placetype":"locality"
},
  "geometry": {"coordinates":[44.38465,33.62730999999999],"type":"Point"}
}