{
  "type": "Feature",
  "properties": {
    "gn:admin1_code":"14.0",
    "gn:admin2_code":"99610.0",
    "gn:asciiname":"Tall ad Dukhkhan",
    "gn:country_code":"IQ",
    "gn:dem":8,
    "gn:feature_class":"P",
    "gn:feature_code":"PPL",
    "gn:name":"Tall ad Dukhkh\u0101n",
    "gn:population":0,
    "gn:timezone":"Asia/Baghdad",
    "iso:country":"IQ",
    "name:und_x_variant":[
        "Tall ad Dukhkh\u0101n"
    ],
    "wof:name":"Tall ad Dukhkhan",
    "wof:placetype":"locality"
},
  "geometry": {"coordinates":[47.3075,31.80028],"type":"Point"}
}