{
  "type": "Feature",
  "properties": {
    "gn:admin1_code":"5.0",
    "gn:admin2_code":"97416.0",
    "gn:asciiname":"Bakr Bajlan",
    "gn:country_code":"IQ",
    "gn:dem":520,
    "gn:feature_class":"P",
    "gn:feature_code":"PPL",
    "gn:name":"Bakr B\u0101jl\u0101n",
    "gn:population":0,
    "gn:timezone":"Asia/Baghdad",
    "iso:country":"IQ",
    "name:ara_x_preferred":[
        "\u0628\u0643\u0631 \u0628\u0627\u062c\u0644\u0627\u0646"
    ],
    "name:und_x_variant":[
        "Bakr B\u0101jl\u0101n"
    ],
    "wof:name":"Bakr Bajlan",
    "wof:placetype":"locality"
},
  "geometry": {"coordinates":[44.92577,35.30592],"type":"Point"}
}