{
  "type": "Feature",
  "properties": {
    "gn:admin1_code":"10.0",
    "gn:admin2_code":"94590.0",
    "gn:asciiname":"Sayyid Hammud",
    "gn:country_code":"IQ",
    "gn:dem":169,
    "gn:feature_class":"P",
    "gn:feature_code":"PPLL",
    "gn:name":"Sayyid \u1e28amm\u016bd",
    "gn:population":0,
    "gn:timezone":"Asia/Baghdad",
    "iso:country":"IQ",
    "name:ara_x_preferred":[
        "\u0633\u064a\u062f \u062d\u0645\u0648\u062f"
    ],
    "name:und_x_variant":[
        "Sayyid \u1e28amm\u016bd"
    ],
    "wof:name":"Sayyid Hammud",
    "wof:placetype":"locality"
},
  "geometry": {"coordinates":[45.22705,34.50227],"type":"Point"}
}