{
  "type": "Feature",
  "properties": {
    "gn:admin1_code":"7.0",
    "gn:admin2_code":"9166542.0",
    "gn:asciiname":"Hamid Hasan",
    "gn:country_code":"IQ",
    "gn:dem":36,
    "gn:feature_class":"P",
    "gn:feature_code":"PPL",
    "gn:name":"\u1e28am\u012bd \u1e28asan",
    "gn:population":0,
    "gn:timezone":"Asia/Baghdad",
    "iso:country":"IQ",
    "name:ara_x_preferred":[
        "\u062d\u0645\u064a\u062f \u062d\u0633\u0646"
    ],
    "name:und_x_variant":[
        "\u1e28am\u012bd \u1e28asan"
    ],
    "wof:name":"Hamid Hasan",
    "wof:placetype":"locality"
},
  "geometry": {"coordinates":[44.09373,33.41327],"type":"Point"}
}