{
  "type": "Feature",
  "properties": {
    "gn:admin1_code":"11.0",
    "gn:admin2_code":"9166591.0",
    "gn:asciiname":"Bashuri Xwaru",
    "gn:country_code":"IQ",
    "gn:dem":572,
    "gn:feature_class":"P",
    "gn:feature_code":"PPL",
    "gn:name":"Bashur\u00ee Xwar\u00fb",
    "gn:population":0,
    "gn:timezone":"Asia/Baghdad",
    "iso:country":"IQ",
    "name:ara_x_preferred":[
        "B\u0101sh\u016br"
    ],
    "name:ara_x_variant":[
        "\u0628\u0627\u0634\u0648\u0631 \u0627\u0644\u0633\u0641\u0644\u0649"
    ],
    "name:kur_x_preferred":[
        "Bashur"
    ],
    "name:kur_x_variant":[
        "Bashur\u00ee Xwar\u00fb",
        "\u0628\u0627\u0634\u0648\u0631\u0649 \u062e\u0648\u0627\u0631\u0648\u0648",
        "\u0628\u0627\u0634\u0648\u0631"
    ],
    "name:und_x_variant":[
        "B\u0101sh\u016br \u015eagh\u012br",
        "\u0628\u0627\u0634\u0648\u0631 \u0635\u063a\u064a\u0631",
        "Bashur Lower",
        "B\u0101sh\u016br as Sufl\u00e1"
    ],
    "wof:name":"Bashuri Xwaru",
    "wof:placetype":"locality"
},
  "geometry": {"coordinates":[44.31008,36.51982],"type":"Point"}
}