{
  "type": "Feature",
  "properties": {
    "gn:admin1_code":"7.0",
    "gn:admin2_code":"99173.0",
    "gn:asciiname":"Jamal al 'Aziz",
    "gn:country_code":"IQ",
    "gn:dem":43,
    "gn:feature_class":"P",
    "gn:feature_code":"PPL",
    "gn:name":"Jam\u0101l al \u2018Az\u012bz",
    "gn:population":0,
    "gn:timezone":"Asia/Baghdad",
    "iso:country":"IQ",
    "name:und_x_variant":[
        "Jam\u0101l al \u2018Az\u012bz"
    ],
    "wof:name":"Jamal al 'Aziz",
    "wof:placetype":"locality"
},
  "geometry": {"coordinates":[44.3411,33.42140999999999],"type":"Point"}
}