{
  "type": "Feature",
  "properties": {
    "gn:admin1_code":"6.0",
    "gn:admin2_code":"6818313.0",
    "gn:asciiname":"'Ubayd Dahil",
    "gn:country_code":"IQ",
    "gn:dem":28,
    "gn:feature_class":"P",
    "gn:feature_code":"PPL",
    "gn:name":"\u2018Ubayd Da\u1e29\u012bl",
    "gn:population":0,
    "gn:timezone":"Asia/Baghdad",
    "iso:country":"IQ",
    "name:ara_x_preferred":[
        "\u0639\u0628\u064a\u062f \u062f\u062d\u064a\u0644"
    ],
    "name:und_x_variant":[
        "\u2018Ubayd Da\u1e29\u012bl"
    ],
    "wof:name":"'Ubayd Dahil",
    "wof:placetype":"locality"
},
  "geometry": {"coordinates":[44.82671,32.68148],"type":"Point"}
}