{
  "type": "Feature",
  "properties": {
    "gn:admin1_code":"17.0",
    "gn:admin2_code":"9166629.0",
    "gn:asciiname":"Qal'at Khatit",
    "gn:country_code":"IQ",
    "gn:dem":25,
    "gn:feature_class":"P",
    "gn:feature_code":"PPL",
    "gn:name":"Qal\u2018at Kha\u0163\u012b\u0163",
    "gn:population":0,
    "gn:timezone":"Asia/Baghdad",
    "iso:country":"IQ",
    "name:ara_x_preferred":[
        "\u0642\u0644\u0639\u0629 \u062e\u0637\u064a\u0637"
    ],
    "name:und_x_variant":[
        "Qal\u2018at Kha\u0163\u012b\u0163"
    ],
    "wof:name":"Qal'at Khatit",
    "wof:placetype":"locality"
},
  "geometry": {"coordinates":[44.49452,31.97875],"type":"Point"}
}