{
  "type": "Feature",
  "properties": {
    "gn:admin1_code":"5.0",
    "gn:admin2_code":"91176.0",
    "gn:asciiname":"Biyanah",
    "gn:country_code":"IQ",
    "gn:dem":1137,
    "gn:feature_class":"P",
    "gn:feature_code":"PPL",
    "gn:name":"Biy\u0101nah",
    "gn:population":0,
    "gn:timezone":"Asia/Baghdad",
    "iso:country":"IQ",
    "name:ara_x_preferred":[
        "\u0628\u064a\u0627\u0646\u0647"
    ],
    "name:kur_x_preferred":[
        "Byan\u00ea"
    ],
    "name:kur_x_variant":[
        "Byane",
        "\u0628\u064a\u0627\u0646\u06ce",
        "\u0628\u064a\u0627\u0646\u06d5"
    ],
    "name:und_x_variant":[
        "Biy\u0101nah",
        "Biyan"
    ],
    "wof:name":"Biyanah",
    "wof:placetype":"locality"
},
  "geometry": {"coordinates":[45.62627,35.72926],"type":"Point"}
}