{
  "type": "Feature",
  "properties": {
    "gn:admin1_code":"1.0",
    "gn:admin2_code":"9166650.0",
    "gn:asciiname":"Fuhaymi",
    "gn:cc2":"IQ",
    "gn:country_code":"IQ",
    "gn:dem":138,
    "gn:feature_class":"P",
    "gn:feature_code":"PPL",
    "gn:name":"Fu\u1e29aym\u012b",
    "gn:population":0,
    "gn:timezone":"Asia/Baghdad",
    "iso:country":"IQ",
    "name:und_x_variant":[
        "Kh\u0101n Fuhaima",
        "Fuhaimi"
    ],
    "wof:name":"Fuhaymi",
    "wof:placetype":"locality"
},
  "geometry": {"coordinates":[42.16667,34.26667],"type":"Point"}
}