{
  "type": "Feature",
  "properties": {
    "gn:admin1_code":"7.0",
    "gn:admin2_code":"9166569.0",
    "gn:asciiname":"Hamid 'Abd Allah",
    "gn:country_code":"IQ",
    "gn:dem":37,
    "gn:feature_class":"P",
    "gn:feature_code":"PPL",
    "gn:name":"\u1e28am\u012bd \u2018Abd All\u0101h",
    "gn:population":0,
    "gn:timezone":"Asia/Baghdad",
    "iso:country":"IQ",
    "name:ara_x_preferred":[
        "\u062d\u0645\u064a\u062f \u0639\u0628\u062f \ufdf2"
    ],
    "name:und_x_variant":[
        "\u1e28am\u012bd \u2018Abd All\u0101h"
    ],
    "wof:name":"Hamid 'Abd Allah",
    "wof:placetype":"locality"
},
  "geometry": {"coordinates":[44.13254000000001,33.64982],"type":"Point"}
}