{
  "type": "Feature",
  "properties": {
    "gn:admin1_code":"18.0",
    "gn:admin2_code":"91594.0",
    "gn:asciiname":"Kazim 'Anad Dayakh",
    "gn:country_code":"IQ",
    "gn:dem":91,
    "gn:feature_class":"P",
    "gn:feature_code":"PPL",
    "gn:name":"K\u0101z\u0327im \u2018An\u0101d D\u0101yakh",
    "gn:population":0,
    "gn:timezone":"Asia/Baghdad",
    "iso:country":"IQ",
    "name:ara_x_preferred":[
        "\u0643\u0627\u0638\u0645 \u0639\u0646\u0627\u062f \u062f\u0627\u064a\u062e"
    ],
    "name:und_x_variant":[
        "K\u0101z\u0327im \u2018An\u0101d D\u0101yakh"
    ],
    "wof:name":"Kazim 'Anad Dayakh",
    "wof:placetype":"locality"
},
  "geometry": {"coordinates":[43.59669,34.25248],"type":"Point"}
}