{
  "type": "Feature",
  "properties": {
    "gn:admin1_code":"17.0",
    "gn:admin2_code":"9166552.0",
    "gn:asciiname":"Al Jawhariyah",
    "gn:country_code":"IQ",
    "gn:dem":20,
    "gn:feature_class":"P",
    "gn:feature_code":"PPL",
    "gn:name":"Al Jawhar\u012byah",
    "gn:population":0,
    "gn:timezone":"Asia/Baghdad",
    "iso:country":"IQ",
    "name:ara_x_preferred":[
        "\u0627\u0644\u062c\u0648\u0647\u0631\u064a\u0629"
    ],
    "name:und_x_variant":[
        "Al Jawhar\u012byah"
    ],
    "wof:name":"Al Jawhariyah",
    "wof:placetype":"locality"
},
  "geometry": {"coordinates":[44.51442,31.71425],"type":"Point"}
}