{
  "type": "Feature",
  "properties": {
    "gn:admin1_code":"5.0",
    "gn:admin2_code":"97416.0",
    "gn:asciiname":"'Umar Khuwa 'Ulya",
    "gn:country_code":"IQ",
    "gn:dem":685,
    "gn:feature_class":"P",
    "gn:feature_code":"PPL",
    "gn:name":"\u2018Umar Khuw\u0101 \u2018Uly\u0101",
    "gn:population":0,
    "gn:timezone":"Asia/Baghdad",
    "iso:country":"IQ",
    "name:und_x_variant":[
        "Umar Khowa Uliya",
        "\u2018Umarkhowa \u2018Ulya",
        "\u2018Umar Kh\u0101wah \u2018Uly\u0101",
        "\u2018Umar Khuw\u0101 \u2018Uly\u0101"
    ],
    "wof:name":"'Umar Khuwa 'Ulya",
    "wof:placetype":"locality"
},
  "geometry": {"coordinates":[44.73333,35.76667],"type":"Point"}
}