{
  "type": "Feature",
  "properties": {
    "gn:admin1_code":"18.0",
    "gn:admin2_code":"90148.0",
    "gn:asciiname":"'Arab Turki al 'Utan",
    "gn:country_code":"IQ",
    "gn:dem":125,
    "gn:feature_class":"P",
    "gn:feature_code":"PPL",
    "gn:name":"\u2018Arab Turk\u012b al \u2018U\u0163\u0101n",
    "gn:population":0,
    "gn:timezone":"Asia/Baghdad",
    "iso:country":"IQ",
    "name:ara_x_preferred":[
        "\u0639\u0631\u0628 \u062a\u0631\u0643\u064a \u0627\u0644\u0639\u0637\u0627\u0646"
    ],
    "name:und_x_variant":[
        "\u2018Arab Turk\u012b al \u2018U\u0163\u0101n"
    ],
    "wof:name":"'Arab Turki al 'Utan",
    "wof:placetype":"locality"
},
  "geometry": {"coordinates":[43.46965,34.48168],"type":"Point"}
}