{
  "type": "Feature",
  "properties": {
    "gn:admin1_code":"1.0",
    "gn:asciiname":"`Ali al Hamadi",
    "gn:country_code":"IQ",
    "gn:dem":42,
    "gn:feature_class":"P",
    "gn:feature_code":"PPL",
    "gn:name":"\u2018Al\u012b al \u1e28am\u0101d\u012b",
    "gn:population":0,
    "gn:timezone":"Asia/Baghdad",
    "iso:country":"IQ",
    "name:ara_x_preferred":[
        "\u0639\u0644\u064a \u0627\u0644\u062d\u0645\u0627\u062f\u064a"
    ],
    "name:und_x_variant":[
        "\u2018Al\u012b al \u1e28am\u0101d\u012b"
    ],
    "wof:name":"`Ali al Hamadi",
    "wof:placetype":"locality"
},
  "geometry": {"coordinates":[44.13343,33.02093],"type":"Point"}
}