{
  "type": "Feature",
  "properties": {
    "gn:admin1_code":"15.0",
    "gn:admin2_code":"98820.0",
    "gn:asciiname":"Khirbat Baykras",
    "gn:country_code":"IQ",
    "gn:dem":484,
    "gn:feature_class":"P",
    "gn:feature_code":"PPL",
    "gn:name":"Khirb\u0101t Baykras",
    "gn:population":0,
    "gn:timezone":"Asia/Baghdad",
    "iso:country":"IQ",
    "name:ara_x_preferred":[
        "\u062e\u0631\u0628\u0627\u062a \u0628\u064a\u0643\u0631\u0633"
    ],
    "name:kur_x_preferred":[
        "B\u00eagirs"
    ],
    "name:kur_x_variant":[
        "\u0628\u06ce\u06af\u0631\u0633"
    ],
    "name:und_x_variant":[
        "Bikras",
        "Khirb\u0101t Baykras",
        "\u062e\u0631\u0628\u0627\u062a \u0628\u064a\u0643\u0631\u0633",
        "Khirbat Qaryat Baykras",
        "\u062e\u0631\u0628\u0629 \u0642\u0631\u064a\u0629 \u0628\u064a\u0643\u0631\u0633",
        "Bekres"
    ],
    "wof:name":"Khirbat Baykras",
    "wof:placetype":"locality"
},
  "geometry": {"coordinates":[44.23178,36.80039],"type":"Point"}
}