{
  "type": "Feature",
  "properties": {
    "gn:admin1_code":"5.0",
    "gn:admin2_code":"92743.0",
    "gn:asciiname":"Ghelu Maxo Biznan",
    "gn:country_code":"IQ",
    "gn:dem":762,
    "gn:feature_class":"P",
    "gn:feature_code":"PPL",
    "gn:name":"Ghelu Maxo Biznan",
    "gn:population":0,
    "gn:timezone":"Asia/Baghdad",
    "iso:country":"IQ",
    "name:ara_x_preferred":[
        "Gh\u0101l\u016b"
    ],
    "name:kur_x_preferred":[
        "Ghelu Maxo Biznan"
    ],
    "name:kur_x_variant":[
        "Ghelu",
        "\u063a\u06d5\u0644\u0648",
        "\u063a\u06d5\u0644\u0648 \u0645\u0627\u062e\u06c6 \u0628\u0632\u0646\u0627\u0646"
    ],
    "name:und_x_variant":[
        "Ghalu",
        "Makhu Bznan"
    ],
    "wof:name":"Ghelu Maxo Biznan",
    "wof:placetype":"locality"
},
  "geometry": {"coordinates":[44.95094,36.31075],"type":"Point"}
}