{
  "type": "Feature",
  "properties": {
    "gn:admin1_code":"10.0",
    "gn:admin2_code":"9166680.0",
    "gn:asciiname":"Bari",
    "gn:country_code":"IQ",
    "gn:dem":114,
    "gn:feature_class":"P",
    "gn:feature_code":"PPL",
    "gn:name":"B\u0101r\u012b",
    "gn:population":0,
    "gn:timezone":"Asia/Baghdad",
    "iso:country":"IQ",
    "name:ara_x_preferred":[
        "B\u0101r\u012b"
    ],
    "name:ara_x_variant":[
        "\u0628\u0627\u0631\u064a"
    ],
    "wof:name":"Bari",
    "wof:placetype":"locality"
},
  "geometry": {"coordinates":[45.5264,33.76924],"type":"Point"}
}