{
  "type": "Feature",
  "properties": {
    "gn:admin1_code":"4.0",
    "gn:admin2_code":"98634.0",
    "gn:asciiname":"An Nakarah",
    "gn:country_code":"IQ",
    "gn:dem":18,
    "gn:feature_class":"P",
    "gn:feature_code":"PPL",
    "gn:name":"An Nak\u0101rah",
    "gn:population":0,
    "gn:timezone":"Asia/Baghdad",
    "iso:country":"IQ",
    "name:ara_x_preferred":[
        "\u0627\u0644\u0646\u0643\u0627\u0631\u0629"
    ],
    "name:und_x_variant":[
        "An Nak\u0101rah"
    ],
    "wof:name":"An Nakarah",
    "wof:placetype":"locality"
},
  "geometry": {"coordinates":[44.53624,31.71019],"type":"Point"}
}