{
  "type": "Feature",
  "properties": {
    "gn:admin1_code":"18.0",
    "gn:admin2_code":"9166616.0",
    "gn:asciiname":"Fayyad Husayn",
    "gn:country_code":"IQ",
    "gn:dem":40,
    "gn:feature_class":"P",
    "gn:feature_code":"PPL",
    "gn:name":"Fayy\u0101\u1e11 \u1e28usayn",
    "gn:population":0,
    "gn:timezone":"Asia/Baghdad",
    "iso:country":"IQ",
    "name:ara_x_preferred":[
        "\u0641\u064a\u0627\u0636 \u062d\u0633\u064a\u0646"
    ],
    "name:und_x_variant":[
        "Fayy\u0101\u1e11 \u1e28usayn"
    ],
    "wof:name":"Fayyad Husayn",
    "wof:placetype":"locality"
},
  "geometry": {"coordinates":[44.19852,33.8318],"type":"Point"}
}