{
  "type": "Feature",
  "properties": {
    "gn:admin1_code":"18.0",
    "gn:admin2_code":"6804454.0",
    "gn:asciiname":"Qaryat Kan'us al 'Ulya",
    "gn:country_code":"IQ",
    "gn:dem":172,
    "gn:feature_class":"P",
    "gn:feature_code":"PPL",
    "gn:name":"Qaryat Kan\u2018\u016b\u015f al \u2018Uly\u0101",
    "gn:population":0,
    "gn:timezone":"Asia/Baghdad",
    "iso:country":"IQ",
    "name:ara_x_preferred":[
        "\u0642\u0631\u064a\u0629 \u0643\u0646\u0639\u0648\u0635 \u0627\u0644\u0639\u0644\u064a\u0627"
    ],
    "name:und_x_variant":[
        "Qan\u2018\u016bsah",
        "Qanf\u016bsah",
        "Qan\u2018awsah",
        "Gan\u2018\u016b\u015f al \u2018Uly\u0101",
        "Qaryat Kan\u2018\u016b\u015f al \u2018Uly\u0101"
    ],
    "wof:name":"Qaryat Kan'us al 'Ulya",
    "wof:placetype":"locality"
},
  "geometry": {"coordinates":[43.29022,35.6763],"type":"Point"}
}