{
  "type": "Feature",
  "properties": {
    "gn:admin1_code":"18.0",
    "gn:admin2_code":"9166616.0",
    "gn:asciiname":"Kan'an Jawhar",
    "gn:country_code":"IQ",
    "gn:dem":44,
    "gn:feature_class":"P",
    "gn:feature_code":"PPL",
    "gn:name":"Kan\u2018\u0101n Jawhar",
    "gn:population":0,
    "gn:timezone":"Asia/Baghdad",
    "iso:country":"IQ",
    "name:ara_x_preferred":[
        "\u0643\u0646\u0639\u0627\u0646 \u062c\u0648\u0647\u0631"
    ],
    "name:und_x_variant":[
        "Kan\u2018\u0101n Jawhar"
    ],
    "wof:name":"Kan'an Jawhar",
    "wof:placetype":"locality"
},
  "geometry": {"coordinates":[44.38577,33.85865],"type":"Point"}
}