{
  "type": "Feature",
  "properties": {
    "gn:admin1_code":"11.0",
    "gn:admin2_code":"93817.0",
    "gn:asciiname":"Qalah Suran",
    "gn:country_code":"IQ",
    "gn:dem":357,
    "gn:feature_class":"P",
    "gn:feature_code":"PPLL",
    "gn:name":"Qal\u0101h S\u016br\u0101n",
    "gn:population":0,
    "gn:timezone":"Asia/Baghdad",
    "iso:country":"IQ",
    "name:ara_x_preferred":[
        "\u0642\u0644\u0627\u0629 \u0633\u0648\u0631\u0627\u0646"
    ],
    "name:kur_x_preferred":[
        "Qe\u0142ate Soran"
    ],
    "name:kur_x_variant":[
        "\u0642\u06d5\u06b5\u0627\u062a\u06d5 \u0633\u06c6\u0631\u0627\u0646"
    ],
    "name:und_x_variant":[
        "Qal\u2018at S\u016br\u012bn",
        "Qalata Soran",
        "Qal\u2018at as Soran",
        "Qal\u0101h S\u016br\u0101n"
    ],
    "wof:name":"Qalah Suran",
    "wof:placetype":"locality"
},
  "geometry": {"coordinates":[43.76192,36.16522],"type":"Point"}
}