{
  "type": "Feature",
  "properties": {
    "gn:admin1_code":"12.0",
    "gn:admin2_code":"99345.0",
    "gn:asciiname":"As Sayyid Muhammad 'Ali",
    "gn:country_code":"IQ",
    "gn:dem":28,
    "gn:feature_class":"P",
    "gn:feature_code":"PPL",
    "gn:name":"As Sayyid Mu\u1e29ammad \u2018Al\u012b",
    "gn:population":0,
    "gn:timezone":"Asia/Baghdad",
    "iso:country":"IQ",
    "name:und_x_variant":[
        "Sayyid Mu\u1e29ammad \u2018Al\u012b",
        "Saiyid Muhammad \u2018Al\u012b",
        "As Sayyid Mu\u1e29ammad \u2018Al\u012b"
    ],
    "wof:name":"As Sayyid Muhammad 'Ali",
    "wof:placetype":"locality"
},
  "geometry": {"coordinates":[44.25694,32.36778],"type":"Point"}
}