{
  "type": "Feature",
  "properties": {
    "gn:admin1_code":"18.0",
    "gn:admin2_code":"90148.0",
    "gn:asciiname":"Qaryat as Sarin",
    "gn:country_code":"IQ",
    "gn:dem":104,
    "gn:feature_class":"P",
    "gn:feature_code":"PPL",
    "gn:name":"Qaryat a\u015f \u015ear\u012bn",
    "gn:population":0,
    "gn:timezone":"Asia/Baghdad",
    "iso:country":"IQ",
    "name:ara_x_preferred":[
        "\u0642\u0631\u064a\u0629 \u0627\u0644\u0635\u0631\u064a\u0646"
    ],
    "name:und_x_variant":[
        "Qaryat a\u015f \u015ear\u012bn"
    ],
    "wof:name":"Qaryat as Sarin",
    "wof:placetype":"locality"
},
  "geometry": {"coordinates":[43.52092,34.8726],"type":"Point"}
}