{
  "type": "Feature",
  "properties": {
    "gn:admin1_code":"11.0",
    "gn:admin2_code":"9166588.0",
    "gn:asciiname":"Tall Kirdi Zazuji",
    "gn:country_code":"IQ",
    "gn:dem":504,
    "gn:feature_class":"P",
    "gn:feature_code":"PPL",
    "gn:name":"Tall Kird\u012b Zaz\u016bj\u012b",
    "gn:population":0,
    "gn:timezone":"Asia/Baghdad",
    "iso:country":"IQ",
    "name:ara_x_preferred":[
        "\u062a\u0644 \u0643\u0631\u062f\u064a \u0632\u0632\u0648\u062c\u064a"
    ],
    "name:und_x_variant":[
        "Tall Kird\u012b Zaz\u016bj\u012b",
        "\u062a\u0644 \u0643\u0631\u062f\u064a \u0632\u0632\u0648\u062c\u064a"
    ],
    "wof:name":"Tall Kirdi Zazuji",
    "wof:placetype":"locality"
},
  "geometry": {"coordinates":[44.57191,36.0337],"type":"Point"}
}