{
  "type": "Feature",
  "properties": {
    "gn:admin1_code":"10.0",
    "gn:admin2_code":"97988.0",
    "gn:asciiname":"Qaryat al Hamidiyah",
    "gn:country_code":"IQ",
    "gn:dem":43,
    "gn:feature_class":"P",
    "gn:feature_code":"PPL",
    "gn:name":"Qaryat al \u1e28am\u012bd\u012byah",
    "gn:population":0,
    "gn:timezone":"Asia/Baghdad",
    "iso:country":"IQ",
    "name:ara_x_preferred":[
        "\u0642\u0631\u064a\u0629 \u0627\u0644\u062d\u0645\u064a\u062f\u064a\u0629"
    ],
    "name:und_x_variant":[
        "Qaryat al \u1e28am\u012bd\u012byah"
    ],
    "wof:name":"Qaryat al Hamidiyah",
    "wof:placetype":"locality"
},
  "geometry": {"coordinates":[44.51481,33.49417],"type":"Point"}
}