{
  "type": "Feature",
  "properties": {
    "gn:admin1_code":"16.0",
    "gn:admin2_code":"9166961.0",
    "gn:asciiname":"Qaryat al 'Urubah",
    "gn:country_code":"IQ",
    "gn:dem":29,
    "gn:feature_class":"P",
    "gn:feature_code":"PPL",
    "gn:name":"Qaryat al \u2018Ur\u016bbah",
    "gn:population":0,
    "gn:timezone":"Asia/Baghdad",
    "iso:country":"IQ",
    "name:ara_x_preferred":[
        "\u0642\u0631\u064a\u0629 \u0627\u0644\u0639\u0631\u0648\u0628\u0629"
    ],
    "name:und_x_variant":[
        "Qaryat al \u2018Ur\u016bbah"
    ],
    "wof:name":"Qaryat al 'Urubah",
    "wof:placetype":"locality"
},
  "geometry": {"coordinates":[44.88658,32.95935],"type":"Point"}
}