{
  "type": "Feature",
  "properties": {
    "gn:admin1_code":"13.0",
    "gn:admin2_code":"9171727.0",
    "gn:asciiname":"Abu Khurjah",
    "gn:country_code":"IQ",
    "gn:dem":264,
    "gn:feature_class":"P",
    "gn:feature_code":"PPL",
    "gn:name":"Ab\u016b Kh\u016brjah",
    "gn:population":0,
    "gn:timezone":"Asia/Baghdad",
    "iso:country":"IQ",
    "name:ara_x_preferred":[
        "\u0627\u0628\u0648 \u062e\u0648\u0631\u062c\u0647"
    ],
    "name:kur_x_preferred":[
        "Ebu Xurce"
    ],
    "name:kur_x_variant":[
        "\u0626\u06d5\u0628\u0648 \u062e\u0648\u0631\u062c\u06d5"
    ],
    "name:und_x_variant":[
        "Abu Khorga",
        "Ab\u016b Kh\u016brjah"
    ],
    "wof:name":"Abu Khurjah",
    "wof:placetype":"locality"
},
  "geometry": {"coordinates":[44.0554,35.58466],"type":"Point"}
}