{
  "type": "Feature",
  "properties": {
    "gn:admin1_code":"4.0",
    "gn:admin2_code":"99763.0",
    "gn:asciiname":"'Ubayd Hasan",
    "gn:country_code":"IQ",
    "gn:dem":26,
    "gn:feature_class":"P",
    "gn:feature_code":"PPL",
    "gn:name":"\u2018Ubayd \u1e28asan",
    "gn:population":0,
    "gn:timezone":"Asia/Baghdad",
    "iso:country":"IQ",
    "name:ara_x_preferred":[
        "\u0639\u0628\u064a\u062f \u062d\u0633\u0646"
    ],
    "name:und_x_variant":[
        "\u2018Ubayd \u1e28asan"
    ],
    "wof:name":"'Ubayd Hasan",
    "wof:placetype":"locality"
},
  "geometry": {"coordinates":[44.61783,32.01104],"type":"Point"}
}