{
  "type": "Feature",
  "properties": {
    "gn:admin1_code":"11.0",
    "gn:admin2_code":"9166534.0",
    "gn:asciiname":"Muke",
    "gn:country_code":"IQ",
    "gn:dem":1405,
    "gn:feature_class":"P",
    "gn:feature_code":"PPL",
    "gn:name":"Muke",
    "gn:population":0,
    "gn:timezone":"Asia/Baghdad",
    "iso:country":"IQ",
    "name:ara_x_preferred":[
        "\u0645\u0648\u0643\u0647"
    ],
    "name:kur_x_preferred":[
        "Muke"
    ],
    "name:kur_x_variant":[
        "\u0645\u0648\u0643\u06d5"
    ],
    "name:und_x_variant":[
        "Muka",
        "M\u014dk\u0101",
        "M\u016bkah"
    ],
    "wof:name":"Muke",
    "wof:placetype":"locality"
},
  "geometry": {"coordinates":[44.06604,37.08432],"type":"Point"}
}