{
  "type": "Feature",
  "properties": {
    "gn:admin1_code":"11.0",
    "gn:admin2_code":"9166592.0",
    "gn:asciiname":"Pirosoan",
    "gn:country_code":"IQ",
    "gn:dem":1012,
    "gn:feature_class":"P",
    "gn:feature_code":"PPL",
    "gn:name":"Pirosoan",
    "gn:population":0,
    "gn:timezone":"Asia/Baghdad",
    "iso:country":"IQ",
    "name:ara_x_preferred":[
        "B\u012br\u0101ws\u016b"
    ],
    "name:ara_x_variant":[
        "\u0628\u064a\u0631\u0627\u0648\u0633\u0648"
    ],
    "name:kur_x_preferred":[
        "P\u00eerosoan"
    ],
    "name:kur_x_variant":[
        "P\u00ee\u1e5fswan",
        "\u067e\u064a\u0631\u06c6\u0633\u06c6\u0627\u0646",
        "\u067e\u064a\u0695\u0633\u0648\u0627\u0646"
    ],
    "name:und_x_variant":[
        "P\u012br \u016as\u016b",
        "Pirosoan",
        "P\u012br Wus\u016b",
        "Pirswan"
    ],
    "wof:name":"Pirosoan",
    "wof:placetype":"locality"
},
  "geometry": {"coordinates":[44.64128,36.65289],"type":"Point"}
}