{
  "type": "Feature",
  "properties": {
    "gn:admin1_code":"5.0",
    "gn:admin2_code":"92743.0",
    "gn:asciiname":"Halshaw",
    "gn:country_code":"IQ",
    "gn:dem":1064,
    "gn:feature_class":"P",
    "gn:feature_code":"PPLA3",
    "gn:name":"Halshaw",
    "gn:population":0,
    "gn:timezone":"Asia/Baghdad",
    "iso:country":"IQ",
    "name:ara_x_preferred":[
        "\u0647\u0644\u0634\u0648"
    ],
    "name:fas_x_preferred":[
        "\u0627\u0644\u0634\u0648"
    ],
    "name:fas_x_variant":[
        "Alsh\u016b"
    ],
    "name:kur_x_preferred":[
        "He\u0142sho"
    ],
    "name:kur_x_variant":[
        "\u06be\u06d5\u06b5\u0634\u06c6"
    ],
    "name:und_x_variant":[
        "Halsho",
        "Halsho Upper"
    ],
    "wof:name":"Halshaw",
    "wof:placetype":"locality"
},
  "geometry": {"coordinates":[45.25926,36.20901],"type":"Point"}
}