{
  "type": "Feature",
  "properties": {
    "gn:admin1_code":"14.0",
    "gn:admin2_code":"99305.0",
    "gn:asciiname":"Qal'at Nasir",
    "gn:country_code":"IQ",
    "gn:dem":14,
    "gn:feature_class":"P",
    "gn:feature_code":"PPL",
    "gn:name":"Qal\u2018at N\u0101\u015fir",
    "gn:population":0,
    "gn:timezone":"Asia/Baghdad",
    "iso:country":"IQ",
    "name:ara_x_preferred":[
        "\u0642\u0644\u0639\u0629 \u0646\u0627\u0635\u0631"
    ],
    "name:und_x_variant":[
        "Qal\u2018at N\u0101\u015fir"
    ],
    "wof:name":"Qal'at Nasir",
    "wof:placetype":"locality"
},
  "geometry": {"coordinates":[46.53581,32.51609000000001],"type":"Point"}
}