{
  "type": "Feature",
  "properties": {
    "gn:admin1_code":"3.0",
    "gn:admin2_code":"9166568.0",
    "gn:asciiname":"Al Jamil",
    "gn:country_code":"IQ",
    "gn:dem":14,
    "gn:feature_class":"P",
    "gn:feature_code":"PPL",
    "gn:name":"Al Jam\u012bl",
    "gn:population":0,
    "gn:timezone":"Asia/Baghdad",
    "iso:country":"IQ",
    "name:ara_x_preferred":[
        "\u0627\u0644\u062c\u0645\u064a\u0644"
    ],
    "name:und_x_variant":[
        "Al Jam\u012bl"
    ],
    "wof:name":"Al Jamil",
    "wof:placetype":"locality"
},
  "geometry": {"coordinates":[45.24800000000001,31.38751],"type":"Point"}
}