{
  "type": "Feature",
  "properties": {
    "gn:admin1_code":"18.0",
    "gn:admin2_code":"6783103.0",
    "gn:asciiname":"Qaryat Kan'an",
    "gn:country_code":"IQ",
    "gn:dem":99,
    "gn:feature_class":"P",
    "gn:feature_code":"PPL",
    "gn:name":"Qaryat Kan\u2018\u0101n",
    "gn:population":0,
    "gn:timezone":"Asia/Baghdad",
    "iso:country":"IQ",
    "name:ara_x_preferred":[
        "\u0642\u0631\u064a\u0629 \u06a9\u0646\u0639\u0627\u0646"
    ],
    "name:und_x_variant":[
        "Qaryat Kan\u2018\u0101n"
    ],
    "wof:name":"Qaryat Kan'an",
    "wof:placetype":"locality"
},
  "geometry": {"coordinates":[44.22989000000001,34.55482],"type":"Point"}
}