{
  "type": "Feature",
  "properties": {
    "gn:admin1_code":"18.0",
    "gn:admin2_code":"91594.0",
    "gn:asciiname":"'Arab Salman Hamud",
    "gn:country_code":"IQ",
    "gn:dem":103,
    "gn:feature_class":"P",
    "gn:feature_code":"PPLL",
    "gn:name":"\u2018Arab Salm\u0101n \u1e28am\u016bd",
    "gn:population":0,
    "gn:timezone":"Asia/Baghdad",
    "iso:country":"IQ",
    "name:ara_x_preferred":[
        "\u0639\u0631\u0628 \u0633\u0644\u0645\u0627\u0646 \u062d\u0645\u0648\u062f"
    ],
    "name:und_x_variant":[
        "\u2018Arab Salm\u0101n \u1e28am\u016bd"
    ],
    "wof:name":"'Arab Salman Hamud",
    "wof:placetype":"locality"
},
  "geometry": {"coordinates":[43.50881,34.25347],"type":"Point"}
}