{
  "type": "Feature",
  "properties": {
    "gn:admin1_code":"7.0",
    "gn:admin2_code":"9166542.0",
    "gn:asciiname":"Qaryat Khalil Ibrahim",
    "gn:country_code":"IQ",
    "gn:dem":33,
    "gn:feature_class":"P",
    "gn:feature_code":"PPL",
    "gn:name":"Qaryat Khal\u012bl Ibr\u0101h\u012bm",
    "gn:population":0,
    "gn:timezone":"Asia/Baghdad",
    "iso:country":"IQ",
    "name:und_x_variant":[
        "\u0642\u0631\u064a\u0629 \u062e\u0644\u064a\u0644 \u0627\u0628\u0631\u0627\u0647\u064a\u0645",
        "Qaryat Khal\u012bl Ibr\u0101h\u012bm"
    ],
    "wof:name":"Qaryat Khalil Ibrahim",
    "wof:placetype":"locality"
},
  "geometry": {"coordinates":[44.17062,33.28157],"type":"Point"}
}