{
  "type": "Feature",
  "properties": {
    "gn:admin1_code":"5.0",
    "gn:admin2_code":"98464.0",
    "gn:asciiname":"Balulan",
    "gn:country_code":"IQ",
    "gn:dem":795,
    "gn:feature_class":"P",
    "gn:feature_code":"PPL",
    "gn:name":"B\u0101l\u016bl\u0101n",
    "gn:population":0,
    "gn:timezone":"Asia/Baghdad",
    "iso:country":"IQ",
    "name:ara_x_preferred":[
        "B\u0101l\u016bl\u0101n"
    ],
    "name:ara_x_variant":[
        "\u0628\u0627\u0644\u0648\u0644\u0627\u0646"
    ],
    "wof:name":"Balulan",
    "wof:placetype":"locality"
},
  "geometry": {"coordinates":[45.17018,35.52761],"type":"Point"}
}