{
  "type": "Feature",
  "properties": {
    "gn:admin1_code":"10.0",
    "gn:admin2_code":"99063.0",
    "gn:asciiname":"As Sayyid 'Ali an Naqib",
    "gn:country_code":"IQ",
    "gn:dem":48,
    "gn:feature_class":"P",
    "gn:feature_code":"PPL",
    "gn:name":"As Sayyid \u2018Al\u012b an Naq\u012bb",
    "gn:population":0,
    "gn:timezone":"Asia/Baghdad",
    "iso:country":"IQ",
    "name:und_x_variant":[
        "As Saiyid \u2018Ali an Naq\u012bb",
        "As Sayyid \u2018Al\u012b an Naq\u012bb"
    ],
    "wof:name":"As Sayyid 'Ali an Naqib",
    "wof:placetype":"locality"
},
  "geometry": {"coordinates":[44.86667,33.83333],"type":"Point"}
}