{
  "type": "Feature",
  "properties": {
    "gn:admin1_code":"13.0",
    "gn:admin2_code":"6770659.0",
    "gn:asciiname":"Salih Musa",
    "gn:country_code":"IQ",
    "gn:dem":124,
    "gn:feature_class":"P",
    "gn:feature_code":"PPL",
    "gn:name":"\u015eali\u1e29 M\u016bs\u00e1",
    "gn:population":0,
    "gn:timezone":"Asia/Baghdad",
    "iso:country":"IQ",
    "name:ara_x_preferred":[
        "\u0635\u0627\u0644\u062d \u0645\u0648\u0633\u0649"
    ],
    "name:und_x_variant":[
        "\u015eali\u1e29 M\u016bs\u00e1"
    ],
    "wof:name":"Salih Musa",
    "wof:placetype":"locality"
},
  "geometry": {"coordinates":[43.44209,35.15588],"type":"Point"}
}