{
  "type": "Feature",
  "properties": {
    "gn:admin1_code":"17.0",
    "gn:admin2_code":"9166629.0",
    "gn:asciiname":"Al Fatlah",
    "gn:country_code":"IQ",
    "gn:dem":26,
    "gn:feature_class":"P",
    "gn:feature_code":"PPL",
    "gn:name":"Al Fatlah",
    "gn:population":0,
    "gn:timezone":"Asia/Baghdad",
    "iso:country":"IQ",
    "name:ara_x_preferred":[
        "\u0627\u0644\u0641\u062a\u0644\u0629"
    ],
    "wof:name":"Al Fatlah",
    "wof:placetype":"locality"
},
  "geometry": {"coordinates":[44.53811,32.08425],"type":"Point"}
}