{
  "type": "Feature",
  "properties": {
    "gn:admin1_code":"11.0",
    "gn:admin2_code":"9166588.0",
    "gn:asciiname":"Wadlawk",
    "gn:country_code":"IQ",
    "gn:dem":741,
    "gn:feature_class":"P",
    "gn:feature_code":"PPL",
    "gn:name":"Wadlawk",
    "gn:population":0,
    "gn:timezone":"Asia/Baghdad",
    "iso:country":"IQ",
    "name:ara_x_preferred":[
        "\u0648\u062f\u0644\u0648\u0643"
    ],
    "name:kur_x_preferred":[
        "\u0639\u06d5\u0648\u062f\u0648\u0644\u0648\u0627\u0646"
    ],
    "name:kur_x_variant":[
        "Audulwan",
        "\u2018Ewdulwan",
        "Awdelok",
        "\u0626\u0627\u0648\u062f\u06d5\u0644\u06c6\u0643"
    ],
    "name:und_x_variant":[
        "Awd\u0101l\u014dk",
        "Wadlawk",
        "\u0648\u062f\u0644\u0648\u0643",
        "Audulwan",
        "Awdalok"
    ],
    "wof:name":"Wadlawk",
    "wof:placetype":"locality"
},
  "geometry": {"coordinates":[44.73815,36.04444],"type":"Point"}
}