{
  "type": "Feature",
  "properties": {
    "gn:admin1_code":"9.0",
    "gn:admin2_code":"98623.0",
    "gn:asciiname":"Jarir al Jabr",
    "gn:country_code":"IQ",
    "gn:dem":8,
    "gn:feature_class":"P",
    "gn:feature_code":"PPL",
    "gn:name":"Jar\u012br al Jabr",
    "gn:population":0,
    "gn:timezone":"Asia/Baghdad",
    "iso:country":"IQ",
    "name:ara_x_preferred":[
        "\u062c\u0631\u064a\u0631 \u0627\u0644\u062c\u0628\u0631"
    ],
    "name:und_x_variant":[
        "Jar\u012br al Jabr"
    ],
    "wof:name":"Jarir al Jabr",
    "wof:placetype":"locality"
},
  "geometry": {"coordinates":[46.10392,31.42107],"type":"Point"}
}