{
  "type": "Feature",
  "properties": {
    "gn:admin1_code":"7.0",
    "gn:admin2_code":"9166569.0",
    "gn:asciiname":"Salih al Hamad",
    "gn:country_code":"IQ",
    "gn:dem":41,
    "gn:feature_class":"P",
    "gn:feature_code":"PPL",
    "gn:name":"\u015e\u0101li\u1e29 al \u1e28amad",
    "gn:population":0,
    "gn:timezone":"Asia/Baghdad",
    "iso:country":"IQ",
    "name:und_x_variant":[
        "\u015e\u0101li\u1e29 al \u1e28amad"
    ],
    "wof:name":"Salih al Hamad",
    "wof:placetype":"locality"
},
  "geometry": {"coordinates":[44.34528,33.62778],"type":"Point"}
}