{
  "type": "Feature",
  "properties": {
    "gn:admin1_code":"1.0",
    "gn:admin2_code":"9166650.0",
    "gn:asciiname":"Al Baridiyah",
    "gn:country_code":"IQ",
    "gn:dem":154,
    "gn:feature_class":"P",
    "gn:feature_code":"PPL",
    "gn:name":"Al Bar\u012bd\u012byah",
    "gn:population":0,
    "gn:timezone":"Asia/Baghdad",
    "iso:country":"IQ",
    "name:ara_x_preferred":[
        "\u0627\u0644\u0628\u0631\u064a\u062f\u064a\u0629"
    ],
    "name:und_x_variant":[
        "Al Bar\u012bd\u012byah"
    ],
    "wof:name":"Al Baridiyah",
    "wof:placetype":"locality"
},
  "geometry": {"coordinates":[41.64187,34.47625],"type":"Point"}
}