{
  "type": "Feature",
  "properties": {
    "gn:admin1_code":"5.0",
    "gn:admin2_code":"9166600.0",
    "gn:asciiname":"Buwwah",
    "gn:country_code":"IQ",
    "gn:dem":609,
    "gn:feature_class":"P",
    "gn:feature_code":"PPL",
    "gn:name":"Buwwah",
    "gn:population":0,
    "gn:timezone":"Asia/Baghdad",
    "iso:country":"IQ",
    "name:ara_x_preferred":[
        "\u0628\u0648\u0629"
    ],
    "name:kur_x_preferred":[
        "B\u00fbe"
    ],
    "name:kur_x_variant":[
        "Bwake",
        "\u0628\u0648\u0648\u06d5",
        "\u0628\u0648\u0627\u0643\u06d5"
    ],
    "name:und_x_variant":[
        "Bashk-i Tuwa",
        "Buwwah",
        "B\u0101shk\u012b Tuwah \u1e28amah Kh\u016brsh\u012bd",
        "Bwa",
        "\u0628\u0627\u0634\u0643\u064a \u062a\u0648\u0647 \u062d\u0645\u0647 \u062e\u0648\u0631\u0634\u064a\u062f"
    ],
    "wof:name":"Buwwah",
    "wof:placetype":"locality"
},
  "geometry": {"coordinates":[45.2728,34.82962],"type":"Point"}
}