{
  "type": "Feature",
  "properties": {
    "gn:admin1_code":"10.0",
    "gn:admin2_code":"99063.0",
    "gn:asciiname":"Fadil Idham",
    "gn:country_code":"IQ",
    "gn:dem":53,
    "gn:feature_class":"P",
    "gn:feature_code":"PPL",
    "gn:name":"F\u0101\u1e11il Idh\u0101m",
    "gn:population":0,
    "gn:timezone":"Asia/Baghdad",
    "iso:country":"IQ",
    "name:ara_x_preferred":[
        "\u0641\u0627\u0636\u0644 \u0627\u062f\u0647\u0627\u0645"
    ],
    "name:ara_x_variant":[
        "F\u0101\u1e11il Idh\u0101m"
    ],
    "name:und_x_variant":[
        "F\u0101\u1e11il Dahh\u0101m",
        "\u0641\u0627\u0636\u0644 \u062f\u0647\u0627\u0645"
    ],
    "wof:name":"Fadil Idham",
    "wof:placetype":"locality"
},
  "geometry": {"coordinates":[44.75702,33.90602],"type":"Point"}
}