{
  "type": "Feature",
  "properties": {
    "gn:admin1_code":"15.0",
    "gn:admin2_code":"9166541.0",
    "gn:asciiname":"Maftiyah Jadidah",
    "gn:country_code":"IQ",
    "gn:dem":268,
    "gn:feature_class":"P",
    "gn:feature_code":"PPL",
    "gn:name":"Maft\u012byah Jad\u012bdah",
    "gn:population":0,
    "gn:timezone":"Asia/Baghdad",
    "iso:country":"IQ",
    "name:ara_x_preferred":[
        "\u0645\u0641\u062a\u064a\u0629 \u062c\u062f\u064a\u062f\u0629"
    ],
    "name:und_x_variant":[
        "Maft\u012byah Jad\u012bdah"
    ],
    "wof:name":"Maftiyah Jadidah",
    "wof:placetype":"locality"
},
  "geometry": {"coordinates":[43.50451,36.29419],"type":"Point"}
}