{
  "type": "Feature",
  "properties": {
    "gn:admin1_code":"5.0",
    "gn:admin2_code":"92051.0",
    "gn:asciiname":"Baz Esip",
    "gn:country_code":"IQ",
    "gn:dem":890,
    "gn:feature_class":"P",
    "gn:feature_code":"PPL",
    "gn:name":"Baz Esip",
    "gn:population":0,
    "gn:timezone":"Asia/Baghdad",
    "iso:country":"IQ",
    "name:kur_x_preferred":[
        "Baz Esip"
    ],
    "name:und_x_variant":[
        "\u0628\u0627\u0632 \u0626\u06d5\u0633\u067e",
        "Baz Asp"
    ],
    "wof:name":"Baz Esip",
    "wof:placetype":"locality"
},
  "geometry": {"coordinates":[44.76447,36.38923],"type":"Point"}
}