{
  "type": "Feature",
  "properties": {
    "gn:admin1_code":"18.0",
    "gn:admin2_code":"91594.0",
    "gn:asciiname":"Hadar 'Abbas Muhammad",
    "gn:country_code":"IQ",
    "gn:dem":84,
    "gn:feature_class":"P",
    "gn:feature_code":"PPL",
    "gn:name":"\u1e28a\u1e11ar \u2018Abb\u0101s Mu\u1e29ammad",
    "gn:population":0,
    "gn:timezone":"Asia/Baghdad",
    "iso:country":"IQ",
    "name:ara_x_preferred":[
        "\u062d\u0636\u0631 \u0639\u0628\u0627\u0633 \u0645\u062d\u0645\u062f"
    ],
    "name:und_x_variant":[
        "\u1e28a\u1e11ar \u2018Abb\u0101s Mu\u1e29ammad"
    ],
    "wof:name":"Hadar 'Abbas Muhammad",
    "wof:placetype":"locality"
},
  "geometry": {"coordinates":[43.6634,34.21501],"type":"Point"}
}