{
  "type": "Feature",
  "properties": {
    "gn:admin1_code":"15.0",
    "gn:admin2_code":"9166649.0",
    "gn:asciiname":"Qaryat 'Ijbat al Akrad",
    "gn:country_code":"IQ",
    "gn:dem":206,
    "gn:feature_class":"P",
    "gn:feature_code":"PPL",
    "gn:name":"Qaryat \u2018Ijbat al Akr\u0101d",
    "gn:population":0,
    "gn:timezone":"Asia/Baghdad",
    "iso:country":"IQ",
    "name:ara_x_preferred":[
        "\u0642\u0631\u064a\u0629 \u0639\u062c\u0628\u0629 \u0627\u0644\u0627\u0643\u0631\u0627\u062f"
    ],
    "name:und_x_variant":[
        "Qaryat \u2018Ijbat al Akr\u0101d"
    ],
    "wof:name":"Qaryat 'Ijbat al Akrad",
    "wof:placetype":"locality"
},
  "geometry": {"coordinates":[43.18372,35.76962],"type":"Point"}
}