{
  "type": "Feature",
  "properties": {
    "gn:admin1_code":"5.0",
    "gn:admin2_code":"97416.0",
    "gn:asciiname":"Dotan",
    "gn:country_code":"IQ",
    "gn:dem":595,
    "gn:feature_class":"P",
    "gn:feature_code":"PPL",
    "gn:name":"D\u014dt\u0101n",
    "gn:population":0,
    "gn:timezone":"Asia/Baghdad",
    "iso:country":"IQ",
    "name:fra_x_preferred":[
        "Dotan"
    ],
    "name:kur_x_preferred":[
        "Dutan"
    ],
    "name:kur_x_variant":[
        "Dotan",
        "\u062f\u06c6\u062a\u0627\u0646",
        "\u062f\u0648\u062a\u0627\u0646"
    ],
    "name:nds_x_preferred":[
        "Dotan"
    ],
    "name:und_x_variant":[
        "D\u014dt\u0101n"
    ],
    "wof:name":"Dotan",
    "wof:placetype":"locality"
},
  "geometry": {"coordinates":[45.05028,35.37944],"type":"Point"}
}