{
  "type": "Feature",
  "properties": {
    "gn:admin1_code":"13.0",
    "gn:admin2_code":"6770659.0",
    "gn:asciiname":"Qaryat an Namlah",
    "gn:country_code":"IQ",
    "gn:dem":167,
    "gn:feature_class":"P",
    "gn:feature_code":"PPL",
    "gn:name":"Qaryat an Namlah",
    "gn:population":0,
    "gn:timezone":"Asia/Baghdad",
    "iso:country":"IQ",
    "name:ara_x_preferred":[
        "\u0642\u0631\u064a\u0629 \u0627\u0644\u0646\u0645\u0644\u0629"
    ],
    "wof:name":"Qaryat an Namlah",
    "wof:placetype":"locality"
},
  "geometry": {"coordinates":[43.59296,35.30828],"type":"Point"}
}