{
  "type": "Feature",
  "properties": {
    "gn:admin1_code":"1.0",
    "gn:admin2_code":"6765480.0",
    "gn:asciiname":"Suwaynikh",
    "gn:cc2":"IQ",
    "gn:country_code":"IQ",
    "gn:dem":90,
    "gn:feature_class":"P",
    "gn:feature_code":"PPL",
    "gn:name":"Suwaynikh",
    "gn:population":0,
    "gn:timezone":"Asia/Baghdad",
    "iso:country":"IQ",
    "name:und_x_variant":[
        "As Suwaynikh",
        "Suwainikh",
        "Suwaynikh"
    ],
    "wof:name":"Suwaynikh",
    "wof:placetype":"locality"
},
  "geometry": {"coordinates":[42.5125,34.01611],"type":"Point"}
}