{
  "type": "Feature",
  "properties": {
    "gn:admin1_code":"11.0",
    "gn:asciiname":"Sardkah",
    "gn:country_code":"IQ",
    "gn:dem":720,
    "gn:feature_class":"P",
    "gn:feature_code":"PPL",
    "gn:name":"S\u0101rdkah",
    "gn:population":0,
    "gn:timezone":"Asia/Baghdad",
    "iso:country":"IQ",
    "name:ara_x_preferred":[
        "\u0633\u0627\u0631\u062f\u0643\u0629"
    ],
    "name:und_x_variant":[
        "S\u0101rdkak",
        "S\u0101rdkah",
        "Sardka"
    ],
    "wof:name":"Sardkah",
    "wof:placetype":"locality"
},
  "geometry": {"coordinates":[44.9505,35.90712],"type":"Point"}
}