{
  "type": "Feature",
  "properties": {
    "gn:admin1_code":"10.0",
    "gn:admin2_code":"94590.0",
    "gn:asciiname":"Habdan",
    "gn:country_code":"IQ",
    "gn:dem":67,
    "gn:feature_class":"P",
    "gn:feature_code":"PPL",
    "gn:name":"Habd\u0101n",
    "gn:population":0,
    "gn:timezone":"Asia/Baghdad",
    "iso:country":"IQ",
    "name:ara_x_preferred":[
        "\u0647\u0628\u062f\u0627\u0646"
    ],
    "name:und_x_variant":[
        "\u1e28amd\u0101n",
        "Habd\u0101n"
    ],
    "wof:name":"Habdan",
    "wof:placetype":"locality"
},
  "geometry": {"coordinates":[44.90044,34.12783],"type":"Point"}
}