{
  "type": "Feature",
  "properties": {
    "gn:admin1_code":"18.0",
    "gn:admin2_code":"9166616.0",
    "gn:asciiname":"Hamad Khalil",
    "gn:country_code":"IQ",
    "gn:dem":42,
    "gn:feature_class":"P",
    "gn:feature_code":"PPL",
    "gn:name":"\u1e28amad Khal\u012bl",
    "gn:population":0,
    "gn:timezone":"Asia/Baghdad",
    "iso:country":"IQ",
    "name:ara_x_preferred":[
        "\u062d\u0645\u062f \u062e\u0644\u064a\u0644"
    ],
    "name:und_x_variant":[
        "\u1e28amad Khal\u012bl"
    ],
    "wof:name":"Hamad Khalil",
    "wof:placetype":"locality"
},
  "geometry": {"coordinates":[44.24023,33.89765999999999],"type":"Point"}
}