{
  "type": "Feature",
  "properties": {
    "gn:admin1_code":"15.0",
    "gn:admin2_code":"9166608.0",
    "gn:asciiname":"Khaznah",
    "gn:country_code":"IQ",
    "gn:dem":274,
    "gn:feature_class":"P",
    "gn:feature_code":"PPL",
    "gn:name":"Khaznah",
    "gn:population":0,
    "gn:timezone":"Asia/Baghdad",
    "iso:country":"IQ",
    "name:ara_x_preferred":[
        "\u062e\u0632\u0646\u0647"
    ],
    "wof:name":"Khaznah",
    "wof:placetype":"locality"
},
  "geometry": {"coordinates":[42.28918,35.93702000000001],"type":"Point"}
}