{
  "type": "Feature",
  "properties": {
    "gn:admin1_code":"15.0",
    "gn:admin2_code":"9166608.0",
    "gn:asciiname":"Al Khaznah",
    "gn:country_code":"IQ",
    "gn:dem":341,
    "gn:feature_class":"P",
    "gn:feature_code":"PPL",
    "gn:name":"Al Khaznah",
    "gn:population":0,
    "gn:timezone":"Asia/Baghdad",
    "iso:country":"IQ",
    "name:ara_x_preferred":[
        "\u0627\u0644\u062e\u0632\u0646\u0629"
    ],
    "wof:name":"Al Khaznah",
    "wof:placetype":"locality"
},
  "geometry": {"coordinates":[41.4031,36.08428],"type":"Point"}
}