{
  "type": "Feature",
  "properties": {
    "gn:admin1_code":"10.0",
    "gn:admin2_code":"9166680.0",
    "gn:asciiname":"Dawud Baqir",
    "gn:country_code":"IQ",
    "gn:dem":146,
    "gn:feature_class":"P",
    "gn:feature_code":"PPL",
    "gn:name":"D\u0101wud B\u0101qir",
    "gn:population":0,
    "gn:timezone":"Asia/Baghdad",
    "iso:country":"IQ",
    "name:ara_x_preferred":[
        "D\u0101wud B\u0101qir"
    ],
    "name:ara_x_variant":[
        "\u062f\u0627\u0648\u062f \u0628\u0627\u0642\u0631"
    ],
    "wof:name":"Dawud Baqir",
    "wof:placetype":"locality"
},
  "geometry": {"coordinates":[45.56855,33.77338],"type":"Point"}
}