{
  "type": "Feature",
  "properties": {
    "gn:admin1_code":"11.0",
    "gn:admin2_code":"93817.0",
    "gn:asciiname":"Qaryat Zumrat 'Abd Allah",
    "gn:country_code":"IQ",
    "gn:dem":219,
    "gn:feature_class":"P",
    "gn:feature_code":"PPL",
    "gn:name":"Qaryat Zumrat \u2018Abd All\u0101h",
    "gn:population":0,
    "gn:timezone":"Asia/Baghdad",
    "iso:country":"IQ",
    "name:ara_x_preferred":[
        "\u0642\u0631\u064a\u0629 \u0632\u0645\u0631\u0647 \u0639\u0628\u062f \ufdf2"
    ],
    "name:und_x_variant":[
        "Sinhis",
        "Zim\u0101ra",
        "Zumrah",
        "Zim\u0101rah",
        "Qaryat Zumrah \u2018Abd All\u0101h"
    ],
    "wof:name":"Qaryat Zumrat 'Abd Allah",
    "wof:placetype":"locality"
},
  "geometry": {"coordinates":[43.48863,36.01197],"type":"Point"}
}