{
  "type": "Feature",
  "properties": {
    "gn:admin1_code":"12.0",
    "gn:admin2_code":"94822.0",
    "gn:asciiname":"Hanumi",
    "gn:country_code":"IQ",
    "gn:dem":36,
    "gn:feature_class":"P",
    "gn:feature_code":"PPL",
    "gn:name":"\u1e28an\u016bm\u012b",
    "gn:population":0,
    "gn:timezone":"Asia/Baghdad",
    "iso:country":"IQ",
    "name:ara_x_preferred":[
        "\u062d\u0646\u0648\u0645\u064a"
    ],
    "name:und_x_variant":[
        "\u1e28an\u016bm\u012b"
    ],
    "wof:name":"Hanumi",
    "wof:placetype":"locality"
},
  "geometry": {"coordinates":[44.13441,32.64923],"type":"Point"}
}