{
  "type": "Feature",
  "properties": {
    "gn:admin1_code":"18.0",
    "gn:admin2_code":"91594.0",
    "gn:asciiname":"Jaddu' Jasim",
    "gn:country_code":"IQ",
    "gn:dem":100,
    "gn:feature_class":"P",
    "gn:feature_code":"PPL",
    "gn:name":"Jadd\u016b\u2018 J\u0101sim",
    "gn:population":0,
    "gn:timezone":"Asia/Baghdad",
    "iso:country":"IQ",
    "name:ara_x_preferred":[
        "\u062c\u062f\u0648\u0639 \u062c\u0627\u0633\u0645"
    ],
    "name:und_x_variant":[
        "Jadd\u016b\u2018 J\u0101sim"
    ],
    "wof:name":"Jaddu' Jasim",
    "wof:placetype":"locality"
},
  "geometry": {"coordinates":[43.52284,34.27543],"type":"Point"}
}