{
  "type": "Feature",
  "properties": {
    "gn:admin1_code":"6.0",
    "gn:admin2_code":"99358.0",
    "gn:asciiname":"'Uwayr Hadi",
    "gn:country_code":"IQ",
    "gn:dem":26,
    "gn:feature_class":"P",
    "gn:feature_code":"PPL",
    "gn:name":"\u2018Uwayr H\u0101d\u012b",
    "gn:population":0,
    "gn:timezone":"Asia/Baghdad",
    "iso:country":"IQ",
    "name:ara_x_preferred":[
        "\u0639\u0648\u064a\u0631 \u0647\u0627\u062f\u064a"
    ],
    "name:und_x_variant":[
        "\u2018Uwayr H\u0101d\u012b"
    ],
    "wof:name":"'Uwayr Hadi",
    "wof:placetype":"locality"
},
  "geometry": {"coordinates":[44.83066,32.34579],"type":"Point"}
}