{
  "type": "Feature",
  "properties": {
    "gn:admin1_code":"15.0",
    "gn:admin2_code":"98820.0",
    "gn:asciiname":"Barawah",
    "gn:country_code":"IQ",
    "gn:dem":382,
    "gn:feature_class":"P",
    "gn:feature_code":"PPL",
    "gn:name":"B\u0101r\u0101wah",
    "gn:population":0,
    "gn:timezone":"Asia/Baghdad",
    "iso:country":"IQ",
    "name:ara_x_preferred":[
        "\u0628\u0627\u0631\u0627\u0648\u0647"
    ],
    "name:kur_x_preferred":[
        "Barawe"
    ],
    "name:kur_x_variant":[
        "\u0628\u0627\u0631\u0627\u0648\u06d5",
        "Behrawe Musa",
        "Behrawa Musa",
        "\u0628\u06d5\u0647\u0631\u0627\u0648\u06d5 \u0645\u0648\u0633\u0627",
        "\u0628\u06d5\u0647\u0631\u0627\u0648\u0627 \u0645\u0648\u0633\u0627"
    ],
    "name:und_x_variant":[
        "Barawa",
        "B\u0101r\u0101wah"
    ],
    "wof:name":"Barawah",
    "wof:placetype":"locality"
},
  "geometry": {"coordinates":[43.97857,36.66334000000001],"type":"Point"}
}