{
  "type": "Feature",
  "properties": {
    "gn:admin1_code":"15.0",
    "gn:admin2_code":"9166608.0",
    "gn:asciiname":"Abu Sadirah",
    "gn:country_code":"IQ",
    "gn:dem":317,
    "gn:feature_class":"P",
    "gn:feature_code":"PPL",
    "gn:name":"Ab\u016b \u015ead\u012brah",
    "gn:population":0,
    "gn:timezone":"Asia/Baghdad",
    "iso:country":"IQ",
    "name:ara_x_preferred":[
        "\u0627\u0628\u0648 \u0635\u062f\u064a\u0631\u0629"
    ],
    "name:und_x_variant":[
        "Ab\u016b \u015ead\u012brah"
    ],
    "wof:name":"Abu Sadirah",
    "wof:placetype":"locality"
},
  "geometry": {"coordinates":[41.87717,36.05263],"type":"Point"}
}