{
  "type": "Feature",
  "properties": {
    "gn:admin1_code":"5.0",
    "gn:admin2_code":"92743.0",
    "gn:asciiname":"Baqi Awa",
    "gn:country_code":"IQ",
    "gn:dem":826,
    "gn:feature_class":"P",
    "gn:feature_code":"PPL",
    "gn:name":"Baq\u00ee Awa",
    "gn:population":0,
    "gn:timezone":"Asia/Baghdad",
    "iso:country":"IQ",
    "name:kur_x_preferred":[
        "Baq\u00ee Awa"
    ],
    "name:kur_x_variant":[
        "\u0628\u0627\u0642\u0649 \u0626\u0627\u0648\u0627"
    ],
    "name:und_x_variant":[
        "Baqiawa",
        "Baqi Awa"
    ],
    "wof:name":"Baqi Awa",
    "wof:placetype":"locality"
},
  "geometry": {"coordinates":[45.18379,36.34642],"type":"Point"}
}