{
  "type": "Feature",
  "properties": {
    "gn:admin1_code":"15.0",
    "gn:admin2_code":"9166620.0",
    "gn:asciiname":"Wardiyah",
    "gn:country_code":"IQ",
    "gn:dem":440,
    "gn:feature_class":"P",
    "gn:feature_code":"PPL",
    "gn:name":"Ward\u012byah",
    "gn:population":0,
    "gn:timezone":"Asia/Baghdad",
    "iso:country":"IQ",
    "name:ara_x_preferred":[
        "\u0648\u0631\u062f\u064a\u0629"
    ],
    "name:und_x_variant":[
        "Wardiya",
        "Ward\u012byah"
    ],
    "wof:name":"Wardiyah",
    "wof:placetype":"locality"
},
  "geometry": {"coordinates":[41.72784,36.28019000000001],"type":"Point"}
}