{
  "type": "Feature",
  "properties": {
    "gn:admin1_code":"14.0",
    "gn:admin2_code":"99305.0",
    "gn:asciiname":"Bayt 'Abbud",
    "gn:country_code":"IQ",
    "gn:dem":10,
    "gn:feature_class":"P",
    "gn:feature_code":"PPL",
    "gn:name":"Bayt \u2018Abb\u016bd",
    "gn:population":0,
    "gn:timezone":"Asia/Baghdad",
    "iso:country":"IQ",
    "name:und_x_variant":[
        "Bait \u2018Abud",
        "Bayt \u2018Abb\u016bd"
    ],
    "wof:name":"Bayt 'Abbud",
    "wof:placetype":"locality"
},
  "geometry": {"coordinates":[46.72833,32.38583],"type":"Point"}
}