{
  "type": "Feature",
  "properties": {
    "gn:admin1_code":"5.0",
    "gn:admin2_code":"9166684.0",
    "gn:asciiname":"Kani Bee",
    "gn:country_code":"IQ",
    "gn:dem":1232,
    "gn:feature_class":"P",
    "gn:feature_code":"PPL",
    "gn:name":"Kani Bee",
    "gn:population":0,
    "gn:timezone":"Asia/Baghdad",
    "iso:country":"IQ",
    "name:ara_x_preferred":[
        "K\u0101n\u012b B\u012b"
    ],
    "name:ara_x_variant":[
        "\u0643\u0627\u0646\u064a \u0628\u064a"
    ],
    "name:kur_x_preferred":[
        "Kan\u00ee B\u00ee"
    ],
    "name:kur_x_variant":[
        "\u0643\u0627\u0646\u0649 \u0628\u0649"
    ],
    "name:und_x_variant":[
        "K\u0101n\u012b Biyy"
    ],
    "wof:name":"Kani Bee",
    "wof:placetype":"locality"
},
  "geometry": {"coordinates":[46.04204,35.75275999999999],"type":"Point"}
}