{
  "type": "Feature",
  "properties": {
    "gn:admin1_code":"10.0",
    "gn:admin2_code":"99063.0",
    "gn:asciiname":"Qaryat Babilan",
    "gn:country_code":"IQ",
    "gn:dem":48,
    "gn:feature_class":"P",
    "gn:feature_code":"PPL",
    "gn:name":"Qaryat B\u0101bil\u0101n",
    "gn:population":0,
    "gn:timezone":"Asia/Baghdad",
    "iso:country":"IQ",
    "name:ara_x_preferred":[
        "\u0642\u0631\u064a\u0629 \u0628\u0627\u0628\u0644\u0627\u0646"
    ],
    "name:und_x_variant":[
        "Qaryat B\u0101bil\u0101n"
    ],
    "wof:name":"Qaryat Babilan",
    "wof:placetype":"locality"
},
  "geometry": {"coordinates":[44.79236,33.83505],"type":"Point"}
}