{
  "type": "Feature",
  "properties": {
    "gn:admin1_code":"15.0",
    "gn:admin2_code":"9166608.0",
    "gn:asciiname":"Umm Sur",
    "gn:country_code":"IQ",
    "gn:dem":342,
    "gn:feature_class":"P",
    "gn:feature_code":"PPL",
    "gn:name":"Umm S\u016br",
    "gn:population":0,
    "gn:timezone":"Asia/Baghdad",
    "iso:country":"IQ",
    "name:ara_x_preferred":[
        "\u0627\u0645 \u0633\u0648\u0631"
    ],
    "name:ara_x_variant":[
        "Umm S\u016br"
    ],
    "wof:name":"Umm Sur",
    "wof:placetype":"locality"
},
  "geometry": {"coordinates":[41.36427,36.08742],"type":"Point"}
}