{
  "type": "Feature",
  "properties": {
    "gn:admin1_code":"10.0",
    "gn:admin2_code":"94590.0",
    "gn:asciiname":"Ghuziljah",
    "gn:cc2":"IQ",
    "gn:country_code":"IQ",
    "gn:dem":57,
    "gn:feature_class":"P",
    "gn:feature_code":"PPL",
    "gn:name":"Ghuziljah",
    "gn:population":0,
    "gn:timezone":"Asia/Baghdad",
    "iso:country":"IQ",
    "name:und_x_variant":[
        "Ghuzilja",
        "Ghuziljah"
    ],
    "wof:name":"Ghuziljah",
    "wof:placetype":"locality"
},
  "geometry": {"coordinates":[44.96667,33.98333],"type":"Point"}
}