{
  "type": "Feature",
  "properties": {
    "gn:admin1_code":"12.0",
    "gn:admin2_code":"99345.0",
    "gn:asciiname":"Shahin Shakir",
    "gn:country_code":"IQ",
    "gn:dem":37,
    "gn:feature_class":"P",
    "gn:feature_code":"PPL",
    "gn:name":"Shah\u012bn Sh\u0101kir",
    "gn:population":0,
    "gn:timezone":"Asia/Baghdad",
    "iso:country":"IQ",
    "name:und_x_variant":[
        "Shah\u012bn Sh\u0101kir"
    ],
    "wof:name":"Shahin Shakir",
    "wof:placetype":"locality"
},
  "geometry": {"coordinates":[44.18639,32.665],"type":"Point"}
}