{
  "type": "Feature",
  "properties": {
    "gn:admin1_code":"17.0",
    "gn:admin2_code":"98861.0",
    "gn:asciiname":"Al Kartayn",
    "gn:country_code":"IQ",
    "gn:dem":347,
    "gn:feature_class":"P",
    "gn:feature_code":"PPL",
    "gn:name":"Al Kartayn",
    "gn:population":0,
    "gn:timezone":"Asia/Baghdad",
    "iso:country":"IQ",
    "name:ara_x_preferred":[
        "\u0627\u0644\u0643\u0631\u062a\u064a\u0646"
    ],
    "wof:name":"Al Kartayn",
    "wof:placetype":"locality"
},
  "geometry": {"coordinates":[43.15264000000001,31.0905],"type":"Point"}
}