{
  "type": "Feature",
  "properties": {
    "gn:admin1_code":"6.0",
    "gn:admin2_code":"99358.0",
    "gn:asciiname":"Shaykh 'Abbas al Khamis",
    "gn:country_code":"IQ",
    "gn:dem":29,
    "gn:feature_class":"P",
    "gn:feature_code":"PPL",
    "gn:name":"Shaykh \u2018Abb\u0101s al Kham\u012bs",
    "gn:population":0,
    "gn:timezone":"Asia/Baghdad",
    "iso:country":"IQ",
    "name:ara_x_preferred":[
        "\u0634\u064a\u062e \u0639\u0628\u0627\u0633 \u0627\u0644\u062e\u0645\u064a\u0633"
    ],
    "name:und_x_variant":[
        "Shaykh \u2018Abb\u0101s al Kham\u012bs"
    ],
    "wof:name":"Shaykh 'Abbas al Khamis",
    "wof:placetype":"locality"
},
  "geometry": {"coordinates":[44.79449,32.32425],"type":"Point"}
}