{
  "type": "Feature",
  "properties": {
    "gn:admin1_code":"18.0",
    "gn:admin2_code":"6872046.0",
    "gn:asciiname":"'Abd 'Abbas Hayfi",
    "gn:country_code":"IQ",
    "gn:dem":142,
    "gn:feature_class":"P",
    "gn:feature_code":"PPL",
    "gn:name":"\u2018Abd \u2018Abb\u0101s Hayf\u012b",
    "gn:population":0,
    "gn:timezone":"Asia/Baghdad",
    "iso:country":"IQ",
    "name:ara_x_preferred":[
        "\u0639\u0628\u062f \u0639\u0628\u0627\u0633 \u0647\u064a\u0641\u064a"
    ],
    "name:und_x_variant":[
        "\u2018Abd \u2018Abb\u0101s Hayf\u012b"
    ],
    "wof:name":"'Abd 'Abbas Hayfi",
    "wof:placetype":"locality"
},
  "geometry": {"coordinates":[43.22156,34.92361],"type":"Point"}
}