{
  "type": "Feature",
  "properties": {
    "gn:admin1_code":"5.0",
    "gn:admin2_code":"97416.0",
    "gn:asciiname":"Kurawah",
    "gn:country_code":"IQ",
    "gn:dem":608,
    "gn:feature_class":"P",
    "gn:feature_code":"PPL",
    "gn:name":"K\u016br\u0101wah",
    "gn:population":0,
    "gn:timezone":"Asia/Baghdad",
    "iso:country":"IQ",
    "name:ara_x_preferred":[
        "\u0643\u0648\u0631\u0627\u0648\u0647"
    ],
    "name:und_x_variant":[
        "Kor\u0101wah",
        "Kor\u0101wa",
        "K\u016br\u0101wah"
    ],
    "wof:name":"Kurawah",
    "wof:placetype":"locality"
},
  "geometry": {"coordinates":[44.8421,35.69532],"type":"Point"}
}