{
  "type": "Feature",
  "properties": {
    "gn:admin1_code":"4.0",
    "gn:admin2_code":"98634.0",
    "gn:asciiname":"Al Warishiyah",
    "gn:country_code":"IQ",
    "gn:dem":24,
    "gn:feature_class":"P",
    "gn:feature_code":"PPL",
    "gn:name":"Al W\u0101rish\u012byah",
    "gn:population":0,
    "gn:timezone":"Asia/Baghdad",
    "iso:country":"IQ",
    "name:ara_x_preferred":[
        "\u0627\u0644\u0648\u0627\u0631\u0634\u064a\u0629"
    ],
    "name:und_x_variant":[
        "Al W\u0101rish\u012byah"
    ],
    "wof:name":"Al Warishiyah",
    "wof:placetype":"locality"
},
  "geometry": {"coordinates":[44.56855,31.96455],"type":"Point"}
}