{
  "type": "Feature",
  "properties": {
    "gn:admin1_code":"16.0",
    "gn:admin2_code":"99351.0",
    "gn:asciiname":"Majid Bayg",
    "gn:country_code":"IQ",
    "gn:dem":17,
    "gn:feature_class":"P",
    "gn:feature_code":"PPL",
    "gn:name":"Maj\u012bd Bayg",
    "gn:population":0,
    "gn:timezone":"Asia/Baghdad",
    "iso:country":"IQ",
    "name:ara_x_preferred":[
        "\u0645\u062c\u064a\u062f \u0628\u064a\u06af"
    ],
    "name:und_x_variant":[
        "Maj\u012bd Bayg"
    ],
    "wof:name":"Majid Bayg",
    "wof:placetype":"locality"
},
  "geometry": {"coordinates":[45.97133,32.01965999999999],"type":"Point"}
}