{
  "type": "Feature",
  "properties": {
    "gn:admin1_code":"11.0",
    "gn:admin2_code":"9166591.0",
    "gn:asciiname":"Mam Pisark",
    "gn:country_code":"IQ",
    "gn:dem":503,
    "gn:feature_class":"P",
    "gn:feature_code":"PPL",
    "gn:name":"Mam P\u00eesark",
    "gn:population":0,
    "gn:timezone":"Asia/Baghdad",
    "iso:country":"IQ",
    "name:kur_x_preferred":[
        "Mam P\u00eesark"
    ],
    "name:kur_x_variant":[
        "\u0645\u0627\u0645 \u067e\u064a\u0633\u0627\u0631\u0643"
    ],
    "wof:name":"Mam Pisark",
    "wof:placetype":"locality"
},
  "geometry": {"coordinates":[44.22426,36.61568],"type":"Point"}
}