{
  "type": "Feature",
  "properties": {
    "gn:admin1_code":"3.0",
    "gn:admin2_code":"98532.0",
    "gn:asciiname":"Dabbus",
    "gn:country_code":"IQ",
    "gn:dem":13,
    "gn:feature_class":"P",
    "gn:feature_code":"PPL",
    "gn:name":"Dabb\u016bs",
    "gn:population":0,
    "gn:timezone":"Asia/Baghdad",
    "iso:country":"IQ",
    "name:ara_x_preferred":[
        "\u062f\u0628\u0648\u0633"
    ],
    "name:und_x_variant":[
        "Dabb\u016bs"
    ],
    "wof:name":"Dabbus",
    "wof:placetype":"locality"
},
  "geometry": {"coordinates":[45.40406,31.30598],"type":"Point"}
}