{
  "type": "Feature",
  "properties": {
    "gn:admin1_code":"3.0",
    "gn:admin2_code":"9166568.0",
    "gn:asciiname":"Sayyid 'Abd Allah",
    "gn:country_code":"IQ",
    "gn:dem":15,
    "gn:feature_class":"P",
    "gn:feature_code":"PPL",
    "gn:name":"Sayyid \u2018Abd All\u0101h",
    "gn:population":0,
    "gn:timezone":"Asia/Baghdad",
    "iso:country":"IQ",
    "name:ara_x_preferred":[
        "\u0633\u064a\u062f \u0639\u0628\u062f \u0627\u0644\u0644\u0647"
    ],
    "name:und_x_variant":[
        "Sayyid \u2018Abd All\u0101h"
    ],
    "wof:name":"Sayyid 'Abd Allah",
    "wof:placetype":"locality"
},
  "geometry": {"coordinates":[45.22079,31.51301],"type":"Point"}
}