{
  "type": "Feature",
  "properties": {
    "gn:admin1_code":"13.0",
    "gn:admin2_code":"94786.0",
    "gn:asciiname":"Al Buwaytir",
    "gn:country_code":"IQ",
    "gn:dem":242,
    "gn:feature_class":"P",
    "gn:feature_code":"PPL",
    "gn:name":"Al Buwayt\u012br",
    "gn:population":0,
    "gn:timezone":"Asia/Baghdad",
    "iso:country":"IQ",
    "name:und_x_variant":[
        "Al Buwayt\u012br"
    ],
    "wof:name":"Al Buwaytir",
    "wof:placetype":"locality"
},
  "geometry": {"coordinates":[44.1425,35.43360999999999],"type":"Point"}
}