{
  "type": "Feature",
  "properties": {
    "gn:admin1_code":"11.0",
    "gn:admin2_code":"9166588.0",
    "gn:asciiname":"Kele Xiwar",
    "gn:country_code":"IQ",
    "gn:dem":685,
    "gn:feature_class":"P",
    "gn:feature_code":"PPL",
    "gn:name":"K\u00eale Xiwar",
    "gn:population":0,
    "gn:timezone":"Asia/Baghdad",
    "iso:country":"IQ",
    "name:ara_x_preferred":[
        "\u0643\u064a\u0644\u0629 \u062e\u0648\u0627\u0631\u064a"
    ],
    "name:kur_x_preferred":[
        "\u0643\u06ce\u0644\u06d5 \u062e\u0648\u0627\u0631"
    ],
    "name:kur_x_variant":[
        "K\u00eale Xiwar",
        "K\u00eale Xiware",
        "\u0643\u06ce\u0644\u06d5 \u062e\u0648\u0627\u0631\u06d5"
    ],
    "name:und_x_variant":[
        "Kayla-\u012b Khw\u0101r\u016b",
        "Kela Khwara",
        "Kaylah Khuw\u0101r\u012b"
    ],
    "wof:name":"Kele Xiwar",
    "wof:placetype":"locality"
},
  "geometry": {"coordinates":[44.61366,36.09499],"type":"Point"}
}