{
  "type": "Feature",
  "properties": {
    "gn:admin1_code":"10.0",
    "gn:admin2_code":"99063.0",
    "gn:asciiname":"Salah ash Shantaf",
    "gn:country_code":"IQ",
    "gn:dem":52,
    "gn:feature_class":"P",
    "gn:feature_code":"PPL",
    "gn:name":"\u015eal\u0101\u1e29 ash Shant\u0101f",
    "gn:population":0,
    "gn:timezone":"Asia/Baghdad",
    "iso:country":"IQ",
    "name:ara_x_preferred":[
        "\u0635\u0644\u0627\u062d \u0627\u0644\u0634\u0646\u062a\u0627\u0641"
    ],
    "name:und_x_variant":[
        "\u2018Arab \u015e\u0101diq ash Shunn\u0101f",
        "\u015e\u0101li\u1e29 ash Shantaf",
        "\u015eal\u0101\u1e29 ash Shant\u0101f"
    ],
    "wof:name":"Salah ash Shantaf",
    "wof:placetype":"locality"
},
  "geometry": {"coordinates":[44.73088,33.99615],"type":"Point"}
}