{
  "type": "Feature",
  "properties": {
    "gn:admin1_code":"7.0",
    "gn:admin2_code":"99173.0",
    "gn:asciiname":"'Abd Mukhlif",
    "gn:country_code":"IQ",
    "gn:dem":36,
    "gn:feature_class":"P",
    "gn:feature_code":"PPL",
    "gn:name":"\u2018Abd Mukhlif",
    "gn:population":0,
    "gn:timezone":"Asia/Baghdad",
    "iso:country":"IQ",
    "name:ara_x_preferred":[
        "\u0639\u0628\u062f \u0645\u062e\u0644\u0641"
    ],
    "name:ara_x_variant":[
        "\u2018Abd Mukhlif"
    ],
    "wof:name":"'Abd Mukhlif",
    "wof:placetype":"locality"
},
  "geometry": {"coordinates":[44.23037,33.52123],"type":"Point"}
}