{
  "type": "Feature",
  "properties": {
    "gn:admin1_code":"15.0",
    "gn:admin2_code":"99414.0",
    "gn:asciiname":"Qaryat 'Abd al Jasim",
    "gn:country_code":"IQ",
    "gn:dem":208,
    "gn:feature_class":"P",
    "gn:feature_code":"PPL",
    "gn:name":"Qaryat \u2018Abd al J\u0101sim",
    "gn:population":0,
    "gn:timezone":"Asia/Baghdad",
    "iso:country":"IQ",
    "name:ara_x_preferred":[
        "\u0642\u0631\u064a\u0629 \u0639\u0628\u062f \u0627\u0644\u062c\u0627\u0633\u0645"
    ],
    "name:und_x_variant":[
        "Qaryat \u2018Abd al J\u0101sim"
    ],
    "wof:name":"Qaryat 'Abd al Jasim",
    "wof:placetype":"locality"
},
  "geometry": {"coordinates":[43.10445,35.69979],"type":"Point"}
}