{
  "type": "Feature",
  "properties": {
    "gn:admin1_code":"5.0",
    "gn:admin2_code":"92051.0",
    "gn:asciiname":"Bute",
    "gn:country_code":"IQ",
    "gn:dem":1031,
    "gn:feature_class":"P",
    "gn:feature_code":"PPL",
    "gn:name":"But\u00ea",
    "gn:population":0,
    "gn:timezone":"Asia/Baghdad",
    "iso:country":"IQ",
    "name:bar_x_preferred":[
        "Bute"
    ],
    "name:bre_x_preferred":[
        "Bute"
    ],
    "name:ceb_x_preferred":[
        "Bute"
    ],
    "name:cym_x_preferred":[
        "Bute"
    ],
    "name:deu_x_preferred":[
        "Bute"
    ],
    "name:fra_x_preferred":[
        "Bute"
    ],
    "name:ita_x_preferred":[
        "Bute"
    ],
    "name:kur_x_preferred":[
        "But\u00ea"
    ],
    "name:kur_x_variant":[
        "\u0628\u0648\u062a\u06ce"
    ],
    "name:nld_x_preferred":[
        "Bute"
    ],
    "name:nor_x_preferred":[
        "Bute"
    ],
    "name:srp_x_preferred":[
        "Bute"
    ],
    "name:swe_x_preferred":[
        "Bute"
    ],
    "name:ukr_x_preferred":[
        "\u0411'\u044e\u0442"
    ],
    "name:und_x_variant":[
        "Bote"
    ],
    "wof:name":"Bute",
    "wof:placetype":"locality"
},
  "geometry": {"coordinates":[44.76117,36.42025],"type":"Point"}
}