{
  "type": "Feature",
  "properties": {
    "gn:admin1_code":"6.0",
    "gn:admin2_code":"99358.0",
    "gn:asciiname":"Al Ibrahimiyah",
    "gn:country_code":"IQ",
    "gn:dem":35,
    "gn:feature_class":"P",
    "gn:feature_code":"PPL",
    "gn:name":"Al Ibr\u0101h\u012bm\u012byah",
    "gn:population":0,
    "gn:timezone":"Asia/Baghdad",
    "iso:country":"IQ",
    "name:ara_x_preferred":[
        "\u0627\u0644\u0627\u0628\u0631\u0627\u0647\u064a\u0645\u064a\u0629"
    ],
    "name:und_x_variant":[
        "Ad Diblah",
        "Qaryat Ibr\u0101h\u012bm\u012byah",
        "\u0627\u0644\u062f\u0628\u0644\u0629",
        "\u0642\u0631\u064a\u0629 \u0627\u0628\u0631\u0627\u0647\u064a\u0645\u064a\u0629",
        "Al Ibr\u0101h\u012bm\u012byah"
    ],
    "wof:name":"Al Ibrahimiyah",
    "wof:placetype":"locality"
},
  "geometry": {"coordinates":[44.53613,32.38661],"type":"Point"}
}