{
  "type": "Feature",
  "properties": {
    "gn:admin1_code":"18.0",
    "gn:admin2_code":"91594.0",
    "gn:asciiname":"Hamid Jum'ah",
    "gn:country_code":"IQ",
    "gn:dem":87,
    "gn:feature_class":"P",
    "gn:feature_code":"PPL",
    "gn:name":"\u1e28am\u012bd Jum\u2018ah",
    "gn:population":0,
    "gn:timezone":"Asia/Baghdad",
    "iso:country":"IQ",
    "name:ara_x_preferred":[
        "\u062d\u0645\u064a\u062f \u062c\u0645\u0639\u0629"
    ],
    "name:und_x_variant":[
        "\u1e28am\u012bd Jum\u2018ah"
    ],
    "wof:name":"Hamid Jum'ah",
    "wof:placetype":"locality"
},
  "geometry": {"coordinates":[43.7009,34.25652],"type":"Point"}
}