{
  "type": "Feature",
  "properties": {
    "gn:admin1_code":"18.0",
    "gn:admin2_code":"9167093.0",
    "gn:asciiname":"Rashid Habib Salih",
    "gn:country_code":"IQ",
    "gn:dem":77,
    "gn:feature_class":"P",
    "gn:feature_code":"PPL",
    "gn:name":"Rash\u012bd \u1e28ab\u012bb \u015e\u0101li\u1e29",
    "gn:population":0,
    "gn:timezone":"Asia/Baghdad",
    "iso:country":"IQ",
    "name:ara_x_preferred":[
        "\u0631\u0634\u064a\u062f \u062d\u0628\u064a\u0628 \u0635\u0627\u0644\u062d"
    ],
    "name:und_x_variant":[
        "Rash\u012bd \u1e28ab\u012bb \u015e\u0101li\u1e29"
    ],
    "wof:name":"Rashid Habib Salih",
    "wof:placetype":"locality"
},
  "geometry": {"coordinates":[43.67023,34.05974000000001],"type":"Point"}
}