{
  "type": "Feature",
  "properties": {
    "gn:admin1_code":"6.0",
    "gn:admin2_code":"99358.0",
    "gn:asciiname":"Kamil Muhammad",
    "gn:country_code":"IQ",
    "gn:dem":28,
    "gn:feature_class":"P",
    "gn:feature_code":"PPL",
    "gn:name":"K\u0101mil Mu\u1e29ammad",
    "gn:population":0,
    "gn:timezone":"Asia/Baghdad",
    "iso:country":"IQ",
    "name:ara_x_preferred":[
        "\u0643\u0627\u0645\u0644 \u0645\u062d\u0645\u062f"
    ],
    "name:und_x_variant":[
        "K\u0101mil Mu\u1e29ammad"
    ],
    "wof:name":"Kamil Muhammad",
    "wof:placetype":"locality"
},
  "geometry": {"coordinates":[44.78484,32.26915],"type":"Point"}
}