{
  "type": "Feature",
  "properties": {
    "gn:admin1_code":"14.0",
    "gn:admin2_code":"99305.0",
    "gn:asciiname":"'As Salihiyah",
    "gn:country_code":"IQ",
    "gn:dem":10,
    "gn:feature_class":"P",
    "gn:feature_code":"PPL",
    "gn:name":"\u2018As \u015e\u0101li\u1e29\u012byah",
    "gn:population":0,
    "gn:timezone":"Asia/Baghdad",
    "iso:country":"IQ",
    "name:und_x_variant":[
        "\u2018As \u015e\u0101li\u1e29\u012byah"
    ],
    "wof:name":"'As Salihiyah",
    "wof:placetype":"locality"
},
  "geometry": {"coordinates":[46.76528,32.09333],"type":"Point"}
}