{
  "type": "Feature",
  "properties": {
    "gn:admin1_code":"10.0",
    "gn:admin2_code":"97988.0",
    "gn:asciiname":"Mahmud al Khamis",
    "gn:country_code":"IQ",
    "gn:dem":37,
    "gn:feature_class":"P",
    "gn:feature_code":"PPL",
    "gn:name":"Ma\u1e29m\u016bd al Kham\u012bs",
    "gn:population":0,
    "gn:timezone":"Asia/Baghdad",
    "iso:country":"IQ",
    "name:und_x_variant":[
        "Ma\u1e29m\u016bd al Kham\u012bs"
    ],
    "wof:name":"Mahmud al Khamis",
    "wof:placetype":"locality"
},
  "geometry": {"coordinates":[44.48333,33.63333],"type":"Point"}
}