{
  "type": "Feature",
  "properties": {
    "gn:admin1_code":"11.0",
    "gn:admin2_code":"9166534.0",
    "gn:asciiname":"Sumi",
    "gn:country_code":"IQ",
    "gn:dem":985,
    "gn:feature_class":"P",
    "gn:feature_code":"PPL",
    "gn:name":"Sumi",
    "gn:population":0,
    "gn:timezone":"Asia/Baghdad",
    "iso:country":"IQ",
    "name:ara_x_preferred":[
        "\u0633\u0648\u0645\u064a"
    ],
    "name:ceb_x_preferred":[
        "Sumi"
    ],
    "name:deu_x_preferred":[
        "Sumi"
    ],
    "name:fra_x_preferred":[
        "Sumi"
    ],
    "name:ita_x_preferred":[
        "Sumi"
    ],
    "name:kur_x_preferred":[
        "Sum\u00ee"
    ],
    "name:kur_x_variant":[
        "\u0633\u0648\u0645\u0649",
        "Sum\u00ea",
        "\u0633\u0648\u0645\u06ce"
    ],
    "name:swe_x_preferred":[
        "Sumi"
    ],
    "name:und_x_variant":[
        "S\u016bmah",
        "S\u016bm\u0113",
        "S\u016bmay"
    ],
    "wof:name":"Sumi",
    "wof:placetype":"locality"
},
  "geometry": {"coordinates":[44.07784,37.14002],"type":"Point"}
}