{
  "type": "Feature",
  "properties": {
    "gn:admin1_code":"7.0",
    "gn:admin2_code":"99101.0",
    "gn:asciiname":"'Arab Jalab Ahmad",
    "gn:country_code":"IQ",
    "gn:dem":35,
    "gn:feature_class":"P",
    "gn:feature_code":"PPL",
    "gn:name":"\u2018Arab Jal\u0101b A\u1e29mad",
    "gn:population":0,
    "gn:timezone":"Asia/Baghdad",
    "iso:country":"IQ",
    "name:ara_x_preferred":[
        "\u0639\u0631\u0628 \u062c\u0644\u0627\u0628 \u0623\u062d\u0645\u062f"
    ],
    "name:und_x_variant":[
        "\u2018Arab Jal\u0101b A\u1e29mad"
    ],
    "wof:name":"'Arab Jalab Ahmad",
    "wof:placetype":"locality"
},
  "geometry": {"coordinates":[44.29469,33.07417],"type":"Point"}
}