{
  "type": "Feature",
  "properties": {
    "gn:admin1_code":"5.0",
    "gn:admin2_code":"96204.0",
    "gn:asciiname":"Kani Sibikah",
    "gn:country_code":"IQ",
    "gn:dem":556,
    "gn:feature_class":"P",
    "gn:feature_code":"PPL",
    "gn:name":"K\u0101n\u012b Sib\u012bkah",
    "gn:population":0,
    "gn:timezone":"Asia/Baghdad",
    "iso:country":"IQ",
    "name:ara_x_preferred":[
        "\u0643\u0627\u0646\u064a \u0633\u0628\u064a\u0643\u0629"
    ],
    "name:fas_x_preferred":[
        "\u06a9\u0627\u0646\u06cc \u0627\u0633\u067e\u06cc\u06a9\u0647"
    ],
    "name:fas_x_variant":[
        "K\u0101n\u012b Esp\u012bkah"
    ],
    "name:kur_x_preferred":[
        "Kan\u00ee Sp\u00eeke Berx"
    ],
    "name:kur_x_variant":[
        "Kan\u00ee Sp\u00eeke",
        "\u06a9\u0627\u0646\u06cc \u0633\u067e\u06cc\u06a9\u0647 \u0628\u06d5\u0631\u062e",
        "\u06a9\u0627\u0646\u06cc \u0633\u067e\u06cc\u06a9\u0647"
    ],
    "name:und_x_variant":[
        "K\u0101n\u012b Sp\u012bka",
        "K\u0101n\u012b Sib\u012bkah",
        "Kani Speeka Barkhi"
    ],
    "wof:name":"Kani Sibikah",
    "wof:placetype":"locality"
},
  "geometry": {"coordinates":[45.79265,35.39530999999999],"type":"Point"}
}