{
  "type": "Feature",
  "properties": {
    "gn:admin1_code":"5.0",
    "gn:admin2_code":"9166596.0",
    "gn:asciiname":"Qemteran",
    "gn:country_code":"IQ",
    "gn:dem":523,
    "gn:feature_class":"P",
    "gn:feature_code":"PPL",
    "gn:name":"Qemteran",
    "gn:population":0,
    "gn:timezone":"Asia/Baghdad",
    "iso:country":"IQ",
    "name:kur_x_preferred":[
        "\u0642\u06d5\u0645\u062a\u06d5\u0631\u0627\u0646"
    ],
    "name:kur_x_variant":[
        "Qamtaran",
        "Qemteran"
    ],
    "name:und_x_variant":[
        "Q\u016bm\u0163ar\u0101n"
    ],
    "wof:name":"Qemteran",
    "wof:placetype":"locality"
},
  "geometry": {"coordinates":[44.74117,36.15403],"type":"Point"}
}