{
  "type": "Feature",
  "properties": {
    "gn:admin1_code":"10.0",
    "gn:admin2_code":"9166680.0",
    "gn:asciiname":"Husayn Ahmad",
    "gn:country_code":"IQ",
    "gn:dem":49,
    "gn:feature_class":"P",
    "gn:feature_code":"PPL",
    "gn:name":"\u1e28usayn A\u1e29mad",
    "gn:population":0,
    "gn:timezone":"Asia/Baghdad",
    "iso:country":"IQ",
    "name:ara_x_preferred":[
        "\u062d\u0633\u064a\u0646 \u0627\u062d\u0645\u062f"
    ],
    "name:und_x_variant":[
        "\u1e28usayn A\u1e29mad"
    ],
    "wof:name":"Husayn Ahmad",
    "wof:placetype":"locality"
},
  "geometry": {"coordinates":[44.93695,33.79511],"type":"Point"}
}