{
  "type": "Feature",
  "properties": {
    "gn:admin1_code":"16.0",
    "gn:admin2_code":"98460.0",
    "gn:asciiname":"Sayyid 'Ulaywi",
    "gn:country_code":"IQ",
    "gn:dem":32,
    "gn:feature_class":"P",
    "gn:feature_code":"PPL",
    "gn:name":"Sayyid \u2018Ulayw\u012b",
    "gn:population":0,
    "gn:timezone":"Asia/Baghdad",
    "iso:country":"IQ",
    "name:und_x_variant":[
        "Saiyid \u2018Ulaiwi",
        "Sayyid \u2018Alaw\u012b",
        "Sayyid \u2018Ulayw\u012b"
    ],
    "wof:name":"Sayyid 'Ulaywi",
    "wof:placetype":"locality"
},
  "geometry": {"coordinates":[44.80389,32.91833],"type":"Point"}
}