{
  "type": "Feature",
  "properties": {
    "gn:admin1_code":"6.0",
    "gn:admin2_code":"99358.0",
    "gn:asciiname":"As Sayyid Muhammad",
    "gn:country_code":"IQ",
    "gn:dem":29,
    "gn:feature_class":"P",
    "gn:feature_code":"PPL",
    "gn:name":"As Sayyid Mu\u1e29ammad",
    "gn:population":0,
    "gn:timezone":"Asia/Baghdad",
    "iso:country":"IQ",
    "name:ara_x_preferred":[
        "\u0627\u0644\u0633\u064a\u062f \u0645\u062d\u0645\u062f"
    ],
    "name:und_x_variant":[
        "As Sayyid Mu\u1e29ammad"
    ],
    "wof:name":"As Sayyid Muhammad",
    "wof:placetype":"locality"
},
  "geometry": {"coordinates":[44.77336,32.35720999999999],"type":"Point"}
}