{
  "type": "Feature",
  "properties": {
    "gn:admin1_code":"5.0",
    "gn:admin2_code":"9166596.0",
    "gn:asciiname":"Qarachatan",
    "gn:country_code":"IQ",
    "gn:dem":945,
    "gn:feature_class":"P",
    "gn:feature_code":"PPL",
    "gn:name":"Qarachat\u0101n",
    "gn:population":0,
    "gn:timezone":"Asia/Baghdad",
    "iso:country":"IQ",
    "name:ara_x_preferred":[
        "\u0642\u0631\u0629 \u062c\u062a\u0627\u0646"
    ],
    "name:kur_x_preferred":[
        "Qerechetan"
    ],
    "name:kur_x_variant":[
        "\u0642\u06d5\u0631\u06d5\u0686\u06d5\u062a\u0627\u0646"
    ],
    "name:und_x_variant":[
        "Qarachat\u0101n",
        "Qarah Jat\u0101n",
        "Qarah Ch\u012bt\u0101n",
        "Qarachatan"
    ],
    "wof:name":"Qarachatan",
    "wof:placetype":"locality"
},
  "geometry": {"coordinates":[45.19157,35.74437],"type":"Point"}
}