{
  "type": "Feature",
  "properties": {
    "gn:admin1_code":"9.0",
    "gn:admin2_code":"98623.0",
    "gn:asciiname":"Jama'at al 'Abd al Yawa",
    "gn:country_code":"IQ",
    "gn:dem":7,
    "gn:feature_class":"P",
    "gn:feature_code":"PPL",
    "gn:name":"Jam\u0101\u2018at al \u2018Abd al Y\u0101w\u0101",
    "gn:population":0,
    "gn:timezone":"Asia/Baghdad",
    "iso:country":"IQ",
    "name:und_x_variant":[
        "Jam\u0101\u2018at al \u2018Abd al Y\u0101w\u0101"
    ],
    "wof:name":"Jama'at al 'Abd al Yawa",
    "wof:placetype":"locality"
},
  "geometry": {"coordinates":[46.36667,31.33333],"type":"Point"}
}