{
  "type": "Feature",
  "properties": {
    "gn:admin1_code":"8.0",
    "gn:admin2_code":"99612.0",
    "gn:asciiname":"Sararu",
    "gn:country_code":"IQ",
    "gn:dem":1394,
    "gn:feature_class":"P",
    "gn:feature_code":"PPL",
    "gn:name":"Sar\u0101r\u016b",
    "gn:population":0,
    "gn:timezone":"Asia/Baghdad",
    "iso:country":"IQ",
    "name:ara_x_preferred":[
        "\u0633\u0631\u0627\u0631\u0648"
    ],
    "name:kur_x_preferred":[
        "Seradu"
    ],
    "name:kur_x_variant":[
        "\u0633\u06d5\u0631\u0627\u062f\u0648",
        "Sere\u1e5fu",
        "\u0633\u06d5\u0631\u06d5\u0695\u0648"
    ],
    "name:und_x_variant":[
        "Sirarah",
        "Srado",
        "Sar\u0101r\u016b",
        "Sur\u016br"
    ],
    "wof:name":"Sararu",
    "wof:placetype":"locality"
},
  "geometry": {"coordinates":[43.29268,37.24622],"type":"Point"}
}