{
  "type": "Feature",
  "properties": {
    "gn:admin1_code":"9.0",
    "gn:admin2_code":"98700.0",
    "gn:asciiname":"Qaryat as Salayit",
    "gn:country_code":"IQ",
    "gn:dem":11,
    "gn:feature_class":"P",
    "gn:feature_code":"PPL",
    "gn:name":"Qaryat as Sal\u0101yi\u0163",
    "gn:population":0,
    "gn:timezone":"Asia/Baghdad",
    "iso:country":"IQ",
    "name:ara_x_preferred":[
        "\u0642\u0631\u064a\u0629 \u0627\u0644\u0633\u0644\u0627\u064a\u0637"
    ],
    "name:und_x_variant":[
        "Qaryat as Sal\u0101yi\u0163"
    ],
    "wof:name":"Qaryat as Salayit",
    "wof:placetype":"locality"
},
  "geometry": {"coordinates":[46.14117,31.92632],"type":"Point"}
}