{
  "type": "Feature",
  "properties": {
    "gn:admin1_code":"11.0",
    "gn:admin2_code":"9166592.0",
    "gn:asciiname":"Xatunawa",
    "gn:country_code":"IQ",
    "gn:dem":665,
    "gn:feature_class":"P",
    "gn:feature_code":"PPL",
    "gn:name":"Xatunawa",
    "gn:population":0,
    "gn:timezone":"Asia/Baghdad",
    "iso:country":"IQ",
    "name:kur_x_preferred":[
        "Xatunawa"
    ],
    "name:kur_x_variant":[
        "\u062e\u0627\u062a\u0648\u0646\u0627\u0648\u06d5"
    ],
    "name:und_x_variant":[
        "Khatonawa"
    ],
    "wof:name":"Xatunawa",
    "wof:placetype":"locality"
},
  "geometry": {"coordinates":[44.51814,36.70014000000001],"type":"Point"}
}