{
  "type": "Feature",
  "properties": {
    "gn:admin1_code":"13.0",
    "gn:admin2_code":"6770659.0",
    "gn:asciiname":"`Arab Sayyid `Abd al Muttalib",
    "gn:country_code":"IQ",
    "gn:dem":178,
    "gn:feature_class":"P",
    "gn:feature_code":"PPL",
    "gn:name":"\u2018Arab Sayyid \u2018Abd al Mu\u0163\u0163alib",
    "gn:population":0,
    "gn:timezone":"Asia/Baghdad",
    "iso:country":"IQ",
    "name:ara_x_preferred":[
        "\u0639\u0631\u0628 \u0633\u064a\u062f \u0639\u0628\u062f \u0627\u0644\u0645\u0637\u0644\u0628"
    ],
    "name:und_x_variant":[
        "Jadad",
        "Jididi",
        "Qaryat al Jad\u012bdah",
        "\u2018Arab Sayyid \u2018Abd al Mu\u0163\u0163alib"
    ],
    "wof:name":"`Arab Sayyid `Abd al Muttalib",
    "wof:placetype":"locality"
},
  "geometry": {"coordinates":[43.74,35.43170999999999],"type":"Point"}
}