{
  "type": "Feature",
  "properties": {
    "gn:admin1_code":"5.0",
    "gn:admin2_code":"9166596.0",
    "gn:asciiname":"Bingird",
    "gn:country_code":"IQ",
    "gn:dem":632,
    "gn:feature_class":"P",
    "gn:feature_code":"PPL",
    "gn:name":"Bingird",
    "gn:population":0,
    "gn:timezone":"Asia/Baghdad",
    "iso:country":"IQ",
    "name:kur_x_preferred":[
        "Bngird"
    ],
    "name:kur_x_variant":[
        "\u0628\u0646\u06af\u0631\u062f"
    ],
    "name:und_x_variant":[
        "Bankard",
        "Bingird",
        "Bngrd",
        "Bingrd"
    ],
    "wof:name":"Bingird",
    "wof:placetype":"locality"
},
  "geometry": {"coordinates":[45.04783,36.06639000000001],"type":"Point"}
}