{
  "type": "Feature",
  "properties": {
    "gn:admin1_code":"13.0",
    "gn:admin2_code":"6770659.0",
    "gn:asciiname":"Muhammad an Nabah",
    "gn:country_code":"IQ",
    "gn:dem":195,
    "gn:feature_class":"P",
    "gn:feature_code":"PPL",
    "gn:name":"Mu\u1e29ammad an Naba\u1e29",
    "gn:population":0,
    "gn:timezone":"Asia/Baghdad",
    "iso:country":"IQ",
    "name:ara_x_preferred":[
        "\u0645\u062d\u0645\u062f \u0627\u0644\u0646\u0628\u062d"
    ],
    "name:und_x_variant":[
        "Mu\u1e29ammad an Naba\u1e29"
    ],
    "wof:name":"Muhammad an Nabah",
    "wof:placetype":"locality"
},
  "geometry": {"coordinates":[43.78716,35.34966],"type":"Point"}
}