{
  "type": "Feature",
  "properties": {
    "gn:admin1_code":"5.0",
    "gn:admin2_code":"97416.0",
    "gn:asciiname":"Gur Gimi Shamar",
    "gn:country_code":"IQ",
    "gn:dem":732,
    "gn:feature_class":"P",
    "gn:feature_code":"PPL",
    "gn:name":"G\u016br G\u012bm\u012b Sh\u0101m\u0101r",
    "gn:population":0,
    "gn:timezone":"Asia/Baghdad",
    "iso:country":"IQ",
    "name:ara_x_preferred":[
        "G\u016br G\u012bm\u012b Sh\u0101m\u0101r"
    ],
    "name:ara_x_variant":[
        "\u06af\u0648\u0631 \u06af\u064a\u0645\u064a \u0634\u0627\u0645\u0627\u0631"
    ],
    "wof:name":"Gur Gimi Shamar",
    "wof:placetype":"locality"
},
  "geometry": {"coordinates":[44.86017,35.57809],"type":"Point"}
}