{
  "type": "Feature",
  "properties": {
    "gn:admin1_code":"7.0",
    "gn:admin2_code":"99101.0",
    "gn:asciiname":"Fadil Harj",
    "gn:country_code":"IQ",
    "gn:dem":38,
    "gn:feature_class":"P",
    "gn:feature_code":"PPL",
    "gn:name":"F\u0101\u1e11il \u1e28arj",
    "gn:population":0,
    "gn:timezone":"Asia/Baghdad",
    "iso:country":"IQ",
    "name:ara_x_preferred":[
        "\u0641\u0627\u0636\u0644 \u062d\u0631\u062c"
    ],
    "name:und_x_variant":[
        "F\u0101\u1e11il \u1e28arj"
    ],
    "wof:name":"Fadil Harj",
    "wof:placetype":"locality"
},
  "geometry": {"coordinates":[44.26983,33.06905],"type":"Point"}
}