{
  "type": "Feature",
  "properties": {
    "gn:admin1_code":"16.0",
    "gn:admin2_code":"9166961.0",
    "gn:asciiname":"Hasim al Ahwab",
    "gn:country_code":"IQ",
    "gn:dem":29,
    "gn:feature_class":"P",
    "gn:feature_code":"PPL",
    "gn:name":"\u1e28\u0101sim al Ahwab",
    "gn:population":0,
    "gn:timezone":"Asia/Baghdad",
    "iso:country":"IQ",
    "name:ara_x_preferred":[
        "\u062d\u0627\u0633\u0645 \u0627\u0644\u0627\u0647\u0648\u0628"
    ],
    "name:und_x_variant":[
        "\u1e28\u0101sim al Ahwab"
    ],
    "wof:name":"Hasim al Ahwab",
    "wof:placetype":"locality"
},
  "geometry": {"coordinates":[44.88678,32.98532],"type":"Point"}
}