{
  "type": "Feature",
  "properties": {
    "gn:admin1_code":"5.0",
    "gn:admin2_code":"97416.0",
    "gn:asciiname":"Mamat Lays",
    "gn:country_code":"IQ",
    "gn:dem":534,
    "gn:feature_class":"P",
    "gn:feature_code":"PPL",
    "gn:name":"M\u0101mat Lays",
    "gn:population":0,
    "gn:timezone":"Asia/Baghdad",
    "iso:country":"IQ",
    "name:ara_x_preferred":[
        "\u0645\u0627\u0645\u0629 \u0644\u064a\u0633"
    ],
    "name:und_x_variant":[
        "M\u0101mat Lays",
        "Nam Lasi"
    ],
    "wof:name":"Mamat Lays",
    "wof:placetype":"locality"
},
  "geometry": {"coordinates":[44.76313,35.81934000000001],"type":"Point"}
}