{
  "type": "Feature",
  "properties": {
    "gn:admin1_code":"18.0",
    "gn:admin2_code":"6872046.0",
    "gn:asciiname":"Qaryat as Sakriyah",
    "gn:country_code":"IQ",
    "gn:dem":128,
    "gn:feature_class":"P",
    "gn:feature_code":"PPL",
    "gn:name":"Qaryat a\u015f \u015eakr\u012byah",
    "gn:population":0,
    "gn:timezone":"Asia/Baghdad",
    "iso:country":"IQ",
    "name:ara_x_preferred":[
        "\u0642\u0631\u064a\u0629 \u0627\u0644\u0635\u0643\u0631\u064a\u0629"
    ],
    "name:und_x_variant":[
        "Qaryat a\u015f \u015eakr\u012byah"
    ],
    "wof:name":"Qaryat as Sakriyah",
    "wof:placetype":"locality"
},
  "geometry": {"coordinates":[43.10258,35.08218],"type":"Point"}
}