{
  "type": "Feature",
  "properties": {
    "gn:admin1_code":"6.0",
    "gn:admin2_code":"99040.0",
    "gn:asciiname":"Qaryat Albu Rajab",
    "gn:country_code":"IQ",
    "gn:dem":36,
    "gn:feature_class":"P",
    "gn:feature_code":"PPL",
    "gn:name":"Qaryat \u0100lb\u016b Rajab",
    "gn:population":0,
    "gn:timezone":"Asia/Baghdad",
    "iso:country":"IQ",
    "name:ara_x_preferred":[
        "\u0642\u0631\u064a\u0629 \u0627\u0644\u0628\u0648 \u0631\u062c\u0628"
    ],
    "name:und_x_variant":[
        "Qaryat \u0100lb\u016b Rajab"
    ],
    "wof:name":"Qaryat Albu Rajab",
    "wof:placetype":"locality"
},
  "geometry": {"coordinates":[44.39572,32.60258],"type":"Point"}
}