{
  "type": "Feature",
  "properties": {
    "gn:admin1_code":"3.0",
    "gn:admin2_code":"98534.0",
    "gn:asciiname":"Ash Shukhayyah",
    "gn:country_code":"IQ",
    "gn:dem":216,
    "gn:feature_class":"P",
    "gn:feature_code":"PPL",
    "gn:name":"Ash Shukhayyah",
    "gn:population":0,
    "gn:timezone":"Asia/Baghdad",
    "iso:country":"IQ",
    "name:ara_x_preferred":[
        "\u0627\u0644\u0634\u062e\u064a\u0629"
    ],
    "wof:name":"Ash Shukhayyah",
    "wof:placetype":"locality"
},
  "geometry": {"coordinates":[45.78763,29.90838],"type":"Point"}
}