{
  "type": "Feature",
  "properties": {
    "gn:admin1_code":"1.0",
    "gn:admin2_code":"9166579.0",
    "gn:asciiname":"Al Habsiyah",
    "gn:country_code":"IQ",
    "gn:dem":65,
    "gn:feature_class":"P",
    "gn:feature_code":"PPL",
    "gn:name":"Al \u1e28abs\u012byah",
    "gn:population":0,
    "gn:timezone":"Asia/Baghdad",
    "iso:country":"IQ",
    "name:ara_x_preferred":[
        "\u0627\u0644\u062d\u0628\u0633\u064a\u0629"
    ],
    "name:und_x_variant":[
        "Al \u1e28abs\u012byah"
    ],
    "wof:name":"Al Habsiyah",
    "wof:placetype":"locality"
},
  "geometry": {"coordinates":[42.78799,33.69221],"type":"Point"}
}