{
  "type": "Feature",
  "properties": {
    "gn:admin1_code":"15.0",
    "gn:admin2_code":"99414.0",
    "gn:asciiname":"Buthat Amshirfah",
    "gn:country_code":"IQ",
    "gn:dem":249,
    "gn:feature_class":"P",
    "gn:feature_code":"PPL",
    "gn:name":"B\u016bthat Amsh\u012brfah",
    "gn:population":0,
    "gn:timezone":"Asia/Baghdad",
    "iso:country":"IQ",
    "name:ara_x_preferred":[
        "\u0628\u0648\u062b\u0647 \u0627\u0645\u0634\u064a\u0631\u0641\u0647"
    ],
    "name:und_x_variant":[
        "B\u016bthat Amsh\u012brfah"
    ],
    "wof:name":"Buthat Amshirfah",
    "wof:placetype":"locality"
},
  "geometry": {"coordinates":[42.38656,35.91722],"type":"Point"}
}