{
  "type": "Feature",
  "properties": {
    "gn:admin1_code":"1.0",
    "gn:admin2_code":"9166579.0",
    "gn:asciiname":"Albu Ghassaf",
    "gn:country_code":"IQ",
    "gn:dem":70,
    "gn:feature_class":"P",
    "gn:feature_code":"PPL",
    "gn:name":"\u0100lb\u016b Ghass\u0101f",
    "gn:population":0,
    "gn:timezone":"Asia/Baghdad",
    "iso:country":"IQ",
    "name:ara_x_preferred":[
        "\u0627\u0644\u0628\u0648 \u063a\u0633\u0627\u0641"
    ],
    "name:und_x_variant":[
        "\u0100lb\u016b Ghass\u0101f"
    ],
    "wof:name":"Albu Ghassaf",
    "wof:placetype":"locality"
},
  "geometry": {"coordinates":[43.03093,34.10147],"type":"Point"}
}