{
  "type": "Feature",
  "properties": {
    "gn:admin1_code":"6.0",
    "gn:admin2_code":"6818313.0",
    "gn:asciiname":"As Sayyid Rida'",
    "gn:country_code":"IQ",
    "gn:dem":28,
    "gn:feature_class":"P",
    "gn:feature_code":"PPL",
    "gn:name":"As Sayyid Ri\u1e11\u0101\u2019",
    "gn:population":0,
    "gn:timezone":"Asia/Baghdad",
    "iso:country":"IQ",
    "name:und_x_variant":[
        "Sayyid Ri\u1e11\u0101",
        "Saiyid Ridha",
        "As Sayyid Ri\u1e11\u0101\u2019"
    ],
    "wof:name":"As Sayyid Rida'",
    "wof:placetype":"locality"
},
  "geometry": {"coordinates":[44.61972,32.56361],"type":"Point"}
}