{
  "type": "Feature",
  "properties": {
    "gn:admin1_code":"3.0",
    "gn:admin2_code":"9166568.0",
    "gn:asciiname":"Albu Hasan",
    "gn:country_code":"IQ",
    "gn:dem":16,
    "gn:feature_class":"P",
    "gn:feature_code":"PPLL",
    "gn:name":"\u0100lb\u016b \u1e28asan",
    "gn:population":0,
    "gn:timezone":"Asia/Baghdad",
    "iso:country":"IQ",
    "name:ara_x_preferred":[
        "\u0627\u0644\u0628\u0648 \u062d\u0633\u0646"
    ],
    "name:und_x_variant":[
        "\u0100lb\u016b \u1e28asan"
    ],
    "wof:name":"Albu Hasan",
    "wof:placetype":"locality"
},
  "geometry": {"coordinates":[45.22846,31.47886],"type":"Point"}
}