{
  "type": "Feature",
  "properties": {
    "gn:admin1_code":"11.0",
    "gn:admin2_code":"9166588.0",
    "gn:asciiname":"Bugad",
    "gn:country_code":"IQ",
    "gn:dem":444,
    "gn:feature_class":"P",
    "gn:feature_code":"PPL",
    "gn:name":"B\u016bgad",
    "gn:population":0,
    "gn:timezone":"Asia/Baghdad",
    "iso:country":"IQ",
    "name:ara_x_preferred":[
        "\u0628\u0648\u06af\u062f"
    ],
    "name:und_x_variant":[
        "B\u016bgad",
        "B\u016bkad",
        "\u0628\u0648\u0643\u062f"
    ],
    "wof:name":"Bugad",
    "wof:placetype":"locality"
},
  "geometry": {"coordinates":[44.8622,35.90442],"type":"Point"}
}