{
  "type": "Feature",
  "properties": {
    "gn:admin1_code":"6.0",
    "gn:admin2_code":"99358.0",
    "gn:asciiname":"Salman Jasim",
    "gn:country_code":"IQ",
    "gn:dem":27,
    "gn:feature_class":"P",
    "gn:feature_code":"PPL",
    "gn:name":"Salm\u0101n J\u0101sim",
    "gn:population":0,
    "gn:timezone":"Asia/Baghdad",
    "iso:country":"IQ",
    "name:ara_x_preferred":[
        "\u0633\u0644\u0645\u0627\u0646 \u062c\u0627\u0633\u0645"
    ],
    "name:und_x_variant":[
        "Salm\u0101n J\u0101sim"
    ],
    "wof:name":"Salman Jasim",
    "wof:placetype":"locality"
},
  "geometry": {"coordinates":[44.84762,32.34337],"type":"Point"}
}