{
  "type": "Feature",
  "properties": {
    "gn:admin1_code":"18.0",
    "gn:admin2_code":"6783103.0",
    "gn:asciiname":"Namis Daham",
    "gn:country_code":"IQ",
    "gn:dem":89,
    "gn:feature_class":"P",
    "gn:feature_code":"PPL",
    "gn:name":"N\u0101mis Da\u1e29\u0101m",
    "gn:population":0,
    "gn:timezone":"Asia/Baghdad",
    "iso:country":"IQ",
    "name:ara_x_preferred":[
        "\u0646\u0627\u0645\u0633 \u062f\u062d\u0627\u0645"
    ],
    "name:und_x_variant":[
        "N\u0101mis Da\u1e29\u0101m"
    ],
    "wof:name":"Namis Daham",
    "wof:placetype":"locality"
},
  "geometry": {"coordinates":[43.87633,34.48135],"type":"Point"}
}