{
  "type": "Feature",
  "properties": {
    "gn:admin1_code":"9.0",
    "gn:admin2_code":"98855.0",
    "gn:asciiname":"Al Umfuwah",
    "gn:country_code":"IQ",
    "gn:dem":6,
    "gn:feature_class":"P",
    "gn:feature_code":"PPL",
    "gn:name":"Al Umfuwah",
    "gn:population":0,
    "gn:timezone":"Asia/Baghdad",
    "iso:country":"IQ",
    "name:ara_x_preferred":[
        "\u0627\u0644\u0627\u0645\u0641\u0648\u0629"
    ],
    "wof:name":"Al Umfuwah",
    "wof:placetype":"locality"
},
  "geometry": {"coordinates":[45.96097,31.02603],"type":"Point"}
}