{
  "type": "Feature",
  "properties": {
    "gn:admin1_code":"9.0",
    "gn:admin2_code":"98855.0",
    "gn:asciiname":"Tall Sabhah",
    "gn:country_code":"IQ",
    "gn:dem":4,
    "gn:feature_class":"P",
    "gn:feature_code":"PPLL",
    "gn:name":"Tall \u015eab\u1e29ah",
    "gn:population":0,
    "gn:timezone":"Asia/Baghdad",
    "iso:country":"IQ",
    "name:ara_x_preferred":[
        "\u062a\u0644 \u0635\u0628\u062d\u0629"
    ],
    "name:und_x_variant":[
        "Tall \u015eab\u1e29ah"
    ],
    "wof:name":"Tall Sabhah",
    "wof:placetype":"locality"
},
  "geometry": {"coordinates":[46.67247,31.10138],"type":"Point"}
}