{
  "type": "Feature",
  "properties": {
    "gn:admin1_code":"4.0",
    "gn:admin2_code":"99763.0",
    "gn:asciiname":"Kuwam 'Umran",
    "gn:country_code":"IQ",
    "gn:dem":26,
    "gn:feature_class":"P",
    "gn:feature_code":"PPL",
    "gn:name":"Kuw\u0101m \u2018Umr\u0101n",
    "gn:population":0,
    "gn:timezone":"Asia/Baghdad",
    "iso:country":"IQ",
    "name:ara_x_preferred":[
        "\u0643\u0648\u0627\u0645 \u0639\u0645\u0631\u0627\u0646"
    ],
    "name:ara_x_variant":[
        "Kuw\u0101m \u2018Umr\u0101n"
    ],
    "wof:name":"Kuwam 'Umran",
    "wof:placetype":"locality"
},
  "geometry": {"coordinates":[44.81603,32.10162],"type":"Point"}
}