{
  "type": "Feature",
  "properties": {
    "gn:admin1_code":"10.0",
    "gn:admin2_code":"97988.0",
    "gn:asciiname":"Mansuriyat ash Shatt",
    "gn:country_code":"IQ",
    "gn:dem":42,
    "gn:feature_class":"P",
    "gn:feature_code":"PPL",
    "gn:name":"Man\u015f\u016br\u012byat ash Sha\u0163\u0163",
    "gn:population":0,
    "gn:timezone":"Asia/Baghdad",
    "iso:country":"IQ",
    "name:ara_x_preferred":[
        "\u0645\u0646\u0635\u0648\u0631\u064a\u0629 \u0627\u0644\u0634\u0637"
    ],
    "name:und_x_variant":[
        "Mansurie",
        "Al Mans\u016br\u012bya",
        "Mans\u016br\u012bya",
        "Al Man\u015f\u016br\u012byah",
        "Man\u015f\u016br\u012byat ash Sha\u0163\u0163",
        "Mansuriyah"
    ],
    "wof:name":"Mansuriyat ash Shatt",
    "wof:placetype":"locality"
},
  "geometry": {"coordinates":[44.39817,33.76002],"type":"Point"}
}