{
  "type": "Feature",
  "properties": {
    "gn:admin1_code":"4.0",
    "gn:admin2_code":"6850588.0",
    "gn:asciiname":"Jabir Faza'",
    "gn:country_code":"IQ",
    "gn:dem":15,
    "gn:feature_class":"P",
    "gn:feature_code":"PPL",
    "gn:name":"J\u0101bir Faz\u0101\u2018",
    "gn:population":0,
    "gn:timezone":"Asia/Baghdad",
    "iso:country":"IQ",
    "name:ara_x_preferred":[
        "\u062c\u0627\u0628\u0631 \u0641\u0632\u0627\u0639"
    ],
    "name:und_x_variant":[
        "Al \u2018Aysh",
        "\u0627\u0644\u0639\u064a\u0634",
        "J\u0101bir Faz\u0101\u2018"
    ],
    "wof:name":"Jabir Faza'",
    "wof:placetype":"locality"
},
  "geometry": {"coordinates":[44.98445,31.50255],"type":"Point"}
}