{
  "type": "Feature",
  "properties": {
    "gn:admin1_code":"4.0",
    "gn:admin2_code":"99737.0",
    "gn:asciiname":"Al 'Awawidah",
    "gn:country_code":"IQ",
    "gn:dem":24,
    "gn:feature_class":"P",
    "gn:feature_code":"PPL",
    "gn:name":"Al \u2018Aw\u0101widah",
    "gn:population":0,
    "gn:timezone":"Asia/Baghdad",
    "iso:country":"IQ",
    "name:ara_x_preferred":[
        "\u0627\u0644\u0639\u0648\u0627\u0648\u062f\u0629"
    ],
    "name:und_x_variant":[
        "Al \u2018Aw\u0101widah"
    ],
    "wof:name":"Al 'Awawidah",
    "wof:placetype":"locality"
},
  "geometry": {"coordinates":[45.16096,32.05003],"type":"Point"}
}