{
  "type": "Feature",
  "properties": {
    "gn:admin1_code":"5.0",
    "gn:admin2_code":"97416.0",
    "gn:asciiname":"Kani Hanjir Shaykh Bazani",
    "gn:country_code":"IQ",
    "gn:dem":442,
    "gn:feature_class":"P",
    "gn:feature_code":"PPL",
    "gn:name":"K\u0101n\u012b Hanj\u012br Shaykh Baz\u0101n\u012b",
    "gn:population":0,
    "gn:timezone":"Asia/Baghdad",
    "iso:country":"IQ",
    "name:ara_x_preferred":[
        "\u0643\u0627\u0646\u064a \u0647\u0646\u062c\u064a\u0631 \u0634\u064a\u062e \u0628\u0632\u0627\u0646\u064a"
    ],
    "name:und_x_variant":[
        "Kh\u0101n\u0101b\u012b",
        "K\u0101n\u012b Hanj\u012br Shaykh Baz\u0101n\u012b",
        "Kan\u012b Hanj\u012br",
        "K\u0101n\u012b Hanj\u012br\u0101",
        "\u0643\u0627\u0646\u064a \u0647\u0646\u062c\u064a\u0631\u0627"
    ],
    "wof:name":"Kani Hanjir Shaykh Bazani",
    "wof:placetype":"locality"
},
  "geometry": {"coordinates":[44.79167,35.8479],"type":"Point"}
}