{
  "type": "Feature",
  "properties": {
    "gn:admin1_code":"5.0",
    "gn:admin2_code":"9166600.0",
    "gn:asciiname":"Chalkah Rustam Shamar",
    "gn:country_code":"IQ",
    "gn:dem":785,
    "gn:feature_class":"P",
    "gn:feature_code":"PPL",
    "gn:name":"Ch\u0101lkah Rustam Sh\u0101m\u0101r",
    "gn:population":0,
    "gn:timezone":"Asia/Baghdad",
    "iso:country":"IQ",
    "name:ara_x_preferred":[
        "\u0686\u0627\u0644\u0643\u0629 \u0631\u0633\u062a\u0645 \u0634\u0627\u0645\u0627\u0631"
    ],
    "name:kur_x_preferred":[
        "Cilke \u1e5eostem Shemer"
    ],
    "name:kur_x_variant":[
        "Celke \u1e5eosey",
        "\u062c\u0644\u0643\u06d5 \u0695\u06c6\u0633\u062a\u06d5\u0645 \u0634\u06d5\u0645\u06d5\u0631",
        "\u062c\u06d5\u0644\u0643\u06d5 \u0695\u06c6\u0633\u06d5\u0649"
    ],
    "name:und_x_variant":[
        "Ch\u0101lkah Rustam Sh\u0101m\u0101r",
        "Ch\u0101lga-i Rustam Sh\u0101m\u0101r",
        "Jalk\u0101",
        "Rustam Sh\u0101m\u0101r",
        "Rosai Shamar",
        "\u0631\u0633\u062a\u0645 \u0634\u0627\u0645\u0627\u0631",
        "\u062c\u0644\u0643\u0627"
    ],
    "wof:name":"Chalkah Rustam Shamar",
    "wof:placetype":"locality"
},
  "geometry": {"coordinates":[45.35872,34.92756],"type":"Point"}
}