{
  "type": "Feature",
  "properties": {
    "gn:admin1_code":"4.0",
    "gn:admin2_code":"99763.0",
    "gn:asciiname":"Jam'iyat al 'Ukayli",
    "gn:country_code":"IQ",
    "gn:dem":27,
    "gn:feature_class":"P",
    "gn:feature_code":"PPL",
    "gn:name":"Jam\u2018\u012byat al \u2018Ukayl\u012b",
    "gn:population":0,
    "gn:timezone":"Asia/Baghdad",
    "iso:country":"IQ",
    "name:ara_x_preferred":[
        "\u062c\u0645\u0639\u064a\u0629 \u0627\u0644\u0639\u0643\u064a\u0644\u064a"
    ],
    "name:und_x_variant":[
        "Jam\u2018\u012byat al \u2018Ukayl\u012b"
    ],
    "wof:name":"Jam'iyat al 'Ukayli",
    "wof:placetype":"locality"
},
  "geometry": {"coordinates":[44.5512,32.00771],"type":"Point"}
}