{
  "type": "Feature",
  "properties": {
    "gn:admin1_code":"10.0",
    "gn:admin2_code":"9166680.0",
    "gn:asciiname":"Karim ar Rabi'",
    "gn:country_code":"IQ",
    "gn:dem":39,
    "gn:feature_class":"P",
    "gn:feature_code":"PPL",
    "gn:name":"Kar\u012bm ar Rab\u012b\u2018",
    "gn:population":0,
    "gn:timezone":"Asia/Baghdad",
    "iso:country":"IQ",
    "name:ara_x_preferred":[
        "\u0643\u0631\u064a\u0645 \u0627\u0644\u0631\u0628\u064a\u0639"
    ],
    "name:und_x_variant":[
        "Kar\u012bm ar Rab\u012b\u2018"
    ],
    "wof:name":"Karim ar Rabi'",
    "wof:placetype":"locality"
},
  "geometry": {"coordinates":[45.39093,33.41836],"type":"Point"}
}