{
  "type": "Feature",
  "properties": {
    "gn:admin1_code":"10.0",
    "gn:admin2_code":"99063.0",
    "gn:asciiname":"Qaryat Abu Hamlah",
    "gn:country_code":"IQ",
    "gn:dem":58,
    "gn:feature_class":"P",
    "gn:feature_code":"PPL",
    "gn:name":"Qaryat Ab\u016b \u1e28amlah",
    "gn:population":0,
    "gn:timezone":"Asia/Baghdad",
    "iso:country":"IQ",
    "name:ara_x_preferred":[
        "\u0642\u0631\u064a\u0629 \u0627\u0628\u0648 \u062d\u0645\u0644\u0629"
    ],
    "name:und_x_variant":[
        "Ab\u016b Jamlah",
        "\u0627\u0628\u0648 \u062c\u0645\u0644\u0629",
        "Qaryat Ab\u016b \u1e28amlah"
    ],
    "wof:name":"Qaryat Abu Hamlah",
    "wof:placetype":"locality"
},
  "geometry": {"coordinates":[44.92379,33.92691],"type":"Point"}
}