{
  "type": "Feature",
  "properties": {
    "gn:admin1_code":"11.0",
    "gn:admin2_code":"95444.0",
    "gn:asciiname":"Ber Zin",
    "gn:country_code":"IQ",
    "gn:dem":480,
    "gn:feature_class":"P",
    "gn:feature_code":"PPL",
    "gn:name":"Ber Zin",
    "gn:population":0,
    "gn:timezone":"Asia/Baghdad",
    "iso:country":"IQ",
    "name:ara_x_preferred":[
        "\u062d\u0635\u0627\u0631 \u0628\u064a\u0631\u0632\u064a\u0646"
    ],
    "name:kur_x_preferred":[
        "P\u00eerz\u00een"
    ],
    "name:kur_x_variant":[
        "\u067e\u064a\u0631\u0632\u064a\u0646"
    ],
    "name:und_x_variant":[
        "\u1e28i\u015f\u0101r B\u012brz\u012bn"
    ],
    "wof:name":"Ber Zin",
    "wof:placetype":"locality"
},
  "geometry": {"coordinates":[44.05539,36.24646],"type":"Point"}
}