{
  "type": "Feature",
  "properties": {
    "gn:admin1_code":"7.0",
    "gn:admin2_code":"99101.0",
    "gn:asciiname":"Salim az Zayk",
    "gn:country_code":"IQ",
    "gn:dem":39,
    "gn:feature_class":"P",
    "gn:feature_code":"PPL",
    "gn:name":"Sal\u012bm az Zayk",
    "gn:population":0,
    "gn:timezone":"Asia/Baghdad",
    "iso:country":"IQ",
    "name:ara_x_preferred":[
        "\u0633\u0644\u064a\u0645 \u0627\u0644\u0632\u064a\u0643"
    ],
    "name:und_x_variant":[
        "Sal\u012bm az Zayk"
    ],
    "wof:name":"Salim az Zayk",
    "wof:placetype":"locality"
},
  "geometry": {"coordinates":[44.10905,33.16602],"type":"Point"}
}