{
  "type": "Feature",
  "properties": {
    "gn:admin1_code":"8.0",
    "gn:admin2_code":"9166607.0",
    "gn:asciiname":"Sardindijin",
    "gn:country_code":"IQ",
    "gn:dem":466,
    "gn:feature_class":"P",
    "gn:feature_code":"PPL",
    "gn:name":"Sardindijin",
    "gn:population":0,
    "gn:timezone":"Asia/Baghdad",
    "iso:country":"IQ",
    "name:ara_x_preferred":[
        "\u0633\u0631\u062f\u0646\u062f\u062c\u0646"
    ],
    "name:kur_x_preferred":[
        "Serdike"
    ],
    "name:kur_x_variant":[
        "\u0633\u06d5\u0631\u062f\u0643\u06d5",
        "S\u00eavd\u00eecin",
        "\u0633\u06ce\u06a4\u062f\u064a\u062c\u0646",
        "S\u00eavd\u00een Cin",
        "\u0633\u06ce\u06a4\u062f\u064a\u0646 \u062c\u0646"
    ],
    "name:und_x_variant":[
        "Sirdenjen",
        "Sardka",
        "Sardindijin",
        "Sevdijin"
    ],
    "wof:name":"Sardindijin",
    "wof:placetype":"locality"
},
  "geometry": {"coordinates":[42.59158,36.97061],"type":"Point"}
}