{
  "type": "Feature",
  "properties": {
    "gn:admin1_code":"8.0",
    "gn:admin2_code":"9166607.0",
    "gn:asciiname":"Hawshik",
    "gn:country_code":"IQ",
    "gn:dem":527,
    "gn:feature_class":"P",
    "gn:feature_code":"PPL",
    "gn:name":"\u1e28awshik",
    "gn:population":0,
    "gn:timezone":"Asia/Baghdad",
    "iso:country":"IQ",
    "name:ara_x_preferred":[
        "\u0645\u0648\u0634\u0643"
    ],
    "name:kur_x_preferred":[
        "Mushik"
    ],
    "name:kur_x_variant":[
        "\u1e26ewshik J\u00ear\u00ee",
        "\u062d\u06d5\u0648\u0634\u0643 \u0698\u06ce\u0631\u0649"
    ],
    "name:und_x_variant":[
        "\u1e28awshik",
        "\u062d\u0648\u0634\u0643",
        "M\u016bshik",
        "Mushk"
    ],
    "wof:name":"Hawshik",
    "wof:placetype":"locality"
},
  "geometry": {"coordinates":[42.90594,36.86985],"type":"Point"}
}