{
  "type": "Feature",
  "properties": {
    "gn:admin1_code":"15.0",
    "gn:admin2_code":"98612.0",
    "gn:asciiname":"Rulik",
    "gn:country_code":"IQ",
    "gn:dem":575,
    "gn:feature_class":"P",
    "gn:feature_code":"PPL",
    "gn:name":"R\u016blik",
    "gn:population":0,
    "gn:timezone":"Asia/Baghdad",
    "iso:country":"IQ",
    "name:ara_x_preferred":[
        "\u0631\u0648\u0644\u0643"
    ],
    "name:ara_x_variant":[
        "R\u016blik"
    ],
    "name:kur_x_preferred":[
        "Dulk"
    ],
    "name:kur_x_variant":[
        "\u062f\u0648\u0644\u0643"
    ],
    "name:und_x_variant":[
        "Ruw\u012bk"
    ],
    "wof:name":"Rulik",
    "wof:placetype":"locality"
},
  "geometry": {"coordinates":[43.55242,36.77743],"type":"Point"}
}