{
  "type": "Feature",
  "properties": {
    "gn:admin1_code":"11.0",
    "gn:admin2_code":"93817.0",
    "gn:asciiname":"Qaryat Kharabat Zard",
    "gn:country_code":"IQ",
    "gn:dem":199,
    "gn:feature_class":"P",
    "gn:feature_code":"PPL",
    "gn:name":"Qaryat Khar\u0101bat Zard",
    "gn:population":0,
    "gn:timezone":"Asia/Baghdad",
    "iso:country":"IQ",
    "name:ara_x_preferred":[
        "\u0642\u0631\u064a\u0629 \u062e\u0631\u0627\u0628\u0647 \u0632\u0631\u062f"
    ],
    "name:und_x_variant":[
        "Qaryat Khar\u0101bat Zard"
    ],
    "wof:name":"Qaryat Kharabat Zard",
    "wof:placetype":"locality"
},
  "geometry": {"coordinates":[43.37769,35.5976],"type":"Point"}
}