{
  "type": "Feature",
  "properties": {
    "gn:admin1_code":"5.0",
    "gn:admin2_code":"98464.0",
    "gn:asciiname":"Binkird",
    "gn:country_code":"IQ",
    "gn:dem":707,
    "gn:feature_class":"P",
    "gn:feature_code":"PPL",
    "gn:name":"Binkird",
    "gn:population":0,
    "gn:timezone":"Asia/Baghdad",
    "iso:country":"IQ",
    "name:ara_x_preferred":[
        "\u0628\u0646\u0643\u0631\u062f"
    ],
    "name:kur_x_preferred":[
        "Bingird"
    ],
    "name:kur_x_variant":[
        "\u0628\u0646\u06af\u0631\u062f"
    ],
    "name:und_x_variant":[
        "Bingrd"
    ],
    "wof:name":"Binkird",
    "wof:placetype":"locality"
},
  "geometry": {"coordinates":[45.33837,35.52864],"type":"Point"}
}