{
  "type": "Feature",
  "properties": {
    "gn:admin1_code":"7.0",
    "gn:admin2_code":"99101.0",
    "gn:asciiname":"Khudayr 'Alwan Khalaf",
    "gn:country_code":"IQ",
    "gn:dem":30,
    "gn:feature_class":"P",
    "gn:feature_code":"PPL",
    "gn:name":"Khu\u1e11ayr \u2018Alw\u0101n Khalaf",
    "gn:population":0,
    "gn:timezone":"Asia/Baghdad",
    "iso:country":"IQ",
    "name:ara_x_preferred":[
        "\u062e\u0636\u064a\u0631 \u0639\u0644\u0648\u0627\u0646 \u062e\u0644\u0641"
    ],
    "name:und_x_variant":[
        "Khu\u1e11ayr \u2018Alw\u0101n Khalaf"
    ],
    "wof:name":"Khudayr 'Alwan Khalaf",
    "wof:placetype":"locality"
},
  "geometry": {"coordinates":[44.47891,33.05131],"type":"Point"}
}