{
  "type": "Feature",
  "properties": {
    "gn:admin1_code":"10.0",
    "gn:admin2_code":"99063.0",
    "gn:asciiname":"Hasan al Khatun",
    "gn:country_code":"IQ",
    "gn:dem":48,
    "gn:feature_class":"P",
    "gn:feature_code":"PPL",
    "gn:name":"\u1e28asan al Kh\u0101t\u016bn",
    "gn:population":0,
    "gn:timezone":"Asia/Baghdad",
    "iso:country":"IQ",
    "name:ara_x_preferred":[
        "\u062d\u0633\u0646 \u0627\u0644\u062e\u0627\u062a\u0648\u0646"
    ],
    "name:und_x_variant":[
        "\u1e28asan al K\u0101n\u016bn",
        "\u1e28asan al Kh\u0101t\u016bn"
    ],
    "wof:name":"Hasan al Khatun",
    "wof:placetype":"locality"
},
  "geometry": {"coordinates":[44.71181,33.80067],"type":"Point"}
}