{
  "type": "Feature",
  "properties": {
    "gn:admin1_code":"5.0",
    "gn:admin2_code":"91176.0",
    "gn:asciiname":"Qaryat Qala Juwalan al Qadim",
    "gn:country_code":"IQ",
    "gn:dem":866,
    "gn:feature_class":"P",
    "gn:feature_code":"PPL",
    "gn:name":"Qaryat Qal\u0101 Juw\u0101l\u0101n al Qad\u012bm",
    "gn:population":0,
    "gn:timezone":"Asia/Baghdad",
    "iso:country":"IQ",
    "name:ara_x_preferred":[
        "\u0642\u0631\u064a\u0629 \u0642\u0644\u0627 \u062c\u0648\u0627\u0644\u0627\u0646 \u0627\u0644\u0642\u062f\u064a\u0645"
    ],
    "name:kur_x_preferred":[
        "Qe\u0142a Chwalan"
    ],
    "name:kur_x_variant":[
        "\u0642\u06d5\u06b5\u0627 \u0686\u0648\u0627\u0644\u0627\u0646"
    ],
    "name:und_x_variant":[
        "Qaryat Qal\u0101 Juw\u0101l\u0101n al Qad\u012bm",
        "Qala Chwalan"
    ],
    "wof:name":"Qaryat Qala Juwalan al Qadim",
    "wof:placetype":"locality"
},
  "geometry": {"coordinates":[45.55058,35.69662],"type":"Point"}
}