{
  "type": "Feature",
  "properties": {
    "gn:admin1_code":"5.0",
    "gn:admin2_code":"98464.0",
    "gn:asciiname":"Daraban",
    "gn:country_code":"IQ",
    "gn:dem":896,
    "gn:feature_class":"P",
    "gn:feature_code":"PPL",
    "gn:name":"D\u0101raban",
    "gn:population":0,
    "gn:timezone":"Asia/Baghdad",
    "iso:country":"IQ",
    "name:ara_x_preferred":[
        "\u062f\u0627\u0631\u0628\u0646"
    ],
    "name:fas_x_preferred":[
        "\u062f\u0627\u0631\u0627\u0628\u0627\u0646"
    ],
    "name:kur_x_preferred":[
        "Dare Ben"
    ],
    "name:kur_x_variant":[
        "\u062f\u0627\u0631\u06d5 \u0628\u06d5\u0646"
    ],
    "name:und_x_variant":[
        "D\u0101raban",
        "Dara Ban"
    ],
    "name:urd_x_preferred":[
        "\u062f\u0627\u0631\u0627\u0628\u0627\u0646"
    ],
    "wof:name":"Daraban",
    "wof:placetype":"locality"
},
  "geometry": {"coordinates":[45.42141,35.61328],"type":"Point"}
}