{
  "type": "Feature",
  "properties": {
    "gn:admin1_code":"3.0",
    "gn:admin2_code":"98534.0",
    "gn:asciiname":"As Silhubiyah",
    "gn:country_code":"IQ",
    "gn:dem":116,
    "gn:feature_class":"P",
    "gn:feature_code":"PPL",
    "gn:name":"As Sil\u1e29\u016bb\u012byah",
    "gn:population":0,
    "gn:timezone":"Asia/Baghdad",
    "iso:country":"IQ",
    "name:ara_x_preferred":[
        "\u0627\u0644\u0633\u0644\u062d\u0648\u0628\u064a\u0629"
    ],
    "name:und_x_variant":[
        "As Sil\u1e29\u016bb\u012byah"
    ],
    "wof:name":"As Silhubiyah",
    "wof:placetype":"locality"
},
  "geometry": {"coordinates":[45.03843,30.92561],"type":"Point"}
}