{
  "type": "Feature",
  "properties": {
    "gn:admin1_code":"9.0",
    "gn:admin2_code":"90509.0",
    "gn:asciiname":"Shuwaykiyah",
    "gn:cc2":"IQ",
    "gn:country_code":"IQ",
    "gn:dem":6,
    "gn:feature_class":"P",
    "gn:feature_code":"PPL",
    "gn:name":"Shuwayk\u012byah",
    "gn:population":0,
    "gn:timezone":"Asia/Baghdad",
    "iso:country":"IQ",
    "name:und_x_variant":[
        "Shuwayj\u012byah",
        "Suwayj\u012byah",
        "Shuwaichiyan",
        "Suwaych\u012byah",
        "Shuwayk\u012byah"
    ],
    "wof:name":"Shuwaykiyah",
    "wof:placetype":"locality"
},
  "geometry": {"coordinates":[46.31667,30.98333],"type":"Point"}
}