{
  "type": "Feature",
  "properties": {
    "gn:admin1_code":"10.0",
    "gn:admin2_code":"99063.0",
    "gn:asciiname":"Muhammad Amin",
    "gn:country_code":"IQ",
    "gn:dem":51,
    "gn:feature_class":"P",
    "gn:feature_code":"PPL",
    "gn:name":"Mu\u1e29ammad Am\u012bn",
    "gn:population":0,
    "gn:timezone":"Asia/Baghdad",
    "iso:country":"IQ",
    "name:und_x_variant":[
        "Mu\u1e29ammad Am\u012bn"
    ],
    "wof:name":"Muhammad Amin",
    "wof:placetype":"locality"
},
  "geometry": {"coordinates":[44.65222,33.85833],"type":"Point"}
}