{
  "type": "Feature",
  "properties": {
    "gn:admin1_code":"14.0",
    "gn:admin2_code":"92536.0",
    "gn:asciiname":"Al 'Isawi",
    "gn:country_code":"IQ",
    "gn:dem":3,
    "gn:feature_class":"P",
    "gn:feature_code":"PPL",
    "gn:name":"Al \u2018\u012as\u0101w\u012b",
    "gn:population":0,
    "gn:timezone":"Asia/Baghdad",
    "iso:country":"IQ",
    "name:ara_x_preferred":[
        "Al \u2018\u012as\u0101w\u012b"
    ],
    "wof:name":"Al 'Isawi",
    "wof:placetype":"locality"
},
  "geometry": {"coordinates":[47.36667,31.38333],"type":"Point"}
}