{
  "type": "Feature",
  "properties": {
    "gn:admin1_code":"8.0",
    "gn:admin2_code":"99612.0",
    "gn:asciiname":"Katula",
    "gn:country_code":"IQ",
    "gn:dem":1802,
    "gn:feature_class":"P",
    "gn:feature_code":"PPL",
    "gn:name":"Katula",
    "gn:population":0,
    "gn:timezone":"Asia/Baghdad",
    "iso:country":"IQ",
    "name:ara_x_preferred":[
        "\u0643\u062a\u0648\u0644\u0627"
    ],
    "name:fas_x_preferred":[
        "\u06a9\u062a\u0648\u0644\u0627"
    ],
    "name:kur_x_preferred":[
        "Katula"
    ],
    "name:kur_x_variant":[
        "\u0643\u0627\u062a\u0648\u0644\u0627",
        "Katola",
        "Art\u00eala",
        "\u0643\u0627\u062a\u06c6\u0644\u0627",
        "\u0626\u0627\u0631\u062a\u06ce\u0644\u0627"
    ],
    "name:msa_x_preferred":[
        "Katula"
    ],
    "name:und_x_variant":[
        "Artela"
    ],
    "wof:name":"Katula",
    "wof:placetype":"locality"
},
  "geometry": {"coordinates":[44.02778,37.25887],"type":"Point"}
}