{
  "type": "Feature",
  "properties": {
    "gn:admin1_code":"6.0",
    "gn:admin2_code":"6818313.0",
    "gn:asciiname":"Khalil 'Alwan",
    "gn:country_code":"IQ",
    "gn:dem":27,
    "gn:feature_class":"P",
    "gn:feature_code":"PPL",
    "gn:name":"Khal\u012bl \u2018Alw\u0101n",
    "gn:population":0,
    "gn:timezone":"Asia/Baghdad",
    "iso:country":"IQ",
    "name:ara_x_preferred":[
        "\u062e\u0644\u064a\u0644 \u0639\u0644\u0648\u0627\u0646"
    ],
    "name:und_x_variant":[
        "Khal\u012bl \u2018Alw\u0101n"
    ],
    "wof:name":"Khalil 'Alwan",
    "wof:placetype":"locality"
},
  "geometry": {"coordinates":[44.86452,32.65417],"type":"Point"}
}