{
  "type": "Feature",
  "properties": {
    "gn:admin1_code":"11.0",
    "gn:admin2_code":"9166592.0",
    "gn:asciiname":"Kawla",
    "gn:country_code":"IQ",
    "gn:dem":624,
    "gn:feature_class":"P",
    "gn:feature_code":"PPLL",
    "gn:name":"Kawla",
    "gn:population":0,
    "gn:timezone":"Asia/Baghdad",
    "iso:country":"IQ",
    "name:ara_x_preferred":[
        "\u0646\u0632\u0627\u0631\u064a \u0643\u0648\u0644\u0627\u0631\u0634\u064a"
    ],
    "name:kur_x_preferred":[
        "Kawla"
    ],
    "name:kur_x_variant":[
        "\u0643\u0627\u0648\u0644\u0627"
    ],
    "name:und_x_variant":[
        "Niz\u0101r\u012b Kawl\u0101rash\u012b"
    ],
    "wof:name":"Kawla",
    "wof:placetype":"locality"
},
  "geometry": {"coordinates":[44.53549,36.74084000000001],"type":"Point"}
}