{
  "type": "Feature",
  "properties": {
    "gn:admin1_code":"5.0",
    "gn:admin2_code":"96204.0",
    "gn:asciiname":"Mirwali",
    "gn:country_code":"IQ",
    "gn:dem":626,
    "gn:feature_class":"P",
    "gn:feature_code":"PPL",
    "gn:name":"Mirw\u0101l\u012b",
    "gn:population":0,
    "gn:timezone":"Asia/Baghdad",
    "iso:country":"IQ",
    "name:ara_x_preferred":[
        "Mirw\u0101l\u012b"
    ],
    "name:ara_x_variant":[
        "\u0645\u0631\u0648\u0627\u0644\u064a"
    ],
    "name:fas_x_preferred":[
        "\u0645\u06cc\u0631\u0627\u0648\u0644\u06cc"
    ],
    "name:fas_x_variant":[
        "M\u012br\u0101val\u012b"
    ],
    "name:kur_x_preferred":[
        "M\u00eerawl\u00ee"
    ],
    "name:und_x_variant":[
        "Mirawli"
    ],
    "wof:name":"Mirwali",
    "wof:placetype":"locality"
},
  "geometry": {"coordinates":[45.87864,35.15620999999999],"type":"Point"}
}