{
  "type": "Feature",
  "properties": {
    "gn:admin1_code":"11.0",
    "gn:admin2_code":"95444.0",
    "gn:asciiname":"Mstawa",
    "gn:country_code":"IQ",
    "gn:dem":303,
    "gn:feature_class":"P",
    "gn:feature_code":"PPL",
    "gn:name":"Mstawa",
    "gn:population":0,
    "gn:timezone":"Asia/Baghdad",
    "iso:country":"IQ",
    "name:ara_x_preferred":[
        "\u0645\u0627\u0633\u062a\u0627\u0648\u0629"
    ],
    "name:kur_x_preferred":[
        "Mstawa"
    ],
    "name:kur_x_variant":[
        "\u0645\u0633\u062a\u0627\u0648\u0627"
    ],
    "name:und_x_variant":[
        "Mast\u0101wah",
        "Mastawa",
        "Mast\u0101wa",
        "M\u0101st\u0101wah"
    ],
    "wof:name":"Mstawa",
    "wof:placetype":"locality"
},
  "geometry": {"coordinates":[43.81663,36.04705],"type":"Point"}
}