{
  "type": "Feature",
  "properties": {
    "gn:admin1_code":"15.0",
    "gn:admin2_code":"9166620.0",
    "gn:asciiname":"Tall Sadkhan",
    "gn:country_code":"IQ",
    "gn:dem":266,
    "gn:feature_class":"P",
    "gn:feature_code":"PPL",
    "gn:name":"Tall Sadkh\u0101n",
    "gn:population":0,
    "gn:timezone":"Asia/Baghdad",
    "iso:country":"IQ",
    "name:ara_x_preferred":[
        "\u062a\u0644 \u0633\u062f\u062e\u0627\u0646"
    ],
    "name:und_x_variant":[
        "Tall Sa\u2018d\u0101n",
        "Tall Sadkh\u0101n"
    ],
    "wof:name":"Tall Sadkhan",
    "wof:placetype":"locality"
},
  "geometry": {"coordinates":[42.23446,36.12207],"type":"Point"}
}