{
  "type": "Feature",
  "properties": {
    "gn:admin1_code":"18.0",
    "gn:admin2_code":"6805736.0",
    "gn:asciiname":"Muhammad an Najaf",
    "gn:country_code":"IQ",
    "gn:dem":47,
    "gn:feature_class":"P",
    "gn:feature_code":"PPL",
    "gn:name":"Mu\u1e29ammad an Najaf",
    "gn:population":0,
    "gn:timezone":"Asia/Baghdad",
    "iso:country":"IQ",
    "name:und_x_variant":[
        "Mu\u1e29ammad an Najaf"
    ],
    "wof:name":"Muhammad an Najaf",
    "wof:placetype":"locality"
},
  "geometry": {"coordinates":[44.17028,34.04528],"type":"Point"}
}