{
  "type": "Feature",
  "properties": {
    "gn:gn_country":"IQ",
    "iso:country":"IQ",
    "qs_pg:aaroncc":"IQ",
    "qs_pg:gn_country":"IQ",
    "qs_pg:name":"Rawandoz",
    "qs_pg:name_adm0":"Iraq",
    "qs_pg:name_adm1":"Arbil",
    "qs_pg:photos":44,
    "qs_pg:photos_1k":9,
    "qs_pg:photos_9k":1,
    "qs_pg:photos_9r":2,
    "qs_pg:photos_all":44,
    "qs_pg:photos_sr":2,
    "qs_pg:pop_sr":0,
    "qs_pg:qs_pg_placetype":"locality",
    "qs_pg:qs_pg_placetype_gp":"Town",
    "qs_pg:woe_adm0":23424855,
    "woe:adm0_id":23424855,
    "woe:name_adm0":"Iraq",
    "woe:name_adm1":"Arbil",
    "woe:placetype":"Town",
    "wof:name":"Rawandoz",
    "wof:placetype":"locality"
},
  "geometry": {"coordinates":[44.504928,36.619936],"type":"Point"}
}