{
  "type": "Feature",
  "properties": {
    "gn:admin1_code":"2.0",
    "gn:admin2_code":"9166563.0",
    "gn:asciiname":"Jalal",
    "gn:country_code":"IQ",
    "gn:dem":4,
    "gn:feature_class":"P",
    "gn:feature_code":"PPL",
    "gn:name":"Jal\u0101l",
    "gn:population":0,
    "gn:timezone":"Asia/Baghdad",
    "iso:country":"IQ",
    "name:ara_x_preferred":[
        "\u062c\u0644\u0627\u0644"
    ],
    "name:und_x_variant":[
        "Jal\u0101l"
    ],
    "wof:name":"Jalal",
    "wof:placetype":"locality"
},
  "geometry": {"coordinates":[47.2485,30.93492],"type":"Point"}
}