{
  "type": "Feature",
  "properties": {
    "gn:admin1_code":"4.0",
    "gn:admin2_code":"98634.0",
    "gn:asciiname":"'Ajami Rahim",
    "gn:country_code":"IQ",
    "gn:dem":24,
    "gn:feature_class":"P",
    "gn:feature_code":"PPL",
    "gn:name":"\u2018Ajam\u012b Ra\u1e29\u012bm",
    "gn:population":0,
    "gn:timezone":"Asia/Baghdad",
    "iso:country":"IQ",
    "name:ara_x_preferred":[
        "\u0639\u062c\u0645\u064a \u0631\u062d\u064a\u0645"
    ],
    "name:und_x_variant":[
        "\u2018Ajam\u012b Ra\u1e29\u012bm"
    ],
    "wof:name":"'Ajami Rahim",
    "wof:placetype":"locality"
},
  "geometry": {"coordinates":[44.5977,31.97841],"type":"Point"}
}