{
  "type": "Feature",
  "properties": {
    "gn:admin1_code":"10.0",
    "gn:admin2_code":"97988.0",
    "gn:asciiname":"Albu 'Amir",
    "gn:country_code":"IQ",
    "gn:dem":38,
    "gn:feature_class":"P",
    "gn:feature_code":"PPL",
    "gn:name":"\u0100lb\u016b \u2018\u0100mir",
    "gn:population":0,
    "gn:timezone":"Asia/Baghdad",
    "iso:country":"IQ",
    "name:ara_x_preferred":[
        "\u0627\u0644\u0628\u0648 \u0639\u0627\u0645\u0631"
    ],
    "name:ara_x_variant":[
        "\u0100lb\u016b \u2018\u0100mir"
    ],
    "name:und_x_variant":[
        "Ash Sham\u0101liah",
        "Alb\u016b \u2018Um\u0101r"
    ],
    "wof:name":"Albu 'Amir",
    "wof:placetype":"locality"
},
  "geometry": {"coordinates":[44.5097,33.46358],"type":"Point"}
}