{
  "type": "Feature",
  "properties": {
    "gn:admin1_code":"10.0",
    "gn:admin2_code":"99170.0",
    "gn:asciiname":"Al Hajj Mahdi as Salih",
    "gn:country_code":"IQ",
    "gn:dem":52,
    "gn:feature_class":"P",
    "gn:feature_code":"PPL",
    "gn:name":"Al \u1e28\u0101jj Mahd\u012b a\u015f \u015e\u0101li\u1e29",
    "gn:population":0,
    "gn:timezone":"Asia/Baghdad",
    "iso:country":"IQ",
    "name:ara_x_preferred":[
        "\u0627\u0644\u062d\u0627\u062c \u0645\u0647\u062f\u064a \u0627\u0644\u0635\u0627\u0644\u062d"
    ],
    "name:und_x_variant":[
        "Al \u1e28\u0101jj Mahd\u012b a\u015f \u015e\u0101li\u1e29"
    ],
    "wof:name":"Al Hajj Mahdi as Salih",
    "wof:placetype":"locality"
},
  "geometry": {"coordinates":[44.62542,33.91832],"type":"Point"}
}