{
  "type": "Feature",
  "properties": {
    "gn:admin1_code":"15.0",
    "gn:admin2_code":"9166620.0",
    "gn:asciiname":"Al Khan",
    "gn:country_code":"IQ",
    "gn:dem":539,
    "gn:feature_class":"P",
    "gn:feature_code":"PPL",
    "gn:name":"Al Kh\u0101n",
    "gn:population":0,
    "gn:timezone":"Asia/Baghdad",
    "iso:country":"IQ",
    "name:ara_x_preferred":[
        "\u0627\u0644\u062e\u0627\u0646"
    ],
    "name:ara_x_variant":[
        "Al Kh\u0101n"
    ],
    "name:kur_x_preferred":[
        "Xan"
    ],
    "name:kur_x_variant":[
        "\u062e\u0627\u0646"
    ],
    "name:und_x_variant":[
        "Khan"
    ],
    "wof:name":"Al Khan",
    "wof:placetype":"locality"
},
  "geometry": {"coordinates":[42.04597,36.36976],"type":"Point"}
}