{
  "type": "Feature",
  "properties": {
    "gn:admin1_code":"5.0",
    "gn:admin2_code":"97416.0",
    "gn:asciiname":"Qashqah",
    "gn:country_code":"IQ",
    "gn:dem":612,
    "gn:feature_class":"P",
    "gn:feature_code":"PPL",
    "gn:name":"Qashqah",
    "gn:population":0,
    "gn:timezone":"Asia/Baghdad",
    "iso:country":"IQ",
    "name:ara_x_preferred":[
        "\u0642\u0634\u0642\u0629"
    ],
    "name:und_x_variant":[
        "Qashghah",
        "Qashqah"
    ],
    "wof:name":"Qashqah",
    "wof:placetype":"locality"
},
  "geometry": {"coordinates":[44.87679,35.26622000000001],"type":"Point"}
}