{
  "type": "Feature",
  "properties": {
    "gn:admin1_code":"4.0",
    "gn:admin2_code":"99763.0",
    "gn:asciiname":"Al 'Abtan al Khaza'i",
    "gn:country_code":"IQ",
    "gn:dem":24,
    "gn:feature_class":"P",
    "gn:feature_code":"PPL",
    "gn:name":"\u0100l \u2018Ab\u0163\u0101n al Khaz\u0101\u2018\u012b",
    "gn:population":0,
    "gn:timezone":"Asia/Baghdad",
    "iso:country":"IQ",
    "name:ara_x_preferred":[
        "\u0627\u0644 \u0639\u0628\u0637\u0627\u0646 \u0627\u0644\u062e\u0632\u0627\u0639\u064a"
    ],
    "name:und_x_variant":[
        "\u0100l \u2018Ab\u0163\u0101n al Khuz\u0101\u2018\u012b",
        "\u0100l \u2018Ab\u0163\u0101n al Khaz\u0101\u2018\u012b"
    ],
    "wof:name":"Al 'Abtan al Khaza'i",
    "wof:placetype":"locality"
},
  "geometry": {"coordinates":[44.68649,31.96558],"type":"Point"}
}