{
  "type": "Feature",
  "properties": {
    "gn:admin1_code":"15.0",
    "gn:admin2_code":"98612.0",
    "gn:asciiname":"Kiluki",
    "gn:country_code":"IQ",
    "gn:dem":496,
    "gn:feature_class":"P",
    "gn:feature_code":"PPL",
    "gn:name":"Kil\u016bk\u012b",
    "gn:population":0,
    "gn:timezone":"Asia/Baghdad",
    "iso:country":"IQ",
    "name:ara_x_preferred":[
        "\u0643\u0644\u0648\u0643\u064a"
    ],
    "name:ara_x_variant":[
        "Kil\u016bk\u012b"
    ],
    "name:kur_x_preferred":[
        "Giluk\u00ee"
    ],
    "name:kur_x_variant":[
        "\u06af\u0644\u0648\u0643\u0649",
        "Gel\u00eek\u00ee",
        "\u06af\u06d5\u0644\u064a\u0643\u0649"
    ],
    "name:und_x_variant":[
        "Gluky",
        "Galiki"
    ],
    "wof:name":"Kiluki",
    "wof:placetype":"locality"
},
  "geometry": {"coordinates":[43.39411,36.74667],"type":"Point"}
}