{
  "type": "Feature",
  "properties": {
    "gn:admin1_code":"18.0",
    "gn:admin2_code":"6783103.0",
    "gn:asciiname":"'Arab Tuwayran Madan",
    "gn:country_code":"IQ",
    "gn:dem":86,
    "gn:feature_class":"P",
    "gn:feature_code":"PPL",
    "gn:name":"\u2018Arab Tuwayr\u0101n Madan",
    "gn:population":0,
    "gn:timezone":"Asia/Baghdad",
    "iso:country":"IQ",
    "name:ara_x_preferred":[
        "\u0639\u0631\u0628 \u062a\u0648\u064a\u0631\u0627\u0646 \u0645\u062f\u0646"
    ],
    "name:und_x_variant":[
        "\u2018Arab Tuwayr\u0101n Madan"
    ],
    "wof:name":"'Arab Tuwayran Madan",
    "wof:placetype":"locality"
},
  "geometry": {"coordinates":[44.41253,34.45365],"type":"Point"}
}