{
  "type": "Feature",
  "properties": {
    "gn:admin1_code":"15.0",
    "gn:admin2_code":"98820.0",
    "gn:asciiname":"Bardah Rashsh as Saghir",
    "gn:country_code":"IQ",
    "gn:dem":351,
    "gn:feature_class":"P",
    "gn:feature_code":"PPL",
    "gn:name":"Bardah Rashsh a\u015f \u015eagh\u012br",
    "gn:population":0,
    "gn:timezone":"Asia/Baghdad",
    "iso:country":"IQ",
    "name:ara_x_preferred":[
        "\u0628\u0631\u062f\u0647 \u0631\u0634 \u0627\u0644\u0635\u063a\u064a\u0631"
    ],
    "name:ara_x_variant":[
        "\u0628\u0631\u062f\u0631\u0634 \u0627\u0644\u0635\u063a\u064a\u0631"
    ],
    "name:kur_x_preferred":[
        "Berde \u1e5eesh"
    ],
    "name:kur_x_variant":[
        "\u0628\u06d5\u0631\u062f\u06d5 \u0695\u06d5\u0634"
    ],
    "name:und_x_variant":[
        "Bardarash",
        "Bardah Rashsh a\u015f \u015eagh\u012br",
        "Bardarash Bchuk",
        "Barda Rash",
        "Bardarash a\u015f \u015eagh\u012br"
    ],
    "wof:name":"Bardah Rashsh as Saghir",
    "wof:placetype":"locality"
},
  "geometry": {"coordinates":[43.5907,36.50311],"type":"Point"}
}