{
  "type": "Feature",
  "properties": {
    "gn:admin1_code":"18.0",
    "gn:admin2_code":"6805736.0",
    "gn:asciiname":"Fayyad 'Ali",
    "gn:country_code":"IQ",
    "gn:dem":50,
    "gn:feature_class":"P",
    "gn:feature_code":"PPL",
    "gn:name":"Fayy\u0101\u1e11 \u2018Al\u012b",
    "gn:population":0,
    "gn:timezone":"Asia/Baghdad",
    "iso:country":"IQ",
    "name:ara_x_preferred":[
        "\u0641\u064a\u0627\u0636 \u0639\u0644\u064a"
    ],
    "name:und_x_variant":[
        "Fayy\u0101\u1e11 \u2018Al\u012b"
    ],
    "wof:name":"Fayyad 'Ali",
    "wof:placetype":"locality"
},
  "geometry": {"coordinates":[44.03308,33.84156],"type":"Point"}
}