{
  "type": "Feature",
  "properties": {
    "gn:admin1_code":"12.0",
    "gn:admin2_code":"99345.0",
    "gn:asciiname":"Tariq 'Abbas",
    "gn:country_code":"IQ",
    "gn:dem":33,
    "gn:feature_class":"P",
    "gn:feature_code":"PPL",
    "gn:name":"\u0162\u0101riq \u2018Abb\u0101s",
    "gn:population":0,
    "gn:timezone":"Asia/Baghdad",
    "iso:country":"IQ",
    "name:ara_x_preferred":[
        "\u0162\u0101riq \u2018Abb\u0101s"
    ],
    "wof:name":"Tariq 'Abbas",
    "wof:placetype":"locality"
},
  "geometry": {"coordinates":[44.24278,32.51],"type":"Point"}
}