{
  "type": "Feature",
  "properties": {
    "gn:admin1_code":"12.0",
    "gn:admin2_code":"94822.0",
    "gn:asciiname":"'Abd Salim Shinafah",
    "gn:country_code":"IQ",
    "gn:dem":29,
    "gn:feature_class":"P",
    "gn:feature_code":"PPL",
    "gn:name":"\u2018Abd S\u0101lim Shin\u0101fah",
    "gn:population":0,
    "gn:timezone":"Asia/Baghdad",
    "iso:country":"IQ",
    "name:ara_x_preferred":[
        "\u0639\u0628\u062f \u0633\u0627\u0644\u0645 \u0634\u0646\u0627\u0641\u0647"
    ],
    "name:und_x_variant":[
        "\u2018Abd S\u0101lim Shin\u0101fah"
    ],
    "wof:name":"'Abd Salim Shinafah",
    "wof:placetype":"locality"
},
  "geometry": {"coordinates":[44.13529000000001,32.60516],"type":"Point"}
}