{
  "type": "Feature",
  "properties": {
    "gn:admin1_code":"4.0",
    "gn:admin2_code":"98634.0",
    "gn:asciiname":"Shakir Sayyid Hamud",
    "gn:country_code":"IQ",
    "gn:dem":21,
    "gn:feature_class":"P",
    "gn:feature_code":"PPL",
    "gn:name":"Sh\u0101kir Sayyid \u1e28am\u016bd",
    "gn:population":0,
    "gn:timezone":"Asia/Baghdad",
    "iso:country":"IQ",
    "name:ara_x_preferred":[
        "\u0634\u0627\u0643\u0631 \u0633\u064a\u062f \u062d\u0645\u0648\u062f"
    ],
    "name:und_x_variant":[
        "Sh\u0101kir Sayyid \u1e28am\u016bd"
    ],
    "wof:name":"Shakir Sayyid Hamud",
    "wof:placetype":"locality"
},
  "geometry": {"coordinates":[44.62908,31.77578],"type":"Point"}
}