{
  "type": "Feature",
  "properties": {
    "gn:admin1_code":"16.0",
    "gn:admin2_code":"9166961.0",
    "gn:asciiname":"Sa'dun 'Abd al Husayn",
    "gn:country_code":"IQ",
    "gn:dem":26,
    "gn:feature_class":"P",
    "gn:feature_code":"PPL",
    "gn:name":"Sa\u2018d\u016bn \u2018Abd al \u1e28usayn",
    "gn:population":0,
    "gn:timezone":"Asia/Baghdad",
    "iso:country":"IQ",
    "name:ara_x_preferred":[
        "\u0633\u0639\u062f\u0648\u0646 \u0639\u0628\u062f \u0627\u0644\u062d\u0633\u064a\u0646"
    ],
    "name:und_x_variant":[
        "Sa\u2018d\u016bn \u2018Abd al \u1e28usayn"
    ],
    "wof:name":"Sa'dun 'Abd al Husayn",
    "wof:placetype":"locality"
},
  "geometry": {"coordinates":[44.84839,33.01352],"type":"Point"}
}