{
  "type": "Feature",
  "properties": {
    "gn:admin1_code":"9.0",
    "gn:admin2_code":"98700.0",
    "gn:asciiname":"An Nasr",
    "gn:country_code":"IQ",
    "gn:dem":11,
    "gn:feature_class":"P",
    "gn:feature_code":"PPL",
    "gn:name":"An Na\u015fr",
    "gn:population":0,
    "gn:timezone":"Asia/Baghdad",
    "iso:country":"IQ",
    "name:ara_x_preferred":[
        "\u0627\u0644\u0646\u0635\u0631"
    ],
    "name:und_x_variant":[
        "Nasr",
        "An Na\u015fr"
    ],
    "wof:name":"An Nasr",
    "wof:placetype":"locality"
},
  "geometry": {"coordinates":[46.12543,31.53873],"type":"Point"}
}