{
  "type": "Feature",
  "properties": {
    "gn:admin1_code":"17.0",
    "gn:admin2_code":"9166552.0",
    "gn:asciiname":"Al Mahajir al Gharbiyah",
    "gn:country_code":"IQ",
    "gn:dem":24,
    "gn:feature_class":"P",
    "gn:feature_code":"PPL",
    "gn:name":"Al Ma\u1e29\u0101j\u012br al Gharb\u012byah",
    "gn:population":0,
    "gn:timezone":"Asia/Baghdad",
    "iso:country":"IQ",
    "name:ara_x_preferred":[
        "\u0627\u0644\u0645\u062d\u0627\u062c\u064a\u0631 \u0627\u0644\u063a\u0631\u0628\u064a\u0629"
    ],
    "name:und_x_variant":[
        "Al Ma\u1e29\u0101j\u012br al Gharb\u012byah"
    ],
    "wof:name":"Al Mahajir al Gharbiyah",
    "wof:placetype":"locality"
},
  "geometry": {"coordinates":[44.49945,31.92934],"type":"Point"}
}