{
  "type": "Feature",
  "properties": {
    "gn:admin1_code":"18.0",
    "gn:admin2_code":"9166616.0",
    "gn:asciiname":"Khalid Hazal",
    "gn:country_code":"IQ",
    "gn:dem":39,
    "gn:feature_class":"P",
    "gn:feature_code":"PPL",
    "gn:name":"Kh\u0101lid Haz\u0101l",
    "gn:population":0,
    "gn:timezone":"Asia/Baghdad",
    "iso:country":"IQ",
    "name:ara_x_preferred":[
        "\u062e\u0627\u0644\u062f \u0647\u0632\u0627\u0644"
    ],
    "name:und_x_variant":[
        "Kh\u0101lid Haz\u0101l"
    ],
    "wof:name":"Khalid Hazal",
    "wof:placetype":"locality"
},
  "geometry": {"coordinates":[44.29943,33.8623],"type":"Point"}
}