{
  "type": "Feature",
  "properties": {
    "gn:admin1_code":"1.0",
    "gn:admin2_code":"98718.0",
    "gn:asciiname":"'Id 'Abd Allah al Hamad",
    "gn:country_code":"IQ",
    "gn:dem":49,
    "gn:feature_class":"P",
    "gn:feature_code":"PPL",
    "gn:name":"\u2018\u012ad \u2018Abd All\u0101h al \u1e28amad",
    "gn:population":0,
    "gn:timezone":"Asia/Baghdad",
    "iso:country":"IQ",
    "name:ara_x_preferred":[
        "\u0639\u064a\u062f \u0639\u0628\u062f \u0627\u0644\u0644\u0647 \u0627\u0644\u062d\u0645\u062f"
    ],
    "name:und_x_variant":[
        "\u2018\u012ad \u2018Abd All\u0101h al \u1e28amad"
    ],
    "wof:name":"'Id 'Abd Allah al Hamad",
    "wof:placetype":"locality"
},
  "geometry": {"coordinates":[43.47518,33.4302],"type":"Point"}
}