{
  "type": "Feature",
  "properties": {
    "gn:admin1_code":"18.0",
    "gn:admin2_code":"6783103.0",
    "gn:asciiname":"'Arab Albu Qaraj",
    "gn:country_code":"IQ",
    "gn:dem":49,
    "gn:feature_class":"P",
    "gn:feature_code":"PPL",
    "gn:name":"\u2018Arab Alb\u016b Qar\u0101j",
    "gn:population":0,
    "gn:timezone":"Asia/Baghdad",
    "iso:country":"IQ",
    "name:ara_x_preferred":[
        "\u0639\u0631\u0628 \u0627\u0644\u0628\u0648 \u0642\u0631\u0627\u062c"
    ],
    "name:und_x_variant":[
        "\u2018Arab Alb\u016b Qar\u0101j"
    ],
    "wof:name":"'Arab Albu Qaraj",
    "wof:placetype":"locality"
},
  "geometry": {"coordinates":[44.14061,34.07344000000001],"type":"Point"}
}