{
  "type": "Feature",
  "properties": {
    "gn:admin1_code":"10.0",
    "gn:admin2_code":"9166680.0",
    "gn:asciiname":"Lami' Mahdi",
    "gn:country_code":"IQ",
    "gn:dem":45,
    "gn:feature_class":"P",
    "gn:feature_code":"PPL",
    "gn:name":"L\u0101mi\u2018 Mahd\u012b",
    "gn:population":0,
    "gn:timezone":"Asia/Baghdad",
    "iso:country":"IQ",
    "name:ara_x_preferred":[
        "\u0644\u0627\u0645\u0639 \u0645\u0647\u062f\u064a"
    ],
    "name:und_x_variant":[
        "L\u0101mi\u2018 Mahd\u012b"
    ],
    "wof:name":"Lami' Mahdi",
    "wof:placetype":"locality"
},
  "geometry": {"coordinates":[44.90682,33.76271],"type":"Point"}
}