{
  "type": "Feature",
  "properties": {
    "gn:admin1_code":"15.0",
    "gn:admin2_code":"90392.0",
    "gn:asciiname":"Bir Khattaf",
    "gn:country_code":"IQ",
    "gn:dem":398,
    "gn:feature_class":"P",
    "gn:feature_code":"PPL",
    "gn:name":"B\u012br Kha\u0163\u0163\u0101f",
    "gn:population":0,
    "gn:timezone":"Asia/Baghdad",
    "iso:country":"IQ",
    "name:ara_x_preferred":[
        "\u0628\u064a\u0631 \u062e\u0637\u0627\u0641"
    ],
    "name:kur_x_preferred":[
        "B\u00eer Xetaf"
    ],
    "name:kur_x_variant":[
        "\u0628\u064a\u0631 \u062e\u06d5\u062a\u0627\u0641"
    ],
    "name:und_x_variant":[
        "Bir Khataf",
        "B\u012br Kha\u0163\u0163\u0101f"
    ],
    "wof:name":"Bir Khattaf",
    "wof:placetype":"locality"
},
  "geometry": {"coordinates":[42.22544,36.61375],"type":"Point"}
}