{
  "type": "Feature",
  "properties": {
    "gn:admin1_code":"15.0",
    "gn:admin2_code":"9166620.0",
    "gn:asciiname":"'Irnah",
    "gn:country_code":"IQ",
    "gn:dem":337,
    "gn:feature_class":"P",
    "gn:feature_code":"PPLF",
    "gn:name":"\u2018Irnah",
    "gn:population":0,
    "gn:timezone":"Asia/Baghdad",
    "iso:country":"IQ",
    "name:ara_x_preferred":[
        "\u0639\u0631\u0646\u0629"
    ],
    "name:und_x_variant":[
        "\u2018Irnah"
    ],
    "wof:name":"'Irnah",
    "wof:placetype":"locality"
},
  "geometry": {"coordinates":[41.74806,36.09647],"type":"Point"}
}