{
  "type": "Feature",
  "properties": {
    "gn:admin1_code":"18.0",
    "gn:admin2_code":"6805736.0",
    "gn:asciiname":"'Arab Hassun 'Abd",
    "gn:country_code":"IQ",
    "gn:dem":47,
    "gn:feature_class":"P",
    "gn:feature_code":"PPL",
    "gn:name":"\u2018Arab \u1e28ass\u016bn \u2018Abd",
    "gn:population":0,
    "gn:timezone":"Asia/Baghdad",
    "iso:country":"IQ",
    "name:ara_x_preferred":[
        "\u0639\u0631\u0628 \u062d\u0633\u0648\u0646 \u0639\u0628\u062f"
    ],
    "name:und_x_variant":[
        "\u2018Arab \u1e28ass\u016bn \u2018Abd"
    ],
    "wof:name":"'Arab Hassun 'Abd",
    "wof:placetype":"locality"
},
  "geometry": {"coordinates":[44.16416,34.04040999999999],"type":"Point"}
}