{
  "type": "Feature",
  "properties": {
    "gn:admin1_code":"4.0",
    "gn:admin2_code":"6850588.0",
    "gn:asciiname":"'Arak al 'Ali",
    "gn:country_code":"IQ",
    "gn:dem":14,
    "gn:feature_class":"P",
    "gn:feature_code":"PPL",
    "gn:name":"\u2018Arak al \u2018Al\u012b",
    "gn:population":0,
    "gn:timezone":"Asia/Baghdad",
    "iso:country":"IQ",
    "name:ara_x_preferred":[
        "\u0639\u0631\u0643 \u0627\u0644\u0639\u0644\u064a"
    ],
    "name:und_x_variant":[
        "\u2018Arak al \u2018Al\u012b"
    ],
    "wof:name":"'Arak al 'Ali",
    "wof:placetype":"locality"
},
  "geometry": {"coordinates":[44.89209,31.45196],"type":"Point"}
}