{
  "type": "Feature",
  "properties": {
    "gn:admin1_code":"10.0",
    "gn:admin2_code":"97988.0",
    "gn:asciiname":"Al Qadisiyah",
    "gn:country_code":"IQ",
    "gn:dem":39,
    "gn:feature_class":"P",
    "gn:feature_code":"PPL",
    "gn:name":"Al Q\u0101dis\u012byah",
    "gn:population":0,
    "gn:timezone":"Asia/Baghdad",
    "iso:country":"IQ",
    "name:ara_x_preferred":[
        "\u0627\u0644\u0642\u0627\u062f\u0633\u064a\u0629"
    ],
    "name:und_x_variant":[
        "Al Q\u0101dis\u012byah"
    ],
    "wof:name":"Al Qadisiyah",
    "wof:placetype":"locality"
},
  "geometry": {"coordinates":[44.43504,33.71955999999999],"type":"Point"}
}