{
  "type": "Feature",
  "properties": {
    "gn:admin1_code":"11.0",
    "gn:admin2_code":"9166592.0",
    "gn:asciiname":"Khalifan",
    "gn:country_code":"IQ",
    "gn:dem":910,
    "gn:feature_class":"P",
    "gn:feature_code":"PPL",
    "gn:name":"Khalif\u0101n",
    "gn:population":0,
    "gn:timezone":"Asia/Baghdad",
    "iso:country":"IQ",
    "name:aze_x_preferred":[
        "X\u0259lifan"
    ],
    "name:ckb_x_preferred":[
        "\u062e\u06d5\u0644\u06cc\u0641\u0627\u0646"
    ],
    "name:fas_x_preferred":[
        "\u062e\u0644\u06cc\u0641\u0627\u0646"
    ],
    "name:und_x_variant":[
        "Khalif\u0101n"
    ],
    "wof:name":"Khalifan",
    "wof:placetype":"locality"
},
  "geometry": {"coordinates":[44.41116,36.6505],"type":"Point"}
}