{
  "type": "Feature",
  "properties": {
    "gn:admin1_code":"10.0",
    "gn:admin2_code":"94296.0",
    "gn:asciiname":"Tawai",
    "gn:country_code":"IQ",
    "gn:dem":174,
    "gn:feature_class":"P",
    "gn:feature_code":"PPL",
    "gn:name":"Tawai",
    "gn:population":0,
    "gn:timezone":"Asia/Baghdad",
    "iso:country":"IQ",
    "name:ara_x_preferred":[
        "\u0637\u064a\u0627\u0648\u064a"
    ],
    "name:und_x_variant":[
        "Tiy\u0101wah",
        "Tay\u0101w\u012b",
        "\u0162ay\u0101w\u012b"
    ],
    "wof:name":"Tawai",
    "wof:placetype":"locality"
},
  "geometry": {"coordinates":[44.66256,34.51947],"type":"Point"}
}