{
  "type": "Feature",
  "properties": {
    "gn:admin1_code":"13.0",
    "gn:asciiname":"Bi'r Muhaydi",
    "gn:country_code":"IQ",
    "gn:dem":276,
    "gn:feature_class":"P",
    "gn:feature_code":"PPL",
    "gn:name":"Bi\u2019r Muhayd\u012b",
    "gn:population":0,
    "gn:timezone":"Asia/Baghdad",
    "iso:country":"IQ",
    "name:ara_x_preferred":[
        "\u0628\u0626\u0631 \u0645\u0647\u064a\u062f\u064a"
    ],
    "name:kur_x_preferred":[
        "Seyd\u00ee"
    ],
    "name:kur_x_variant":[
        "\u0633\u06d5\u064a\u062f\u0649"
    ],
    "name:und_x_variant":[
        "Bar Muhaidi",
        "B\u0101r Muhayd\u012b",
        "Bi\u2019r Muhayd\u012b",
        "Saidy"
    ],
    "wof:name":"Bi'r Muhaydi",
    "wof:placetype":"locality"
},
  "geometry": {"coordinates":[43.78461,35.63171],"type":"Point"}
}