{
  "type": "Feature",
  "properties": {
    "gn:admin1_code":"5.0",
    "gn:admin2_code":"91176.0",
    "gn:asciiname":"Qularash",
    "gn:country_code":"IQ",
    "gn:dem":1319,
    "gn:feature_class":"P",
    "gn:feature_code":"PPL",
    "gn:name":"Q\u016bl\u0101rash",
    "gn:population":0,
    "gn:timezone":"Asia/Baghdad",
    "iso:country":"IQ",
    "name:ara_x_preferred":[
        "\u0642\u0648\u0644\u0627\u0631\u0634"
    ],
    "name:kur_x_preferred":[
        "Qu\u0142e \u1e5eesh"
    ],
    "name:kur_x_variant":[
        "\u0642\u0648\u06b5\u06d5 \u0695\u06d5\u0634"
    ],
    "name:und_x_variant":[
        "Q\u016bl\u0101rash",
        "Qula Rash"
    ],
    "wof:name":"Qularash",
    "wof:placetype":"locality"
},
  "geometry": {"coordinates":[45.4632,35.65561],"type":"Point"}
}