{
  "type": "Feature",
  "properties": {
    "gn:admin1_code":"7.0",
    "gn:admin2_code":"99101.0",
    "gn:asciiname":"Sha'lan Jasim 'Udwan",
    "gn:country_code":"IQ",
    "gn:dem":36,
    "gn:feature_class":"P",
    "gn:feature_code":"PPL",
    "gn:name":"Sha\u2018l\u0101n J\u0101sim \u2018Udw\u0101n",
    "gn:population":0,
    "gn:timezone":"Asia/Baghdad",
    "iso:country":"IQ",
    "name:ara_x_preferred":[
        "\u062c\u0627\u0633\u0645 \u0627\u0644\u0639\u062f\u0648\u0627\u0646"
    ],
    "name:ara_x_variant":[
        "\u0634\u0639\u0644\u0627\u0646 \u062c\u0627\u0633\u0645 \u0639\u062f\u0648\u0627\u0646"
    ],
    "name:und_x_variant":[
        "J\u0101sim al \u2018Udw\u0101n",
        "Sha\u2018l\u0101n J\u0101sim \u2018Udw\u0101n"
    ],
    "wof:name":"Sha'lan Jasim 'Udwan",
    "wof:placetype":"locality"
},
  "geometry": {"coordinates":[44.38446,33.14891],"type":"Point"}
}