{
  "type": "Feature",
  "properties": {
    "gn:admin1_code":"6.0",
    "gn:admin2_code":"99348.0",
    "gn:asciiname":"Qaryat Albu Hasan",
    "gn:country_code":"IQ",
    "gn:dem":29,
    "gn:feature_class":"P",
    "gn:feature_code":"PPL",
    "gn:name":"Qaryat \u0100lb\u016b \u1e28asan",
    "gn:population":0,
    "gn:timezone":"Asia/Baghdad",
    "iso:country":"IQ",
    "name:ara_x_preferred":[
        "\u0642\u0631\u064a\u0629 \u0627\u0644\u0628\u0648 \u062d\u0633\u0646"
    ],
    "name:und_x_variant":[
        "Qaryat \u0100lb\u016b \u1e28asan"
    ],
    "wof:name":"Qaryat Albu Hasan",
    "wof:placetype":"locality"
},
  "geometry": {"coordinates":[44.35705,32.41194],"type":"Point"}
}