{
  "type": "Feature",
  "properties": {
    "gn:admin1_code":"7.0",
    "gn:admin2_code":"9166569.0",
    "gn:asciiname":"Fadil Salim",
    "gn:country_code":"IQ",
    "gn:dem":39,
    "gn:feature_class":"P",
    "gn:feature_code":"PPL",
    "gn:name":"F\u0101\u1e11il Sal\u012bm",
    "gn:population":0,
    "gn:timezone":"Asia/Baghdad",
    "iso:country":"IQ",
    "name:ara_x_preferred":[
        "\u0641\u0627\u0636\u0644 \u0633\u0644\u064a\u0645"
    ],
    "name:und_x_variant":[
        "F\u0101\u1e11il Sal\u012bm \u1e28asan",
        "\u0641\u0627\u0636\u0644 \u0633\u0644\u064a\u0645 \u062d\u0633\u0646",
        "F\u0101\u1e11il Sal\u012bm"
    ],
    "wof:name":"Fadil Salim",
    "wof:placetype":"locality"
},
  "geometry": {"coordinates":[44.23123,33.64915],"type":"Point"}
}