{
  "type": "Feature",
  "properties": {
    "gn:admin1_code":"18.0",
    "gn:admin2_code":"6805736.0",
    "gn:asciiname":"Kashkariyah",
    "gn:country_code":"IQ",
    "gn:dem":45,
    "gn:feature_class":"P",
    "gn:feature_code":"PPL",
    "gn:name":"Kashkar\u012byah",
    "gn:population":0,
    "gn:timezone":"Asia/Baghdad",
    "iso:country":"IQ",
    "name:ara_x_preferred":[
        "\u0643\u0634\u0643\u0631\u064a\u0629"
    ],
    "name:und_x_variant":[
        "Kashkar\u012byah"
    ],
    "wof:name":"Kashkariyah",
    "wof:placetype":"locality"
},
  "geometry": {"coordinates":[44.17609,33.9349],"type":"Point"}
}