{
  "type": "Feature",
  "properties": {
    "gn:admin1_code":"18.0",
    "gn:admin2_code":"6805736.0",
    "gn:asciiname":"Hariz al 'Ali",
    "gn:country_code":"IQ",
    "gn:dem":61,
    "gn:feature_class":"P",
    "gn:feature_code":"PPL",
    "gn:name":"\u1e28ar\u012bz al \u2018Al\u012b",
    "gn:population":0,
    "gn:timezone":"Asia/Baghdad",
    "iso:country":"IQ",
    "name:ara_x_preferred":[
        "\u062d\u0631\u064a\u0632 \u0627\u0644\u0639\u0644\u064a"
    ],
    "name:und_x_variant":[
        "\u1e28ar\u012bz al \u2018Al\u012b"
    ],
    "wof:name":"Hariz al 'Ali",
    "wof:placetype":"locality"
},
  "geometry": {"coordinates":[43.81924,33.9391],"type":"Point"}
}