{
  "type": "Feature",
  "properties": {
    "gn:admin1_code":"10.0",
    "gn:admin2_code":"94590.0",
    "gn:asciiname":"Shaykh Jasim",
    "gn:country_code":"IQ",
    "gn:dem":141,
    "gn:feature_class":"P",
    "gn:feature_code":"PPL",
    "gn:name":"Shaykh J\u0101sim",
    "gn:population":0,
    "gn:timezone":"Asia/Baghdad",
    "iso:country":"IQ",
    "name:ara_x_preferred":[
        "\u0634\u064a\u062e \u062c\u0627\u0633\u0645"
    ],
    "name:und_x_variant":[
        "Shaikh J\u0101sim",
        "Shaykh J\u0101sim"
    ],
    "wof:name":"Shaykh Jasim",
    "wof:placetype":"locality"
},
  "geometry": {"coordinates":[45.23855,34.36483],"type":"Point"}
}