{
  "type": "Feature",
  "properties": {
    "gn:admin1_code":"5.0",
    "gn:admin2_code":"96204.0",
    "gn:asciiname":"Kirdi Safa al 'Ulya",
    "gn:country_code":"IQ",
    "gn:dem":544,
    "gn:feature_class":"P",
    "gn:feature_code":"PPL",
    "gn:name":"Kird\u012b \u015eaf\u0101 al \u2018Uly\u0101",
    "gn:population":0,
    "gn:timezone":"Asia/Baghdad",
    "iso:country":"IQ",
    "name:ara_x_preferred":[
        "\u0643\u0631\u062f\u064a \u0635\u0641\u0627 \u0627\u0644\u0639\u0644\u064a\u0627"
    ],
    "name:kur_x_preferred":[
        "Tepey Sefay Ser\u00fb"
    ],
    "name:kur_x_variant":[
        "Tepe Sefa",
        "\u062a\u06d5\u067e\u06d5\u0649 \u0633\u06d5\u0641\u0627\u0649 \u0633\u06d5\u0631\u0648\u0648",
        "\u062a\u06d5\u067e\u06d5 \u0633\u06d5\u0641\u0627"
    ],
    "name:und_x_variant":[
        "Kird\u012b \u015eaf\u0101 al \u2018Uly\u0101",
        "Gird-\u012b \u015eaf\u0101\u2019",
        "Tapa Safa"
    ],
    "wof:name":"Kirdi Safa al 'Ulya",
    "wof:placetype":"locality"
},
  "geometry": {"coordinates":[45.98014000000001,35.28831],"type":"Point"}
}