{
  "type": "Feature",
  "properties": {
    "gn:admin1_code":"13.0",
    "gn:admin2_code":"9166581.0",
    "gn:asciiname":"Qaryat Mulla Nasr",
    "gn:country_code":"IQ",
    "gn:dem":163,
    "gn:feature_class":"P",
    "gn:feature_code":"PPL",
    "gn:name":"Qaryat Mull\u0101 N\u0101\u015fr",
    "gn:population":0,
    "gn:timezone":"Asia/Baghdad",
    "iso:country":"IQ",
    "name:ara_x_preferred":[
        "\u0642\u0631\u064a\u0629 \u0645\u0644\u0627 \u0646\u0627\u0635\u0631"
    ],
    "name:und_x_variant":[
        "Qaryat Mull\u0101 N\u0101\u015fr"
    ],
    "wof:name":"Qaryat Mulla Nasr",
    "wof:placetype":"locality"
},
  "geometry": {"coordinates":[44.08063,34.97605],"type":"Point"}
}