{
  "type": "Feature",
  "properties": {
    "gn:admin1_code":"8.0",
    "gn:admin2_code":"97269.0",
    "gn:asciiname":"Baraybahar",
    "gn:country_code":"IQ",
    "gn:dem":679,
    "gn:feature_class":"P",
    "gn:feature_code":"PPL",
    "gn:name":"Baraybah\u0101r",
    "gn:population":0,
    "gn:timezone":"Asia/Baghdad",
    "iso:country":"IQ",
    "name:ara_x_preferred":[
        "\u0628\u0631\u064a\u0628\u0647\u0627\u0631"
    ],
    "name:kur_x_preferred":[
        "Bir\u00ee Behar"
    ],
    "name:kur_x_variant":[
        "\u0628\u0631\u06cc \u0628\u06d5\u06be\u0627\u0631",
        "Ber\u00ea Behar",
        "\u0628\u06d5\u0631\u06ce \u0628\u06d5\u06be\u0627\u0631"
    ],
    "name:und_x_variant":[
        "B\u0113ribah\u0101r",
        "Bribahar",
        "Baraybah\u0101r",
        "Bare Bahar"
    ],
    "wof:name":"Baraybahar",
    "wof:placetype":"locality"
},
  "geometry": {"coordinates":[43.0978,36.87785],"type":"Point"}
}