{
  "type": "Feature",
  "properties": {
    "gn:admin1_code":"5.0",
    "gn:admin2_code":"98464.0",
    "gn:asciiname":"Harginah",
    "gn:country_code":"IQ",
    "gn:dem":915,
    "gn:feature_class":"P",
    "gn:feature_code":"PPL",
    "gn:name":"Harg\u012bnah",
    "gn:population":0,
    "gn:timezone":"Asia/Baghdad",
    "iso:country":"IQ",
    "name:ara_x_preferred":[
        "\u0647\u0631\u06af\u064a\u0646\u0629"
    ],
    "name:kur_x_preferred":[
        "Herg\u00eane"
    ],
    "name:kur_x_variant":[
        "\u0647\u06d5\u0631\u06af\u06ce\u0646\u06d5"
    ],
    "name:und_x_variant":[
        "Harg\u0113na",
        "Harg\u012bnah",
        "Harg\u0113na Sh\u0101ykh",
        "Hark\u012bnah",
        "Hargena",
        "\u0647\u0631\u0643\u064a\u0646\u0629"
    ],
    "wof:name":"Harginah",
    "wof:placetype":"locality"
},
  "geometry": {"coordinates":[45.34052,35.42342],"type":"Point"}
}