{
  "type": "Feature",
  "properties": {
    "gn:admin1_code":"6.0",
    "gn:admin2_code":"99358.0",
    "gn:asciiname":"Shabib Zahir",
    "gn:country_code":"IQ",
    "gn:dem":25,
    "gn:feature_class":"P",
    "gn:feature_code":"PPL",
    "gn:name":"Shab\u012bb Z\u0327\u0101hir",
    "gn:population":0,
    "gn:timezone":"Asia/Baghdad",
    "iso:country":"IQ",
    "name:ara_x_preferred":[
        "\u0634\u0628\u064a\u0628 \u0638\u0627\u0647\u0631"
    ],
    "name:und_x_variant":[
        "Shab\u012bb Z\u0327\u0101hir"
    ],
    "wof:name":"Shabib Zahir",
    "wof:placetype":"locality"
},
  "geometry": {"coordinates":[44.98498,32.4334],"type":"Point"}
}