{
  "type": "Feature",
  "properties": {
    "gn:admin1_code":"1.0",
    "gn:admin2_code":"98718.0",
    "gn:asciiname":"Albu Julayb",
    "gn:country_code":"IQ",
    "gn:dem":57,
    "gn:feature_class":"P",
    "gn:feature_code":"PPL",
    "gn:name":"\u0100lb\u016b Julayb",
    "gn:population":0,
    "gn:timezone":"Asia/Baghdad",
    "iso:country":"IQ",
    "name:ara_x_preferred":[
        "\u0627\u0644\u0628\u0648 \u0686\u0644\u064a\u0628"
    ],
    "name:und_x_variant":[
        "\u0100lb\u016b Julayb",
        "\u0627\u0644\u0628\u0648 \u062c\u0644\u064a\u0628",
        "\u0100lb\u016b Chulayb"
    ],
    "wof:name":"Albu Julayb",
    "wof:placetype":"locality"
},
  "geometry": {"coordinates":[43.1772,33.46555],"type":"Point"}
}