{
  "type": "Feature",
  "properties": {
    "gn:admin1_code":"11.0",
    "gn:admin2_code":"93817.0",
    "gn:asciiname":"Majid Yunus",
    "gn:country_code":"IQ",
    "gn:dem":275,
    "gn:feature_class":"P",
    "gn:feature_code":"PPL",
    "gn:name":"M\u0101jid Y\u016bnus",
    "gn:population":0,
    "gn:timezone":"Asia/Baghdad",
    "iso:country":"IQ",
    "name:ara_x_preferred":[
        "\u0645\u0627\u062c\u062f \u064a\u0648\u0646\u0633"
    ],
    "name:ara_x_variant":[
        "M\u0101jid Y\u016bnus"
    ],
    "name:kur_x_preferred":[
        "Majid Yunis"
    ],
    "name:kur_x_variant":[
        "Mec\u00eed Yunis",
        "\u0645\u06d5\u062c\u064a\u062f \u064a\u0648\u0646\u0633"
    ],
    "name:und_x_variant":[
        "Maj\u012bd Y\u016bnis",
        "M\u0101jid Y\u016bmus",
        "M\u0101jid Yunis",
        "Majid Yunis"
    ],
    "wof:name":"Majid Yunus",
    "wof:placetype":"locality"
},
  "geometry": {"coordinates":[43.66299,35.93275999999999],"type":"Point"}
}