{
  "type": "Feature",
  "properties": {
    "gn:admin1_code":"4.0",
    "gn:admin2_code":"99763.0",
    "gn:asciiname":"Qaryat Azdir",
    "gn:country_code":"IQ",
    "gn:dem":22,
    "gn:feature_class":"P",
    "gn:feature_code":"PPL",
    "gn:name":"Qaryat Azd\u012br",
    "gn:population":0,
    "gn:timezone":"Asia/Baghdad",
    "iso:country":"IQ",
    "name:ara_x_preferred":[
        "\u0642\u0631\u064a\u0629 \u0627\u0632\u062f\u064a\u0631"
    ],
    "name:und_x_variant":[
        "Qaryat Azd\u012br"
    ],
    "wof:name":"Qaryat Azdir",
    "wof:placetype":"locality"
},
  "geometry": {"coordinates":[44.9559,32.08873],"type":"Point"}
}