{
  "type": "Feature",
  "properties": {
    "gn:admin1_code":"17.0",
    "gn:admin2_code":"9166629.0",
    "gn:asciiname":"Kamil 'Abbud",
    "gn:country_code":"IQ",
    "gn:dem":25,
    "gn:feature_class":"P",
    "gn:feature_code":"PPL",
    "gn:name":"K\u0101mil \u2018Abb\u016bd",
    "gn:population":0,
    "gn:timezone":"Asia/Baghdad",
    "iso:country":"IQ",
    "name:ara_x_preferred":[
        "\u0643\u0627\u0645\u0644 \u0639\u0628\u0648\u062f"
    ],
    "name:ara_x_variant":[
        "K\u0101mil \u2018Abb\u016bd"
    ],
    "wof:name":"Kamil 'Abbud",
    "wof:placetype":"locality"
},
  "geometry": {"coordinates":[44.54907,32.13561],"type":"Point"}
}