{
  "type": "Feature",
  "properties": {
    "gn:admin1_code":"7.0",
    "gn:admin2_code":"9166569.0",
    "gn:asciiname":"Sabbar Badawi",
    "gn:country_code":"IQ",
    "gn:dem":38,
    "gn:feature_class":"P",
    "gn:feature_code":"PPL",
    "gn:name":"\u015eabb\u0101r Badaw\u012b",
    "gn:population":0,
    "gn:timezone":"Asia/Baghdad",
    "iso:country":"IQ",
    "name:ara_x_preferred":[
        "\u0635\u0628\u0627\u0631 \u0628\u062f\u0648\u064a"
    ],
    "name:und_x_variant":[
        "\u015eabb\u0101r Badaw\u012b"
    ],
    "wof:name":"Sabbar Badawi",
    "wof:placetype":"locality"
},
  "geometry": {"coordinates":[44.14739,33.69155],"type":"Point"}
}