{
  "type": "Feature",
  "properties": {
    "gn:admin1_code":"7.0",
    "gn:admin2_code":"9166569.0",
    "gn:asciiname":"Mahmud al Husayn",
    "gn:cc2":"IQ",
    "gn:country_code":"IQ",
    "gn:dem":34,
    "gn:feature_class":"P",
    "gn:feature_code":"PPL",
    "gn:name":"Ma\u1e29m\u016bd al \u1e28usayn",
    "gn:population":0,
    "gn:timezone":"Asia/Baghdad",
    "iso:country":"IQ",
    "name:und_x_variant":[
        "Mahm\u016bd al Husain",
        "Ma\u1e29m\u016bd al \u1e28usayn"
    ],
    "wof:name":"Mahmud al Husayn",
    "wof:placetype":"locality"
},
  "geometry": {"coordinates":[44.33333,33.68333],"type":"Point"}
}