{
  "type": "Feature",
  "properties": {
    "gn:admin1_code":"11.0",
    "gn:admin2_code":"9166534.0",
    "gn:asciiname":"Tuya",
    "gn:country_code":"IQ",
    "gn:dem":1310,
    "gn:feature_class":"P",
    "gn:feature_code":"PPL",
    "gn:name":"Tuya",
    "gn:population":0,
    "gn:timezone":"Asia/Baghdad",
    "iso:country":"IQ",
    "name:ara_x_preferred":[
        "\u062a\u0648\u064a"
    ],
    "name:ara_x_variant":[
        "Tuw\u012b"
    ],
    "name:deu_x_preferred":[
        "Tafelvulkan"
    ],
    "name:fra_x_preferred":[
        "Tuya"
    ],
    "name:ind_x_preferred":[
        "Tuya"
    ],
    "name:isl_x_preferred":[
        "Stapi"
    ],
    "name:ita_x_preferred":[
        "Tuya"
    ],
    "name:kur_x_preferred":[
        "Tuy\u00ee"
    ],
    "name:kur_x_variant":[
        "\u062a\u0648\u064a\u0649",
        "Tuya",
        "\u062a\u0648\u064a\u0627"
    ],
    "name:por_x_preferred":[
        "Tuya"
    ],
    "name:spa_x_preferred":[
        "Tuya"
    ],
    "name:ukr_x_preferred":[
        "\u0422\u0443\u0439\u044f"
    ],
    "name:und_x_variant":[
        "Tupy",
        "T\u016by\u0113"
    ],
    "wof:name":"Tuya",
    "wof:placetype":"locality"
},
  "geometry": {"coordinates":[44.08863,37.18027],"type":"Point"}
}