{
  "type": "Feature",
  "properties": {
    "gn:admin1_code":"5.0",
    "gn:admin2_code":"96204.0",
    "gn:asciiname":"Dallah Mar",
    "gn:country_code":"IQ",
    "gn:dem":1075,
    "gn:feature_class":"P",
    "gn:feature_code":"PPL",
    "gn:name":"D\u0101llah M\u0101r",
    "gn:population":0,
    "gn:timezone":"Asia/Baghdad",
    "iso:country":"IQ",
    "name:ara_x_preferred":[
        "\u062f\u0627\u0644\u0629 \u0645\u0627\u0631"
    ],
    "name:kur_x_preferred":[
        "De\u0142e Me\u1e5f"
    ],
    "name:kur_x_variant":[
        "\u062f\u06d5\u06b5\u06d5 \u0645\u06d5\u0695"
    ],
    "name:und_x_variant":[
        "D\u0101l\u0101m\u0101",
        "D\u0101llah M\u0101r",
        "D\u0101l\u0101m\u0101r",
        "Dalamar"
    ],
    "wof:name":"Dallah Mar",
    "wof:placetype":"locality"
},
  "geometry": {"coordinates":[46.04028,35.15733],"type":"Point"}
}