{
  "type": "Feature",
  "properties": {
    "gn:admin1_code":"6.0",
    "gn:admin2_code":"99358.0",
    "gn:asciiname":"Qaryat Luhyah",
    "gn:country_code":"IQ",
    "gn:dem":27,
    "gn:feature_class":"P",
    "gn:feature_code":"PPL",
    "gn:name":"Qaryat Lu\u1e29yah",
    "gn:population":0,
    "gn:timezone":"Asia/Baghdad",
    "iso:country":"IQ",
    "name:ara_x_preferred":[
        "\u0642\u0631\u064a\u0629 \u0644\u062d\u064a\u0629"
    ],
    "name:und_x_variant":[
        "Qaryat Lu\u1e29yah"
    ],
    "wof:name":"Qaryat Luhyah",
    "wof:placetype":"locality"
},
  "geometry": {"coordinates":[44.5918,32.26886],"type":"Point"}
}