{
  "type": "Feature",
  "properties": {
    "gn:admin1_code":"3.0",
    "gn:admin2_code":"98532.0",
    "gn:asciiname":"'Arab al Yasir",
    "gn:country_code":"IQ",
    "gn:dem":15,
    "gn:feature_class":"P",
    "gn:feature_code":"PPLL",
    "gn:name":"\u2018Arab al Y\u0101sir",
    "gn:population":0,
    "gn:timezone":"Asia/Baghdad",
    "iso:country":"IQ",
    "name:ara_x_preferred":[
        "\u0639\u0631\u0628 \u0627\u0644\u064a\u0627\u0633\u0631"
    ],
    "name:und_x_variant":[
        "\u2018Arab al Y\u0101sir"
    ],
    "wof:name":"'Arab al Yasir",
    "wof:placetype":"locality"
},
  "geometry": {"coordinates":[45.19681,31.39637],"type":"Point"}
}