{
  "type": "Feature",
  "properties": {
    "gn:admin1_code":"18.0",
    "gn:admin2_code":"6783103.0",
    "gn:asciiname":"'Arab 'Alwan Ahmad",
    "gn:country_code":"IQ",
    "gn:dem":54,
    "gn:feature_class":"P",
    "gn:feature_code":"PPL",
    "gn:name":"\u2018Arab \u2018Alw\u0101n A\u1e29mad",
    "gn:population":0,
    "gn:timezone":"Asia/Baghdad",
    "iso:country":"IQ",
    "name:ara_x_preferred":[
        "\u0639\u0631\u0628 \u0639\u0644\u0648\u0627\u0646 \u0627\u062d\u0645\u062f"
    ],
    "name:und_x_variant":[
        "\u2018Arab \u2018Alw\u0101n A\u1e29mad"
    ],
    "wof:name":"'Arab 'Alwan Ahmad",
    "wof:placetype":"locality"
},
  "geometry": {"coordinates":[44.05421,34.08938],"type":"Point"}
}