{
  "type": "Feature",
  "properties": {
    "gn:admin1_code":"6.0",
    "gn:admin2_code":"6818313.0",
    "gn:asciiname":"Bayt Munawir",
    "gn:country_code":"IQ",
    "gn:dem":26,
    "gn:feature_class":"P",
    "gn:feature_code":"PPL",
    "gn:name":"Bayt Mun\u0101wir",
    "gn:population":0,
    "gn:timezone":"Asia/Baghdad",
    "iso:country":"IQ",
    "name:ara_x_preferred":[
        "\u0628\u064a\u062a \u0645\u0646\u0627\u0648\u0631"
    ],
    "name:und_x_variant":[
        "Bayt Mun\u0101wir"
    ],
    "wof:name":"Bayt Munawir",
    "wof:placetype":"locality"
},
  "geometry": {"coordinates":[44.75373,32.44354000000001],"type":"Point"}
}