{
  "type": "Feature",
  "properties": {
    "gn:admin1_code":"15.0",
    "gn:admin2_code":"9166620.0",
    "gn:asciiname":"Shehab",
    "gn:country_code":"IQ",
    "gn:dem":474,
    "gn:feature_class":"P",
    "gn:feature_code":"PPL",
    "gn:name":"Shehab",
    "gn:population":0,
    "gn:timezone":"Asia/Baghdad",
    "iso:country":"IQ",
    "name:ara_x_preferred":[
        "\u0627\u0644\u0635\u0628\u0627\u062d\u064a\u0629"
    ],
    "name:kur_x_preferred":[
        "Shehab"
    ],
    "name:kur_x_variant":[
        "\u0634\u06d5\u0647\u0627\u0628"
    ],
    "name:und_x_variant":[
        "\u015eab\u0101\u1e29\u012byah",
        "A\u015f \u015eab\u0101\u1e29\u012byah"
    ],
    "wof:name":"Shehab",
    "wof:placetype":"locality"
},
  "geometry": {"coordinates":[41.8942,36.30526],"type":"Point"}
}