{
  "type": "Feature",
  "properties": {
    "gn:admin1_code":"6.0",
    "gn:admin2_code":"6818313.0",
    "gn:asciiname":"Kazim Isma'il",
    "gn:country_code":"IQ",
    "gn:dem":30,
    "gn:feature_class":"P",
    "gn:feature_code":"PPL",
    "gn:name":"K\u0101z\u0327im Ism\u0101\u2018\u012bl",
    "gn:population":0,
    "gn:timezone":"Asia/Baghdad",
    "iso:country":"IQ",
    "name:ara_x_preferred":[
        "\u0643\u0627\u0638\u0645 \u0627\u0633\u0645\u0627\u0639\u064a\u0644"
    ],
    "name:ara_x_variant":[
        "K\u0101z\u0327im Ism\u0101\u2018\u012bl"
    ],
    "wof:name":"Kazim Isma'il",
    "wof:placetype":"locality"
},
  "geometry": {"coordinates":[44.51138,32.49144],"type":"Point"}
}