{
  "type": "Feature",
  "properties": {
    "gn:admin1_code":"5.0",
    "gn:admin2_code":"98464.0",
    "gn:asciiname":"Darband Faqarah",
    "gn:country_code":"IQ",
    "gn:dem":822,
    "gn:feature_class":"P",
    "gn:feature_code":"PPL",
    "gn:name":"Darband Faqarah",
    "gn:population":0,
    "gn:timezone":"Asia/Baghdad",
    "iso:country":"IQ",
    "name:ara_x_preferred":[
        "\u062f\u0631\u0628\u0646\u062f \u0641\u0642\u0631\u0629"
    ],
    "name:kur_x_preferred":[
        "Derbend Fiqra"
    ],
    "name:kur_x_variant":[
        "Feq\u00eere Taze",
        "\u062f\u06d5\u0631\u0628\u06d5\u0646\u062f \u0641\u0642\u0631\u0627",
        "\u0641\u06d5\u0642\u064a\u0631\u06d5 \u062a\u0627\u0632\u06d5"
    ],
    "name:und_x_variant":[
        "Darband Faq\u0101r",
        "Darband Faqara",
        "Darband-i Faqara",
        "Darbanah Faqarah",
        "\u062f\u0631\u0628\u0646\u0629 \u0641\u0642\u0631\u0629",
        "Feqeera"
    ],
    "wof:name":"Darband Faqarah",
    "wof:placetype":"locality"
},
  "geometry": {"coordinates":[45.54973,35.29759],"type":"Point"}
}