{
  "type": "Feature",
  "properties": {
    "gn:admin1_code":"6.0",
    "gn:admin2_code":"99358.0",
    "gn:asciiname":"Qal'at Duhan",
    "gn:country_code":"IQ",
    "gn:dem":25,
    "gn:feature_class":"P",
    "gn:feature_code":"PPL",
    "gn:name":"Qal\u2018at D\u016bh\u0101n",
    "gn:population":0,
    "gn:timezone":"Asia/Baghdad",
    "iso:country":"IQ",
    "name:ara_x_preferred":[
        "\u0642\u0644\u0639\u0629 \u062f\u0648\u0647\u0627\u0646"
    ],
    "name:und_x_variant":[
        "Daw\u1e29\u0101n",
        "Qal\u2018at D\u016bh\u0101n"
    ],
    "wof:name":"Qal'at Duhan",
    "wof:placetype":"locality"
},
  "geometry": {"coordinates":[44.54027,32.262],"type":"Point"}
}