{
  "type": "Feature",
  "properties": {
    "gn:admin1_code":"15.0",
    "gn:admin2_code":"9166620.0",
    "gn:asciiname":"Sito",
    "gn:country_code":"IQ",
    "gn:dem":434,
    "gn:feature_class":"P",
    "gn:feature_code":"PPL",
    "gn:name":"Sito",
    "gn:population":0,
    "gn:timezone":"Asia/Baghdad",
    "iso:country":"IQ",
    "name:ara_x_preferred":[
        "\u2018Ayn Sind"
    ],
    "name:ara_x_variant":[
        "\u0633\u064a\u0646\u0648"
    ],
    "name:kur_x_preferred":[
        "S\u00eeto"
    ],
    "name:kur_x_variant":[
        "\u0633\u064a\u062a\u06c6"
    ],
    "name:und_x_variant":[
        "\u2018Ain Sind",
        "S\u012bn\u016b",
        "Sayn\u016b",
        "Sito"
    ],
    "wof:name":"Sito",
    "wof:placetype":"locality"
},
  "geometry": {"coordinates":[42.15472000000001,36.36472],"type":"Point"}
}