{
  "type": "Feature",
  "properties": {
    "gn:admin1_code":"11.0",
    "gn:admin2_code":"9166591.0",
    "gn:asciiname":"Barbi Bat",
    "gn:country_code":"IQ",
    "gn:dem":415,
    "gn:feature_class":"P",
    "gn:feature_code":"PPL",
    "gn:name":"Barb\u012b B\u0101t",
    "gn:population":0,
    "gn:timezone":"Asia/Baghdad",
    "iso:country":"IQ",
    "name:ara_x_preferred":[
        "\u0628\u0631\u0628\u064a \u0628\u0627\u062a"
    ],
    "name:und_x_variant":[
        "Barb\u012b B\u0101t"
    ],
    "wof:name":"Barbi Bat",
    "wof:placetype":"locality"
},
  "geometry": {"coordinates":[43.99754,36.4024],"type":"Point"}
}