{
  "type": "Feature",
  "properties": {
    "gn:admin1_code":"5.0",
    "gn:admin2_code":"9166684.0",
    "gn:asciiname":"Darahwirgan",
    "gn:country_code":"IQ",
    "gn:dem":1533,
    "gn:feature_class":"P",
    "gn:feature_code":"PPL",
    "gn:name":"Darahwirgan",
    "gn:population":0,
    "gn:timezone":"Asia/Baghdad",
    "iso:country":"IQ",
    "name:ara_x_preferred":[
        "\u062f\u0631\u0647 \u0648\u0631\u06af\u0627\u0646"
    ],
    "name:kur_x_preferred":[
        "Dire Wirgan"
    ],
    "name:kur_x_variant":[
        "Sereb Dere",
        "\u0633\u06d5\u0631\u06d5 \u062f\u06d5\u0631\u06d5",
        "\u062f\u0631\u06d5 \u0648\u0631\u06af\u0627\u0646"
    ],
    "name:und_x_variant":[
        "Dirahwirk\u0101n",
        "\u062f\u0631\u0647 \u0648\u0631\u0643\u0627\u0646",
        "Darawarkan",
        "Darahwirgan",
        "Drawrgan"
    ],
    "wof:name":"Darahwirgan",
    "wof:placetype":"locality"
},
  "geometry": {"coordinates":[45.8466,35.66415999999999],"type":"Point"}
}