{
  "type": "Feature",
  "properties": {
    "gn:admin1_code":"11.0",
    "gn:admin2_code":"95444.0",
    "gn:asciiname":"Koske",
    "gn:country_code":"IQ",
    "gn:dem":385,
    "gn:feature_class":"P",
    "gn:feature_code":"PPL",
    "gn:name":"Koske",
    "gn:population":0,
    "gn:timezone":"Asia/Baghdad",
    "iso:country":"IQ",
    "name:kur_x_preferred":[
        "Koske"
    ],
    "name:kur_x_variant":[
        "\u0643\u06c6\u0633\u0643\u06d5"
    ],
    "name:und_x_variant":[
        "G\u016bzkah",
        "K\u016bzkah",
        "G\u014dzkah",
        "Gozka",
        "K\u014dska",
        "Koska"
    ],
    "wof:name":"Koske",
    "wof:placetype":"locality"
},
  "geometry": {"coordinates":[44.00979,36.04103],"type":"Point"}
}