{
  "type": "Feature",
  "properties": {
    "gn:admin1_code":"7.0",
    "gn:admin2_code":"9166569.0",
    "gn:asciiname":"Jasim Muhammad Khalaf",
    "gn:country_code":"IQ",
    "gn:dem":38,
    "gn:feature_class":"P",
    "gn:feature_code":"PPL",
    "gn:name":"J\u0101sim Mu\u1e29ammad Khalaf",
    "gn:population":0,
    "gn:timezone":"Asia/Baghdad",
    "iso:country":"IQ",
    "name:ara_x_preferred":[
        "\u062c\u0627\u0633\u0645 \u0645\u062d\u0645\u062f \u062e\u0644\u0641"
    ],
    "name:und_x_variant":[
        "J\u0101sim Mu\u1e29ammad Khalaf"
    ],
    "wof:name":"Jasim Muhammad Khalaf",
    "wof:placetype":"locality"
},
  "geometry": {"coordinates":[44.16889000000001,33.64276],"type":"Point"}
}