{
  "type": "Feature",
  "properties": {
    "gn:admin1_code":"10.0",
    "gn:admin2_code":"99063.0",
    "gn:asciiname":"'Arab Husayn al Khalaf",
    "gn:country_code":"IQ",
    "gn:dem":46,
    "gn:feature_class":"P",
    "gn:feature_code":"PPL",
    "gn:name":"\u2018Arab \u1e28usayn al Khalaf",
    "gn:population":0,
    "gn:timezone":"Asia/Baghdad",
    "iso:country":"IQ",
    "name:ara_x_preferred":[
        "\u0639\u0631\u0628 \u062d\u0633\u064a\u0646 \u0627\u0644\u062e\u0644\u0641"
    ],
    "name:und_x_variant":[
        "\u2018Arab \u1e28usayn al Khalaf"
    ],
    "wof:name":"'Arab Husayn al Khalaf",
    "wof:placetype":"locality"
},
  "geometry": {"coordinates":[44.56183,33.72051],"type":"Point"}
}