{
  "type": "Feature",
  "properties": {
    "gn:admin1_code":"4.0",
    "gn:admin2_code":"99737.0",
    "gn:asciiname":"'Arab Sayyid Yassin",
    "gn:country_code":"IQ",
    "gn:dem":22,
    "gn:feature_class":"P",
    "gn:feature_code":"PPLL",
    "gn:name":"\u2018Arab Sayyid Y\u0101ss\u012bn",
    "gn:population":0,
    "gn:timezone":"Asia/Baghdad",
    "iso:country":"IQ",
    "name:ara_x_preferred":[
        "\u0639\u0631\u0628 \u0633\u064a\u062f \u064a\u0627\u0633\u064a\u0646"
    ],
    "name:und_x_variant":[
        "\u2018Arab Sayyid Y\u0101ss\u012bn"
    ],
    "wof:name":"'Arab Sayyid Yassin",
    "wof:placetype":"locality"
},
  "geometry": {"coordinates":[45.1019,32.08614],"type":"Point"}
}