{
  "type": "Feature",
  "properties": {
    "gn:admin1_code":"7.0",
    "gn:admin2_code":"9179819.0",
    "gn:asciiname":"'Arab Mahmud al Matar",
    "gn:country_code":"IQ",
    "gn:dem":30,
    "gn:feature_class":"P",
    "gn:feature_code":"PPL",
    "gn:name":"\u2018Arab Ma\u1e29m\u016bd al Ma\u0163ar",
    "gn:population":0,
    "gn:timezone":"Asia/Baghdad",
    "iso:country":"IQ",
    "name:ara_x_preferred":[
        "\u0639\u0631\u0628 \u0645\u062d\u0645\u0648\u062f \u0627\u0644\u0645\u0637\u0631"
    ],
    "name:und_x_variant":[
        "\u2018Arab Ma\u1e29m\u016bd al Ma\u0163ar"
    ],
    "wof:name":"'Arab Mahmud al Matar",
    "wof:placetype":"locality"
},
  "geometry": {"coordinates":[44.75157,33.06748],"type":"Point"}
}