{
  "type": "Feature",
  "properties": {
    "gn:admin1_code":"7.0",
    "gn:admin2_code":"9166542.0",
    "gn:asciiname":"Qaryat Al Yunus",
    "gn:country_code":"IQ",
    "gn:dem":46,
    "gn:feature_class":"P",
    "gn:feature_code":"PPL",
    "gn:name":"Qaryat \u0100l Y\u016bnus",
    "gn:population":0,
    "gn:timezone":"Asia/Baghdad",
    "iso:country":"IQ",
    "name:ara_x_preferred":[
        "\u0642\u0631\u064a\u0629 \u0622\u0644 \u064a\u0648\u0646\u0633"
    ],
    "name:und_x_variant":[
        "Qaryat \u0100l Y\u016bnis",
        "Qaryat \u0100l Y\u016bnus"
    ],
    "wof:name":"Qaryat Al Yunus",
    "wof:placetype":"locality"
},
  "geometry": {"coordinates":[43.85348,33.25067],"type":"Point"}
}