{
  "type": "Feature",
  "properties": {
    "gn:admin1_code":"5.0",
    "gn:admin2_code":"98464.0",
    "gn:asciiname":"Surkat al 'Ulya",
    "gn:country_code":"IQ",
    "gn:dem":910,
    "gn:feature_class":"P",
    "gn:feature_code":"PPL",
    "gn:name":"S\u016brkat al \u2018Uly\u0101",
    "gn:population":0,
    "gn:timezone":"Asia/Baghdad",
    "iso:country":"IQ",
    "name:ara_x_preferred":[
        "\u0633\u0648\u0631\u0643\u0629 \u0627\u0644\u0639\u0644\u064a\u0627"
    ],
    "name:kur_x_preferred":[
        "Surgey Ser\u00fb"
    ],
    "name:kur_x_variant":[
        "Surge",
        "\u0633\u0648\u0631\u06af\u06d5\u0649 \u0633\u06d5\u0631\u0648\u0648",
        "\u0633\u0648\u0631\u06af\u06d5"
    ],
    "name:und_x_variant":[
        "S\u016brkah al \u2018Uly\u0101",
        "S\u016brka-i Zh\u016br\u016b",
        "Sorga"
    ],
    "wof:name":"Surkat al 'Ulya",
    "wof:placetype":"locality"
},
  "geometry": {"coordinates":[45.30707,35.64239],"type":"Point"}
}