{
  "type": "Feature",
  "properties": {
    "gn:admin1_code":"6.0",
    "gn:admin2_code":"6818313.0",
    "gn:asciiname":"'Ali Muhsin",
    "gn:country_code":"IQ",
    "gn:dem":28,
    "gn:feature_class":"P",
    "gn:feature_code":"PPL",
    "gn:name":"\u2018Al\u012b Mu\u1e29sin",
    "gn:population":0,
    "gn:timezone":"Asia/Baghdad",
    "iso:country":"IQ",
    "name:ara_x_preferred":[
        "\u0639\u0644\u064a \u0645\u062d\u0633\u0646"
    ],
    "name:ara_x_variant":[
        "\u2018Al\u012b Mu\u1e29sin"
    ],
    "wof:name":"'Ali Muhsin",
    "wof:placetype":"locality"
},
  "geometry": {"coordinates":[44.64547,32.79362],"type":"Point"}
}