{
  "type": "Feature",
  "properties": {
    "gn:admin1_code":"10.0",
    "gn:admin2_code":"9166680.0",
    "gn:asciiname":"Hasan Laftah",
    "gn:country_code":"IQ",
    "gn:dem":36,
    "gn:feature_class":"P",
    "gn:feature_code":"PPL",
    "gn:name":"\u1e28asan Laftah",
    "gn:population":0,
    "gn:timezone":"Asia/Baghdad",
    "iso:country":"IQ",
    "name:ara_x_preferred":[
        "\u062d\u0633\u0646 \u0644\u0641\u062a\u0647"
    ],
    "name:und_x_variant":[
        "\u1e28asan Laftah"
    ],
    "wof:name":"Hasan Laftah",
    "wof:placetype":"locality"
},
  "geometry": {"coordinates":[45.21748,33.53645],"type":"Point"}
}