{
  "type": "Feature",
  "properties": {
    "gn:admin1_code":"9.0",
    "gn:admin2_code":"98855.0",
    "gn:asciiname":"Ash Shaykh Salman an Nasr Allah",
    "gn:country_code":"IQ",
    "gn:dem":4,
    "gn:feature_class":"P",
    "gn:feature_code":"PPL",
    "gn:name":"Ash Shaykh Salm\u0101n an Na\u015fr All\u0101h",
    "gn:population":0,
    "gn:timezone":"Asia/Baghdad",
    "iso:country":"IQ",
    "name:ara_x_preferred":[
        "\u0627\u0644\u0634\u064a\u062e \u0633\u0644\u0645\u0627\u0646 \u0627\u0644\u0646\u0635\u0631 \u0627\u0644\u0644\u0647"
    ],
    "name:und_x_variant":[
        "Ash Shaykh Salm\u0101n an Na\u015fr All\u0101h"
    ],
    "wof:name":"Ash Shaykh Salman an Nasr Allah",
    "wof:placetype":"locality"
},
  "geometry": {"coordinates":[46.53295,31.20305],"type":"Point"}
}