{
  "type": "Feature",
  "properties": {
    "gn:admin1_code":"11.0",
    "gn:admin2_code":"9166534.0",
    "gn:asciiname":"Safrah",
    "gn:country_code":"IQ",
    "gn:dem":868,
    "gn:feature_class":"P",
    "gn:feature_code":"PPL",
    "gn:name":"Safrah",
    "gn:population":0,
    "gn:timezone":"Asia/Baghdad",
    "iso:country":"IQ",
    "name:ara_x_preferred":[
        "\u0633\u0641\u0631\u0629"
    ],
    "name:kur_x_preferred":[
        "Sefre"
    ],
    "name:kur_x_variant":[
        "\u0633\u06d5\u0641\u0631\u06d5",
        "Sevra",
        "\u0633\u06d5\u06a4\u0631\u0627"
    ],
    "name:und_x_variant":[
        "Savr\u0101",
        "Safra",
        "Safrah",
        "Savra"
    ],
    "wof:name":"Safrah",
    "wof:placetype":"locality"
},
  "geometry": {"coordinates":[43.90657,36.99057],"type":"Point"}
}