{
  "type": "Feature",
  "properties": {
    "gn:admin1_code":"18.0",
    "gn:admin2_code":"6805736.0",
    "gn:asciiname":"Albu -affah",
    "gn:country_code":"IQ",
    "gn:dem":61,
    "gn:feature_class":"P",
    "gn:feature_code":"PPL",
    "gn:name":"\u0100lb\u016b -affah",
    "gn:population":0,
    "gn:timezone":"Asia/Baghdad",
    "iso:country":"IQ",
    "name:und_x_variant":[
        "\u0100lb\u016b -affah"
    ],
    "wof:name":"Albu -affah",
    "wof:placetype":"locality"
},
  "geometry": {"coordinates":[43.98333,34.03333],"type":"Point"}
}