{
  "type": "Feature",
  "properties": {
    "gn:admin1_code":"5.0",
    "gn:admin2_code":"9166600.0",
    "gn:asciiname":"Bahrkal Mil",
    "gn:country_code":"IQ",
    "gn:dem":644,
    "gn:feature_class":"P",
    "gn:feature_code":"PPL",
    "gn:name":"Bahrkal Mil",
    "gn:population":0,
    "gn:timezone":"Asia/Baghdad",
    "iso:country":"IQ",
    "name:ara_x_preferred":[
        "\u0628\u06d5\u0631\u0643\u0644 \u0645\u0644"
    ],
    "name:kur_x_preferred":[
        "Bi\u1e5fka\u0142"
    ],
    "name:kur_x_variant":[
        "Berkel",
        "\u0628\u0695\u0643\u0627\u06b5",
        "\u0628\u06d5\u0631\u0643\u06d5\u0644"
    ],
    "name:und_x_variant":[
        "Barkal"
    ],
    "wof:name":"Bahrkal Mil",
    "wof:placetype":"locality"
},
  "geometry": {"coordinates":[45.59063,35.09793],"type":"Point"}
}