{
  "type": "Feature",
  "properties": {
    "gn:admin1_code":"10.0",
    "gn:admin2_code":"94590.0",
    "gn:asciiname":"Saraw",
    "gn:country_code":"IQ",
    "gn:dem":692,
    "gn:feature_class":"P",
    "gn:feature_code":"PPL",
    "gn:name":"Sar\u0101w",
    "gn:population":0,
    "gn:timezone":"Asia/Baghdad",
    "iso:country":"IQ",
    "name:ara_x_preferred":[
        "\u0633\u0631\u0627\u0648"
    ],
    "name:kur_x_preferred":[
        "Seraw"
    ],
    "name:kur_x_variant":[
        "\u0633\u06d5\u0631\u0627\u0648"
    ],
    "name:und_x_variant":[
        "Sar\u0101w",
        "Saraw"
    ],
    "wof:name":"Saraw",
    "wof:placetype":"locality"
},
  "geometry": {"coordinates":[45.73171,35.00614],"type":"Point"}
}