{
  "type": "Feature",
  "properties": {
    "gn:admin1_code":"15.0",
    "gn:admin2_code":"9166649.0",
    "gn:asciiname":"Qaryat Kubbat Jad`ah",
    "gn:country_code":"IQ",
    "gn:dem":170,
    "gn:feature_class":"P",
    "gn:feature_code":"PPL",
    "gn:name":"Qaryat Kubbat Jad\u2018ah",
    "gn:population":0,
    "gn:timezone":"Asia/Baghdad",
    "iso:country":"IQ",
    "name:ara_x_preferred":[
        "\u0642\u0631\u064a\u0629 \u0643\u0628\u0647 \u062c\u062f\u0639\u0647"
    ],
    "name:ara_x_variant":[
        "\u0642\u0631\u064a\u0629 \u0643\u0628\u0629 \u062c\u062f\u0639\u0629"
    ],
    "name:und_x_variant":[
        "Qaryat Kabbah Jad\u2018ah",
        "Qaryat Kubbat Jad\u2018ah"
    ],
    "wof:name":"Qaryat Kubbat Jad`ah",
    "wof:placetype":"locality"
},
  "geometry": {"coordinates":[43.27495,35.74349],"type":"Point"}
}