{
  "type": "Feature",
  "properties": {
    "gn:admin1_code":"9.0",
    "gn:admin2_code":"98623.0",
    "gn:asciiname":"Husayn",
    "gn:cc2":"IQ",
    "gn:country_code":"IQ",
    "gn:dem":6,
    "gn:feature_class":"P",
    "gn:feature_code":"PPL",
    "gn:name":"\u1e28usayn",
    "gn:population":0,
    "gn:timezone":"Asia/Baghdad",
    "iso:country":"IQ",
    "name:und_x_variant":[
        "Husain",
        "\u1e28usayn"
    ],
    "wof:name":"Husayn",
    "wof:placetype":"locality"
},
  "geometry": {"coordinates":[46.16667,31.18333],"type":"Point"}
}