{
  "type": "Feature",
  "properties": {
    "gn:admin1_code":"2.0",
    "gn:admin2_code":"9166563.0",
    "gn:asciiname":"Al Harah",
    "gn:country_code":"IQ",
    "gn:dem":5,
    "gn:feature_class":"P",
    "gn:feature_code":"PPL",
    "gn:name":"Al Harah",
    "gn:population":0,
    "gn:timezone":"Asia/Baghdad",
    "iso:country":"IQ",
    "name:ara_x_preferred":[
        "\u0627\u0644\u0647\u0631\u0647"
    ],
    "wof:name":"Al Harah",
    "wof:placetype":"locality"
},
  "geometry": {"coordinates":[47.31749,30.96673],"type":"Point"}
}