{
  "type": "Feature",
  "properties": {
    "gn:admin1_code":"9.0",
    "gn:admin2_code":"98623.0",
    "gn:asciiname":"Ash Shaykh Salih",
    "gn:country_code":"IQ",
    "gn:dem":9,
    "gn:feature_class":"P",
    "gn:feature_code":"PPL",
    "gn:name":"Ash Shaykh \u015e\u0101li\u1e29",
    "gn:population":0,
    "gn:timezone":"Asia/Baghdad",
    "iso:country":"IQ",
    "name:ara_x_preferred":[
        "\u0627\u0644\u0634\u064a\u062e \u0635\u0627\u0644\u062d"
    ],
    "name:und_x_variant":[
        "Ash Shaykh \u015e\u0101li\u1e29"
    ],
    "wof:name":"Ash Shaykh Salih",
    "wof:placetype":"locality"
},
  "geometry": {"coordinates":[46.11916,31.27611],"type":"Point"}
}