{
  "type": "Feature",
  "properties": {
    "gn:admin1_code":"18.0",
    "gn:admin2_code":"6872046.0",
    "gn:asciiname":"Bayt Khalaf al Ma'n",
    "gn:country_code":"IQ",
    "gn:dem":187,
    "gn:feature_class":"P",
    "gn:feature_code":"PPL",
    "gn:name":"Bayt Khalaf al Ma\u2018n",
    "gn:population":0,
    "gn:timezone":"Asia/Baghdad",
    "iso:country":"IQ",
    "name:ara_x_preferred":[
        "\u0628\u064a\u062a \u062e\u0644\u0641 \u0627\u0644\u0645\u0639\u0646"
    ],
    "name:und_x_variant":[
        "Bayt Khalaf al Ma\u2018n"
    ],
    "wof:name":"Bayt Khalaf al Ma'n",
    "wof:placetype":"locality"
},
  "geometry": {"coordinates":[43.25984,35.18052],"type":"Point"}
}