{
  "type": "Feature",
  "properties": {
    "gn:admin1_code":"15.0",
    "gn:admin2_code":"99414.0",
    "gn:asciiname":"Qal'at ath Thuraythir",
    "gn:country_code":"IQ",
    "gn:dem":195,
    "gn:feature_class":"P",
    "gn:feature_code":"PPL",
    "gn:name":"Qal\u2018at ath Thurayth\u012br",
    "gn:population":0,
    "gn:timezone":"Asia/Baghdad",
    "iso:country":"IQ",
    "name:ara_x_preferred":[
        "\u0642\u0644\u0639\u0629 \u0627\u0644\u062b\u0631\u064a\u062b\u064a\u0631"
    ],
    "name:und_x_variant":[
        "Qal\u2018at ath Thurayth\u012br"
    ],
    "wof:name":"Qal'at ath Thuraythir",
    "wof:placetype":"locality"
},
  "geometry": {"coordinates":[42.7448,35.79295],"type":"Point"}
}