{
  "type": "Feature",
  "properties": {
    "gn:admin1_code":"9.0",
    "gn:admin2_code":"98623.0",
    "gn:asciiname":"Jama'at Sa'dun al Muhammad",
    "gn:country_code":"IQ",
    "gn:dem":8,
    "gn:feature_class":"P",
    "gn:feature_code":"PPL",
    "gn:name":"Jam\u0101\u2018at Sa\u2018d\u016bn al Mu\u1e29ammad",
    "gn:population":0,
    "gn:timezone":"Asia/Baghdad",
    "iso:country":"IQ",
    "name:und_x_variant":[
        "Jam\u0101\u2018at Sa\u2018d\u016bn al Mu\u1e29ammad"
    ],
    "wof:name":"Jama'at Sa'dun al Muhammad",
    "wof:placetype":"locality"
},
  "geometry": {"coordinates":[46.28333,31.41667],"type":"Point"}
}