{
  "type": "Feature",
  "properties": {
    "gn:admin1_code":"10.0",
    "gn:admin2_code":"97988.0",
    "gn:asciiname":"Na'ur",
    "gn:country_code":"IQ",
    "gn:dem":40,
    "gn:feature_class":"P",
    "gn:feature_code":"PPL",
    "gn:name":"N\u0101\u2018\u016br",
    "gn:population":0,
    "gn:timezone":"Asia/Baghdad",
    "iso:country":"IQ",
    "name:ara_x_preferred":[
        "N\u0101\u2018\u016br"
    ],
    "wof:name":"Na'ur",
    "wof:placetype":"locality"
},
  "geometry": {"coordinates":[44.46667,33.71667],"type":"Point"}
}