{
  "type": "Feature",
  "properties": {
    "gn:admin1_code":"15.0",
    "gn:admin2_code":"9166608.0",
    "gn:asciiname":"Athril Gharah",
    "gn:country_code":"IQ",
    "gn:dem":274,
    "gn:feature_class":"P",
    "gn:feature_code":"PPL",
    "gn:name":"Athr\u012bl Ghar\u0101h",
    "gn:population":0,
    "gn:timezone":"Asia/Baghdad",
    "iso:country":"IQ",
    "name:ara_x_preferred":[
        "\u0627\u062b\u0631\u064a\u0644 \u063a\u0631\u0627\u0647"
    ],
    "name:und_x_variant":[
        "Thar\u012b al Kar\u0101\u1e29",
        "Athr\u012bl Ghar\u0101h"
    ],
    "wof:name":"Athril Gharah",
    "wof:placetype":"locality"
},
  "geometry": {"coordinates":[42.18627,35.91005999999999],"type":"Point"}
}