{
  "type": "Feature",
  "properties": {
    "gn:admin1_code":"2.0",
    "gn:admin2_code":"98994.0",
    "gn:asciiname":"Shahbaziyah",
    "gn:cc2":"IQ",
    "gn:country_code":"IQ",
    "gn:dem":0,
    "gn:feature_class":"P",
    "gn:feature_code":"PPL",
    "gn:name":"Shahb\u0101z\u012byah",
    "gn:population":0,
    "gn:timezone":"Asia/Baghdad",
    "iso:country":"IQ",
    "name:und_x_variant":[
        "Shahbalz\u012byah",
        "Shabaziya",
        "Sha\u2018b\u0101z\u012byah",
        "Shahb\u0101z\u012byah"
    ],
    "wof:name":"Shahbaziyah",
    "wof:placetype":"locality"
},
  "geometry": {"coordinates":[47.48333,30.93333],"type":"Point"}
}