{
  "type": "Feature",
  "properties": {
    "gn:admin1_code":"10.0",
    "gn:admin2_code":"94590.0",
    "gn:asciiname":"Imam 'Abbas",
    "gn:country_code":"IQ",
    "gn:dem":58,
    "gn:feature_class":"P",
    "gn:feature_code":"PPL",
    "gn:name":"Im\u0101m \u2018Abb\u0101s",
    "gn:population":0,
    "gn:timezone":"Asia/Baghdad",
    "iso:country":"IQ",
    "name:ara_x_preferred":[
        "\u0627\u0645\u0627\u0645 \u0639\u0628\u0627\u0633"
    ],
    "name:ara_x_variant":[
        "Im\u0101m \u2018Abb\u0101s"
    ],
    "wof:name":"Imam 'Abbas",
    "wof:placetype":"locality"
},
  "geometry": {"coordinates":[44.96189,34.01102],"type":"Point"}
}