{
  "type": "Feature",
  "properties": {
    "gn:admin1_code":"11.0",
    "gn:admin2_code":"93817.0",
    "gn:asciiname":"Kirah Bashay Sabir",
    "gn:country_code":"IQ",
    "gn:dem":247,
    "gn:feature_class":"P",
    "gn:feature_code":"PPL",
    "gn:name":"Kirah B\u0101sh\u0101y \u015e\u0101bir",
    "gn:population":0,
    "gn:timezone":"Asia/Baghdad",
    "iso:country":"IQ",
    "name:ara_x_preferred":[
        "\u0643\u0631\u0647 \u0628\u0627\u0634\u0627\u064a \u0635\u0627\u0628\u0631"
    ],
    "name:kur_x_preferred":[
        "G\u1e5fe Pasha"
    ],
    "name:kur_x_variant":[
        "Gira Pasha",
        "\u06af\u0695\u06d5 \u067e\u0627\u0634\u0627"
    ],
    "name:und_x_variant":[
        "Garah Bisha",
        "K\u0101rah B\u012bsha",
        "Qarah B\u012bsh",
        "Kirah B\u0101sh\u0101y \u015e\u0101bir",
        "Gira Pasha"
    ],
    "wof:name":"Kirah Bashay Sabir",
    "wof:placetype":"locality"
},
  "geometry": {"coordinates":[43.51255,35.77236],"type":"Point"}
}