{
  "type": "Feature",
  "properties": {
    "gn:admin1_code":"7.0",
    "gn:admin2_code":"99173.0",
    "gn:asciiname":"Ibrahim as Salih",
    "gn:country_code":"IQ",
    "gn:dem":42,
    "gn:feature_class":"P",
    "gn:feature_code":"PPL",
    "gn:name":"Ibr\u0101h\u012bm a\u015f \u015e\u0101li\u1e29",
    "gn:population":0,
    "gn:timezone":"Asia/Baghdad",
    "iso:country":"IQ",
    "name:und_x_variant":[
        "Ibr\u0101h\u012bm a\u015f \u015e\u0101li\u1e29"
    ],
    "wof:name":"Ibrahim as Salih",
    "wof:placetype":"locality"
},
  "geometry": {"coordinates":[44.33481,33.44127],"type":"Point"}
}