{
  "type": "Feature",
  "properties": {
    "gn:admin1_code":"5.0",
    "gn:admin2_code":"98464.0",
    "gn:asciiname":"Kani Spikah",
    "gn:country_code":"IQ",
    "gn:dem":860,
    "gn:feature_class":"P",
    "gn:feature_code":"PPL",
    "gn:name":"K\u0101n\u012b Sp\u012bkah",
    "gn:population":0,
    "gn:timezone":"Asia/Baghdad",
    "iso:country":"IQ",
    "name:ara_x_preferred":[
        "\u0643\u0627\u0646\u064a \u0633\u067e\u064a\u0643\u0629"
    ],
    "name:kur_x_preferred":[
        "Kan\u00ee Sp\u00eeke"
    ],
    "name:kur_x_variant":[
        "\u0643\u0627\u0646\u0649 \u0633\u067e\u064a\u0643\u06d5"
    ],
    "name:und_x_variant":[
        "K\u0101n\u012b Sp\u012bkah",
        "Kani Spika"
    ],
    "wof:name":"Kani Spikah",
    "wof:placetype":"locality"
},
  "geometry": {"coordinates":[45.41652,35.58619],"type":"Point"}
}