{
  "type": "Feature",
  "properties": {
    "gn:admin1_code":"18.0",
    "gn:admin2_code":"91594.0",
    "gn:asciiname":"Taha Kazim",
    "gn:country_code":"IQ",
    "gn:dem":83,
    "gn:feature_class":"P",
    "gn:feature_code":"PPL",
    "gn:name":"\u0162\u0101h\u0101 K\u0101z\u0327im",
    "gn:population":0,
    "gn:timezone":"Asia/Baghdad",
    "iso:country":"IQ",
    "name:ara_x_preferred":[
        "\u0637\u0647 \u0643\u0627\u0638\u0645"
    ],
    "name:ara_x_variant":[
        "\u0162\u0101h\u0101 K\u0101z\u0327im"
    ],
    "wof:name":"Taha Kazim",
    "wof:placetype":"locality"
},
  "geometry": {"coordinates":[43.73279,34.20071],"type":"Point"}
}