{
  "type": "Feature",
  "properties": {
    "gn:admin1_code":"18.0",
    "gn:admin2_code":"6872046.0",
    "gn:asciiname":"Hamid al Hamadi",
    "gn:country_code":"IQ",
    "gn:dem":191,
    "gn:feature_class":"P",
    "gn:feature_code":"PPL",
    "gn:name":"\u1e28am\u012bd al \u1e28am\u0101d\u012b",
    "gn:population":0,
    "gn:timezone":"Asia/Baghdad",
    "iso:country":"IQ",
    "name:ara_x_preferred":[
        "\u062d\u0645\u064a\u062f \u0627\u0644\u062d\u0645\u0627\u062f\u064a"
    ],
    "name:und_x_variant":[
        "\u1e28am\u012bd al \u1e28am\u0101d\u012b"
    ],
    "wof:name":"Hamid al Hamadi",
    "wof:placetype":"locality"
},
  "geometry": {"coordinates":[43.3374,35.13314],"type":"Point"}
}