{
  "type": "Feature",
  "properties": {
    "gn:admin1_code":"16.0",
    "gn:admin2_code":"99351.0",
    "gn:asciiname":"Abu Rayat",
    "gn:country_code":"IQ",
    "gn:dem":13,
    "gn:feature_class":"P",
    "gn:feature_code":"PPL",
    "gn:name":"Ab\u016b R\u0101y\u0101t",
    "gn:population":0,
    "gn:timezone":"Asia/Baghdad",
    "iso:country":"IQ",
    "name:ara_x_preferred":[
        "\u0623\u0628\u0648 \u0631\u0627\u064a\u0627\u062a"
    ],
    "name:ara_x_variant":[
        "Ab\u016b R\u0101y\u0101t"
    ],
    "wof:name":"Abu Rayat",
    "wof:placetype":"locality"
},
  "geometry": {"coordinates":[45.80065,31.95089],"type":"Point"}
}