{
  "type": "Feature",
  "properties": {
    "gn:admin1_code":"10.0",
    "gn:admin2_code":"94296.0",
    "gn:asciiname":"Rahim Warkah",
    "gn:country_code":"IQ",
    "gn:dem":198,
    "gn:feature_class":"P",
    "gn:feature_code":"PPL",
    "gn:name":"Ra\u1e29\u012bm Warkah",
    "gn:population":0,
    "gn:timezone":"Asia/Baghdad",
    "iso:country":"IQ",
    "name:ara_x_preferred":[
        "\u0631\u062d\u064a\u0645 \u0648\u0631\u0643\u0629"
    ],
    "name:ara_x_variant":[
        "\u0631\u062d\u064a\u0645 \u0648\u0631\u06af\u0629"
    ],
    "name:kur_x_preferred":[
        "\u1e5ee\u1e27\u00eem We\u1e5fqe"
    ],
    "name:kur_x_variant":[
        "\u0695\u06d5\u062d\u064a\u0645 \u0648\u06d5\u0695\u0642\u06d5"
    ],
    "name:und_x_variant":[
        "Qaryat Ra\u1e29\u012bm Warqah",
        "Ra\u1e29\u012bm",
        "Ra\u1e29\u012bm M\u0101rqah",
        "Ra\u1e29\u012bm \u0100gh\u0101",
        "Ra\u1e29\u012bm Wargah",
        "Ra\u1e29\u012bm Warkah",
        "Ra\u1e29\u012bm Warqa",
        "Rahim Warka"
    ],
    "wof:name":"Rahim Warkah",
    "wof:placetype":"locality"
},
  "geometry": {"coordinates":[45.03847,34.61607],"type":"Point"}
}