{
  "type": "Feature",
  "properties": {
    "gn:admin1_code":"4.0",
    "gn:admin2_code":"99763.0",
    "gn:asciiname":"Hamad ash Shuhayb",
    "gn:country_code":"IQ",
    "gn:dem":24,
    "gn:feature_class":"P",
    "gn:feature_code":"PPL",
    "gn:name":"\u1e28am\u0101d ash Shuhayb",
    "gn:population":0,
    "gn:timezone":"Asia/Baghdad",
    "iso:country":"IQ",
    "name:ara_x_preferred":[
        "\u062d\u0645\u0627\u062f \u0627\u0644\u0634\u0647\u064a\u0628"
    ],
    "name:und_x_variant":[
        "\u1e28am\u0101d ash Shuhayb"
    ],
    "wof:name":"Hamad ash Shuhayb",
    "wof:placetype":"locality"
},
  "geometry": {"coordinates":[44.96468,32.13608],"type":"Point"}
}