{
  "type": "Feature",
  "properties": {
    "gn:admin1_code":"3.0",
    "gn:admin2_code":"98532.0",
    "gn:asciiname":"Al Khashabah",
    "gn:country_code":"IQ",
    "gn:dem":15,
    "gn:feature_class":"P",
    "gn:feature_code":"PPL",
    "gn:name":"Al Khash\u0101bah",
    "gn:population":0,
    "gn:timezone":"Asia/Baghdad",
    "iso:country":"IQ",
    "name:ara_x_preferred":[
        "\u0627\u0644\u062e\u0634\u0627\u0628\u0629"
    ],
    "name:und_x_variant":[
        "Al Khas\u0101ba",
        "Al Khash\u0101bah"
    ],
    "wof:name":"Al Khashabah",
    "wof:placetype":"locality"
},
  "geometry": {"coordinates":[45.28367,31.29062],"type":"Point"}
}