{
  "type": "Feature",
  "properties": {
    "gn:admin1_code":"16.0",
    "gn:admin2_code":"9166606.0",
    "gn:asciiname":"Basim Jasim al Filfil",
    "gn:country_code":"IQ",
    "gn:dem":21,
    "gn:feature_class":"P",
    "gn:feature_code":"PPL",
    "gn:name":"B\u0101sim J\u0101sim al Filfil",
    "gn:population":0,
    "gn:timezone":"Asia/Baghdad",
    "iso:country":"IQ",
    "name:ara_x_preferred":[
        "\u0628\u0627\u0633\u0645 \u062c\u0627\u0633\u0645 \u0627\u0644\u0641\u0644\u0641\u0644"
    ],
    "name:und_x_variant":[
        "B\u0101sim J\u0101sim al Filfil"
    ],
    "wof:name":"Basim Jasim al Filfil",
    "wof:placetype":"locality"
},
  "geometry": {"coordinates":[45.35048,32.48463],"type":"Point"}
}