{
  "type": "Feature",
  "properties": {
    "gn:admin1_code":"5.0",
    "gn:admin2_code":"96204.0",
    "gn:asciiname":"Seyyed Karim",
    "gn:country_code":"IQ",
    "gn:dem":678,
    "gn:feature_class":"P",
    "gn:feature_code":"PPL",
    "gn:name":"Seyyed Kar\u012bm",
    "gn:population":0,
    "gn:timezone":"Asia/Baghdad",
    "iso:country":"IQ",
    "name:fas_x_preferred":[
        "\u0633\u064a\u062f \u06a9\u0631\u064a\u0645"
    ],
    "name:fas_x_variant":[
        "Seyyed Kar\u012bm"
    ],
    "wof:name":"Seyyed Karim",
    "wof:placetype":"locality"
},
  "geometry": {"coordinates":[45.8509,34.9769],"type":"Point"}
}