{
  "type": "Feature",
  "properties": {
    "gn:admin1_code":"8.0",
    "gn:admin2_code":"9166607.0",
    "gn:asciiname":"Al Qari al Qadimah",
    "gn:cc2":"IQ",
    "gn:country_code":"IQ",
    "gn:dem":314,
    "gn:feature_class":"P",
    "gn:feature_code":"PPL",
    "gn:name":"Al Qari al Qad\u012bmah",
    "gn:population":0,
    "gn:timezone":"Asia/Baghdad",
    "iso:country":"IQ",
    "name:und_x_variant":[
        "`Al Qad\u012bmah"
    ],
    "wof:name":"Al Qari al Qadimah",
    "wof:placetype":"locality"
},
  "geometry": {"coordinates":[42.64056,36.78833],"type":"Point"}
}