{
  "type": "Feature",
  "properties": {
    "gn:admin1_code":"8.0",
    "gn:admin2_code":"99612.0",
    "gn:asciiname":"Chay",
    "gn:country_code":"IQ",
    "gn:dem":1553,
    "gn:feature_class":"P",
    "gn:feature_code":"PPL",
    "gn:name":"Ch\u0101y",
    "gn:population":0,
    "gn:timezone":"Asia/Baghdad",
    "iso:country":"IQ",
    "name:ara_x_preferred":[
        "\u0686\u0627\u064a"
    ],
    "name:ara_x_variant":[
        "Ch\u0101y"
    ],
    "name:ceb_x_preferred":[
        "Chay"
    ],
    "name:deu_x_preferred":[
        "Chay"
    ],
    "name:ita_x_preferred":[
        "Chay"
    ],
    "name:kur_x_preferred":[
        "Chay"
    ],
    "name:kur_x_variant":[
        "\u0686\u0627\u0649",
        "Ch\u00eay",
        "\u0686\u06ce\u0649"
    ],
    "name:nld_x_preferred":[
        "Chay"
    ],
    "name:pol_x_preferred":[
        "Chay"
    ],
    "name:scn_x_preferred":[
        "Chay"
    ],
    "name:und_x_variant":[
        "Ch\u0101h",
        "Ch\u0113",
        "Chai"
    ],
    "name:vie_x_preferred":[
        "Chay"
    ],
    "wof:name":"Chay",
    "wof:placetype":"locality"
},
  "geometry": {"coordinates":[44.04264000000001,37.26152],"type":"Point"}
}