{
  "type": "Feature",
  "properties": {
    "gn:admin1_code":"9.0",
    "gn:admin2_code":"98855.0",
    "gn:asciiname":"'Abd al Maz'al",
    "gn:country_code":"IQ",
    "gn:dem":7,
    "gn:feature_class":"P",
    "gn:feature_code":"PPL",
    "gn:name":"\u2018Abd al Maz\u2018al",
    "gn:population":0,
    "gn:timezone":"Asia/Baghdad",
    "iso:country":"IQ",
    "name:ara_x_preferred":[
        "\u0639\u0628\u062f \u0627\u0644\u0645\u0632\u0639\u0644"
    ],
    "name:und_x_variant":[
        "\u2018Abd al Maz\u2018al"
    ],
    "wof:name":"'Abd al Maz'al",
    "wof:placetype":"locality"
},
  "geometry": {"coordinates":[46.30171,31.25198],"type":"Point"}
}