{
  "type": "Feature",
  "properties": {
    "gn:admin1_code":"10.0",
    "gn:admin2_code":"99170.0",
    "gn:asciiname":"Qaryat ad Darawish",
    "gn:country_code":"IQ",
    "gn:dem":52,
    "gn:feature_class":"P",
    "gn:feature_code":"PPL",
    "gn:name":"Qaryat ad Dar\u0101w\u012bsh",
    "gn:population":0,
    "gn:timezone":"Asia/Baghdad",
    "iso:country":"IQ",
    "name:ara_x_preferred":[
        "\u0642\u0631\u064a\u0629 \u0627\u0644\u062f\u0631\u0627\u0648\u064a\u0634"
    ],
    "name:und_x_variant":[
        "Ad Dar\u0101w\u012bsh",
        "Qaryat ad Dar\u0101w\u012bsh"
    ],
    "wof:name":"Qaryat ad Darawish",
    "wof:placetype":"locality"
},
  "geometry": {"coordinates":[44.30656,34.04451],"type":"Point"}
}