{
  "type": "Feature",
  "properties": {
    "gn:admin1_code":"2.0",
    "gn:admin2_code":"98247.0",
    "gn:asciiname":"Riya` al Barat",
    "gn:cc2":"KW",
    "gn:country_code":"IQ",
    "gn:dem":10,
    "gn:feature_class":"P",
    "gn:feature_code":"PPL",
    "gn:name":"Riy\u0101\u2018 al B\u0101r\u0101t",
    "gn:population":0,
    "gn:timezone":"Asia/Baghdad",
    "iso:country":"IQ",
    "name:ara_x_preferred":[
        "\u0631\u064a\u0627\u0639 \u0627\u0644\u0628\u0627\u0631\u0627\u062a"
    ],
    "name:und_x_variant":[
        "R\u012bj al Bar\u0101t",
        "Riy\u0101\u2018 al B\u0101r\u0101t"
    ],
    "wof:name":"Riya` al Barat",
    "wof:placetype":"locality"
},
  "geometry": {"coordinates":[47.91494,30.05638],"type":"Point"}
}