{
  "type": "Feature",
  "properties": {
    "gn:admin1_code":"15.0",
    "gn:admin2_code":"9166620.0",
    "gn:asciiname":"Kani Sarik",
    "gn:country_code":"IQ",
    "gn:dem":455,
    "gn:feature_class":"P",
    "gn:feature_code":"PPL",
    "gn:name":"K\u0101n\u012b \u015e\u0101rik",
    "gn:population":0,
    "gn:timezone":"Asia/Baghdad",
    "iso:country":"IQ",
    "name:ara_x_preferred":[
        "\u0643\u0627\u0646\u064a \u0635\u0627\u0631\u0643"
    ],
    "name:ara_x_variant":[
        "K\u0101n\u012b \u015e\u0101rik"
    ],
    "wof:name":"Kani Sarik",
    "wof:placetype":"locality"
},
  "geometry": {"coordinates":[41.83392,36.29541],"type":"Point"}
}