{
  "type": "Feature",
  "properties": {
    "gn:admin1_code":"1.0",
    "gn:admin2_code":"9166579.0",
    "gn:asciiname":"Jubbah",
    "gn:country_code":"IQ",
    "gn:dem":83,
    "gn:feature_class":"P",
    "gn:feature_code":"PPL",
    "gn:name":"Jubbah",
    "gn:population":0,
    "gn:timezone":"Asia/Baghdad",
    "iso:country":"IQ",
    "name:ara_x_preferred":[
        "\u062c\u0628\u0629"
    ],
    "name:und_x_variant":[
        "Qaryat Jubbah",
        "Jubba",
        "Jubbah"
    ],
    "wof:name":"Jubbah",
    "wof:placetype":"locality"
},
  "geometry": {"coordinates":[42.54353,33.9075],"type":"Point"}
}