{
  "type": "Feature",
  "properties": {
    "gn:admin1_code":"4.0",
    "gn:admin2_code":"99763.0",
    "gn:asciiname":"Shakir Idham",
    "gn:country_code":"IQ",
    "gn:dem":25,
    "gn:feature_class":"P",
    "gn:feature_code":"PPL",
    "gn:name":"Sh\u0101kir Idh\u0101m",
    "gn:population":0,
    "gn:timezone":"Asia/Baghdad",
    "iso:country":"IQ",
    "name:ara_x_preferred":[
        "\u0634\u0627\u0643\u0631 \u0627\u062f\u0647\u0627\u0645"
    ],
    "name:ara_x_variant":[
        "Sh\u0101kir Idh\u0101m"
    ],
    "wof:name":"Shakir Idham",
    "wof:placetype":"locality"
},
  "geometry": {"coordinates":[44.59246,32.01545],"type":"Point"}
}