{
  "type": "Feature",
  "properties": {
    "gn:admin1_code":"6.0",
    "gn:admin2_code":"99348.0",
    "gn:asciiname":"Qaryat Albu Hajim",
    "gn:country_code":"IQ",
    "gn:dem":30,
    "gn:feature_class":"P",
    "gn:feature_code":"PPL",
    "gn:name":"Qaryat \u0100lb\u016b \u1e28\u0101jim",
    "gn:population":0,
    "gn:timezone":"Asia/Baghdad",
    "iso:country":"IQ",
    "name:ara_x_preferred":[
        "\u0642\u0631\u064a\u0629 \u0627\u0644\u0628\u0648 \u062d\u0627\u062c\u0645"
    ],
    "name:und_x_variant":[
        "Qaryat \u0100lb\u016b \u1e28\u0101jim"
    ],
    "wof:name":"Qaryat Albu Hajim",
    "wof:placetype":"locality"
},
  "geometry": {"coordinates":[44.39635,32.21387],"type":"Point"}
}