{
  "type": "Feature",
  "properties": {
    "gn:admin1_code":"2.0",
    "gn:admin2_code":"9166563.0",
    "gn:asciiname":"Al Janabah",
    "gn:country_code":"IQ",
    "gn:dem":4,
    "gn:feature_class":"P",
    "gn:feature_code":"PPL",
    "gn:name":"Al Janabah",
    "gn:population":0,
    "gn:timezone":"Asia/Baghdad",
    "iso:country":"IQ",
    "name:ara_x_preferred":[
        "\u0627\u0644\u062c\u0646\u0628\u0629"
    ],
    "wof:name":"Al Janabah",
    "wof:placetype":"locality"
},
  "geometry": {"coordinates":[47.24049,30.93517],"type":"Point"}
}