{
  "type": "Feature",
  "properties": {
    "gn:admin1_code":"18.0",
    "gn:admin2_code":"6783103.0",
    "gn:asciiname":"'Arab Mahdi al Kammun",
    "gn:country_code":"IQ",
    "gn:dem":47,
    "gn:feature_class":"P",
    "gn:feature_code":"PPL",
    "gn:name":"\u2018Arab Mahd\u012b al Kamm\u016bn",
    "gn:population":0,
    "gn:timezone":"Asia/Baghdad",
    "iso:country":"IQ",
    "name:ara_x_preferred":[
        "\u0639\u0631\u0628 \u0645\u0647\u062f\u064a \u0627\u0644\u0643\u0645\u0648\u0646"
    ],
    "name:und_x_variant":[
        "Mahdi al Kumun",
        "Mahd\u012b al Kan\u016bm",
        "Mahd\u012b al Kamm\u016bn",
        "\u2018Arab Mahd\u012b al Kamm\u016bn"
    ],
    "wof:name":"'Arab Mahdi al Kammun",
    "wof:placetype":"locality"
},
  "geometry": {"coordinates":[44.18286,34.0614],"type":"Point"}
}