{
  "type": "Feature",
  "properties": {
    "gn:admin1_code":"11.0",
    "gn:admin2_code":"9166586.0",
    "gn:asciiname":"Wasan",
    "gn:country_code":"IQ",
    "gn:dem":1149,
    "gn:feature_class":"P",
    "gn:feature_code":"PPL",
    "gn:name":"Wasan",
    "gn:population":0,
    "gn:timezone":"Asia/Baghdad",
    "iso:country":"IQ",
    "name:ara_x_preferred":[
        "\u0648\u0627\u0633\u0627\u0646"
    ],
    "name:kur_x_preferred":[
        "Wasan"
    ],
    "name:kur_x_variant":[
        "Wesan",
        "\u0648\u06d5\u0633\u0627\u0646"
    ],
    "name:und_x_variant":[
        "Was\u0101n",
        "W\u0101s\u0101n"
    ],
    "wof:name":"Wasan",
    "wof:placetype":"locality"
},
  "geometry": {"coordinates":[44.85758,36.51549],"type":"Point"}
}