{
  "type": "Feature",
  "properties": {
    "gn:admin1_code":"4.0",
    "gn:admin2_code":"6850588.0",
    "gn:asciiname":"Sabih Jabbar",
    "gn:country_code":"IQ",
    "gn:dem":20,
    "gn:feature_class":"P",
    "gn:feature_code":"PPL",
    "gn:name":"\u015eab\u012b\u1e29 Jabb\u0101r",
    "gn:population":0,
    "gn:timezone":"Asia/Baghdad",
    "iso:country":"IQ",
    "name:ara_x_preferred":[
        "\u0635\u0628\u064a\u062d \u062c\u0628\u0627\u0631"
    ],
    "name:und_x_variant":[
        "As Sayyid \u015eab\u012b\u1e29",
        "Saiyid Sab\u012bh\u012bh",
        "As Sayyid Sab\u012b\u1e29\u012b\u1e29",
        "\u015eab\u012b\u1e29 Jabb\u0101r"
    ],
    "wof:name":"Sabih Jabbar",
    "wof:placetype":"locality"
},
  "geometry": {"coordinates":[44.98179,31.74398],"type":"Point"}
}