{
  "type": "Feature",
  "properties": {
    "gn:admin1_code":"18.0",
    "gn:admin2_code":"90148.0",
    "gn:asciiname":"'Abd Muhammad 'Antar",
    "gn:country_code":"IQ",
    "gn:dem":91,
    "gn:feature_class":"P",
    "gn:feature_code":"PPL",
    "gn:name":"\u2018Abd Mu\u1e29ammad \u2018Antar",
    "gn:population":0,
    "gn:timezone":"Asia/Baghdad",
    "iso:country":"IQ",
    "name:ara_x_preferred":[
        "\u0639\u0628\u062f \u0645\u062d\u0645\u062f \u0639\u0646\u062a\u0631"
    ],
    "name:und_x_variant":[
        "\u2018Abd Mu\u1e29ammad \u2018Antar"
    ],
    "wof:name":"'Abd Muhammad 'Antar",
    "wof:placetype":"locality"
},
  "geometry": {"coordinates":[43.90897,34.64937],"type":"Point"}
}