{
  "type": "Feature",
  "properties": {
    "gn:admin1_code":"4.0",
    "gn:admin2_code":"98634.0",
    "gn:asciiname":"Al Ma'yarah",
    "gn:country_code":"IQ",
    "gn:dem":19,
    "gn:feature_class":"P",
    "gn:feature_code":"PPL",
    "gn:name":"Al Ma\u2018yarah",
    "gn:population":0,
    "gn:timezone":"Asia/Baghdad",
    "iso:country":"IQ",
    "name:ara_x_preferred":[
        "\u0627\u0644\u0645\u0639\u064a\u0631\u0629"
    ],
    "name:und_x_variant":[
        "Al Ma\u2018yarah"
    ],
    "wof:name":"Al Ma'yarah",
    "wof:placetype":"locality"
},
  "geometry": {"coordinates":[44.57593,31.7076],"type":"Point"}
}