{
  "type": "Feature",
  "properties": {
    "gn:admin1_code":"14.0",
    "gn:admin2_code":"92536.0",
    "gn:asciiname":"Ishan",
    "gn:country_code":"IQ",
    "gn:dem":8,
    "gn:feature_class":"P",
    "gn:feature_code":"PPL",
    "gn:name":"\u012ash\u0101n",
    "gn:population":0,
    "gn:timezone":"Asia/Baghdad",
    "iso:country":"IQ",
    "name:ara_x_preferred":[
        "\u012ash\u0101n"
    ],
    "wof:name":"Ishan",
    "wof:placetype":"locality"
},
  "geometry": {"coordinates":[47.28333,31.55],"type":"Point"}
}