{
  "type": "Feature",
  "properties": {
    "gn:admin1_code":"16.0",
    "gn:admin2_code":"99351.0",
    "gn:asciiname":"Shahid 'Ala Gat'",
    "gn:country_code":"IQ",
    "gn:dem":16,
    "gn:feature_class":"P",
    "gn:feature_code":"PPL",
    "gn:name":"Sha\u1e29\u012bd \u2018Al\u00e1 G\u0101\u0163\u2018",
    "gn:population":0,
    "gn:timezone":"Asia/Baghdad",
    "iso:country":"IQ",
    "name:ara_x_preferred":[
        "\u0634\u062d\u064a\u062f \u0639\u0644\u0649 \u06af\u0627\u0637\u0639"
    ],
    "name:und_x_variant":[
        "Sha\u1e29\u012bd \u2018Al\u00e1 G\u0101\u0163\u2018"
    ],
    "wof:name":"Shahid 'Ala Gat'",
    "wof:placetype":"locality"
},
  "geometry": {"coordinates":[46.09603,32.29496],"type":"Point"}
}