{
  "type": "Feature",
  "properties": {
    "gn:admin1_code":"7.0",
    "gn:admin2_code":"99173.0",
    "gn:asciiname":"Zaya",
    "gn:cc2":"IQ",
    "gn:country_code":"IQ",
    "gn:dem":35,
    "gn:feature_class":"P",
    "gn:feature_code":"PPL",
    "gn:name":"Z\u0101y\u0101",
    "gn:population":0,
    "gn:timezone":"Asia/Baghdad",
    "iso:country":"IQ",
    "name:ara_x_preferred":[
        "Z\u0101y\u0101"
    ],
    "name:ara_x_variant":[
        "\u0632\u0627\u064a\u0627"
    ],
    "name:bul_x_preferred":[
        "\u0417\u0430\u044f"
    ],
    "name:fas_x_preferred":[
        "\u0632\u0627\u06cc\u0627"
    ],
    "name:kaz_x_preferred":[
        "\u0417\u0430\u044f"
    ],
    "name:pol_x_preferred":[
        "Zaja"
    ],
    "name:ron_x_preferred":[
        "Zaia"
    ],
    "name:rus_x_preferred":[
        "\u0417\u0430\u044f"
    ],
    "name:ukr_x_preferred":[
        "\u0417\u0430\u044f"
    ],
    "name:und_x_variant":[
        "Z\u0101ve"
    ],
    "wof:name":"Zaya",
    "wof:placetype":"locality"
},
  "geometry": {"coordinates":[44.20778,33.54611],"type":"Point"}
}