{
  "type": "Feature",
  "properties": {
    "gn:admin1_code":"7.0",
    "gn:admin2_code":"99173.0",
    "gn:asciiname":"Zaya",
    "gn:cc2":"IQ",
    "gn:country_code":"IQ",
    "gn:dem":35,
    "gn:feature_class":"P",
    "gn:feature_code":"PPL",
    "gn:name":"Z\u0101y\u0101",
    "gn:population":0,
    "gn:timezone":"Asia/Baghdad",
    "iso:country":"IQ",
    "name:ara_x_preferred":[
        "Z\u0101y\u0101"
    ],
    "name:und_x_variant":[
        "Z\u0101ve"
    ],
    "wof:name":"Zaya",
    "wof:placetype":"locality"
},
  "geometry": {"coordinates":[44.20778,33.54611],"type":"Point"}
}