{
  "type": "Feature",
  "properties": {
    "gn:admin1_code":"1.0",
    "gn:admin2_code":"6765480.0",
    "gn:asciiname":"Bansiz Yakhanah",
    "gn:country_code":"IQ",
    "gn:dem":146,
    "gn:feature_class":"P",
    "gn:feature_code":"PPL",
    "gn:name":"B\u0101nsiz Yakh\u0101nah",
    "gn:population":0,
    "gn:timezone":"Asia/Baghdad",
    "iso:country":"IQ",
    "name:ara_x_preferred":[
        "\u0628\u0627\u0646\u0633\u0632 \u064a\u062e\u0627\u0646\u0629"
    ],
    "name:und_x_variant":[
        "B\u0101nsiz Yakh\u0101nah"
    ],
    "wof:name":"Bansiz Yakhanah",
    "wof:placetype":"locality"
},
  "geometry": {"coordinates":[42.34821,34.07883],"type":"Point"}
}