{
  "type": "Feature",
  "properties": {
    "gn:admin1_code":"5.0",
    "gn:admin2_code":"96204.0",
    "gn:asciiname":"Suskan",
    "gn:country_code":"IQ",
    "gn:dem":1340,
    "gn:feature_class":"P",
    "gn:feature_code":"PPL",
    "gn:name":"S\u016bsk\u0101n",
    "gn:population":0,
    "gn:timezone":"Asia/Baghdad",
    "iso:country":"IQ",
    "name:fas_x_preferred":[
        "\u0633\u0648\u0633\u06a9\u0627\u0646"
    ],
    "wof:name":"Suskan",
    "wof:placetype":"locality"
},
  "geometry": {"coordinates":[46.1688,35.1818],"type":"Point"}
}