{
  "type": "Feature",
  "properties": {
    "gn:admin1_code":"15.0",
    "gn:admin2_code":"99414.0",
    "gn:asciiname":"Abtayshah",
    "gn:country_code":"IQ",
    "gn:dem":239,
    "gn:feature_class":"P",
    "gn:feature_code":"PPL",
    "gn:name":"Ab\u0163ayshah",
    "gn:population":0,
    "gn:timezone":"Asia/Baghdad",
    "iso:country":"IQ",
    "name:ara_x_preferred":[
        "\u0627\u0628\u0637\u064a\u0634\u0629"
    ],
    "name:und_x_variant":[
        "Ab\u0163ayshah"
    ],
    "wof:name":"Abtayshah",
    "wof:placetype":"locality"
},
  "geometry": {"coordinates":[42.94752,35.88711],"type":"Point"}
}