{
  "type": "Feature",
  "properties": {
    "gn:admin1_code":"8.0",
    "gn:admin2_code":"89569.0",
    "gn:asciiname":"Banik as Sufla",
    "gn:country_code":"IQ",
    "gn:dem":939,
    "gn:feature_class":"P",
    "gn:feature_code":"PPL",
    "gn:name":"B\u0101nik as Sufl\u00e1",
    "gn:population":0,
    "gn:timezone":"Asia/Baghdad",
    "iso:country":"IQ",
    "name:ara_x_preferred":[
        "\u0628\u0627\u0646\u0643 \u0627\u0644\u0633\u0641\u0644\u0649"
    ],
    "name:kur_x_preferred":[
        "Ban\u00eek"
    ],
    "name:kur_x_variant":[
        "\u0628\u0627\u0646\u064a\u0643",
        "Banka J\u00ear\u00ee",
        "\u0628\u0627\u0646\u0643\u0627 \u0698\u06ce\u0631\u0649"
    ],
    "name:und_x_variant":[
        "Banik",
        "B\u0101nik Zh\u0113r\u012b",
        "B\u0101nik as Sufl\u00e1",
        "B\u0101nik Zh\u014dr\u012b"
    ],
    "wof:name":"Banik as Sufla",
    "wof:placetype":"locality"
},
  "geometry": {"coordinates":[42.97039,37.21913],"type":"Point"}
}