{
  "type": "Feature",
  "properties": {
    "gn:admin1_code":"16.0",
    "gn:admin2_code":"98460.0",
    "gn:asciiname":"'Abd al Amir 'Usayb",
    "gn:country_code":"IQ",
    "gn:dem":34,
    "gn:feature_class":"P",
    "gn:feature_code":"PPL",
    "gn:name":"\u2018Abd al Am\u012br \u2018U\u015fayb",
    "gn:population":0,
    "gn:timezone":"Asia/Baghdad",
    "iso:country":"IQ",
    "name:ara_x_preferred":[
        "\u0639\u0628\u062f \u0627\u0644\u0627\u0645\u064a\u0631 \u0639\u0635\u064a\u0628"
    ],
    "name:und_x_variant":[
        "\u2018Abd al Am\u012br \u2018U\u015fayb"
    ],
    "wof:name":"'Abd al Amir 'Usayb",
    "wof:placetype":"locality"
},
  "geometry": {"coordinates":[44.80298,32.91962],"type":"Point"}
}