{
  "type": "Feature",
  "properties": {
    "gn:admin1_code":"5.0",
    "gn:admin2_code":"96204.0",
    "gn:asciiname":"Nusinjar",
    "gn:country_code":"IQ",
    "gn:dem":648,
    "gn:feature_class":"P",
    "gn:feature_code":"PPL",
    "gn:name":"N\u016bsinj\u0101r",
    "gn:population":0,
    "gn:timezone":"Asia/Baghdad",
    "iso:country":"IQ",
    "name:ara_x_preferred":[
        "N\u016bsinj\u0101r"
    ],
    "name:ara_x_variant":[
        "\u0646\u0648\u0633\u0646\u062c\u0627\u0631"
    ],
    "name:fas_x_preferred":[
        "Mazgosj\u0101r"
    ],
    "name:fas_x_variant":[
        "\u0645\u0632\u06af\u0633\u062c\u0627\u0631"
    ],
    "name:kur_x_preferred":[
        "N\u00eargize Ca\u1e5f"
    ],
    "name:kur_x_variant":[
        "\u0646\u06ce\u0631\u06af\u0632\u06d5 \u062c\u0627\u0695"
    ],
    "name:und_x_variant":[
        "Nergisai\u0101r",
        "Nargisaiar",
        "Narj\u012bs\u0101 J\u0101r",
        "Nergiza Jar"
    ],
    "wof:name":"Nusinjar",
    "wof:placetype":"locality"
},
  "geometry": {"coordinates":[45.82058,35.1886],"type":"Point"}
}