{
  "type": "Feature",
  "properties": {
    "gn:admin1_code":"1.0",
    "gn:admin2_code":"98718.0",
    "gn:asciiname":"Makinat Mish'an",
    "gn:country_code":"IQ",
    "gn:dem":94,
    "gn:feature_class":"P",
    "gn:feature_code":"PPL",
    "gn:name":"Mak\u012bnat Mish\u2018\u0101n",
    "gn:population":0,
    "gn:timezone":"Asia/Baghdad",
    "iso:country":"IQ",
    "name:ara_x_preferred":[
        "\u0645\u0643\u064a\u0646\u0629 \u0645\u0634\u0639\u0627\u0646"
    ],
    "name:und_x_variant":[
        "Mak\u012bnat Mish\u2018\u0101n"
    ],
    "wof:name":"Makinat Mish'an",
    "wof:placetype":"locality"
},
  "geometry": {"coordinates":[43.06812,33.15056],"type":"Point"}
}