{
  "type": "Feature",
  "properties": {
    "gn:admin1_code":"7.0",
    "gn:admin2_code":"9166545.0",
    "gn:asciiname":"'Abbas Salih",
    "gn:country_code":"IQ",
    "gn:dem":37,
    "gn:feature_class":"P",
    "gn:feature_code":"PPL",
    "gn:name":"\u2018Abb\u0101s \u015e\u0101li\u1e29",
    "gn:population":0,
    "gn:timezone":"Asia/Baghdad",
    "iso:country":"IQ",
    "name:ara_x_preferred":[
        "\u0639\u0628\u0627\u0633 \u0635\u0627\u0644\u062d"
    ],
    "name:ara_x_variant":[
        "\u2018Abb\u0101s \u015e\u0101li\u1e29"
    ],
    "wof:name":"'Abbas Salih",
    "wof:placetype":"locality"
},
  "geometry": {"coordinates":[44.44194,33.23631],"type":"Point"}
}