{
  "type": "Feature",
  "properties": {
    "gn:admin1_code":"10.0",
    "gn:admin2_code":"94590.0",
    "gn:asciiname":"Khayal",
    "gn:country_code":"IQ",
    "gn:dem":206,
    "gn:feature_class":"P",
    "gn:feature_code":"PPL",
    "gn:name":"Khay\u0101l",
    "gn:population":0,
    "gn:timezone":"Asia/Baghdad",
    "iso:country":"IQ",
    "name:ara_x_preferred":[
        "\u062e\u064a\u0627\u0644"
    ],
    "name:kur_x_preferred":[
        "Xeya\u0142"
    ],
    "name:kur_x_variant":[
        "\u062e\u06d5\u064a\u0627\u06b5"
    ],
    "name:und_x_variant":[
        "Khiy\u0101l",
        "Khi\u0101l",
        "Khay\u0101l",
        "Khay\u0101r",
        "Khayal"
    ],
    "wof:name":"Khayal",
    "wof:placetype":"locality"
},
  "geometry": {"coordinates":[45.31972,34.5702],"type":"Point"}
}