{
  "type": "Feature",
  "properties": {
    "gn:admin1_code":"15.0",
    "gn:admin2_code":"9166620.0",
    "gn:asciiname":"Tall I'ab",
    "gn:country_code":"IQ",
    "gn:dem":304,
    "gn:feature_class":"P",
    "gn:feature_code":"PPL",
    "gn:name":"Tall \u012a\u2018\u0101b",
    "gn:population":0,
    "gn:timezone":"Asia/Baghdad",
    "iso:country":"IQ",
    "name:ara_x_preferred":[
        "\u062a\u0644 \u0627\u064a\u0639\u0627\u0628"
    ],
    "name:und_x_variant":[
        "Tall \u012a\u2018\u0101b"
    ],
    "wof:name":"Tall I'ab",
    "wof:placetype":"locality"
},
  "geometry": {"coordinates":[42.16838,36.18847],"type":"Point"}
}