{
  "type": "Feature",
  "properties": {
    "gn:admin1_code":"16.0",
    "gn:admin2_code":"98460.0",
    "gn:asciiname":"Qaryat Bilad ash Sham",
    "gn:country_code":"IQ",
    "gn:dem":28,
    "gn:feature_class":"P",
    "gn:feature_code":"PPL",
    "gn:name":"Qaryat Bil\u0101d ash Sh\u0101m",
    "gn:population":0,
    "gn:timezone":"Asia/Baghdad",
    "iso:country":"IQ",
    "name:ara_x_preferred":[
        "\u0642\u0631\u064a\u0629 \u0628\u0644\u0627\u062f \u0627\u0644\u0634\u0627\u0645"
    ],
    "name:und_x_variant":[
        "Qaryat Bil\u0101d ash Sh\u0101m"
    ],
    "wof:name":"Qaryat Bilad ash Sham",
    "wof:placetype":"locality"
},
  "geometry": {"coordinates":[44.84908,32.8686],"type":"Point"}
}