{
  "type": "Feature",
  "properties": {
    "gn:admin1_code":"1.0",
    "gn:admin2_code":"6765480.0",
    "gn:asciiname":"Qaryat ash Sha'i",
    "gn:country_code":"IQ",
    "gn:dem":116,
    "gn:feature_class":"P",
    "gn:feature_code":"PPL",
    "gn:name":"Qaryat ash Sh\u0101\u2018\u012b",
    "gn:population":0,
    "gn:timezone":"Asia/Baghdad",
    "iso:country":"IQ",
    "name:ara_x_preferred":[
        "\u0642\u0631\u064a\u0629 \u0627\u0644\u0634\u0627\u0639\u064a"
    ],
    "name:und_x_variant":[
        "Qaryat ash Sh\u0101\u2018\u012b"
    ],
    "wof:name":"Qaryat ash Sha'i",
    "wof:placetype":"locality"
},
  "geometry": {"coordinates":[42.39654,34.11843],"type":"Point"}
}