{
  "type": "Feature",
  "properties": {
    "gn:admin1_code":"5.0",
    "gn:admin2_code":"98464.0",
    "gn:asciiname":"Warmuzyar",
    "gn:country_code":"IQ",
    "gn:dem":815,
    "gn:feature_class":"P",
    "gn:feature_code":"PPL",
    "gn:name":"Warm\u016bzy\u0101r",
    "gn:population":0,
    "gn:timezone":"Asia/Baghdad",
    "iso:country":"IQ",
    "name:ara_x_preferred":[
        "\u0648\u0631\u0645\u0648\u0632\u064a\u0627\u0631"
    ],
    "name:und_x_variant":[
        "Warmezy\u0101r",
        "Warm\u016bzy\u0101r",
        "Warmazy\u0101r"
    ],
    "wof:name":"Warmuzyar",
    "wof:placetype":"locality"
},
  "geometry": {"coordinates":[45.24735,35.51945999999999],"type":"Point"}
}