{
  "type": "Feature",
  "properties": {
    "gn:admin1_code":"18.0",
    "gn:admin2_code":"6804454.0",
    "gn:asciiname":"Qaryat Lazakah",
    "gn:country_code":"IQ",
    "gn:dem":164,
    "gn:feature_class":"P",
    "gn:feature_code":"PPL",
    "gn:name":"Qaryat Laz\u0101kah",
    "gn:population":0,
    "gn:timezone":"Asia/Baghdad",
    "iso:country":"IQ",
    "name:ara_x_preferred":[
        "\u0642\u0631\u064a\u0629 \u0644\u0632\u0627\u0643\u0647"
    ],
    "name:und_x_variant":[
        "Qaryat Laz\u0101kah"
    ],
    "wof:name":"Qaryat Lazakah",
    "wof:placetype":"locality"
},
  "geometry": {"coordinates":[43.26186,35.64508],"type":"Point"}
}