{
  "type": "Feature",
  "properties": {
    "gn:admin1_code":"7.0",
    "gn:admin2_code":"9179819.0",
    "gn:asciiname":"Midhat",
    "gn:cc2":"IQ",
    "gn:country_code":"IQ",
    "gn:dem":34,
    "gn:feature_class":"P",
    "gn:feature_code":"PPL",
    "gn:name":"Mid\u1e29at",
    "gn:population":0,
    "gn:timezone":"Asia/Baghdad",
    "iso:country":"IQ",
    "name:und_x_variant":[
        "Madhat",
        "Mid\u1e29at"
    ],
    "wof:name":"Midhat",
    "wof:placetype":"locality"
},
  "geometry": {"coordinates":[44.53333,33.25],"type":"Point"}
}