{
  "type": "Feature",
  "properties": {
    "gn:admin1_code":"15.0",
    "gn:admin2_code":"9166608.0",
    "gn:asciiname":"Al 'A'ishiyah",
    "gn:country_code":"IQ",
    "gn:dem":322,
    "gn:feature_class":"P",
    "gn:feature_code":"PPL",
    "gn:name":"Al \u2018\u0100\u2019ish\u012byah",
    "gn:population":0,
    "gn:timezone":"Asia/Baghdad",
    "iso:country":"IQ",
    "name:ara_x_preferred":[
        "\u0627\u0644\u0639\u0627\u0626\u0634\u064a\u0629"
    ],
    "name:und_x_variant":[
        "Al \u2018\u0100\u2019ish\u012byah"
    ],
    "wof:name":"Al 'A'ishiyah",
    "wof:placetype":"locality"
},
  "geometry": {"coordinates":[41.40675,36.01113],"type":"Point"}
}