{
  "type": "Feature",
  "properties": {
    "gn:admin1_code":"17.0",
    "gn:admin2_code":"9166552.0",
    "gn:asciiname":"'Arab al Masakh",
    "gn:country_code":"IQ",
    "gn:dem":18,
    "gn:feature_class":"P",
    "gn:feature_code":"PPL",
    "gn:name":"\u2018Arab al Ma\u015f\u0101kh",
    "gn:population":0,
    "gn:timezone":"Asia/Baghdad",
    "iso:country":"IQ",
    "name:ara_x_preferred":[
        "\u0639\u0631\u0628 \u0627\u0644\u0645\u0635\u0627\u062e"
    ],
    "name:und_x_variant":[
        "\u2018Arab al Ma\u015f\u0101kh"
    ],
    "wof:name":"'Arab al Masakh",
    "wof:placetype":"locality"
},
  "geometry": {"coordinates":[44.51047,31.65172],"type":"Point"}
}