{
  "type": "Feature",
  "properties": {
    "gn:admin1_code":"18.0",
    "gn:admin2_code":"6805736.0",
    "gn:asciiname":"'Abbas al Ahmad",
    "gn:country_code":"IQ",
    "gn:dem":49,
    "gn:feature_class":"P",
    "gn:feature_code":"PPL",
    "gn:name":"\u2018Abb\u0101s al A\u1e29mad",
    "gn:population":0,
    "gn:timezone":"Asia/Baghdad",
    "iso:country":"IQ",
    "name:und_x_variant":[
        "\u2018Abb\u0101s",
        "\u2018Abb\u0101s al A\u1e29mad"
    ],
    "wof:name":"'Abbas al Ahmad",
    "wof:placetype":"locality"
},
  "geometry": {"coordinates":[44.24389,34.02806],"type":"Point"}
}