{
  "type": "Feature",
  "properties": {
    "gn:admin1_code":"6.0",
    "gn:admin2_code":"99358.0",
    "gn:asciiname":"Muhammad al Balu",
    "gn:country_code":"IQ",
    "gn:dem":25,
    "gn:feature_class":"P",
    "gn:feature_code":"PPL",
    "gn:name":"Mu\u1e29ammad al Bal\u016b",
    "gn:population":0,
    "gn:timezone":"Asia/Baghdad",
    "iso:country":"IQ",
    "name:ara_x_preferred":[
        "\u0645\u062d\u0645\u062f \u0627\u0644\u0628\u0644\u0648"
    ],
    "name:und_x_variant":[
        "Mu\u1e29ammad al Bal\u016b"
    ],
    "wof:name":"Muhammad al Balu",
    "wof:placetype":"locality"
},
  "geometry": {"coordinates":[44.70988,32.25039],"type":"Point"}
}