{
  "type": "Feature",
  "properties": {
    "gn:admin1_code":"7.0",
    "gn:asciiname":"Qaryat al Haqq",
    "gn:country_code":"IQ",
    "gn:dem":25,
    "gn:feature_class":"P",
    "gn:feature_code":"PPL",
    "gn:name":"Qaryat al \u1e28aqq",
    "gn:population":0,
    "gn:timezone":"Asia/Baghdad",
    "iso:country":"IQ",
    "name:ara_x_preferred":[
        "\u0642\u0631\u064a\u0629 \u0627\u0644\u062d\u0642"
    ],
    "name:und_x_variant":[
        "Qaryat al \u1e28aqq"
    ],
    "wof:name":"Qaryat al Haqq",
    "wof:placetype":"locality"
},
  "geometry": {"coordinates":[44.54989000000001,32.83297],"type":"Point"}
}