{
  "type": "Feature",
  "properties": {
    "gn:admin1_code":"17.0",
    "gn:admin2_code":"9166629.0",
    "gn:asciiname":"Al Sayyid Hamzah",
    "gn:country_code":"IQ",
    "gn:dem":26,
    "gn:feature_class":"P",
    "gn:feature_code":"PPL",
    "gn:name":"\u0100l Sayyid \u1e28amzah",
    "gn:population":0,
    "gn:timezone":"Asia/Baghdad",
    "iso:country":"IQ",
    "name:ara_x_preferred":[
        "\u0622\u0644 \u0633\u064a\u062f \u062d\u0645\u0632\u0629"
    ],
    "name:und_x_variant":[
        "\u0100l Sayyid \u1e28amzah"
    ],
    "wof:name":"Al Sayyid Hamzah",
    "wof:placetype":"locality"
},
  "geometry": {"coordinates":[44.54347,32.08673],"type":"Point"}
}