{
  "type": "Feature",
  "properties": {
    "gn:admin1_code":"1.0",
    "gn:admin2_code":"9166650.0",
    "gn:asciiname":"Jarb",
    "gn:cc2":"IQ",
    "gn:country_code":"IQ",
    "gn:dem":138,
    "gn:feature_class":"P",
    "gn:feature_code":"PPL",
    "gn:name":"Jarb",
    "gn:population":0,
    "gn:timezone":"Asia/Baghdad",
    "iso:country":"IQ",
    "name:und_x_variant":[
        "Jurn",
        "Jarab"
    ],
    "wof:name":"Jarb",
    "wof:placetype":"locality"
},
  "geometry": {"coordinates":[42.2025,34.295],"type":"Point"}
}