{
  "type": "Feature",
  "properties": {
    "gn:admin1_code":"14.0",
    "gn:admin2_code":"99097.0",
    "gn:asciiname":"Rubayyah",
    "gn:cc2":"IQ",
    "gn:country_code":"IQ",
    "gn:dem":7,
    "gn:feature_class":"P",
    "gn:feature_code":"PPL",
    "gn:name":"Rubayyah",
    "gn:population":0,
    "gn:timezone":"Asia/Baghdad",
    "iso:country":"IQ",
    "name:und_x_variant":[
        "Rubaybah",
        "Rubaibyah",
        "Rubaiya",
        "Rubayyah"
    ],
    "wof:name":"Rubayyah",
    "wof:placetype":"locality"
},
  "geometry": {"coordinates":[47.16667,31.63333],"type":"Point"}
}