{
  "type": "Feature",
  "properties": {
    "gn:admin1_code":"14.0",
    "gn:admin2_code":"9166562.0",
    "gn:asciiname":"Al Hamidiyah",
    "gn:country_code":"IQ",
    "gn:dem":8,
    "gn:feature_class":"P",
    "gn:feature_code":"PPL",
    "gn:name":"Al \u1e28am\u012bd\u012byah",
    "gn:population":0,
    "gn:timezone":"Asia/Baghdad",
    "iso:country":"IQ",
    "name:ara_x_preferred":[
        "\u0627\u0644\u062d\u0645\u064a\u062f\u064a\u0629"
    ],
    "name:und_x_variant":[
        "Al \u1e28am\u012bd\u012byah"
    ],
    "wof:name":"Al Hamidiyah",
    "wof:placetype":"locality"
},
  "geometry": {"coordinates":[46.88399999999999,31.62237],"type":"Point"}
}