{
  "type": "Feature",
  "properties": {
    "gn:admin1_code":"4.0",
    "gn:admin2_code":"99763.0",
    "gn:asciiname":"Rahi 'Uwayz",
    "gn:country_code":"IQ",
    "gn:dem":25,
    "gn:feature_class":"P",
    "gn:feature_code":"PPL",
    "gn:name":"R\u0101h\u012b \u2018Uwayz",
    "gn:population":0,
    "gn:timezone":"Asia/Baghdad",
    "iso:country":"IQ",
    "name:ara_x_preferred":[
        "\u0631\u0627\u0647\u064a \u0639\u0648\u064a\u0632"
    ],
    "name:und_x_variant":[
        "R\u0101h\u012b \u2018Uwayz"
    ],
    "wof:name":"Rahi 'Uwayz",
    "wof:placetype":"locality"
},
  "geometry": {"coordinates":[44.72031,32.09078],"type":"Point"}
}