{
  "type": "Feature",
  "properties": {
    "gn:admin1_code":"9.0",
    "gn:admin2_code":"98700.0",
    "gn:asciiname":"Qal'at Kanj Samit",
    "gn:country_code":"IQ",
    "gn:dem":13,
    "gn:feature_class":"P",
    "gn:feature_code":"PPL",
    "gn:name":"Qal\u2018at Kanj S\u0101mit",
    "gn:population":0,
    "gn:timezone":"Asia/Baghdad",
    "iso:country":"IQ",
    "name:und_x_variant":[
        "Qal\u2018at Kanj S\u0101mit"
    ],
    "wof:name":"Qal'at Kanj Samit",
    "wof:placetype":"locality"
},
  "geometry": {"coordinates":[45.91667,31.93333],"type":"Point"}
}