{
  "type": "Feature",
  "properties": {
    "gn:admin1_code":"2.0",
    "gn:admin2_code":"9166563.0",
    "gn:asciiname":"Al Madinah",
    "gn:country_code":"IQ",
    "gn:dem":6,
    "gn:feature_class":"P",
    "gn:feature_code":"PPLA2",
    "gn:name":"Al Mad\u012bnah",
    "gn:population":0,
    "gn:timezone":"Asia/Baghdad",
    "iso:country":"IQ",
    "name:ara_x_preferred":[
        "\u0627\u0644\u0645\u062f\u064a\u0646\u0629"
    ],
    "name:und_x_variant":[
        "Medineh",
        "Al Madina",
        "Medina",
        "Al Mad\u012bnah"
    ],
    "wof:name":"Al Madinah",
    "wof:placetype":"locality"
},
  "geometry": {"coordinates":[47.26998,30.96324000000001],"type":"Point"}
}