{
  "type": "Feature",
  "properties": {
    "gn:admin1_code":"7.0",
    "gn:admin2_code":"99101.0",
    "gn:asciiname":"As Suwaydi",
    "gn:country_code":"IQ",
    "gn:dem":36,
    "gn:feature_class":"P",
    "gn:feature_code":"PPL",
    "gn:name":"As S\u016bwayd\u012b",
    "gn:population":0,
    "gn:timezone":"Asia/Baghdad",
    "iso:country":"IQ",
    "name:ara_x_preferred":[
        "\u0627\u0644\u0633\u0648\u064a\u062f\u064a"
    ],
    "name:und_x_variant":[
        "As S\u016bwayd\u012b"
    ],
    "wof:name":"As Suwaydi",
    "wof:placetype":"locality"
},
  "geometry": {"coordinates":[44.34355,33.13609],"type":"Point"}
}