{
  "type": "Feature",
  "properties": {
    "gn:admin1_code":"6.0",
    "gn:admin2_code":"99358.0",
    "gn:asciiname":"Yasir Kazim",
    "gn:country_code":"IQ",
    "gn:dem":24,
    "gn:feature_class":"P",
    "gn:feature_code":"PPL",
    "gn:name":"Y\u0101sir K\u0101z\u0327im",
    "gn:population":0,
    "gn:timezone":"Asia/Baghdad",
    "iso:country":"IQ",
    "name:ara_x_preferred":[
        "\u064a\u0627\u0633\u0631 \u0643\u0627\u0638\u0645"
    ],
    "name:ara_x_variant":[
        "Y\u0101sir K\u0101z\u0327im"
    ],
    "wof:name":"Yasir Kazim",
    "wof:placetype":"locality"
},
  "geometry": {"coordinates":[44.90875,32.38062],"type":"Point"}
}