{
  "type": "Feature",
  "properties": {
    "gn:admin1_code":"15.0",
    "gn:admin2_code":"98820.0",
    "gn:asciiname":"Shaykh Khanuk",
    "gn:country_code":"IQ",
    "gn:dem":509,
    "gn:feature_class":"P",
    "gn:feature_code":"PPL",
    "gn:name":"Shaykh Kh\u0101n\u016bk",
    "gn:population":0,
    "gn:timezone":"Asia/Baghdad",
    "iso:country":"IQ",
    "name:ara_x_preferred":[
        "\u0634\u064a\u062e \u062e\u0627\u0646\u0648\u0643"
    ],
    "name:kur_x_preferred":[
        "Sh\u00eax Xanuk"
    ],
    "name:kur_x_variant":[
        "\u0634\u06ce\u062e \u062e\u0627\u0646\u0648\u0643"
    ],
    "name:und_x_variant":[
        "Sheikh Khanuk",
        "Shaikh Kh\u0101nuk",
        "Shaykh Kh\u0101n\u016bk"
    ],
    "wof:name":"Shaykh Khanuk",
    "wof:placetype":"locality"
},
  "geometry": {"coordinates":[43.76214,36.61001],"type":"Point"}
}