{
  "type": "Feature",
  "properties": {
    "gn:admin1_code":"17.0",
    "gn:admin2_code":"9166629.0",
    "gn:asciiname":"Kitab Mahdi",
    "gn:country_code":"IQ",
    "gn:dem":25,
    "gn:feature_class":"P",
    "gn:feature_code":"PPL",
    "gn:name":"Kit\u0101b Mahd\u012b",
    "gn:population":0,
    "gn:timezone":"Asia/Baghdad",
    "iso:country":"IQ",
    "name:ara_x_preferred":[
        "\u0643\u062a\u0627\u0628 \u0645\u0647\u062f\u064a"
    ],
    "name:und_x_variant":[
        "Kit\u0101b Mahd\u012b"
    ],
    "wof:name":"Kitab Mahdi",
    "wof:placetype":"locality"
},
  "geometry": {"coordinates":[44.5397,32.07508],"type":"Point"}
}