{
  "type": "Feature",
  "properties": {
    "gn:admin1_code":"6.0",
    "gn:admin2_code":"99358.0",
    "gn:asciiname":"Qaryat as Salt al Uwla",
    "gn:country_code":"IQ",
    "gn:dem":31,
    "gn:feature_class":"P",
    "gn:feature_code":"PPL",
    "gn:name":"Qaryat as Sal\u0163 al \u016awl\u00e1",
    "gn:population":0,
    "gn:timezone":"Asia/Baghdad",
    "iso:country":"IQ",
    "name:ara_x_preferred":[
        "\u0642\u0631\u064a\u0629 \u0627\u0644\u0633\u0644\u0637 \u0627\u0644\u0627\u0648\u0644\u0649"
    ],
    "name:und_x_variant":[
        "Qaryat as Sal\u0163 al \u016awl\u00e1"
    ],
    "wof:name":"Qaryat as Salt al Uwla",
    "wof:placetype":"locality"
},
  "geometry": {"coordinates":[44.62597,32.3285],"type":"Point"}
}