{
  "type": "Feature",
  "properties": {
    "gn:admin1_code":"12.0",
    "gn:admin2_code":"99345.0",
    "gn:asciiname":"Khiyarah",
    "gn:country_code":"IQ",
    "gn:dem":27,
    "gn:feature_class":"P",
    "gn:feature_code":"PPL",
    "gn:name":"Khiy\u0101rah",
    "gn:population":0,
    "gn:timezone":"Asia/Baghdad",
    "iso:country":"IQ",
    "name:und_x_variant":[
        "Khiy\u0101rah"
    ],
    "wof:name":"Khiyarah",
    "wof:placetype":"locality"
},
  "geometry": {"coordinates":[44.26667,32.38333],"type":"Point"}
}