{
  "type": "Feature",
  "properties": {
    "gn:admin1_code":"18.0",
    "gn:admin2_code":"90148.0",
    "gn:asciiname":"Madi Hasan",
    "gn:country_code":"IQ",
    "gn:dem":124,
    "gn:feature_class":"P",
    "gn:feature_code":"PPL",
    "gn:name":"M\u0101\u1e11\u012b \u1e28asan",
    "gn:population":0,
    "gn:timezone":"Asia/Baghdad",
    "iso:country":"IQ",
    "name:ara_x_preferred":[
        "\u0645\u0627\u0636\u064a \u062d\u0633\u0646"
    ],
    "name:und_x_variant":[
        "M\u0101\u1e11\u012b \u1e28asan"
    ],
    "wof:name":"Madi Hasan",
    "wof:placetype":"locality"
},
  "geometry": {"coordinates":[43.48748,34.55258],"type":"Point"}
}