{
  "type": "Feature",
  "properties": {
    "gn:admin1_code":"15.0",
    "gn:admin2_code":"98820.0",
    "gn:asciiname":"Der Awdisho",
    "gn:country_code":"IQ",
    "gn:dem":838,
    "gn:feature_class":"P",
    "gn:feature_code":"PPL",
    "gn:name":"D\u0113r Awd\u012bsho",
    "gn:population":0,
    "gn:timezone":"Asia/Baghdad",
    "iso:country":"IQ",
    "name:ara_x_preferred":[
        "D\u0113r Awd\u012bsho"
    ],
    "wof:name":"Der Awdisho",
    "wof:placetype":"locality"
},
  "geometry": {"coordinates":[43.78806,36.79917],"type":"Point"}
}