{
  "type": "Feature",
  "properties": {
    "gn:admin1_code":"15.0",
    "gn:admin2_code":"9166649.0",
    "gn:asciiname":"Qaryat al Fajj",
    "gn:country_code":"IQ",
    "gn:dem":210,
    "gn:feature_class":"P",
    "gn:feature_code":"PPL",
    "gn:name":"Qaryat al Fajj",
    "gn:population":0,
    "gn:timezone":"Asia/Baghdad",
    "iso:country":"IQ",
    "name:ara_x_preferred":[
        "\u0642\u0631\u064a\u0629 \u0627\u0644\u0641\u062c"
    ],
    "name:ara_x_variant":[
        "\u0642\u0631\u064a\u0629 \u0627\u0644\u0641\u0686"
    ],
    "name:und_x_variant":[
        "Qaryat al Fach"
    ],
    "wof:name":"Qaryat al Fajj",
    "wof:placetype":"locality"
},
  "geometry": {"coordinates":[43.24686,35.8726],"type":"Point"}
}