{
  "type": "Feature",
  "properties": {
    "gn:admin1_code":"13.0",
    "gn:admin2_code":"9171727.0",
    "gn:asciiname":"Kitkah",
    "gn:country_code":"IQ",
    "gn:dem":331,
    "gn:feature_class":"P",
    "gn:feature_code":"PPL",
    "gn:name":"Kitkah",
    "gn:population":0,
    "gn:timezone":"Asia/Baghdad",
    "iso:country":"IQ",
    "name:ara_x_preferred":[
        "\u0643\u062a\u0643\u0629"
    ],
    "name:kur_x_preferred":[
        "kitke"
    ],
    "name:kur_x_variant":[
        "\u0643\u062a\u0643\u06d5",
        "Kitka"
    ],
    "name:und_x_variant":[
        "Gitkah",
        "Kitkah",
        "Kitka"
    ],
    "wof:name":"Kitkah",
    "wof:placetype":"locality"
},
  "geometry": {"coordinates":[44.16253,35.70032],"type":"Point"}
}