{
  "type": "Feature",
  "properties": {
    "gn:admin1_code":"13.0",
    "gn:admin2_code":"6770659.0",
    "gn:asciiname":"Qaryat Tar al Baghal",
    "gn:country_code":"IQ",
    "gn:dem":185,
    "gn:feature_class":"P",
    "gn:feature_code":"PPL",
    "gn:name":"Qaryat \u0162\u0101r al Baghal",
    "gn:population":0,
    "gn:timezone":"Asia/Baghdad",
    "iso:country":"IQ",
    "name:ara_x_preferred":[
        "\u0642\u0631\u064a\u0629 \u0637\u0627\u0631 \u0627\u0644\u0628\u063a\u0644"
    ],
    "name:und_x_variant":[
        "Qaryat \u0162\u0101r al Baghal"
    ],
    "wof:name":"Qaryat Tar al Baghal",
    "wof:placetype":"locality"
},
  "geometry": {"coordinates":[43.87312,35.24041],"type":"Point"}
}