{
  "type": "Feature",
  "properties": {
    "gn:admin1_code":"18.0",
    "gn:admin2_code":"6805736.0",
    "gn:asciiname":"Mahal al Fayad",
    "gn:country_code":"IQ",
    "gn:dem":44,
    "gn:feature_class":"P",
    "gn:feature_code":"PPL",
    "gn:name":"Ma\u1e29al al Fay\u0101\u1e11",
    "gn:population":0,
    "gn:timezone":"Asia/Baghdad",
    "iso:country":"IQ",
    "name:ara_x_preferred":[
        "\u0645\u062d\u0644 \u0627\u0644\u0641\u064a\u0627\u0636"
    ],
    "name:und_x_variant":[
        "Ma\u1e29al al Fay\u0101\u1e11"
    ],
    "wof:name":"Mahal al Fayad",
    "wof:placetype":"locality"
},
  "geometry": {"coordinates":[44.07106,33.8362],"type":"Point"}
}