{
  "type": "Feature",
  "properties": {
    "gn:admin1_code":"6.0",
    "gn:admin2_code":"99348.0",
    "gn:asciiname":"Qaryat Qital al Janubi",
    "gn:country_code":"IQ",
    "gn:dem":34,
    "gn:feature_class":"P",
    "gn:feature_code":"PPL",
    "gn:name":"Qaryat Qit\u0101l al Jan\u016bb\u012b",
    "gn:population":0,
    "gn:timezone":"Asia/Baghdad",
    "iso:country":"IQ",
    "name:ara_x_preferred":[
        "\u0642\u0631\u064a\u0629 \u0642\u062a\u0627\u0644 \u0627\u0644\u062c\u0646\u0648\u0628\u064a"
    ],
    "name:und_x_variant":[
        "Qaryat Qit\u0101l al Jan\u016bb\u012b"
    ],
    "wof:name":"Qaryat Qital al Janubi",
    "wof:placetype":"locality"
},
  "geometry": {"coordinates":[44.31392,32.36873],"type":"Point"}
}