{
  "type": "Feature",
  "properties": {
    "gn:admin1_code":"6.0",
    "gn:admin2_code":"6818313.0",
    "gn:asciiname":"Mush'an Shayya'",
    "gn:country_code":"IQ",
    "gn:dem":29,
    "gn:feature_class":"P",
    "gn:feature_code":"PPL",
    "gn:name":"Mush\u2018\u0101n Shayy\u0101\u2018",
    "gn:population":0,
    "gn:timezone":"Asia/Baghdad",
    "iso:country":"IQ",
    "name:ara_x_preferred":[
        "\u0645\u0634\u0639\u0627\u0646 \u0634\u064a\u0627\u0639"
    ],
    "name:und_x_variant":[
        "Mush\u2018\u0101n Shayy\u0101\u2018"
    ],
    "wof:name":"Mush'an Shayya'",
    "wof:placetype":"locality"
},
  "geometry": {"coordinates":[44.69522,32.72702],"type":"Point"}
}