{
  "type": "Feature",
  "properties": {
    "gn:admin1_code":"9.0",
    "gn:admin2_code":"98700.0",
    "gn:asciiname":"Albu Thabit",
    "gn:country_code":"IQ",
    "gn:dem":14,
    "gn:feature_class":"P",
    "gn:feature_code":"PPL",
    "gn:name":"\u0100lb\u016b Th\u0101bit",
    "gn:population":0,
    "gn:timezone":"Asia/Baghdad",
    "iso:country":"IQ",
    "name:ara_x_preferred":[
        "\u0627\u0644\u0628\u0648 \u062b\u0627\u0628\u062a"
    ],
    "name:ara_x_variant":[
        "\u0100lb\u016b Th\u0101bit"
    ],
    "wof:name":"Albu Thabit",
    "wof:placetype":"locality"
},
  "geometry": {"coordinates":[45.90012,31.90254],"type":"Point"}
}