{
  "type": "Feature",
  "properties": {
    "gn:admin1_code":"1.0",
    "gn:admin2_code":"99455.0",
    "gn:asciiname":"Qaryat al 'Ujayz al Gharbi",
    "gn:country_code":"IQ",
    "gn:dem":43,
    "gn:feature_class":"P",
    "gn:feature_code":"PPL",
    "gn:name":"Qaryat al \u2018Ujayz al Gharb\u012b",
    "gn:population":0,
    "gn:timezone":"Asia/Baghdad",
    "iso:country":"IQ",
    "name:ara_x_preferred":[
        "\u0642\u0631\u064a\u0629 \u0627\u0644\u0639\u062c\u064a\u0632 \u0627\u0644\u063a\u0631\u0628\u064a"
    ],
    "name:und_x_variant":[
        "Qaryat al \u2018Ujayz al Gharb\u012b"
    ],
    "wof:name":"Qaryat al 'Ujayz al Gharbi",
    "wof:placetype":"locality"
},
  "geometry": {"coordinates":[43.96108,33.14135],"type":"Point"}
}