{
  "type": "Feature",
  "properties": {
    "gn:admin1_code":"5.0",
    "gn:admin2_code":"96204.0",
    "gn:asciiname":"Khayli Hamah",
    "gn:country_code":"IQ",
    "gn:dem":593,
    "gn:feature_class":"P",
    "gn:feature_code":"PPL",
    "gn:name":"Khayl\u012b \u1e28amah",
    "gn:population":0,
    "gn:timezone":"Asia/Baghdad",
    "iso:country":"IQ",
    "name:ara_x_preferred":[
        "\u062e\u064a\u0644\u064a \u062d\u0645\u0629"
    ],
    "name:fas_x_preferred":[
        "\u062e\u0644 \u0647\u0645\u0647"
    ],
    "name:kur_x_preferred":[
        "X\u00ea\u0142\u00ee \u1e26eme"
    ],
    "name:kur_x_variant":[
        "\u062e\u06ce\u06b5\u0649 \u062d\u06d5\u0645\u06d5"
    ],
    "name:und_x_variant":[
        "Kh\u0113-l-e \u1e28ama",
        "Khail-\u012b Hama",
        "Khayl\u012b \u1e28amah",
        "Khel-e Hamah",
        "Kh\u0101l\u012b \u1e28amah",
        "Khely Hama",
        "\u062e\u0627\u0644\u064a \u062d\u0645\u0629"
    ],
    "wof:name":"Khayli Hamah",
    "wof:placetype":"locality"
},
  "geometry": {"coordinates":[46.01103,35.26622000000001],"type":"Point"}
}