{
  "type": "Feature",
  "properties": {
    "gn:admin1_code":"13.0",
    "gn:admin2_code":"9171727.0",
    "gn:asciiname":"Qaryat an Nahatiyah",
    "gn:country_code":"IQ",
    "gn:dem":227,
    "gn:feature_class":"P",
    "gn:feature_code":"PPL",
    "gn:name":"Qaryat an Na\u1e29\u0101t\u012byah",
    "gn:population":0,
    "gn:timezone":"Asia/Baghdad",
    "iso:country":"IQ",
    "name:ara_x_preferred":[
        "\u0642\u0631\u064a\u0629 \u0627\u0644\u0646\u062d\u0627\u062a\u064a\u0629"
    ],
    "name:und_x_variant":[
        "Qaryat an Na\u1e29\u0101t\u012byah"
    ],
    "wof:name":"Qaryat an Nahatiyah",
    "wof:placetype":"locality"
},
  "geometry": {"coordinates":[43.92719,35.44703],"type":"Point"}
}