{
  "type": "Feature",
  "properties": {
    "gn:admin1_code":"5.0",
    "gn:admin2_code":"91176.0",
    "gn:asciiname":"Kawrah Daym",
    "gn:country_code":"IQ",
    "gn:dem":1352,
    "gn:feature_class":"P",
    "gn:feature_code":"PPL",
    "gn:name":"Kawrah Daym",
    "gn:population":0,
    "gn:timezone":"Asia/Baghdad",
    "iso:country":"IQ",
    "name:kur_x_preferred":[
        "Go\u1e5fe D\u00eam"
    ],
    "name:kur_x_variant":[
        "\u06af\u06c6\u0695\u06d5 \u062f\u06ce\u0645"
    ],
    "name:und_x_variant":[
        "G\u014drad\u0113m",
        "Goradah",
        "Kawrah Daym",
        "\u0643\u0648\u0631\u0629 \u062f\u064a\u0645",
        "Goradeh",
        "Gora Dem"
    ],
    "wof:name":"Kawrah Daym",
    "wof:placetype":"locality"
},
  "geometry": {"coordinates":[45.63593,35.73564000000001],"type":"Point"}
}