{
  "type": "Feature",
  "properties": {
    "gn:admin1_code":"1.0",
    "gn:admin2_code":"98678.0",
    "gn:asciiname":"'Uklat Sawab",
    "gn:country_code":"IQ",
    "gn:dem":534,
    "gn:feature_class":"P",
    "gn:feature_code":"PPL",
    "gn:name":"\u2018Uklat \u015eaw\u0101b",
    "gn:population":0,
    "gn:timezone":"Asia/Baghdad",
    "iso:country":"IQ",
    "name:ara_x_preferred":[
        "\u0639\u0643\u0644\u0647 \u0635\u0648\u0627\u0628"
    ],
    "name:und_x_variant":[
        "\u2018Uklat \u015eaw\u0101b"
    ],
    "wof:name":"'Uklat Sawab",
    "wof:placetype":"locality"
},
  "geometry": {"coordinates":[40.02087,33.89605],"type":"Point"}
}