{
  "type": "Feature",
  "properties": {
    "gn:admin1_code":"4.0",
    "gn:admin2_code":"98634.0",
    "gn:asciiname":"Husayn Al 'Ayyar",
    "gn:country_code":"IQ",
    "gn:dem":20,
    "gn:feature_class":"P",
    "gn:feature_code":"PPL",
    "gn:name":"\u1e28usayn \u0100l \u2018Ayy\u0101r",
    "gn:population":0,
    "gn:timezone":"Asia/Baghdad",
    "iso:country":"IQ",
    "name:ara_x_preferred":[
        "\u062d\u0633\u064a\u0646 \u0627\u0644 \u0639\u064a\u0627\u0631"
    ],
    "name:und_x_variant":[
        "\u1e28usayn \u0100l \u2018Ayy\u0101r"
    ],
    "wof:name":"Husayn Al 'Ayyar",
    "wof:placetype":"locality"
},
  "geometry": {"coordinates":[44.57126,31.83495],"type":"Point"}
}