{
  "type": "Feature",
  "properties": {
    "gn:admin1_code":"11.0",
    "gn:admin2_code":"9166586.0",
    "gn:asciiname":"Daykah",
    "gn:country_code":"IQ",
    "gn:dem":1264,
    "gn:feature_class":"P",
    "gn:feature_code":"PPL",
    "gn:name":"Daykah",
    "gn:population":0,
    "gn:timezone":"Asia/Baghdad",
    "iso:country":"IQ",
    "name:ara_x_preferred":[
        "\u062f\u064a\u0643\u0629"
    ],
    "name:kur_x_preferred":[
        "D\u00eake"
    ],
    "name:kur_x_variant":[
        "\u062f\u06ce\u0643\u06d5"
    ],
    "name:und_x_variant":[
        "D\u0113ga",
        "Dega"
    ],
    "wof:name":"Daykah",
    "wof:placetype":"locality"
},
  "geometry": {"coordinates":[44.73067,36.64911],"type":"Point"}
}