{
  "type": "Feature",
  "properties": {
    "gn:admin1_code":"6.0",
    "gn:admin2_code":"99040.0",
    "gn:asciiname":"'Abd Rabbuh",
    "gn:country_code":"IQ",
    "gn:dem":29,
    "gn:feature_class":"P",
    "gn:feature_code":"PPL",
    "gn:name":"\u2018Abd Rabbuh",
    "gn:population":0,
    "gn:timezone":"Asia/Baghdad",
    "iso:country":"IQ",
    "name:ara_x_preferred":[
        "\u0639\u0628\u062f \u0631\u0628\u0647"
    ],
    "name:und_x_variant":[
        "\u2018Abd Rabbuh"
    ],
    "wof:name":"'Abd Rabbuh",
    "wof:placetype":"locality"
},
  "geometry": {"coordinates":[44.27949,32.62639],"type":"Point"}
}