{
  "type": "Feature",
  "properties": {
    "gn:admin1_code":"4.0",
    "gn:admin2_code":"6850588.0",
    "gn:asciiname":"Hajj Harchan",
    "gn:country_code":"IQ",
    "gn:dem":14,
    "gn:feature_class":"P",
    "gn:feature_code":"PPL",
    "gn:name":"\u1e28\u0101jj \u1e28arch\u0101n",
    "gn:population":0,
    "gn:timezone":"Asia/Baghdad",
    "iso:country":"IQ",
    "name:ara_x_preferred":[
        "\u062d\u0627\u062c \u062d\u0631\u0686\u0627\u0646"
    ],
    "name:und_x_variant":[
        "\u1e28\u0101jj \u1e28arch\u0101n"
    ],
    "wof:name":"Hajj Harchan",
    "wof:placetype":"locality"
},
  "geometry": {"coordinates":[45.05839,31.57342],"type":"Point"}
}