{
  "type": "Feature",
  "properties": {
    "gn:admin1_code":"10.0",
    "gn:admin2_code":"94590.0",
    "gn:asciiname":"Husayn Bak",
    "gn:country_code":"IQ",
    "gn:dem":153,
    "gn:feature_class":"P",
    "gn:feature_code":"PPL",
    "gn:name":"\u1e28usayn Bak",
    "gn:population":0,
    "gn:timezone":"Asia/Baghdad",
    "iso:country":"IQ",
    "name:ara_x_preferred":[
        "\u062d\u0633\u064a\u0646 \u0628\u0643"
    ],
    "name:und_x_variant":[
        "Hasan Beg",
        "\u1e28asan Bayk",
        "Al \u1e28urr\u012byah",
        "\u0627\u0644\u062d\u0631\u064a\u0629",
        "\u1e28usayn Bak"
    ],
    "wof:name":"Husayn Bak",
    "wof:placetype":"locality"
},
  "geometry": {"coordinates":[45.30095,34.3439],"type":"Point"}
}