{
  "type": "Feature",
  "properties": {
    "gn:admin1_code":"16.0",
    "gn:admin2_code":"9166961.0",
    "gn:asciiname":"Hassun 'Iyal Wahid Ghazi",
    "gn:country_code":"IQ",
    "gn:dem":35,
    "gn:feature_class":"P",
    "gn:feature_code":"PPL",
    "gn:name":"\u1e28ass\u016bn \u2018Iy\u0101l Wa\u1e29\u012bd Gh\u0101z\u012b",
    "gn:population":0,
    "gn:timezone":"Asia/Baghdad",
    "iso:country":"IQ",
    "name:ara_x_preferred":[
        "\u062d\u0633\u0648\u0646 \u0639\u064a\u0627\u0644 \u0648\u062d\u064a\u062f \u063a\u0627\u0632\u064a"
    ],
    "name:und_x_variant":[
        "\u1e28ass\u016bn \u2018Iy\u0101l Wa\u1e29\u012bd Gh\u0101z\u012b"
    ],
    "wof:name":"Hassun 'Iyal Wahid Ghazi",
    "wof:placetype":"locality"
},
  "geometry": {"coordinates":[44.75661,32.98398],"type":"Point"}
}