{
  "type": "Feature",
  "properties": {
    "gn:admin1_code":"9.0",
    "gn:admin2_code":"98623.0",
    "gn:asciiname":"Ash Shaykh Hamid",
    "gn:country_code":"IQ",
    "gn:dem":8,
    "gn:feature_class":"P",
    "gn:feature_code":"PPL",
    "gn:name":"Ash Shaykh \u1e28\u0101mid",
    "gn:population":0,
    "gn:timezone":"Asia/Baghdad",
    "iso:country":"IQ",
    "name:ara_x_preferred":[
        "\u0627\u0644\u0634\u064a\u062e \u062d\u0627\u0645\u062f"
    ],
    "name:und_x_variant":[
        "Ash Shaykh \u1e28\u0101mid"
    ],
    "wof:name":"Ash Shaykh Hamid",
    "wof:placetype":"locality"
},
  "geometry": {"coordinates":[46.3435,31.53977],"type":"Point"}
}