{
  "type": "Feature",
  "properties": {
    "gn:admin1_code":"11.0",
    "gn:admin2_code":"9166592.0",
    "gn:asciiname":"Karwah as Sufla",
    "gn:country_code":"IQ",
    "gn:dem":1003,
    "gn:feature_class":"P",
    "gn:feature_code":"PPL",
    "gn:name":"Karwah as Sufl\u00e1",
    "gn:population":0,
    "gn:timezone":"Asia/Baghdad",
    "iso:country":"IQ",
    "name:ara_x_preferred":[
        "\u0643\u0631\u0648\u0647 \u0627\u0644\u0633\u0641\u0644\u0649"
    ],
    "name:kur_x_preferred":[
        "Girwan"
    ],
    "name:kur_x_variant":[
        "Gerwan\u00ee Xwar\u00fb",
        "\u06af\u0631\u0648\u0627\u0646",
        "\u06af\u06d5\u0631\u0648\u0627\u0646\u0649 \u062e\u0648\u0627\u0631\u0648\u0648"
    ],
    "name:und_x_variant":[
        "Karwah as Sufl\u00e1",
        "Garawan"
    ],
    "wof:name":"Karwah as Sufla",
    "wof:placetype":"locality"
},
  "geometry": {"coordinates":[44.58462,36.52083],"type":"Point"}
}