{
  "type": "Feature",
  "properties": {
    "gn:admin1_code":"16.0",
    "gn:admin2_code":"99132.0",
    "gn:asciiname":"Al Musandaq",
    "gn:cc2":"IQ",
    "gn:country_code":"IQ",
    "gn:dem":12,
    "gn:feature_class":"P",
    "gn:feature_code":"PPL",
    "gn:name":"Al Mu\u015fandaq",
    "gn:population":0,
    "gn:timezone":"Asia/Baghdad",
    "iso:country":"IQ",
    "name:und_x_variant":[
        "Musandaq",
        "Umm Sunduk",
        "Musandak",
        "Al Mu\u015fandaq"
    ],
    "wof:name":"Al Musandaq",
    "wof:placetype":"locality"
},
  "geometry": {"coordinates":[46.43083,32.51833],"type":"Point"}
}