{
  "type": "Feature",
  "properties": {
    "gn:admin1_code":"10.0",
    "gn:admin2_code":"9166680.0",
    "gn:asciiname":"Zayn al 'Abidin",
    "gn:country_code":"IQ",
    "gn:dem":42,
    "gn:feature_class":"P",
    "gn:feature_code":"PPL",
    "gn:name":"Zayn al \u2018\u0100bid\u012bn",
    "gn:population":0,
    "gn:timezone":"Asia/Baghdad",
    "iso:country":"IQ",
    "name:ara_x_preferred":[
        "\u0632\u064a\u0646 \u0627\u0644\u0639\u0627\u0628\u062f\u064a\u0646"
    ],
    "name:und_x_variant":[
        "Zayn al \u2018\u0100bid\u012bn"
    ],
    "wof:name":"Zayn al 'Abidin",
    "wof:placetype":"locality"
},
  "geometry": {"coordinates":[45.09578,33.67279],"type":"Point"}
}