{
  "type": "Feature",
  "properties": {
    "gn:admin1_code":"17.0",
    "gn:admin2_code":"9166629.0",
    "gn:asciiname":"Qaryat al Barakiyah",
    "gn:country_code":"IQ",
    "gn:dem":28,
    "gn:feature_class":"P",
    "gn:feature_code":"PPL",
    "gn:name":"Qaryat al Bar\u0101k\u012byah",
    "gn:population":0,
    "gn:timezone":"Asia/Baghdad",
    "iso:country":"IQ",
    "name:ara_x_preferred":[
        "\u0642\u0631\u064a\u0629 \u0627\u0644\u0628\u0631\u0627\u0643\u064a\u0629"
    ],
    "name:und_x_variant":[
        "Qaryat al Bar\u0101k\u012byah"
    ],
    "wof:name":"Qaryat al Barakiyah",
    "wof:placetype":"locality"
},
  "geometry": {"coordinates":[44.40801,32.01377],"type":"Point"}
}