{
  "type": "Feature",
  "properties": {
    "gn:admin1_code":"2.0",
    "gn:asciiname":"Al Jabas al Kabir",
    "gn:country_code":"IQ",
    "gn:dem":5,
    "gn:feature_class":"P",
    "gn:feature_code":"PPL",
    "gn:name":"Al Jab\u0101s al Kab\u012br",
    "gn:population":0,
    "gn:timezone":"Asia/Baghdad",
    "iso:country":"IQ",
    "name:ara_x_preferred":[
        "Kib\u0101s\u012b"
    ],
    "name:ara_x_variant":[
        "\u0627\u0644\u062c\u0628\u0627\u0633 \u0627\u0644\u0643\u0628\u064a\u0631"
    ],
    "name:und_x_variant":[
        "Chabaisi",
        "Kabasi",
        "Al Jab\u0101s al Kab\u012br",
        "Al Jabb\u0101s al Kab\u012br"
    ],
    "wof:name":"Al Jabas al Kabir",
    "wof:placetype":"locality"
},
  "geometry": {"coordinates":[47.81115,30.58147],"type":"Point"}
}