{
  "type": "Feature",
  "properties": {
    "gn:admin1_code":"1.0",
    "gn:admin2_code":"9166579.0",
    "gn:asciiname":"Kurayyah",
    "gn:country_code":"IQ",
    "gn:dem":87,
    "gn:feature_class":"P",
    "gn:feature_code":"PPL",
    "gn:name":"Kurayyah",
    "gn:population":0,
    "gn:timezone":"Asia/Baghdad",
    "iso:country":"IQ",
    "name:ara_x_preferred":[
        "\u0643\u0631\u064a\u0629"
    ],
    "name:und_x_variant":[
        "Qurayyah",
        "Kurayyah"
    ],
    "wof:name":"Kurayyah",
    "wof:placetype":"locality"
},
  "geometry": {"coordinates":[42.54776,33.90325],"type":"Point"}
}