{
  "type": "Feature",
  "properties": {
    "gn:admin1_code":"15.0",
    "gn:admin2_code":"9166649.0",
    "gn:asciiname":"Mankubah al Qadimah",
    "gn:country_code":"IQ",
    "gn:dem":184,
    "gn:feature_class":"P",
    "gn:feature_code":"PPL",
    "gn:name":"Mank\u016bbah al Qad\u012bmah",
    "gn:population":0,
    "gn:timezone":"Asia/Baghdad",
    "iso:country":"IQ",
    "name:ara_x_preferred":[
        "\u0645\u0646\u0643\u0648\u0628\u0629 \u0627\u0644\u0642\u062f\u064a\u0645\u0629"
    ],
    "name:und_x_variant":[
        "Mank\u016bbah al Qad\u012bmah"
    ],
    "wof:name":"Mankubah al Qadimah",
    "wof:placetype":"locality"
},
  "geometry": {"coordinates":[43.33351,35.91172],"type":"Point"}
}