{
  "type": "Feature",
  "properties": {
    "gn:admin1_code":"10.0",
    "gn:admin2_code":"9166680.0",
    "gn:asciiname":"'Abd Ansif Khalil",
    "gn:country_code":"IQ",
    "gn:dem":71,
    "gn:feature_class":"P",
    "gn:feature_code":"PPL",
    "gn:name":"\u2018Abd An\u015f\u012bf Khal\u012bl",
    "gn:population":0,
    "gn:timezone":"Asia/Baghdad",
    "iso:country":"IQ",
    "name:ara_x_preferred":[
        "\u0639\u0628\u062f \u0627\u0646\u0635\u064a\u0641 \u062e\u0644\u064a\u0644"
    ],
    "name:und_x_variant":[
        "\u2018Abd An\u015f\u012bf Khal\u012bl"
    ],
    "wof:name":"'Abd Ansif Khalil",
    "wof:placetype":"locality"
},
  "geometry": {"coordinates":[45.19685,33.94577],"type":"Point"}
}