{
  "type": "Feature",
  "properties": {
    "gn:admin1_code":"1.0",
    "gn:admin2_code":"6765480.0",
    "gn:asciiname":"'Ali Buqan",
    "gn:country_code":"IQ",
    "gn:dem":107,
    "gn:feature_class":"P",
    "gn:feature_code":"PPL",
    "gn:name":"\u2018Al\u012b B\u016bq\u0101n",
    "gn:population":0,
    "gn:timezone":"Asia/Baghdad",
    "iso:country":"IQ",
    "name:ara_x_preferred":[
        "\u0639\u0644\u064a \u0628\u0648\u0642\u0627\u0646"
    ],
    "name:ara_x_variant":[
        "\u2018Al\u012b B\u016bq\u0101n"
    ],
    "wof:name":"'Ali Buqan",
    "wof:placetype":"locality"
},
  "geometry": {"coordinates":[42.37906,34.19591],"type":"Point"}
}