{
  "type": "Feature",
  "properties": {
    "gn:admin1_code":"7.0",
    "gn:admin2_code":"99101.0",
    "gn:asciiname":"Abu Jarbu'",
    "gn:country_code":"IQ",
    "gn:dem":31,
    "gn:feature_class":"P",
    "gn:feature_code":"PPL",
    "gn:name":"Ab\u016b Jarb\u016b\u2018",
    "gn:population":0,
    "gn:timezone":"Asia/Baghdad",
    "iso:country":"IQ",
    "name:ara_x_preferred":[
        "\u0627\u0628\u0648 \u062c\u0631\u0628\u0648\u0639"
    ],
    "name:und_x_variant":[
        "Ab\u016b Jarb\u016b\u2018"
    ],
    "wof:name":"Abu Jarbu'",
    "wof:placetype":"locality"
},
  "geometry": {"coordinates":[44.57185,32.89759],"type":"Point"}
}