{
  "type": "Feature",
  "properties": {
    "gn:admin1_code":"2.0",
    "gn:admin2_code":"9166563.0",
    "gn:asciiname":"Umm az Zahdi",
    "gn:country_code":"IQ",
    "gn:dem":4,
    "gn:feature_class":"P",
    "gn:feature_code":"PPL",
    "gn:name":"Umm az Zahd\u012b",
    "gn:population":0,
    "gn:timezone":"Asia/Baghdad",
    "iso:country":"IQ",
    "name:ara_x_preferred":[
        "\u0627\u0645 \u0627\u0644\u0632\u0647\u062f\u064a"
    ],
    "name:und_x_variant":[
        "Umm az Zahd\u012b"
    ],
    "wof:name":"Umm az Zahdi",
    "wof:placetype":"locality"
},
  "geometry": {"coordinates":[47.22396,31.02291],"type":"Point"}
}