{
  "type": "Feature",
  "properties": {
    "gn:admin1_code":"6.0",
    "gn:admin2_code":"6818313.0",
    "gn:asciiname":"Shadhar al Lami",
    "gn:country_code":"IQ",
    "gn:dem":31,
    "gn:feature_class":"P",
    "gn:feature_code":"PPL",
    "gn:name":"Shadhar al L\u0101m\u012b",
    "gn:population":0,
    "gn:timezone":"Asia/Baghdad",
    "iso:country":"IQ",
    "name:ara_x_preferred":[
        "\u0634\u0630\u0631 \u0627\u0644\u0644\u0627\u0645\u064a"
    ],
    "name:und_x_variant":[
        "Shadhar al L\u0101m\u012b"
    ],
    "wof:name":"Shadhar al Lami",
    "wof:placetype":"locality"
},
  "geometry": {"coordinates":[44.77369,32.72618],"type":"Point"}
}