{
  "type": "Feature",
  "properties": {
    "gn:admin1_code":"6.0",
    "gn:admin2_code":"99358.0",
    "gn:asciiname":"Qaryat al Jubur",
    "gn:country_code":"IQ",
    "gn:dem":27,
    "gn:feature_class":"P",
    "gn:feature_code":"PPL",
    "gn:name":"Qaryat al Jub\u016br",
    "gn:population":0,
    "gn:timezone":"Asia/Baghdad",
    "iso:country":"IQ",
    "name:ara_x_preferred":[
        "\u0642\u0631\u064a\u0629 \u0627\u0644\u062c\u0628\u0648\u0631"
    ],
    "name:und_x_variant":[
        "Qaryat al Jub\u016br"
    ],
    "wof:name":"Qaryat al Jubur",
    "wof:placetype":"locality"
},
  "geometry": {"coordinates":[44.72388,32.36084],"type":"Point"}
}