{
  "type": "Feature",
  "properties": {
    "gn:admin1_code":"7.0",
    "gn:admin2_code":"9166542.0",
    "gn:asciiname":"'Arab Salih",
    "gn:country_code":"IQ",
    "gn:dem":42,
    "gn:feature_class":"P",
    "gn:feature_code":"PPL",
    "gn:name":"\u2018Arab \u015e\u0101li\u1e29",
    "gn:population":0,
    "gn:timezone":"Asia/Baghdad",
    "iso:country":"IQ",
    "name:ara_x_preferred":[
        "\u0639\u0631\u0628 \u0635\u0627\u0644\u062d"
    ],
    "name:und_x_variant":[
        "\u2018Arab \u015e\u0101li\u1e29"
    ],
    "wof:name":"'Arab Salih",
    "wof:placetype":"locality"
},
  "geometry": {"coordinates":[43.92355,33.22412],"type":"Point"}
}