{
  "type": "Feature",
  "properties": {
    "gn:admin1_code":"17.0",
    "gn:admin2_code":"9166629.0",
    "gn:asciiname":"Muhammad 'Abbas",
    "gn:country_code":"IQ",
    "gn:dem":27,
    "gn:feature_class":"P",
    "gn:feature_code":"PPL",
    "gn:name":"Mu\u1e29ammad \u2018Abb\u0101s",
    "gn:population":0,
    "gn:timezone":"Asia/Baghdad",
    "iso:country":"IQ",
    "name:ara_x_preferred":[
        "\u0645\u062d\u0645\u062f \u0639\u0628\u0627\u0633"
    ],
    "name:und_x_variant":[
        "Mu\u1e29ammad \u2018Abb\u0101s"
    ],
    "wof:name":"Muhammad 'Abbas",
    "wof:placetype":"locality"
},
  "geometry": {"coordinates":[44.56168,32.06583],"type":"Point"}
}