{
  "type": "Feature",
  "properties": {
    "gn:admin1_code":"14.0",
    "gn:admin2_code":"99610.0",
    "gn:asciiname":"Mudarras",
    "gn:cc2":"IQ",
    "gn:country_code":"IQ",
    "gn:dem":6,
    "gn:feature_class":"P",
    "gn:feature_code":"PPL",
    "gn:name":"Mudarras",
    "gn:population":0,
    "gn:timezone":"Asia/Baghdad",
    "iso:country":"IQ",
    "name:und_x_variant":[
        "Madarras",
        "Mudarras"
    ],
    "wof:name":"Mudarras",
    "wof:placetype":"locality"
},
  "geometry": {"coordinates":[47.18333,31.85],"type":"Point"}
}