{
  "type": "Feature",
  "properties": {
    "gn:admin1_code":"6.0",
    "gn:admin2_code":"99358.0",
    "gn:asciiname":"'Ubays al 'Ali",
    "gn:country_code":"IQ",
    "gn:dem":25,
    "gn:feature_class":"P",
    "gn:feature_code":"PPL",
    "gn:name":"\u2018Ubays al \u2018Al\u012b",
    "gn:population":0,
    "gn:timezone":"Asia/Baghdad",
    "iso:country":"IQ",
    "name:ara_x_preferred":[
        "\u0639\u0628\u064a\u0633 \u0627\u0644\u0639\u0644\u064a"
    ],
    "name:und_x_variant":[
        "\u2018Ubays al \u2018Al\u012b"
    ],
    "wof:name":"'Ubays al 'Ali",
    "wof:placetype":"locality"
},
  "geometry": {"coordinates":[44.86543,32.36593],"type":"Point"}
}