{
  "type": "Feature",
  "properties": {
    "gn:admin1_code":"14.0",
    "gn:admin2_code":"9166562.0",
    "gn:asciiname":"As Salam",
    "gn:cc2":"IQ",
    "gn:country_code":"IQ",
    "gn:dem":5,
    "gn:feature_class":"P",
    "gn:feature_code":"PPL",
    "gn:name":"As Sal\u0101m",
    "gn:population":0,
    "gn:timezone":"Asia/Baghdad",
    "iso:country":"IQ",
    "name:und_x_variant":[
        "Salam",
        "As Sal\u0101m"
    ],
    "wof:name":"As Salam",
    "wof:placetype":"locality"
},
  "geometry": {"coordinates":[46.93333,31.46667],"type":"Point"}
}