{
  "type": "Feature",
  "properties": {
    "gn:admin1_code":"11.0",
    "gn:admin2_code":"9166592.0",
    "gn:asciiname":"Herute Kewn",
    "gn:country_code":"IQ",
    "gn:dem":1078,
    "gn:feature_class":"P",
    "gn:feature_code":"PPL",
    "gn:name":"Herute Kewn",
    "gn:population":0,
    "gn:timezone":"Asia/Baghdad",
    "iso:country":"IQ",
    "name:ara_x_preferred":[
        "\u0647\u0631\u062a\u0627 \u0643\u0648\u0646"
    ],
    "name:kur_x_preferred":[
        "Herute Kone"
    ],
    "name:kur_x_variant":[
        "\u0647\u06d5\u0631\u0648\u062a\u06d5 \u0643\u06c6\u0646\u06d5",
        "Herute Kewn",
        "\u0647\u06d5\u0631\u0648\u062a\u06d5 \u0643\u06d5\u0648\u0646"
    ],
    "name:und_x_variant":[
        "Haruti\u0101n",
        "Harutiy\u0101n",
        "Hrurta Kuna",
        "Hart\u0101 Kawn",
        "Haruta Kawn",
        "Hahrutah Kawn"
    ],
    "wof:name":"Herute Kewn",
    "wof:placetype":"locality"
},
  "geometry": {"coordinates":[44.49756,36.47045],"type":"Point"}
}