{
  "type": "Feature",
  "properties": {
    "gn:admin1_code":"15.0",
    "gn:admin2_code":"9166649.0",
    "gn:asciiname":"Qaryat Tall ash Shawk",
    "gn:country_code":"IQ",
    "gn:dem":188,
    "gn:feature_class":"P",
    "gn:feature_code":"PPL",
    "gn:name":"Qaryat Tall ash Shawk",
    "gn:population":0,
    "gn:timezone":"Asia/Baghdad",
    "iso:country":"IQ",
    "name:ara_x_preferred":[
        "\u0642\u0631\u064a\u0629 \u062a\u0644 \u0627\u0644\u0634\u0648\u0643"
    ],
    "wof:name":"Qaryat Tall ash Shawk",
    "wof:placetype":"locality"
},
  "geometry": {"coordinates":[43.31918,35.92453],"type":"Point"}
}