{
  "type": "Feature",
  "properties": {
    "gn:admin1_code":"11.0",
    "gn:admin2_code":"95444.0",
    "gn:asciiname":"Kurak as Saghir",
    "gn:country_code":"IQ",
    "gn:dem":687,
    "gn:feature_class":"P",
    "gn:feature_code":"PPL",
    "gn:name":"K\u016brak a\u015f \u015eagh\u012br",
    "gn:population":0,
    "gn:timezone":"Asia/Baghdad",
    "iso:country":"IQ",
    "name:ara_x_preferred":[
        "\u0643\u0648\u0631\u0643 \u0627\u0644\u0635\u063a\u064a\u0631"
    ],
    "name:kur_x_preferred":[
        "Kork"
    ],
    "name:kur_x_variant":[
        "\u0643\u06c6\u0631\u0643"
    ],
    "name:und_x_variant":[
        "K\u016brak a\u015f \u015eagh\u012br"
    ],
    "wof:name":"Kurak as Saghir",
    "wof:placetype":"locality"
},
  "geometry": {"coordinates":[44.1466,36.26396],"type":"Point"}
}