{
  "type": "Feature",
  "properties": {
    "gn:admin1_code":"7.0",
    "gn:admin2_code":"9166542.0",
    "gn:asciiname":"Shaykh Dir' al Muhammad",
    "gn:country_code":"IQ",
    "gn:dem":38,
    "gn:feature_class":"P",
    "gn:feature_code":"PPL",
    "gn:name":"Shaykh Dir\u2018 al Mu\u1e29ammad",
    "gn:population":0,
    "gn:timezone":"Asia/Baghdad",
    "iso:country":"IQ",
    "name:ara_x_preferred":[
        "\u0634\u064a\u062e \u062f\u0631\u0639 \u0627\u0644\u0645\u062d\u0645\u062f"
    ],
    "name:und_x_variant":[
        "Shaykh Dar\u2018ah",
        "Shaykh Dir\u2018 al Mu\u1e29ammad"
    ],
    "wof:name":"Shaykh Dir' al Muhammad",
    "wof:placetype":"locality"
},
  "geometry": {"coordinates":[44.025,33.34834],"type":"Point"}
}