{
  "type": "Feature",
  "properties": {
    "gn:admin1_code":"18.0",
    "gn:admin2_code":"90148.0",
    "gn:asciiname":"Khidr Sultan",
    "gn:country_code":"IQ",
    "gn:dem":154,
    "gn:feature_class":"P",
    "gn:feature_code":"PPL",
    "gn:name":"Khi\u1e11r Sul\u0163\u0101n",
    "gn:population":0,
    "gn:timezone":"Asia/Baghdad",
    "iso:country":"IQ",
    "name:ara_x_preferred":[
        "\u062e\u0636\u0631 \u0633\u0644\u0637\u0627\u0646"
    ],
    "name:ara_x_variant":[
        "Khi\u1e11r Sul\u0163\u0101n"
    ],
    "wof:name":"Khidr Sultan",
    "wof:placetype":"locality"
},
  "geometry": {"coordinates":[43.67471,34.88359000000001],"type":"Point"}
}