{
  "type": "Feature",
  "properties": {
    "gn:admin1_code":"1.0",
    "gn:admin2_code":"98718.0",
    "gn:asciiname":"Qaryat al 'Ankur",
    "gn:country_code":"IQ",
    "gn:dem":58,
    "gn:feature_class":"P",
    "gn:feature_code":"PPL",
    "gn:name":"Qaryat al \u2018Ank\u016br",
    "gn:population":0,
    "gn:timezone":"Asia/Baghdad",
    "iso:country":"IQ",
    "name:ara_x_preferred":[
        "\u0642\u0631\u064a\u0629 \u0627\u0644\u0639\u0646\u0643\u0648\u0631"
    ],
    "name:und_x_variant":[
        "Al-Angor",
        "\u2018Arab \u0100lb\u016b Mar\u2018\u012b",
        "Qaryat al \u2018nk\u016br",
        "\u2018Arab Ab\u016b Mura\u2018\u012b",
        "Qarayat al \u2018Ank\u016br Ab\u016b La\u1e29\u012byah",
        "Qaryat al \u2018Ank\u016br Ab\u016b Li\u1e29yah",
        "\u2018Arab Ab\u016b Mar\u2018\u012b",
        "\u0639\u0631\u0628 \u0627\u0628\u0648 \u0645\u0631\u0639\u064a",
        "\u0642\u0631\u064a\u0629 \u0627\u0644\u0639\u0646\u0643\u0648\u0631 \u0627\u0628\u0648 \u0644\u062d\u064a\u0629",
        "\u0642\u064f\u0631\u064a\u0629 \u0627\u0644\u0639\u0646\u0643\u0648\u0631",
        "Qaryat al \u2018Ank\u016br"
    ],
    "wof:name":"Qaryat al 'Ankur",
    "wof:placetype":"locality"
},
  "geometry": {"coordinates":[43.43202,33.25088],"type":"Point"}
}