{
  "type": "Feature",
  "properties": {
    "gn:admin1_code":"15.0",
    "gn:admin2_code":"98820.0",
    "gn:asciiname":"Marane",
    "gn:country_code":"IQ",
    "gn:dem":743,
    "gn:feature_class":"P",
    "gn:feature_code":"PPL",
    "gn:name":"Marane",
    "gn:population":0,
    "gn:timezone":"Asia/Baghdad",
    "iso:country":"IQ",
    "name:kur_x_preferred":[
        "Me\u1e5fan\u00ea"
    ],
    "name:kur_x_variant":[
        "\u0645\u06d5\u0695\u0627\u0646\u06ce"
    ],
    "wof:name":"Marane",
    "wof:placetype":"locality"
},
  "geometry": {"coordinates":[44.04466,36.7749],"type":"Point"}
}