{
  "type": "Feature",
  "properties": {
    "gn:admin1_code":"8.0",
    "gn:admin2_code":"89569.0",
    "gn:asciiname":"Xuwalish",
    "gn:country_code":"IQ",
    "gn:dem":524,
    "gn:feature_class":"P",
    "gn:feature_code":"PPLF",
    "gn:name":"Xuwalish",
    "gn:population":0,
    "gn:timezone":"Asia/Baghdad",
    "iso:country":"IQ",
    "name:ara_x_preferred":[
        "\u062e\u0648\u0627\u0644\u064a\u0634"
    ],
    "name:ara_x_variant":[
        "Khuw\u0101l\u012bsh"
    ],
    "name:kur_x_preferred":[
        "Xuwal\u00eesh"
    ],
    "name:kur_x_variant":[
        "Xuwalish",
        "\u062e\u0648\u0627\u0644\u0634"
    ],
    "name:und_x_variant":[
        "Khaw\u0101lish",
        "Khalish",
        "Khuwalish"
    ],
    "wof:name":"Xuwalish",
    "wof:placetype":"locality"
},
  "geometry": {"coordinates":[42.7326,37.10979],"type":"Point"}
}