{
  "type": "Feature",
  "properties": {
    "gn:admin1_code":"15.0",
    "gn:admin2_code":"98820.0",
    "gn:asciiname":"Serkevir",
    "gn:country_code":"IQ",
    "gn:dem":493,
    "gn:feature_class":"P",
    "gn:feature_code":"PPL",
    "gn:name":"Serkevir",
    "gn:population":0,
    "gn:timezone":"Asia/Baghdad",
    "iso:country":"IQ",
    "name:kur_x_preferred":[
        "Serkevir"
    ],
    "name:kur_x_variant":[
        "\u0633\u06d5\u0631\u0643\u06d5\u06a4\u0631"
    ],
    "name:und_x_variant":[
        "Sarkavr"
    ],
    "wof:name":"Serkevir",
    "wof:placetype":"locality"
},
  "geometry": {"coordinates":[44.06336,36.85556],"type":"Point"}
}