{
  "type": "Feature",
  "properties": {
    "gn:admin1_code":"13.0",
    "gn:admin2_code":"6770659.0",
    "gn:asciiname":"Qaryat Jar Shilw",
    "gn:country_code":"IQ",
    "gn:dem":166,
    "gn:feature_class":"P",
    "gn:feature_code":"PPL",
    "gn:name":"Qaryat J\u0101r Shilw",
    "gn:population":0,
    "gn:timezone":"Asia/Baghdad",
    "iso:country":"IQ",
    "name:ara_x_preferred":[
        "\u0642\u0631\u064a\u0629 \u062c\u0627\u0631 \u0634\u0644\u0648"
    ],
    "name:und_x_variant":[
        "Al Charshal\u016b",
        "Qaryat J\u0101r Shilw"
    ],
    "wof:name":"Qaryat Jar Shilw",
    "wof:placetype":"locality"
},
  "geometry": {"coordinates":[43.58293,35.25326],"type":"Point"}
}