{
  "type": "Feature",
  "properties": {
    "gn:admin1_code":"11.0",
    "gn:admin2_code":"95444.0",
    "gn:asciiname":"Kirdah Rash As`ad",
    "gn:country_code":"IQ",
    "gn:dem":412,
    "gn:feature_class":"P",
    "gn:feature_code":"PPL",
    "gn:name":"Kirdah Rash As\u2018ad",
    "gn:population":0,
    "gn:timezone":"Asia/Baghdad",
    "iso:country":"IQ",
    "name:ara_x_preferred":[
        "\u0643\u0631\u062f\u0629 \u0631\u0634 \u0627\u0633\u0639\u062f"
    ],
    "name:kur_x_preferred":[
        "Grde \u1e5eesh Es\u2018ed"
    ],
    "name:kur_x_variant":[
        "\u06af\u0631\u062f\u06d5 \u0695\u06d5\u0634 \u0626\u06d5\u0633\u0639\u06d5\u062f"
    ],
    "name:und_x_variant":[
        "Girda Rash Asad",
        "Girdarash Asad",
        "Kirdah Rash As\u2018ad"
    ],
    "wof:name":"Kirdah Rash As`ad",
    "wof:placetype":"locality"
},
  "geometry": {"coordinates":[44.0235,36.09743],"type":"Point"}
}