{
  "type": "Feature",
  "properties": {
    "gn:admin1_code":"5.0",
    "gn:admin2_code":"97416.0",
    "gn:asciiname":"Babekr",
    "gn:country_code":"IQ",
    "gn:dem":407,
    "gn:feature_class":"P",
    "gn:feature_code":"PPL",
    "gn:name":"Babekr",
    "gn:population":0,
    "gn:timezone":"Asia/Baghdad",
    "iso:country":"IQ",
    "name:ara_x_preferred":[
        "\u0628\u0627\u0628\u0643\u0631"
    ],
    "name:kur_x_preferred":[
        "Babekr"
    ],
    "name:kur_x_variant":[
        "Bawekr",
        "\u0628\u0627\u0628\u06d5\u0643\u0631",
        "\u0628\u0627\u0648\u06d5\u0643\u0631"
    ],
    "name:und_x_variant":[
        "B\u0101bakr",
        "Bawakr"
    ],
    "wof:name":"Babekr",
    "wof:placetype":"locality"
},
  "geometry": {"coordinates":[45.04219000000001,34.98619],"type":"Point"}
}