{
  "type": "Feature",
  "properties": {
    "gn:admin1_code":"3.0",
    "gn:admin2_code":"9166626.0",
    "gn:asciiname":"Abu Dishah",
    "gn:country_code":"IQ",
    "gn:dem":10,
    "gn:feature_class":"P",
    "gn:feature_code":"PPL",
    "gn:name":"Ab\u016b D\u012bshah",
    "gn:population":0,
    "gn:timezone":"Asia/Baghdad",
    "iso:country":"IQ",
    "name:ara_x_preferred":[
        "\u0627\u0628\u0648 \u062f\u064a\u0634\u0629"
    ],
    "name:und_x_variant":[
        "Ab\u016b D\u012bshah"
    ],
    "wof:name":"Abu Dishah",
    "wof:placetype":"locality"
},
  "geometry": {"coordinates":[45.59367,31.19083],"type":"Point"}
}