{
  "type": "Feature",
  "properties": {
    "gn:admin1_code":"18.0",
    "gn:admin2_code":"6783103.0",
    "gn:asciiname":"Saba' al Ahmad",
    "gn:country_code":"IQ",
    "gn:dem":62,
    "gn:feature_class":"P",
    "gn:feature_code":"PPL",
    "gn:name":"Saba\u2018 al A\u1e29mad",
    "gn:population":0,
    "gn:timezone":"Asia/Baghdad",
    "iso:country":"IQ",
    "name:ara_x_preferred":[
        "\u0633\u0628\u0639 \u0627\u0644\u0627\u062d\u0645\u062f"
    ],
    "name:und_x_variant":[
        "Saba\u2018 al A\u1e29mad"
    ],
    "wof:name":"Saba' al Ahmad",
    "wof:placetype":"locality"
},
  "geometry": {"coordinates":[44.02982,34.25595999999999],"type":"Point"}
}