{
  "type": "Feature",
  "properties": {
    "gn:admin1_code":"18.0",
    "gn:admin2_code":"6872046.0",
    "gn:asciiname":"Muhammad Rashid",
    "gn:country_code":"IQ",
    "gn:dem":122,
    "gn:feature_class":"P",
    "gn:feature_code":"PPL",
    "gn:name":"Mu\u1e29ammad Rash\u012bd",
    "gn:population":0,
    "gn:timezone":"Asia/Baghdad",
    "iso:country":"IQ",
    "name:ara_x_preferred":[
        "\u0645\u062d\u0645\u062f \u0631\u0634\u064a\u062f"
    ],
    "name:und_x_variant":[
        "Mu\u1e29ammad Rash\u012bd"
    ],
    "wof:name":"Muhammad Rashid",
    "wof:placetype":"locality"
},
  "geometry": {"coordinates":[43.1848,34.68258],"type":"Point"}
}