{
  "type": "Feature",
  "properties": {
    "gn:admin1_code":"7.0",
    "gn:admin2_code":"99101.0",
    "gn:asciiname":"'Arab Muhammad 'Ali Khalaf",
    "gn:country_code":"IQ",
    "gn:dem":37,
    "gn:feature_class":"P",
    "gn:feature_code":"PPL",
    "gn:name":"\u2018Arab Mu\u1e29ammad \u2018Al\u012b Khalaf",
    "gn:population":0,
    "gn:timezone":"Asia/Baghdad",
    "iso:country":"IQ",
    "name:ara_x_preferred":[
        "\u0639\u0631\u0628 \u0645\u062d\u0645\u062f \u0639\u0644\u064a \u062e\u0644\u0641"
    ],
    "name:und_x_variant":[
        "\u2018Arab Mu\u1e29ammad \u2018Al\u012b Khalaf"
    ],
    "wof:name":"'Arab Muhammad 'Ali Khalaf",
    "wof:placetype":"locality"
},
  "geometry": {"coordinates":[44.41587,33.1542],"type":"Point"}
}