{
  "type": "Feature",
  "properties": {
    "gn:admin1_code":"15.0",
    "gn:admin2_code":"9166649.0",
    "gn:asciiname":"Qaryat Tarti'ah",
    "gn:country_code":"IQ",
    "gn:dem":219,
    "gn:feature_class":"P",
    "gn:feature_code":"PPL",
    "gn:name":"Qaryat \u0162ar\u0163\u012b\u2018ah",
    "gn:population":0,
    "gn:timezone":"Asia/Baghdad",
    "iso:country":"IQ",
    "name:ara_x_preferred":[
        "\u0642\u0631\u064a\u0629 \u0637\u0631\u0637\u064a\u0639\u0629"
    ],
    "name:und_x_variant":[
        "Qaryat \u0162ar\u0163\u012b\u2018ah"
    ],
    "wof:name":"Qaryat Tarti'ah",
    "wof:placetype":"locality"
},
  "geometry": {"coordinates":[43.14746,35.80882000000001],"type":"Point"}
}