{
  "type": "Feature",
  "properties": {
    "gn:admin1_code":"2.0",
    "gn:admin2_code":"100049.0",
    "gn:asciiname":"Qows",
    "gn:country_code":"IQ",
    "gn:dem":0,
    "gn:feature_class":"P",
    "gn:feature_code":"PPL",
    "gn:name":"Qows",
    "gn:population":0,
    "gn:timezone":"Asia/Baghdad",
    "iso:country":"IQ",
    "name:fas_x_preferred":[
        "\u0642\u0648\u0633"
    ],
    "name:und_x_variant":[
        "Qaryat K\u0101ws",
        "Q\u0101us",
        "Qaws",
        "Qows"
    ],
    "wof:name":"Qows",
    "wof:placetype":"locality"
},
  "geometry": {"coordinates":[48.1001,30.4339],"type":"Point"}
}