{
  "type": "Feature",
  "properties": {
    "gn:admin1_code":"7.0",
    "gn:admin2_code":"9166569.0",
    "gn:asciiname":"Harish al 'Awwad",
    "gn:country_code":"IQ",
    "gn:dem":37,
    "gn:feature_class":"P",
    "gn:feature_code":"PPL",
    "gn:name":"\u1e28ar\u012bsh al \u2018Aww\u0101d",
    "gn:population":0,
    "gn:timezone":"Asia/Baghdad",
    "iso:country":"IQ",
    "name:ara_x_preferred":[
        "\u062d\u0631\u064a\u0634 \u0627\u0644\u0639\u0648\u0627\u062f"
    ],
    "name:und_x_variant":[
        "\u1e28ar\u012bsh al \u2018Aww\u0101d"
    ],
    "wof:name":"Harish al 'Awwad",
    "wof:placetype":"locality"
},
  "geometry": {"coordinates":[44.25841,33.64474000000001],"type":"Point"}
}