{
  "type": "Feature",
  "properties": {
    "gn:admin1_code":"2.0",
    "gn:admin2_code":"100049.0",
    "gn:asciiname":"Mir'abul",
    "gn:country_code":"IQ",
    "gn:dem":0,
    "gn:feature_class":"P",
    "gn:feature_code":"PPL",
    "gn:name":"M\u012br\u2018ab\u016bl",
    "gn:population":0,
    "gn:timezone":"Asia/Baghdad",
    "iso:country":"IQ",
    "name:und_x_variant":[
        "M\u012br\u2018ab\u016bl"
    ],
    "wof:name":"Mir'abul",
    "wof:placetype":"locality"
},
  "geometry": {"coordinates":[48.17528,30.40194],"type":"Point"}
}