{
  "type": "Feature",
  "properties": {
    "gn:admin1_code":"6.0",
    "gn:admin2_code":"99040.0",
    "gn:asciiname":"Qaryat al Maythur",
    "gn:country_code":"IQ",
    "gn:dem":39,
    "gn:feature_class":"P",
    "gn:feature_code":"PPL",
    "gn:name":"Qaryat al Mayth\u016br",
    "gn:population":0,
    "gn:timezone":"Asia/Baghdad",
    "iso:country":"IQ",
    "name:ara_x_preferred":[
        "\u0642\u0631\u064a\u0629 \u0627\u0644\u0645\u064a\u062b\u0648\u0631"
    ],
    "name:und_x_variant":[
        "Qaryat al Mayth\u016br"
    ],
    "wof:name":"Qaryat al Maythur",
    "wof:placetype":"locality"
},
  "geometry": {"coordinates":[44.32121,32.69323],"type":"Point"}
}