{
  "type": "Feature",
  "properties": {
    "gn:admin1_code":"18.0",
    "gn:admin2_code":"6872046.0",
    "gn:asciiname":"'Askar an Nayif",
    "gn:country_code":"IQ",
    "gn:dem":145,
    "gn:feature_class":"P",
    "gn:feature_code":"PPL",
    "gn:name":"\u2018Askar an N\u0101yif",
    "gn:population":0,
    "gn:timezone":"Asia/Baghdad",
    "iso:country":"IQ",
    "name:ara_x_preferred":[
        "\u0639\u0633\u0643\u0631 \u0627\u0644\u0646\u0627\u064a\u0641"
    ],
    "name:und_x_variant":[
        "\u2018Askar an N\u0101yif"
    ],
    "wof:name":"'Askar an Nayif",
    "wof:placetype":"locality"
},
  "geometry": {"coordinates":[43.42428,34.90811],"type":"Point"}
}