{
  "type": "Feature",
  "properties": {
    "gn:admin1_code":"18.0",
    "gn:admin2_code":"6872046.0",
    "gn:asciiname":"'Ubayd ar Raghal",
    "gn:country_code":"IQ",
    "gn:dem":210,
    "gn:feature_class":"P",
    "gn:feature_code":"PPL",
    "gn:name":"\u2018Ubayd ar Raghal",
    "gn:population":0,
    "gn:timezone":"Asia/Baghdad",
    "iso:country":"IQ",
    "name:ara_x_preferred":[
        "\u0639\u0628\u064a\u062f \u0627\u0644\u0631\u063a\u0644"
    ],
    "name:und_x_variant":[
        "\u2018Ubayd ar Raghal"
    ],
    "wof:name":"'Ubayd ar Raghal",
    "wof:placetype":"locality"
},
  "geometry": {"coordinates":[43.22771,35.26933],"type":"Point"}
}