{
  "type": "Feature",
  "properties": {
    "gn:admin1_code":"14.0",
    "gn:admin2_code":"99610.0",
    "gn:asciiname":"Ad Da'irayat",
    "gn:country_code":"IQ",
    "gn:dem":9,
    "gn:feature_class":"P",
    "gn:feature_code":"PPL",
    "gn:name":"Ad Da\u2018\u012bray\u0101t",
    "gn:population":0,
    "gn:timezone":"Asia/Baghdad",
    "iso:country":"IQ",
    "name:ara_x_preferred":[
        "\u0627\u0644\u062f\u0639\u064a\u0631\u064a\u0627\u062a"
    ],
    "name:und_x_variant":[
        "Ad Da\u2018\u012bray\u0101t"
    ],
    "wof:name":"Ad Da'irayat",
    "wof:placetype":"locality"
},
  "geometry": {"coordinates":[47.41534,31.81787000000001],"type":"Point"}
}