{
  "type": "Feature",
  "properties": {
    "gn:admin1_code":"18.0",
    "gn:admin2_code":"6783103.0",
    "gn:asciiname":"Sattar Turki",
    "gn:country_code":"IQ",
    "gn:dem":69,
    "gn:feature_class":"P",
    "gn:feature_code":"PPL",
    "gn:name":"Satt\u0101r Turk\u012b",
    "gn:population":0,
    "gn:timezone":"Asia/Baghdad",
    "iso:country":"IQ",
    "name:ara_x_preferred":[
        "\u0633\u062a\u0627\u0631 \u062a\u0631\u0643\u064a"
    ],
    "name:und_x_variant":[
        "Satt\u0101r Turk\u012b"
    ],
    "wof:name":"Sattar Turki",
    "wof:placetype":"locality"
},
  "geometry": {"coordinates":[43.8026,34.33049],"type":"Point"}
}