{
  "type": "Feature",
  "properties": {
    "gn:admin1_code":"10.0",
    "gn:admin2_code":"94296.0",
    "gn:asciiname":"Chwarshakh",
    "gn:country_code":"IQ",
    "gn:dem":424,
    "gn:feature_class":"P",
    "gn:feature_code":"PPL",
    "gn:name":"Chw\u0101rsh\u0101kh",
    "gn:population":0,
    "gn:timezone":"Asia/Baghdad",
    "iso:country":"IQ",
    "name:ara_x_preferred":[
        "Chw\u0101rsh\u0101kh"
    ],
    "wof:name":"Chwarshakh",
    "wof:placetype":"locality"
},
  "geometry": {"coordinates":[44.98333,34.83333],"type":"Point"}
}