{
  "type": "Feature",
  "properties": {
    "gn:admin1_code":"18.0",
    "gn:admin2_code":"6805736.0",
    "gn:asciiname":"'Arab Sinjar",
    "gn:country_code":"IQ",
    "gn:dem":49,
    "gn:feature_class":"P",
    "gn:feature_code":"PPL",
    "gn:name":"\u2018Arab Sinj\u0101r",
    "gn:population":0,
    "gn:timezone":"Asia/Baghdad",
    "iso:country":"IQ",
    "name:ara_x_preferred":[
        "\u0639\u0631\u0628 \u0633\u0646\u062c\u0627\u0631"
    ],
    "name:und_x_variant":[
        "\u2018Arab Sinj\u0101r"
    ],
    "wof:name":"'Arab Sinjar",
    "wof:placetype":"locality"
},
  "geometry": {"coordinates":[44.14564,34.05787],"type":"Point"}
}