{
  "type": "Feature",
  "properties": {
    "gn:admin1_code":"7.0",
    "gn:admin2_code":"9166569.0",
    "gn:asciiname":"Hamad al Mahmud",
    "gn:country_code":"IQ",
    "gn:dem":37,
    "gn:feature_class":"P",
    "gn:feature_code":"PPL",
    "gn:name":"\u1e28am\u0101d al Ma\u1e29m\u016bd",
    "gn:population":0,
    "gn:timezone":"Asia/Baghdad",
    "iso:country":"IQ",
    "name:ara_x_preferred":[
        "\u062d\u0645\u0627\u062f \u0627\u0644\u0645\u062d\u0645\u0648\u062f"
    ],
    "name:und_x_variant":[
        "\u1e28am\u0101d al Ma\u1e29m\u016bd"
    ],
    "wof:name":"Hamad al Mahmud",
    "wof:placetype":"locality"
},
  "geometry": {"coordinates":[44.31099,33.73368],"type":"Point"}
}