{
  "type": "Feature",
  "properties": {
    "gn:admin1_code":"8.0",
    "gn:admin2_code":"99612.0",
    "gn:asciiname":"Geleka",
    "gn:country_code":"IQ",
    "gn:dem":649,
    "gn:feature_class":"P",
    "gn:feature_code":"PPL",
    "gn:name":"Geleka",
    "gn:population":0,
    "gn:timezone":"Asia/Baghdad",
    "iso:country":"IQ",
    "name:ara_x_preferred":[
        "\u06af\u0627\u0644\u0643\u0648"
    ],
    "name:ara_x_variant":[
        "G\u0101lk\u016b"
    ],
    "name:kur_x_preferred":[
        "Galko"
    ],
    "name:kur_x_variant":[
        "\u06af\u0627\u0644\u0643\u06c6",
        "Geleka",
        "\u06af\u06d5\u0644\u06d5\u0643\u0627"
    ],
    "name:und_x_variant":[
        "K\u0101lk\u016b",
        "\u0643\u0627\u0644\u0643\u0648",
        "Galaka",
        "Z\u00eabar\u00ea",
        "Zebare",
        "Gund\u00ea Geleka"
    ],
    "wof:name":"Geleka",
    "wof:placetype":"locality"
},
  "geometry": {"coordinates":[43.6426,37.04081],"type":"Point"}
}