{
  "type": "Feature",
  "properties": {
    "gn:admin1_code":"10.0",
    "gn:admin2_code":"9166680.0",
    "gn:asciiname":"Shukr Hamud",
    "gn:country_code":"IQ",
    "gn:dem":43,
    "gn:feature_class":"P",
    "gn:feature_code":"PPL",
    "gn:name":"Shukr \u1e28am\u016bd",
    "gn:population":0,
    "gn:timezone":"Asia/Baghdad",
    "iso:country":"IQ",
    "name:ara_x_preferred":[
        "\u0634\u0643\u0631 \u062d\u0645\u0648\u062f"
    ],
    "name:und_x_variant":[
        "Shukr \u1e28am\u016bd"
    ],
    "wof:name":"Shukr Hamud",
    "wof:placetype":"locality"
},
  "geometry": {"coordinates":[44.83358,33.60252],"type":"Point"}
}