{
  "type": "Feature",
  "properties": {
    "gn:admin1_code":"5.0",
    "gn:admin2_code":"96204.0",
    "gn:asciiname":"Khakilan",
    "gn:country_code":"IQ",
    "gn:dem":745,
    "gn:feature_class":"P",
    "gn:feature_code":"PPL",
    "gn:name":"Kh\u0101k\u012bl\u0101n",
    "gn:population":0,
    "gn:timezone":"Asia/Baghdad",
    "iso:country":"IQ",
    "name:ara_x_preferred":[
        "Kh\u0101k\u012bl\u0101n"
    ],
    "name:ara_x_variant":[
        "\u062e\u0627\u0643\u064a\u0644\u0627\u0646"
    ],
    "name:kur_x_preferred":[
        "Xerg\u00eelan"
    ],
    "name:kur_x_variant":[
        "Xag\u00ealan",
        "\u062e\u06d5\u0631\u06af\u064a\u0644\u0627\u0646",
        "\u062e\u0627\u06af\u06ce\u0644\u0627\u0646"
    ],
    "name:und_x_variant":[
        "\u1e28\u0101j\u012b L\u0101n",
        "Kh\u0101g\u012blan",
        "Khagillan",
        "Khargelan"
    ],
    "wof:name":"Khakilan",
    "wof:placetype":"locality"
},
  "geometry": {"coordinates":[46.05591,35.2428],"type":"Point"}
}