{
  "type": "Feature",
  "properties": {
    "gn:admin1_code":"8.0",
    "gn:admin2_code":"99612.0",
    "gn:asciiname":"Hemeza",
    "gn:country_code":"IQ",
    "gn:dem":803,
    "gn:feature_class":"P",
    "gn:feature_code":"PPL",
    "gn:name":"Hemeza",
    "gn:population":0,
    "gn:timezone":"Asia/Baghdad",
    "iso:country":"IQ",
    "name:ara_x_preferred":[
        "\u0647\u0645\u0632\u0627\u0646"
    ],
    "name:kur_x_preferred":[
        "Hemzan"
    ],
    "name:kur_x_variant":[
        "\u0647\u06d5\u0645\u0632\u0627\u0646",
        "Hemeza",
        "\u0647\u06d5\u0645\u06d5\u0632\u0627"
    ],
    "name:und_x_variant":[
        "Hamzan",
        "Hamz\u0101n"
    ],
    "wof:name":"Hemeza",
    "wof:placetype":"locality"
},
  "geometry": {"coordinates":[43.16588,37.11874],"type":"Point"}
}