{
  "type": "Feature",
  "properties": {
    "gn:admin1_code":"10.0",
    "gn:admin2_code":"9166680.0",
    "gn:asciiname":"'Abd as Sattar ash Shatb",
    "gn:country_code":"IQ",
    "gn:dem":41,
    "gn:feature_class":"P",
    "gn:feature_code":"PPL",
    "gn:name":"\u2018Abd as Satt\u0101r ash Sha\u0163b",
    "gn:population":0,
    "gn:timezone":"Asia/Baghdad",
    "iso:country":"IQ",
    "name:ara_x_preferred":[
        "\u0639\u0628\u062f \u0627\u0644\u0633\u062a\u0627\u0631 \u0627\u0644\u0634\u0637\u0628"
    ],
    "name:und_x_variant":[
        "Kar\u012bm Shatib",
        "\u2018Abd as Satt\u0101r ash Sha\u0163b"
    ],
    "wof:name":"'Abd as Sattar ash Shatb",
    "wof:placetype":"locality"
},
  "geometry": {"coordinates":[45.03407,33.65157],"type":"Point"}
}