{
  "type": "Feature",
  "properties": {
    "gn:admin1_code":"15.0",
    "gn:admin2_code":"9166608.0",
    "gn:asciiname":"As Sahrij",
    "gn:country_code":"IQ",
    "gn:dem":304,
    "gn:feature_class":"P",
    "gn:feature_code":"PPL",
    "gn:name":"A\u015f \u015eahr\u012bj",
    "gn:population":0,
    "gn:timezone":"Asia/Baghdad",
    "iso:country":"IQ",
    "name:ara_x_preferred":[
        "\u0627\u0644\u0635\u0647\u0631\u064a\u062c"
    ],
    "name:und_x_variant":[
        "A\u015f \u015eahr\u012bj"
    ],
    "wof:name":"As Sahrij",
    "wof:placetype":"locality"
},
  "geometry": {"coordinates":[41.75715,36.00693],"type":"Point"}
}