{
  "type": "Feature",
  "properties": {
    "gn:admin1_code":"12.0",
    "gn:admin2_code":"99345.0",
    "gn:asciiname":"Qaryat al Kamuniyah",
    "gn:country_code":"IQ",
    "gn:dem":32,
    "gn:feature_class":"P",
    "gn:feature_code":"PPL",
    "gn:name":"Qaryat al Kam\u016bn\u012byah",
    "gn:population":0,
    "gn:timezone":"Asia/Baghdad",
    "iso:country":"IQ",
    "name:ara_x_preferred":[
        "\u0642\u0631\u064a\u0629 \u0627\u0644\u0643\u0645\u0648\u0646\u064a\u0647"
    ],
    "name:und_x_variant":[
        "Qaryat al Kam\u016bn\u012byah"
    ],
    "wof:name":"Qaryat al Kamuniyah",
    "wof:placetype":"locality"
},
  "geometry": {"coordinates":[44.2214,32.64677],"type":"Point"}
}