{
  "type": "Feature",
  "properties": {
    "gn:admin1_code":"7.0",
    "gn:admin2_code":"9166545.0",
    "gn:asciiname":"Qal'at Hamid al Habash",
    "gn:country_code":"IQ",
    "gn:dem":35,
    "gn:feature_class":"P",
    "gn:feature_code":"PPL",
    "gn:name":"Qal\u2018at \u1e28am\u012bd al \u1e28abash",
    "gn:population":0,
    "gn:timezone":"Asia/Baghdad",
    "iso:country":"IQ",
    "name:und_x_variant":[
        "Qal\u2018a Ham\u012bd al Habash",
        "Qal\u2018at \u1e28am\u012bd al \u1e28abash"
    ],
    "wof:name":"Qal'at Hamid al Habash",
    "wof:placetype":"locality"
},
  "geometry": {"coordinates":[44.36335,33.23041],"type":"Point"}
}