{
  "type": "Feature",
  "properties": {
    "gn:admin1_code":"15.0",
    "gn:admin2_code":"9166649.0",
    "gn:asciiname":"Qaryat 'Ayn al Baydah",
    "gn:country_code":"IQ",
    "gn:dem":283,
    "gn:feature_class":"P",
    "gn:feature_code":"PPL",
    "gn:name":"Qaryat \u2018Ayn al Bay\u1e11ah",
    "gn:population":0,
    "gn:timezone":"Asia/Baghdad",
    "iso:country":"IQ",
    "name:ara_x_preferred":[
        "\u0642\u0631\u064a\u0629 \u0639\u064a\u0646 \u0627\u0644\u0628\u064a\u0636\u0629"
    ],
    "name:und_x_variant":[
        "Qaryat \u2018Ayn al Bay\u1e11ah"
    ],
    "wof:name":"Qaryat 'Ayn al Baydah",
    "wof:placetype":"locality"
},
  "geometry": {"coordinates":[43.05283,36.01023],"type":"Point"}
}