{
  "type": "Feature",
  "properties": {
    "gn:admin1_code":"7.0",
    "gn:admin2_code":"9166569.0",
    "gn:asciiname":"Hamadi al Hamad",
    "gn:country_code":"IQ",
    "gn:dem":39,
    "gn:feature_class":"P",
    "gn:feature_code":"PPL",
    "gn:name":"\u1e28am\u0101d\u012b al \u1e28amad",
    "gn:population":0,
    "gn:timezone":"Asia/Baghdad",
    "iso:country":"IQ",
    "name:ara_x_preferred":[
        "\u062d\u0645\u0627\u062f\u064a \u0627\u0644\u062d\u0645\u062f"
    ],
    "name:und_x_variant":[
        "\u1e28am\u0101d\u012b al \u1e28amad"
    ],
    "wof:name":"Hamadi al Hamad",
    "wof:placetype":"locality"
},
  "geometry": {"coordinates":[44.25367,33.6091],"type":"Point"}
}