{
  "type": "Feature",
  "properties": {
    "gn:admin1_code":"16.0",
    "gn:admin2_code":"98460.0",
    "gn:asciiname":"Qaryat al Jamahir ath Thalithah",
    "gn:country_code":"IQ",
    "gn:dem":30,
    "gn:feature_class":"P",
    "gn:feature_code":"PPL",
    "gn:name":"Qaryat al Jam\u0101h\u012br ath Th\u0101lithah",
    "gn:population":0,
    "gn:timezone":"Asia/Baghdad",
    "iso:country":"IQ",
    "name:ara_x_preferred":[
        "\u0642\u0631\u064a\u0629 \u0627\u0644\u062c\u0645\u0627\u0647\u064a\u0631 \u0627\u0644\u062b\u0627\u0644\u062b\u0629"
    ],
    "name:und_x_variant":[
        "Qaryat al Jam\u0101h\u012br ath Th\u0101lithah"
    ],
    "wof:name":"Qaryat al Jamahir ath Thalithah",
    "wof:placetype":"locality"
},
  "geometry": {"coordinates":[44.65695,32.86149],"type":"Point"}
}