{
  "type": "Feature",
  "properties": {
    "gn:admin1_code":"14.0",
    "gn:admin2_code":"99610.0",
    "gn:asciiname":"Salaf Kamil Muhammad",
    "gn:country_code":"IQ",
    "gn:dem":9,
    "gn:feature_class":"P",
    "gn:feature_code":"PPL",
    "gn:name":"Salaf K\u0101mil Mu\u1e29ammad",
    "gn:population":0,
    "gn:timezone":"Asia/Baghdad",
    "iso:country":"IQ",
    "name:ara_x_preferred":[
        "\u0633\u0644\u0641 \u0643\u0627\u0645\u0644 \u0645\u062d\u0645\u062f"
    ],
    "name:und_x_variant":[
        "Salaf K\u0101mil Mu\u1e29ammad"
    ],
    "wof:name":"Salaf Kamil Muhammad",
    "wof:placetype":"locality"
},
  "geometry": {"coordinates":[46.73841,31.82813],"type":"Point"}
}