{
  "type": "Feature",
  "properties": {
    "gn:admin1_code":"5.0",
    "gn:asciiname":"Kutaban",
    "gn:country_code":"IQ",
    "gn:dem":766,
    "gn:feature_class":"P",
    "gn:feature_code":"PPL",
    "gn:name":"K\u016btab\u0101n",
    "gn:population":0,
    "gn:timezone":"Asia/Baghdad",
    "iso:country":"IQ",
    "name:ara_x_preferred":[
        "\u0643\u0648\u062a\u0628\u0627\u0646"
    ],
    "name:und_x_variant":[
        "K\u016btah B\u0101n",
        "Kutab\u0101n",
        "K\u016btab\u0101n"
    ],
    "wof:name":"Kutaban",
    "wof:placetype":"locality"
},
  "geometry": {"coordinates":[44.79068,35.39816],"type":"Point"}
}