{
  "type": "Feature",
  "properties": {
    "gn:admin1_code":"11.0",
    "gn:admin2_code":"95444.0",
    "gn:asciiname":"Biwkah",
    "gn:country_code":"IQ",
    "gn:dem":845,
    "gn:feature_class":"P",
    "gn:feature_code":"PPL",
    "gn:name":"B\u012bwkah",
    "gn:population":0,
    "gn:timezone":"Asia/Baghdad",
    "iso:country":"IQ",
    "name:ara_x_preferred":[
        "\u0628\u064a\u0648\u0643\u0629"
    ],
    "name:ara_x_variant":[
        "\u0628\u064a\u0631\u0643\u0629"
    ],
    "name:kur_x_preferred":[
        "B\u00eewke"
    ],
    "name:kur_x_variant":[
        "\u0628\u064a\u0648\u0643\u06d5"
    ],
    "name:und_x_variant":[
        "Beuka",
        "Biy\u016bkah",
        "B\u012bwkah",
        "B\u012brkah"
    ],
    "wof:name":"Biwkah",
    "wof:placetype":"locality"
},
  "geometry": {"coordinates":[44.21369,36.18914],"type":"Point"}
}