{
  "type": "Feature",
  "properties": {
    "gn:admin1_code":"11.0",
    "gn:admin2_code":"9166586.0",
    "gn:asciiname":"Kawayrtik",
    "gn:country_code":"IQ",
    "gn:dem":1210,
    "gn:feature_class":"P",
    "gn:feature_code":"PPL",
    "gn:name":"Kawayrtik",
    "gn:population":0,
    "gn:timezone":"Asia/Baghdad",
    "iso:country":"IQ",
    "name:ara_x_preferred":[
        "\u0643\u0648\u064a\u0631\u062a\u0643"
    ],
    "name:kur_x_preferred":[
        "Cizl\u00eenge"
    ],
    "name:kur_x_variant":[
        "\u062c\u0632\u0644\u064a\u0646\u06af\u06d5"
    ],
    "name:und_x_variant":[
        "Guw\u012bzlangah",
        "Kortik",
        "Gwizlinga"
    ],
    "wof:name":"Kawayrtik",
    "wof:placetype":"locality"
},
  "geometry": {"coordinates":[44.73741,36.63252],"type":"Point"}
}