{
  "type": "Feature",
  "properties": {
    "gn:admin1_code":"4.0",
    "gn:admin2_code":"6850588.0",
    "gn:asciiname":"Al Hajji",
    "gn:country_code":"IQ",
    "gn:dem":15,
    "gn:feature_class":"P",
    "gn:feature_code":"PPL",
    "gn:name":"\u0100l \u1e28\u0101jj\u012b",
    "gn:population":0,
    "gn:timezone":"Asia/Baghdad",
    "iso:country":"IQ",
    "name:ara_x_preferred":[
        "\u0627\u0644 \u062d\u0627\u062c\u064a"
    ],
    "name:ara_x_variant":[
        "\u0100l \u1e28\u0101jj\u012b"
    ],
    "wof:name":"Al Hajji",
    "wof:placetype":"locality"
},
  "geometry": {"coordinates":[44.99381,31.60749],"type":"Point"}
}