{
  "type": "Feature",
  "properties": {
    "gn:admin1_code":"8.0",
    "gn:admin2_code":"9166607.0",
    "gn:asciiname":"Tall Zayn",
    "gn:country_code":"IQ",
    "gn:dem":456,
    "gn:feature_class":"P",
    "gn:feature_code":"PPL",
    "gn:name":"Tall Zayn",
    "gn:population":0,
    "gn:timezone":"Asia/Baghdad",
    "iso:country":"IQ",
    "name:ara_x_preferred":[
        "\u062a\u0644 \u0632\u064a\u0646"
    ],
    "name:kur_x_preferred":[
        "Tilz\u00eat"
    ],
    "name:kur_x_variant":[
        "\u062a\u0644\u0632\u06ce\u062a",
        "Tel Z\u00ead",
        "\u062a\u06d5\u0644 \u0632\u06ce\u062f"
    ],
    "name:und_x_variant":[
        "Tal Zet"
    ],
    "wof:name":"Tall Zayn",
    "wof:placetype":"locality"
},
  "geometry": {"coordinates":[42.77736,36.8982],"type":"Point"}
}