{
  "type": "Feature",
  "properties": {
    "gn:admin1_code":"17.0",
    "gn:admin2_code":"9166629.0",
    "gn:asciiname":"Al 'Abir",
    "gn:country_code":"IQ",
    "gn:dem":27,
    "gn:feature_class":"P",
    "gn:feature_code":"PPL",
    "gn:name":"\u0100l \u2018\u0100bir",
    "gn:population":0,
    "gn:timezone":"Asia/Baghdad",
    "iso:country":"IQ",
    "name:ara_x_preferred":[
        "\u0627\u0644 \u0639\u0627\u0628\u0631"
    ],
    "name:ara_x_variant":[
        "\u0100l \u2018\u0100bir"
    ],
    "wof:name":"Al 'Abir",
    "wof:placetype":"locality"
},
  "geometry": {"coordinates":[44.3534,32.12241],"type":"Point"}
}