{
  "type": "Feature",
  "properties": {
    "gn:admin1_code":"6.0",
    "gn:admin2_code":"99358.0",
    "gn:asciiname":"Majid",
    "gn:country_code":"IQ",
    "gn:dem":26,
    "gn:feature_class":"P",
    "gn:feature_code":"PPL",
    "gn:name":"M\u0101jid",
    "gn:population":0,
    "gn:timezone":"Asia/Baghdad",
    "iso:country":"IQ",
    "name:ara_x_preferred":[
        "\u0645\u0627\u062c\u062f"
    ],
    "name:ara_x_variant":[
        "M\u0101jid"
    ],
    "wof:name":"Majid",
    "wof:placetype":"locality"
},
  "geometry": {"coordinates":[44.6451,32.22548],"type":"Point"}
}