{
  "type": "Feature",
  "properties": {
    "gn:admin1_code":"5.0",
    "gn:admin2_code":"91176.0",
    "gn:asciiname":"Satar Darreh",
    "gn:country_code":"IQ",
    "gn:dem":1119,
    "gn:feature_class":"P",
    "gn:feature_code":"PPL",
    "gn:name":"Satar Darreh",
    "gn:population":0,
    "gn:timezone":"Asia/Baghdad",
    "iso:country":"IQ",
    "name:fas_x_preferred":[
        "\u0633\u062a\u0631\u062f\u0631\u0651\u0647"
    ],
    "wof:name":"Satar Darreh",
    "wof:placetype":"locality"
},
  "geometry": {"coordinates":[45.8001,35.5847],"type":"Point"}
}