{
  "type": "Feature",
  "properties": {
    "gn:admin1_code":"14.0",
    "gn:admin2_code":"9166562.0",
    "gn:asciiname":"Salaf Shiya' al Fahd",
    "gn:country_code":"IQ",
    "gn:dem":9,
    "gn:feature_class":"P",
    "gn:feature_code":"PPL",
    "gn:name":"Salaf Sh\u012by\u0101\u2018 al Fahd",
    "gn:population":0,
    "gn:timezone":"Asia/Baghdad",
    "iso:country":"IQ",
    "name:ara_x_preferred":[
        "\u0633\u0644\u0641 \u0634\u064a\u0627\u0639 \u0627\u0644\u0641\u0647\u062f"
    ],
    "name:und_x_variant":[
        "Salaf Sh\u012by\u0101\u2018 al Fahd"
    ],
    "wof:name":"Salaf Shiya' al Fahd",
    "wof:placetype":"locality"
},
  "geometry": {"coordinates":[46.96764,31.65953],"type":"Point"}
}