{
  "type": "Feature",
  "properties": {
    "gn:admin1_code":"14.0",
    "gn:admin2_code":"99610.0",
    "gn:asciiname":"Salaf Shaykh Sadij",
    "gn:country_code":"IQ",
    "gn:dem":9,
    "gn:feature_class":"P",
    "gn:feature_code":"PPL",
    "gn:name":"Salaf Shaykh \u015e\u0101dij",
    "gn:population":0,
    "gn:timezone":"Asia/Baghdad",
    "iso:country":"IQ",
    "name:ara_x_preferred":[
        "\u0633\u0644\u0641 \u0634\u064a\u062e \u0635\u0627\u062f\u062c"
    ],
    "name:und_x_variant":[
        "Salaf Shaykh \u015e\u0101dij"
    ],
    "wof:name":"Salaf Shaykh Sadij",
    "wof:placetype":"locality"
},
  "geometry": {"coordinates":[47.45265,31.78356],"type":"Point"}
}