{
  "type": "Feature",
  "properties": {
    "gn:admin1_code":"5.0",
    "gn:admin2_code":"9166684.0",
    "gn:asciiname":"Maysharaw",
    "gn:country_code":"IQ",
    "gn:dem":1534,
    "gn:feature_class":"P",
    "gn:feature_code":"PPL",
    "gn:name":"Maysharaw",
    "gn:population":0,
    "gn:timezone":"Asia/Baghdad",
    "iso:country":"IQ",
    "name:ara_x_preferred":[
        "\u0645\u064a\u0634\u0631\u0648"
    ],
    "name:kur_x_preferred":[
        "M\u00eashe\u1e5fo"
    ],
    "name:kur_x_variant":[
        "Mush\u00eare",
        "\u0645\u06ce\u0634\u06d5\u0695\u06c6",
        "\u0645\u0648\u0634\u06ce\u0631\u06d5"
    ],
    "name:und_x_variant":[
        "Mush\u012brah",
        "M\u012bshar\u016b",
        "M\u016bsh\u012br\u0101w",
        "Mashirwah",
        "\u0645\u0634\u0631\u0648\u0647",
        "Mosherau",
        "Maysharaw",
        "Moshera",
        "Mayshirwah",
        "\u0645\u064a\u0634\u0631\u0648\u0647"
    ],
    "wof:name":"Maysharaw",
    "wof:placetype":"locality"
},
  "geometry": {"coordinates":[45.84684,35.80485],"type":"Point"}
}