{
  "type": "Feature",
  "properties": {
    "gn:admin1_code":"10.0",
    "gn:admin2_code":"97988.0",
    "gn:asciiname":"'Ali al Matar",
    "gn:country_code":"IQ",
    "gn:dem":41,
    "gn:feature_class":"P",
    "gn:feature_code":"PPL",
    "gn:name":"\u2018Al\u012b al Ma\u0163ar",
    "gn:population":0,
    "gn:timezone":"Asia/Baghdad",
    "iso:country":"IQ",
    "name:ara_x_preferred":[
        "\u0639\u0644\u064a \u0627\u0644\u0645\u0637\u0631"
    ],
    "name:und_x_variant":[
        "\u2018Al\u012b al Ma\u0163ar"
    ],
    "wof:name":"'Ali al Matar",
    "wof:placetype":"locality"
},
  "geometry": {"coordinates":[44.47318,33.52528],"type":"Point"}
}