{
  "type": "Feature",
  "properties": {
    "gn:admin1_code":"6.0",
    "gn:admin2_code":"6818313.0",
    "gn:asciiname":"Musa Husayn",
    "gn:country_code":"IQ",
    "gn:dem":33,
    "gn:feature_class":"P",
    "gn:feature_code":"PPL",
    "gn:name":"M\u016bs\u00e1 \u1e28usayn",
    "gn:population":0,
    "gn:timezone":"Asia/Baghdad",
    "iso:country":"IQ",
    "name:ara_x_preferred":[
        "\u0645\u0648\u0633\u0649 \u062d\u0633\u064a\u0646"
    ],
    "name:und_x_variant":[
        "M\u016bs\u00e1 \u1e28usayn"
    ],
    "wof:name":"Musa Husayn",
    "wof:placetype":"locality"
},
  "geometry": {"coordinates":[44.57611,32.74440999999999],"type":"Point"}
}