{
  "type": "Feature",
  "properties": {
    "gn:admin1_code":"18.0",
    "gn:admin2_code":"6805736.0",
    "gn:asciiname":"Makinat al Urfali",
    "gn:country_code":"IQ",
    "gn:dem":54,
    "gn:feature_class":"P",
    "gn:feature_code":"PPL",
    "gn:name":"M\u0101kinat al Urfal\u012b",
    "gn:population":0,
    "gn:timezone":"Asia/Baghdad",
    "iso:country":"IQ",
    "name:und_x_variant":[
        "M\u0101kinat al Urfal\u012b"
    ],
    "wof:name":"Makinat al Urfali",
    "wof:placetype":"locality"
},
  "geometry": {"coordinates":[44.01667,34.0675],"type":"Point"}
}