{
  "type": "Feature",
  "properties": {
    "gn:admin1_code":"13.0",
    "gn:admin2_code":"6770659.0",
    "gn:asciiname":"'Aziz Ansif",
    "gn:country_code":"IQ",
    "gn:dem":176,
    "gn:feature_class":"P",
    "gn:feature_code":"PPL",
    "gn:name":"\u2018Az\u012bz An\u015f\u012bf",
    "gn:population":0,
    "gn:timezone":"Asia/Baghdad",
    "iso:country":"IQ",
    "name:ara_x_preferred":[
        "\u0639\u0632\u064a\u0632 \u0627\u0646\u0635\u064a\u0641"
    ],
    "name:ara_x_variant":[
        "\u2018Az\u012bz An\u015f\u012bf"
    ],
    "wof:name":"'Aziz Ansif",
    "wof:placetype":"locality"
},
  "geometry": {"coordinates":[43.95398,35.12692],"type":"Point"}
}