{
  "type": "Feature",
  "properties": {
    "gn:admin1_code":"16.0",
    "gn:admin2_code":"9166606.0",
    "gn:asciiname":"'Abbud al Husayn",
    "gn:country_code":"IQ",
    "gn:dem":20,
    "gn:feature_class":"P",
    "gn:feature_code":"PPL",
    "gn:name":"\u2018Abb\u016bd al \u1e28usayn",
    "gn:population":0,
    "gn:timezone":"Asia/Baghdad",
    "iso:country":"IQ",
    "name:ara_x_preferred":[
        "\u0639\u0628\u0648\u062f \u0627\u0644\u062d\u0633\u064a\u0646"
    ],
    "name:und_x_variant":[
        "\u2018Ub\u016bd al \u1e28usayn",
        "\u2018Ub\u016bd al Husain",
        "\u2018Abd al \u1e28usayn",
        "\u2018Abb\u016bd al \u1e28usayn"
    ],
    "wof:name":"'Abbud al Husayn",
    "wof:placetype":"locality"
},
  "geometry": {"coordinates":[45.64534,32.49533],"type":"Point"}
}