{
  "type": "Feature",
  "properties": {
    "gn:admin1_code":"15.0",
    "gn:admin2_code":"98820.0",
    "gn:asciiname":"Mamurin",
    "gn:country_code":"IQ",
    "gn:dem":354,
    "gn:feature_class":"P",
    "gn:feature_code":"PPL",
    "gn:name":"Mamurin",
    "gn:population":0,
    "gn:timezone":"Asia/Baghdad",
    "iso:country":"IQ",
    "name:ara_x_preferred":[
        "\u0645\u0627\u0645\u0648\u0632\u064a\u0646"
    ],
    "name:ara_x_variant":[
        "M\u0101m\u016bz\u012bn"
    ],
    "name:kur_x_preferred":[
        "Memuz\u00een"
    ],
    "name:kur_x_variant":[
        "\u0645\u06d5\u0645\u0648\u0632\u064a\u0646"
    ],
    "name:und_x_variant":[
        "M\u0101mozin",
        "Mamurin",
        "Mamuzin"
    ],
    "wof:name":"Mamurin",
    "wof:placetype":"locality"
},
  "geometry": {"coordinates":[43.62009000000001,36.54543],"type":"Point"}
}