{
  "type": "Feature",
  "properties": {
    "gn:admin1_code":"11.0",
    "gn:admin2_code":"9166592.0",
    "gn:asciiname":"Mawetawe",
    "gn:country_code":"IQ",
    "gn:dem":1112,
    "gn:feature_class":"P",
    "gn:feature_code":"PPL",
    "gn:name":"Mawetawe",
    "gn:population":0,
    "gn:timezone":"Asia/Baghdad",
    "iso:country":"IQ",
    "name:ara_x_preferred":[
        "\u0645\u0627\u0648\u062a\u0627\u0648\u06d5 \u0633\u0641\u0644\u0649"
    ],
    "name:kur_x_preferred":[
        "Mawetawe"
    ],
    "name:kur_x_variant":[
        "\u0645\u0627\u0648\u06d5\u062a\u0627\u0648\u06d5",
        "Mawet Awa",
        "\u0645\u0627\u0648\u06d5\u062a \u0626\u0627\u0648\u0627"
    ],
    "name:und_x_variant":[
        "M\u0101wat\u0101wah Sufl\u00e1",
        "M\u0101wat\u0101w\u0101 Zh\u0113r\u012b",
        "Mawat Awa",
        "Mawatawa Lower"
    ],
    "wof:name":"Mawetawe",
    "wof:placetype":"locality"
},
  "geometry": {"coordinates":[44.70789,36.81464],"type":"Point"}
}