{
  "type": "Feature",
  "properties": {
    "gn:admin1_code":"4.0",
    "gn:admin2_code":"98634.0",
    "gn:asciiname":"Maluh Sultan",
    "gn:country_code":"IQ",
    "gn:dem":18,
    "gn:feature_class":"P",
    "gn:feature_code":"PPL",
    "gn:name":"Mal\u016b\u1e29 Sul\u0163\u0101n",
    "gn:population":0,
    "gn:timezone":"Asia/Baghdad",
    "iso:country":"IQ",
    "name:ara_x_preferred":[
        "\u0645\u0644\u0648\u062d \u0633\u0644\u0637\u0627\u0646"
    ],
    "name:und_x_variant":[
        "Mal\u016b\u1e29 Sul\u0163\u0101n"
    ],
    "wof:name":"Maluh Sultan",
    "wof:placetype":"locality"
},
  "geometry": {"coordinates":[44.63069,31.75349000000001],"type":"Point"}
}