{
  "type": "Feature",
  "properties": {
    "gn:admin1_code":"18.0",
    "gn:admin2_code":"90148.0",
    "gn:asciiname":"Qaryat Albu 'Ajil",
    "gn:country_code":"IQ",
    "gn:dem":83,
    "gn:feature_class":"P",
    "gn:feature_code":"PPL",
    "gn:name":"Qaryat \u0100lb\u016b \u2018Aj\u012bl",
    "gn:population":0,
    "gn:timezone":"Asia/Baghdad",
    "iso:country":"IQ",
    "name:ara_x_preferred":[
        "\u0642\u0631\u064a\u0629 \u0627\u0644\u0628\u0648 \u0639\u062c\u064a\u0644"
    ],
    "name:und_x_variant":[
        "Qaryat \u0100lb\u016b \u2018Aj\u012bl"
    ],
    "wof:name":"Qaryat Albu 'Ajil",
    "wof:placetype":"locality"
},
  "geometry": {"coordinates":[43.72209,34.57414],"type":"Point"}
}