{
  "type": "Feature",
  "properties": {
    "gn:admin1_code":"4.0",
    "gn:admin2_code":"6850588.0",
    "gn:asciiname":"Kawwam 'Isa",
    "gn:country_code":"IQ",
    "gn:dem":19,
    "gn:feature_class":"P",
    "gn:feature_code":"PPL",
    "gn:name":"Kaww\u0101m \u2018\u012as\u00e1",
    "gn:population":0,
    "gn:timezone":"Asia/Baghdad",
    "iso:country":"IQ",
    "name:ara_x_preferred":[
        "\u0643\u0648\u0627\u0645 \u0639\u064a\u0633\u0649"
    ],
    "name:und_x_variant":[
        "Kaww\u0101m \u2018\u012as\u00e1"
    ],
    "wof:name":"Kawwam 'Isa",
    "wof:placetype":"locality"
},
  "geometry": {"coordinates":[44.71811,31.65018],"type":"Point"}
}