{
  "type": "Feature",
  "properties": {
    "gn:admin1_code":"5.0",
    "gn:admin2_code":"92051.0",
    "gn:asciiname":"Swera",
    "gn:country_code":"IQ",
    "gn:dem":771,
    "gn:feature_class":"P",
    "gn:feature_code":"PPL",
    "gn:name":"Swera",
    "gn:population":0,
    "gn:timezone":"Asia/Baghdad",
    "iso:country":"IQ",
    "name:kur_x_preferred":[
        "\u0633\u0648\u06ce\u0631\u06d5"
    ],
    "name:kur_x_variant":[
        "Sw\u00eare"
    ],
    "name:und_x_variant":[
        "S\u0113w\u0113rah",
        "Suw\u0113ra",
        "Swera"
    ],
    "wof:name":"Swera",
    "wof:placetype":"locality"
},
  "geometry": {"coordinates":[44.57847,36.37456],"type":"Point"}
}