{
  "type": "Feature",
  "properties": {
    "gn:admin1_code":"14.0",
    "gn:admin2_code":"99305.0",
    "gn:asciiname":"Qaryat Hasan Subhi",
    "gn:country_code":"IQ",
    "gn:dem":12,
    "gn:feature_class":"P",
    "gn:feature_code":"PPL",
    "gn:name":"Qaryat \u1e28asan \u015eub\u1e29\u012b",
    "gn:population":0,
    "gn:timezone":"Asia/Baghdad",
    "iso:country":"IQ",
    "name:ara_x_preferred":[
        "\u0642\u0631\u064a\u0629 \u062d\u0633\u0646 \u0635\u0628\u062d\u064a"
    ],
    "name:und_x_variant":[
        "Qaryat \u1e28asan \u015eub\u1e29\u012b"
    ],
    "wof:name":"Qaryat Hasan Subhi",
    "wof:placetype":"locality"
},
  "geometry": {"coordinates":[46.53073,32.5235],"type":"Point"}
}