{
  "type": "Feature",
  "properties": {
    "gn:admin1_code":"7.0",
    "gn:admin2_code":"9179819.0",
    "gn:asciiname":"Husayn al Latif",
    "gn:country_code":"IQ",
    "gn:dem":37,
    "gn:feature_class":"P",
    "gn:feature_code":"PPL",
    "gn:name":"\u1e28usayn al La\u0163\u012bf",
    "gn:population":0,
    "gn:timezone":"Asia/Baghdad",
    "iso:country":"IQ",
    "name:und_x_variant":[
        "Husain al Latif",
        "\u1e28usayn al La\u0163\u012bf"
    ],
    "wof:name":"Husayn al Latif",
    "wof:placetype":"locality"
},
  "geometry": {"coordinates":[44.54611,33.27167],"type":"Point"}
}