{
  "type": "Feature",
  "properties": {
    "gn:admin1_code":"11.0",
    "gn:admin2_code":"9166586.0",
    "gn:asciiname":"Chawman",
    "gn:country_code":"IQ",
    "gn:dem":840,
    "gn:feature_class":"P",
    "gn:feature_code":"PPL",
    "gn:name":"Chawm\u0101n",
    "gn:population":0,
    "gn:timezone":"Asia/Baghdad",
    "iso:country":"IQ",
    "name:ara_x_preferred":[
        "\u0686\u0648\u0645\u0627\u0646"
    ],
    "name:ara_x_variant":[
        "\u0627\u0633\u0645\u0627\u0639\u064a\u0644 \u0622\u063a\u0627"
    ],
    "name:kur_x_preferred":[
        "Choman\u00ee Simayil Agha"
    ],
    "name:kur_x_variant":[
        "\u0686\u06c6\u0645\u0627\u0646\u0649 \u0633\u0645\u0627\u064a\u0644 \u0626\u0627\u063a\u0627",
        "Choman",
        "\u0686\u06c6\u0645\u0627\u0646"
    ],
    "name:und_x_variant":[
        "Guman",
        "Chawm\u0101n",
        "Ch\u014dm\u0101n",
        "Ch\u014dm\u0101n Esmael",
        "Ism\u0101\u2018\u012bl \u0100gh\u0101",
        "Choman Esmael",
        "Choman Smail Agha"
    ],
    "wof:name":"Chawman",
    "wof:placetype":"locality"
},
  "geometry": {"coordinates":[44.70308,36.65908],"type":"Point"}
}