{
  "type": "Feature",
  "properties": {
    "gn:admin1_code":"18.0",
    "gn:admin2_code":"6783103.0",
    "gn:asciiname":"Albu Razuqi",
    "gn:country_code":"IQ",
    "gn:dem":64,
    "gn:feature_class":"P",
    "gn:feature_code":"PPL",
    "gn:name":"Alb\u016b Raz\u016bq\u012b",
    "gn:population":0,
    "gn:timezone":"Asia/Baghdad",
    "iso:country":"IQ",
    "name:ara_x_preferred":[
        "\u0627\u0644\u0628\u0648 \u0631\u0632\u0648\u0642\u064a"
    ],
    "name:und_x_variant":[
        "Alb\u016b Raz\u016bq\u012b"
    ],
    "wof:name":"Albu Razuqi",
    "wof:placetype":"locality"
},
  "geometry": {"coordinates":[44.32355,34.27114],"type":"Point"}
}