{
  "type": "Feature",
  "properties": {
    "gn:admin1_code":"14.0",
    "gn:admin2_code":"9166562.0",
    "gn:asciiname":"Salaf Sayyid Hatim",
    "gn:country_code":"IQ",
    "gn:dem":7,
    "gn:feature_class":"P",
    "gn:feature_code":"PPL",
    "gn:name":"Salaf Sayyid \u1e28\u0101tim",
    "gn:population":0,
    "gn:timezone":"Asia/Baghdad",
    "iso:country":"IQ",
    "name:ara_x_preferred":[
        "\u0633\u0644\u0641 \u0633\u064a\u062f \u062d\u0627\u062a\u0645"
    ],
    "name:und_x_variant":[
        "Salaf Sayyid \u1e28\u0101tim"
    ],
    "wof:name":"Salaf Sayyid Hatim",
    "wof:placetype":"locality"
},
  "geometry": {"coordinates":[46.9211,31.63502],"type":"Point"}
}