{
  "type": "Feature",
  "properties": {
    "gn:admin1_code":"9.0",
    "gn:admin2_code":"98855.0",
    "gn:asciiname":"Al Hamran",
    "gn:country_code":"IQ",
    "gn:dem":6,
    "gn:feature_class":"P",
    "gn:feature_code":"PPL",
    "gn:name":"Al \u1e28amr\u0101n",
    "gn:population":0,
    "gn:timezone":"Asia/Baghdad",
    "iso:country":"IQ",
    "name:ara_x_preferred":[
        "\u0627\u0644\u062d\u0645\u0631\u0627\u0646"
    ],
    "name:und_x_variant":[
        "Yas\u012bn al Hamr\u0101n",
        "Al \u1e28amrah",
        "Al Hamra",
        "Al \u1e28amr\u0101n"
    ],
    "wof:name":"Al Hamran",
    "wof:placetype":"locality"
},
  "geometry": {"coordinates":[46.44088,31.17103],"type":"Point"}
}