{
  "type": "Feature",
  "properties": {
    "gn:admin1_code":"17.0",
    "gn:admin2_code":"9166629.0",
    "gn:asciiname":"Qaryat Umm Rafash",
    "gn:country_code":"IQ",
    "gn:dem":27,
    "gn:feature_class":"P",
    "gn:feature_code":"PPL",
    "gn:name":"Qaryat Umm Rafash",
    "gn:population":0,
    "gn:timezone":"Asia/Baghdad",
    "iso:country":"IQ",
    "name:ara_x_preferred":[
        "\u0642\u0631\u064a\u0629 \u0623\u0645 \u0631\u0641\u0634"
    ],
    "wof:name":"Qaryat Umm Rafash",
    "wof:placetype":"locality"
},
  "geometry": {"coordinates":[44.55289000000001,32.08996],"type":"Point"}
}