{
  "type": "Feature",
  "properties": {
    "gn:admin1_code":"14.0",
    "gn:admin2_code":"99097.0",
    "gn:asciiname":"Salaf Laftat 'Uklah",
    "gn:country_code":"IQ",
    "gn:dem":8,
    "gn:feature_class":"P",
    "gn:feature_code":"PPL",
    "gn:name":"Salaf Laftat \u2018Uklah",
    "gn:population":0,
    "gn:timezone":"Asia/Baghdad",
    "iso:country":"IQ",
    "name:ara_x_preferred":[
        "\u0633\u0644\u0641 \u0644\u0641\u062a\u0629 \u0639\u0643\u0644\u0629"
    ],
    "name:und_x_variant":[
        "\u2018Uqlah",
        "Sayyid \u2018Aql",
        "Saiyid Uqlah",
        "Sayyid \u2018Uqlah",
        "Salaf Laftat \u2018Uklah"
    ],
    "wof:name":"Salaf Laftat 'Uklah",
    "wof:placetype":"locality"
},
  "geometry": {"coordinates":[47.26725,31.57737],"type":"Point"}
}