{
  "type": "Feature",
  "properties": {
    "gn:admin1_code":"18.0",
    "gn:admin2_code":"91594.0",
    "gn:asciiname":"Qaryat ad Dahiri",
    "gn:country_code":"IQ",
    "gn:dem":63,
    "gn:feature_class":"P",
    "gn:feature_code":"PPL",
    "gn:name":"Qaryat ad D\u0101hir\u012b",
    "gn:population":0,
    "gn:timezone":"Asia/Baghdad",
    "iso:country":"IQ",
    "name:ara_x_preferred":[
        "\u0642\u0631\u064a\u0629 \u0627\u0644\u062f\u0627\u0647\u0631\u064a"
    ],
    "name:ara_x_variant":[
        "\u0627\u0644\u062f\u0627\u0647\u0631\u064a"
    ],
    "name:und_x_variant":[
        "Qaryat ad D\u0101hir\u012b",
        "Al Dahri",
        "Ad D\u0101hir\u012b"
    ],
    "wof:name":"Qaryat ad Dahiri",
    "wof:placetype":"locality"
},
  "geometry": {"coordinates":[43.85665,34.15693],"type":"Point"}
}