{
  "type": "Feature",
  "properties": {
    "gn:admin1_code":"6.0",
    "gn:admin2_code":"99358.0",
    "gn:asciiname":"Hatim 'Abd 'Ali",
    "gn:country_code":"IQ",
    "gn:dem":24,
    "gn:feature_class":"P",
    "gn:feature_code":"PPL",
    "gn:name":"\u1e28\u0101tim \u2018Abd \u2018Al\u012b",
    "gn:population":0,
    "gn:timezone":"Asia/Baghdad",
    "iso:country":"IQ",
    "name:ara_x_preferred":[
        "\u062d\u0627\u062a\u0645 \u0639\u0628\u062f \u0639\u0644\u064a"
    ],
    "name:ara_x_variant":[
        "\u1e28\u0101tim \u2018Abd \u2018Al\u012b"
    ],
    "wof:name":"Hatim 'Abd 'Ali",
    "wof:placetype":"locality"
},
  "geometry": {"coordinates":[44.88041,32.36454000000001],"type":"Point"}
}