{
  "type": "Feature",
  "properties": {
    "gn:admin1_code":"4.0",
    "gn:admin2_code":"99737.0",
    "gn:asciiname":"Jamil",
    "gn:country_code":"IQ",
    "gn:dem":21,
    "gn:feature_class":"P",
    "gn:feature_code":"PPL",
    "gn:name":"Jam\u012bl",
    "gn:population":0,
    "gn:timezone":"Asia/Baghdad",
    "iso:country":"IQ",
    "name:aze_x_preferred":[
        "C\u0259mil"
    ],
    "name:cat_x_preferred":[
        "Jamil"
    ],
    "name:deu_x_preferred":[
        "Dscham\u012bl"
    ],
    "name:fra_x_preferred":[
        "Jamil"
    ],
    "name:ita_x_preferred":[
        "Jamil"
    ],
    "name:pol_x_preferred":[
        "D\u017cemil"
    ],
    "name:por_x_preferred":[
        "Jamil"
    ],
    "name:rus_x_preferred":[
        "\u0414\u0436\u0430\u043c\u0438\u043b\u044c"
    ],
    "wof:name":"Jamil",
    "wof:placetype":"locality"
},
  "geometry": {"coordinates":[45.16667,32.06667],"type":"Point"}
}