{
  "type": "Feature",
  "properties": {
    "gn:admin1_code":"4.0",
    "gn:admin2_code":"98634.0",
    "gn:asciiname":"Jalal Abu Khirbah",
    "gn:country_code":"IQ",
    "gn:dem":23,
    "gn:feature_class":"P",
    "gn:feature_code":"PPL",
    "gn:name":"Jal\u0101l Ab\u016b Khirbah",
    "gn:population":0,
    "gn:timezone":"Asia/Baghdad",
    "iso:country":"IQ",
    "name:ara_x_preferred":[
        "\u062c\u0644\u0627\u0644 \u0627\u0628\u0648 \u062e\u0631\u0628\u0629"
    ],
    "name:und_x_variant":[
        "Jal\u0101l Ab\u016b Khirbah"
    ],
    "wof:name":"Jalal Abu Khirbah",
    "wof:placetype":"locality"
},
  "geometry": {"coordinates":[44.61569,31.89928],"type":"Point"}
}