{
  "type": "Feature",
  "properties": {
    "gn:admin1_code":"7.0",
    "gn:admin2_code":"9179819.0",
    "gn:asciiname":"Tall Abu Tamarah",
    "gn:country_code":"IQ",
    "gn:dem":36,
    "gn:feature_class":"P",
    "gn:feature_code":"PPL",
    "gn:name":"Tall Ab\u016b Tam\u0101rah",
    "gn:population":0,
    "gn:timezone":"Asia/Baghdad",
    "iso:country":"IQ",
    "name:ara_x_preferred":[
        "\u062a\u0644 \u0627\u0628\u0648 \u062a\u0645\u0627\u0631\u0629"
    ],
    "name:und_x_variant":[
        "Tall Ab\u016b Tam\u0101rah"
    ],
    "wof:name":"Tall Abu Tamarah",
    "wof:placetype":"locality"
},
  "geometry": {"coordinates":[44.71646,33.2899],"type":"Point"}
}