{
  "type": "Feature",
  "properties": {
    "iso:country":"IQ",
    "name:ara_x_colloquial":[
        "Abbas Hayy Al",
        "Abbas, Hayy Al"
    ],
    "name:ara_x_preferred":[
        "\u2018abb\u0101s H\u0327ayy Al"
    ],
    "name:ara_x_variant":[
        "\u2018abbas Hayy Al",
        "\u2018abbas, Hayy Al",
        "\u2018abb\u0101s, H\u0327ayy Al"
    ],
    "qs:gn_adm0_cc":"IQ",
    "qs:gn_local":94824,
    "qs:gn_nam_loc":"Karbala, Kerbala, Kerbela, IQ",
    "qs:gn_namadm1":"12",
    "qs:local_max":4,
    "qs:local_sum":4,
    "qs:localhoods":1,
    "qs:name":"\u2018abb\u0101s H\u0327ayy Al",
    "qs:name_adm0":"Iraq",
    "qs:name_adm1":"Karbala'",
    "qs:name_adm2":"Kerbala",
    "qs:name_local":"Kerbela",
    "qs:photo_max":4,
    "qs:photo_sum":4,
    "qs:placetype":"Suburb",
    "qs:quad_count":1,
    "qs:woe_adm0":23424855,
    "qs:woe_adm1":2345844,
    "qs:woe_adm2":55999986,
    "qs:woe_lau":0,
    "qs:woe_local":1979497,
    "qs:woe_ver":"7.10.0",
    "wof:lang":[
        "ara"
    ],
    "wof:name":"\u2018abb\u0101s H\u0327ayy Al",
    "wof:placetype":"neighbourhood"
},
  "geometry": {"coordinates":[44.03595,32.618557],"type":"Point"}
}