{
  "type": "Feature",
  "properties": {
    "gn:admin1_code":"15.0",
    "gn:admin2_code":"9166541.0",
    "gn:asciiname":"Qaryat Ba'wizah",
    "gn:country_code":"IQ",
    "gn:dem":265,
    "gn:feature_class":"P",
    "gn:feature_code":"PPL",
    "gn:name":"Qaryat Ba\u2018w\u012bzah",
    "gn:population":0,
    "gn:timezone":"Asia/Baghdad",
    "iso:country":"IQ",
    "name:ara_x_preferred":[
        "\u0642\u0631\u064a\u0629 \u0628\u0639\u0648\u064a\u0632\u0629"
    ],
    "name:und_x_variant":[
        "Qaryat Ba\u2018w\u012bdawah",
        "Ba\u2018w\u012bzah",
        "Qaryat Ba\u2018w\u012bdah",
        "\u0642\u0631\u064a\u0629 \u0628\u0639\u0648\u064a\u062f\u0648\u0629",
        "\u0642\u0631\u064a\u0629 \u0628\u0639\u0648\u064a\u062f\u0629",
        "Qaryat Ba\u2018w\u012bzah"
    ],
    "wof:name":"Qaryat Ba'wizah",
    "wof:placetype":"locality"
},
  "geometry": {"coordinates":[43.15733,36.43215],"type":"Point"}
}