{
  "type": "Feature",
  "properties": {
    "gn:admin1_code":"6.0",
    "gn:admin2_code":"6818313.0",
    "gn:asciiname":"Qaryat al Mansuri",
    "gn:country_code":"IQ",
    "gn:dem":30,
    "gn:feature_class":"P",
    "gn:feature_code":"PPL",
    "gn:name":"Qaryat al Man\u015f\u016br\u012b",
    "gn:population":0,
    "gn:timezone":"Asia/Baghdad",
    "iso:country":"IQ",
    "name:ara_x_preferred":[
        "\u0642\u0631\u064a\u0629 \u0627\u0644\u0645\u0646\u0635\u0648\u0631\u064a"
    ],
    "name:und_x_variant":[
        "Qaryat al Man\u015f\u016br\u012b"
    ],
    "wof:name":"Qaryat al Mansuri",
    "wof:placetype":"locality"
},
  "geometry": {"coordinates":[44.48224,32.73984],"type":"Point"}
}