{
  "type": "Feature",
  "properties": {
    "gn:admin1_code":"5.0",
    "gn:admin2_code":"97416.0",
    "gn:asciiname":"Shawk ash Shatawiyah",
    "gn:country_code":"IQ",
    "gn:dem":456,
    "gn:feature_class":"P",
    "gn:feature_code":"PPL",
    "gn:name":"Shawk ash Shataw\u012byah",
    "gn:population":0,
    "gn:timezone":"Asia/Baghdad",
    "iso:country":"IQ",
    "name:ara_x_preferred":[
        "\u0634\u0648\u0643 \u0627\u0644\u0634\u062a\u0648\u064a\u0629"
    ],
    "name:und_x_variant":[
        "Shawk ash Shataw\u012byah"
    ],
    "wof:name":"Shawk ash Shatawiyah",
    "wof:placetype":"locality"
},
  "geometry": {"coordinates":[44.92988,35.20708],"type":"Point"}
}