{
  "type": "Feature",
  "properties": {
    "gn:admin1_code":"10.0",
    "gn:admin2_code":"9166680.0",
    "gn:asciiname":"'Arab Bayt 'Adday",
    "gn:country_code":"IQ",
    "gn:dem":43,
    "gn:feature_class":"P",
    "gn:feature_code":"PPL",
    "gn:name":"\u2018Arab Bayt \u2018Add\u0101y",
    "gn:population":0,
    "gn:timezone":"Asia/Baghdad",
    "iso:country":"IQ",
    "name:ara_x_preferred":[
        "\u0639\u0631\u0628 \u0628\u064a\u062a \u0639\u062f\u0627\u064a"
    ],
    "name:und_x_variant":[
        "\u2018Arab Bayt \u2018Add\u0101y"
    ],
    "wof:name":"'Arab Bayt 'Adday",
    "wof:placetype":"locality"
},
  "geometry": {"coordinates":[45.08582,33.64687],"type":"Point"}
}