{
  "type": "Feature",
  "properties": {
    "gn:admin1_code":"5.0",
    "gn:admin2_code":"91176.0",
    "gn:asciiname":"Qulah Kani",
    "gn:country_code":"IQ",
    "gn:dem":1814,
    "gn:feature_class":"P",
    "gn:feature_code":"PPL",
    "gn:name":"Q\u016blah K\u0101n\u012b",
    "gn:population":0,
    "gn:timezone":"Asia/Baghdad",
    "iso:country":"IQ",
    "name:ara_x_preferred":[
        "\u0642\u0648\u0644\u0629 \u0643\u0627\u0646\u064a"
    ],
    "name:kur_x_preferred":[
        "Ku\u0142e Kan\u00ee"
    ],
    "name:kur_x_variant":[
        "Qu\u0142e Kan\u00ee",
        "\u0643\u0648\u06b5\u06d5 \u0643\u0627\u0646\u0649",
        "\u0642\u0648\u06b5\u06d5 \u0643\u0627\u0646\u0649"
    ],
    "name:und_x_variant":[
        "Q\u016blah Kan",
        "\u0642\u0648\u0644\u0629 \u0643\u0646",
        "Q\u016blah K\u0101n\u012b",
        "Kula Kani"
    ],
    "wof:name":"Qulah Kani",
    "wof:placetype":"locality"
},
  "geometry": {"coordinates":[45.53927,35.90119],"type":"Point"}
}