{
  "type": "Feature",
  "properties": {
    "gn:admin1_code":"11.0",
    "gn:admin2_code":"95444.0",
    "gn:asciiname":"Qela Mortke",
    "gn:country_code":"IQ",
    "gn:dem":545,
    "gn:feature_class":"P",
    "gn:feature_code":"PPL",
    "gn:name":"Qe\u0142a Mortke",
    "gn:population":0,
    "gn:timezone":"Asia/Baghdad",
    "iso:country":"IQ",
    "name:ara_x_preferred":[
        "\u0642\u0644\u0629 \u0645\u0648\u062c\u064a\u0627\u0646"
    ],
    "name:kur_x_preferred":[
        "Qe\u0142a Mortke"
    ],
    "name:kur_x_variant":[
        "\u0642\u06d5\u06b5\u0627 \u0645\u06c6\u0631\u062a\u0643\u06d5"
    ],
    "name:und_x_variant":[
        "Qala Mortka",
        "Qallat M\u016bjiy\u0101n"
    ],
    "wof:name":"Qela Mortke",
    "wof:placetype":"locality"
},
  "geometry": {"coordinates":[44.10245,36.35524],"type":"Point"}
}