{
  "type": "Feature",
  "properties": {
    "gn:admin1_code":"14.0",
    "gn:admin2_code":"92536.0",
    "gn:asciiname":"Salaf at Turabah",
    "gn:country_code":"IQ",
    "gn:dem":5,
    "gn:feature_class":"P",
    "gn:feature_code":"PPL",
    "gn:name":"Salaf at Tur\u0101bah",
    "gn:population":0,
    "gn:timezone":"Asia/Baghdad",
    "iso:country":"IQ",
    "name:ara_x_preferred":[
        "\u0633\u0644\u0641 \u0627\u0644\u062a\u0631\u0627\u0628\u0629"
    ],
    "name:fas_x_preferred":[
        "\u062a\u0631\u0627\u0628\u0647"
    ],
    "name:fas_x_variant":[
        "Tor\u0101bh"
    ],
    "name:und_x_variant":[
        "Turabah",
        "Salaf at Tur\u0101bah"
    ],
    "wof:name":"Salaf at Turabah",
    "wof:placetype":"locality"
},
  "geometry": {"coordinates":[47.53193,31.49072],"type":"Point"}
}