{
  "type": "Feature",
  "properties": {
    "gn:admin1_code":"15.0",
    "gn:admin2_code":"9166649.0",
    "gn:asciiname":"Arkabah Gharbiyah",
    "gn:country_code":"IQ",
    "gn:dem":173,
    "gn:feature_class":"P",
    "gn:feature_code":"PPL",
    "gn:name":"Arkabah Gharb\u012byah",
    "gn:population":0,
    "gn:timezone":"Asia/Baghdad",
    "iso:country":"IQ",
    "name:ara_x_preferred":[
        "\u0627\u0631\u0643\u0628\u0629 \u063a\u0631\u0628\u064a\u0629"
    ],
    "name:und_x_variant":[
        "\u2018Aqubah",
        "\u2018Aquwah",
        "\u2018Arg\u016bbah al Gharb\u012byah",
        "\u2018Arkubah al Gharb\u012byah",
        "Arkabah Gharb\u012byah"
    ],
    "wof:name":"Arkabah Gharbiyah",
    "wof:placetype":"locality"
},
  "geometry": {"coordinates":[43.28472,35.76888],"type":"Point"}
}