{
  "type": "Feature",
  "properties": {
    "gn:admin1_code":"9.0",
    "gn:admin2_code":"98855.0",
    "gn:asciiname":"Rahman Albu Karun",
    "gn:country_code":"IQ",
    "gn:dem":9,
    "gn:feature_class":"P",
    "gn:feature_code":"PPL",
    "gn:name":"Ra\u1e29m\u0101n \u0100lb\u016b Kar\u016bn",
    "gn:population":0,
    "gn:timezone":"Asia/Baghdad",
    "iso:country":"IQ",
    "name:ara_x_preferred":[
        "\u0631\u062d\u0645\u0627\u0646 \u0627\u0644\u0628\u0648 \u0643\u0631\u0648\u0646"
    ],
    "name:und_x_variant":[
        "Ra\u1e29m\u0101n \u0100lb\u016b Kar\u016bn"
    ],
    "wof:name":"Rahman Albu Karun",
    "wof:placetype":"locality"
},
  "geometry": {"coordinates":[46.07452,31.10861],"type":"Point"}
}