{
  "type": "Feature",
  "properties": {
    "gn:admin1_code":"13.0",
    "gn:admin2_code":"9171727.0",
    "gn:asciiname":"`Ali Ghayr",
    "gn:country_code":"IQ",
    "gn:dem":234,
    "gn:feature_class":"P",
    "gn:feature_code":"PPL",
    "gn:name":"\u2018Al\u012b Ghayr",
    "gn:population":0,
    "gn:timezone":"Asia/Baghdad",
    "iso:country":"IQ",
    "name:ara_x_preferred":[
        "\u0639\u0644\u064a \u063a\u064a\u0631 \u0633\u064a\u062f \u0627\u062d\u0645\u062f"
    ],
    "name:und_x_variant":[
        "Al\u0101 Ghair Saiyid Ahmad",
        "Saiyid Ahmad",
        "Sayyid A\u1e29mad",
        "\u2018Al\u012b Ghayr",
        "\u0639\u0644\u064a \u063a\u064a\u0631",
        "\u0633\u064a\u062f \u0627\u062d\u0645\u062f",
        "\u2018Al\u012b Ghayr Sayyid A\u1e29mad"
    ],
    "wof:name":"`Ali Ghayr",
    "wof:placetype":"locality"
},
  "geometry": {"coordinates":[43.97217,35.57312],"type":"Point"}
}