{
  "type": "Feature",
  "properties": {
    "gn:admin1_code":"7.0",
    "gn:admin2_code":"99101.0",
    "gn:asciiname":"'Arab Khudayr 'Alaywi",
    "gn:country_code":"IQ",
    "gn:dem":30,
    "gn:feature_class":"P",
    "gn:feature_code":"PPL",
    "gn:name":"\u2018Arab Khu\u1e11ayr \u2018Alayw\u012b",
    "gn:population":0,
    "gn:timezone":"Asia/Baghdad",
    "iso:country":"IQ",
    "name:ara_x_preferred":[
        "\u0639\u0631\u0628 \u062e\u0636\u064a\u0631 \u0639\u0644\u064a\u0648\u064a"
    ],
    "name:und_x_variant":[
        "\u2018Arab Khu\u1e11ayr \u2018Alayw\u012b"
    ],
    "wof:name":"'Arab Khudayr 'Alaywi",
    "wof:placetype":"locality"
},
  "geometry": {"coordinates":[44.49548,32.90539],"type":"Point"}
}