{
  "type": "Feature",
  "properties": {
    "gn:admin1_code":"8.0",
    "gn:admin2_code":"89569.0",
    "gn:asciiname":"Suwriya",
    "gn:country_code":"IQ",
    "gn:dem":894,
    "gn:feature_class":"P",
    "gn:feature_code":"PPL",
    "gn:name":"Suwriya",
    "gn:population":0,
    "gn:timezone":"Asia/Baghdad",
    "iso:country":"IQ",
    "name:ara_x_preferred":[
        "\u0633\u0648\u0631\u064a\u0647"
    ],
    "name:kur_x_preferred":[
        "Surye"
    ],
    "name:kur_x_variant":[
        "\u0633\u0648\u0631\u064a\u06d5",
        "Suwriya",
        "\u0633\u0648\u0648\u0631\u064a\u0627",
        "Sorya",
        "\u0633\u06c6\u0631\u064a\u0627",
        "Gund\u00ea Suriy\u00ea",
        "\u06af\u0648\u0646\u062f\u06ce \u0633\u0648\u0631\u064a\u06ce"
    ],
    "name:und_x_variant":[
        "S\u014driya",
        "Suraya",
        "S\u016br\u012byah",
        "Surya"
    ],
    "wof:name":"Suwriya",
    "wof:placetype":"locality"
},
  "geometry": {"coordinates":[43.07217,37.22626],"type":"Point"}
}