{
  "type": "Feature",
  "properties": {
    "gn:admin1_code":"9.0",
    "gn:admin2_code":"98700.0",
    "gn:asciiname":"Ribat al Jammas",
    "gn:country_code":"IQ",
    "gn:dem":12,
    "gn:feature_class":"P",
    "gn:feature_code":"PPL",
    "gn:name":"Rib\u0101\u0163 al Jamm\u0101s",
    "gn:population":0,
    "gn:timezone":"Asia/Baghdad",
    "iso:country":"IQ",
    "name:ara_x_preferred":[
        "\u0631\u0628\u0627\u0637 \u0627\u0644\u062c\u0645\u0627\u0633"
    ],
    "name:und_x_variant":[
        "Rib\u0101\u0163 al Jamm\u0101s"
    ],
    "wof:name":"Ribat al Jammas",
    "wof:placetype":"locality"
},
  "geometry": {"coordinates":[45.92889,31.88366],"type":"Point"}
}