{
  "type": "Feature",
  "properties": {
    "gn:admin1_code":"1.0",
    "gn:admin2_code":"9166576.0",
    "gn:asciiname":"Laktah",
    "gn:country_code":"IQ",
    "gn:dem":315,
    "gn:feature_class":"P",
    "gn:feature_code":"PPL",
    "gn:name":"Lak\u0163ah",
    "gn:population":0,
    "gn:timezone":"Asia/Baghdad",
    "iso:country":"IQ",
    "name:ara_x_preferred":[
        "\u0644\u0643\u0637\u0629"
    ],
    "name:und_x_variant":[
        "Lak\u0163ah"
    ],
    "wof:name":"Laktah",
    "wof:placetype":"locality"
},
  "geometry": {"coordinates":[41.51981,34.67146],"type":"Point"}
}