{
  "type": "Feature",
  "properties": {
    "gn:admin1_code":"9.0",
    "gn:admin2_code":"98700.0",
    "gn:asciiname":"Rahim al Mani'",
    "gn:country_code":"IQ",
    "gn:dem":11,
    "gn:feature_class":"P",
    "gn:feature_code":"PPL",
    "gn:name":"Ra\u1e29\u012bm al M\u0101ni\u2018",
    "gn:population":0,
    "gn:timezone":"Asia/Baghdad",
    "iso:country":"IQ",
    "name:ara_x_preferred":[
        "\u0631\u062d\u064a\u0645 \u0627\u0644\u0645\u0627\u0646\u0639"
    ],
    "name:und_x_variant":[
        "Qal\u2018at \u1e28\u0101ji M\u0101n\u012b",
        "Qal\u2018a H\u0101ji M\u0101ni",
        "Qal\u2018at \u1e28\u0101jj M\u0101n\u012b",
        "Ra\u1e29\u012bm al M\u0101ni\u2018"
    ],
    "wof:name":"Rahim al Mani'",
    "wof:placetype":"locality"
},
  "geometry": {"coordinates":[46.01461,31.6652],"type":"Point"}
}