{
  "type": "Feature",
  "properties": {
    "gn:admin1_code":"7.0",
    "gn:admin2_code":"9179819.0",
    "gn:asciiname":"Qaryat Raqm Thamaniyah",
    "gn:country_code":"IQ",
    "gn:dem":37,
    "gn:feature_class":"P",
    "gn:feature_code":"PPL",
    "gn:name":"Qaryat Raqm Tham\u0101n\u012byah",
    "gn:population":0,
    "gn:timezone":"Asia/Baghdad",
    "iso:country":"IQ",
    "name:ara_x_preferred":[
        "\u0642\u0631\u064a\u0629 \u0631\u0642\u0645 \u0668"
    ],
    "name:und_x_variant":[
        "Qaryat Raqm Tham\u0101n\u012byah"
    ],
    "wof:name":"Qaryat Raqm Thamaniyah",
    "wof:placetype":"locality"
},
  "geometry": {"coordinates":[44.63823,33.30044],"type":"Point"}
}