{
  "type": "Feature",
  "properties": {
    "gn:admin1_code":"8.0",
    "gn:admin2_code":"97269.0",
    "gn:asciiname":"Kura",
    "gn:country_code":"IQ",
    "gn:dem":940,
    "gn:feature_class":"P",
    "gn:feature_code":"PPL",
    "gn:name":"Kura",
    "gn:population":0,
    "gn:timezone":"Asia/Baghdad",
    "iso:country":"IQ",
    "name:ara_x_preferred":[
        "\u0643\u0648\u0631\u064a \u0643\u0627\u0641\u0627\u0646\u0629"
    ],
    "name:ara_x_variant":[
        "\u0643\u0648\u0631\u064a \u0643\u0627\u06a4\u0627\u0646\u0629"
    ],
    "name:aze_x_preferred":[
        "K\u00fcr"
    ],
    "name:cat_x_preferred":[
        "Kura"
    ],
    "name:ceb_x_preferred":[
        "Kura"
    ],
    "name:deu_x_preferred":[
        "Kura"
    ],
    "name:est_x_preferred":[
        "Kura"
    ],
    "name:fas_x_preferred":[
        "\u06a9\u0648\u0631\u0627"
    ],
    "name:fra_x_preferred":[
        "Kura"
    ],
    "name:hin_x_preferred":[
        "\u0915\u0941\u0930\u093e"
    ],
    "name:ita_x_preferred":[
        "Kura"
    ],
    "name:kur_x_preferred":[
        "Kuri Kavane"
    ],
    "name:kur_x_variant":[
        "\u0643\u0648\u0631\u0649 \u0643\u0627\u06a4\u0627\u0646\u06d5",
        "Kura",
        "\u0643\u0648\u0631\u0627",
        "Kur\u00eat Kavane",
        "\u0643\u0648\u0631\u06ce\u062a \u0643\u0627\u06a4\u0627\u0646\u06d5",
        "Kumelgeha Kur\u00eat Gavane",
        "Kur\u00ee Kavane",
        "\u0643\u0648\u0645\u06d5\u0644\u06af\u06d5\u06be\u0627 \u0643\u0648\u0631\u06ce\u062a \u06af\u0627\u06a4\u0627\u0646\u06d5"
    ],
    "name:lav_x_preferred":[
        "K\u016bra"
    ],
    "name:nld_x_preferred":[
        "Kura"
    ],
    "name:pol_x_preferred":[
        "Kura"
    ],
    "name:slk_x_preferred":[
        "Kura"
    ],
    "name:slv_x_preferred":[
        "Kura"
    ],
    "name:swe_x_preferred":[
        "Kura"
    ],
    "name:und_x_variant":[
        "G\u014dr\u0113g\u0101v\u0101n",
        "Kuri Gavana",
        "K\u016br\u012b K\u0101f\u0101nah",
        "K\u016br\u012b K\u0101v\u0101nah",
        "Kura Kavana",
        "Kuret Gavana Collective",
        "Kuri Kavana"
    ],
    "name:urd_x_preferred":[
        "\u06a9\u0648\u0631\u0627\u0628"
    ],
    "wof:name":"Kura",
    "wof:placetype":"locality"
},
  "geometry": {"coordinates":[43.14855,36.93356],"type":"Point"}
}