{
  "type": "Feature",
  "properties": {
    "gn:admin1_code":"5.0",
    "gn:admin2_code":"9166600.0",
    "gn:asciiname":"Qala Raywilah",
    "gn:country_code":"IQ",
    "gn:dem":707,
    "gn:feature_class":"P",
    "gn:feature_code":"PPL",
    "gn:name":"Qal\u0101 Rayw\u012blah",
    "gn:population":0,
    "gn:timezone":"Asia/Baghdad",
    "iso:country":"IQ",
    "name:ara_x_preferred":[
        "\u0642\u0644\u0627 \u0631\u064a\u0648\u064a\u0644\u0629"
    ],
    "name:ara_x_variant":[
        "\u0642\u0644\u0629 \u0631\u064a\u0648\u064a\u0644\u0629"
    ],
    "name:kur_x_preferred":[
        "Qe\u0142a \u1e5ew\u00ea\u0142e"
    ],
    "name:kur_x_variant":[
        "Qe\u0142a \u1e5ew\u00ea\u0142ey Bchuk",
        "\u0642\u06d5 \u06b5\u0627 \u0695\u0648\u06ce\u06b5\u06d5",
        "\u0642\u06d5 \u06b5\u0627 \u0695\u0648\u06ce\u06b5\u06d5\u0649 \u0628\u0686\u0648\u0643"
    ],
    "name:und_x_variant":[
        "Qula R\u0113w\u012bla",
        "Qal\u0101 Rayw\u012blah",
        "Qala Rewela",
        "Qallat Rayw\u012blah"
    ],
    "wof:name":"Qala Raywilah",
    "wof:placetype":"locality"
},
  "geometry": {"coordinates":[45.23844,34.89106],"type":"Point"}
}