{
  "type": "Feature",
  "properties": {
    "gn:admin1_code":"9.0",
    "gn:admin2_code":"99185.0",
    "gn:asciiname":"Bayt Bahar",
    "gn:country_code":"IQ",
    "gn:dem":1,
    "gn:feature_class":"P",
    "gn:feature_code":"PPL",
    "gn:name":"Bayt Ba\u1e29\u0101r",
    "gn:population":0,
    "gn:timezone":"Asia/Baghdad",
    "iso:country":"IQ",
    "name:ara_x_preferred":[
        "\u0628\u064a\u062a \u0628\u062d\u0627\u0631"
    ],
    "name:und_x_variant":[
        "Bayt Ba\u1e29\u0101r"
    ],
    "wof:name":"Bayt Bahar",
    "wof:placetype":"locality"
},
  "geometry": {"coordinates":[46.92719,30.90088],"type":"Point"}
}