{
  "type": "Feature",
  "properties": {
    "gn:admin1_code":"16.0",
    "gn:admin2_code":"98197.0",
    "gn:asciiname":"Ma-adan",
    "gn:country_code":"IQ",
    "gn:dem":45,
    "gn:feature_class":"P",
    "gn:feature_code":"PPL",
    "gn:name":"Ma-ad\u0101n",
    "gn:population":0,
    "gn:timezone":"Asia/Baghdad",
    "iso:country":"IQ",
    "name:und_x_variant":[
        "Ma-ad\u0101n"
    ],
    "wof:name":"Ma-adan",
    "wof:placetype":"locality"
},
  "geometry": {"coordinates":[45.95494,33.06921],"type":"Point"}
}