{
  "type": "Feature",
  "properties": {
    "gn:admin1_code":"10.0",
    "gn:admin2_code":"99063.0",
    "gn:asciiname":"Qaryat Muhammad Mutlik",
    "gn:country_code":"IQ",
    "gn:dem":57,
    "gn:feature_class":"P",
    "gn:feature_code":"PPL",
    "gn:name":"Qaryat Mu\u1e29ammad Mu\u0163lik",
    "gn:population":0,
    "gn:timezone":"Asia/Baghdad",
    "iso:country":"IQ",
    "name:ara_x_preferred":[
        "\u0642\u0631\u064a\u0629 \u0645\u062d\u0645\u062f \u0627\u0644\u0645\u0637\u0644\u0643"
    ],
    "name:und_x_variant":[
        "Mu\u1e29ammad al Mu\u0163lik",
        "\u0645\u062d\u0645\u062f \u0627\u0644\u0645\u0637\u0644\u0643",
        "Qaryat Mu\u1e29ammad Mu\u0163lik"
    ],
    "wof:name":"Qaryat Muhammad Mutlik",
    "wof:placetype":"locality"
},
  "geometry": {"coordinates":[44.86798,33.97862],"type":"Point"}
}