{
  "type": "Feature",
  "properties": {
    "gn:admin1_code":"1.0",
    "gn:admin2_code":"9166650.0",
    "gn:asciiname":"Shari'ah",
    "gn:country_code":"IQ",
    "gn:dem":349,
    "gn:feature_class":"P",
    "gn:feature_code":"PPL",
    "gn:name":"Shar\u012b\u2018ah",
    "gn:population":0,
    "gn:timezone":"Asia/Baghdad",
    "iso:country":"IQ",
    "name:ara_x_preferred":[
        "\u0634\u0631\u064a\u0639\u0629"
    ],
    "name:und_x_variant":[
        "Shar\u012b\u2018ah"
    ],
    "wof:name":"Shari'ah",
    "wof:placetype":"locality"
},
  "geometry": {"coordinates":[41.74164,34.87736],"type":"Point"}
}