{
  "type": "Feature",
  "properties": {
    "gn:admin1_code":"5.0",
    "gn:admin2_code":"98464.0",
    "gn:asciiname":"Bawah Mirdah al 'Ulya",
    "gn:country_code":"IQ",
    "gn:dem":776,
    "gn:feature_class":"P",
    "gn:feature_code":"PPL",
    "gn:name":"B\u0101wah Mirdah al \u2018Uly\u0101",
    "gn:population":0,
    "gn:timezone":"Asia/Baghdad",
    "iso:country":"IQ",
    "name:ara_x_preferred":[
        "\u0628\u0627\u0648\u0629 \u0645\u0631\u062f\u0629 \u0627\u0644\u0639\u0644\u064a\u0627"
    ],
    "name:kur_x_preferred":[
        "Bawe Mrdey Ser\u00fb"
    ],
    "name:kur_x_variant":[
        "Bawe M\u00eard\u00ee Ser\u00fb",
        "\u0628\u0627\u0648\u06d5 \u0645\u0631\u062f\u06d5\u0649 \u0633\u06d5\u0631\u0648\u0648",
        "\u0628\u0627\u0648\u06d5 \u0645\u06ce\u0631\u062f\u0649 \u0633\u06d5\u0631\u0648\u0648"
    ],
    "name:und_x_variant":[
        "B\u0101wamirda-i Sar\u016b",
        "B\u0101wah Mirdah al \u2018Uly\u0101",
        "B\u0101wa Mirdah",
        "Bawa Mrda",
        "B\u0101wah Mirdah",
        "\u0628\u0627\u0648\u0629 \u0645\u0631\u062f\u0629"
    ],
    "wof:name":"Bawah Mirdah al 'Ulya",
    "wof:placetype":"locality"
},
  "geometry": {"coordinates":[45.32327,35.58429],"type":"Point"}
}