{
  "type": "Feature",
  "properties": {
    "gn:admin1_code":"11.0",
    "gn:admin2_code":"9166592.0",
    "gn:asciiname":"Sajak",
    "gn:country_code":"IQ",
    "gn:dem":1314,
    "gn:feature_class":"P",
    "gn:feature_code":"PPL",
    "gn:name":"Sajak",
    "gn:population":0,
    "gn:timezone":"Asia/Baghdad",
    "iso:country":"IQ",
    "name:ara_x_preferred":[
        "\u0633\u062c\u0643"
    ],
    "name:kur_x_preferred":[
        "Kejek"
    ],
    "name:kur_x_variant":[
        "\u0643\u06d5\u0698\u06d5\u0643",
        "Kejik",
        "\u0643\u06d5\u0698\u0643"
    ],
    "name:und_x_variant":[
        "Kuzek",
        "Kazhak"
    ],
    "wof:name":"Sajak",
    "wof:placetype":"locality"
},
  "geometry": {"coordinates":[44.64,36.75996],"type":"Point"}
}