{
  "type": "Feature",
  "properties": {
    "gn:admin1_code":"10.0",
    "gn:admin2_code":"94296.0",
    "gn:asciiname":"Quraysh",
    "gn:country_code":"IQ",
    "gn:dem":80,
    "gn:feature_class":"P",
    "gn:feature_code":"PPL",
    "gn:name":"Quraysh",
    "gn:population":0,
    "gn:timezone":"Asia/Baghdad",
    "iso:country":"IQ",
    "name:ara_x_preferred":[
        "\u0642\u0631\u064a\u0634"
    ],
    "name:und_x_variant":[
        "Quraish",
        "Quraysh"
    ],
    "wof:name":"Quraysh",
    "wof:placetype":"locality"
},
  "geometry": {"coordinates":[44.50781,34.41096],"type":"Point"}
}