{
  "type": "Feature",
  "properties": {
    "gn:admin1_code":"17.0",
    "gn:admin2_code":"9166629.0",
    "gn:asciiname":"'Alyawi Kazim",
    "gn:country_code":"IQ",
    "gn:dem":25,
    "gn:feature_class":"P",
    "gn:feature_code":"PPL",
    "gn:name":"\u2018Alyaw\u012b K\u0101z\u0327im",
    "gn:population":0,
    "gn:timezone":"Asia/Baghdad",
    "iso:country":"IQ",
    "name:ara_x_preferred":[
        "\u0639\u0644\u064a\u0648\u064a \u0643\u0627\u0638\u0645"
    ],
    "name:und_x_variant":[
        "\u2018Alyaw\u012b K\u0101z\u0327im"
    ],
    "wof:name":"'Alyawi Kazim",
    "wof:placetype":"locality"
},
  "geometry": {"coordinates":[44.56881,32.07924000000001],"type":"Point"}
}