{
  "type": "Feature",
  "properties": {
    "gn:admin1_code":"5.0",
    "gn:admin2_code":"9166596.0",
    "gn:asciiname":"Heware Berze",
    "gn:country_code":"IQ",
    "gn:dem":1307,
    "gn:feature_class":"P",
    "gn:feature_code":"PPL",
    "gn:name":"Heware Berze",
    "gn:population":0,
    "gn:timezone":"Asia/Baghdad",
    "iso:country":"IQ",
    "name:ara_x_preferred":[
        "\u0647\u0648\u0627\u0631\u0647 \u0628\u0631\u0632\u0629"
    ],
    "name:kur_x_preferred":[
        "Heware Berze"
    ],
    "name:kur_x_variant":[
        "\u0647\u06d5\u0648\u0627\u0631\u06d5 \u0628\u06d5\u0631\u0632\u06d5"
    ],
    "name:und_x_variant":[
        "Hawar\u0101 B\u0101rz\u0101",
        "Haw\u0101ra Barza",
        "Haw\u0101rah Barzah",
        "Hawara Barza"
    ],
    "wof:name":"Heware Berze",
    "wof:placetype":"locality"
},
  "geometry": {"coordinates":[45.13961,35.99983],"type":"Point"}
}