{
  "type": "Feature",
  "properties": {
    "gn:admin1_code":"7.0",
    "gn:admin2_code":"9166569.0",
    "gn:asciiname":"Taha Yasin",
    "gn:country_code":"IQ",
    "gn:dem":42,
    "gn:feature_class":"P",
    "gn:feature_code":"PPL",
    "gn:name":"\u0162\u0101h\u0101 Y\u0101s\u012bn",
    "gn:population":0,
    "gn:timezone":"Asia/Baghdad",
    "iso:country":"IQ",
    "name:ara_x_preferred":[
        "\u0637\u0647 \u064a\u0627\u0633\u064a\u0646"
    ],
    "name:ara_x_variant":[
        "\u0162\u0101h\u0101 Y\u0101s\u012bn"
    ],
    "wof:name":"Taha Yasin",
    "wof:placetype":"locality"
},
  "geometry": {"coordinates":[44.34608,33.64383],"type":"Point"}
}