{
  "type": "Feature",
  "properties": {
    "gn:admin1_code":"13.0",
    "gn:admin2_code":"9166581.0",
    "gn:asciiname":"Mam `Ashshah",
    "gn:country_code":"IQ",
    "gn:dem":350,
    "gn:feature_class":"P",
    "gn:feature_code":"PPL",
    "gn:name":"M\u0101m \u2018Ashshah",
    "gn:population":0,
    "gn:timezone":"Asia/Baghdad",
    "iso:country":"IQ",
    "name:ara_x_preferred":[
        "\u0645\u0627\u0645 \u0639\u0634\u0629"
    ],
    "name:und_x_variant":[
        "M\u0101m \u2018Ashshah",
        "M\u0101m \u2018Ashah",
        "M\u0101ma Rasn"
    ],
    "wof:name":"Mam `Ashshah",
    "wof:placetype":"locality"
},
  "geometry": {"coordinates":[44.64922,35.21508],"type":"Point"}
}