{
  "type": "Feature",
  "properties": {
    "gn:admin1_code":"6.0",
    "gn:admin2_code":"99358.0",
    "gn:asciiname":"Jasim 'Abd al Hussayn",
    "gn:country_code":"IQ",
    "gn:dem":24,
    "gn:feature_class":"P",
    "gn:feature_code":"PPL",
    "gn:name":"J\u0101sim \u2018Abd al \u1e28ussayn",
    "gn:population":0,
    "gn:timezone":"Asia/Baghdad",
    "iso:country":"IQ",
    "name:ara_x_preferred":[
        "\u062c\u0627\u0633\u0645 \u0639\u0628\u062f \u0627\u0644\u062d\u0633\u064a\u0646"
    ],
    "name:und_x_variant":[
        "J\u0101sim \u2018Abd al \u1e28ussayn"
    ],
    "wof:name":"Jasim 'Abd al Hussayn",
    "wof:placetype":"locality"
},
  "geometry": {"coordinates":[44.9607,32.29677],"type":"Point"}
}