{
  "type": "Feature",
  "properties": {
    "gn:admin1_code":"4.0",
    "gn:admin2_code":"99763.0",
    "gn:asciiname":"Qaryat Sayyid Ridda",
    "gn:country_code":"IQ",
    "gn:dem":23,
    "gn:feature_class":"P",
    "gn:feature_code":"PPL",
    "gn:name":"Qaryat Sayyid Ri\u1e11\u1e11\u0101",
    "gn:population":0,
    "gn:timezone":"Asia/Baghdad",
    "iso:country":"IQ",
    "name:ara_x_preferred":[
        "\u0642\u0631\u064a\u0629 \u0633\u064a\u062f \u0631\u0636\u0627"
    ],
    "name:und_x_variant":[
        "Qaryat Sayyid Ri\u1e11\u1e11\u0101"
    ],
    "wof:name":"Qaryat Sayyid Ridda",
    "wof:placetype":"locality"
},
  "geometry": {"coordinates":[45.11857,32.12003],"type":"Point"}
}