{
  "type": "Feature",
  "properties": {
    "gn:admin1_code":"5.0",
    "gn:admin2_code":"9166684.0",
    "gn:asciiname":"Seyvagaz",
    "gn:country_code":"IQ",
    "gn:dem":1512,
    "gn:feature_class":"P",
    "gn:feature_code":"PPL",
    "gn:name":"Seyv\u0101gaz",
    "gn:population":0,
    "gn:timezone":"Asia/Baghdad",
    "iso:country":"IQ",
    "name:fas_x_preferred":[
        "\u0633\u06cc\u0648\u0627\u06af\u0632"
    ],
    "wof:name":"Seyvagaz",
    "wof:placetype":"locality"
},
  "geometry": {"coordinates":[45.8009,35.8053],"type":"Point"}
}