{
  "type": "Feature",
  "properties": {
    "gn:admin1_code":"2.0",
    "gn:admin2_code":"99534.0",
    "gn:asciiname":"Qaryat al Mu'aydi al Janubi",
    "gn:country_code":"IQ",
    "gn:dem":3,
    "gn:feature_class":"P",
    "gn:feature_code":"PPL",
    "gn:name":"Qaryat al Mu\u2018ayd\u012b al Jan\u016bb\u012b",
    "gn:population":0,
    "gn:timezone":"Asia/Baghdad",
    "iso:country":"IQ",
    "name:ara_x_preferred":[
        "\u0642\u0631\u064a\u0629 \u0627\u0644\u0645\u0639\u064a\u062f\u064a \u0627\u0644\u062c\u0646\u0648\u0628\u064a"
    ],
    "name:und_x_variant":[
        "Qaryat al Mu\u2018ayd\u012b al Jan\u016bb\u012b"
    ],
    "wof:name":"Qaryat al Mu'aydi al Janubi",
    "wof:placetype":"locality"
},
  "geometry": {"coordinates":[47.73768,30.68776],"type":"Point"}
}