{
  "type": "Feature",
  "properties": {
    "gn:admin1_code":"15.0",
    "gn:admin2_code":"9166608.0",
    "gn:asciiname":"Al Absisiyah",
    "gn:country_code":"IQ",
    "gn:dem":306,
    "gn:feature_class":"P",
    "gn:feature_code":"PPL",
    "gn:name":"Al Ab\u015f\u012b\u015f\u012byah",
    "gn:population":0,
    "gn:timezone":"Asia/Baghdad",
    "iso:country":"IQ",
    "name:ara_x_preferred":[
        "\u0627\u0644\u0627\u0628\u0635\u064a\u0635\u064a\u0647"
    ],
    "name:und_x_variant":[
        "Al Ab\u015f\u012b\u015f\u012byah"
    ],
    "wof:name":"Al Absisiyah",
    "wof:placetype":"locality"
},
  "geometry": {"coordinates":[42.0047,35.9387],"type":"Point"}
}