{
  "type": "Feature",
  "properties": {
    "gn:admin1_code":"18.0",
    "gn:admin2_code":"6804454.0",
    "gn:asciiname":"Qaryat an Nahiyah",
    "gn:country_code":"IQ",
    "gn:dem":179,
    "gn:feature_class":"P",
    "gn:feature_code":"PPL",
    "gn:name":"Qaryat an N\u0101\u1e29iyah",
    "gn:population":0,
    "gn:timezone":"Asia/Baghdad",
    "iso:country":"IQ",
    "name:ara_x_preferred":[
        "\u0642\u0631\u064a\u0629 \u0627\u0644\u0646\u0627\u062d\u064a\u0647"
    ],
    "name:und_x_variant":[
        "An N\u0101\u1e29iyah",
        "Qaryat an N\u0101\u1e29iyah"
    ],
    "wof:name":"Qaryat an Nahiyah",
    "wof:placetype":"locality"
},
  "geometry": {"coordinates":[43.30877,35.65178],"type":"Point"}
}