{
  "type": "Feature",
  "properties": {
    "gn:admin1_code":"1.0",
    "gn:admin2_code":"99455.0",
    "gn:asciiname":"Qaryat Kazim Hasim",
    "gn:country_code":"IQ",
    "gn:dem":38,
    "gn:feature_class":"P",
    "gn:feature_code":"PPL",
    "gn:name":"Qaryat K\u0101z\u0327im \u1e28\u0101sim",
    "gn:population":0,
    "gn:timezone":"Asia/Baghdad",
    "iso:country":"IQ",
    "name:ara_x_preferred":[
        "\u0642\u0631\u064a\u0629 \u06a9\u0627\u0638\u0645 \u062d\u0627\u0633\u0645"
    ],
    "name:und_x_variant":[
        "Qaryat K\u0101z\u0327am \u1e28\u0101sim",
        "Qaryat K\u0101z\u0327im \u1e28\u0101sim"
    ],
    "wof:name":"Qaryat Kazim Hasim",
    "wof:placetype":"locality"
},
  "geometry": {"coordinates":[43.98174,33.48952],"type":"Point"}
}