{
  "type": "Feature",
  "properties": {
    "gn:admin1_code":"4.0",
    "gn:admin2_code":"6850588.0",
    "gn:asciiname":"Al Zuwayr",
    "gn:country_code":"IQ",
    "gn:dem":21,
    "gn:feature_class":"P",
    "gn:feature_code":"PPL",
    "gn:name":"\u0100l Zuwayr",
    "gn:population":0,
    "gn:timezone":"Asia/Baghdad",
    "iso:country":"IQ",
    "name:ara_x_preferred":[
        "\u0627\u0644 \u0632\u0648\u064a\u0631"
    ],
    "name:und_x_variant":[
        "Kharayb az Zuwayr",
        "\u0100l Zuwayr"
    ],
    "wof:name":"Al Zuwayr",
    "wof:placetype":"locality"
},
  "geometry": {"coordinates":[44.8724,31.80963],"type":"Point"}
}