{
  "type": "Feature",
  "properties": {
    "gn:admin1_code":"8.0",
    "gn:admin2_code":"89569.0",
    "gn:asciiname":"Sindi",
    "gn:country_code":"IQ",
    "gn:dem":1148,
    "gn:feature_class":"P",
    "gn:feature_code":"PPL",
    "gn:name":"Sind\u00ee",
    "gn:population":0,
    "gn:timezone":"Asia/Baghdad",
    "iso:country":"IQ",
    "name:ara_x_preferred":[
        "\u0645\u0631\u0643\u0632 \u0646\u0627\u062d\u064a\u0629 \u0633\u0646\u062f\u064a"
    ],
    "name:ceb_x_preferred":[
        "Sindi"
    ],
    "name:deu_x_preferred":[
        "Sindi"
    ],
    "name:kur_x_preferred":[
        "Sind\u00ee"
    ],
    "name:kur_x_variant":[
        "\u0633\u0646\u062f\u0649"
    ],
    "name:lav_x_preferred":[
        "Sindi"
    ],
    "name:nld_x_preferred":[
        "Sindi"
    ],
    "name:por_x_preferred":[
        "Sindi"
    ],
    "name:rus_x_preferred":[
        "\u0421\u0438\u043d\u0434\u0438"
    ],
    "name:swe_x_preferred":[
        "Sindi"
    ],
    "name:ukr_x_preferred":[
        "\u0421\u0456\u043d\u0434\u0456"
    ],
    "name:und_x_variant":[
        "Markaz N\u0101\u1e29\u012byat Sind\u012b",
        "Sindy"
    ],
    "wof:name":"Sindi",
    "wof:placetype":"locality"
},
  "geometry": {"coordinates":[42.84628,37.23437],"type":"Point"}
}