{
  "type": "Feature",
  "properties": {
    "gn:admin1_code":"3.0",
    "gn:admin2_code":"9166568.0",
    "gn:asciiname":"Hasan ar Raml",
    "gn:country_code":"IQ",
    "gn:dem":14,
    "gn:feature_class":"P",
    "gn:feature_code":"PPL",
    "gn:name":"\u1e28asan ar Raml",
    "gn:population":0,
    "gn:timezone":"Asia/Baghdad",
    "iso:country":"IQ",
    "name:ara_x_preferred":[
        "\u062d\u0633\u0646 \u0627\u0644\u0631\u0645\u0644"
    ],
    "name:und_x_variant":[
        "\u1e28asan ar Raml"
    ],
    "wof:name":"Hasan ar Raml",
    "wof:placetype":"locality"
},
  "geometry": {"coordinates":[45.10401,31.41962],"type":"Point"}
}