{
  "type": "Feature",
  "properties": {
    "gn:admin1_code":"18.0",
    "gn:admin2_code":"6805736.0",
    "gn:asciiname":"'Arab Karim al Ghazal",
    "gn:country_code":"IQ",
    "gn:dem":45,
    "gn:feature_class":"P",
    "gn:feature_code":"PPL",
    "gn:name":"\u2018Arab Kar\u012bm al Ghaz\u0101l",
    "gn:population":0,
    "gn:timezone":"Asia/Baghdad",
    "iso:country":"IQ",
    "name:ara_x_preferred":[
        "\u0639\u0631\u0628 \u0643\u0631\u064a\u0645 \u0627\u0644\u063a\u0632\u0627\u0644"
    ],
    "name:und_x_variant":[
        "\u2018Arab Kar\u012bm al Ghaz\u0101l"
    ],
    "wof:name":"'Arab Karim al Ghazal",
    "wof:placetype":"locality"
},
  "geometry": {"coordinates":[44.06557,33.86006],"type":"Point"}
}