{
  "type": "Feature",
  "properties": {
    "gn:admin1_code":"15.0",
    "gn:admin2_code":"98820.0",
    "gn:asciiname":"Chamah",
    "gn:country_code":"IQ",
    "gn:dem":308,
    "gn:feature_class":"P",
    "gn:feature_code":"PPL",
    "gn:name":"Chamah",
    "gn:population":0,
    "gn:timezone":"Asia/Baghdad",
    "iso:country":"IQ",
    "name:ara_x_preferred":[
        "\u0686\u0645\u0647"
    ],
    "name:kur_x_preferred":[
        "Cheme"
    ],
    "name:kur_x_variant":[
        "\u0686\u06d5\u0645\u06d5"
    ],
    "name:und_x_variant":[
        "Chama",
        "Chammah",
        "Chamma",
        "Chamah"
    ],
    "wof:name":"Chamah",
    "wof:placetype":"locality"
},
  "geometry": {"coordinates":[43.83914,36.51051],"type":"Point"}
}