{
  "type": "Feature",
  "properties": {
    "gn:admin1_code":"17.0",
    "gn:admin2_code":"9166552.0",
    "gn:asciiname":"'Abd Allah",
    "gn:country_code":"IQ",
    "gn:dem":20,
    "gn:feature_class":"P",
    "gn:feature_code":"PPL",
    "gn:name":"\u2018Abd Allah",
    "gn:population":0,
    "gn:timezone":"Asia/Baghdad",
    "iso:country":"IQ",
    "name:ara_x_preferred":[
        "\u0639\u0628\u062f \u0627\u0644\u0644\u0647"
    ],
    "name:ukr_x_preferred":[
        "\u0410\u0431\u0434-\u0410\u043b\u043b\u0430\u0445"
    ],
    "name:und_x_variant":[
        "\u2018Abd Allah"
    ],
    "wof:name":"'Abd Allah",
    "wof:placetype":"locality"
},
  "geometry": {"coordinates":[44.50664,31.71748],"type":"Point"}
}