{
  "type": "Feature",
  "properties": {
    "gn:admin1_code":"11.0",
    "gn:admin2_code":"9166592.0",
    "gn:asciiname":"Kani Kawlawk",
    "gn:country_code":"IQ",
    "gn:dem":832,
    "gn:feature_class":"P",
    "gn:feature_code":"PPL",
    "gn:name":"K\u0101n\u012b K\u0101wlawk",
    "gn:population":0,
    "gn:timezone":"Asia/Baghdad",
    "iso:country":"IQ",
    "name:ara_x_preferred":[
        "K\u0101n\u012b Gulik"
    ],
    "name:ara_x_variant":[
        "K\u0101n\u012b K\u0101wilk",
        "\u0643\u0627\u0646\u064a \u0643\u0627\u0648\u0644\u0648\u0643"
    ],
    "name:kur_x_preferred":[
        "Kan\u00ee Kolk"
    ],
    "name:kur_x_variant":[
        "\u0643\u0627\u0646\u0649 \u0643\u06c6\u0644\u0643",
        "Kan\u00ee Kawlok",
        "\u0643\u0627\u0646\u0649 \u0643\u0627\u0648\u0644\u06c6\u0643"
    ],
    "name:und_x_variant":[
        "K\u0101n\u012b K\u0101wlawk",
        "\u0643\u0627\u0646\u064a \u0643\u0627\u0648\u0644\u0648\u0643",
        "\u0643\u0627\u0646\u064a \u0643\u0627\u0648\u0644\u0643",
        "K\u0101n\u012b Gulik",
        "Kani Kawlok"
    ],
    "wof:name":"Kani Kawlawk",
    "wof:placetype":"locality"
},
  "geometry": {"coordinates":[44.34789,36.64733],"type":"Point"}
}