{
  "type": "Feature",
  "properties": {
    "gn:admin1_code":"12.0",
    "gn:admin2_code":"99345.0",
    "gn:asciiname":"'Abd 'Ali al Mulla Hadhdhal",
    "gn:country_code":"IQ",
    "gn:dem":31,
    "gn:feature_class":"P",
    "gn:feature_code":"PPL",
    "gn:name":"\u2018Abd \u2018Al\u012b al Mull\u0101 Hadhdh\u0101l",
    "gn:population":0,
    "gn:timezone":"Asia/Baghdad",
    "iso:country":"IQ",
    "name:und_x_variant":[
        "\u2018Abd \u2018Ali Mulla Hadhdhal",
        "\u2018Abd \u2018Al\u012b al Mull\u0101",
        "\u2018Abd \u2018Al\u012b al Mull\u0101 Hadhdh\u0101l"
    ],
    "wof:name":"'Abd 'Ali al Mulla Hadhdhal",
    "wof:placetype":"locality"
},
  "geometry": {"coordinates":[44.18333,32.53333],"type":"Point"}
}