{
  "type": "Feature",
  "properties": {
    "gn:admin1_code":"15.0",
    "gn:admin2_code":"98820.0",
    "gn:asciiname":"Kochina Mala Farzo",
    "gn:country_code":"IQ",
    "gn:dem":607,
    "gn:feature_class":"P",
    "gn:feature_code":"PPL",
    "gn:name":"Kochina Mala Farzo",
    "gn:population":0,
    "gn:timezone":"Asia/Baghdad",
    "iso:country":"IQ",
    "name:kur_x_preferred":[
        "Kuch\u00eene Mela Ferzu"
    ],
    "name:kur_x_variant":[
        "Kuch\u00eene Mella Ferzu",
        "\u0643\u0648\u0686\u064a\u0646\u06d5 \u0645\u06d5\u0644\u0627 \u0641\u06d5\u0631\u0632\u0648",
        "\u0643\u0648\u0686\u064a\u0646\u06d5 \u0645\u06d5\u0644\u0644\u0627 \u0641\u06d5\u0631\u0632\u0648"
    ],
    "name:und_x_variant":[
        "Zintah Ch\u016blah",
        "Kochina Mala Farzo"
    ],
    "wof:name":"Kochina Mala Farzo",
    "wof:placetype":"locality"
},
  "geometry": {"coordinates":[43.85192,36.73513],"type":"Point"}
}