{
  "type": "Feature",
  "properties": {
    "gn:admin1_code":"16.0",
    "gn:admin2_code":"99132.0",
    "gn:asciiname":"Qaryat al Mutanabi",
    "gn:country_code":"IQ",
    "gn:dem":13,
    "gn:feature_class":"P",
    "gn:feature_code":"PPL",
    "gn:name":"Qaryat al Mutanab\u012b",
    "gn:population":0,
    "gn:timezone":"Asia/Baghdad",
    "iso:country":"IQ",
    "name:ara_x_preferred":[
        "\u0642\u0631\u064a\u0629 \u0627\u0644\u0645\u062a\u0646\u0628\u064a"
    ],
    "name:und_x_variant":[
        "Qaryat al Mutanab\u012b",
        "Al Far\u0101disah",
        "\u0627\u0644\u0641\u0631\u0627\u062f\u0633\u0629"
    ],
    "wof:name":"Qaryat al Mutanabi",
    "wof:placetype":"locality"
},
  "geometry": {"coordinates":[46.20781,32.57962],"type":"Point"}
}