{
  "type": "Feature",
  "properties": {
    "gn:admin1_code":"18.0",
    "gn:admin2_code":"6805736.0",
    "gn:asciiname":"'Arab 'Umar Yusuf",
    "gn:country_code":"IQ",
    "gn:dem":55,
    "gn:feature_class":"P",
    "gn:feature_code":"PPL",
    "gn:name":"\u2018Arab \u2018Umar Y\u016bsuf",
    "gn:population":0,
    "gn:timezone":"Asia/Baghdad",
    "iso:country":"IQ",
    "name:ara_x_preferred":[
        "\u0639\u0631\u0628 \u0639\u0645\u0631 \u064a\u0648\u0633\u0641"
    ],
    "name:und_x_variant":[
        "\u2018Arab \u2018Umar Y\u016bsuf"
    ],
    "wof:name":"'Arab 'Umar Yusuf",
    "wof:placetype":"locality"
},
  "geometry": {"coordinates":[44.0159,34.0123],"type":"Point"}
}