{
  "type": "Feature",
  "properties": {
    "gn:admin1_code":"15.0",
    "gn:admin2_code":"9166649.0",
    "gn:asciiname":"Zarnuk",
    "gn:country_code":"IQ",
    "gn:dem":255,
    "gn:feature_class":"P",
    "gn:feature_code":"PPL",
    "gn:name":"Zarn\u016bk",
    "gn:population":0,
    "gn:timezone":"Asia/Baghdad",
    "iso:country":"IQ",
    "name:ara_x_preferred":[
        "\u0632\u0631\u0646\u0648\u0643"
    ],
    "name:und_x_variant":[
        "Zarn\u016bk"
    ],
    "wof:name":"Zarnuk",
    "wof:placetype":"locality"
},
  "geometry": {"coordinates":[42.87922,36.48682],"type":"Point"}
}