{
  "type": "Feature",
  "properties": {
    "gn:admin1_code":"6.0",
    "gn:admin2_code":"99040.0",
    "gn:asciiname":"Anhad",
    "gn:country_code":"IQ",
    "gn:dem":31,
    "gn:feature_class":"P",
    "gn:feature_code":"PPL",
    "gn:name":"Anhad",
    "gn:population":0,
    "gn:timezone":"Asia/Baghdad",
    "iso:country":"IQ",
    "wof:name":"Anhad",
    "wof:placetype":"locality"
},
  "geometry": {"coordinates":[44.36667,32.73333],"type":"Point"}
}