{
  "type": "Feature",
  "properties": {
    "gn:admin1_code":"3.0",
    "gn:admin2_code":"9166568.0",
    "gn:asciiname":"Sayyid Ibrahim",
    "gn:country_code":"IQ",
    "gn:dem":15,
    "gn:feature_class":"P",
    "gn:feature_code":"PPL",
    "gn:name":"Sayyid Ibr\u0101h\u012bm",
    "gn:population":0,
    "gn:timezone":"Asia/Baghdad",
    "iso:country":"IQ",
    "name:ara_x_preferred":[
        "\u0633\u064a\u062f \u0627\u0628\u0631\u0627\u0647\u064a\u0645"
    ],
    "name:und_x_variant":[
        "Sayyid Ibr\u0101h\u012bm"
    ],
    "wof:name":"Sayyid Ibrahim",
    "wof:placetype":"locality"
},
  "geometry": {"coordinates":[45.13367,31.50996],"type":"Point"}
}