{
  "type": "Feature",
  "properties": {
    "gn:admin1_code":"11.0",
    "gn:admin2_code":"95444.0",
    "gn:asciiname":"Karah Jin",
    "gn:country_code":"IQ",
    "gn:dem":529,
    "gn:feature_class":"P",
    "gn:feature_code":"PPL",
    "gn:name":"Karah J\u012bn",
    "gn:population":0,
    "gn:timezone":"Asia/Baghdad",
    "iso:country":"IQ",
    "name:ara_x_preferred":[
        "\u0643\u0631\u0629 \u062c\u064a\u0646"
    ],
    "name:und_x_variant":[
        "Karah J\u012bn"
    ],
    "wof:name":"Karah Jin",
    "wof:placetype":"locality"
},
  "geometry": {"coordinates":[44.09367,36.25559000000001],"type":"Point"}
}