{
  "type": "Feature",
  "properties": {
    "gn:admin1_code":"5.0",
    "gn:admin2_code":"96204.0",
    "gn:asciiname":"Bani Karam",
    "gn:country_code":"IQ",
    "gn:dem":502,
    "gn:feature_class":"P",
    "gn:feature_code":"PPL",
    "gn:name":"Ban\u012b Karam",
    "gn:population":0,
    "gn:timezone":"Asia/Baghdad",
    "iso:country":"IQ",
    "name:ara_x_preferred":[
        "\u0628\u0646\u064a \u0643\u0631\u0645"
    ],
    "name:fas_x_preferred":[
        "B\u0101n-e Karam"
    ],
    "name:fas_x_variant":[
        "\u0628\u0627\u0646 \u06a9\u0631\u0645"
    ],
    "name:kur_x_preferred":[
        "Ban\u00ee Kerem"
    ],
    "name:kur_x_variant":[
        "\u0628\u0627\u0646\u0649 \u0643\u06d5\u0631\u06d5\u0645",
        "Tepey Kerem",
        "\u062a\u06d5\u067e\u06d5\u0649 \u0643\u06d5\u0631\u06d5\u0645"
    ],
    "name:und_x_variant":[
        "B\u0101n-i Karam",
        "Ban\u012b Karam",
        "\u0628\u0627\u0646 \u06a9\u0631\u0645",
        "Ban Karam",
        "Tapi Karam"
    ],
    "wof:name":"Bani Karam",
    "wof:placetype":"locality"
},
  "geometry": {"coordinates":[45.75607,35.33858],"type":"Point"}
}