{
  "type": "Feature",
  "properties": {
    "gn:admin1_code":"11.0",
    "gn:admin2_code":"95444.0",
    "gn:asciiname":"Gird Cutyar",
    "gn:country_code":"IQ",
    "gn:dem":413,
    "gn:feature_class":"P",
    "gn:feature_code":"PPL",
    "gn:name":"Gird Cutyar",
    "gn:population":0,
    "gn:timezone":"Asia/Baghdad",
    "iso:country":"IQ",
    "name:ara_x_preferred":[
        "\u0643\u0631\u062c\u0648\u062a\u064a\u0627\u0631"
    ],
    "name:ara_x_variant":[
        "Kirj\u016bty\u0101r"
    ],
    "name:kur_x_preferred":[
        "Gird Cutyar"
    ],
    "name:kur_x_variant":[
        "\u06af\u0631\u062f \u062c\u0648\u062a\u064a\u0627\u0631"
    ],
    "name:und_x_variant":[
        "Jutiar",
        "G\u012brj\u016bty\u0101r"
    ],
    "wof:name":"Gird Cutyar",
    "wof:placetype":"locality"
},
  "geometry": {"coordinates":[43.99242,36.2725],"type":"Point"}
}