{
  "type": "Feature",
  "properties": {
    "gn:admin1_code":"10.0",
    "gn:admin2_code":"9166680.0",
    "gn:asciiname":"Tall Khuraymah",
    "gn:country_code":"IQ",
    "gn:dem":43,
    "gn:feature_class":"P",
    "gn:feature_code":"PPL",
    "gn:name":"Tall Khuraymah",
    "gn:population":0,
    "gn:timezone":"Asia/Baghdad",
    "iso:country":"IQ",
    "name:ara_x_preferred":[
        "\u062a\u0644 \u062e\u0631\u064a\u0645\u0629"
    ],
    "wof:name":"Tall Khuraymah",
    "wof:placetype":"locality"
},
  "geometry": {"coordinates":[44.75317,33.57607],"type":"Point"}
}