{
  "type": "Feature",
  "properties": {
    "iso:country":"IQ",
    "name:ara_x_preferred":[
        "\u0627\u0644\u0631\u0645\u064a\u062b\u0629"
    ],
    "name:und_x_variant":[
        "Rumetha"
    ],
    "qs:gn_country":"IQ",
    "qs:gn_fcode":"PPL",
    "qs:gn_pop":47248,
    "qs:name":"Ar Rumaythah",
    "qs:name_adm0":"Iraq",
    "qs:name_adm1":"Al Muthanna",
    "qs:photos":0,
    "qs:photos_1k":0,
    "qs:photos_9k":0,
    "qs:photos_9r":0,
    "qs:photos_all":0,
    "qs:photos_sr":0,
    "qs:placetype":"Town",
    "qs:pop_sr":"7",
    "qs:woe_adm0":23424855,
    "wof:name":"Ar Rumaythah",
    "wof:placetype":"locality",
    "wof:population":47248
},
  "geometry": {"coordinates":[45.20377,31.52845],"type":"Point"}
}