{
  "type": "Feature",
  "properties": {
    "gn:admin1_code":"8.0",
    "gn:admin2_code":"9166607.0",
    "gn:asciiname":"Kiflan",
    "gn:country_code":"IQ",
    "gn:dem":578,
    "gn:feature_class":"P",
    "gn:feature_code":"PPL",
    "gn:name":"Kifl\u0101n",
    "gn:population":0,
    "gn:timezone":"Asia/Baghdad",
    "iso:country":"IQ",
    "name:ara_x_preferred":[
        "\u0643\u0641\u0644\u0627\u0646"
    ],
    "name:ara_x_variant":[
        "Kifl\u0101n"
    ],
    "name:kur_x_preferred":[
        "Kiflan"
    ],
    "name:kur_x_variant":[
        "K\u00eavla",
        "\u0643\u06ce\u06a4\u0644\u0627"
    ],
    "name:und_x_variant":[
        "Kafl\u0101n",
        "Kvlan"
    ],
    "wof:name":"Kiflan",
    "wof:placetype":"locality"
},
  "geometry": {"coordinates":[42.91341,36.89157],"type":"Point"}
}