{
  "type": "Feature",
  "properties": {
    "gn:admin1_code":"11.0",
    "gn:admin2_code":"9166591.0",
    "gn:asciiname":"Sibilk",
    "gn:country_code":"IQ",
    "gn:dem":1070,
    "gn:feature_class":"P",
    "gn:feature_code":"PPL",
    "gn:name":"Sib\u012blk",
    "gn:population":0,
    "gn:timezone":"Asia/Baghdad",
    "iso:country":"IQ",
    "name:ara_x_preferred":[
        "Sib\u012blk"
    ],
    "name:ara_x_variant":[
        "\u0633\u0628\u064a\u0644\u0643"
    ],
    "name:kur_x_preferred":[
        "Sip\u00eelke"
    ],
    "name:kur_x_variant":[
        "\u0633\u067e\u064a\u0644\u0643\u06d5",
        "Siprok",
        "\u0633\u067e\u0631\u06c6\u0643"
    ],
    "name:und_x_variant":[
        "\u0633\u0628\u064a\u0644\u0643",
        "Spilka",
        "Sprok"
    ],
    "wof:name":"Sibilk",
    "wof:placetype":"locality"
},
  "geometry": {"coordinates":[44.51427,36.43004000000001],"type":"Point"}
}