{
  "type": "Feature",
  "properties": {
    "gn:admin1_code":"2.0",
    "gn:admin2_code":"100049.0",
    "gn:asciiname":"Sahil",
    "gn:country_code":"IQ",
    "gn:dem":2,
    "gn:feature_class":"P",
    "gn:feature_code":"PPL",
    "gn:name":"Sah\u012bl",
    "gn:population":0,
    "gn:timezone":"Asia/Baghdad",
    "iso:country":"IQ",
    "name:ceb_x_preferred":[
        "Sahil"
    ],
    "name:fas_x_preferred":[
        "\u0633\u0647\u06cc\u0644"
    ],
    "name:fra_x_preferred":[
        "Sahil"
    ],
    "name:rus_x_preferred":[
        "\u0421\u0430\u0445\u0438\u043b"
    ],
    "name:swe_x_preferred":[
        "Sahil"
    ],
    "name:tur_x_preferred":[
        "Sahil"
    ],
    "wof:name":"Sahil",
    "wof:placetype":"locality"
},
  "geometry": {"coordinates":[48.1739,30.3582],"type":"Point"}
}