{
  "type": "Feature",
  "properties": {
    "gn:admin1_code":"15.0",
    "gn:admin2_code":"98820.0",
    "gn:asciiname":"Kashkah",
    "gn:country_code":"IQ",
    "gn:dem":465,
    "gn:feature_class":"P",
    "gn:feature_code":"PPL",
    "gn:name":"Kashkah",
    "gn:population":0,
    "gn:timezone":"Asia/Baghdad",
    "iso:country":"IQ",
    "name:ara_x_preferred":[
        "\u0643\u0634\u0643\u0647"
    ],
    "name:kur_x_preferred":[
        "Keshke"
    ],
    "name:kur_x_variant":[
        "\u0643\u06d5\u0634\u0643\u06d5",
        "Keshka J\u00ear\u00ee",
        "\u0643\u06d5\u0634\u0643\u0627 \u0698\u06ce\u0631\u0649"
    ],
    "name:und_x_variant":[
        "Kashka",
        "Kashkah",
        "Gashka Lower"
    ],
    "wof:name":"Kashkah",
    "wof:placetype":"locality"
},
  "geometry": {"coordinates":[43.91289,36.65719],"type":"Point"}
}