{
  "type": "Feature",
  "properties": {
    "gn:admin1_code":"9.0",
    "gn:admin2_code":"98855.0",
    "gn:asciiname":"Albu Jum'ah",
    "gn:country_code":"IQ",
    "gn:dem":6,
    "gn:feature_class":"P",
    "gn:feature_code":"PPL",
    "gn:name":"Alb\u016b Jum\u2018ah",
    "gn:population":0,
    "gn:timezone":"Asia/Baghdad",
    "iso:country":"IQ",
    "name:und_x_variant":[
        "Alb\u016b Jum\u2018ah"
    ],
    "wof:name":"Albu Jum'ah",
    "wof:placetype":"locality"
},
  "geometry": {"coordinates":[46.37278,31.10139],"type":"Point"}
}