{
  "type": "Feature",
  "properties": {
    "gn:admin1_code":"16.0",
    "gn:admin2_code":"98197.0",
    "gn:asciiname":"Al Muhammad Huriyah",
    "gn:country_code":"IQ",
    "gn:dem":20,
    "gn:feature_class":"P",
    "gn:feature_code":"PPL",
    "gn:name":"Al Mu\u1e29ammad H\u016br\u012byah",
    "gn:population":0,
    "gn:timezone":"Asia/Baghdad",
    "iso:country":"IQ",
    "name:ara_x_preferred":[
        "\u0627\u0644\u0645\u062d\u0645\u062f \u0647\u0648\u0631\u064a\u0629"
    ],
    "name:und_x_variant":[
        "Al Mu\u1e29ammad H\u016br\u012byah"
    ],
    "wof:name":"Al Muhammad Huriyah",
    "wof:placetype":"locality"
},
  "geometry": {"coordinates":[46.02419,32.88099],"type":"Point"}
}