{
  "type": "Feature",
  "properties": {
    "gn:admin1_code":"16.0",
    "gn:admin2_code":"9166961.0",
    "gn:asciiname":"Al Fadiliyah",
    "gn:country_code":"IQ",
    "gn:dem":24,
    "gn:feature_class":"P",
    "gn:feature_code":"PPL",
    "gn:name":"Al F\u0101\u1e11il\u012byah",
    "gn:population":0,
    "gn:timezone":"Asia/Baghdad",
    "iso:country":"IQ",
    "name:ara_x_preferred":[
        "\u0627\u0644\u0641\u0627\u0636\u0644\u064a\u0647"
    ],
    "name:und_x_variant":[
        "Al F\u0101\u1e11il\u012byah"
    ],
    "wof:name":"Al Fadiliyah",
    "wof:placetype":"locality"
},
  "geometry": {"coordinates":[45.2589,32.6859],"type":"Point"}
}