{
  "type": "Feature",
  "properties": {
    "gn:admin1_code":"15.0",
    "gn:admin2_code":"9166618.0",
    "gn:asciiname":"Sarayshkan",
    "gn:country_code":"IQ",
    "gn:dem":396,
    "gn:feature_class":"P",
    "gn:feature_code":"PPL",
    "gn:name":"Sarayshk\u0101n",
    "gn:population":0,
    "gn:timezone":"Asia/Baghdad",
    "iso:country":"IQ",
    "name:ara_x_preferred":[
        "\u0633\u0631\u064a\u0634\u0643\u0627\u0646"
    ],
    "name:kur_x_preferred":[
        "Ser\u00ee Shkan"
    ],
    "name:kur_x_variant":[
        "\u0633\u06d5\u0631\u0649 \u0634\u0643\u0627\u0646"
    ],
    "name:und_x_variant":[
        "Sir\u0113shk\u0101n",
        "S\u0101r\u0113shk\u0101n",
        "Sareshkan",
        "Sarayshk\u0101n"
    ],
    "wof:name":"Sarayshkan",
    "wof:placetype":"locality"
},
  "geometry": {"coordinates":[43.14794000000001,36.63499],"type":"Point"}
}