{
  "type": "Feature",
  "properties": {
    "gn:admin1_code":"10.0",
    "gn:admin2_code":"99063.0",
    "gn:asciiname":"'Ali Jawad",
    "gn:country_code":"IQ",
    "gn:dem":52,
    "gn:feature_class":"P",
    "gn:feature_code":"PPL",
    "gn:name":"\u2018Al\u012b Jaw\u0101d",
    "gn:population":0,
    "gn:timezone":"Asia/Baghdad",
    "iso:country":"IQ",
    "name:ara_x_preferred":[
        "\u0639\u0644\u064a \u062c\u0648\u0627\u062f"
    ],
    "name:und_x_variant":[
        "\u2018Al\u012b Jaw\u0101d"
    ],
    "wof:name":"'Ali Jawad",
    "wof:placetype":"locality"
},
  "geometry": {"coordinates":[44.68658,33.94228],"type":"Point"}
}