{
  "type": "Feature",
  "properties": {
    "gn:admin1_code":"7.0",
    "gn:admin2_code":"99101.0",
    "gn:asciiname":"'Arab 'Abd Jawad",
    "gn:country_code":"IQ",
    "gn:dem":31,
    "gn:feature_class":"P",
    "gn:feature_code":"PPL",
    "gn:name":"\u2018Arab \u2018Abd Jaw\u0101d",
    "gn:population":0,
    "gn:timezone":"Asia/Baghdad",
    "iso:country":"IQ",
    "name:ara_x_preferred":[
        "\u0639\u0631\u0628 \u0639\u0628\u062f \u062c\u0648\u0627\u062f"
    ],
    "name:und_x_variant":[
        "\u2018Arab \u2018Abd Jaw\u0101d"
    ],
    "wof:name":"'Arab 'Abd Jawad",
    "wof:placetype":"locality"
},
  "geometry": {"coordinates":[44.50864,32.90688],"type":"Point"}
}