{
  "type": "Feature",
  "properties": {
    "gn:admin1_code":"5.0",
    "gn:admin2_code":"92743.0",
    "gn:asciiname":"Deshtewi Xwaru",
    "gn:country_code":"IQ",
    "gn:dem":688,
    "gn:feature_class":"P",
    "gn:feature_code":"PPL",
    "gn:name":"Desht\u00eaw\u00ee Xwar\u00fb",
    "gn:population":0,
    "gn:timezone":"Asia/Baghdad",
    "iso:country":"IQ",
    "name:kur_x_preferred":[
        "Desht\u00eaw\u00ee Xwar\u00fb"
    ],
    "name:kur_x_variant":[
        "\u062f\u06d5\u0634\u062a\u06ce\u0648\u0649 \u062e\u0648\u0627\u0631\u0648\u0648"
    ],
    "name:und_x_variant":[
        "Dashtew Lower"
    ],
    "wof:name":"Deshtewi Xwaru",
    "wof:placetype":"locality"
},
  "geometry": {"coordinates":[45.21748,36.10071],"type":"Point"}
}