{
  "type": "Feature",
  "properties": {
    "gn:admin1_code":"4.0",
    "gn:admin2_code":"99737.0",
    "gn:asciiname":"Al Fawwarah",
    "gn:country_code":"IQ",
    "gn:dem":24,
    "gn:feature_class":"P",
    "gn:feature_code":"PPL",
    "gn:name":"Al Faww\u0101rah",
    "gn:population":0,
    "gn:timezone":"Asia/Baghdad",
    "iso:country":"IQ",
    "name:ara_x_preferred":[
        "\u0627\u0644\u0641\u0648\u0627\u0631\u0629"
    ],
    "name:fas_x_preferred":[
        "\u0627\u0644\u0641\u0648\u0627\u0631\u0627\u0647"
    ],
    "name:nno_x_preferred":[
        "Al Fawwarah"
    ],
    "name:und_x_variant":[
        "Fawar",
        "Al Faww\u0101r",
        "Al Faww\u0101rah"
    ],
    "name:urd_x_preferred":[
        "\u0627\u0644\u0641\u0648\u0627\u0631\u06c1"
    ],
    "wof:name":"Al Fawwarah",
    "wof:placetype":"locality"
},
  "geometry": {"coordinates":[45.15795,32.10379],"type":"Point"}
}