{
  "type": "Feature",
  "properties": {
    "gn:admin1_code":"10.0",
    "gn:admin2_code":"9166680.0",
    "gn:asciiname":"Mustafa Bik",
    "gn:country_code":"IQ",
    "gn:dem":92,
    "gn:feature_class":"P",
    "gn:feature_code":"PPL",
    "gn:name":"Mu\u015f\u0163af\u00e1 B\u012bk",
    "gn:population":0,
    "gn:timezone":"Asia/Baghdad",
    "iso:country":"IQ",
    "name:ara_x_preferred":[
        "\u0645\u0635\u0637\u0641\u0649 \u0628\u064a\u0643"
    ],
    "name:fas_x_preferred":[
        "\u0645\u0635\u0637\u0641\u06cc \u0646\u064a\u06a9"
    ],
    "name:fas_x_variant":[
        "Mo\u015f\u0163af\u00e1 N\u012bk"
    ],
    "name:und_x_variant":[
        "Mustafah Beg",
        "Mu\u015f\u0163af\u00e1",
        "Mu\u015f\u0163af\u00e1 B\u012bk"
    ],
    "wof:name":"Mustafa Bik",
    "wof:placetype":"locality"
},
  "geometry": {"coordinates":[45.44315,33.83217],"type":"Point"}
}