{
  "type": "Feature",
  "properties": {
    "gn:admin1_code":"9.0",
    "gn:admin2_code":"98623.0",
    "gn:asciiname":"'Arab Karim Zahir",
    "gn:country_code":"IQ",
    "gn:dem":9,
    "gn:feature_class":"P",
    "gn:feature_code":"PPLL",
    "gn:name":"\u2018Arab Kar\u012bm Z\u0327\u0101hir",
    "gn:population":0,
    "gn:timezone":"Asia/Baghdad",
    "iso:country":"IQ",
    "name:ara_x_preferred":[
        "\u0639\u0631\u0628 \u06a9\u0631\u064a\u0645 \u0637\u0627\u0647\u0631"
    ],
    "name:und_x_variant":[
        "\u2018Arab Kar\u012bm Z\u0327\u0101hir"
    ],
    "wof:name":"'Arab Karim Zahir",
    "wof:placetype":"locality"
},
  "geometry": {"coordinates":[46.39032,31.50704],"type":"Point"}
}