{
  "type": "Feature",
  "properties": {
    "gn:admin1_code":"10.0",
    "gn:admin2_code":"94590.0",
    "gn:asciiname":"Mahmud al Jawhar",
    "gn:country_code":"IQ",
    "gn:dem":60,
    "gn:feature_class":"P",
    "gn:feature_code":"PPL",
    "gn:name":"Ma\u1e29m\u016bd al Jawhar",
    "gn:population":0,
    "gn:timezone":"Asia/Baghdad",
    "iso:country":"IQ",
    "name:ara_x_preferred":[
        "\u0645\u062d\u0645\u0648\u062f \u0627\u0644\u062c\u0648\u0647\u0631"
    ],
    "name:und_x_variant":[
        "Ma\u1e29m\u016bd al Jawhar"
    ],
    "wof:name":"Mahmud al Jawhar",
    "wof:placetype":"locality"
},
  "geometry": {"coordinates":[44.78904,34.05181],"type":"Point"}
}