{
  "type": "Feature",
  "properties": {
    "gn:admin1_code":"5.0",
    "gn:admin2_code":"92051.0",
    "gn:asciiname":"Kerek",
    "gn:country_code":"IQ",
    "gn:dem":839,
    "gn:feature_class":"P",
    "gn:feature_code":"PPL",
    "gn:name":"Kerek",
    "gn:population":0,
    "gn:timezone":"Asia/Baghdad",
    "iso:country":"IQ",
    "name:ceb_x_preferred":[
        "Kerek"
    ],
    "name:kur_x_preferred":[
        "Kerek"
    ],
    "name:kur_x_variant":[
        "\u0643\u06d5\u0631\u06d5\u0643"
    ],
    "name:swe_x_preferred":[
        "Kerek"
    ],
    "name:und_x_variant":[
        "Karak"
    ],
    "wof:name":"Kerek",
    "wof:placetype":"locality"
},
  "geometry": {"coordinates":[44.76205,36.362],"type":"Point"}
}