{
  "type": "Feature",
  "properties": {
    "gn:admin1_code":"10.0",
    "gn:admin2_code":"94590.0",
    "gn:asciiname":"Bzainan",
    "gn:country_code":"IQ",
    "gn:dem":393,
    "gn:feature_class":"P",
    "gn:feature_code":"PPL",
    "gn:name":"Bzainan",
    "gn:population":0,
    "gn:timezone":"Asia/Baghdad",
    "iso:country":"IQ",
    "wof:name":"Bzainan",
    "wof:placetype":"locality"
},
  "geometry": {"coordinates":[45.64167,34.58611],"type":"Point"}
}