{
  "type": "Feature",
  "properties": {
    "gn:admin1_code":"9.0",
    "gn:admin2_code":"98700.0",
    "gn:asciiname":"Qaryat as Sadah",
    "gn:country_code":"IQ",
    "gn:dem":11,
    "gn:feature_class":"P",
    "gn:feature_code":"PPL",
    "gn:name":"Qaryat as S\u0101dah",
    "gn:population":0,
    "gn:timezone":"Asia/Baghdad",
    "iso:country":"IQ",
    "name:ara_x_preferred":[
        "\u0642\u0631\u064a\u0629 \u0627\u0644\u0633\u0627\u062f\u0629"
    ],
    "name:und_x_variant":[
        "\u0100lb\u016b \u2018Al\u012b",
        "\u0627\u0644\u0628\u0648 \u0639\u0644\u064a",
        "Qaryat as S\u0101dah"
    ],
    "wof:name":"Qaryat as Sadah",
    "wof:placetype":"locality"
},
  "geometry": {"coordinates":[46.01148,31.79807000000001],"type":"Point"}
}