{
  "type": "Feature",
  "properties": {
    "gn:admin1_code":"10.0",
    "gn:admin2_code":"9166680.0",
    "gn:asciiname":"'Arab Kumat al 'Arabiyah",
    "gn:country_code":"IQ",
    "gn:dem":93,
    "gn:feature_class":"P",
    "gn:feature_code":"PPL",
    "gn:name":"\u2018Arab K\u016bmat al \u2018Arab\u012byah",
    "gn:population":0,
    "gn:timezone":"Asia/Baghdad",
    "iso:country":"IQ",
    "name:ara_x_preferred":[
        "\u0639\u0631\u0628 \u0643\u0648\u0645\u0629 \u0627\u0644\u0639\u0631\u0628\u064a\u0629"
    ],
    "name:und_x_variant":[
        "\u2018Arab K\u016bmat al \u2018Arab\u012byah"
    ],
    "wof:name":"'Arab Kumat al 'Arabiyah",
    "wof:placetype":"locality"
},
  "geometry": {"coordinates":[45.62472,33.6727],"type":"Point"}
}