{
  "type": "Feature",
  "properties": {
    "gn:admin1_code":"18.0",
    "gn:admin2_code":"91594.0",
    "gn:asciiname":"Muhammad al 'Abud",
    "gn:country_code":"IQ",
    "gn:dem":77,
    "gn:feature_class":"P",
    "gn:feature_code":"PPL",
    "gn:name":"Mu\u1e29ammad al \u2018Ab\u016bd",
    "gn:population":0,
    "gn:timezone":"Asia/Baghdad",
    "iso:country":"IQ",
    "name:ara_x_preferred":[
        "\u0645\u062d\u0645\u062f \u0627\u0644\u0639\u0628\u0648\u062f"
    ],
    "name:und_x_variant":[
        "Mu\u1e29ammad al \u2018Ab\u016bd"
    ],
    "wof:name":"Muhammad al 'Abud",
    "wof:placetype":"locality"
},
  "geometry": {"coordinates":[43.75479,34.45208],"type":"Point"}
}