{
  "type": "Feature",
  "properties": {
    "gn:admin1_code":"10.0",
    "gn:admin2_code":"99063.0",
    "gn:asciiname":"Mulla Khadir Salih",
    "gn:country_code":"IQ",
    "gn:dem":59,
    "gn:feature_class":"P",
    "gn:feature_code":"PPL",
    "gn:name":"Mull\u0101 Kha\u1e11\u012br \u015e\u0101li\u1e29",
    "gn:population":0,
    "gn:timezone":"Asia/Baghdad",
    "iso:country":"IQ",
    "name:ara_x_preferred":[
        "\u0645\u0644\u0627 \u062e\u0636\u064a\u0631 \u0635\u0627\u0644\u062d"
    ],
    "name:und_x_variant":[
        "Mull\u0101 Kha\u1e11\u012br \u015e\u0101li\u1e29"
    ],
    "wof:name":"Mulla Khadir Salih",
    "wof:placetype":"locality"
},
  "geometry": {"coordinates":[44.91947,33.92271],"type":"Point"}
}