{
  "type": "Feature",
  "properties": {
    "gn:admin1_code":"7.0",
    "gn:admin2_code":"9166545.0",
    "gn:asciiname":"Hamad Muhsin",
    "gn:country_code":"IQ",
    "gn:dem":38,
    "gn:feature_class":"P",
    "gn:feature_code":"PPL",
    "gn:name":"\u1e28amad Mu\u1e29sin",
    "gn:population":0,
    "gn:timezone":"Asia/Baghdad",
    "iso:country":"IQ",
    "name:ara_x_preferred":[
        "\u062d\u0645\u062f \u0645\u062d\u0633\u0646"
    ],
    "name:und_x_variant":[
        "\u1e28amad Mu\u1e29sin"
    ],
    "wof:name":"Hamad Muhsin",
    "wof:placetype":"locality"
},
  "geometry": {"coordinates":[44.49573,33.22331],"type":"Point"}
}