{
  "type": "Feature",
  "properties": {
    "gn:admin1_code":"1.0",
    "gn:admin2_code":"98718.0",
    "gn:asciiname":"Albu Sulayman",
    "gn:country_code":"IQ",
    "gn:dem":49,
    "gn:feature_class":"P",
    "gn:feature_code":"PPL",
    "gn:name":"\u0100lb\u016b Sulaym\u0101n",
    "gn:population":0,
    "gn:timezone":"Asia/Baghdad",
    "iso:country":"IQ",
    "name:ara_x_preferred":[
        "\u0622\u0644\u0628\u0648 \u0633\u0644\u064a\u0645\u0627\u0646"
    ],
    "name:und_x_variant":[
        "\u0100lb\u016b Sulaym\u0101n"
    ],
    "wof:name":"Albu Sulayman",
    "wof:placetype":"locality"
},
  "geometry": {"coordinates":[43.41289,33.46837],"type":"Point"}
}