{
  "type": "Feature",
  "properties": {
    "gn:admin1_code":"15.0",
    "gn:admin2_code":"9166541.0",
    "gn:asciiname":"Qaryat an Na'maniyah",
    "gn:country_code":"IQ",
    "gn:dem":198,
    "gn:feature_class":"P",
    "gn:feature_code":"PPL",
    "gn:name":"Qaryat an Na\u2018m\u0101n\u012byah",
    "gn:population":0,
    "gn:timezone":"Asia/Baghdad",
    "iso:country":"IQ",
    "name:ara_x_preferred":[
        "\u0642\u0631\u064a\u0629 \u0627\u0644\u0646\u0639\u0645\u0627\u0646\u064a\u0629"
    ],
    "name:und_x_variant":[
        "Qaryat an Nu\u2018m\u0101n\u012byah"
    ],
    "wof:name":"Qaryat an Na'maniyah",
    "wof:placetype":"locality"
},
  "geometry": {"coordinates":[43.31962,36.09325],"type":"Point"}
}