{
  "type": "Feature",
  "properties": {
    "gn:admin1_code":"6.0",
    "gn:admin2_code":"6818313.0",
    "gn:asciiname":"Qaryat Muhammad 'Abud",
    "gn:country_code":"IQ",
    "gn:dem":35,
    "gn:feature_class":"P",
    "gn:feature_code":"PPL",
    "gn:name":"Qaryat Mu\u1e29ammad \u2018Ab\u016bd",
    "gn:population":0,
    "gn:timezone":"Asia/Baghdad",
    "iso:country":"IQ",
    "name:ara_x_preferred":[
        "\u0642\u0631\u064a\u0629 \u0645\u062d\u0645\u062f \u0639\u0628\u0648\u062f"
    ],
    "name:und_x_variant":[
        "Qaryat Mu\u1e29ammad \u2018Ab\u016bd"
    ],
    "wof:name":"Qaryat Muhammad 'Abud",
    "wof:placetype":"locality"
},
  "geometry": {"coordinates":[44.33171,32.78766],"type":"Point"}
}