{
  "type": "Feature",
  "properties": {
    "gn:admin1_code":"6.0",
    "gn:admin2_code":"99358.0",
    "gn:asciiname":"Jasim Hurayz",
    "gn:country_code":"IQ",
    "gn:dem":20,
    "gn:feature_class":"P",
    "gn:feature_code":"PPL",
    "gn:name":"J\u0101sim \u1e28urayz",
    "gn:population":0,
    "gn:timezone":"Asia/Baghdad",
    "iso:country":"IQ",
    "name:ara_x_preferred":[
        "\u062c\u0627\u0633\u0645 \u062d\u0631\u064a\u0632"
    ],
    "name:und_x_variant":[
        "J\u0101sim \u1e28urayz"
    ],
    "wof:name":"Jasim Hurayz",
    "wof:placetype":"locality"
},
  "geometry": {"coordinates":[44.94181,32.30627],"type":"Point"}
}