{
  "type": "Feature",
  "properties": {
    "gn:admin1_code":"5.0",
    "gn:admin2_code":"92743.0",
    "gn:asciiname":"Pisht Ashan",
    "gn:country_code":"IQ",
    "gn:dem":1316,
    "gn:feature_class":"P",
    "gn:feature_code":"PPL",
    "gn:name":"Pisht Ashan",
    "gn:population":0,
    "gn:timezone":"Asia/Baghdad",
    "iso:country":"IQ",
    "name:ara_x_preferred":[
        "\u0628\u0634\u062a \u0627\u0634\u0627\u0646"
    ],
    "name:kur_x_preferred":[
        "Pisht Ashan"
    ],
    "name:kur_x_variant":[
        "\u067e\u0634\u062a \u0626\u0627\u0634\u0627\u0646"
    ],
    "name:und_x_variant":[
        "Bisht Ash\u0101n",
        "Pisht\u0101sh\u0101n",
        "Psht Ashan",
        "Pshtashan Lower",
        "Pshtashan Upper"
    ],
    "wof:name":"Pisht Ashan",
    "wof:placetype":"locality"
},
  "geometry": {"coordinates":[45.00556,36.44333],"type":"Point"}
}