{
  "type": "Feature",
  "properties": {
    "gn:admin1_code":"13.0",
    "gn:asciiname":"Nisar Missar",
    "gn:country_code":"IQ",
    "gn:dem":746,
    "gn:feature_class":"P",
    "gn:feature_code":"PPL",
    "gn:name":"Ni\u015f\u0101r Mi\u015f\u015f\u0101r",
    "gn:population":0,
    "gn:timezone":"Asia/Baghdad",
    "iso:country":"IQ",
    "name:ara_x_preferred":[
        "Ni\u015f\u0101r Mi\u015f\u015f\u0101r"
    ],
    "name:ara_x_variant":[
        "\u0646\u0635\u0627\u0631 \u0645\u0635\u0627\u0631"
    ],
    "name:und_x_variant":[
        "N\u012bs\u0101r M\u0101s\u0101r"
    ],
    "wof:name":"Nisar Missar",
    "wof:placetype":"locality"
},
  "geometry": {"coordinates":[44.6892,35.74398],"type":"Point"}
}