{
  "type": "Feature",
  "properties": {
    "gn:admin1_code":"15.0",
    "gn:admin2_code":"90392.0",
    "gn:asciiname":"Al Jussah ash Shimaliyah",
    "gn:country_code":"IQ",
    "gn:dem":355,
    "gn:feature_class":"P",
    "gn:feature_code":"PPL",
    "gn:name":"Al Ju\u015f\u015fah ash Shim\u0101l\u012byah",
    "gn:population":0,
    "gn:timezone":"Asia/Baghdad",
    "iso:country":"IQ",
    "name:ara_x_preferred":[
        "\u0627\u0644\u062c\u0635\u0647 \u0627\u0644\u0634\u0645\u0627\u0644\u064a\u0629"
    ],
    "name:kur_x_preferred":[
        "\u1e26esse"
    ],
    "name:kur_x_variant":[
        "\u062d\u06d5\u0633\u0633\u06d5"
    ],
    "name:und_x_variant":[
        "Al Ju\u015f\u015fah ash Sham\u0101l\u012byah",
        "Hassa"
    ],
    "wof:name":"Al Jussah ash Shimaliyah",
    "wof:placetype":"locality"
},
  "geometry": {"coordinates":[42.67781,36.5971],"type":"Point"}
}