{
  "type": "Feature",
  "properties": {
    "gn:admin1_code":"17.0",
    "gn:admin2_code":"9166629.0",
    "gn:asciiname":"'Ubayd Julhum",
    "gn:country_code":"IQ",
    "gn:dem":23,
    "gn:feature_class":"P",
    "gn:feature_code":"PPL",
    "gn:name":"\u2018Ubayd Julhum",
    "gn:population":0,
    "gn:timezone":"Asia/Baghdad",
    "iso:country":"IQ",
    "name:ara_x_preferred":[
        "\u0639\u0628\u064a\u062f \u062c\u0644\u0647\u0645"
    ],
    "name:und_x_variant":[
        "\u2018Ubayd Julhum"
    ],
    "wof:name":"'Ubayd Julhum",
    "wof:placetype":"locality"
},
  "geometry": {"coordinates":[44.55979,32.12783],"type":"Point"}
}