{
  "type": "Feature",
  "properties": {
    "gn:admin1_code":"6.0",
    "gn:admin2_code":"6818313.0",
    "gn:asciiname":"Muhammad Khidr",
    "gn:country_code":"IQ",
    "gn:dem":33,
    "gn:feature_class":"P",
    "gn:feature_code":"PPL",
    "gn:name":"Mu\u1e29ammad Khi\u1e11r",
    "gn:population":0,
    "gn:timezone":"Asia/Baghdad",
    "iso:country":"IQ",
    "name:ara_x_preferred":[
        "\u0645\u062d\u0645\u062f \u062e\u0636\u0631"
    ],
    "name:und_x_variant":[
        "Mu\u1e29ammad Khi\u1e11r"
    ],
    "wof:name":"Muhammad Khidr",
    "wof:placetype":"locality"
},
  "geometry": {"coordinates":[44.4664,32.51834],"type":"Point"}
}