{
  "type": "Feature",
  "properties": {
    "gn:admin1_code":"15.0",
    "gn:admin2_code":"90392.0",
    "gn:asciiname":"Burghalah",
    "gn:country_code":"IQ",
    "gn:dem":381,
    "gn:feature_class":"P",
    "gn:feature_code":"PPL",
    "gn:name":"Burghalah",
    "gn:population":0,
    "gn:timezone":"Asia/Baghdad",
    "iso:country":"IQ",
    "name:ara_x_preferred":[
        "\u0628\u0631\u063a\u0644\u0629"
    ],
    "name:kur_x_preferred":[
        "Burghe\u0142e"
    ],
    "name:kur_x_variant":[
        "\u0628\u0648\u0631\u063a\u06d5\u06b5\u06d5"
    ],
    "name:und_x_variant":[
        "Burghla",
        "Burghulah",
        "Burghalah"
    ],
    "wof:name":"Burghalah",
    "wof:placetype":"locality"
},
  "geometry": {"coordinates":[42.36296,36.59319],"type":"Point"}
}