{
  "type": "Feature",
  "properties": {
    "gn:admin1_code":"10.0",
    "gn:admin2_code":"94590.0",
    "gn:asciiname":"Amin Habib",
    "gn:country_code":"IQ",
    "gn:dem":142,
    "gn:feature_class":"P",
    "gn:feature_code":"PPL",
    "gn:name":"Am\u012bn \u1e28ab\u012bb",
    "gn:population":0,
    "gn:timezone":"Asia/Baghdad",
    "iso:country":"IQ",
    "name:ara_x_preferred":[
        "\u0627\u0645\u064a\u0646 \u062d\u0628\u064a\u0628"
    ],
    "name:und_x_variant":[
        "Am\u012bn \u1e28ab\u012bb"
    ],
    "wof:name":"Amin Habib",
    "wof:placetype":"locality"
},
  "geometry": {"coordinates":[45.14878,34.38927],"type":"Point"}
}