{
  "type": "Feature",
  "properties": {
    "gn:admin1_code":"6.0",
    "gn:admin2_code":"6818313.0",
    "gn:asciiname":"'Arab Munif Shahir",
    "gn:country_code":"IQ",
    "gn:dem":26,
    "gn:feature_class":"P",
    "gn:feature_code":"PPL",
    "gn:name":"\u2018Arab Mun\u012bf Sh\u0101hir",
    "gn:population":0,
    "gn:timezone":"Asia/Baghdad",
    "iso:country":"IQ",
    "name:ara_x_preferred":[
        "\u0639\u0631\u0628 \u0645\u0646\u064a\u0641 \u0634\u0627\u0647\u0631"
    ],
    "name:und_x_variant":[
        "\u2018Arab Mun\u012bf Sh\u0101hir"
    ],
    "wof:name":"'Arab Munif Shahir",
    "wof:placetype":"locality"
},
  "geometry": {"coordinates":[44.73309,32.47724],"type":"Point"}
}