{
  "type": "Feature",
  "properties": {
    "gn:admin1_code":"18.0",
    "gn:admin2_code":"90148.0",
    "gn:asciiname":"Mahdi Salih",
    "gn:country_code":"IQ",
    "gn:dem":121,
    "gn:feature_class":"P",
    "gn:feature_code":"PPL",
    "gn:name":"Mahd\u012b \u015e\u0101li\u1e29",
    "gn:population":0,
    "gn:timezone":"Asia/Baghdad",
    "iso:country":"IQ",
    "name:ara_x_preferred":[
        "\u0645\u0647\u062f\u064a \u0635\u0627\u0644\u062d"
    ],
    "name:und_x_variant":[
        "Mahd\u012b \u015e\u0101li\u1e29"
    ],
    "wof:name":"Mahdi Salih",
    "wof:placetype":"locality"
},
  "geometry": {"coordinates":[43.53493,34.48494],"type":"Point"}
}