{
  "type": "Feature",
  "properties": {
    "gn:admin1_code":"10.0",
    "gn:admin2_code":"9166680.0",
    "gn:asciiname":"Tall adh Dhahab",
    "gn:country_code":"IQ",
    "gn:dem":41,
    "gn:feature_class":"P",
    "gn:feature_code":"PPL",
    "gn:name":"Tall adh Dhahab",
    "gn:population":0,
    "gn:timezone":"Asia/Baghdad",
    "iso:country":"IQ",
    "name:ara_x_preferred":[
        "\u062a\u0644 \u0627\u0644\u0630\u0647\u0628"
    ],
    "name:und_x_variant":[
        "Tall al Thahib",
        "Tall adh Dhahab"
    ],
    "wof:name":"Tall adh Dhahab",
    "wof:placetype":"locality"
},
  "geometry": {"coordinates":[44.68406,33.52203],"type":"Point"}
}