{
  "type": "Feature",
  "properties": {
    "gn:admin1_code":"16.0",
    "gn:admin2_code":"98460.0",
    "gn:asciiname":"'Allawi 'Ubayd",
    "gn:country_code":"IQ",
    "gn:dem":32,
    "gn:feature_class":"P",
    "gn:feature_code":"PPL",
    "gn:name":"\u2018All\u0101w\u012b \u2018Ubayd",
    "gn:population":0,
    "gn:timezone":"Asia/Baghdad",
    "iso:country":"IQ",
    "name:ara_x_preferred":[
        "\u0639\u0644\u0627\u0648\u064a \u0639\u0628\u064a\u062f"
    ],
    "name:und_x_variant":[
        "\u2018All\u0101w\u012b \u2018Ubayd"
    ],
    "wof:name":"'Allawi 'Ubayd",
    "wof:placetype":"locality"
},
  "geometry": {"coordinates":[44.71406,32.94345],"type":"Point"}
}