{
  "type": "Feature",
  "properties": {
    "gn:admin1_code":"14.0",
    "gn:admin2_code":"92536.0",
    "gn:asciiname":"Al Aqub",
    "gn:cc2":"IQ",
    "gn:country_code":"IQ",
    "gn:dem":4,
    "gn:feature_class":"P",
    "gn:feature_code":"PPL",
    "gn:name":"Al Aqub",
    "gn:population":0,
    "gn:timezone":"Asia/Baghdad",
    "iso:country":"IQ",
    "name:und_x_variant":[
        "Al \u2018Ut\u016bb",
        "Al Aqub"
    ],
    "wof:name":"Al Aqub",
    "wof:placetype":"locality"
},
  "geometry": {"coordinates":[47.51667,31.35],"type":"Point"}
}