{
  "type": "Feature",
  "properties": {
    "gn:admin1_code":"15.0",
    "gn:admin2_code":"9166649.0",
    "gn:asciiname":"Qaryat Munirah",
    "gn:country_code":"IQ",
    "gn:dem":217,
    "gn:feature_class":"P",
    "gn:feature_code":"PPL",
    "gn:name":"Qaryat Mun\u012brah",
    "gn:population":0,
    "gn:timezone":"Asia/Baghdad",
    "iso:country":"IQ",
    "name:ara_x_preferred":[
        "\u0642\u0631\u064a\u0629 \u0645\u0646\u064a\u0631\u0629"
    ],
    "name:und_x_variant":[
        "Mun\u012brah",
        "Qaryat Mun\u012brah"
    ],
    "wof:name":"Qaryat Munirah",
    "wof:placetype":"locality"
},
  "geometry": {"coordinates":[43.28583,36.08823],"type":"Point"}
}