{
  "type": "Feature",
  "properties": {
    "gn:admin1_code":"10.0",
    "gn:admin2_code":"9166680.0",
    "gn:asciiname":"Hakim Latif",
    "gn:country_code":"IQ",
    "gn:dem":46,
    "gn:feature_class":"P",
    "gn:feature_code":"PPL",
    "gn:name":"\u1e28\u0101kim La\u0163\u012bf",
    "gn:population":0,
    "gn:timezone":"Asia/Baghdad",
    "iso:country":"IQ",
    "name:ara_x_preferred":[
        "\u062d\u0643\u064a\u0645 \u0644\u0637\u064a\u0641"
    ],
    "name:und_x_variant":[
        "\u1e28\u0101kim La\u0163\u012bf"
    ],
    "wof:name":"Hakim Latif",
    "wof:placetype":"locality"
},
  "geometry": {"coordinates":[44.85363,33.74878],"type":"Point"}
}