{
  "type": "Feature",
  "properties": {
    "gn:admin1_code":"18.0",
    "gn:admin2_code":"9167093.0",
    "gn:asciiname":"'Abd Hulylih",
    "gn:country_code":"IQ",
    "gn:dem":72,
    "gn:feature_class":"P",
    "gn:feature_code":"PPL",
    "gn:name":"\u2018Abd \u1e28ulyl\u012b\u1e29",
    "gn:population":0,
    "gn:timezone":"Asia/Baghdad",
    "iso:country":"IQ",
    "name:ara_x_preferred":[
        "\u0639\u0628\u062f \u062d\u0644\u0644\u064a\u062d"
    ],
    "name:ara_x_variant":[
        "\u2018Abd \u1e28ulyl\u012b\u1e29"
    ],
    "wof:name":"'Abd Hulylih",
    "wof:placetype":"locality"
},
  "geometry": {"coordinates":[43.64357,34.01063],"type":"Point"}
}