{
  "type": "Feature",
  "properties": {
    "gn:admin1_code":"4.0",
    "gn:admin2_code":"6850588.0",
    "gn:asciiname":"Hariz as Sultan",
    "gn:country_code":"IQ",
    "gn:dem":15,
    "gn:feature_class":"P",
    "gn:feature_code":"PPL",
    "gn:name":"\u1e28ar\u012bz as Sul\u0163\u0101n",
    "gn:population":0,
    "gn:timezone":"Asia/Baghdad",
    "iso:country":"IQ",
    "name:ara_x_preferred":[
        "\u062d\u0631\u064a\u0632 \u0627\u0644\u0633\u0644\u0637\u0627\u0646"
    ],
    "name:und_x_variant":[
        "\u1e28ar\u012bz as Sul\u0163\u0101n"
    ],
    "wof:name":"Hariz as Sultan",
    "wof:placetype":"locality"
},
  "geometry": {"coordinates":[44.85524,31.47405],"type":"Point"}
}