{
  "type": "Feature",
  "properties": {
    "gn:admin1_code":"7.0",
    "gn:admin2_code":"99173.0",
    "gn:asciiname":"Hamdi al Pachachi",
    "gn:cc2":"IQ",
    "gn:country_code":"IQ",
    "gn:dem":37,
    "gn:feature_class":"P",
    "gn:feature_code":"PPL",
    "gn:name":"\u1e28amd\u012b al P\u0101chach\u012b",
    "gn:population":0,
    "gn:timezone":"Asia/Baghdad",
    "iso:country":"IQ",
    "name:und_x_variant":[
        "Hamdi P\u0101chachi",
        "\u1e28amd\u012b al Bajaj\u012b",
        "\u1e28amd\u012b al P\u0101chahch\u012b",
        "\u1e28amd\u012b al P\u0101chach\u012b"
    ],
    "wof:name":"Hamdi al Pachachi",
    "wof:placetype":"locality"
},
  "geometry": {"coordinates":[44.24667,33.54917],"type":"Point"}
}