{
  "type": "Feature",
  "properties": {
    "gn:admin1_code":"14.0",
    "gn:admin2_code":"9166557.0",
    "gn:asciiname":"Salaf al Masfah",
    "gn:country_code":"IQ",
    "gn:dem":9,
    "gn:feature_class":"P",
    "gn:feature_code":"PPL",
    "gn:name":"Salaf al Ma\u015ff\u0101h",
    "gn:population":0,
    "gn:timezone":"Asia/Baghdad",
    "iso:country":"IQ",
    "name:ara_x_preferred":[
        "\u0633\u0644\u0641 \u0627\u0644\u0645\u0635\u0641\u0627\u0629"
    ],
    "name:und_x_variant":[
        "Salaf al Ma\u015ff\u0101h"
    ],
    "wof:name":"Salaf al Masfah",
    "wof:placetype":"locality"
},
  "geometry": {"coordinates":[47.35951,31.63709],"type":"Point"}
}