{
  "type": "Feature",
  "properties": {
    "gn:admin1_code":"5.0",
    "gn:admin2_code":"92743.0",
    "gn:asciiname":"Zurkani Xwaru",
    "gn:country_code":"IQ",
    "gn:dem":614,
    "gn:feature_class":"P",
    "gn:feature_code":"PPL",
    "gn:name":"Zurkan\u00ee Xwar\u00fb",
    "gn:population":0,
    "gn:timezone":"Asia/Baghdad",
    "iso:country":"IQ",
    "name:kur_x_preferred":[
        "Zurkan\u00ee Xwar\u00fb"
    ],
    "name:kur_x_variant":[
        "\u0632\u0648\u0631\u0643\u0627\u0646\u0649 \u062e\u0648\u0627\u0631\u0648\u0648"
    ],
    "name:und_x_variant":[
        "Zurkan Lower"
    ],
    "wof:name":"Zurkani Xwaru",
    "wof:placetype":"locality"
},
  "geometry": {"coordinates":[45.03106,36.28014],"type":"Point"}
}