{
  "type": "Feature",
  "properties": {
    "gn:admin1_code":"1.0",
    "gn:admin2_code":"6765480.0",
    "gn:asciiname":"Qaryat ash Sham'un",
    "gn:country_code":"IQ",
    "gn:dem":109,
    "gn:feature_class":"P",
    "gn:feature_code":"PPL",
    "gn:name":"Qaryat ash Sham\u2018\u016bn",
    "gn:population":0,
    "gn:timezone":"Asia/Baghdad",
    "iso:country":"IQ",
    "name:ara_x_preferred":[
        "\u0642\u0631\u064a\u0629 \u0627\u0644\u0634\u0645\u0639\u0648\u0646"
    ],
    "name:und_x_variant":[
        "Qaryat ash Sham\u2018\u016bn"
    ],
    "wof:name":"Qaryat ash Sham'un",
    "wof:placetype":"locality"
},
  "geometry": {"coordinates":[42.4511,34.00768],"type":"Point"}
}