{
  "type": "Feature",
  "properties": {
    "gn:admin1_code":"10.0",
    "gn:admin2_code":"9166680.0",
    "gn:asciiname":"'Alwan Khudayr",
    "gn:country_code":"IQ",
    "gn:dem":39,
    "gn:feature_class":"P",
    "gn:feature_code":"PPL",
    "gn:name":"\u2018Alw\u0101n Khu\u1e11ayr",
    "gn:population":0,
    "gn:timezone":"Asia/Baghdad",
    "iso:country":"IQ",
    "name:ara_x_preferred":[
        "\u0639\u0644\u0648\u0627\u0646 \u062e\u0636\u064a\u0631"
    ],
    "name:und_x_variant":[
        "\u2018Alw\u0101n Khu\u1e11ayr"
    ],
    "wof:name":"'Alwan Khudayr",
    "wof:placetype":"locality"
},
  "geometry": {"coordinates":[44.98813,33.64667],"type":"Point"}
}