{
  "type": "Feature",
  "properties": {
    "gn:admin1_code":"14.0",
    "gn:admin2_code":"9166557.0",
    "gn:asciiname":"Salaf Jabar Karam",
    "gn:country_code":"IQ",
    "gn:dem":10,
    "gn:feature_class":"P",
    "gn:feature_code":"PPL",
    "gn:name":"Salaf Jab\u0101r Karam",
    "gn:population":0,
    "gn:timezone":"Asia/Baghdad",
    "iso:country":"IQ",
    "name:ara_x_preferred":[
        "\u0633\u0644\u0641 \u062c\u0628\u0627\u0631 \u0643\u0631\u0645"
    ],
    "name:und_x_variant":[
        "Salaf Jab\u0101r Karam"
    ],
    "wof:name":"Salaf Jabar Karam",
    "wof:placetype":"locality"
},
  "geometry": {"coordinates":[47.31384,31.65413],"type":"Point"}
}