{
  "type": "Feature",
  "properties": {
    "gn:admin1_code":"5.0",
    "gn:admin2_code":"98464.0",
    "gn:asciiname":"Hawmahr Qala",
    "gn:country_code":"IQ",
    "gn:dem":828,
    "gn:feature_class":"P",
    "gn:feature_code":"PPL",
    "gn:name":"Hawmahr Qal\u0101",
    "gn:population":0,
    "gn:timezone":"Asia/Baghdad",
    "iso:country":"IQ",
    "name:ara_x_preferred":[
        "\u0647\u0648\u0645\u0629\u0631 \u0642\u0644\u0627"
    ],
    "name:kur_x_preferred":[
        "Homer Qe\u0142a"
    ],
    "name:kur_x_variant":[
        "\u06be\u06c6\u0645\u06d5\u0631 \u0642\u06d5\u06b5\u0627"
    ],
    "name:und_x_variant":[
        "Amar Qal\u2018a",
        "\u2018Umar Qal\u2018ah",
        "Hawmahr Qal\u0101",
        "H\u014dmar Qal\u0101",
        "Homar Qala"
    ],
    "wof:name":"Hawmahr Qala",
    "wof:placetype":"locality"
},
  "geometry": {"coordinates":[45.54361,35.14530999999999],"type":"Point"}
}