{
  "type": "Feature",
  "properties": {
    "gn:admin1_code":"13.0",
    "gn:admin2_code":"94786.0",
    "gn:asciiname":"Milhe",
    "gn:country_code":"IQ",
    "gn:dem":215,
    "gn:feature_class":"P",
    "gn:feature_code":"PPL",
    "gn:name":"Milhe",
    "gn:population":0,
    "gn:timezone":"Asia/Baghdad",
    "iso:country":"IQ",
    "name:ara_x_preferred":[
        "\u062d\u0645\u0649"
    ],
    "name:kur_x_preferred":[
        "Milhe"
    ],
    "name:kur_x_variant":[
        "M\u00eel\u1e27\u00ee",
        "\u0645\u064a\u0644\u062d\u0649"
    ],
    "name:und_x_variant":[
        "\u1e28am\u00e1",
        "Milhe"
    ],
    "wof:name":"Milhe",
    "wof:placetype":"locality"
},
  "geometry": {"coordinates":[44.07619,35.34022],"type":"Point"}
}