{
  "type": "Feature",
  "properties": {
    "gn:admin1_code":"18.0",
    "gn:admin2_code":"6805736.0",
    "gn:asciiname":"Qaryat Ahmad Husayn",
    "gn:country_code":"IQ",
    "gn:dem":45,
    "gn:feature_class":"P",
    "gn:feature_code":"PPL",
    "gn:name":"Qaryat A\u1e29mad \u1e28usayn",
    "gn:population":0,
    "gn:timezone":"Asia/Baghdad",
    "iso:country":"IQ",
    "name:ara_x_preferred":[
        "\u0642\u0631\u064a\u0629 \u0627\u062d\u0645\u062f \u062d\u0633\u064a\u0646"
    ],
    "name:und_x_variant":[
        "Qaryat A\u1e29mad \u1e28usayn"
    ],
    "wof:name":"Qaryat Ahmad Husayn",
    "wof:placetype":"locality"
},
  "geometry": {"coordinates":[44.33659,34.00376],"type":"Point"}
}