{
  "type": "Feature",
  "properties": {
    "gn:admin1_code":"9.0",
    "gn:admin2_code":"90509.0",
    "gn:asciiname":"Al Bassah",
    "gn:cc2":"IQ",
    "gn:country_code":"IQ",
    "gn:dem":6,
    "gn:feature_class":"P",
    "gn:feature_code":"PPL",
    "gn:name":"Al Ba\u015f\u015fah",
    "gn:population":0,
    "gn:timezone":"Asia/Baghdad",
    "iso:country":"IQ",
    "name:ara_x_preferred":[
        "\u0627\u0644\u0628\u0635\u0629"
    ],
    "name:fas_x_preferred":[
        "\u0628\u0633\u0627\u062d"
    ],
    "name:nno_x_preferred":[
        "Al Bassah"
    ],
    "name:sco_x_preferred":[
        "Al Bassah"
    ],
    "name:sqi_x_preferred":[
        "Al Bassah"
    ],
    "name:und_x_variant":[
        "Bassa",
        "Al Ba\u015f\u015fah"
    ],
    "name:urd_x_preferred":[
        "\u0627\u0644\u0628\u0635\u06c1"
    ],
    "wof:name":"Al Bassah",
    "wof:placetype":"locality"
},
  "geometry": {"coordinates":[46.45,30.86667000000001],"type":"Point"}
}