{
  "type": "Feature",
  "properties": {
    "gn:admin1_code":"11.0",
    "gn:admin2_code":"95444.0",
    "gn:asciiname":"Baghemre Shehab",
    "gn:country_code":"IQ",
    "gn:dem":502,
    "gn:feature_class":"P",
    "gn:feature_code":"PPL",
    "gn:name":"Baghemre Shehab",
    "gn:population":0,
    "gn:timezone":"Asia/Baghdad",
    "iso:country":"IQ",
    "name:ara_x_preferred":[
        "\u0628\u0627\u063a\u0645\u0631\u0629 \u0627\u0644\u0635\u063a\u064a\u0631"
    ],
    "name:kur_x_preferred":[
        "Baghemre Shehab"
    ],
    "name:kur_x_variant":[
        "\u0628\u0627\u063a\u06d5\u0645\u0631\u06d5 \u0634\u06d5\u0647\u0627\u0628"
    ],
    "name:und_x_variant":[
        "B\u0101ghumray\u012b Ayy\u016bh",
        "Bakhumar-i Ayy\u016bb",
        "Baghamra Shah\u0101b",
        "Baghamra Shahab",
        "B\u0101ghmrah a\u015f \u015eagh\u012br"
    ],
    "wof:name":"Baghemre Shehab",
    "wof:placetype":"locality"
},
  "geometry": {"coordinates":[44.11637,36.11126],"type":"Point"}
}