{
  "type": "Feature",
  "properties": {
    "gn:admin1_code":"11.0",
    "gn:admin2_code":"9166534.0",
    "gn:asciiname":"Khirrah",
    "gn:country_code":"IQ",
    "gn:dem":705,
    "gn:feature_class":"P",
    "gn:feature_code":"PPL",
    "gn:name":"Khirrah",
    "gn:population":0,
    "gn:timezone":"Asia/Baghdad",
    "iso:country":"IQ",
    "name:ara_x_preferred":[
        "\u062e\u0631\u0647"
    ],
    "name:kur_x_preferred":[
        "Xi\u1e5fa"
    ],
    "name:kur_x_variant":[
        "\u062e\u0695\u0627",
        "Xi\u1e5fe",
        "\u062e\u0695\u06d5"
    ],
    "name:und_x_variant":[
        "Khara",
        "Khirrah",
        "\u062e\u0631\u0647",
        "Khra"
    ],
    "wof:name":"Khirrah",
    "wof:placetype":"locality"
},
  "geometry": {"coordinates":[44.41628,36.77476],"type":"Point"}
}