{
  "type": "Feature",
  "properties": {
    "gn:admin1_code":"18.0",
    "gn:admin2_code":"6783103.0",
    "gn:asciiname":"'Arab Sifah Madhi",
    "gn:country_code":"IQ",
    "gn:dem":128,
    "gn:feature_class":"P",
    "gn:feature_code":"PPLL",
    "gn:name":"\u2018Arab Sif\u0101\u1e29 Ma\u1e11\u1e29\u012b",
    "gn:population":0,
    "gn:timezone":"Asia/Baghdad",
    "iso:country":"IQ",
    "name:ara_x_preferred":[
        "\u0639\u0631\u0628 \u0633\u0641\u0627\u062d \u0645\u0636\u062d\u064a"
    ],
    "name:und_x_variant":[
        "\u2018Arab Sif\u0101\u1e29 Ma\u1e11\u1e29\u012b"
    ],
    "wof:name":"'Arab Sifah Madhi",
    "wof:placetype":"locality"
},
  "geometry": {"coordinates":[44.0697,34.71764],"type":"Point"}
}