{
  "type": "Feature",
  "properties": {
    "gn:admin1_code":"18.0",
    "gn:admin2_code":"6783103.0",
    "gn:asciiname":"'Arab Mahdi Faydi",
    "gn:country_code":"IQ",
    "gn:dem":55,
    "gn:feature_class":"P",
    "gn:feature_code":"PPL",
    "gn:name":"\u2018Arab Mahd\u012b Fay\u1e11\u012b",
    "gn:population":0,
    "gn:timezone":"Asia/Baghdad",
    "iso:country":"IQ",
    "name:ara_x_preferred":[
        "\u0639\u0631\u0628 \u0645\u0647\u062f\u064a \u0641\u064a\u0636\u064a"
    ],
    "name:und_x_variant":[
        "\u2018Arab Mahd\u012b Fay\u1e11\u012b"
    ],
    "wof:name":"'Arab Mahdi Faydi",
    "wof:placetype":"locality"
},
  "geometry": {"coordinates":[44.07876,34.09220999999999],"type":"Point"}
}