{
  "type": "Feature",
  "properties": {
    "gn:admin1_code":"12.0",
    "gn:admin2_code":"94822.0",
    "gn:asciiname":"'Abd Mufid",
    "gn:country_code":"IQ",
    "gn:dem":27,
    "gn:feature_class":"P",
    "gn:feature_code":"PPL",
    "gn:name":"\u2018Abd Muf\u012b\u1e11",
    "gn:population":0,
    "gn:timezone":"Asia/Baghdad",
    "iso:country":"IQ",
    "name:ara_x_preferred":[
        "\u0639\u0628\u062f \u0645\u0641\u064a\u0636"
    ],
    "name:ara_x_variant":[
        "\u2018Abd Muf\u012b\u1e11"
    ],
    "wof:name":"'Abd Mufid",
    "wof:placetype":"locality"
},
  "geometry": {"coordinates":[43.99223,32.67208],"type":"Point"}
}