{
  "type": "Feature",
  "properties": {
    "gn:admin1_code":"6.0",
    "gn:admin2_code":"99358.0",
    "gn:asciiname":"'Arab Ghazi",
    "gn:country_code":"IQ",
    "gn:dem":28,
    "gn:feature_class":"P",
    "gn:feature_code":"PPLL",
    "gn:name":"\u2018Arab Gh\u0101z\u012b",
    "gn:population":0,
    "gn:timezone":"Asia/Baghdad",
    "iso:country":"IQ",
    "name:ara_x_preferred":[
        "\u0639\u0631\u0628 \u063a\u0627\u0632\u064a"
    ],
    "name:und_x_variant":[
        "\u2018Arab Gh\u0101z\u012b"
    ],
    "wof:name":"'Arab Ghazi",
    "wof:placetype":"locality"
},
  "geometry": {"coordinates":[44.75975,32.33754],"type":"Point"}
}