{
  "type": "Feature",
  "properties": {
    "gn:admin1_code":"10.0",
    "gn:admin2_code":"94296.0",
    "gn:asciiname":"'Ali Saray as Sufla",
    "gn:country_code":"IQ",
    "gn:dem":121,
    "gn:feature_class":"P",
    "gn:feature_code":"PPL",
    "gn:name":"\u2018Al\u012b Sar\u0101y as Sufl\u00e1",
    "gn:population":0,
    "gn:timezone":"Asia/Baghdad",
    "iso:country":"IQ",
    "name:ara_x_preferred":[
        "\u0639\u0644\u064a \u0633\u0631\u0627\u064a \u0627\u0644\u0633\u0641\u0644\u0649"
    ],
    "name:und_x_variant":[
        "\u2018Al\u012b Sar\u0101y as Sufl\u00e1"
    ],
    "wof:name":"'Ali Saray as Sufla",
    "wof:placetype":"locality"
},
  "geometry": {"coordinates":[44.89647,34.44864],"type":"Point"}
}