{
  "type": "Feature",
  "properties": {
    "gn:admin1_code":"4.0",
    "gn:admin2_code":"6850588.0",
    "gn:asciiname":"Karim al 'Inad",
    "gn:country_code":"IQ",
    "gn:dem":14,
    "gn:feature_class":"P",
    "gn:feature_code":"PPL",
    "gn:name":"Kar\u012bm al \u2018In\u0101d",
    "gn:population":0,
    "gn:timezone":"Asia/Baghdad",
    "iso:country":"IQ",
    "name:ara_x_preferred":[
        "\u0643\u0631\u064a\u0645 \u0627\u0644\u0639\u0646\u0627\u062f"
    ],
    "name:und_x_variant":[
        "Kar\u012bm al \u2018In\u0101d"
    ],
    "wof:name":"Karim al 'Inad",
    "wof:placetype":"locality"
},
  "geometry": {"coordinates":[45.03383,31.59447],"type":"Point"}
}