{
  "type": "Feature",
  "properties": {
    "gn:admin1_code":"4.0",
    "gn:admin2_code":"99763.0",
    "gn:asciiname":"Al Hajj Ruhayt",
    "gn:country_code":"IQ",
    "gn:dem":22,
    "gn:feature_class":"P",
    "gn:feature_code":"PPL",
    "gn:name":"Al \u1e28\u0101jj Ruhay\u0163",
    "gn:population":0,
    "gn:timezone":"Asia/Baghdad",
    "iso:country":"IQ",
    "name:ara_x_preferred":[
        "\u0627\u0644\u062d\u0627\u062c \u0631\u0647\u064a\u0637"
    ],
    "name:und_x_variant":[
        "Al \u1e28\u0101jj Ruhay\u0163"
    ],
    "wof:name":"Al Hajj Ruhayt",
    "wof:placetype":"locality"
},
  "geometry": {"coordinates":[44.88009,31.88247],"type":"Point"}
}