{
  "type": "Feature",
  "properties": {
    "gn:admin1_code":"10.0",
    "gn:admin2_code":"99063.0",
    "gn:asciiname":"Qaryat Sunsul",
    "gn:country_code":"IQ",
    "gn:dem":57,
    "gn:feature_class":"P",
    "gn:feature_code":"PPL",
    "gn:name":"Qaryat Sunsul",
    "gn:population":0,
    "gn:timezone":"Asia/Baghdad",
    "iso:country":"IQ",
    "name:ara_x_preferred":[
        "\u0642\u0631\u064a\u0629 \u0633\u0646\u0633\u0644"
    ],
    "name:und_x_variant":[
        "Qaryat Shunshul",
        "Al \u2018Ukayd\u0101t",
        "\u0627\u0644\u0639\u0643\u064a\u062f\u0627\u062a",
        "\u0642\u0631\u064a\u0629 \u0634\u0646\u0634\u0644",
        "Qaryat Sunsul"
    ],
    "wof:name":"Qaryat Sunsul",
    "wof:placetype":"locality"
},
  "geometry": {"coordinates":[44.87693,33.9942],"type":"Point"}
}