{
  "type": "Feature",
  "properties": {
    "gn:admin1_code":"1.0",
    "gn:admin2_code":"98718.0",
    "gn:asciiname":"Al Khalidiyah",
    "gn:country_code":"IQ",
    "gn:dem":53,
    "gn:feature_class":"P",
    "gn:feature_code":"PPL",
    "gn:name":"Al Kh\u0101lid\u012byah",
    "gn:population":0,
    "gn:timezone":"Asia/Baghdad",
    "iso:country":"IQ",
    "name:und_x_variant":[
        "Al Kh\u0101lid\u012byah"
    ],
    "wof:name":"Al Khalidiyah",
    "wof:placetype":"locality"
},
  "geometry": {"coordinates":[43.52722,33.38333],"type":"Point"}
}