{
  "type": "Feature",
  "properties": {
    "gn:admin1_code":"5.0",
    "gn:admin2_code":"9166600.0",
    "gn:asciiname":"Sharwayran",
    "gn:cc2":"IQ",
    "gn:country_code":"IQ",
    "gn:dem":604,
    "gn:feature_class":"P",
    "gn:feature_code":"PPL",
    "gn:name":"Sharwayr\u0101n",
    "gn:population":0,
    "gn:timezone":"Asia/Baghdad",
    "iso:country":"IQ",
    "name:und_x_variant":[
        "Shar Wairah",
        "Shar Wairan",
        "Sharwayr\u0101n"
    ],
    "wof:name":"Sharwayran",
    "wof:placetype":"locality"
},
  "geometry": {"coordinates":[45.36667,34.88333],"type":"Point"}
}