{
  "type": "Feature",
  "properties": {
    "gn:admin1_code":"11.0",
    "gn:admin2_code":"9166592.0",
    "gn:asciiname":"Bilesinan",
    "gn:country_code":"IQ",
    "gn:dem":1016,
    "gn:feature_class":"P",
    "gn:feature_code":"PPL",
    "gn:name":"Bilesinan",
    "gn:population":0,
    "gn:timezone":"Asia/Baghdad",
    "iso:country":"IQ",
    "name:kur_x_preferred":[
        "Bilesinan"
    ],
    "name:kur_x_variant":[
        "\u0628\u0644\u06d5\u0633\u0646\u0627\u0646"
    ],
    "name:und_x_variant":[
        "Bal\u012bsin\u0101n",
        "Belisinan",
        "Blasnan"
    ],
    "wof:name":"Bilesinan",
    "wof:placetype":"locality"
},
  "geometry": {"coordinates":[44.53764,36.91931],"type":"Point"}
}