{
  "type": "Feature",
  "properties": {
    "gn:admin1_code":"4.0",
    "gn:admin2_code":"6850588.0",
    "gn:asciiname":"Fahd Radi",
    "gn:country_code":"IQ",
    "gn:dem":16,
    "gn:feature_class":"P",
    "gn:feature_code":"PPL",
    "gn:name":"Fahd R\u0101\u1e11\u012b",
    "gn:population":0,
    "gn:timezone":"Asia/Baghdad",
    "iso:country":"IQ",
    "name:ara_x_preferred":[
        "\u0641\u0647\u0631 \u0631\u0627\u0636\u064a"
    ],
    "name:und_x_variant":[
        "Fahd R\u0101\u1e11\u012b"
    ],
    "wof:name":"Fahd Radi",
    "wof:placetype":"locality"
},
  "geometry": {"coordinates":[44.93944000000001,31.46604],"type":"Point"}
}