{
  "type": "Feature",
  "properties": {
    "gn:admin1_code":"6.0",
    "gn:admin2_code":"99040.0",
    "gn:asciiname":"Su'ud Darwish",
    "gn:country_code":"IQ",
    "gn:dem":37,
    "gn:feature_class":"P",
    "gn:feature_code":"PPL",
    "gn:name":"Su\u2018\u016bd Darw\u012bsh",
    "gn:population":0,
    "gn:timezone":"Asia/Baghdad",
    "iso:country":"IQ",
    "name:ara_x_preferred":[
        "\u0633\u0639\u0648\u062f \u062f\u0631\u0648\u064a\u0634"
    ],
    "name:und_x_variant":[
        "Su\u2018\u016bd Darw\u012bsh"
    ],
    "wof:name":"Su'ud Darwish",
    "wof:placetype":"locality"
},
  "geometry": {"coordinates":[44.40552,32.61272],"type":"Point"}
}