{
  "type": "Feature",
  "properties": {
    "gn:admin1_code":"1.0",
    "gn:admin2_code":"99455.0",
    "gn:asciiname":"Qaryat Albu Sawdah",
    "gn:country_code":"IQ",
    "gn:dem":38,
    "gn:feature_class":"P",
    "gn:feature_code":"PPL",
    "gn:name":"Qaryat \u0100lb\u016b Sawdah",
    "gn:population":0,
    "gn:timezone":"Asia/Baghdad",
    "iso:country":"IQ",
    "name:ara_x_preferred":[
        "\u0642\u0631\u064a\u0629 \u0627\u0644\u0628\u0648 \u0633\u0648\u062f\u0647"
    ],
    "name:und_x_variant":[
        "Qaryat \u0100lb\u016b Sawdah"
    ],
    "wof:name":"Qaryat Albu Sawdah",
    "wof:placetype":"locality"
},
  "geometry": {"coordinates":[43.92017,33.4339],"type":"Point"}
}