{
  "type": "Feature",
  "properties": {
    "gn:admin1_code":"15.0",
    "gn:admin2_code":"90392.0",
    "gn:asciiname":"Bizawnah",
    "gn:country_code":"IQ",
    "gn:dem":382,
    "gn:feature_class":"P",
    "gn:feature_code":"PPL",
    "gn:name":"Bizawnah",
    "gn:population":0,
    "gn:timezone":"Asia/Baghdad",
    "iso:country":"IQ",
    "name:ara_x_preferred":[
        "\u0628\u0632\u064e\u0648\u0646\u0629"
    ],
    "name:kur_x_preferred":[
        "Mrune"
    ],
    "name:kur_x_variant":[
        "\u0645\u0631\u0648\u0646\u06d5"
    ],
    "name:und_x_variant":[
        "Mruna",
        "Bizawnah"
    ],
    "wof:name":"Bizawnah",
    "wof:placetype":"locality"
},
  "geometry": {"coordinates":[41.94652,36.62264],"type":"Point"}
}