{
  "type": "Feature",
  "properties": {
    "gn:admin1_code":"16.0",
    "gn:admin2_code":"99351.0",
    "gn:asciiname":"Salman as Sa'dun",
    "gn:country_code":"IQ",
    "gn:dem":20,
    "gn:feature_class":"P",
    "gn:feature_code":"PPL",
    "gn:name":"Salm\u0101n as Sa\u2018d\u016bn",
    "gn:population":0,
    "gn:timezone":"Asia/Baghdad",
    "iso:country":"IQ",
    "name:ara_x_preferred":[
        "\u0633\u0644\u0645\u0627\u0646 \u0627\u0644\u0633\u0639\u062f\u0648\u0646"
    ],
    "name:und_x_variant":[
        "Salm\u0101n as Sa\u2018d\u016bn"
    ],
    "wof:name":"Salman as Sa'dun",
    "wof:placetype":"locality"
},
  "geometry": {"coordinates":[45.92859,32.34138],"type":"Point"}
}