{
  "type": "Feature",
  "properties": {
    "gn:admin1_code":"5.0",
    "gn:admin2_code":"9166684.0",
    "gn:asciiname":"Lalah",
    "gn:country_code":"IQ",
    "gn:dem":1471,
    "gn:feature_class":"P",
    "gn:feature_code":"PPL",
    "gn:name":"L\u0101lah",
    "gn:population":0,
    "gn:timezone":"Asia/Baghdad",
    "iso:country":"IQ",
    "name:fas_x_preferred":[
        "\u0644\u0627\u0644\u0647"
    ],
    "wof:name":"Lalah",
    "wof:placetype":"locality"
},
  "geometry": {"coordinates":[46.2083,35.7484],"type":"Point"}
}