{
  "type": "Feature",
  "properties": {
    "gn:admin1_code":"14.0",
    "gn:admin2_code":"92536.0",
    "gn:asciiname":"Albu Bulaysim",
    "gn:cc2":"IQ",
    "gn:country_code":"IQ",
    "gn:dem":4,
    "gn:feature_class":"P",
    "gn:feature_code":"PPL",
    "gn:name":"\u0100lb\u016b Bulaysim",
    "gn:population":0,
    "gn:timezone":"Asia/Baghdad",
    "iso:country":"IQ",
    "name:und_x_variant":[
        "Al Bu Bulaisim",
        "\u0100lb\u016b Bulaysim"
    ],
    "wof:name":"Albu Bulaysim",
    "wof:placetype":"locality"
},
  "geometry": {"coordinates":[47.53333,31.38333],"type":"Point"}
}