{
  "type": "Feature",
  "properties": {
    "gn:admin1_code":"1.0",
    "gn:admin2_code":"99455.0",
    "gn:asciiname":"Qaryat al 'Ankur",
    "gn:country_code":"IQ",
    "gn:dem":45,
    "gn:feature_class":"P",
    "gn:feature_code":"PPL",
    "gn:name":"Qaryat al \u2018Ank\u016br",
    "gn:population":0,
    "gn:timezone":"Asia/Baghdad",
    "iso:country":"IQ",
    "name:ara_x_preferred":[
        "\u0642\u0631\u064a\u0629 \u0627\u0644\u0639\u0646\u06a9\u0648\u0631"
    ],
    "name:und_x_variant":[
        "Qaryat al \u2018Ank\u016br"
    ],
    "wof:name":"Qaryat al 'Ankur",
    "wof:placetype":"locality"
},
  "geometry": {"coordinates":[43.83138,33.18905],"type":"Point"}
}