{
  "type": "Feature",
  "properties": {
    "gn:admin1_code":"6.0",
    "gn:admin2_code":"99358.0",
    "gn:asciiname":"Salman",
    "gn:country_code":"IQ",
    "gn:dem":25,
    "gn:feature_class":"P",
    "gn:feature_code":"PPL",
    "gn:name":"Salm\u0101n",
    "gn:population":0,
    "gn:timezone":"Asia/Baghdad",
    "iso:country":"IQ",
    "name:ara_x_preferred":[
        "\u0633\u0644\u0645\u0627\u0646"
    ],
    "name:ceb_x_preferred":[
        "Salman"
    ],
    "name:deu_x_preferred":[
        "Salman"
    ],
    "name:fra_x_preferred":[
        "Salman"
    ],
    "name:heb_x_preferred":[
        "\u05e1\u05dc\u05de\u05d0\u05df"
    ],
    "name:jpn_x_preferred":[
        "\u30b5\u30eb\u30de\u30fc\u30f3"
    ],
    "name:msa_x_preferred":[
        "Salman"
    ],
    "name:pol_x_preferred":[
        "Salman"
    ],
    "name:rus_x_preferred":[
        "\u0421\u0430\u043b\u043c\u0430\u043d"
    ],
    "name:swe_x_preferred":[
        "Salman"
    ],
    "name:tgk_x_preferred":[
        "\u0421\u0430\u043b\u043c\u043e\u043d"
    ],
    "name:tur_x_preferred":[
        "Salman"
    ],
    "name:und_x_variant":[
        "Salm\u0101n"
    ],
    "wof:name":"Salman",
    "wof:placetype":"locality"
},
  "geometry": {"coordinates":[44.90167,32.28012],"type":"Point"}
}