{
  "type": "Feature",
  "properties": {
    "gn:admin1_code":"17.0",
    "gn:admin2_code":"9166629.0",
    "gn:asciiname":"Ni'mat Sa'd",
    "gn:country_code":"IQ",
    "gn:dem":26,
    "gn:feature_class":"P",
    "gn:feature_code":"PPL",
    "gn:name":"Ni\u2018mat Sa\u2018d",
    "gn:population":0,
    "gn:timezone":"Asia/Baghdad",
    "iso:country":"IQ",
    "name:ara_x_preferred":[
        "\u0646\u0639\u0645\u0629 \u0633\u0639\u062f"
    ],
    "name:und_x_variant":[
        "Ni\u2018mat Sa\u2018d"
    ],
    "wof:name":"Ni'mat Sa'd",
    "wof:placetype":"locality"
},
  "geometry": {"coordinates":[44.52778,32.02861],"type":"Point"}
}