{
  "type": "Feature",
  "properties": {
    "gn:admin1_code":"18.0",
    "gn:admin2_code":"9166598.0",
    "gn:asciiname":"Nuzul",
    "gn:country_code":"IQ",
    "gn:dem":356,
    "gn:feature_class":"P",
    "gn:feature_code":"PPL",
    "gn:name":"N\u016bz\u016bl",
    "gn:population":0,
    "gn:timezone":"Asia/Baghdad",
    "iso:country":"IQ",
    "name:ara_x_preferred":[
        "\u0646\u0648\u0632\u0648\u0644"
    ],
    "name:ara_x_variant":[
        "N\u016bz\u016bl"
    ],
    "name:und_x_variant":[
        "Nozhol",
        "Nujul",
        "Nujaylah",
        "Nojol"
    ],
    "wof:name":"Nuzul",
    "wof:placetype":"locality"
},
  "geometry": {"coordinates":[44.77548,34.97969000000001],"type":"Point"}
}