{
  "type": "Feature",
  "properties": {
    "gn:admin1_code":"15.0",
    "gn:admin2_code":"9166649.0",
    "gn:asciiname":"Qaryat az Ziftiyah",
    "gn:country_code":"IQ",
    "gn:dem":341,
    "gn:feature_class":"P",
    "gn:feature_code":"PPL",
    "gn:name":"Qaryat az Zift\u012byah",
    "gn:population":0,
    "gn:timezone":"Asia/Baghdad",
    "iso:country":"IQ",
    "name:ara_x_preferred":[
        "\u0642\u0631\u064a\u0629 \u0627\u0644\u0632\u0641\u062a\u064a\u0629"
    ],
    "name:und_x_variant":[
        "Qaryat az Zift\u012byah"
    ],
    "wof:name":"Qaryat az Ziftiyah",
    "wof:placetype":"locality"
},
  "geometry": {"coordinates":[43.08292,36.15825],"type":"Point"}
}