{
  "type": "Feature",
  "properties": {
    "gn:admin1_code":"9.0",
    "gn:admin2_code":"98855.0",
    "gn:asciiname":"Sayyid 'Aziz",
    "gn:country_code":"IQ",
    "gn:dem":6,
    "gn:feature_class":"P",
    "gn:feature_code":"PPL",
    "gn:name":"Sayyid \u2018Az\u012bz",
    "gn:population":0,
    "gn:timezone":"Asia/Baghdad",
    "iso:country":"IQ",
    "name:und_x_variant":[
        "Saiyid Aziz",
        "Sayyid \u2018Az\u012bz"
    ],
    "wof:name":"Sayyid 'Aziz",
    "wof:placetype":"locality"
},
  "geometry": {"coordinates":[46.41667,31.26667],"type":"Point"}
}