{
  "type": "Feature",
  "properties": {
    "gn:admin1_code":"7.0",
    "gn:admin2_code":"9166545.0",
    "gn:asciiname":"Kazim al Jawad",
    "gn:cc2":"IQ",
    "gn:country_code":"IQ",
    "gn:dem":45,
    "gn:feature_class":"P",
    "gn:feature_code":"PPL",
    "gn:name":"K\u0101z\u0327im al Jaw\u0101d",
    "gn:population":0,
    "gn:timezone":"Asia/Baghdad",
    "iso:country":"IQ",
    "name:und_x_variant":[
        "Qal\u2018at K\u0101z\u0327im al Jaw\u0101d",
        "Kadhim al Jaw\u0101d",
        "K\u0101z\u0327im al Jaw\u0101d"
    ],
    "wof:name":"Kazim al Jawad",
    "wof:placetype":"locality"
},
  "geometry": {"coordinates":[44.43333,33.28333],"type":"Point"}
}