{
  "type": "Feature",
  "properties": {
    "gn:admin1_code":"15.0",
    "gn:admin2_code":"9166620.0",
    "gn:asciiname":"Tall al Jarabi'",
    "gn:country_code":"IQ",
    "gn:dem":263,
    "gn:feature_class":"P",
    "gn:feature_code":"PPL",
    "gn:name":"Tall al Jar\u0101b\u012b\u2018",
    "gn:population":0,
    "gn:timezone":"Asia/Baghdad",
    "iso:country":"IQ",
    "name:ara_x_preferred":[
        "\u062a\u0644 \u0627\u0644\u062c\u0631\u0627\u0628\u064a\u0639"
    ],
    "name:und_x_variant":[
        "Tall al Jar\u0101b\u012b\u2018"
    ],
    "wof:name":"Tall al Jarabi'",
    "wof:placetype":"locality"
},
  "geometry": {"coordinates":[42.38382,36.1384],"type":"Point"}
}