{
  "type": "Feature",
  "properties": {
    "gn:admin1_code":"10.0",
    "gn:admin2_code":"94590.0",
    "gn:asciiname":"Tanurah",
    "gn:country_code":"IQ",
    "gn:dem":290,
    "gn:feature_class":"P",
    "gn:feature_code":"PPL",
    "gn:name":"Tan\u016brah",
    "gn:population":0,
    "gn:timezone":"Asia/Baghdad",
    "iso:country":"IQ",
    "name:ara_x_preferred":[
        "\u062a\u0646\u0648\u0631\u0647"
    ],
    "name:fas_x_preferred":[
        "Nat\u016breh"
    ],
    "name:fas_x_variant":[
        "\u0646\u062a\u0648\u0631\u0647"
    ],
    "name:und_x_variant":[
        "Tann\u016brah",
        "Tanora",
        "Tan\u016brah"
    ],
    "wof:name":"Tanurah",
    "wof:placetype":"locality"
},
  "geometry": {"coordinates":[45.52,34.6655],"type":"Point"}
}