{
  "type": "Feature",
  "properties": {
    "gn:admin1_code":"9.0",
    "gn:admin2_code":"90509.0",
    "gn:asciiname":"'Ali Sultan",
    "gn:country_code":"IQ",
    "gn:dem":8,
    "gn:feature_class":"P",
    "gn:feature_code":"PPL",
    "gn:name":"\u2018Al\u012b Sul\u0163\u0101n",
    "gn:population":0,
    "gn:timezone":"Asia/Baghdad",
    "iso:country":"IQ",
    "name:ara_x_preferred":[
        "\u0639\u0644\u064a \u0633\u0644\u0637\u0627\u0646"
    ],
    "name:ara_x_variant":[
        "\u2018Al\u012b Sul\u0163\u0101n"
    ],
    "wof:name":"'Ali Sultan",
    "wof:placetype":"locality"
},
  "geometry": {"coordinates":[46.33139,30.98027],"type":"Point"}
}