{
  "type": "Feature",
  "properties": {
    "gn:admin1_code":"7.0",
    "gn:admin2_code":"99101.0",
    "gn:asciiname":"Qarayt Bazayiz Kilu Ithnayn",
    "gn:country_code":"IQ",
    "gn:dem":36,
    "gn:feature_class":"P",
    "gn:feature_code":"PPL",
    "gn:name":"Qarayt Baz\u0101yiz K\u012bl\u016b Ithnayn",
    "gn:population":0,
    "gn:timezone":"Asia/Baghdad",
    "iso:country":"IQ",
    "name:ara_x_preferred":[
        "\u0642\u0631\u064a\u0629 \u0628\u0632\u0627\u064a\u0632 \u0643\u064a\u0644\u0648 \u0662"
    ],
    "name:und_x_variant":[
        "Qarayt Baz\u0101yiz K\u012bl\u016b Ithnayn"
    ],
    "wof:name":"Qarayt Bazayiz Kilu Ithnayn",
    "wof:placetype":"locality"
},
  "geometry": {"coordinates":[44.31169000000001,32.96485],"type":"Point"}
}