{
  "type": "Feature",
  "properties": {
    "gn:admin1_code":"15.0",
    "gn:admin2_code":"9166649.0",
    "gn:asciiname":"Qaryat al Karamah",
    "gn:country_code":"IQ",
    "gn:dem":176,
    "gn:feature_class":"P",
    "gn:feature_code":"PPL",
    "gn:name":"Qaryat al Kar\u0101mah",
    "gn:population":0,
    "gn:timezone":"Asia/Baghdad",
    "iso:country":"IQ",
    "name:ara_x_preferred":[
        "\u0642\u0631\u064a\u0629 \u0627\u0644\u0643\u0631\u0627\u0645\u0629"
    ],
    "name:und_x_variant":[
        "Qaryat al Kar\u0101mah"
    ],
    "wof:name":"Qaryat al Karamah",
    "wof:placetype":"locality"
},
  "geometry": {"coordinates":[43.32187,35.73441],"type":"Point"}
}