{
  "type": "Feature",
  "properties": {
    "gn:admin1_code":"11.0",
    "gn:admin2_code":"95444.0",
    "gn:asciiname":"Mam Zawah",
    "gn:country_code":"IQ",
    "gn:dem":368,
    "gn:feature_class":"P",
    "gn:feature_code":"PPL",
    "gn:name":"M\u0101m Z\u0101wah",
    "gn:population":0,
    "gn:timezone":"Asia/Baghdad",
    "iso:country":"IQ",
    "name:ara_x_preferred":[
        "\u0645\u0627\u0645 \u0632\u0627\u0648\u0629"
    ],
    "name:und_x_variant":[
        "M\u0101m Z\u0101wah"
    ],
    "wof:name":"Mam Zawah",
    "wof:placetype":"locality"
},
  "geometry": {"coordinates":[43.95265,36.11045],"type":"Point"}
}