{
  "type": "Feature",
  "properties": {
    "gn:admin1_code":"11.0",
    "gn:admin2_code":"95444.0",
    "gn:asciiname":"Sardasht",
    "gn:country_code":"IQ",
    "gn:dem":468,
    "gn:feature_class":"P",
    "gn:feature_code":"PPL",
    "gn:name":"Sardasht",
    "gn:population":0,
    "gn:timezone":"Asia/Baghdad",
    "iso:country":"IQ",
    "name:ara_x_preferred":[
        "\u0633\u0631\u062f\u0634\u062a"
    ],
    "name:ceb_x_preferred":[
        "Sardasht"
    ],
    "name:fas_x_preferred":[
        "\u0633\u0631\u062f\u0634\u062a"
    ],
    "name:kur_x_preferred":[
        "Serdesht"
    ],
    "name:kur_x_variant":[
        "\u0633\u06d5\u0631\u062f\u06d5\u0634\u062a"
    ],
    "name:rus_x_preferred":[
        "\u0421\u0435\u0440\u0434\u0435\u0448\u0442"
    ],
    "name:swe_x_preferred":[
        "Sardasht"
    ],
    "wof:name":"Sardasht",
    "wof:placetype":"locality"
},
  "geometry": {"coordinates":[44.09834,36.03598],"type":"Point"}
}