{
  "type": "Feature",
  "properties": {
    "gn:admin1_code":"16.0",
    "gn:admin2_code":"99132.0",
    "gn:asciiname":"Hajj Khalaf",
    "gn:country_code":"IQ",
    "gn:dem":11,
    "gn:feature_class":"P",
    "gn:feature_code":"PPL",
    "gn:name":"\u1e28\u0101jj Khalaf",
    "gn:population":0,
    "gn:timezone":"Asia/Baghdad",
    "iso:country":"IQ",
    "name:ara_x_preferred":[
        "\u062d\u0627\u062c \u062e\u0644\u0641"
    ],
    "name:und_x_variant":[
        "Kh\u0101n",
        "\u1e28\u0101jj Khalaf"
    ],
    "wof:name":"Hajj Khalaf",
    "wof:placetype":"locality"
},
  "geometry": {"coordinates":[46.26033,32.54975],"type":"Point"}
}