{
  "type": "Feature",
  "properties": {
    "gn:admin1_code":"5.0",
    "gn:admin2_code":"92051.0",
    "gn:asciiname":"Fentazi",
    "gn:country_code":"IQ",
    "gn:dem":817,
    "gn:feature_class":"P",
    "gn:feature_code":"PPL",
    "gn:name":"Fentaz\u00ee",
    "gn:population":0,
    "gn:timezone":"Asia/Baghdad",
    "iso:country":"IQ",
    "name:kur_x_preferred":[
        "Fentaz\u00ee"
    ],
    "name:kur_x_variant":[
        "\u0641\u06d5\u0646\u062a\u0627\u0632\u0649"
    ],
    "name:und_x_variant":[
        "Fantazi"
    ],
    "wof:name":"Fentazi",
    "wof:placetype":"locality"
},
  "geometry": {"coordinates":[44.7637,36.35925],"type":"Point"}
}