{
  "type": "Feature",
  "properties": {
    "gn:admin1_code":"17.0",
    "gn:admin2_code":"9166629.0",
    "gn:asciiname":"Jidam Sa'dun Hadi",
    "gn:country_code":"IQ",
    "gn:dem":26,
    "gn:feature_class":"P",
    "gn:feature_code":"PPL",
    "gn:name":"Jid\u0101m Sa\u2018d\u016bn H\u0101d\u012b",
    "gn:population":0,
    "gn:timezone":"Asia/Baghdad",
    "iso:country":"IQ",
    "name:ara_x_preferred":[
        "\u062c\u062f\u0627\u0645 \u0633\u0639\u062f\u0648\u0646 \u0647\u0627\u062f\u064a"
    ],
    "name:und_x_variant":[
        "Jid\u0101m Sa\u2018d\u016bn H\u0101d\u012b"
    ],
    "wof:name":"Jidam Sa'dun Hadi",
    "wof:placetype":"locality"
},
  "geometry": {"coordinates":[44.53562,32.02452],"type":"Point"}
}