{
  "type": "Feature",
  "properties": {
    "gn:admin1_code":"18.0",
    "gn:admin2_code":"9166616.0",
    "gn:asciiname":"'Ali Harish",
    "gn:country_code":"IQ",
    "gn:dem":46,
    "gn:feature_class":"P",
    "gn:feature_code":"PPL",
    "gn:name":"\u2018Al\u012b \u1e28ar\u012bsh",
    "gn:population":0,
    "gn:timezone":"Asia/Baghdad",
    "iso:country":"IQ",
    "name:ara_x_preferred":[
        "\u0639\u0644\u064a \u062d\u0631\u064a\u0634"
    ],
    "name:und_x_variant":[
        "\u2018Al\u012b \u1e28ar\u012bsh"
    ],
    "wof:name":"'Ali Harish",
    "wof:placetype":"locality"
},
  "geometry": {"coordinates":[44.00421,33.79336],"type":"Point"}
}