{
  "type": "Feature",
  "properties": {
    "gn:admin1_code":"6.0",
    "gn:admin2_code":"99040.0",
    "gn:asciiname":"'Abbas Na'mah",
    "gn:country_code":"IQ",
    "gn:dem":31,
    "gn:feature_class":"P",
    "gn:feature_code":"PPL",
    "gn:name":"\u2018Abb\u0101s Na\u2018mah",
    "gn:population":0,
    "gn:timezone":"Asia/Baghdad",
    "iso:country":"IQ",
    "name:ara_x_preferred":[
        "\u0639\u0628\u0627\u0633 \u0646\u0639\u0645\u0629"
    ],
    "name:und_x_variant":[
        "\u2018Abb\u0101s Na\u2018mah"
    ],
    "wof:name":"'Abbas Na'mah",
    "wof:placetype":"locality"
},
  "geometry": {"coordinates":[44.29418,32.60087],"type":"Point"}
}