{
  "type": "Feature",
  "properties": {
    "gn:admin1_code":"11.0",
    "gn:admin2_code":"9166591.0",
    "gn:asciiname":"Rashwan",
    "gn:country_code":"IQ",
    "gn:dem":352,
    "gn:feature_class":"P",
    "gn:feature_code":"PPL",
    "gn:name":"Rashw\u0101n",
    "gn:population":0,
    "gn:timezone":"Asia/Baghdad",
    "iso:country":"IQ",
    "name:ara_x_preferred":[
        "\u0631\u0634\u0648\u0627\u0646"
    ],
    "name:deu_x_preferred":[
        "Rashwan"
    ],
    "name:kur_x_preferred":[
        "\u1e5eeshwan"
    ],
    "name:kur_x_variant":[
        "\u0695\u06d5\u0634\u0648\u0627\u0646"
    ],
    "name:und_x_variant":[
        "Rashw\u0101n"
    ],
    "wof:name":"Rashwan",
    "wof:placetype":"locality"
},
  "geometry": {"coordinates":[43.91024,36.4314],"type":"Point"}
}