{
  "type": "Feature",
  "properties": {
    "gn:admin1_code":"13.0",
    "gn:admin2_code":"6770659.0",
    "gn:asciiname":"Qaryat al Madmumah",
    "gn:country_code":"IQ",
    "gn:dem":182,
    "gn:feature_class":"P",
    "gn:feature_code":"PPL",
    "gn:name":"Qaryat al Ma\u1e11m\u016bmah",
    "gn:population":0,
    "gn:timezone":"Asia/Baghdad",
    "iso:country":"IQ",
    "name:ara_x_preferred":[
        "\u0642\u0631\u064a\u0629 \u0627\u0644\u0645\u0636\u0645\u0648\u0645\u0629"
    ],
    "name:und_x_variant":[
        "Qaryat al Ma\u1e11m\u016bmah"
    ],
    "wof:name":"Qaryat al Madmumah",
    "wof:placetype":"locality"
},
  "geometry": {"coordinates":[43.91166,35.09619],"type":"Point"}
}