{
  "type": "Feature",
  "properties": {
    "gn:admin1_code":"7.0",
    "gn:admin2_code":"9167085.0",
    "gn:asciiname":"Al Masraf al Gharbi",
    "gn:cc2":"IQ",
    "gn:country_code":"IQ",
    "gn:dem":40,
    "gn:feature_class":"P",
    "gn:feature_code":"PPL",
    "gn:name":"Al Ma\u015fraf al Gharb\u012b",
    "gn:population":0,
    "gn:timezone":"Asia/Baghdad",
    "iso:country":"IQ",
    "name:und_x_variant":[
        "Masraf al Gharbi",
        "Ma\u015fraf",
        "Al Ma\u015fraf al Gharb\u012b"
    ],
    "wof:name":"Al Masraf al Gharbi",
    "wof:placetype":"locality"
},
  "geometry": {"coordinates":[44.30694,33.52444000000001],"type":"Point"}
}