{
  "type": "Feature",
  "properties": {
    "gn:admin1_code":"16.0",
    "gn:admin2_code":"98460.0",
    "gn:asciiname":"Sayyid Tahir",
    "gn:country_code":"IQ",
    "gn:dem":26,
    "gn:feature_class":"P",
    "gn:feature_code":"PPL",
    "gn:name":"Sayyid \u0162\u0101hir",
    "gn:population":0,
    "gn:timezone":"Asia/Baghdad",
    "iso:country":"IQ",
    "name:ara_x_preferred":[
        "\u0633\u064a\u062f \u0637\u0627\u0647\u0631"
    ],
    "name:und_x_variant":[
        "Sayyid \u0162\u0101hir"
    ],
    "wof:name":"Sayyid Tahir",
    "wof:placetype":"locality"
},
  "geometry": {"coordinates":[45.04923,32.87184],"type":"Point"}
}