{
  "type": "Feature",
  "properties": {
    "gn:admin1_code":"1.0",
    "gn:admin2_code":"9166579.0",
    "gn:asciiname":"Marabidiyah",
    "gn:cc2":"IQ",
    "gn:country_code":"IQ",
    "gn:dem":74,
    "gn:feature_class":"P",
    "gn:feature_code":"PPL",
    "gn:name":"Mar\u0101bid\u012byah",
    "gn:population":0,
    "gn:timezone":"Asia/Baghdad",
    "iso:country":"IQ",
    "name:und_x_variant":[
        "Mar\u0101bd\u012bya",
        "Mur\u0101biyah",
        "Mar\u0101bid\u012byah"
    ],
    "wof:name":"Marabidiyah",
    "wof:placetype":"locality"
},
  "geometry": {"coordinates":[42.63333,33.90361],"type":"Point"}
}