{
  "type": "Feature",
  "properties": {
    "gn:admin1_code":"11.0",
    "gn:admin2_code":"9166588.0",
    "gn:asciiname":"Tall Kirdi 'Abdalan",
    "gn:country_code":"IQ",
    "gn:dem":522,
    "gn:feature_class":"P",
    "gn:feature_code":"PPL",
    "gn:name":"Tall Kird\u012b \u2018Abd\u0101l\u0101n",
    "gn:population":0,
    "gn:timezone":"Asia/Baghdad",
    "iso:country":"IQ",
    "name:ara_x_preferred":[
        "\u062a\u0644 \u0643\u0631\u062f\u064a \u0639\u0628\u062f\u0627\u0644\u0627\u0646"
    ],
    "name:kur_x_preferred":[
        "\u0639\u06d5\u0628\u062f\u0627\u06b5\u0627\u0646"
    ],
    "name:kur_x_variant":[
        "\u2018Ebda\u0142an",
        "\u2018Ewda\u0142an",
        "\u0639\u06d5\u0648\u062f\u0627\u06b5\u0627\u0646"
    ],
    "name:und_x_variant":[
        "\u0100b D\u016bl\u0101n",
        "Abdalan",
        "Tall Kird\u012b \u2018Abd\u0101l\u0101n",
        "\u062a\u0644 \u0643\u0631\u062f\u064a \u0639\u0628\u062f\u0627\u0644\u0627\u0646",
        "Awdalan"
    ],
    "wof:name":"Tall Kirdi 'Abdalan",
    "wof:placetype":"locality"
},
  "geometry": {"coordinates":[44.63084,36.04039],"type":"Point"}
}