{
  "type": "Feature",
  "properties": {
    "gn:admin1_code":"10.0",
    "gn:admin2_code":"9166680.0",
    "gn:asciiname":"Mahdi al Mutlag",
    "gn:country_code":"IQ",
    "gn:dem":39,
    "gn:feature_class":"P",
    "gn:feature_code":"PPL",
    "gn:name":"Mahd\u012b al Mu\u0163lag",
    "gn:population":0,
    "gn:timezone":"Asia/Baghdad",
    "iso:country":"IQ",
    "name:ara_x_preferred":[
        "\u0645\u0647\u062f\u064a \u0627\u0644\u0645\u0637\u0644\u06af"
    ],
    "name:und_x_variant":[
        "Mahd\u012b al Mu\u0163lag"
    ],
    "wof:name":"Mahdi al Mutlag",
    "wof:placetype":"locality"
},
  "geometry": {"coordinates":[45.38213,33.51278],"type":"Point"}
}