{
  "type": "Feature",
  "properties": {
    "gn:admin1_code":"9.0",
    "gn:admin2_code":"98700.0",
    "gn:asciiname":"Khidr al Fashshakh",
    "gn:country_code":"IQ",
    "gn:dem":11,
    "gn:feature_class":"P",
    "gn:feature_code":"PPL",
    "gn:name":"Khi\u1e11r al Fashsh\u0101kh",
    "gn:population":0,
    "gn:timezone":"Asia/Baghdad",
    "iso:country":"IQ",
    "name:ara_x_preferred":[
        "\u062e\u0636\u0631 \u0627\u0644\u0641\u0634\u0627\u062e"
    ],
    "name:und_x_variant":[
        "Khi\u1e11r al Fashsh\u0101kh"
    ],
    "wof:name":"Khidr al Fashshakh",
    "wof:placetype":"locality"
},
  "geometry": {"coordinates":[46.07411,31.75251],"type":"Point"}
}