{
  "type": "Feature",
  "properties": {
    "gn:admin1_code":"5.0",
    "gn:admin2_code":"9166600.0",
    "gn:asciiname":"'Umar Aghajan",
    "gn:country_code":"IQ",
    "gn:dem":666,
    "gn:feature_class":"P",
    "gn:feature_code":"PPL",
    "gn:name":"\u2018Umar \u0100gh\u0101j\u0101n",
    "gn:population":0,
    "gn:timezone":"Asia/Baghdad",
    "iso:country":"IQ",
    "name:ara_x_preferred":[
        "\u0639\u0645\u0631 \u0627\u063a\u0627\u062c\u0627\u0646"
    ],
    "name:kur_x_preferred":[
        "\u2018Umer Agha Can Wel\u00ee"
    ],
    "name:kur_x_variant":[
        "\u2018Umer Agha",
        "\u0639\u0648\u0645\u06d5\u0631 \u0626\u0627\u063a\u0627 \u062c\u0627\u0646 \u0648\u06d5\u0644\u0649",
        "\u0639\u0648\u0645\u06d5\u0631 \u0626\u0627\u063a\u0627"
    ],
    "name:und_x_variant":[
        "\u2018Umar \u0100gh\u0101j\u0101n",
        "Omer Agha"
    ],
    "wof:name":"'Umar Aghajan",
    "wof:placetype":"locality"
},
  "geometry": {"coordinates":[45.33472,35.04522],"type":"Point"}
}