{
  "type": "Feature",
  "properties": {
    "gn:admin1_code":"14.0",
    "gn:admin2_code":"9166562.0",
    "gn:asciiname":"Al Jabaran",
    "gn:country_code":"IQ",
    "gn:dem":6,
    "gn:feature_class":"P",
    "gn:feature_code":"PPL",
    "gn:name":"Al Jab\u0101r\u0101n",
    "gn:population":0,
    "gn:timezone":"Asia/Baghdad",
    "iso:country":"IQ",
    "name:ara_x_preferred":[
        "\u0627\u0644\u062c\u0628\u0627\u0631\u0627\u0646"
    ],
    "name:und_x_variant":[
        "Al Jab\u0101r\u0101n"
    ],
    "wof:name":"Al Jabaran",
    "wof:placetype":"locality"
},
  "geometry": {"coordinates":[46.93821,31.35404],"type":"Point"}
}