{
  "type": "Feature",
  "properties": {
    "iso:country":"IQ",
    "qs:gn_pop":0,
    "qs:name":"\u0627\u0644\u0646\u0627\u0635\u0631\u064a\u0629",
    "qs:name_adm0":"Iraq",
    "qs:name_adm1":"Dhi Qar",
    "qs:photos":12,
    "qs:photos_1k":2,
    "qs:photos_9k":1,
    "qs:photos_9r":1,
    "qs:photos_all":12,
    "qs:photos_sr":1,
    "qs:placetype":"Town",
    "qs:pop_sr":"0",
    "qs:woe_adm0":23424855,
    "wof:name":"\u0627\u0644\u0646\u0627\u0635\u0631\u064a\u0629",
    "wof:placetype":"locality"
},
  "geometry": {"coordinates":[46.245523,31.0363145],"type":"Point"}
}