{
  "type": "Feature",
  "properties": {
    "gn:admin1_code":"1.0",
    "gn:admin2_code":"9166576.0",
    "gn:asciiname":"Nazwah",
    "gn:country_code":"IQ",
    "gn:dem":158,
    "gn:feature_class":"P",
    "gn:feature_code":"PPL",
    "gn:name":"Nazwah",
    "gn:population":0,
    "gn:timezone":"Asia/Baghdad",
    "iso:country":"IQ",
    "name:ara_x_preferred":[
        "\u0646\u0632\u0648\u0647"
    ],
    "wof:name":"Nazwah",
    "wof:placetype":"locality"
},
  "geometry": {"coordinates":[41.52214,34.42781],"type":"Point"}
}