{
  "type": "Feature",
  "properties": {
    "gn:admin1_code":"5.0",
    "gn:admin2_code":"91176.0",
    "gn:asciiname":"Dusah Darah",
    "gn:country_code":"IQ",
    "gn:dem":1181,
    "gn:feature_class":"P",
    "gn:feature_code":"PPL",
    "gn:name":"D\u016bsah Darah",
    "gn:population":0,
    "gn:timezone":"Asia/Baghdad",
    "iso:country":"IQ",
    "name:ara_x_preferred":[
        "\u062f\u0648\u0633\u0629 \u062f\u0631\u0647"
    ],
    "name:fas_x_preferred":[
        "\u062f\u0648\u0633\u062a\u0631\u062f\u0631\u0651\u0647"
    ],
    "name:kur_x_preferred":[
        "Dusera"
    ],
    "name:kur_x_variant":[
        "Dostedere",
        "\u062f\u0648\u0633\u06d5\u0631\u0627",
        "\u062f\u06c6\u0633\u062a\u06d5\u062f\u06d5\u0631\u06d5"
    ],
    "name:und_x_variant":[
        "D\u014dstardara",
        "Dosta Dara",
        "D\u016bsah Darah",
        "Dowstar Darreh",
        "Dusara"
    ],
    "wof:name":"Dusah Darah",
    "wof:placetype":"locality"
},
  "geometry": {"coordinates":[45.77948,35.58166],"type":"Point"}
}