{
  "type": "Feature",
  "properties": {
    "gn:admin1_code":"14.0",
    "gn:admin2_code":"99305.0",
    "gn:asciiname":"Salaf al Jayaznah",
    "gn:country_code":"IQ",
    "gn:dem":9,
    "gn:feature_class":"P",
    "gn:feature_code":"PPL",
    "gn:name":"Salaf al Jay\u0101znah",
    "gn:population":0,
    "gn:timezone":"Asia/Baghdad",
    "iso:country":"IQ",
    "name:ara_x_preferred":[
        "\u0633\u0644\u0641 \u0627\u0644\u062c\u064a\u0627\u0632\u0646\u0629"
    ],
    "name:und_x_variant":[
        "Salaf al Jay\u0101znah"
    ],
    "wof:name":"Salaf al Jayaznah",
    "wof:placetype":"locality"
},
  "geometry": {"coordinates":[46.79541,32.07171],"type":"Point"}
}