{
  "type": "Feature",
  "properties": {
    "gn:admin1_code":"13.0",
    "gn:admin2_code":"94786.0",
    "gn:asciiname":"Wastaniyah",
    "gn:country_code":"IQ",
    "gn:dem":225,
    "gn:feature_class":"P",
    "gn:feature_code":"PPL",
    "gn:name":"Was\u0163\u0101n\u012byah",
    "gn:population":0,
    "gn:timezone":"Asia/Baghdad",
    "iso:country":"IQ",
    "name:ara_x_preferred":[
        "\u0648\u0633\u0637\u0627\u0646\u064a\u0629"
    ],
    "name:kur_x_preferred":[
        "Wistania"
    ],
    "name:kur_x_variant":[
        "Westan\u00eee",
        "\u0648\u06d5\u0633\u062a\u0627\u0646\u064a\u06d5"
    ],
    "name:und_x_variant":[
        "Was\u0163\u0101n\u012byah",
        "Wistania"
    ],
    "wof:name":"Wastaniyah",
    "wof:placetype":"locality"
},
  "geometry": {"coordinates":[44.17113,35.29681],"type":"Point"}
}