{
  "type": "Feature",
  "properties": {
    "gn:admin1_code":"6.0",
    "gn:admin2_code":"99358.0",
    "gn:asciiname":"Khafir Hamad",
    "gn:country_code":"IQ",
    "gn:dem":27,
    "gn:feature_class":"P",
    "gn:feature_code":"PPL",
    "gn:name":"Khaf\u012br \u1e28amad",
    "gn:population":0,
    "gn:timezone":"Asia/Baghdad",
    "iso:country":"IQ",
    "name:ara_x_preferred":[
        "\u062e\u0641\u064a\u0631 \u062d\u0645\u062f"
    ],
    "name:und_x_variant":[
        "Khaf\u012br \u1e28amad"
    ],
    "wof:name":"Khafir Hamad",
    "wof:placetype":"locality"
},
  "geometry": {"coordinates":[44.80537,32.30009],"type":"Point"}
}