{
  "type": "Feature",
  "properties": {
    "gn:admin1_code":"5.0",
    "gn:admin2_code":"91176.0",
    "gn:asciiname":"Kani Waysah",
    "gn:country_code":"IQ",
    "gn:dem":1027,
    "gn:feature_class":"P",
    "gn:feature_code":"PPL",
    "gn:name":"K\u0101n\u012b Waysah",
    "gn:population":0,
    "gn:timezone":"Asia/Baghdad",
    "iso:country":"IQ",
    "name:ara_x_preferred":[
        "\u0643\u0627\u0646\u064a \u0648\u064a\u0633\u0629"
    ],
    "name:kur_x_preferred":[
        "Kan\u00ee Weyse"
    ],
    "name:kur_x_variant":[
        "\u0643\u0627\u0646\u0649 \u0648\u06d5\u064a\u0633\u06d5"
    ],
    "name:und_x_variant":[
        "K\u0101n\u012b Waysah",
        "K\u0101n\u012b W\u0113la",
        "Kani Waisa"
    ],
    "wof:name":"Kani Waysah",
    "wof:placetype":"locality"
},
  "geometry": {"coordinates":[45.55468,35.67225],"type":"Point"}
}