{
  "type": "Feature",
  "properties": {
    "gn:admin1_code":"15.0",
    "gn:admin2_code":"98820.0",
    "gn:asciiname":"Darbotk",
    "gn:country_code":"IQ",
    "gn:dem":600,
    "gn:feature_class":"P",
    "gn:feature_code":"PPL",
    "gn:name":"Darbotk",
    "gn:population":0,
    "gn:timezone":"Asia/Baghdad",
    "iso:country":"IQ",
    "name:kur_x_preferred":[
        "Derb\u00fbtik"
    ],
    "name:kur_x_variant":[
        "\u062f\u06d5\u0631\u0628\u0648\u0648\u062a\u0643"
    ],
    "wof:name":"Darbotk",
    "wof:placetype":"locality"
},
  "geometry": {"coordinates":[44.12447,36.83087],"type":"Point"}
}