{
  "type": "Feature",
  "properties": {
    "gn:admin1_code":"5.0",
    "gn:admin2_code":"98464.0",
    "gn:asciiname":"Tafan",
    "gn:country_code":"IQ",
    "gn:dem":842,
    "gn:feature_class":"P",
    "gn:feature_code":"PPL",
    "gn:name":"T\u0101f\u0101n",
    "gn:population":0,
    "gn:timezone":"Asia/Baghdad",
    "iso:country":"IQ",
    "name:ara_x_preferred":[
        "T\u0101f\u0101n"
    ],
    "name:ara_x_variant":[
        "\u062a\u0627\u0641\u0627\u0646"
    ],
    "name:kur_x_preferred":[
        "Tavan"
    ],
    "name:kur_x_variant":[
        "\u062a\u0627\u06a4\u0627\u0646"
    ],
    "name:und_x_variant":[
        "\u0162\u016bf\u0101n"
    ],
    "wof:name":"Tafan",
    "wof:placetype":"locality"
},
  "geometry": {"coordinates":[45.36461,35.30945],"type":"Point"}
}