{
  "type": "Feature",
  "properties": {
    "gn:admin1_code":"10.0",
    "gn:admin2_code":"9166680.0",
    "gn:asciiname":"Qaryat Hamid Yahya al Hasan",
    "gn:country_code":"IQ",
    "gn:dem":46,
    "gn:feature_class":"P",
    "gn:feature_code":"PPL",
    "gn:name":"Qaryat \u1e28am\u012bd Ya\u1e29y\u00e1 al \u1e28asan",
    "gn:population":0,
    "gn:timezone":"Asia/Baghdad",
    "iso:country":"IQ",
    "name:ara_x_preferred":[
        "\u0642\u0631\u064a\u0629 \u062d\u0645\u064a\u062f \u064a\u062d\u064a\u0649 \u0627\u0644\u062d\u0633\u0646"
    ],
    "name:und_x_variant":[
        "Qaryat \u1e28am\u012bd Ya\u1e29y\u00e1 al \u1e28asan"
    ],
    "wof:name":"Qaryat Hamid Yahya al Hasan",
    "wof:placetype":"locality"
},
  "geometry": {"coordinates":[45.07197,33.83707],"type":"Point"}
}