{
  "type": "Feature",
  "properties": {
    "gn:admin1_code":"6.0",
    "gn:admin2_code":"99358.0",
    "gn:asciiname":"As Sayyid Hammadi",
    "gn:country_code":"IQ",
    "gn:dem":29,
    "gn:feature_class":"P",
    "gn:feature_code":"PPL",
    "gn:name":"As Sayyid \u1e28amm\u0101d\u012b",
    "gn:population":0,
    "gn:timezone":"Asia/Baghdad",
    "iso:country":"IQ",
    "name:ara_x_preferred":[
        "\u0627\u0644\u0633\u064a\u062f \u062d\u0645\u0627\u062f\u064a"
    ],
    "name:und_x_variant":[
        "As Sayyid \u1e28amm\u0101d\u012b"
    ],
    "wof:name":"As Sayyid Hammadi",
    "wof:placetype":"locality"
},
  "geometry": {"coordinates":[44.83902,32.25810999999999],"type":"Point"}
}