{
  "type": "Feature",
  "properties": {
    "gn:admin1_code":"16.0",
    "gn:admin2_code":"9166606.0",
    "gn:asciiname":"'Imarah",
    "gn:country_code":"IQ",
    "gn:dem":20,
    "gn:feature_class":"P",
    "gn:feature_code":"PPL",
    "gn:name":"\u2018Im\u0101rah",
    "gn:population":0,
    "gn:timezone":"Asia/Baghdad",
    "iso:country":"IQ",
    "name:ara_x_preferred":[
        "\u0639\u0645\u0627\u0631\u0647"
    ],
    "name:und_x_variant":[
        "\u2018Im\u0101rah"
    ],
    "wof:name":"'Imarah",
    "wof:placetype":"locality"
},
  "geometry": {"coordinates":[45.60114,32.39485999999999],"type":"Point"}
}