{
  "type": "Feature",
  "properties": {
    "gn:admin1_code":"13.0",
    "gn:admin2_code":"6770659.0",
    "gn:asciiname":"Qaryat Thuwaym Sablan",
    "gn:country_code":"IQ",
    "gn:dem":189,
    "gn:feature_class":"P",
    "gn:feature_code":"PPL",
    "gn:name":"Qaryat Thuwaym Sabl\u0101n",
    "gn:population":0,
    "gn:timezone":"Asia/Baghdad",
    "iso:country":"IQ",
    "name:ara_x_preferred":[
        "\u0642\u0631\u064a\u0629 \u062b\u0648\u064a\u0645 \u0633\u0628\u0644\u0627\u0646"
    ],
    "name:und_x_variant":[
        "Qaryat Thuwayyim Sabl\u0101n",
        "Qaryat Thuwaym Sabl\u0101n"
    ],
    "wof:name":"Qaryat Thuwaym Sablan",
    "wof:placetype":"locality"
},
  "geometry": {"coordinates":[43.9299,35.23403],"type":"Point"}
}