{
  "type": "Feature",
  "properties": {
    "gn:admin1_code":"6.0",
    "gn:admin2_code":"6818313.0",
    "gn:asciiname":"Muwayzin Hasan",
    "gn:country_code":"IQ",
    "gn:dem":26,
    "gn:feature_class":"P",
    "gn:feature_code":"PPL",
    "gn:name":"Muwayzin \u1e28asan",
    "gn:population":0,
    "gn:timezone":"Asia/Baghdad",
    "iso:country":"IQ",
    "name:ara_x_preferred":[
        "\u0645\u0648\u064a\u0632\u0646 \u062d\u0633\u0646"
    ],
    "name:und_x_variant":[
        "Muwayzin \u1e28asan"
    ],
    "wof:name":"Muwayzin Hasan",
    "wof:placetype":"locality"
},
  "geometry": {"coordinates":[44.78108,32.66698],"type":"Point"}
}