{
  "type": "Feature",
  "properties": {
    "gn:admin1_code":"16.0",
    "gn:admin2_code":"98460.0",
    "gn:asciiname":"Dahish",
    "gn:country_code":"IQ",
    "gn:dem":30,
    "gn:feature_class":"P",
    "gn:feature_code":"PPL",
    "gn:name":"Dahish",
    "gn:population":0,
    "gn:timezone":"Asia/Baghdad",
    "iso:country":"IQ",
    "wof:name":"Dahish",
    "wof:placetype":"locality"
},
  "geometry": {"coordinates":[45.06639000000001,32.89528],"type":"Point"}
}