{
  "type": "Feature",
  "properties": {
    "gn:admin1_code":"14.0",
    "gn:admin2_code":"9166557.0",
    "gn:asciiname":"Salaf Hatab Mahud",
    "gn:country_code":"IQ",
    "gn:dem":9,
    "gn:feature_class":"P",
    "gn:feature_code":"PPL",
    "gn:name":"Salaf \u1e28a\u0163ab M\u0101h\u016bd",
    "gn:population":0,
    "gn:timezone":"Asia/Baghdad",
    "iso:country":"IQ",
    "name:ara_x_preferred":[
        "\u0633\u0644\u0641 \u062d\u0637\u0628 \u0645\u0627\u0647\u0648\u062f"
    ],
    "name:und_x_variant":[
        "Salaf \u1e28a\u0163ab M\u0101h\u016bd"
    ],
    "wof:name":"Salaf Hatab Mahud",
    "wof:placetype":"locality"
},
  "geometry": {"coordinates":[47.3313,31.61211],"type":"Point"}
}