{
  "type": "Feature",
  "properties": {
    "gn:admin1_code":"6.0",
    "gn:admin2_code":"99040.0",
    "gn:asciiname":"Madinat Babil",
    "gn:country_code":"IQ",
    "gn:dem":34,
    "gn:feature_class":"P",
    "gn:feature_code":"PPL",
    "gn:name":"Mad\u012bnat B\u0101bil",
    "gn:population":0,
    "gn:timezone":"Asia/Baghdad",
    "iso:country":"IQ",
    "name:ara_x_preferred":[
        "\u0645\u062f\u064a\u0646\u0629 \u0628\u0627\u0628\u0644"
    ],
    "name:und_x_variant":[
        "B\u0101bil",
        "Mad\u012bnat B\u0101bil"
    ],
    "wof:name":"Madinat Babil",
    "wof:placetype":"locality"
},
  "geometry": {"coordinates":[44.41477,32.53991],"type":"Point"}
}