{
  "type": "Feature",
  "properties": {
    "gn:admin1_code":"18.0",
    "gn:admin2_code":"90148.0",
    "gn:asciiname":"Muhi al Hasu",
    "gn:country_code":"IQ",
    "gn:dem":101,
    "gn:feature_class":"P",
    "gn:feature_code":"PPL",
    "gn:name":"Mu\u1e29\u012b al \u1e28as\u016b",
    "gn:population":0,
    "gn:timezone":"Asia/Baghdad",
    "iso:country":"IQ",
    "name:ara_x_preferred":[
        "\u0645\u062d\u064a \u0627\u0644\u062d\u0633\u0648"
    ],
    "name:und_x_variant":[
        "Mu\u1e29\u012b al \u1e28as\u016b"
    ],
    "wof:name":"Muhi al Hasu",
    "wof:placetype":"locality"
},
  "geometry": {"coordinates":[43.66854,34.45881],"type":"Point"}
}