{
  "type": "Feature",
  "properties": {
    "gn:admin1_code":"11.0",
    "gn:admin2_code":"9166586.0",
    "gn:asciiname":"Chawge",
    "gn:country_code":"IQ",
    "gn:dem":914,
    "gn:feature_class":"P",
    "gn:feature_code":"PPL",
    "gn:name":"Chawge",
    "gn:population":0,
    "gn:timezone":"Asia/Baghdad",
    "iso:country":"IQ",
    "name:ara_x_preferred":[
        "\u062c\u0627\u0648\u0643\u0629"
    ],
    "name:kur_x_preferred":[
        "Chawge"
    ],
    "name:kur_x_variant":[
        "\u0686\u0627\u0648\u06af\u06d5",
        "Chawege",
        "\u0686\u0627\u0648\u06d5\u06af\u06d5"
    ],
    "name:und_x_variant":[
        "J\u0101wakah",
        "J\u0101waka",
        "Jawaka",
        "Chawaga"
    ],
    "wof:name":"Chawge",
    "wof:placetype":"locality"
},
  "geometry": {"coordinates":[44.7075,36.67911],"type":"Point"}
}