{
  "type": "Feature",
  "properties": {
    "gn:admin1_code":"12.0",
    "gn:admin2_code":"99345.0",
    "gn:asciiname":"'Ali al Husayn",
    "gn:country_code":"IQ",
    "gn:dem":34,
    "gn:feature_class":"P",
    "gn:feature_code":"PPL",
    "gn:name":"\u2018Al\u012b al \u1e28usayn",
    "gn:population":0,
    "gn:timezone":"Asia/Baghdad",
    "iso:country":"IQ",
    "name:und_x_variant":[
        "\u2018Al\u012b",
        "\u2018Ali al Husain",
        "\u2018Al\u012b al \u1e28usayn"
    ],
    "wof:name":"'Ali al Husayn",
    "wof:placetype":"locality"
},
  "geometry": {"coordinates":[44.21306,32.47],"type":"Point"}
}