{
  "type": "Feature",
  "properties": {
    "gn:admin1_code":"16.0",
    "gn:admin2_code":"98460.0",
    "gn:asciiname":"Kazim Judayh",
    "gn:country_code":"IQ",
    "gn:dem":28,
    "gn:feature_class":"P",
    "gn:feature_code":"PPL",
    "gn:name":"K\u0101z\u0327im Juday\u1e29",
    "gn:population":0,
    "gn:timezone":"Asia/Baghdad",
    "iso:country":"IQ",
    "name:ara_x_preferred":[
        "\u0643\u0627\u0638\u0645 \u062c\u062f\u064a\u062d"
    ],
    "name:und_x_variant":[
        "K\u0101z\u0327im Juday\u1e29"
    ],
    "wof:name":"Kazim Judayh",
    "wof:placetype":"locality"
},
  "geometry": {"coordinates":[44.88816,32.82292],"type":"Point"}
}