{
  "type": "Feature",
  "properties": {
    "gn:admin1_code":"5.0",
    "gn:admin2_code":"9166600.0",
    "gn:asciiname":"Binkird",
    "gn:country_code":"IQ",
    "gn:dem":211,
    "gn:feature_class":"P",
    "gn:feature_code":"PPL",
    "gn:name":"Binkird",
    "gn:population":0,
    "gn:timezone":"Asia/Baghdad",
    "iso:country":"IQ",
    "name:kur_x_preferred":[
        "Bingird"
    ],
    "name:kur_x_variant":[
        "\u0628\u0646\u06af\u0631\u062f"
    ],
    "name:und_x_variant":[
        "P\u012bn Gird",
        "Binkird",
        "Bngird",
        "\u0628\u0646\u0643\u0631\u062f"
    ],
    "wof:name":"Binkird",
    "wof:placetype":"locality"
},
  "geometry": {"coordinates":[45.31615,34.61499],"type":"Point"}
}