{
  "type": "Feature",
  "properties": {
    "gn:admin1_code":"18.0",
    "gn:admin2_code":"91594.0",
    "gn:asciiname":"'Abd Khalifat 'Abbas",
    "gn:country_code":"IQ",
    "gn:dem":96,
    "gn:feature_class":"P",
    "gn:feature_code":"PPL",
    "gn:name":"\u2018Abd Khal\u012bfat \u2018Abb\u0101s",
    "gn:population":0,
    "gn:timezone":"Asia/Baghdad",
    "iso:country":"IQ",
    "name:ara_x_preferred":[
        "\u0639\u0628\u062f \u062e\u0644\u064a\u0641\u0629 \u0639\u0628\u0627\u0633"
    ],
    "name:und_x_variant":[
        "\u2018Abd Khal\u012bfat \u2018Abb\u0101s"
    ],
    "wof:name":"'Abd Khalifat 'Abbas",
    "wof:placetype":"locality"
},
  "geometry": {"coordinates":[43.46462,34.21212],"type":"Point"}
}