{
  "type": "Feature",
  "properties": {
    "gn:admin1_code":"10.0",
    "gn:admin2_code":"99063.0",
    "gn:asciiname":"Qaryat Shiqraq",
    "gn:country_code":"IQ",
    "gn:dem":59,
    "gn:feature_class":"P",
    "gn:feature_code":"PPL",
    "gn:name":"Qaryat Sh\u012bqr\u0101q",
    "gn:population":0,
    "gn:timezone":"Asia/Baghdad",
    "iso:country":"IQ",
    "name:ara_x_preferred":[
        "\u0642\u0631\u064a\u0629 \u0634\u064a\u0642\u0631\u0627\u0642"
    ],
    "name:und_x_variant":[
        "Qaryat Sh\u012bqr\u0101q"
    ],
    "wof:name":"Qaryat Shiqraq",
    "wof:placetype":"locality"
},
  "geometry": {"coordinates":[44.9166,33.99413],"type":"Point"}
}