{
  "type": "Feature",
  "properties": {
    "gn:admin1_code":"15.0",
    "gn:admin2_code":"9166608.0",
    "gn:asciiname":"Az Zahuriyah",
    "gn:country_code":"IQ",
    "gn:dem":308,
    "gn:feature_class":"P",
    "gn:feature_code":"PPL",
    "gn:name":"Az Zah\u016br\u012byah",
    "gn:population":0,
    "gn:timezone":"Asia/Baghdad",
    "iso:country":"IQ",
    "name:ara_x_preferred":[
        "\u0627\u0644\u0632\u0647\u0648\u0631\u064a\u0629"
    ],
    "name:und_x_variant":[
        "Az Zah\u016br\u012byah"
    ],
    "wof:name":"Az Zahuriyah",
    "wof:placetype":"locality"
},
  "geometry": {"coordinates":[41.48735,35.93185],"type":"Point"}
}