{
  "type": "Feature",
  "properties": {
    "gn:admin1_code":"11.0",
    "gn:admin2_code":"95444.0",
    "gn:asciiname":"Awmar Awa",
    "gn:country_code":"IQ",
    "gn:dem":319,
    "gn:feature_class":"P",
    "gn:feature_code":"PPL",
    "gn:name":"Awmar Aw\u0101",
    "gn:population":0,
    "gn:timezone":"Asia/Baghdad",
    "iso:country":"IQ",
    "name:ara_x_preferred":[
        "\u0623\u0648\u0645\u0631\u0622\u0648\u0627"
    ],
    "name:kur_x_preferred":[
        "\u0626\u06c6\u0645\u06d5\u0631\u0626\u0627\u0648\u0627"
    ],
    "name:kur_x_variant":[
        "Omerawa"
    ],
    "name:und_x_variant":[
        "\u2019\u016amr\u0101w\u0101",
        "\u2018Umar\u0101wah",
        "Awmar Aw\u0101"
    ],
    "wof:name":"Awmar Awa",
    "wof:placetype":"locality"
},
  "geometry": {"coordinates":[44.10794,35.8539],"type":"Point"}
}