{
  "type": "Feature",
  "properties": {
    "gn:admin1_code":"6.0",
    "gn:admin2_code":"99358.0",
    "gn:asciiname":"Kazim Al 'Atiyah",
    "gn:country_code":"IQ",
    "gn:dem":25,
    "gn:feature_class":"P",
    "gn:feature_code":"PPL",
    "gn:name":"K\u0101z\u0327im \u0100l \u2018A\u0163\u012byah",
    "gn:population":0,
    "gn:timezone":"Asia/Baghdad",
    "iso:country":"IQ",
    "name:ara_x_preferred":[
        "\u0643\u0627\u0638\u0645 \u0622\u0644 \u0639\u0637\u064a\u0629"
    ],
    "name:und_x_variant":[
        "K\u0101z\u0327im \u0100l \u2018A\u0163\u012byah"
    ],
    "wof:name":"Kazim Al 'Atiyah",
    "wof:placetype":"locality"
},
  "geometry": {"coordinates":[44.57988,32.32812],"type":"Point"}
}