{
  "type": "Feature",
  "properties": {
    "gn:admin1_code":"5.0",
    "gn:admin2_code":"96204.0",
    "gn:asciiname":"Zerinjo-i Khwaru",
    "gn:country_code":"IQ",
    "gn:dem":541,
    "gn:feature_class":"P",
    "gn:feature_code":"PPL",
    "gn:name":"Z\u0113rinj\u014d-i Khw\u0101r\u016b",
    "gn:population":0,
    "gn:timezone":"Asia/Baghdad",
    "iso:country":"IQ",
    "name:ara_x_preferred":[
        "Z\u0113rinj\u014d-i Khw\u0101r\u016b"
    ],
    "name:kur_x_preferred":[
        "Z\u00ea\u1e5f\u00een Co"
    ],
    "name:kur_x_variant":[
        "\u0632\u06ce\u0695\u064a\u0646 \u062c\u06c6",
        "Z\u00ea\u1e5f\u00eencoy Ser\u00fb",
        "\u0632\u06ce\u0695\u064a\u0646\u062c\u06c6\u0649 \u0633\u06d5\u0631\u0648\u0648"
    ],
    "name:und_x_variant":[
        "Zerin Jo"
    ],
    "wof:name":"Zerinjo-i Khwaru",
    "wof:placetype":"locality"
},
  "geometry": {"coordinates":[45.69139000000001,35.35833],"type":"Point"}
}