{
  "type": "Feature",
  "properties": {
    "gn:admin1_code":"11.0",
    "gn:admin2_code":"93817.0",
    "gn:asciiname":"Cadruk",
    "gn:country_code":"IQ",
    "gn:dem":248,
    "gn:feature_class":"P",
    "gn:feature_code":"PPL",
    "gn:name":"Cadruk",
    "gn:population":0,
    "gn:timezone":"Asia/Baghdad",
    "iso:country":"IQ",
    "name:ara_x_preferred":[
        "\u062c\u0627\u062f\u0631\u0648\u0643"
    ],
    "name:ara_x_variant":[
        "J\u0101dr\u016bk"
    ],
    "name:kur_x_preferred":[
        "Cadruk"
    ],
    "name:und_x_variant":[
        "Jadrok"
    ],
    "wof:name":"Cadruk",
    "wof:placetype":"locality"
},
  "geometry": {"coordinates":[43.6038,36.07505],"type":"Point"}
}