{
  "type": "Feature",
  "properties": {
    "gn:admin1_code":"2.0",
    "gn:admin2_code":"9166563.0",
    "gn:asciiname":"Qaryat at Tamar",
    "gn:country_code":"IQ",
    "gn:dem":5,
    "gn:feature_class":"P",
    "gn:feature_code":"PPL",
    "gn:name":"Qaryat at Tam\u0101r",
    "gn:population":0,
    "gn:timezone":"Asia/Baghdad",
    "iso:country":"IQ",
    "name:ara_x_preferred":[
        "\u0642\u0631\u064a\u0629 \u0627\u0644\u062a\u0645\u0627\u0631"
    ],
    "name:und_x_variant":[
        "Qaryat at Tam\u0101r"
    ],
    "wof:name":"Qaryat at Tamar",
    "wof:placetype":"locality"
},
  "geometry": {"coordinates":[47.28631,30.92396],"type":"Point"}
}