{
  "type": "Feature",
  "properties": {
    "gn:admin1_code":"18.0",
    "gn:admin2_code":"90148.0",
    "gn:asciiname":"Tha'ir Ahmad Husayn",
    "gn:country_code":"IQ",
    "gn:dem":84,
    "gn:feature_class":"P",
    "gn:feature_code":"PPL",
    "gn:name":"Th\u0101\u2019ir A\u1e29mad \u1e28usayn",
    "gn:population":0,
    "gn:timezone":"Asia/Baghdad",
    "iso:country":"IQ",
    "name:ara_x_preferred":[
        "\u062b\u0627\u0626\u0631 \u0627\u062d\u0645\u062f \u062d\u0633\u064a\u0646"
    ],
    "name:und_x_variant":[
        "Th\u0101\u2019ir A\u1e29mad \u1e28usayn"
    ],
    "wof:name":"Tha'ir Ahmad Husayn",
    "wof:placetype":"locality"
},
  "geometry": {"coordinates":[43.71419,34.41305999999999],"type":"Point"}
}