{
  "type": "Feature",
  "properties": {
    "gn:admin1_code":"18.0",
    "gn:admin2_code":"91594.0",
    "gn:asciiname":"'Ali as Salim",
    "gn:country_code":"IQ",
    "gn:dem":101,
    "gn:feature_class":"P",
    "gn:feature_code":"PPL",
    "gn:name":"\u2018Al\u012b as S\u0101lim",
    "gn:population":0,
    "gn:timezone":"Asia/Baghdad",
    "iso:country":"IQ",
    "name:ara_x_preferred":[
        "\u0639\u0644\u064a \u0627\u0644\u0633\u0627\u0644\u0645"
    ],
    "name:und_x_variant":[
        "\u2018Al\u012b as S\u0101lim"
    ],
    "wof:name":"'Ali as Salim",
    "wof:placetype":"locality"
},
  "geometry": {"coordinates":[43.62533,34.3545],"type":"Point"}
}