{
  "type": "Feature",
  "properties": {
    "gn:admin1_code":"18.0",
    "gn:admin2_code":"91594.0",
    "gn:asciiname":"Nahiyat al 'Abbasiyah",
    "gn:country_code":"IQ",
    "gn:dem":71,
    "gn:feature_class":"P",
    "gn:feature_code":"PPL",
    "gn:name":"N\u0101\u1e29iyat al \u2018Abb\u0101s\u012byah",
    "gn:population":0,
    "gn:timezone":"Asia/Baghdad",
    "iso:country":"IQ",
    "name:ara_x_preferred":[
        "\u0646\u0627\u062d\u064a\u0629 \u0627\u0644\u0639\u0628\u0627\u0633\u064a\u0629"
    ],
    "name:und_x_variant":[
        "Al \u2018Abb\u0101s\u012byah",
        "\u0627\u0644\u0639\u0628\u0627\u0633\u064a\u0629",
        "N\u0101\u1e29iyat al \u2018Abb\u0101s\u012byah"
    ],
    "wof:name":"Nahiyat al 'Abbasiyah",
    "wof:placetype":"locality"
},
  "geometry": {"coordinates":[43.78237,34.31097],"type":"Point"}
}