{
  "type": "Feature",
  "properties": {
    "gn:admin1_code":"6.0",
    "gn:admin2_code":"99358.0",
    "gn:asciiname":"'Atuf Ma'ariz",
    "gn:country_code":"IQ",
    "gn:dem":29,
    "gn:feature_class":"P",
    "gn:feature_code":"PPL",
    "gn:name":"\u2018A\u0163\u016bf Ma\u2018\u0101riz",
    "gn:population":0,
    "gn:timezone":"Asia/Baghdad",
    "iso:country":"IQ",
    "name:ara_x_preferred":[
        "\u0639\u0637\u0648\u0641 \u0645\u0639\u0627\u0631\u0632"
    ],
    "name:und_x_variant":[
        "\u2018A\u0163\u016bf Ma\u2018\u0101riz"
    ],
    "wof:name":"'Atuf Ma'ariz",
    "wof:placetype":"locality"
},
  "geometry": {"coordinates":[44.5221,32.42491],"type":"Point"}
}