{
  "type": "Feature",
  "properties": {
    "gn:admin1_code":"1.0",
    "gn:admin2_code":"9166579.0",
    "gn:asciiname":"Dulab",
    "gn:country_code":"IQ",
    "gn:dem":74,
    "gn:feature_class":"P",
    "gn:feature_code":"PPL",
    "gn:name":"D\u016bl\u0101b",
    "gn:population":0,
    "gn:timezone":"Asia/Baghdad",
    "iso:country":"IQ",
    "name:ara_x_preferred":[
        "\u062f\u0648\u0644\u0627\u0628"
    ],
    "name:ara_x_variant":[
        "D\u016bl\u0101b"
    ],
    "name:fra_x_preferred":[
        "Doulab"
    ],
    "wof:name":"Dulab",
    "wof:placetype":"locality"
},
  "geometry": {"coordinates":[42.61859000000001,33.89199],"type":"Point"}
}