{
  "type": "Feature",
  "properties": {
    "gn:admin1_code":"6.0",
    "gn:admin2_code":"99358.0",
    "gn:asciiname":"Qal'at 'Abbas ad Dakhil",
    "gn:country_code":"IQ",
    "gn:dem":26,
    "gn:feature_class":"P",
    "gn:feature_code":"PPL",
    "gn:name":"Qal\u2018at \u2018Abb\u0101s ad Dakh\u012bl",
    "gn:population":0,
    "gn:timezone":"Asia/Baghdad",
    "iso:country":"IQ",
    "name:und_x_variant":[
        "\u2018Abb\u0101s ad D\u0101kh\u012bl",
        "Qal\u2018at \u2018Abb\u0101s ad Dakh\u012bl"
    ],
    "wof:name":"Qal'at 'Abbas ad Dakhil",
    "wof:placetype":"locality"
},
  "geometry": {"coordinates":[44.86667,32.31667],"type":"Point"}
}