{
  "type": "Feature",
  "properties": {
    "gn:admin1_code":"8.0",
    "gn:admin2_code":"99612.0",
    "gn:asciiname":"Khuwari",
    "gn:country_code":"IQ",
    "gn:dem":804,
    "gn:feature_class":"P",
    "gn:feature_code":"PPL",
    "gn:name":"Khuw\u0101r\u012b",
    "gn:population":0,
    "gn:timezone":"Asia/Baghdad",
    "iso:country":"IQ",
    "name:ara_x_preferred":[
        "\u062e\u0648\u0627\u0631\u064a"
    ],
    "name:ara_x_variant":[
        "Khuw\u0101r\u012b"
    ],
    "name:kur_x_preferred":[
        "Xuwar\u00ee"
    ],
    "name:kur_x_variant":[
        "\u062e\u0648\u0627\u0631\u0649",
        "Xar\u00ee",
        "\u062e\u0627\u0631\u0649"
    ],
    "name:und_x_variant":[
        "Khaw\u0101rah",
        "Hawari",
        "Halva Fala"
    ],
    "wof:name":"Khuwari",
    "wof:placetype":"locality"
},
  "geometry": {"coordinates":[43.51967,37.19923],"type":"Point"}
}