{
  "type": "Feature",
  "properties": {
    "gn:admin1_code":"12.0",
    "gn:admin2_code":"99345.0",
    "gn:asciiname":"Majid Salih",
    "gn:country_code":"IQ",
    "gn:dem":32,
    "gn:feature_class":"P",
    "gn:feature_code":"PPL",
    "gn:name":"Maj\u012bd \u015e\u0101li\u1e29",
    "gn:population":0,
    "gn:timezone":"Asia/Baghdad",
    "iso:country":"IQ",
    "name:ara_x_preferred":[
        "\u0645\u062c\u064a\u062f \u0635\u0627\u0644\u062d"
    ],
    "name:und_x_variant":[
        "Maj\u012bd \u015e\u0101li\u1e29"
    ],
    "wof:name":"Majid Salih",
    "wof:placetype":"locality"
},
  "geometry": {"coordinates":[44.16633,32.57129],"type":"Point"}
}