{
  "type": "Feature",
  "properties": {
    "gn:admin1_code":"17.0",
    "gn:admin2_code":"9166552.0",
    "gn:asciiname":"Al Fatlah",
    "gn:country_code":"IQ",
    "gn:dem":24,
    "gn:feature_class":"P",
    "gn:feature_code":"PPLL",
    "gn:name":"\u0100l Fatlah",
    "gn:population":0,
    "gn:timezone":"Asia/Baghdad",
    "iso:country":"IQ",
    "name:ara_x_preferred":[
        "\u0622\u0644 \u0641\u062a\u0644\u0647"
    ],
    "name:und_x_variant":[
        "\u0100l Fatlah"
    ],
    "wof:name":"Al Fatlah",
    "wof:placetype":"locality"
},
  "geometry": {"coordinates":[44.46341,31.83446],"type":"Point"}
}