{
  "type": "Feature",
  "properties": {
    "gn:admin1_code":"18.0",
    "gn:admin2_code":"6872046.0",
    "gn:asciiname":"Mahal Khulayf",
    "gn:country_code":"IQ",
    "gn:dem":208,
    "gn:feature_class":"P",
    "gn:feature_code":"PPL",
    "gn:name":"Ma\u1e29al Khulayf",
    "gn:population":0,
    "gn:timezone":"Asia/Baghdad",
    "iso:country":"IQ",
    "name:ara_x_preferred":[
        "\u0645\u062d\u0644 \u062e\u0644\u064a\u0641"
    ],
    "name:und_x_variant":[
        "Ma\u1e29al Khulayf"
    ],
    "wof:name":"Mahal Khulayf",
    "wof:placetype":"locality"
},
  "geometry": {"coordinates":[43.18789,35.2932],"type":"Point"}
}