{
  "type": "Feature",
  "properties": {
    "gn:admin1_code":"10.0",
    "gn:admin2_code":"9166680.0",
    "gn:asciiname":"'Ali Aghah",
    "gn:country_code":"IQ",
    "gn:dem":111,
    "gn:feature_class":"P",
    "gn:feature_code":"PPL",
    "gn:name":"\u2018Al\u012b Aghah",
    "gn:population":0,
    "gn:timezone":"Asia/Baghdad",
    "iso:country":"IQ",
    "name:und_x_variant":[
        "\u2018Al\u012b Aghah"
    ],
    "wof:name":"'Ali Aghah",
    "wof:placetype":"locality"
},
  "geometry": {"coordinates":[45.51306,33.80833],"type":"Point"}
}