{
  "type": "Feature",
  "properties": {
    "gn:admin1_code":"15.0",
    "gn:admin2_code":"90392.0",
    "gn:asciiname":"Cham Hasnah",
    "gn:country_code":"IQ",
    "gn:dem":307,
    "gn:feature_class":"P",
    "gn:feature_code":"PPL",
    "gn:name":"Cham \u1e28asnah",
    "gn:population":0,
    "gn:timezone":"Asia/Baghdad",
    "iso:country":"IQ",
    "wof:name":"Cham Hasnah",
    "wof:placetype":"locality"
},
  "geometry": {"coordinates":[42.75,36.73333],"type":"Point"}
}