{
  "type": "Feature",
  "properties": {
    "gn:admin1_code":"5.0",
    "gn:admin2_code":"97416.0",
    "gn:asciiname":"Tappah Charmaq",
    "gn:country_code":"IQ",
    "gn:dem":458,
    "gn:feature_class":"P",
    "gn:feature_code":"PPL",
    "gn:name":"Tappah Charmaq",
    "gn:population":0,
    "gn:timezone":"Asia/Baghdad",
    "iso:country":"IQ",
    "name:und_x_variant":[
        "Tepe Charmaq",
        "Tappah Charmaq"
    ],
    "wof:name":"Tappah Charmaq",
    "wof:placetype":"locality"
},
  "geometry": {"coordinates":[44.9775,35.25556],"type":"Point"}
}