{
  "type": "Feature",
  "properties": {
    "gn:admin1_code":"11.0",
    "gn:admin2_code":"93817.0",
    "gn:asciiname":"Ad Dibakah",
    "gn:country_code":"IQ",
    "gn:dem":347,
    "gn:feature_class":"P",
    "gn:feature_code":"PPL",
    "gn:name":"Ad D\u012bbakah",
    "gn:population":0,
    "gn:timezone":"Asia/Baghdad",
    "iso:country":"IQ",
    "name:ara_x_preferred":[
        "\u0627\u0644\u062f\u064a\u0628\u0643\u0629"
    ],
    "name:kur_x_preferred":[
        "D\u00eebege"
    ],
    "name:kur_x_variant":[
        "\u062f\u064a\u0628\u06d5\u06af\u06d5"
    ],
    "name:und_x_variant":[
        "Debecka",
        "Dibikan",
        "Dibega",
        "D\u012bbagah",
        "Dibaga",
        "Ad D\u012bbakah"
    ],
    "wof:name":"Ad Dibakah",
    "wof:placetype":"locality"
},
  "geometry": {"coordinates":[43.80801,35.87528],"type":"Point"}
}