{
  "type": "Feature",
  "properties": {
    "gn:admin1_code":"18.0",
    "gn:admin2_code":"91594.0",
    "gn:asciiname":"Husayn as Sayyid",
    "gn:country_code":"IQ",
    "gn:dem":99,
    "gn:feature_class":"P",
    "gn:feature_code":"PPL",
    "gn:name":"\u1e28usayn as Sayyid",
    "gn:population":0,
    "gn:timezone":"Asia/Baghdad",
    "iso:country":"IQ",
    "name:ara_x_preferred":[
        "\u062d\u0633\u064a\u0646 \u0627\u0644\u0633\u064a\u062f"
    ],
    "name:und_x_variant":[
        "\u1e28usayn as Sayyid"
    ],
    "wof:name":"Husayn as Sayyid",
    "wof:placetype":"locality"
},
  "geometry": {"coordinates":[43.53261,34.26464],"type":"Point"}
}