{
  "type": "Feature",
  "properties": {
    "gn:admin1_code":"11.0",
    "gn:admin2_code":"9166592.0",
    "gn:asciiname":"Dayla",
    "gn:country_code":"IQ",
    "gn:dem":994,
    "gn:feature_class":"P",
    "gn:feature_code":"PPL",
    "gn:name":"Dayla",
    "gn:population":0,
    "gn:timezone":"Asia/Baghdad",
    "iso:country":"IQ",
    "name:ara_x_preferred":[
        "\u062f\u0627\u064a\u0644\u0629"
    ],
    "name:kur_x_preferred":[
        "\u062f\u0627\u064a\u0644\u0627"
    ],
    "name:kur_x_variant":[
        "D\u00eele",
        "\u062f\u064a\u0644\u06d5"
    ],
    "name:und_x_variant":[
        "Daylah",
        "Dayla",
        "Daila",
        "Dile",
        "D\u0101ylah"
    ],
    "wof:name":"Dayla",
    "wof:placetype":"locality"
},
  "geometry": {"coordinates":[44.50631,36.93361],"type":"Point"}
}