{
  "type": "Feature",
  "properties": {
    "gn:admin1_code":"15.0",
    "gn:admin2_code":"9166620.0",
    "gn:asciiname":"Mujamma` Dawmiz",
    "gn:country_code":"IQ",
    "gn:dem":420,
    "gn:feature_class":"P",
    "gn:feature_code":"PPL",
    "gn:name":"Mujamma\u2018 Dawm\u012bz",
    "gn:population":0,
    "gn:timezone":"Asia/Baghdad",
    "iso:country":"IQ",
    "name:ara_x_preferred":[
        "\u0645\u062c\u0645\u0639 \u062f\u0648\u0645\u064a\u0632"
    ],
    "name:und_x_variant":[
        "Mujamma\u2018 Dawm\u012bz"
    ],
    "wof:name":"Mujamma` Dawmiz",
    "wof:placetype":"locality"
},
  "geometry": {"coordinates":[41.82373,36.26687],"type":"Point"}
}