{
  "type": "Feature",
  "properties": {
    "gn:admin1_code":"18.0",
    "gn:admin2_code":"6872046.0",
    "gn:asciiname":"Hamid Khalifah",
    "gn:country_code":"IQ",
    "gn:dem":97,
    "gn:feature_class":"P",
    "gn:feature_code":"PPL",
    "gn:name":"\u1e28am\u012bd Khal\u012bfah",
    "gn:population":0,
    "gn:timezone":"Asia/Baghdad",
    "iso:country":"IQ",
    "name:ara_x_preferred":[
        "\u062d\u0645\u064a\u062f \u062e\u0644\u064a\u0641\u0629"
    ],
    "name:und_x_variant":[
        "\u1e28am\u012bd Khal\u012bfah"
    ],
    "wof:name":"Hamid Khalifah",
    "wof:placetype":"locality"
},
  "geometry": {"coordinates":[43.16798,34.56006],"type":"Point"}
}