{
  "type": "Feature",
  "properties": {
    "gn:admin1_code":"18.0",
    "gn:admin2_code":"90148.0",
    "gn:asciiname":"'Arab Rashid al 'Utan",
    "gn:country_code":"IQ",
    "gn:dem":123,
    "gn:feature_class":"P",
    "gn:feature_code":"PPL",
    "gn:name":"\u2018Arab Rash\u012bd al \u2018U\u0163\u0101n",
    "gn:population":0,
    "gn:timezone":"Asia/Baghdad",
    "iso:country":"IQ",
    "name:ara_x_preferred":[
        "\u0639\u0631\u0628 \u0631\u0634\u064a\u062f \u0627\u0644\u0639\u0637\u0627\u0646"
    ],
    "name:und_x_variant":[
        "\u2018Arab Rash\u012bd al \u2018U\u0163\u0101n"
    ],
    "wof:name":"'Arab Rashid al 'Utan",
    "wof:placetype":"locality"
},
  "geometry": {"coordinates":[43.43812,34.4612],"type":"Point"}
}