{
  "type": "Feature",
  "properties": {
    "gn:admin1_code":"7.0",
    "gn:admin2_code":"9166545.0",
    "gn:asciiname":"Qaryat Budaywi Radan",
    "gn:country_code":"IQ",
    "gn:dem":33,
    "gn:feature_class":"P",
    "gn:feature_code":"PPL",
    "gn:name":"Qaryat Budayw\u012b Rad\u0101n",
    "gn:population":0,
    "gn:timezone":"Asia/Baghdad",
    "iso:country":"IQ",
    "name:ara_x_preferred":[
        "\u0642\u0631\u064a\u0629 \u0628\u062f\u064a\u0648\u064a \u0631\u062f\u0627\u0646"
    ],
    "name:und_x_variant":[
        "Qaryat Budayw\u012b Rad\u0101n"
    ],
    "wof:name":"Qaryat Budaywi Radan",
    "wof:placetype":"locality"
},
  "geometry": {"coordinates":[44.44803,33.1985],"type":"Point"}
}