{
  "type": "Feature",
  "properties": {
    "gn:admin1_code":"4.0",
    "gn:admin2_code":"99763.0",
    "gn:asciiname":"Sayyid Hamid",
    "gn:country_code":"IQ",
    "gn:dem":23,
    "gn:feature_class":"P",
    "gn:feature_code":"PPL",
    "gn:name":"Sayyid \u1e28\u0101mid",
    "gn:population":0,
    "gn:timezone":"Asia/Baghdad",
    "iso:country":"IQ",
    "name:ara_x_preferred":[
        "\u0633\u064a\u062f \u062d\u0627\u0645\u062f"
    ],
    "name:und_x_variant":[
        "As Saiyid Ham\u0101di",
        "Saiyid Hammadi",
        "As Saiyid Hamm\u0101di",
        "As Sayyid \u1e28amm\u0101d\u012b",
        "Sayyid \u1e28\u0101mid"
    ],
    "wof:name":"Sayyid Hamid",
    "wof:placetype":"locality"
},
  "geometry": {"coordinates":[44.89388,31.91799],"type":"Point"}
}