{
  "type": "Feature",
  "properties": {
    "gn:admin1_code":"13.0",
    "gn:admin2_code":"94786.0",
    "gn:asciiname":"Dugmat al 'Ulya",
    "gn:country_code":"IQ",
    "gn:dem":180,
    "gn:feature_class":"P",
    "gn:feature_code":"PPL",
    "gn:name":"D\u016bgm\u0101t al \u2018Uly\u0101",
    "gn:population":0,
    "gn:timezone":"Asia/Baghdad",
    "iso:country":"IQ",
    "name:ara_x_preferred":[
        "\u062f\u0648\u06af\u0645\u0627\u062a \u0627\u0644\u0639\u0644\u064a\u0627"
    ],
    "name:und_x_variant":[
        "Dugm\u0101t",
        "D\u016bgm\u0101t al \u2018Uly\u0101"
    ],
    "wof:name":"Dugmat al 'Ulya",
    "wof:placetype":"locality"
},
  "geometry": {"coordinates":[44.05761,35.09205],"type":"Point"}
}