{
  "type": "Feature",
  "properties": {
    "gn:admin1_code":"6.0",
    "gn:admin2_code":"6818313.0",
    "gn:asciiname":"Imam Sayyid 'Isa",
    "gn:country_code":"IQ",
    "gn:dem":31,
    "gn:feature_class":"P",
    "gn:feature_code":"PPL",
    "gn:name":"Im\u0101m Sayyid \u2018\u012as\u00e1",
    "gn:population":0,
    "gn:timezone":"Asia/Baghdad",
    "iso:country":"IQ",
    "name:ara_x_preferred":[
        "\u0627\u0645\u0627\u0645 \u0633\u064a\u062f \u0639\u064a\u0633\u0649"
    ],
    "name:und_x_variant":[
        "Im\u0101m Sayyid \u2018\u012as\u00e1"
    ],
    "wof:name":"Imam Sayyid 'Isa",
    "wof:placetype":"locality"
},
  "geometry": {"coordinates":[44.46056,32.44732],"type":"Point"}
}