{
  "type": "Feature",
  "properties": {
    "gn:admin1_code":"13.0",
    "gn:admin2_code":"9166581.0",
    "gn:asciiname":"Sayyid Haydar",
    "gn:country_code":"IQ",
    "gn:dem":200,
    "gn:feature_class":"P",
    "gn:feature_code":"PPL",
    "gn:name":"Sayyid \u1e28aydar",
    "gn:population":0,
    "gn:timezone":"Asia/Baghdad",
    "iso:country":"IQ",
    "name:und_x_variant":[
        "Saiyid Haidar",
        "Sayyid \u1e28aydar"
    ],
    "wof:name":"Sayyid Haydar",
    "wof:placetype":"locality"
},
  "geometry": {"coordinates":[44.35,35.13333],"type":"Point"}
}