{
  "type": "Feature",
  "properties": {
    "gn:admin1_code":"1.0",
    "gn:admin2_code":"9166650.0",
    "gn:asciiname":"Tarifawi",
    "gn:country_code":"IQ",
    "gn:dem":209,
    "gn:feature_class":"P",
    "gn:feature_code":"PPL",
    "gn:name":"\u0162ar\u012bf\u0101w\u012b",
    "gn:population":0,
    "gn:timezone":"Asia/Baghdad",
    "iso:country":"IQ",
    "name:ara_x_preferred":[
        "\u0637\u0631\u064a\u0641\u0627\u0648\u064a"
    ],
    "name:und_x_variant":[
        "\u0162arf\u0101w\u012b",
        "\u0637\u0631\u0641\u0627\u0648\u064a",
        "\u0162ar\u012bf\u0101w\u012b"
    ],
    "wof:name":"Tarifawi",
    "wof:placetype":"locality"
},
  "geometry": {"coordinates":[41.37587,35.13548],"type":"Point"}
}