{
  "type": "Feature",
  "properties": {
    "gn:admin1_code":"7.0",
    "gn:admin2_code":"9166569.0",
    "gn:asciiname":"Qaryat an Nasiri",
    "gn:country_code":"IQ",
    "gn:dem":41,
    "gn:feature_class":"P",
    "gn:feature_code":"PPL",
    "gn:name":"Qaryat an N\u0101\u015fir\u012b",
    "gn:population":0,
    "gn:timezone":"Asia/Baghdad",
    "iso:country":"IQ",
    "name:ara_x_preferred":[
        "\u0642\u0631\u064a\u0629 \u0627\u0644\u0646\u0627\u0635\u0631\u064a"
    ],
    "name:und_x_variant":[
        "Qaryat an N\u0101\u015fir\u012b"
    ],
    "wof:name":"Qaryat an Nasiri",
    "wof:placetype":"locality"
},
  "geometry": {"coordinates":[44.24552,33.73767],"type":"Point"}
}