{
  "type": "Feature",
  "properties": {
    "gn:admin1_code":"18.0",
    "gn:admin2_code":"6872046.0",
    "gn:asciiname":"Qaryat Arunin Hadi",
    "gn:country_code":"IQ",
    "gn:dem":193,
    "gn:feature_class":"P",
    "gn:feature_code":"PPL",
    "gn:name":"Qaryat Ar\u016bn\u012bn H\u0101d\u012b",
    "gn:population":0,
    "gn:timezone":"Asia/Baghdad",
    "iso:country":"IQ",
    "name:ara_x_preferred":[
        "\u0642\u0631\u064a\u0629 \u0627\u0631\u0648\u0646\u064a\u0646 \u0647\u0627\u062f\u064a"
    ],
    "name:und_x_variant":[
        "Qaryat Ar\u016bn\u012bn H\u0101d\u012b"
    ],
    "wof:name":"Qaryat Arunin Hadi",
    "wof:placetype":"locality"
},
  "geometry": {"coordinates":[43.16683,35.2824],"type":"Point"}
}