{
  "type": "Feature",
  "properties": {
    "gn:admin1_code":"9.0",
    "gn:admin2_code":"98700.0",
    "gn:asciiname":"Mahmulat Umm al Gattah",
    "gn:country_code":"IQ",
    "gn:dem":12,
    "gn:feature_class":"P",
    "gn:feature_code":"PPL",
    "gn:name":"Ma\u1e29m\u016blat Umm al Ga\u0163\u0163ah",
    "gn:population":0,
    "gn:timezone":"Asia/Baghdad",
    "iso:country":"IQ",
    "name:ara_x_preferred":[
        "\u0645\u062d\u0645\u0648\u0644\u0629 \u0627\u0645 \u0627\u0644\u06af\u0637\u0647"
    ],
    "name:und_x_variant":[
        "Ma\u1e29m\u016blat Umm al Ga\u0163\u0163ah"
    ],
    "wof:name":"Mahmulat Umm al Gattah",
    "wof:placetype":"locality"
},
  "geometry": {"coordinates":[46.30934,31.91083],"type":"Point"}
}