{
  "type": "Feature",
  "properties": {
    "gn:admin1_code":"13.0",
    "gn:admin2_code":"9166581.0",
    "gn:asciiname":"Tukhama Khalu",
    "gn:country_code":"IQ",
    "gn:dem":281,
    "gn:feature_class":"P",
    "gn:feature_code":"PPL",
    "gn:name":"T\u016bkham\u0101 Khal\u016b",
    "gn:population":0,
    "gn:timezone":"Asia/Baghdad",
    "iso:country":"IQ",
    "name:ara_x_preferred":[
        "\u062a\u0648\u062e\u0645\u0627 \u062e\u0644\u0648"
    ],
    "name:kur_x_preferred":[
        "Toxme"
    ],
    "name:kur_x_variant":[
        "Tokhma",
        "\u062a\u06c6\u062e\u0645\u06d5"
    ],
    "name:und_x_variant":[
        "Taqm\u0101ql\u016b",
        "T\u016bqm\u0101qlu",
        "Tauq M\u0101qlu",
        "\u0162\u0101w\u016bq M\u0101ql\u016b",
        "T\u016bkham\u0101 Khal\u016b"
    ],
    "wof:name":"Tukhama Khalu",
    "wof:placetype":"locality"
},
  "geometry": {"coordinates":[44.39219,35.3565],"type":"Point"}
}