{
  "type": "Feature",
  "properties": {
    "gn:admin1_code":"5.0",
    "gn:admin2_code":"9166684.0",
    "gn:asciiname":"Shiwah Kalah",
    "gn:country_code":"IQ",
    "gn:dem":1278,
    "gn:feature_class":"P",
    "gn:feature_code":"PPL",
    "gn:name":"Sh\u012bwah K\u0101lah",
    "gn:population":0,
    "gn:timezone":"Asia/Baghdad",
    "iso:country":"IQ",
    "name:ara_x_preferred":[
        "\u0634\u064a\u0648\u0647 \u0643\u0627\u0644\u0629"
    ],
    "name:kur_x_preferred":[
        "Sh\u00eewe Ke\u0142e"
    ],
    "name:kur_x_variant":[
        "Sh\u00eewe Gu\u0142e",
        "\u0634\u064a\u0648\u06d5 \u0643\u06d5\u06b5\u06d5",
        "\u0634\u064a\u0648\u06d5 \u06af\u0648\u06b5\u06d5"
    ],
    "name:und_x_variant":[
        "Sh\u012bwah K\u0101lah",
        "Sheewakala"
    ],
    "wof:name":"Shiwah Kalah",
    "wof:placetype":"locality"
},
  "geometry": {"coordinates":[46.03668,35.78987],"type":"Point"}
}