{
  "type": "Feature",
  "properties": {
    "gn:admin1_code":"6.0",
    "gn:admin2_code":"6818313.0",
    "gn:asciiname":"'Arab Farhan Mays",
    "gn:country_code":"IQ",
    "gn:dem":28,
    "gn:feature_class":"P",
    "gn:feature_code":"PPL",
    "gn:name":"\u2018Arab Far\u1e29\u0101n Mays",
    "gn:population":0,
    "gn:timezone":"Asia/Baghdad",
    "iso:country":"IQ",
    "name:ara_x_preferred":[
        "\u0639\u0631\u0628 \u0641\u0631\u062d\u0627\u0646 \u0645\u064a\u0633"
    ],
    "name:und_x_variant":[
        "\u2018Arab Far\u1e29\u0101n Mays"
    ],
    "wof:name":"'Arab Farhan Mays",
    "wof:placetype":"locality"
},
  "geometry": {"coordinates":[44.76232,32.56613],"type":"Point"}
}