{
  "type": "Feature",
  "properties": {
    "gn:admin1_code":"7.0",
    "gn:admin2_code":"9166545.0",
    "gn:asciiname":"'Arab Fadil Shabib",
    "gn:country_code":"IQ",
    "gn:dem":36,
    "gn:feature_class":"P",
    "gn:feature_code":"PPL",
    "gn:name":"\u2018Arab F\u0101\u1e11il Shab\u012bb",
    "gn:population":0,
    "gn:timezone":"Asia/Baghdad",
    "iso:country":"IQ",
    "name:ara_x_preferred":[
        "\u0639\u0631\u0628 \u0641\u0627\u0636\u0644 \u0634\u0628\u064a\u0628"
    ],
    "name:und_x_variant":[
        "\u2018Arab F\u0101\u1e11il Shab\u012bb"
    ],
    "wof:name":"'Arab Fadil Shabib",
    "wof:placetype":"locality"
},
  "geometry": {"coordinates":[44.45645,33.21085],"type":"Point"}
}