{
  "type": "Feature",
  "properties": {
    "gn:admin1_code":"9.0",
    "gn:admin2_code":"98623.0",
    "gn:asciiname":"Baq'ah",
    "gn:country_code":"IQ",
    "gn:dem":9,
    "gn:feature_class":"P",
    "gn:feature_code":"PPL",
    "gn:name":"Baq\u2018ah",
    "gn:population":0,
    "gn:timezone":"Asia/Baghdad",
    "iso:country":"IQ",
    "name:und_x_variant":[
        "Baq\u2018ah"
    ],
    "wof:name":"Baq'ah",
    "wof:placetype":"locality"
},
  "geometry": {"coordinates":[46.16667,31.43333],"type":"Point"}
}