{
  "type": "Feature",
  "properties": {
    "gn:admin1_code":"7.0",
    "gn:admin2_code":"99101.0",
    "gn:asciiname":"Muzhir ash Shawi",
    "gn:country_code":"IQ",
    "gn:dem":39,
    "gn:feature_class":"P",
    "gn:feature_code":"PPL",
    "gn:name":"Muz\u0327hir ash Sh\u0101w\u012b",
    "gn:population":0,
    "gn:timezone":"Asia/Baghdad",
    "iso:country":"IQ",
    "name:und_x_variant":[
        "Muz\u0327hir ash Sh\u0101w\u012b"
    ],
    "wof:name":"Muzhir ash Shawi",
    "wof:placetype":"locality"
},
  "geometry": {"coordinates":[44.46218,33.09014000000001],"type":"Point"}
}