{
  "type": "Feature",
  "properties": {
    "gn:admin1_code":"11.0",
    "gn:admin2_code":"9166534.0",
    "gn:asciiname":"Shaykhan",
    "gn:country_code":"IQ",
    "gn:dem":1050,
    "gn:feature_class":"P",
    "gn:feature_code":"PPL",
    "gn:name":"Shaykh\u0101n",
    "gn:population":0,
    "gn:timezone":"Asia/Baghdad",
    "iso:country":"IQ",
    "name:ara_x_preferred":[
        "\u0634\u064a\u062e\u0627\u0646"
    ],
    "name:kur_x_preferred":[
        "Sh\u00eaxan"
    ],
    "name:kur_x_variant":[
        "\u0634\u06ce\u062e\u0627\u0646"
    ],
    "name:und_x_variant":[
        "Shaykh\u0101n",
        "\u0634\u064a\u062e\u0627\u0646",
        "Shekhan",
        "Sheikhan"
    ],
    "wof:name":"Shaykhan",
    "wof:placetype":"locality"
},
  "geometry": {"coordinates":[44.44119,36.7955],"type":"Point"}
}