{
  "type": "Feature",
  "properties": {
    "gn:admin1_code":"5.0",
    "gn:admin2_code":"91176.0",
    "gn:asciiname":"Kunah Masi",
    "gn:country_code":"IQ",
    "gn:dem":806,
    "gn:feature_class":"P",
    "gn:feature_code":"PPL",
    "gn:name":"K\u016bnah M\u0101s\u012b",
    "gn:population":0,
    "gn:timezone":"Asia/Baghdad",
    "iso:country":"IQ",
    "name:ara_x_preferred":[
        "\u0643\u0648\u0646\u0647 \u0645\u0627\u0633\u064a"
    ],
    "name:und_x_variant":[
        "K\u016bnah M\u0101s\u012b",
        "Kunam\u0101s\u012b"
    ],
    "wof:name":"Kunah Masi",
    "wof:placetype":"locality"
},
  "geometry": {"coordinates":[45.41438,35.79711],"type":"Point"}
}