{
  "type": "Feature",
  "properties": {
    "gn:admin1_code":"11.0",
    "gn:admin2_code":"95444.0",
    "gn:asciiname":"Yadi Qizlar",
    "gn:country_code":"IQ",
    "gn:dem":320,
    "gn:feature_class":"P",
    "gn:feature_code":"PPL",
    "gn:name":"Y\u0101d\u012b Qizlar",
    "gn:population":0,
    "gn:timezone":"Asia/Baghdad",
    "iso:country":"IQ",
    "name:ara_x_preferred":[
        "\u064a\u0627\u062f\u064a \u0642\u0632\u0644\u0631"
    ],
    "name:kur_x_preferred":[
        "Yad\u00ee Qzler"
    ],
    "name:kur_x_variant":[
        "\u064a\u0627\u062f\u0649 \u0642\u0632\u0644\u0631"
    ],
    "name:und_x_variant":[
        "Yad\u012b Qiziar",
        "Yedi Qizlar",
        "Y\u0101d\u012b Qizlar",
        "Yad\u012b Qizlar",
        "Yady Qiz"
    ],
    "wof:name":"Yadi Qizlar",
    "wof:placetype":"locality"
},
  "geometry": {"coordinates":[43.87089,35.98361],"type":"Point"}
}