{
  "type": "Feature",
  "properties": {
    "gn:admin1_code":"14.0",
    "gn:admin2_code":"9166562.0",
    "gn:asciiname":"Dar 'Amir Hasan al Badr",
    "gn:country_code":"IQ",
    "gn:dem":7,
    "gn:feature_class":"P",
    "gn:feature_code":"PPL",
    "gn:name":"D\u0101r \u2018\u0100mir \u1e28asan al Badr",
    "gn:population":0,
    "gn:timezone":"Asia/Baghdad",
    "iso:country":"IQ",
    "name:ara_x_preferred":[
        "\u062f\u0627\u0631 \u0639\u0627\u0645\u0631 \u062d\u0633\u0646 \u0627\u0644\u0628\u062f\u0631"
    ],
    "name:und_x_variant":[
        "D\u0101r \u2018\u0100mir \u1e28asan al Badr"
    ],
    "wof:name":"Dar 'Amir Hasan al Badr",
    "wof:placetype":"locality"
},
  "geometry": {"coordinates":[46.74457,31.27845],"type":"Point"}
}