{
  "type": "Feature",
  "properties": {
    "gn:admin1_code":"13.0",
    "gn:admin2_code":"6770659.0",
    "gn:asciiname":"Qaryat Tall adh Dhahab as Sufla",
    "gn:country_code":"IQ",
    "gn:dem":120,
    "gn:feature_class":"P",
    "gn:feature_code":"PPL",
    "gn:name":"Qaryat Tall adh Dhahab as Sufl\u00e1",
    "gn:population":0,
    "gn:timezone":"Asia/Baghdad",
    "iso:country":"IQ",
    "name:ara_x_preferred":[
        "\u0642\u0631\u064a\u0629 \u062a\u0644 \u0627\u0644\u0630\u0647\u0628 \u0627\u0644\u0633\u0641\u0644\u0649"
    ],
    "name:und_x_variant":[
        "Tall adh Dhahab",
        "Qaryat Tall adh Dhahab as Sufl\u00e1"
    ],
    "wof:name":"Qaryat Tall adh Dhahab as Sufla",
    "wof:placetype":"locality"
},
  "geometry": {"coordinates":[43.5124,35.11035],"type":"Point"}
}