{
  "type": "Feature",
  "properties": {
    "gn:admin1_code":"4.0",
    "gn:admin2_code":"99763.0",
    "gn:asciiname":"Karim Kazim",
    "gn:country_code":"IQ",
    "gn:dem":25,
    "gn:feature_class":"P",
    "gn:feature_code":"PPL",
    "gn:name":"Kar\u012bm K\u0101z\u0327im",
    "gn:population":0,
    "gn:timezone":"Asia/Baghdad",
    "iso:country":"IQ",
    "name:ara_x_preferred":[
        "\u0643\u0631\u064a\u0645 \u0643\u0627\u0638\u0645"
    ],
    "name:und_x_variant":[
        "Kar\u012bm K\u0101z\u0327im"
    ],
    "wof:name":"Karim Kazim",
    "wof:placetype":"locality"
},
  "geometry": {"coordinates":[44.61903,32.05504000000001],"type":"Point"}
}