{
  "type": "Feature",
  "properties": {
    "gn:admin1_code":"5.0",
    "gn:admin2_code":"97416.0",
    "gn:asciiname":"Masui Rahim Agha",
    "gn:country_code":"IQ",
    "gn:dem":562,
    "gn:feature_class":"P",
    "gn:feature_code":"PPL",
    "gn:name":"Mas\u016b\u012b Ra\u1e29\u012bm \u0100gh\u0101",
    "gn:population":0,
    "gn:timezone":"Asia/Baghdad",
    "iso:country":"IQ",
    "wof:name":"Masui Rahim Agha",
    "wof:placetype":"locality"
},
  "geometry": {"coordinates":[45.225,35.11833],"type":"Point"}
}