{
  "type": "Feature",
  "properties": {
    "gn:admin1_code":"16.0",
    "gn:admin2_code":"9166961.0",
    "gn:asciiname":"Hajji Qataniyah",
    "gn:country_code":"IQ",
    "gn:dem":28,
    "gn:feature_class":"P",
    "gn:feature_code":"PPL",
    "gn:name":"\u1e28\u0101jj\u012b Qa\u0163\u0101n\u012byah",
    "gn:population":0,
    "gn:timezone":"Asia/Baghdad",
    "iso:country":"IQ",
    "name:und_x_variant":[
        "\u1e28\u0101jj\u012b Qa\u0163\u0101n\u012byah"
    ],
    "wof:name":"Hajji Qataniyah",
    "wof:placetype":"locality"
},
  "geometry": {"coordinates":[44.92139,32.91917],"type":"Point"}
}