{
  "type": "Feature",
  "properties": {
    "gn:admin1_code":"14.0",
    "gn:admin2_code":"9166562.0",
    "gn:asciiname":"Salaf al Bahadil",
    "gn:country_code":"IQ",
    "gn:dem":9,
    "gn:feature_class":"P",
    "gn:feature_code":"PPL",
    "gn:name":"Salaf al Bah\u0101dil",
    "gn:population":0,
    "gn:timezone":"Asia/Baghdad",
    "iso:country":"IQ",
    "name:ara_x_preferred":[
        "\u0633\u0644\u0641 \u0627\u0644\u0628\u0647\u0627\u062f\u0644"
    ],
    "name:und_x_variant":[
        "Salaf al Bah\u0101dil"
    ],
    "wof:name":"Salaf al Bahadil",
    "wof:placetype":"locality"
},
  "geometry": {"coordinates":[47.11611,31.76112],"type":"Point"}
}