{
  "type": "Feature",
  "properties": {
    "gn:admin1_code":"6.0",
    "gn:admin2_code":"6818313.0",
    "gn:asciiname":"Dar al Iskandariyah",
    "gn:country_code":"IQ",
    "gn:dem":36,
    "gn:feature_class":"P",
    "gn:feature_code":"PPL",
    "gn:name":"D\u0101r al Iskandar\u012byah",
    "gn:population":0,
    "gn:timezone":"Asia/Baghdad",
    "iso:country":"IQ",
    "name:und_x_variant":[
        "D\u0101r al Iskandar\u012byah"
    ],
    "wof:name":"Dar al Iskandariyah",
    "wof:placetype":"locality"
},
  "geometry": {"coordinates":[44.21472,32.94194],"type":"Point"}
}