{
  "type": "Feature",
  "properties": {
    "gn:admin1_code":"3.0",
    "gn:admin2_code":"98534.0",
    "gn:asciiname":"Thaqb Abu Tabrah",
    "gn:country_code":"IQ",
    "gn:dem":120,
    "gn:feature_class":"P",
    "gn:feature_code":"PPL",
    "gn:name":"Thaqb \u0100b\u016b \u0162abrah",
    "gn:population":0,
    "gn:timezone":"Asia/Baghdad",
    "iso:country":"IQ",
    "name:ara_x_preferred":[
        "\u062b\u0642\u0628 \u0623\u0628\u0648 \u0637\u0628\u0631\u0629"
    ],
    "name:und_x_variant":[
        "Thaqb \u0100b\u016b \u0162abrah"
    ],
    "wof:name":"Thaqb Abu Tabrah",
    "wof:placetype":"locality"
},
  "geometry": {"coordinates":[45.05287,30.90889],"type":"Point"}
}