{
  "type": "Feature",
  "properties": {
    "gn:admin1_code":"18.0",
    "gn:admin2_code":"6872046.0",
    "gn:asciiname":"'Abbas Ziyaz",
    "gn:country_code":"IQ",
    "gn:dem":162,
    "gn:feature_class":"P",
    "gn:feature_code":"PPL",
    "gn:name":"\u2018Abb\u0101s Ziy\u0101z",
    "gn:population":0,
    "gn:timezone":"Asia/Baghdad",
    "iso:country":"IQ",
    "name:ara_x_preferred":[
        "\u0639\u0628\u0627\u0633 \u0632\u064a\u0627\u0632"
    ],
    "name:ara_x_variant":[
        "\u2018Abb\u0101s Ziy\u0101z"
    ],
    "wof:name":"'Abbas Ziyaz",
    "wof:placetype":"locality"
},
  "geometry": {"coordinates":[43.29867,34.97583],"type":"Point"}
}