{
  "type": "Feature",
  "properties": {
    "gn:admin1_code":"17.0",
    "gn:admin2_code":"9166552.0",
    "gn:asciiname":"'Abd al Hasan Jabir",
    "gn:country_code":"IQ",
    "gn:dem":21,
    "gn:feature_class":"P",
    "gn:feature_code":"PPL",
    "gn:name":"\u2018Abd al \u1e28asan J\u0101bir",
    "gn:population":0,
    "gn:timezone":"Asia/Baghdad",
    "iso:country":"IQ",
    "name:ara_x_preferred":[
        "\u0639\u0628\u062f \u0627\u0644\u062d\u0633\u0646 \u062c\u0627\u0628\u0631"
    ],
    "name:und_x_variant":[
        "\u2018Abd al \u1e28asan J\u0101bir"
    ],
    "wof:name":"'Abd al Hasan Jabir",
    "wof:placetype":"locality"
},
  "geometry": {"coordinates":[44.50573,31.76546],"type":"Point"}
}