{
  "type": "Feature",
  "properties": {
    "gn:admin1_code":"2.0",
    "gn:admin2_code":"9166549.0",
    "gn:asciiname":"'Uwayyan",
    "gn:country_code":"IQ",
    "gn:dem":1,
    "gn:feature_class":"P",
    "gn:feature_code":"PPL",
    "gn:name":"\u2018Uwayy\u0101n",
    "gn:population":0,
    "gn:timezone":"Asia/Baghdad",
    "iso:country":"IQ",
    "name:und_x_variant":[
        "\u2018Uwayy\u0101n"
    ],
    "wof:name":"'Uwayyan",
    "wof:placetype":"locality"
},
  "geometry": {"coordinates":[48.40083,30.09472],"type":"Point"}
}