{
  "type": "Feature",
  "properties": {
    "gn:admin1_code":"9.0",
    "gn:admin2_code":"98700.0",
    "gn:asciiname":"Thamar al Mazbud",
    "gn:country_code":"IQ",
    "gn:dem":13,
    "gn:feature_class":"P",
    "gn:feature_code":"PPL",
    "gn:name":"Th\u0101mar al Mazb\u016bd",
    "gn:population":0,
    "gn:timezone":"Asia/Baghdad",
    "iso:country":"IQ",
    "name:ara_x_preferred":[
        "\u062b\u0627\u0645\u0631 \u0627\u0644\u0645\u0632\u0628\u0648\u062f"
    ],
    "name:und_x_variant":[
        "Th\u0101mar al Mazb\u016bd"
    ],
    "wof:name":"Thamar al Mazbud",
    "wof:placetype":"locality"
},
  "geometry": {"coordinates":[45.95675,31.86814],"type":"Point"}
}