{
  "type": "Feature",
  "properties": {
    "gn:admin1_code":"7.0",
    "gn:admin2_code":"99173.0",
    "gn:asciiname":"Hamdi al Khalifah",
    "gn:country_code":"IQ",
    "gn:dem":39,
    "gn:feature_class":"P",
    "gn:feature_code":"PPL",
    "gn:name":"\u1e28amd\u012b al Khal\u012bfah",
    "gn:population":0,
    "gn:timezone":"Asia/Baghdad",
    "iso:country":"IQ",
    "name:ara_x_preferred":[
        "\u062d\u0645\u062f\u064a \u0627\u0644\u062e\u0644\u064a\u0641\u0629"
    ],
    "name:und_x_variant":[
        "\u1e28amd\u012b al Khal\u012bfah"
    ],
    "wof:name":"Hamdi al Khalifah",
    "wof:placetype":"locality"
},
  "geometry": {"coordinates":[44.30185,33.51076],"type":"Point"}
}