{
  "type": "Feature",
  "properties": {
    "gn:admin1_code":"9.0",
    "gn:admin2_code":"90509.0",
    "gn:asciiname":"Saynakh",
    "gn:cc2":"IQ",
    "gn:country_code":"IQ",
    "gn:dem":3,
    "gn:feature_class":"P",
    "gn:feature_code":"PPL",
    "gn:name":"Saynakh",
    "gn:population":0,
    "gn:timezone":"Asia/Baghdad",
    "iso:country":"IQ",
    "name:und_x_variant":[
        "Sainak",
        "Sainakh",
        "Saynakh"
    ],
    "wof:name":"Saynakh",
    "wof:placetype":"locality"
},
  "geometry": {"coordinates":[46.75694,30.92306],"type":"Point"}
}