{
  "type": "Feature",
  "properties": {
    "gn:admin1_code":"18.0",
    "gn:admin2_code":"91594.0",
    "gn:asciiname":"Muhammad Khamis",
    "gn:country_code":"IQ",
    "gn:dem":97,
    "gn:feature_class":"P",
    "gn:feature_code":"PPL",
    "gn:name":"Mu\u1e29ammad Kham\u012bs",
    "gn:population":0,
    "gn:timezone":"Asia/Baghdad",
    "iso:country":"IQ",
    "name:ara_x_preferred":[
        "\u0645\u062d\u0645\u062f \u062e\u0645\u064a\u0633"
    ],
    "name:und_x_variant":[
        "Mu\u1e29ammad Kham\u012bs"
    ],
    "wof:name":"Muhammad Khamis",
    "wof:placetype":"locality"
},
  "geometry": {"coordinates":[43.52495,34.23683],"type":"Point"}
}