{
  "type": "Feature",
  "properties": {
    "gn:admin1_code":"7.0",
    "gn:admin2_code":"9166569.0",
    "gn:asciiname":"Ahmad Dawud",
    "gn:country_code":"IQ",
    "gn:dem":37,
    "gn:feature_class":"P",
    "gn:feature_code":"PPL",
    "gn:name":"A\u1e29mad D\u0101wud",
    "gn:population":0,
    "gn:timezone":"Asia/Baghdad",
    "iso:country":"IQ",
    "name:ara_x_preferred":[
        "\u0627\u062d\u0645\u062f \u062f\u0627\u0648\u062f"
    ],
    "name:und_x_variant":[
        "A\u1e29mad D\u0101wud"
    ],
    "wof:name":"Ahmad Dawud",
    "wof:placetype":"locality"
},
  "geometry": {"coordinates":[44.25446,33.65723],"type":"Point"}
}