{
  "type": "Feature",
  "properties": {
    "gn:admin1_code":"1.0",
    "gn:admin2_code":"9166579.0",
    "gn:asciiname":"Al Baghdadi",
    "gn:country_code":"IQ",
    "gn:dem":93,
    "gn:feature_class":"P",
    "gn:feature_code":"PPL",
    "gn:name":"Al Baghd\u0101d\u012b",
    "gn:population":0,
    "gn:timezone":"Asia/Baghdad",
    "iso:country":"IQ",
    "name:ara_x_preferred":[
        "\u0627\u0644\u0628\u063a\u062f\u0627\u062f\u064a"
    ],
    "name:und_x_variant":[
        "Fort Bagdadiah",
        "Kh\u0101n Bagd\u0101di",
        "Khan Baghdadi",
        "Kh\u0101n al Baghd\u0101d\u012b",
        "Al Baghd\u0101d\u012b"
    ],
    "wof:name":"Al Baghdadi",
    "wof:placetype":"locality"
},
  "geometry": {"coordinates":[42.54868,33.85136],"type":"Point"}
}