{
  "type": "Feature",
  "properties": {
    "gn:admin1_code":"11.0",
    "gn:admin2_code":"9166592.0",
    "gn:asciiname":"Bine Kawl",
    "gn:country_code":"IQ",
    "gn:dem":1073,
    "gn:feature_class":"P",
    "gn:feature_code":"PPLL",
    "gn:name":"Bine Kawl",
    "gn:population":0,
    "gn:timezone":"Asia/Baghdad",
    "iso:country":"IQ",
    "name:ara_x_preferred":[
        "\u0628\u0646\u064a \u0643\u0627\u0648\u0644"
    ],
    "name:kur_x_preferred":[
        "Bine Kawl"
    ],
    "name:kur_x_variant":[
        "\u0628\u0646\u06d5 \u0643\u0627\u0648\u0644"
    ],
    "name:und_x_variant":[
        "Ban\u012b K\u0101wl",
        "Binik\u0101wul",
        "Ban Kawl",
        "Bna Kawl"
    ],
    "wof:name":"Bine Kawl",
    "wof:placetype":"locality"
},
  "geometry": {"coordinates":[44.56376,36.58223],"type":"Point"}
}