{
  "type": "Feature",
  "properties": {
    "gn:admin1_code":"18.0",
    "gn:admin2_code":"6805736.0",
    "gn:asciiname":"'Arkub al Basil",
    "gn:country_code":"IQ",
    "gn:dem":57,
    "gn:feature_class":"P",
    "gn:feature_code":"PPL",
    "gn:name":"\u2018Ark\u016bb al Ba\u015f\u012bl",
    "gn:population":0,
    "gn:timezone":"Asia/Baghdad",
    "iso:country":"IQ",
    "name:ara_x_preferred":[
        "\u0639\u0631\u0643\u0648\u0628 \u0627\u0644\u0628\u0635\u064a\u0644"
    ],
    "name:und_x_variant":[
        "\u2018Ark\u016bb al Ba\u015f\u012bl"
    ],
    "wof:name":"'Arkub al Basil",
    "wof:placetype":"locality"
},
  "geometry": {"coordinates":[44.01845,34.02994],"type":"Point"}
}