{
  "type": "Feature",
  "properties": {
    "gn:admin1_code":"7.0",
    "gn:admin2_code":"99101.0",
    "gn:asciiname":"Salim Hamud",
    "gn:country_code":"IQ",
    "gn:dem":38,
    "gn:feature_class":"P",
    "gn:feature_code":"PPL",
    "gn:name":"Sal\u012bm \u1e28am\u016bd",
    "gn:population":0,
    "gn:timezone":"Asia/Baghdad",
    "iso:country":"IQ",
    "name:ara_x_preferred":[
        "\u0633\u0644\u064a\u0645 \u062d\u0645\u0648\u062f"
    ],
    "name:und_x_variant":[
        "Sal\u012bm \u1e28am\u016bd"
    ],
    "wof:name":"Salim Hamud",
    "wof:placetype":"locality"
},
  "geometry": {"coordinates":[44.45108,33.17957],"type":"Point"}
}