{
  "type": "Feature",
  "properties": {
    "gn:admin1_code":"5.0",
    "gn:admin2_code":"9166596.0",
    "gn:asciiname":"Kani Binaw",
    "gn:country_code":"IQ",
    "gn:dem":692,
    "gn:feature_class":"P",
    "gn:feature_code":"PPL",
    "gn:name":"Kan\u00ee Binaw",
    "gn:population":0,
    "gn:timezone":"Asia/Baghdad",
    "iso:country":"IQ",
    "name:ara_x_preferred":[
        "K\u0101n\u012b Bin\u0101w"
    ],
    "name:kur_x_preferred":[
        "\u0643\u0627\u0646\u0649 \u0628\u0646\u0627\u0648"
    ],
    "name:kur_x_variant":[
        "Kani Bnaw",
        "Kan\u00ee Binaw"
    ],
    "name:und_x_variant":[
        "K\u0101ni Bin\u0101o",
        "Kani Bnaw"
    ],
    "wof:name":"Kani Binaw",
    "wof:placetype":"locality"
},
  "geometry": {"coordinates":[44.91533,36.0266],"type":"Point"}
}