{
  "type": "Feature",
  "properties": {
    "gn:admin1_code":"7.0",
    "gn:admin2_code":"9166545.0",
    "gn:asciiname":"Mahmud Farhan",
    "gn:country_code":"IQ",
    "gn:dem":35,
    "gn:feature_class":"P",
    "gn:feature_code":"PPL",
    "gn:name":"Ma\u1e29m\u016bd Far\u1e29\u0101n",
    "gn:population":0,
    "gn:timezone":"Asia/Baghdad",
    "iso:country":"IQ",
    "name:ara_x_preferred":[
        "\u0645\u062d\u0645\u0648\u062f \u0641\u0631\u062d\u0627\u0646"
    ],
    "name:und_x_variant":[
        "Ma\u1e29m\u016bd Far\u1e29\u0101n"
    ],
    "wof:name":"Mahmud Farhan",
    "wof:placetype":"locality"
},
  "geometry": {"coordinates":[44.42702,33.20381],"type":"Point"}
}