{
  "type": "Feature",
  "properties": {
    "gn:admin1_code":"18.0",
    "gn:admin2_code":"90148.0",
    "gn:asciiname":"Hamid 'Awdah",
    "gn:country_code":"IQ",
    "gn:dem":120,
    "gn:feature_class":"P",
    "gn:feature_code":"PPL",
    "gn:name":"\u1e28am\u012bd \u2018Awdah",
    "gn:population":0,
    "gn:timezone":"Asia/Baghdad",
    "iso:country":"IQ",
    "name:ara_x_preferred":[
        "\u062d\u0645\u064a\u062f \u0639\u0648\u062f\u0629"
    ],
    "name:und_x_variant":[
        "\u1e28am\u012bd \u2018Awdah"
    ],
    "wof:name":"Hamid 'Awdah",
    "wof:placetype":"locality"
},
  "geometry": {"coordinates":[43.51483,34.48373],"type":"Point"}
}