{
  "type": "Feature",
  "properties": {
    "gn:admin1_code":"12.0",
    "gn:admin2_code":"99345.0",
    "gn:asciiname":"Hadi Ibrahim",
    "gn:country_code":"IQ",
    "gn:dem":30,
    "gn:feature_class":"P",
    "gn:feature_code":"PPL",
    "gn:name":"H\u0101d\u012b Ibr\u0101h\u012bm",
    "gn:population":0,
    "gn:timezone":"Asia/Baghdad",
    "iso:country":"IQ",
    "name:ara_x_preferred":[
        "H\u0101d\u012b Ibr\u0101h\u012bm"
    ],
    "wof:name":"Hadi Ibrahim",
    "wof:placetype":"locality"
},
  "geometry": {"coordinates":[44.20722,32.73417],"type":"Point"}
}