{
  "type": "Feature",
  "properties": {
    "gn:admin1_code":"18.0",
    "gn:admin2_code":"91594.0",
    "gn:asciiname":"Ra'uwf Jasim",
    "gn:country_code":"IQ",
    "gn:dem":106,
    "gn:feature_class":"P",
    "gn:feature_code":"PPL",
    "gn:name":"Ra\u2019\u016bwf J\u0101sim",
    "gn:population":0,
    "gn:timezone":"Asia/Baghdad",
    "iso:country":"IQ",
    "name:ara_x_preferred":[
        "\u0631\u0624\u0648\u0641 \u062c\u0627\u0633\u0645"
    ],
    "name:und_x_variant":[
        "Ra\u2019\u016bwf J\u0101sim"
    ],
    "wof:name":"Ra'uwf Jasim",
    "wof:placetype":"locality"
},
  "geometry": {"coordinates":[43.4688,34.28349],"type":"Point"}
}