{
  "type": "Feature",
  "properties": {
    "gn:admin1_code":"7.0",
    "gn:admin2_code":"9179819.0",
    "gn:asciiname":"Hamdi ash Shakhli",
    "gn:country_code":"IQ",
    "gn:dem":40,
    "gn:feature_class":"P",
    "gn:feature_code":"PPL",
    "gn:name":"\u1e28amd\u012b ash Shakhl\u012b",
    "gn:population":0,
    "gn:timezone":"Asia/Baghdad",
    "iso:country":"IQ",
    "name:ara_x_preferred":[
        "\u062d\u0645\u062f\u064a \u0627\u0644\u0634\u062e\u0644\u064a"
    ],
    "name:und_x_variant":[
        "\u1e28amd\u012b ash Shakhl\u012b"
    ],
    "wof:name":"Hamdi ash Shakhli",
    "wof:placetype":"locality"
},
  "geometry": {"coordinates":[44.49473,33.17104],"type":"Point"}
}