{
  "type": "Feature",
  "properties": {
    "gn:admin1_code":"15.0",
    "gn:admin2_code":"98820.0",
    "gn:asciiname":"Malah Musa",
    "gn:country_code":"IQ",
    "gn:dem":486,
    "gn:feature_class":"P",
    "gn:feature_code":"PPL",
    "gn:name":"M\u0101lah M\u016bs\u00e1",
    "gn:population":0,
    "gn:timezone":"Asia/Baghdad",
    "iso:country":"IQ",
    "name:ara_x_preferred":[
        "\u0645\u0627\u0644\u06d5 \u0645\u0648\u0633\u0649"
    ],
    "name:kur_x_preferred":[
        "Mala Musa"
    ],
    "name:kur_x_variant":[
        "Mela Musa",
        "\u0645\u0627\u0644\u0627 \u0645\u0648\u0633\u0627",
        "\u0645\u06d5\u0644\u0627 \u0645\u0648\u0633\u0627"
    ],
    "name:und_x_variant":[
        "Mal\u0101 M\u016bsa",
        "M\u0101lah M\u016bs\u00e1",
        "M\u016bs",
        "\u0645\u0648\u0633"
    ],
    "wof:name":"Malah Musa",
    "wof:placetype":"locality"
},
  "geometry": {"coordinates":[44.26484,36.71365],"type":"Point"}
}