{
  "type": "Feature",
  "properties": {
    "gn:admin1_code":"9.0",
    "gn:admin2_code":"98623.0",
    "gn:asciiname":"Ishan as Subud",
    "gn:country_code":"IQ",
    "gn:dem":8,
    "gn:feature_class":"P",
    "gn:feature_code":"PPL",
    "gn:name":"\u012ash\u0101n a\u015f \u015eub\u016bd",
    "gn:population":0,
    "gn:timezone":"Asia/Baghdad",
    "iso:country":"IQ",
    "name:ara_x_preferred":[
        "\u0627\u064a\u0634\u0627\u0646 \u0627\u0644\u0635\u0628\u0648\u062f"
    ],
    "name:und_x_variant":[
        "\u012ash\u0101n a\u015f \u015eub\u016bd"
    ],
    "wof:name":"Ishan as Subud",
    "wof:placetype":"locality"
},
  "geometry": {"coordinates":[46.31339000000001,31.40858],"type":"Point"}
}