{
  "type": "Feature",
  "properties": {
    "gn:admin1_code":"17.0",
    "gn:admin2_code":"9166629.0",
    "gn:asciiname":"Al Bidaywi",
    "gn:country_code":"IQ",
    "gn:dem":26,
    "gn:feature_class":"P",
    "gn:feature_code":"PPL",
    "gn:name":"\u0100l Bidayw\u012b",
    "gn:population":0,
    "gn:timezone":"Asia/Baghdad",
    "iso:country":"IQ",
    "name:ara_x_preferred":[
        "\u0627\u0644 \u0628\u062f\u064a\u0648\u064a"
    ],
    "name:und_x_variant":[
        "\u0100l Bidayw\u012b"
    ],
    "wof:name":"Al Bidaywi",
    "wof:placetype":"locality"
},
  "geometry": {"coordinates":[44.35645,32.13982],"type":"Point"}
}