{
  "type": "Feature",
  "properties": {
    "gn:admin1_code":"18.0",
    "gn:admin2_code":"9166616.0",
    "gn:asciiname":"Hasan 'Alu",
    "gn:country_code":"IQ",
    "gn:dem":40,
    "gn:feature_class":"P",
    "gn:feature_code":"PPL",
    "gn:name":"\u1e28as\u0101n \u2018Al\u016b",
    "gn:population":0,
    "gn:timezone":"Asia/Baghdad",
    "iso:country":"IQ",
    "name:ara_x_preferred":[
        "\u062d\u0633\u0627\u0646 \u0639\u0644\u0648"
    ],
    "name:und_x_variant":[
        "\u1e28as\u0101n \u2018Al\u016b"
    ],
    "wof:name":"Hasan 'Alu",
    "wof:placetype":"locality"
},
  "geometry": {"coordinates":[44.29588,33.73917],"type":"Point"}
}