{
  "type": "Feature",
  "properties": {
    "gn:admin1_code":"18.0",
    "gn:admin2_code":"9167093.0",
    "gn:asciiname":"Hasan Mukhlaf Hamadi",
    "gn:country_code":"IQ",
    "gn:dem":67,
    "gn:feature_class":"P",
    "gn:feature_code":"PPL",
    "gn:name":"\u1e28asan Mukhlaf \u1e28am\u0101d\u012b",
    "gn:population":0,
    "gn:timezone":"Asia/Baghdad",
    "iso:country":"IQ",
    "name:ara_x_preferred":[
        "\u062d\u0633\u0646 \u0645\u062e\u0644\u0641 \u062d\u0645\u0627\u062f\u064a"
    ],
    "name:und_x_variant":[
        "\u1e28asan Mukhlaf \u1e28am\u0101d\u012b"
    ],
    "wof:name":"Hasan Mukhlaf Hamadi",
    "wof:placetype":"locality"
},
  "geometry": {"coordinates":[43.72866,34.00613],"type":"Point"}
}