{
  "type": "Feature",
  "properties": {
    "gn:admin1_code":"10.0",
    "gn:admin2_code":"94590.0",
    "gn:asciiname":"Imam Sultan",
    "gn:country_code":"IQ",
    "gn:dem":157,
    "gn:feature_class":"P",
    "gn:feature_code":"PPL",
    "gn:name":"Im\u0101m Sul\u0163\u0101n",
    "gn:population":0,
    "gn:timezone":"Asia/Baghdad",
    "iso:country":"IQ",
    "name:ara_x_preferred":[
        "\u0627\u0645\u0627\u0645 \u0633\u0644\u0637\u0627\u0646"
    ],
    "name:ara_x_variant":[
        "Im\u0101m Sul\u0163\u0101n"
    ],
    "wof:name":"Imam Sultan",
    "wof:placetype":"locality"
},
  "geometry": {"coordinates":[45.32039,34.33312],"type":"Point"}
}