{
  "type": "Feature",
  "properties": {
    "gn:admin1_code":"5.0",
    "gn:admin2_code":"96204.0",
    "gn:asciiname":"Zankal",
    "gn:country_code":"IQ",
    "gn:dem":502,
    "gn:feature_class":"P",
    "gn:feature_code":"PPL",
    "gn:name":"Zankal",
    "gn:population":0,
    "gn:timezone":"Asia/Baghdad",
    "iso:country":"IQ",
    "name:fas_x_preferred":[
        "\u0632\u0646\u06a9\u0627\u0644"
    ],
    "name:fas_x_variant":[
        "Zank\u0101l"
    ],
    "name:kur_x_preferred":[
        "Zenkel"
    ],
    "name:kur_x_variant":[
        "\u0632\u06d5\u0646\u0643\u06d5\u0644"
    ],
    "wof:name":"Zankal",
    "wof:placetype":"locality"
},
  "geometry": {"coordinates":[45.9167,35.2449],"type":"Point"}
}