{
  "type": "Feature",
  "properties": {
    "gn:admin1_code":"13.0",
    "gn:admin2_code":"9166581.0",
    "gn:asciiname":"Abu Hamad",
    "gn:country_code":"IQ",
    "gn:dem":200,
    "gn:feature_class":"P",
    "gn:feature_code":"PPL",
    "gn:name":"Ab\u016b \u1e28amad",
    "gn:population":0,
    "gn:timezone":"Asia/Baghdad",
    "iso:country":"IQ",
    "name:ara_x_preferred":[
        "\u0627\u0628\u0648 \u062d\u0645\u062f"
    ],
    "name:ara_x_variant":[
        "\u0623\u0628\u0648 \u062d\u0645\u062f"
    ],
    "name:arz_x_preferred":[
        "\u0645\u062f\u064a\u0646\u0629 \u0623\u0628\u0648\u062d\u0645\u062f"
    ],
    "name:azb_x_preferred":[
        "\u0627\u0628\u0648 \u062d\u0627\u0645\u062f"
    ],
    "name:cat_x_preferred":[
        "Abu Hamed"
    ],
    "name:epo_x_preferred":[
        "Abu-Hamado"
    ],
    "name:fas_x_preferred":[
        "\u0627\u0628\u0648 \u062d\u0627\u0645\u062f"
    ],
    "name:ita_x_preferred":[
        "Abu Hamad"
    ],
    "name:pol_x_preferred":[
        "Abu Hamad"
    ],
    "name:spa_x_preferred":[
        "Abu Hamad"
    ],
    "name:swe_x_preferred":[
        "Abu Hamad"
    ],
    "name:und_x_variant":[
        "Ab\u016b \u1e28amad"
    ],
    "name:urd_x_preferred":[
        "\u0627\u0628\u0648 \u062d\u0645\u062f"
    ],
    "wof:name":"Abu Hamad",
    "wof:placetype":"locality"
},
  "geometry": {"coordinates":[44.37344,35.0491],"type":"Point"}
}