{
  "type": "Feature",
  "properties": {
    "gn:admin1_code":"17.0",
    "gn:admin2_code":"9166552.0",
    "gn:asciiname":"Qal'at Umm Kubrah",
    "gn:country_code":"IQ",
    "gn:dem":16,
    "gn:feature_class":"P",
    "gn:feature_code":"PPL",
    "gn:name":"Qal\u2018at Umm Kubrah",
    "gn:population":0,
    "gn:timezone":"Asia/Baghdad",
    "iso:country":"IQ",
    "name:ara_x_preferred":[
        "\u0642\u0644\u0639\u0629 \u0627\u0645 \u0643\u0628\u0631\u0647"
    ],
    "name:und_x_variant":[
        "Qal\u2018at Umm Kubrah"
    ],
    "wof:name":"Qal'at Umm Kubrah",
    "wof:placetype":"locality"
},
  "geometry": {"coordinates":[44.47271,31.65654],"type":"Point"}
}