{
  "type": "Feature",
  "properties": {
    "gn:admin1_code":"5.0",
    "gn:admin2_code":"96204.0",
    "gn:asciiname":"Tahnah",
    "gn:country_code":"IQ",
    "gn:dem":1696,
    "gn:feature_class":"P",
    "gn:feature_code":"PPL",
    "gn:name":"Tahnah",
    "gn:population":0,
    "gn:timezone":"Asia/Baghdad",
    "iso:country":"IQ",
    "name:ara_x_preferred":[
        "\u062a\u06d5\u0646\u06d5"
    ],
    "name:kur_x_preferred":[
        "Tene"
    ],
    "name:und_x_variant":[
        "Tahtah",
        "Tana",
        "\u062a\u06d5\u062a\u0647"
    ],
    "wof:name":"Tahnah",
    "wof:placetype":"locality"
},
  "geometry": {"coordinates":[46.139,35.29646],"type":"Point"}
}