{
  "type": "Feature",
  "properties": {
    "gn:admin1_code":"12.0",
    "gn:admin2_code":"99345.0",
    "gn:asciiname":"Kazim Hamud",
    "gn:country_code":"IQ",
    "gn:dem":34,
    "gn:feature_class":"P",
    "gn:feature_code":"PPL",
    "gn:name":"K\u0101z\u0327im \u1e28am\u016bd",
    "gn:population":0,
    "gn:timezone":"Asia/Baghdad",
    "iso:country":"IQ",
    "name:ara_x_preferred":[
        "\u0643\u0627\u0638\u0645 \u062d\u0645\u0648\u062f"
    ],
    "name:und_x_variant":[
        "K\u0101z\u0327im \u1e28amm\u016bd",
        "K\u0101z\u0327im \u1e28am\u016bd"
    ],
    "wof:name":"Kazim Hamud",
    "wof:placetype":"locality"
},
  "geometry": {"coordinates":[44.15785,32.51418],"type":"Point"}
}