{
  "type": "Feature",
  "properties": {
    "gn:admin1_code":"6.0",
    "gn:admin2_code":"99358.0",
    "gn:asciiname":"'Allawi Jabbar",
    "gn:country_code":"IQ",
    "gn:dem":25,
    "gn:feature_class":"P",
    "gn:feature_code":"PPL",
    "gn:name":"\u2018All\u0101w\u012b Jabb\u0101r",
    "gn:population":0,
    "gn:timezone":"Asia/Baghdad",
    "iso:country":"IQ",
    "name:ara_x_preferred":[
        "\u0639\u0644\u0627\u0648\u064a \u062c\u0628\u0627\u0631"
    ],
    "name:und_x_variant":[
        "\u2018All\u0101w\u012b Jabb\u0101r"
    ],
    "wof:name":"'Allawi Jabbar",
    "wof:placetype":"locality"
},
  "geometry": {"coordinates":[44.97875,32.28516],"type":"Point"}
}