{
  "type": "Feature",
  "properties": {
    "gn:admin1_code":"5.0",
    "gn:admin2_code":"91176.0",
    "gn:asciiname":"Sawayrah",
    "gn:country_code":"IQ",
    "gn:dem":1128,
    "gn:feature_class":"P",
    "gn:feature_code":"PPL",
    "gn:name":"Sawayrah",
    "gn:population":0,
    "gn:timezone":"Asia/Baghdad",
    "iso:country":"IQ",
    "name:ara_x_preferred":[
        "\u0633\u0648\u064a\u0631\u0647"
    ],
    "name:fas_x_preferred":[
        "\u0633\u0631\u0648"
    ],
    "name:fas_x_variant":[
        "Sor\u016b"
    ],
    "name:kur_x_preferred":[
        "Sw\u00eare"
    ],
    "name:kur_x_variant":[
        "\u0633\u0648\u06ce\u0631\u06d5"
    ],
    "name:und_x_variant":[
        "S\u00f6ra",
        "S\u016brah",
        "Suira",
        "Sawayrah",
        "Swera"
    ],
    "wof:name":"Sawayrah",
    "wof:placetype":"locality"
},
  "geometry": {"coordinates":[45.77472,35.63642],"type":"Point"}
}