{
  "type": "Feature",
  "properties": {
    "gn:admin1_code":"17.0",
    "gn:admin2_code":"9166629.0",
    "gn:asciiname":"'Abd az Zahrah",
    "gn:country_code":"IQ",
    "gn:dem":25,
    "gn:feature_class":"P",
    "gn:feature_code":"PPL",
    "gn:name":"\u2018Abd az Zahrah",
    "gn:population":0,
    "gn:timezone":"Asia/Baghdad",
    "iso:country":"IQ",
    "name:ara_x_preferred":[
        "\u0639\u0628\u062f \u0627\u0644\u0632\u0647\u0631\u0629"
    ],
    "name:und_x_variant":[
        "\u2018Abd az Zahrah"
    ],
    "wof:name":"'Abd az Zahrah",
    "wof:placetype":"locality"
},
  "geometry": {"coordinates":[44.58474,32.08652],"type":"Point"}
}