{
  "type": "Feature",
  "properties": {
    "gn:admin1_code":"2.0",
    "gn:admin2_code":"9166563.0",
    "gn:asciiname":"Al Hadah",
    "gn:country_code":"IQ",
    "gn:dem":4,
    "gn:feature_class":"P",
    "gn:feature_code":"PPL",
    "gn:name":"Al \u1e28adah",
    "gn:population":0,
    "gn:timezone":"Asia/Baghdad",
    "iso:country":"IQ",
    "name:ara_x_preferred":[
        "\u0627\u0644\u062d\u062f\u0629"
    ],
    "name:und_x_variant":[
        "Al \u1e28adah"
    ],
    "wof:name":"Al Hadah",
    "wof:placetype":"locality"
},
  "geometry": {"coordinates":[47.32161,30.94661],"type":"Point"}
}