{
  "type": "Feature",
  "properties": {
    "gn:admin1_code":"6.0",
    "gn:admin2_code":"99348.0",
    "gn:asciiname":"Faris",
    "gn:country_code":"IQ",
    "gn:dem":32,
    "gn:feature_class":"P",
    "gn:feature_code":"PPL",
    "gn:name":"F\u0101ris",
    "gn:population":0,
    "gn:timezone":"Asia/Baghdad",
    "iso:country":"IQ",
    "name:ara_x_preferred":[
        "F\u0101ris"
    ],
    "name:ceb_x_preferred":[
        "Faris"
    ],
    "name:deu_x_preferred":[
        "Faris"
    ],
    "name:heb_x_preferred":[
        "\u05e4\u05d0\u05e8\u05d9\u05e1"
    ],
    "name:ita_x_preferred":[
        "Faris"
    ],
    "name:rus_x_preferred":[
        "\u0424\u044d\u0440\u0438\u0441"
    ],
    "wof:name":"Faris",
    "wof:placetype":"locality"
},
  "geometry": {"coordinates":[44.31694,32.33139],"type":"Point"}
}