{
  "type": "Feature",
  "properties": {
    "gn:admin1_code":"11.0",
    "gn:admin2_code":"93817.0",
    "gn:asciiname":"Qaryat Sakiyah",
    "gn:country_code":"IQ",
    "gn:dem":215,
    "gn:feature_class":"P",
    "gn:feature_code":"PPL",
    "gn:name":"Qaryat S\u0101k\u012byah",
    "gn:population":0,
    "gn:timezone":"Asia/Baghdad",
    "iso:country":"IQ",
    "name:ara_x_preferred":[
        "\u0642\u0631\u064a\u0629 \u0633\u0627\u0643\u064a\u0629"
    ],
    "name:kur_x_preferred":[
        "Saq\u00eee"
    ],
    "name:kur_x_variant":[
        "\u0633\u0627\u0642\u064a\u06d5"
    ],
    "name:und_x_variant":[
        "S\u0101k\u012byah",
        "S\u0101qiyah",
        "Saqia",
        "Qaryat S\u0101k\u012byah"
    ],
    "wof:name":"Qaryat Sakiyah",
    "wof:placetype":"locality"
},
  "geometry": {"coordinates":[43.4248,35.98957],"type":"Point"}
}