{
  "type": "Feature",
  "properties": {
    "gn:admin1_code":"18.0",
    "gn:admin2_code":"90148.0",
    "gn:asciiname":"Qaryat al Hurayjiyah",
    "gn:country_code":"IQ",
    "gn:dem":105,
    "gn:feature_class":"P",
    "gn:feature_code":"PPL",
    "gn:name":"Qaryat al \u1e28urayj\u012byah",
    "gn:population":0,
    "gn:timezone":"Asia/Baghdad",
    "iso:country":"IQ",
    "name:ara_x_preferred":[
        "\u0642\u0631\u064a\u0629 \u0627\u0644\u062d\u0631\u064a\u062c\u064a\u0629"
    ],
    "name:und_x_variant":[
        "Qaryat al \u1e28urayj\u012byah"
    ],
    "wof:name":"Qaryat al Hurayjiyah",
    "wof:placetype":"locality"
},
  "geometry": {"coordinates":[43.50348,34.91713],"type":"Point"}
}