{
  "type": "Feature",
  "properties": {
    "gn:admin1_code":"10.0",
    "gn:admin2_code":"99063.0",
    "gn:asciiname":"Qaryat Abu al Hadid",
    "gn:country_code":"IQ",
    "gn:dem":51,
    "gn:feature_class":"P",
    "gn:feature_code":"PPL",
    "gn:name":"Qaryat Ab\u016b al \u1e28ad\u012bd",
    "gn:population":0,
    "gn:timezone":"Asia/Baghdad",
    "iso:country":"IQ",
    "name:ara_x_preferred":[
        "\u0642\u0631\u064a\u0629 \u0627\u0628\u0648 \u0627\u0644\u062d\u062f\u064a\u062f"
    ],
    "name:und_x_variant":[
        "Ab\u016b al \u1e28ad\u012bd",
        "\u2018Arab Ab\u016b al \u1e28ad\u012bd",
        "\u0627\u0628\u0648 \u0627\u0644\u062d\u062f\u064a\u062f",
        "Qaryat Ab\u016b al \u1e28ad\u012bd"
    ],
    "wof:name":"Qaryat Abu al Hadid",
    "wof:placetype":"locality"
},
  "geometry": {"coordinates":[44.80004,33.84935],"type":"Point"}
}