{
  "type": "Feature",
  "properties": {
    "gn:admin1_code":"4.0",
    "gn:admin2_code":"99763.0",
    "gn:asciiname":"Fahim Hamzah",
    "gn:country_code":"IQ",
    "gn:dem":23,
    "gn:feature_class":"P",
    "gn:feature_code":"PPL",
    "gn:name":"F\u0101him \u1e28amzah",
    "gn:population":0,
    "gn:timezone":"Asia/Baghdad",
    "iso:country":"IQ",
    "name:ara_x_preferred":[
        "\u0641\u0627\u0647\u0645 \u062d\u0645\u0632\u0629"
    ],
    "name:und_x_variant":[
        "F\u0101him \u1e28amzah"
    ],
    "wof:name":"Fahim Hamzah",
    "wof:placetype":"locality"
},
  "geometry": {"coordinates":[44.65033,32.07751],"type":"Point"}
}