{
  "type": "Feature",
  "properties": {
    "gn:admin1_code":"18.0",
    "gn:admin2_code":"91594.0",
    "gn:asciiname":"'Arab 'Awwad Jasim",
    "gn:country_code":"IQ",
    "gn:dem":63,
    "gn:feature_class":"P",
    "gn:feature_code":"PPL",
    "gn:name":"\u2018Arab \u2018Aww\u0101d J\u0101sim",
    "gn:population":0,
    "gn:timezone":"Asia/Baghdad",
    "iso:country":"IQ",
    "name:ara_x_preferred":[
        "\u0639\u0631\u0628 \u0639\u0648\u0627\u062f \u062c\u0627\u0633\u0645"
    ],
    "name:und_x_variant":[
        "\u2018Arab \u2018Aww\u0101d J\u0101sim"
    ],
    "wof:name":"'Arab 'Awwad Jasim",
    "wof:placetype":"locality"
},
  "geometry": {"coordinates":[43.1814,34.33544000000001],"type":"Point"}
}