{
  "type": "Feature",
  "properties": {
    "gn:admin1_code":"16.0",
    "gn:admin2_code":"98197.0",
    "gn:asciiname":"Shahrak-e Hashmiyeh",
    "gn:country_code":"IQ",
    "gn:dem":87,
    "gn:feature_class":"P",
    "gn:feature_code":"PPL",
    "gn:name":"Shahrak-e Hashm\u012byeh",
    "gn:population":0,
    "gn:timezone":"Asia/Baghdad",
    "iso:country":"IQ",
    "name:fas_x_preferred":[
        "\u0634\u0647\u0631\u06a9 \u0647\u0634\u0645\u06cc\u0647"
    ],
    "wof:name":"Shahrak-e Hashmiyeh",
    "wof:placetype":"locality"
},
  "geometry": {"coordinates":[45.9635,33.3054],"type":"Point"}
}