{
  "type": "Feature",
  "properties": {
    "gn:admin1_code":"6.0",
    "gn:admin2_code":"99358.0",
    "gn:asciiname":"Hani Hirz",
    "gn:country_code":"IQ",
    "gn:dem":25,
    "gn:feature_class":"P",
    "gn:feature_code":"PPL",
    "gn:name":"H\u0101n\u012b \u1e28irz",
    "gn:population":0,
    "gn:timezone":"Asia/Baghdad",
    "iso:country":"IQ",
    "name:ara_x_preferred":[
        "\u0647\u0627\u0646\u064a \u062d\u0631\u0632"
    ],
    "name:ara_x_variant":[
        "H\u0101n\u012b \u1e28irz"
    ],
    "wof:name":"Hani Hirz",
    "wof:placetype":"locality"
},
  "geometry": {"coordinates":[44.97563,32.35465],"type":"Point"}
}