{
  "type": "Feature",
  "properties": {
    "gn:admin1_code":"6.0",
    "gn:admin2_code":"99358.0",
    "gn:asciiname":"Hajji Shu'ayl Radi",
    "gn:country_code":"IQ",
    "gn:dem":24,
    "gn:feature_class":"P",
    "gn:feature_code":"PPL",
    "gn:name":"\u1e28ajj\u012b Shu\u2018ayl R\u0101\u1e11\u012b",
    "gn:population":0,
    "gn:timezone":"Asia/Baghdad",
    "iso:country":"IQ",
    "name:ara_x_preferred":[
        "\u062d\u062c\u064a \u0634\u0639\u064a\u0644 \u0631\u0627\u0636\u064a"
    ],
    "name:und_x_variant":[
        "\u1e28ajj\u012b Shu\u2018ayl R\u0101\u1e11\u012b"
    ],
    "wof:name":"Hajji Shu'ayl Radi",
    "wof:placetype":"locality"
},
  "geometry": {"coordinates":[44.88261,32.37753],"type":"Point"}
}