{
  "type": "Feature",
  "properties": {
    "gn:admin1_code":"5.0",
    "gn:admin2_code":"98464.0",
    "gn:asciiname":"Day Kawn",
    "gn:country_code":"IQ",
    "gn:dem":848,
    "gn:feature_class":"P",
    "gn:feature_code":"PPL",
    "gn:name":"Day Kawn",
    "gn:population":0,
    "gn:timezone":"Asia/Baghdad",
    "iso:country":"IQ",
    "name:ara_x_preferred":[
        "\u062f\u064a \u0643\u0648\u0646"
    ],
    "name:kur_x_preferred":[
        "D\u00ea Kon"
    ],
    "name:kur_x_variant":[
        "\u062f\u06ce \u0643\u06c6\u0646"
    ],
    "name:und_x_variant":[
        "Dayy Kawn",
        "D\u0113k\u014dn",
        "Decon"
    ],
    "wof:name":"Day Kawn",
    "wof:placetype":"locality"
},
  "geometry": {"coordinates":[45.31767,35.50567],"type":"Point"}
}