{
  "type": "Feature",
  "properties": {
    "gn:admin1_code":"6.0",
    "gn:admin2_code":"99040.0",
    "gn:asciiname":"Muhammad",
    "gn:country_code":"IQ",
    "gn:dem":33,
    "gn:feature_class":"P",
    "gn:feature_code":"PPL",
    "gn:name":"Mu\u1e29ammad",
    "gn:population":0,
    "gn:timezone":"Asia/Baghdad",
    "iso:country":"IQ",
    "name:und_x_variant":[
        "Mu\u1e29ammad"
    ],
    "wof:name":"Muhammad",
    "wof:placetype":"locality"
},
  "geometry": {"coordinates":[44.25972,32.78611],"type":"Point"}
}