{
  "type": "Feature",
  "properties": {
    "gn:admin1_code":"17.0",
    "gn:admin2_code":"9166552.0",
    "gn:asciiname":"Al Kawwah",
    "gn:country_code":"IQ",
    "gn:dem":21,
    "gn:feature_class":"P",
    "gn:feature_code":"PPL",
    "gn:name":"Al Kawwah",
    "gn:population":0,
    "gn:timezone":"Asia/Baghdad",
    "iso:country":"IQ",
    "name:ara_x_preferred":[
        "\u0627\u0644\u0643\u0648\u0629"
    ],
    "wof:name":"Al Kawwah",
    "wof:placetype":"locality"
},
  "geometry": {"coordinates":[44.5187,31.70384],"type":"Point"}
}