{
  "type": "Feature",
  "properties": {
    "gn:admin1_code":"11.0",
    "gn:admin2_code":"95444.0",
    "gn:asciiname":"Batirtaq",
    "gn:cc2":"IQ",
    "gn:country_code":"IQ",
    "gn:dem":343,
    "gn:feature_class":"P",
    "gn:feature_code":"PPL",
    "gn:name":"Batirtaq",
    "gn:population":0,
    "gn:timezone":"Asia/Baghdad",
    "iso:country":"IQ",
    "name:und_x_variant":[
        "Batirtoq",
        "Batirtaq"
    ],
    "wof:name":"Batirtaq",
    "wof:placetype":"locality"
},
  "geometry": {"coordinates":[43.91667,36.08333],"type":"Point"}
}