{
  "type": "Feature",
  "properties": {
    "gn:admin1_code":"6.0",
    "gn:admin2_code":"99358.0",
    "gn:asciiname":"Dakhr as Sayir",
    "gn:country_code":"IQ",
    "gn:dem":30,
    "gn:feature_class":"P",
    "gn:feature_code":"PPL",
    "gn:name":"\u1e10akhr as S\u0101yir",
    "gn:population":0,
    "gn:timezone":"Asia/Baghdad",
    "iso:country":"IQ",
    "name:ara_x_preferred":[
        "\u0636\u062e\u0631 \u0627\u0644\u0633\u0627\u064a\u0631"
    ],
    "name:und_x_variant":[
        "\u1e10akhr as S\u0101yir"
    ],
    "wof:name":"Dakhr as Sayir",
    "wof:placetype":"locality"
},
  "geometry": {"coordinates":[44.73271,32.42276],"type":"Point"}
}