{
  "type": "Feature",
  "properties": {
    "gn:admin1_code":"15.0",
    "gn:admin2_code":"98820.0",
    "gn:asciiname":"Qaryat Kayli",
    "gn:country_code":"IQ",
    "gn:dem":290,
    "gn:feature_class":"P",
    "gn:feature_code":"PPL",
    "gn:name":"Qaryat Kayl\u012b",
    "gn:population":0,
    "gn:timezone":"Asia/Baghdad",
    "iso:country":"IQ",
    "name:ara_x_preferred":[
        "\u0642\u0631\u064a\u0629 \u0643\u064a\u0644\u064a"
    ],
    "name:kur_x_preferred":[
        "C\u00ear\u00ee"
    ],
    "name:kur_x_variant":[
        "G\u00eal\u00ee S\u00eenan",
        "\u062c\u06ce\u0631\u0649",
        "\u06af\u06ce\u0644\u0649 \u0633\u064a\u0646\u0627\u0646"
    ],
    "name:und_x_variant":[
        "Kel\u012b",
        "Qaryat Kayl\u012b",
        "\u0642\u0631\u064a\u0629 \u0643\u064a\u0644\u064a",
        "Jeri"
    ],
    "wof:name":"Qaryat Kayli",
    "wof:placetype":"locality"
},
  "geometry": {"coordinates":[44.05164,36.61553],"type":"Point"}
}