{
  "type": "Feature",
  "properties": {
    "gn:admin1_code":"10.0",
    "gn:admin2_code":"9166680.0",
    "gn:asciiname":"Qal'at Sa'ud al Hamad",
    "gn:country_code":"IQ",
    "gn:dem":98,
    "gn:feature_class":"P",
    "gn:feature_code":"PPL",
    "gn:name":"Qal\u2018at Sa\u2018\u016bd al \u1e28amad",
    "gn:population":0,
    "gn:timezone":"Asia/Baghdad",
    "iso:country":"IQ",
    "name:ara_x_preferred":[
        "\u0642\u0644\u0639\u0629 \u0633\u0639\u0648\u062f \u0627\u0644\u062d\u0645\u062f"
    ],
    "name:fas_x_preferred":[
        "\u0642\u0644\u0639\u0647 \u0645\u0633\u0639\u0648\u062f\u0627\u0644\u0645\u062d\u0645\u062f"
    ],
    "name:fas_x_variant":[
        "Qal\u2018eh-ye Mas\u2018\u016bd ol Mo\u1e29ammad"
    ],
    "name:und_x_variant":[
        "Qal\u2018at Sa\u2018\u016bd al \u1e28amad"
    ],
    "wof:name":"Qal'at Sa'ud al Hamad",
    "wof:placetype":"locality"
},
  "geometry": {"coordinates":[45.77486,33.5214],"type":"Point"}
}