{
  "type": "Feature",
  "properties": {
    "gn:admin1_code":"1.0",
    "gn:admin2_code":"99455.0",
    "gn:asciiname":"Ad Dulaimiya",
    "gn:country_code":"IQ",
    "gn:dem":40,
    "gn:feature_class":"P",
    "gn:feature_code":"PPL",
    "gn:name":"Ad Dulaimiya",
    "gn:population":0,
    "gn:timezone":"Asia/Baghdad",
    "iso:country":"IQ",
    "wof:name":"Ad Dulaimiya",
    "wof:placetype":"locality"
},
  "geometry": {"coordinates":[43.95421,33.41214],"type":"Point"}
}