{
  "type": "Feature",
  "properties": {
    "gn:admin1_code":"6.0",
    "gn:admin2_code":"99358.0",
    "gn:asciiname":"Muhammad Sirhan",
    "gn:country_code":"IQ",
    "gn:dem":23,
    "gn:feature_class":"P",
    "gn:feature_code":"PPL",
    "gn:name":"Mu\u1e29ammad Sir\u1e29\u0101n",
    "gn:population":0,
    "gn:timezone":"Asia/Baghdad",
    "iso:country":"IQ",
    "name:ara_x_preferred":[
        "\u0645\u062d\u0645\u062f \u0633\u0631\u062d\u0627\u0646"
    ],
    "name:und_x_variant":[
        "Mu\u1e29ammad Sir\u1e29\u0101n"
    ],
    "wof:name":"Muhammad Sirhan",
    "wof:placetype":"locality"
},
  "geometry": {"coordinates":[44.52658,32.259],"type":"Point"}
}