{
  "type": "Feature",
  "properties": {
    "gn:admin1_code":"18.0",
    "gn:admin2_code":"9167093.0",
    "gn:asciiname":"Khalaf Fayad",
    "gn:country_code":"IQ",
    "gn:dem":67,
    "gn:feature_class":"P",
    "gn:feature_code":"PPL",
    "gn:name":"Khalaf Fay\u0101\u1e11",
    "gn:population":0,
    "gn:timezone":"Asia/Baghdad",
    "iso:country":"IQ",
    "name:ara_x_preferred":[
        "\u062e\u0644\u0641 \u0641\u064a\u0627\u0636"
    ],
    "name:und_x_variant":[
        "Khalaf Fay\u0101\u1e11"
    ],
    "wof:name":"Khalaf Fayad",
    "wof:placetype":"locality"
},
  "geometry": {"coordinates":[43.71845,34.02909],"type":"Point"}
}