{
  "type": "Feature",
  "properties": {
    "gn:admin1_code":"9.0",
    "gn:admin2_code":"98623.0",
    "gn:asciiname":"Jabbar al Hami",
    "gn:country_code":"IQ",
    "gn:dem":10,
    "gn:feature_class":"P",
    "gn:feature_code":"PPL",
    "gn:name":"Jabb\u0101r al \u1e28\u0101m\u012b",
    "gn:population":0,
    "gn:timezone":"Asia/Baghdad",
    "iso:country":"IQ",
    "name:ara_x_preferred":[
        "\u062c\u0628\u0627\u0631 \u0627\u0644\u062d\u0627\u0645\u064a"
    ],
    "name:und_x_variant":[
        "Jabb\u0101r al \u1e28\u0101m\u012b"
    ],
    "wof:name":"Jabbar al Hami",
    "wof:placetype":"locality"
},
  "geometry": {"coordinates":[46.1311,31.4066],"type":"Point"}
}