{
  "type": "Feature",
  "properties": {
    "gn:admin1_code":"6.0",
    "gn:admin2_code":"6818313.0",
    "gn:asciiname":"Hasan al Musa",
    "gn:country_code":"IQ",
    "gn:dem":34,
    "gn:feature_class":"P",
    "gn:feature_code":"PPL",
    "gn:name":"\u1e28asan al M\u016bs\u00e1",
    "gn:population":0,
    "gn:timezone":"Asia/Baghdad",
    "iso:country":"IQ",
    "name:ara_x_preferred":[
        "\u062d\u0633\u0646 \u0627\u0644\u0645\u0648\u0633\u0649"
    ],
    "name:und_x_variant":[
        "\u1e28usayn al M\u016bs\u00e1",
        "\u1e28asan al M\u016bs\u00e1"
    ],
    "wof:name":"Hasan al Musa",
    "wof:placetype":"locality"
},
  "geometry": {"coordinates":[44.48481,32.49232],"type":"Point"}
}