{
  "type": "Feature",
  "properties": {
    "gn:admin1_code":"2.0",
    "gn:admin2_code":"100049.0",
    "gn:asciiname":"Manazel Al Kharabeh",
    "gn:country_code":"IQ",
    "gn:dem":3,
    "gn:feature_class":"P",
    "gn:feature_code":"PPL",
    "gn:name":"Man\u0101zel Al Kharabeh",
    "gn:population":0,
    "gn:timezone":"Asia/Baghdad",
    "iso:country":"IQ",
    "name:fas_x_preferred":[
        "Man\u0101zel Al Kharabeh"
    ],
    "wof:name":"Manazel Al Kharabeh",
    "wof:placetype":"locality"
},
  "geometry": {"coordinates":[48.3225,30.2663],"type":"Point"}
}