{
  "type": "Feature",
  "properties": {
    "gn:admin1_code":"4.0",
    "gn:admin2_code":"6850588.0",
    "gn:asciiname":"Ahmad Abu Tubaykh",
    "gn:country_code":"IQ",
    "gn:dem":14,
    "gn:feature_class":"P",
    "gn:feature_code":"PPL",
    "gn:name":"A\u1e29mad Ab\u016b \u0162ubaykh",
    "gn:population":0,
    "gn:timezone":"Asia/Baghdad",
    "iso:country":"IQ",
    "name:ara_x_preferred":[
        "\u0627\u062d\u0645\u062f \u0627\u0628\u0648 \u0637\u0628\u064a\u062e"
    ],
    "name:und_x_variant":[
        "A\u1e29mad Ab\u016b \u0162ubaykh"
    ],
    "wof:name":"Ahmad Abu Tubaykh",
    "wof:placetype":"locality"
},
  "geometry": {"coordinates":[44.97331,31.57963],"type":"Point"}
}