{
  "type": "Feature",
  "properties": {
    "gn:admin1_code":"10.0",
    "gn:admin2_code":"94590.0",
    "gn:asciiname":"Tappah Qalandari",
    "gn:cc2":"IQ",
    "gn:country_code":"IQ",
    "gn:dem":365,
    "gn:feature_class":"P",
    "gn:feature_code":"PPL",
    "gn:name":"Tappah Qalandar\u012b",
    "gn:population":0,
    "gn:timezone":"Asia/Baghdad",
    "iso:country":"IQ",
    "name:und_x_variant":[
        "Tepe Qalandari",
        "Tappah Qalandar\u012b"
    ],
    "wof:name":"Tappah Qalandari",
    "wof:placetype":"locality"
},
  "geometry": {"coordinates":[45.66667,34.88333],"type":"Point"}
}