{
  "type": "Feature",
  "properties": {
    "gn:admin1_code":"18.0",
    "gn:admin2_code":"6783103.0",
    "gn:asciiname":"Tarayshah",
    "gn:country_code":"IQ",
    "gn:dem":55,
    "gn:feature_class":"P",
    "gn:feature_code":"PPL",
    "gn:name":"Tarayshah",
    "gn:population":0,
    "gn:timezone":"Asia/Baghdad",
    "iso:country":"IQ",
    "name:und_x_variant":[
        "A\u0163 \u0162urayshah"
    ],
    "wof:name":"Tarayshah",
    "wof:placetype":"locality"
},
  "geometry": {"coordinates":[44.04778,34.10667],"type":"Point"}
}