{
  "type": "Feature",
  "properties": {
    "gn:admin1_code":"4.0",
    "gn:admin2_code":"98634.0",
    "gn:asciiname":"Hilal Daghsh",
    "gn:country_code":"IQ",
    "gn:dem":18,
    "gn:feature_class":"P",
    "gn:feature_code":"PPL",
    "gn:name":"Hil\u0101l Daghsh",
    "gn:population":0,
    "gn:timezone":"Asia/Baghdad",
    "iso:country":"IQ",
    "name:ara_x_preferred":[
        "\u0647\u0644\u0627\u0644 \u062f\u063a\u0634"
    ],
    "name:und_x_variant":[
        "Hil\u0101l Daghsh"
    ],
    "wof:name":"Hilal Daghsh",
    "wof:placetype":"locality"
},
  "geometry": {"coordinates":[44.70131,31.72695],"type":"Point"}
}