{
  "type": "Feature",
  "properties": {
    "gn:admin1_code":"9.0",
    "gn:admin2_code":"98855.0",
    "gn:asciiname":"Ar Rashadah",
    "gn:country_code":"IQ",
    "gn:dem":8,
    "gn:feature_class":"P",
    "gn:feature_code":"PPL",
    "gn:name":"Ar Rash\u0101dah",
    "gn:population":0,
    "gn:timezone":"Asia/Baghdad",
    "iso:country":"IQ",
    "name:ara_x_preferred":[
        "\u0627\u0644\u0631\u0634\u0627\u062f\u0629"
    ],
    "name:und_x_variant":[
        "Ar Rash\u0101dah"
    ],
    "wof:name":"Ar Rashadah",
    "wof:placetype":"locality"
},
  "geometry": {"coordinates":[45.78893,31.16294000000001],"type":"Point"}
}