{
  "type": "Feature",
  "properties": {
    "gn:admin1_code":"6.0",
    "gn:admin2_code":"99358.0",
    "gn:asciiname":"Khara'ib Kazim Musa",
    "gn:country_code":"IQ",
    "gn:dem":25,
    "gn:feature_class":"P",
    "gn:feature_code":"PPL",
    "gn:name":"Khar\u0101\u2019ib K\u0101z\u0327im M\u016bs\u00e1",
    "gn:population":0,
    "gn:timezone":"Asia/Baghdad",
    "iso:country":"IQ",
    "name:ara_x_preferred":[
        "\u062e\u0631\u0627\u0626\u0628 \u0643\u0627\u0638\u0645 \u0645\u0648\u0633\u0649"
    ],
    "name:und_x_variant":[
        "Khar\u0101\u2019ib K\u0101z\u0327im M\u016bs\u00e1"
    ],
    "wof:name":"Khara'ib Kazim Musa",
    "wof:placetype":"locality"
},
  "geometry": {"coordinates":[44.72326,32.21658],"type":"Point"}
}