{
  "type": "Feature",
  "properties": {
    "gn:admin1_code":"5.0",
    "gn:admin2_code":"92743.0",
    "gn:asciiname":"Nuradin",
    "gn:country_code":"IQ",
    "gn:dem":559,
    "gn:feature_class":"P",
    "gn:feature_code":"PPL",
    "gn:name":"N\u016brad\u012bn",
    "gn:population":0,
    "gn:timezone":"Asia/Baghdad",
    "iso:country":"IQ",
    "name:ara_x_preferred":[
        "\u0646\u0648\u0631\u062f\u064a\u0646"
    ],
    "name:kur_x_preferred":[
        "Nured\u00een"
    ],
    "name:kur_x_variant":[
        "\u0646\u0648\u0631\u06d5\u062f\u064a\u0646"
    ],
    "name:und_x_variant":[
        "N\u016bradd\u012bn",
        "N\u016brad\u012bn",
        "N\u016brudd\u012bn",
        "Nuraddin",
        "Nooradeen"
    ],
    "wof:name":"Nuradin",
    "wof:placetype":"locality"
},
  "geometry": {"coordinates":[45.15669000000001,36.13177],"type":"Point"}
}