{
  "type": "Feature",
  "properties": {
    "gn:admin1_code":"1.0",
    "gn:admin2_code":"98718.0",
    "gn:asciiname":"Salih al 'Ayyash",
    "gn:country_code":"IQ",
    "gn:dem":59,
    "gn:feature_class":"P",
    "gn:feature_code":"PPL",
    "gn:name":"\u015e\u0101li\u1e29 al \u2018Ayy\u0101sh",
    "gn:population":0,
    "gn:timezone":"Asia/Baghdad",
    "iso:country":"IQ",
    "name:ara_x_preferred":[
        "\u0635\u0627\u0644\u062d \u0627\u0644\u0639\u064a\u0627\u0634"
    ],
    "name:und_x_variant":[
        "\u015e\u0101li\u1e29 al \u2018Ayy\u0101sh"
    ],
    "wof:name":"Salih al 'Ayyash",
    "wof:placetype":"locality"
},
  "geometry": {"coordinates":[43.039,33.46762],"type":"Point"}
}