{
  "type": "Feature",
  "properties": {
    "gn:admin1_code":"6.0",
    "gn:admin2_code":"99348.0",
    "gn:asciiname":"Qaryat Al Kaysam",
    "gn:country_code":"IQ",
    "gn:dem":34,
    "gn:feature_class":"P",
    "gn:feature_code":"PPL",
    "gn:name":"Qaryat \u0100l Kaysam",
    "gn:population":0,
    "gn:timezone":"Asia/Baghdad",
    "iso:country":"IQ",
    "name:ara_x_preferred":[
        "\u0642\u0631\u064a\u0629 \u0627\u0644 \u0643\u064a\u0633\u0645"
    ],
    "name:und_x_variant":[
        "Qaryat \u0100l Kaysam"
    ],
    "wof:name":"Qaryat Al Kaysam",
    "wof:placetype":"locality"
},
  "geometry": {"coordinates":[44.30095,32.47228],"type":"Point"}
}