{
  "type": "Feature",
  "properties": {
    "gn:admin1_code":"7.0",
    "gn:admin2_code":"9166545.0",
    "gn:asciiname":"Munkhi Sarhid",
    "gn:country_code":"IQ",
    "gn:dem":37,
    "gn:feature_class":"P",
    "gn:feature_code":"PPL",
    "gn:name":"Munkh\u012b Sarhid",
    "gn:population":0,
    "gn:timezone":"Asia/Baghdad",
    "iso:country":"IQ",
    "name:ara_x_preferred":[
        "\u0645\u0646\u062e\u064a \u0633\u0631\u0647\u062f"
    ],
    "name:und_x_variant":[
        "Munkh\u012b Sarhid"
    ],
    "wof:name":"Munkhi Sarhid",
    "wof:placetype":"locality"
},
  "geometry": {"coordinates":[44.39797,33.19427],"type":"Point"}
}