{
  "type": "Feature",
  "properties": {
    "gn:admin1_code":"6.0",
    "gn:admin2_code":"99358.0",
    "gn:asciiname":"Jabr 'Ali",
    "gn:country_code":"IQ",
    "gn:dem":27,
    "gn:feature_class":"P",
    "gn:feature_code":"PPL",
    "gn:name":"Jabr \u2018Al\u012b",
    "gn:population":0,
    "gn:timezone":"Asia/Baghdad",
    "iso:country":"IQ",
    "name:ara_x_preferred":[
        "\u062c\u0628\u0631 \u0639\u0644\u064a"
    ],
    "name:und_x_variant":[
        "Jabr \u2018Al\u012b"
    ],
    "wof:name":"Jabr 'Ali",
    "wof:placetype":"locality"
},
  "geometry": {"coordinates":[44.82982,32.27898],"type":"Point"}
}