{
  "type": "Feature",
  "properties": {
    "gn:admin1_code":"16.0",
    "gn:admin2_code":"98460.0",
    "gn:asciiname":"'Arab 'Ujayl",
    "gn:country_code":"IQ",
    "gn:dem":22,
    "gn:feature_class":"P",
    "gn:feature_code":"PPL",
    "gn:name":"\u2018Arab \u2018Ujayl",
    "gn:population":0,
    "gn:timezone":"Asia/Baghdad",
    "iso:country":"IQ",
    "name:ara_x_preferred":[
        "\u0639\u0631\u0628 \u0639\u062c\u064a\u0644"
    ],
    "name:und_x_variant":[
        "\u2018Arab \u2018Ujayl"
    ],
    "wof:name":"'Arab 'Ujayl",
    "wof:placetype":"locality"
},
  "geometry": {"coordinates":[45.15277,32.6728],"type":"Point"}
}