{
  "type": "Feature",
  "properties": {
    "gn:admin1_code":"14.0",
    "gn:admin2_code":"99610.0",
    "gn:asciiname":"Salaf Al Mushar'ah",
    "gn:country_code":"IQ",
    "gn:dem":9,
    "gn:feature_class":"P",
    "gn:feature_code":"PPL",
    "gn:name":"Salaf \u0100l Mushar\u2018ah",
    "gn:population":0,
    "gn:timezone":"Asia/Baghdad",
    "iso:country":"IQ",
    "name:ara_x_preferred":[
        "\u0633\u0644\u0641 \u0622\u0644 \u0645\u0634\u0631\u0639\u0647"
    ],
    "name:und_x_variant":[
        "Salaf \u0100l Mushar\u2018ah"
    ],
    "wof:name":"Salaf Al Mushar'ah",
    "wof:placetype":"locality"
},
  "geometry": {"coordinates":[46.98607,31.83317000000001],"type":"Point"}
}