{
  "type": "Feature",
  "properties": {
    "gn:admin1_code":"1.0",
    "gn:admin2_code":"99455.0",
    "gn:asciiname":"Qaryat Duwaylah",
    "gn:country_code":"IQ",
    "gn:dem":42,
    "gn:feature_class":"P",
    "gn:feature_code":"PPL",
    "gn:name":"Qaryat Duwaylah",
    "gn:population":0,
    "gn:timezone":"Asia/Baghdad",
    "iso:country":"IQ",
    "name:ara_x_preferred":[
        "\u0642\u0631\u064a\u0629 \u062f\u0648\u064a\u0644\u0629"
    ],
    "wof:name":"Qaryat Duwaylah",
    "wof:placetype":"locality"
},
  "geometry": {"coordinates":[43.93402,33.17375999999999],"type":"Point"}
}