{
  "type": "Feature",
  "properties": {
    "gn:admin1_code":"5.0",
    "gn:admin2_code":"98464.0",
    "gn:asciiname":"Dar Barulah",
    "gn:country_code":"IQ",
    "gn:dem":840,
    "gn:feature_class":"P",
    "gn:feature_code":"PPL",
    "gn:name":"D\u0101r Bar\u016blah",
    "gn:population":0,
    "gn:timezone":"Asia/Baghdad",
    "iso:country":"IQ",
    "name:ara_x_preferred":[
        "\u062f\u0627\u0631 \u0628\u0631\u0648\u0644\u0647"
    ],
    "name:kur_x_preferred":[
        "Dar Be\u1e5fu"
    ],
    "name:kur_x_variant":[
        "Dar Be\u1e5fule",
        "\u062f\u0627\u0631 \u0628\u06d5\u0695\u0648",
        "\u062f\u0627\u0631 \u0628\u06d5\u0695\u0648\u0644\u06d5"
    ],
    "name:und_x_variant":[
        "D\u0101r Bar\u016blah",
        "D\u0101rbar\u016bla",
        "Dar Baroola"
    ],
    "wof:name":"Dar Barulah",
    "wof:placetype":"locality"
},
  "geometry": {"coordinates":[45.30941,35.51738],"type":"Point"}
}