{
  "type": "Feature",
  "properties": {
    "gn:admin1_code":"9.0",
    "gn:admin2_code":"98700.0",
    "gn:asciiname":"Zufayr",
    "gn:country_code":"IQ",
    "gn:dem":9,
    "gn:feature_class":"P",
    "gn:feature_code":"PPL",
    "gn:name":"Z\u0327ufayr",
    "gn:population":0,
    "gn:timezone":"Asia/Baghdad",
    "iso:country":"IQ",
    "name:ara_x_preferred":[
        "\u0638\u0641\u064a\u0631"
    ],
    "name:und_x_variant":[
        "Z\u0327ufayr"
    ],
    "wof:name":"Zufayr",
    "wof:placetype":"locality"
},
  "geometry": {"coordinates":[46.06808,31.6139],"type":"Point"}
}