{
  "type": "Feature",
  "properties": {
    "gn:admin1_code":"13.0",
    "gn:admin2_code":"6770659.0",
    "gn:asciiname":"Qaryat al `Arishah al `Ulya",
    "gn:country_code":"IQ",
    "gn:dem":202,
    "gn:feature_class":"P",
    "gn:feature_code":"PPL",
    "gn:name":"Qaryat al \u2018Ar\u012bshah al \u2018Uly\u0101",
    "gn:population":0,
    "gn:timezone":"Asia/Baghdad",
    "iso:country":"IQ",
    "name:ara_x_preferred":[
        "\u0642\u0631\u064a\u0629 \u0627\u0644\u0639\u0631\u064a\u0634\u0629 \u0627\u0644\u0639\u0644\u064a\u0627"
    ],
    "name:und_x_variant":[
        "Qaryat al \u2018Ar\u012bshah al \u2018Uly\u0101"
    ],
    "wof:name":"Qaryat al `Arishah al `Ulya",
    "wof:placetype":"locality"
},
  "geometry": {"coordinates":[43.82378,35.46731],"type":"Point"}
}