{
  "type": "Feature",
  "properties": {
    "gn:admin1_code":"4.0",
    "gn:admin2_code":"99763.0",
    "gn:asciiname":"Jihad Sharaji",
    "gn:country_code":"IQ",
    "gn:dem":24,
    "gn:feature_class":"P",
    "gn:feature_code":"PPL",
    "gn:name":"Jih\u0101d Sharaj\u012b",
    "gn:population":0,
    "gn:timezone":"Asia/Baghdad",
    "iso:country":"IQ",
    "name:ara_x_preferred":[
        "\u062c\u0647\u0627\u062f \u0634\u0631\u062c\u064a"
    ],
    "name:und_x_variant":[
        "Jih\u0101d Sharaj\u012b"
    ],
    "wof:name":"Jihad Sharaji",
    "wof:placetype":"locality"
},
  "geometry": {"coordinates":[44.6238,31.94071],"type":"Point"}
}