{
  "type": "Feature",
  "properties": {
    "gn:admin1_code":"7.0",
    "gn:admin2_code":"9166569.0",
    "gn:asciiname":"Mutlab",
    "gn:country_code":"IQ",
    "gn:dem":39,
    "gn:feature_class":"P",
    "gn:feature_code":"PPL",
    "gn:name":"Mu\u0163lab",
    "gn:population":0,
    "gn:timezone":"Asia/Baghdad",
    "iso:country":"IQ",
    "name:ara_x_preferred":[
        "\u0645\u0637\u0644\u0628"
    ],
    "name:und_x_variant":[
        "Mu\u0163lab"
    ],
    "wof:name":"Mutlab",
    "wof:placetype":"locality"
},
  "geometry": {"coordinates":[44.2847,33.63778],"type":"Point"}
}