{
  "type": "Feature",
  "properties": {
    "gn:admin1_code":"8.0",
    "gn:admin2_code":"89569.0",
    "gn:asciiname":"Karbat 'Ali",
    "gn:country_code":"IQ",
    "gn:dem":587,
    "gn:feature_class":"P",
    "gn:feature_code":"PPL",
    "gn:name":"Karbat \u2018Al\u012b",
    "gn:population":0,
    "gn:timezone":"Asia/Baghdad",
    "iso:country":"IQ",
    "name:ara_x_preferred":[
        "\u0643\u0631\u0628\u0629 \u0639\u0644\u064a"
    ],
    "name:kur_x_preferred":[
        "Kerbe \u2018El\u00ee"
    ],
    "name:kur_x_variant":[
        "\u0643\u06d5\u0631\u0628\u06d5 \u0639\u06d5\u0644\u0649",
        "Kerpit \u2018El\u00ee",
        "\u0643\u06d5\u0631\u067e\u062a \u0639\u06d5\u0644\u0649"
    ],
    "name:und_x_variant":[
        "Karpit \u2018Al\u012b",
        "K-Ala",
        "Karpite",
        "Karbat \u2018Al\u012b",
        "Karpit Ali"
    ],
    "wof:name":"Karbat 'Ali",
    "wof:placetype":"locality"
},
  "geometry": {"coordinates":[42.96068,37.10926],"type":"Point"}
}