{
  "type": "Feature",
  "properties": {
    "gn:admin1_code":"5.0",
    "gn:admin2_code":"97416.0",
    "gn:asciiname":"Kani 'Arban",
    "gn:country_code":"IQ",
    "gn:dem":609,
    "gn:feature_class":"P",
    "gn:feature_code":"PPL",
    "gn:name":"K\u0101n\u012b \u2018\u0100rb\u0101n",
    "gn:population":0,
    "gn:timezone":"Asia/Baghdad",
    "iso:country":"IQ",
    "name:ara_x_preferred":[
        "K\u0101n\u012b \u2018\u0100rb\u0101n"
    ],
    "name:ara_x_variant":[
        "\u0643\u0627\u0646\u064a \u0639\u0627\u0631\u0628\u0627\u0646"
    ],
    "name:und_x_variant":[
        "K\u0101ni A\u2018ab\u0101n",
        "K\u0101n\u012b \u2018Ab\u0101n"
    ],
    "wof:name":"Kani 'Arban",
    "wof:placetype":"locality"
},
  "geometry": {"coordinates":[44.80023,35.69537000000001],"type":"Point"}
}