{
  "type": "Feature",
  "properties": {
    "gn:admin1_code":"1.0",
    "gn:admin2_code":"9166579.0",
    "gn:asciiname":"Radi al Mish'al",
    "gn:country_code":"IQ",
    "gn:dem":55,
    "gn:feature_class":"P",
    "gn:feature_code":"PPL",
    "gn:name":"R\u0101\u1e11\u012b al Mish\u2018al",
    "gn:population":0,
    "gn:timezone":"Asia/Baghdad",
    "iso:country":"IQ",
    "name:ara_x_preferred":[
        "\u0631\u0627\u0636\u064a \u0627\u0644\u0645\u0634\u0639\u0644"
    ],
    "name:und_x_variant":[
        "R\u0101\u1e11\u012b al Mish\u2018al"
    ],
    "wof:name":"Radi al Mish'al",
    "wof:placetype":"locality"
},
  "geometry": {"coordinates":[43.04728,33.48746],"type":"Point"}
}