{
  "type": "Feature",
  "properties": {
    "gn:admin1_code":"2.0",
    "gn:admin2_code":"99534.0",
    "gn:asciiname":"Qaryat Umm al Hawali",
    "gn:country_code":"IQ",
    "gn:dem":3,
    "gn:feature_class":"P",
    "gn:feature_code":"PPL",
    "gn:name":"Qaryat Umm al \u1e28aw\u0101l\u012b",
    "gn:population":0,
    "gn:timezone":"Asia/Baghdad",
    "iso:country":"IQ",
    "name:ara_x_preferred":[
        "\u0642\u0631\u064a\u0629 \u0627\u0645 \u0627\u0644\u062d\u0648\u0627\u0644\u064a"
    ],
    "name:und_x_variant":[
        "Qaryat Umm al \u1e28aw\u0101l\u012b"
    ],
    "wof:name":"Qaryat Umm al Hawali",
    "wof:placetype":"locality"
},
  "geometry": {"coordinates":[47.68845,30.61525],"type":"Point"}
}