{
  "type": "Feature",
  "properties": {
    "gn:admin1_code":"9.0",
    "gn:admin2_code":"98855.0",
    "gn:asciiname":"Hajj Ihlil",
    "gn:country_code":"IQ",
    "gn:dem":8,
    "gn:feature_class":"P",
    "gn:feature_code":"PPL",
    "gn:name":"\u1e28\u0101jj Ihl\u012bl",
    "gn:population":0,
    "gn:timezone":"Asia/Baghdad",
    "iso:country":"IQ",
    "name:ara_x_preferred":[
        "\u062d\u0627\u062c \u0627\u0647\u0644\u064a\u0644"
    ],
    "name:ara_x_variant":[
        "\u1e28\u0101jj Ihl\u012bl"
    ],
    "wof:name":"Hajj Ihlil",
    "wof:placetype":"locality"
},
  "geometry": {"coordinates":[45.95129,31.10995],"type":"Point"}
}