{
  "type": "Feature",
  "properties": {
    "gn:admin1_code":"18.0",
    "gn:admin2_code":"6783103.0",
    "gn:asciiname":"Ta'mat Nasif",
    "gn:country_code":"IQ",
    "gn:dem":78,
    "gn:feature_class":"P",
    "gn:feature_code":"PPL",
    "gn:name":"\u0162a\u2018mat Na\u015f\u012bf",
    "gn:population":0,
    "gn:timezone":"Asia/Baghdad",
    "iso:country":"IQ",
    "name:ara_x_preferred":[
        "\u0637\u0639\u0645\u0629 \u0646\u0635\u064a\u0641"
    ],
    "name:und_x_variant":[
        "\u0162a\u2018mat Na\u015f\u012bf"
    ],
    "wof:name":"Ta'mat Nasif",
    "wof:placetype":"locality"
},
  "geometry": {"coordinates":[43.87239,34.26178],"type":"Point"}
}