{
  "type": "Feature",
  "properties": {
    "gn:admin1_code":"5.0",
    "gn:admin2_code":"96204.0",
    "gn:asciiname":"Lamarkazi",
    "gn:country_code":"IQ",
    "gn:dem":498,
    "gn:feature_class":"P",
    "gn:feature_code":"PPL",
    "gn:name":"L\u0101markaz\u012b",
    "gn:population":0,
    "gn:timezone":"Asia/Baghdad",
    "iso:country":"IQ",
    "name:ara_x_preferred":[
        "\u0644\u0627\u0645\u0631\u0643\u0632\u064a"
    ],
    "name:und_x_variant":[
        "L\u0101markaz\u012b"
    ],
    "wof:name":"Lamarkazi",
    "wof:placetype":"locality"
},
  "geometry": {"coordinates":[45.95045,35.28482],"type":"Point"}
}