{
  "type": "Feature",
  "properties": {
    "gn:admin1_code":"18.0",
    "gn:admin2_code":"91594.0",
    "gn:asciiname":"Rashid Mahdi",
    "gn:country_code":"IQ",
    "gn:dem":83,
    "gn:feature_class":"P",
    "gn:feature_code":"PPL",
    "gn:name":"Rash\u012bd Mahd\u012b",
    "gn:population":0,
    "gn:timezone":"Asia/Baghdad",
    "iso:country":"IQ",
    "name:ara_x_preferred":[
        "\u0631\u0634\u064a\u062f \u0645\u0647\u062f\u064a"
    ],
    "name:und_x_variant":[
        "Rash\u012bd Mahd\u012b"
    ],
    "wof:name":"Rashid Mahdi",
    "wof:placetype":"locality"
},
  "geometry": {"coordinates":[43.7222,34.18881],"type":"Point"}
}