{
  "type": "Feature",
  "properties": {
    "gn:admin1_code":"10.0",
    "gn:admin2_code":"97988.0",
    "gn:asciiname":"Qaryat Husayn al Hamadi",
    "gn:country_code":"IQ",
    "gn:dem":44,
    "gn:feature_class":"P",
    "gn:feature_code":"PPL",
    "gn:name":"Qaryat \u1e28usayn al \u1e28am\u0101d\u012b",
    "gn:population":0,
    "gn:timezone":"Asia/Baghdad",
    "iso:country":"IQ",
    "name:ara_x_preferred":[
        "\u0642\u0631\u064a\u0629\u062d\u0633\u064a\u0646 \u0627\u0644\u062d\u0645\u0627\u062f\u064a"
    ],
    "name:und_x_variant":[
        "Qaryat \u1e28usayn al \u1e28am\u0101d\u012b"
    ],
    "wof:name":"Qaryat Husayn al Hamadi",
    "wof:placetype":"locality"
},
  "geometry": {"coordinates":[44.61095,33.61493],"type":"Point"}
}