{
  "type": "Feature",
  "properties": {
    "gn:admin1_code":"6.0",
    "gn:admin2_code":"99040.0",
    "gn:asciiname":"Hifdi al Baghdadi",
    "gn:country_code":"IQ",
    "gn:dem":32,
    "gn:feature_class":"P",
    "gn:feature_code":"PPL",
    "gn:name":"\u1e28if\u1e11\u012b al Baghd\u0101d\u012b",
    "gn:population":0,
    "gn:timezone":"Asia/Baghdad",
    "iso:country":"IQ",
    "name:ara_x_preferred":[
        "\u062d\u0641\u0636\u064a \u0627\u0644\u0628\u063a\u062f\u0627\u062f\u064a"
    ],
    "name:und_x_variant":[
        "\u1e28if\u1e11\u012b al Baghd\u0101d\u012b"
    ],
    "wof:name":"Hifdi al Baghdadi",
    "wof:placetype":"locality"
},
  "geometry": {"coordinates":[44.34553,32.54254],"type":"Point"}
}