{
  "type": "Feature",
  "properties": {
    "gn:admin1_code":"15.0",
    "gn:admin2_code":"9166649.0",
    "gn:asciiname":"Qaryat Najmah",
    "gn:country_code":"IQ",
    "gn:dem":264,
    "gn:feature_class":"P",
    "gn:feature_code":"PPL",
    "gn:name":"Qaryat Najmah",
    "gn:population":0,
    "gn:timezone":"Asia/Baghdad",
    "iso:country":"IQ",
    "name:ara_x_preferred":[
        "\u0642\u0631\u064a\u0629 \u0646\u062c\u0645\u0629"
    ],
    "name:und_x_variant":[
        "Kh\u0101n Najma",
        "Kh\u0101n Najmah",
        "Qaryat Najmah"
    ],
    "wof:name":"Qaryat Najmah",
    "wof:placetype":"locality"
},
  "geometry": {"coordinates":[43.10663,35.89427],"type":"Point"}
}