{
  "type": "Feature",
  "properties": {
    "gn:admin1_code":"18.0",
    "gn:admin2_code":"90148.0",
    "gn:asciiname":"'Arab Mahmud 'Ali",
    "gn:country_code":"IQ",
    "gn:dem":127,
    "gn:feature_class":"P",
    "gn:feature_code":"PPL",
    "gn:name":"\u2018Arab Ma\u1e29m\u016bd \u2018Al\u012b",
    "gn:population":0,
    "gn:timezone":"Asia/Baghdad",
    "iso:country":"IQ",
    "name:ara_x_preferred":[
        "\u0639\u0631\u0628 \u0645\u062d\u0645\u0648\u062f \u0639\u0644\u064a"
    ],
    "name:und_x_variant":[
        "\u2018Arab Ma\u1e29m\u016bd \u2018Al\u012b"
    ],
    "wof:name":"'Arab Mahmud 'Ali",
    "wof:placetype":"locality"
},
  "geometry": {"coordinates":[43.49032,34.46120999999999],"type":"Point"}
}