{
  "type": "Feature",
  "properties": {
    "gn:admin1_code":"5.0",
    "gn:admin2_code":"9166594.0",
    "gn:asciiname":"Baw Khusayn",
    "gn:country_code":"IQ",
    "gn:dem":625,
    "gn:feature_class":"P",
    "gn:feature_code":"PPL",
    "gn:name":"B\u0101w Kh\u016bsayn",
    "gn:population":0,
    "gn:timezone":"Asia/Baghdad",
    "iso:country":"IQ",
    "name:ara_x_preferred":[
        "\u0628\u0627\u0648 \u062e\u0648\u0633\u064a\u0646"
    ],
    "name:kur_x_preferred":[
        "Bawe Xosh\u00ean"
    ],
    "name:kur_x_variant":[
        "\u0628\u0627\u0648\u06d5 \u062e\u06c6\u0634\u06ce\u0646"
    ],
    "name:und_x_variant":[
        "B\u0101wa Khosh\u0113n",
        "Bawa Khoshain",
        "B\u0101w Kh\u016bsayn",
        "B\u0101wah Kh\u014dshayn",
        "Bawa Khoshen"
    ],
    "wof:name":"Baw Khusayn",
    "wof:placetype":"locality"
},
  "geometry": {"coordinates":[45.6123,35.17318],"type":"Point"}
}