{
  "type": "Feature",
  "properties": {
    "gn:admin1_code":"8.0",
    "gn:admin2_code":"89569.0",
    "gn:asciiname":"Mayrkay",
    "gn:country_code":"IQ",
    "gn:dem":670,
    "gn:feature_class":"P",
    "gn:feature_code":"PPL",
    "gn:name":"Mayrkay",
    "gn:population":0,
    "gn:timezone":"Asia/Baghdad",
    "iso:country":"IQ",
    "name:ara_x_preferred":[
        "\u0645\u064a\u0631\u0643\u064a"
    ],
    "name:kur_x_preferred":[
        "M\u00earg\u00ee"
    ],
    "name:kur_x_variant":[
        "\u0645\u06ce\u0631\u06af\u0649",
        "M\u00earg\u00ea",
        "\u0645\u06ce\u0631\u06af\u06ce"
    ],
    "name:und_x_variant":[
        "Barki",
        "Mergy",
        "Mayrkay",
        "Merge"
    ],
    "wof:name":"Mayrkay",
    "wof:placetype":"locality"
},
  "geometry": {"coordinates":[42.79311,37.21033],"type":"Point"}
}