{
  "type": "Feature",
  "properties": {
    "gn:admin1_code":"5.0",
    "gn:admin2_code":"97416.0",
    "gn:asciiname":"Kird Khabr",
    "gn:country_code":"IQ",
    "gn:dem":366,
    "gn:feature_class":"P",
    "gn:feature_code":"PPL",
    "gn:name":"Kird Khabr",
    "gn:population":0,
    "gn:timezone":"Asia/Baghdad",
    "iso:country":"IQ",
    "name:ara_x_preferred":[
        "\u0643\u0631\u062f \u062e\u0628\u0631"
    ],
    "name:und_x_variant":[
        "Kird Khabar",
        "Girdakhirr",
        "Kird Khabr",
        "Girdkhabar"
    ],
    "wof:name":"Kird Khabr",
    "wof:placetype":"locality"
},
  "geometry": {"coordinates":[44.71368,35.87183],"type":"Point"}
}