{
  "type": "Feature",
  "properties": {
    "gn:admin1_code":"9.0",
    "gn:admin2_code":"98855.0",
    "gn:asciiname":"Al Hadidi",
    "gn:country_code":"IQ",
    "gn:dem":9,
    "gn:feature_class":"P",
    "gn:feature_code":"PPL",
    "gn:name":"Al \u1e28ad\u012bd\u012b",
    "gn:population":0,
    "gn:timezone":"Asia/Baghdad",
    "iso:country":"IQ",
    "name:ara_x_preferred":[
        "\u0627\u0644\u062d\u062f\u064a\u062f\u064a"
    ],
    "name:und_x_variant":[
        "Al \u1e28ad\u012bd\u012b"
    ],
    "wof:name":"Al Hadidi",
    "wof:placetype":"locality"
},
  "geometry": {"coordinates":[46.11351,31.07588],"type":"Point"}
}