{
  "type": "Feature",
  "properties": {
    "gn:admin1_code":"11.0",
    "gn:admin2_code":"9166591.0",
    "gn:asciiname":"Kirdi Mawt",
    "gn:country_code":"IQ",
    "gn:dem":375,
    "gn:feature_class":"P",
    "gn:feature_code":"PPL",
    "gn:name":"Kird\u012b M\u0101wt",
    "gn:population":0,
    "gn:timezone":"Asia/Baghdad",
    "iso:country":"IQ",
    "name:ara_x_preferred":[
        "\u0643\u0631\u062f\u064a \u0645\u0627\u0648\u062a"
    ],
    "name:kur_x_preferred":[
        "Grd\u00ee Mawl\u00een"
    ],
    "name:kur_x_variant":[
        "\u06af\u0631\u062f\u0649 \u0645\u0627\u0648\u0644\u064a\u0646"
    ],
    "name:und_x_variant":[
        "Girdi M\u0101w\u0101n",
        "Kird\u012b M\u0101wt",
        "Grdi Mawlin"
    ],
    "wof:name":"Kirdi Mawt",
    "wof:placetype":"locality"
},
  "geometry": {"coordinates":[43.9475,36.4192],"type":"Point"}
}