{
  "type": "Feature",
  "properties": {
    "gn:admin1_code":"7.0",
    "gn:admin2_code":"99173.0",
    "gn:asciiname":"'Awwad Fayyad",
    "gn:country_code":"IQ",
    "gn:dem":38,
    "gn:feature_class":"P",
    "gn:feature_code":"PPL",
    "gn:name":"\u2018Aww\u0101d Fayy\u0101\u1e11",
    "gn:population":0,
    "gn:timezone":"Asia/Baghdad",
    "iso:country":"IQ",
    "name:ara_x_preferred":[
        "\u0639\u0648\u0627\u062f \u0641\u064a\u0627\u0636"
    ],
    "name:und_x_variant":[
        "\u2018Aww\u0101d Fayy\u0101\u1e11"
    ],
    "wof:name":"'Awwad Fayyad",
    "wof:placetype":"locality"
},
  "geometry": {"coordinates":[44.17538,33.56974],"type":"Point"}
}