{
  "type": "Feature",
  "properties": {
    "gn:admin1_code":"5.0",
    "gn:admin2_code":"96204.0",
    "gn:asciiname":"Shayshikal Haji 'Isa",
    "gn:country_code":"IQ",
    "gn:dem":535,
    "gn:feature_class":"P",
    "gn:feature_code":"PPL",
    "gn:name":"Shayshikal \u1e28\u0101j\u012b \u2018\u012as\u00e1",
    "gn:population":0,
    "gn:timezone":"Asia/Baghdad",
    "iso:country":"IQ",
    "name:ara_x_preferred":[
        "\u0634\u064a\u0634\u0643\u0644 \u062d\u0627\u062c\u064a \u0639\u064a\u0633\u0649"
    ],
    "name:fas_x_preferred":[
        "\u0634\u0634\u06a9 \u062d\u0627\u062c\u06cc \u0639\u06cc\u0633\u06cc"
    ],
    "name:fas_x_variant":[
        "Shashek-e \u1e28\u0101jj\u012b \u2018\u012as\u00e1"
    ],
    "name:kur_x_preferred":[
        "Shashk\u00ee Ser\u00fb"
    ],
    "name:kur_x_variant":[
        "Sh\u00eashk\u00ee",
        "\u0634\u0627\u0634\u0643\u0649 \u0633\u06d5\u0631\u0648\u0648",
        "\u0634\u06ce\u0634\u0643\u0649"
    ],
    "name:und_x_variant":[
        "Sheshikal H\u0101ji \u2018\u012asa",
        "Sheshikal \u1e28\u0101jj\u012b \u2018\u012as\u00e1",
        "Shayshikal \u1e28\u0101j\u012b \u2018\u012as\u00e1",
        "Sheshky"
    ],
    "wof:name":"Shayshikal Haji 'Isa",
    "wof:placetype":"locality"
},
  "geometry": {"coordinates":[45.97441,35.26637],"type":"Point"}
}