{
  "type": "Feature",
  "properties": {
    "gn:admin1_code":"15.0",
    "gn:admin2_code":"9166649.0",
    "gn:asciiname":"Damarji al Kubra",
    "gn:country_code":"IQ",
    "gn:dem":284,
    "gn:feature_class":"P",
    "gn:feature_code":"PPL",
    "gn:name":"D\u0101marj\u012b al Kubr\u00e1",
    "gn:population":0,
    "gn:timezone":"Asia/Baghdad",
    "iso:country":"IQ",
    "name:ara_x_preferred":[
        "\u062f\u0627\u0645\u0631\u062c\u064a \u0627\u0644\u0643\u0628\u0631\u0649"
    ],
    "name:und_x_variant":[
        "D\u0101marj\u012b al Kubr\u00e1"
    ],
    "wof:name":"Damarji al Kubra",
    "wof:placetype":"locality"
},
  "geometry": {"coordinates":[42.98055,36.36742],"type":"Point"}
}