{
  "type": "Feature",
  "properties": {
    "gn:admin1_code":"10.0",
    "gn:admin2_code":"9166680.0",
    "gn:asciiname":"Abtirah",
    "gn:country_code":"IQ",
    "gn:dem":39,
    "gn:feature_class":"P",
    "gn:feature_code":"PPL",
    "gn:name":"Abt\u012brah",
    "gn:population":0,
    "gn:timezone":"Asia/Baghdad",
    "iso:country":"IQ",
    "name:ara_x_preferred":[
        "\u0627\u0628\u062a\u064a\u0631\u0629"
    ],
    "name:und_x_variant":[
        "Abt\u012brah"
    ],
    "wof:name":"Abtirah",
    "wof:placetype":"locality"
},
  "geometry": {"coordinates":[45.06774,33.68437],"type":"Point"}
}