{
  "type": "Feature",
  "properties": {
    "gn:admin1_code":"18.0",
    "gn:admin2_code":"90148.0",
    "gn:asciiname":"Rajib Mahmud Fad'im",
    "gn:country_code":"IQ",
    "gn:dem":126,
    "gn:feature_class":"P",
    "gn:feature_code":"PPL",
    "gn:name":"Rajib Ma\u1e29m\u016bd Fad\u2018im",
    "gn:population":0,
    "gn:timezone":"Asia/Baghdad",
    "iso:country":"IQ",
    "name:ara_x_preferred":[
        "\u0631\u062c\u0628 \u0645\u062d\u0645\u0648\u062f \u0641\u062f\u0639\u0645"
    ],
    "name:und_x_variant":[
        "Rajib Ma\u1e29m\u016bd Fad\u2018im"
    ],
    "wof:name":"Rajib Mahmud Fad'im",
    "wof:placetype":"locality"
},
  "geometry": {"coordinates":[43.71167,34.83421],"type":"Point"}
}