{
  "type": "Feature",
  "properties": {
    "gn:admin1_code":"10.0",
    "gn:admin2_code":"94590.0",
    "gn:asciiname":"Shaykh 'Abbas",
    "gn:country_code":"IQ",
    "gn:dem":144,
    "gn:feature_class":"P",
    "gn:feature_code":"PPL",
    "gn:name":"Shaykh \u2018Abb\u0101s",
    "gn:population":0,
    "gn:timezone":"Asia/Baghdad",
    "iso:country":"IQ",
    "name:ara_x_preferred":[
        "\u0634\u064a\u062e \u0639\u0628\u0627\u0633"
    ],
    "name:fas_x_preferred":[
        "Sheykh \u2018Abb\u0101s"
    ],
    "name:und_x_variant":[
        "Shaikh \u2018Abbas",
        "Ash Shaykh \u2018Abb\u0101s",
        "Shaykh \u2018Abb\u0101s"
    ],
    "wof:name":"Shaykh 'Abbas",
    "wof:placetype":"locality"
},
  "geometry": {"coordinates":[45.23577,34.35899000000001],"type":"Point"}
}