{
  "type": "Feature",
  "properties": {
    "gn:admin1_code":"7.0",
    "gn:admin2_code":"9166569.0",
    "gn:asciiname":"Nawwaf Fayyad",
    "gn:country_code":"IQ",
    "gn:dem":38,
    "gn:feature_class":"P",
    "gn:feature_code":"PPL",
    "gn:name":"Naww\u0101f Fayy\u0101\u1e11",
    "gn:population":0,
    "gn:timezone":"Asia/Baghdad",
    "iso:country":"IQ",
    "name:ara_x_preferred":[
        "\u0646\u0648\u0627\u0641 \u0641\u064a\u0627\u0636"
    ],
    "name:und_x_variant":[
        "Naww\u0101f Fayy\u0101\u1e11"
    ],
    "wof:name":"Nawwaf Fayyad",
    "wof:placetype":"locality"
},
  "geometry": {"coordinates":[44.20759,33.60644],"type":"Point"}
}