{
  "type": "Feature",
  "properties": {
    "gn:admin1_code":"4.0",
    "gn:admin2_code":"98634.0",
    "gn:asciiname":"At Tasfiyah",
    "gn:country_code":"IQ",
    "gn:dem":25,
    "gn:feature_class":"P",
    "gn:feature_code":"PPL",
    "gn:name":"At Ta\u015ff\u012byah",
    "gn:population":0,
    "gn:timezone":"Asia/Baghdad",
    "iso:country":"IQ",
    "name:ara_x_preferred":[
        "\u0627\u0644\u062a\u0635\u0641\u064a\u0629"
    ],
    "name:und_x_variant":[
        "At Ta\u015ff\u012byah"
    ],
    "wof:name":"At Tasfiyah",
    "wof:placetype":"locality"
},
  "geometry": {"coordinates":[44.59551,31.94513],"type":"Point"}
}