{
  "type": "Feature",
  "properties": {
    "gn:admin1_code":"10.0",
    "gn:admin2_code":"94590.0",
    "gn:asciiname":"Ja`far al Jum`ah",
    "gn:country_code":"IQ",
    "gn:dem":77,
    "gn:feature_class":"P",
    "gn:feature_code":"PPL",
    "gn:name":"Ja\u2018far al Jum\u2018ah",
    "gn:population":0,
    "gn:timezone":"Asia/Baghdad",
    "iso:country":"IQ",
    "name:ara_x_preferred":[
        "\u062c\u0639\u0641\u0631 \u0627\u0644\u062c\u0645\u0639\u0629"
    ],
    "name:und_x_variant":[
        "Ja\u2018far al Jum\u2018ah"
    ],
    "wof:name":"Ja`far al Jum`ah",
    "wof:placetype":"locality"
},
  "geometry": {"coordinates":[44.99294,34.04662],"type":"Point"}
}