{
  "type": "Feature",
  "properties": {
    "gn:admin1_code":"18.0",
    "gn:admin2_code":"90148.0",
    "gn:asciiname":"Qaryat al U'aywij",
    "gn:country_code":"IQ",
    "gn:dem":120,
    "gn:feature_class":"P",
    "gn:feature_code":"PPL",
    "gn:name":"Qaryat al U\u2018aywij",
    "gn:population":0,
    "gn:timezone":"Asia/Baghdad",
    "iso:country":"IQ",
    "name:ara_x_preferred":[
        "\u0642\u0631\u064a\u0629 \u0627\u0644\u0627\u0639\u064a\u0648\u062c"
    ],
    "name:und_x_variant":[
        "Qaryat al A\u2018aywij",
        "Qaryat al U\u2018aywij",
        "Qaryat al A\u2018y\u016bj"
    ],
    "wof:name":"Qaryat al U'aywij",
    "wof:placetype":"locality"
},
  "geometry": {"coordinates":[43.60345,34.62155],"type":"Point"}
}