{
  "type": "Feature",
  "properties": {
    "gn:admin1_code":"6.0",
    "gn:admin2_code":"99358.0",
    "gn:asciiname":"Qaryat 'Abd as Sadah Sa'dun",
    "gn:country_code":"IQ",
    "gn:dem":28,
    "gn:feature_class":"P",
    "gn:feature_code":"PPL",
    "gn:name":"Qaryat \u2018Abd as S\u0101dah Sa\u2018d\u016bn",
    "gn:population":0,
    "gn:timezone":"Asia/Baghdad",
    "iso:country":"IQ",
    "name:ara_x_preferred":[
        "\u0642\u0631\u064a\u0629 \u0639\u0628\u062f \u0627\u0644\u0633\u0627\u062f\u0629 \u0633\u0639\u062f\u0648\u0646"
    ],
    "name:und_x_variant":[
        "Qaryat \u2018Abd as S\u0101dah Sa\u2018d\u016bn"
    ],
    "wof:name":"Qaryat 'Abd as Sadah Sa'dun",
    "wof:placetype":"locality"
},
  "geometry": {"coordinates":[44.61808,32.46139],"type":"Point"}
}