{
  "type": "Feature",
  "properties": {
    "gn:admin1_code":"11.0",
    "gn:admin2_code":"93817.0",
    "gn:asciiname":"Tekale",
    "gn:country_code":"IQ",
    "gn:dem":354,
    "gn:feature_class":"P",
    "gn:feature_code":"PPL",
    "gn:name":"T\u00eaka\u0142e",
    "gn:population":0,
    "gn:timezone":"Asia/Baghdad",
    "iso:country":"IQ",
    "name:ara_x_preferred":[
        "\u062a\u064a\u0643\u0627\u0644\u0629"
    ],
    "name:ara_x_variant":[
        "\u062a\u064a\u0643\u0627\u0644\u0648 \u062e\u0631\u0627\u0626\u0628"
    ],
    "name:kur_x_preferred":[
        "T\u00eaka\u0142e"
    ],
    "name:kur_x_variant":[
        "Tikala",
        "\u062a\u06ce \u0643\u0627\u06b5\u06d5"
    ],
    "name:und_x_variant":[
        "Tik\u0101la",
        "Tik\u0101lah",
        "Tayk\u0101l\u016b Khar\u0101\u2019ib",
        "Tayk\u0101lah"
    ],
    "wof:name":"Tekale",
    "wof:placetype":"locality"
},
  "geometry": {"coordinates":[43.86344,35.84763],"type":"Point"}
}