{
  "type": "Feature",
  "properties": {
    "gn:admin1_code":"11.0",
    "gn:admin2_code":"93817.0",
    "gn:asciiname":"Kirdah Jall",
    "gn:country_code":"IQ",
    "gn:dem":207,
    "gn:feature_class":"P",
    "gn:feature_code":"PPL",
    "gn:name":"Kirdah Jall",
    "gn:population":0,
    "gn:timezone":"Asia/Baghdad",
    "iso:country":"IQ",
    "name:ara_x_preferred":[
        "\u0643\u0631\u062f\u0629 \u062c\u0644"
    ],
    "name:kur_x_preferred":[
        "Girde Cha\u0142"
    ],
    "name:kur_x_variant":[
        "Girda Chal",
        "\u06af\u0631\u062f\u06d5 \u0686\u0627\u06b5"
    ],
    "name:und_x_variant":[
        "Kirdah J\u016bl",
        "Kirdah Ch\u0101l",
        "Kirdah Jall",
        "Girda Chal"
    ],
    "wof:name":"Kirdah Jall",
    "wof:placetype":"locality"
},
  "geometry": {"coordinates":[43.61794,35.59393],"type":"Point"}
}