{
  "type": "Feature",
  "properties": {
    "gn:admin1_code":"7.0",
    "gn:admin2_code":"99173.0",
    "gn:asciiname":"Mahmud 'Abd Allah",
    "gn:country_code":"IQ",
    "gn:dem":35,
    "gn:feature_class":"P",
    "gn:feature_code":"PPL",
    "gn:name":"Ma\u1e29m\u016bd \u2018Abd All\u0101h",
    "gn:population":0,
    "gn:timezone":"Asia/Baghdad",
    "iso:country":"IQ",
    "name:ara_x_preferred":[
        "\u0645\u062d\u0645\u0648\u062f \u0639\u0628\u062f \ufdf2"
    ],
    "name:und_x_variant":[
        "Ma\u1e29m\u016bd \u2018Abd All\u0101h"
    ],
    "wof:name":"Mahmud 'Abd Allah",
    "wof:placetype":"locality"
},
  "geometry": {"coordinates":[44.16774,33.51152],"type":"Point"}
}