{
  "type": "Feature",
  "properties": {
    "gn:admin1_code":"11.0",
    "gn:admin2_code":"95444.0",
    "gn:asciiname":"Ghulan",
    "gn:country_code":"IQ",
    "gn:dem":293,
    "gn:feature_class":"P",
    "gn:feature_code":"PPL",
    "gn:name":"Gh\u016bl\u0101n",
    "gn:population":0,
    "gn:timezone":"Asia/Baghdad",
    "iso:country":"IQ",
    "name:ara_x_preferred":[
        "\u063a\u0648\u0644\u0627\u0646"
    ],
    "name:und_x_variant":[
        "Gh\u016bl\u0101n"
    ],
    "wof:name":"Ghulan",
    "wof:placetype":"locality"
},
  "geometry": {"coordinates":[43.75771,36.32065],"type":"Point"}
}