{
  "type": "Feature",
  "properties": {
    "gn:admin1_code":"15.0",
    "gn:admin2_code":"90392.0",
    "gn:asciiname":"Girjan",
    "gn:country_code":"IQ",
    "gn:dem":396,
    "gn:feature_class":"P",
    "gn:feature_code":"PPL",
    "gn:name":"Girj\u0101n",
    "gn:population":0,
    "gn:timezone":"Asia/Baghdad",
    "iso:country":"IQ",
    "name:ara_x_preferred":[
        "\u06af\u0631\u062c\u0627\u0646"
    ],
    "name:ara_x_variant":[
        "Girj\u0101n"
    ],
    "name:kur_x_preferred":[
        "Gircan"
    ],
    "name:und_x_variant":[
        "Girch\u0101l",
        "Grjaz"
    ],
    "wof:name":"Girjan",
    "wof:placetype":"locality"
},
  "geometry": {"coordinates":[42.52849000000001,36.7191],"type":"Point"}
}