{
  "type": "Feature",
  "properties": {
    "gn:admin1_code":"1.0",
    "gn:admin2_code":"98718.0",
    "gn:asciiname":"Albu Rishah",
    "gn:country_code":"IQ",
    "gn:dem":52,
    "gn:feature_class":"P",
    "gn:feature_code":"PPL",
    "gn:name":"\u0100lb\u016b R\u012bshah",
    "gn:population":0,
    "gn:timezone":"Asia/Baghdad",
    "iso:country":"IQ",
    "name:ara_x_preferred":[
        "\u0627\u0644\u0628\u0648 \u0631\u064a\u0634\u0629"
    ],
    "name:und_x_variant":[
        "Ab\u016b Rishah",
        "\u0100lb\u016b R\u012bshah"
    ],
    "wof:name":"Albu Rishah",
    "wof:placetype":"locality"
},
  "geometry": {"coordinates":[43.23104,33.46746],"type":"Point"}
}