{
  "type": "Feature",
  "properties": {
    "gn:admin1_code":"15.0",
    "gn:admin2_code":"9166608.0",
    "gn:asciiname":"Um'ayzilat ash Sharqiyah",
    "gn:country_code":"IQ",
    "gn:dem":284,
    "gn:feature_class":"P",
    "gn:feature_code":"PPL",
    "gn:name":"Um\u2018ayz\u012blat ash Sharq\u012byah",
    "gn:population":0,
    "gn:timezone":"Asia/Baghdad",
    "iso:country":"IQ",
    "name:ara_x_preferred":[
        "\u0627\u0645\u0639\u064a\u0632\u064a\u0644\u0629 \u0627\u0644\u0634\u0631\u0642\u064a\u0629"
    ],
    "name:und_x_variant":[
        "Majr\u016bd",
        "\u0645\u062c\u0631\u0648\u062f",
        "Um\u2018ayz\u012blat ash Sharq\u012byah"
    ],
    "wof:name":"Um'ayzilat ash Sharqiyah",
    "wof:placetype":"locality"
},
  "geometry": {"coordinates":[41.61967,35.91775999999999],"type":"Point"}
}