{
  "type": "Feature",
  "properties": {
    "gn:admin1_code":"6.0",
    "gn:admin2_code":"99358.0",
    "gn:asciiname":"Qaryat Albu Haradah",
    "gn:country_code":"IQ",
    "gn:dem":24,
    "gn:feature_class":"P",
    "gn:feature_code":"PPL",
    "gn:name":"Qaryat \u0100lb\u016b Haradah",
    "gn:population":0,
    "gn:timezone":"Asia/Baghdad",
    "iso:country":"IQ",
    "name:ara_x_preferred":[
        "\u0642\u0631\u064a\u0629 \u0627\u0644\u0628\u0648 \u0647\u0631\u062f\u0629"
    ],
    "name:und_x_variant":[
        "Qaryat \u0100lb\u016b Haradah"
    ],
    "wof:name":"Qaryat Albu Haradah",
    "wof:placetype":"locality"
},
  "geometry": {"coordinates":[44.6412,32.16257],"type":"Point"}
}