{
  "type": "Feature",
  "properties": {
    "gn:admin1_code":"2.0",
    "gn:admin2_code":"9166563.0",
    "gn:asciiname":"Turabah",
    "gn:country_code":"IQ",
    "gn:dem":4,
    "gn:feature_class":"P",
    "gn:feature_code":"PPL",
    "gn:name":"Tur\u0101bah",
    "gn:population":0,
    "gn:timezone":"Asia/Baghdad",
    "iso:country":"IQ",
    "name:ara_x_preferred":[
        "\u062a\u0631\u0627\u0628\u0629"
    ],
    "name:und_x_variant":[
        "Tarabah",
        "Tirubah",
        "Taraba",
        "Turaba",
        "Turabeh",
        "Turbah",
        "Tur\u0101bah"
    ],
    "wof:name":"Turabah",
    "wof:placetype":"locality"
},
  "geometry": {"coordinates":[47.27862,31.00234],"type":"Point"}
}