{
  "type": "Feature",
  "properties": {
    "gn:admin1_code":"8.0",
    "gn:admin2_code":"99612.0",
    "gn:asciiname":"Guheriz",
    "gn:country_code":"IQ",
    "gn:dem":773,
    "gn:feature_class":"P",
    "gn:feature_code":"PPL",
    "gn:name":"Guheriz",
    "gn:population":0,
    "gn:timezone":"Asia/Baghdad",
    "iso:country":"IQ",
    "name:ara_x_preferred":[
        "\u062c\u0648\u0647\u0631\u0632"
    ],
    "name:kur_x_preferred":[
        "Goherz\u00ea"
    ],
    "name:kur_x_variant":[
        "\u06af\u06c6\u06be\u06d5\u0631\u0632\u06ce",
        "Guheriz",
        "\u06af\u0648\u06be\u06d5\u0631\u0632"
    ],
    "name:und_x_variant":[
        "Guh\u0113rz",
        "Joharze",
        "J\u016bhariz",
        "Guharz",
        "Gunde Guherz",
        "Goharz"
    ],
    "wof:name":"Guheriz",
    "wof:placetype":"locality"
},
  "geometry": {"coordinates":[43.6055,37.07317000000001],"type":"Point"}
}