{
  "type": "Feature",
  "properties": {
    "gn:admin1_code":"7.0",
    "gn:admin2_code":"99101.0",
    "gn:asciiname":"'Arab 'Abd Allah al Hadid",
    "gn:country_code":"IQ",
    "gn:dem":28,
    "gn:feature_class":"P",
    "gn:feature_code":"PPL",
    "gn:name":"\u2018Arab \u2018Abd All\u0101h al \u1e28ad\u012bd",
    "gn:population":0,
    "gn:timezone":"Asia/Baghdad",
    "iso:country":"IQ",
    "name:ara_x_preferred":[
        "\u0639\u0631\u0628 \u0639\u0628\u062f \u0627\u0644\u0644\u0647 \u0627\u0644\u062d\u062f\u064a\u062f"
    ],
    "name:und_x_variant":[
        "\u2018Arab \u2018Abd All\u0101h al \u1e28ad\u012bd"
    ],
    "wof:name":"'Arab 'Abd Allah al Hadid",
    "wof:placetype":"locality"
},
  "geometry": {"coordinates":[44.56156,32.84847],"type":"Point"}
}