{
  "type": "Feature",
  "properties": {
    "gn:admin1_code":"10.0",
    "gn:admin2_code":"99063.0",
    "gn:asciiname":"Rahim Husayn",
    "gn:country_code":"IQ",
    "gn:dem":54,
    "gn:feature_class":"P",
    "gn:feature_code":"PPL",
    "gn:name":"Ra\u1e29\u012bm \u1e28usayn",
    "gn:population":0,
    "gn:timezone":"Asia/Baghdad",
    "iso:country":"IQ",
    "name:ara_x_preferred":[
        "\u0631\u062d\u064a\u0645 \u062d\u0633\u064a\u0646"
    ],
    "name:und_x_variant":[
        "Ra\u1e29\u012bm \u1e28usayn"
    ],
    "wof:name":"Rahim Husayn",
    "wof:placetype":"locality"
},
  "geometry": {"coordinates":[44.76578,33.91193],"type":"Point"}
}