{
  "type": "Feature",
  "properties": {
    "gn:admin1_code":"15.0",
    "gn:admin2_code":"98820.0",
    "gn:asciiname":"Baykhmah",
    "gn:country_code":"IQ",
    "gn:dem":417,
    "gn:feature_class":"P",
    "gn:feature_code":"PPL",
    "gn:name":"Baykhmah",
    "gn:population":0,
    "gn:timezone":"Asia/Baghdad",
    "iso:country":"IQ",
    "name:ara_x_preferred":[
        "\u0628\u064a\u062e\u0645\u0647"
    ],
    "name:kur_x_preferred":[
        "Bexme"
    ],
    "name:kur_x_variant":[
        "B\u00eaxm\u00ea",
        "\u0628\u06ce\u062e\u0645\u0647",
        "\u0628\u06d5\u062e\u0645\u0647",
        "\u0628\u06ce\u062e\u0645\u06ce",
        "B\u00eaxme"
    ],
    "name:und_x_variant":[
        "Bakhma",
        "B\u0113kma",
        "Baykhmah",
        "\u0628\u064a\u062e\u0645\u0647",
        "Qaryat Bakhmah",
        "\u0642\u0631\u064a\u0629 \u0628\u062e\u0645\u0647",
        "Bekhme"
    ],
    "wof:name":"Baykhmah",
    "wof:placetype":"locality"
},
  "geometry": {"coordinates":[44.22481,36.66286],"type":"Point"}
}