{
  "type": "Feature",
  "properties": {
    "gn:admin1_code":"8.0",
    "gn:admin2_code":"97269.0",
    "gn:asciiname":"Shawrik",
    "gn:country_code":"IQ",
    "gn:dem":684,
    "gn:feature_class":"P",
    "gn:feature_code":"PPL",
    "gn:name":"Sh\u0101wr\u012bk",
    "gn:population":0,
    "gn:timezone":"Asia/Baghdad",
    "iso:country":"IQ",
    "name:ara_x_preferred":[
        "Sh\u0101wr\u012bk"
    ],
    "name:kur_x_preferred":[
        "Shawr\u00eek"
    ],
    "name:kur_x_variant":[
        "\u0634\u0627\u0648\u0631\u064a\u0643"
    ],
    "wof:name":"Shawrik",
    "wof:placetype":"locality"
},
  "geometry": {"coordinates":[42.98771,37.00687],"type":"Point"}
}