{
  "type": "Feature",
  "properties": {
    "gn:admin1_code":"10.0",
    "gn:admin2_code":"9166680.0",
    "gn:asciiname":"'Abbas al Mardi",
    "gn:country_code":"IQ",
    "gn:dem":45,
    "gn:feature_class":"P",
    "gn:feature_code":"PPL",
    "gn:name":"\u2018Abb\u0101s al Mard\u012b",
    "gn:population":0,
    "gn:timezone":"Asia/Baghdad",
    "iso:country":"IQ",
    "name:und_x_variant":[
        "\u2018Abb\u0101s al Mard\u012b"
    ],
    "wof:name":"'Abbas al Mardi",
    "wof:placetype":"locality"
},
  "geometry": {"coordinates":[44.98333,33.75],"type":"Point"}
}