{
  "type": "Feature",
  "properties": {
    "gn:admin1_code":"10.0",
    "gn:admin2_code":"99063.0",
    "gn:asciiname":"'Arab Hassun",
    "gn:country_code":"IQ",
    "gn:dem":45,
    "gn:feature_class":"P",
    "gn:feature_code":"PPL",
    "gn:name":"\u2018Arab \u1e28ass\u016bn",
    "gn:population":0,
    "gn:timezone":"Asia/Baghdad",
    "iso:country":"IQ",
    "name:ara_x_preferred":[
        "\u0639\u0631\u0628 \u062d\u0633\u0648\u0646"
    ],
    "name:und_x_variant":[
        "\u2018Arab \u1e28ass\u016bn \u2018Alw\u0101n",
        "\u0639\u0631\u0628 \u062d\u0633\u0648\u0646 \u0639\u0644\u0648\u0627\u0646",
        "\u2018Arab \u1e28ass\u016bn"
    ],
    "wof:name":"'Arab Hassun",
    "wof:placetype":"locality"
},
  "geometry": {"coordinates":[44.57766,33.72907],"type":"Point"}
}