{
  "type": "Feature",
  "properties": {
    "gn:admin1_code":"9.0",
    "gn:admin2_code":"98855.0",
    "gn:asciiname":"Sayyid Dakhil",
    "gn:cc2":"IQ",
    "gn:country_code":"IQ",
    "gn:dem":8,
    "gn:feature_class":"P",
    "gn:feature_code":"PPL",
    "gn:name":"Sayyid Dakh\u012bl",
    "gn:population":0,
    "gn:timezone":"Asia/Baghdad",
    "iso:country":"IQ",
    "name:und_x_variant":[
        "Im\u0101m Sayyid Dakh\u012bl",
        "Im\u0101m Saiyid Dakh\u012bl",
        "Sayyid Dakh\u012bl"
    ],
    "wof:name":"Sayyid Dakhil",
    "wof:placetype":"locality"
},
  "geometry": {"coordinates":[46.43417,31.13167],"type":"Point"}
}