{
  "type": "Feature",
  "properties": {
    "gn:admin1_code":"16.0",
    "gn:admin2_code":"98197.0",
    "gn:asciiname":"Imam Shayikh Salman",
    "gn:country_code":"IQ",
    "gn:dem":36,
    "gn:feature_class":"P",
    "gn:feature_code":"PPL",
    "gn:name":"Im\u0101m Sh\u0101yikh Salm\u0101n",
    "gn:population":0,
    "gn:timezone":"Asia/Baghdad",
    "iso:country":"IQ",
    "name:und_x_variant":[
        "Im\u0101m Sh\u0101\u012bkh Salm\u0101n",
        "Im\u0101m Sh\u0101yikh Salm\u0101n",
        "Im\u0101m Shaykh Salm\u0101n"
    ],
    "wof:name":"Imam Shayikh Salman",
    "wof:placetype":"locality"
},
  "geometry": {"coordinates":[45.80643,33.0015],"type":"Point"}
}