{
  "type": "Feature",
  "properties": {
    "gn:admin1_code":"9.0",
    "gn:admin2_code":"98855.0",
    "gn:asciiname":"Albu Kuraydi",
    "gn:country_code":"IQ",
    "gn:dem":5,
    "gn:feature_class":"P",
    "gn:feature_code":"PPL",
    "gn:name":"\u0100lb\u016b Kurayd\u012b",
    "gn:population":0,
    "gn:timezone":"Asia/Baghdad",
    "iso:country":"IQ",
    "name:ara_x_preferred":[
        "\u0627\u0644\u0628\u0648 \u0643\u0631\u064a\u062f\u064a"
    ],
    "name:und_x_variant":[
        "\u0100lb\u016b Kar\u0101d\u012b",
        "Alb\u016b Kurayd\u012b",
        "\u0100lb\u016b Kurayd\u012b"
    ],
    "wof:name":"Albu Kuraydi",
    "wof:placetype":"locality"
},
  "geometry": {"coordinates":[46.33846,31.07777],"type":"Point"}
}