{
  "type": "Feature",
  "properties": {
    "gn:admin1_code":"5.0",
    "gn:admin2_code":"92051.0",
    "gn:asciiname":"Sartike",
    "gn:country_code":"IQ",
    "gn:dem":856,
    "gn:feature_class":"P",
    "gn:feature_code":"PPL",
    "gn:name":"Sartike",
    "gn:population":0,
    "gn:timezone":"Asia/Baghdad",
    "iso:country":"IQ",
    "name:kur_x_preferred":[
        "Sartike"
    ],
    "name:kur_x_variant":[
        "\u0633\u0627\u0631\u062a\u0643\u06d5"
    ],
    "name:und_x_variant":[
        "Sartka"
    ],
    "wof:name":"Sartike",
    "wof:placetype":"locality"
},
  "geometry": {"coordinates":[44.75708,36.36942],"type":"Point"}
}