{
  "type": "Feature",
  "properties": {
    "gn:admin1_code":"18.0",
    "gn:admin2_code":"91594.0",
    "gn:asciiname":"'Arab Muhammad 'Ali Salim",
    "gn:country_code":"IQ",
    "gn:dem":79,
    "gn:feature_class":"P",
    "gn:feature_code":"PPL",
    "gn:name":"\u2018Arab Mu\u1e29ammad \u2018Al\u012b Sal\u012bm",
    "gn:population":0,
    "gn:timezone":"Asia/Baghdad",
    "iso:country":"IQ",
    "name:ara_x_preferred":[
        "\u0639\u0631\u0628 \u0645\u062d\u0645\u062f \u0639\u0644\u064a \u0633\u0644\u064a\u0645"
    ],
    "name:und_x_variant":[
        "\u2018Arab Mu\u1e29ammad \u2018Al\u012b Sal\u012bm"
    ],
    "wof:name":"'Arab Muhammad 'Ali Salim",
    "wof:placetype":"locality"
},
  "geometry": {"coordinates":[43.76853,34.20614],"type":"Point"}
}