{
  "type": "Feature",
  "properties": {
    "gn:admin1_code":"11.0",
    "gn:admin2_code":"9166534.0",
    "gn:asciiname":"Biziyan",
    "gn:country_code":"IQ",
    "gn:dem":1083,
    "gn:feature_class":"P",
    "gn:feature_code":"PPL",
    "gn:name":"B\u012bziy\u0101n",
    "gn:population":0,
    "gn:timezone":"Asia/Baghdad",
    "iso:country":"IQ",
    "name:ara_x_preferred":[
        "\u0628\u064a\u0632\u064a\u0627\u0646"
    ],
    "name:kur_x_preferred":[
        "B\u00ea Ziyan"
    ],
    "name:kur_x_variant":[
        "\u0628\u06ce \u0632\u064a\u0627\u0646",
        "B\u00eajiyan",
        "\u0628\u06ce\u0698\u064a\u0627\u0646"
    ],
    "name:und_x_variant":[
        "B\u012bzhiy\u0101n",
        "Bizian",
        "Bayziy\u0101n"
    ],
    "wof:name":"Biziyan",
    "wof:placetype":"locality"
},
  "geometry": {"coordinates":[44.09019,37.12277],"type":"Point"}
}