{
  "type": "Feature",
  "properties": {
    "gn:admin1_code":"10.0",
    "gn:admin2_code":"99170.0",
    "gn:asciiname":"Khan al Firfah",
    "gn:country_code":"IQ",
    "gn:dem":65,
    "gn:feature_class":"P",
    "gn:feature_code":"PPL",
    "gn:name":"Kh\u0101n al Firfah",
    "gn:population":0,
    "gn:timezone":"Asia/Baghdad",
    "iso:country":"IQ",
    "name:ara_x_preferred":[
        "\u062e\u0627\u0646 \u0627\u0644\u0641\u0631\u0641\u0629"
    ],
    "name:und_x_variant":[
        "Kh\u0101n al Firfah"
    ],
    "wof:name":"Khan al Firfah",
    "wof:placetype":"locality"
},
  "geometry": {"coordinates":[44.59857,34.1224],"type":"Point"}
}