{
  "type": "Feature",
  "properties": {
    "gn:admin1_code":"5.0",
    "gn:admin2_code":"91176.0",
    "gn:asciiname":"Mkil",
    "gn:country_code":"IQ",
    "gn:dem":1091,
    "gn:feature_class":"P",
    "gn:feature_code":"PPL",
    "gn:name":"Mkil",
    "gn:population":0,
    "gn:timezone":"Asia/Baghdad",
    "iso:country":"IQ",
    "name:ara_x_preferred":[
        "\u0645\u0643\u0644"
    ],
    "name:kur_x_preferred":[
        "Mk\u0142"
    ],
    "name:kur_x_variant":[
        "\u0645\u0643\u06b5"
    ],
    "wof:name":"Mkil",
    "wof:placetype":"locality"
},
  "geometry": {"coordinates":[45.76715,35.6299],"type":"Point"}
}