{
  "type": "Feature",
  "properties": {
    "gn:admin1_code":"6.0",
    "gn:admin2_code":"99358.0",
    "gn:asciiname":"Hamzat al 'Abbud",
    "gn:country_code":"IQ",
    "gn:dem":23,
    "gn:feature_class":"P",
    "gn:feature_code":"PPL",
    "gn:name":"\u1e28amzat al \u2018Abb\u016bd",
    "gn:population":0,
    "gn:timezone":"Asia/Baghdad",
    "iso:country":"IQ",
    "name:ara_x_preferred":[
        "\u062d\u0645\u0632\u0629 \u0627\u0644\u0639\u0628\u0648\u062f"
    ],
    "name:und_x_variant":[
        "\u1e28amzat al \u2018Abb\u016bd"
    ],
    "wof:name":"Hamzat al 'Abbud",
    "wof:placetype":"locality"
},
  "geometry": {"coordinates":[44.56848,32.23035],"type":"Point"}
}