{
  "type": "Feature",
  "properties": {
    "gn:admin1_code":"14.0",
    "gn:admin2_code":"99610.0",
    "gn:asciiname":"Salaf al Mashtal",
    "gn:country_code":"IQ",
    "gn:dem":9,
    "gn:feature_class":"P",
    "gn:feature_code":"PPL",
    "gn:name":"Salaf al Mashtal",
    "gn:population":0,
    "gn:timezone":"Asia/Baghdad",
    "iso:country":"IQ",
    "name:ara_x_preferred":[
        "\u0633\u0644\u0641 \u0627\u0644\u0645\u0634\u062a\u0644"
    ],
    "wof:name":"Salaf al Mashtal",
    "wof:placetype":"locality"
},
  "geometry": {"coordinates":[47.19283,31.78726],"type":"Point"}
}