{
  "type": "Feature",
  "properties": {
    "gn:admin1_code":"10.0",
    "gn:admin2_code":"94590.0",
    "gn:asciiname":"As Sa'diyah",
    "gn:country_code":"IQ",
    "gn:dem":105,
    "gn:feature_class":"P",
    "gn:feature_code":"PPL",
    "gn:name":"As Sa\u2018d\u012byah",
    "gn:population":0,
    "gn:timezone":"Asia/Baghdad",
    "iso:country":"IQ",
    "name:ara_x_preferred":[
        "\u0627\u0644\u0633\u0639\u062f\u064a\u0629"
    ],
    "name:und_x_variant":[
        "Qizil Ribat",
        "As Sa\u2018d\u012bya",
        "Sa\u2018diyah",
        "Sa\u2018diye",
        "Sa\u2018diyeh",
        "Qizil Robat",
        "Al-Saadiyh",
        "As Sa\u2018d\u012byah"
    ],
    "wof:name":"As Sa'diyah",
    "wof:placetype":"locality"
},
  "geometry": {"coordinates":[45.11746,34.18749],"type":"Point"}
}