{
  "type": "Feature",
  "properties": {
    "gn:admin1_code":"6.0",
    "gn:admin2_code":"99040.0",
    "gn:asciiname":"'Abbas Hasan",
    "gn:country_code":"IQ",
    "gn:dem":31,
    "gn:feature_class":"P",
    "gn:feature_code":"PPL",
    "gn:name":"\u2018Abb\u0101s \u1e28asan",
    "gn:population":0,
    "gn:timezone":"Asia/Baghdad",
    "iso:country":"IQ",
    "name:ara_x_preferred":[
        "\u0639\u0628\u0627\u0633 \u062d\u0633\u0646"
    ],
    "name:und_x_variant":[
        "\u2018Abb\u0101s \u1e28asan"
    ],
    "wof:name":"'Abbas Hasan",
    "wof:placetype":"locality"
},
  "geometry": {"coordinates":[44.23842,32.56179],"type":"Point"}
}