{
  "type": "Feature",
  "properties": {
    "gn:admin1_code":"11.0",
    "gn:admin2_code":"93817.0",
    "gn:asciiname":"Dusere",
    "gn:country_code":"IQ",
    "gn:dem":221,
    "gn:feature_class":"P",
    "gn:feature_code":"PPL",
    "gn:name":"Dusere",
    "gn:population":0,
    "gn:timezone":"Asia/Baghdad",
    "iso:country":"IQ",
    "name:ara_x_preferred":[
        "\u062f\u0648\u0633\u0631\u0629 \u0627\u0644\u0633\u0641\u0644\u0649"
    ],
    "name:kur_x_preferred":[
        "Dwsara"
    ],
    "name:kur_x_variant":[
        "Dusere",
        "\u062f\u0648\u0633\u06d5\u0631\u06d5"
    ],
    "name:und_x_variant":[
        "D\u016bsrah as Sufl\u00e1"
    ],
    "wof:name":"Dusere",
    "wof:placetype":"locality"
},
  "geometry": {"coordinates":[43.73032,35.56847],"type":"Point"}
}