{
  "type": "Feature",
  "properties": {
    "gn:admin1_code":"1.0",
    "gn:admin2_code":"98718.0",
    "gn:asciiname":"Hajj 'Awdah",
    "gn:country_code":"IQ",
    "gn:dem":48,
    "gn:feature_class":"P",
    "gn:feature_code":"PPLL",
    "gn:name":"\u1e28\u0101jj \u2018Awdah",
    "gn:population":0,
    "gn:timezone":"Asia/Baghdad",
    "iso:country":"IQ",
    "name:ara_x_preferred":[
        "\u062d\u0627\u062c \u0639\u0648\u062f\u0629"
    ],
    "name:und_x_variant":[
        "Bayt \u1e28\u0101jj \u2018Awdah",
        "\u0628\u064a\u062a \u062d\u0627\u062c \u0639\u0648\u062f\u0629",
        "\u1e28\u0101jj \u2018Awdah"
    ],
    "wof:name":"Hajj 'Awdah",
    "wof:placetype":"locality"
},
  "geometry": {"coordinates":[43.39965,33.25628],"type":"Point"}
}