{
  "type": "Feature",
  "properties": {
    "gn:admin1_code":"15.0",
    "gn:admin2_code":"9166620.0",
    "gn:asciiname":"Kurkurkan",
    "gn:country_code":"IQ",
    "gn:dem":468,
    "gn:feature_class":"P",
    "gn:feature_code":"PPL",
    "gn:name":"K\u016brk\u016brk\u0101n",
    "gn:population":0,
    "gn:timezone":"Asia/Baghdad",
    "iso:country":"IQ",
    "name:ara_x_preferred":[
        "\u0643\u0648\u0631\u0643\u0648\u0631\u0643\u0627\u0646"
    ],
    "name:ara_x_variant":[
        "K\u016brk\u016brk\u0101n"
    ],
    "wof:name":"Kurkurkan",
    "wof:placetype":"locality"
},
  "geometry": {"coordinates":[41.81626,36.30143],"type":"Point"}
}