{
  "type": "Feature",
  "properties": {
    "gn:admin1_code":"18.0",
    "gn:admin2_code":"9166598.0",
    "gn:asciiname":"Shammakh",
    "gn:country_code":"IQ",
    "gn:dem":105,
    "gn:feature_class":"P",
    "gn:feature_code":"PPL",
    "gn:name":"Shamm\u0101kh",
    "gn:population":0,
    "gn:timezone":"Asia/Baghdad",
    "iso:country":"IQ",
    "name:ara_x_preferred":[
        "\u0634\u0645\u0627\u062e"
    ],
    "name:und_x_variant":[
        "Sh\u0101m\u0101kh",
        "Shamm\u0101kh"
    ],
    "wof:name":"Shammakh",
    "wof:placetype":"locality"
},
  "geometry": {"coordinates":[44.52954,34.60496],"type":"Point"}
}