{
  "type": "Feature",
  "properties": {
    "gn:admin1_code":"15.0",
    "gn:admin2_code":"9166649.0",
    "gn:asciiname":"Mayjarin",
    "gn:country_code":"IQ",
    "gn:dem":356,
    "gn:feature_class":"P",
    "gn:feature_code":"PPL",
    "gn:name":"Mayjar\u012bn",
    "gn:population":0,
    "gn:timezone":"Asia/Baghdad",
    "iso:country":"IQ",
    "name:ara_x_preferred":[
        "\u0645\u064a\u062c\u0631\u064a\u0646"
    ],
    "name:und_x_variant":[
        "Mayjar\u012bn"
    ],
    "wof:name":"Mayjarin",
    "wof:placetype":"locality"
},
  "geometry": {"coordinates":[42.71769000000001,36.3593],"type":"Point"}
}