{
  "type": "Feature",
  "properties": {
    "gn:admin1_code":"18.0",
    "gn:admin2_code":"6872046.0",
    "gn:asciiname":"'Arab Aswad al Muzhir",
    "gn:country_code":"IQ",
    "gn:dem":133,
    "gn:feature_class":"P",
    "gn:feature_code":"PPL",
    "gn:name":"\u2018Arab Aswad al Muzhir",
    "gn:population":0,
    "gn:timezone":"Asia/Baghdad",
    "iso:country":"IQ",
    "name:ara_x_preferred":[
        "\u0639\u0631\u0628 \u0627\u0633\u0648\u062f \u0627\u0644\u0645\u0632\u0647\u0631"
    ],
    "name:und_x_variant":[
        "\u2018Arab Aswad al Muzhir"
    ],
    "wof:name":"'Arab Aswad al Muzhir",
    "wof:placetype":"locality"
},
  "geometry": {"coordinates":[43.14032,35.05859],"type":"Point"}
}