{
  "type": "Feature",
  "properties": {
    "gn:admin1_code":"18.0",
    "gn:admin2_code":"9166616.0",
    "gn:asciiname":"Hamud Jasam",
    "gn:country_code":"IQ",
    "gn:dem":42,
    "gn:feature_class":"P",
    "gn:feature_code":"PPL",
    "gn:name":"\u1e28am\u016bd Jas\u0101m",
    "gn:population":0,
    "gn:timezone":"Asia/Baghdad",
    "iso:country":"IQ",
    "name:ara_x_preferred":[
        "\u062d\u0645\u0648\u062f \u062c\u0633\u0627\u0645"
    ],
    "name:und_x_variant":[
        "\u1e28am\u016bd Jas\u0101m"
    ],
    "wof:name":"Hamud Jasam",
    "wof:placetype":"locality"
},
  "geometry": {"coordinates":[44.34482,33.80917],"type":"Point"}
}