{
  "type": "Feature",
  "properties": {
    "gn:admin1_code":"15.0",
    "gn:admin2_code":"9166620.0",
    "gn:asciiname":"Qubbat al Wahbi",
    "gn:country_code":"IQ",
    "gn:dem":341,
    "gn:feature_class":"P",
    "gn:feature_code":"PPL",
    "gn:name":"Qubbat al Wahb\u012b",
    "gn:population":0,
    "gn:timezone":"Asia/Baghdad",
    "iso:country":"IQ",
    "name:ara_x_preferred":[
        "\u0642\u0628\u0647 \u0627\u0644\u0648\u0647\u0628\u064a"
    ],
    "name:und_x_variant":[
        "Qubbat al Wahb\u012b"
    ],
    "wof:name":"Qubbat al Wahbi",
    "wof:placetype":"locality"
},
  "geometry": {"coordinates":[41.90115,36.12955],"type":"Point"}
}