{
  "type": "Feature",
  "properties": {
    "iso:country":"IQ",
    "qs:gn_pop":0,
    "qs:name":"\u062a\u0643\u0631\u064a\u062a",
    "qs:name_adm0":"Iraq",
    "qs:name_adm1":"S-Alah Ad Din",
    "qs:photos":66,
    "qs:photos_1k":13,
    "qs:photos_9k":1,
    "qs:photos_9r":2,
    "qs:photos_all":66,
    "qs:photos_sr":2,
    "qs:placetype":"Town",
    "qs:pop_sr":"0",
    "qs:woe_adm0":23424855,
    "wof:name":"\u062a\u0643\u0631\u064a\u062a",
    "wof:placetype":"locality"
},
  "geometry": {"coordinates":[43.655548,34.626427],"type":"Point"}
}