{
  "type": "Feature",
  "properties": {
    "gn:admin1_code":"18.0",
    "gn:admin2_code":"91594.0",
    "gn:asciiname":"Mukayshifah",
    "gn:country_code":"IQ",
    "gn:dem":74,
    "gn:feature_class":"P",
    "gn:feature_code":"PPL",
    "gn:name":"Mukaysh\u012bfah",
    "gn:population":0,
    "gn:timezone":"Asia/Baghdad",
    "iso:country":"IQ",
    "name:und_x_variant":[
        "Mukaysh\u012bfah"
    ],
    "wof:name":"Mukayshifah",
    "wof:placetype":"locality"
},
  "geometry": {"coordinates":[43.74278,34.3675],"type":"Point"}
}