{
  "type": "Feature",
  "properties": {
    "gn:admin1_code":"7.0",
    "gn:admin2_code":"9166569.0",
    "gn:asciiname":"'Abd al Hadi",
    "gn:country_code":"IQ",
    "gn:dem":40,
    "gn:feature_class":"P",
    "gn:feature_code":"PPL",
    "gn:name":"\u2018Abd al H\u0101d\u012b",
    "gn:population":0,
    "gn:timezone":"Asia/Baghdad",
    "iso:country":"IQ",
    "name:ara_x_preferred":[
        "\u0639\u0628\u062f \u0627\u0644\u0647\u0627\u062f\u064a"
    ],
    "name:und_x_variant":[
        "Qaryat \u2018Abd al H\u0101d\u012b",
        "\u0642\u0631\u064a\u0629 \u0639\u0628\u062f \u0627\u0644\u0647\u0627\u062f\u064a",
        "\u2018Abd al H\u0101d\u012b"
    ],
    "wof:name":"'Abd al Hadi",
    "wof:placetype":"locality"
},
  "geometry": {"coordinates":[44.24237,33.66571],"type":"Point"}
}