{
  "type": "Feature",
  "properties": {
    "gn:admin1_code":"8.0",
    "gn:admin2_code":"9166607.0",
    "gn:asciiname":"Qalat Bardi",
    "gn:country_code":"IQ",
    "gn:dem":549,
    "gn:feature_class":"P",
    "gn:feature_code":"PPL",
    "gn:name":"Qal\u0101t Bard\u012b",
    "gn:population":0,
    "gn:timezone":"Asia/Baghdad",
    "iso:country":"IQ",
    "name:ara_x_preferred":[
        "\u0642\u0644\u0627\u062a \u0628\u0631\u062f\u064a"
    ],
    "name:kur_x_preferred":[
        "Ke\u0142e Berd\u00ee"
    ],
    "name:kur_x_variant":[
        "\u0643\u06d5\u06b5\u06d5 \u0628\u06d5\u0631\u062f\u0649"
    ],
    "name:und_x_variant":[
        "Qal\u2019 al Badr\u012b",
        "Qal\u2018at Badr\u012b",
        "Qal\u0101\u2018at Badr\u012b",
        "Qala Bardi",
        "Qal\u0101t Bard\u012b"
    ],
    "wof:name":"Qalat Bardi",
    "wof:placetype":"locality"
},
  "geometry": {"coordinates":[42.98253,36.81554000000001],"type":"Point"}
}