{
  "type": "Feature",
  "properties": {
    "gn:admin1_code":"11.0",
    "gn:admin2_code":"9166534.0",
    "gn:asciiname":"Rayzan",
    "gn:country_code":"IQ",
    "gn:dem":455,
    "gn:feature_class":"P",
    "gn:feature_code":"PPL",
    "gn:name":"Rayz\u0101n",
    "gn:population":0,
    "gn:timezone":"Asia/Baghdad",
    "iso:country":"IQ",
    "name:ara_x_preferred":[
        "R\u0113z\u0101n"
    ],
    "name:ara_x_variant":[
        "R\u012bz\u0101n",
        "\u0631\u064a\u0632\u0627\u0646"
    ],
    "name:kur_x_preferred":[
        "\u1e5e\u00eazan"
    ],
    "name:kur_x_variant":[
        "\u0695\u06ce\u0632\u0627\u0646"
    ],
    "name:und_x_variant":[
        "Rayz\u0101n",
        "\u0631\u064a\u0632\u0627\u0646",
        "R\u0113z\u0101n",
        "Rezan"
    ],
    "wof:name":"Rayzan",
    "wof:placetype":"locality"
},
  "geometry": {"coordinates":[44.12875,36.85706],"type":"Point"}
}