{
  "type": "Feature",
  "properties": {
    "gn:admin1_code":"15.0",
    "gn:admin2_code":"9166649.0",
    "gn:asciiname":"Qaryat Kahriz",
    "gn:country_code":"IQ",
    "gn:dem":240,
    "gn:feature_class":"P",
    "gn:feature_code":"PPL",
    "gn:name":"Qaryat Kahr\u012bz",
    "gn:population":0,
    "gn:timezone":"Asia/Baghdad",
    "iso:country":"IQ",
    "name:ara_x_preferred":[
        "\u0642\u0631\u064a\u0629 \u0643\u0647\u0631\u064a\u0632"
    ],
    "name:und_x_variant":[
        "Qaryat Kahr\u012bz"
    ],
    "wof:name":"Qaryat Kahriz",
    "wof:placetype":"locality"
},
  "geometry": {"coordinates":[43.03474,35.83116],"type":"Point"}
}