{
  "type": "Feature",
  "properties": {
    "gn:admin1_code":"7.0",
    "gn:admin2_code":"99101.0",
    "gn:asciiname":"'Arab Muhammad Jasim",
    "gn:country_code":"IQ",
    "gn:dem":36,
    "gn:feature_class":"P",
    "gn:feature_code":"PPL",
    "gn:name":"\u2018Arab Mu\u1e29ammad J\u0101sim",
    "gn:population":0,
    "gn:timezone":"Asia/Baghdad",
    "iso:country":"IQ",
    "name:ara_x_preferred":[
        "Al \u1e28\u0101jj J\u0101sim"
    ],
    "name:ara_x_variant":[
        "\u0639\u0631\u0628 \u0645\u062d\u0645\u062f \u062c\u0627\u0633\u0645",
        "\u0627\u0644\u062d\u0627\u062c \u062c\u0627\u0633\u0645"
    ],
    "name:und_x_variant":[
        "Majj\u0101sim",
        "\u2018Arab Mu\u1e29ammad J\u0101sim"
    ],
    "wof:name":"'Arab Muhammad Jasim",
    "wof:placetype":"locality"
},
  "geometry": {"coordinates":[44.30907,33.19528],"type":"Point"}
}