{
  "type": "Feature",
  "properties": {
    "gn:admin1_code":"9.0",
    "gn:admin2_code":"90509.0",
    "gn:asciiname":"Husayn as Sabt",
    "gn:country_code":"IQ",
    "gn:dem":4,
    "gn:feature_class":"P",
    "gn:feature_code":"PPL",
    "gn:name":"\u1e28usayn as Sab\u0163",
    "gn:population":0,
    "gn:timezone":"Asia/Baghdad",
    "iso:country":"IQ",
    "name:ara_x_preferred":[
        "\u062d\u0633\u064a\u0646 \u0627\u0644\u0633\u0628\u0637"
    ],
    "name:und_x_variant":[
        "Im\u0101m Husain as Sabt",
        "\u1e28usayn",
        "Im\u0101m al Husain Ibn \u2018Ali",
        "Im\u0101m al \u1e28usayn Bin \u2018Al\u012b",
        "\u1e28usayn as Sab\u0163"
    ],
    "wof:name":"Husayn as Sabt",
    "wof:placetype":"locality"
},
  "geometry": {"coordinates":[46.5075,31.01919],"type":"Point"}
}