{
  "type": "Feature",
  "properties": {
    "gn:admin1_code":"10.0",
    "gn:admin2_code":"99170.0",
    "gn:asciiname":"'Arab Husayn Halaqah",
    "gn:country_code":"IQ",
    "gn:dem":45,
    "gn:feature_class":"P",
    "gn:feature_code":"PPL",
    "gn:name":"\u2018Arab \u1e28usayn \u1e28alaqah",
    "gn:population":0,
    "gn:timezone":"Asia/Baghdad",
    "iso:country":"IQ",
    "name:ara_x_preferred":[
        "\u0639\u0631\u0628 \u062d\u0633\u064a\u0646 \u062d\u0644\u0642\u0629"
    ],
    "name:und_x_variant":[
        "\u2018Arab \u1e28usayn \u1e28alaqah"
    ],
    "wof:name":"'Arab Husayn Halaqah",
    "wof:placetype":"locality"
},
  "geometry": {"coordinates":[44.44658,33.84666],"type":"Point"}
}