{
  "type": "Feature",
  "properties": {
    "gn:admin1_code":"4.0",
    "gn:admin2_code":"99737.0",
    "gn:asciiname":"'Arab",
    "gn:country_code":"IQ",
    "gn:dem":19,
    "gn:feature_class":"P",
    "gn:feature_code":"PPLL",
    "gn:name":"\u2018Arab",
    "gn:population":0,
    "gn:timezone":"Asia/Baghdad",
    "iso:country":"IQ",
    "name:ara_x_preferred":[
        "\u0639\u0631\u0628"
    ],
    "name:und_x_variant":[
        "\u2018Arab"
    ],
    "wof:name":"'Arab",
    "wof:placetype":"locality"
},
  "geometry": {"coordinates":[45.35216,32.09633],"type":"Point"}
}