{
  "type": "Feature",
  "properties": {
    "gn:admin1_code":"13.0",
    "gn:admin2_code":"94786.0",
    "gn:asciiname":"Quli Bak",
    "gn:country_code":"IQ",
    "gn:dem":566,
    "gn:feature_class":"P",
    "gn:feature_code":"PPL",
    "gn:name":"Q\u016bl\u012b Bak",
    "gn:population":0,
    "gn:timezone":"Asia/Baghdad",
    "iso:country":"IQ",
    "name:ara_x_preferred":[
        "\u0642\u0648\u0644\u064a \u0628\u0643"
    ],
    "name:kur_x_preferred":[
        "Qul\u00ee Beg"
    ],
    "name:kur_x_variant":[
        "\u0642\u0648\u0644\u0649 \u0628\u06d5\u06af"
    ],
    "name:und_x_variant":[
        "Qal\u012bbak",
        "Quli Beg",
        "Quly Bag",
        "Q\u016bl\u012b Bak"
    ],
    "wof:name":"Quli Bak",
    "wof:placetype":"locality"
},
  "geometry": {"coordinates":[44.43892,35.73667000000001],"type":"Point"}
}