{
  "type": "Feature",
  "properties": {
    "gn:admin1_code":"9.0",
    "gn:admin2_code":"90509.0",
    "gn:asciiname":"Al Karimat",
    "gn:country_code":"IQ",
    "gn:dem":4,
    "gn:feature_class":"P",
    "gn:feature_code":"PPL",
    "gn:name":"Al Kar\u012bm\u0101t",
    "gn:population":0,
    "gn:timezone":"Asia/Baghdad",
    "iso:country":"IQ",
    "name:ara_x_preferred":[
        "\u0627\u0644\u0643\u0631\u064a\u0645\u0627\u062a"
    ],
    "name:und_x_variant":[
        "Al Kar\u012bm\u0101t"
    ],
    "wof:name":"Al Karimat",
    "wof:placetype":"locality"
},
  "geometry": {"coordinates":[46.61179,30.88728],"type":"Point"}
}