{
  "type": "Feature",
  "properties": {
    "gn:admin1_code":"15.0",
    "gn:admin2_code":"90392.0",
    "gn:asciiname":"Malishah",
    "gn:country_code":"IQ",
    "gn:dem":322,
    "gn:feature_class":"P",
    "gn:feature_code":"PPL",
    "gn:name":"Mal\u012bshah",
    "gn:population":0,
    "gn:timezone":"Asia/Baghdad",
    "iso:country":"IQ",
    "name:ara_x_preferred":[
        "\u0645\u0644\u064a\u0634\u0629"
    ],
    "name:und_x_variant":[
        "Mal\u012bshah"
    ],
    "wof:name":"Malishah",
    "wof:placetype":"locality"
},
  "geometry": {"coordinates":[42.71061,36.43513],"type":"Point"}
}