{
  "type": "Feature",
  "properties": {
    "gn:admin1_code":"6.0",
    "gn:admin2_code":"6818313.0",
    "gn:asciiname":"Qal'at Husayn al Barrak",
    "gn:country_code":"IQ",
    "gn:dem":31,
    "gn:feature_class":"P",
    "gn:feature_code":"PPL",
    "gn:name":"Qal\u2018at \u1e28usayn al Barr\u0101k",
    "gn:population":0,
    "gn:timezone":"Asia/Baghdad",
    "iso:country":"IQ",
    "name:ara_x_preferred":[
        "\u0642\u0644\u0639\u0629 \u062d\u0633\u064a\u0646 \u0627\u0644\u0628\u0631\u0627\u0643"
    ],
    "name:und_x_variant":[
        "Qal\u2018at Husain al Barr\u0101k",
        "\u1e28usayn al Barr\u0101k",
        "Qal\u2018at \u1e28usayn al Barr\u0101k"
    ],
    "wof:name":"Qal'at Husayn al Barrak",
    "wof:placetype":"locality"
},
  "geometry": {"coordinates":[44.50851,32.48695],"type":"Point"}
}