{
  "type": "Feature",
  "properties": {
    "gn:admin1_code":"3.0",
    "gn:admin2_code":"9166626.0",
    "gn:asciiname":"Dahlus",
    "gn:country_code":"IQ",
    "gn:dem":9,
    "gn:feature_class":"P",
    "gn:feature_code":"PPL",
    "gn:name":"Da\u1e29l\u016bs",
    "gn:population":0,
    "gn:timezone":"Asia/Baghdad",
    "iso:country":"IQ",
    "name:ara_x_preferred":[
        "\u062f\u062d\u0644\u0648\u0633"
    ],
    "name:und_x_variant":[
        "Da\u1e29l\u016bs"
    ],
    "wof:name":"Dahlus",
    "wof:placetype":"locality"
},
  "geometry": {"coordinates":[45.57039,31.22886],"type":"Point"}
}