{
  "type": "Feature",
  "properties": {
    "gn:admin1_code":"16.0",
    "gn:admin2_code":"99132.0",
    "gn:asciiname":"Mahmud al Amarhid",
    "gn:country_code":"IQ",
    "gn:dem":23,
    "gn:feature_class":"P",
    "gn:feature_code":"PPL",
    "gn:name":"Ma\u1e29m\u016bd al Amarh\u012bd",
    "gn:population":0,
    "gn:timezone":"Asia/Baghdad",
    "iso:country":"IQ",
    "name:ara_x_preferred":[
        "\u0645\u062d\u0645\u0648\u062f \u0627\u0644\u0623\u0645\u0631\u0647\u064a\u062f"
    ],
    "name:und_x_variant":[
        "Ma\u1e29m\u016bd al Amarh\u012bd"
    ],
    "wof:name":"Mahmud al Amarhid",
    "wof:placetype":"locality"
},
  "geometry": {"coordinates":[45.52842,32.59266],"type":"Point"}
}