{
  "type": "Feature",
  "properties": {
    "gn:admin1_code":"15.0",
    "gn:admin2_code":"9166649.0",
    "gn:asciiname":"Umm Hijarah as Sufla",
    "gn:country_code":"IQ",
    "gn:dem":234,
    "gn:feature_class":"P",
    "gn:feature_code":"PPL",
    "gn:name":"Umm \u1e28ij\u0101rah as Sufl\u00e1",
    "gn:population":0,
    "gn:timezone":"Asia/Baghdad",
    "iso:country":"IQ",
    "name:ara_x_preferred":[
        "\u0627\u0645 \u062d\u062c\u0627\u0631\u0629 \u0627\u0644\u0633\u0641\u0644\u0649"
    ],
    "name:und_x_variant":[
        "Umm \u1e28ij\u0101rah as Sufl\u00e1"
    ],
    "wof:name":"Umm Hijarah as Sufla",
    "wof:placetype":"locality"
},
  "geometry": {"coordinates":[42.63564,36.10378],"type":"Point"}
}