{
  "type": "Feature",
  "properties": {
    "gn:admin1_code":"15.0",
    "gn:admin2_code":"9166620.0",
    "gn:asciiname":"Husayn Idris",
    "gn:country_code":"IQ",
    "gn:dem":348,
    "gn:feature_class":"P",
    "gn:feature_code":"PPL",
    "gn:name":"\u1e28usayn Idr\u012bs",
    "gn:population":0,
    "gn:timezone":"Asia/Baghdad",
    "iso:country":"IQ",
    "name:ara_x_preferred":[
        "\u062d\u0633\u064a\u0646 \u0627\u062f\u0631\u064a\u0633"
    ],
    "name:kur_x_preferred":[
        "\u1e26s\u00ean Idr\u00ees"
    ],
    "name:kur_x_variant":[
        "\u062d\u0633\u06ce\u0646 \u0626\u064a\u062f\u0631\u064a\u0633"
    ],
    "name:und_x_variant":[
        "Husein Idris",
        "\u1e28usayn Idr\u012bs"
    ],
    "wof:name":"Husayn Idris",
    "wof:placetype":"locality"
},
  "geometry": {"coordinates":[42.33856,36.36458],"type":"Point"}
}