{
  "type": "Feature",
  "properties": {
    "gn:admin1_code":"8.0",
    "gn:admin2_code":"99612.0",
    "gn:asciiname":"Birkuhinah",
    "gn:country_code":"IQ",
    "gn:dem":978,
    "gn:feature_class":"P",
    "gn:feature_code":"PPL",
    "gn:name":"Birk\u016bh\u012bnah",
    "gn:population":0,
    "gn:timezone":"Asia/Baghdad",
    "iso:country":"IQ",
    "name:ara_x_preferred":[
        "\u0628\u0631\u0643\u0648\u0647\u064a\u0646\u0647"
    ],
    "name:kur_x_preferred":[
        "Birkuh\u00eene"
    ],
    "name:kur_x_variant":[
        "\u0628\u0631\u0643\u0648\u06be\u064a\u0646\u06d5"
    ],
    "name:und_x_variant":[
        "Brkuhna",
        "Birk\u016bh\u012bnah",
        "Birkuhaynah"
    ],
    "wof:name":"Birkuhinah",
    "wof:placetype":"locality"
},
  "geometry": {"coordinates":[43.59697,37.07614],"type":"Point"}
}