{
  "type": "Feature",
  "properties": {
    "gn:admin1_code":"18.0",
    "gn:admin2_code":"6872046.0",
    "gn:asciiname":"Dhahab 'Asal",
    "gn:country_code":"IQ",
    "gn:dem":147,
    "gn:feature_class":"P",
    "gn:feature_code":"PPL",
    "gn:name":"Dhahab \u2018Asal",
    "gn:population":0,
    "gn:timezone":"Asia/Baghdad",
    "iso:country":"IQ",
    "name:ara_x_preferred":[
        "\u0630\u0647\u0628 \u0639\u0633\u0644"
    ],
    "name:und_x_variant":[
        "Dhahab \u2018Asal"
    ],
    "wof:name":"Dhahab 'Asal",
    "wof:placetype":"locality"
},
  "geometry": {"coordinates":[43.42541,34.76957],"type":"Point"}
}