{
  "type": "Feature",
  "properties": {
    "gn:admin1_code":"17.0",
    "gn:admin2_code":"9166629.0",
    "gn:asciiname":"Jubar al 'Abidi",
    "gn:country_code":"IQ",
    "gn:dem":24,
    "gn:feature_class":"P",
    "gn:feature_code":"PPL",
    "gn:name":"Jub\u0101r al \u2018\u0100bid\u012b",
    "gn:population":0,
    "gn:timezone":"Asia/Baghdad",
    "iso:country":"IQ",
    "name:ara_x_preferred":[
        "\u062c\u0628\u0627\u0631 \u0627\u0644\u0639\u0627\u0628\u062f\u064a"
    ],
    "name:und_x_variant":[
        "Jub\u0101r al \u2018\u0100bid\u012b"
    ],
    "wof:name":"Jubar al 'Abidi",
    "wof:placetype":"locality"
},
  "geometry": {"coordinates":[44.54387,32.12251],"type":"Point"}
}