{
  "type": "Feature",
  "properties": {
    "gn:admin1_code":"18.0",
    "gn:admin2_code":"90148.0",
    "gn:asciiname":"Majid Makhlaf Salih",
    "gn:country_code":"IQ",
    "gn:dem":125,
    "gn:feature_class":"P",
    "gn:feature_code":"PPL",
    "gn:name":"Maj\u012bd Makhlaf \u015e\u0101li\u1e29",
    "gn:population":0,
    "gn:timezone":"Asia/Baghdad",
    "iso:country":"IQ",
    "name:ara_x_preferred":[
        "\u0645\u062c\u064a\u062f \u0645\u062e\u0644\u0641 \u0635\u0627\u0644\u062d"
    ],
    "name:und_x_variant":[
        "Maj\u012bd Makhlaf \u015e\u0101li\u1e29"
    ],
    "wof:name":"Majid Makhlaf Salih",
    "wof:placetype":"locality"
},
  "geometry": {"coordinates":[43.3511,34.36845],"type":"Point"}
}