{
  "type": "Feature",
  "properties": {
    "gn:admin1_code":"12.0",
    "gn:admin2_code":"94822.0",
    "gn:asciiname":"Bustan Juwad Kazim",
    "gn:country_code":"IQ",
    "gn:dem":34,
    "gn:feature_class":"P",
    "gn:feature_code":"PPLL",
    "gn:name":"Bust\u0101n Juw\u0101d K\u0101z\u0327im",
    "gn:population":0,
    "gn:timezone":"Asia/Baghdad",
    "iso:country":"IQ",
    "name:ara_x_preferred":[
        "Bust\u0101n Juw\u0101d K\u0101z\u0327im"
    ],
    "wof:name":"Bustan Juwad Kazim",
    "wof:placetype":"locality"
},
  "geometry": {"coordinates":[44.07944,32.6225],"type":"Point"}
}