{
  "type": "Feature",
  "properties": {
    "gn:admin1_code":"8.0",
    "gn:admin2_code":"97269.0",
    "gn:asciiname":"Dulya",
    "gn:country_code":"IQ",
    "gn:dem":886,
    "gn:feature_class":"P",
    "gn:feature_code":"PPL",
    "gn:name":"Dulya",
    "gn:population":0,
    "gn:timezone":"Asia/Baghdad",
    "iso:country":"IQ",
    "name:ara_x_preferred":[
        "\u062f\u0648\u0644\u064a\u0629"
    ],
    "name:kur_x_preferred":[
        "Dulye"
    ],
    "name:kur_x_variant":[
        "\u062f\u0648\u0644\u064a\u06d5",
        "Dulya",
        "\u062f\u0648\u0644\u064a\u0627"
    ],
    "name:und_x_variant":[
        "Dulia",
        "D\u016bliya",
        "D\u016bliyah"
    ],
    "wof:name":"Dulya",
    "wof:placetype":"locality"
},
  "geometry": {"coordinates":[43.05592,37.03229],"type":"Point"}
}