{
  "type": "Feature",
  "properties": {
    "gn:admin1_code":"5.0",
    "gn:admin2_code":"9166600.0",
    "gn:asciiname":"Bi Rash",
    "gn:country_code":"IQ",
    "gn:dem":294,
    "gn:feature_class":"P",
    "gn:feature_code":"PPL",
    "gn:name":"B\u012b Rash",
    "gn:population":0,
    "gn:timezone":"Asia/Baghdad",
    "iso:country":"IQ",
    "name:ara_x_preferred":[
        "\u0628\u064a \u0631\u0634"
    ],
    "name:kur_x_preferred":[
        "B\u00eeye \u1e5eesh"
    ],
    "name:kur_x_variant":[
        "\u0628\u0649 \u064a\u06d5 \u0695\u06d5\u0634"
    ],
    "name:und_x_variant":[
        "B\u012b Rash",
        "B\u012byarash",
        "Qaryat B\u012b Rash",
        "Bia Rash",
        "\u0642\u0631\u064a\u0629 \u0628\u064a \u0631\u0634"
    ],
    "wof:name":"Bi Rash",
    "wof:placetype":"locality"
},
  "geometry": {"coordinates":[45.46348,34.7923],"type":"Point"}
}