{
  "type": "Feature",
  "properties": {
    "gn:admin1_code":"10.0",
    "gn:admin2_code":"9166680.0",
    "gn:asciiname":"'Abbas ar Rajib",
    "gn:country_code":"IQ",
    "gn:dem":38,
    "gn:feature_class":"P",
    "gn:feature_code":"PPL",
    "gn:name":"\u2018Abb\u0101s ar R\u0101jib",
    "gn:population":0,
    "gn:timezone":"Asia/Baghdad",
    "iso:country":"IQ",
    "name:und_x_variant":[
        "Ab\u0101s ar Rajib",
        "\u2018Abb\u0101s ar R\u0101jib"
    ],
    "wof:name":"'Abbas ar Rajib",
    "wof:placetype":"locality"
},
  "geometry": {"coordinates":[45.03361,33.74333],"type":"Point"}
}