{
  "type": "Feature",
  "properties": {
    "gn:admin1_code":"6.0",
    "gn:admin2_code":"99358.0",
    "gn:asciiname":"Barmanah",
    "gn:country_code":"IQ",
    "gn:dem":32,
    "gn:feature_class":"P",
    "gn:feature_code":"PPL",
    "gn:name":"Barm\u0101nah",
    "gn:population":0,
    "gn:timezone":"Asia/Baghdad",
    "iso:country":"IQ",
    "name:ara_x_preferred":[
        "\u0628\u0631\u0645\u0627\u0646\u0629"
    ],
    "name:und_x_variant":[
        "Barm\u0101nah"
    ],
    "wof:name":"Barmanah",
    "wof:placetype":"locality"
},
  "geometry": {"coordinates":[44.53621,32.39368],"type":"Point"}
}