{
  "type": "Feature",
  "properties": {
    "gn:admin1_code":"10.0",
    "gn:admin2_code":"9166680.0",
    "gn:asciiname":"'Abd al Hanash",
    "gn:country_code":"IQ",
    "gn:dem":40,
    "gn:feature_class":"P",
    "gn:feature_code":"PPL",
    "gn:name":"\u2018Abd al \u1e28anash",
    "gn:population":0,
    "gn:timezone":"Asia/Baghdad",
    "iso:country":"IQ",
    "name:ara_x_preferred":[
        "\u0639\u0628\u062f \u0627\u0644\u062d\u0646\u0634"
    ],
    "name:und_x_variant":[
        "\u2018Abd al \u1e28anash"
    ],
    "wof:name":"'Abd al Hanash",
    "wof:placetype":"locality"
},
  "geometry": {"coordinates":[45.39339,33.42846],"type":"Point"}
}