{
  "type": "Feature",
  "properties": {
    "gn:admin1_code":"16.0",
    "gn:admin2_code":"99351.0",
    "gn:asciiname":"Nahiyat al Basha'r",
    "gn:country_code":"IQ",
    "gn:dem":17,
    "gn:feature_class":"P",
    "gn:feature_code":"PPL",
    "gn:name":"N\u0101\u1e29\u012byat al Bash\u0101\u2019r",
    "gn:population":0,
    "gn:timezone":"Asia/Baghdad",
    "iso:country":"IQ",
    "name:ara_x_preferred":[
        "\u0646\u0627\u062d\u064a\u0629 \u0627\u0644\u0628\u0634\u0627\u0626\u0631"
    ],
    "name:und_x_variant":[
        "N\u0101\u1e29\u012byat al Bash\u0101\u2019r"
    ],
    "wof:name":"Nahiyat al Basha'r",
    "wof:placetype":"locality"
},
  "geometry": {"coordinates":[46.11685,32.12327],"type":"Point"}
}