{
  "type": "Feature",
  "properties": {
    "gn:admin1_code":"10.0",
    "gn:admin2_code":"9166680.0",
    "gn:asciiname":"Humayyid Shanun",
    "gn:cc2":"IQ",
    "gn:country_code":"IQ",
    "gn:dem":58,
    "gn:feature_class":"P",
    "gn:feature_code":"PPL",
    "gn:name":"\u1e28umayyid Sh\u0101n\u016bn",
    "gn:population":0,
    "gn:timezone":"Asia/Baghdad",
    "iso:country":"IQ",
    "name:und_x_variant":[
        "Humayyid Sh\u0101n\u016bm",
        "\u1e28umayyid Sh\u0101n\u016bn"
    ],
    "wof:name":"Humayyid Shanun",
    "wof:placetype":"locality"
},
  "geometry": {"coordinates":[45.66667,33.48333],"type":"Point"}
}