{
  "type": "Feature",
  "properties": {
    "gn:admin1_code":"4.0",
    "gn:admin2_code":"98634.0",
    "gn:asciiname":"Bur Sa'id",
    "gn:country_code":"IQ",
    "gn:dem":20,
    "gn:feature_class":"P",
    "gn:feature_code":"PPL",
    "gn:name":"B\u016br Sa\u2018\u012bd",
    "gn:population":0,
    "gn:timezone":"Asia/Baghdad",
    "iso:country":"IQ",
    "name:ara_x_preferred":[
        "\u0628\u0648\u0631 \u0633\u0639\u064a\u062f"
    ],
    "name:und_x_variant":[
        "B\u016br Sa\u2018\u012bd"
    ],
    "wof:name":"Bur Sa'id",
    "wof:placetype":"locality"
},
  "geometry": {"coordinates":[44.55027000000001,31.89183],"type":"Point"}
}