{
  "type": "Feature",
  "properties": {
    "gn:admin1_code":"18.0",
    "gn:admin2_code":"6783103.0",
    "gn:asciiname":"Qaryat Banat al Hasan",
    "gn:country_code":"IQ",
    "gn:dem":59,
    "gn:feature_class":"P",
    "gn:feature_code":"PPL",
    "gn:name":"Qaryat Ban\u0101t al \u1e28asan",
    "gn:population":0,
    "gn:timezone":"Asia/Baghdad",
    "iso:country":"IQ",
    "name:ara_x_preferred":[
        "\u0642\u0631\u064a\u0629 \u0628\u0646\u0627\u062a \u0627\u0644\u062d\u0633\u0646"
    ],
    "name:und_x_variant":[
        "Jal\u0101mat Bint al \u1e28asan",
        "\u2018Arab Ban\u0101t al \u1e28asan",
        "Bint al \u1e28asan",
        "Qaryat Ban\u0101t al \u1e28asan"
    ],
    "wof:name":"Qaryat Banat al Hasan",
    "wof:placetype":"locality"
},
  "geometry": {"coordinates":[44.01225,34.14639],"type":"Point"}
}