{
  "type": "Feature",
  "properties": {
    "gn:admin1_code":"11.0",
    "gn:admin2_code":"9166588.0",
    "gn:asciiname":"Axure",
    "gn:country_code":"IQ",
    "gn:dem":508,
    "gn:feature_class":"P",
    "gn:feature_code":"PPL",
    "gn:name":"Axure",
    "gn:population":0,
    "gn:timezone":"Asia/Baghdad",
    "iso:country":"IQ",
    "name:ara_x_preferred":[
        "\u0627\u062e\u0648\u0631\u0629"
    ],
    "name:kur_x_preferred":[
        "Axure"
    ],
    "name:kur_x_variant":[
        "\u0626\u0627\u062e\u0648\u0631\u06d5"
    ],
    "name:und_x_variant":[
        "Akhura",
        "Akh\u016brah"
    ],
    "wof:name":"Axure",
    "wof:placetype":"locality"
},
  "geometry": {"coordinates":[44.31602,36.04789],"type":"Point"}
}