{
  "type": "Feature",
  "properties": {
    "gn:admin1_code":"7.0",
    "gn:admin2_code":"99101.0",
    "gn:asciiname":"Khalaf Mukhlif",
    "gn:country_code":"IQ",
    "gn:dem":32,
    "gn:feature_class":"P",
    "gn:feature_code":"PPL",
    "gn:name":"Khalaf Mukhlif",
    "gn:population":0,
    "gn:timezone":"Asia/Baghdad",
    "iso:country":"IQ",
    "name:ara_x_preferred":[
        "\u062e\u0644\u0641 \u0645\u062e\u0644\u0641"
    ],
    "wof:name":"Khalaf Mukhlif",
    "wof:placetype":"locality"
},
  "geometry": {"coordinates":[44.46907,32.87375],"type":"Point"}
}