{
  "type": "Feature",
  "properties": {
    "gn:admin1_code":"12.0",
    "gn:admin2_code":"9166603.0",
    "gn:asciiname":"Albu Huwaydi",
    "gn:country_code":"IQ",
    "gn:dem":60,
    "gn:feature_class":"P",
    "gn:feature_code":"PPL",
    "gn:name":"\u0100lb\u016b Huwayd\u012b",
    "gn:population":0,
    "gn:timezone":"Asia/Baghdad",
    "iso:country":"IQ",
    "name:ara_x_preferred":[
        "\u0627\u0644\u0628\u0648 \u0647\u0648\u064a\u062f\u064a"
    ],
    "name:und_x_variant":[
        "\u0100lb\u016b Huwayd\u012b"
    ],
    "wof:name":"Albu Huwaydi",
    "wof:placetype":"locality"
},
  "geometry": {"coordinates":[43.4815,32.57788],"type":"Point"}
}