{
  "type": "Feature",
  "properties": {
    "gn:admin1_code":"8.0",
    "gn:admin2_code":"99612.0",
    "gn:asciiname":"Pir Avdel",
    "gn:country_code":"IQ",
    "gn:dem":1909,
    "gn:feature_class":"P",
    "gn:feature_code":"PPL",
    "gn:name":"P\u00eer Avdel",
    "gn:population":0,
    "gn:timezone":"Asia/Baghdad",
    "iso:country":"IQ",
    "name:kur_x_preferred":[
        "P\u00eer Avdel"
    ],
    "name:kur_x_variant":[
        "\u067e\u064a\u0631 \u0626\u0627\u06a4\u062f\u06d5\u0644"
    ],
    "name:und_x_variant":[
        "P\u012br\u0101vdala"
    ],
    "wof:name":"Pir Avdel",
    "wof:placetype":"locality"
},
  "geometry": {"coordinates":[43.88775,37.21971],"type":"Point"}
}