{
  "type": "Feature",
  "properties": {
    "gn:admin1_code":"10.0",
    "gn:admin2_code":"99063.0",
    "gn:asciiname":"Tall Farid",
    "gn:country_code":"IQ",
    "gn:dem":47,
    "gn:feature_class":"P",
    "gn:feature_code":"PPL",
    "gn:name":"Tall Far\u012bd",
    "gn:population":0,
    "gn:timezone":"Asia/Baghdad",
    "iso:country":"IQ",
    "name:ara_x_preferred":[
        "\u062a\u0644 \u0641\u0631\u064a\u062f"
    ],
    "name:und_x_variant":[
        "Tall Far\u012bd"
    ],
    "wof:name":"Tall Farid",
    "wof:placetype":"locality"
},
  "geometry": {"coordinates":[44.7367,33.80397],"type":"Point"}
}