{
  "type": "Feature",
  "properties": {
    "gn:admin1_code":"18.0",
    "gn:admin2_code":"6805736.0",
    "gn:asciiname":"Muhammad Ahmad Jasim",
    "gn:country_code":"IQ",
    "gn:dem":44,
    "gn:feature_class":"P",
    "gn:feature_code":"PPL",
    "gn:name":"Mu\u1e29ammad A\u1e29mad J\u0101sim",
    "gn:population":0,
    "gn:timezone":"Asia/Baghdad",
    "iso:country":"IQ",
    "name:ara_x_preferred":[
        "\u0645\u062d\u0645\u062f \u0627\u062d\u0645\u062f \u062c\u0627\u0633\u0645"
    ],
    "name:und_x_variant":[
        "Mu\u1e29ammad A\u1e29mad J\u0101sim"
    ],
    "wof:name":"Muhammad Ahmad Jasim",
    "wof:placetype":"locality"
},
  "geometry": {"coordinates":[44.32308,33.9303],"type":"Point"}
}