{
  "type": "Feature",
  "properties": {
    "gn:admin1_code":"6.0",
    "gn:admin2_code":"99358.0",
    "gn:asciiname":"Qaryat al 'Ubidin",
    "gn:country_code":"IQ",
    "gn:dem":28,
    "gn:feature_class":"P",
    "gn:feature_code":"PPL",
    "gn:name":"Qaryat al \u2018\u016abid\u012bn",
    "gn:population":0,
    "gn:timezone":"Asia/Baghdad",
    "iso:country":"IQ",
    "name:ara_x_preferred":[
        "\u0642\u0631\u064a\u0629 \u0627\u0644\u0639\u0648\u0628\u062f\u064a\u0646"
    ],
    "name:und_x_variant":[
        "Qaryat al \u2018\u016abid\u012bn"
    ],
    "wof:name":"Qaryat al 'Ubidin",
    "wof:placetype":"locality"
},
  "geometry": {"coordinates":[44.83242,32.25475],"type":"Point"}
}