{
  "type": "Feature",
  "properties": {
    "gn:admin1_code":"6.0",
    "gn:asciiname":"Jijan Husayn",
    "gn:country_code":"IQ",
    "gn:dem":26,
    "gn:feature_class":"P",
    "gn:feature_code":"PPL",
    "gn:name":"Jij\u0101n \u1e28usayn",
    "gn:population":0,
    "gn:timezone":"Asia/Baghdad",
    "iso:country":"IQ",
    "name:ara_x_preferred":[
        "\u062c\u062c\u0627\u0646 \u062d\u0633\u064a\u0646"
    ],
    "name:und_x_variant":[
        "Jij\u0101n \u1e28usayn"
    ],
    "wof:name":"Jijan Husayn",
    "wof:placetype":"locality"
},
  "geometry": {"coordinates":[44.55579,32.81243],"type":"Point"}
}