{
  "type": "Feature",
  "properties": {
    "gn:admin1_code":"7.0",
    "gn:admin2_code":"99101.0",
    "gn:asciiname":"Yasin Ahmad",
    "gn:country_code":"IQ",
    "gn:dem":34,
    "gn:feature_class":"P",
    "gn:feature_code":"PPL",
    "gn:name":"Y\u0101s\u012bn A\u1e29mad",
    "gn:population":0,
    "gn:timezone":"Asia/Baghdad",
    "iso:country":"IQ",
    "name:ara_x_preferred":[
        "\u064a\u0627\u0633\u064a\u0646 \u0623\u062d\u0645\u062f"
    ],
    "name:und_x_variant":[
        "Y\u0101s\u012bn A\u1e29mad"
    ],
    "wof:name":"Yasin Ahmad",
    "wof:placetype":"locality"
},
  "geometry": {"coordinates":[44.49169000000001,33.1394],"type":"Point"}
}