{
  "type": "Feature",
  "properties": {
    "gn:admin1_code":"8.0",
    "gn:admin2_code":"89569.0",
    "gn:asciiname":"Xishtana",
    "gn:country_code":"IQ",
    "gn:dem":417,
    "gn:feature_class":"P",
    "gn:feature_code":"PPLF",
    "gn:name":"Xishtana",
    "gn:population":0,
    "gn:timezone":"Europe/Istanbul",
    "iso:country":"IQ",
    "name:ara_x_preferred":[
        "\u0642\u064a\u0634\u0637\u0627\u064a\u0629"
    ],
    "name:kur_x_preferred":[
        "Xishtana"
    ],
    "name:kur_x_variant":[
        "\u062e\u0634\u062a\u0627\u0646\u0627"
    ],
    "name:und_x_variant":[
        "Khisht\u0101nah",
        "Khisht\u0101na",
        "Q\u012bsh\u0163\u0101yah"
    ],
    "wof:name":"Xishtana",
    "wof:placetype":"locality"
},
  "geometry": {"coordinates":[42.59522,37.17178],"type":"Point"}
}