{
  "type": "Feature",
  "properties": {
    "gn:admin1_code":"16.0",
    "gn:admin2_code":"98460.0",
    "gn:asciiname":"'Abd Muhsin",
    "gn:country_code":"IQ",
    "gn:dem":32,
    "gn:feature_class":"P",
    "gn:feature_code":"PPL",
    "gn:name":"\u2018Abd Mu\u1e29sin",
    "gn:population":0,
    "gn:timezone":"Asia/Baghdad",
    "iso:country":"IQ",
    "name:ara_x_preferred":[
        "\u0639\u0628\u062f \u0645\u062d\u0633\u0646"
    ],
    "name:ara_x_variant":[
        "\u2018Abd Mu\u1e29sin"
    ],
    "wof:name":"'Abd Muhsin",
    "wof:placetype":"locality"
},
  "geometry": {"coordinates":[44.89569,32.92224],"type":"Point"}
}