{
  "type": "Feature",
  "properties": {
    "gn:admin1_code":"5.0",
    "gn:admin2_code":"91176.0",
    "gn:asciiname":"Surah Dizah",
    "gn:country_code":"IQ",
    "gn:dem":1365,
    "gn:feature_class":"P",
    "gn:feature_code":"PPL",
    "gn:name":"S\u016brah Dizah",
    "gn:population":0,
    "gn:timezone":"Asia/Baghdad",
    "iso:country":"IQ",
    "name:ara_x_preferred":[
        "\u0633\u0648\u0631\u0647 \u062f\u0632\u0647"
    ],
    "name:kur_x_preferred":[
        "Sure Dze"
    ],
    "name:kur_x_variant":[
        "\u0633\u0648\u0631\u06d5 \u062f\u0632\u06d5"
    ],
    "name:und_x_variant":[
        "S\u016brah Dizah",
        "S\u016bradiza",
        "Sw\u0101rah Dizah",
        "\u0633\u0648\u0627\u0631\u0647 \u062f\u0632\u0647",
        "Suradizeh",
        "Soora Dza"
    ],
    "wof:name":"Surah Dizah",
    "wof:placetype":"locality"
},
  "geometry": {"coordinates":[45.58123,35.93711],"type":"Point"}
}