{
  "type": "Feature",
  "properties": {
    "gn:admin1_code":"15.0",
    "gn:admin2_code":"9166649.0",
    "gn:asciiname":"An Naddas",
    "gn:country_code":"IQ",
    "gn:dem":235,
    "gn:feature_class":"P",
    "gn:feature_code":"PPL",
    "gn:name":"An Nadd\u0101s",
    "gn:population":0,
    "gn:timezone":"Asia/Baghdad",
    "iso:country":"IQ",
    "name:ara_x_preferred":[
        "\u0627\u0644\u0646\u062f\u0627\u0633"
    ],
    "name:und_x_variant":[
        "An Nadd\u0101s"
    ],
    "wof:name":"An Naddas",
    "wof:placetype":"locality"
},
  "geometry": {"coordinates":[42.9497,35.89991],"type":"Point"}
}