{
  "type": "Feature",
  "properties": {
    "gn:admin1_code":"16.0",
    "gn:admin2_code":"99132.0",
    "gn:asciiname":"'Ali al Juburi",
    "gn:country_code":"IQ",
    "gn:dem":24,
    "gn:feature_class":"P",
    "gn:feature_code":"PPL",
    "gn:name":"\u2018Al\u012b al Jub\u016br\u012b",
    "gn:population":0,
    "gn:timezone":"Asia/Baghdad",
    "iso:country":"IQ",
    "name:ara_x_preferred":[
        "\u0639\u0644\u064a \u0627\u0644\u062c\u0628\u0648\u0631\u064a"
    ],
    "name:und_x_variant":[
        "\u2018Al\u012b al Jub\u016br\u012b"
    ],
    "wof:name":"'Ali al Juburi",
    "wof:placetype":"locality"
},
  "geometry": {"coordinates":[45.48387,32.59798],"type":"Point"}
}