{
  "type": "Feature",
  "properties": {
    "gn:admin1_code":"16.0",
    "gn:admin2_code":"98197.0",
    "gn:asciiname":"Isma'il al 'Abbasi",
    "gn:country_code":"IQ",
    "gn:dem":35,
    "gn:feature_class":"P",
    "gn:feature_code":"PPL",
    "gn:name":"Ism\u0101\u2018\u012bl al \u2018Abb\u0101s\u012b",
    "gn:population":0,
    "gn:timezone":"Asia/Baghdad",
    "iso:country":"IQ",
    "name:ara_x_preferred":[
        "\u0627\u0633\u0645\u0627\u0639\u064a\u0644 \u0627\u0644\u0639\u0628\u0627\u0633\u064a"
    ],
    "name:und_x_variant":[
        "Ism\u0101\u2018\u012bl al \u2018Abb\u0101s\u012b"
    ],
    "wof:name":"Isma'il al 'Abbasi",
    "wof:placetype":"locality"
},
  "geometry": {"coordinates":[45.95499,32.98945],"type":"Point"}
}