{
  "type": "Feature",
  "properties": {
    "gn:admin1_code":"2.0",
    "gn:admin2_code":"9166563.0",
    "gn:asciiname":"Murid Agha",
    "gn:country_code":"IQ",
    "gn:dem":4,
    "gn:feature_class":"P",
    "gn:feature_code":"PPL",
    "gn:name":"Mur\u012bd \u0100gh\u0101",
    "gn:population":0,
    "gn:timezone":"Asia/Baghdad",
    "iso:country":"IQ",
    "name:ara_x_preferred":[
        "Mur\u012bd \u0100gh\u0101"
    ],
    "wof:name":"Murid Agha",
    "wof:placetype":"locality"
},
  "geometry": {"coordinates":[47.33806,30.96028],"type":"Point"}
}