{
  "type": "Feature",
  "properties": {
    "gn:admin1_code":"8.0",
    "gn:admin2_code":"99612.0",
    "gn:asciiname":"Ikmalah",
    "gn:country_code":"IQ",
    "gn:dem":1128,
    "gn:feature_class":"P",
    "gn:feature_code":"PPL",
    "gn:name":"Ikm\u0101lah",
    "gn:population":0,
    "gn:timezone":"Asia/Baghdad",
    "iso:country":"IQ",
    "name:ara_x_preferred":[
        "\u0625\u0643\u0645\u0627\u0644\u0629"
    ],
    "name:kur_x_preferred":[
        "Yekma\u0142e"
    ],
    "name:kur_x_variant":[
        "\u064a\u06d5\u0643\u0645\u0627\u06b5\u06d5",
        "\u00cakmal\u00ea",
        "\u0626\u06ce\u0643\u0645\u0627\u0644\u06ce",
        "\u00cakmale",
        "\u0626\u06ce\u0643\u0645\u0627\u0644\u06d5"
    ],
    "name:und_x_variant":[
        "Yakm\u0101lah",
        "Yakm\u0101la",
        "Iekmala",
        "Ikm\u0101lah",
        "Ekmala"
    ],
    "wof:name":"Ikmalah",
    "wof:placetype":"locality"
},
  "geometry": {"coordinates":[43.43469,37.17075],"type":"Point"}
}