{
  "type": "Feature",
  "properties": {
    "gn:admin1_code":"7.0",
    "gn:admin2_code":"99173.0",
    "gn:asciiname":"Muhammad as Sultan",
    "gn:country_code":"IQ",
    "gn:dem":35,
    "gn:feature_class":"P",
    "gn:feature_code":"PPLL",
    "gn:name":"Mu\u1e29ammad as Sul\u0163\u0101n",
    "gn:population":0,
    "gn:timezone":"Asia/Baghdad",
    "iso:country":"IQ",
    "name:ara_x_preferred":[
        "\u0645\u062d\u0645\u062f \u0627\u0644\u0633\u0644\u0637\u0627\u0646"
    ],
    "name:und_x_variant":[
        "Mu\u1e29ammad as Sul\u0163\u0101n"
    ],
    "wof:name":"Muhammad as Sultan",
    "wof:placetype":"locality"
},
  "geometry": {"coordinates":[44.09898,33.44841],"type":"Point"}
}