{
  "type": "Feature",
  "properties": {
    "gn:admin1_code":"5.0",
    "gn:admin2_code":"9166596.0",
    "gn:asciiname":"Shushke",
    "gn:country_code":"IQ",
    "gn:dem":797,
    "gn:feature_class":"P",
    "gn:feature_code":"PPL",
    "gn:name":"Shushke",
    "gn:population":0,
    "gn:timezone":"Asia/Baghdad",
    "iso:country":"IQ",
    "name:kur_x_preferred":[
        "\u0634\u0648\u0634\u0643\u06d5"
    ],
    "name:kur_x_variant":[
        "Shoshka",
        "Shushke"
    ],
    "name:und_x_variant":[
        "Sh\u016bshka",
        "Shoshka",
        "Shushka"
    ],
    "wof:name":"Shushke",
    "wof:placetype":"locality"
},
  "geometry": {"coordinates":[44.85513,36.07019],"type":"Point"}
}