{
  "type": "Feature",
  "properties": {
    "gn:admin1_code":"6.0",
    "gn:admin2_code":"99358.0",
    "gn:asciiname":"Hadi Hasan Daykan",
    "gn:country_code":"IQ",
    "gn:dem":31,
    "gn:feature_class":"P",
    "gn:feature_code":"PPL",
    "gn:name":"H\u0101d\u012b \u1e28asan \u1e10ayk\u0101n",
    "gn:population":0,
    "gn:timezone":"Asia/Baghdad",
    "iso:country":"IQ",
    "name:ara_x_preferred":[
        "\u0647\u0627\u062f\u064a \u062d\u0633\u0646 \u0636\u064a\u0643\u0627\u0646"
    ],
    "name:und_x_variant":[
        "H\u0101d\u012b \u1e28asan \u1e10ayk\u0101n"
    ],
    "wof:name":"Hadi Hasan Daykan",
    "wof:placetype":"locality"
},
  "geometry": {"coordinates":[44.71039,32.33755],"type":"Point"}
}