{
  "type": "Feature",
  "properties": {
    "gn:admin1_code":"5.0",
    "gn:admin2_code":"92743.0",
    "gn:asciiname":"Badilyan",
    "gn:country_code":"IQ",
    "gn:dem":750,
    "gn:feature_class":"P",
    "gn:feature_code":"PPLL",
    "gn:name":"Badilyan",
    "gn:population":0,
    "gn:timezone":"Asia/Baghdad",
    "iso:country":"IQ",
    "name:ara_x_preferred":[
        "\u0628\u062f\u064a\u0644\u064a\u0627\u0646"
    ],
    "name:kur_x_preferred":[
        "Badilyan"
    ],
    "name:kur_x_variant":[
        "\u0628\u0627\u062f\u0644\u064a\u0627\u0646"
    ],
    "name:und_x_variant":[
        "Bad\u012bliy\u0101n",
        "Badaliyan",
        "Badlyan",
        "Badalyan",
        "\u0628\u062f\u064a\u0644\u064a\u0627\u0646"
    ],
    "wof:name":"Badilyan",
    "wof:placetype":"locality"
},
  "geometry": {"coordinates":[45.17484,36.16718],"type":"Point"}
}