{
  "type": "Feature",
  "properties": {
    "gn:admin1_code":"18.0",
    "gn:admin2_code":"90148.0",
    "gn:asciiname":"Hamad Jasim",
    "gn:country_code":"IQ",
    "gn:dem":126,
    "gn:feature_class":"P",
    "gn:feature_code":"PPL",
    "gn:name":"\u1e28amad J\u0101sim",
    "gn:population":0,
    "gn:timezone":"Asia/Baghdad",
    "iso:country":"IQ",
    "name:ara_x_preferred":[
        "\u062d\u0645\u062f \u062c\u0627\u0633\u0645"
    ],
    "name:und_x_variant":[
        "\u1e28amad J\u0101sim"
    ],
    "wof:name":"Hamad Jasim",
    "wof:placetype":"locality"
},
  "geometry": {"coordinates":[43.52879,34.55196],"type":"Point"}
}